{"m_szDocID":"1031297","m_szDocTitle":"search-results","m_szYear":"2016","m_szDocSumamry":"Be kind - we're currently a work in progress. Come back soon to see us become awesome. About Share your spare The Share Collection Global Sharing Week Contact Discover About Share your spare The Share Collection Global Sharing Week Contact Reports Share Guide Donate Get involved 979 experiences found   AuH2o Sells clothing made of recycled materials.... Read more Autolib' / Lyon Electric vehicle rental program based in France.... Read more B Global Bglobal’s vision is TO BE RECOGNISED AS A TRUSTED PROVIDER OF SMART ENERGY SOLUTIONS, HELPING ENERGY... Read more Ballard Power Systems, Inc. is a ","m_szDocBody":"kind work progress back awesome share spare share collection global sharing week contact discover share spare share collection global sharing week contact report share guide donate involved experience found auho sell clothing made recycled material read autolib lyon electric vehicle rental programme based france read global bglobal vision recognised trusted provider smart energy solution helping energy read ballard power system inc global leader pem proton exchange membrane fuel cell technology read banyan energy banyan energy inc solar power company based berkeley california usa develop breakthro read barcelona transici barcelona barcelona transici transition movement fight climate change read barcelona freecycle barcelona freecycle grassroot nonprofit movement people giving and getting read basf the chemical company meet challenge strategic organisational implementation read basin electric power cooperative transmission cooperative supplemental power rural electric coop basin electric read sharing economy place discover sharing change everyday life share directory company offering shared experience opportunity save cash meet people great time refine type sharing exchange collective purchasing membership scheme cocreation coproduction crowdsourcing resource category community network corporate sharing creativity media eco finance food drink good health fitness insurance knowledge learning leisure entertainment logistic older people pet property space public governance service task job skill transport trust security insurance utility country afghanistan australia austria belgium canada colombia denmark france germany india ireland italy netherland spain united kingdom united state update result found for add experience share share spare top trending sharing experience voted user pet coworking space meal sharing made brighton tonne people share benita matofska contact media cookie policy discover blog share spare share collection share guide sharing involved global sharing week supporter partner sponsor donate job career corporate sharing economy consultancy signup signing agree compare share term condition member log signing agree compare share term condition member log ","m_szGeo1":"","m_szSourceType":"source_industry","m_szSrcUrl":"http://www.thepeoplewhoshare.com/sharing-economy-guide/search-results/params/categories/eco//pageNo/6/","m_Places":["Sells","Made","Lyon","France","California","Usa","Barcelona","Afghanistan","Australia","Austria","Belgium","Canada","Colombia","Denmark","Germany","India","Ireland","Italy","Netherlands","Spain","United Kingdom","United States","Brighton","Uk"],"m_People":["Benita Matofska"],"m_Companies":["Ballard Power Systems, Inc.","Banyan Energy Inc.","Basin Electric Power Cooperative","Facebook","Twitter"],"m_BiGrams":["share spare","spare share","share collection","global sharing","sharing week"],"m_TriGrams":["global sharing week"],"m_SocialTags":[],"m_Topics":[],"m_Industry":[],"m_Technology":[],"m_BiCnt":[3,3,3,3,3],"m_TriCnt":[3],"m_iDocBodyWordCnt":292}
