{"m_szDocID":"1046687","m_szDocTitle":"LS:N Global","m_szYear":"2014","m_szDocSumamry":"LS:N Global is a division of: Â  Filter Login Menu Briefing Trends Macro Trends Micro Trends Trend Tracker Insight Behaviours Markets Shows Tribes Opinion Inspire Design Directions Talent Activate Filter by: Past day Past week Past month Past 6 months Past year Past 2 years Briefing Trends - Macro Trends - Micro Trends - Trend Tracker Insight - Behaviours - Markets - Shows - Tribes - Opinion Inspire - Design Directions - Talent - Activate Architecture Advertising Auto Beauty & Wellness Branding Culture Design Digital Drinks / Beverages Fashion Finance Food Hospitality Interiors Leisure LS:N Lux","m_szDocBody":"lsn global division philtre menu briefing trend macro trend micro trend trend tracker insight behaviour market show tribe opinion inspire design direction talent activate philtre past day past week past month past month past year past year briefing trend macro trend micro trend trend tracker insight behaviour market show tribe opinion inspire design direction talent activate architecture advertising auto beauty wellness branding culture design digital drink beverage fashion finance food hospitality interior leisure lsn luxury media packaging product design sport leisure retail technology travel generation generation millennial ups generation jone baby boomer africa asia eastern europe western europe global middle east north america nordic south america male female collaborative consumption behaviour staying power paris french hotel accor bought sharing economy house rental company onefinestay onefinestay accor sebel video opinion economy explained trend briefing final webinar sery revisiting trend briefing lsn global sharing economy reputation video opinion sharing economy dax lovegrove traditional businesse integrating platform dax lovegrovedirector dax lovegrove economy sharing economy european summit video opinion sharing economy sally davy isthe sharing economy ready mainstream ask sally davy technology innovation sharing economy airbnb uber opinion alex stephany understand sharing economy sharing economy airbnb sharing economy justpark collaborative consumption behaviour vending machine electric car debut china multistorey car vending machine china enable people rent compact electric car hour china vending machine vending behaviour ebay pilot service recommerce grow online marketplace ebay piloting physical service designed appeal local recommerce ebay collaborative consumption behaviour hearst plan hackathon york fashion week hearst plan hackathon york fashion week hacktivism crowdsourcing tech briefing gear lsn global made car gear lsn global made car nissan medicar inpatient behaviour invitation dine supperking invitation dine supperking los angele supperking dinner party market collaborative consumption market emerging product suited rented shared owned collaborative consumption hospitality boutique hotel behaviour collaborative consumer kickstart revolution collaborative consumer kickstart revolution collaborative consumption airbnb zipcar video micro trend cocommerce squeezed consumer dollar euro pound spend retailer collaborative consumption community customer power opinion roo roger barter sell trade consultant roo roger talk barter sell trade hyperconsumption collaborative consumption roo roger video briefing room service network act kind hotel room service network act kind hotel hotel london network briefing vice swap website let member swap good vice swap website let member swap good local los angele home loading editorial team profile event calendar lsn membership shop term condition glossary join mailing list lsn global elder street london phone email ","m_szGeo1":"United States","m_szSourceType":"source_general","m_szSrcUrl":"https://www.lsnglobal.com/tag/Collaborative%20Consumption","m_Places":["Boomers","Africa","Asia","Nz","Eastern","Europe","Middle East","North America","South America","Paris","China","New York","Los Angeles","London","United States"],"m_People":["Dax Lovegrove","Sally Davies"],"m_Companies":["Accor","Onefinestay","Airbnb","Uber","Ebay","Fifth Gear","Revolution","Zipcar"],"m_BiGrams":["sharing economy","collaborative consumption","lsn global","micro trend","consumption behaviour","video opinion","vending machine","roo roger"],"m_TriGrams":["collaborative consumption behaviour"],"m_SocialTags":[],"m_Topics":[],"m_Industry":[],"m_Technology":[],"m_BiCnt":[10,8,5,3,3,3,3,3],"m_TriCnt":[3],"m_iDocBodyWordCnt":401}
