{"m_szDocID":"1063747","m_szDocTitle":"The Rise of the On-Demand Economy - CIO Journal. - WSJ","m_szYear":"2015","m_szDocSumamry":"DOW JONES, A NEWS CORP COMPANY News Corp is a network of leading companies in the worlds of diversified media, news, education, and information services. DOW JONES Barron's BigCharts DJX Dow Jones Newswires Factiva Financial News Mansion Global MarketWatch Newsmart Newsplus Private Markets Risk & Compliance WSJ.com WSJ Pro WSJ Conference WSJ Video NEWS CORP Big Decisions Business Spectator Checkout51 Harper Collins New York Post PropTiger REA realtor.com Storyful The Australian The Sun The Times Nikkei ▲ 15430.53 -3.07%   Hang Seng ▲ 20042.29 -2.08%   U.S. 10 Yr ▲ 8/32 yield 1.545%   Crude Oil","m_szDocBody":"dow jone new corp company new corp network leading company world diversified media new education information service dow jone barron bigchart djx dow jone newswire factiva financial new mansion global marketwatch newsmart newsplus private market risk compliance wsjcom wsj pro wsj conference wsj video new corp big decision business spectator checkout harper collin york post proptiger rea realtorcom storyful australian sun time nikkei hang seng yield crude oil yen djia wall street section home world politic economy business tech market opinion art life real estate today paper show section hide section world home africa asia canada china europe latin america middle east brussel real time china real time india real time economy world video home economy law york politic real time economic number washington wire report video new podcast politic home tank washington wire politic video new poll economy home real time economic economic forecasting survey economy video business home management aerospace defence autos transportation commercial real estate consumer product energy entrepreneurship financial service food service health care hospitality law manufacturing media marketing natural resource retail cfo cio cmo today logistic report risk compliance bankruptcy beat heard street business video report business podcast tech home cio ecommerce mobile personal tech privacy security startup christopher mim geoffrey fowler joanna stern personal tech new venture capital dispatch billion dollar startup club tech trader daily tech video accelerator tech podcast market home bond commercial real estate commodity future currency deal financial service fund stock money heard street moneybeat private equity beat wealth adviser ahead tape cfo report market data market video market podcast moneybeat podcast heard street podcast watching wealth podcast opinion home art review book review commentary editorial letter editor web columnist morning editorial report peggy noonan political diary opinion video potomac watch podcast foreign edition podcast art home art review book speakeasy art video wsj magazine speakeasy podcast life home career car food drink health ideas real estate science sport style fashion travel expat duty daily daily fix life video wsj magazine wsj puzzle duty podcast future real estate home commercial real estate house day mansion real estate video hide section aim higher reach further wall street week reveal navigation option home world region africa asia canada china europe latin america middle east blog brussel real time china real time india real time section economy world video section economy law york politic column blog real time economic number washington wire report video new podcast politic blog tank washington wire politic video new poll economy blog real time economic economic forecasting survey economy video business section management industry aerospace defence autos transportation commercial real estate consumer product energy entrepreneurship financial service food service health care hospitality law manufacturing media marketing natural resource retail csuite cfo cio cmo today logistic report risk compliance column blog bankruptcy beat heard street business video report business podcast tech section cio ecommerce mobile personal tech privacy security startup column blog christopher mim geoffrey fowler joanna stern personal tech new venture capital dispatch billion dollar startup club tech trader daily tech video accelerator tech podcast market section bond commercial real estate commodity future currency deal financial service fund stock money column blog heard street moneybeat private equity beat wealth adviser ahead tape cfo report market data market video market podcast moneybeat podcast heard street podcast watching wealth podcast opinion section art review book review commentary editorial letter editor column blog web columnist morning editorial report peggy noonan political diary opinion video potomac watch podcast foreign edition podcast art section art review book blog speakeasy art video wsj magazine speakeasy podcast life section career car food drink health ideas real estate science sport style fashion travel blog expat duty daily daily fix life video wsj magazine wsj puzzle duty podcast future real estate section commercial real estate house day mansion real estate video chinas tencent near deal clash clan maker corporate client push back law firm hike starting salary envision healthcare amsurg merge zuckerberg venture invest startup andela disney triumphant week mired tragedy iran near tentative deal buy boeing plane judith rodin step head rockefeller foundation samsung buy cloud service firm philip green apologise retailer bhs collapse gawker hogan agree complete standstill privacy suit volkswagen boost electric vehicle pursue selfdriving car exxon seeking injunction climatechange investigation weak business investment weigh policy maker uberchinadidi fight drive deal talk microsoft deal linkedin shine light dynamic business walmart cut backoffice job store lawyer uber driver offer cut fee continent corporation urge remain spacex rocket crashes latest attempt barge landing birchbox pioneer subscription beauty sale retrenches zara owner inditex stay ahead competition copy personal noncommercial only order presentationready copy distribution colleague client customer visit save save wsj size regular medium large google print storey cio journal rise ondemand economy irving wladawskyberger comment industrial revolution led creation large midsize company people worked produce good deliver service good job meant working company worker unionised enjoyed secure stable job number company benefit including healthcare insurance vacation retirement pension thiscorporate capitalismera characterised hierarchically organised institution reached height period world war country craved sense stability pain chaos thegreat depressionand war year day long gone recent past slow moving organisation fast changing technology market individual assume loyal company translate secure job good benefit justin pressphoto agency rise ondemand economy led political regulatory challenge supporter airbnb operation york hold sign rally city hall jan stead rise whatthe economistcalled theondemand economyin arecent article manufacturing job automated existence outsourced abroad big company abandoned lifetime employment american worker work freelance sharing economy evolving new ubiquitous communication freelance work force low transaction cost giving rise ondemand company aim apply principle uber airbnb broader range market powerful force speeding trend ondemand worker pushing part economy availability ubiquitous inexpensive computing power sophisticated application cloudbased service kind complex task programming computer writing legal brief divided component part subcontracted specialist world great force changing social habit karl marx world divided people owned mean production idle rich people worked them fact increasingly divided people money time people time money ondemand economy group trade other understand emerging ondemand economyan evolution what calledthe sharing economylet changing nature firm time theintrinsic structure companieshas long subject study famously byronald coase eminent british economist recipient the nobel prizein economic professor coase published seminal paperthe nature firm heexplainedthat principle firm cheapest productive good service contracting efficient open marketplace however market perfectly fluid transaction cost incurred obtaining good service firm searching people negotiating contract coordinating work managing intellectual property thus firm make easier costly work done firm expanding adding people long expensive securing additional service marketplace but limit produced efficiently firm big firm remain competitive faster moving company growth generally lead larger multilayered hierarchical organisation additional layer management staff organisation bureaucratic significantly impacting ability quickly embrace ideas technology market condition change wellmanaged company strive achieve optimal balance work boundary advance information communication technology huge impact structure company fundamental taking place organisation firm flow good service economy significantly lower transaction coordination cost leading organisational decomposition company fragmenting smaller smaller entity individual provider time economy scale network effect leading organisational consolidation winnertakeall world largest survive fragmentation consolidation coexist greater lesser extent company ecosystem future work heading economy freelance worker moment notice reshape nature company structure careerssaysthe economist people carry computer pocket connected other are understand social network transaction cost involved finding people pushed long down ubiquitous communication low transaction cost giving rise class firm theondemand company firm aim efficiently bring consumer supplier good service highly scalable platform innovative application variety companieshave emergedin year aspiring achieve scale success ofuberandairbnb theyre hoping uber airbnbofx limited founder imagination unlike industrial economy counterpart ondemand firm tying trusted brand chosen market segment relying large freelance workforce classic company workforce economistis sceptical chance company citing main potential obstacle way first ondemand company generally cost low possible face difficulty training managing motivating freelance workforce moreover economy recover harder company attract casual low cost quality labour potential obstacle regulatory political problem ondemand company face large recent month uber plagued number ofsuch problemsaround world scalability potential issue uber airbnb similar company clear network effect ondemand model scaling difficult barrier entry low bond loyalty nonexistent hard worker loyal middleman number uber driver work lyft service industry hard obvious economy scale national global level sort world ondemand model create asksthe economist pessimist worry reduced status thcentury docker crowded quayside dawn waiting hired contractor booster maintain usher world control live work camp remember ondemand economy introducing serpent casual labour garden full employment exploiting casualised workforce way ameliorate problem aggravate other ondemand economy happy experience people stability flexibility middleaged professional children educate mortgage pay hand benefit people flexibility security student supplement income bohemian afford dip labour market young mother combine bringing children parttime job semiretired voluntarily not irving wladawskyberger worked ibm year strategic advisor citigroup year affiliated mit nyu imperial college regular contributor cio journal share this airbnb lyft uber previous morning download microsoft reportedly preparing cortana apple platform ceo reading mind mapping ceo humble cfo take hike save save wsj size regular medium large google print sponsor deloitte businessled technologyenabled insight written compiled deloitte mobileminded millennial rely pcs younger millennial flocking smartphone prefer pcs online activity watching video conducting complex banking transaction tmt prediction video deloitte global researcher discuss yearold continued computer read about mobile wireless video note wall street new department involved creation above deloitte comment livefyre faq follow post comment link newest oldest show archive editor pick election bernie sander vetted hillary clinton running mate uks immigration unease animate brexit vote market hedge fund michael milken touch middle seat allyoucanfly experience prosecutor rest case freddie grey murder trial grieving orlando ready wave funeral ahed bluegrass jam banjos corny joke side fry play art entertainment samsung cloud company advertisement popular wsj popular videos aliase orlandos gay scene made iding victim harder child body found alligator toddler alligator disney world orlando gunman disgruntled employee film orlando shooting unfolded popular article florida sheriff child body found alligator bernie sander vetted hillary clinton running mate opinion obama radical islam allyoucanfly experience donald trump cast gayright champion wall street edition asia europe amrica latina brasil china india indonesia japan korea edition asia europe amrica latina brasil china india indonesia japan korea nowsign wsj membership benefit download wsj app customer centre legal policy top wsj membership wsj membership benefit digital subscription print subscription print digital subscription subscribe download wsj app ios android corporate subscription professor student customer service customer centre live redesign guided tour tool feature email alert guide new portfolio feed topic video centre watchlist podcast ads advertise advertise locally commercial real estate ads place classified sell business sell home recruitment career ads partnership correction job wsj new archive free reprint google podcast snapchat googleplay appstore window dow jone product barron bigchart djx dow jone newswire factiva financial new mansion global marketwatch private market realtorcom risk compliance wsj conference wsj pro central banking wsj video wsj wine privacy policy cookie policy copyright policy data policy subscriber agreement term choice copyright dow jone company inc right reserved copyright dow jone company inc right reserved copy personal noncommercial only distribution material governed subscriber agreement copyright law nonpersonal order multiple copy contact dow jone reprint visit ","m_szGeo1":"United States","m_szSourceType":"source_general","m_szSrcUrl":"http://blogs.wsj.com/cio/2015/03/13/the-rise-of-the-on-demand-economy/","m_Places":["Rea","United States","Africa","Asia","Canada","China","Europe","Latin America","Middle East","Brussels","New York","Washington","Mobile","Best","Starting","Iran","U.k.","Landing","Justin","Most","Reading","Orlando","Fries","Florida","Brazil","India","Indonesia","Japan","Korea","Central"],"m_People":["Harper Collins","India Real","Christopher Mims","Geoffrey Fowler","Joanna Stern","Peggy Noonan","Irving Wladawsky-berger","Karl Marx","Ronald Coase","Professor Coase","Bernie Sanders","Hillary Rodham Clinton","Banjos, Corny","Made Iding","Donald Trump","Wsj Apps"],"m_Companies":["News Corp Company","News Corp","Barron's","Dow Jones Newswires","Factiva","Marketwatch","Spectator","New York Post","Nikkei","Wall Street Journal","Nbc News Poll","Natural Resources","Cmo","Venture","Billion Dollar Startup","Trader Daily","Potomac","Speakeasy","Andela","Disney","Boeing","Rockefeller Foundation","Samsung","U.s. Cloud Services Firm","Bhs","Volkswagen","Exxon","Microsoft","Linkedin","Shines","Wal-mart","Uber","Eu","Spacex","Birchbox","Pioneer","Zara","Google","Airbnb","Boundaries","Lyft","Ibm","Citigroup","Nyu","Imperial College","Apple","Deloitte","News Department","Seat","Jam","Cloud Company","Facebook","Twitter","Youtube","Dow Jones & Company, Inc."],"m_BiGrams":["real estate","real time","dow jone","commercial real","heard street","video new","video wsj","column blog","ondemand economy","risk compliance","wall street","time economic","washington wire","financial service","personal tech","art review","review book","wsj magazine","transaction cost","good service","new corp","rise ondemand","ondemand company","wsj membership"],"m_TriGrams":["commercial real estate","real time economic","video wsj magazine"],"m_SocialTags":[],"m_Topics":[],"m_Industry":[],"m_Technology":[],"m_BiCnt":[14,10,8,7,6,5,5,5,5,4,4,4,4,4,4,4,4,4,4,4,3,3,3,3],"m_TriCnt":[7,4,4],"m_iDocBodyWordCnt":1840}
