{"m_szDocID":"1064220","m_szDocTitle":"Expect Great Things From These 9 Tech Startups in 2016","m_szYear":"2012","m_szDocSumamry":"Home Latest Top 50 How To Magazine Events Subscribe Limited-Time Offer: Give one year of Entrepreneur for $5 8 min read Radicals & Visionaries Expect Great Things From These 9 Tech Startups in 2016 Image credit: Beepi | Facebook Kim Lachance Shandrow Entrepreneur Staff West Coast editor. Frequently covers celebrities, future tech, social media, startups, gadgets and apps. Radicals & Visionaries 4 Credit Card Tips to Make Business Travel Easier Thomas Donaldson Radicals & Visionaries The Most Powerful Advice Entrepreneurs Ignore Graham Young Radicals & Visionaries Take a Virtual Reality Hot Air","m_szDocBody":"home latest top magazine event limitedtime offer give year entrepreneur min read radical visionary expect great tech startup image credit beepi kim lachance shandrow entrepreneur staff west coast editor frequently cover celebrity future tech social media startup gadget app radical visionary credit card tip make business travel easier thomas donaldson radical visionary powerful advice entrepreneur ignore graham young radical visionary virtual reality hot air balloon trip est fat jew king socialmedia empire erin schultz free strategy session exclusive ebook habit highly successful entrepreneur learn apply enterpreneur company world success storey started world tech startup hype anticipation short supply weve heard time again big forever transform live work play make killing odd that case point airbnb uber amazon emerged obscurity shot top shook world whos next upandcomer rise rest year make mark course sure fun taking educated guesse relatedthis startup fill gas tank demand raised million here list hot tech startup watch year turning marketable ideas reality gaining traction customer stirring buzz process product hunt image credit product hunt founder ryan hoover year founded headquarter san francisco billion website crowding interweb discovering product massive challenge blogger ryan hoover couldnt allinone dedicated surfacing cool stuff techy geek created one first list then begun side project evolved product hunt wildly popular online tastemaking hub showcase latest gadget game podcast book ycombinatorbacked website blew year launch attracting million user investor early adopter scour product hunt cleancut curated list great innovation date product hunt raised estimated million venture capital related product hunt thrive startup showcasing startup doordash image credit doordash founder andy fang stanley tang evan moore tony year founded headquarter san francisco out postmate doordash rearview mirror driving market share fast powered ten thousand uberstyle driver called dasher ondemand food delivery app ferry fresh grub local restaurant customer plus city canada scrappy startup long stanford dorm room launched short time penned partnership top brand kfc eleven dunkin donut ponying million investment and legal battle innout burger way related startup helping restaurant efficient delivery boxed image credit boxed instagram founder chieh huang william fong christopher cheung jared yaman year founded headquarter edison shopping place costco sam club logistical nightmare live heart big city pain schlep glut wholesale good home public transit example stocking suburban bigbox retail giant headache live boondock enter boxed wholesale ecommerce startup let consumer shop smartphone laptop grocery household item bulk minus long line membership fee and free food sample started windowless conference room friend young company total headcount fastgrowing national footprint fresh million sery funding round total investment haul stand approximately million related business owner paying employee kid college luxe valet image credit luxe founder curtis lee craig martin year founded headquarter san francisco parking car city exercise frustration circling block multiple time spot waste time luxe valet relieve fittingly valetparking upstart launched smartphoneapp based service parking nightmare san francisco fueled approximately million venture capital venture driven major city hourly rate which vary location luxe valet park car company lot additional fee wash ride put gas change oil happen drive tesla theyll charge even park itself startup partnered elon musk electric car company week related sharing economy niche future market capitalism medium image credit medium blog founder jose pino evan william year founded headquarter san francisco period medium looked inviteonly blogging platform then long opened quickly viral social mecca quickly place heard amateur marketer politician journalist alike publish written kind popular site include short storey meandering manifestos deep reportage political puffery more medium cofounded billionaire evan william ceo member founding team site recently repositioned internet version newspaper oped section unorthodoxly measure success time people spend reading article versus amount click rack hundred thousand people published platform year rolled sponsored content native advertising far company raised nonetooshabby million venture capital infusion highprofile investorentrepreneur chris sacca gary vaynerchuk related write book selfpublishing option classpass image credit classpass instagram founder payal kadakia mary biggin year founded headquarter york classpass managed thrive dead arrival year named classivity barely booked fitness classe appbased gym membership platform lastditch effort save floundering service founder offered onemonth pass people classe studios smart move today company roll venturesbacked upstart employ people connect growing base customer exercise classe boutique gym participating studios plus city canada europe australia date silicon alley standout banked estimated million venture capital related sxsw classpass learned making decision easier customer beepi image credit beepi enhanced entrepreneur founder alejandro resnik owen savir year founded headquarter los altos calif recent tweet pretty perfect pitch beepi bought car today internet app phone hand #millennial ive done basically buying selling car well cool beepi officially launched innovative service year ago fast lane since steadily expanding percent annual rate san jose mercury new cofounder ceo alejandro resnik idea app buying jeep caught fire mit grad serial entrepreneur claim beepi company sell car percent online far secured million investment revving rapid growth related company make concept creation shyp image credit shyp founder kevin gibbon joshua scott jack smith year founded headquarter san francisco shyp making promising taking boxmoving big boy ups fedex postal service trendy ondemand shipping app enable people order courier cart item warehouse there good professionally packed shipped destination daymond johnbacked service flush million venture capital fresh incredible year shyp bike car courier shyp heroe contract full time tied partnership ebay debuted feature brushed branding san francisco york city extended package pickup reach los angele chicago forgive cheesy pun hunch consumer give shyp startup soon related shyp shaking process mailing package acorn image credit acorn founder mark dru walter cruttenden jeffrey cruttenden year founded headquarter newport beach calif fatherson duo walter jeffrey cruttenden founded acorn goal making investing tedious intimidating automation smartphone app built automatically invest user leftover change routine credit debit card purchase exchangetraded fund launch company increased headcount employee spring jeffrey cruttenden acorn serving registered user opened approximately investment account latest funding round bring southern california startup total million venture capital spare change related industry driving top small city business owner startup entrepreneur technology app car company advertise brand licencing contact staff contribute upcoming event marketing bootcamp webinar sery product business book reprint licencing classified entrepreneur coaching edition united state middle east india espaol philippine south africa china connect linkedin google pinterest instagram tumblr gift subscription subscriber service digital edition iosandroidkindle copyright entrepreneur media inc right reserved term privacy policy map follow current edition united state india middle east espaol section latest top magazine leadership growth strategy marketing technology social media finance entrepreneur starting business franchise magazine entrepreneur coaching business form video event newsletter bookstore contact advertise reprint licencing privacy policy term entrepreneur media inc skip advertisement close second","m_szGeo1":"United States","m_szSourceType":"source_general","m_szSrcUrl":"https://www.entrepreneur.com/slideshow/270040","m_Places":["Most","Take","Est","United States","Canada","Tesla","New York, N.y.","Europe","Australia","New York City","Los Angeles","Chicago","Newport","Southern California","Small Cities","Brand","Middle East","India","Philippines","South Africa","China","Starting"],"m_People":["Kim Lachance Shandrow","Thomas Donaldson","Graham Young","Jew, King","Erin Schultz","Mark Dru","Ryan Hoover","Andy Fang","Stanley Tang","Evan Moore","Tony Xu","William Fong","Christopher Cheung","Jared Yaman","Curtis Lee","Craig Martin","Elon Musk","Jose Pino","Evan Williams","Chris Sacca","Gary Vaynerchuk","Mary Biggins","Alejandro Resnik","Owen Savir","Kevin Gibbon","Joshua Scott","Jack Smith","Daymond John","Walter Cruttenden","Jeffrey Cruttenden","Walter"],"m_Companies":["Tech Startups","Facebook","Airbnb","Uber","Amazon","Startup Showcasing Startups","7-eleven","Dunkinâ€™ Donuts","In-n-out Burger","Boxed","Costco","Enter Boxed","Google","Twitter","Infusions","San Jose Mercury News","Fedex","U.s. Postal Service","Ebay","Linkedin","Pinterest","Youtube","Entrepreneur Media, Inc."],"m_BiGrams":["image credit","year founded","founded headquarter","san francisco","product hunt","million venture","venture capital","headquarter san","radical visionary","tech startup","luxe valet","car company","jeffrey cruttenden"],"m_TriGrams":["year founded headquarter","million venture capital","founded headquarter san","headquarter san francisco"],"m_SocialTags":[],"m_Topics":[],"m_Industry":[],"m_Technology":[],"m_BiCnt":[10,9,9,7,6,6,6,5,4,3,3,3,3],"m_TriCnt":[9,6,5,5],"m_iDocBodyWordCnt":1089}
