{"m_szDocID":"1065474","m_szDocTitle":"Airbnb vs The Hotel Industry, Who Will Win | Investopedia","m_szYear":"2016","m_szDocSumamry":"Topics What's New Germany and India Aim to Only Register Electric Cars by 2030 Uber Poised to Close Up to $2B in Leveraged Loans Topics Markets Financial Advisors Trading Anxiety Index Retirement Personal Finance ETFs & Mutual Funds Election Center Managing Wealth Investing Stock Analysis Reference Dictionary Term Of The Day VIX - CBOE Volatility Index The ticker symbol for the Chicago Board Options Exchange (CBOE) Volatility Index, ... Read More » Latest Videos Investopedia Originals: Wealth Transfer 5 ETF Flaws You Shouldnâ€™t Overlook Guides Stock Basics Economics Basics Options Basics Exam","m_szDocBody":"topic germany india aim electric car uber poised close leveraged loan topic market financial advisor trading anxiety index retirement personal finance etf mutual fund election centre managing wealth investing stock analysis reference dictionary term day vix cboe volatility index ticker symbol chicago board option exchange cboe volatility index read latest videos investopedia original wealth transfer etf flaw shouldnt overlook guide stock basic economic basic option basic exam prep sery exam cfa level sery exam simulator stock simulator trade starting balance risk trader trade forex market risk free free forex trading simulator advisor insight newsletter log airbnb hotel industry win trevir nath est airbnb largest peertopeer exchange service hospitality world continue grow government notice york attorney general eric schneiderman argue airbnb rental regulated hotel airbnb provider subject hotel occupancy taxe airbnb argue business model connect host rent private property shortterm subletter major hotel chain marriot season hilton insist primary demographic hotel patron differ vastly airbnb guest revenue affected age internet disruption assume hotel industry negatively affected rise airbnb understanding price structure airbnb primary demographic variety factor illuminate fundamental difference hotel industry airbnb for more see make money fast sharing economy airbnb airbnb rapid growth inception revenue million doubled revenue promise listing country airbnb established largest peer peer hospitality service airbnb business model focuse marketplace platform host guest exchange housing money application process host guest review social media connexion build trust user marketplace valuable approach unique airbnb influx digital technology user dictate experience affect future consumer choice number online platform board review system directly hotel website party platform yelp expedia provide service pricing structure airbnb platform peertopeer exchange direct effect price lodging offered host airbnb host follow guideline similar hotel renting home guest seeking short term lodging night pay premium compared seeking longer term stay listing home airbnb host liberty set price individual night weekly stay cleaning fee weekend price additional guest hotel room fetch premium price weekend holiday guest exceed number bed hotel visit charge cleaning fee hotel onstaff cleaning service furthermore hotel room airbnb lodging expensive higherdemand areas major city tourist attraction major city rent cost living higher host hotel factor rent premium location price however major hotel chain maintain pricing scheme meet consumer demand airbnb host liberty charge deem appropriate case prospective consumer airbnb offer expensive alternative hotel for more see website save money hotel room primary demographic inconclusive explosive growth airbnb effect hotel industry visitor major hotel chain hilton marriott luxury business traveller airbnb operate space offer vacation rental homey environ lowbudget consumer airbnb rental end hotel cross path case lowend hotel motel losse due airbnb average hotel room offer consumer bed bathroom closet varying level comfort alternatively average apartment offer luxury kitchen larger living space family group vacation hotel limiting apartment accommodating far airbnb entered highend hotel market traveller charging expense company beginning seek increased amount business accommodation airbnb concur business travel expense management platform confirmed trend recording growing number airbnb booking corporate client taxe regulation primary difference hotel industry airbnb presence taxe regulation short term rental york term hotel include hotel motel inn b&b apartment hotel condos rental category require operator collect additional sale tax based charge room furthermore hotel york city charge hotel unit fee day additional occupancy taxe prime point contention airbnb subject occupancy tax law forgone paying local government sale tax hotel though airbnb incorporate valueadded tax service fee added tax tax assessed final sale good service typically accommodation european union due tax law airbnb hotel charge vat guest airbnb fortunate avoid rental hotel tax law far regulation property law major concern host state exist squatter law visitor occupying space day law attain tenant right rented space state illegal sublet residential space home apartment room fewer day resident time guest bottom line hotel lobbyist state government continue impose taxe regulation airbnb continue rapid growth recent valuation billion airbnb valued individual hotel chain directly providing good consumer airbnb dipped revenue lower end hotel group sharing economy continue quick ascension airbnb disrupt end hotel revenue sharing economy service uber taxi service browse topic airbnb business strategy travel industry learn invest subscribing investing basic newsletter hot definition vix cboe volatility index ticker symbol chicago board option exchange cboe volatility index show market expectation classification trading share declared dividend belong seller buyer stock asset allocation investment strategy aim balance risk reward apportioning portfolios asset individual hedge making investment reduce risk adverse price movement asset normally hedge consist taking offsetting foreign aid foreign aid money country voluntarily transfer another form gift grant loan estate planning collection preparation task serve manage individual asset base event incapacitation trading centre partner link investopedia make smarter new newsletter latest expert analysis market insight new enter symbol dictionary article term videos guide slideshow faqs calculator chart advisor stock analysis stock simulator fxtrader exam prep quizzer net worth calculator connect investopedia work investopedia advertise write contact career free newsletter newsletter investopedia llc right reserved term privacy policy","m_szGeo1":"United States","m_szSourceType":"source_general","m_szSrcUrl":"http://www.investopedia.com/articles/investing/112414/airbnb-brings-sharing-economy-hotels.asp","m_Places":["Germany","India","Est","New York","New York City","Enter","United States"],"m_People":["Trevir Nath","Eric Schneiderman"],"m_Companies":["Uber","Election Center","Cboe","Chicago Board Options Exchange","Airbnb","Four Seasons","Yelp","Expedia","Marriott","Travelers","European Union","Bottom Line"],"m_BiGrams":["hotel industry","cboe volatility","volatility index","hotel chain","hotel room","major hotel","primary demographic","sharing economy","airbnb host","consumer airbnb","end hotel","taxe regulation","tax law"],"m_TriGrams":["cboe volatility index","major hotel chain"],"m_SocialTags":[],"m_Topics":[],"m_Industry":[],"m_Technology":[],"m_BiCnt":[5,4,4,4,4,3,3,3,3,3,3,3,3],"m_TriCnt":[4,3],"m_iDocBodyWordCnt":812}
