{"m_szDocID":"1066512","m_szDocTitle":"Innovation Strategies – Seeking Alpha and Long Term Growth","m_szYear":"2013","m_szDocSumamry":"Twitter Linkedin Gplus Facebook Log In Register Research All Research White Papers Advisor Services Strategies Solutions Thought Leadership Our Clients Innovation ETFs The ARK Ecosystem About ARK Research Process ARK Team Theme Developers Board of Advisors Contact Search We seek to deliver long-term capital appreciation and alpha with low correlation of relative returns to traditional investment strategies. Innovation Strategies We achieve long-term alpha by focusing on disruptive innovation that is changing the way the world works. ARK researches a broad global universe that spans all countri","m_szDocBody":"linkedin gplus log research research white paper advisor service strategy solution thought leadership client innovation etf ark ecosystem ark research process ark team theme developer board advisor contact seek deliver longterm capital appreciation alpha low correlation relative return traditional investment strategy innovation strategy achieve longterm alpha focusing disruptive innovation changing world work ark researches broad global universe span country market capitalization identify company leader enabler beneficiary innovation creative research ecosystem designed capitalise rapid change convergence research insight combination topdown bottomup research ark identify disruptive innovation early innovation highest growth potential capture venture capitallike exposure public market security capitalise opportunity excess return created company benefitting disruptive innovation arkinnovation strategy ark disruptive innovation arkdisruptive innovation strategy cornerstone theme disruptive innovation ark disruptive innovation strategy built investment riskreward opportunity ark innovationbased theme strategy offer diversified portfolio areas disruptive innovation autonomous electric vehicle smarter robot cloud sharing economy increase utilisation fixed asset semiautonomous vehicle savs replace vehicle million parking space worth trillion use learn generation internet generation internet connecting digital world ark generation internet strategy recognise internet transforming sector economy strategy focuse disruptive innovation changingthe world manage information analyse data purchase good communicate globe amount analysed data set grow year estimated annual growth rate learn industrial innovation industrialinnovation strategy industrial revolution advancement robotic printing modern infrastructure space exploration energy storage technology enhancing productivity reducing cost ark industrial innovation strategy focuse disruptive innovation transforming manufacturing production infrastructure investment automation robotic generate trillion additional gdp forthe united state learn genomic revolution genomic revolution strategy health care meet technology genomic sequencing changing biological information collected processed applied ark genomic revolution strategy focuse disruptive innovation reduce guesswork increase precision restructuring health care agriculture pharmaceutical enhancing quality life human genomic sequencing projected grow annual growth rate year plant animal tumour viruse bacteria sequenced learn fintech innovation fintech innovation strategy financial transformation ark fintech innovation strategy focuse disruptive innovation revolutionising financial industry regulatory shifted economic intermediating capital reconfiguring valuechain allowing exploitation competitor simultaneously technological innovation platform changing ability financial institution assess risk interact customer transfer asset facilitate transaction financial service spend mobility cloud big data analytic increase year cross billion annum learn printing ark printingstrategy shaping future design experiencing dramatic cost decline enhancing speed accuracy customization printing highest growth potential industry economy total printing index seek capture disruptive innovation set transform manufacturing production landscape printing year reach market billion year reach billion analyst project grow year learn israel innovative technology israel innovative technology innovation powerhouse israel world leader development innovative product service advancement scientific research ark israel innovation index seek capture disruptive innovation coming technological powerhouse promotion developed market status israel portfolios underweight relative growth innovation projection represent msci world index teva imd global competitiveness yearbook ranked israel business expenditure r&d cyber security innovative capacity entrepreneurship expenditure education scientific research learn benefit investing ark innovation strategy longterm capital appreciation alpha hedge rapid changerisk oldguard industry company diversification withlow correlation relative traditionalstrategy complement broadmarket indice traditional manager international exposure tailored meet client objective investment vehicle preference world changing rapidly broad benchmark reflect past successe thematic investing seek capture future growth download ark white paper thematic investing exponential world download download ark white paper disruptive innovation marketsnew download source time centre automotive research car usdt federal highway admin national household travel survey zipcar annual report projection guarantee source ark investment management llc source ark investment management llc based research from carl benedikt frey michael osborne future employment susceptible job computerization university oxford source ark investment management llc based research from idc financial insight perspectiveworldwide financial service platform spend opportunity abound source siemen additive manufacturing printing fact forecast sourceimd global competitiveness yearbook research white paper market review advisor service strategy solution thought leadership client explore ark etf ark ecosystem ark research process ark team theme developer board advisor contact faqs press media job opportunity ark investment management llc ark original researched produced ark stated part ark original reproduced form referred publication express written permission ark informational purpose subject change notice statement made company security financial information site relating ark strictly belief point held ark party making statement endorsement ark company security recommendation ark buy sell hold security list purchase sale made ark client account past year considered sec recommendation here assumed recommendation made future profitable equal performance security list full disclosure term site privacy policy term patent scroll top","m_szGeo1":"United Kingdom","m_szSourceType":"source_general","m_szSrcUrl":"https://ark-invest.com/innovation-strategies","m_Places":["United States","Israel"],"m_People":["Carl Benedikt","Michael A. Osborne"],"m_Companies":["Twitter","Linkedin","Facebook","Venture","Innovations","Fintech","La Times","Zipcar","Source: Ark Investment Management Llc","University Of Oxford","Idc","Ark Investment Management Llc","“ark”","Sec"],"m_BiGrams":["disruptive innovation","innovation strategy","white paper","strategy focuse","focuse disruptive","ark investment","investment management","management llc","generation internet","genomic revolution","fintech innovation","seek capture","source ark"],"m_TriGrams":["strategy focuse disruptive","focuse disruptive innovation","ark investment management","investment management llc","source ark investment"],"m_SocialTags":[],"m_Topics":[],"m_Industry":[],"m_Technology":[],"m_BiCnt":[14,7,4,4,4,4,4,4,3,3,3,3,3],"m_TriCnt":[4,4,4,4,3],"m_iDocBodyWordCnt":715}
