{"m_szDocID":"1066513","m_szDocTitle":"Disruptive Innovation Research by ARK Invest","m_szYear":"2016","m_szDocSumamry":"Twitter Linkedin Gplus Facebook Log In Register Research All Research White Papers Advisor Services Strategies Solutions Thought Leadership Our Clients Innovation ETFs The ARK Ecosystem About ARK Research Process ARK Team Theme Developers Board of Advisors Contact Search Bitcoin: Ringing the Bell for a New Asset Class Download ARK’s Research White Paper Subscribe to ARK Research All 42 |Digital 19 |Health 4 |Industrial 16 |Market Insights 3 |News 0 |Review 0 |White Paper 0 |White Paper 0 Bitcoin: Ringing the Bell for a New Asset Class Digital, White Paper/by Christopher Burniske, ARK Analyst B","m_szDocBody":"linkedin gplus log research research white paper advisor service strategy solution thought leadership client innovation etf ark ecosystem ark research process ark team theme developer board advisor contact bitcoin ringing bell asset class download ark research white paper ark research digital health industrial market insight new review white paper white paper bitcoin ringing bell asset class digital white christopher burniske ark analyst bitcoin ethereum smart contract work christopher burniske ark analyst printing innovation case study tasha keeney ark analyst machine learning open cloud opportunity gpus jame wang ark analyst shared autonomous vehicle multihundredbillion dollar opportunity tasha keeney ark analyst illumina bedrock genomic revolution catherine wood ark invest ceo printing market analyst underestimating future tasha keeney ark analyst netflix largest global network jame wang ark analyst bitcoin blockchain christopher burniske ark analyst cerus intercept prevent transmission zika virus manisha samy ark analyst rocket rise space market bring explosive opportunity sam korus ark analyst year electric vehicle leave gas car dust sam korus ark analyst artificial intelligence jame wang ark analyst low cost lidar save live tasha keeney ark analyst streaming giant netflix reach million subscriber jame wang ark analyst update tesla sell million vehicle year sam korus ark analyst market outlook flip side market insight catherine wood ark invest ceo thematic investing strategy exponential world market insight white christopher burniske ark analyst retail ready robot sam korus ark analyst undercover big data company health care christopher burniske ark analyst amazon drone deliver package thirty minute dollar tasha keeney ark analyst brewing iot standard battle christopher burniske ark analyst instagram monetization potential range billion billion jame wang ark analyst steep cost labour market friction billion sam korus ark analyst microsharing economy driving good deflation christopher burniske ark analyst securing bitcoin network white paper digital white christopher burniske ark analyst teslas battery technology power moat faster falling sam korus ark analyst health care system changed interview alex cahana jame bannon ark analyst silicon alley dissect bitcoin unique bitcoin panel discussion christopher burniske ark analyst bitcoin currency investigating bitcoin christopher burniske ark analyst bitcoin unit account investigating bitcoin christopher burniske ark analyst update supercharger charge cost half price gas tasha keeney ark analyst bitcoin store investigating bitcoin christopher burniske ark analyst bitter pill cost sovaldi erik tvetenstrand ark analyst bitcoin mean exchange investigating bitcoin christopher burniske ark analyst automation growing economy creating job david conway ark analyst bitcoin primer investigating bitcoin christopher burniske ark analyst mega trend shaping advertising market jame wang ark analyst autonomous vehicle reduce chance dying auto accident tasha keeney ark analyst bull market continue surprise market insight catherine wood ark invest ceo benefit commercial drone off tasha keeney ark analyst tesla real disruptor ark research case study ark invest load ark disruptive innovation research original disruptive innovation research vetted ark research ecosystem director research published reviewed ark catherine wood research white paper market review advisor service strategy solution thought leadership client explore ark etf ark ecosystem ark research process ark team theme developer board advisor contact faqs press media job opportunity ark investment management llc ark original researched produced ark stated part ark original reproduced form referred publication express written permission ark informational purpose subject change notice statement made company security financial information site relating ark strictly belief point held ark party making statement endorsement ark company security recommendation ark buy sell hold security list purchase sale made ark client account past year considered sec recommendation here assumed recommendation made future profitable equal performance security list full disclosure term site privacy policy term patent scroll top","m_szGeo1":"United Kingdom","m_szSourceType":"source_general","m_szSrcUrl":"https://ark-invest.com/disruptive-innovation-research","m_Places":["United States","Tesla","Outlook","Means"],"m_People":["Christopher Burniske","Tasha Keeney","James Wang","Catherine Wood","Manisha Samy","Sam Korus","Alex Cahana","James Bannon","Erik Tvetenstrand","David Conway","Real Disruptor"],"m_Companies":["Twitter","Linkedin","Facebook","Google","Illumina","Netflix","Will Cerus","2020","Undercover","Big Data Companies","Amazon","Bitcoin Network","Bull","Ark Investment Management Llc","“ark”","Sec"],"m_BiGrams":["ark analyst","christopher burniske","burniske ark","tasha keeney","keeney ark","analyst bitcoin","white paper","ark research","jame wang","wang ark","sam korus","korus ark","investigating bitcoin","bitcoin christopher","market insight","catherine wood","ark invest","white christopher","wood ark","invest ceo"],"m_TriGrams":["christopher burniske ark","burniske ark analyst","tasha keeney ark","keeney ark analyst","ark analyst bitcoin","jame wang ark","wang ark analyst","sam korus ark","korus ark analyst","investigating bitcoin christopher","bitcoin christopher burniske","white christopher burniske","catherine wood ark","wood ark invest","ark invest ceo"],"m_SocialTags":[],"m_Topics":[],"m_Industry":[],"m_Technology":[],"m_BiCnt":[38,14,14,8,8,7,6,6,6,6,6,6,5,5,4,4,4,3,3,3],"m_TriCnt":[14,14,8,8,7,6,6,6,6,5,5,3,3,3,3],"m_iDocBodyWordCnt":585}
