{"m_szDocID":"1066213","m_szDocTitle":"Learn About Green Living With Scotiabank EcoLiving | Scotiabank EcoLiving","m_szYear":"2016","m_szDocSumamry":"Toggle navigation Learn to Live Green Calculate Savings Eco-Partnerships English Fran√ßais A Decrease A Normal A Increase Search Featured Article Are Programmable Thermostats Worth the Investment? Smart thermostats can be a good investment when utilized correctly Read more Indoor Spaces 5 min read Filter Articles by Viewing all articles Show filters Condo Living Cost Saving Green Lifestyle How to Indoor Spaces Outdoor Spaces Latest Most Popular Is Solar a Good Investment for Residential Homes in Canada? Should Canadian homeowners invest in residential solar arrays? Read more Green LifestyleCost","m_szDocBody":"toggle navigation learn live green calculate saving ecopartnership english franais decrease normal increase featured programmable thermostat worth investment smart thermostat good investment utilised correctly read indoor space min read philtre article viewing article show philtre condo living cost saving green lifestyle indoor space outdoor space latest popular solar good investment residential home canada canadian homeowner invest residential solar array read green lifestylecost saving min read making big difference environment combined effort ecoliving individual changing world read green lifestyle min read way save energy kitchen hydro cost increasing tip result significant saving read green lifestylecost saving min read way green commute way reduce cost environmental impact commute read green lifestyle min read country run renewable energy long list country energy renewable source read green lifestyle min read green electric car life cycle electric car worth investment read green lifestylecost saving min read cheque amazing shipping container home favourite upcycled shipping container home read outdoor spacesgreen lifestyle min read back nature building home natural material homeowner turning natural material building dream home read green lifestyle min read ecoliving condo building condo living offer opportunity make profound impact environment read green lifestylecondo living min read awesome app green living app greening home reducing carbon footprint saving money read green lifestyle min read edible indoor garden ideas innovative system growing fruit vegetable armchair botanist read indoor spacesgreen lifestylecost saving min read easy year resolution energy saving saving energy money easier think read green lifestylecost saving min read upcycled christmas gift make make upcycled christmas gift reduce carbon footprint holiday read green lifestylecost savinghow min read incredible netzero home love live ecoliving family netzero home read outdoor spacesgreen lifestyle min read growing hydro bill giving chill cut energy bill half winter read green lifestylecost saving min read greener leaner driver driving technique save money read green lifestylecost saving min read solar installation worthwhile investment home residential solar worth requirement projected profit read green lifestylecost saving min read greenest thanksgiving tip greening thanksgiving save planet money read green lifestyle min read incredibly easy energysaving tip havent heard reduce home condo energy bill massive investment read indoor spacesgreen lifestyle min read ecogadget cat pyjamas favourite green goody make ecoliving easier read green lifestyle min read tiny house movement huge imagine living square foot home read indoor spacesgreen lifestylecost saving min read easy way green home make home greener quick fixe read green lifestyle min read time car reduce climate impact choosing electric hybrid diesel read green lifestyle min read giving make year thanksgiving energy efficient kitchen tip read green lifestyle min read join sharing economy save money environment sharing resource buying read green lifestyle min read live lower impact advice environmental professional green read green lifestyle min read build netzero house home produce energy use saving money utility read green lifestyle min read bike foot active transportation good you budget climate read green lifestyle min read ecofriendly summer fun discover way family spend time learning nature read green lifestyle min read dad save dollar father day gift gadget perfect energywise guy read green lifestyle min read based philtre selected article select philtre visit future article continually added load article back top question ecoliving faqs privacy legal sitemap franais","m_szGeo1":"","m_szSourceType":"source_general","m_szSrcUrl":"https://ecoliving.scotiabank.com/learn-to-live-green/green-lifestyle","m_Places":["Most","Canada"],"m_People":["Lifestylecost Saving"],"m_Companies":["Back To Nature","Diesel"],"m_BiGrams":["min read","read green","lifestyle min","green lifestyle","lifestylecost saving","saving min","green lifestylecost","read indoor","home read","spacesgreen lifestyle","money read","indoor spacesgreen"],"m_TriGrams":["lifestyle min read","read green lifestyle","green lifestyle min","lifestylecost saving min","saving min read","read green lifestylecost","green lifestylecost saving","spacesgreen lifestyle min","money read green","read indoor spacesgreen"],"m_SocialTags":[],"m_Topics":[],"m_Industry":[],"m_Technology":[],"m_BiCnt":[31,26,19,17,9,9,8,4,4,3,3,3],"m_TriCnt":[19,15,15,9,9,8,7,3,3,3],"m_iDocBodyWordCnt":530}
