{"m_szDocID":"1067621","m_szDocTitle":"About - Juniper Research","m_szYear":"2002","m_szDocSumamry":"We use cookies to ensure that we give you the best experience. By continuing to use our site you agree to our cookie and privacy policy, if you do not agree please leave the site Dismiss this message REGISTER SIGN IN My Juniper Basket Home ResearchStore Services Subscriptions Consultancy Data Resources Blog Press Clients About Contact Menu Home ResearchStore Commerce & Fintech Disruptive Technologies Contactless Payments Digital Payment Strategies Digital Retail Marketing Mobile & Online Coupons Mobile & Online Purchases Mobile & Online Ticketing Digital Commerce Markets Mobile Banking & Conta","m_szDocBody":"cooky ensure give experience continuing agree cookie privacy policy agree leave dismiss message juniper basket home researchstore service subscription consultancy data resource blog press client contact menu home researchstore commerce fintech disruptive technology contactless payment digital payment strategy digital retail marketing mobile online coupon mobile online purchase mobile online ticketing digital commerce market mobile banking contactless payment survey mobile banking contactless payment survey mobile financial service mobile identity biometric tokenisation digital money transfer remittance mobile wallet online payment fraud future cryptocurrency worldwide digital banking worldwide mpos market application app app store digital music digital adult mobile worldwide digital game market digital game esport mobile online entertainment mobile online gambling mobile online messaging mobile online video device wearable consumer printing scanning consumer wearable market survey drone green mobile smart clothing jewellery smart glasse future health fitness wearable smart toy smart watches smart wearable device smart wireless device smartphone market tablet phablet hybrid wireless charging worldwide consumer robotic key vertical market autonomous vehicle commercial connected vehicle consumer connected car hybrid electric vehicle worldwide digital health embedded device inflight entertainment wifi connectivity mobile online entertainment worldwide smart city smart home ecosystem internet internet internet thing consumer internet thing industrial internet thing public service strategy competition crowdfunding worldwide digital advertising digital business model future voice strategy sharing economy future cybercrime security mobile operator business model mobile roaming enabling technology market strategy augmented reality cloud computing consumer market cloud computing enterprise market human interface biometric device context location based service mobile data offload onload virtual reality wifi hotspot service corporate subscription consultancy consultancy analyst support case study data forecast browse dataset resource event future digital award juniper new videos radio insight whitepaper free research blog archive press analyst relation file media file press release client logos contact home researchstore service subscription consultancy data resource blog press client contact live support sorry support moment home juniper specialise identifying appraising growth market sector digital ecosystem juniper research founded industry consultant tony crabtree midst telecom dotcom crash business fully incorporated grown leading analyst firm mobile digital tech sector juniper specialise identifying appraising growth market sector digital ecosystem market sizing forecasting cornerstone offering competitive analysis strategic assessment business modelling endeavour provide independent impartial analysis current emerging opportunity team dedicated specialist knowledgeable experienced expert field client range mobile operator provider vendor financial institution juniper client base span globe majority client based north america western europe east interested offer corporate subscription browse research provide wide range consultancy service utilising extensive knowledge database sector indicator tailor deliverable fit specific requirement learn choose juniper research reliable dependable analysis built period twelve year wireless database research analysis service indepth dependable covering mainstream specialist sector digital service chain indepth expertise knowledge analyst offer specialist knowledge wealth experience online mobile digital ecosystem intouch market invest great deal effort keeping abreast key market trend shifting sand market demand extensive research activity backed rigorous analysis robust interviewing programme established trusted juniper research trusted digital sector industry leader innovator rely research analysis chart strategic planning process trade ethically conduct business ethically providing quality product service fair price actionable research research designed easily accessed absorbed specific recommendation opinion analysis presented friendly report excel spreadsheet powerpoint slide designed meet highest level quality clarity juniper research located main office located michael church cottage house building great historical interest tudor built manor house section ground floor dating back newer part building constructed era isaac newton american declaration independence period building farming and latterly victorian period children school today building house future gazing technology research firm registered england based basingstoke heart tech corridor minute central london heathrow contact juniper research church cottage house church square basingstoke hampshire rgqw tel fax email navigation home researchstore service subscription consultancy data resource blog press client contact myjuniper career legal privacy cooky term condition juniper research registered england wale company copyright juniper research licensor right reserved built ","m_szGeo1":"","m_szSourceType":"source_general","m_szSrcUrl":"http://www.juniperresearch.com/about-us","m_Places":["Mobile","Uk","Us","Worldwide Smart Cities","North America","Europe","England","London"],"m_People":["Tony Crabtree"],"m_Companies":["Fintech","Powerpoint","St Michael's Church","Juniper Research Ltd","Wales Company"],"m_BiGrams":["mobile online","juniper research","home researchstore","subscription consultancy","worldwide digital","researchstore service","service subscription","consultancy data","data resource","resource blog","blog press","press client","client contact","contactless payment","internet thing","sector digital","digital ecosystem"],"m_TriGrams":["home researchstore service","researchstore service subscription","service subscription consultancy","subscription consultancy data","consultancy data resource","data resource blog","resource blog press","blog press client","press client contact"],"m_SocialTags":[],"m_Topics":[],"m_Industry":[],"m_Technology":[],"m_BiCnt":[8,7,4,4,4,3,3,3,3,3,3,3,3,3,3,3,3],"m_TriCnt":[3,3,3,3,3,3,3,3,3],"m_iDocBodyWordCnt":639}
