{"m_szDocID":"1141002","m_szDocTitle":"Energy Efficiency News Buffet | CleanTechnica","m_szYear":"2014","m_szDocSumamry":"textArticle -------------------- Energy Efficiency News Buffet July 26th, 2014 by Zachary Shahan   As noted in  an article yesterday , I’ve been very busy in the past month (well, months…) moving into a new home and following the birth of a sweet little cleantech lover. Inevitably, “roundup articles” of important or interesting cleantech news we didn’t cover dropped off as a result. With a big backlog of stories I wanted to share, I’m breaking them up into even more articles than normal. Here’s one on energy efficiency news. Your refrigerator is one of the biggest electricity hogs in your hous","m_szDocBody":"energy efficiency new buffet zachary shahan noted yesterday ive busy past month well month moving home birth sweet cleantech lover inevitably roundup article important interesting cleantech new didnt cover dropped result big backlog storey wanted share breaking article normal here energy efficiencynew refrigerator biggest electricity hog house make efficient cleaning condenser coil here that green living ideas instal waterefficient shower head how read piece peter young green living ideas step instal shower flow valve adapter peter you green living ideas youre energyefficient product market energyefficient light bulb lindsay wilson video making switch intelligent informed way shrink footprint electricitygulping giant home air conditioning unit lindsay tip cut cooling load videos shrink footprint turn dang gadget shrink footprint bigger gadget lighting energy power car assuming dont huge lindsay discusse way understand youremission vehicle shrink footprint matter vehicle drive hack fuel emission way lindsay offer tip efficient driving shrink footprint efficient road transit modern age call part sharing economy right shrink footprint led work ingreenhouse whos surprised green building element europe losing energy efficiency lead how energypost energy efficient goal least progress cleantechnicas completely free electric car report electric car early adopter follower want date hottest cleantech new subscribing free cleantech newsletter eye sectorspecific new also free solar energy newsletter electric vehicle newsletter wind energy newsletter tag air conditioning cfl diy shower flow valve adapter energy efficient driving energy efficiency energy efficiency target europe greenhouse hypermiling refrigerator sharing economy shower flow valve adapter waterefficient shower head zachary shahan tryin and specy letter time spend time cleantechnica director chief editor otherwise enthusiastically fulfilling duty obsession gas solar love planetsave bikocity president important media zach recognised globally solar energy electric car energy storage wind energy expert speak related conference event connect social media zacharyshahancom related post ","m_szGeo1":"United States","m_szSourceType":"source_industry","m_szSrcUrl":"http://cleantechnica.com/2014/07/26/energy-efficiency-news-buffet/","m_Places":["Europe"],"m_People":["Zachary Shahan","Peter Young","Lindsay Wilson"],"m_Companies":["Eu","Target"],"m_BiGrams":["shrink footprint","energy efficiency","green living","living ideas","shower flow","flow valve","valve adapter","electric car"],"m_TriGrams":["green living ideas","shower flow valve","flow valve adapter"],"m_SocialTags":[],"m_Topics":[],"m_Industry":[],"m_Technology":[],"m_BiCnt":[6,4,3,3,3,3,3,3],"m_TriCnt":[3,3,3],"m_iDocBodyWordCnt":291}
