{"m_szDocID":"1394301","m_szDocTitle":"In Sweden, your next car-charging spot could be at someone else's house - Roadshow","m_szYear":"2016","m_szDocSumamry":"textArticle -------------------- In Sweden, your next car-charging spot could be at someone else's house Volkswagen's diesel deadline delayed...again In Sweden, your next car-charging spot could be at someone else's house Renault has launched a service called Elbnb where people share their power outlets with drivers of electric vehicles for a price. Bonnie Burton Crave freelancer Bonnie Burton is the best-selling author of \"The Star Wars Craft Book\" and host of the Web show \"Geek DIY.\" When she's not writing or vlogging about sci-fi pop culture, robot fighters, and taco-delivery drones, she en","m_szDocBody":"sweden carcharging spot else house volkswagen diesel deadline delayedagain sweden carcharging spot else house renault launched service called elbnb people share power outlet driver electric vehicle price bonnie burton crave freelancer bonnie burton bestselling the star war craft book host web show geek diy writing vlogging scifi pop culture robot fighter tacodelivery drone enjoy acting benedict cumberbatch replicant fantasy admiral sackbar puppet bonnie full bio sweden carcharging spot else house share sweden carcharging spot else house enlarge image elbnb online platform aim add handy charging location sweden renault home heart home sweden energy stored people hoping give electric car added boost renault launched elbnb service sweden transform house charging station electric car related storey germany mandating electric car yet elbnb online platform meant add handy charging location country encourage resident lessen carbon footprint driving electric car privatehome station featured map quickly located electriccar driver charging price time determined driver homeowner swede sharing economy car apartment lar hglin renault nordic brand engagement manager statement after conversation local politician initiative positively perceived swede ready start sharing power outlet service local politician move faster legislation build publicly accessible charging station sweden electric car reality year year environmental issue big topic infrastructure lacking hglin said that started elbnb initiative run local showing swede ready contribute political action slow show making case greener road easy charging electric car tag datemeta ","m_szGeo1":"United States","m_szSourceType":"source_news","m_szSrcUrl":"http://www.cnet.com/roadshow/news/in-sweden-your-next-car-charging-spot-could-be-at-someone-elses-house/","m_Places":["Sweden","Germany"],"m_People":["Bonnie Burton","Benedict Cumberbatch","Sackbar","Lars HÃ¶glin"],"m_Companies":["Volkswagen","Diesel","Renault","Star"],"m_BiGrams":["electric car","sweden carcharging","carcharging spot","spot else","else house"],"m_TriGrams":["sweden carcharging spot","carcharging spot else","spot else house"],"m_SocialTags":[],"m_Topics":[],"m_Industry":[],"m_Technology":[],"m_BiCnt":[6,4,4,4,4],"m_TriCnt":[4,4,4],"m_iDocBodyWordCnt":225}
