{"m_szDocID":"1450744","m_szDocTitle":"Wozniak talks: Self-driving cars, Apple Watch, and how AI will benefit humanity","m_szYear":"2016","m_szDocSumamry":"textArticle -------------------- Wozniak talks: Self-driving cars, Apple Watch, and how AI will benefit humanity Teena Hammond Pin it Send This article, Wozniak talks: Self-driving cars, Apple Watch, and how AI will benefit humanity , originally appeared on TechRepublic.com . View photos Steve Wozniak talks to John Dixon, Freescale's director of corporate marketing, at the Freescale Technology Forum 2015 in Austin, Texas. Â Image: Freescale Steve Wozniak forsees a world far in the future controlled by artificial intelligence. This used to scare him, but after reasoning his way through it in a u","m_szDocBody":"wozniak talk selfdriving car apple watch benefit humanity teena hammond pin send article wozniak talk selfdriving car apple watch benefit humanity originally appeared techrepubliccom photos steve wozniak talk john dixon freescale director corporate marketing freescale technology forum austin texas image freescale steve wozniak forsee world future controlled artificial intelligence scare him reasoning uniquely woz way decided benefit humanity long run theyre smarter smarter realise wozniak told audience people today moody theatre austin texas part freescale technology forum run wozniak lie awake worry concept finally realised its turn good human hundred year stream ability smart nature human part nature fear replaced computer god originally artificial intelligence world controlled computer slowly happening internet iot pointed out meant iot bad thing mean internet thing think internet thing world send message computer today saying build internet thing need make nice human this turned surprise family pet care time said idea year ago started feeding dog fillet steak chicken night other quipped wozniak utilise iot fun right stage change phone prank life let see morning california honk horn garage make wife fedex guy shown early morning turn light phone harass wife hewlettpackard early year wozniak talked bit started innovating engineer hewlettpackard originally triggered desire build computer work hewlettpackard wanted computer share computer engineer wanted badly build myself wanted computer type programme into said all school college day computer problem sleep thinking hard wake thinking solution good bad steve wozniak time said computer big expensive boxe front panel light realised afford owned television learned analogue television school electronic lucked built project arpanet university computer arpanet rigged home keyboard just free money said laughed recalled back then computer ram ideas adding colour monitor tired mind wandering thought colour ataris arcade game worked steve job small project written breakout atari back think god almighty mind wandered resulting colour monitor appeared apple machine started personal computer movement noted previously techrepublic letting mind wander way innovate wozniak said all school college day computer problem sleep thinking hard wake thinking solution good bad oftentime forget dream said started writing down discovered solution dreaming good discarded before mind thinking time nerd girlfriend wife lot free time added spend lot time innovating because said hewlettpackard value day unbelievable making tool engineer need hewlettpackard policy part storeroom design supervisor approved said work head home heat dinner then said back office work project fun wozniak developed computer said offered hewlettpackard first turned time personal computer good did because bought they built boring product engineer colour animation fun apple made huge change there creating computer important social change accomplish knew improve communication the thought type message computer people read hour later man turned thought photos apple computer steve wozniak built image zdnet showing computer homebrew computer club friend job showed said you this crowd demonstrated said start computer company sell board build sell computer apple starting exit plan wozniak talked apple began steve young early business course money mentor mike markkula owned apple stock start technology company told role steve role photos steve wozniak steve job circa image apple exit plan thought company acquired stuff company forever nowaday entrepreneur plan selling year think desperately passionate reason when started apple investor mike markkula thought billon dollar company year thought however successful life talk bigger number thought you make time current salary wozniak job thought apple people family recipe hand balance chequebook luckily wrong for company failed wozniak said photos apple computer launched tech revolution image zdnet soon the killer app along helped small business owner set basic accounting programme sale shot time realised bigger market small business direction based killer app ill idea start riches turned big money start inside head wanted work hewlettpackard design investor leave hewlettpackard said ive moonlighting said decision tuesday wozniak said said engineer life hewlettpackard finally turned around friend mine convinced start company stay engineer engineer apple like wow thought kick ran company engineer kick out people wozniak considered founder addition job makkula huge wealth top people early day deserved more gave million stock people considered founder stop there engineer marketing people apple sold preipo stock price make house public force thinking people afraid confrontation apple watch john dixon freescale director corporate marketing pointed wozniak wearing apple watch wozniak explained apple employee discount apple watch officially employee person payroll beginning somehow plane crash shrug photos image techrepublic tim cook employee apple watches trouble said bought one preferred model opted expensive watch said you buy watch buy band apple level watches difference band spend band said mimicking sale pitch riches wozniak cost conscious purchase quipped the time buy gold one buy band gold rolex matter watch work like watch determined they shipped yet said apple future selfdriving car wozniak interested selfdriving car that artificial intelligence obstacle detour noticing thing task show ups simulating intelligence there fewer accident human driver law passed human driver road start giving car gave cds order uber car pick apple share that should company apple market huge growth auto market huge make sense wozniak said adding specific apple plan higherup lowerdown friend apple respect product development broadband latenight download switching gear wozniak talked longtime home los gatos calif home notch silicon valley broadband said ordered movie night wait hour download wife trick navigation programme called navigon iphone take hour download updated map month time drove apple store town parked night long parked midnight morning downloading true insisted easier live broadband said love home netflix city pet rock invented video game industry began los gatos tip woz innovate wozniak modern day thomas edison share wisdom invent worthwhile clear head innovate said how clear head out start clean slate like here world have improve type engineer type study book solve problem type invent ideas large company problem encouraging innovation procedure rule asked company think innovative now said real small group scratch nothing replacement uber twist innovate idea goal goal ideas occur kind people large company bureaucracy chain command hard company set division called innovation division secret spin city how clear head out start clean slate like here world have improve steve wozniak silicon valley campus place hewlettpackard people independent thinker apple executive campus place control city block young engineer said the engineer spent hour day thinking working solution engineer would kid left work engineer age play role innovation you physical energy mental energy younger are point say person designer inventor lot designed fun steve job town make money apple that said key innovating differently longtime apple slogan think different wozniak worked hewlettpackard slump industry company laying employee employer decided board cut salary give employee off lot people that off great young engineer liberal approach agreed friday off man gave threeday weekend portland oregon steve job college visit friend thing way doing said innovation sake making cool have making people make money thought way innovating clever trick back created computer said started think save part chip panel fewer part money think create job better motivation important content said show off motivating factor found apply education key learn gonna segway augmented reality wozniak drawn thing favourite invention segway twowheeled electric vehicle debuted quickly bought market frequently head town comparing riding bicycle car problem dealing seatbelt fuel tinker segway arrived photos steve wozniak play segway polo image daniel the key code told segway fast allowed online started ordering part build board programme key speed code safety conscious laugh tell people ive segway mph helmet add back car wife carry segway back car prius swapped tesla invention touched augmented reality preventing masse accepting its real abundant real cost efficient yet take grow market job thought macintosh over year build macintosh market replace apple market augmented reality said love glass small processor small interface justify cost virtual reality realm oculus rift gear will change world world change world technology emotional feeling left over acceptance augmented reality virtual reality gear slowed cost equipment said android apple question audience asked wozniak would android involved apple response lot reason apple talking smartphone iphone set pattern admire company set direction apple product make work people expert favour people technical skill the rest call macintosh day like tech tested android phone finally pretty useable time samsung galaxy galaxy note smile phone automatically photo large screen those big screen stood year apple friend poopoo steve job throw nuclear war putting android market compete thermonuclear war compete left big screen market wide open samsung year gave big chunk market year pleased apple finally offer smartphone large small screen educating future inventor wozniak strong opinion education student spending time focused subject passionate about kid microprocessor instance said its bad learn subject school microprocessor school day kid thirdyear college student pursue main interest ignore other year college graduate level course hardware software design read answer question halfway book day class started school thinking yourself said wozniak mentioned robotic competition freescale foundation support part initiative promote study science technology engineering math underprivileged underrepresented student wozniak acted judge competition first robotic school student discover technology about build mechanic motor power supply microprocessor software discipline discover this life said woz jumping completely separate subject mind wandered said piece random advice mother hospital call back computer hospital ","m_szGeo1":"United States","m_szSourceType":"source_news","m_szSrcUrl":"https://www.yahoo.com/news/wozniak-talks-self-driving-cars-205900126.html?ref=gs","m_Places":["Austin, Texas","California","Starting","Silicon Valley","Portland, Oregon","Tesla"],"m_People":["Steve Wozniak","Teena Hammond","John Dixon","Said He Still Frequently Uses","Mike Markkula","Tim Cook","Thomas Edison","Daniel Terdiman"],"m_Companies":["Freescale Technology","Fedex","Hewlett-packard","Atari","Apple","Homebrew Computer Club","Revolution","Rolex","Uber","Netflix","Facebook","Segway","Cnet","Mph","Segways","Google","Oculus","Samsung","College I","Freescale Foundation"],"m_BiGrams":["steve wozniak","apple watch","steve job","selfdriving car","wozniak said","augmented reality","wozniak talk","benefit humanity","photos steve","artificial intelligence","internet thing","wozniak talked","clear head"],"m_TriGrams":["photos steve wozniak"],"m_SocialTags":[],"m_Topics":[],"m_Industry":[],"m_Technology":[],"m_BiCnt":[7,5,5,4,4,4,3,3,3,3,3,3,3],"m_TriCnt":[3],"m_iDocBodyWordCnt":1508}
