{"m_szDocID":"1493005","m_szDocTitle":"The Queens Speech in Full Text : unitedkingdom","m_szYear":"2016","m_szDocSumamry":"The Queens Speech in Full Text : unitedkingdom  012The Queens Speech in Full Text (self.unitedkingdom)submitted 1 month ago by ObidomCheshireTaken from: https://www.gov.uk/government/speeches/queens-speech-2016 My Lords and Members of the House of Commons. My government will use the opportunity of a strengthening economy to deliver security for working people, to increase life chances for the most disadvantaged and to strengthen national defences. My ministers will continue to bring the public finances under control so that Britain lives within its means, and to move to a higher wage and lower","m_szDocBody":"queen speech full unitedkingdom the queen speech full selfunitedkingdomsubmitted month ago obidomcheshiretaken from lord member house common government opportunity strengthening economy deliver security working people increase life chance disadvantaged strengthen national defence minister continue bring public finance control britain live mean move higher wage lower welfare economy work rewarded support economic recovery create job apprenticeship legislation introduced ensure britain infrastructure businesse grow measure brought forward create household speed broadband legislation introduced improve britain competitiveness make united kingdom world leader digital economy minister ensure united kingdom forefront technology form transport including autonomous electric vehicle spread economic prosperity government continue support development northern powerhouse england power devolved directly elected mayor including power governing local bus service legislation local authority retain business rate giving freedom invest local community government support aspiration promote home ownership commitment build million home week anticorruption summit london legislation introduced tackle corruption money laundering tax evasion government continue work deliver nhs service day week england legislation introduced ensure overseas visitor pay health treatment receive public expense legislation introduced tackle deepest social problem society improve life chance bill introduced ensure children adopted family delay improve standard social work opportunity young people care england tackle poverty deprivation including family instability addiction debt government introduce indicator measuring life chance legislation introduced establish soft drink industry levy tackle childhood obesity measure introduced lowestincome family save save scheme create lifetime isa young people save longterm government continue reform public service hardesttoreach bill brought forward lay foundation educational excellence school giving child start life fairer balance school national funding formula ensure people opportunity education legislation introduced support establishment university promote choice competition higher education sector government legislate reform prison court give individual chance prison governor unprecedented freedom ensure prisoner receive education inefficient prison closed institution built prisoner put effectively work action ensure mental health provision individual criminal justice system government continue work bring community strengthen society legislation introduced prevent radicalisation tackle extremism form promote community integration national citizen service permanent statutory footing government continue safeguard national security minister invest britain armed force honouring military covenant meeting nato commitment spend national income defence act secure longterm future britain nuclear deterrent government continue play leading role world affair global presence tackle climate change address major international security economic humanitarian challenge government continue work resolve conflict ukraine play leading role campaign daesh support international effort bring peace syria lasting political settlement britain commitment international development spending honoured helping deliver global stability support sustainable development goal prevent threat national security prince philip forward welcoming excellency president colombia state visit november government continue legislation modernise law governing oversight investigatory power law enforcement security intelligence agency legislation strengthen capability accountability police service england wale government hold referendum membership european union proposal brought forward british bill right minister uphold sovereignty parliament primacy house common government continue work cooperation devolved administration implement extensive power scotland act establish strong lasting devolution settlement wale government work northern ireland secure progress implementing stormont house fresh start agreement member house common estimate public service laid you lord member house common measure laid you pray blessing almighty god rest counsel commentsshare deleted point point point month ago childrensuch absolute waste time obvious parroting cameron osborne spiel cameron stuck hand arse started ventriloquist act common minister continue bring public finance control britain live mean move higher wage lower welfare economy work rewarded tae fuck legislation introduced improve britain competitiveness make united kingdom world leader digital economy snooper charter entire tech community scared scare tech startup firm government continue work deliver nhs service day week england continuing refuse talk actual medical staff run nhs tackle poverty deprivation including family instability addiction debt government introduce indicator measuring life chance legislation introduced establish soft drink industry levy tackle childhood obesity the start announcement tackling deprivation end taxing soft drink people living poverty bent forced live slum sunny fucking pepsi bill brought forward lay foundation educational excellence school giving child start life delight nicky morgan year cant absolute parody rid queen speech point cambo osber stand announce crap themselve called directly year lady shield permalinkembedsavereportreplyquager point point point month ago children obvious parroting cameron osborne spiel cameron stuck hand arse started ventriloquist act common sound listened queen speech literally point permalinkembedsaveparentreportgive goldreplyadrianblakeyorkshireman living dorset point point point month ago childrenshes supposed publicly announce political view supposed conduit democratically elected government act constitutionally convenient service permalinkembedsaveparentreportgive goldreply quager point point point month ago children obvious parroting cameron osborne spiel cameron stuck hand arse started ventriloquist act common sound listened queen speech literally point permalinkembedsaveparentreportgive goldreply adrianblakeyorkshireman living dorset point point point month ago childrenshes supposed publicly announce political view supposed conduit democratically elected government act constitutionally convenient service permalinkembedsaveparentreportgive goldreply","m_szGeo1":"United States","m_szSourceType":"source_general","m_szSrcUrl":"https://www.reddit.com/r/unitedkingdom/comments/4jwumv/the_queens_speech_in_full_text/?ref=search_posts","m_Places":["Queens","Britain","United Kingdom","England","London","Isa","Ukraine","Syria","Colombia","Wales","Scotland","Northern Ireland","Uk"],"m_People":["Prince Philip","Nicky Morgan"],"m_Companies":["Lifetime","Nato","Daesh","European Union","Parliament","Pepsi"],"m_BiGrams":["legislation introduced","government continue","queen speech","continue work","house common","life chance","brought forward","member house","introduced ensure","united kingdom","soft drink","obvious parroting","parroting cameron","cameron osborne","osborne spiel","spiel cameron","cameron stuck","stuck hand","hand arse","arse started","started ventriloquist","ventriloquist act","act common"],"m_TriGrams":["government continue work","member house common","obvious parroting cameron","parroting cameron osborne","cameron osborne spiel","osborne spiel cameron","spiel cameron stuck","cameron stuck hand","stuck hand arse","hand arse started","arse started ventriloquist","started ventriloquist act","ventriloquist act common"],"m_SocialTags":[],"m_Topics":[],"m_Industry":[],"m_Technology":[],"m_BiCnt":[10,10,5,5,4,4,4,3,3,3,3,3,3,3,3,3,3,3,3,3,3,3,3],"m_TriCnt":[5,3,3,3,3,3,3,3,3,3,3,3,3],"m_iDocBodyWordCnt":775}
