{"m_szDocID":"1564451","m_szDocTitle":"House OKs tax-cut package, first leg of year-end budget deal - Chicago Tribune","m_szYear":"2015","m_szDocSumamry":"textArticle -------------------- House OKs tax-cut package, first leg of year-end budget deal House Speaker Paul D. Ryan J. Scott Applewhite / Associated Press House Speaker Paul D. Ryan (R-Wis.) was apparently able to overcome internal party divisions to work out a spending bill and tax measure. House Speaker Paul D. Ryan (R-Wis.) was apparently able to overcome internal party divisions to work out a spending bill and tax measure. (J. Scott Applewhite / Associated Press) Tribune wire reports Contact Reporter Republicans overwhelmed divided Democrats to whisk tax breaks for businesses, familie","m_szDocBody":"house oks taxcut package leg yearend budget deal house speaker paul ryan scott applewhite press house speaker paul ryan rwis apparently overcome internal party division work spending bill tax measure house speaker paul ryan rwis apparently overcome internal party division work spending bill tax measure scott applewhite press tribune wire report contact reporter republican overwhelmed divided democrat whisk tax break businesse family special interest house congress sped final vote yearcrowning budget accord bankroll government tax measure approved include political coup party expiring tax cut extended permanent including credit company expenditure research equipment purchase reduction lowerearning family household children college student finally tax bill family businesse longterm certainty scrambling year year next declared house speaker paul ryan rwis ryan week ago succeeded deposed speaker john boehner claimed bill passage personal triumph citing drive house back track senate aimed approve tax bill friday chamber planned vote leg budget compromise trillion measure financing government congress ready adjourn january overall budget pact modest side describing deal divided government arguably noteworthy include gop effort halt planned parenthood federal money democratic pushes stiffened gun curb republican voted lockstep tax measure split democrat opposed democrat opportunity make family tax break permanent complained skewed business price tag exceeding billion decade swell federal deficit make money scarcer domestic programme party treasure tribune wire report its trojan horse fooled house minority leader nancy pelosi dcalif attitude shared senate minority leader harry reid dnev backing measure white house president barack obama tax spending bill combined totaled page pelosi added suspense friday spending bill debate questioning democratic vote pass cited opposition lifting yearold ban exporting american crude oil bill lack language letting puerto rico restructure debt avoid bankruptcy largescale democratic opposition significant republican expected oppose measure expenditure excessive late thursday pelosi urged colleague support bill arguing democratic win outweighed atrocious policy ending oil export ban lisa mascaro empower big oil upend victory hardworking american family wrote democratic lawmaker gop leader worked build republican vote exhibited nervousness fate wideranging bill included thing language restricting visafree entry prodding company give cyber threat information government presidential politic provided bit background music senate sen marco rubio rfla presidential candidate complained fox new channel spending bill syrian refugee suggested procedural delay slow measure call attention issue senate majority leader mitch mcconnell rky scheduled vote anyway its perfect wanted mcconnell budget compromise advance conservative priority cutting taxe boosting defence spending tax cut sprinkled spending bill too attract gop vote together bill pare taxe billion year crammed bill provision trimming levy finance obamas prized health care overhaul white house opposed rollback republican democrat savoured them tax medical device suspended year levy health insurer stop year and victory union tax highercost insurance policy postponed year exchange ending oil export ban democrat won extension tax break alternative power source solar wind energy extended tax cut include break teacher commuter timber investor electric vehicle owner maker hard cider drink people state income taxe deduct local sale taxe federal return tax bill make easier group seeking tax exemption information case internal revenue service echo controversy irs admission subjected conservative group seeking status unfairly tough investigation press datemeta ","m_szGeo1":"United States","m_szSourceType":"source_news","m_szSrcUrl":"http://www.chicagotribune.com/news/nationworld/politics/ct-congress-end-of-year-taxes-spending-20151217-story.html","m_Places":["Puerto Rico","United States"],"m_People":["Paul Ryan","J. Scott Applewhite","John Boehner","House Minority Leader","Nancy Pelosi","Harry Reid","President Barack Obama","Lisa Mascaro","Marco Rubio","Mitch Mcconnell"],"m_Companies":["House","Associated Press","Tribune","Democrats","Congress","Senate","White House","Fox News Channel","2020","Internal Revenue Service","Irs"],"m_BiGrams":["spending bill","house speaker","speaker paul","paul ryan","tax measure","ryan rwis","tax break","tax cut","tax bill"],"m_TriGrams":["house speaker paul","speaker paul ryan","paul ryan rwis"],"m_SocialTags":[],"m_Topics":[],"m_Industry":[],"m_Technology":[],"m_BiCnt":[6,4,4,4,4,3,3,3,3],"m_TriCnt":[4,4,3],"m_iDocBodyWordCnt":514}
