{"m_szDocID":"1582050","m_szDocTitle":"Driverless Vehicles Powered by Artificial Intelligence","m_szYear":"2016","m_szDocSumamry":"Driverless Vehicles Powered by Artificial Intelligence $ Daily Business Report M A R K E T S Mercantile Article Archives US Economic Forecast for 2012 and the Election Year Cycle Shop the Local Merchant Economy Right to Work vs Union State Economies Rational Tariffs Lower Irrational Trade Deficits International Business - Davos Style Banking, Housing and Mortgages David Stockman's Viewpoint on the Obama Budget Disaster Regulations Harm Small Business and Protects Corporations Gas Prices as an Indicator of Energy Costs Governments Acting as Venture Capitalists College Education Economics Indust","m_szDocBody":"driverless vehicle powered artificial intelligence daily business report mercantile archive economic forecast election year cycle shop local merchant economy work union state economy rational tariff lower irrational trade deficit international business davos style banking housing mortgage david stockman viewpoint obama budget disaster regulation harm small business protect corporation gas price indicator energy cost government acting venture capitalist college education economic industrial wind production tax credit medicare ryan budget corporate tax rate consequence corporate spying intellectual theft foolish exporting natural gas policy matter time vat tax big small bank loan bankruptcy trend post meltdown era money centre bank stricter financial oversight electric power generation nys growth national debt advantage chinese trade policy unemployment lifestyle immigration hurt american employment bank international settlement big bank small business assault obamacare compound interest debt bubble federal centralization economy parking offshore profit hurt domestic economy record olympic economic financial algorithmic trading goldman sach law global magical mystery tour destroying internet freedom taxation permanent unemployment economy jackal jekyll island federal reserve audit blowing debt bubble riot rotten apple mania gap college cost inflation counterproductive minimum wage mandate derivative meltdown dollar collapse central bank game plan world currency european commission single supervisory mechanism lunacy fema hurricane insurance subsidy taxmageddon holding hand jumping cliff direction equity obama economy fair tax rich business california dreaming bankruptcy pension taxe pay differential private sector federal government long history hsbc money laundering swan dive economy federal reserve pause quantitative easing economic sequestration stateowned bank north dakota chinese takeover free trade zone low interest rate impoverish saver bond bubble expectation currency war race bottom government subsidise bankrupt company economic gun control refuse buy sell federal government cyprus great bank robbery keystone pipeline blockage move imf bric development bank obama budget propose cut social security medicare risk reward bitcoin farm support social welfare internet sale taxe dialectic warren buffett house card irs political hit squad revenue budget projection nsa connexion roubini faber debate hydrofracking boom bust goldman sach learn earn serve federal reserve ben bernanke implication pyrrhic real estate rebound normal parttime employmentyment europe trade deal honeymoon detroit city bankruptcy blue morgan commodity manipulation strange business success venture business evangelism religion nfl marketing machine privacy offshore asset chinese bank quasi government institution forecast doomed economy financial meltdown year corporate profit worker unemployment renminbi reserve currency rehypothecation collateral imf proposal tax bank deposit transfer excluded morgan chase wired insurance company profit obamacare climate change executive order economic nongovernmental organisation business franchising bad deal business christmas season china largest trading nation obamacare job killer trillion debt total matter underground commerce real economy technology future job japanese debt economy individual wealth perspective inevitability financial bubble russian sanction backfire dollar equity ready crash economic reality wealth tax stable bond market international stock safer equity david stockman great deformation chinese japanese deflationary economy euro crisis deepen russias swift settlement alternative swiss business global warming fraud economic nys southern tier secession fear irs tax audit diminish global economic growth government share minimum wage increase economic growth impossible replace business cycle permanent poverty benefit lifting iranian sanction win currency devaluation war labour day work municipal bankruptcy undeniable social security demographic grinch stole christmass business merger soar chinese market crash driverless vehicle powered artificial intelligence bank ready negative interest rate international trade sink baltic dry index sunedison green power bankruptcy inevitability record collection federal taxe breaking rule breaking rule forum batr index hub corporatocracy forbidden history reign terror stuck stupid totalitarian collectivism global gulag inherent autonomy radical reactionary strappado wrack mount solitary purdah duelling twin varying verity war terror hope driverless vehicle powered artificial intelligence joy driving important part american dream open road meant freedom adventure utilitarian objective moving place possess romance reminiscence past lingering memory good time close block trouble possible trait applied distinctly national love affair auto thing time move tech community advancement land travel revolution motor vehicle manufacturer oil industry fuel large part creating big business model money made name ford firestone rubbed shoulder like rockefeller today stable electric hybrid appeal muscle power consumer horsepower save planet believer concerned cost mile dilemma transformed programming software designed thinking driving aptitude passing lane point promise autobahn hangout plugin enhance gaming experience transit well controlling direction rubber meet road jumbo tech giant smell money twentyfirst century bonanza washington post reported google artificial intelligence breakthrough huge impact selfdriving car more researcher created algorithm humanlike ability learn marking significant breakthrough field artificial intelligence part timer uber notice appealing solution car develop level intelligence high wouldnt preloaded map simply scan road front teach drive anywhere account breitbart artificial intelligence breakthrough singularity several company testing selfdriving car theyre expected commercially corner stop make turn economic brave world myth robot artificial intelligence erase job industry predict manufacturing returning shore robot job chinese worker american carmaker massproducing selfdriving electric vehicle bring large wave unemployment caused selfdriving car provide tremendous benefit eliminating traffic accident congestion making commuting time productive reducing energy usage eliminate job million taxi truck driver delivery people xconomy san francisco bay area offer analysis conversation selfdriving car focus personal vehicle fully autonomous car daily commute year commercial trucking selfdriving vehicle emerge sooner company peloton making reality long haul trucking easier technical challenge interstate generally straight line wellmarked digitally mapped definition generally free pedestrian bicycle random obstacle economic productivity truck justify substantial investment sophisticated cameras sensor computer needed autopilot system economic autonomous truck huge due cost shortage driver regulatory limit driving time fuel efficiency gained convoy travelling close peloton formation lastly respective mckinsey company global management consulting firm way autonomous driving redefine automotive world entire description read site industrial fleet lead car oem face decision mobility model emerge carservice landscape car insurer shift business model company reshape supply chain driver time parking easier accident rate drop avs accelerate robotic development consumer application economic dislocation earth shattering however buggy maker round transpiration technology interchange promise employment uplifting henry ford accomplished fivedollar dayjumpstarting middle class well doubt starbuck order iced caramel macchiato change kind benefit consumer expect time everything control transport market bear apple logo microsoft operating system built toyota delivered bezos drone sold musk marketing programming commercial carried ads displaced uaw worker chat smart device unemployment benefit ran out future truck stop nation interstate convert electric plug station dependable green renewal rest areas travelling porn circuit engagement service replace argue true merchant economy alternative metropolis melodrama induced destroying financial future household billionaire rank swell consumer starve trading ferrari sport car dependable argentine criollos steed practical appealing most however compared navigating highway cargo artificial intelligence environment taking greyhound bus attractive ever jame hall batr realpolitik newsletter discuss comment essay batr forum weekly batr newsletter negotium update enter address delivered feedburner free speech forum open public web batr toolbar alexa batr right reserved breaking rule site breaking rule entry breaking rule portal breaking rule breaking rule new breaking rule forum breaking rule batr new batr index sartre commentary sartre commentary forbidden history reign terror stuck stupid totalitarian collectivism radical reactionary inherent autonomy global gulag corporatocracy negotium strappado wrack mount solitary purdah duelling twin varying verity sartre nest gem neocon watch washington merrygoround daily business report hope war terror batr sartre batr sartre world war world war newsletter election race uncensored political newsletter election race batr video batr channel breaking rule channel batr sartre videos breaking rule videos batr sartre tumblr realpolitik montage video bijou batr videos batr forum batr map nest gem archive scvhn global gulag archive strappado wrack archive view mount archive cohocton wind watch citizen power alliance batr hub site batr site web powered freefind web ","m_szGeo1":"","m_szSourceType":"source_general","m_szSrcUrl":"http://www.batr.org/negotium/012716.html","m_Places":["United States","Jekyll Island","California","Sale","Warren","Europe","Detroit City","China","Russian Federation","Hub","Well","Toyota","Argentina","Enter","Washington","Cohocton"],"m_People":["David Stockman","Harm Small Business","Ben Bernanke","Renminbi Soon","Henry Ford","Batr Sartre"],"m_Companies":["Daily Business","Cycle","Davos","Viewpoint","College Education Economics","Medicare","Small Bank Loans","Bank For International Settlements","Goldman Sachs","Federal Reserve","Rotten Apple","Gap","College Costs","Central Banks","European Commission","Fema","Federal Government","Hsbc","Bank Of North Dakota","Zones","Imf","Development Bank","Social Security","Irs","Google","Nsa Connection","Bust","The Federal Reserve","Rebound","Nfl","Jp Morgan","Underground","Eu","Sunedison","Revolution","Uber","2020","Mckinsey & Company","Starbucks","Apple","Microsoft","Facebook","Batr Sartre Facebook","Twitter","War Facebook","Race Facebook","Youtube","Power Alliance"],"m_BiGrams":["breaking rule","artificial intelligence","selfdriving car","batr sartre","driverless vehicle","vehicle powered","powered artificial","federal reserve","global gulag","strappado wrack"],"m_TriGrams":["driverless vehicle powered","vehicle powered artificial","powered artificial intelligence"],"m_SocialTags":[],"m_Topics":[],"m_Industry":[],"m_Technology":[],"m_BiCnt":[11,8,4,4,3,3,3,3,3,3],"m_TriCnt":[3,3,3],"m_iDocBodyWordCnt":1247}
