{"m_szDocID":"1587802","m_szDocTitle":"Gas Prices as an Indicator of Energy Costs","m_szYear":"2012","m_szDocSumamry":"Gas Prices as an Indicator of Energy Costs $ Daily Business Report M A R K E T S Mercantile Article Archives US Economic Forecast for 2012 and the Election Year Cycle Shop the Local Merchant Economy Right to Work vs Union State Economies Rational Tariffs Lower Irrational Trade Deficits International Business - Davos Style Banking, Housing and Mortgages David Stockman's Viewpoint on the Obama Budget Disaster Regulations Harm Small Business and Protects Corporations Gas Prices as an Indicator of Energy Costs Governments Acting as Venture Capitalists College Education Economics Industrial Wind an","m_szDocBody":"gas price indicator energy cost daily business report mercantile archive economic forecast election year cycle shop local merchant economy work union state economy rational tariff lower irrational trade deficit international business davos style banking housing mortgage david stockman viewpoint obama budget disaster regulation harm small business protect corporation gas price indicator energy cost government acting venture capitalist college education economic industrial wind production tax credit medicare ryan budget corporate tax rate consequence corporate spying intellectual theft foolish exporting natural gas policy matter time vat tax big small bank loan bankruptcy trend post meltdown era money centre bank stricter financial oversight electric power generation nys growth national debt advantage chinese trade policy unemployment lifestyle immigration hurt american employment bank international settlement big bank small business assault obamacare compound interest debt bubble federal centralization economy parking offshore profit hurt domestic economy record olympic economic financial algorithmic trading goldman sach law global magical mystery tour destroying internet freedom taxation permanent unemployment economy jackal jekyll island federal reserve audit blowing debt bubble riot rotten apple mania gap college cost inflation counterproductive minimum wage mandate derivative meltdown dollar collapse central bank game plan world currency european commission single supervisory mechanism lunacy fema hurricane insurance subsidy taxmageddon holding hand jumping cliff direction equity obama economy fair tax rich business california dreaming bankruptcy pension taxe pay differential private sector federal government long history hsbc money laundering swan dive economy federal reserve pause quantitative easing economic sequestration stateowned bank north dakota chinese takeover free trade zone low interest rate impoverish saver bond bubble expectation currency war race bottom government subsidise bankrupt company economic gun control refuse buy sell federal government cyprus great bank robbery keystone pipeline blockage move imf bric development bank obama budget propose cut social security medicare risk reward bitcoin farm support social welfare internet sale taxe dialectic warren buffett house card irs political hit squad revenue budget projection nsa connexion roubini faber debate hydrofracking boom bust goldman sach learn earn serve federal reserve ben bernanke implication pyrrhic real estate rebound normal parttime employmentyment europe trade deal honeymoon detroit city bankruptcy blue morgan commodity manipulation strange business success venture business evangelism religion nfl marketing machine privacy offshore asset chinese bank quasi government institution forecast doomed economy financial meltdown year corporate profit worker unemployment renminbi reserve currency rehypothecation collateral imf proposal tax bank deposit transfer excluded morgan chase wired insurance company profit obamacare climate change executive order economic nongovernmental organisation business franchising bad deal business christmas season china largest trading nation obamacare job killer trillion debt total matter underground commerce real economy technology future job japanese debt economy individual wealth perspective inevitability financial bubble russian sanction backfire dollar equity ready crash economic reality wealth tax stable bond market international stock safer equity david stockman great deformation chinese japanese deflationary economy euro crisis deepen russias swift settlement alternative swiss business global warming fraud economic nys southern tier secession fear irs tax audit diminish global economic growth government share minimum wage increase economic growth impossible replace business cycle permanent poverty benefit lifting iranian sanction win currency devaluation war labour day work municipal bankruptcy undeniable social security demographic grinch stole christmass business merger soar chinese market crash driverless vehicle powered artificial intelligence bank ready negative interest rate international trade sink baltic dry index sunedison green power bankruptcy inevitability record collection federal taxe breaking rule breaking rule forum batr index hub corporatocracy forbidden history reign terror stuck stupid totalitarian collectivism global gulag inherent autonomy radical reactionary strappado wrack mount solitary purdah duelling twin varying verity war terror hope gas price indicator energy cost consumer reminder pain experienced fill pump drain pocketbook growing economic dislocation diminished vitality prospect turnaround dim gas approaches gallon beyond idea time economy effected unreasonable cost energy rising impact gas price personal burden everyday budget price fuel synopsis while crude oil traded global market gasoline part regional market price crude oil account half price gallon gasoline transition supply affect shortterm availability gasoline peak summer driving season refinery adjusting gasoline formulas state switching ethanolblended gasoline state require specific formulation gasoline separate gasoline formulas region countryand difficult import gasoline supply region another gallon gasoline subject numerous taxe fee vary state crude oil processed refinery finished gasoline product transported terminal sold wholesaler distribution wholesaler retail network delivered retail location retailer set street price factor industry explanation establishes price but commodity manipulated crude oil business insider add viewpoint real reason gasoline price surging you heard price barrel oil domestic west texas intermediate price oil international benchmark brent crude surged year problem judging global pace oil demand growth epicentre growth moved asia china particular yet due lack prompt alternative readily oil data global guide health oil market suggest worse gas easily crush national economy the usa evolved twotier gas market supply crude canada bakken field created lower cost supply central portion country differential notable market spread wti future contract settle physical delivery oklahoma lls louisiana light sweet crude pricing crude big gulf refinery conclusion factor suggest domestic retail price gas vary reason stated level hurt based individual transportation however added cost moving consumer good experienced added charged register published government inflation rate skewed tap actual increase buying replacing gasoline personal vehicle efficient cost form energy deny practical diesel fuel road eighteenwheeler promising conversion natural gas honda cng version automobile gasoline lot longer hybrid electric car reason unmistakable lowest cost fuel equate identical vehicle performance win battle marketplace spite aspect business government corporate partner pushing force conversion gasoline yugo syndrome government motor volt failure sell consumer ridiculous car clear chevy volt fleet sale rise government purchase increase according volt sold retail customer fleet purchaser government purchase vehicle rose year represent conflict obama administration vested interest gms success spend taxpayer dollar support company election near favourite obama corporate collaborator general electric muscle coverup botched venture forcing employee chevy volt report memo leaked green car report lay ges plan fleet volt expected people crying foul memo employee healthcare americas team explain sedan crossover minivan purchase replaced chevy volt field engineer exempt drive company volt offer estimate installation level charging station allgas allowed electric option employee opt volt programme compensated expense ignore economic cost failed foolish green energy project idea forced buying expensive government subsidised vehicle future border irrational paranoia environmental true believer global warming hoax pay price gasoline rich afford opposition building keystone pipeline reduce addition oil supply lauded peak oil charlatan seek higher gas price compel consumer convert anti fossil fuel existence reduce energy cost abolishing obama green energy tax lower gasoline price foster dynamic economic growth long policy wonk determined bankrupt public gas cost experience fallen standard living jame hall discuss comment essay batr forum weekly batr newsletter negotium update enter address delivered feedburner free speech forum open public web batr toolbar alexa batr right reserved breaking rule site breaking rule entry breaking rule portal breaking rule breaking rule new breaking rule forum breaking rule batr new batr index sartre commentary sartre commentary forbidden history reign terror stuck stupid totalitarian collectivism radical reactionary inherent autonomy global gulag corporatocracy negotium strappado wrack mount solitary purdah duelling twin varying verity sartre nest gem neocon watch washington merrygoround daily business report hope war terror batr sartre batr sartre world war world war newsletter election race uncensored political newsletter election race batr video batr channel breaking rule channel batr sartre videos breaking rule videos batr sartre tumblr realpolitik montage video bijou batr videos batr forum batr map nest gem archive scvhn global gulag archive strappado wrack archive view mount archive cohocton wind watch citizen power alliance batr hub site batr site web powered freefind web ","m_szGeo1":"","m_szSourceType":"source_general","m_szSrcUrl":"http://www.batr.org/negotium/022912.html","m_Places":["United States","Jekyll Island","California","Sale","Warren","Europe","Detroit City","China","Russian Federation","Hub","West Texas","Brent","Asia","Canada","Oklahoma","Louisiana","Yugo","Americas","Enter","Washington","Cohocton"],"m_People":["David Stockman","Harm Small Business","Ben Bernanke","Renminbi Soon","Chevy Volts","Chevy Volt","James Hall","Batr Sartre"],"m_Companies":["Daily Business","Cycle","Davos","Viewpoint","College Education Economics","Medicare","Small Bank Loans","Bank For International Settlements","Goldman Sachs","Federal Reserve","Rotten Apple","Gap","College Costs","Central Banks","European Commission","Fema","Federal Government","Hsbc","Bank Of North Dakota","Zones","Imf","Development Bank","Social Security","Irs","Google","Nsa Connection","Bust","The Federal Reserve","Rebound","Nfl","Jp Morgan","Underground","Real","Eu","Sunedison","Transitions","Diesel","Honda","Volt","Volts","Obama Administration","General Electric","Ge Healthcare","Facebook","Batr Sartre Facebook","Twitter","War Facebook","Race Facebook","Youtube","Power Alliance"],"m_BiGrams":["breaking rule","gas price","energy cost","crude oil","batr sartre","price indicator","indicator energy","federal reserve","economic growth","global gulag","strappado wrack","chevy volt"],"m_TriGrams":["gas price indicator","price indicator energy","indicator energy cost"],"m_SocialTags":[],"m_Topics":[],"m_Industry":[],"m_Technology":[],"m_BiCnt":[11,5,4,4,4,3,3,3,3,3,3,3],"m_TriCnt":[3,3,3],"m_iDocBodyWordCnt":1257}
