{"m_szDocID":"1597633","m_szDocTitle":"Johnson Controls and Tyco announce future executive leadership team upon close of planned merger","m_szYear":"2016","m_szDocSumamry":"textArticle -------------------- Johnson Controls and Tyco announce future executive leadership team upon close of planned merger May 27, 2016, 08:00 ET      from Johnson Controls MILWAUKEE and CORK, Ireland, May 27, 2016 /PRNewswire/ -- Johnson Controls (NYSE: JCI ) and Tyco International (NYSE: TYC ) today announced the senior executive team that will lead the combined company following the close of their planned merger, which is expected on or around Oct. 1, 2016.  As previously announced, at the effective time of the merger, Johnson Controls chairman and chief executive officer Alex Molina","m_szDocBody":"johnson control tyco announce future executive leadership team close planned merger johnson control milwaukee cork ireland johnson control nyse jci tyco international nyse tyc today announced senior executive team lead combined company close planned merger expected oct previously announced effective time merger johnson control chairman chief executive officer alex molinaroli appointed role combined company tyco chief executive officergeorge oliverwill serve president chief operating officer responsibility operating businesse leading integration director company boardmr molinaroli serve chairman chief executive officer month closing time oliver chief executive officer molinaroli executive chair year oliver chairman chief executive officer pleased reach major milestone journey bring great company create global leader building product technology integrated solution energy storage molinaroli this team talented executive ensure combined company continue thrive grow create unique customer shareholder forward bringing complementary capability turn possibility smart building urban environment reality world corporate executive officer addition oliver completion merger enterprise leader report molinaroli grady crosby serve vice president public affair chief diversity officer hold role johnson control simon davis serve vice president chief human resource officer hold role johnson control kim metcalfkupre serve vice president chief marketing officer hold role johnson control judy reinsdorf serve executive vice president general counsel hold role tyco john repko serve vice president chief information officer chief information officer enterprise transformation leader tyco brian stief serve executive vice president chief financial officer hold role johnson control jeff william serve vice president operation engineering hold role johnson control business leader completion merger business leader report oliver bill jackson executive vice president president building efficiency trent nevill vice president president asia pacific colleen repplier president fire protection product girish rishi executive vice president north america integrated solution service tyco retail solution mike ryan president security product life safety product johan pfeiffer executive vice president rest world integrated solution service joe walicki vice president president power solution close transaction johnson control tyco continue operate independently current leadership structure johnson control johnson control global diversified technology industrial leader serving customer country employee create quality product service solution optimise energy operational efficiency building leadacid automotive battery advanced battery hybrid electric vehicle seating component system automobile commitment sustainability date back root invention electric room thermostat growth strategy increasing market share committed delivering shareholder making customer successful corporate responsibility magazine recognised johnson control company annual corporate citizen list additional information visit follow johnson control investor relation tyco tyco nyse tyc world largest pureplay fire protection security company tyco million customer globe latest fire protection security product service tyco employee location country serving end market including commercial institutional governmental retail industrial energy residential small business information visit offer solicitation communication intended constitute offer sell solicitation offer buy invitation purchase security solicitation vote approval jurisdiction sale issuance transfer security jurisdiction contravention applicable law additional information connexion proposed transaction johnson control inc johnson control tyco international plc tyco tyco filed security exchange commission the sec registration statement form include preliminary joint proxy statement johnson control tyco constitute preliminary prospectus tyco the joint proxy material final amended johnson control tyco plan mail respective shareholder definitive joint proxy connexion transaction registration statement effective investor security holder johnson control tyco urged read joint proxy relevant document filed filed sec carefully important information johnson control tyco transaction related matter investor security holder obtain free copy joint proxy document filed sec johnson control tyco website maintained sec addition investor security holder obtain free copy document filed sec johnson control contacting johnson control shareholder service calling obtain free copy document filed sec tyco contacting tyco investor relation calling participant solicitation johnson control tyco respective director executive officer employee considered participant solicitation proxy connexion proposed transaction information person may rule sec deemed participant solicitation respective shareholder johnson control tyco connexion proposed transaction including description direct indirect interest security holding otherwise set joint proxy information johnson control director executive officer contained johnson control proxy statement annual meeting shareholder filed sec information tycos director executive officer contained tycos proxy statement annual meeting shareholder filed sec johnson control cautionary statement forwardlooking statement statement communication are forwardlooking statement meaning private security litigation reform act and therefore subject risk uncertainty including limited statement johnson control combined company future financial position sale cost earning cash flow measure result operation capital expenditure debt level forwardlooking statement word may will expect intend estimate anticipate believe should forecast project plan term similar meaning generally intended identify forwardlooking statement johnson control caution statement subject numerous important risk uncertainty assumption factor johnson control control johnson control combined company actual result differ materially expressed implied forwardlooking statement including other risk related johnson control tycos ability obtain regulatory approval shareholder approval satisfy condition transaction timely basis all delay inability combined company realise expected benefit synergy transaction tax law regulation rate policy interpretation loss key senior management anticipated tax treatment combined company tyco share issued transaction significant transaction cost unknown liability potential litigation relating proposed transaction risk disruption proposed transaction harm johnson control business competitive response proposed transaction general economic business condition affect combined company transaction detailed discussion risk related johnson control business included section entitled risk factor johnson control annual report form fiscal year ended filed sec johnson control quarterly report form filed sec date investor tab forwardlooking statement communication made date communication specified and required law johnson control assume obligation disclaim obligation update statement reflect event circumstance occurring date communication tyco cautionary statement forwardlooking statement communication forwardlooking statement meaning private security litigation reform act including limited tycos expectation prediction future financial business performance condition forwardlooking statement typically identified word believe expect anticipate intend target estimate continue position plan predict project forecast guidance goal objective prospect possible potential future conditional verb assume will would should could may variation word similar expression forwardlooking statement subject numerous assumption risk uncertainty change time forwardlooking statement speak date made assume duty update forwardlooking statement actual result differ materially current projection forwardlooking statement nature address matter are degree uncertain statement consummation proposed transaction factor actual result differ materially forwardlooking statement including addition factor previously disclosed tycos report filed sec investor relation tab identified communication risk relating completion proposed transaction anticipated term timing including obtaining shareholder regulatory approval anticipated tax treatment unforeseen liability future capital expenditure revenue expense earning synergy economic performance indebtedness financial condition losse future prospect business management strategy management expansion growth combined company operation ability tyco johnson control integrate businesse successfully achieve anticipated synergy tax law interpretation financing potential litigation relating proposed transaction risk disruption proposed transaction harm tycos business annualised pro forma projected estimated number illustrative purpose only forecast reflect actual result statement required irish takeover rule director johnson control accept responsibility information contained communication relating tyco tyco company director tyco member family related trust person connected them knowledge belief director johnson control who reasonable care ensure case information contained communication accept responsibility accordance fact omit affect import information director tyco accept responsibility information contained communication relating tyco director tyco member family related trust person connected them knowledge belief director tyco who reasonable care ensure case information contained communication accept responsibility accordance fact omit affect import information centerview partner llc broker dealer registered united state security exchange commission acting financial advisor johnson control connexion proposed transaction connexion proposed transaction centerview partner llc affiliate related entity respective partner director officer employee agent regard person client responsible johnson control providing protection afforded client giving advice connexion proposed transaction matter referred announcement barclay capital inc broker dealer registered united state security exchange commission acting financial advisor johnson control connexion proposed transaction connexion proposed transaction barclay capital inc affiliate related entity respective partner director officer employee agent regard person client responsible johnson control providing protection afforded client giving advice connexion proposed transaction matter referred announcement lazard frere llc registered broker dealer sec acting tyco connexion proposed transaction responsible tyco providing protection afforded client lazard frere llc giving advice connexion proposed transaction matter referred herein release distribution part jurisdiction constitute violation relevant law regulation jurisdiction communication intended prospectus purpose part company act ireland the act prospectus directive regulation ireland amended time time prospectus rule issued central bank ireland pursuant section act central bank ireland cbi approved communication ","m_szGeo1":"United States","m_szSourceType":"source_news","m_szSrcUrl":"http://www.prnewswire.com/news-releases/johnson-controls-and-tyco-announce-future-executive-leadership-team-upon-close-of-planned-merger-300275968.html","m_Places":["Milwaukee","Cork","Ireland","Protection","North America","Best","Holders","Reform"],"m_People":["Alex Molinaroli","George Oliver","Mr. Molinaroli","Grady Crosby","Simon Davis","Kim Metcalf","Judy Reinsdorf","John Repko","Brian Stief","Jeff Williams","Bill Jackson","Trent Nevill","Colleen Repplier","Girish Rishi","Mike Ryan","Johan Pfeiffer","Joe Walicki"],"m_Companies":["Johnson Controls","Tyco","Tyco International","Twitter","Johnson Controls, Inc.","'johnson Controls'","Tyco International Plc","'tyco'","U.s. Securities And Exchange Commission","Sec","Target","Centerview Partners Llc","United States Securities And Exchange Commission","Barclays Capital Inc.","Lazard Freres & Co","Ec","The Central Bank Of Ireland","'cbi'"],"m_BiGrams":["johnson control","proposed transaction","forwardlooking statement","connexion proposed","control tyco","combined company","filed sec","hold role","joint proxy","serve vice","role johnson","executive vice","officer hold","document filed","sec johnson","actual result","accept responsibility","information contained","contained communication","director tyco","chairman chief","company tyco","integrated solution","control business","fire protection","investor relation","security exchange","exchange commission","proxy statement","statement johnson","investor security","security holder","obtain free","free copy","participant solicitation","director executive","risk uncertainty","result differ","differ materially","broker dealer","providing protection","protection afforded","afforded client","giving advice","advice connexion","transaction matter","matter referred"],"m_TriGrams":["connexion proposed transaction","johnson control tyco","serve vice president","hold role johnson","role johnson control","executive vice president","vice president chief","filed sec johnson","sec johnson control","information contained communication","chairman chief executive","officer hold role","johnson control business","security exchange commission","statement johnson control","investor security holder","obtain free copy","document filed sec","director executive officer","actual result differ","result differ materially","providing protection afforded","protection afforded client","giving advice connexion","advice connexion proposed","proposed transaction matter","transaction matter referred"],"m_SocialTags":[],"m_Topics":[],"m_Industry":[],"m_Technology":[],"m_BiCnt":[45,18,14,11,10,9,8,6,6,5,5,5,4,4,4,4,4,4,4,4,3,3,3,3,3,3,3,3,3,3,3,3,3,3,3,3,3,3,3,3,3,3,3,3,3,3,3],"m_TriCnt":[11,10,5,5,5,5,4,4,4,4,3,3,3,3,3,3,3,3,3,3,3,3,3,3,3,3,3],"m_iDocBodyWordCnt":1342}
