{"m_szDocID":"1707299","m_szDocTitle":"Markets Live: CBA hits next record high","m_szYear":"2007","m_szDocSumamry":"textArticle -------------------- Markets Live: CBA hits next record high Date Read later The Australian share market recovered from a heavy fall at the open to post a modest gain. Sort comments by: No new comments Forbe's richest 100 don't short the market. No, they get their hedge funds to do it for them. Forbe's recommend it: http://www.forbes.com/sites/investopedia/2013/09/24/when-to-short-a-stock/ Date and time November 06, 2013, 4:39PM Woo hoo...Napoleon's been here today alright with about fifty posts. Not even the EDs could keep up with that....well done genius. Commenter Date and time ","m_szDocBody":"market live cba hit record date read australian share market recovered heavy fall open post modest gain sort comment comment forbe richest short market hedge fund them forbe recommend date time woo hoonapoleon today alright fifty post eds thatwell genius commenter date time tax internet purchase changing long hockey announce vehicle fbt rort history well commenter how bank allan rolling over shorter forecast clean enjoy date time yeah classic love idealistic pollyanna mumbo jumbo positive people short major bank shorted product paying billion fine commenter the warning regulator crack scheme regulation real estate industry lol joke property investment spruiked usual there time buy property price property double year etc regulator been mortgage scheme spuiked guaranteed income redemption frozen holding creditor meeting offering cent dollar investor regulator been property gold coast spruiked local paper represented new infomercial recent property spruiked local paper listed million sell million paper publishes comment local real estate agent sale great result show strength market regulator commenter oohhh man boring choirboy again seem alan brought back life again commenter change tax internet good joe hockey department store manager head explode commenter date time minute trading informative trade happen buy sell queue minute huge parcel suddenly queue volume make scratch share buy list knowledge offload huge parcel remove prospect shortterm capital gain mean buy cheaper shortly conversely huge buy order suddenly appearing make defer decision sell share anticipation higher price demand commenter asx blow shorter beware pleaseare alive commenter grr finally moving substantially alongside iron ore miner today magnetite harder extract haematite nonetheless debt make attractive company recent resurgence commenter date time cba share hit record today plenty talk stock due reversal kidding unsustainable gouging customer forever commenter date time cba pretty good stock hopeless investment stock sustain longer term future touch anything pillar collapse weight indeed sad people commenter fluke commenter action climate change bad commenter direct action tax action action commenter put back please commenter date time thinking negative trader deep pocket body forbe rich list shorter theyre positive visionary forward thinking optomistic doom sayer eventually gain miss meantime commenter positive visionary forward thinking optomistic key dont geniuspessimist chance btwthe great shorter positive visionary forward thinking optomistic commenter featured comment morgan himself short longno diff long run optomist win pessimist doomed date time body forbe rich list shorter theyre positive visionary forward thinking optomistic yeah soros pauper roflmao commenter date time guy give allan break great insight amusing character matter opinion share holder small fry mass market manipulation make sense good buyer beware commenter date time allan insight punter backed verema cupand likable alarm clock cold morningcmon commenter date time lesswelloff pay rich make sacrifice socalled ficticious budget emergency sympathy serve right time pay attention voting for date time australia elbowed drinker italy britain china emerge export destination mumm champagne yay proud ofespecially tasted australias sidebyside commenter pain wbc shorter commenter nice steady downtrend cab goodbye annoying company asx commenter date time downtrend higher high sounding technical analyst useless commenter date time trading methodology outlined today downtrend pick low buy buying matter falling trend turn genius commenter date time brought undone greed hear tax commissioner art raising taxe pluck goose amount hiss cab made goose customer charge point hissing attracted attention regulator commenter wise bloke short asx company uptrend forever yeahthe whiz kid prahranridic commenter amp seek investor lose well investment advisor rule broken business model syonara commenter date time better disappointing company amp back put misery commenter daahh amp dudbut ill short boq insteadgift commenter date time the corporate regulator warned real estate agent offence promote selfmanaged superannuation fund smsf investor hold financial licence cover week course commenter add xro short gift xro apple commenter gift commenter evidence support claim evidence detailed analysis financial xero compared apple evidence not unthinking copy paste random web site commenter date time shame support sad men obsessed single poster commenter date time lol posted winning trade credibility one commenter attention friendly place adult post trade research opinion market disgusting term nfi here grow all aww poor lil sook allan commenter excepted grow commenter allan backed verema yesterday big race lol date time nope horse racing cruel abusive sport fact laugh animal put tell you commenter date time yeah hehe sort bloke mate week ago neighbour roof blew off busy loling posting misfortune blognice work commenter nope called ses her posted commenter posted here lol made truck load super human giftsi you commenter date time global share market overpriced based earning projection numpty pollyannas forever post contact detail send buy clue roflmao commenter note allan posted gift crz mentioned approx timesbig buckssssss roflmao aww stand you commenter date time forgotten gift provided fmg christmas present handed month commenter boq gift posted event burnt weird bloke time pulling leg thoughcant dumb commenter nailed itbut give break matecmmon commenter still waiting allanbut anyway huge broad losse asx watch week waiting write weird roflmao commenter hey youre fos posted commenter date time allan gifted numpty like jump early insult wrong time lol sore loser you commenter date time abbott isnt global warming thing howard big deal alarmist make out polical scientific based grant science proven wrong before released current level ppm commenter date time howard statement halfroom climate sceptic core noncore remember bloke nickname honest john good reason feeling growing irrelevancy stage make provocative remark attention attention history believing halftruth spun lie ended participating illegal invasion iraq commenter scared love commenter whod wanna shorter beat well ago now woken commenter allan short share dare lol commenter date time concentrate trade obsessing mine better commenter nab making high cba commenter date time short anz wbc nab exdiv tomorrow think shorting mqg please lower climb commenter young squire cba concurbut nab nice uptrendshort iti dare you commenter joined team cba killin commenter div obiwon commenter dissention pollyannas girl fight commenter day day trillion dollar market manipulation scheme time currency guardian care home case won bought libor based financial product sold manipulated price walk deal allan laughing bank scuse pun roman scheme decimation criminal spivs control seal trader financial adviser wall street arrest tenth one commenter give consolation dog psse poor rich man grave commenter date time shorted cba today jumped bit early rsi reversal daily chart making higher high volume etc bhp short same above stopped fmg good win toppy signal asx hit screaming sell short burned commenter date time rsi good indicator newswork stock move new commenter xjo put morning dollar premium xjo put strike expiry date time result new anticipated lack commitment higher telling think commenter gunna stopped commenter understand long xjo put xjo put commenter guy gift crzdid gifted ppl commenter slow day lowood roflmao commenter hehehehe nutty allan boring guess commenter date time nutty printing money solution overpriced asset commenter true worry join make easy dough honest are youseem angry winner commenter lowood bowl called geriatric back commenter date time point cost both labour real estate canada control inflation hence cad ensure cost imported product low standard living higher point ridiculously australian minimum wage cost living scaring international investor coming create job commenter ave wage problem min wage fair enuff commenter hey eds beginning rule forum relevant civilised important participant remove key keyboard mean trade recommendation wealthy gina woman what fight family thank commenter date time wondering post allan nom plume eds allan multiplicity post carrying meeting eds kpis als entry incite entry daily volume lot less causing eds miss bonuse bout eds categorical denial nice conspiracy theory happily firmly deny thrive back multiple denial however fairfax doubt bonuse pretty rare day commenter categorical stuff commenter allan thankfully commenter removing key make bud want commenter wildlife photographer year date time date time head forum notice philtre offering latest oldest most replied suggest add one get rid allan good long room add short sighted commenter gift love biting irony ouch commenter imitate succeed commenter date time alan together jumped bandwagon cba long time bring bad boy down commenter date time bad game shorting major uptrendcoz cant forevercant itdoh mug punter friendly allan commenter date time cbas time come laughed alan shorting high commenter previous trade otherwise fake screen name commenter date time people said bank priced perfection credit exceeding that people realising starting scrape bottom barrel profit growing faster financial service industry unsustainable commenter date time bank short month may nice though commenter bank god nick andy you bank week prior nab div month trend big then month commenter blank sixth sense off sell commenter date time sorry good game allan nab good buyill short behave commenter date time wrong again lost wbc special dividend trade posted loser commenter date time conclusion happyall well good luck wow look volume big killing made hmmm careful allan youve jumped front speeding train commenter hmmmabout recent boq gift good work champ commenter accounting software difficult average programmer write commenter listen laugh himenjoy commenter date time help fmg day based iron ore macq good write them ago follow today side missing there commenter rum jungle resource rum market update signing mou chinese government date time tesla government subsidy back tax time airbag touch screen yeah list real car mile enforced rest battery charge poor them turkey world buy commenter date time peter correct common sense prevail teslas bubble burst year battery electric car shot cost run equivalent small petrol car resale low fad started year ago expect bubble pricked anytime soon year low tsla commenter teslas common sight commenter tim comment damn thousand paragraph could commenter date time peter link engineer talking commenter minimum wage australia hour commenter min wage max wage salary lead saddlebag point commenter date time average hourly rate australia applying average weekly hour worked employed person commenter date time data calculated aggregate hour worked data part labour force release required income data obtained median income reckoning work hour week which waaay hour considered work wage productivity productivity much and difficult simple labour productivity measure suggest commenter date time census median wage fulltime worker worker median rate hour commenter date time higher wage mean people quality life shareholder prosper people forget time time commenter date time based trailer foreign correspondent tonight report radiation poisoning children fukushima kissofdeath nuclear power uranium real pity nuclear power guaranteed baseload carbonfree power provider build reactor areas prone natural disaster commenter mitch seriously spout nonsense abc ran storey ago storey slx biggest conjob overhyped illinformed green crap seen storey focusing slxs uranium technology oushed uninformed scaremongering agenda remember storey idiot stupid agenda mentioned slx produce pretty sweet solarcell nuclear power built using newer safer technology plant fukushima built incredibly vulnerable position boiling water reactor memory dated technology due plant failure greater appreciation risk impact catastrophic considerable work make plant robust note long slx commenter date time nuclear power carbon free convince uranium remove ground refine manufacture fuel rod magic commenter date time bet abc gut independence air pandoras promise week timeslot willacy piece tonight void primary research usual abc journalistic piece bet lot grab essentially south korean antinuke commenter jimmy coffee ear howard sew lip together commenter date time yeah overly sarcastic life cycle carbon footprint analysis nuclear power compared source cut dried people make out commenter yike allan hollow head hehe commenter cba reaches record highslol hahahahha ohhhh complete utter madness commenter mad mad mad world location date time bank supported government guarantee mega mortgage mug market overpriced based earning global asset price eventually give quantitative easing experiment asset price fall commenter greta new djs shrinking store size match shrinking sale profit short yes agree one hvn too commenter date time longer joyce qantas gig destroyed shareholder value pie sky strategy working great shorting though commenter date time saving money buy sold today loss hec wait commenter date time worked sbm stand sado bloody masochist commenter commenter date time exited microsoft ford long night market completely nice big crash coming asx enjoy crashing month ago please total commenter add cba short gift shorting wait top pick consistently short priced ans add continue rise gee gee hard commenter hard fact down commenter date time hard wrong time time again spectacularly case cba commenter date time bank rollercoaster ride cba strong yield riskfree rate buyer seller negative sentiment horizon higher commenter date time lol miss crz lnc fmg time time again cracker commenter date time genius claimed shorting financial sector big gift year true commenter total allan again dumb jbh short jbh short sep add heap recent call fmg short oct now fmg short sep boq short oct now anz short oct now ari short sep now ari short aug flt short sep now flt short aug allan guy nfi triggered stop losse galore complete dud roflmao commenter date time matt left half trade honest commenter date time gee matt keeping spreadsheet allan transaction huge fan suggestion freaking out commenter yeah left wbc nab gift respectively boo hoocmon mate honest commenter allan shorted flt feb miss out commenter date time nab plain making make better commenter date time nope really dud good shortsurely short dud stockcorrect fibbing young man commenter link nope naughty naughty commenter date time matt left gift more laugh allanhe idea doesnt trade base invesment decision parrotnfi allan commenter friendly forum adult derogatory term nfi commenter put back please commenter worse dollar issue manufacturing australia this our intention move quickly can disappointed conclude significant freetrade agreement china month quote tony abbott show appalling judgement give china open book negotiate goodbye australian manufacturing forever people calling phoney toney buy share sell raw material china commenter date time agreed rerun appalling howard comment lead fta side however guilty sticking oar way tie hand negotiating team stay space deal landed profoundly dumb comment abbott commenter date time hey repoman post antitony abbott post forum peeved encroached territory pleased spin unravelling now planning spending year gloating commenter date time mitch allan day day out though peanut trotting phoney tony line blind lib cheerleader better consistent glad endure juliar rubbish now commenter added mqg long gift interesting note believe technical analysis waste time higher high yesterday commenter holding long mqg hit exdividend commenter bad idea rogue dividend syd share pretty juicy plenty leg left yet albeit odd pullback target break volume good month good luck commenter date time sell house sydney move york house live city bring gun too gunwership restricted gun welcome commenter date time gunwership great word sum complex situation gun ownership obsession gun word commenter djs exec buy stock sale data release that david jone chairman peter mason said view possess pricesensitive information sale figure beforehand people chairman position commenter date time and australia exec sort bulldust america prosecuted commenter date time disgrace failing duty director ignoring information provided case sale figure have bigger issue possibly explain djs poor investment late reason blatant insider trading punished full extent possible disgusting commenter date time kindly point obtain channel ipo prospectus cheer commenter analyst rubbish bin commenter bin also commenter date time jack businesse pay australias minimum wage contribute national gdp productivity business low demand weak tolerate idea world wage australia commenter thinking while reason print money australia main effect money printing are downward effect currency upward effect inflation right understand inflation major economy approaches threshold percent month long now print money moderate scale pay fast train network vital infrastructure nbn top needed infrastructure construction moving push dollar down maintain inflation targeting mandate reserve bank say cheque win win what downside downside printing money trashing saver trashed stupidly low rate unleashing inflation started control real inflation country reported processed inflating asset housing bubble hand devaluation currency compete industry chance competing due stratospheric wage difference rain spending buy quality asset usa discount rate favourable exchange work norway commenter date time money economy rate place cantillion effect idea implemented back rba print aud buy gold defend currency sell gold cheaper currency asset winwin wtf know commenter date time well agree saver screwed interest rate low money printing necessarily crushingly low interest rate economy built medium currency year adaptation industry struggling dollar agree buying overseas asset capital poor country hard swallow philosophically opposed hard alternative graincorp takeover capital country invest productive asset capital place involve tough decision prefer make problem worse encouraging retail spending saving winding back piss weak mining tax place acquiring significant amount extracting historically currency putting work productive asset australia money otherwise commenter date time australia nation saver property storage wealth gold silver private debt thrown speculation productive venture people state cash bank referring super holding retirement commenter date time typically antiunion situation manufacturing retail dollar ridiculous rba comment dollar essentially pay cut areas steven politician burning electorate central bank intervene directly currency war result debatable print cash give talking dollar down commenter date time exactly noted yesterday canada including bank canada low dollar ordinary canadian voter cad measure canadian worth relative american political party wanting low cad committing political suicide canada remain competitive keeping labour cost control there stupidly minimum wage paying hour unskilled labour practise australia stupid policy paying hour backpacker pick fruit either local produce cheap competitive importing cheap thirdworld labour hour plus room board travel cost canadian job anyway bank canadas inflation policy lower australia midpoint australia midpoint canada actual inflation past year automatic price increase canada people price increase cent result widespread disdain customer commenter date time canada comparison apt interesting closer commenter canada suggest closer look canadian dairy poultry egg producer set price protected foreign competition prohibitively tariff number industry nafta agreement canadian company owner inc monsanto worldwide reach agriculture nirvana land rampant consumerism sacrificed western country independent production capability human condition cheapest price blame commenter good comment jack sentiment exactly canada similar country term economic structure heavily resource based similar geographical polulation size course advantage disadvantage neighbour country minimum wage destroy economic paying worth similar propping inefficient industry commenter date time canadas low wage policy response low wage direct competitor south border wage demand canada invite employer move couple kms south low wage low cost living borne any price increase cent result widespread disdain customer australian wage cost living off mean made paying everything govt charge commenter date time pay attention canada treasury dept canadian experience model drafting tax policy similarity economy rightwing govt commenter date time understand people canada perfect public debt percent gdp compared australias percent unemployment rate higher way similar economy pushed resource boom made small population compared sheer quantity resource potential housing price boom canadian recent encouraged extravagant irresponsibility true wage higher sector australia intensity property mining boom compared eastern canada lot worker coming work border car worker canada higher wage counterpart canadian industry built serve north american market huge scale advantage our canada special paradise sector canada manufacturing agriculture east complaining canadian dollar guess canada people realise milk honey land mounty commenter minimum wage aus dollar median full time income aus median full time income aus dollar dollar average household income aus spent food average household income spent food purported difference country apparently make commenter date time pay cut change dollar pay cut make harder people repay domestic loan bad new lot people decrease dollar make harder people buy foreign product largely discretionary spending threatening sudden inability meet loan repayment commenter date time home price canada problem solved difference gross income cover extra cost inflated property market commenter date time canada ridiculous amount nationalism xenophobia australia business agriculture dairy egg protection canadian policy consumer retail canadian buy cheapest support american retailer coming canada provide competition walmart home depot target the real target directly operated crappy wesfarmer version here retailer canada competition strong price low commenter date time point cost both labour real estate canada control inflation hence cad ensure cost imported product low standard living higher point ridiculously australian minimum wage cost living scaring international investor coming create job small forced shorter hour lower customer service level also lowering job labour expensive commenter date time record canada imposed ridiculous condition bhp bid potash protect company free trade illusion parroted giant corporation solely benefit thought thinking man knew this commenter date time lib price real estate market based income and asset aus real estate price debt default rate appear low problem here jack aus standard living disadvantaged place remote aboriginal community commenter date time yes standard living canada higher income australia personally lived canada earn income australia numeric term canada working professional job standard living higher and cost living lower canada lower cost housing there food clothing beer utility electricity gas water cheaper canada commenter date time pay cut sudden realisation problem slow fix good start btw point making differing aud pay cut mangle original post broad based pay cut oil cost food transportation remove huge amount discretionary spend debate losing manufacturing capability australia commenter datexpath ","m_szGeo1":"Australia","m_szSourceType":"source_news","m_szSrcUrl":"http://www.smh.com.au/business/markets-live/markets-live-cba-hits-next-record-high-20131105-2x053","m_Places":["Well","Shorter","United States","Gold Coast","Most","Australia","Italy","Britain","China","Nice","Iraq","Wall Street","Canada","Fairfax","Tesla","Turkeys","Teslas","Fukushima","Uk","Look","Sado","Toney","Sydney","New York","Ny","America","Norway"],"m_People":["Sook Allan","He He","G.h. Mumm","Aww Poor","Care Homes","Peter Mason","Yikes, Allan","Tony Abbott","David Jones"],"m_Companies":["Eds","Indeed","Forbes","Jp Morgan","Apple","Nfi","Fmg","Abbott","Twitter","Dare","Nab","Short Anz","Guardian","Signal","Ive","Ppl","Guess","Dough","Rum Jungle Resources Ltd","Rum","Real","Abc","Mk.1","Pandora","Gg","Qantas","Microsoft","Anz","Target","Reserve Bank","Eu","Rba","Central Banks","Bank Of Canada","Us Incs","Monsanto","Treasury","Wal-marts","Home Depot","Wesfarmers"],"m_BiGrams":["date time","commenter date","real estate","minimum wage","pay cut","roflmao commenter","you commenter","standard living","cost living","nuclear power","positive visionary","visionary forward","forward thinking","thinking optomistic","time pay","commenter allan","xjo put","short sep","time yeah","higher high","time lol","allan commenter","living higher","wage cost","down commenter","time bank","out commenter","short oct","oct now","price increase","low wage","income aus"],"m_TriGrams":["commenter date time","positive visionary forward","visionary forward thinking","forward thinking optomistic","you commenter date","date time yeah","standard living higher","wage cost living","down commenter date","date time bank","short oct now","date time pay"],"m_SocialTags":[],"m_Topics":[],"m_Industry":[],"m_Technology":[],"m_BiCnt":[96,85,7,7,6,5,5,5,5,5,4,4,4,4,4,4,4,4,3,3,3,3,3,3,3,3,3,3,3,3,3,3],"m_TriCnt":[85,4,4,4,4,3,3,3,3,3,3,3],"m_iDocBodyWordCnt":3427}
