{"m_szDocID":"1726014","m_szDocTitle":"NVE Corporation's (NVEC) CEO Daniel Baker on Q1 2016 Results - Earnings Call Transcript | Seeking Alpha","m_szYear":"2016","m_szDocSumamry":"textArticle -------------------- NVE Corporation's (NVEC) CEO Daniel Baker on Q1 2016 Results - Earnings Call Transcript Q1 2016 Earnings Conference Call July 22, 2015 5:00 PM ET Executives Daniel Baker - President and Chief Executive Officer Curt Reynders - Chief Financial Officer, Treasurer and Secretary Analysts Charles Haff - Craig-Hallum Capital Group Thomas Cochran - Lake Road Partners Jeff Bernstein - Concept Capital Markets Operator Good day, ladies and gentlemen, and welcome to the NVE Conference Call on First Quarter 2016 Results. At this time, all participants are in a listen-only m","m_szDocBody":"nve corporation nvec ceo daniel baker result earning call transcript earning conference call executive daniel baker president chief executive officer curt reynder chief financial officer treasurer secretary analyst charle haff craighallum capital thomas cochran lake road partner jeff bernstein concept capital market operator good day lady gentlemen nve conference call quarter result time participant listenonly mode later conduct questionandanswer session instruction follow time operator instruction reminder conference recorded introduce host today conference daniel baker president ceo sir begin daniel baker good afternoon conference call quarter ended quarter fiscal alway joined curt reynder chief financial officer call webcast live recorded replay website nvecom opening comment curt financial review quarter ill cover business governance item open call question issued press release filed quarterly report form past hour close market link document sec website website nve corporation comment make relate future plan event financial result performance forwardlooking statement subject risk uncertainty including other factor uncertainty related future revenue earning risk related reliance large customer significant percentage revenue uncertainty related future dividend stock repurchase risk factor listed timetotime filing sec including annual report form year ended company undertake obligation update forwardlooking statement make pleased report solid revenue earning large increase contract r&d revenue dollar share dividend ill curt cover detail financial result curt reynder thank dan quarter fiscal total revenue decreased million due decrease product sale partially offset increase contract research development revenue yearoveryear comparison record total revenue product sale earning year ago quarter total revenue increased compared immediately prior quarter decrease product sale prior year quarter due decreased purchase volume existing customer cautioned based customer forecast aggressive pricing strategy market expect product sale future quarter including remaining quarter fiscal significantly product sale quarter fiscal forecasting impact million million quarter starting quarter large increase r&d revenue due contract contract activity gross margin revenue compared year due higher percentage revenue contract r&d margin tend significantly higher product sale contract r&d total expense decreased quarter fiscal compared prior year quarter due decrease selling general administrative expense decrease r&d expense decrease sg&a primarily due decreased performancebased compensation decrease r&d expense due increase contract r&d caused reallocate resource expensed research development interest income decreased quarter due decrease interestbearing marketable security decrease marketable security proceed maturating security fund cash dividend reinvesting proceed past net income quarter million diluted share compared record million year cash cash equivalent million compared million increase primarily due million operating cash flow million bond maturity million dividend paid quarter fixed asset purchase quarter prior year quarter investment quarter lower quarter history free cash flow net cash provided operating activity fixed asset purchase million quarter free cash flow higher compared net income past quarter quarter reason first income taxe payable increased million estimated income tax payment due quarter estimated tax payment quarter second inventory decreased primarily due reduction work process related contract r&d revenue recognition timing million marketable security million decrease marketable security fund dividend pleased announce board declared quarterly dividend share aggregate approximately million payable shareholder record dividend net income quarter slightly free cash flow now ill turn dan perspective business dan daniel baker thank curt cover growth strategy product development r&d contract patent governance curt covered nearterm product revenue forecast longterm goal replace revenue shortfall unique cuttingedge valueadded product growth strategy product lower pricing increase market penetration market lower price reduce revenue nearterm fuel longterm growth newer product starting generate revenue continuing innovation past quarter made significant upgrade coupler line increasing key isolation rating volt build bestinclass introduced vsery coupler year upgrade cutting edge coupler technology test vsery coupler peak volt remarkable device small fit postage stamp equivalent flashlight battery dcell flashlight quartermile long introduced grade coupler month plan add part type quarter application highvoltage coupler include medical instrument internet power management highvoltage coupler target market called switchmode power supply supply efficiently convert voltage transmitted power line voltage computer phone computer infrastructure power supply ubiquitous consumer power adapter facilitate design win past quarter began selling switchmode power supply demonstration board arent make money board show technology smaller efficient power conversion sale front participated major tradeshow past quarter cooperation distributor embedded system expo conference japan pcim europe sensor test germany report show positive demonstration angle sensor popular esec isolated transceiver msop coupler received pcim sensor test show focuse centerline good boot traffic solid interest angle sensor contract r&d support longterm growth ideas biosensor past quarter awarded biosensor grant department agriculture small business innovation research phase contract titled throughput salmonella detector contract approximately month started june project focus detecting live salmonella industry sample volume faster lower cost comparable accuracy existing method goal dramatically improve food safety contract develop commercial system maria torija phd physicist principal investigator programme awarded usdas national institute food agriculture nifa nifas mission advancing agricultural science solve societal challenge link contract summary new website timeline discussion commercial deployment leading company food industry received r&d contract related antitamper spintronic technology addition revenue modest profit contract typically build technology portfolio enable commercial product sale future granted patent past quarter titled spindependent tunnelling device magnetization state based stress condition spindependent tunnelling sdt spintronic effect produce large change resistance insulating layer spin sensed electrical resistance interface conventional electronic sdt device structure thin atomic layer product spintronic effect called giant magnetoresistance gmr developing product sdt patent granted quarter titled thinfilm structure magnetizable bead detector patent relate system detecting presence selected molecular specy biosensor patent strengthen biosensor intellectual property portfolio link patent website nvecom finally cover governance item annual meeting scheduled eden prairie material proxy statement letter shareholder annual report form filed sec investor section website agenda annual meeting elect director serve annual meeting advisory approval compensation named executive officer neos ratify selection independent registered public accounting firm good corporate practise entire board director stand election year fortunate exceptionally experienced accomplished board annual meeting agenda item prove officer compensation strive good compensation practise dos dont proxy dont overpay compensation committee believe difficult achieve performance result ceo compensation comparable public company comparable revenue market capitalization dont unduly dilute shareholder neos granted stock option recent year executive perk neos received significant benefit perquisite offered employee weve received pension benefit nonqualified deferred compensation post employment potential payment dont golden parachute employee neos employee change control severance agreement ill talk dos named executive officer skin game arent required retain substantial portion share exercise option granted align neo compensation performance growth profitability total shareholder return item business annual meeting ratify selection independent registered public accounting firm fiscal year grant thornton audited past year financial recommend shareholder ratify selection annual meeting generally attended forward there year meeting theme year celebrate internet social media highlight nve internet social media strategy overusing internet jargon tia ftf mean advance follow open call question lis questionandanswer session operator certainly operator instruction question line charle haff craighallum capital line open ahead charle haff guy taking question question guidance curt goal kind setting remainder fiscal year bit confused mentioning that wanted clarification product sale million roughly quarter quarterly impact million million fullyear subsequent quarter second fourth quarter expect quarter million million lower quarter clarify helpful curt reynder sure subsequent quarter second fourth quarter fiscal year charle haff quarter million million lower level curt reynder yes correct charle charle haff divergence previous couple fiscal guess year fiscal year lower level lower asp product higher volume understand bit daniel baker dan revenue headwind lower customer forecast variety factor control aggressive pricing maintain build market share long run pricing strategy sacrifice shortterm revenue longterm share shortterm effect longterm game charle haff okay changing pricing strategy here talking gross margin bit year gross margin quarter fair assume assume similar gross margin quarter remainder fiscal year curt reynder assume gross margin decrease remaining quarter fiscal year expect contract r&d revenue roughly range quarter product sale tend higher margin mentioned expect million million quarter charle haff okay lower quarter rough idea end fiscal bit early year guess range provide gross margin curt reynder pretty speculative point charle haff okay question biosensor business sound interest dan biosensor platform wondering discussion commercial partner give name anything talk dialogue youve biosensor term sensitivity biosensor relative standard care remind sensitive product versus kind standard care pathogen detection you daniel baker right goal deploy market targeting biosensor food production wholesale food production areas promise areas susceptible salmonella working pathogen salmonella focus focus usda grant salmonella show lot poultry turkey particular large large business large industry minnesota technology increase speed accuracy combination usda contract goal comparable accuracy comparable sensitivity existing method faster trade off goal industry type industry targeting larger sample volume lower cost higher speed reason higher speed faster detect salmonella downstream production process risk consumer hand making sick focusing comparable accuracy higher speed larger sample volume charle haff okay kind characterise level interest potential commercial customer buyer biosensor product juncture daniel baker interest strong usda nifa charged protecting food safety regulatory pressure help opposed medical business slow down requirement online online detecting pathogen sensor system work harsh industrial environment pretty valuable pleased win support nifa mentioned prepared remark mission solving societal challenge big goal bold mission feel technology kind potential solve societal problem food safety charle haff yes make lot sense apologise push bit more pretty exciting part business commercial customer there year year kind estimate give that daniel baker quickly humanly mentioned sixmonth contract goal demonstrate feasibility goal weve set comparable accuracy existing method large sample volume commercial type sample volume higher speed month started june started month month goal demonstrate feasibility position potential commercial partner have let work deployment thatll time goal programme meet key goal supported regulatory agency charged usda charged food safety feasibility type system demonstrated month goal move quickly charle haff okay question complementary acquisition bit cash started dividend programme that bit left wondering spent time complementary tuckin type acquisition distribution partner technology partner kind frame thought specific term nve possibly acquisition extra cash daniel baker right key part capital allocation strategy good investment hold standard pride bestinclass financial metric bestinclass technology acquisition dilute make excellent potential opportunity hold standard goal isnt conglomerate mini conglomerate goal acquisition advance mission dramatically distribution mentioned technology product development continuous opportunistic activity specific goal bound number acquisition time period acquisition arent them prepared move quickly charle haff okay taking question daniel baker you charle operator question line tom cochran lake road partner line open thomas cochran tom thomas cochran audio dip bit charle asked asking recall month mentioned quarterly call active talk couple big food processing company thought heard youve mentioned month demonstrate feasibility system question problem developing this question unrelated time factor year ago mentioned spintronic looked big place automotive field heard nothing explain delay aspect company daniel baker well question tom part question problem biosensor technology isnt successful phase contract grant contract national science foundation demonstrated feasibility basic technology contract usda nifa charged food safety opposed advancing basic science feel part natural progression working system specific meeting specific industry goal larger volume higher speed goal make basically realtime detection major leap forward advancing mission discussion feasibility unit prototype position specific commercialization plan part question automotive automotive excellent growth market weve number sensor car projected increase rapidly part smaller precise rugged lower power conventional sensor semiconductor sensor car now initiative including current sensor today car controller area network transceiver network tomorrow hybrid electric vehicle hope specifically that meantime product introduced industrial market current sensor introduced controller area network transceiver world smallest controller area network transceiver introduced theyre primarily automotive market now theyve received hope make impact network generation car hybrid electric vehicle thomas cochran right you dan daniel baker you tom operator operator instruction question line jeff bernstein concept capital line open jeff bernstein dan taking question wanted bit update unclonable function market hearing lot cyber security day sale sophisticated weapon system country what update there daniel baker right great question position terribly specific nature antitamper defeat purpose mention prepared remark received additional contract related antitamper mentioned patent received related magnetization state based stress condition spindependent tunnelling device application antitamper well specific mentioned folk arent jargon developed called posture physical quotable function device key cryptokey prevent hacking prevent reverse engineering device type device continue develop point interest military concern military system fall wrong hand sold ally test electronic important area helped business help develop generation device commercial application valuable phone gaming system communication credit card information secure point lot example information isnt secure area continue work develop small part revenue mix now great potential jeff bernstein dan route market include partnership folk licencing technology order huge huge market kind opposed developing product individually own daniel baker yes absolutely commercialization plan antitamper programme public agency judge programme contract award commercialization plan weve developed partnership potential commercialization company potential user technology credit card smartcard credit card card united state magnetic stripe security secure generation card chip area security area make credit card sell those partnership company technology focus good spintronic partner good areas highvolume consumer electronic broader market jeff bernstein ","m_szGeo1":"United States","m_szSourceType":"source_investments","m_szSrcUrl":"http://seekingalpha.com/article/3347875-nve-corporations-nvec-ceo-daniel-baker-on-q1-2016-results-earnings-call-transcript?all=true&find=accounting+AND+regulatory+AND+advisory","m_Places":["Most","Japan","Europe","Germany","Well","Craig-hallum","Turkey","Minnesota","United States"],"m_People":["Daniel Baker","Curt Reynders","Charles Haff - Craig","Thomas Cochran - Lake","Jeff Bernstein","Maria Torija","Tia Ftf","Charles Haff","Tom Cochran","Thomas Cochran"],"m_Companies":["Nve Corporation","Hallum Capital Group","Sec","Twitter","Volts","Target","Usda","National Institute Of Food","Grant Thornton","Guess","Remind","National Science Foundation","U.s. Military"],"m_BiGrams":["daniel baker","charle haff","product sale","curt reynder","quarter fiscal","contract r&d","gross margin","past quarter","annual meeting","fiscal year","haff okay","jeff bernstein","sample volume","food safety","higher speed","thomas cochran","r&d revenue","marketable security","cash flow","comparable accuracy","credit card","conference call","report form","increase contract","total revenue","due decrease","prior year","year quarter","quarter due","pricing strategy","primarily due","net income","quarter million","lower quarter","free cash","quarter second","power supply","existing method","spindependent tunnelling","ratify selection","question line","line open","taking question","baker right","demonstrate feasibility","commercialization plan","controller area","area network","network transceiver"],"m_TriGrams":["charle haff okay","contract r&d revenue","prior year quarter","free cash flow","daniel baker right","controller area network","area network transceiver"],"m_SocialTags":[],"m_Topics":[],"m_Industry":[],"m_Technology":[],"m_BiCnt":[15,11,9,7,7,7,6,6,6,6,6,5,5,5,5,4,4,4,4,4,4,3,3,3,3,3,3,3,3,3,3,3,3,3,3,3,3,3,3,3,3,3,3,3,3,3,3,3,3],"m_TriCnt":[6,3,3,3,3,3,3],"m_iDocBodyWordCnt":2139}
