{"m_szDocID":"1727068","m_szDocTitle":"On Analysis of the Development of Chinese Regional Economy and Countermeasures","m_szYear":"2011","m_szDocSumamry":"textArticle -------------------- Home > Advanced Materials Research > Renewable and Sustainable Energy > On Analysis of the Development of Chinese Regional... Paper Title: On Analysis of the Development of Chinese Regional Economy and Countermeasures   Abstract Revitalizing regional economy is one of the economic development basic strategies in our country. Finance-taxation policies, as the main macroeconomic control legal means under the conditions of market economy, play a positive and key role in revitalizing regional economy, including the development process of special economic zones, sou","m_szDocBody":"homeadvanced material researchrenewable sustainable energyon analysis development chinese regional paper title analysis development chinese regional economy countermeasure revitalising regional economy economic development basic strategy country financetaxation policy main macroeconomic control legal mean condition market economy play positive key role revitalising regional economy including development process special economic zone southeast coastal open developing western region revitalising northeast industrial base etc taking preferential tax eastern coastal areas regional economic development financial system weakening midwest financial capability limited role equalisation financial transfer payment tax system widening gap development region account considered financetaxation policy carried out renovating prevailing financial system carrying comprehensive financetaxation policy normalising transfer payment system strengthening preferential tax policy info add cart periodical advanced material research volume main theme renewable sustainable energy chapter chapter energy vehicle electric vehicle edited weiguo pan jianxing ren yongguang page wang jin analysis development chinese regional economy countermeasure advanced material research vol online author shu guang wang xiang xin jin keyword financetaxation policy financial system preferential tax regional economy transfer payment export ris bibtex price share preview add cart related article measure analysis shandong economic development author guang zhang xue ning yuan yan cheng abstractthe analysis shandong development power important practical significance promoting country sustained rapid coordinated decoupling analysis based relationship economic growth electricity consumption city nanchang author gui cheng chapter urban regional planning abstractthe relationship energy consumption economic growth research focus scholar home abroad role analysis xian real estate investment contribution regional economic development author cheng hua zheng wen jing chapter infrastructure construction management sustainable urban development abstractthis paper study historical data real estate investment development xian city relevant data the technical analysis relationship human capital economic growth author xiao yan chapter sustainable city regional development abstractshanxi province made tremendous progress economic human capital development shanxi province before research energy development midwest region china regional economic development author mei song bing yan shu xin chapter development management energy resource industry abstractwith increasing demand energy chinas economic development gradual depletion resource eastern areas the datexpath wang jin analysis development chinese regional economy countermeasure advanced material research vol ","m_szGeo1":"Switzerland","m_szSourceType":"source_academic","m_szSrcUrl":"http://www.scientific.net/AMR.347-353.3968","m_Places":["Shandong","Nanchang","Xi'an","Xi'an City","Sustainable City","Shanxi","China"],"m_People":["Weiguo Pan","Jianxing Ren","Yongguang Li","Shu Xin Wang","Xiang Xin Jin","Guang Yi Zhang","Ning Yuan","Yan Cheng","Yu Gui Cheng","Cheng Hua","Zheng, Wen","Jing Li","Yu Xiao Yan","Mei Song","Bing Yan"],"m_Companies":["Gap"],"m_BiGrams":["regional economy","economic development","analysis development","development chinese","chinese regional","financetaxation policy","economy countermeasure","preferential tax","regional economic","financial system","transfer payment","advanced material","material research","development author","economic growth"],"m_TriGrams":["analysis development chinese","development chinese regional","chinese regional economy","regional economy countermeasure","regional economic development","advanced material research","economic development author"],"m_SocialTags":[],"m_Topics":[],"m_Industry":[],"m_Technology":[],"m_BiCnt":[6,6,4,4,4,4,3,3,3,3,3,3,3,3,3],"m_TriCnt":[4,4,3,3,3,3,3],"m_iDocBodyWordCnt":341}
