{"m_szDocID":"1748052","m_szDocTitle":"Environmental pioneer John Hardy envisions a greener Singapore | TODAYonline","m_szYear":"2016","m_szDocSumamry":"textArticle -------------------- Lifestyle Environmental pioneer John Hardy envisions a greener Singapore World-renowned green and sustainability advocate John Hardy says he wants to build a greener world through education and design. Photo: Suki Zoe John Hardy wants to build a greener world through education and design Published: 4:00 AM, July 12, 2016 Updated: 5:01 PM, July 12, 2016 SINGAPORE â€” The little red dot we live in might be a concrete jungle, but renowned green and sustainability advocate John Hardy feels that Singapore has the potential to go big on its eco-friendly efforts. The 67","m_szDocBody":"lifestyle environmental pioneer john hardy envision greener singapore worldrenowned green sustainability advocate john hardy build greener world education design photo suki zoe john hardy build greener world education design published updated singapore red dot live concrete jungle renowned green sustainability advocate john hardy feel singapore potential big ecofriendly effort yearold environmental pioneer set green school bali said singapore sustainable country world singapore small fast rich continued singapore ability model future world singapore decide ive pet ideas singapore change world singapore decreed year vehicle electric environment suggested singapore guest worker trimming bushes road redirected planting organic food city stage electric car grand prix hardy giving talk mochtar riady auditorium singapore management university jewellery business set sold started green school year student today student body student country school uniqueness ly fact structure built bamboo powered water solar power student study openair classroom surrounded garden tend school aim provide environment creativity innovation learning flourish children studying challenged think experience build creative solution problem local hardy said adding encouraged make happen put simply learning doing unconventional ideas making happen bit creative process worse walk hole sky ideas fall out ive questioned traditional answer education teach spend time allowing possible question solar panel ugly green school make part earth produce electricity small river vision greener world education design turn lead greener world student studying green solution completely unsustainable environment student green school studying green theyre living green affect forever back nongreen world start innovating stop them education system today green school landscape corporal punishment worked english world running empire year ago modern age learning nurturing inclusive fearbased system ranking pass fail category create world bully brute innovator world innovator sharing economy innovator dropout dont thrive corporal system world desperately leadership general idea green school create green leader future kid green school singapore country kid return country leader political leader nurturing generation green leadership desperately needed important young people make difference why student want for grinding rulefilled bureaucracy place place arent rule rule flexible there make difference make difference world see affect place difference made change ","m_szGeo1":"Singapore","m_szSourceType":"source_news","m_szSrcUrl":"http://www.todayonline.com/lifestyle/thinking-green","m_Places":["Singapore","Bali"],"m_People":["John Hardy","Suki Zoe"],"m_Companies":["Singapore Management University"],"m_BiGrams":["green school","john hardy","greener world","world education","education design","world singapore","make difference"],"m_TriGrams":["greener world education","world education design"],"m_SocialTags":[],"m_Topics":[],"m_Industry":[],"m_Technology":[],"m_BiCnt":[7,4,4,3,3,3,3],"m_TriCnt":[3,3],"m_iDocBodyWordCnt":340}
