{"m_szDocID":"1755938","m_szDocTitle":"UK and China agree £20 million Low Carbon Innovation program | EurekAlert! Science News","m_szYear":"2014","m_szDocSumamry":"textArticle -------------------- UK and China agree £20 million Low Carbon Innovation program Engineering and Physical Sciences Research Council  Print  E-Mail A new £20 million three-year programme that will support research to develop new low carbon manufacturing processes and technologies, low carbon cities and offshore renewables in the UK and China was agreed yesterday, Wednesday 5th  March 2014. Representatives from the National Natural Science Foundation of China (NSFC) and the Engineering and Physical Sciences Research Council (EPSRC), as part of the Research Councils UK (RCUK) Energy ","m_szDocBody":"china agree million low carbon innovation programme engineering physical science research council print million threeyear programme support research develop low carbon manufacturing processe technology low carbon city offshore renewable china agreed yesterday representative national natural science foundation china nsfc engineering physical science research council epsrc part research council rcuk energy programme signed memorandum understanding mou meeting london witnessed uks minister state climate change greg barker mou china commit million matched resource year approximately million year agreement latest collaboration sery joint research programme stretching year reaped rich reward country professor ming deputy director department engineering material science nsfc said past year nsfc rcuk witnessed substantive development bilateral relationship enjoyed successful collaboration area energy research forward continuing collaboration bringing benefit scientific community professor david delpy epsrc chief executive said this latest agreement addresse develop low carbon method manufacturing urban living energy production meeting industry consumer reducing demand humankind place environment similar challenge china international collaboration bring academic talent solution benefit all welcoming programme minister state climate change greg barker said pleased witness stage ambitious programme investing innovation science essential china address energy supply issue meet emission target drive longterm economic growth ringfenced science budget worth billion year invested million joint project china ### epsrc press office tel email note editor engineering physical science research council epsrc engineering physical science research council epsrc uks main agency funding research engineering physical science epsrc invest million year research postgraduate training nation handle generation technological change areas covered range information technology structural engineering mathematic material science research form basis future economic development improvement everyone health lifestyle culture epsrc work alongside research council responsibility areas research research council work collectively issue common concern research council previous ukchina energy collaboration rcuk invested million joint ukchina energy research project supported matched resource chinese funder national natural science foundation china nsfc ministry science technology most chinese academy science cas collaborative effort support worldleading research will turn facilitate transition lowcarbon economy included number call initial ukchina energy call launched partnership most topic included renewable energy technology cleaner fossil fuel rcuk funded innovationfocused project rcuk science bridge initiative collaboration theme sustainable energy built environment rcuk energy programme launched cofunded call cas nsfc rcuk nsfc invested million call supporting research carbon capture storage technology call focused solar cell solar fuel fuel cell million investment rcuk cas call run rcuk nsfc smart grid rcuk nsfc investment totalled million call focused integration smart grid electric vehicle total investment million rcuk nsfc supported joint project energy storage million investment rcuk energy programme nsfc research council energy programme research council energy programme aim position meet energy environmental target policy goal worldclass research training energy programme investing million research skill pioneer low carbon future build investment million past year december led epsrc energy programme bring work epsrc biotechnology biological science research council bbsrc economic social research council esrc natural environment research council nerc science technology facility council stfc disclaimer aaas eurekalert responsible accuracy new release posted eurekalert contributing institution information eurekalert system american chemical societynational meeting expositionmarch san diego mar mar","m_szGeo1":"United States","m_szSourceType":"source_news","m_szSrcUrl":"http://www.eurekalert.org/pub_releases/2014-03/eaps-uac030614.php","m_Places":["Uk","China","London"],"m_People":["Greg Barker","Li Ming","Professor David","Delpy"],"m_Companies":["Engineering And Physical Sciences Research Council","Epsrc","Research Councils","Department Of Engineering","Most","Ministry Of Science And Technology","Cas","Research Council","Bbsrc","Esrc","Nerc","Science And Technology Facilities Council","Stfc","Aaas"],"m_BiGrams":["research council","energy programme","science research","low carbon","engineering physical","physical science","rcuk nsfc","council epsrc","rcuk energy","invested million","ukchina energy"],"m_TriGrams":["engineering physical science","science research council","physical science research","research council epsrc","rcuk energy programme"],"m_SocialTags":[],"m_Topics":[],"m_Industry":[],"m_Technology":[],"m_BiCnt":[12,7,6,5,5,5,4,3,3,3,3],"m_TriCnt":[5,5,4,3,3],"m_iDocBodyWordCnt":502}
