{"m_szDocID":"1760777","m_szDocTitle":"U.S. stocks fall for the fourth straight day - Sun Sentinel","m_szYear":"2003","m_szDocSumamry":"textArticle -------------------- U.S. stocks fall for the fourth straight day New York Stock Exchange Traders work at the New York Stock Exchange on Thursday. Traders work at the New York Stock Exchange on Thursday. (Mark Lennihan / Associated Press) Privacy Policy Jitters over the global economy and a steep drop in crude oil prices knocked U.S. stocks lower for the fourth day in a row Thursday. The drop in the U.S. followed large losses all around the world, and left all three major U.S. indexes down at least 10% since the beginning of the year. The latest slump reflected heightened concerns ","m_szDocBody":"stock fall fourth straight day york stock exchange trader work york stock exchange thursday trader work york stock exchange thursday mark lennihan press privacy policy jitter global economy steep drop crude oil price knocked stock lower fourth day row thursday drop large losse world left major indexe beginning year latest slump reflected heightened concern global economic growth slowing federal reserve chair janet yellen reiterated confidence economy testimony congress thursday lot people trouble assessing true stock kinahan ameritrade chief strategist continue volatility financial company biggest decliner amid growing anxiety interest rate remain low sap bank profit price oil tumbled barrel lowest level investor fled traditional haven bond precious metal gold jumped weekly business new briefing open link stock ended lower recovered greater losse earlier day dow jone industrial average dropped point average point standard poor lost point nasdaq composite fell point investor increasingly worried mounting market turmoil put brake global economy time struggling litany issue including chinas slowdown low inflation plunging energy market yellen day testimony lawmaker acknowledged global economic pressure posed risk economy early risk severe alter central bank interestrate policy failed reassure investor hoping fed signal rate hike table remainder year katie nixon chief investment officer northern trust wealth management market disappointed direct comment pushing rate increase nixon said opportunity that feeding market anxiety sector s&p index closed lower financial stock fell most citigroup fell bank america shed cent jpmorgan slid benchmark crude oil fell sixth day row sliding barrel york brent crude benchmark international oil dropped cent barrel london natural gas fell cent cubic feet drop oil natural gas price share energy company lower southwestern energy lost cent nrg energy shed boeing plunged report security exchange commission investigating aircraft manufacturer accounting practise stock worst performer dow losing trader bid share tripadvisor travel website operator fourthquarter profit revenue topped estimate stock gained performing stock s&p tesla motor climbed electric car maker lowerpriced model sedan schedule release stock added europe germany dax dropped france cac slid dragged drop share bank societe generale warned profit britain ftse shed asia indexe reopened holiday caught day market turmoil hong kong hang seng dived south koreas kospi biggest daily drop year trading china taiwan resume monday japan market closed separate public holiday government bond price rose driving yield year treasury late wednesday gold surged ounce silver climbed cent ounce copper industrial metal rise fall investor optimism global economy fell cent pound energy trading york wholesale gasoline changed cent gallon home heating oil flat cent gallon dollar dive investor adjusted expectation fewer interest rate increase fell yen yen fell euro also datemeta ","m_szGeo1":"United States","m_szSourceType":"source_news","m_szSrcUrl":"http://www.sun-sentinel.com/business/la-fi-financial-markets-20160211-story.html","m_Places":["United States","China","New York","Brent","London","Europe","Germany","France","Britain","Asia","Hong Kong","South Korea","Taiwan","Japan"],"m_People":["Mark Lennihan","Janet Yellen","J.j. Kinahan","Katie Nixon"],"m_Companies":["Associated Press","Congress","Td Ameritrade","Sap","Signal","Northern Trust","Citigroup","Bank Of America","Nrg Energy","Boeing","Securities And Exchange Commission","Tesla Motors","U.s. Government","Treasury"],"m_BiGrams":["york stock","stock exchange","global economy"],"m_TriGrams":["york stock exchange"],"m_SocialTags":[],"m_Topics":[],"m_Industry":[],"m_Technology":[],"m_BiCnt":[3,3,3],"m_TriCnt":[3],"m_iDocBodyWordCnt":427}
