{"m_szDocID":"1764038","m_szDocTitle":"Clean tech a priority issue as Chinese president lands in U.S. - Chicago Tribune","m_szYear":"2015","m_szDocSumamry":"textArticle -------------------- Clean tech a priority issue as Chinese president lands in U.S. China's President arrives for official US visit Chinese President Xi Jinping arrives in Washington state to begin first official US visit. Sept. 22 (AP) Chinese President Xi Jinping arrives in Washington state to begin first official US visit. Sept. 22 (AP) Tribune wire reports Contact Reporter Chinese President Xi Jinping arrived in Washington state Tuesday for a visit to the U.S. that will include talks on how U.S. and Chinese experts and businesses can collaborate on nuclear energy, smarter elect","m_szDocBody":"clean tech priority chinese president land chinas president arrive official visit chinese president jinping arrive washington state begin official visit sept chinese president jinping arrive washington state begin official visit sept tribune wire report contact reporter chinese president jinping arrived washington state visit include talk chinese expert businesse collaborate nuclear energy smarter electricity clean technology visit year president barack obama announced nation cooperate fight climate change xis plane landed paine field everett welcomed included washington gov jay inslee washington governor ambassador china gary locke seattle mayor murray talk seattle handful governor chinese counterpart include improving energy efficiency building modernising electrical grid commercialising renewable energy governor expected meet privately day university washington tsinghua university beijing expected agreement collaborate research related clean tech addition terrapower inc energy company founded bill gate entering agreement china national nuclear corp work nextgeneration nuclear power plant technology these largest economy world biggest emitter greenhouse gase improving cooperation collaboration necessity brian young washington state director economic development clean technology sector second huge business opportunity side recognise opportunity job creation uschina cooperation climatechange warm fuzzy point relation superpower obama thenpresident jintao formalised renewable energy partnership including establishment cleanenergy research centre focused electric vehicle cleaner coal water energy programme november obama announced country work climate change china announcing cap greenhouse gas emission sooner possible contrast hacking attack directed beijing chinas move assert territorial claim south china sea sore spot travelling seattle washington white house state dinner friday trip time chinas economic growth slowed considerably communist nation overhauling economy put emphasis consumer spending export oftenwasteful investment factory real estate infrastructure railway airport shift demand vast amount energy chinas middle class expand noted tom ranken president cleantech alliance seattlebased trade company organisation stake clean energy technology including boeing university washington hundred other china curb pollution obvious spent time beijing shanghai said for american city stunning said theyre ultramodern storey including morning running sick halfmile air pollution cleantech firm washington state rely largely hydropower natural gas cheap market investment china sooner domestically said china invested record billion renewable energy year frankfurt school centre climate sustainable energy finance germany they huge business opportunity future solar wind mikkal herberg research director energy security programme national bureau asian research china leader nuclear energy governor meeting include inslee jerry brown california rick snyder michigan terry branstad iowa kate brown oregon press datemeta ","m_szGeo1":"United States","m_szSourceType":"source_news","m_szSrcUrl":"http://www.chicagotribune.com/news/nationworld/ct-chinese-president-in-us-20150922-story.html","m_Places":["United States","China","Washington","Everett","Seattle","Beijing","China Sea","Washington, D.c.","Shanghai","Germany","California","Michigan","Iowa","Oregon"],"m_People":["Xi Jinping","Barack Obama","Jay Inslee","Gary Locke","Ed Murray","Bill Gates","Brian Young","Hu Jintao","Tom Ranken","Mikkal Herberg","Inslee, Jerry Brown","Rick Snyder","Terry Branstad"],"m_Companies":["Ap","Tribune","University Of Washington","Tsinghua University","Terrapower Inc.","China National Nuclear Corp.","White House","Cleantech","Alliance","Boeing","Frankfurt School's Center","Associated Press"],"m_BiGrams":["washington state","chinese president","official visit","president jinping","renewable energy"],"m_TriGrams":["chinese president jinping"],"m_SocialTags":[],"m_Topics":[],"m_Industry":[],"m_Technology":[],"m_BiCnt":[5,4,3,3,3],"m_TriCnt":[3],"m_iDocBodyWordCnt":386}
