{"m_szDocID":"1773800","m_szDocTitle":"Happy Birthday Ratan Tata: Here are 26 investments since his retirement three years ago | Latest News & Updates at Daily News & Analysis","m_szYear":"2015","m_szDocSumamry":"textArticle -------------------- Happy Birthday Ratan Tata: Here are 26 investments since his retirement three years ago 3800 3.8k dna Web Team | Mon, 28 Dec 2015-11:45am , Mumbai , dna webdesk Ratan Tata stepped down as the Chairman of Tata Sons three years ago -- December 28, 2012, his 74th birthday -- after being at the helm of one of the largest Indian conglomerate for over two decades. Since then, he has slipped into the role of being the Chairman of Tata Trusts and the Chairman Emeritus of Tata Group. However, if one were to follow Tata's movements in the last two years atleast, you'd kn","m_szDocBody":"happy birthday ratan tata investment retirement year ago dna web team mon mumbai dna webdesk ratan tata stepped chairman tata son year ago birthday helm largest indian conglomerate decade then slipped role chairman tata trust chairman emeritus tata group however follow tatas movement year atleast time traditional retirement industralist chairman emeritus tata group erstwhile tata frontman role angel investor mentor ecommerce company startup ndtv report cited unnamed source retirement industrialist invested huge portion crore eretail businesse crore consumer market crore software firm crore business aggregator crore adtargeting network retired year ago tata started actively investing company mid then back investing company single month time tata board kalaari capital idg venture jungle venture advisor investment ratan tata made retirement early altaeros energy bostonbased company set commercialise world airborne wind turbine late company raised million softbank snapdeal ratan tatas invested crore indias ecommerce website snapdealcom backed kalaari capital tata bought share company snapdeal angel investor including kenneth glass media report portal wipros azim premji investor read ratan tata take flipkart amazon invest snapdealcom bluestone online jewellery portal bluestone founded gaurav singh kushwaha iit graduate ceo company bluestone backed kalaari capital urban ladder leading furniture home decor eportal started iimbangalore graduate ashish goel rajiv srivatsa sprang popularity welknown online portal furniture swasth india swasth india startup healthcare service lower income population society received investment crore tata company set iit bombay graduate sundeep kapila ankur pegu cardekhocom started iitdelhi graduate anuraj amit jain cardekho user buy sell compare price car market review car duo run bikedekhocom read ratan tata invest car platform cardekhocom grameen capital grameen capital investment advisory company ranging space microfinance education healthcare list aim catalysing inclusive growth make capital market enterprise positive impact including microfinance institution healthcare provider lowcost education firm one communication one communication company operate paytm online payment solution company headquartered noida company offer option online wallet user now company website million registered user handle million order month septmeber company received funding chinese giant alibaba holding month company signed deal bcci replace outgoing ipl sponsor pepsico read ratan tata invest paytm founding company one communication xiaomi chinas largest smartphone maker xiaomi indian investor form ratan tata company ceo lei plan make india important market phone too china happy announce ratan tata chairman emeritus tata son made investment #xiaomi read ratan tata indian invest chinas apple xiaom fashion portal kaaryah nidhi agarwal kashyap boast ratan tata investor online fashion portal deal noncasual wear women literally tatas attention email read ratan tata acquire stake fashion portal kaaryah ola bhavish aggarwal ola cab ceo made announcement twitter company learn rich experience finest business leader time blogpost ola cab website honoured invest mission build mobility billion indian bhavish aggarwal founded ola cab operate city driver read ratan tata invest appbased taxi service app ola invest tripura tata investing state great potential received recognition deserve promised tata forward investment industry support state development read ratan tata invest tripur support development jungle venture jungle venture singapore based venture capital company focuse technologybased company asiapacific region tata joined company board special advisor mentor company venture capital firm portfolio company invested odd technologybased startup zipdial crayondata livespace read ratan tata join jungle venture special advisor lybrate investment crore made healthcare startup lybrate tata tiger global management nexus venture partner nvp usbased company platform connect doctor patient read app solve problem healthcare inaccessibility lybrate founder internet saathi heel narendra modis digital india announcement tata trust tied intel kicked net initiative women strive bring internet women rural india internet saathi programme bicycle internet connectivity device cover village month starting gujarat rajasthan jharkhand target reaching women cycle give villager internet experience tata said read ratan tata laud digital india launches internet initiative women ampere tata invested undisclosed amount coimbatorebased electric vehicle startup company move launch internet saathi programme bring internet women rural india ampere manufacture electric vehicle cycle trolly scooter vehicle differentlyabled charger dealer karnataka kerala tamil nadu read ratan tata invest coimbatorebased electric vehicle startup yourstorycom undisclosed amount invested online startup entrepreneur storey portal yourstorycom cover storey new littleknown entrepreneur storey startup started year ago sharma wanted storey entrepreneur superstar spark drive hope read ratan tata invest yourstorycom zivame online lingerie portal joined long line startup received funding tata zivame boast style lingerie offer brand read ratan tata invest undisclosed amount zivame infinite analytic tata made investment predictive technology firm infinite analytic scale operation investment made tatas personal capacity amount left undisclosed infinite analytic count company airbnb comcast digital babyoye croma retail ebay future group infibeam nba ndtv retail trendin tata marketplace client read now ratan tata invest infinite analytic holachef chairman emeritus tata son ratan tata made personal investment undisclosed amount online marketplace chef holachef launched saurabh saxena anil gelra holachef substantial growth mumbai pune company statement read ratan tata invest undisclosed amount startup holachef virtual currency abra ratan tata american express made undisclosed amount investment usbased abra making digital virtual currency investment tata tata american express made strategic investment abra part recently announced sery round investment cryptocurrency world american express ratan tata abra added read ratan tata american express invest digital currency startup abra letsventure funding marketplace letsventure received undisclosed amount tata mohandas pai chairman manipal global education letsventure act middleman startup angel investor far year company investor board country raised crore startup read ratan tata invest undisclosed amount letsventure sabse technology global telecom carrier sabse technology inc started hotmail founder sabeer bhatia announced strategic investment tata company silicon valleybased company operate sabsebolo popular communication cloud platform small medium businesse disclose detail investment crayon data singaporebased big data company crayon data received funding disclosed amount tata crayon portfolio company jungle venture previously raised million singapore dollar seed sery funding angel institutional investor jungle venture spring seed read ratan tata invest singapore startup crayon data emission tech bill gate mark zuckerberg jack thirty leading investor including ratan tata form coalition invest clean energy technology bid move emission energy future media report organisation businessmen invest money develop clean energy solution world move emission energy ahead however far exact amount initial total investment yet read ratan tata mukesh ambani jack bill gate invest emission tech urbanclap undisclosed amount invested service startup urbanclap urbanclap indias largest service marketplace happy announce ratan tata invested company personal capacity company statement operational city delhincr bengaluru mumbai chennai pune hyderabad urbanclap user book service including plumbing electrical work beauty wellness tutorial wedding photography company network service professional snapdeal swasth india grameen capital datemeta ","m_szGeo1":"India","m_szSourceType":"source_news","m_szSrcUrl":"http://www.dnaindia.com/money/report-happy-birthday-ratan-tata-here-are-26-investments-since-his-retirement-three-years-ago-2160099","m_Places":["Mumbai","Boston","India","Bangalore","Bombay","Pegu","Delhi","Noida","China","Ola","Tripura","Singapore","Asia","United States","Rajasthan","Coimbatore","Pune","Silicon Valley","Bengaluru","Chennai","Hyderabad"],"m_People":["Kenneth Glass","Azim Premji","Gaurav Singh Kushwaha","Ashish Goel","Rajiv Srivatsa","Sundeep Kapila","Amit Jain","Lei Jun","Bhavish Aggarwal","Narendra Modi","Saurabh Saxena","Anil Gelra","Mohandas Pai","Sabeer Bhatia","Bill Gates","Mark Zuckerberg","Mukesh Ambani"],"m_Companies":["Tata Group","Idg","Wipro","Amazon","Alibaba Group","Pepsico","Twitter","Apple","Venture","Nexus","Venture Partners","Nvp","Google","Intel","Target","Airbnb","Comcast","Ebay","Nba","American Express","Sabse Technologies","Sabse Technologies Inc","Hotmail","Ncr"],"m_BiGrams":["ratan tata","read ratan","tata invest","undisclosed amount","jungle venture","chairman emeritus","emeritus tata","infinite analytic","american express","tata son","angel investor","kalaari capital","tata made","swasth india","tata company","grameen capital","one communication","received funding","fashion portal","ola cab","internet saathi","electric vehicle","invest undisclosed","crayon data"],"m_TriGrams":["read ratan tata","ratan tata invest","chairman emeritus tata","tata invest undisclosed","invest undisclosed amount"],"m_SocialTags":[],"m_Topics":[],"m_Industry":[],"m_Technology":[],"m_BiCnt":[29,17,11,9,6,4,4,4,4,3,3,3,3,3,3,3,3,3,3,3,3,3,3,3],"m_TriCnt":[17,11,4,3,3],"m_iDocBodyWordCnt":1068}
