{"m_szDocID":"1777012","m_szDocTitle":"Car bosses talk China, Tesla battle and luxury SUVs","m_szYear":"2015","m_szDocSumamry":"textArticle -------------------- Car bosses talk China, Tesla battle and luxury SUVs Tuesday, 15 Sep 2015 | 10:43  AM ET CNBC.com 09/15/15  4:30 AM ET › Bosses of some of the world's biggest automakers have shrugged off concerns over future economic growth in China, telling CNBC that they are adapting to the \"new normal\" in the world's second-largest economy. Speaking in interviews at the Frankfurt Motor Show, the CEO's of Jaguar Land Rover, Daimler, SEAT and Porsche, talked about China, the growing SUV market, and the future of electric cars. China’s ‘new normal’ Stock market turmoil in the w","m_szDocBody":"car bosse talk china tesla battle luxury suvs tuesday cnbccom bosse world biggest automaker shrugged concern future economic growth china telling cnbc adapting new normal world secondlargest economy speaking interview frankfurt motor show ceos jaguar land rover daimler seat porsche talked china growing suv market future electric car chinas normal stock market turmoil world secondlargest economy fear slowing growth caused concern major carmaker hit china automobile manufacturer cut growth forecast percent percent car sale year auto bosse dismissed concern suggesting resilient handle situation the normal normal adapt good line good productsand manage situation well ralf speth ceo jaguar land rover told cnbc tuesday adding company scale back investment china show chapter adapt chinas normal jaguar land rover ceo ralf speth ceo jaguar land rover company hand adapt handle economic reality emerging china tuesday suv market heat suv market entrant frankfurt motor show like bentley jaguar seat unveiling model fastestgrowing auto segment number carmaker betting increasing number luxury player jumping space bentley unveiled suv called bentayga jaguar showed inaugural suv called fpace its luxury sporty dynamic good drivabilityand jaguar kind segment taking dna jaguar speth told cnbc seat released model called seat leon cross sport show car cross suv coupe the seat brand defined designorientated young brand great quality great functionalitywe coming seat dna company ceo jrgen stackmann told cnbc interview show chapter confident spanish market seat ceo jrgen stackmann ceo seat tell cnbc confidence spain high explaining country biggest investor tuesday teslas competition electric car hot topic frankfurt continued government pressure world cut carbon emission sale electric car small number manufacturer shown real concept design bid challenge like tesla luxury offering porsche wrap mission fully electric fourseat sport car charge minute battery life mller decide end year put concept car production car better market proud tesla competitor accept porsche better mller told cnbc show chapter car beat tesla taiwanese car maker thunder power unveiled electric car give tesla run money cnbc phil han report frankfurt motor show datemeta tuesday ","m_szGeo1":"United States","m_szSourceType":"source_news","m_szSrcUrl":"http://www.cnbc.com/2015/09/15/car-bosses-talk-china-tesla-battle-and-luxury-suvs.html","m_Places":["China","Tesla","Frankfurt","Leon","Spain"],"m_People":["Ralf Speth","Jürgen Stackmann","Phil Han"],"m_Companies":["Cnbc.com","Cnbc","Jaguar","Land Rover","Seat"],"m_BiGrams":["jaguar land","land rover","electric car","told cnbc","frankfurt motor","motor show","suv market","show chapter"],"m_TriGrams":["jaguar land rover","frankfurt motor show"],"m_SocialTags":[],"m_Topics":[],"m_Industry":[],"m_Technology":[],"m_BiCnt":[4,4,4,4,3,3,3,3],"m_TriCnt":[4,3],"m_iDocBodyWordCnt":329}
