{"m_szDocID":"1781850","m_szDocTitle":"Full text of Christie's New Hampshire economic policy speech |       NJ.com","m_szYear":"2015","m_szDocSumamry":"textArticle -------------------- Full text of Christie's New Hampshire economic policy speech Chris Christie New Jersey Gov. Chris Christie, a likely Republican 2016 presidential candidate, gestures during an event at the University of New Hampshire in Manchester, N.H., Tuesday, May 12, 2015. (Charles Krupa/AP) The governor unveiled his proposal for economic growth in the country . Here are the governor's remarks as prepared for delivery: I have returned to New Hampshire today to talk to you about the most important issue facing the country today: fixing the economy and creating jobs. The fund","m_szDocBody":"full christy hampshire economic policy speech chris christie jersey gov chris christie republican presidential candidate gesture event university hampshire manchester tuesday charle governor unveiled proposal economic growth country governor remark prepared delivery returned hampshire today talk important facing country today fixing economy creating job fundamental question vexing income middleclass american grown year critical understand answer question fix problem anxiety unhappiness weigh middleclass america resolved continue mistrust people government continue america weakened world continue middleclass american fearful future american lived forward tomorrow believed heart tomorrow today belief live heart diminished year small part national government failed bad biggovernment policy hurt job growth middleclass income horrific execution existing law people perceive unfair ability desire work together manchester today path view key boosting income middle class increasing economic mobility american making tomorrow today increase rate economic growth today describe fivepoint plan america percent growth first perspective remind back then optimistic teenager raised impossible country watching gas line doubledigit inflation interest rate soviet afghanistan hostage iran president ran single idea trust telling problem tough handle optimism misplaced least nave unrealistic country bound powerful influential home abroad accept fact life america steward diminished status allocator diminished resource today stagnant economy brutal recession unimaginably national debt growing entitlement state control compromise future heavy hand government regulation corner live and again president ran single idea hope change tell live that not fault fault washington culture made worse put end toxic mix pessimism arrogance belief government exert greater control live refuse accept responsibility failure control wrought fantasy year great success wage flat fulltime employment middle class shrinking wealth alltime high privileged president american people lyin eye week ago commerce department report gdp growth quarter year percent economy virtually ground halt obama economy plagued america year growth eeking barely percent year percent fact economic recovery presided administration weakest postwar american history pay price white house congress wealthy hardworking middleclass american american work hard fulltime work joint economic committee congress growth averaged pace recovery fifty year additional million private sector job united state today hasnt weak recovery america performing potential specific plan bring back percent growth weak growth coincidence direct result policy president worst economic president jimmy carter current administration washington pursued antigrowth policy tax increase overregulation hostility business policy discourage work inception administration focused redistribution wealth creating wealth middleclass citizen fact fair president antigrowth president postwar american history today president united state specific plan restore growth americas middle class ironic president labelled latest version hightax heavyregulation slowgrowth policy middle class economic precisely middle class hurt group president policy first weak recovery pushed fulltime worker parttime work true employment higher today prerecession peak cover troubling bureau labour statistic number fulltime employee million peak quarter number parttime worker higher quarter million huge shift president fulltime parttime work often parttime job pay bill number parttimer forced juggle multiple parttime position climbed percent reaching year high second labour participation rate remained unacceptably low administration fact percent lowest jimmy carter true assert low labour participation due demographic fact biggest drop labour force participation percentage term youngest member work force sad state affair economy weak young people america raise white flag give working america dangerous future our slow start working hurt career earning year come fact people discouraged job lack opportunity telling number measured gallup payroll population survey this percentage american population working fulltime employer percent right half american today working fulltime chairman ceo gallup unguarded moment called percent rate staggeringly low certain healthy recovery president sell america finally course weak economy combined set monetary policy year geared wealthy exacerbated problem left love harp income inequality reality that stronger higher growth economy enjoyed income grew american real growth slower inflation higher late income inequality grew more year administration overwhelming policydriven factor made income inequality worse materially worse easy money policy federal reserve helped financial asset grow substantially asset including stock fine job hard find wage stagnant weak gdp growth middle enjoy higher income time history median income declined postrecession recovery president roaring financial economy wealthy weak real economy middle class worsened income inequality policy bottom line fed easy money policy president antigrowth policy made rich richer made middle class work longer harder pay promise future equally troubling this longer united state kill real growth competitiveness world economy decline administration hurting jobseeker today compromising future generation well time send signal american people world america returning progrowth root progrowth policy time investor america open business american people build economy growth leader growth laggard discuss happen today propose fivepoint plan percent growth target tax code today targeting discouraging individual hampering businesse sending job creator offshore tax code bloated page million word rule regulation quirk quack good exception tax preparer irs control apparently unaccountable irss estimate american spend billion hour time complying code system discourage american discourage growth year long hampshire state income taxe tax freedom day day year working uncle sam key difference party republican tax freedom day spring training democrat time world sery propose comprehensive tax reform now principle lower income tax rate american improve americas competitiveness world and all make taxe easier create flatter fairer simpler tax code outline proposed multiple leader party lacking political leadership top done president push comprehensive tax reform congress day one tax reform propose trojan horse net tax increase american people net tax reduction worst case deficit neutral overdue citizen reform reduce increase taxe propose comprehensive tax reform first personal income tax side code individual income tax rate current six reform include lower tax rate american top rate higher percent set major successful tax reform effort country bradleygephardtreagan law signed bottom rate single digit code reward create disincentive work eliminate modify deduction credit targeted provision code personal corporate side ensure plan combined measure proposing revenue neutral materially increase deficit approach regard cap total amount deduction credit individual married couple take seek place deduction charitable contribution interest home mortgage home make majority american minute taxe day week month simple outline tax code flatter fairer simpler progrowth major tax reform proposal encourage capital formation quarter gdp report mentioned moment ago fixed investment weak fact signature feature recovery weak business investment today policy chase financial capital shore capital equipment factory businesse invest productivity lag wage nowhere day ago obama labour department reported quarter year productivity dropped percent annual rate company making capital investment united state part concerned antigrowth direction washington spur capital investment create opportunity job permit full expensing corporate investment capital equipment encourage type important investment spur type growth create middle class job urgent send clear progrowth signal company additionally great american company apple general electric manufacture product overseas global economy many company tax code discourage taking profit abroad reinvesting america create job here income generated abroad brought back america create job tax rate percent taxed country earned company money abroad escape tax united state effect obvious company way conduct r&d design innovative product overseas america meanwhile national science board share global research development declined percent percent meanwhile trillion dollar profit generated internationally sitting offshore policy insanity time profit home time job here corporate side feature tax reform proposal this american company onetime opportunity repatriate profit earned overseas decade lower tax rate propose rate percent onetime holiday combine onetime rate past earning legislation establish territorial tax system forward territorial system profit earned taxed country generated once twice stand now america tiny handful nation including north korea system taxe profit twice generated home largest trading partner territorial system small change unleash wave investment capital invested united state america expand company build factory warehouse improve infrastructure short create job joint tax committee change conjunction larger tax reform moneymaker government generating revenue smaller onetime tax earning repatriated corporate side united state today highest tax rate industrialised world country reducing rate improve competitive position united state stuck percent republican party ronald reagan taught world tax rate hurt growth ironically country heeded lesson forgotten piece tax reform plan cut corporate tax rate percent percent study shown corporate taxe harmful growth highest corporate tax rate industrialised world simple highest tax rate world expect attractive place investment world fact standard poor capital reported cutting corporate tax rate percentage point create million job year small important point corporate side taxe repeal obamacare taxrelated jobkilling provision percent tax medical device tax apply advanced lifesaving pace maker simplest denture medical device industry source growth economy source export source innovation thing strong bipartisan support repeal tax today bias higher taxe current administration stunted growth produced weak recovery government today wield heavy hand regulation point fivepoint plan growth reform reduce overbearing government regulation time current administration targeting private industry another undermining prospect heavyhanded regulation set awful record page federal regulation record electric power today percent americas electricity generated coal large amount fired natural gas move cloud computing reliable electric power data centre estimated consume percent electricity generated country virtually short year ago number surely grown plug electric car electric power power battery manufacture semiconductor lawn mower electric power reliable electric power power process administration done interpretation section clean air act interpretation challenged court administration prevent coalfired electric plant built onebyone force closure existing plant mind course china building dozen coalfired power plant year hurt american industry making electric power available reliable expensive ironically president obama africa held length importance electric power generating economic growth launched power africa initiative sadly remember connexion home example internet you internet pretty asset america world now completely highly aggressive interpretation authority federal communication commission administration regulate internet network electric utility set price rule force build network give service regard cost build network government running internet good idea forcing someone government fiat give network induce build network fact broadband wireless network fewer fact united state slipped term broadband access federal government dictating internet past year individual ability surf million website stream million videos save billion dollar purchase today president obama way waiting whiny squeal dialup decide connexion monumentally bad idea partisan national labour relation board attacking company move productive probusiness location administration undermining innovative education company fit vision uniondominated education system board administration heavy hand regulation brake growth point progrowth plan regulatory reform history taking aggressive action replacing administration regulation advance liberal agenda strangle business day office replacing gov jon corzine signed executive order froze day issuance regulation send clear message overzealous regulator business owner tormented progrowth approach regulation day one first president send message regulatory beast federal government president second regulation implement action explicitly authorised statute era ideological administration accomplish regulatory state vote accomplish duly elected congress end third regulation rational administration party requirement benefit major regulation supposed outweigh cost common sense administration costbenefit analysis largely ignored gamed second insist costbenefit analysis heed result required law president obamas small business administration admitted federal regulation cost employee company pay unnecessary regulation cut paycheck employee cut back investment raise price consumer why offer fourth proposal regulatory reform congress adopt regulatory budget cost complying regulation adopted federal government year exceed set amount fifth pay system fiscal side create regulatory zero rule rule promulgated equal cost sunsetted removed rule growth regulatory state smothering entire economy lastly respect regulation year president time major cleanup president commit transition review rule executive order published administration day one egregious unlawful revoked long regulatory arm government extended reach year time make long arm continue strangle prospect percent growth point fivepoint plan economic growth related number two time comprehensive effective national energy strategy year middle energy renaissance country north america really technology directional drilling hydraulic fracturing dramatically expanded americas production recoverable reserve oil gas result staggering lower gas price pump dramatic reduction oil import lower cost manufacturer shale gale major source job recovery job simply energy time year steel plant erected ohio supply pipe needed exploration visited mexico met president pena nieto fall north american energy renaissance surge production accompanied government led denationalisation mexicos energy industry north america friendly neighbour close trading partner canada mexico front major opportunity increase competitiveness regional economy world improve strategic security position time strengthen manufacturing sector reduce reliance european ally aggressive russia reduce exposure bad actor world economy venezuela iran create job home once make mistake energy boom occurred effort administration them energy boom revealed opportunity energy picture seize potential north american energy renaissance thing first build infrastructure product market ensure smooth functioning energy market mean constructing pipeline infrastructure needed yes including keystone pipeline mean infrastructure make increased energy export well second lift decade ban crude oil export market function producer advantage higher price type energy europe asia third mentioned above rationalise approach regulation make fair regulatory framework form energy compete fourth research technology capturing sequestering carbon improving battery technology storage wind solar tap form energy environmentally sound manner favour fuel political reason disfavour other end day critical measure success growth plan people work job worth doing today however federal policy discourage work obamacare discourage employer hiring taxe disincentive year multiple front allowed system grow people choosing work discouraged work incentive work great fourth point growth plan change system disincentivize work make government policy encourage work reduce marginal cost employee taking job reduce federally imposed cost employer hiring someone effect policy discourage fulltime work pew research centre year american age living parent home highest share decade failure launch problem hurt economic mobility hold back economic prospect generation long term start simple proposal heading repeal obamacare hour workweek requirement employer employing hour week required provide health insurance surprise effect provision massive incentive shift employee hour week mentioned earlier massive shift fulltime parttime employment president clear contributor hour workweek endangered specy list put american back work second week ago proposed eliminate payroll tax nearing end working career age propose similar tax break newly entering work force age encourage nearing retirement working make easier young enter work force good america third outlined hampshire week ago reform social security disability system encourage return work reward employer rehire disability proposed eligibility disability conditioned entering rehabilitation programme rehabilitation plan initial step broader philosophy this dignity work promote incentive work remove disincentive can finally point fivepoint growth plan america remain home innovation world america blessed decade home innovation successful startup company big company began startup hampshire greater boston silicon valley place country examine there realise step today preserve building block here first spend entitlement research lead innovation week ago hampshire outline specific ideas curbing growth entitlement spending federal government ideas save trillion dollar coming decade what innovation ask this past decade government spending entitlement health care percent gdp soared investment r&d basically flat year budget example spending medicaid percent budget national institute health percent budget national science foundation declined percent president budget congress touched blame them exact investment basic r&d areas biomedical research material science performance computing delivered large part individual investigator university laid vital groundwork innovation americas fastest growing industry technology biotech america remain home innovation crown jewel great research university lead world wither vine encourage private sector innovation part tax reform mentioned earlier make r&d tax credit permanent company including manufacturer r&d tax credit second leader innovation require focus education higher future speeches topic outline clear fix school give student parent choice reward great teacher paying more support expand charter school reform tenure prepare work force tomorrow create opportunity student higher side addition investing university federally supported research job matching skill produce student employer fastchanging economy standard practise country china majority job today america require postsecondary education good new american education before bad new that decade tuition cost tripled student debt soared graduate underemployed higher time focused student credential degree employer value greater transparency paying greater choice pay leverage technology make delivery education higher quality lower cost work private sector make pathway school postsecondary education entrylevel job market seamless match skill job opportunity compete global economy requirement key home innovation make young growing company source job creation america capital america year deepest liquid transparent capital market world principal home venture capital industry percent world venture capital managed here again destroying goose laid golden egg america losing lead global ipo market number stock listing dropping sharply part due unintended consequence regulation eliot spitzer research settlement helped destroy equity research trading business sarbanesoxley made expensive young company public doddfrank requirement fix young company window capital market close them reform make easier young growth company capital market essential socalled job act enacted step small step solved key problem equity small mediumsized businesse problem doddfrank hurt main street credit flowing middle america percentage bank balance sheet devoted making loan lease lowest level again back jimmy carter era number bank united state shrunk lowest level century doddfrank effect increasing big fail problem concentrating power big bank curtailed lending small business smaller bank economically vital fivepoint plan growth progrowth tax reform regulation control launching national energy strategy creating incentive removing disincentive work ensuring america home innovation manchester importance economic growth time samuel blodget helped organise city manchester goal leading place business succeeded today cnn rank manchester top city america live launch business now america attractive home company formation energy american people pent demand freed regulation pent capital ready invested growth plan reason american return strong economic growth path goal percent gdp growth restoration dream upward economic mobility generation american shared piece fivepoint plan growth interesting observation emerge subject bipartisan agreement past comprehensive tax reform lowering rate removing complexity tax code enacted president reagan working jersey senator bill bradley other welfare reform incentivize work product president clinton republican congress energy independence america ally discussed agreed policy party past subject bipartisan agreement happened politic happened today democratic party today democrat oppose tax reform promote growth make easier taxe year oppose provision incentivize work dependency today democrat turned left reflexively left oppose growth initiative party supported past nominee answer question answer this time america time put partisanship focus growth america future depend ability deliver standard living future generation obligation deliver life hang balance together fivepoint plan growth send strong signal change direction left afford tax cut point biggest loser low growth economy federal government revenue sag deficit swell afford prolonged period slow growth unwilling trim unrestrained growth entitlement change sowing seed demise programme preserve worry innovation pull slump cumbersome regulation underinvestment economy you country adopting progrowth policy making forwardlooking investment competitive world talent distributed globe home innovation earned given time recognise economic policy driven overwhelmingly belief government pick winner loser effort ingenuity american people path misery lower standard living loss opportunity freedom american republican suffer disease democrat political vilify wealthy accomplished token protect either policy president led crippling decline middleclass wage opportunity wealthiest wealthier stock market fueled borrowing easy money attack vilify successful america leader fight middle class growing economy unleashing opportunity growth president told villain blame loss opportunity blame president bush republican congress corporate ceos lobbyist take responsibility failed policy initiated hurt economy cut taxe year higher tax rate uncompetitive tax system world economy wealthy work year middleclass wage stock market wealth wanted america energy independent fight natural gas exploration coal technology refuse build keystone pipeline promised make college education affordable everyone year children graduate parent couches student debt generation history time protect social security year remain silent collision insolvency complicit trillion debt finally health insurance plan doctor them now due policy million american lost both failure led weak economy overwhelming anxiety american today kitchen table president doctor heal thyself stop blaming else fear late now american people cure ail cure today availed rejecting weak manipulative arrogant leadership failed democratic president ran onesentence slogan led country economic morass home timidity world embrace strong simple direct leadership trusting people grow economy fix live resolute truthtelling home globe restore american authority strength optimism telling american people truth hard truth grow economy provide middle class growing wage result growing opportunity fivepoint plan percent growth type honest specific plan america reach goal you god bless you god bless america ","m_szGeo1":"United States","m_szSourceType":"source_news","m_szSrcUrl":"http://www.nj.com/politics/index.ssf/2015/05/full_text_of_christies_economic_plan.html","m_Places":["New Hampshire","New Jersey","Manchester, N.h.","America","Afghanistan","Iran","Washington, Dc","Washington","United States","Reform","Well","Take","North Korea","China","Africa","North America","Ohio","Mexico","Canada","Russian Federation","Venezuala","Europe","Asia","Boston","Silicon Valley","Manchester"],"m_People":["Chris Christie","Charles Krupa","Barack Obama","Jimmy Carter","Ronald Wilson Reagan","Jon Corzine","Pena Nieto","Eliot Spitzer","Samuel Blodget","Bill Bradley"],"m_Companies":["Christie's","University Of New Hampshire","Ap","New Hampshire Today","Manchester Today","Path","White House","Congress","U.s. Congress","Bureau Of Labor Statistics","Bottom Line","Signal","Target","Irs","Uncle Sam","Democrats","Apple","General Electric","National Science Board","Republican Party","Federal Communications Commission","National Labor Relations Board","Small Business Administration","New Technologies","Pew Research Center","Social Security","National Institutes Of Health","National Science Foundation","Groundwork","Cnn","Democratic Party"],"m_BiGrams":["tax reform","tax rate","middle class","united state","fivepoint plan","american people","electric power","economic growth","tax code","home innovation","percent growth","federal government","week ago","work force","income inequality","comprehensive tax","corporate side","create job","plan growth","growth plan","middleclass american","economic mobility","plan america","president ran","heavy hand","gdp growth","private sector","weak recovery","specific plan","policy president","jimmy carter","current administration","policy discourage","growth economy","easy money","world economy","income tax","day one","rate percent","corporate tax","point fivepoint","build network","energy renaissance","make easier","capital market"],"m_TriGrams":["comprehensive tax reform","fivepoint plan growth","corporate tax rate"],"m_SocialTags":[],"m_Topics":[],"m_Industry":[],"m_Technology":[],"m_BiCnt":[13,12,10,10,8,8,7,6,6,6,5,5,4,4,4,4,4,4,4,4,3,3,3,3,3,3,3,3,3,3,3,3,3,3,3,3,3,3,3,3,3,3,3,3,3],"m_TriCnt":[4,4,3],"m_iDocBodyWordCnt":3257}
