{"m_szDocID":"1793019","m_szDocTitle":"Errata Security","m_szYear":"2016","m_szDocSumamry":"textArticle -------------------- Errata Security Use the freakin' debugger This post is by a guy who does \" not use a debugger \". That's stupid. Using a friendly source-level debugger (Visual Studio, XCode, Eclipse) to step line-by-line through working code is what separates the 10x programmers from the wannabes. Yes, it's a bit of a learning hurdle, and creating \"project\" files for small projects is a bit of a burden, but do it. It'll vastly improve your coding skill. That post quotes people like Rob Pike saying that stepping line-by-line is a crutch, that instead you should be able to reason","m_szDocBody":"errata security freakin debugger post guy debugger stupid friendly sourcelevel debugger visual studio xcode eclipse step linebyline workingcodeis separate programmer wannabe yes bit learning hurdle creating project file small project bit burden vastly improve coding skill post quote people rob pike stepping linebyline crutch reason code true understand completely real world programmer constantly forced stretch unfamiliar language worse yet forced unfamiliar library documentation suck understand apis step code watching returned value compiling source stepping experienced programmer true step line line understand completely fully reason about bother programmer spend small percentage time understand time spent coding noodling understand debugger account real world programmer spend lot time working people code set breakpoint run unit test reaches point programmer fetishize editor real programmer produce lot code fetishize debugger built ide debugging working code specialised tool diagnosing problem buggy code seriously learning programme learn debugger integrated ide step linebyline line code grok microsoft visual code good system debugging which good starting language learn pulling figure programmer contrary position aggressive debugger insight mere inspection window licence window homeor window professional difference question website ooh button download table technical list fluff scroll part concern encryption wait what difference device encryption bitlocker bitlocker device encryption well purchase screen window friendly pop offering help course techy worse useless while thought changed pop chat window start chatting same press difference admit different read document reading nonmicrosoft third party site true windowsnet microsoft site apparently allowed appear microsoft firewall internet jerk social engineer them difference point acting markov bot searching microsoft internal term give him selecting random phrase spew back understanding support tpm difference finally admit answer question offer send technical people work far planning write post continue game point learned precise questioning take awhile research answer time careful sleuthing google real answer below eventually back this previous person gibberish looked phrase spewed back random sampling tech term eventually device encryption was ars technica post designed window installed tabletstyle device ipad notebook computer strict hardware requirement work desktop laptop computer require tpm ssd fan sleeping tldr people situation desktop computer winhome device encryption work work tablet full disc encryption desktop winpro idea future tech support replaced bot natural language processing answer question like have tech support text find plausible answer understand regurgitate back word turing test finally won tech support welldesigned bot outperform human answering question tesla review charging buy electric car understand charging huge deal work filling gas tank doesnt long trip math bit planning math bmw model number engine size tesla model number size battery tesla kwh killowatthour battery mile range lowest end model tesla kwh hour battery mile advertised range united state typical plug volt circuit maximum amp math long itll recharge battery right day day kwh car absolute worse case scenario mind you demonstrate pay attention charging simply drive station fill tank couple minute drive away let live austin texas meeting dallas drive dallas tesla car charge meeting drive home dinner there letting car charge longer stay overnight nope hour later charge left home mile range kwh battery day recharge normal electric circuit faster charging worst case scenario luckily wont charging normal circuit emergency backup fail home highwatt device oven air conditioner clothes dryer higher wattage circuit typical max home circuit power connector normal circuit thicker wire forth math sucker get mile drive then drive dallas charge meeting dinner hour youll juice back home buy tesla youll hire electrician pay instal highend circuit garage car port garage circuit breaker located anyway lowend range choose nema plug power electric car tesla hpwc high power wall charger bundle cord together making easier charge back garage car pull cord plug real simple standard nema plug layout accidentally plug wrong blow circuit tesla proprietary wall charger trip dallas though problem charging circuit home road common possibly sound hard find well electric car thing people them unnaturally noticed electric vehicle plug you everywhere people ahead this storey driving dallas visit lookup charging station tonne them oilrich city dallas left coast california insane chance business meeting parking lot building door drive meeting drink dinner afterward drive home full charge note charging station primarily plug standard electric car support car standard electrical plug nema any note charging station run profit part network charging station free member popular network nationwide chargepoint popular city vary join couple network ive joined chargepoint free street park drive walk suck free juice sort franchise network own parking space network chargepoint buy unit pay installation payment back chargepoint parking space businesse encourage visit charge you ideally charging station deliver max power practise bit weaker luckily read people review online stress charging parking cost electricity negligible charging for instead charge time alway charge time leave car parked there power use tesla owner plug special tesla plug tesla make hpwc charger free business owner hotel call destination charging charge reach destination awesome tesla owner vastly option charge normal electric car level level charging charging map chargepoint mention level charging level mean standard plug electrical device business home external plug put map care charging level slow level mean faster level connector usually wide range charging speed original nissan leaf charge lot range car deal range tesla mercede model full charger support juice level tesla map mean hpwc mentioned above appeared month tesla aggressively pushed businesse hotel amp amp note car handle speed upgrade dualcharger level nema charging map month ago appeared now tell big reason businesse put tesla hpwc put nema plug cheap attract car teslas though standard plug reason exist camping park plug drive hook local electricity plug drive tesla indeed back car big sleep option describe below fast charging electricity wall alternating current battery however deal direct current plug car device inside called chargermust convert current car limitation juice consume limited charger capacity alternative place charger car bigger feed direct current car lot complexity here car computer talk external charger time order adjust flow current computer networking protocol copper connexion power car regenerative brakingoften charge battery time faster level charger mentioned above battery pack handle indeed tesla supercharger charge rate mile driving range minute charging tesla network supercharger freeway united state drive country idea couple hour stop minute relax drink coffee pee charge car stage driving scenario above supercharger waco halfway austin dallas stall available waco mile dallas meaning fully charge there make dallas back waco recharging cutting bit close kwh model though destination east side dallas corsicana supercharger easier supercharger teslas solution problem standard asian standard chademo european standard called combo adapter component combined standard chademo early standard coming japanese car combo adapter appear winning standard long run tesla support standard standard tesla charging speed maxing and less tesla mentioned direct charging dump power battery fast battery mean battery bottleneck experience charging phone laptop charging full forever true tesla trick kwh car ship kwh battery tesla upgrade car higher range consist tesla turning switch enabling entire battery but supercharging kwh battery mean charge full minute minute charging lower lifetime battery tesla recommend charge anyway again kwh battery charging mean anyway thus benefit larger battery paying extra range kwh upgrade kwh kwh model year free supercharger access true cheapest model they changing this cheque this offpeak charging revolution recently smart electrical metre bill timeofday consume power charging peak hour offpeak paying attention this billing plan changing live charge one cent kilowatthour offoffpeak insane compared country tesla configured charge home plug start charging away wait offpeak offoffpeak start charging conclusion electric charging math appreciation power gasoline filling gas tank equivalent charging multiple megawatt speed electric car close driving range limit car require planning math new bitcoin world hack thought write simplified explanation bitcoin know idea bitcoin explain term important here bitcoin public ledger the blockchain transaction was ledger huge gigabyte growing moore law computer grow faster problem entry ledger move coin received previous entry give recipient word move coin received there guy future guy spend coin transaction refer back transaction here called chain transaction refer previous one back original creation coin actually transaction fixed simply moving money around instead scriptis used written bitcoinspecific programming language add multiply compare number however full programming language call function execute loop complex creativity allowing transaction escrowed party that altcoin bitcoin off people started create variation variation offered meaningful improvement bitcoin popular speculator pump dump hoping buy low price sell fool higher price altcoin made improvement zerocoin ethereum zerocoin work making transaction anonymous ethereum altcoin discussed here ethereum ethereum variation bitcoin full programming language simple scripting language reason ethereum support smart contract organise small conference people money rent hotel such people date deposit refunded ethereum write javascriptlike language code contract guarantee ticket conference money refunded depending simple example possibility endless lot people excited which course make believer insufferable nonbeliever system dao dao stand decentralised autonomous organisation notionally fund small conference include more member buy share dao number share have vote thing dreamer idea replace democracy run entire country way type daos ethereum blockchain thedao sort daobased buy vote investment fund make reap return big organisation run bit code data etherium blockchain investment scheme gobbled ethereum coin million worth ethereum billion ecosystem leave fund splitfrom include share unspent ethereum coin token representing return investment part paid out split cash out dao shard track investment pay out dao hacked member exit investment scheme call function namesplitdao issue member supply code transaction code dao code transfer ethereum coin feature part bitcoin well ethereum code recursive mean function running call time bug whensplitdaois called call recipient code transfer ethereum coin recipient code call splitdao againbefore finishing process repeat itself transferring ethereum coin calling splitdao again call hacker code call splitdao call hacker code process continue endlessly drain thedaos coin yousplitlike this force wait day etherium coin thus hacker month recover stolen money destroying entire principle cryptocurrency cure cancer howitzer solution rollback blockchain theft course mean screwing made transaction then screwing people million order compensate theft million course type corrupt thinking banking failure real world screw order protect bank big fail solution update ethereum code blacklist address yet insert magic key give control fund back thedao problem changing code fork blockchain transaction added chain miner decentralised people include you run mining software computer miner update code change working blockchain dont blockchain repair miner update latest code softfork hopeless broken hardforkof irreconcilable chain mean cryptoanarchist entire point cryptocurrency corrupt human repair problem corruption violation thedaos contract code contract superseded human reinterpretation tacit acknowledgement thedao deserve special treatment smaller maker contract similar recursionbug miner vote choosing software run point ethereum favouritism miner consensus profound betrayal trust maintaining code helping thedao obviously complexity ethereum huge security repeatedly exploited future recursion demand writing contract write code extraordinarily carefully hindsight obvious recursion allowed feature fixed hardfork also future additional problem dangerous recursionissue fascinating past people hired lawyer review complicated contract future hire hacker contract signed motivated hire good hacker reading code hack advantage case original concept thedao useless utopian nonsense original bitcoin created people understood lot currency thedao created people hopelessly naive investing put system hand trained monkey wisdom crowd proposed ignorance mob hacker put stop nonsense slid sort ponzi scheme creator arrested couple year now updatethe hacker bribing miner fork promising give miner etherium protocol create transaction take money blacklisted address donate directly mine block skyhigh transaction fee choosing fork forgoing payment thus hacker power corruptly subvert system counterbalance etherium power link scanning clamav day week day released clamav well day noticed idiotic feature clamav scanned internet problem feature daemon listen command scan file normally listen locallyfor command reconfigured listen remotelyon tcp port package include clamav default this simple protocol consist sending command clear text ping version shutdown scan ran masscan command masscan hellostring vkvsulptg scan address range port port case find million machine instead establish full tcp connexion banner option doe giving thousand machine successfully establish connexion remaining machine large range internet firewall configured respond synack express purpose frustrating port scanner machine web server running odd port machine running vnc machine running ssh specifically clamav send command hellostringfeature send version encoded base commandline masscanin case send binary find machine respond back clamav signature typical example response are thought date updated software page roughly half date morning day before date updated signature conclude roughly half clamav installation configured autoupdate signature roughly machine nearly half version released four year old thinking appliance maker barracuda bundled software appliance notorious updated software hint nondefault configuration common user made decision software bundle clamav thing scanning port clue map version ssh service running ssl version thought mail server since thatd common task clamav server ran mail server software mystery specific version popular manually tested machine scan foo replied file found hint unit found vulnerable day thing bunch system claiming chinaddos system conclusion sort stuff exist number clamav system public internet zero inside corporate network number stuff turned firewalled such iptable specific machine important result half system eoled longer supported half system latest update overlap system latest signature outofdate software and connect computer together musky feudalism mar recently press fawned elon musk comment conference musk direct democracy system citizen vote directly law voting corrupt nonsense political system feudalism direct democracy representative congress layer top bureaucracy rule restrict law voted congress regulation decided bureaucrat gulf oil spill example happened oil company cosy regulator mineral management service mms part department interior bureaucrat dual mandate protect environment promote economic activity oil company lobbied risk environment favour profit obamcare controversial mandate health insurer pay abortion part law pass congress decision bureaucrat charge detail carrying law federal communication commission fcc regulation internet base power regulate internet law essentially predate internet matter ideal direct democracy musk leave decision making hand bureaucracy true space flight mar something wrong air system technician making quick decision fix otherwise people suffocate long chance vote issue technician trusted important decision jettisoning pod killing people order save remaining matter political system bureaucracy making tactical daytoday decision upper tier making long term strategic decision political system work monarchy direct democracy largely change name bureaucrat substantively different corruption democracy necessarily power voter themselve voter idiot vote idiot candidate uss current election season populist demagogue preying people ignorance proposing solution educated people unworkable majority voter economic class understand foreign policy qualification make decision make education voter overwhelming decide themselve dispassionately whole college student vote free college people vote social security health care mother vote child leave child care racist vote unwanted type community corruption core tocqueville famous noting democracy last point population realise vote call corruption current system member lobby congress screwed indeed lobbyist special favour government alleviate special punishment sort corruption defending voter corruption famous quote goe democracy worst form government other horrible system found better space exploration rule longer apply imagine political system overwhelmingly system vote feet future billionaire creation space station earth asteroid belt yes absolutely dictator artificial world evil competing people work live space station system work earth barrier changing country high european union example citizen country move country wish dont tied language culture community space exploration barrier movement exist space united state people move lot move state best sure culture south york midwest texas west coast tiny barrier compared stopped movement past thus people vote vote deciding space station best free health care space station money pocket station free health care benefit vote feet system coercion democracy backed police state coerce you point gun conform majority decided earth submit country leaving viable option imagine petit dictator musky space station coerce people simply leave law voluntary leave leave imagine musky surprise inhabitant seal airlock enslaving sudden happen once space station dictator together agree sort big charter guaranteeing people right leave space station agree member violate charter rest break outside freeing people plausible scenario billionaire trick people slavery good uber worker cheap loan car worry activist enslave worker working long hour low pay order satisfy agreement uber agreement signed realising consequence happen future worker leave space station paid debt system rigged them happen note above happen current system word around uber deal fairly worker hear storey billionaire dictator space station likewise deal bit fairly system billionaire corporation dictator serf them monolithic corporation disaster instead space station outsource life support company managing life support propulsion company managing rocket contract food service company dictator world deal banking corporation world monarchy midevil time borrow money bank conduct war political system space exploration lot feudalism full yeomen who free move about serf tied land morally defensible system government coerced follow law dislike vote feet choose law suite them bad rule suffer make good rule prosper post work progress read tweet today fuzzing masscan afl forgot remove crashhandler crashes logged hang david davidson turn fuzzing input file good apparently found bug huge threat instead fuzzed network input chronic problem afl designed inserting file network traffic programme making work pretty trivial make tiny change masscanso opening libpcapadapter open libpcapformatted file change trivial successfully running tough configure commandline addresse match libpcap file content pain created sample lipcapfile checked project document explaining git clonethe project run make run command line run yourself nobacktrace adapter sourceip sourceport sourcemac routermac cccabd seed banner nostatus run commandline appear return immediately appear millisecond wait limit fuzzing speed attempt second thousand second tougher change fixing that meanwhile run bunch afl parallel this run afl working moment error see command return hanging run afl return option increase timeout help running masscanin way parsing configuration file work fine update changed join thread cleanly entire run cleanly stop wait however create problem afl refused run crashing hanging afl suggest outofmemory issue increase memory bumped memory running memory problem along masscan assume big scanning set large data structure start exceed megabyte assumed afl running fuzzing server response input success pcap file byte long however afl trimmed input file byte file testing libpcaplibrary moment fact support multiple file type determined magic string byte make fuzz starting deeper file byte update llvm version working raspberry odroid arm naturally spread work core odroid slightly faster cpus raspberry importantly bit linux raspberry apparently stilldoesnt fellow republican support trump scott adam creator dilbertcomic strip post claiming trump presidency bad people fear good post wrong trump bad hater claim trump disable criticalthinking ability supporter enemy conversation end defending trump support candidate support criticalthinking racist sometime time love political incorrectness said horrible president longterm republican prefer hillary clinton presidency hate hillary depth soul corrupt worst all leftist worse leftist rightwinger populist demagogue populist demagogue problem caused you know thosepeople unrealistic solution problem appeal base emotion ignorance nation fail politic alwaysdue populist demagogue virtually dictator man people protecting people interest powerful somehow dictator part powerful definition people venezuela now economy crashed oil price gdp oil export leader making worse running playbook bad populist policy printing money year economic textbook inflation blaming resulting inflation united state cia manipulating price essence populism pursue horrible policy blame consequence them trump presidency bad result educated people caused government policy blamed mexico china worst get crowd cheer trump congresss bad policy punish mexico china make bad policy worse minimum wage promoted bernie sander hateful populist demagogue anything worse trump hillary wanted minimum wage presumably negative thingy happen hike minimum wage presumably educated people studied problem measure thing are nonpartisan congressional office management budget omb analysis raising minimum wage describe numerous positive negative effect fit demagogic sound bite raising minimum wage broad popular support republican educated downside yet raised explanation populist bernie trump conspiracy such wall street billionaire prevent minimum wage raised truth political leader basing decision omb report basing vote educatedanalysis policy corruption bribe wall street note wrong answer raising minimum wage reasonable people side true debate based education public debate based emotion ignorance trade bernie trump oppose way educated people obvious benefit population whole yet special interest exploit ignorance populace people oppose trade again antitrade policy crowd pleaser populace demagogue explain policy adopted blaming vast conspiracy powerful chinese lobbyist wall street executive move factory mexico again wrong answer oppose latest trade deal tpp ttip expand regulation reduce tarif example benefit trade exceed cost cost change born unfairly group point support trade oppose raising minimum wage instead point populist moral issue transcended educated thought policy opposed reasonable educated people populist create conspiracy theory explaining opposition power rest quality conspiracy theory politician populist regard current president obama obama failed populist policy closing gitmo blame republican bit scorchedearth populistdemagogue them danger democracy populist demagoguery alexis tsipras elected wave populism proceded make greek debt crisis worse populist leader venezuela making oil crisis worse educated opposed policy smart reason ignorant crowd overran them educated learned quiet happen trump presidency crisis happen crisis happen revert populist demagoguery sweep informed rational debate issue republican politician meekly agreed trump candidacy politician backbone stand him republican mute criticism trump democrat frothing mouth hatred trump listen them either trump unforgivably racist though barely white supremacist enemy claim trump crappy businessman successful claim successe based flimflam faulty belief success con man good manager negotiator claim international politic work negotiating price building material world stage laugh him forgiven candidate suck much instead make trump dangerous populist demagoguery historically destroy democracy make people live worse off drumpf german work willingness evil trump claimed original drumpf true german language work trump power shortcircuit critical thinking supporter enemy drumpf meme example official pronunciation spelling german trump grandfather born thisthe guardianarticle describe city kallstadt trump grandfather born spelling family church record drumb tromb tromp trum trumpff dromb trump person spell way document name children spelled parent make german genealogy tough sometime time areas german dialect dutch german today indeed dialect persist german grow city learn local dialect standard german language understand standard german villager speak live entire live hundred kilometre grew away people longer understand them german dialect subdialect accent consistent language shift sound pronounced differently word example word english german instead word pennybecoming pfennig pepperbecoming pfeffer kallstadt located pfalzregion germany pronounce local dialect palz german like english local dialect thus trump speak pfalz dialect trumpf speaking standard german word stocking standard german strumpf document written time pfalz region spelling strumpstrumpf strumpffstrimp andstrompboth vowel consonant change according pfalz dictionary found online friederich trump born time germany split numerous smaller country german empire unified germany created counsel standardise language spelling friederich emigrated america word birth predate era wouldve standardised spelling name record have trump baptism record trump spelled america trumpf immigration form perfectly reasonable immigration officer german speaker asked name spelled version german idea official modern invention invention modern state government official exist back friederich born birth record baptismal record local church thus trump spelled trump officially spelled past changed sure church document stuff spelling word name handled back then insisting drumpf ignorant german language work updatesomebody named gwenda blair wrote book trump family claim hann drumpf settled kallstadt connect dot after year war happened famous event germany burnt church record german family tree traced back year war further probable related hann ancestor trump time spelled drumpf official spelling german worked time update snope true donald trump ancestor changed surname drumpf trump snope wrong moron correct answer there record change fact difference source make conflicting claim shouldve proof snope evidence support claim btw greatgrandmother pennsylvania dutch region distantly related trump btw weird talking grandfatherborn year ago grandfather son born father trump born generation back prehistorical era say era writing standardised spelling thursday wednesday ","m_szGeo1":"United States","m_szSourceType":"source_news","m_szSrcUrl":"http://blog.erratasec.com/","m_Places":["Most","Well","Tesla","United States","Austin, Texas","Dallas","California","Teslas","Waco","Austin","Corsicana","New York","Texas","Venezuala","Mexico","China","Wall Street","Germany","America","Morons"],"m_People":["Elon Musk","David D. Davidson","Friederich Trump","Scott Adams","Hillary Rodham Clinton","Bernie Sanders","Barack Obama","Alexis Tsipras","Gwenda Blair","Hanns Drumpf","Donald Trump"],"m_Companies":["Microsoft","Google","Technica","Bmw","Real Simple","Nationwide","Indeed","Revolutions","Bp","Gulf Oil","Department Of The Interior","Federal Communication Commission","Fcc","European Union","Uber","Afl","Afls","Linux","Cia","Congressional Office Of Management","Omb","Democrats","Guardian"],"m_BiGrams":["space station","minimum wage","electric car","charging station","ethereum coin","political system","populist demagogue","educated people","device encryption","united state","kwh battery","direct democracy","raising minimum","standard german","real world","tech support","battery tesla","nema plug","programming language","health care","space exploration","vote feet","file byte","trump presidency","wall street","populist demagoguery","german language","local dialect"],"m_TriGrams":["raising minimum wage"],"m_SocialTags":[],"m_Topics":[],"m_Industry":[],"m_Technology":[],"m_BiCnt":[10,8,6,5,5,5,5,5,4,4,4,4,4,4,3,3,3,3,3,3,3,3,3,3,3,3,3,3],"m_TriCnt":[4],"m_iDocBodyWordCnt":3844}
