{"m_szDocID":"1804825","m_szDocTitle":"An Economic Forecast for the European Union - The New York Times","m_szYear":"2016","m_szDocSumamry":"textArticle -------------------- The New York Times Business Day |An Economic Forecast for the European Union Advertisement Business Day | The Week Ahead An Economic Forecast for the European Union By THE NEW YORK TIMES MAY 1, 2016 This is what to expect from the week ahead: ECONOMY Taking the pulse of the eurozone. Tuesday morning, the European Commission will announce its spring economic forecast for growth and employment across the 28 member states of the European Union. The forecast may also shed light on whether the long-awaited recovery in the eurozone may finally be consolidating and on","m_szDocBody":"york time business day economic forecast european union advertisement business day week ahead economic forecast european union york time expect week ahead economy taking pulse eurozone morning european commission announce spring economic forecast growth employment member state european union forecast shed light longawaited recovery eurozone finally consolidating effect falling price economic slowdown china commission make forecast time year update estimate cost benefit ongoing largescale migration european nation jame kanter job market number due labour department scheduled release report nation hiring unemployment april month uninterrupted job growth private sector american economy broken record report encouraging gain impressive addition job average hourly wage increased percent proportion american labour force decline hit twoyear percent economy growth rate sluggish job market remained bright spot wall street estimate employer hired worker month wage continue forward momentum patricia cohen autos analyst expect vehicle sale rise automaker scheduled report sale vehicle united state april analyst expect industry report increase month year ago research firm kelley blue book forecast percent improvement seasonally adjusted annual sale rate month million vehicle truck sport utility vehicle continue propel growth market passenger car made honda nissan selling well analyst watching auto company increasing discount incentive improve sale volkswagen halt steady decline united state admitting year cheated diesel emission test bill vlasic tesla share model number electric carmaker tesla motor expected report firstquarter earning wednesday release detail money raised taking reservation forthcoming model vehicle company received deposit newest electric car sale end year earliest tesla preparing expand manufacturing operation california planning build battery plant nevada bill vlasic bank quarterly result european bank busy week bank earning europe largest institution report firstquarter result british bank hsbc swiss lender ubs french bank bnp paribas socit gnrale expected provide update investor quarter difficult lender uncertainty financial market weighed banking result europe united state challenging environment europe biggest lender midst reshaping businesse chad bray advertisement technology alibaba focuse efficiency expansion alibaba build momentum strong earning end year announce result quarter thursday chinese ecommerce giant struggled live huge hype ahead listing working efficient expand operation rural part china analyst watching company performance indication broader confidence chinese consumer world secondlargest economy continue experience slower economic growth paul mozur commodity steel industry hope stabilisation arcelormittal world largest steel company planning report firstquarter earning friday investor study result beleaguered steel industry beginning turn around arcelormittal lost billion steel maker success persuading united state european union impose protective tariff chinese steel export company undercutting product analyst expect luxembourgbased company report lower profit quarter stanley reed photo arcelormittal factory eastern france company report firstquarter earning friday credit nicolas pressphoto agency media redstone trial set begin month ailing media mogul sumner redstone subject salacious legal battle mental capacity friday public trial scheduled begin suit filed manuela herzer companion redstone herzer claim redstone mentally competent removed directive supervision health decision day redstone removed herzer personal estate planned leave million los angele mansion valued million photo sumner redstone credit fred herzer fought legal battle love redstone concerned wellbeing lawyer redstone called suit meritless money courtroom drama concern redstone personal life broad implication viacom cbs media company continue control emily steel version appear print york edition headline economic forecast european union order reprint today paper datemeta ","m_szGeo1":"United States","m_szSourceType":"source_news","m_szSrcUrl":"http://www.nytimes.com/2016/05/02/business/an-economic-forecast-for-the-european-union.html?partner=rss&emc=rss","m_Places":["China","United States","Wall Street","Tesla","California","Nevada","Europe","Luxembourg","France","Los Angeles","New York"],"m_People":["James Kanter","Patricia Cohen","Bill Vlasic","Chad Bray","Paul Mozur","Emily Steel","Stanley Reed","Sumner Redstone","Manuela Herzer","Fred Prouser"],"m_Companies":["New York Times","European Union","European Commission","Labor Department","Honda","Volkswagen","Diesel","Tesla Motors","European Banks","British Bank","Hsbc","Ubs","Bnp Paribas","Société Générale","Alibaba","Arcelormittal","Reuters","Viacom","Cbs"],"m_BiGrams":["european union","economic forecast","united state","report firstquarter","forecast european","analyst expect","firstquarter earning"],"m_TriGrams":["economic forecast european","forecast european union","report firstquarter earning"],"m_SocialTags":[],"m_Topics":[],"m_Industry":[],"m_Technology":[],"m_BiCnt":[5,4,4,4,3,3,3],"m_TriCnt":[3,3,3],"m_iDocBodyWordCnt":529}
