{"m_szDocID":"1806061","m_szDocTitle":"China Development Bank Finances LDK-SPI Solar International Expansion Plans  | CleanTechnica","m_szYear":"2012","m_szDocSumamry":"textArticle -------------------- China Development Bank Finances LDK-SPI Solar International Expansion Plans January 6th, 2012 by Andrew   Photo courtesy LDK Solar Roseville, California-based SPI Solar, a US subsidiary of China’s LDK Solar, today announced it has secured $44 million in construction financing from China Development Bank (CDB) to carry out solar photovoltaic (PV) projects with KDC Solar in New Jersey. Separately, LDK secured $20 million in CDB financing for two projects in California for which its providing engineering, construction and procurement (EPC) services to SPI. SPI and","m_szDocBody":"china development bank finance ldkspi solar international expansion plan andrew photo courtesy ldk solar roseville californiabased spi solar subsidiary chinas ldk solar today announced secured million construction financing china development bank cdb carry solar photovoltaic project kdc solar jersey separately ldk secured million cdb financing project california providing engineering construction procurement epc service spi spi ldk announced provide construction financing facilitate longterm financing supported ldk million solar energy facility sef project part preferred provider agreement jersey kdc solar cdb financing solar china development bank chinese government economic development bank such chinese bank authorised corporate bond shortterm commercial paper supershortterm commercial paper mediumterm note packaged sme note underwriting private placement bond cdb strategic focal point financing emerging industry china include solar power form clean energy line chinas global exportoriented policy directive scaling international lending book outstanding domestic foreign currency loan totaling rmb billion usd million yearend cdb expanding credit rapidly recent year total funding reached rmb trillion usd billion issuance rmbdenominated debt security rose rmb billion usd billion billion usd billion increasing proportion coming international investor foreign currency denominated debt security total rmb billion usd million issued hong kong international market foreign currencydenominated debt security issuance amounted usd billion cdb supported ldk growth chinas largest integrated solar company solar power company founding continue now ldk struggling stay solvent amid collapse solar cell panel price growing uncertainty government support solar power key market worldwide support company scaling back expanding amidst industry shakeout drop demand put ldk verge insolvency ldkspi solar expansion part spi adding largescale solar project pipeline domestically internationally applying cdb additional financing jan spi announced awarded epc contract jersey seashore solar development llc megawatt fixed ground mount sef egg harbour township supply clean renewable electricity southern jersey power grid addition helping meet clean energy target established state renewable energy portfolio standard egg harbour sef expected create local job construction construction due begin quarter contingent seashore solar closing project financing successful relationship cdb direct result close working relationship ldk steve kircher ceo spi solar continue develop pipeline project globally partnership cdb grow stronger china cdb fiscal position adopt countercyclical economic policy case european union stepping government support now time flagging demand deflationary force work correct keynesian macroeconomic policy response provided monetary fiscal stimulus credit expansion contraction limited ability pursue needed worse arent able prone employ fiscal monetary stimulus work great effect china burden accumulated debt leverage accumulated past decade more date hottest cleantech new subscribing free cleantech newsletter eye sectorspecific new also free solar energy newsletter electric vehicle newsletter wind energy newsletter havent reader survey yet now tag california solar energy china development bank china economic development china global china solar energy clean tech investment egg harbour solar kdc solar ldk solar jersey solar renewable energy finance solar finance solar spi solar china solar trade uschina solar uschina trade andrew reporting writing wide range topic nexus economic technology year now asiapacific europe americas africa middle east issue related broad topical areas pose tremendous opportunity challenge define quality live relationship natural environment related post ","m_szGeo1":"United States","m_szSourceType":"source_industry","m_szSrcUrl":"http://cleantechnica.com/2012/01/06/china-development-bank-finances-ldk-spi-solar-international-expansion-plans/","m_Places":["Roseville, California","United States","China","New Jersey","California","Hong Kong","Asia","Europe","Africa","Middle East"],"m_People":["Steve Kircher"],"m_Companies":["China Development Bank","Cdb","Seashore Solar Development Llc","European Union","Eu","Nexus"],"m_BiGrams":["development bank","china development","solar energy","usd billion","ldk solar","spi solar","kdc solar","solar power","rmb billion","billion usd","debt security","egg harbour"],"m_TriGrams":["china development bank","rmb billion usd"],"m_SocialTags":[],"m_Topics":[],"m_Industry":[],"m_Technology":[],"m_BiCnt":[5,4,4,4,3,3,3,3,3,3,3,3],"m_TriCnt":[4,3],"m_iDocBodyWordCnt":502}
