{"m_szDocID":"1808150","m_szDocTitle":"After Zynga announcement, bitcoin price tops $1,000 - Chicago Tribune","m_szYear":"2014","m_szDocSumamry":"textArticle -------------------- After Zynga announcement, bitcoin price tops $1,000 Rick Bowmer/Associated Press The price of bitcoin topped $1,000 Monday after Zynga, an online gaming company, announced it would begin testing using the digital currency as payment. Above, an April 2013 file photos shows a roll of bitcoin tokens. The price of bitcoin topped $1,000 Monday after Zynga, an online gaming company, announced it would begin testing using the digital currency as payment. Above, an April 2013 file photos shows a roll of bitcoin tokens. (Rick Bowmer/Associated Press) Ricardo Lopez The p","m_szDocBody":"zynga announcement bitcoin price top rick press price bitcoin topped zynga online gaming company announced begin testing digital currency payment above file photos show roll bitcoin token price bitcoin topped zynga online gaming company announced begin testing digital currency payment above file photos show roll bitcoin token rick press ricardo lopez price bitcoin shot past zynga online gaming company announced test digital currency payment bitcoin volatile unregulated currency hit high low recent week gained widespread use currency recently plummeted china action limit country hit gox online exchange major bitcoin trading exchange retreating morning announcement posted reddit weekend zynga accept bitcoin payment game farmville castleville game response bitcoin rise popularity world zynga bitpay testing expanded payment option player make ingame purchase bitcoin company said fouryear currency elbowing digital ether popular people company organisation decided currency university cyprus recently announced begin accepting tuition payment bitcoin newport beach auto dealership month accepted bitcoin payment time sale tesla model performance electric car summer twin cameron tyler winklevoss settled claim social network inc idea filed paperwork launch bitcoinrelated investment offering wall street bank america merrill lynch analyst recently issued note digital currency supporter formed political action committee back bitcoin washington also datemeta ","m_szGeo1":"United States","m_szSourceType":"source_news","m_szSrcUrl":"http://www.chicagotribune.com/bluesky/technology/la-fi-mo-zynga-bitcoin-price-tops-1000-20140106-story.html","m_Places":["China","Farmville","Cyprus","Newport","Wall Street","Washington"],"m_People":["Rick Bowmer","Ricardo Lopez","Cameron","Tyler Winklevoss"],"m_Companies":["Zynga","Associated Press","Reddit","Facebook Inc.","Bank Of America","Merrill Lynch"],"m_BiGrams":["digital currency","price bitcoin","zynga online","online gaming","gaming company","company announced","announced begin","currency payment"],"m_TriGrams":["zynga online gaming","online gaming company","gaming company announced","digital currency payment"],"m_SocialTags":[],"m_Topics":[],"m_Industry":[],"m_Technology":[],"m_BiCnt":[4,3,3,3,3,3,3,3],"m_TriCnt":[3,3,3,3],"m_iDocBodyWordCnt":197}
