{"m_szDocID":"1810249","m_szDocTitle":"You Can Now Buy Victoria's Secret Lingerie With Bitcoins - SFGate","m_szYear":"2013","m_szDocSumamry":"You Can Now Buy Victoria's Secret Lingerie With Bitcoins Julie Bort, provided by Published 6:12Â pm, Monday, December 23, 2013 You can buy a house with bitcoins , a Tesla electric car , a trip into outer space on Richard Branson's Virgin Galactic airline , and all kinds of other things from pizza to illegal drugs . And now, you can use bitcoin to buy Victoria's Secret lingerie via a gift card from Gyft , the app that replaces physical gift cards. The Gyft app is an interesting take on gift cards because it does a couple of cool things. It lets you buy gift cards from about 200 retailers using c","m_szDocBody":"buy victorias secret lingerie bitcoin julie bort provided published monday buy house bitcoin tesla electric car trip outer space richard branson virgin galactic airline kind pizza illegal drug now bitcoin buy victorias secret lingerie gift card gyft app replace physical gift card gyft app interesting gift card couple cool thing let buy gift card retailer conventional currency bitcoin victoria secret signed retailer gyft say business insider ","m_szGeo1":"United States","m_szSourceType":"source_news","m_szSrcUrl":"http://www.sfgate.com/technology/businessinsider/article/You-Can-Now-Buy-Victoria-s-Secret-Lingerie-With-5089750.php","m_Places":["Tesla","Victoria"],"m_People":["Julie Bort","Richard Branson"],"m_Companies":["Victoria's Secret","Virgin Galactic"],"m_BiGrams":["gift card"],"m_TriGrams":[],"m_SocialTags":[],"m_Topics":[],"m_Industry":[],"m_Technology":[],"m_BiCnt":[4],"m_TriCnt":[],"m_iDocBodyWordCnt":66}
