{"m_szDocID":"1817874","m_szDocTitle":"ADB Approves $135 million Loan For Cleaner Coal-fired Power Plant In China | CleanTechnica","m_szYear":"2010","m_szDocSumamry":"textArticle -------------------- ADB Approves $135 million Loan For Cleaner Coal-fired Power Plant In China February 10th, 2010 by Mridul Chadha Â  Asian Development Bank has approved a loan of $135 million to facilitate the construction of an Integrated Gasification Combined Cycle power plant. Although the power plant will be using coal as the primary fuel it air pollution and greenhouse gas emissions from the plant will be lower than the conventional coal-fired power plants. [social_buttons] An Integrated Gasification Combined Cycle power plant converts coal into gas through the process of ga","m_szDocBody":"adb approve million loan cleaner coalfired power plant china mridul chadha asian development bank approved loan million facilitate construction integrated gasification combined cycle power plant power plant coal primary fuel air pollution greenhouse gas emission plant lower conventional coalfired power plant socialbutton integrated gasification combined cycle power plant convert coal gas process gasification coal converted synthetic natural gas syngas resulting mixture gase comprising hydrogen carbon monoxide filtered remove particulate matter filtered gas ignited highly compressed air flue gasesresultingfrom combustion gas mixture fed gas turbine connected generator produced electricity igcc power plant efficient exhaust gase gas turbine convert water steam heat recovery steam generator whichprincipally work heat exchanger utilise heat exhaust gase coming gas turbine steam produced fed steam turbine produce electricity generator efficiency power plant higher conventional gasfired coalfired power plant utilise energy exhaust gase gas turbine conventional coalfired power plant burn coal directly generate steam release exhaust gase atmosphere extracting work power plant thermal efficiency produce lesser amount sulphur dioxide carbon dioxide emission addition exhaust gase free particulate matter captured duringfiltration average efficiency coalfired power plant china iea focus clean coal report thermal efficiency combined cycle power plant increased temperature flue gase fed gas turbine increased power plant prove bridge carbonintensive conventional coalfired power plant renewable energy based power plant developing country china india highly dependent coal power generation power plant boost economic growth providing low cost power poor limiting amount greenhouse gas emission problem though plant capital cost unit cost generation compared coalfired power plant higher case igcc power plant still adb note cheapest reducing carbon emission compared expensive untested technology cost generation expected match conventional power plant government world launch cap trade scheme efficient cheaper cleaner power plant combined cycle gas turbine power plant natural gas directly fuel eliminating energy requirement gasification filtration china substantial gas reserve larger find reported frequently cnooc found underwater gas field south china sea verified reserve billion cubic metre combined cycle based power plant developing country avoid transition expensive efficient renewable energy based technology reduce carbon output india china announced target reducing carbon intensity carbon output unit gdp developing country set power plant trend potentially result increase production equipment required reduction capital cost additionally power plant gradually popular carbon offsetting trading scheme kick developed country setting coalfired power plant developed country support power plant financing technical assistance via people daily online image credit wallyg under creative common licence view presented author personal view represent university pursuing master degree date hottest cleantech new subscribing free cleantech newsletter eye sectorspecific new also free solar energy newsletter electric vehicle newsletter wind energy newsletter havent reader survey yet now ","m_szGeo1":"United States","m_szSourceType":"source_industry","m_szSrcUrl":"http://cleantechnica.com/2010/02/10/adb-approves-135-million-loan-for-cleaner-coal-fired-power-plant-in-china/","m_Places":["Appear","China","India","China Sea"],"m_People":["Mridul Chadha"],"m_Companies":["Asian Development Bank","Cycle","Iea","Cnooc","Daily Online","Creative Commons","Teri University"],"m_BiGrams":["power plant","coalfired power","gas turbine","combined cycle","exhaust gase","cycle power","conventional coalfired","developing country"],"m_TriGrams":["coalfired power plant","combined cycle power","cycle power plant","conventional coalfired power"],"m_SocialTags":[],"m_Topics":[],"m_Industry":[],"m_Technology":[],"m_BiCnt":[26,8,6,5,5,3,3,3],"m_TriCnt":[8,3,3,3],"m_iDocBodyWordCnt":433}
