{"m_szDocID":"1817681","m_szDocTitle":"What The Joint Climate Policy Announcement From US And China Means","m_szYear":"2014","m_szDocSumamry":"textArticle -------------------- Originally published on Rocky Mountain Institute . By Clay Stranger and Jon Creyts, Ph.D. Yesterday the United States and the People’s Republic of China reached an historic agreement in the global effort to reduce greenhouse gas emissions and address the impending consequences of climate change through commitments by President Obama and President Xi. The U.S. announced plans to reduce greenhouse gas emissions 26–28 percent below 2005 levels by 2025, with a commitment to a “best effort” to realize 28 percent.  Achieving those targets will require doubling annual","m_szDocBody":"originally published rocky mountain institute clay stranger jon creyt phd yesterday united state people republic china reached historic agreement global effort reduce greenhouse gas emission address impending consequence climate change commitment president obama president announced plan reduce greenhouse gas emission percent level commitment effort realise percent achieving target require doubling annual emission reduction rate current percent percent set realise percent emission reduction part china committed peak carbon emission possibly sooner capping emission growth world largest emitter announcement kind china todate shied international commitment realise target president announced zeroemission nonfossil energy source nuclear renewable represent percent chinas supply mix zeroemission source represented percent chinas total energy consumption sign progress optimism world top emitter carbonjointly responsible approximately percent global energyrelated emissionsleadership cooperation nation critical charting path rest world follow china independently initiate change scale required country act jointly decisively president obama echoed sentiment earlier week stating china work effectively world benefit joint announcement set powerful precedent country emulate foster ambitious international action term eye international climate negotiation paris year chinas bilateral cooperation lay groundwork potential future international climate treaty ongoing additional progress synchronised commitment represent decisive moment history global nationallevel climate action panacea intergovernmental panel climate change ipcc warming held beneath degree celsius avoid catastrophic effect rapidly changing climate related analysis suggest hold carbon budget the cumulative amount emission generated roughly billion tonne achieve goal agreement relative collective carbon budget lynn price leader china energy lawrence berkeley national laboratory explain reduction related chinese emission trend compare chinas target result number recent ongoing study chinas energy emission pathway appear ambitious date achieve emission peak imply meaningful effort business usual important consideration though level emission peak occur included chinas announcement current study show range gtco billion tonne baseline scenarios range gtco ambitious scenarios absolute magnitude peak unclear pulling forward undeniable benefit dissipating momentum fossil asset development driving total emission timing magnitude effect factoring number alongside similar analysis united state suggest combined agreement result billionton reduction country business usual undeniable progress however bely fact country emit global budget commitment carbon budget leave remaining percent global population clear yesterday agreement momentumbuilder transforming global energy economy end goal effectively rise climate challenge opportunity energy efficiency marketbased solution chinas announcement set significant target study show current trajectory business usual scenario country target percent nonfossil energy share good start require additional supportive measure ensure carbon emission peak manageable level example demandside resource omitted recent announcement play substantial role realising country target energy efficiency continue contribute deeply decarbonized future account china built equivalent virtual gorge dam energy saved national standard efficient refrigerator air conditioner efficiency measure expanded areas economy china meet beat target addition nationallevel government target supportive policy standard exist nimble fastscaling marketbased solution play significant role mobilising capital global clean energy economy dynamism business rapidly mobilizeand mobilizingagainst challenge annual global investment energy efficiency renewable energy billion billion respectively driven largely business road ahead role reinventing fire china partnership chinas energy research institute energy foundation china lawrence berkeley national laboratory rocky mountain institute month month study called reinventing fire china project panpacific cooperative research effort reimagine chinas future energy system clean connected distributed secure reinventing fire china pathway designed enhance energy environmental security compromising economic growth initiative analysis aim measure economic social environmental benefit rapidly deploying renewable energy efficiency technology china focuse economywide analysis energyproducing consuming sector economy building industry transportation electricity analysis refined project team believe china double target percent nonfossil supply economically addition officially sanctioned cooperative effort chinathe uschina clean energy research centre climate change working reinventing fire china contributing technical analysis policy framework market strategy designed support broadest adoption energy efficiency renewable china china committed ambitious important climate goal week representing watershed moment president commitment bilateral agreement acknowledging target critical step stating pool begin drop water goal clear significant remain clarified realised exciting challenging work ly ahead great power great responsibility announcement made week president president obama signal china responsibility seriously ongoing panpacific collaboration prove vital realising goal outlined week world powerful head state reprinted permission date hottest cleantech new subscribing free cleantech newsletter eye sectorspecific new also free solar energy newsletter electric vehicle newsletter wind energy newsletter havent reader survey yet now tag china climate change climate change working climate policy emission energy efficiency energy foundation china energy research institute fossil fuel ipcc lawrence berkeley national laboratory president obama president reinventing fire china renewable energy uschina clean energy research centre rocky mountain institute rocky mountain institute advanced marketbased solution transform global energy create clean prosperous secure future independent nonprofit thinkanddo tank rmi engage businesse community institution accelerate scale replicable solution drive costeffective shift fossil fuel efficiency renewable visit information related post ","m_szGeo1":"United States","m_szSourceType":"source_industry","m_szSrcUrl":"http://cleantechnica.com/2014/11/14/joint-climate-policy-announcement-us-china-means/","m_Places":["United States","Republic Of China","China","Paris"],"m_People":["Jon Creyts","Barack Obama","Lynn Price"],"m_Companies":["Rocky Mountain Institute","2020","2020 To 2025","Target","Path","Groundwork","Intergovernmental Panel On Climate Change","Ipcc","China Energy Group","Lawrence Berkeley National Laboratory","Research Institute","Research Center","Working Group","Pool","Signal"],"m_BiGrams":["energy efficiency","climate change","reinventing fire","fire china","rocky mountain","mountain institute","energy research","president obama","carbon budget","lawrence berkeley","berkeley national","national laboratory","emission peak","business usual","marketbased solution","clean energy","efficiency renewable","renewable energy"],"m_TriGrams":["reinventing fire china","rocky mountain institute","lawrence berkeley national","berkeley national laboratory"],"m_SocialTags":[],"m_Topics":[],"m_Industry":[],"m_Technology":[],"m_BiCnt":[6,5,5,5,4,4,4,3,3,3,3,3,3,3,3,3,3,3],"m_TriCnt":[5,4,3,3],"m_iDocBodyWordCnt":766}
