{"m_szDocID":"1817973","m_szDocTitle":"Renewables Use By Top Emitters Will More Than Double By 2030 | CleanTechnica","m_szYear":"2015","m_szDocSumamry":"textArticle -------------------- Renewables Use By Top Emitters Will More Than Double By 2030 November 6th, 2015 by Sandy Dechert Â  The World Resources Institute released a couple of positive international findings today for renewable energy in its Assessing the Post-2020 Clean Energy Landscape report. Breaking down the 127 INDCs submitted to the United Nations by late October, the think tank discovered: 80% reference clean energy; 53% mention clean energy targets; and 27% put forward clean energy actions. Looking at data on renewables use from the International Energy Agency and other publish","m_szDocBody":"renewable top emitter double sandy dechert world resource institute released couple positive international finding today renewable energy assessing post clean energy landscape report breaking indc submitted united nation late october tank discovered reference clean energy mention clean energy target put forward clean energy action data renewable international energy agency published source wri author analysed number top emitting countriesbrazil china european union india indonesia japan mexico united state collectively consume world primary energy include data clean energy plan brazil china european union india indonesia japan mexico united state provided textin summary table found based current commitment total annual clean energy supply major consuming nation double terawatthour year amount rise approximately existing climate plan fully achieved increase equivalent indias current energy demand analyst thomas damassa katherine ross international observer hoping estimate higher paris summit analysis renewable energy level measure higher target projection previously made detail brazil achieve renewable energy mix china increase share nonfossil fuel primary energy consumption european union achieve share renewable energy consumption india achieve cumulative electric power installed capacity nonfossil fuel energy resource with international assistance indonesia achieve energy supply coming renewable energy japan increase share renewable total electricity generation approximately mexico increase clean energy source national electricity generation mix united state increase share renewable hydropower electricity generation mix countriesbrazil india japan mexico united statesare set increase total renewable capacity level time from top polluter canada russia announced post renewable energy target note nonfossil expansion china india mexico nuclear energy jennifer morgan global director world resource institute climate programme renewable energy target send strong signal energy market investment circle combined paris climate agreement clear renewable energy poised surge forward year bringing clean affordable power million people worldwide renewable result important increasing clean energy solve problem climate change ghg emission energy security economic growth energy billion people live electricity date hottest cleantech new subscribing free cleantech newsletter eye sectorspecific new also free solar energy newsletter electric vehicle newsletter wind energy newsletter havent reader survey yet now tag brazil canada china clean energy plan cop economic growth energy energy security european union ghg emission indc india indonesia international energy agency japan mexico russia united state world resource institute sandy dechert cover environmental health renewable conventional energy climate change new climate beat important media attended year cop lima peru sandy worked groundbreaking environmental consultant fortune health care firm write weblog attribute modest success indelible habit poking satisfy curiosity related post ","m_szGeo1":"United States","m_szSourceType":"source_industry","m_szSrcUrl":"http://cleantechnica.com/2015/11/06/renewables-use-top-emitters-will-double-2030/","m_Places":["Brazil","China","India","Indonesia","Japan","Mexico","United States","Atmosphere","Canada","Russian Federation","Paris"],"m_People":["Sandy Dechert","Thomas Damassa","Katherine Ross","Jennifer Morgan","Lima Peru"],"m_Companies":["World Resources Institute","2020","Landscape","United Nations","International Energy Agency","European Union","Target"],"m_BiGrams":["clean energy","renewable energy","european union","japan mexico","united state","world resource","resource institute","energy target","india indonesia","mexico united","increase share","share renewable","electricity generation"],"m_TriGrams":["world resource institute","japan mexico united"],"m_SocialTags":[],"m_Topics":[],"m_Industry":[],"m_Technology":[],"m_BiCnt":[9,8,4,4,4,3,3,3,3,3,3,3,3],"m_TriCnt":[3,3],"m_iDocBodyWordCnt":398}
