{"m_szDocID":"1817982","m_szDocTitle":"Cleantech Politics News of the Week | CleanTechnica","m_szYear":"2011","m_szDocSumamry":"textArticle -------------------- Cleantech Politics News of the Week February 5th, 2011 by Zachary Shahan   Here’s a wrap-up of some of the good or big cleantech (and dirty tech) politics stories we didn’t cover from the last week or so, to complement our wrap-ups of big solar and wind energy news and other cleantech news . Obama Says “Climate Change” Again As I noted over on our sister site Planetsave a few days ago (and many others have noted), Obama has uttered the words “climate change” again . After notoriously leaving “climate change” and “global weirding” and the fact that  2010 was the","m_szDocBody":"cleantech politic new week zachary shahan here wrapup good big cleantech and dirty tech politic storey didnt cover week complement wrapup big solar wind energy new cleantech new obama climate change noted sister planetsave day ago and noted obama uttered word climate change notoriously leaving climate change global weirding fact hottest year record state union address obama recently made mention speech penn state university crowd guess believe science understand scientific process obamas energy climate czar carol browner leave white house shocking announcement found carol browner president barack obamas energy adviser plan leave white house soon announcement obamas state union address connexion obamas silence climate change speculate official announcement happy speech stay long ensure orderly transition white house official said carol confident mission office remain critical president pleased state union address budget next month clean energy fossil fuel industry keeping massive energy subsidy far obama stated state union address extremely wealthy fossil fuel industry doesnt anymore tax break innovation pay congress eliminate billion taxpayer dollar give oil company dont youve noticed theyre fine own subsidising yesterday energy let invest tomorrow senate shot attempt cut massive energy subsidy bruce alpert sadly start post matter oil gas industry beat back regulatory bill worst day year massivebp oil spill gulf mexico scored victory week oil price continue rise rapid rate american struggle big oil attack clean energy programme congress significantly address issue and successfully kill them leading oil company raked trillion profit decade give multimillionaire billionaire exec tax loophole bonuse epa strike back attack jurisdiction republican congress throw multiple attack epas legal authority regulate greenhouse gas emission epa administrator lisa jackson striking back ben geman hill report environmental protection agency administrator lisa jackson attacked bill piling congress block agency ability regulate greenhouse gas emission reiterated white house veto threat jackson speaking reporter initially declined address president obama veto bill stop climate rule past threat stand should cutting rail funding hurt americas transportation future eric jaffe infrastructurist delve republican study committee proposal cut federal rail spending ignorant chinas starting kick cleantech back top kate gordon centre american progrss vice president energy policy touches china leading world cleantech global innovation leader republican study committee proposal totally undermine chance lowcarbon industry dominate chinas year trillion investment plan lowcarbon investment game day dominate global economy china put chip this conerning chinas year investment plan total trillion reuter recently reported china envisage highend equipment manufacturing including highspeed rail aviation equipment pillar economic growth alongside energysaving environmentally friendly technology biotechnology generation information technology telecom internet strategic sector alternative energy advanced material alternativefuel car china number economy world number shift production cheap good innovation development production cleantech epa regulate carbon pollution close out centre american progress great indepth piece day epa allowed regulate carbon pollution epa greenhouse gase cheque out date hottest cleantech new subscribing free cleantech newsletter eye sectorspecific new also free solar energy newsletter electric vehicle newsletter wind energy newsletter havent reader survey yet now tag big oil carbon carbon pollution carol browner china china year investment plan china investment plan china trillion investment plan congress energy energy adviser epa epa regulate carbon epa regulate carbon pollution federal rail spending fossil fuel fossil fuel subsidy fossil fuel tax loophole global weirding kate gordon lisa jackson low carbon obama obama state union obama state union address regulate carbon regulate carbon pollution republican study committee senate state union tax loophole white house zachary shahan tryin and specy letter time spend time cleantechnica director chief editor otherwise enthusiastically fulfilling duty obsession gas solar love planetsave bikocity president important media zach recognised globally solar energy electric car energy storage wind energy expert speak related conference event connect social media zacharyshahancom related post ","m_szGeo1":"United States","m_szSourceType":"source_industry","m_szSrcUrl":"http://cleantechnica.com/2011/02/05/cleantech-politics-news-of-the-week/","m_Places":["Gulf Of Mexico","United States","Jackson","America","China","Starting"],"m_People":["Zachary Shahan","Barack Obama","Carol M. Browner","Bruce Alpert","Lisa Jackson","Ben Geman","Eric Jaffe","Kate Gordon"],"m_Companies":["Cleantech","Penn State University","Guess","White House","Congress","Senate","Bp","Epa","Environmental Protection Agency","Republican Study Committee","Carbon Industries","Reuters"],"m_BiGrams":["state union","regulate carbon","union address","white house","fossil fuel","investment plan","climate change","carbon pollution","wind energy","carol browner","tax loophole","lisa jackson","republican study","study committee"],"m_TriGrams":["state union address","republican study committee","regulate carbon pollution"],"m_SocialTags":[],"m_Topics":[],"m_Industry":[],"m_Technology":[],"m_BiCnt":[7,6,5,5,5,5,4,4,3,3,3,3,3,3],"m_TriCnt":[5,3,3],"m_iDocBodyWordCnt":609}
