{"m_szDocID":"1817986","m_szDocTitle":"Energy Business Leaders Getting Antsy, but Is the US Already Out of the Clean Energy Race? | CleanTechnica","m_szYear":"2010","m_szDocSumamry":"textArticle -------------------- Energy Business Leaders Getting Antsy, but Is the US Already Out of the Clean Energy Race? March 8th, 2010 by Zachary Shahan   At the Wall Street Journal‘s recent ECO:nomics conference , the “only CEO-level event focused on the relationship between the environment and the bottom line,” the CEOs of some major energy companies expressed their impatience at the US’ slow and unclear movement to take action on climate change and clean energy. Royal Dutch Shell chief executive Peter Voser said that the industry needs “certainty on the carbon price, certainty on legis","m_szDocBody":"energy business leader antsy clean energy race zachary shahan wall street journal recent economic conference ceolevel event focused relationship environment bottom line ceos major energy company expressed impatience slow unclear movement action climate change clean energy royal dutch shell chief executive peter voser industry certainty carbon price certainty legislation shell member climate action partnership socialbutton american electric power chairman michael morris climate change clean energy legislation done america lead world clean technology fpl chief executive lew hay reiterated certainty economic top ceos impatient question why bottom line lead global economy significant player cracking clean energy legislation similar manner question centre american progress cap recently decided pose this clean energy race released report topic wonderful quick video introduction report energy policy kate gordon detail matter show stand today stay global clean energy revolution cap state worldwide clean energy sale compare total sale gross domestic product gdp germany spain china large clean energy leader hand respectively centre american progress reiterate weve time now clean energy world biggest industry totaling trillion country spain china made huge stride forward year continuing order capitalise that essentially sitting sideline cap put simple choice table feast enormous economic opportunity reducing global warming pollution item menu economic competitor forge ahead build prosperity world leader installed renewable energy capita cap clean tech invention patent cap chronicle successful startup moved proactive country china continue development lose businesse economic benefit future doesnt head game game bottom line clean energy clean tech preventing catastrophic climate change economic growth economic future world cap write china germany spain early winner great technological industrial revolution country denmark japan south korea discuss report forging ahead ambitious clean energy economic strategy united state fully embrace sustainable growth strategy lowcarbon future not cap prime order compete world leader cap price carbon energy giant well game late date hottest cleantech new subscribing free cleantech newsletter eye sectorspecific new also free solar energy newsletter electric vehicle newsletter wind energy newsletter havent reader survey yet now tag american electric power cap centre american progress china climate action partnership economic fpl germany kate gordon lew hay michael morris peter vose race royal dutch shell shell spain climate action partnership wall street wsj zachary shahan tryin and specy letter time spend time cleantechnica director chief editor otherwise enthusiastically fulfilling duty obsession gas solar love planetsave bikocity president important media zach recognised globally solar energy electric car energy storage wind energy expert speak related conference event connect social media zacharyshahancom related post ","m_szGeo1":"United States","m_szSourceType":"source_industry","m_szSrcUrl":"http://cleantechnica.com/2010/03/08/energy-business-leaders-getting-antsy-but-is-the-us-already-out-of-the-clean-energy-race/","m_Places":["United States","America","Germany","Spain","China","Denmark","Japan","South Korea"],"m_People":["Zachary Shahan","Peter Voser","Michael Morris","Lew Hay","Kate Gordon","Peter Vose"],"m_Companies":["Wall Street Journal","Royal Dutch Shell","Shell","American Electric Power","Fpl Group","Revolution","2020","Center For American Progress"],"m_BiGrams":["clean energy","bottom line","climate change","climate action","action partnership","centre american","american progress"],"m_TriGrams":["climate action partnership","centre american progress"],"m_SocialTags":[],"m_Topics":[],"m_Industry":[],"m_Technology":[],"m_BiCnt":[11,3,3,3,3,3,3],"m_TriCnt":[3,3],"m_iDocBodyWordCnt":408}
