{"m_szDocID":"1817872","m_szDocTitle":"China is #2 Cleantech Producer, U.S. #17, New Report Finds | CleanTechnica","m_szYear":"2011","m_szDocSumamry":"textArticle -------------------- China is #2 Cleantech Producer, U.S. #17, New Report Finds May 8th, 2011 by Zachary Shahan   “Denmark earns the biggest share of its national revenue from producing windmills and other clean technologies, the United States is rapidly expanding its clean-tech sector, but no country can match China’s pace of growth, according to a new report obtained by The Associated Press,” the AP reported today . “China’s production of green technologies has grown by a remarkable 77 per cent a year, according to the report, which was commissioned by the World Wildlife Fund for","m_szDocBody":"china cleantech producer report find zachary shahan denmark earn biggest share national revenue producing windmill clean technology united state rapidly expanding cleantech sector country match chinas pace growth report obtained press reported today chinas production green technology grown remarkable cent year report commissioned world wildlife fund nature unveiled industry conference amsterdam key finding conclusion report compared cleantech production country gdp follow denmark lead world percentage gdp cleantech production china germany brazil obamas cleantech policy helped cleantech industry growing chinas growth cleantech production incomparable however make china cleantech world leader barring radical unexpected change chinas cleantech growth based clear understanding threat world and facing result climate change understanding cleantech industry growth driver tremendously economic ascent flat dollar term not percentage gdp china world leader cleantech production bringing billion year bring billion chinese made political level conscious decision capture market develop market aggressively donald pol economist wwf speak chinese climate change ideological issue fact life debate climate change transition low carbon economy debate passed china pol said implementation growth sector capture sector report completed germanybased roland berger strategy consultant gathered data country energy association bank brokerage report investor presentation international energy agency score source measured earning producing renewable biofuel wind turbine thermal equipment energy efficiency technology lowenergy lighting insulation chinas cleantech industry focused export awhile producing domestic well surprising finding chinas projected energy consumption report recent report lawrence berkeley national laboratory lbnl found that counter conventional wisdom chinas energy greenhouse gas emission hit plateau long middle century population surpassing billion report chinas energy andcarbon emission outlook found chinas steeply rising energy consumption start level household own refrigerator washing machine air conditioner appliance housing area capita stabilised household electricity growth slow report coauthor mark levine explained reach saturation point critical industry taper sooner china reach saturation road rail construction time frame resulting large decrease iron steel demand additionally energyintensive industry demand product flatten unprecedented detail analysis accurate projection hard make sure analysis apparently nonchina analysis date great depth matter key finding deeper pattern energy demand china bottomup modelling system develop projection energy greater detail standard method time laborintensive undertake work project ongoing year study dont kind detail levine model china close kind information data housing stock appliance bottom line chinas economic growth resulting energy consumption global warming emission strong focus clean energy natural societal pattern make chinas impact global warming significant projecting course projection perfect and chinese decision make everyday change history let forget mother day mother nature part play change history itself related storey tag china china carbon emission china clean energy china clean energy production china economic growth china emission china energy china growth clean energy leader clean energy gdp clean energy production clean energy production gdp clean energy world leader denmark denmark clean energy denmark clean energy production global weirding clean energy clean energy production united state clean energy united state clean energy production clean energy clean energy production world wildlife fund world wildlife fund nature wwf zachary shahan tryin and specy letter time spend time cleantechnica director chief editor otherwise enthusiastically fulfilling duty obsession gas solar love planetsave bikocity president important media zach recognised globally solar energy electric car energy storage wind energy expert speak related conference event connect social media zacharyshahancom related post ","m_szGeo1":"United States","m_szSourceType":"source_industry","m_szSrcUrl":"http://cleantechnica.com/2011/05/08/china-is-2-cleantech-producer-u-s-17-new-report-finds/","m_Places":["China","United States","Denmark","Germany","Brazil","Outlook"],"m_People":["Zachary Shahan","Donald Pols","Roland Berger","Mark Levine"],"m_Companies":["Cleantech","Associated Press","Ap","World Wildlife Fund","International Energy Agency","Lawrence Berkeley National Laboratory","Lbnl"],"m_BiGrams":["clean energy","energy production","cleantech production","united state","world wildlife","wildlife fund","cleantech industry","world leader","climate change","energy consumption"],"m_TriGrams":["clean energy production","world wildlife fund"],"m_SocialTags":[],"m_Topics":[],"m_Industry":[],"m_Technology":[],"m_BiCnt":[16,7,4,3,3,3,3,3,3,3],"m_TriCnt":[5,3],"m_iDocBodyWordCnt":535}
