{"m_szDocID":"1818227","m_szDocTitle":"Massachusetts' Clean Energy Economy Grows 11.2%, Creates 71K+ Jobs - CleanTechnica","m_szYear":"2012","m_szDocSumamry":"textArticle -------------------- Massachusetts’ Clean Energy Economy Grows 11.2%, Creates 71K+ Jobs August 31st, 2012 by Andrew     Government investment and support for clean, renewable energy development is paying off handsomely in Massachusetts, where the clean energy economy grew 11.2% between July 2011 and July 2012. The state’s fast-growing clean energy sector now employs 71,523 people at 4,995 clean energy businesses across the state, according to a Massachusetts Clean Energy Center (MassCEC) report released Aug. 16. “I have said from the beginning of this Administration that, if we get","m_szDocBody":"massachusett clean energy economy grow create job andrew government investment support clean renewable energy development paying handsomely massachusett clean energy economy grew state fastgrowing clean energy sector employ people clean energy businesse state massachusett clean energy centre masscec report released aug beginning administration that clean energy right world customer governor deval patrick whos serving term office stated press release past year percent increase clean energy job mean world investing nationleading clean energy agenda environment energy independence public health economic vitality owe future momentum strong investing clean energy paying massachusett economic growth rate massachusett clean energy sector rapidly industrialising country china people employed clean energy businesse recorded masscec latest annual report working job directly related state clean energy sector sign growth continue employer surveyed optimistic coming year expect hire worker masscec state press release clean energy continue maintain place commonwealth marquee industry percent total massachusett workforce masscec found state clean energy sector diversified one businesse involved construction manufacturing research development massachusett clean energy industry report masscec identified large number company dont necessarily identify clean energy company first directly engage activity related clean energy sector showing clean energy penetrate numerous sector massachusett economy report proof massachusett innovation economy succeeding incoming masscec executive director chief executive officer alicia barton mcdevitt begin term report affirm massachusett role national global leader clean energy development deployment success made talented workforce worldclass academic research institution governor patrick vision clean energy future massachusett report clean energy business defined employer engaged part providing good service related renewable energy energy efficiency alternative transportation carbon management clean energy worker defined spending portion time supporting clean energy aspect businesse prepared research partnership behalf masscec massachusett clean energy industry report include breakdown company employment technology sector geographic region information workforce trend date hottest cleantech new subscribing free cleantech newsletter eye sectorspecific new also free solar energy newsletter electric vehicle newsletter wind energy newsletter havent reader survey yet now tag clean energy economy massachusett clean energy industry massachusett carbon emission reduction massachusett clean energy massachusett clean energy centre gov deval patrick massachusett clean energy economy massachusett clean energy incentive massachusett clean energy industry massachusett energy policy massachusett green ecoonomic growth massachusett green job massachusett renewable energy massachusett renewable energy investment massachusett renewable energy manufacturing massachusett renewable energy r&d renewable energy development sustainable development carbon economy andrew reporting writing wide range topic nexus economic technology year now asiapacific europe americas africa middle east issue related broad topical areas pose tremendous opportunity challenge define quality live relationship natural environment related post ","m_szGeo1":"United States","m_szSourceType":"source_industry","m_szSrcUrl":"http://cleantechnica.com/2012/08/31/massachusetts-clean-energy-economy-grows-11-2-creates-71k-jobs/","m_Places":["Massachusetts","China","Asia","Europe","Africa","Middle East"],"m_People":["Deval","Alicia Barton Mcdevitt"],"m_Companies":["Energy Center","Masscec","Energy Future","Nexus"],"m_BiGrams":["clean energy","massachusett clean","renewable energy","energy sector","energy economy","energy industry","massachusett renewable","energy development"],"m_TriGrams":["massachusett clean energy","clean energy sector","clean energy economy","clean energy industry","massachusett renewable energy"],"m_SocialTags":[],"m_Topics":[],"m_Industry":[],"m_Technology":[],"m_BiCnt":[31,12,7,5,4,4,4,3],"m_TriCnt":[12,5,4,4,4],"m_iDocBodyWordCnt":415}
