{"m_szDocID":"1822434","m_szDocTitle":"Apple's $1B bet in China is all about timing","m_szYear":"2016","m_szDocSumamry":"textArticle -------------------- Apple's $1B bet in China is all about timing In its biggest acquisition since Beats, Apple picks up Uber rival in China, Didi. Post to Facebook Apple's $1B bet in China is all about timing In its biggest acquisition since Beats, Apple picks up Uber rival in China, Didi. Check out this story on USATODAY.com: http://usat.ly/27jYXh0 CancelSend A link has been sent to your friend's email address. Posted! A link has been posted to your Facebook feed. 11 To find out more about Facebook commenting please read the Conversation Guidelines and FAQs Apple's $1B bet in Chi","m_szDocBody":"apple bet china timing biggest acquisition beat apple pick uber rival china didi post apple bet china timing biggest acquisition beat apple pick uber rival china didi cheque storey usatodaycom cancelsend link friend address posted link posted feed commenting read conversation guideline faqs apple bet china timing jon swartz usa today edt share apple announced invest billion didi chuxing uber biggest ridesharing competitor china wochit leaf logo apple store turn green world earth day hangzhou zhejiang province china photo vcg getty image san francisco apple billion investment didi uber rival china timing firmly plant apple aapl lucrative ridehailing market world mostpopulous country underscore company commitment china week ahead ceo tim cook trip there making investment number strategic reason including chance learn segmentsof china market cook told reuter late thursday apple announced deal admire many level term innovation term cutting edge technology didi president jean liu new conference there lot learn apple report apple investing uber rival didi chuxing china apple secondlargest market hold vast potentialbut significant hurdle account roughly billion annual sale apple companysmost recentquarterly sale fell% yearago period saturated smartphone market slowing economy apple navigate market ruled communist government assuring consumer product secure privacy resonate china consumer spooked government surveillance hacking cybercrime apple cook stresse privacy asia growth plan investor activist investor carl icahn month sold million share apple stock concern business china cook making trip halfway world visit government official envision sprawling middleclass eager snap apple device recent appearance cnbc mad money programme the middle class china booming cook said optimistic future tim cook china optimistic apple billiondollar bet didi biggest acquired beat music service headphonemakerfor billion important then didi whoseinvestor includealibaba tencent largest service kind china operation city serving million people market leadership prompted uber raise billion year specifically uber china note piper jaffray analyst gene munster didis political standing benefit apple chinas sovereign wealth fund invested didi year bloomberg reportapple investment confirm faith region economic growth give positive chinese public apple analyst tim bajarin say investment mark departure apple whichtypically buy tiny startup week feel reason show apple continued commitment china imply company plan deploy selfdriving car country taxis far apple mum itsmysterious electric car project clear apple needed bold reverse recent stock slide enabled alphabet surpass mostvaluable company world apple stumble included straight losing session coincided decline yearoveryear iphone sale investment apple guide car effort analyst munster hisnote today day least strategy clicked investor s&p global market intelligence issued statement maintaining strong buy recommendation apple stock company share rose friday theysettledwith gain contributing jessica guynn connect tweet linkedin commentemailmore read share storey top videos edt datemeta ","m_szGeo1":"United States","m_szSourceType":"source_news","m_szSrcUrl":"http://www.usatoday.com/story/tech/columnist/2016/05/13/apples-1b-bet-china-all-timing/84316306/","m_Places":["China","Hangzhou","Zhejiang Province","United States","Asia","Munster"],"m_People":["Didi Chuxing","Jon Swartz","Tim Cook","Jean Liu","Carl Icahn","Piper Jaffray","Gene Munster","Tim Bajarin","Jessica Guynn"],"m_Companies":["Apple","Uber","Facebook","Usatoday.com","Usa Today","Getty Images","Aapl","Reuters","Cnbc","Alibaba","Linkedin"],"m_BiGrams":["china timing","uber rival","apple bet","bet china","rival china"],"m_TriGrams":["apple bet china","bet china timing","uber rival china"],"m_SocialTags":[],"m_Topics":[],"m_Industry":[],"m_Technology":[],"m_BiCnt":[4,4,3,3,3],"m_TriCnt":[3,3,3],"m_iDocBodyWordCnt":431}
