{"m_szDocID":"1831927","m_szDocTitle":"3 of Our Wildest Predictions for 2015 -- The Motley Fool","m_szYear":"2014","m_szDocSumamry":"Search: 3 of Our Wildest Predictions for 2015 The stock market can do crazy things, and here are three wild Motley Fool predictions for next year. Travis Hoium ( TMFFlushDraw ) Dec 27, 2014 at 4:00PM This has been a wild year for those following the stock market. We've seen new record highs, oil crumble in a matter of months, and the U.S. economy power along, driven by new innovations that seemed impossible just a few years ago (think electric vehicles, solar energy, and Uber). Next year will surely bring its fair share of surprises as well, so we've rounded up a few predictions about what cou","m_szDocBody":"search wildest prediction stock market crazy thing wild motley fool prediction year travis hoium tmfflushdraw wild year stock market record high oil crumble matter month economy power along driven innovation impossible year ago think electric vehicle solar energy uber year surely bring fair share surprise well rounded prediction happen chinas economy grown crazy decade eventually slow doe danger lurk image owned motley fool travis hoium wild but realistic prediction china market crash people risk bubbling chinese economy central government control staterun bank fuel economic growth decade bubble burst spectacular fashion eventually bubble begin burst yearand government scramble increase highquality lending boost economy prop market wall street crash china country economic growth end crack thesis roil market china transparent itseconomic lending data number analyse show alarming credit trend ceic total social financing measure bank loan shadow banking grown chinese gdpin gdp today stephen greenat standard chartered earlier year chinas total social financingtogdp ratio compared debttogdp figure low world reserve currency stable economy handle higher debt load china risk chinas growing credit bubble burst real estate price recently turned negative economic growth slowing chinas government reinin risky lending led credit boom place factor consumer businesse lose confidence asset price fall drop credit market dramatic credit crunch china style predicting financial crisis impossible predict chinas credit bubble burst deflate impact global economy happen bad looming china market beating light printing improved dramatically profit hard image owned motley fool steve heller dprinted crystal ball predict printing company profit difficult spite strong industry growth rate industry insight firm wohler associate printing industry expected grow year compounded eventually generate billion annual revenue worldwide robust industry growth trajectory make investor salivate prospect owning printing stock clear date robust industry growth show bottom line form profit publicly traded printing company granted established player asstratasy system nyseddd represented onethird worldwide printing revenue undergone rapid investment phase depressed profitability short term imply profitability horizon stratasy system pace investment normalise investor mind promise guaranteed company forthe industry large all printing attractive growth potential attracted lot competition hewlettpackard included create pricing pressure difficulttomanage headwind sap future profitability potential industry player fact system major printing company consistently turn profit generally accepted accounting principle basis recent year profit industry notcurrently easy revenue prove problematic long term profit eventually determine printing company sustainable longterm investment meantime investor caught excitement printing impressive growth potential chevy volt supercharged image owned motley fool john rosevear wild prediction general motor nysegm yes general motor blow mind crazy recall scandal big push forward technology surprise lot folk watch auto industry closely form take job watch auto industry closely struck relentless flow hint big brewing noise recall mess know midapril allnew chevy volt expected significant leap forward technology big plush cadillac sedan incorporate technology yes confirmed big cadillac plugin hybrid more ceo mary barra company super cruise system selfdriving car folk circumstance ready production time put model advanced electric car development advanced give tesla motor nasdaqtsla run money long told yet general drop technological bombshell two year jolt industry john rosevear own share general motor steve heller own share system tesla motor travis hoium position stock mentioned motley fool recommend system general motor tesla motor motley fool own share system tesla motor foolish newsletter service free day fool hold opinion diverse range insight make investor motley fool disclosure policy ","m_szGeo1":"United States","m_szSourceType":"source_investments","m_szSrcUrl":"http://www.fool.com/investing/general/2014/12/27/3-of-our-wildest-predictions-for-2015.aspx?source=isesitlnk0000001&mrr=0.14","m_Places":["United States","China","Wall Street"],"m_People":["Travis Hoium","Steve Heller","Chevy Volt","John Rosevear","Mary Barra"],"m_Companies":["Motley Fool","Uber","Wohlers Associates","2020","Stratasys","Hewlett-packard","Sap","General Motors","Cadillac","Tesla Motors","Nasdaq"],"m_BiGrams":["motley fool","printing company","general motor","tesla motor","travis hoium","image owned","owned motley","economic growth","bubble burst","industry growth","own share"],"m_TriGrams":["image owned motley","owned motley fool"],"m_SocialTags":[],"m_Topics":[],"m_Industry":[],"m_Technology":[],"m_BiCnt":[7,4,4,4,3,3,3,3,3,3,3],"m_TriCnt":[3,3],"m_iDocBodyWordCnt":548}
