{"m_szDocID":"1845061","m_szDocTitle":"Oculus Rift creator defends $600 price, promises cost will eventually drop - CNET","m_szYear":"2016","m_szDocSumamry":"textArticle -------------------- CNET Oculus Rift creator defends $600 price, promises cost will eventually drop Oculus Rift creator defends $600 price, promises cost will eventually drop Oculus VR founder Palmer Luckey says the goal for Rift to be \"cheap, functional and disruptive\" has never changed -- though the timeline has. @gamespot Following the announcement last week that the first Oculus Rift consumer model will cost $600 , 23-year-old creator Palmer Luckey has again defended and explained that premium price point. In a new Reddit AMA , Luckey says the goal for Rift to be \"cheap, funct","m_szDocBody":"cnet oculus rift creator defend price promise cost eventually drop oculus rift creator defend price promise cost eventually drop oculus founder palmer luckey goal rift cheap functional disruptive changed timeline has announcement week oculus rift consumer model cost yearold creator palmer luckey defended explained premium price point reddit ama luckey goal rift cheap functional disruptive changedthough timeline achieve goal has make cheap functional disruptive take amount quality that luckey said three year ago thought good headset built run decent gaming then learned lot take induce presence landscape industry changed lot longer player burden bringing good longer solely luckey elon musk car company tesla path oculus hoping follow the make technology mainstream simple making cheap product quickly possible lead crash luckey said tesla good elon musk convince public electric car awesome build technology make electric car mainstream tesla make massmarket electric car back accomplished little instead made roadster model proved electric car awesome invested heavily r&d clear path everpresent longterm goal making electric car mainstream luckey point exist viable lowercost option form gearvr oculus working samsung eventually ubiquitous luckey predicted multitude option meet desired quality price unlike technology device gearvr awesome headset flagship samsung phone like ten million people company entering scene future said eventually run computer sold wide range hardware price quality point lot television monitor oculus luckey added totally understand price include headset capable people pay virtualreality experience stressed that phone tvs price fall time plan the rift headset capable delivering presence sensation feeling inside virtual scene subconscious level said afford totally understand people spend current cost making good headset smartphone cost quality time buy unsubsidized phone blow phone year ago time cost technology datemeta ","m_szGeo1":"United States","m_szSourceType":"source_industry","m_szSrcUrl":"http://www.cnet.com/uk/news/oculus-rift-creator-defends-600-price-point-promises-cost-will-eventually-drop/","m_Places":["Luckey"],"m_People":["Palmer Luckey","Elon Musk"],"m_Companies":["Cnet","Oculus","Reddit","Ama","Indeed","Tesla","Path","Samsung"],"m_BiGrams":["electric car","oculus rift","cheap functional","functional disruptive"],"m_TriGrams":["cheap functional disruptive"],"m_SocialTags":[],"m_Topics":[],"m_Industry":[],"m_Technology":[],"m_BiCnt":[5,3,3,3],"m_TriCnt":[3],"m_iDocBodyWordCnt":276}
