{"m_szDocID":"1849834","m_szDocTitle":"Faraday Future and Snapchat stand to gain millions in state tax breaks for adding jobs - Sun Sentinel","m_szYear":"2016","m_szDocSumamry":"textArticle -------------------- Faraday Future and Snapchat stand to gain millions in state tax breaks for adding jobs Firms stand to gain big tax breaks Gregory Bull / Associated Press Faraday Future would get $12.7 million in tax credits if it meets goals, including adding 2,000 jobs. Faraday Future would get $12.7 million in tax credits if it meets goals, including adding 2,000 jobs. (Gregory Bull / Associated Press) Privacy Policy Electric car start-up Faraday Future Inc. and mobile app maker Snapchat Inc. are poised to receive millions of dollars in state tax breaks over the next five ye","m_szDocBody":"faraday future snapchat stand gain million state tax break adding job firm stand gain big tax break gregory bull press faraday future million tax credit meet goal including adding job faraday future million tax credit meet goal including adding job gregory bull press privacy policy electric car startup faraday future inc mobile app maker snapchat inc poised receive million dollar state tax break year hit hiring investment goal chinese billionaire jia yueting faraday future total million credit corporate income taxe meeting requirement set state including adding worker gardena california weekly business new briefing open link snapchat receive million credit annually year employee venice headquarter now award lucrative latest round california compete tax credit programme launched boost employment industry statewide award snapchat faraday future company approved state committee scheduled meet thursday year panel rejected agreement approving other clear effective young programme replacement controversial enterprise zone system sought stimulate development economically depressed neighbourhood criticised giveaway large employer help company credit led aggressively california expansion debating bigger presence california philip krim chief executive casper sleep inc retailer mattresse backed million venture capital investment and made feel confident making investment approved week casper recorded sale totaling million credit year expanding california workforce tax break enabled company double hiring projection california krim said workforce include designer engineer working mattress product san francisco bay area sale marketing employee los angele employed york headquartered begin put plan place coming week casper open office showroom venice upscale abbot kinney boulevard shutting showroom hollywood hill startup declined comment including snapchat augmented reality firm magic leap agreed hire people mountain santa monica exchange million credit state official receive hundred application batch credit give preference company biggest hiring investment plan relative size tax break sought weighed salary indirect effect rest economy money set smaller businesse company accounted million awarded led electric car maker tesla motor inc million aerospace giant northrop grumman corp technology manufacturer samsung electronic nordstrom join big beneficiary million credit retailer hire distributioncenter worker central valley approved faraday future electric car maker intend rival tesla faraday future worker nissan sale office gardena company spokesperson said smaller number engineer working tech facility san jose part million tax incentive company selected nevada planned billion factory application california tax credit company continue hire california including spot rancho dominguez build vehicle testing spokesperson stacy morris said qualify fund faraday future reach employee year employee earn minimum groupwide average faraday future spending equipment office investment million million company told state total investment million tax credit kick tax year million tax break million tax credit year company declared bring car market named morris promised premium electric vehicle industryleading range roll next couple year state tax official track company hit target far pair company lost small amount bigger million return approval week pharmaceutical giant novartis scaled back california plan datemeta ","m_szGeo1":"United States","m_szSourceType":"source_news","m_szSrcUrl":"http://www.sun-sentinel.com/business/la-fi-tn-tax-credits-20160408-story.html","m_Places":["California","Casper","San Francisco Bay Area","Los Angeles","New York","Venice","Hollywood","Hills","Mountain View","Tesla","San Jose","Nevada"],"m_People":["Jia Yueting","Philip Krim","Abbot Kinney","Santa Monica","Stacy Morris"],"m_Companies":["Gregory Bull","Associated Press","Faraday Future Inc.","Gardena","2020","Casper Sleep Inc.","Magic Leap","Tesla Motors Inc.","Northrop Grumman Corp","Samsung Electronics Co","Nordstrom","2016 To 2020","Novartis"],"m_BiGrams":["faraday future","tax break","million tax","tax credit","million credit","state tax","adding job","including adding","electric car"],"m_TriGrams":["million tax credit"],"m_SocialTags":[],"m_Topics":[],"m_Industry":[],"m_Technology":[],"m_BiCnt":[10,6,6,6,5,3,3,3,3],"m_TriCnt":[4],"m_iDocBodyWordCnt":464}
