{"m_szDocID":"1862370","m_szDocTitle":"Million-dollar matchup: fans to race against professional drivers in exciting virtual reality offshoot of Formula E series | South China Morning Post","m_szYear":"2016","m_szDocSumamry":"South China Morning Post Now Reading Million-dollar matchup: fans to race against professional drivers in exciting virtual reality offshoot of Formula E series   Million-dollar matchup: fans to race against professional drivers in exciting virtual reality offshoot of Formula E series PUBLISHED : Wednesday, 22 June, 2016, 10:11am UPDATED : Wednesday, 22 June, 2016, 10:14am It won’t come cheap: grandstand tickets for Hong Kong Formula E race set at HK$2,380 1 Jun 2016 Formula E, the world’s first fully electric car racing series, is planning a virtual race in Las Vegas in January with a likely U","m_szDocBody":"south china morning post reading milliondollar matchup fan race professional driver exciting virtual reality offshoot formula sery milliondollar matchup fan race professional driver exciting virtual reality offshoot formula sery published wednesday june updated wednesday june wont cheap grandstand ticket hong kong formula race set formula world fully electric car racing sery planning virtual race las vegas million jackpot winner sery chief executive alejandro agag event pitting regular race driver handful fan simulator round regular championship future esport electronic sport huge opportunity fully immersed that ahead week london finale formula season hong kong host leg sery central october speaking las vegas virtual race agag said virtual race professional driver racing championship big stage large prize fund spanish entrepreneur race part global consumer electronic show ces insider million prize agag amount significantly figure good jackpot vegas added agag agreeing people win million vegas qualify race vegas competition launched month advance gamer compete online secure slot fun gamer win professional driver tough agag race disclose show virtual track player morning real formula time city race city practise before gamer game driver hand driver gamer quickly feel racetrack interesting competition sport including formula raced past las vegas linked return famed strip experimenting virtual reality technology engage fan attract audience tech giant google samsung investing heavily predicting immersive technology effect television internet newspaper concept virtual race gamer challenging driver eprix point prize money mooted agag formula season experiment vegas race depending envisage virtual race give point championship future now spaniard talked fan day race driver competing physical racetrack day off problem that weve lot lag real race virtual experience provide gamer said difficult technology speed broadband driver racing time race dreamt started formula hand erace formula car make noise slower formula complete race driver changing car due limitation battery technology however major manufacturer audi renault citroen involved british entrepreneur richard branson predicted year ago electric racing overtake formula popularity year ","m_szGeo1":"Hong Kong","m_szSourceType":"source_news","m_szSrcUrl":"http://www.scmp.com/sport/other-sport/article/1979144/million-dollar-matchup-fans-race-against-professional-drivers","m_Places":["Reading","Hong Kong","Las Vegas","United States","London","Central"],"m_People":["Alejandro Agag","Richard Branson"],"m_Companies":["South China Morning Post","Consumer Electronics Show","Ces","Formula One","Google","Facebook","Samsung","Audi","Renault","Citroen"],"m_BiGrams":["virtual race","professional driver","race professional","virtual reality","las vegas","race driver"],"m_TriGrams":["race professional driver"],"m_SocialTags":[],"m_Topics":[],"m_Industry":[],"m_Technology":[],"m_BiCnt":[5,4,3,3,3,3],"m_TriCnt":[3],"m_iDocBodyWordCnt":315}
