{"m_szDocID":"1863721","m_szDocTitle":"Hong Kong could lead the world if we made this one simple change to our social model | South China Morning Post","m_szYear":"2016","m_szDocSumamry":"South China Morning Post Now Reading Hong Kong could lead the world if we made this one simple change to our social model Â  Hong Kong could lead the world if we made this one simple change to our social model Allowing users of government services to upgrade to higher levels of pampering fits with our economic culture PUBLISHED : Thursday, 31 March, 2016, 4:16pm UPDATED : Friday, 01 April, 2016, 9:40am Print Email The government has just announced the building of a new large public housing estate that charges (quite) high rents, a government hospital where the treatment costs (but not too much)","m_szDocBody":"south china morning post reading hong kong lead world made simple change social model hong kong lead world made simple change social model allowing user government service upgrade higher level pampering fit economic culture published thursday march updated friday april print government announced building large public housing estate charge quite rent government hospital treatment cost but much sery school run education bureau fee but very fool announced kind should city spawned slogan country system region speed hong kong wealthy average income head disparity measured gini coefficient measure owned many cent global average cent forbe city boast billionaire cent hong kong gdp million cent hong kong resident technically poor live twospeed city hong kong easily afford capital cost upgrading public service incorporate paying business class middle classe class service rich people universal economy class service poor people dont business class service large middle class afford pay reasonable price reasonable quality service housing sector average private sector property cost million cent higher greater york represent class average hong kong earner take year earn money making property half affordable london time worse tokyo live square foot space parent did price expected confined space big city top scale uncomfortable rightly proud economy class public housing sector shelter full cent population unsurprisingly pressure government housing continue immense demand massively outpaced build business class housing sector public sector resource charging business class rent reduce load speed healthcare rightly proud excellent economy class public medical system treat sick income level payment naturally full overflowing private health treatment hong kong class attention immediate surgery hotellike accommodation charged egregiously fine medical staff fair price everything roughly hour surgeon fair critical health problem end economy class low cost government hospital business class medical system paid government charge higher fee recoup operating cost produce balance demand supply service quicker attention smaller crowded ward nurse twospeed education system boast economy class public school system free poorly equip employee service global marketplace student opt class educated overseas locally based international school cost government establish business class system feepaying school middle class smaller classe wider facility business class service model reduce pressure public service provide cash contribution reduce cost maintaining standard expensive doctor top professional hong kong efficient helpful good restriction overseas qualification hamper competition hong kong easily afford capital cost upgrading public service incorporate paying business class middle classe reallocating part billion reserve hypothecated fund education fund health fund housing fund government instantly popular reward people hong kong hard work build paid service middle class leaving economy class service lowest cent income scale hong kong advantage give opportunity world class areas business class model provide class benchmark social service worldwide richard harris chief executive port shelter investment management shortly christmas photograph family entitled visiting grandma circulated email showed lady bemused surrounded happy family hunched posture prayer smart device boxing day brother photograph family adopting position including yearold mother peering intently ipad mini finger hovering purposefully outright share price winner straight race global personal technology company amazon amazing cent google alphabet soared cent rose cent tencent cent price movement illustrate grip technology live market big company making steady acquisition bearing fruit microsoft own hotmail skype stake apple expedia picked instagram lightbox oculus whatsapp alphabet boast android operating system search youtube analyst week worth netflix account cent alphabet revenue key youtube growth largely free amazon seeking charge premium service free part success tech monster youthful business model adapted change laggard apple led competitor cornering ecosystem hardware software retail ware consolidation mode billion cash burning hole pocket enormous opportunity special part success tech monster youthful business model adapted change amazon began online bookshop nearest online department store selling wide variety product book pioneered online marketing payment distribution provided platform use increasing trend shop owned online provider internet idea illustrated alibabas billion tie year electronic retailer suning recent figure suggest onethird clothing bought internet returned doesnt include tshirt gave brother christmas couldnt bothered return return big business tying cash driving impulse buying return process internet customer product suning buy alibaba return back suning advantage online offline shopping shop develop megastore shopping experience shelve good sample physical window online shopping combined coffee book entertainment mock big innovation past year corner year wrist flurry digital wrist jewellery commonly downloaded free application apple store christmas fitbit device tell asleep exercising burning calory swap breitling clunky piece digital plastic found gps enabled jogging watch tell run mount butler metre vertically calorific cream cake neutralise other give visibility life twenty driverless car stay ticketed policeman faster regulator lucky karl benz deal them electric car invading hong kong road invented abandoned robert anderson heavy expensive requiring constant charging hoverboard develop real alternative walking central drone technology revolutionised warfare peaceful live virtual reality technology smartphone app controlling live processe paying bill monitoring health norm unspoken negative rapid decline privacy security gps identify movement arm span accuracy bring bigger frightening cyber security breakdown before tech company investment surge sector protect have richard harris chief executive port shelter investment management article ","m_szGeo1":"Hong Kong","m_szSourceType":"source_news","m_szSrcUrl":"http://www.scmp.com/business/article/1931787/hong-kong-could-lead-world-if-we-made-one-simple-change-our-social","m_Places":["Reading","Hong Kong","United States","London","Tokyo","Most","Central"],"m_People":["Richard Harris","Karl Benz","Robert Anderson"],"m_Companies":["South China Morning Post","Education Bureau","Forbes","Universal","Indeed","Education Fund","Amazon","Google","Facebook","Microsoft","Hotmail","Skype","Apple","Expedia","Oculus","Youtube","Netflix","Alibaba","Fitbit","Breitling"],"m_BiGrams":["hong kong","business class","economy class","class service","public service","middle class","housing sector","class public"],"m_TriGrams":["economy class public"],"m_SocialTags":[],"m_Topics":[],"m_Industry":[],"m_Technology":[],"m_BiCnt":[13,9,6,5,3,3,3,3],"m_TriCnt":[3],"m_iDocBodyWordCnt":825}
