{"m_szDocID":"1864022","m_szDocTitle":"China’s LeEco to enter Indian market with flagship Le Max and Le 1s smartphones through online retail partner Flipkart | South China Morning Post","m_szYear":"2016","m_szDocSumamry":"South China Morning Post Print Email Now Reading China’s LeEco to enter Indian market with flagship Le Max and Le 1s smartphones through online retail partner Flipkart   China’s LeEco to enter Indian market with flagship Le Max and Le 1s smartphones through online retail partner Flipkart PUBLISHED : Friday, 22 January, 2016, 1:03pm UPDATED : Friday, 22 January, 2016, 1:35pm Print Email LeEco, the Chinese entertainment giant formerly known as Letv, is bidding to become a top brand in India’s fast-growing smartphone market with the release of two handsets next month through leading online retail","m_szDocBody":"south china morning post print reading chinas leeco enter indian market flagship max smartphone online retail partner flipkart chinas leeco enter indian market flagship max smartphone online retail partner flipkart published friday january updated friday january print leeco chinese entertainment giant letv bidding top brand indias fastgrowing smartphone market release handset month leading online retail partner flipkart inch flagship max sale week inch midrange whet consumer appetite leeco due limited supply initially provide unit online india destination top priority home smart product mok tsuitin chief executive leeco asiapacific launch event gurgaon haryana state earlier week addressing crowd city located kilometre south delhi mok india largest young population world drive switch traditional feature phone smartphone atul jain chief operating officer smart electronic business leeco india presented handset enthusiastic crowd jain senior vice president samsung electronic south west asia regional headquarter phone sold exclusively leading online retailer flipkart claimed largest online retailer india read more riding digital wave videostreaming letv claim ecommerce player china alibaba jdcom lemall take smartphone sold india today flipkart ankit nagori chief business officer flipkart leeco announced deal eros international major indian film production distribution company posted annual revenue million run leecos website partnered usbased streaming provider yupptv local indian content leeco company quarter max released china leeco sell smartphone price cost tactic attract subscriber streaming service retail price india close china max cost rupee model memory rupess version retail rupee company build research centre bangalore indias technology centre year mok leeco plan recruit local staff support localization leecos product businesse operation landing country this require large number talented staff mok leeco bring smart television india year wide array product virtual reality headset smart bicycle accessory spokesperson leeco chinese smartphone maker entering emerging south asian market face competition peer chinas computer maker lenovo popular smartphone maker xiaomi top brand india flipkart motorolas moto popular smartphone shopping site brand owned chinas lenovo group xiaomis redmi prime lenovo brand note occupy place leeco run major streaming website china sell smartphone tvs earned billion yuan million quarter representing cent growth period year company announced month partnership electric car startup faraday future building billion factory home market ","m_szGeo1":"Hong Kong","m_szSourceType":"source_news","m_szSrcUrl":"http://www.scmp.com/tech/social-gadgets/article/1903806/chinas-leeco-enter-indian-market-flagship-le-max-and-le-1s","m_Places":["Reading","China","Leeco","India","Asia","Gurgaon","Haryana","New Delhi","Atul","United States","Bangalore"],"m_People":["Mok Tsui-tin","Ankit Nagori"],"m_Companies":["South China Morning Post","Samsung Electronics","Alibaba","Jd.com","India Today","Lenovo","Motorola","Moto","Lenovo Group"],"m_BiGrams":["flagship max","online retail","retail partner","partner flipkart"],"m_TriGrams":["online retail partner","retail partner flipkart"],"m_SocialTags":[],"m_Topics":[],"m_Industry":[],"m_Technology":[],"m_BiCnt":[3,3,3,3],"m_TriCnt":[3,3],"m_iDocBodyWordCnt":355}
