{"m_szDocID":"1866027","m_szDocTitle":"How Much Does It Take To Make The Electricity Sector Compatible With A 2°C Scenario? | CleanTechnica","m_szYear":"2016","m_szDocSumamry":"textArticle -------------------- How Much Does It Take To Make The Electricity Sector Compatible With A 2°C Scenario? February 2nd, 2016 by Dr. Elie Chachoua   How much should we invest in renewables by 2040 to make the electricity sector compatible with a 2°C scenario? $12.1 trillion, says BNEF. Data released last week by BNEF and CERES on the occasion of the 2016 investor summit on climate risk suggest that $12.1 trillion of renewable energy investments could be needed by 2040 to make the electricity sector compatible with a 2°C scenario. This represents an average of $485 billion per year, ","m_szDocBody":"make electricity sector compatible scenario elie chachoua invest renewable make electricity sector compatible scenario trillionsay bnef data released week bnef cere occasion investor summit climate risk suggest trillion renewable energy investment needed make electricity sector compatible scenario represent average billion year increase year record level billion nonoecd market driving energy demand period main recipient attracting total investment period from ratio investment radically change time period roughly nature respective share debt equity instrument expected evolve reflect increased familiarity investor renewable energy investment region investment made equity side expert interviewed bnef part itsresearch expect publicmarket instrument yieldcos reach total equity financing year addition institutional investor familiar riskreturn profile clean energy investment increase direct equity investment renewable energy infrastructure project result expert panel share direct equity investment provided institutional investor account total equity finance evolution equity financing scenario source bloomberg energy finance debt side growing green bond market higher reliance securitization financing distributed power generation project increased role assetbacked security financing clean energy way role onbalance sheet financing expected increase utility active deploying renewable investment refinance investment issuing debt result decrease role bank financing total debt finance today evolution debt instrument scenario source bloomberg energy finance real challenge achieving increase investment course capital move oecd where money emerging market where investment happen capital market mature issuance national standard green bond recently china important growing market expand faster similar standardsetting effort development emerging market including india deliver ambitious goal set indias nationally determined contribution instance aim increase share nonfossil power generation from today wind solar key part effort goal deploying gigawatt solar wind estimated cost billion financed debt create doubledigit dollar return institutional investor feel comfortable risk key government work institutional investor reduce risk uday khemka vice chairman sun group investor summit climate risk conference held york city week attended cleantechnica partial credit guarantee infrastructure debt fund part solution urgently needed indias coal power plant subcritical technology iea india doesnt financial solution fact cost capital executive secretary united nation framework convention climate change christiana figuere summit investor investing coal policy effort technology cost reduction brought renewable energy investment level india back level far however hasnt substantial modi bump noted michael liebreich chairman advisory board bloomberg energy finance address investor summit climate risk india reach climate goal noted increase investment figure pretty darn quickly methodology newanalysis indepth presentation bnef cere found date hottest cleantech new subscribing free cleantech newsletter eye sectorspecific new also free solar energy newsletter electric vehicle newsletter wind energy newsletter havent reader survey yet now tag cere china christiana figuere debt financing india india solar energy india wind energy investor summit climate risk michael liebreich securitization solar securitization yieldcos elie chachoua strategist thought leadership expert work focuse trend globalisation technology implication sustainability government civil society private sector elie extensive experience managing multidisciplinary research project international team worked renowned organisation including international oecd undp academic columbia university private the economist group kpmg act managing editor awardwinning blog economist dealing innovation trend industrial economy hold phd theoretical physic university pierre marie curie master public administration columbia university school international public affair related post ","m_szGeo1":"United States","m_szSourceType":"source_industry","m_szSrcUrl":"http://cleantechnica.com/2016/02/02/how-much-does-it-take-to-make-the-electricity-sector-compatible-with-a-2c-scenario/","m_Places":["China","India","Atmosphere","New York City"],"m_People":["Elie Chachoua","Uday Khemka","Christiana Figueres","Michael Liebreich","Marie Curie"],"m_Companies":["Oecd","Sun Group","Iea","United Nations","Un","Columbia University","Economist Group","Kpmg","School Of International","Public Affairs"],"m_BiGrams":["investor summit","summit climate","climate risk","renewable energy","energy investment","institutional investor","make electricity","electricity sector","sector compatible","compatible scenario","bloomberg energy","energy finance"],"m_TriGrams":["investor summit climate","summit climate risk","make electricity sector","electricity sector compatible","sector compatible scenario","renewable energy investment","bloomberg energy finance"],"m_SocialTags":[],"m_Topics":[],"m_Industry":[],"m_Technology":[],"m_BiCnt":[4,4,4,4,4,4,3,3,3,3,3,3],"m_TriCnt":[4,4,3,3,3,3,3],"m_iDocBodyWordCnt":509}
