{"m_szDocID":"1966592","m_szDocTitle":"Reno Puck Club makes pitch for hockey team downtown","m_szYear":"2016","m_szDocSumamry":"textArticle -------------------- FacebookEmail Twitter Google+ LinkedIn Pinterest Reno Puck Club makes pitch for hockey team downtown Reno Puck Club lobbying to get management of Reno Events Center in order to bring professional hockey, ice shows to Reno. Post to Facebook Reno Puck Club makes pitch for hockey team downtown Reno Puck Club lobbying to get management of Reno Events Center in order to bring professional hockey, ice shows to Reno. Check out this story on rgj.com: http://on.rgj.com/2brRiX9 CancelSend A link has been sent to your friend's email address. Posted! A link has been posted","m_szDocBody":"facebookemail google linkedin pinterest reno puck club make pitch hockey team downtown reno puck club lobbying management reno event centre order bring professional hockey ice show reno post reno puck club make pitch hockey team downtown reno puck club lobbying management reno event centre order bring professional hockey ice show reno cheque storey rgjcom cancelsend link friend address posted link posted feed reno puck club make pitch hockey team downtown winning big economic development fuel northern nevada growth toughest recession history northern nevada fair share economic development victory year followed list major economic development win region seen sponsored big tesla motor gigafactory costing billion projected employ people running tesla motor gigafactory tahoe reno industrial centre considered biggest win economic development history gigafactory linchpin teslas plan expansion manufacturing estimated battery pack company electric car year operational company eventually scale tesla energy line storage battery home businesse important raw number however impact renos reputation place business company expand superloop switch supernap tahoe reno industrial campus colocation data centre tahoe reno industrial centre huge undertaking projected cost billion comprise million square feet finished supernap key part switch superloop system allowing incredibly fast connexion speed client circular area bordered reno san francisco las vegas los angele largest data centre campus world house largest single data centre building million square feet switch client number include highprofile name ebay xerox dreamwork shutterfly cloud rackspace data centre san antoniobased rackspace plan build million squarefoot data centre reno technology park serving client west coast company projecting million payroll projected economic impact million rackspace managed cloud service company client country taking bite apple data centre started all reno area fair share economic development triumph including distribution centre wellknown company apple million data centre however sexy project put reno map making viable location data centre time apple arrival area racked nice list data centre facility highprofile project tesla switch data centre continue expand year announcement poised percent power renewable energy prime distribution amazon reno fulfilment centre amazon operated fulfilment centre fernley year deciding horizontal move reno building squarefoot facility compared fernley centre facility reno literally supersized handle larger package featuring latest technology amazon warehousing arsenal facility processe ten thousand item day taking flight unmanned aerial system designation nevada site chosen federal aviation administration approved test developing technology drone unmanned aerial vehicle system then state leveraged federal designation kickstart research programme north south attracting company specialising technology research firm teal corp project drone billion industry nasa partnership nuance drone virtual reality lab joint venture nasa university nevada reno nextgen collaborative environment laboratory nuance lab located renostead airport freedom flight terminal facility tackle airspace management research connect nasas airspace simulation system addition work unmanned aerial vehicle software nuance lab feature workshop building drone unmanned aerial system facility officially unveiled publicly natural thrive market food meet costco online retailer natural organic product relocated commerce calif distribution centre tahoereno industrial centre squarefoot facility staffed employee year projected provide region total economic impact million year period million employee payroll job creator zulily ecommerce giant doubled northern nevada presence expanding facility announcing ramp employment plus job expansion tahoe reno industrial centre facility square feet represented million investment job commitment record economic development authority western nevada time crackin mary cracker growing manufacturer organic glutenfree item announced building manufacturing r&d facility reno moving headquarter biggest city boot mary cracker plan invest million capital expenditure project hiring worker end average wage hour lead aqua metal aquarefinery world commercialscale electrochemical lead battery recycling plant aqua metal aquarefinery clean technology recycle lead leadacid battery lower cost emission compared traditional method smelting company acquired million loan green bank backed loan guarantee usda funding expand capacity refinery located tahoe reno industrial centre milking dairy farmer america plant economic development win northern nevada limited economy dairy farmer america opened fallon plant boasting sustainable facility fewer natural resource leaving smaller carbon footprint operation scope scoff dairy plant processe million gallon raw milk daily turn pound milk powder shipped worldwide jason hidalgo pdt datemeta ","m_szGeo1":"United States","m_szSourceType":"source_news","m_szSrcUrl":"http://www.rgj.com/story/money/reno-rebirth/2016/08/25/reno-puck-club-makes-pitch-echl-hockey-team-downtown/89356922/","m_Places":["Reno","Northern Nevada","Tesla","Las Vegas","Los Angeles","San Antonio","Fernley","Nevada","Biggest Little City","Green Bank"],"m_People":["Jason Hidalgo"],"m_Companies":["Twitter","Google","Linkedin","Pinterest","Facebook","Tesla Motors","Supernap","Ebay","Xerox","Dreamworks","Shutterfly","Rackspace","Reno Technology","Apple","Amazon","Federal Aviation Administration","Teal Group Corp.","Nasa","University Of Nevada, Reno","Costco","Economic Development Authority Of Western Nevada","Aqua","Usda","Dairy Farmers Of America"],"m_BiGrams":["data centre","economic development","reno puck","puck club","tahoe reno","reno industrial","industrial centre","northern nevada","unmanned aerial","club make","make pitch","pitch hockey","hockey team","team downtown","square feet","centre facility"],"m_TriGrams":["tahoe reno industrial","reno puck club","reno industrial centre","puck club make","club make pitch","make pitch hockey","pitch hockey team","hockey team downtown"],"m_SocialTags":[],"m_Topics":[],"m_Industry":[],"m_Technology":[],"m_BiCnt":[10,7,5,5,5,5,5,4,4,3,3,3,3,3,3,3],"m_TriCnt":[5,4,4,3,3,3,3,3],"m_iDocBodyWordCnt":658}
