{"m_szDocID":"1998851","m_szDocTitle":"Chinese car-hailing app Didi Kuaidi invests in regional player GrabTaxi to help stymie Uber’s expansion plans in Asia | South China Morning Post","m_szYear":"2015","m_szDocSumamry":"South China Morning Post Print Email Now Reading Chinese car-hailing app Didi Kuaidi invests in regional player GrabTaxi to help stymie Uber’s expansion plans in Asia   Chinese car-hailing app Didi Kuaidi invests in regional player GrabTaxi to help stymie Uber’s expansion plans in Asia PUBLISHED : Thursday, 20 August, 2015, 2:03pm UPDATED : Thursday, 03 September, 2015, 3:58pm As electric car usage grows, what can Hong Kong do with all the old batteries? 1 Sep 2016 Chinese car-hailing giant Didi Kuaidi has made an investment in GrabTaxi, a Southeast Asian taxi-booking company, in a move widely","m_szDocBody":"south china morning post print reading chinese carhailing app didi kuaidi invest regional player grabtaxi stymie uber expansion plan asia chinese carhailing app didi kuaidi invest regional player grabtaxi stymie uber expansion plan asia published thursday august updated thursday september electric car usage grow hong kong battery chinese carhailing giant didi kuaidi made investment grabtaxi southeast asian taxibooking company move widely posing challenge san franciscobased uber overseas expansion plan singaporeheadquartered grabtaxi uber top regional rivalsrecently million funding round didi kuaidi played role size contribution made public investor included chinas sovereign wealth fund china investment corporation investor didi kuaidi hedge fund coatue management llc enlarged previous investment company grabtaxi operate city country plan fund expand fastgrowing region investment statement grabtaxis dominance region growth potential southeast asia global level anthony tan ceo cofounder grabtaxi didi kuaidis interest pundit strategic company moving expand rapidly fend competition uber company swallowed domestic competition earlier year didi dache kuaidi dache chinas leading taxihailing app merged didi kuaidi uber smaller player chinese market increased attack taxi driver authority china hong kong year operating regulatory grey area encroaching regular cabby income uber office sichuan chengdu guangdong guangzhou raided police may driver arrested hong kong month lacking proper permitsas government decide deal key element emerging sharing peertopeer economy ","m_szGeo1":"Hong Kong","m_szSourceType":"source_news","m_szSrcUrl":"http://www.scmp.com/tech/apps-gaming/article/1851082/chinese-car-hailing-app-didi-kuaidi-invests-regional-player","m_Places":["Reading","Asia","Hong Kong","Singapore","United States","China","Southeast Asia","Chengdu","Guangzhou"],"m_People":["Didi Kuaidi","Anthony Tan","Didi Dache","Kuaidi Dache"],"m_Companies":["South China Morning Post","Uber","China Investment Corporation","Coatue Management Llc"],"m_BiGrams":["didi kuaidi","chinese carhailing","expansion plan","hong kong"],"m_TriGrams":[],"m_SocialTags":[],"m_Topics":[],"m_Industry":[],"m_Technology":[],"m_BiCnt":[6,3,3,3],"m_TriCnt":[],"m_iDocBodyWordCnt":209}
