{"m_szDocID":"1999477","m_szDocTitle":"Sharing Economy Part II: See It in Action · Environmental Leader · Environmental Management News","m_szYear":"2014","m_szDocSumamry":"textArticle -------------------- Sustainable Strategy & Leadership Last week, I wrote about how the Sharing Economy is transforming capitalism (by emphasizing access to goods rather than ownership) and providing an important part of the solution to our urgent environmental needs (by enabling more people to use fewer resources.) The Sharing Economy has been propelled by a shift in core values, embracing collaborative, peer-to-peer, cloud-based, and distributed networks. On a social level, people are disseminating and accessing information like never before. On a corporate level, companies that ","m_szDocBody":"sustainable strategy leadership week wrote sharing economy transforming capitalism emphasising good ownership providing important part solution urgent environmental enabling people fewer resource sharing economy propelled shift core value embracing collaborative peertopeer cloudbased distributed network social level people disseminating accessing information before corporate level company espouse sharing economy amassing loyal customer enjoying financial success course company airbnb uber snapgood developed business model based sharing economy principle company traditional model paving collaborative approach google example made android operating software competitor charge move risky time company recognised win expanding market mobile device ensuring engine revenuebased digital service compatible prominently featured google opensource strategy served company well stock soared android widely adopted mobile operating system world billion device similar move drive market growth electric vehicle maker tesla recently opened patent portfolio anyone including competitor intellectual property productive purpose clear path creation compelling electric vehicle lay intellectual property landmine inhibit other acting manner contrary goal elon musk teslas founder ceo musk emphatic growing electric vehicle market realise tesla achieve exponential change alone car electric say annual vehicle production approaching million year global fleet approximately billion car impossible tesla build electric car fast address carbon crisis tesla produced model vehicle year expect deliver yearonly drop bucket compared number vehicle sold year choosing collaboration protectionism tesla embraced pivotal principle sharing economytransforming competitor ally tesla opened opportunity new complimentary business relationship automotive company positioned essential source intellectual property innovative solution the company make electric system daimler toyota discussion bmw electromobility solution bold move enhance david versus goliath storey teslathe company founded accelerate advent sustainable transport unabashedly taking automotive industry innovative disruptive technology model sedan with mile battery range compared mile range nissan leaf national supercharger network free power driver travelling long distance the supercharger replenish approximately electric vehicle battery power minute less proposed billion lithiumion battery gigafactory encouraging collaboration tesla fasttracked electric vehicle industry increased demand super charging network laid groundwork future battery sale tesla shattered traditional thinking raised bar itselfselfimposing mandate perpetually remain leader breakthrough transportation solution company surfaced early leader sharing economy iconic outdoor clothing maker patagonia recent interview company director environmental strategy jill dumain asserted company outdoor industry collaborating before newfound collaboration manifested sustainable apparel coalition manufacturer retailer ngos partner working reduce environmental social impact apparel footwear coalition created higg index suite assessment tool measure lifecycle impact apparel product year company industry break historical barrier competition embrace collaboration have creating real positive change together dumain share information raw material supply chain issue sustainability topic therefore industry deliver unprecedented level transparency customer buy inception patagonia embraced radical thinking endeavoured catalyst change company common thread worn wear initiative revolutionised concept transparency authenticity apparel sector patagonia share information public increasing level transparency profitability encouraged competitor follow suit dumain confirm sharing economy transforming consumer purchasing pattern people millennial happier stuff way challenging patagonia company sell product order stay business but here radical conceptwhat consumed half today purchased quality product budget dumain present intriguing propositionmore people fewer resource negative impact economy sound win around sara cofounder ceo green builder media experienced entrepreneur investor sustainability consultant sara specialise developing company simultaneously sustainable profitable sara venture capitalist participated portion life cycle from funding exit company sara graduated cum laude dartmouth college hold mba entrepreneurship finance university colorado reprinted permission green builder media republished permission green builder media information green building sustainable living visit green builder media follow regular update breaking new ","m_szGeo1":"United States","m_szSourceType":"source_industry","m_szSrcUrl":"http://www.environmentalleader.com/2014/07/24/sharing-economy-part-ii-see-it-in-action/","m_Places":["Tesla","Toyota"],"m_People":["Elon Musk","Jill Dumain"],"m_Companies":["Airbnb","Uber","Take Google","Google","Path","Bmw","Groundwork","Patagonia","Dartmouth College","University Of Colorado","Facebook","Twitter"],"m_BiGrams":["sharing economy","electric vehicle","green builder","builder media","intellectual property"],"m_TriGrams":["green builder media"],"m_SocialTags":[],"m_Topics":[],"m_Industry":[],"m_Technology":[],"m_BiCnt":[6,5,4,4,3],"m_TriCnt":[4],"m_iDocBodyWordCnt":559}
