{"m_szDocID":"1999494","m_szDocTitle":"Hong Kong car-sharing start-up goes from strength to strength | South China Morning Post","m_szYear":"2015","m_szDocSumamry":"South China Morning Post Hong Kong car-sharing start-up goes from strength to strength Â  Autos Hong Kong car-sharing start-up goes from strength to strength Two years after sowing the radical idea of drivers renting their cars to others when not in use, Carshare.HK has electric car deal with BYD, has spread to Shanghai and is eyeing Shenzhen PUBLISHED : Wednesday, 15 April, 2015, 1:44pm UPDATED : Friday, 17 April, 2015, 6:28pm Electric car start-up eyeing US midwest to test its self-driving vehicles 7 Jun 2016 Encouraging Hongkongers to loan their cars to complete strangers seemed like a radic","m_szDocBody":"south china morning post hong kong carsharing startup strength strength autos hong kong carsharing startup strength strength year sowing radical idea driver renting car use carsharehk electric car deal byd spread shanghai eyeing shenzhen published wednesday april updated friday april electric car startup eyeing midwest test selfdriving vehicle encouraging hongkonger loan car complete stranger radical idea nevertheless christopher yeung team pitched carsharehk concept startup exchange cocoon coworking space tin hau walked prize modest chunk capital seeking carsharehk gear year later startup place car shortterm rental carsharehk member venture integral part hong kong fringe sharing economy spread sharing creed company month launched project shenzhenbased carmaker byd give member chance experience driving electric car byd provided carsharehk model ambassador sharing programme ambassador chosen applicant month carsharehk member rent day free battery recharge ambassador rent member month receive parking voucher worth carsharehk cofounder marketing officer joyce kan team contacted angel investor shortly won pitch cocoon invested million venture like car lot read pitch south china morning post approached helped started month later launch website found great designer web developer managed close insurance deal directasia carsharehk enable owner car rent neighbour estate occasionally vehicle hour day wide variety car price vary carsharehk owner making average month rent startup take commission transaction platform take care identity verification insurance technical issue busy work people joyce kan kan initially uphill battle persuading people share car people didnt know business based trust insurance major hurdle unfamiliar business model insurer found risky launched people put car website kan say review owner user reputation word mouth people share car slower start expected sharing economy popular time gogovan easyvan uber transport segment sharing economy recent month growing faster matter timing new startup now helped carsharehk founder heed warning speaker cocoon event local startup ideas scalable small kong market startup established shanghai eye city china shenzhen target started trial shanghai started september competition intense peer company thing kan say shanghai people surprisingly open ideas car owner share car month kan startup raise round funding expansion mainland team collaborate sharing programme carmaker similar byd initiative kan yeung remaining member original carsharehk team four moved venture member board kan say busy work people shared commented ","m_szGeo1":"Hong Kong","m_szSourceType":"source_news","m_szSrcUrl":"http://www.scmp.com/lifestyle/motoring/article/1766926/hong-kong-car-sharing-start-goes-strength-strength","m_Places":["Hong Kong","Shanghai","Shenzhen","United States","China"],"m_People":["Christopher Yeung","Tin Hau","Joyce Kan"],"m_Companies":["South China Morning Post","Cocoon Co","Uber","Kong","Target"],"m_BiGrams":["hong kong","electric car","sharing economy","share car","kan say"],"m_TriGrams":[],"m_SocialTags":[],"m_Topics":[],"m_Industry":[],"m_Technology":[],"m_BiCnt":[3,3,3,3,3],"m_TriCnt":[],"m_iDocBodyWordCnt":361}
