{"m_szDocID":"2000503","m_szDocTitle":"Market leader Didi Kuaidi launches carpooling service to take on 'the People's Uber' | South China Morning Post","m_szYear":"2015","m_szDocSumamry":"South China Morning Post Market leader Didi Kuaidi launches carpooling service to take on 'the People's Uber' Â  Market leader Didi Kuaidi launches carpooling service to take on 'the People's Uber' PUBLISHED : Monday, 01 June, 2015, 5:31pm UPDATED : Thursday, 03 September, 2015, 3:58pm As electric car usage grows, what can Hong Kong do with all the old batteries? 1 Sep 2016 Mainland China's largest taxi and car-hailing app Didi Kuaidi has launched a car-pooling service as it seeks to head off US rival Uber. Didi Kuaidi said it has already recruited more than one million drivers to the service, ","m_szDocBody":"south china morning post market leader didi kuaidi launches carpooling service the people uber market leader didi kuaidi launches carpooling service the people uber published monday june updated thursday september electric car usage grow hong kong battery mainland chinas largest taxi carhailing app didi kuaidi launched carpooling service seek head rival uber didi kuaidi recruited million driver service didi shun fen che which loosely translate didi carpool driver motivated desire cost share commute make profit company said committed work government build greener china carpooling sharing economy internet travel sector reduce pollution traffic spoil life big chinese city reshape persontoperson relation jean liu president didi kuaidi service initially beijing expanding city mainland china month user app connect driver charge standard fee yuan kilometre half beijing taxi additional surchage yuan kilometre travelled strategy endorsed beijing government part green travel initiative liu company planned launch service long time goal encourage chinese adopt carpooling make contribution emissionreduction million private car short trip china day said carpooling reduce traffic emission however didi kuaidi entering carpooling business late market extremely competitive china week due lack funding rising carpooling app pin che closed service attracting hundred thousand user launch early bird pin che founded expanded cover chinese city million user raised million recent funding round app dida pin che raised million yuan spread service chinese city beijing didi carpool compete people uber carpool service launched company chinese capital mid user catch ride paying driver petrol cost uber expanded service make money chinese city including shanghai guangzhou october american company struggled mainland china recently earlier year office guangzhou chengdu raided authority nationwide ban private car offering taxi service visit china week uber chief executive founder travis kalanick company learn local law bylaw make service legal china valued billion active country city worldwide uber faced strenuous competition china domestic rival didi dache kuaidi dache announced merger leave combined company cent market share didi kuaidi announced month spend billion yuan million give free discounted ride passenger promote chauffer service didi express month chinese social media giant weibo announced million investment didi kuaidi valued billion viewed ","m_szGeo1":"Hong Kong","m_szSourceType":"source_news","m_szSrcUrl":"http://www.scmp.com/tech/apps-gaming/article/1814547/market-leader-didi-kuaidi-launches-carpooling-service-take-peoples","m_Places":["Hong Kong","United States","Most","China","Beijing","Shanghai","Guangzhou","Chengdu"],"m_People":["Didi Kuaidi","Dida Pin Che","Jean Liu","Ai Pin Che","Travis Kalanick","Didi Dache","Kuaidi Dache"],"m_Companies":["South China Morning Post","Uber","Pooling","Beijing Government","Aa","Nationwide"],"m_BiGrams":["didi kuaidi","chinese city","carpooling service","people uber","pin che"],"m_TriGrams":[],"m_SocialTags":[],"m_Topics":[],"m_Industry":[],"m_Technology":[],"m_BiCnt":[8,4,3,3,3],"m_TriCnt":[],"m_iDocBodyWordCnt":345}
