{"m_szDocID":"2003739","m_szDocTitle":"First fuel cell car-sharing programme launching in Germany - Circulate","m_szYear":"2016","m_szDocSumamry":"dateText -------------------- May 4, 2016  textArticle -------------------- LATEST  What drives companies towards remanufacturing?  5 reasons why businesses should be building circular economy into their strategy  Accelerating the impact of bio-based materials to further the apparel industry  Oil price uncertainty remains, time for an energy re-think?  New Suez report finds Â£9bn circular economy benefit for UK  Why the circular economy matters  Why you should grab a piece of the sharing economy  Five ways artificial intelligence will change enterprise IT  Home  About  Sections  Featured  News ","m_szDocBody":"latest drive company remanufacturing reason businesse building circular economy strategy accelerating impact biobased material apparel industry oil price uncertainty remain time energy rethink suez report find circular economy benefit circular economy matter grab piece sharing economy way artificial intelligence change enterprise home section featured new international correspondent emerging market future podcast reading city energy material flow food business people home section featured new international correspondent emerging market future podcast reading city energy material flow food business people city new fuel cell carsharing programme launching germany seb egertonread seb egertonread hydrogen fuelcell car competitive term cost seemingly viable intheir performance characteristic well however infrastructure challenge continue barrier hand user dont buy hydrogen car filling station dont exist other company dont build filling station people hydrogen car enter business model photo credit sheriffmitchell visual hunt byncsa linde large german industrial gase company entering transport sector launching world carsharing service hydrogen car service called beezero offer customer opportunity rent hyundai fuel cell electric vehicle city munich range single charge mile significantly battery based electric vehicle mean car longer trip city use germany hydrogen filling station currently linde hope beezero carsharing model make fuelcell vehicle economic choice assist creating greater consumer demand turn shift current infrastructure source world fuelcell carsharing programme open germany share this friend open window share open window share open window share linkedin open window share pocket open window share google open window tag renewable sharing economy previous post plastic economy post future mobility tech driver seb egertonread seb write daily circulate full spectrum website topic previously spent year freelance writer number website blog seb sebatcirculatenewsorg related post business city new circulate friday city dictate future finance business city food new circulate friday patagonias film cashing circular economy business energy material flow featured people sharing economy circular economy recent post business drive company remanufacturing reading reason businesse building circular economy strategy reading accelerating impact biobased material apparel industry energy material flow oil price uncertainty remain time energy rethink reading suez report find circular economy benefit explore circulate dprinting agriculture automotive biomimicry brazil built environment business model circular economy city cradle cradle design education electronic emerging market energy europe finance food food waste green chemistry health industrial ecology internet japan job material mobility money natural capital business model oil plastic policy recycling remanufacturing renewable energy renewable repair reverse logistic sharing economy solar synthetic biology system thinking transport water newsletter circular economy new direct inbox created core philanthropic partner sun global partner cisco h&m intesa sanpaolo nike philip renault unilever contributor copyright right reserved share fuel cell carsharing programme launching germany send address address cancel post cheque addresse cheque failed sorry blog share post email ","m_szGeo1":"United Kingdom","m_szSourceType":"source_general","m_szSrcUrl":"http://circulatenews.org/2016/05/first-fuel-cell-car-sharing-programme-launching-in-germany/","m_Places":["Suez","Uk","Germany","Enter","Linde","Munich","Brazil","Europe","Japan"],"m_People":["Seb Egerton"],"m_Companies":["Hyundai","Facebook","Twitter","Linkedin","Google","Seb","Patagonia","Global Partners","Cisco","H&m","Intesa Sanpaolo","Nike, Inc","Philips","Renault","Unilever"],"m_BiGrams":["circular economy","open window","window share","sharing economy","energy material","material flow","emerging market","fuel cell","carsharing programme","seb egertonread","hydrogen car","filling station","business model"],"m_TriGrams":["open window share","energy material flow"],"m_SocialTags":[],"m_Topics":[],"m_Industry":[],"m_Technology":[],"m_BiCnt":[9,6,5,4,4,4,3,3,3,3,3,3,3],"m_TriCnt":[5,4],"m_iDocBodyWordCnt":442}
