{"m_szDocID":"2018348","m_szDocTitle":"Parking","m_szYear":"2015","m_szDocSumamry":"Subscribe  Flights  Plan A Flight  Flight Status  Nonstop Destinations  Terminal Map  Airport Security  PARKING & TRANSPORTATION  Parking  Ground Transportation  Drop Off & Pick Up  Passenger Guide  Navigating MEM  Checking In  Arriving at MEM  Passenger Services  FAQs  Visit Memphis  Dining  Shopping  ABOUT MEM  Leadership  MEM Modernization  MEM Blog  Community Events & Partnerships  Memphis International Airport Arts Program  Memphis International Airport Partnerships With Local Schools  HMSHost & the Warriors Center  MEM, Memphis Grizzlies and Tony Allen  Fun & Games  Do Business with MEM ","m_szDocBody":"flight plan flight flight status nonstop destination terminal map airport security parking transportation parking ground transportation drop pick passenger guide navigating mem checking arriving mem passenger service faqs visit memphis dining shopping mem leadership mem modernization mem community event partnership memphis international airport art programme memphis international airport partnership local school hmshost warrior centre mem memphis grizzly tony allen fun game business mem disadvantaged business enterprise programme business diversity development programme small business participation programme mem rule regulation opportunity future project property cargo surplus property press room guideline media media airport ground general aviation fbos general dewitt spain airport charle baker airport wilson air centre memphis fbo signature flight support memphis fbo environment aircraft fire fighting facility airport police board meeting agendas strategic overview report career contact parking ground transportation drop pick plan flight flight status parking parking memphis international airport mem offer variety convenient affordable parking option covered facility parking areas lit evenfree vehicle assistancefor car trouble jump started vehicle year helped traveller car economy parking economy parking space new levelground transportation centre gtc economy parking follow car pickup sign left airport left exit past gtc quick left take facility economy pricing minute free minute minute minute hour hour interval electric vehicle level offer charging station electric vehicle including handicapaccessible space charging station elevator level complimentary luggage cart elevator level economy parker reach terminal easily ground transportation centre pedestrian walkway moving sidewalk beautiful landscaping memphis music playing speaker above elevator level pedestrian walkway walkway take straight terminal proceed level ticketing security longterm parking longterm parking good offer convenient parking spacesto long term parking follow long term sign left airport left exit past gtc long term parking entrance straight ahead longterm pricing minute free minute additional minute hour maximum fee shortterm parking shortterm parking space ground level threestory parking facility directly terminal short term parking stay left lane approaching airport follow overhead sign shortterm parking shortterm pricing minute free minute additional min hour maximum oversize vehicle oversize vehicle parking parking space rvs tractor trailer large van vehicle trailer large commercial vehicle contact parking office question special request accessible parking accessible space parking areas elevator walkway vehicle parked accessible space display appropriately designated licence plate hang tag rearview mirror regular rate apply accessible parking inquiry related accessible parking call extended parking traveller day parking asked call parking office advanced notification extended parking need vehicle towed expense day pay pay cash debit major credit card convenience offercredit card express ticketless transaction simply insert credit card entrance credit card exiting lost parking receipt copy problem call parking office monday friday cell phone lot mem free waiting area minute drive terminal safely conveniently wait ready pick call greet passenger curbside pickup driveway cell phone lot located maindrivejust enter airport ground updated flight information display arrival time improved lighting landscaping dropping picking passenger dropped ticketing upper level baggage ground level terminal airport ground follow sign terminal lane upper level stay centre lane ground level remember picking dropping off efficient possible security purpose courteous fellow traveller party extra luggage spend extra time inside terminal park shortterm parking space terminal minute free assistance service jump remember parked mem covered free hour customer assistance service offered include battery start tyre inflation lost car location security escort call info flight mem winchester memphis follow free wifi privacy business mem memphis international airport","m_szGeo1":"Spain","m_szSourceType":"source_general","m_szSrcUrl":"http://www.flymemphis.com/parking","m_Places":["Memphis","Take","Memphis, Tn","United States"],"m_People":["Tony Allen","Charles W. Baker"],"m_Companies":["Hmshost","Memphis Grizzlies","Air Center","Signature Flight Support","Travelers","Lot"],"m_BiGrams":["memphis international","international airport","minute free","shortterm parking","ground transportation","airport ground","economy parking","parking space","pricing minute","free minute","elevator level","long term","term parking","ground level","parking office","accessible parking","credit card"],"m_TriGrams":["memphis international airport","pricing minute free"],"m_SocialTags":[],"m_Topics":[],"m_Industry":[],"m_Technology":[],"m_BiCnt":[4,4,4,4,3,3,3,3,3,3,3,3,3,3,3,3,3],"m_TriCnt":[4,3],"m_iDocBodyWordCnt":552}
