{"m_szDocID":"2019898","m_szDocTitle":"Private chargers, like Airbnb for EVs, emerge to fill need - Autoblog","m_szYear":"2016","m_szDocSumamry":"dateText -------------------- Aug 5th 2016 at 3:55PM  textArticle -------------------- New Cars  New Cars Hub  Models & Styles  Car Buying  Guides  Car Finder  Compare Cars  Best Deals  Dealer Directory  Car Loans  Research Tools  For Sale  For Sale Hub  Cars for Sale  Book Values  Rebates &  Incentives  Calculators  News & Reviews  News & Reviews Hub  Autoblog Reviews  Owner Reviews  Auto Shows  Photos  News by Make  News by Category  Press Releases  News Archive  Ownership  Ownership Hub  Recalls  Safety  Repair &  Maintenance  Repair Shops  Gas Prices  Sell Your Vehicle  Insurance  Insuranc","m_szDocBody":"car car hub model style car buying guide car finder compare car deal dealer directory car loan research tool sale sale hub car sale book value rebate incentive calculator new review new review hub autoblog review owner review auto show photos new make new category press release new archive ownership ownership hub recall safety repair maintenance repair shop gas price sell vehicle insurance insurance quote videos videos translogic list car club usa autoblog detail short cut autoblog minute store car care oil fluid performance tool part accessory spec review car sale spec review select make select model spec review car sale select make select model select style convertible coupe crossover hatchback hybrid luxury minivan sedan suv performance truck van waggon certified preowned cpo select make select model shop spec review sale announced complete agenda upshift cheque detail ticket green green add private charger airbnb evs emerge fill charging join sharing economy infrastructure gap filled google reddit linkedin pinterest licence licence john beltz snyder car ridesharing service airbnb peertopeer rental even pet rental transacted app helped bring rise sharing economy prefer call economy affordable convenient something put work rise sort collaborative consumption coinciding growing popularity electric vehicle make sense sharing economy eventually extend car private electric vehicle charger well gap nascent web charging infrastructure plugshare launched driver locate charging addition charger installed government businesse map residential charger owner share driver aided driver time need enabled crosscountry electric road trip similarly renault launched elbnb sweden homeowner shared residential charger outlet driver plug mobile charger public elbnb raised sweden number charging location percent week helped bring attention shortfall infrastructure renault owner await public charging infrastructure catch local level charge car owner nearby driveway sort feelgood juice help reduce range anxiety lessen congestion public charger and owner plug charging fillup help fellow human offset cost charger ownership household turn home solar system energy need sharing plug driver cleaner charge plugshare recently teamed sungevity provide free residential charger solar customer monetary incentive albeit small instal solar good planet helpful grid stability make extra electron peak hour solar user and traditional grid customer offer plug free happy likeminded individual palo alto resident sven thesen tell scientific american this educational tool bust myth price electricity soon though public infrastructure catch demand people feel comfortable making switch electric driving meantime fellow owner back related video related gallery chargepoint home charger new source scientific american local image credit plugshare green green culture electric charging charging infrastructure elbnb electric vehicle plugshare sharing economy google reddit linkedin pinterest licence licence reporting comment rude offensive constructive offtopic sexual spam misleading reported comment user reviewed autoblog staff hour day day week determine violate community guideline account penalised community guideline violation repeated violation lead account termination submit logout post reply ago read delete report reply trending dumbest car time mercedesamg topless car question autoblog q&a platform emission kill run oil autonomous grand ride autoblogvr app dumbest car time mercedesamg topless car question autoblog q&a platform emission kill run oil autonomous grand ride autoblogvr app follow shop book automotive technology principle diagnosis service edition toyota way management principle world greatest manufacturer wide bring horizon today technician automotive electricity electronic classroom shop manual pack movy merchandise part accessory book part accessory chemical guy mic chenille microfiber premium scratchfree wash mitt camco tastepure water philtre flexible hose protector microfiber cleaning cloth pack camco tastepure drinking water hose lead free movy merchandise part accessory book shop merchandise green auto masking tape rollspaint car green clean automotive quick wax superior ecological car care product powerful eff mictuning universal rocker style car usb charger green led light dual usb power socket for zone tech flexible waterproof green light strip pack led car flexible waterproof green movy merchandise part accessory book shop movy brother sister season school musical twodisc remix edition learn language everyday language lesson children volume vhs fun car care tip movy merchandise part accessory book dieselpowered ford caught completely undisguised tesla ceo elon musk allegedly impersonated oil exec mobileye bailed tesla autopilot safety concern partner link zergnet consumer resource compare top model choose vehicle compare sidebyside price feature performance cost ownership more advanced driver assistance system adas guide latest adas offering including blind spot monitoring turn assist backup collision warning more local car dealer car dealer make location videos futuristic tech technical centre translogic watch video watch navy shock testing deck lcs watch video formula driving arctic ice ethanol emission problem recharge wrap watch video opel sell station waggon free underwear watch video ninja viking strongman walk junkyard carboom watch video lamborghini huracan horse thief mile autoblogvr watch video ken block unleashes focus industrial park gymkhana watch video walk nrburgring watch video proof maseratipowered lazareth quad work watch video bristol motor speedway turned football stadium watch video sitemap widget contact tip feedback licencing app autoblog autoblog iphone autoblog apple autoblog podcast itune archive advertising ads advertise legal term service privacy policy trademark copyright aol inc right reserved service share photo google reddit linkedin pinterest select option voting datemeta ","m_szGeo1":"United States","m_szSourceType":"source_general","m_szSrcUrl":"http://www.autoblog.com/2016/08/05/private-ev-charging-share-economy/","m_Places":["Hub","Best","United States","Sweden","Palo Alto","Toyota","Guys","Superior - Best","Brothers","Sisters","Tesla","Bristol"],"m_People":["John Beltz Snyder","Sven Thesen","Wash Mitt","Elon Musk","Ken Block"],"m_Companies":["Airbnb","Facebook","Twitter","Google","Reddit","Linkedin","Pinterest","Renault","Sungevity","Scientific American","Autoblog Staff","Amg","3m","Universal","Diesel","Top Models","Adas","Navy","Lamborghini","Huracan","Aol Inc."],"m_BiGrams":["watch video","part accessory","spec review","sharing economy","movy merchandise","merchandise part","accessory book","car sale","car care","select make","make select","select model","google reddit","reddit linkedin","linkedin pinterest","electric vehicle","residential charger"],"m_TriGrams":["movy merchandise part","merchandise part accessory","part accessory book","google reddit linkedin","reddit linkedin pinterest"],"m_SocialTags":[],"m_Topics":[],"m_Industry":[],"m_Technology":[],"m_BiCnt":[10,6,4,4,4,4,4,3,3,3,3,3,3,3,3,3,3],"m_TriCnt":[4,4,4,3,3],"m_iDocBodyWordCnt":830}
