{"m_szDocID":"2037611","m_szDocTitle":"Welcome to the new economy built on sharing - CBS News","m_szYear":"2013","m_szDocSumamry":"dateText -------------------- March 24, 2013, 10:13 AM  textArticle -------------------- The all new  CBS News App  for Android  ®  for iPad  ®  for iPhone  ®  Fully redesigned. Featuring CBSN, 24/7 live news.  Get the App  ╳  CBS News  CBS Evening News  CBS This Morning  48 Hours  60 Minutes  Sunday Morning  Face The Nation  CBSN  GO  Log In  Log In  Join CBSNews.com  Sign in with              CBS Sunday Morning  Home  Arts  Books  Commentaries  Nature  Profiles  Notes  About  Trending Videos  CBSN Live »  Sunday Morning  Share and share alike  CBS Evening News  Trump's economic plan  CBS Eve","m_szDocBody":"allnew cbs new app android ipad iphone fully redesigned featuring cbsn app cbs new cbs evening new cbs morning hour minute morning face nation cbsn log log join cbsnewscom cbs morning home art book commentary nature profile note trending videos cbsn live morning share share alike cbs evening new trump economic plan cbs evening new sandra settlement cbsn campaign jingle cbs evening new back cbs evening new muslim marine dy cbs evening new chilling call cbs evening new aleppo aid cbs evening new morley safer remembered morning week sunday morning sept morning bruce springsteen bout crippling depression morning nature close vortex spring morning send message charle osgood morning demi lovato fighting back morning next recap link morning week sunday morning sept morning italian beauty wheel morning sorrow healing coexist ground morning calendar week morning trump supporter candidate morning almanack henry hudson cbs new economy built sharing comment share tweet stumble cbs new share share alike good advice family friend good advice business perfect stranger cover storey reported john blackstone place spend night san francisco suggest skip downtown hotel step limb doug studebaker tree house clear day mount diablo tallest point bay area told blackstone people world studebaker treehouse airbnb website made anybody rent room night room yearold california oak studebaker imagined hospitality business people world stay whimsical tree house airbnb handle booking payment night studebaker tree house make money this said adding nice share studebaker part called sharing economy internet acting matchmaker individual rent anybody carsharing service getaround relayride pretend afford electric car well owner tesla share you hour unconditional love affection well share dog bow tie night lifetime tie society sharing site offering parking space electronic individual increasingly business other big company rental listed airbnb rival hotel chain forbe magazine recently estimated billion flow sharing economy year treasury secretary lawrence summer big booster sharing economy make people feel good think good business bringing people together sharing resource efficiently economy live better summer said were moving kind economy car used parked summer continued where empty apartment lowercost place stay people money immediately put good use helping people credit card debt consolidate kid send college car buy summer recently joined board lending club business let people share money giving lender borrower deal bank yes easy compete onepercent interest rate laughed lending club founder french financial guru renaud laplanche especially delivered average six ninepercent net return investor year started prev cbs interactive inc right reserved comment share tweet stumble morning demi lovato singer music dominate radio airwave succeeded battling substance abuse bulimia depression oculus world trade centre transportation hub ground rise soaring transit centre photographed daniel jone popular follow icon icon icon icon cbs new email powell slam clinton trump view clinton leave ceremony feeling overheated view clinton remark half trump backer spark uproar view arson fire destroy mosque attended pulse nightclub gunman authority view police chief fatally shoot bad new view play video muslim marine dy play video back play video campaign jingle play video trump economic plan play video sandra settlement previous watch cbsn live watch cbs new anytime digital new network stream cbsn live demand free computer tablet smartphone watch photos bellissima stunning italian car design photos oculus world trade centre transportation hub photos demi lovato photos world trade centre photos and worst original star trek episode previous tweet apple app cbsnewscom map contact cbs bios career cbsi career internship development programme cbs interactive privacy policy choice term mobile agreement cbs advertise closed captioning cbs new store follow newsletter cbs radio new cbs local cbs new copyright cbs interactive inc right reserved ","m_szGeo1":"United States","m_szSourceType":"source_general","m_szSrcUrl":"http://www.cbsnews.com/news/welcome-to-the-new-economy-built-on-sharing-24-03-2013/","m_Places":["Aleppo","Diablo","Bay Area","California","Well","Tesla","Hub","United States","Mobile"],"m_People":["Morley Safer","Bruce Springsteen","Charles Osgood","Henry Hudson","John Blackstone","Doug Studebaker","Renaud Laplanche","Daniel Jones","Ad Choice"],"m_Companies":["Cbs News","Cbs","Blackstone","Airbnb","Tie Society","Forbes Magazine","Treasury","Lending Club","Cbs Interactive Inc.","Oculus","Trade Center","Pulse","Twitter","Facebook","Youtube","Cbs Radio"],"m_BiGrams":["cbs new","cbs evening","evening new","play video","new cbs","cbsn live","demi lovato","tree house","sharing economy","cbs interactive","world trade","trade centre"],"m_TriGrams":["cbs evening new","world trade centre"],"m_SocialTags":[],"m_Topics":[],"m_Industry":[],"m_Technology":[],"m_BiCnt":[8,8,8,5,3,3,3,3,3,3,3,3],"m_TriCnt":[7,3],"m_iDocBodyWordCnt":593}
