{"m_szDocID":"2038439","m_szDocTitle":"Market Data & Forecasts - Global, regional & Country-Level - Juniper Research","m_szYear":"2016","m_szDocSumamry":"We use cookies to ensure that we give you the best experience. By continuing to use our site you agree to our  cookie and privacy policy  , if you do not agree please leave the site  Dismiss this message  REGISTER  SIGN IN  My Juniper  Basket  Home  Subscriptions  ResearchStore  Services  Consultancy  Data  Resources  Blog  Press  Clients  About  Contact  Menu  Home  Corporate Subscriptions  ResearchStore  Commerce & Fintech  AI & Machine Learning – Fintech  AI & Machine Learning – Retail  POS Terminals  Top 10 Disruptive Technologies in Fintech  Contactless Payments  Digital Payment Strategie","m_szDocBody":"cooky ensure give experience continuing agree cookie privacy policy agree leave dismiss message juniper basket home subscription researchstore service consultancy data resource blog press client contact menu home corporate subscription researchstore commerce fintech machine learning fintech machine learning retail pos terminal top disruptive technology fintech contactless payment digital payment strategy digital retail marketing mobile online coupon mobile online remote payment mobile online ticketing digital commerce market mobile banking contactless payment survey mobile banking contactless payment survey mobile financial service emerging market mobile identity biometric tokenisation digital money transfer remittance mobile wallet online payment fraud future blockchain worldwide digital banking worldwide mpos market application app app store digital music digital adult mobile worldwide digital game market digital game esport mobile online entertainment mobile online gambling mobile online messaging digital video device wearable consumer printing scanning consumer wearable market survey drone future hearable smart audio green mobile smart clothing jewellery smart glasse future health fitness wearable smart toy smart watches smart wearable device smart wireless device smartphone market tablet phablet hybrid wireless charging worldwide consumer robotic key vertical market machine learning healthcare automotive hud autonomous vehicle commercial connected vehicle consumer connected car worldwide digital health hybrid electric vehicle inflight entertainment wifi connectivity mobile online entertainment worldwide smart city smart home ecosystem internet internet internet thing consumer internet thing industrial internet thing public service strategy competition machine learning media crowdfunding top technology innovator disruptor worldwide digital advertising digital business model future voice strategy sharing economy future cybercrime security mobile operator business model mobile roaming enabling technology market strategy augmented reality cloud computing consumer market cloud computing enterprise market digital voice assistant human interface biometric device context location based service mobile data offload onload virtual reality wifi hotspot service consultancy consultancy analyst support case study data forecast browse dataset resource event future digital award juniper new videos radio insight whitepaper free research blog archive press analyst relation file media file press release client logos contact home subscription researchstore service consultancy data resource blog press client contact live support sorry support moment home data data forecast data forecast browse dataset data forecast reliable indepth friendly data priority further addition indepth report strategic level powerpoint offer comprehensive dataset covering major mobile online market dataset essential tool require reliable source market data higher level granularity found research report market sizing forecast data offer deep granular insight size shape digital market providing vast array indicator including growth rate adoption rate price point user geographical split submarket breakdown generally forecast period year and embryonic market data available include market scenarios forecast map low medium projection depending specific development milestone occurring sector fixed timeline data purchase individual topic part wider corporate subscription interactive excel whatif analysis forecast excel format excel offering interactive functionality allowing user manipulate key data point inputting assumption data ability perform whatif analysis data enabled client gain deeper understanding market opportunity therein ability compare adjacent market side side effect growth rate adoption curve proven highly popular methodology assumption commentary interactive excel ifxl accompanied report explaining methodology assumption forecast suite addition key chart table presented accompanying commentary explanatory text key takeaway highlighted implication impact discussed juniper client detail forecast data offering contact jon king call browse dataset contact juniper research church cottage house church square basingstoke hampshire rgqw tel fax email navigation home subscription researchstore service consultancy data resource blog press client contact myjuniper career legal privacy cooky term condition juniper research registered england wale company copyright juniper research licensor right reserved built ","m_szGeo1":"United Kingdom","m_szSourceType":"source_general","m_szSrcUrl":"http://www.juniperresearch.com/data-forecasts","m_Places":["Mobile","Uk","United States","Worldwide Smart Cities","Friendly","England"],"m_People":["Jon King"],"m_Companies":["Fintech","Huds","Powerpoints","Excel","Ifxl","Juniper Research Ltd","Wales Company"],"m_BiGrams":["mobile online","subscription researchstore","service consultancy","machine learning","worldwide digital","home subscription","researchstore service","consultancy data","data resource","resource blog","blog press","press client","client contact","contactless payment","internet thing","data forecast","browse dataset","forecast data","juniper research"],"m_TriGrams":["home subscription researchstore","subscription researchstore service","researchstore service consultancy","service consultancy data","consultancy data resource","data resource blog","resource blog press","blog press client","press client contact"],"m_SocialTags":[],"m_Topics":[],"m_Industry":[],"m_Technology":[],"m_BiCnt":[8,4,4,4,4,3,3,3,3,3,3,3,3,3,3,3,3,3,3],"m_TriCnt":[3,3,3,3,3,3,3,3,3],"m_iDocBodyWordCnt":575}
