{"m_szDocID":"2038438","m_szDocTitle":"Blog","m_szYear":"2016","m_szDocSumamry":"dateText -------------------- July 2016  May 2016  April 2016  textArticle -------------------- We use cookies to ensure that we give you the best experience. By continuing to use our site you agree to our  cookie and privacy policy  , if you do not agree please leave the site  Dismiss this message  REGISTER  SIGN IN  My Juniper  Basket  Home  Subscriptions  ResearchStore  Services  Consultancy  Data  Resources  Blog  Press  Clients  About  Contact  Menu  Home  Corporate Subscriptions  ResearchStore  Commerce & Fintech  AI & Machine Learning – Fintech  AI & Machine Learning – Retail  POS Termi","m_szDocBody":"cooky ensure give experience continuing agree cookie privacy policy agree leave dismiss message juniper basket home subscription researchstore service consultancy data resource blog press client contact menu home corporate subscription researchstore commerce fintech machine learning fintech machine learning retail pos terminal top disruptive technology fintech contactless payment digital payment strategy digital retail marketing mobile online coupon mobile online remote payment mobile online ticketing digital commerce market mobile banking contactless payment survey mobile banking contactless payment survey mobile financial service emerging market mobile identity biometric tokenisation digital money transfer remittance mobile wallet online payment fraud future blockchain worldwide digital banking worldwide mpos market application app app store digital music digital adult mobile worldwide digital game market digital game esport mobile online entertainment mobile online gambling mobile online messaging digital video device wearable consumer printing scanning consumer wearable market survey drone future hearable smart audio green mobile smart clothing jewellery smart glasse future health fitness wearable smart toy smart watches smart wearable device smart wireless device smartphone market tablet phablet hybrid wireless charging worldwide consumer robotic key vertical market machine learning healthcare automotive hud autonomous vehicle commercial connected vehicle consumer connected car worldwide digital health hybrid electric vehicle inflight entertainment wifi connectivity mobile online entertainment worldwide smart city smart home ecosystem internet internet internet thing consumer internet thing industrial internet thing public service strategy competition machine learning media crowdfunding top technology innovator disruptor worldwide digital advertising digital business model future voice strategy sharing economy future cybercrime security mobile operator business model mobile roaming enabling technology market strategy augmented reality cloud computing consumer market cloud computing enterprise market digital voice assistant human interface biometric device context location based service mobile data offload onload virtual reality wifi hotspot service consultancy consultancy analyst support case study data forecast browse dataset resource event future digital award juniper new videos radio insight whitepaper free research blog archive press analyst relation file media file press release client logos contact home subscription researchstore service consultancy data resource blog press client contact live support sorry support moment home blog saviour network internet subscription cable skinny bundle posted lauren foye juniper recent research digital video industry discovered network expanding online video model mean delivery continue reading smarter street lighting posted steffen sorrell street lighting undoubtedly pain point city price traditional lighting fixture hps high pressure sodium lps low pressure sodium lamp inefficient produce unpleasant colour cast simultaneously chemical toxic environment continue reading contactless payment consumer insight posted nitin bhas latest survey consumer attitude mobile banking contactless payment unique insight consumer usage attitude indication future adoption service continue reading mobile banking consumer insight posted nitin bhas latest survey consumer attitude mobile banking contactless payment unique insight consumer usage attitude indication future adoption service continue reading uber lyft ride sharing service revenue double posted lauren foye juniper latest research sharing economy opportunity impact disruptor found shared transport platform typically driver earning revenue grow estimated billion billion continue reading ushering era digital health posted sam barker juniper latest research digital health found ageing population homebased care needed digital health deliverable system medical adherence remote patient monitoring unhealthy lifestyle lead increase chronic disease create targeted information education continue reading smartwatches apple bring presence direction posted jame moar launch relative success apple watch set clear benchmark upper end smartwatch market term functionality didnt bring market release generally expanded device aesthetic redefining capability vendor released smartwatches limited compared released large mobile player continue reading future toy smart toy posted steffen sorrell world concept applying internet connectivity considered physical object unsurprising toy industry increasingly involved development sale connected smart toy continue reading future mobile roaming posted nitin bhas number negotiation policy reversal state government operator parliament finally voted end mobile roaming charge the roaming regulation adopted year established cap mobile tariff automatic safeguard data roaming bill shock price transparency continue reading race autonomy posted sam barker report published juniper research autonomous vehicle week autonomous vehicle adoption regulation business model found autonomous vehicle hit road consumer adoption set market witnessed significant development past month stakeholder conducting live trial continue reading displaying result for feed analystxpress recent post saviour network internet subscription cable skinny bundle smarter street lighting contactless payment consumer insight mobile banking consumer insight uber lyft ride sharing service revenue double category commerce money application device wearable key vertical market strategy competition enabling technology archive month blog archive tag advertising amazon android app apple apple pay app at&t autonomous banking big data billing bitcoin bitfury black btcchina bull bundle carrier car channel churn city city cloud comcast commerce computer connected connected tvs consumer contactless continuum cord credit card cryptocurrency cutting cyber cybersecurity daimler deezer digital digital health disney driverless drone ecommerce economy emerging emv espn esport explorer fpool fintech fitness forking freedompop freemium game gaming glass glasse handset hce health health app home htc huawei hybrid inflight information internet iot iptv isis jaunt joris laarman laptop league led legend lighting line lol lte lumia lyft malware maritime market messaging mhealth microfinance microinsurance microloan microsaving microsoft mno mnos mobile mobile payment monitoring morpheus mshwari mst music mvno mxd netflix network nfc nintendo nokia nvidia oculus operator ott pay payment phablet playstation printing project rdio reality red regulation remote retail revenue roaming roku samsung service sharing shaving skinny smart smarthphone smartphone softcard software sony spotify store strategy streaming surface svod swift tablet taylor telefonica tesla trai twitch uavs uber ubermoto universal vehicle video videogame virtual vive vod voice voip volvo wearable wearable whatsapp window window xbox contact juniper research church cottage house church square basingstoke hampshire rgqw tel fax email navigation home subscription researchstore service consultancy data resource blog press client contact myjuniper career legal privacy cooky term condition juniper research registered england wale company copyright juniper research licensor right reserved built ","m_szGeo1":"United Kingdom","m_szSourceType":"source_general","m_szSrcUrl":"http://www.juniperresearch.com/analystxpress","m_Places":["Mobile","Uk","United States","Worldwide Smart Cities","Tesla","England"],"m_People":["Lauren Foye","Steffen Sorrell","Nitin Bhas","Sam Barker","James Moar"],"m_Companies":["Fintech","Huds","Consumer Insights","Uber","Lyft","2016-2020","2020","Apple","Eu","Parliament","Amazon","At&t","Bull","Comcast","Deezer","Disney","Espn","Facebook","Google","Htc","Huawei","Isis","Microsoft","Morpheus","Netflix","Nintendo","Nokia","Nvidia","O2","Oculus","Rdio","Roku","Samsung","Telefonica","Universal","Volvo","Youtube","Juniper Research Ltd","Wales Company"],"m_BiGrams":["contactless payment","mobile online","mobile banking","subscription researchstore","service consultancy","machine learning","banking contactless","worldwide digital","autonomous vehicle","digital health","consumer insight","juniper research","home subscription","researchstore service","consultancy data","data resource","resource blog","blog press","press client","client contact","smart toy","internet thing","business model","mobile roaming","street lighting","posted nitin","nitin bhas"],"m_TriGrams":["mobile banking contactless","banking contactless payment","home subscription researchstore","subscription researchstore service","researchstore service consultancy","service consultancy data","consultancy data resource","data resource blog","resource blog press","blog press client","press client contact","posted nitin bhas"],"m_SocialTags":[],"m_Topics":[],"m_Industry":[],"m_Technology":[],"m_BiCnt":[7,7,6,4,4,4,4,4,4,4,4,4,3,3,3,3,3,3,3,3,3,3,3,3,3,3,3],"m_TriCnt":[4,4,3,3,3,3,3,3,3,3,3,3],"m_iDocBodyWordCnt":952}
