{"m_szDocID":"2038437","m_szDocTitle":"Clients - Juniper Research","m_szYear":"2016","m_szDocSumamry":"We use cookies to ensure that we give you the best experience. By continuing to use our site you agree to our  cookie and privacy policy  , if you do not agree please leave the site  Dismiss this message  REGISTER  SIGN IN  My Juniper  Basket  Home  Subscriptions  ResearchStore  Services  Consultancy  Data  Resources  Blog  Press  Clients  About  Contact  Menu  Home  Corporate Subscriptions  ResearchStore  Commerce & Fintech  AI & Machine Learning – Fintech  AI & Machine Learning – Retail  POS Terminals  Top 10 Disruptive Technologies in Fintech  Contactless Payments  Digital Payment Strategie","m_szDocBody":"cooky ensure give experience continuing agree cookie privacy policy agree leave dismiss message juniper basket home subscription researchstore service consultancy data resource blog press client contact menu home corporate subscription researchstore commerce fintech machine learning fintech machine learning retail pos terminal top disruptive technology fintech contactless payment digital payment strategy digital retail marketing mobile online coupon mobile online remote payment mobile online ticketing digital commerce market mobile banking contactless payment survey mobile banking contactless payment survey mobile financial service emerging market mobile identity biometric tokenisation digital money transfer remittance mobile wallet online payment fraud future blockchain worldwide digital banking worldwide mpos market application app app store digital music digital adult mobile worldwide digital game market digital game esport mobile online entertainment mobile online gambling mobile online messaging digital video device wearable consumer printing scanning consumer wearable market survey drone future hearable smart audio green mobile smart clothing jewellery smart glasse future health fitness wearable smart toy smart watches smart wearable device smart wireless device smartphone market tablet phablet hybrid wireless charging worldwide consumer robotic key vertical market machine learning healthcare automotive hud autonomous vehicle commercial connected vehicle consumer connected car worldwide digital health hybrid electric vehicle inflight entertainment wifi connectivity mobile online entertainment worldwide smart city smart home ecosystem internet internet internet thing consumer internet thing industrial internet thing public service strategy competition machine learning media crowdfunding top technology innovator disruptor worldwide digital advertising digital business model future voice strategy sharing economy future cybercrime security mobile operator business model mobile roaming enabling technology market strategy augmented reality cloud computing consumer market cloud computing enterprise market digital voice assistant human interface biometric device context location based service mobile data offload onload virtual reality wifi hotspot service consultancy consultancy analyst support case study data forecast browse dataset resource event future digital award juniper new videos radio insight whitepaper free research blog archive press analyst relation file media file press release client logos contact home subscription researchstore service consultancy data resource blog press client contact live support sorry support moment home client client client broad spectrum sector industry represent world leading player trailblazing innovatorsthey juniper research quickly acquire industry knowledge gain market insight benefit competitive advantage small sample customer challenge facing thought working juniper research sony mobile benefit greatly juniper report particular annual benchmark report smart wearable technology henry kondo product planning manager sony mobile japan testimonial juniper research assessment disruptive factor feature function comparison solution provider relevant interest bank andrew mikesell omnichannel banking director sap united state testimonial business planning market research data source experienced juniper credible partner purpose peter heuman deputy head business unit support solution ericsson sweden testimonial way bluetooth sig bluetooth industry benefited juniper research suke jawanda chief marketing officer bluetooth sig united state testimonial quarterly tracker annual benchmarking report smart wearable technology provided valuable insight forecast market trend sector giuseppe torre product marketing manager dialogue semiconductor united kingdom testimonial juniper research provide opportunity learn player market alessandro adriani chief executive officer bridge alliance singapore testimonial mobile adult sector specifically juniper research analyst assessing reporting highly lucrative taboo sector julia dimambro founder mobile strategist cherry media spain testimonial juniper report extremely beneficial resource numerous way mary clark chief marketing officer syniverse united state testimonial call external validation strategy citing juniper report changing marketplace dominance mobile validation micah adler president ceo founder fiksu united state testimonial juniper wellestablished company strong focus research top company world rely predict future predict happen vishal gondal founder chief executive officer goqii united state testimonial company operating rapidly evolving space important source accurate reliable current research paolo montessori ceo managing director eservglobal france testimonial vuzix like juniper research anticipate trend market homework monitor confirm trend unfold paul traver chairman president chief executive officer vuzix corp united state testimonial ive long considered juniper authoritative voice operator billing bangos focus area richard leyland marketing communication bango united kingdom testimonial approached juniper research work reputation knowledge experience mobile commerce space roland tauchner chief executive officer dimoco austria testimonial providing essential data market intelligence juniper help identify opportunity accurately define position mobile landscape silvio kutic founder chief executive officer infobip croatia testimonial started juniper research regularly key player mobile commerce area supplied key insight steve rothwell founder cto eagle eye solution united kingdom testimonial contact juniper research church cottage house church square basingstoke hampshire rgqw tel fax email navigation home subscription researchstore service consultancy data resource blog press client contact myjuniper career legal privacy cooky term condition juniper research registered england wale company copyright juniper research licensor right reserved built ","m_szGeo1":"United Kingdom","m_szSourceType":"source_general","m_szSrcUrl":"http://www.juniperresearch.com/clients","m_Places":["Mobile","Uk","United States","Worldwide Smart Cities","Japan","Sweden","United Kingdom","Singapore","Spain","France","Austria","Croatia","England"],"m_People":["Henry Kondo","Andrew Mikesell","Peter Heuman","Giuseppe Torres","Alessandro Adriani","Julia Dimambro","Mary Clark","Micah Adler","Vishal Gondal","Paolo Montessori","Paul Travers","Richard Leyland","Roland Tauchner","Silvio Kutic","Steve Rothwell"],"m_Companies":["Fintech","Huds","Sony","Sap","Ericsson","Bluetooth","Bridge Alliance","Vuzix","Vuzix Corp.","Eye Solutions","Juniper Research Ltd","Wales Company"],"m_BiGrams":["juniper research","mobile online","united state","state testimonial","subscription researchstore","service consultancy","machine learning","worldwide digital","testimonial juniper","home subscription","researchstore service","consultancy data","data resource","resource blog","blog press","press client","client contact","contactless payment","smart wearable","internet thing","juniper report","united kingdom","kingdom testimonial"],"m_TriGrams":["united state testimonial","home subscription researchstore","subscription researchstore service","researchstore service consultancy","service consultancy data","consultancy data resource","data resource blog","resource blog press","blog press client","press client contact","united kingdom testimonial"],"m_SocialTags":[],"m_Topics":[],"m_Industry":[],"m_Technology":[],"m_BiCnt":[12,7,6,6,4,4,4,4,4,3,3,3,3,3,3,3,3,3,3,3,3,3,3],"m_TriCnt":[6,3,3,3,3,3,3,3,3,3,3],"m_iDocBodyWordCnt":751}
