{"m_szDocID":"2041882","m_szDocTitle":"June | 2014 | Web Strategy by Jeremiah Owyang | Digital Business","m_szYear":"2014","m_szDocSumamry":"dateText -------------------- Archive for June, 2014  August 2016  July 2016  textArticle -------------------- Jeremiah Owyang  BLOG  RESEARCH  SPEAKING  MEDIA  ABOUT  CONTACT  Blog  Research  Speaking  Media  About  Contact  Archive for June, 2014  12 Collaborative Services for Success at Work  Posted on June 16th, 2014 in:  Collaborative Economy  12  This post was originally posted on  Shareable  , the leading website on the growing movement. Top photo credit:   Yusuke Kawasaki  .  The collaborative economy empowers ordinary people to share their unused resources, such as time and goods, oft","m_szDocBody":"archive june jeremiah owyang blog research speaking media contact blog research speaking media contact archive june collaborative service success work posted collaborative economy post originallyposted shareable leading website growing movementtop photo credit yusuke kawasaki collaborative economy empower ordinary people share unused resource time good peertopeer commerce model tend model impacting individual illustrated popular honeycomb graphic however shared service arent limited personal use collaborative economy model expanding include strategy technology level quick guide company integrating strategy successful expansion application beg question sharing model work individual professional work work service personal use expand business world service professionalsoutsource task work life focus core responsibility competency here list collaborative economy service targeting business professional youll see market isnt ride sharing home sharing similar service share comment below fon hotspot paris francephoto credit nrkbeta airpr ondemand professional twosided marketplace provider communication buyer airpr track actionable insight not driving engagement cloudpeep ondemand community manager ready company scale launches seasonal period cloudpeep service experienced professional assist startup small businesse mature enterprise asneeded basis fraction cost fulltime manager peerspace team creative inspirational workspace peerspace offer side unused space sector bringing workspace unused space app that zirtual virtual executive assistant service matches busy people dedicated personal assistant manage detail dont trunk club busy male executive stylish professional personal stylist trunk club set profile you save time sending trunk clothes selected regularly scheduled basis pay like return rest shopping best refashion clothes female executive million dollar wardrobe expense low closet manageable threadflip bag borrow steal rent runway crowdspring design create website microsite logo powerpoint presentation make amazing crowdsourced expert odesk world largest online collaborative workspace elance providing million skilled independent contractor bring savvy professional professional freelancer offering large market worker copy editing online research translating digital production programming administrative work more breather place work executive breather online repository beautiful private place work meet relax big city step pervasive regus location worldwide loud coffee shop sprig deliver inexpensive hot meal demand youor employee boss family minute san francisco area fast food handcrafted meal created executive chefnate keller and yes app service too fon offer free shared wifi million location shapeway custommade printed product gift customer colleague including jewellery miniature desk accessory art collaborative economy exploding reaching areas life work service enable professional broad marketplace talent hire fulltime basis flip side enable provider set schedule work project want control work life balance invention sliced bread good this tesla let gain market posted collaborative economy corporation order win all tesla deployed business strategy call provide platform enable ecosystem design build enhance fulfil support product you tesla whos market leader category made surprising move releasing patent open source move pattern coinnovation move company collaborative economy partnering customer create product gequirky barclay card ring company share presentation show teslas commitment social good musk write car company fraction sale electric vehicle write impossible tesla build electric car fast address carbon crisis essence help tesla foster ecosystem maker hacker developer partner brand growing position ecosystem tesla standard electric vehicle industry dominant player enable build top platform order replicate enhance improve existing tesla vehicle additional business benefit commenter point securing industry building spec tesla dominant position upsell added service battery super charging station service company learn unprecedented move world partnering crowd tenet collaborative economy providing platform ecosystem build top spec enable innovation company scale partner deliver additional capability company secure place ecosystem offering added service demonstrate true commitment mission enabling participate tesla open secure architecture industry standard assuring place electric vehicle market company gain innovation crowd securing place ecosystem incredible business move incredible potential collaborative planet dont protest collaborative economy lead posted collaborative economy yesterday thousand infuriated taxi driver dozen european city brought transportation service standstill taxis launched escargot protest intended stopped traffic objection collaborative economy startup uber lyft similar startup raised global attention lost day wage angered customer seeking commute and ironically caused increase uber business making uber trending term resulting government official mocking taxi driver taxi protest collaborative economy backfired made uber popular ever cooler mind prevailed neelie kroesa european commission wrote seminal post stating sharing economy driver accommodation host equipment owner artisan people pay taxe play rule job national local authority make collaborative economy movement spreading industry startup space theyre heavily funded backed powerful technology company world growing desire faster cheaper service fact recently published honeycomb framework published show vertical impacted commerce significant disruption business people business customer competitor ceo taxi company month left time adopt strategy technology tech startup which financially backed google vcs powerful technology facebook apple samsung taxi company continue adopt ondemand technology company flywheel who visiting tomorrow launch marketplace driver truck tool nearme localmotion build own understand promote accountability enabling customer rate driver experience retain reward perform retrain release not year ago published research report showed business model needed succeed market month ago launched crowd company whichconnect big brand leader startup community collaborative economy let recap european commissioner neelie kroe final line post state time face fact digital innovation taxi app stay work agree youre protesting collaborative economy proof youre late party change business model lead movement dear businesse dont protest collaborative economy adopt lead related respected robin chase founder zipcar buzzcar write cooperative capitalism also executive auto company scott monty share taxis fighting unconventional battlefield image creative common george pauwel collaborative economy customer score posted collaborative economy move klout move fico score collaborative economy customer score today groundbreaking deal struck uber amex day ago received million dollar fidelity amex loyalty point pay ride amex card pay transaction glean additional time loyalty point table stake important pushes fuzzy squishy social media reveal matter finding behaviour peertopeer trust backed factual financial data collaborative economy based peertopeer commerce result increased transaction level and likely higher trust collaboration uber amex enable construction measure type customer collaborative economy customer score insight combined customer rating uber driver rate passenger customer whos worthy late night ride provider quality yelp ebay customer rate driver social metric local transaction data transaction happening local level provide data traffic route time can accurately predict people uber service loyalty data uber amex sharing data reward lock powerful relationship perspective combined traditional financial data loyalty point credit score net worth powerful insight customer behaviour putting data point together mean marry traditional financial data customer provider rating forecast network behaviour local level combined insight predict whos spend money friction transaction top brand important data accurate data directly tied actual commerce data point recent research found people make participate economy ceo american express record card holder spent hundred million dollar year uber ride statement money made here great crowd company corporation crowdbased businesse work business model ready collaborative economy customer score related prediction uber amazon timeline graphic corporate partnership collaborative economy collaborative economy business business posted collaborative economy collaborative economy include sharing economy maker movement crowd funding crowd lending perceived peertopeer movement yet limited individual helping alone company large small replicating strategy tactic improve business company peer collectively tapping collaborative space year ago rise social network myspace friendster facebook company frustrated participate peertopeer social network response rise branded online community emerge lithium jive telligent chatter mzinga today majority corporation branded online forum community employee partner customer progression happening collaborative economy peertopeer businesstobusiness tenet movement include activating idle resource usage reducing waste paradigm versus ownership reducing ownership people ondemand technology idle resource accessing internet thing mobile device social network online marketplace digital reputation online payment system collaborative economy businesstobusiness example feel free add comment section space association provided easy understand company replicating solution example airbnb supply chain localmotion replicate zipcar feature company enable car vehicle sharing software reduce key employee shared resource digital badge fleet vehicle twogo sap ridesharing software enable worker rideshare reducing global waste car road parking snafus corporate office encouraging productivity workforce communicate real time flow enable company share good resource staff company online marketplace akin ebay yerdle craigslist service offer company ability efficient resource obtaining additional resource quickly demand odesk elance which merged enable corporation online worker demand business employment solution provider offer business service project management software development office work copy editing company ondemand globe cargomatic uber shipping enable company efficiently manage supply chain enable businesse truck local route capacity managing ondemand planning reducing waste nearme white label airbnb enable company build marketplace company disrupted rapidly growing marketplace airbnb lyft lending club taskrabbit build marketplace tap crowd nearme storefront airbnb retail enable retailer excess idle space rent businesse ondemand form popup retail foster product offering shelve reduce profiteating expense wasted space warpit ebay business enable employee distribute idle resource demanddoe business chair desk printer lying unused share employee organisation maximising efficiency use myturn offer tool sharing library workforce buy scanner buy use inventory tracking software coworking startup liquidspace sharedesk pivotdesk other enable desksharing worker seeking place work business excess space work shift shared location businesse flexible offering desk ondemand crowdflower offer human computing demand hire thousand employee process simple task tap organised workforce worker conduct microtask online keeping workforce focused selfstarter open source starting point business build adhoc crowd funding website building crowd funding platform business branded data accessible costly open source software launch crowd funding site perk enable employer offer benefit perk employee add example comment expect large enterprise software company usher suite company replicating feature commerce solution airbnb uber sidecar taskrabbit kickstarter advantage growing trend powered technology front end movement expect explosion collaborative economy app startup emerge serve company player uber airbnb offer apis enabling form connectivitylooking year expect software giant sap ibm oracle salesforce offer version corporation replication acquisition learn more body work research report presentation framework post collaborative economy image creative common licencing panama jeremiah owyang silicon valley founder crowd company council linkedin slideshare mail research upcoming recent report infographic growth sharing collaborative economy report sharing buying winning collaborative economy report corporation join collaborative economy slide video risk management guarding gate altimeter report altimeter report paid owned earned converged media popular popular post image diagram list white label private label application rebrand social networking platform community platform conversation shifted future social web eras collection social network stat list social computing strategist community manager enterprise corporation social media job professional list corporate social media strategist corporate community manager printing admin advertising advocacy agency aggregation altimeter analysis analyst api asia augmented reality autonomous world blogger dinner book review breakdown budget business model calendar career case study challenge citizen journalism cmad cmo collaboration collaborative consumption collaborative economy communication community manager community marketing conference management system management system marketing converged media corporate innovation crowd company crowd economy crowdfunding culture curated social data portability data storage digest digital disruption disruption dynamic customer journey ecommerce economy enterprise web entrepreneurism ethic europe event excursion expert sery extranet strategy fansumer faq feedback forbe forrester funding future social web futureproofing gamification generation geo tagging global web google groundswell hitachi hitachi data system identity industry index influence infographic information architecture innovation intelligent web intention web interactive marketing internet interview intranet iptv job job survey leadership legal live video maker movement management marketing mashup matrix media microformat micromedia micromeme middle east mmorpg mobile myspace profit demand move open leadership open research opensocial operationbluewater persona personalization platform podcast podtech politic pollination privacy process reading sampler real time report retail rich media robot roundtable rumination scorecard strategy life security selfdriving car sharing economy silicon valley silicon valley sighting update social analytic social cms social commerce social computing social crm social gaming social graph social inbox aggregator social insight social media social media job social media management system social media measurement social media service social media stat social movement social networking social performance social software suite social strategist social support socialgraphic speech storyboard superbowl supply chain management support sustainable syndication technographic technology travel trend upcoming webinar experience vcs venture capital video virtual event virtual world voice customer voip vrm walkthrough web advertising web analytic web design web industry web law web marketing web strategy web strategy show web team web theory web tool web usage webinar white label social network widget strategy wireless word mouth word mouth marketing linkedin mail slideshare googleplus right reserved web strategy llc research speaking media contact engage science hyperdrivemedia","m_szGeo1":"United States","m_szSourceType":"source_general","m_szSrcUrl":"http://www.web-strategist.com/blog/2014/06/","m_Places":["Paris, France","Tesla","Uk","Mobile","Panama","Silicon Valley","Asia","Europe","Take","Hitachi","Middle East","Reading"],"m_People":["Jeremiah Owyang","Yusuke Kawasaki","Nate Keller","Neelie Kroes","Scott Monty","George Pauwels"],"m_Companies":["Rent The Runway","99designs","Powerpoint","Google","Facebook","Tenet","Uber","Lyft","Taxi","European Commission","Apple","Samsung","Crowd Companies","Digital Innovations","Zipcar","Fico","Yelp","Ebay","American Express","Crowd Company","Amazon","Myspace","Jive","Tenets","Airbnb","Sap","Craigslist","Lending Club","Software Companies","Startups To Emerge To Serve Companies","Ibm","Oracle","Crowd Companies Council","Twitter","Slideshare","Cmo","Community Marketing","Forbes","Hitachi Data Systems","Matrix","Roundtable","Second Life","Venture","Theory","Word Of Mouth","Web Strategy Llc"],"m_BiGrams":["collaborative economy","social media","posted collaborative","social network","community manager","business model","crowd company","economy customer","customer score","crowd funding","research speaking","speaking media","media contact","million dollar","place work","open source","electric vehicle","protest collaborative","sharing economy","uber amex","loyalty point","financial data","idle resource","supply chain","enable company","white label","silicon valley","management system","web strategy"],"m_TriGrams":["posted collaborative economy","collaborative economy customer","economy customer score","protest collaborative economy"],"m_SocialTags":[],"m_Topics":[],"m_Industry":[],"m_Technology":[],"m_BiCnt":[34,9,5,5,4,4,4,4,4,4,3,3,3,3,3,3,3,3,3,3,3,3,3,3,3,3,3,3,3],"m_TriCnt":[5,4,4,3],"m_iDocBodyWordCnt":2002}
