{"m_szDocID":"2042148","m_szDocTitle":"Peter Schiff Scores his Latest Win…","m_szYear":"2016","m_szDocSumamry":"dateText -------------------- Jun 11, 2016  Jun 7, 2016  Jun 6, 2016  textArticle -------------------- Wall Street Daily  All premium content can be found on the Agora Financial website, please  click here to login  and access your paid material.  Home  Innovation  GeoMacro  Special Situations  Contributors  Free Reports  Archives  About Us  Home  Innovation  GeoMacro  Special Situations  Contributors  Free Reports  Archives  About Us  Income Industries  Dividends  Bonds  Foreign Dividends  Real Estate  The Evolution of the Marketplace: From the Mall to the Internet  By    Sarah Adler  -  Jun ","m_szDocBody":"wall street daily premium found agora financial website paid material home innovation geomacro special situation contributor free report archive home innovation geomacro special situation contributor free report archive income industry dividend bond foreign dividend real estate evolution marketplace mall internet sarah adler closer dimension commercial real estate crisis effect great recession retail industry managing editor sarah adler reit avoid leverage reit martin hutchinson price oil fell mlp devastated leaving income investor alternative martin hutchinson discusse real estate reit noting avoid buy real estate coming commercial real estate bust alan gula store closing consolidation curtailing demand retail space wide alan gula examine online shopping affected brickandmortar store foreign dividend country buy duck martin hutchinson challenge facing income investor give verdict country buy avoid dividend investing hunting income bank stock martin hutchinson investor searching income increasingly turning bank bank represent sound investment dividend investing earning slow dividend stock trap martin hutchinson dividend payment secure solid income play found albeit price inflation longterm bond huge trap martin hutchinson incomeoriented investor continue scramble decent yield enticed longterm bond dont yield etf offer investor highyield haven alan gula yield hard find unloved government bond attractive option simple invest them yield executing sleeping beauty strategy martin hutchinson martin hutchinson explain sleeping beauty strategy preserve wealth foreign dividend country buy duck martin hutchinson challenge facing income investor give verdict country buy avoid foreign dividend north young man martin hutchinson income investor diversify holding canadian stock place turn now asia india emerging market martin hutchinson indias potential great madness overlook progress smooth sailing archive archive archive archive technology healthcare pharma security defence emerging market healthcare technology theranos rise fall empire ly david dittman recount storey theranos bloodtesting technology full hole managed acquire billion valuation guard smoke detector cancer internet softbank bet big internet greg miller softbank billion buyout british chip designer arm holding company paid large price acquisition tech innovation forget nintendo gaming stock scorching competition jonathan rodriguez late invest nintendo time invest rising star video gaming war jonathan rodriguez explain biopharma big pharma hunt profit tim maverick profit growth big pharma firm slowing tim maverick uncover hunt growth m&a biotech firm neuroscience electroceutical future medicine tim maverick future doctor treat disease drug instead theyll tiny implantable device communicate body electrical language biotechnology live longer rid zombie cell tim maverick fountain youth age study mayo clinic step forward slowing ageing process cyber security bank heist expose staggering security flaw greg miller recent robbery million central bank bangladesh exposed unbelievably alarming cybersecurity flaw worse cyber security cyber threat digital health tim maverick digital healthcare offer promise future threat lurk cyber attack medical system device stock gun stock buy greg miller recent death supreme court justice antonin scalia obama presidency coming end impact gun industry stock asia asian market surge wake brexit carl delfeld european market continue falter asia burgeoning rising middle class booming consumer market region watch international growing middle class create market carl delfeld international rise middleclass population mean spending emerging market carl delfeld reveal invest china timeless strategy opportunity carl delfeld pinpointing amazing investment opportunity isnt easy feat but carl delfeld explain piece fall perfectly place archive archive archive archive energy agricultural rare tangible asset metal mineral energy membrane technology save world david dittman profile membrane technology compelling innovation desalinate seawater generate power electricity natural gas helium shortage averted tim maverick helium crucial industry making current shortage increasingly worrisome huge tanzania ready change game oil energy saudi arabias solar planning paved oil production tim maverick saudi arabia see future solar power road riches paved oil tim maverick talk mbs middle eastern energy future agriculture agricultural commodity awaken tim maverick agricultural commodity price dump year tim maverick see turnaround sight garnering investor interest agriculture commodity market sweet tooth shelley goldberg commodity market running month sugar high indulge sweet tooth grain investing organic profitable endeavour shelley goldberg shelley goldberg examine move organic farming company profiting handsomely art market overheated art market sizzling shelley goldberg analyst redhot art market finally overheated international investor helping maintain momentum art market art market add beauty portfolio shelley goldberg shelley goldberg explain four reason think sizzling art market continue grow profit art market art market hot hot alan gula fine art market fire worth investing tangible asset part diversified portfolio lithium play small cap lithium boom tim maverick lithium demand soaring tim maverick reveal invest large company small cap rare earth metal china set control crucial metal electric car tim maverick investor rosy expectation tesla firm face cobalt cliff restricting battery production base metal china take gamble commodity tim maverick industrial metal red hot market economic reason archive archive archive archive personal finance portfolio management retirement millennial financing investing children saving future tim maverick cost education increase family save money future children investment young prudent young prudent build relationship money samantha solomon solomon halpern reveal top step changing relationship finance mindful one young prudent young prudent parent dont understand samantha solomon samantha solomon take closer distinct economic difference millennial adulthood past generation asset allocation invest windfall tim maverick windfall what tim maverick unveil game plan smart investing asset allocation investing age stage life tim maverick investing lifelong process tim maverick map phase market interaction monetize moment asset allocation ready half jonathan rodriguez investor faced unpredictable market year jonathan rodriguez offer plan profit rest retirement planning guide iras care sarah adler navigating retirement plan option challenging here offer breakdown pros con iras retirement investing howto investing comfortable retirement tim maverick low interest rate devastating retirement investor seeking income tim maverick offer tip coping retirement planning wild ride retiring bull market tim maverick midst history secondlargest bull market allocate stock secure retirement young prudent young prudent certainty death taxe samantha solomon ahead wall street daily samantha solomon close young prudent recap aspiration young prudent young prudent big spend samantha solomon successfully saving chunk money samantha solomon contemplate making big purchase challenge millennial investing read more spend chris worthington american spend billion book year why pocketing money reading free archive archive archive archive stock technical analysis fundamental analysis alternative investing stock orbital atk opportunity defence contractor david dittman fundamental reason justify recent selloff defence aerospace stock mean significant opportunity investor forecast brexit sector making huge comeback jonathan rodriguez brexit stirred major market pullback jonathan rodriguez perfectly hospitable investment hold over forecast small big profit postbrexit jonathan rodriguez jonathan rodriguez expose soft underbelly large cap stock underline investor profit small cap stock stock market chart charting path investing success jonathan rodriguez day moving average extremely tool investor identify trend profit stock market chart trade simple moving average jonathan rodriguez trader leg turn simple moving average easy powerful tool trading stock equity bottom jonathan rodriguez stock made significant gain week now technical pattern showing downtrend reversal time buy market analysis peter schiff score latest win robert william again peter schiff predicted falsehood rate hike hope and dollar fall robert william offer future crash crise market analysis week wall street daily sarah adler missed wall street daily problem featured week valuation control roe doesnt cut shelley goldberg dupont method take roe level shelley goldberg explain math reveal truth special situation perpetual bond equity disguise shelley goldberg troubled economic time perpetual bond offer refuge shelley goldberg caution jumping investigation special situation investor betterment tim maverick brexit crisis roboadvisor betterment market tim maverick explain option stay linkedin calculating real shelley goldberg full company linkedin crucial understand operating margin calculated shelley goldberg explain archive archive archive archive exchangetraded fund equity fund specialty fund ipos dividend etf dividend cool tim maverick world negative interest rate tim maverick take promising dividend etf etf tripleleveraged etf carry wealth risk alan gula lot leveraged speculation buyer beware etf mutual fund etf carl delfeld special correspondent carl delfeld explain mutual fund versus etf type portfolios suited for mutual fund fund stock carl delfeld carl delfeld break investing beatendown market fund making maximum profit maximum pessimism closedend fund cheap preferred fund perfect low rate alan gula fed push back rate increase now income investor closedend preferred fund mutual fund roboadvisor kill human advisor alan gula here online investment advisory platform roboadvisor crowdfunding closer risk reward crowdfunding tim maverick advent crowdfunding average person invest startup risk tim maverick explain specialty fund lending club trouble show doesnt work martin hutchinson lending club example martin hutchinson explain investor avoid lending closedend fund closedend fund craziness alan gula closedend fund cef price irrational dont follow herd cef inflated premium net asset value ipos twilios ipo hot not louis basenese ipo market struggling mightily upcoming debut tech firm twilio weigh company pros con give verdict ipos twilio spark stronger ipo market louis basenese proved slow ipo market far history show summer month dont necessarily promise same company kickstart upswing ipos square ipo flop good investor louis basenese ipo flop digital payment firm square tech analyst predicting doom future tech ipos here good new tech investor archive archive archive archive true alpha digital fortune shockproof investor trigger point pro instant money trader venturecap strategist extreme alpha currency capital president club gold president club platinum wsd team contact archive ensure delivery frequently asked question broker listing peter schiff score latest win published fri robert william founder now hope youve documentary york time bestselling author peter schiff part documentary offered free copy schiff special edition real crash americas coming bankruptcy worth noting book prediction coming pass skating economic ice thinner mainstream economist imagined peter economy good chance financial prediction follow suit fact investment strategy spectacular year strongly suggest havent time review investment strategy now option table crucial prepare portfolio world politician financial mainstream pretend peter schiff euro pacific capital think differently typical wall street firm adding exposure strategy make huge difference financial wellbeing year come fasten seatbelt end wall street washington stood united belief coming year economy finally emerge clear year weakness federal government federal reserve showered economy unprecedented amount monetary fiscal stimulus trillion dollar form deficit spending percent interest rate quantitative easing supposedly saved economy ruin fact growth time close rate economist normal chalked long list temporary unforeseen manageable problem imported abroad economist imagined cloud lift argued global economy led resurgent united state finally reaping benefit fed bold stimulus experiment move central bank supposedly timid stupid undertake believed economic strength fed muchneeded opportunity finally raise interest rate significantly they remained year draw trillion asset added balance sheet crisis began fed raised rate pace ratetightening cycle concluded rate end assumption powered dollar generational high basket nondollar currency contrast peter schiff predicted smallest rate increase destabilise market rate increase create economic condition prevent additional hike argued great dollar rally based assumption higher rate strong growth dollar fall sharply assumption proved false guess what virtually wrong bumpy ride ahead promised fed raise rate onefourth percentage point rate increase decade confidence inspired hike collapsed immediately then weve continuous deterioration forwardlooking economic statistic percent growth again pipe dream half tracking rate and government ridiculously low inflation claim lucky avoid outright recession time stock market stumbled horribly gate notched worst record written bleeding didnt stop fed finally relented promised slower rate increase further fed continually softened tough talk rate summer virtually conceded theyre ratehiking business foreseeable future peter believe matter time recessionary force compel fed opposite direction additional stimulus expansion balance sheet current level amazingly reality virtually mainstream economist financial advisor consider theyre talking speed bump soft patches weve hit brick wall collision course folk latest wind buffet market arrived england voter defied expectation decided united kingdom european union brexit resulting uncertainty threatened financial market convinced investor fed raise rate time soon fact market pricing higher probability rate cut rate hike current uncertainty however brexit vote global financial system healthy brexit nonevent all decision country million people simply disengage trading bloc disrupt global economy great britain suddenly fall black hole expect strategic trading alliance change meaningful way economy continue function full member event supposed upend prior economic calculation brexit market reaction reveal investor economist priced market perfection outcome unleash panic show fragile market become easily investor confidence shaken stock price record level united state bond selling negative yield europe investment represent good value offer good return printed money forcefed alreadybloated asset bad economic new finally light overbought asset classe face day reckoning however fanfare investment option peter schiff favoured starting heat year alone market average struggled tread water euro pacific strategy investing dollar highvalue dividend commodity stock halfyear recent memory example morningstar peter international fund epivx rose half beating average fund category ranking bestperforming fund fund tracked morningstar foreign large cap category average fund category lost quarter investor peter fund gained absolute term investor peter gold fund epgfx better fund rose staggering half beating average gold fund peter believe strong move payment larger move rankandfile investor finally perceive real risk facing dollar economy good new unwinding carried trade brexit temporallypropped weakening dollar increase attributed dollar safe haven status truth japanese yen stronger dollar hard argue japan safe haven anything leveraged speculator caught major european bank decimated experiencing spectacular decline financial crisis dust settle fundamental reassert quickly dollar head lower brexit providing fed excuse waiting for market begin preparing round monetary stimulus fed reduce rate back negative launching peter predict gamechanger dollar false expectation higher growth interest rate set currency crash wealth protect grow urge call euro pacific capital speak experienced investment advisor speak great detail peter schiff positioning client withstand coming economic reshuffling wall street coming reach addition urge tosubscribe free newsletter weekly digest chockfull peter latest response breaking economic development schiff digest link video interview video blog commentary press coverage uptodate current thinking put knowledge good use action today event nasty habit overtaking unresponsive onward upward robert william addition fulltime trader equity equity derivative robert served lead financial analyst forbe top private corporation analyst institution endowment largest world learn newsletter faq cancel time privacy related article smallcap utility stock flash cash apocalypse pending earth stat cure humanity worst addiction green smoke comment nvootny say peter preaching bad new long sooner later right year remember joe granville remember joe spoke listened well told follower market well went end decade wrong shortly that market crashed predict future reply add comment cancel reply required published mail required published website cancel reply newsletter faq cancel time privacy innovation space travel mar david dittman elon musk falcon exploded launchpad recently minor setback major move made groundbreaking space exploration nasa hopeful sight set mar geomacro presidential election clinton trump science technology david dittman amid muck mire presidential election campaign clinton trump top science technology issue special situation sun hydraulic shattering morass middle management david dittman time end mediocre middlemanagement structure put manpower work valuable position company track for powered ajaxy premium research true alpha venturecap strategist extreme alpha company contributor contact whitelist instruction privacy policy disclaimer syndicate faq learn free report premium research income growth commodity geomacro money trading fund spotlight contact paul baltimore wall street daily llc right reserved","m_szGeo1":"United States","m_szSourceType":"source_general","m_szSrcUrl":"http://www.wallstreetdaily.com/2016/07/08/peter-schiff-u-s-economy-brexit/","m_Places":["United States","Take","Asia","India","Best","Lies","Gun","China","Tanzania","Saudi Arabia","Endeavor","Tesla","America","Wall Street","Washington","England","United Kingdom","Uk","Europe","Japan","Well","Baltimore, Md"],"m_People":["Sarah Adler","Martin Hutchinson","Alan Gula","David Dittman","Greg Miller","Jonathan Rodriguez","Tim Maverick","Antonin Scalia","Carl Delfeld","Shelley Goldberg","Samantha Solomon","Solomon Halpern","Chris Worthington","Peter Schiff","Robert Williams","Louis Basenese","Morningstar, Peter","Joe Granville","Elon Musk"],"m_Companies":["Wall Street Daily","Agora","Income Industries","Bust","Arm Holdings","Nintendo","Mayo Clinic","Security Bank","Central Bank Of Bangladesh","Supreme Court","Timeless","Energy Futures","Overheated Art","Iras","Bull","Orbital","Path","Dupont","Linkedin","Real","Equity Funds","Lending Club","Twilio","New York Times","United","U.s. Federal Government","Central Banks","Guess","European Union","Bloc","Alliances","Eu","Value Fund","Morningstar","European Banks","Forbes","Nasa","Manpower"],"m_BiGrams":["tim maverick","martin hutchinson","shelley goldberg","jonathan rodriguez","carl delfeld","art market","young prudent","wall street","alan gula","peter schiff","samantha solomon","david dittman","street daily","special situation","real estate","income investor","interest rate","rate increase","foreign dividend","sarah adler","country buy","prudent young","robert william","mutual fund","closedend fund","free report","give verdict","emerging market","greg miller","goldberg explain","small cap","asset allocation","moving average","louis basenese","ipo market","euro pacific"],"m_TriGrams":["wall street daily"],"m_SocialTags":[],"m_Topics":[],"m_Industry":[],"m_Technology":[],"m_BiCnt":[28,13,12,11,9,9,9,8,8,8,7,6,5,5,5,5,5,5,4,4,4,4,4,4,4,3,3,3,3,3,3,3,3,3,3,3],"m_TriCnt":[5],"m_iDocBodyWordCnt":2462}
