{"m_szDocID":"2042183","m_szDocTitle":"Gun Control: The Best Stocks Amid Fears of More Regulation","m_szYear":"2016","m_szDocSumamry":"dateText -------------------- Jun 11, 2016  Jun 7, 2016  Jun 6, 2016  textArticle -------------------- Wall Street Daily  All premium content can be found on the Agora Financial website, please  click here to login  and access your paid material.  Home  Innovation  GeoMacro  Special Situations  Contributors  Free Reports  Archives  About Us  Home  Innovation  GeoMacro  Special Situations  Contributors  Free Reports  Archives  About Us  Income Industries  Dividends  Bonds  Foreign Dividends  Real Estate  The Evolution of the Marketplace: From the Mall to the Internet  By    Sarah Adler  -  Jun ","m_szDocBody":"wall street daily premium found agora financial website paid material home innovation geomacro special situation contributor free report archive home innovation geomacro special situation contributor free report archive income industry dividend bond foreign dividend real estate evolution marketplace mall internet sarah adler closer dimension commercial real estate crisis effect great recession retail industry managing editor sarah adler reit avoid leverage reit martin hutchinson price oil fell mlp devastated leaving income investor alternative martin hutchinson discusse real estate reit noting avoid buy real estate coming commercial real estate bust alan gula store closing consolidation curtailing demand retail space wide alan gula examine online shopping affected brickandmortar store foreign dividend country buy duck martin hutchinson challenge facing income investor give verdict country buy avoid dividend investing hunting income bank stock martin hutchinson investor searching income increasingly turning bank bank represent sound investment dividend investing earning slow dividend stock trap martin hutchinson dividend payment secure solid income play found albeit price inflation longterm bond huge trap martin hutchinson incomeoriented investor continue scramble decent yield enticed longterm bond dont yield etf offer investor highyield haven alan gula yield hard find unloved government bond attractive option simple invest them yield executing sleeping beauty strategy martin hutchinson martin hutchinson explain sleeping beauty strategy preserve wealth foreign dividend country buy duck martin hutchinson challenge facing income investor give verdict country buy avoid foreign dividend north young man martin hutchinson income investor diversify holding canadian stock place turn now asia india emerging market martin hutchinson indias potential great madness overlook progress smooth sailing archive archive archive archive technology healthcare pharma security defence emerging market healthcare technology theranos rise fall empire ly david dittman recount storey theranos bloodtesting technology full hole managed acquire billion valuation guard smoke detector cancer internet softbank bet big internet greg miller softbank billion buyout british chip designer arm holding company paid large price acquisition tech innovation forget nintendo gaming stock scorching competition jonathan rodriguez late invest nintendo time invest rising star video gaming war jonathan rodriguez explain biopharma big pharma hunt profit tim maverick profit growth big pharma firm slowing tim maverick uncover hunt growth m&a biotech firm neuroscience electroceutical future medicine tim maverick future doctor treat disease drug instead theyll tiny implantable device communicate body electrical language biotechnology live longer rid zombie cell tim maverick fountain youth age study mayo clinic step forward slowing ageing process cyber security bank heist expose staggering security flaw greg miller recent robbery million central bank bangladesh exposed unbelievably alarming cybersecurity flaw worse cyber security cyber threat digital health tim maverick digital healthcare offer promise future threat lurk cyber attack medical system device stock gun stock buy greg miller recent death supreme court justice antonin scalia obama presidency coming end impact gun industry stock asia asian market surge wake brexit carl delfeld european market continue falter asia burgeoning rising middle class booming consumer market region watch international growing middle class create market carl delfeld international rise middleclass population mean spending emerging market carl delfeld reveal invest china timeless strategy opportunity carl delfeld pinpointing amazing investment opportunity isnt easy feat but carl delfeld explain piece fall perfectly place archive archive archive archive energy agricultural rare tangible asset metal mineral energy membrane technology save world david dittman profile membrane technology compelling innovation desalinate seawater generate power electricity natural gas helium shortage averted tim maverick helium crucial industry making current shortage increasingly worrisome huge tanzania ready change game oil energy saudi arabias solar planning paved oil production tim maverick saudi arabia see future solar power road riches paved oil tim maverick talk mbs middle eastern energy future agriculture agricultural commodity awaken tim maverick agricultural commodity price dump year tim maverick see turnaround sight garnering investor interest agriculture commodity market sweet tooth shelley goldberg commodity market running month sugar high indulge sweet tooth grain investing organic profitable endeavour shelley goldberg shelley goldberg examine move organic farming company profiting handsomely art market overheated art market sizzling shelley goldberg analyst redhot art market finally overheated international investor helping maintain momentum art market art market add beauty portfolio shelley goldberg shelley goldberg explain four reason think sizzling art market continue grow profit art market art market hot hot alan gula fine art market fire worth investing tangible asset part diversified portfolio lithium play small cap lithium boom tim maverick lithium demand soaring tim maverick reveal invest large company small cap rare earth metal china set control crucial metal electric car tim maverick investor rosy expectation tesla firm face cobalt cliff restricting battery production base metal china take gamble commodity tim maverick industrial metal red hot market economic reason archive archive archive archive personal finance portfolio management retirement millennial financing investing children saving future tim maverick cost education increase family save money future children investment young prudent young prudent build relationship money samantha solomon solomon halpern reveal top step changing relationship finance mindful one young prudent young prudent parent dont understand samantha solomon samantha solomon take closer distinct economic difference millennial adulthood past generation asset allocation invest windfall tim maverick windfall what tim maverick unveil game plan smart investing asset allocation investing age stage life tim maverick investing lifelong process tim maverick map phase market interaction monetize moment asset allocation ready half jonathan rodriguez investor faced unpredictable market year jonathan rodriguez offer plan profit rest retirement planning guide iras care sarah adler navigating retirement plan option challenging here offer breakdown pros con iras retirement investing howto investing comfortable retirement tim maverick low interest rate devastating retirement investor seeking income tim maverick offer tip coping retirement planning wild ride retiring bull market tim maverick midst history secondlargest bull market allocate stock secure retirement young prudent young prudent certainty death taxe samantha solomon ahead wall street daily samantha solomon close young prudent recap aspiration young prudent young prudent big spend samantha solomon successfully saving chunk money samantha solomon contemplate making big purchase challenge millennial investing read more spend chris worthington american spend billion book year why pocketing money reading free archive archive archive archive stock technical analysis fundamental analysis alternative investing stock orbital atk opportunity defence contractor david dittman fundamental reason justify recent selloff defence aerospace stock mean significant opportunity investor forecast brexit sector making huge comeback jonathan rodriguez brexit stirred major market pullback jonathan rodriguez perfectly hospitable investment hold over forecast small big profit postbrexit jonathan rodriguez jonathan rodriguez expose soft underbelly large cap stock underline investor profit small cap stock stock market chart charting path investing success jonathan rodriguez day moving average extremely tool investor identify trend profit stock market chart trade simple moving average jonathan rodriguez trader leg turn simple moving average easy powerful tool trading stock equity bottom jonathan rodriguez stock made significant gain week now technical pattern showing downtrend reversal time buy market analysis peter schiff score latest win robert william again peter schiff predicted falsehood rate hike hope and dollar fall robert william offer future crash crise market analysis week wall street daily sarah adler missed wall street daily problem featured week valuation control roe doesnt cut shelley goldberg dupont method take roe level shelley goldberg explain math reveal truth special situation perpetual bond equity disguise shelley goldberg troubled economic time perpetual bond offer refuge shelley goldberg caution jumping investigation special situation investor betterment tim maverick brexit crisis roboadvisor betterment market tim maverick explain option stay linkedin calculating real shelley goldberg full company linkedin crucial understand operating margin calculated shelley goldberg explain archive archive archive archive exchangetraded fund equity fund specialty fund ipos dividend etf dividend cool tim maverick world negative interest rate tim maverick take promising dividend etf etf tripleleveraged etf carry wealth risk alan gula lot leveraged speculation buyer beware etf mutual fund etf carl delfeld special correspondent carl delfeld explain mutual fund versus etf type portfolios suited for mutual fund fund stock carl delfeld carl delfeld break investing beatendown market fund making maximum profit maximum pessimism closedend fund cheap preferred fund perfect low rate alan gula fed push back rate increase now income investor closedend preferred fund mutual fund roboadvisor kill human advisor alan gula here online investment advisory platform roboadvisor crowdfunding closer risk reward crowdfunding tim maverick advent crowdfunding average person invest startup risk tim maverick explain specialty fund lending club trouble show doesnt work martin hutchinson lending club example martin hutchinson explain investor avoid lending closedend fund closedend fund craziness alan gula closedend fund cef price irrational dont follow herd cef inflated premium net asset value ipos twilios ipo hot not louis basenese ipo market struggling mightily upcoming debut tech firm twilio weigh company pros con give verdict ipos twilio spark stronger ipo market louis basenese proved slow ipo market far history show summer month dont necessarily promise same company kickstart upswing ipos square ipo flop good investor louis basenese ipo flop digital payment firm square tech analyst predicting doom future tech ipos here good new tech investor archive archive archive archive true alpha digital fortune shockproof investor trigger point pro instant money trader venturecap strategist extreme alpha currency capital president club gold president club platinum wsd team contact archive ensure delivery frequently asked question broker listing gun stock buy published thu greg miller senior analyst completely intention president obama proven greatest gun salesman american history presidency fear gun control regulation gun sale soaring occasion turn share gun manufacturer gunrelated stock risen sharply too early january obama announced executive order aimed tightening gun regulation spate mass shooting announcement triggered price spike like smith wesson holding corp swhc however ability unilaterally impose gun control regulation highly limited virtually chance gun law amendmentfriendly congress recent death supreme court justice antonin scalia offer chance shift term debate significantly scalias death boost gun sale secret scalia passionate persuasive defender constitution including amendment famous heller case declared amendment protect individual possess firearm unconnected service militia firearm traditionally lawful purpose selfdefense home supreme court spoken clarity amendment now scalia gone replacement ardent defender scalias reading amendment uncertainty meantime proven bullish gunrelated stock scalias death share stock classic case buy rumour sell new stock play rising gun industry trend gun stock performed extremely obama administration theyve tended trade peak hit shortly politicalinspired spike dealer ordered stock struggled sell bloated inventory obamas term coming end great inadvertent gun salesman retiring presidential candidate republican pretty gunfriendly bernie sander democratic side hillary clinton gunfriendly kind hysteria accompanied obama administration continue clinton presidency secular trend helping gun industry example millennial embracing shooting sport college school instituting gun club student attracted sport inclusiveness safety relative contact sport national shooting sport foundation number sport shooter united state increased million million affecting gunrelated stock let briefly shown chart above smith wesson holding corporation swhc smith wesson renowned gun industry company bankrupt disastrous deal clinton administration triggered consumer boycott today though smith wesson enjoyed annual revenue growth past year decline year excess inventory pureplay gun stock sell gun ammunition related enforcement accessory handcuff training academy police department sport shooting gun tend expensive hunting home defence company benefit demand higherend gun doesnt manufacture ammunition line shotgun key beneficiary increase sport shooting sturm ruger rgr pureplay sturm ruger sell firearm ruger name smith wesson handgun dominate company sale lack ammunition division shotgun offering company offer good potential investor smith wesson handily outperformed sturm ruger year trade half sturm valuation youre pureplay exposure firearm market separate growth shooting sport smith wesson stock choose diversified play vista outdoor inc vsto vista player firearm market spun alliant techsystem early year vista make federal premium line ammunition savage arm long gun firearm ammunition represent sale percentage decline company busy acquiring outdoorrelated company bushnell optical product bell recreational helmet camelbak water storage olin corp oln olin corp make winchester ammunition licence however company invested heavily businesse primarily chlorinerelated chemical product company sale firearmsrelated chlorine business big trouble now turnaround bring good reward chemical investor youre play firearm youre company winner ultimately vista firearm play reason shooting sport activity ammunitionintensive hunting selfdefense application company firearm focused area smith wesson sturm particular vista line highend shotgun tailored clay skeet trap shooting diversification vistas acquisition outdoorrelated businesse give strategic relation big box outdoor retailer cabelas bass pro shop increasing share outdoor product business including firearm vistas firearm business make half sale business larger smith wesson sturm combined make plenty sense vista cash generated firearm business good year expand nonfirearm offering riding coattail cabelas bass smarter too chasing fear gun regulation company take longerterm outdoor sport general mind firearm market isnt large plus cyclical fairly highly fragmented play gun owner fear time fear subside little taking share price them concern gun owner nottoodistant future living investing future greg miller greg miller spent year financial industry working analyst portfolio manager eventually institutional investor managed million worth asset mutual fund private account learn newsletter faq cancel time privacy related article presidential election clinton trump science technology bcorporation profit social responsibility global war global warming orbital atk opportunity defence contractor comment spencer say catalogue publish this ruger branded ammunition made red label shotgun year now lastly forgot licencing ruger airgun manufacturer reply walt reply red label production listed website catalogue lasted year redesign ruger offering arx ammo made polycase arent ammo manufacturing compared remington reply troy scott say opinion durability synthetic outweigh appearance wood reply marty say spencer correct ruger red label outstanding shotgun owned year reply walt reply red label production listed website catalogue lasted year redesign reply rick pasek say wall streetthis govwanting gun rightsbecause full control everythingand gun right big timeagain full control protectting selfsbecause world crazyand pick good people gun cpllicenceand member wall street daily rick pasekand robert william homework research good lou also reply howard say bernie sander socialist anti gun commie gun friendly scenario stated ban defensive firearm handgun home defence shotgun research claiming gun friendly reply wayne lapierre say true howard wayne lapierre publicly stated problem bernie sander research claiming gun friendly entitled opinion fact reply add comment cancel reply required published mail required published website cancel reply newsletter faq cancel time privacy innovation space travel mar david dittman elon musk falcon exploded launchpad recently minor setback major move made groundbreaking space exploration nasa hopeful sight set mar geomacro presidential election clinton trump science technology david dittman amid muck mire presidential election campaign clinton trump top science technology issue special situation sun hydraulic shattering morass middle management david dittman time end mediocre middlemanagement structure put manpower work valuable position company track for powered ajaxy premium research true alpha venturecap strategist extreme alpha company contributor contact whitelist instruction privacy policy disclaimer syndicate faq learn free report premium research income growth commodity geomacro money trading fund spotlight contact paul baltimore wall street daily llc right reserved","m_szGeo1":"United States","m_szSourceType":"source_general","m_szSrcUrl":"http://www.wallstreetdaily.com/2016/03/03/gun-control-stocks/","m_Places":["United States","Take","Asia","India","Best","Lies","Gun","China","Tanzania","Saudi Arabia","Endeavor","Tesla","Wesson","Winner","Wall Street","Baltimore, Md"],"m_People":["Sarah Adler","Martin Hutchinson","Alan Gula","David Dittman","Greg Miller","Jonathan Rodriguez","Tim Maverick","Antonin Scalia","Carl Delfeld","Shelley Goldberg","Samantha Solomon","Solomon Halpern","Chris Worthington","Peter Schiff","Robert Williams","Will Scalia","Louis Basenese","Barack Obama","Bernie Sanders","Hillary Rodham Clinton","Troy Scott","Rick Pasek","Wayne Lapierre","Elon Musk"],"m_Companies":["Wall Street Daily","Agora","Income Industries","Bust","Arm Holdings","Nintendo","Mayo Clinic","Security Bank","Central Bank Of Bangladesh","Supreme Court","Timeless","Energy Futures","Overheated Art","Iras","Bull","Orbital","Path","Dupont","Linkedin","Real","Equity Funds","Lending Club","Twilio","Holding Corp.","Congress","U.s. Supreme Court","Obama Administration","National Shooting Sports Foundation","Smith & Wesson Holding Corporation","Clinton Administration","Vista Outdoors Inc.","Vista","Alliant Techsystems","Related Companies","Olin Corp","Bass Pro","Does Indeed Have","Nasa","Manpower"],"m_BiGrams":["tim maverick","martin hutchinson","shelley goldberg","jonathan rodriguez","carl delfeld","art market","young prudent","smith wesson","alan gula","samantha solomon","wall street","street daily","david dittman","greg miller","special situation","real estate","income investor","mutual fund","foreign dividend","sarah adler","country buy","gun stock","gun industry","prudent young","closedend fund","shooting sport","red label","free report","give verdict","emerging market","supreme court","goldberg explain","small cap","asset allocation","moving average","robert william","louis basenese","ipo market","gunrelated stock","bernie sander","sturm ruger","firearm market","presidential election","clinton trump","science technology","gun friendly"],"m_TriGrams":["wall street daily"],"m_SocialTags":[],"m_Topics":[],"m_Industry":[],"m_Technology":[],"m_BiCnt":[28,13,12,11,9,9,9,9,8,7,6,6,6,6,5,5,5,5,4,4,4,4,4,4,4,4,4,3,3,3,3,3,3,3,3,3,3,3,3,3,3,3,3,3,3,3],"m_TriCnt":[6],"m_iDocBodyWordCnt":2424}
