{"m_szDocID":"2042196","m_szDocTitle":"Canada Dividends: Boost Your Income North of the Border","m_szYear":"2016","m_szDocSumamry":"dateText -------------------- Jun 11, 2016  Jun 7, 2016  Jun 6, 2016  textArticle -------------------- Wall Street Daily  All premium content can be found on the Agora Financial website, please  click here to login  and access your paid material.  Home  Innovation  GeoMacro  Special Situations  Contributors  Free Reports  Archives  About Us  Home  Innovation  GeoMacro  Special Situations  Contributors  Free Reports  Archives  About Us  Income Industries  Dividends  Bonds  Foreign Dividends  Real Estate  The Evolution of the Marketplace: From the Mall to the Internet  By    Sarah Adler  -  Jun ","m_szDocBody":"wall street daily premium found agora financial website paid material home innovation geomacro special situation contributor free report archive home innovation geomacro special situation contributor free report archive income industry dividend bond foreign dividend real estate evolution marketplace mall internet sarah adler closer dimension commercial real estate crisis effect great recession retail industry managing editor sarah adler reit avoid leverage reit martin hutchinson price oil fell mlp devastated leaving income investor alternative martin hutchinson discusse real estate reit noting avoid buy real estate coming commercial real estate bust alan gula store closing consolidation curtailing demand retail space wide alan gula examine online shopping affected brickandmortar store foreign dividend country buy duck martin hutchinson challenge facing income investor give verdict country buy avoid dividend investing hunting income bank stock martin hutchinson investor searching income increasingly turning bank bank represent sound investment dividend investing earning slow dividend stock trap martin hutchinson dividend payment secure solid income play found albeit price inflation longterm bond huge trap martin hutchinson incomeoriented investor continue scramble decent yield enticed longterm bond dont yield etf offer investor highyield haven alan gula yield hard find unloved government bond attractive option simple invest them yield executing sleeping beauty strategy martin hutchinson martin hutchinson explain sleeping beauty strategy preserve wealth foreign dividend country buy duck martin hutchinson challenge facing income investor give verdict country buy avoid foreign dividend north young man martin hutchinson income investor diversify holding canadian stock place turn now asia india emerging market martin hutchinson indias potential great madness overlook progress smooth sailing archive archive archive archive technology healthcare pharma security defence emerging market healthcare technology theranos rise fall empire ly david dittman recount storey theranos bloodtesting technology full hole managed acquire billion valuation guard smoke detector cancer internet softbank bet big internet greg miller softbank billion buyout british chip designer arm holding company paid large price acquisition tech innovation forget nintendo gaming stock scorching competition jonathan rodriguez late invest nintendo time invest rising star video gaming war jonathan rodriguez explain biopharma big pharma hunt profit tim maverick profit growth big pharma firm slowing tim maverick uncover hunt growth m&a biotech firm neuroscience electroceutical future medicine tim maverick future doctor treat disease drug instead theyll tiny implantable device communicate body electrical language biotechnology live longer rid zombie cell tim maverick fountain youth age study mayo clinic step forward slowing ageing process cyber security bank heist expose staggering security flaw greg miller recent robbery million central bank bangladesh exposed unbelievably alarming cybersecurity flaw worse cyber security cyber threat digital health tim maverick digital healthcare offer promise future threat lurk cyber attack medical system device stock gun stock buy greg miller recent death supreme court justice antonin scalia obama presidency coming end impact gun industry stock asia asian market surge wake brexit carl delfeld european market continue falter asia burgeoning rising middle class booming consumer market region watch international growing middle class create market carl delfeld international rise middleclass population mean spending emerging market carl delfeld reveal invest china timeless strategy opportunity carl delfeld pinpointing amazing investment opportunity isnt easy feat but carl delfeld explain piece fall perfectly place archive archive archive archive energy agricultural rare tangible asset metal mineral energy membrane technology save world david dittman profile membrane technology compelling innovation desalinate seawater generate power electricity natural gas helium shortage averted tim maverick helium crucial industry making current shortage increasingly worrisome huge tanzania ready change game oil energy saudi arabias solar planning paved oil production tim maverick saudi arabia see future solar power road riches paved oil tim maverick talk mbs middle eastern energy future agriculture agricultural commodity awaken tim maverick agricultural commodity price dump year tim maverick see turnaround sight garnering investor interest agriculture commodity market sweet tooth shelley goldberg commodity market running month sugar high indulge sweet tooth grain investing organic profitable endeavour shelley goldberg shelley goldberg examine move organic farming company profiting handsomely art market overheated art market sizzling shelley goldberg analyst redhot art market finally overheated international investor helping maintain momentum art market art market add beauty portfolio shelley goldberg shelley goldberg explain four reason think sizzling art market continue grow profit art market art market hot hot alan gula fine art market fire worth investing tangible asset part diversified portfolio lithium play small cap lithium boom tim maverick lithium demand soaring tim maverick reveal invest large company small cap rare earth metal china set control crucial metal electric car tim maverick investor rosy expectation tesla firm face cobalt cliff restricting battery production base metal china take gamble commodity tim maverick industrial metal red hot market economic reason archive archive archive archive personal finance portfolio management retirement millennial financing investing children saving future tim maverick cost education increase family save money future children investment young prudent young prudent build relationship money samantha solomon solomon halpern reveal top step changing relationship finance mindful one young prudent young prudent parent dont understand samantha solomon samantha solomon take closer distinct economic difference millennial adulthood past generation asset allocation invest windfall tim maverick windfall what tim maverick unveil game plan smart investing asset allocation investing age stage life tim maverick investing lifelong process tim maverick map phase market interaction monetize moment asset allocation ready half jonathan rodriguez investor faced unpredictable market year jonathan rodriguez offer plan profit rest retirement planning guide iras care sarah adler navigating retirement plan option challenging here offer breakdown pros con iras retirement investing howto investing comfortable retirement tim maverick low interest rate devastating retirement investor seeking income tim maverick offer tip coping retirement planning wild ride retiring bull market tim maverick midst history secondlargest bull market allocate stock secure retirement young prudent young prudent certainty death taxe samantha solomon ahead wall street daily samantha solomon close young prudent recap aspiration young prudent young prudent big spend samantha solomon successfully saving chunk money samantha solomon contemplate making big purchase challenge millennial investing read more spend chris worthington american spend billion book year why pocketing money reading free archive archive archive archive stock technical analysis fundamental analysis alternative investing stock orbital atk opportunity defence contractor david dittman fundamental reason justify recent selloff defence aerospace stock mean significant opportunity investor forecast brexit sector making huge comeback jonathan rodriguez brexit stirred major market pullback jonathan rodriguez perfectly hospitable investment hold over forecast small big profit postbrexit jonathan rodriguez jonathan rodriguez expose soft underbelly large cap stock underline investor profit small cap stock stock market chart charting path investing success jonathan rodriguez day moving average extremely tool investor identify trend profit stock market chart trade simple moving average jonathan rodriguez trader leg turn simple moving average easy powerful tool trading stock equity bottom jonathan rodriguez stock made significant gain week now technical pattern showing downtrend reversal time buy market analysis peter schiff score latest win robert william again peter schiff predicted falsehood rate hike hope and dollar fall robert william offer future crash crise market analysis week wall street daily sarah adler missed wall street daily problem featured week valuation control roe doesnt cut shelley goldberg dupont method take roe level shelley goldberg explain math reveal truth special situation perpetual bond equity disguise shelley goldberg troubled economic time perpetual bond offer refuge shelley goldberg caution jumping investigation special situation investor betterment tim maverick brexit crisis roboadvisor betterment market tim maverick explain option stay linkedin calculating real shelley goldberg full company linkedin crucial understand operating margin calculated shelley goldberg explain archive archive archive archive exchangetraded fund equity fund specialty fund ipos dividend etf dividend cool tim maverick world negative interest rate tim maverick take promising dividend etf etf tripleleveraged etf carry wealth risk alan gula lot leveraged speculation buyer beware etf mutual fund etf carl delfeld special correspondent carl delfeld explain mutual fund versus etf type portfolios suited for mutual fund fund stock carl delfeld carl delfeld break investing beatendown market fund making maximum profit maximum pessimism closedend fund cheap preferred fund perfect low rate alan gula fed push back rate increase now income investor closedend preferred fund mutual fund roboadvisor kill human advisor alan gula here online investment advisory platform roboadvisor crowdfunding closer risk reward crowdfunding tim maverick advent crowdfunding average person invest startup risk tim maverick explain specialty fund lending club trouble show doesnt work martin hutchinson lending club example martin hutchinson explain investor avoid lending closedend fund closedend fund craziness alan gula closedend fund cef price irrational dont follow herd cef inflated premium net asset value ipos twilios ipo hot not louis basenese ipo market struggling mightily upcoming debut tech firm twilio weigh company pros con give verdict ipos twilio spark stronger ipo market louis basenese proved slow ipo market far history show summer month dont necessarily promise same company kickstart upswing ipos square ipo flop good investor louis basenese ipo flop digital payment firm square tech analyst predicting doom future tech ipos here good new tech investor archive archive archive archive true alpha digital fortune shockproof investor trigger point pro instant money trader venturecap strategist extreme alpha currency capital president club gold president club platinum wsd team contact archive ensure delivery frequently asked question broker listing north young man published tue martin hutchinson senior analyst income investor worried direction stock peek north border overall canada highly stable economy track record united state recent year indeed canadas political economic risk modest youve watching primary currently composite index trading trailing pricetoearning ratio time compared s&p indexs time top that canadian economy benefit recent recovery mineral price thus good time explore canadian company make sense dividend investor diversification risk financial crisis canada generally pursued sound policy united state suffered result reason canadian bank undertook moderate amount bigticket investment banking regulated bank canadian budget policy profligate budget close balance policy resulted conservative government stephen harper finance minister jimflaherty interest rate low dropped zero canadian corra shortterm rate bad new harper lost election september replaced justin trudeau liberal government committed usual keynesian expansion wasteful spending election trudeau promised resulting budget deficit billion projected deficit year starting billion stimulus set announced fair decline oil price hit canadas budget receipt trudeaus fault still canadian budget deficit watched closely public debt around gdp lower figure ultimately canada run excessive budget deficit year recovery resource price economy rebound thus canadian income stock give income investor benefit diversification lot risk bank worth noting dividend withholding tax problem income investor buying foreign stock canada impose withholding tax which offset tax however canada provision tax treaty exempt dividend ira canadian withholding tax account canadian dividend essentially treated dividend finally company pay dividend canadian dollar broker exchange automatically currency now let canadian company juicy yield dont eating seed corn risk highyielding company potash corporation saskatchewan inc pot world largest producer potash fertiliser operate segment potash nitrogen phosphate land holding involve acre saskatchewan brunswick pot invest potash producer jordan chile potash earning totaled share guidance share based depressed potash price company recently reduced quarterly dividend share preserve credit rating however lower dividend rate yield trading time trader estimate earning potash business increasing world population place continual pressure food production encourage fertiliser usage inter pipeline limited ipplf midstream company carrying petroleum transportation natural gas liquid extraction natural gas storage businesse canada europe inter reported net income million previous year share obviously hasnt adversely affected decline oil price company pay monthly dividend share isnt covered earning amply covered cash flow yielding offer excellent combination attractive yield good security finally trading time trader estimate earning national bank canada ntiof sixthlargest bank canada operation focused primarily province quebec brunswick quarter yearend bank reported net income million million excluding writeoff disposed businesse bank pay quarterly dividend yielding trading reasonable time trader estimate earning year strongly mediumsized bank sector sweet spot large efficient modern largest behemoth tempted risky investment banking canadian dollar bargainpriced versus dollar now good time income investor make purchase north border good investing martin hutchinson year martin hutchinson international merchant banker london york zagreb ran derivative platform european bank serving director spanish venture capital company advisor korean company sunkyong chairman modular building company learn newsletter faq cancel time privacy related article smallcap utility stock flash cash orbital atk opportunity defence contractor apocalypse pending earth sun hydraulic shattering morass middle management comment allen novotny say read publish however havent noticed obvious stock pay wonderful dividend month hpi hps paid great recession block share smiling bank allen reply brian quinn say agree comment current previous canadian government respect departed finance minister jim flaherty correction reply wall street daily research reply brian reading error noticed corrected reply add comment cancel reply required published mail required published website cancel reply newsletter faq cancel time privacy innovation space travel mar david dittman elon musk falcon exploded launchpad recently minor setback major move made groundbreaking space exploration nasa hopeful sight set mar geomacro presidential election clinton trump science technology david dittman amid muck mire presidential election campaign clinton trump top science technology issue special situation sun hydraulic shattering morass middle management david dittman time end mediocre middlemanagement structure put manpower work valuable position company track for powered ajaxy premium research true alpha venturecap strategist extreme alpha company contributor contact whitelist instruction privacy policy disclaimer syndicate faq learn free report premium research income growth commodity geomacro money trading fund spotlight contact paul baltimore wall street daily llc right reserved","m_szGeo1":"United States","m_szSourceType":"source_general","m_szSrcUrl":"http://www.wallstreetdaily.com/2016/03/01/canada-dividend-investing/","m_Places":["United States","Take","Asia","India","Best","Lies","Gun","China","Tanzania","Saudi Arabia","Endeavor","Tesla","Canada","Harper","Saskatchewan","New Brunswick","Jordan","Chile","Europe","Quebec","London, New York","Zagreb","Baltimore, Md"],"m_People":["Sarah Adler","Martin Hutchinson","Alan Gula","David Dittman","Greg Miller","Jonathan Rodriguez","Tim Maverick","Antonin Scalia","Carl Delfeld","Shelley Goldberg","Samantha Solomon","Solomon Halpern","In A United States Ira","Chris Worthington","Peter Schiff","Robert Williams","Louis Basenese","Stephen Harper","Jim Flaherty","Justin Trudeau","Allen Novotny","Brian Quinn","Elon Musk"],"m_Companies":["Wall Street Daily","Agora","Income Industries","Bust","Arm Holdings","Nintendo","Mayo Clinic","Security Bank","Central Bank Of Bangladesh","Supreme Court","Timeless","Energy Futures","Overheated Art","Iras","Bull","Orbital","Path","Dupont","Linkedin","Real","Equity Funds","Lending Club","Twilio","Indeed","Canadian Banks","Trudeau","Potash Corporation","Saskatchewan Inc.","Inter Pipeline Limited","National Bank Of Canada","European Banks","Wall Street Daily Research","Nasa","Manpower"],"m_BiGrams":["tim maverick","martin hutchinson","shelley goldberg","jonathan rodriguez","income investor","carl delfeld","art market","young prudent","alan gula","samantha solomon","wall street","street daily","david dittman","special situation","real estate","foreign dividend","sarah adler","country buy","prudent young","mutual fund","closedend fund","free report","give verdict","emerging market","greg miller","natural gas","goldberg explain","small cap","asset allocation","interest rate","moving average","louis basenese","ipo market","budget deficit","withholding tax","time trader","trader estimate","estimate earning"],"m_TriGrams":["wall street daily","time trader estimate","trader estimate earning"],"m_SocialTags":[],"m_Topics":[],"m_Industry":[],"m_Technology":[],"m_BiCnt":[28,16,12,11,9,9,9,9,8,7,6,6,6,5,5,4,4,4,4,4,4,3,3,3,3,3,3,3,3,3,3,3,3,3,3,3,3,3],"m_TriCnt":[6,3,3],"m_iDocBodyWordCnt":2198}
