{"m_szDocID":"2042144","m_szDocTitle":"How to Take Control When ROE Just Doesn’t Cut It","m_szYear":"2016","m_szDocSumamry":"dateText -------------------- Jun 11, 2016  Jun 7, 2016  Jun 6, 2016  textArticle -------------------- Wall Street Daily  All premium content can be found on the Agora Financial website, please  click here to login  and access your paid material.  Home  Innovation  GeoMacro  Special Situations  Contributors  Free Reports  Archives  About Us  Home  Innovation  GeoMacro  Special Situations  Contributors  Free Reports  Archives  About Us  Income Industries  Dividends  Bonds  Foreign Dividends  Real Estate  The Evolution of the Marketplace: From the Mall to the Internet  By    Sarah Adler  -  Jun ","m_szDocBody":"wall street daily premium found agora financial website paid material home innovation geomacro special situation contributor free report archive home innovation geomacro special situation contributor free report archive income industry dividend bond foreign dividend real estate evolution marketplace mall internet sarah adler closer dimension commercial real estate crisis effect great recession retail industry managing editor sarah adler reit avoid leverage reit martin hutchinson price oil fell mlp devastated leaving income investor alternative martin hutchinson discusse real estate reit noting avoid buy real estate coming commercial real estate bust alan gula store closing consolidation curtailing demand retail space wide alan gula examine online shopping affected brickandmortar store foreign dividend country buy duck martin hutchinson challenge facing income investor give verdict country buy avoid dividend investing hunting income bank stock martin hutchinson investor searching income increasingly turning bank bank represent sound investment dividend investing earning slow dividend stock trap martin hutchinson dividend payment secure solid income play found albeit price inflation longterm bond huge trap martin hutchinson incomeoriented investor continue scramble decent yield enticed longterm bond dont yield etf offer investor highyield haven alan gula yield hard find unloved government bond attractive option simple invest them yield executing sleeping beauty strategy martin hutchinson martin hutchinson explain sleeping beauty strategy preserve wealth foreign dividend country buy duck martin hutchinson challenge facing income investor give verdict country buy avoid foreign dividend north young man martin hutchinson income investor diversify holding canadian stock place turn now asia india emerging market martin hutchinson indias potential great madness overlook progress smooth sailing archive archive archive archive technology healthcare pharma security defence emerging market healthcare technology theranos rise fall empire ly david dittman recount storey theranos bloodtesting technology full hole managed acquire billion valuation guard smoke detector cancer internet softbank bet big internet greg miller softbank billion buyout british chip designer arm holding company paid large price acquisition tech innovation forget nintendo gaming stock scorching competition jonathan rodriguez late invest nintendo time invest rising star video gaming war jonathan rodriguez explain biopharma big pharma hunt profit tim maverick profit growth big pharma firm slowing tim maverick uncover hunt growth m&a biotech firm neuroscience electroceutical future medicine tim maverick future doctor treat disease drug instead theyll tiny implantable device communicate body electrical language biotechnology live longer rid zombie cell tim maverick fountain youth age study mayo clinic step forward slowing ageing process cyber security bank heist expose staggering security flaw greg miller recent robbery million central bank bangladesh exposed unbelievably alarming cybersecurity flaw worse cyber security cyber threat digital health tim maverick digital healthcare offer promise future threat lurk cyber attack medical system device stock gun stock buy greg miller recent death supreme court justice antonin scalia obama presidency coming end impact gun industry stock asia asian market surge wake brexit carl delfeld european market continue falter asia burgeoning rising middle class booming consumer market region watch international growing middle class create market carl delfeld international rise middleclass population mean spending emerging market carl delfeld reveal invest china timeless strategy opportunity carl delfeld pinpointing amazing investment opportunity isnt easy feat but carl delfeld explain piece fall perfectly place archive archive archive archive energy agricultural rare tangible asset metal mineral energy membrane technology save world david dittman profile membrane technology compelling innovation desalinate seawater generate power electricity natural gas helium shortage averted tim maverick helium crucial industry making current shortage increasingly worrisome huge tanzania ready change game oil energy saudi arabias solar planning paved oil production tim maverick saudi arabia see future solar power road riches paved oil tim maverick talk mbs middle eastern energy future agriculture agricultural commodity awaken tim maverick agricultural commodity price dump year tim maverick see turnaround sight garnering investor interest agriculture commodity market sweet tooth shelley goldberg commodity market running month sugar high indulge sweet tooth grain investing organic profitable endeavour shelley goldberg shelley goldberg examine move organic farming company profiting handsomely art market overheated art market sizzling shelley goldberg analyst redhot art market finally overheated international investor helping maintain momentum art market art market add beauty portfolio shelley goldberg shelley goldberg explain four reason think sizzling art market continue grow profit art market art market hot hot alan gula fine art market fire worth investing tangible asset part diversified portfolio lithium play small cap lithium boom tim maverick lithium demand soaring tim maverick reveal invest large company small cap rare earth metal china set control crucial metal electric car tim maverick investor rosy expectation tesla firm face cobalt cliff restricting battery production base metal china take gamble commodity tim maverick industrial metal red hot market economic reason archive archive archive archive personal finance portfolio management retirement millennial financing investing children saving future tim maverick cost education increase family save money future children investment young prudent young prudent build relationship money samantha solomon solomon halpern reveal top step changing relationship finance mindful one young prudent young prudent parent dont understand samantha solomon samantha solomon take closer distinct economic difference millennial adulthood past generation asset allocation invest windfall tim maverick windfall what tim maverick unveil game plan smart investing asset allocation investing age stage life tim maverick investing lifelong process tim maverick map phase market interaction monetize moment asset allocation ready half jonathan rodriguez investor faced unpredictable market year jonathan rodriguez offer plan profit rest retirement planning guide iras care sarah adler navigating retirement plan option challenging here offer breakdown pros con iras retirement investing howto investing comfortable retirement tim maverick low interest rate devastating retirement investor seeking income tim maverick offer tip coping retirement planning wild ride retiring bull market tim maverick midst history secondlargest bull market allocate stock secure retirement young prudent young prudent certainty death taxe samantha solomon ahead wall street daily samantha solomon close young prudent recap aspiration young prudent young prudent big spend samantha solomon successfully saving chunk money samantha solomon contemplate making big purchase challenge millennial investing read more spend chris worthington american spend billion book year why pocketing money reading free archive archive archive archive stock technical analysis fundamental analysis alternative investing stock orbital atk opportunity defence contractor david dittman fundamental reason justify recent selloff defence aerospace stock mean significant opportunity investor forecast brexit sector making huge comeback jonathan rodriguez brexit stirred major market pullback jonathan rodriguez perfectly hospitable investment hold over forecast small big profit postbrexit jonathan rodriguez jonathan rodriguez expose soft underbelly large cap stock underline investor profit small cap stock stock market chart charting path investing success jonathan rodriguez day moving average extremely tool investor identify trend profit stock market chart trade simple moving average jonathan rodriguez trader leg turn simple moving average easy powerful tool trading stock equity bottom jonathan rodriguez stock made significant gain week now technical pattern showing downtrend reversal time buy market analysis peter schiff score latest win robert william again peter schiff predicted falsehood rate hike hope and dollar fall robert william offer future crash crise market analysis week wall street daily sarah adler missed wall street daily problem featured week valuation control roe doesnt cut shelley goldberg dupont method take roe level shelley goldberg explain math reveal truth special situation perpetual bond equity disguise shelley goldberg troubled economic time perpetual bond offer refuge shelley goldberg caution jumping investigation special situation investor betterment tim maverick brexit crisis roboadvisor betterment market tim maverick explain option stay linkedin calculating real shelley goldberg full company linkedin crucial understand operating margin calculated shelley goldberg explain archive archive archive archive exchangetraded fund equity fund specialty fund ipos dividend etf dividend cool tim maverick world negative interest rate tim maverick take promising dividend etf etf tripleleveraged etf carry wealth risk alan gula lot leveraged speculation buyer beware etf mutual fund etf carl delfeld special correspondent carl delfeld explain mutual fund versus etf type portfolios suited for mutual fund fund stock carl delfeld carl delfeld break investing beatendown market fund making maximum profit maximum pessimism closedend fund cheap preferred fund perfect low rate alan gula fed push back rate increase now income investor closedend preferred fund mutual fund roboadvisor kill human advisor alan gula here online investment advisory platform roboadvisor crowdfunding closer risk reward crowdfunding tim maverick advent crowdfunding average person invest startup risk tim maverick explain specialty fund lending club trouble show doesnt work martin hutchinson lending club example martin hutchinson explain investor avoid lending closedend fund closedend fund craziness alan gula closedend fund cef price irrational dont follow herd cef inflated premium net asset value ipos twilios ipo hot not louis basenese ipo market struggling mightily upcoming debut tech firm twilio weigh company pros con give verdict ipos twilio spark stronger ipo market louis basenese proved slow ipo market far history show summer month dont necessarily promise same company kickstart upswing ipos square ipo flop good investor louis basenese ipo flop digital payment firm square tech analyst predicting doom future tech ipos here good new tech investor archive archive archive archive true alpha digital fortune shockproof investor trigger point pro instant money trader venturecap strategist extreme alpha currency capital president club gold president club platinum wsd team contact archive ensure delivery frequently asked question broker listing control roe doesnt cut published thu shelley goldberg senior correspondent investor making equity investment decision based return equity roe missing boat roe closely watched number savvy investor strong measure effective company management creating shareholder misleading vulnerable measure increase which default make stock consideration risky investment therefore investor break roe component avoid duped believing company good investment fact dupont method eponymousdupontanalysis ratio performance measurement developed dupont fabros technology inc dft internal use fastforward today firm analyst evaluate effectively asset utilised measure combined effect profit margin asset turnover dupont analysis essentially deconstruct roe factor influence company performance calculating roe simple equation consist number roe increase typically company rate return shareholder equity rising here problem number rise company simply take debt decreasing shareholder equity yes called leverage leverage good thing increase stock risk effort avoid mistaken assumption analyst required indepth knowledge roe dupont corporation addressed specific creating method analysis break roe complex equation dupont method dupontidentity measure asset company gross book net book value applying dupontanalysis roe affected thing operating efficiency measured profit margin asset efficiency measured total asset turnover and financial leverage measured equity multiplier equation roe thereby broken net profit margin how profit company revenue asset turnover how effectively company make asset equity multiplier measure company leveraged dissecting dupont measuring asset gross net book remove incentive delay avoid investing asset why asset avoidance occur depreciation method applied financial accounting artificially produce lower roe initial year asset service turn roe unsatisfactory dupont model reveal part business underperforming real world application dupont threestepmodel follow begin taking closer margin industry example highend fashion derive significant amount competitive advantage selling higher margin versus higher sale retailer increasing sale sacrificing margin factor critical maintaining profit applying dupont identity determine element dominant change roe turnover industry grocery store significant multiple asset sold year roe dependent performance metric asset turnover analysed carefully sign under overperformance retailer commonly samestore sale examining profit margin refer difference revenue generated retail chain existing outlet period fiscal quarter shopping season compared identical period past samestore sale offer company important measure business deriving greater profit existing store opposed showing improved performance opening store finally highly leveraged industry financial service bank financial institution typically rely leverage generate acceptable roe unlike industry leverage unacceptable risky assessing financial statement institution dupont analysis enable analyst compare leverage similar company fivestep game second extended variation dupont referred fivestep equation take method analysis further discussed company roe rise result increase net profit marginor asset turnover positive company equity multiplier however source rise company appropriately leveraged higher risk company overleveraged stock price warrant discount irrespective higher roe company underleveraged indicative managed roe remain unchanged utilising dupont analysis show net profit margin asset turnover decreased negative sign company thus reason roe stayed due sizable increase leverage bad sign fivestep dupont method handy break net profit margin further equation show increase leverage dont increase roe numerator net profit margin net income turned intoearning interest taxe ebit multiplying threestep equation minus company tax rate result calculation whereas operating profit margin ebit sale asset turnover sale asset interest expense rate interest expense asset equity multiplier asset equity tax retention rate tax rate company borrowing cost interest expense additional debt negate positive effect leverage fivestep method conclude company lower roe creditor perceive company riskier charge higher rate interest alternatively company poor management leverage higher cost decreasing operating profit margin ultimately three fivestep equation provide deeper understanding company roe examining what changing company company roe lower peer methodology identify company lagging alternatively company lifting propping roe type analysis crucial identifying solid investment good investing shelley goldberg newsletter faq cancel time privacy related article orbital atk opportunity defence contractor smallcap utility stock flash cash brainsonix revolutionary technology show bring brain back life wave robotic surgery add comment cancel reply required published mail required published website cancel reply newsletter faq cancel time privacy innovation space travel mar david dittman elon musk falcon exploded launchpad recently minor setback major move made groundbreaking space exploration nasa hopeful sight set mar geomacro presidential election clinton trump science technology david dittman amid muck mire presidential election campaign clinton trump top science technology issue special situation sun hydraulic shattering morass middle management david dittman time end mediocre middlemanagement structure put manpower work valuable position company track for powered ajaxy premium research true alpha venturecap strategist extreme alpha company contributor contact whitelist instruction privacy policy disclaimer syndicate faq learn free report premium research income growth commodity geomacro money trading fund spotlight contact paul baltimore wall street daily llc right reserved","m_szGeo1":"United States","m_szSourceType":"source_general","m_szSrcUrl":"http://www.wallstreetdaily.com/2016/06/16/roe-dupont-method/","m_Places":["United States","Take","Asia","India","Best","Lies","Gun","China","Tanzania","Saudi Arabia","Endeavor","Tesla","Baltimore, Md"],"m_People":["Sarah Adler","Martin Hutchinson","Alan Gula","David Dittman","Greg Miller","Jonathan Rodriguez","Tim Maverick","Antonin Scalia","Carl Delfeld","Shelley Goldberg","Samantha Solomon","Solomon Halpern","Chris Worthington","Peter Schiff","Robert Williams","Louis Basenese","Elon Musk"],"m_Companies":["Wall Street Daily","Agora","Income Industries","Bust","Arm Holdings","Nintendo","Mayo Clinic","Security Bank","Central Bank Of Bangladesh","Supreme Court","Timeless","Energy Futures","Overheated Art","Iras","Bull","Orbital","Path","Dupont","Linkedin","Real","Equity Funds","Lending Club","Twilio","Dupont Fabros Technology Inc.","Dupont Corporation","Indicative","Step Dupont","Nasa","Manpower"],"m_BiGrams":["tim maverick","shelley goldberg","martin hutchinson","jonathan rodriguez","carl delfeld","art market","young prudent","profit margin","alan gula","samantha solomon","asset turnover","david dittman","wall street","street daily","special situation","real estate","income investor","net profit","foreign dividend","sarah adler","country buy","prudent young","dupont method","mutual fund","closedend fund","equity multiplier","free report","give verdict","emerging market","greg miller","goldberg explain","small cap","asset allocation","moving average","louis basenese","ipo market","margin asset","dupont analysis","asset equity","interest expense"],"m_TriGrams":["wall street daily","net profit margin","profit margin asset"],"m_SocialTags":[],"m_Topics":[],"m_Industry":[],"m_Technology":[],"m_BiCnt":[28,14,13,11,9,9,9,9,8,7,7,6,5,5,5,5,5,5,4,4,4,4,4,4,4,4,3,3,3,3,3,3,3,3,3,3,3,3,3,3],"m_TriCnt":[5,4,3],"m_iDocBodyWordCnt":2254}
