{"m_szDocID":"298762","m_szDocTitle":"2014 Kicks Off with Mine Closures and Mining Negotiations - Investing News Network","m_szYear":"2014","m_szDocSumamry":"UraniumInvesting News Your trusted source for investing success Uranium Member? Login Menu Daily News Resource Investing Precious Metals Gold Silver Platinum Palladium Base Metals Copper Nickel Iron Lead Zinc Critical Metals Graphite Tungsten Tantalum Scandium Cobalt Magnesium Manganese Tellurium Rare Earth Industrial Metals Molybendum Coal Tin Aluminum Vanadium Chromium Energy Uranium Oil Gas Oil and Gas Lithium Gem Diamond Agriculture Potash Phosphate Cannabis About Resource Investing Technology Investing 3D Printing Cleantech Cloud Data Cybersecurity Fintech Graphene Mobile Web Nanotech Abo","m_szDocBody":"uraniuminvesting new trusted source investing success uranium member menu daily new resource investing precious metal gold silver platinum palladium base metal copper nickel iron lead zinc critical metal graphite tungsten tantalum scandium cobalt magnesium manganese tellurium rare earth industrial metal molybendum coal tin aluminium vanadium chromium energy uranium oil gas oil gas lithium gem diamond agriculture potash phosphate cannabis resource investing technology investing printing cleantech cloud data cybersecurity fintech graphene mobile web nanotech technology investing life science investing biotech pharmaceutical medical device genetic life science investing free investor report resource free report technology free report life science free report outlook free report stock resource investing technology investing life science investing uranium investing kick mine closure mining negotiation uranium stock watch project update kivalliq vivien diniz add comment round day year uranium spot price faring uranium consultancy firm uxc spot price checked slightly previous week pound market quiet week activity uranium space mine closure kicked mine closure time niger areva epaareva nigerian government negotiate agreement year licence lapse renegotiation happening areva advanced maintenance schedule somair cominak closing mine month research note dated cantor fitzgerald rob chang mine closure positive uranium nigerbased production account onethird arevas total uranium production note telling areva afford shut mine negotiation contractual obligation meet chang wrote adding tell areva comfortable amount stockpiled material meet obligation economic acquire material spot market deliver contract opposed producing uranium mine niger talk renewed licence nigerian government french company year appear government attempting extract increased royalty areva niger world fourth largest uranium producer fall higher end spectrum cost said chang areva accepting licence agreement paying government royalty reuter reported licence negotiation extended month agreement failed reached ahead yearend deadline cantor fitzgerald combined forecast uranium production cominak somair slotted million pound percent firm see shutdown favourable uranium mean excess global inventory deliver arevas committed delivery greenland denmark uranium end year agreement place uranium mining greenland confident cooperation agreement place half danish prime minister helle thorningschmidt press conference greenlandic counterpart aleqa hammond dont agree issue made progress coming agreement uranium extraction party met discuss copenhagen uranium mining greenland global post wrote greenland home rule colonial power denmark hold control foreign affair defence policy said thoringschmidt believe cooperation agreement nation begin mining uranium late greenland parliament removed uranium mining ban mean pave industrial boom hope gain independence denmark company new lakeland resource tsxvlk option partner declan resource tsxvlan successfully completed landbased radonex survey gibbon creek property showed peak believe highest reported radonex value athabasca basin company groundprospecting sampling programme confirmed existence historic radioactive boulder field property work brought boulder lakeland attention showed assay result greater work conducted property show potential significant uranium discovery interest extremely radon value reported radonex knowledge highest reported theathabascabasin area jonathan arme president lakeland resource company statement pistol bay mining tsxvpst announced joint venture partner rio tinto canada uranium corporation rtcuc mobilised camp intention start drilling block athabasca basin latest press release metre diamond drilling proposed winter programme block budget million programme designed test hole west corridor target followup exploration programme company winter programme expected week security disclosure vivien diniz hold investment interest company mentioned latest uranium investing stock information latest information company uranium investing delivered directly inbox uraniumanfield resourcesenergy fuelsforum uraniumkivalliq energypeninsula energyplateau uraniumwestern uraniumselect select selecting company company above giving consent receive company remember unsubscribe time expert guide uranium investing free download free special reporturanium future outlook uranium price forecast top uranium stock watch return uranium investing index meta data uranium stock watch project update kivalliq related post top uranium stock yeartodate nexgen announce appointment charle scorer special advisor uranium marketing uranium export legislation passed greenland denmark solid foundation set asx listed greenland mineral energy forum uranium wellpositioned athabasca highgrade uranium discovery nexgen energy announce assay result tag areva athabasca basin canada cantor fitzgerald diamond inc lakeland resource largest uranium producer mine closure mining pistol bay mining rio tinto rio tinto canada uranium corporation rob chang tsxv tsxvlk tsxvpst uranium uranium mining uranium producer uranium spot zinc supply comment leave reply cancel reply required will published required comment market top resource storey uranium ready run view top tsx stock gold mining sto view silver mining canada view cobalt ready boom view lithium ontario view mesothermal vein gold deposit view top technology storey bitcoin price surge view datawind ceo talk mobile data view electric vehicle drive cleant view big bioprin view cybersecurity venture release view printing material driv view top life science storey top nasdaq biotech stock cell view invest life science view invest biotech view medx health corp announce ontar view marina biotech announce resignat view delmar pharmaceutical present view popular stock galaxy resource view nemaska lithium view danakali ltd view formation metal view dajin resource view brixton metal view tweet download free report resource investing resource forecast expert opinion covering precious metal energy critical metal gold trend gold outlook key highlight investor base metal opinion expert ceos lithium stock price analyst ceos graphite new graphite mining graphite stock buy lme copper copper etf understanding today copper price investing copper rare earth new rare earth metal price investing lithium stock post rockwood lithium potash stock potash new agriculture investing opportunity investing today critical metal context lynas new molycorp new silver highest price silver come potash type potash potash stock uranium price forecast top uranium stock watch invest platinum stock future hold lonmin amcu south african platinum production investing opportunity lme price base metal new investing tungsten tungsten price tungsten demand tungsten company glance zinc commodity new zinc market outlook coal price forecast type coal coal price coal stock forecasting oil price investing wisely top oil producing country palladium price forecast palladium investment opportunity investing medical cannabis information cannabis legal cannabis stock investing stornoway diamond canadian diamond mine diamond price calculator gold good investment gold price today future gold price prediction kitco mint sold out top article resource investing new gold trend gold outlook key highlight investor lithium stock price analyst ceos resource forecast expert opinion covering precious metal energy critical metal industrial metal oversupply market base metal opinion expert ceos energy investing outlook moving carbon agriculture investing opportunity forecast precious metal outlook ceos analyst gold silver platinum palladium critical metal outlook potential lme copper copper etf understanding today copper price investing copper kitco mint sold out top article resource investing new gold good investment gold price today future gold price prediction investing lithium stock post rockwood lithium free lithium investing newsletter free uranium investing newsletter life science investing life science investing primer finding opportunity medtronic ariad pharmaceutical pharmacyte investing pharmaceutical company pharmaceutical new top pharmaceutical stock buy biotech investing new top biotech company biotech stock life science investing ethic app revolution tech investing understanding bitcoin bitcoin mining bitcoin rate nanotechnology nanotech application nanotech investing investing graphene company graphene cost graphene property graphene market future printing company printing stock buy tech investing primer bitcoin rate printing company instagram stock cleantech investing clean technology investor technology investing trend outlook successful technology investing browse topic resource investing agriculture investing cannabis investing phosphate investing potash investing base metal investing copper investing iron investing lead investing nickel investing zinc investing critical metal investing cobalt investing graphite investing magnesium investing manganese investing rare earth investing scandium investing tantalum investing tellurium investing tungsten investing energy investing gas investing lithium investing oil gas investing oil investing uranium investing gem investing diamond investing industrial metal investing aluminium investing chromium investing coal investing molybdenum investing tin investing vanadium investing precious metal investing gold investing palladium investing platinum investing silver investing tech investing printing investing app investing cleantech investing cloud investing cybersecurity investing data investing fintech investing graphene investing mobile web investing nanotech investing life science investing biotech investing genetic investing longevity investing medical device investing pharmaceutical investing featured stock plateau uraniumemerging uranium district peru peninsula energy featured stock enter log credential remember lost password create password manage account contact privacy policy stock index keyword index browsetopic advertise free report event glossary press release copyright dig media inc investing new network daily new resource investing precious metal gold silver platinum palladium back base metal copper nickel iron lead zinc back critical metal graphite tungsten tantalum scandium cobalt magnesium manganese tellurium rare earth back industrial metal molybendum coal tin aluminium vanadium chromium back energy uranium oil gas oil gas lithium back gem diamond back agriculture potash phosphate cannabis back resource investing back technology investing printing cleantech cloud data back cybersecurity fintech graphene mobile web nanotech technology investing back life science investing biotech pharmaceutical medical device genetic life science investing back free investor report resource free report technology free report life science free report outlook free report back stock resource investing technology investing life science investing back","m_szGeo1":"Canada","m_szSourceType":"source_general","m_szSrcUrl":"http://investingnews.com/daily/resource-investing/energy-investing/uranium-investing/2014-kicks-off-with-mine-closures-and-mining-negotiations/","m_Places":["Tin","Mobile","Outlook","Niger","United States","Greenland","Denmark","Copenhagen","Pistol Bay","Meta","Well","Canada","Ontario","Delmar","Most","Best","Rockwood","Outlooks","Uranium District","Peru","Enter"],"m_People":["Vivien Diniz","Diamond Mines","Rob Chang","Helle","Aleqa Hammond","Jonathan Armes","Diamond Price"],"m_Companies":["Daily News","Palladium","Cleantech","Fintech","Areva","Epa","Nigerian Government","Reuters","The Global Post","Lakeland Resources Inc","Rio Tinto","Canada Uranium Corporation","Rtcuc","Target","Special Report","Top Technology","Datawind","Top Nasdaq","Medx Health Corp.","Danakali Ltd.","Lonmin","Tungsten Companies","Us Mint","Medtronic","Ariad Pharmaceuticals","Top Biotech Companies","Revolution","Graphene Companies","Printing Companies","Dig Media Inc."],"m_BiGrams":["life science","resource investing","science investing","free report","technology investing","critical metal","uranium investing","precious metal","base metal","rare earth","oil gas","investing life","mine closure","uranium stock","industrial metal","stock watch","price forecast","lithium stock","price investing","gold price","investing new","metal investing","investing back","investing precious","metal gold","gold silver","silver platinum","platinum palladium","investing technology","investing printing","mobile web","investing biotech","medical device","report resource","cantor fitzgerald","uranium producer","uranium mining","lakeland resource","athabasca basin","rio tinto","top uranium","view top","stock buy","investing copper","investing lithium","agriculture investing","investing opportunity","tech investing"],"m_TriGrams":["life science investing","uranium stock watch","investing precious metal","gold silver platinum","silver platinum palladium","resource investing technology","science investing biotech","top uranium stock"],"m_SocialTags":[],"m_Topics":[],"m_Industry":[],"m_Technology":[],"m_BiCnt":[14,10,10,10,8,7,7,6,6,5,5,5,5,5,4,4,4,4,4,4,4,4,4,3,3,3,3,3,3,3,3,3,3,3,3,3,3,3,3,3,3,3,3,3,3,3,3,3],"m_TriCnt":[10,4,3,3,3,3,3,3],"m_iDocBodyWordCnt":1434}
