{"m_szDocID":"298759","m_szDocTitle":"Aldrin Resource Acquires Uranium Exploration Property in the Upper Maybelle River - Investing News Network","m_szYear":"2015","m_szDocSumamry":"EnergyInvesting News Your trusted source for investing success Energy Member? Login Menu Daily News Resource Investing Precious Metals Gold Silver Platinum Palladium Base Metals Copper Nickel Iron Lead Zinc Critical Metals Graphite Tungsten Tantalum Scandium Cobalt Magnesium Manganese Tellurium Rare Earth Industrial Metals Molybendum Coal Tin Aluminum Vanadium Chromium Energy Uranium Oil Gas Oil and Gas Lithium Gem Diamond Agriculture Potash Phosphate Cannabis About Resource Investing Technology Investing 3D Printing Cleantech Cloud Data Cybersecurity Fintech Graphene Mobile Web Nanotech About","m_szDocBody":"energyinvesting new trusted source investing success energy member menu daily new resource investing precious metal gold silver platinum palladium base metal copper nickel iron lead zinc critical metal graphite tungsten tantalum scandium cobalt magnesium manganese tellurium rare earth industrial metal molybendum coal tin aluminium vanadium chromium energy uranium oil gas oil gas lithium gem diamond agriculture potash phosphate cannabis resource investing technology investing printing cleantech cloud data cybersecurity fintech graphene mobile web nanotech technology investing life science investing biotech pharmaceutical medical device genetic life science investing free investor report resource free report technology free report life science free report outlook free report stock resource investing technology investing life science investing energy investing aldrin resource acquire uranium exploration property upper maybelle river uranium new fcu oversig uranium outlook matthew spizziri add comment aldrin resource corporation tsxvaln announced ithas purchased upper maybelle river uranium property southwest margin region athabasca basin maybelle cover hectare upper maybelle river drainage saskatchewan alberta provincial border quoted press release property early stage exploration property located fission uranium grade patterson lake uranium discovery southeast arevas reported grade uranium drill intersection maybelle river project northwest saskatchewan government geological mapping regional geophysical data consistent property located low magnetic susceptibility terrain potentially representing folded meta sediment host grade uranium deposit athabasca basin consideration property include aldrin paying past staking cost issuance common share property vendor harrison cookenboo non arm length arthur brown arm length subject approval tsxv finder fee transaction paid security issued acquisition subject month hold period acquisition result change control aldrin aldrin acquisition maybelle part company continuing programme evaluating opportunity uranium discovery economically efficient target areas maybelle strategic addition company major project triple property key lake property aldrin remain focused completion follow drill programme priority triple property located adjacent fission uranium patterson lake pls property contained triple uranium deposit aldrin drill programme triple property uranium mineralization intersected anticline target basement conductor aldrin believe consistent potential halo grade uranium discovery aldrin new release dated set detail uranium mineralization date margin anticline target conductor drill tested aldrin remain focused financing winter drill programme test heart long conductor target aldrin maintaining agreement fission corp earn highly prospective key lake package southeastern athabasca basin region geological setting property package basement rock host major uranium deposit eastern side athabasca basin hectare property potential host surface grade uranium mineralization similar historic key lake deposit new release key lake property package proximal highway primary year round maintained road servicing operational key lake mill connect withaldrin resource corporation tsxvaln receive investor kit latest energy investing stock information latest information company energy investing delivered directly inbox lithiumalix resourcesamerican manganeseavalon advanced material inccritical element corporationdajin resourceseureka resourcesgalaxy resourceshouston lake mininglithium australiamgx mineralsmacarthur mineralsnemaska lithiumnevada energy metalsnevada sunrise gold corporationoakridge global energy solutionspilbara mineralssienna resourcesstria lithiumselect select uraniumanfield resourcesenergy fuelsforum uraniumkivalliq energypeninsula energyplateau uraniumwestern uraniumselect select selecting company company above giving consent receive company remember unsubscribe time expert guide cleantech investing free download free special reportcleantech investing clean technology investor knowabout past year return company new index meta data uranium new fcu oversig uranium outlook related post top uranium stock yeartodate eureka resource acquire interest gemini lithium project nexgen announce appointment charle scorer special advisor uranium marketing uranium export legislation passed greenland denmark solid foundation set asx listed greenland mineral energy alix resource acquire lithium project quebec tag alberta athabasca basin patterson lake uranium saskatchewan uranium uranium deposit comment leave reply cancel reply required will published required comment market top resource storey uranium ready run view top tsx stock gold mining sto view silver mining canada view cobalt ready boom view lithium ontario view mesothermal vein gold deposit view top technology storey bitcoin price surge view datawind ceo talk mobile data view electric vehicle drive cleant view big bioprin view cybersecurity venture release view printing material driv view top life science storey top nasdaq biotech stock cell view invest life science view invest biotech view medx health corp announce ontar view marina biotech announce resignat view delmar pharmaceutical present view popular stock galaxy resource view nemaska lithium view danakali ltd view formation metal view dajin resource view brixton metal view tweet download free report resource investing resource forecast expert opinion covering precious metal energy critical metal gold trend gold outlook key highlight investor base metal opinion expert ceos lithium stock price analyst ceos graphite new graphite mining graphite stock buy lme copper copper etf understanding today copper price investing copper rare earth new rare earth metal price investing lithium stock post rockwood lithium potash stock potash new agriculture investing opportunity investing today critical metal context lynas new molycorp new silver highest price silver come potash type potash potash stock uranium price forecast top uranium stock watch invest platinum stock future hold lonmin amcu south african platinum production investing opportunity lme price base metal new investing tungsten tungsten price tungsten demand tungsten company glance zinc commodity new zinc market outlook coal price forecast type coal coal price coal stock forecasting oil price investing wisely top oil producing country palladium price forecast palladium investment opportunity investing medical cannabis information cannabis legal cannabis stock investing stornoway diamond canadian diamond mine diamond price calculator gold good investment gold price today future gold price prediction kitco mint sold out top article resource investing new gold trend gold outlook key highlight investor lithium stock price analyst ceos resource forecast expert opinion covering precious metal energy critical metal industrial metal oversupply market base metal opinion expert ceos energy investing outlook moving carbon agriculture investing opportunity forecast precious metal outlook ceos analyst gold silver platinum palladium critical metal outlook potential lme copper copper etf understanding today copper price investing copper kitco mint sold out top article resource investing new gold good investment gold price today future gold price prediction investing lithium stock post rockwood lithium free lithium investing newsletter free uranium investing newsletter life science investing life science investing primer finding opportunity medtronic ariad pharmaceutical pharmacyte investing pharmaceutical company pharmaceutical new top pharmaceutical stock buy biotech investing new top biotech company biotech stock life science investing ethic app revolution tech investing understanding bitcoin bitcoin mining bitcoin rate nanotechnology nanotech application nanotech investing investing graphene company graphene cost graphene property graphene market future printing company printing stock buy tech investing primer bitcoin rate printing company instagram stock cleantech investing clean technology investor technology investing trend outlook successful technology investing browse topic resource investing agriculture investing cannabis investing phosphate investing potash investing base metal investing copper investing iron investing lead investing nickel investing zinc investing critical metal investing cobalt investing graphite investing magnesium investing manganese investing rare earth investing scandium investing tantalum investing tellurium investing tungsten investing energy investing gas investing lithium investing oil gas investing oil investing uranium investing gem investing diamond investing industrial metal investing aluminium investing chromium investing coal investing molybdenum investing tin investing vanadium investing precious metal investing gold investing palladium investing platinum investing silver investing tech investing printing investing app investing cleantech investing cloud investing cybersecurity investing data investing fintech investing graphene investing mobile web investing nanotech investing life science investing biotech investing genetic investing longevity investing medical device investing pharmaceutical investing featured stock american manganese recycling solution lithium battery metal supply challenge stria lithium houston lake mining alix resource macarthur mineral featured stock enter log credential remember lost password create password manage account contact privacy policy stock index keyword index browsetopic advertise free report event glossary press release copyright dig media inc investing new network daily new resource investing precious metal gold silver platinum palladium back base metal copper nickel iron lead zinc back critical metal graphite tungsten tantalum scandium cobalt magnesium manganese tellurium rare earth back industrial metal molybendum coal tin aluminium vanadium chromium back energy uranium oil gas oil gas lithium back gem diamond back agriculture potash phosphate cannabis back resource investing back technology investing printing cleantech cloud data back cybersecurity fintech graphene mobile web nanotech technology investing back life science investing biotech pharmaceutical medical device genetic life science investing back free investor report resource free report technology free report life science free report outlook free report back stock resource investing technology investing life science investing back","m_szGeo1":"Canada","m_szSourceType":"source_general","m_szSrcUrl":"http://investingnews.com/daily/resource-investing/energy-investing/aldrin-resource-acquires-uranium-exploration-property-in-the-upper-maybelle-river/","m_Places":["Tin","Mobile","Outlook","Saskatchewan","Alberta","Meta","Most","Greenland","Denmark","Alix","Quebec","Canada","Ontario","Delmar","United States","Best","Rockwood","Outlooks","Enter"],"m_People":["Maybelle River","Matthew Spizziri","Resourceshouston Lake","Harrison Cookenboo","Arthur Brown","Diamond Price","Diamond Mines","Ev Lithium","Houston Lake"],"m_Companies":["Daily News","Palladium","Cleantech","Fintech","Aldrin Resource Corporation","Patterson","Areva","River Project","Saskatchewan Government","Target","Lake Mill","Manganeseavalon Advanced Materials Inc.","Special Report","Top Technology","Datawind","Top Nasdaq","Medx Health Corp.","Danakali Ltd.","Lonmin","Tungsten Companies","Us Mint","Medtronic","Ariad Pharmaceuticals","Top Biotech Companies","Revolution","Graphene Companies","Printing Companies","Dig Media Inc."],"m_BiGrams":["life science","resource investing","science investing","free report","technology investing","critical metal","precious metal","base metal","rare earth","oil gas","investing life","energy investing","athabasca basin","key lake","industrial metal","maybelle river","grade uranium","lithium stock","price investing","gold price","investing new","metal investing","investing back","investing precious","metal gold","gold silver","silver platinum","platinum palladium","investing technology","investing printing","mobile web","investing biotech","medical device","report resource","resource acquire","upper maybelle","property located","patterson lake","uranium discovery","uranium deposit","triple property","drill programme","uranium mineralization","cleantech investing","view top","stock buy","investing copper","investing lithium","agriculture investing","investing opportunity","price forecast","tech investing"],"m_TriGrams":["life science investing","investing precious metal","gold silver platinum","silver platinum palladium","resource investing technology","science investing biotech","upper maybelle river"],"m_SocialTags":[],"m_Topics":[],"m_Industry":[],"m_Technology":[],"m_BiCnt":[14,10,10,10,8,7,6,6,5,5,5,5,5,5,4,4,4,4,4,4,4,4,4,3,3,3,3,3,3,3,3,3,3,3,3,3,3,3,3,3,3,3,3,3,3,3,3,3,3,3,3,3],"m_TriCnt":[10,3,3,3,3,3,3],"m_iDocBodyWordCnt":1344}
