{"m_szDocID":"307103","m_szDocTitle":"What a drag: Roof racks wasted 100 million gallons of gas last year - Roadshow","m_szYear":"2016","m_szDocSumamry":"textArticle -------------------- What a drag: Roof racks wasted 100 million gallons of gas last year What a drag: Roof racks wasted 100 million gallons of gas last year You might want to take that sucker off between trips to the Catskills. Andrew Krok Cars are Andrew's jam, as is strawberry. He started his auto-industry career working as a photographer and social media coordinator for Fluid MotorUnion, a prominent aftermarket parts fabrication garage for late-model European vehicles. That led to a job writing freelance features for \"Total 911: The Porsche Magazine.\" His most recent job prior t","m_szDocBody":"drag roof rack wasted million gallon gas year drag roof rack wasted million gallon gas year sucker trip catskill andrew krok car andrew jam strawberry started autoindustry career working photographer social media coordinator fluid motorunion prominent aftermarket part fabrication garage latemodel european vehicle led job writing freelance feature total porsche magazine recent job prior cnet senior writer webcarzcom helped tweak develop buyingandselling site editorial department bring today day buy dream day full bio drag roof rack wasted million gallon gas year share drag roof rack wasted million gallon gas year enlarge image worry adventureforum buddy mock too badly taking rack favour superior fuel economy live dirt road subaru dealership fair share roof rack road laden unladen rack great hauling crap vehicle carry perfect fact burning gasoline ludicrous rate researcher berkeley lab national renewable energy lab teamed firstofitskind study environmental impact roof rack relied wealth data including forum highway video survey crowdsourcing study published energy policy roof rack responsible percent annual lightduty vehicle fuel consumption sound much amount million gallon gas move roof rack road worse well study estimate roof rack increase percent for comparison additional fuel consumption caused roof rack time larger anticipated fuel saving fuel cell vehicle percent anticipated fuel saving battery electric vehicle wrote press release reasoning simple aerodynamic roof rack create drag require car exert effort cut air wasting fuel process study note roof rack reduce fuel economy percent easiest solution problem remove roof rack used yes pain rack lose street cred rei parking lot feel shelling money gas pump best tag datemeta ","m_szGeo1":"United States","m_szSourceType":"source_news","m_szSrcUrl":"http://www.cnet.com/roadshow/news/roof-racks-wasted-100-million-gallons-of-gas-last-year/","m_Places":["Catskills","United States","Subaru"],"m_People":["Andrew Krok"],"m_Companies":["Cnet","Corbis"],"m_BiGrams":["roof rack","million gallon","gallon gas","drag roof","rack wasted","wasted million","gas year"],"m_TriGrams":["million gallon gas","drag roof rack","roof rack wasted","rack wasted million","wasted million gallon","gallon gas year"],"m_SocialTags":[],"m_Topics":[],"m_Industry":[],"m_Technology":[],"m_BiCnt":[13,5,5,4,4,4,4],"m_TriCnt":[5,4,4,4,4,4],"m_iDocBodyWordCnt":256}
