{"m_szDocID":"318951","m_szDocTitle":"Mitsubishi Motors North America Names Ally as its Preferred Financing Source - InsuranceNewsNet","m_szYear":"2016","m_szDocSumamry":"Mitsubishi Motors North America Names Ally as its Preferred Financing Source DETROIT /PRNewswire/ --Â Ally Financial (NYSE: ALLY) and Mitsubishi Motors North America, Inc. (MMNA) today announced that Ally will become the preferred financing source for Mitsubishi Motors in the U.S., replacing the brand's captive finance company, Mitsubishi Motors Credit of America, Inc. The agreement broadens the existing relationship between Ally and MMNA, continuing to make Ally's full suite of automotive financial products and services available to all Mitsubishi dealers and their customers. Through the agree","m_szDocBody":"mitsubishi motor north america name ally preferred financing source detroit ally financial nyse ally mitsubishi motor north america inc mmna today announced ally preferred financing source mitsubishi motor replacing brand captive finance company mitsubishi motor credit america inc agreement broaden existing relationship ally mmna continuing make ally full suite automotive financial product service mitsubishi dealer customer agreement ally provide premium service comprehensive product offering including retail financing wholesale financing remarketing insurance offering mitsubishis dealership mitsubishi motor dealer leverage ally industryleading education training programme customised marketing benefit dealer service centre day week ally committed success oem dealer relationship continually opportunity strengthen interaction premium product offering bestinclass service innovative ideas tim russi president auto finance ally pleased mitsubishi motor north america chosen place trust ally support retail sale growth plan improved customer experience agreement ally part number initiative mitsubishi motor undertaking grow brand continue deliver outstanding sale momentum united state mitsubishi motor introduced design language concept world premiere mitsubishi outlander york international auto show critical acclaim appearance change outlander received complete makeover heavy emphasis driving ride quality implementing improvement model previous year mitsubishi motor resurgence sale quarter yearoveryear sale increase accomplished bringing model market and large part loyal dealer network stayed good time bad excited model promise bring don swearingen executive vice president mmna pursue growth plan dynamic landscape pleased financial partner ally support product service dealer integral success ally financial inc ally financial inc nyse ally leading automotive financial service company powered top direct banking franchise ally automotive service business offer full spectrum financial product service including vehicle inventory consumer financing leasing vehicle service contract commercial loan vehicle remarketing service variety insurance offering including inventory insurance insurance consultative service dealer ancillary product ally bank company direct banking subsidiary member fdic offer array deposit product including certificate deposit saving account money market account ira deposit product interest checking ally corporate finance unit financing middlemarket company broad range industry approximately asset dec ally operate financial holding company information visit ally media follow ally twitter mitsubishi motor north america inc mitsubishi motor north america inc mmna responsible research development manufacturing marketing sale financial service mitsubishi motor united state mmna sell sedan network approximately dealer mmna leading development highlyefficient affordablypriced gasolinepowered automobile industryleading knowledge battery electric vehicle develop future phev model information contact mitsubishi motor new bureau visit mediamitsubishicarscom media contact ","m_szGeo1":"United States","m_szSourceType":"source_industry","m_szSrcUrl":"http://insurancenewsnet.com/oarticle/Mitsubishi-Motors-North-America-Names-Ally-as-its-Preferred-Financing-Source-a-616047","m_Places":["North America","Detroit","United States","America"],"m_People":["Mmna","Tim Russi","Don Swearingen"],"m_Companies":["Mitsubishi Motors","Ally","Ally Financial","U.s. Mitsubishi Motors","Service Center","New York International Auto Show","Ally Financial Inc.","Ally Bank","Ira","Twitter"],"m_BiGrams":["mitsubishi motor","motor north","north america","america inc","ally financial","product service"],"m_TriGrams":["mitsubishi motor north","motor north america","north america inc"],"m_SocialTags":[],"m_Topics":[],"m_Industry":[],"m_Technology":[],"m_BiCnt":[13,5,5,4,3,3],"m_TriCnt":[5,5,3],"m_iDocBodyWordCnt":386}
