{"m_szDocID":"319632","m_szDocTitle":"New CO2 Emissions Report Shows China's Central Role in Shaping World's Climate Path - The New York Times","m_szYear":"2014","m_szDocSumamry":"textArticle -------------------- The New York Times Dot Earth | New CO2 Emissions Report Shows China’s Central Role in Shaping World’s Climate Path Advertisement New CO2 Emissions Report Shows China’s Central Role in Shaping World’s Climate Path By September 23, 2014 7:25 am September 23, 2014 7:25 am Photo A report from the Global Carbon Project shows China's soaring trajectory for heat-trapping carbon dioxide.Credit Global Carbon Project While President Obama and more than 100 other heads of state are expected to participate in the United Nations Climate Summit today, President Xi Jinping of","m_szDocBody":"york time dot earth emission report show chinas central role shaping world climate path advertisement emission report show chinas central role shaping world climate path photo report global carbon project show chinas soaring trajectory heattrapping carbon dioxidecredit global carbon project president obama head state expected participate united nation climate summit today president jinping china country making biggest contribution atmospheric buildup greenhouse gase appear indication enormous roadblock facing press strong global agreement stemming global warming negotiation year for roadblock read recent oped robert stavin head environmental economic programme harvard kennedy school chris buckley longtime china correspondent time written valuable piece sinosphere blog chinas central role propelling possibly slowing buildup greenhouse gase linked global warming post centre interview glen peter scientist author year global carbon budget report tracking emission trend carbon dioxide energy cement production excerpt link rest photo coalfired power plant chinas hunan province junecredit jason latest global carbon budget china prominently ever that all country emitting carbon dioxide wealthy country higher average emission person china undergone unprecedented economic structural decade true carbon dioxide emission china emitted percent global emission international energy agency wrote chinese emission remain united state then chinese emission grown percent year passing united state emission china emit percent global carbon dioxide emission united state european union combined double emission united state alone china percapita emission percent global average higher percapita emission european union sixty percent growth global emission due china china emitted total united state european union preindustrial time gap fast closing major happening china world eye china recent research chinas carbon emission headed theyll bend give world chance meeting twodegree target china responsible percent current global emission emission continue robust growth realistic chance keeping degree require strong action china estimate remaining emission quota stay degree celsius require china reduce emission percent year case greater mitigation challenge united state comparison transition nuclear energy france belgium sweden led reduction percent year lasted decade mitigation challenge china immense sound daunting explain implication chinese scientist official chinas carbon emission growing possibly year that youre keeping twodegree goal demand faster deeper cut china speak rest world right broad misconception mean degree analyse model optimistic assumption implementation carbon pricing globally availability key technology carbon capture storage analyse focus global level hiding countryspecific detail impression mitigation easy sufficient political societal support engineering reality ground different china moving forward stronger stronger climate policy unclear chinas current level ambition consistent keeping global warming degree arithmetic small remaining emission quota mean china emit emit bring issue equity fairness directly debate positive progress chinese climate policy reality that consistent degree peak decline chinese emission occur sooner faster youve that failure advanced country cutting emission china chance lead climate negotiation make kind emission reduction mind hurting economy know great deal reluctance china making put economic growth risk country historical context psychologically constrain option moving forward norway richest nation world path dependence oil gas extraction contrast neighbour denmark sweden finland successful oil gas way country riches secret china make part solution clear degree require massive investment renewable technology battery electric car carbon capture storage bold move forward ensure technology made china riches closely follow datemeta ","m_szGeo1":"United States","m_szSourceType":"source_news","m_szSrcUrl":"http://dotearth.blogs.nytimes.com/2014/09/23/new-co2-emissions-report-shows-chinas-central-role-in-shaping-worlds-climate-path/?partner=rss&emc=rss","m_Places":["China","Central","United States","Most","France","Belgium","Sweden","Norway","Denmark","Finland","Made"],"m_People":["Barack Obama","Xi Jinping","Robert N. Stavins","Chris Buckley","Glen Peters","Jason Lee"],"m_Companies":["New York Times","Path","Harvard","Kennedy School","The Post","Reuters","International Energy Agency","European Union","Target"],"m_BiGrams":["united state","global carbon","carbon dioxide","show chinas","chinas central","central role","global warming","emission china","percent global","global emission","chinese emission","percent year","european union"],"m_TriGrams":["chinas central role"],"m_SocialTags":[],"m_Topics":[],"m_Industry":[],"m_Technology":[],"m_BiCnt":[6,5,4,3,3,3,3,3,3,3,3,3,3],"m_TriCnt":[3],"m_iDocBodyWordCnt":516}
