{"m_szDocID":"319875","m_szDocTitle":"Austria Launching Legal Challenge Against EU Decision To Allow Hinkley Point C Nuclear Subsidies | CleanTechnica","m_szYear":"1990","m_szDocSumamry":"textArticle -------------------- Austria Launching Legal Challenge Against EU Decision To Allow Hinkley Point C Nuclear Subsidies January 28th, 2015 by James Ayre   The government of Austria is planning to make a legal challenge with regard to the European Union’s relatively recent decision to allow the Hinkley Point C nuclear energy project to be subsidized to the tune of billions of pounds, according to recent reports. The European Union (EU) approved Hinkley Point C nuclear power plant receiving a £17.6 billion subsidy deal last October — a decision that was met with a fair amount of debate","m_szDocBody":"austria launching legal challenge decision hinkley point nuclear subsidy jame ayre government austria planning make legal challenge regard european union recent decision hinkley point nuclear energy project subsidised tune billion pound recent report european union approved hinkley point nuclear power plant receiving billion subsidy deal decision met fair amount debate time austrias appeal launched april thesubsidy deal least delayed year luxembourg nuclearfree austria considered support appeal appear fair deal opposition approval subsidy package reportedly country mightback appeal well unverified now reasoning legal challenge uks year loan guarantee constitute illegal state aid highlevel decision chancellor vice chancellor challenge decision hinkley month eus official journal stated andreas molin director austrias environment ministry conversation guardian foreign policy adviser austrian federal chancellory stefan pehringer stated austrian government announced readiness appeal european commission decision state aid hinkley point project nuclear power sustainable form technology environmental economic term hinkley project represent completed nuclear reactor year representing step backward opponent technology there numerous good reason opposing technology evidenced recent new uranium contamination persisting processing site remediation worth noting here though hinkley cis completed perform expectation expected cover roughly uks electricity generating capacity power generated bought strike price megawatthour roughly market rate approval project subsidy deal french stateowned edf government previously david cameroon big day country commenting analysis european court case type austrian government molin stated longer normal complicated fundamental case bit longer year rough guess molina concluded accept argument hinkley constitute market failure put forward commission apply mean electricity production form energy conversion apply energy sector single energy market stake case work project reportedly begun image credit hinkley wiki cleantechnicas completely free electric car report electric car early adopter follower want date hottest cleantech new subscribing free cleantech newsletter eye sectorspecific new also free solar energy newsletter electric vehicle newsletter wind energy newsletter tag austria hinkley nuclear project jame ayre background predominantly geopolitic history obsessive interest pretty everything early life spent imperial free city dortmund jame river ruhr cofbuokheim attended university astnide briefly considered entering coal mining business write living broad variety subject ranging science politic military history renewable energy follow work google related post energy efficiency sector confidence plummet amidst fear brexit legally complex overturn decision undermining government ability set marketbeating strike price rate wind renewable tech manifest excellent green initiative market distortion strike price offshore wind pmw compared agreed hink subsidy generate more longer single development voicing support important number context sault power hinkley sold market rate guaranteed base rate adjustment inflation year holding constant inflation rate hinkley guaranteed kwh cheap amazing renewable energy then jameswimberley work britain general election may austrias lawsuit held ukip unwarranted interference british national policy project popular economic worse day wind cost continue fall edf face major regulatory risk ecjs ruling year time sweetheart deal backing out decommission sellafield nuclear plant cost billion done cost decommisson nuclear plant stjernobil fukushima luxembourg shut worst polluter capita clean energy project tiny rich country fossil free basically fossil fuel energy larmion interestingly luxemburg highest share nuclear electricity world all import virtually huge share power france nuclear smaller share belgium nuclear foersom all import virtually huge share power france luxembourg power transmission line france national grid connected germany small separate industrialgrid connected belgium bobwallace cheque germany suppiier conduit fair amount power flow germany route country another france germany luxembourg german transmission could critical word here larmion cease amaze austria manage actively oppose nuclear power plant issue coalfired capacity project door eastern europe coal kill people mining stage nuclear energy source entire life cycle doesnt matter subsidy wait coal receive incredible level subsidy health externality climate change factored wasting money sure austrias job prevent nation making poor spending choice directly threaten opposition czech slovakian nuclear power plant rational austria experience discomfort awry lost tourism revenue example neptune strong free market movement austria dont subsidy coal subsidised term health climate change externality free market movement doesnt answer yet larmion plausible argument austria didnt fit germany member state subsidise form electricity generation extent neptune fit excluded fair competition law dont called that nuclear hasnt excluded sue receiving subsidy coal gas subsidy member state obliged phase out externality remain free larmion earlier commission investigation required minor modification support mechanism found fundamentally violate rule recently october released final report subsidy scheme hinkley point finished simple phrase basis investigation commission conclude support compatible state aid rule correct direct state subsidy energy illegal rule for renewable too way however rule explicit fit considered subsidy technicality caused legal challenge germany energiewende fail far philip fight battle chose project know martin support cost alternative common sense jenny sommer politic big stinking trade deal china allowed built operate nuke speed rail briton abn gas supply contract side fossilnuclear industry work austria hand problem deal legal precedent country including czech love subsidise failing nuclear industry austria banned nuclear energy import industry import nuclear energy vesel honest czech nuclear power specific situation czech nuclear facility fact great success consider temelin plant cost billion large part cost sunken artificially induced inflation czk early plant finished wholesale electricity price spiked construction time year started run paid back year large part czech energy maker think success replicated breakeven cost electricity nuclear estimated very optimistic power cost set leipzig power exchange country huge electricity overproduction electricity produced exported year ","m_szGeo1":"United States","m_szSourceType":"source_news","m_szSrcUrl":"http://cleantechnica.com/2015/01/28/austria-launching-legal-challenge-eu-decision-allow-hinkley-point-c-nuclear-subsidies/?utm_source=feedburner&utm_medium=feed&utm_campaign=Feed%3A+IM-cleantechnica+%28CleanTechnica%29","m_Places":["Austria","Hinkley","Luxembourg","Uk","Atmosphere","Cameroon","Molina","Free City","Dortmund","Britain","Fukushima","France","Belgium","Germany","Eastern","Europe","Czech","China","Czech Nuclear Facilities","Leipzig"],"m_People":["James Ayre","Andreas Molin","Stefan Pehringer","Tiny Rich","Jenny Sommer","Jan Veselý"],"m_Companies":["Eu","European Union","Guardian","Austrian Government","European Commission","Uk Government","Guess","University Of Astnide","Google","Amaze","Indeed","Bp"],"m_BiGrams":["hinkley point","nuclear power","legal challenge","nuclear energy","decision hinkley","point nuclear","power plant","state aid","strike price"],"m_TriGrams":["hinkley point nuclear","nuclear power plant"],"m_SocialTags":[],"m_Topics":[],"m_Industry":[],"m_Technology":[],"m_BiCnt":[5,5,4,4,3,3,3,3,3],"m_TriCnt":[3,3],"m_iDocBodyWordCnt":869}
