{"m_szDocID":"321250","m_szDocTitle":"The Alternative - Free Energy And Free Thinking","m_szYear":"2012","m_szDocSumamry":"Home Page for FEandFT.com My Free Book: Free Thinking and Free Energy Space is Dark Light not Dark Matter Spiral Light Waves The Absurdity of Nothingness The Age of Reason The Alternative The Alternative Paradigm The Arm Chair Physics of Kinematics The Case Against the Nuclear Atom The Corrupt and Degenerate Control Of Our World The Cosmological Implications of 2012 The Curved and Divided Electric Universe The Dire Consequences Of Academic Theory The E=MC Squared Mythematical Theory The Electric Car Sabotaged The Electric Sun The Escalation of the Energy Fraud The Eternal Cyclical Universe The","m_szDocBody":"home feandftcom free book free thinking free energy space dark light dark matter spiral light wave absurdity nothingness age reason alternative alternative paradigm arm chair physic kinematic case nuclear atom corrupt degenerate control world cosmological implication curved divided electric universe dire consequence academic theory emc squared mythematical theory electric car sabotaged electric sun escalation energy fraud eternal cyclical universe imploding structure atom motion light nature space nuclear fusion fraud real nature light secret light structure atom string theory fraud free energy free thinking robert otey unidirectional academic physic vortex basic vortex mechanic review stephen hawking history time academic atom smasher academic gravity theory academicism social engineering basic concept free energy big bang black hole biomagnetism levity blaze lab mirrored chapter xii secret light crooked trail curriculum vitae pallathadka keshava bhat curved light decentralisation energy production dead end academic physic bhat book einstein ether electricity magnetism electricity sold electricity magnetism energy baron astronomical profit financial control fractal geometry free energy solution gravity gravity tidal action speed motion increase mass debunked implosion technology introduction free energy light light misunderstood socalled scientist magnetism cathode plane stillness control electricity mental image sensory information mirrored magnetic energy creator heart creation particle accelerator lunacy problem reaction solution qualification disclaimer quantum flakiness age movement quantum quackery quackademia quasar pulsarsfaster light motion red shifted light doppler effect sound debunked sacred geometry scalar mechanic scalar motion social engineering sound wave light wave vortex basic crooked trail music robert otey alternative alternative world based sacred treatment water viktor schaubergerwas pioneering environmentalist whodiscovered natural solutionsto pressing problem relating energy pure water need poor health continuing destruction planet ignorant negligent treatment earth air waterit exaggeration acknowledge prophet aquarian age age water bearer work revealed direction humanity harmonise nature cosmos biomimicry solution ubiquitous problem entire array technology fighting nature losing miserably schaubeger work required reading school virtuous foundation life healthand sanity insane world long corporate americacontrol schoolswith sound sciencethe truth taught heard word aboutalternative physicsplasma physicsfree energyoverunityzero point energyteslaschaubergermoraytownsendgraygiordano brunodb larson especiallywalter russell physic class school junior college university california graduated fromone immediately why called social engineering folk dont clue thought own programme loaded mind nonthinking servile lemming lash threaten comfort zone matrix cling ly enslave perpetually linkteslas free energy secret linktesla sabotaged morgan acted orson well brilliant thinker listed believed form ofphysicswhich produced technology free centralization energy production andaristocratic financial controlthese technology suppressed upset balance power thewealthy aristocratic classhas possessedsince hoary timesof ancient babylon egypt pyramidal system control centralization energy production extremely bad idea relationship terrorism whetherhomemade false flag operation orreal imported terrorism easy disrupt flow energy million customer system world presently energy produced large plantsterroristscould target manynuclear reactorsin country causingexponential damageand death academic scientistdr robert bussard claimed harness free energy electrical fusion boron smallinertial electrostatic confinementfusion reactor academic explanation based nuclear theory atom provably wrong call question device work brussard claim example bussardsexcellent minute taped presentation googleexplain electric fusion process basic physic context concept minimal background basic physic relate which mean explanation provably failed nuclear theory atom reason including academic source claiming produce overunity free energy invention point unfortunate corporate controlled mind set typical academician watch video previous link speak deeply entrenched bondage academic corporation shamelessly serve academic funding consideration humanity whole brussard talking free energy masse break profit margin scenario audience centralised production energy coming iec reactor plan sell reactor energy baron continue make massive profit energy supplied planet nothing represent actual cost overunity energy capital outlay recovered human extremely cheap energy reach fullest potential absolute dedication academic scientist master charge economic machine serve witnessed video problem unending faithfulness pyramid control indoctrination accepted normal living fact slavery corporate funding control worse slavery live limited condition scarcity imposed mankind energy baron planetary disaster academic physic linkthe corporate manufactured fraud called scarcity disturbing nerd like wise crack remark carelessly dropped about nuclear tragedy hiroshima nagasaki slaughter innocent civilian absolute billion dollar waste failure tokamak fusion reactor based failed theory nuclear furnace sun easily laughed brussard audience scientific slave geek reprehensible egghead mistake past academic quackery attending scientist scientific groupy laughing about laughing matter fact reason problem world craven academic mindset laugh academic stupidity human live failed world backward academically mind controlled theory prevented free energy technology invented geniuse tesla intentionally suppressed past year system academician faithfully serve eye wide shut linkfree energy hope humanity centralization energy production reason iec reactor liberate mankind era abundance brussard energy grid place enslaved humanity energy baron retrofit current energy plant iec boron fusion reactor convenient energy baron nonpolluting source energy swap technology massive revenue promised brussard flooding time however pay fraction cost fuel source boron larger profit control political leader humanity whole shifty shyster energy baron freedom human decentralisation energy production freedom energy baron destroyed world quest realise unquenchable greed point energy production solution put power hand directly construction thousand iec reactor insure wealthy energy baron skim massive profit enslave customer implosion turbinesandpermanent magnetic motorsare kind technology place unlimited energy production hand people planet eternal abundance universe operate generate enormous amount wealth masse usher era untold abundance construction earth saving generator bring great fortune country employ legion worker job building billion machine needed planetary population end current system energy slavery untold death due poison centralised form overunity technology rejected immediately point free energy technology hidden masse released immediately reverse descent living environmental societal hell linkfree energy magnetic generator power grid linkthe surge technology magnetic free energy motor linkoverunity magnetic motor breaking socalled law physic pyramid control energy baron enjoy great stolen privilege torn held responsible pay crime humanity environment parasitic system stolen resource exploited human labour energy baron remove oil well restore land mined coal uranium clean toxic filth left planet enjoyed untold wealth past century expense living planet electrical grid exploited reverse masse profit distribution wealth selling power back corporation torn down grid major eye sore concentration camp appearance ugly marring sky environmental disaster unnatural electromagnetic pollution cancer causing toxin energy baron generated created endless misery family affected false system theft environmental destruction laugh bank masse cry grief senseless loss life imposed diseased degenerate system control corporation make law free walk destruction left globe process extracting fuel taxpayer pay clean mess created them absolutely unacceptable real human untold astronomical profit immediately clean filth prosecute legal system justice served banking system american pay riches fat cat parasite put themselve crashed economy enron style schwarzenegger craven approval greedy fuck lived life absolute degenerate filth greed past year bondage media lie justified false flag fraud pay extravagant lifestyle interest accumulated orgy selfish gluttony rich wannabee brown nosing shill pretend money disappeared economy personal account long phony crash orchestrated entire middle class mean resistance traitorous plan dictated master globalist planetary casino monopoly game metaphor phony heavily rigged monetary system linkzetigeist truth money taxe war monger mind control bring good point monetary system huge lie money backing confidence every living soul planet guaranteed annual income deposited directly bank account beginning month passing monopoly game played kid make money valuable rich poorest people for food clothes housing recreation enjoyment freedom travel experience world meant too receive receive provide economic base assure planet live fulfilling life work top pay amount guaranteed annual income poorest getting kind economic system build wealth security nation fact ripoff system fraud ly slaved crashing prove worthless low life parasite sponged past millennia apice power free energy free thinking right reserved proudly built startup wordpress theme wordpress","m_szGeo1":"United States","m_szSourceType":"source_general","m_szSrcUrl":"http://www.feandft.com/the-alternative/","m_Places":["Waves","Uni","Bang","United States","Gravity","America","Tesla","Orson","Egypt","Hiroshima","Nagasaki"],"m_People":["Robert Otey","Stephen W. Hawking","Pallathadka Keshava","Viktor Schauberger","Giordano Bruno","Walter Russell","Robert W. Bussard","Brussard"],"m_Companies":["Paradigm","Atom","Theory","Atoms","Real","Gravity Theory","Particle","New Age Movement","Quasars","Prophet","Cosmos","Junior Colleges","University Of California","Matrix","Youtube","Jp Morgan","Target","Surge Technology","Wordpress"],"m_BiGrams":["free energy","energy baron","energy production","free thinking","academic physic","social engineering","centralization energy","iec reactor"],"m_TriGrams":["centralization energy production"],"m_SocialTags":[],"m_Topics":[],"m_Industry":[],"m_Technology":[],"m_BiCnt":[13,11,7,3,3,3,3,3],"m_TriCnt":[3],"m_iDocBodyWordCnt":1218}
