{"m_szDocID":"324344","m_szDocTitle":"'Renegade' UK physicists say they’re on fast track to nuclear fusion | Climate Home - climate change news","m_szYear":"2015","m_szDocSumamry":"Menu Menu News TV Magazine About us Contact us Sponsors About us Contact us Sponsors Sections Politics World Energy Finance Cities Technology Science Opinion Social Media Facebook Twitter Google+ LinkedIn RSS Feed Subscribe Home Politics World Energy Finance Cities Technology Science Opinion Renewables Fossil Fuels Nuclear energy Efficiency ‘Renegade’ UK physicists say they’re on fast track to nuclear fusion Published on 09/09/2015, 5:00am Venture capitalists take on establishment with experimental device, but are optimistic time frames damaging race? CEO David Kingham with stage two device of","m_szDocBody":"menu menu new magazine contact sponsor contact sponsor section politic world energy finance city technology science opinion social media google linkedin feed home politic world energy finance city technology science opinion renewable fossil fuel nuclear energy efficiency renegade physicist theyre fast track nuclear fusion published venture capitalist establishment experimental device optimistictime frame damagingrace ceo david kingham stage device tokamak bid fusion energy credit alexpashley alex pashley doughnutshaped coredapple pintsized nuclear reactor recreate sun earth startup southeast england betting tokamak energyte privately funded venture mile west london pursuing faster fusion strong teamaim convert energy fuel star electricity year colossal feat physic engineering eluded scientistssince timeframe reach call wright brother moment bullish industry scarred rash proclamation fusion arrival small spinoff nearby world leadingculham laboratoryis grain channel government consensus budget back billion joint research effort southern franceseeking produce fusion powerplant scale international thermonuclear experimental reactor iter aim start operation mid achieve fusion electricity latest sofar resemble vast quantity concrete poured ground mounting setback pushing back date nation endeavour start mixing fuel enduring appeal fusion generation habitual refrain observer scoff glacial progress stymie race fusion policymaker lose interest divert research fund warn chief executive david kingham achieve fusion energy gain smaller people conventionally think kingham tell rtcc venture aircraftstyle hangar oxfordshire science park nuclear fusion appeal enduring reason produce nearlimitless energy abundant source radioactive waste minimal risk proliferation produce greenhouse gas emission global temperature continue unrelenting climb account energy fossil fuel panglossian viewing goe tokamak russian acronym meaningtoroidal chamber magentic coilscredit rtcc hitch fusion outstandingly complex decade forward step endeavour stuck rut kingham say pursuit gain onward catalysed splitting atom breaking record british cooperative produced fusion energy joint european torus jet culham generated megawatt energy put goal net energy gain achieve fusion charged particle heated million degree collided stay apart fuel mixture deuterium tritium isotype hydrogen found seawater tritium made lithium inside reactor create fastmoving soup called plasma confined trapped fuel hot long fusion occur theory method exist ranging laser magnet confine plasma jet engine fivestep plan goal million required drummed million investment grant tax break work early version aim roll production line jet engine kingham calculate machine megawatt capacity power uks energy need device tweaked spherical tokamak russian acronym stand toroidal chamber magnetic coil plasma heated microwave stabilised controlling shape magnetic field machine stronger superconductor magnet progress liquid nitrogen eventually helium gas cool down onetwentieth iter size balance realistic risk pretend arent technological development ability raise investment goal sufficiently people justify taking bold view add tes logic believe large amount energy saved cooling reactor less boost chance scoring finance scaling model fusion mind boggling disruptive technology optimistic timeline ruffled feather guess call renegade yes kingham submit meeting sizing fusion potential house lord country scrutinising upper chamber kingham steve cowley head uks atomic energy authority traded barb tes plan boggle mind cowley transcript fearing dent uks scientific credibility forecast claim investor fusion drove say arm length charged cowley director culham centre fusion energy cowley argued process getnuclear licencing draw process fifteen year achievingfusion electricity see realistic bulk million invested state funding engineering physical science research council culham reputation key basic ingredient give good shot make rapid progress kingham responded tokamak energy fivestep plan fusion credit rtcc venture backed scientific evidence fillip world economic forum named technological pioneer spotify dropbox past winner howard wilson fusion expert york university suggested ahead pack iter path follow knowledge arising construction giving chance fusion said aim produce megawatt power input jonathan menard direct national spherical torus experimentupgrade princeton university rival project welcomed tes research line iter protracted problem insisted milestone relevant timeframe field burned promise making timescale reluctant that andhe urged patience race achieve scientifically challenging humankind done weakness solar wind shore baseload power fusion address meant deserved interest report buoy climate talk support carbon goal growing realisation planet halt emission bloc advanced economy calling decarbonisation global economy mean interest remain fusion initiative whirring europe china menard say world clean energy superpower shovelling money project phd student west emphasis money spite complex challenge kingham defiant outfit longshot bet fascinating plasma control hot wriggly object arent solid liquid gase producing sun earth related post track hit renewable target country track meet energy saving target report nuclear face tough renewable growth soar geothermal potential fill japan nuclear gap read energy nuclear featured energy climate home rphunter read fusion energy year away read fusion power year away read fusion power year away guy cut year live hold breath walter gratified wild claim minimum progress stressed skh electricity plasma out equivalent thermonuclear weapon detonated fukushima safety first jayarc sorry ive heard storey time before jam tomorrow lost credibility please netenergy achieved timmy wagner energy mogul usa wont work rich happen oil gone doe big boy cheap power future frederick douglass achieving fusion easy star work emf ambitious yes good thing holy grail energy production solve problem deserve attention nation private programme all good luck good luck money put project crowdfunding kickstarter speculate small bit not tiredofplusquellic storey nuclear fusion year away year ago pjbthree grain salt scientist consider renegade corporate raider hole let hope doesnt work kill earth human planet seanhunt number company path now reason feasible development key technology super conductor dont remember two fusion finally happen economical package hope live day year robb park cold fusion generator ready aint karl martell cheap metre karl martell energy fusion expressed fast moving neutron good fission boosting tus tellerulamsakharov type thermonuclear explosive protonboron cleaner solid borane decompose operating temperature creating boron soot nuclear fusion appeal enduring reason produce nearlimitless energy abundant source radioactive waste minimal risk proliferation produce greenhouse gas emissionsas global temperature continue unrelenting climb account energy fossil fuel substitute thorium fission nuclear fusion appeal thorium fission proven difference weaponize thorium government wont support fusion lagging year experience tokamac princeton plasma physic local government radiological accident analyst officer found fusion real benefit performance catastrophic failure accident detectable radiation property boundary drop background level fusion reaction stop radioactive gase particulate solid drift plume contaminate countryside drinking water river lake crop farm animal fusion plant physically damaged slight release tritium deuterium aka heavy water local environmental water sample health physicist heavy water easily flushed body beer soft beta emission superficial damage cellular wall biologically eliminated bob monteleone dont hold hope scheme long list scheme work tokamak failed break even main stumbling block abysmally low cross section fusion reaction occur trillion atom fuse time trillion heated compressed input power great break difficult obtain article week touting lab working fusion explaining grandiose plan article mention net power output achieved material cost requirement make economically viable power source simply history year are sterling pennington worked company research nuclear fusion viable technology decade away danfrommv year year now jame eldridge simple mimic condition centre sun stainless steel half metre diameter test apparatus tennengineer drop safety good new fusion long closer have wait result corporatism world controller stark afraid control price feed resulting soonerthanexpected fusion power world world planet race reaching for david house lord government entity engaged development protect investor protector protect bad thing you nanny risk physically endangering environment common fusion fusion research well advise investor risk wish hell way course system ready public utility yes regulate tax prohibit govern heart content mallen sun comprised hydrogen helium why isnt play scheme thing jeremy goff tes proposal fuel handling tritium recovery divertor technology power plant application jake clear scientist replicated processe power sun earth couldnt harnessed controlled exploded small island pacific pcah earth recreate sun earth weve sun there safely sky waiting message focus earth site world interconnected continuously supplying cheap electricity jrg staudenmann speaking heart humankind focus farend technology challenge harvesting optimising simple solution hand wango tango fusion come empty beer can year starting arithmetic that chance method god sake britain dont give invention free virtually great invention past meteor youkolalee what joe reason elude scientist immense repercussion way percent government planet receive lucrative taxe fossil fuel tax barrel transport entry port refining product production textile solvent gasoline diesel genny left bottle government funded case european union litre gallon gasoline produce enormous revenue transition nuclear energy year humanity survive long fusioneer year ive lone voice advocating fusion process itself ive proven elementary charge particle overlapping momentum space behave opposite expectation coulomb law mean fusion work scientist hundred year believed doe success teller design hbomb difficult argue impossible processe occurring underway microsecond fission igniter portion fusion weapon activated force large number fusion fuel nuclei overlap momentum space convinced top nuclear weapon designer thomas grissom year ago time exclaimed ideas ideas physic ive heard year encouragement led eventually developing rock solid proof ephraim fischbach break genuine excited exclamation office purdue successful defence hour intense grilling was wow charle youre talking brand physic here hastily instructed grad student erase detail put chalkboard discussed year phone internet finally met definitive proof fusion work scientist believed score year reason inertial confinement magnetic compression scheme work worked work glasstone loveberg controlled thermonuclear reaction paper wrote atomic energy commission stated energy order magnitude the equation supplied nuclei combine fairly rapidly experiment made accelerated nuclei shown nuclear reaction place detectable rate energy considerably top coulomb barrier word threshold energy determined maximum electrostatic repulsion interacting nuclei fusion reaction occur behaviour explained classical mechanic interpreted mean wave mechanic shown probability nuclei combine sufficient energy surmount coulomb barrier effect commonly referred barrier penetration wave mechanical tunnelling quantum tunnelling back late fusion researcher evidence fusion reaction necessarily catalysed extreme temperature condition quantum mechanical interpretation fusion deal discrete real state particle probabilistic state clue pointing idea real pairwise relationship developed fusion fuel nuclei allowed combine relationship require energy collision fusion community developed antithesis concept pairwise relationship involved extreme energy led nuclear fusion reaction success hbomb bolstered confidence suggesting fusion fuel absorbed energy soft xray gave considerable kinetic energy that then led fusion problem clear understanding atom absorb soft xray absorption converted kinetic energy closest compton effect heavy element obtain recoil recoil impart sufficient kinetic energy surmount supposed coulombic barrier atom absorb photon nucleus aborbing electron boosted higher energy level electron thousand time massive nucleus kinetic energy real understood method fusion fuel nuclei obtain energy needed proposed mechanism collisional fusion true weapon community los alamos designed hydrogen bomb made hydrogen bomb work accept idea technology worked understanding worked consequently project sherwood auspice atomic energy commission mission harnessing thermonuclear fusion peaceful energy purpose mission bore taint prejudice prejudice fusion derived thermal energy interacting nuclei however found nuclei combine spite lack relative energy physic community believed way induce fusion reaction nuclei slam considerable energy other well place probabilistically interest dropped ball interested path fusion ive discovered contact emailprotected ian elliott happened byus cold fusion george william read fusion practical year out sadly doubt live long just return moon percenter tiny percentage adoption solar power utility likewise take small number electric car stabilise oil price government heavily invested oil energy market bankrupted completely disrupt industry water engine inventor fusion year off donc global warming add effectiveness efficiency fusion reactor glen wurden true tokamak disruptive technologybut good sense word disruption tokamak achille heel approach fusion solution disruption problem hand that future toakamak reactor doomed destroy energy force teller hbomb worked confining fusion hydrogen nuclei explosive completion thermonuclear reaction fusion technology controlled confined condition safe knowledge physical chemical thermodynamic addition particle physic mathematic chemistry engineering material science etc work design fusion powered electricity station comprise initiation fusion reactor confinement hot plasma wall reactor removal heat controlled manner net energy gain energyreaction coordinate reactant equal product equal denote forward reverse reaction sustained equilibrium slowly increasing reactant drive fusion reaction importantly controlled cooling plasma needed exothermic reaction proceed forward smoothly initiated gaseous catalyst readily accept early stripped electron needed lower energy needed activation fusion reaction sun hydrogen helium gas drive controlled fusion process element act catalyst stream inert gas cool plasma sustaining controlled fusion reaction remove heat exchanger electricity generation electricity generation fusion hydrogen nuclei highly complicated human achieve someday bountiful energy year global warming control longterm future humanity depend achieving fusion power herbert impossible solution endup solution sponsor latest new real rich poor climate battle start green climate fund money project christiana figuere impossible fact attitude weekly wrap oil major split trump climate karaoke brexit leave china running global climate policy popular climate home right reserved weekly briefing breaking global climate change new analysis commentary weekly briefing ","m_szGeo1":"United States","m_szSourceType":"source_general","m_szSrcUrl":"http://www.climatechangenews.com/2015/09/09/renegade-uk-physicists-say-theyre-on-fast-track-to-nuclear-fusion/","m_Places":["United States","Uk","England","London","France","Most","Jet","Cowley","Europe","China","Menard","Japan","Fukushima","Princeton","Britain","Compton","Los Alamos","Sherwood","Heel"],"m_People":["David Kingham","Alex Pashley","Wright Brothers","Steve Cowley","Howard Wilson","Jonathan Menard","Timmy Wagner","Frederick Douglass","Karl Martell","Bob Monteleone","Sterling Pennington","James Eldridge","Jeremy Goff","Jürg Staudenmann","Thomas Grissom","Ephraim Fischbach","Ian Elliott","George Williams","Christiana Figueres"],"m_Companies":["Facebook","Twitter","Google","Linkedin","Apple","2020s","Spherical","Guess","House Of Lords","Atomic Energy Authority","Engineering And Physical Sciences Research Council","World Economic Forum","York University","Path","Princeton University","G7","Bloc","2020","Eu","Target","Gap","Jam","Would Indeed Speculate","Boundary","Diesel","European Union","Atomic Energy Commission","Ball","Ea"],"m_BiGrams":["fusion reaction","nuclear fusion","fusion energy","fossil fuel","sun earth","read fusion","year away","fusion power","fusion fuel","kinetic energy","achieve fusion","energy gain","fusion appeal","atomic energy","energy year","fuel nuclei","nuclei combine"],"m_TriGrams":["nuclear fusion appeal","fusion fuel nuclei"],"m_SocialTags":[],"m_Topics":[],"m_Industry":[],"m_Technology":[],"m_BiCnt":[9,7,5,4,4,4,4,4,4,4,3,3,3,3,3,3,3],"m_TriCnt":[3,3],"m_iDocBodyWordCnt":2039}
