{"m_szDocID":"330431","m_szDocTitle":"Press Releases | Argonne National Laboratory","m_szYear":"2016","m_szDocSumamry":"Skip to main content Argonne National Laboratory Toggle Navigation Toggle Search Energy Environment Security User Facilities Science Work with Argonne About Safety News Press Releases Feature Stories Science Highlights In the News Media Contacts Social Media Photos Videos Fact Sheets, Brochures and Reports Summer Science Writing Internship Careers Education Community Diversity Directory Argonne National Laboratory About Safety News Careers Education Community Diversity Directory Energy Environment Security User Facilities Science Work with Argonne News Press Releases Feature Stories Science Hi","m_szDocBody":"skip main argonne national laboratory toggle navigation toggle energy environment security facility science work argonne safety new press release feature storey science highlight new media contact social media photos videos fact sheet brochure report summer science writing internship career education community diversity directory argonne national laboratory safety new career education community diversity directory energy environment security facility science work argonne new press release feature storey science highlight new media contact social media photos videos fact sheet brochure report summer science writing internship press release topic general argonne information award honour energy energy efficiency vehicle alternative fuel automotive engineering biofuel diesel electric drive technology fuel economy fuel injection heavyduty vehicle hybrid electric vehicle hydrogen fuel cell internal combustion maglev system powertrain research vehicle testing building design construction industrial heating cooling industrial lighting manufacturing energy source renewable energy bioenergy geothermal energy hydropower solar energy wind energy fossil fuel coal carbon capture sequestration oil natural gas hydrogen nuclear energy nuclear energy modelling simulation nuclear fuel cycle geology disposal reactor nuclear reactor safety nuclear reactor material nuclear system technology diagnostic energy usage energy lifecycle analysis energy storage battery lithiumion battery lithiumair battery sodium battery electricity transmission smart grid energy economy energy policy environment biology computational biology bioinformatic molecular dynamic environmental biology metagenomic terrestrial ecology molecular biology clinical proteomic biomarker discovery interventional biology proteomic structural biology environmental science technology air quality atmospheric climate research bioprocessing ecology environmental modelling tool environmental policy planning geochemistry integrated environmental assessment land reclamation water quality security arm control nonproliferation research reactor conversion biometric biotechnology national security cyber security facility security decision science emergency disaster management policy analysis public health preparedness infrastructure protection hazardous waste management intelligence counterterrorrism vulnerability assessment sensor detector programme chemical science engineering fundamental interaction catalysis energy conversion electrochemical energy storage photosynthesis biomimetic material science complex oxide defect material magnetism metal fatigue nanoscience semiconductor material simulation theory superconductivity surface interface study thin film tribology mathematic computing computer science agentbased modelling applied mathematic artificial intelligence cloud computing computational differentiation geographic information system grid computing information architecture modelling simulation visualisation networking data management parallel computing petascale exascale computing statistic software development supercomputing highperformance computing system architecture design physic lowenergy physic mediumenergy physic highenergy physic accelerator r&d astrophysic collider physic detector r&d electronic design particle physic neutrino physic theoretical physic condensedmatter physic nuclear physic plasma physic synchrotron radiation atomic physic surface science biostructure synchrotron instrument technique xray freeelectron laser xray imaging holography xray scattering detection safety biosafety community outreach tour speaker bureau education ecocar challenge middle school high school undergraduate student internship graduate student internship research opportunity postdoctoral programme science bowl teacher training introduce girl engineering day rube goldberg machine contest science career women economic impact site environmental protection site waste management site infrastructure site sustainability site transportation fleet site pollution prevention site renewable energy site energy water conservation operation leadership institute business diversity technology transfer americas top energy innovator r&d start america procurement human resource diversity mentoring workplace pipeline organisation research division computing environment life science bioscience environmental science mathematic computer science energy global security energy system global security science nuclear engineering photon science accelerator system aps engineering support xray science physical science engineering chemical science engineering high energy physic material science nanoscience technology physic facility centre institute user facility advanced photon source argonne leadership computing facility argonne tandem linear accelerator system centre nanoscale material transportation research analysis computing centre centre joint institute argonne accelerator institute argonne collaborative centre energy storage science centre electrochemical energy science chain reaction innovation computation institute institute atomefficient chemical transformation institute genomic system biology institute molecular engineering joint centre energy storage research midwest centre structural genomic nano design work northwesternargonne institute science engineering risk infrastructure science centre structural biology centre organisation argonnenorthwestern solar energy research centre arm climate research facility centre energy environmental economic system analysis date posted glass warmly argonne nanomaterial make window efficienta team argonne researcher nanomaterial closer holy grail building efficiency technology singlepane window efficiency good multipane lowemission window team recently received million award advanced research project agencyenergy develop technology achieve goal argonnedeveloped technology achieving superlubricity win techconnect national innovation awarda graphenenanodiamond solution achieving superlubricity developed argonne national laboratory won techconnect national innovation award miniscule diamond wrapped graphene friction reduced value superlubricity effect enticing prospect industry making computer hard drive wind turbine scientist create magnetic charge icea team scientist working argonne national laboratory led northern illinois university physicist argonne material scientist zhili xiao created material called rewritable magnetic charge ice permit unprecedented degree control local magnetic field pave computing technology argonne launches tech incubatorthe department energy office energy efficiency renewable energy eere argonne national laboratory announced innovation accelerator programme science energy entrepreneur called chain reaction innovation device step isolating single electron quantum computingif biochemist quantum computer perfectly simulate property molecule develop drug way fastest existing computer decade wind argonne coating show surprising potential improve reliability wind powera researcher argonne national laboratory university akron discovered form carbon coating necessarily designed wind turbine prove boon wind industry technique improve efficacy fuel cellsresearcher advanced photon source argonne found harness quantum behaviour solid oxide fuel cell make efficient robust theyve observed type phase transition oxide material microbiome centre combine uchicago marine biological laboratory argonne expertisethe university chicago marine biological laboratory mbl department energy argonne national laboratory announced today partnership called microbiome centre combine institution effort understand identity function microbe environment argonne join crowdsourcing effortargonne national laboratory join ongoing crowdsourcing effort established department energy develop energy efficient building technology drawing creativity american public technical expertise national laboratory argonne roll version alternative fuel advanced vehicle analysis toolargonne releasing updated version afleet tool reflect latest advance alternative fuel vehicle technology updated emission data free publicly tool user roadmap assessing type vehicle fuel them previous feed back top linked pinterest monthly update argonne national laboratory cass avenue argonne contact direction visitor information research division computing environment life science biobioscience evsenvironmental science mcsmathematic computer science energy global security esenergy system gssglobal security science nenuclear engineering photon science asdaccelerator system aesap engineering support xsdxray science physical science engineering csechemical science engineering hephigh energy physic msdmaterial science nstnanoscience technology phyphysic facility centre institute facility apsadvanced photon source alcfargonne leadership computing facility atlasargonne tandem linear accelerator system cnmcenter nanoscale material tracctransportation research analysis computing centre centre joint institute aaiargonne accelerator institute accessargonne collaborative centre energy storage science ceescenter electrochemical energy science crichain reaction innovation cicomputation institute iactinstitute atomefficient chemical transformation igsbinstitute genomic system biology imeinstitute molecular engineering jcesrjoint centre energy storage research mcsgmidwest centre structural genomic ndwnano design work naisenorthwesternargonne institute science engineering riscrisk infrastructure science centre sbcstructural biology centre energygov department energy office science uchicago argonne llc privacy security notice argonne uchicago","m_szGeo1":"United States","m_szSourceType":"source_general","m_szSrcUrl":"http://www.anl.gov/press-releases","m_Places":["Tours","America","United States"],"m_People":["Rube Goldberg","Zhili Xiao"],"m_Companies":["Argonne National Laboratory","News Press","Diesel","Solar Energy","Waste Management","Particle","Leadership Institute","Photon","Innovations","Computation Institute","Atom","Joint Center","Northwestern","Argonne Institute","Science Center","Research Center","Northern Illinois University","University Of Akron","May Indeed Prove","Marine Biological Laboratory","University Of Chicago","Mbl","Twitter","Flickr","Facebook","Youtube","Pinterest","Google","Aaiargonne Accelerator Institute","Cicomputation Institute","Uchicago Argonne Llc"],"m_BiGrams":["national laboratory","argonne national","science engineering","energy storage","centre energy","department energy","security facility","press release","alternative fuel","renewable energy","electrochemical energy","computer science","science energy","global security","accelerator system","facility centre","photon source","science centre","reaction innovation","centre structural"],"m_TriGrams":["argonne national laboratory","centre energy storage"],"m_SocialTags":[],"m_Topics":[],"m_Industry":[],"m_Technology":[],"m_BiCnt":[10,8,7,6,5,4,3,3,3,3,3,3,3,3,3,3,3,3,3,3],"m_TriCnt":[8,4],"m_iDocBodyWordCnt":1098}
