{"m_szDocID":"331025","m_szDocTitle":"Global rise reported in 2013 greenhouse gas emissions","m_szYear":"2014","m_szDocSumamry":"textArticle -------------------- Global rise reported in 2013 greenhouse gas emissions Justin Gillissept The New York Times SHARES Global emissions of greenhouse gases jumped 2.3 percent in 2013 to record levels, scientists reported Sunday, in the latest indication that the world remains far off track in its efforts to control global warming. The emissions growth last year was a bit slower than the average growth rate of 2.5 percent over the past decade, and much of the dip was caused by an economic slowdown in China, which is the world's single largest source of emissions. It may take an addi","m_szDocBody":"global rise reported greenhouse gas emission justin gillissept york time share global emission greenhouse gase jumped percent record level scientist reported sunday latest indication world remain track effort control global warming emission growth year bit slower average growth rate percent past decade dip caused economic slowdown china world single largest source emission additional year china turned corner slower emission growth runaway pace recent year resume united state emission rose percent declining recent year querbeet vetta getty image number reported tracking initiative called global carbon project published nature geoscience eve united nation summit meeting meant harness fresh political ambition tackling climate change scientist figure showed vastly greater effort needed longterm global warming tolerable limit you longer country later time glen peter scientist centre international climate environmental research oslo helped compile number hand deck now expectation summit meeting low political breakthrough lead ambitious effort scientist emission peak year begin decline world hope keeping global warming upper limit country agreed year ago far plan place close achieving that emission falling gradually recent year developed country part economic weakness strengthening climate policy emission nation european union fell percent increase coal consumption country including germany poland emission decreased sharply britain italy spain york time jerry brown seek electric car california united state emission declining increased burning natural gas power generation emit carbon dioxide unit energy coal nation reported increase coal regained market share trend continue prove challenge obama administration seek institute tighter policy greenhouse gase economy hit hard climate change mohamed nureldin abdallah reuter year slow emission decline west swamped rising emission east trend continued chinas emission grew percent indias percent country constructing coalburning power plant breakneck pace china spending heavily renewable nuclear energy slow growth coal effort largest emitter greenhouse gase emission billion tonne year carbon dioxide burning fossil fuel cement manufacturing united state emission person higher united state datemeta monday ","m_szGeo1":"United States","m_szSourceType":"source_news","m_szSrcUrl":"http://www.cnbc.com/2014/09/22/global-rise-reported-in-2013-greenhouse-gas-emissions.html","m_Places":["China","United States","Oslo","Germany","Britain","Italy","Spain","California","India"],"m_People":["Justin Gillissept","Glen P. Peters","Nureldin Abdallah"],"m_Companies":["New York Times","Getty Images","United Nations","European Union","Obama Administration","Reuters"],"m_BiGrams":["united state","greenhouse gase","global warming","recent year","state emission"],"m_TriGrams":["united state emission"],"m_SocialTags":[],"m_Topics":[],"m_Industry":[],"m_Technology":[],"m_BiCnt":[4,3,3,3,3],"m_TriCnt":[3],"m_iDocBodyWordCnt":307}
