{"m_szDocID":"339734","m_szDocTitle":"Fuel for a Revolution -- Beijing Review","m_szYear":"2014","m_szDocSumamry":"textArticle -------------------- UPDATED:  July 31, 2014 NO. 27 JULY 3, 2014 Fuel for a Revolution The world's largest energy producer and consumer is considering some big changes By Zhou Xiaoyan 下载安装Flash播放器 LOOKING TO GET NUCLEAR: The nuclear power generator with the world's largest installation capacity is shipped out from the production base in Deyang, southwest China's Sichuan Province, to Taishan Nuclear Power plant in south China's Guangdong Province, on August 24, 2013 (WU MINGJUN) On the back of expanding industrialization and urbanization, China's energy demand has been on the rise f","m_szDocBody":"updated fuel revolution world largest energy producer consumer big zhou xiaoyan flash nuclear nuclear power generator world largest installation capacity shipped production base deyang southwest chinas sichuan province taishan nuclear power plant south chinas guangdong province mingjun back expanding industrialization urbanisation chinas energy demand rise year making largest energy producer consumer world external uncertainty international geopolitical front put china producing energy controlling runaway energy consumption pollution problem forced country reduce fossil fuel increase energy efficiency chinese president jinping urged effort revolutionise country energy production consumption habit heading meeting central leading financial economic affair acknowledged china face challenge coping rising energy demand supply restraint huge environmental cost backward technology china working guideline direct energy production consumption coming year accelerate revision outdated regulation china upgrade coalburning power generator fail meet emission reduction requirement continue develop longdistance power transmission line expand oil gas cooperation country central asia middle east america africa country intensify effort energy exploration exploitation building oil gas pipeline storage facility lin boqiang energy researcher xiamen university chinese leadership viewing standpoint national development security revolution energy sector bound impact greatly central authority revolution commonly term reform show determination shift status quo lin analyst innovation administrative governance required affect revolution energy production consumption niu economist state information centre government tank shale gas gas hydrate electric vehicle energyefficient housing areas boost energy revolution wake financial crisis nation nurture energy technology engine drive economic growth niu said structural change china attempt reform pricing mechanism nurture competitive energy market president expert reacted favourably xis call accelerate chinas energy production diversity raise energy efficiency leadership resolve pursuing energy revolution pave nonstate company enter industry foster healthier competition sector lin impressed proposed institutional revolution energy sector task paramount revolutionising chinas energy sectorbreaking monopoly stateowned enterprise soe letting market decide energy price currently chinas energy sector monopolised soe energy price controlled government right now percent energy sector stateowned proportion increasing soe monopoly broken add competition sector lin said chinas energy resource located developed central western region developed coastal region huge energy demand energy output province made tremendous contribution economic development diverting energy betteroff region governmentmandated price worse still energy production process heavily polluted energyrich region situation analogous poor helping rich analyst said lin lack marketbased pricing mechanism make harder attract private capital energy sector reform pricing mechanism energy product progressing slowly partly price tool government macrocontrol policy setting adjusting energy price involve complicated work inside government represent game interest party concerned direct government price intervention lead uncertainty profit making private capital reluctant enter energy sector lin added updated ","m_szGeo1":"China","m_szSourceType":"source_news","m_szSrcUrl":"http://www.bjreview.com/quotes/txt/2014-07/31/content_632067.htm","m_Places":["Deyang","China","Sichuan Province","Central","Asia","Middle East","America","Africa"],"m_People":["Wu Mingjun","Xi Jinping","Lin Boqiang"],"m_Companies":["Revolution","器","Xiamen University","Information Center"],"m_BiGrams":["energy sector","chinas energy","energy production","energy demand","production consumption","revolution energy","pricing mechanism","sector lin","energy price"],"m_TriGrams":["energy production consumption"],"m_SocialTags":[],"m_Topics":[],"m_Industry":[],"m_Technology":[],"m_BiCnt":[6,5,5,3,3,3,3,3,3],"m_TriCnt":[3],"m_iDocBodyWordCnt":420}
