{"m_szDocID":"347661","m_szDocTitle":"Energy Fuels CEO: Why Obama Must Embrace Nuclear Power as Clean Energy","m_szYear":"2015","m_szDocSumamry":"Home   Street Talk   Personal Finance   Economy   Companies   Markets   Investing & Analysis   Insiders   Money Wire   Newsletters Special Jim Rogers Warns: Coming Collapse Will Be Worst \"We Have Ever Seen in Recorded History\" Home | Markets Tags: obama | nuclear power | clean energy | air pollution Energy Fuels CEO Stephen Antony: Why the President Should Support All Carbon-Free Energy Production By Stephen Antony   |   Sunday, 10 May 2015 12:35 PM Close  More ways to share... Stumbled LinkedIn Vine Reddit Delicious Newstrust Tell my politician Technocrati Short URL| Email Article| Comment| C","m_szDocBody":"home street talk personal finance economy company market investing analysis insider money wire newsletter special jim roger warn coming collapse worst recorded history home market tag obama nuclear power clean energy air pollution energy fuel ceo stephen antony president support carbonfree energy production stephen antony sunday close way share stumbled linkedin vine reddit delicious newstrust politician technocrati short url article comment contact print president obama recently announced support nuclear power plant smaller megawatt size known small modular reactor smr clean energy source executive order good start however president endorsement nuclear energy didnt enough fact including entire nuclear sector definition qualified alternative energy resource threaten nation ability energy independent remotely close meeting pledge cut greenhouse gas emission president embrace nuclear power clean energy source subgroup industry current fleet nuclear power plant generate energy avoid billion tonne air emission key point ignored this today surrounded increased amount consumer good require plugged recharged accessible whenever wherever smartphone bigger tvs electric vehicle smart product connecting internet iot modern economy energy intensive widespread efficiency conservation effort case consistent source clean baseload power generation supplied nuclear sector critical ever applaud technological innovation redefining renewable commercialization battery storage solution make renewable competitive however renewable long reaching power generating level nuclear industry clean energy president focus nuclear energy credible bridge fuel natural gas burning natural gas electricity create lot air pollution carbon emission this switched coalfired electrical generation natural gas emit billion tonne tonne carbon dioxide atmosphere single year nuclear energy coexist renewable energy source play vital role helping quickly adopt sustainable lowcarbon lowair pollution energy landscape president expect meet new stringent climate goal energy information administration eia reporting oil output jumped year lot misconception risk form energy production including nuclear yet today nuclear industry vastly year ago including advance uranium production method needed supply today nuclear industry fact modern uranium mining cleaner safer production rare earth element china essential produce renewable energy lead topic energy independence import roughly uranium fuel current fleet nuclear power plant rare earth mineral needed produce renewable china enjoy nearmonopoly production highlighted recent minute piece therefore declaring nation energy independent flawed thinking nuclear power account energy power generation committed reducing air pollution producing domestic reliable clean energy source president move qualify nuclear power clean energy resource smr technology appealing excited president smr technology clean energy solution but shouldnt nuclear facility uranium fuel needed run smr receive clean energy distinction stephen antony president ceo energy fuel nyse mkt uuuu year antony held increasingly senior position technical managerial sector mining uranium industry company including mobil energy fuel nuclear inc power resource inc consulted cameco corp antony served president ceo energy fuel served chief operating officer extensive experience uranium exploration ore production mill processing registered professional engineer graduate colorado school mine hold master business administration university denver newsmax finance right reserved comment close way share stumbled linkedin vine reddit delicious newstrust politician technocrati short url article comment contact print like share share market committed reducing air pollution producing domestic reliable clean energy source president move qualify nuclear power clean energy resource obama nuclear power clean energy air pollution sunday special web powered newsmax recommended join newsmax community comment comment review community guideline posting comment enable comment powered disqus blog comment powered disqus free newsmax ealert email country zip code privacy share email mortgage rate today low rate widget request mortgage refinance powered recommended newsmax commented obamas latest whopper raise social security benefit friday comment storey start labelling social security entitlement lost dismal job report expose obamas liberal failure friday comment what obama failed obama create job did trump call weak job report bombshell friday comment terrible imagine bad liberal hate just yellen trump well happen tuesday comment what recession economy slowly hillary clinton bernie sander plan destroy million job wednesday comment time save remain country fanatical home street talk personal finance economy company market investing analysis insider money wire newsletter newsmax moneynew newsmax health independent american registered trademark newsmax media inc newsmax newsmax world trademark newsmax media inc newsmaxcom newsmax media inc right reserved contact advertise shop archive link privacy policy term condition","m_szGeo1":"United States","m_szSourceType":"source_general","m_szSrcUrl":"http://www.newsmax.com/Finance/Markets/obama-nuclear-power-clean-energy-air-pollution/2015/05/10/id/643733/","m_Places":["Warns","United States","China","Most"],"m_People":["Jim Rogers","Barack Obama","Stephen Antony","Hillary Rodham Clinton","Bernie Sanders"],"m_Companies":["Linkedin","Reddit","Energy Information Administration","Eia","Mobil","Power Resources Inc.","Cameco Corp","Mill","Colorado School Of Mines","Business Administration","University Of Denver","Social Security"],"m_BiGrams":["clean energy","nuclear power","power clean","air pollution","energy source","energy fuel","stephen antony","power plant","nuclear energy","energy resource","nuclear industry","natural gas","friday comment","newsmax media","media inc"],"m_TriGrams":["nuclear power clean","power clean energy","clean energy source","nuclear power plant","newsmax media inc"],"m_SocialTags":[],"m_Topics":[],"m_Industry":[],"m_Technology":[],"m_BiCnt":[11,9,5,5,5,4,3,3,3,3,3,3,3,3,3],"m_TriCnt":[5,5,4,3,3],"m_iDocBodyWordCnt":676}
