{"m_szDocID":"370516","m_szDocTitle":"Information Library - World Nuclear Association","m_szYear":"2016","m_szDocSumamry":"Javascript Required! Javascript is required for this site. Go MENU Nuclear Basics Information Library Facts and Figures Country Profiles Countries A-F Countries G-N Countries O-S Countries T-Z Others Nuclear Fuel Cycle Introduction Uranium Resources Mining of Uranium Conversion Enrichment and Fabrication Nuclear Power Reactors Fuel Recycling Nuclear Wastes Transport Safety and Security Safety of Plants Radiation and Health Non-Proliferation Non-power Nuclear Applications Industry Transport Current and Future Generation Energy and the Environment Economic Aspects Our Association Who We Are What","m_szDocBody":"required required site menu nuclear basic information fact figure country profile country country country country nuclear fuel cycle introduction uranium resource mining uranium conversion enrichment fabrication nuclear power reactor fuel recycling nuclear waste transport safety security safety plant radiation health nonproliferation nonpower nuclear application industry transport current future generation energy environment economic aspect membership publication press press statement briefing event gallery shop member information home information fact figure country profile nuclear fuel cycle safety security nonpower nuclear application current future generation energy environment economic aspect fact figure world nuclear power reactor uranium requirement nuclear generation country uranium production figure heat value fuel reactor database country profile country argentina armenia australia bangladesh belarus belgium brazil bulgaria canada nuclear power canada uranium china nuclear fuel cycle china nuclear power czech republic denmark finland france country germany hungary india indonesia iran italy japan nuclear fuel cycle japan nuclear power jordan kazakhstan kyrgyzstan lithuania mexico mongolia namibia netherland zealand niger country pakistan poland romania russia nuclear fuel cycle russia nuclear power saudi arabia slovakia slovenia south africa south korea spain sweden switzerland country turkey ukraine united arab emirate united kingdom usa nuclear fuel cycle usa nuclear power usa nuclear power policy uzbekistan vietnam asias nuclear energy growth californias electricity emerging nuclear energy country european union nuclear power taiwan uranium africa uranium central asia safety security safety plant safety nuclear power reactor chernobyl accident fukushima accident liability nuclear damage nuclear power plant earthquake mile island accident tokaimura criticality accident radiation health nuclear radiation health effect radiation life occupational safety uranium mining hiroshima nagasaki subsequent weapon testing naturallyoccurring radioactive material norm nonproliferation safeguard prevent nuclear proliferation india china npt nonpower nuclear application overview nuclear technology radioisotope research radioisotope industry radioisotope medicine research reactor smoke detector americium industry nuclear desalination nuclear process heat industry peaceful nuclear explosion transport electricity car nuclear reactor space nuclearpowered ship transport hydrogen economy nuclear fuel cycle introduction nuclear fuel cycle overview uranium work energy world uranium physic nuclear energy uranium resource uranium market supply uranium geology uranium deposit military warhead source nuclear fuel uranium depleted uranium uranium phosphate uranium rare earth deposit cosmic origin uranium mining uranium world uranium mining production uranium mining overview situ leach mining uranium environmental aspect uranium mining conversion enrichment fabrication conversion deconversion uranium enrichment fuel fabrication nuclear power reactor nuclear power reactor advanced nuclear power reactor small nuclear power reactor generation nuclear reactor heavy manufacturing power plant fuel recycling processing nuclear fuel mixed oxide fuel mox plutonium nuclear waste radioactive waste management international nuclear waste disposal concept radioactive waste myth reality synroc decommissioning nuclear facility transport transport radioactive material japanese waste mox shipment europe energy environment clean coal technology climate change science energy analysis power system energy balance implication environment health electricity generation policy response climate change renewable energy electricity responding global climate change potential contribution nuclear power sustainable energy uranium stewardship uranium electricity climate change current future generation nuclear power world today outline history nuclear energy world energy nuclear power acceleratordriven nuclear energy cooling power plant cooperation nuclear power electricity transmission grid fast neutron reactor international framework nuclear energy cooperation lithium molten salt reactor nuclear fusion power plan reactor worldwide nuclear debate nuclear renaissance thorium economic aspect economic nuclear power energy security energy subsidy external cost information index abcdefghijklmnopqrstuvwxyz nuclear basic information fact figure country briefing nuclear fuel cycle current future generation safety security energy environment economic aspect nonpower nuclear application membership publication shop press statement briefing gallery event member contact world nuclear association registered england wale number registered office tower house southampton street london wce united kingdom reuse world nuclear ","m_szGeo1":"United Kingdom","m_szSourceType":"source_general","m_szSrcUrl":"http://www.world-nuclear.org/information-library.aspx","m_Places":["Argentina","Armenia","Australia","Bangladesh","Belarus","Belgium","Brazil","Bulgaria","Canada","China","Czech Republic","Denmark","Finland","France","Germany","Hungary","India","Indonesia","Iran","Italy","Japan","Jordan","Kazakhstan","Kyrgyzstan","Lithuania","Mexico","Mongolia","Namibia","Netherlands","New Zealand","Niger","Pakistan","Romania","Russian Federation","Saudi Arabia","Slovakia","Slovenia","South Africa","South Korea","Spain","Sweden","Switzerland","Turkey","Ukraine","United Arab Emirates","United Kingdom","United States","Uzbekistan","Viet Nam","Asia","California","Taiwan","Africa","Central","Chernobyl","Fukushima","Three Mile Island","Hiroshima","Nagasaki","Europe","England","Wales","London"],"m_People":[],"m_Companies":["Cycle","Our Association","European Union","Renaissance","Our Association Who","Association Content"],"m_BiGrams":["nuclear power","nuclear fuel","fuel cycle","power reactor","nuclear energy","uranium mining","fact figure","safety security","nonpower nuclear","nuclear application","current future","future generation","energy environment","economic aspect","climate change","information fact","figure country","country profile","mining uranium","nuclear waste","radiation health","environment economic","world nuclear","usa nuclear","power plant"],"m_TriGrams":["nuclear fuel cycle","nuclear power reactor","nonpower nuclear application","current future generation","fact figure country","energy environment economic","environment economic aspect"],"m_SocialTags":[],"m_Topics":[],"m_Industry":[],"m_Technology":[],"m_BiCnt":[20,11,9,7,6,5,4,4,4,4,4,4,4,4,4,3,3,3,3,3,3,3,3,3,3],"m_TriCnt":[9,7,4,4,3,3,3],"m_iDocBodyWordCnt":595}
