{"m_szDocID":"370616","m_szDocTitle":"OilVoice | IMAP's Alternative Energy Global Report Sees Heightened M&A Activity","m_szYear":"2010","m_szDocSumamry":"IMAP's Alternative Energy Global Report Sees Heightened M&A Activity Monday, August 2, 2010       Follow @OilVoice Follow @OilVoice   IMAP, Inc., an exclusive global merger and acquisition (M&A) organization, announces the availability of its 2010 Alternative Energy Global Report. The report details M&A activity in the alternative energy industry by country and region for the last 12 months, growth projections for the remainder of 2010 and beyond, and insight into industry trends. Although the global economic recession had a deep impact on worldwide energy demand, the global alternative energy","m_szDocBody":"imap alternative energy global report see heightened m&a activity monday follow follow imap inc exclusive global merger acquisition m&a organisation announce availability alternative energy global report report detail m&a activity alternative energy industry country region month growth projection remainder beyond insight industry trend global economic recession deep impact worldwide energy demand global alternative energy industry continued expand rapidly month demand worldwide energy decline however combined revenue major source alternative energy billion percent government support including stimulus package helped boost global capacity wind percent solar percent biofuel percent additionally time energy smart technology digital energy application power saving appliance electric vehicle attracted venture capital private equity investment renewable energy technology industry faced financial crisis north america europe longterm growth fundamental remain intact quarter quarter industry transaction valued billion total transaction value percent deal versus previous period solar wind accounted percent total dollar volume period term country china highest transaction billion total transaction month transaction billion transaction spain philippine india region asia led total transaction europe north america middle east oilvoice training london smart selling advanced technique growing market share industry downturn day running summary workshop designed initially basic build delegate core selling skill introduce adva information price ketil wig chairman imap energy power industry group said although investor cautious research development spending government corporation amounted billion cost clean technology decreasing technology utilised application decade expect solar photovoltaic installation smart metre energy storage device wind turbine clean technology commodity market mature notable recent m&a transaction completed imap adviser alternative energy industry imap represented ireland power structure maintenance company shanahan engineering sale ukbased international energy service company john wood plc imap represented denmark supplier wind turbine industry skykon investment swedish private equity fund eqt expansion capital imap advised costa rican wind energy developer operator energias renovable mesoamerica sale usbased energy oriented fund owned actis globeleq americas imap advised croatian leading system automation engineering firm exor doo sale selected asset switzerlandbased global leader power automation technology abb addition traditional driver climate change energy insecurity renewable portfolio standard renewable fuel standard building code efficiency regulation drive demand alternative energy richard wottrich senior managing director imap alternative energy group regulatory certainty big driver renewable energy example china initiated law require power grid buy power renewable plant wind farm face stiff fine result huge uptick investment renewable energy sector demand increase expect trend digital energy hydrogen storage system capture storage ccs implementation nanotechnology generate alternative energy future growth energy demand largely concentrated developing economy due demand region emerging market rapidly expand power generation capacity imap adviser predict focus wind solar bio hydropower imap periodically conduct report major industry providing global perspective m&a activity period imap report result internal information gathered completed m&a project imap adviser country world external industry source ","m_szGeo1":"United Kingdom","m_szSourceType":"source_industry","m_szSrcUrl":"http://www.OilVoice.com/n/IMAPs-Alternative-Energy-Global-Report-Sees-Heightened-MA-Activity/9080bbb35.aspx","m_Places":["North America","Europe","Spain","Philippines","India","Asia","Middle East","London","Ireland","U.k.","Denmark","Switzerland"],"m_People":["Shanahan","Actis","Globeleq Americas"],"m_Companies":["Imap, Inc.","Intact","Energy & Power Industry Group","John Wood Group Plc","Exor","Abb","Alternative Energy Group"],"m_BiGrams":["alternative energy","m&a activity","energy industry","renewable energy","total transaction","imap adviser"],"m_TriGrams":["alternative energy industry"],"m_SocialTags":[],"m_Topics":[],"m_Industry":[],"m_Technology":[],"m_BiCnt":[9,3,3,3,3,3],"m_TriCnt":[3],"m_iDocBodyWordCnt":453}
