{"m_szDocID":"370707","m_szDocTitle":"Honda Supporting Growth of California Hydrogen Network with Financial Support to FirstElement Fuel - Oil & Gas 360","m_szYear":"2014","m_szDocSumamry":"Honda Supporting Growth of California Hydrogen Network with Financial Support to FirstElement Fuel  November 19, 2014 - 4:02 PM EST close yes               Honda Supporting Growth of California Hydrogen Network with Financial Support to FirstElement Fuel - Honda contribution of $13.8 million will further expand and accelerate the network of public hydrogen refueling stations - Funding could enable FirstElement to add at least 12 stations to its California hydrogen network TORRANCE, Calif., Nov. 19, 2014 /PRNewswire/ -- Seeking to expand California's public hydrogen refueling station network as","m_szDocBody":"honda supporting growth california hydrogen network financial support firstelement fuel est close honda supporting growth california hydrogen network financial support firstelement fuel honda contribution million expand accelerate network public hydrogen refuelling station funding enable firstelement add station california hydrogen network torrance calif nov seeking expand californias public hydrogen refuelling station network mean support wider introduction fuelcell vehicle honda provide million financial assistance firstelement fuel build additional hydrogen refuelling station state additional state grant combined honda financing enable firstelement add station california hydrogen network firstelement fuel providing vital piece needed successful launch fuelcell vehicle steven centre vice president hondas environmental business development office through collaboration firstelement enable customer experience hydrogen refuelling reliable convenient consumerfriendly vehicle are firstelement received grant totaling million california energy commission earlier year build network station state state california plan invest million hydrogen station development year financial support honda anticipated future grant state california firstelement expand network station percent station this extremely positive step forward advancement fuelcell vehicle state california joel ewanick ceo firstelement fuel were grateful confidence honda shown team hondas leadership development deployment fuelcell vehicle firstelement fuel creating world true retail hydrogen refuelling network developing operating station californias metro areas connector destination location company goal driver fuelcell vehicle travel seamlessly state ina conventional gasoline vehicle today leader development fuel cell honda advocated robust comprehensive network hydrogen refuelling station serve customer honda led industry decade development deployment fuelcell technology extensive real world testing including government fleet deployment retail customer programme united state honda made significant technological advancement fuel cell operation hot subfreezing temperature meeting safety regulation introduction generation fuelcell vehicle fcx honda launched recent fuelcell vehicle fcx clarity real technological breakthrough areas design sedan packaging assembly line manufacturing fuelcell stack size efficiency winning world green car year award honda fcv concept unveiled japan pointing allnew honda fuelcell vehicle slated launch japan launches europe hondas nextgeneration fuelcell vehicle feature fuelcell powertrain packaged completely engine room vehicle allowing efficiency cabin space flexibility potential application fuelcell technology multiple vehicle type future nextgeneration honda fcv anticipated driving range mile honda environmental leadership based vision blue sky children honda working advance technology address society environmental energy concern diverse lineup product technology including fuelefficient gasoline engine natural gas hybrid plugin hybrid battery electric vehicle bevs fuelcell vehicle fcvs today honda targeting percent reduction emission automobile product lineup compared level pursuit vision zerocarbon future company advancing electromotive technology form slated introduce advanced fuelcell vehicle keeping commitment produce vehicle lowest emission plant smallest environmental footprint company broadly addressing emission energy water waste phase product life cycle manufacturing realm include percent reduction waste landfill north america honda working extend green factory green purchasing initiative part supplier north america pursuing environmentally responsible business practise dealer honda demonstrating vision zerocarbon mobility living creation honda smart home davis california opened early capable producing energy onsite renewable source consume annually including energy power honda fit daily commuting ","m_szGeo1":"","m_szSourceType":"source_industry","m_szSrcUrl":"http://www.oilandgas360.com/honda-supporting-growth-of-california-hydrogen-network-with-financial-support-to-firstelement-fuel/","m_Places":["California","United States","Japan","Europe","North America"],"m_People":["Joel Ewanick","Fcx Clarity"],"m_Companies":["Honda","Energy Commission","State Of California","Cell Technology","November 17"],"m_BiGrams":["fuelcell vehicle","firstelement fuel","hydrogen refuelling","california hydrogen","hydrogen network","refuelling station","financial support"],"m_TriGrams":["california hydrogen network","hydrogen refuelling station"],"m_SocialTags":[],"m_Topics":[],"m_Industry":[],"m_Technology":[],"m_BiCnt":[11,6,6,4,4,4,3],"m_TriCnt":[4,4],"m_iDocBodyWordCnt":477}
