{"m_szDocID":"377177","m_szDocTitle":"Tech Times","m_szYear":"2016","m_szDocSumamry":"MENU Tech Science Health Culture Reviews Features Videos HOMEPAGE Tech Gadgets Computers Phones/Tablets/Mobile Tech Wearable Tech Apps/Software Business Tech Internet Car Tech Security Apple Google Microsoft Smart Home Science Space Energy Earth/Environment Animals Material Science Ancient Health Healthy Living/Wellness Medicine Public Health Biotech Neuroscience Culture Movies/TV Shows Video Games Comic Books Geek Life & Style Viral Reviews Comic Books Features Health Culture Advertisement TAG Chernobyl, Nuclear Power, nuclear radiation Chernobyl Nuclear Power Plant Disaster Still Haunts The ","m_szDocBody":"menu tech science health culture review feature videos homepage tech gadget computer tech wearable tech business tech internet car tech security apple microsoft smart home science space energy animal material science ancient health healthy medicine public health biotech neuroscience culture show video game comic book geek life style viral review comic book feature health culture advertisement tag chernobyl nuclear power nuclear radiation chernobyl nuclear power plant disaster haunt world year incident edt rina marie doctor tech time shared google linkedin reddit flipboard stumble fark slashdot mail chernobyl disaster threedecade anniversary happen year ukraine nuclear power plant catastrophe haunt affect people environment year later daniel berehulak getty image advertisement chernobyl nuclear power plant disaster happened year ago now haunt world event book past event part history people contribute negative impact health people environment situation ukraine belarus russia chernobyl foundation report incident longterm effect started flourish the government affected country continue spend resource recovery contaminated areas say back date technician midst reactor system testing sudden jolt power destroyed unit nuclear power plant ukraine combination incident fire occurred afterward released amount radioactive material emergency staff aboard helicopter poured sand reactor remnant stop fire radiation emission poured boron prevent nuclear reaction crew fully area temporary concrete structure called sarcophagus authority cut buried pine forest nearby closed mile area plant all soviet government evacuated approximately people year haunting health health effect incident death worker hour explosion due nonradiological cause outpour radiation incident caused bigger health problem worker died month exposed dose radiation causing develop acute radiation sickness present thyroid cancer radiationrelated cancer linked event children drunk milk contaminated radioactive iodine significantly affected thyroid gland far thyroid cancer linked incident recorded good new percent patient successfully treated expert say however cancer mortality worker staff nearby resident attributed incident day contaminated land amount radionuclide expert gave land level severity derived radiation measurement this animal found thrivein area decade long time unfortunately long bury effect chernobyl nuclear power plant disaster completely effect event expected affect environment people decade come tech time right reserved reproduce permission related article radioactive wild boar flourish fukushima farmland greenpeace government reducing radiation protection areas contaminated fukushima chernobyl chernobyl virtual reality game element named periodic table precious reallife hobbit back year advertisement advertisement newsletter advertisement popular softwareapp microsoft plan kill competition planner succeed smartphone samsung galaxy note detail advanced iris scanner feature android marshmallow launch date revealed healthyliving married fight cancer study advertisement smartphone microsoft surface pro launch date pricing spec report release ram uhd display option softwareapp oneplus finally marshmallow update oxygenos biztech tmobile free pizza free small frosty free movie rental smartphone samsung galaxy owner report lock issue android marshmallow hold update softwareapp kid swipe tinder ups age restriction smartphone smartphone deal unlocked nexus sale auto bmw win lapd beat tesla electric car coming life style life style people psychopathic trait helpful work black ice cream latest summer treat trend here newly renovated pilgrim ship replica mayflower return plymouth float butterfly sting bee quote boxing icon muhammad ali surviving dog dy texas biden launches openaccess database researcher develop effective treatment sleep loss increase heart disease risk shift worker music star entice teen unhealthy junk food beverage study tech science health culture review feature videos contact term condition privacy policy media kit techtime inc right reserved top storey tech time delivered inbox thank","m_szGeo1":"United States","m_szSourceType":"source_general","m_szSrcUrl":"http://www.techtimes.com/articles/151000/20160419/chernobyl-nuclear-power-plant-disaster-still-haunts-the-world-30-years-after-incident.htm","m_Places":["Mobile Tech","Chernobyl","Ukraine","Most","Belarus","Russian Federation","Fukushima","Protection","In Areas","Sale","Tesla","Plymouth","Best","Texas","United States"],"m_People":["Rina Marie","Daniel Berehulak"],"m_Companies":["Apple","Google","Microsoft","Life & Style","Chernobyl Nuclear Power Plant","Facebook","Reddit","Flipboard","Getty Images","Chernobyl Foundation","Greenpeace","Samsung","T-mobile","Tinder","Nexus","Bmw","Lapd","I3","Techtimes Inc."],"m_BiGrams":["nuclear power","power plant","chernobyl nuclear","health culture","life style","plant disaster","tech time"],"m_TriGrams":["nuclear power plant","chernobyl nuclear power","power plant disaster"],"m_SocialTags":[],"m_Topics":[],"m_Industry":[],"m_Technology":[],"m_BiCnt":[6,5,4,3,3,3,3],"m_TriCnt":[5,4,3],"m_iDocBodyWordCnt":549}
