{"m_szDocID":"377138","m_szDocTitle":"Solar cells for the masses | Science! | Geek.com","m_szYear":"2005","m_szDocSumamry":"textArticle -------------------- Solar cells for the masses Subscribing to a newsletter indicates your consent to our Terms of Use and Privacy Policy . More Geek Eco-Cooler air conditioner cools a home without using electricity A new kind of solar cell is set to come to market and possibly revolutionize the use of solar power, or at least the amount of devices it can be used with. The company Konarka Technologies is currently testing a newly developed type of solar cell that is unlike those you commonly see used in calculators and on the sides of houses. These new cells come in flexible strips","m_szDocBody":"solar cell masse subscribing newsletter consent term privacy policy geek ecocooler air conditioner cool home electricity kind solar cell set market possibly revolutionise solar power amount device with company konarka technology testing newly developed type solar cell unlike commonly calculator side house cell flexible strip wide long similar photographic film strip easy cheap make mass produced coating machine strip wired uneven surface due flexible nature meaning integrated number product laptop pdas mobile phone fitted layer panel receive boost electricity exposed sunlight increasing battery life reason panel due advancement nanomaterial nanotechnology allowed plastic nanoparticle mixed solution printed plastic surface solution form structure act solar panel konarka plan solarcell strip made semiconducting particle titanium dioxide coated lightabsorbing dye market year consumer product defence industry siemen plasticbased solarcell based electrically conducting polymer buckyball work read technology review matthew opinion great new world growing energy problem breakthrough continue living solar strip konarkas viable product surely flourish industry save money sell product environmentconscious consumer technology electronic device building vehicle laying sheet solar cell roof save occupant fortune energy cost corporate building built frame glass window laid roof vehicle sunroof solar cell inside cost bit more consumer save fuel cost beginning road diverse cheap solar technology future sunny day bring smile face hot out saving money comment comment ummm est tue rock solar cell paint job vehicle solar cell plaster exterior wall solar cell drive way home wondering dont geneticly modified plant work solar cell post thingy illero nice extra est tue boost energy line clothing wear walk around clothing laptop pdas connect bottom shirt bingo extra power post better est tue solar cell dye cam manufactured chassis injected moulding read liek better source findit good est tue compare conventional solar cell term efficency cost also integrated solar cell roofing example expected replace that fmbeachbum spinach power est tue illero asked dont geneticly modified plant work solar cell storey relate jzoom matthew opinion est tue care useless opinion alien master bigger est tue adding supplemental solar energy house cost enough goal run house free energy solar panel sell back energy company deduct amount supplied bill end month give back use credit future bill cash back people now cost replacement cost tad taste waiting along people moaning electricity bill summer kick back accooled house read energy bill kinda spiffy cancelled est tue texas instrument spheral solar technology back discovered people purchase technology rate proffitable sold technology based tiny len sphere meshed thin aluminium sheet flexible inexpensive efficiency range freakycow good luck est tue roof feet long feet wide power unit produce exlectric bill cubic footage cool wind power solar est tue portion energy needed power building for example photovoltaic portion wait perfect technology perfect technology combination solar wind tidal wave geothermal generator technology make sense contribute energy need resistance ideas born fact power company friendly idea decentralised power company government money spent promote ideas innovative business model huge shift power produced profit people power lovin est tue hope start great house consumer electronic device liking idea hybrid pda run solar lithium ion spider jzoom est tue plant grown produce electrical current itself component grow prolific ivy god forbid lol grass nice green lawn function aestic power house drool illero good est tue pretty jaded waiting life improve solar technology promise term earth space path big hit place california price right sad note power company buy patent raise price reasonable level good rax solar power free close est tue friend built home wanted solar add cost solar electronic boil cost pretty depressing break number solar power company year assuming repair summer cost upfront risk paying substancial good lightning strike year break point guy tend house year take amortorize nre take solar real solar masse long off money spent insulation solar powerhumm est tue power enuff run entire house cancelled free energy solar panel sell back energy company device feed electric electric company tonne paperwork insurance device rental cost month include protection plan responsiable solar system fried electric company electric company dont pay bill balance build electric propertey rentin equipment house solar powerd house hooked electric company taxed sun put property tax wait till technology power device watt size car battery solar wack ugh est tue negative people cost watt hundred dollar solar technology advanced price today expensive compete natural gas oil nuclear coal etc but start close solar profitable government subsidy technology promise offer solar power mass production pat world changing make hydrogen synthetic fuel production cheaper pumping oil ground powering grid daylight hour when energy used directly cost watt people damnproudamerican thinfilm solar cell est tue new selling printed screened solar cell year now btw efficient standard amorphous cell rocketboy hmmm est tue link expected loaded point nausea futureworld revolutionise everthing storey world power big market renewable resource green cool tech expensive manufacture dirt cheap etc ultimately deep link developing mode efficiency panel date but quite single crystal silicon now increasing generation ovonic amorphous silicon ranged hint panel hint year allweather efficency else lot claptrap investor partner potential product green earth policy etc smoking goatchip humble opinion comment freedom grid absolutely correct electronic expensive insurance interlocked system expensive system extraordinarily inexpensive electronic fall line make sense community afford thing individual homeowner still today cost watt exceed estimated american energy council competitive nuclear coal gas hydro energy price including electronic dropped long baby goatguy cancelled est tue wack right looked building home based solar panel wind generator year ago number jive case freakin insurance premium hard time finding insurance company astronomical building figured year back black live place long change higer efficiency solar panel great deal cheaper what there device speak thought power back grid made metre run backward interesting geekzilla est tue pay bill year add capital house back sell sell low cost hydro strong selling point think hand people put solar cell windmill ect resulting lack broad base customer require electricity producer raise price offset loss customer pay time pay now neighbour afford alternative technology which afford due crushing electricity bill dar billion est tue spend billion develop pvs magical spend secure source oil year maxc est tue good point insurance cost ponted year ago people started put windmill property electric company lobby hard make illegal again make cheap hydro everyone infrastructure supported everyone loss say% customer boost cost system crash strain money fix anything dar insurance est tue insurance cost insurance solar panel factor missing here confused hmm est tue photovoltaic panel range price depending efficiency construction factor expensive part complete system batteriescharge system inverter transfer switch lead acid battery housed explosion proof vented container potential ignition sourcesanything sparksthat isnt cheep container heated winter month canada remote community rely solar power rely solar generator required peek power consumption environmental factor limit energy production good start work big head speek goat guy est tue study account inflation closer start cost effective market pretty brainer cost watt today efficiency solar cell relevant case real estate expensive repeat trend people complaining coming decade missing point decade ago solar hundred dollar watt steadily declining closing finish line looked trend people year year most talking number work looked based solar panel inverter inverter dropping price faster solar number start solar drive cost panel today cost silicon solar cell silicon plastic problem reduced problem cost good problem damnproudamerican maxc est tue premise billion oil left wing spew world economy billion result device produce electricy penny kwh basis asserting developed successfully developed successfully govt funding choose fund welfare space project instead because politic problem wind energy est tue problem wind energy nimby not back yard people nimby people wind turbine eyesore offshore wind turbine eyesore people hard offshore wind turbine tour wind turbine wind turbine kill bird migration reported case bird kill wind turbine wind turbine blade rotate slowly bird easily avoid hit turbine wind guy solar est tue country iraq swoop thier natural resource soldier cost watt est tue pay electric company watt onehundredthousandth dollar watt expect impressed solar million time rate renewable resource ridiculous solar long long latest incremental improvement dave jordan est tue dave cost watt ongoing cost cost set system produce system run set ongoing cost run joke est tue clown office screwed squash kind resource second postion iraq funny read too prefer hit people head purse smokin thier hole nano tech est tue technology read transparent solar panel electric window module based nanocrystalline titania solar cell phani mpj bertoz hopkin skryabin tulloch armelo house portable electronic est tue discussion focussed argument solar power residence however benefit technology physical flexibility low weight factor great cell phone portable electronic recharging either charged solar operate solar batterybabe regw est tue enron buddy rape california fooled killing american day excited kerry picked edward running mate gut kerry unite country adding mccain ticket bush kill solar innovation started stop oil buddy making money chance solar product forward bush office winner kerry rebatterybabe est tue cool solar player rax est tue doctored pictured solared powered ipod real renot real est tue picture thinking loud solar cell phone cool too rax renewable power source est tue year child sugar high boy tired jrink immoral est tue green then oil power vast rightwing conspiracy nooe pollute wind turbine violently murder poor bird omg hydroelelectric dam fish swin upstream breeding ground bastard fuel cell mass hydrogen production fry upper atmosphere somehow panic solar big toxic battery store power nighttime day battery end landfill poisening stream run away satisfy whiner suggest million hamster running wheel produce energyoh wait extra methane emission add global warming golly darn ideas people jame beatty jame beatty est tue yes one shoot people winner kerry scare crap vote kerry gimp running mate put nader fur coat send main street portland est tue sound wing zealot bad case hero worship king george message board suited political tirade cross wood geekcom politic put est tue love purchase battery make put cell phone charger night storage power battery well battery send power power company send power poor folk possibility solar wind hydro combine together global warming true sun solar kick wind work hydro put river progress good better bush comment hmmm bush move cuba power source plastic solar cell est tue plastic wetre made petroleum still thought jimjjnn stop nra kerry est tue lokked site phony out date incidence heard till now mass shooting too fetched laughable vote dem year farfetched changed mind quick guess join nra yuk yuk jimjjnn cost watt est tue friend damn proud american right cost watt mass production kick fall panel sprouting rooftop ship coming japanese leading solar revolution sharpe set hit mass production factory pay attention man right guy dauncey guy people bought patent est tue guy division ats canada decent outfit leverage automation technology make solar cell cheaply mrmcfeely damn proud canadian est tue cheer damn proud southern neighbour damnproudamerican guy est tue thing site bcsea biodiesel talk ongoing project algae biodiesel production lot progress there starting point learn guy number optimistic suprised seperate section ethanol specifically cellulose ethanol produce billion gallon year about gas supply growing year gas price are advanced cellulose ethanol method ethanol priced gas before ethanol subsidy gas taxe amazing exact environmental view opposite foreign policy view cheer again damnproudamerican est tue right inappropriately compared watt watt time doh reiterate solar power stop monkeying tiny improvement already pisse invent cell like efficient last whatever called revolutionary spell sound lower lip vibrating tongue pbpbpbpbpb situation middle east fact hydrocarbon messy inelegant anyway gigawatt solar generator now dave living read learn change est tue grid yrs handy instal yourself powerline property cheaper also power company mile line extension system cost adding water catching system added time nuked dinner system reached payback time few see black white badly change design appliance educate public comparing house full phantom load antiquated apliance careless people compare home put cost payback calculation site good luck you stop negative battery warm solar cell cool adios solarman chris cheque augrid corp est wed nano usa based stock tip damnproudamerican est wed platform reelection prime minister paul martin promised wind turbine generating electricity canada election paul martin leading minority government vote party combined paul martin liberal government collapse wind turbine agenda approved party too britain ahead offshore wind development generate electricity wind power lot hot air texas lot powering wind turbine rural texas txu creating wind farm hope txu live ads houston solution wind guy fact anyone est wed tell konarka hoping product year hope produce sceptical optimistic estimate doe price year konarka interested pumping stock price advancing solar technology produce flexible solar cell year lifetime competitive application demonstrate year lifetime doubt product competitive wind year fddoty solar est thu damn proud american right spec cost power home solar sell excess profit year worth nevada dave jordan live learn read power statement pay minute hoover dam cheapest power country november kidding guess person convince idiot statement yourself bush oilrich failure preserve current energy model slow america rest world moving germany japan biggest consumer solar power demand raised government energy policy forwardlooking our currently solar panel installator company wait longer pay panel producer top dollar germany japan now backward energy policy subsidise gasoline contribute massive corporate profit oil company gas gallon year driving hydrid efficient produced now hybrid weaker guess again electric motor acceleration takeoff produce torque gasoline engine giving acceleration time gasoline engine inefficient acceleration ethanol prevalent government subsidy research development grant diverted oil company solar power made solar now sea shiny happy power producing roof good economy joe american remember people bad energy policy preserving current energy model oil bush vote kerry put back road progress make registered there homework pisting yawa est thu iyot kayat bilat mga wala moi ayo kolitogkayat politic est sun talking people year solar wind power found majority percent conservative minded people people save move country mountain tend type person type resourceful hear leftminded enron bush big boogey man keeping locked status quo dont remember clinton gore yrs gore made big green oil stock forget notice type people solar conserving cheap worse government isnt pay wander back speed picking good movie bottle wine good free rarely easy what wrong people day rate people pop suprised totally tit already guess talk cheap bush hater type jump good themselve terrorist bay personal action else act make difference voting multimillionaire jet setter fix problem naive solution closer think read chris chris cost watt est fri fascinating people whove installed solar electric system cost watt home offgrid cost cdn connect grid pretty nobrainer spend system however cost watt system day battery backup run guerrila grid interconnect system see homepowercom safe illegal area battery backup professional installation cost work myself initial installation professionally solar panel cost for newest one surprised expected california rebate panel price rebate amount inverter charge controller metre wiring load disconnect etc etc price add derek cost oil stupid est tue include day ago cost solar watt uncompetitive cost current energy oil natural gas etc remain constant wont buy wind solar soon anotherproudcanuck cut cost est wed bought home seventeen large cost cost heat cool outrage electric month gas mention square feet live limited income way money like looked way cut cost repair found lighting watt put watt left room revampted heater efficiant started putting solor heat roof found combination working gether pulled inside wall insolated wall wall husband thought quack monthes elictric average month gas month started way money saved added custom panel order neighbour hood historical hid mess look end sventeen year elictric company paying hefty break taxe sold house average house brought great return sold walked happy owner lot money pocked make simple thier calling stupid hear cut make cutting luxury reasonable cost hard pay electric cost cut buying love car grand pianos chalk youngster good measure turned planning built dream home square feet electric company gas company product home lived plan giving luxury annual income year lost husband car reck live rene cut cost est wed bought home seventeen large cost cost heat cool outrage electric month gas mention square feet live limited income way money like looked way cut cost repair found lighting watt put watt left room revampted heater efficiant started putting solor heat roof found combination working gether pulled inside wall insolated wall wall husband thought quack monthes elictric average month gas month started way money saved added custom panel order neighbour hood historical hid mess look end sventeen year elictric company paying hefty break taxe sold house average house brought great return sold walked happy owner lot money pocked make simple thier calling stupid hear cut make cutting luxury reasonable cost hard pay electric cost cut buying love car grand pianos chalk youngster good measure turned planning built dream home square feet electric company gas company product home lived plan giving luxury annual income year lost husband car reck live renee silicon king est tue yes distant future alternative silicon solar cell design fruition time yet thin film solar cell promoter promising low cost largevolume year yet single crystalline csi multicrystalline mcsi silicon solar cell have largest market share over enjoing now yes explosive wireless world require lowefficiency low cost solar cell application type thin film solar cell along asi cell niche market however larger power requirement csi mcsi cell sometime larger power mikeoh saving planet est sat found save recharging small battery solar garden light rainwater flush toilet drinking water main miniscule bit cut water bill half foresight bit world stop fannying late phil reduk yawa est wed taka lang iyota ninyo inyong mga mama kayater cover car chasis electrical car est wed yuri mxico eney est mon uncle hit car car reck year polise department haihaishi est mon ineed anser eney hurry haihaishi hay est mon haihaishi est tue est tue est tue ","m_szGeo1":"United States","m_szSourceType":"source_news","m_szSrcUrl":"http://www.geek.com/science/solar-cells-for-the-masses-555756/","m_Places":["United States","Est","Well","Most","California","Ee","Best","Canada","Iraq","United States Soldier","Jordan","Atmosphere","Us","Portland","Cuba","Middle East","Britain","Texas","Houston","Nevada","America","Germany","Japan"],"m_People":["Guy Dauncey","Dave Jordan","I.l. Skryabin","G.e. Tulloch","James Beatty","Mcfeely","Paul Martin","Moi Ayo","Taka Lang"],"m_Companies":["Konarka Technologies","Plastic","Technology Review","Matthew's","Texas Instruments","Path","Electric Company","American Energy Council","Jive","Goat","Enron","Nra","Guess","Revolution","Augrid Corp","Martin's","Txu","Renee"],"m_BiGrams":["solar cell","cost watt","wind turbine","solar panel","solar power","electric company","est wed","solar technology","power company","damn proud","cut cost","month gas","square feet","way money","wind power","solar est","solar wind","cost solar","mass production","low cost","silicon solar","offshore wind","turbine wind","watt est","pay electric","cell phone","paul martin","current energy","energy policy","company gas","est mon"],"m_TriGrams":["silicon solar cell","cost watt est"],"m_SocialTags":[],"m_Topics":[],"m_Industry":[],"m_Technology":[],"m_BiCnt":[29,11,11,10,9,7,7,5,5,4,4,4,4,4,3,3,3,3,3,3,3,3,3,3,3,3,3,3,3,3,3],"m_TriCnt":[3,3],"m_iDocBodyWordCnt":2943}
