{"m_szDocID":"377696","m_szDocTitle":"How inefficient are microprocessors? | Chips | Geek.com","m_szYear":"2007","m_szDocSumamry":"textArticle -------------------- How inefficient are microprocessors? Subscribing to a newsletter indicates your consent to our Terms of Use and Privacy Policy . More Geek Nvidia: virtual reality will take another 20 years to fix As regular Geek.com readers will know, I have recently purchased an AMD Athlon 64 X2 Dual-Core Processor. It's a 4400+ rated at 65 Watts. Now, when I read the sign on the front of the package which says “65w” I began thinking to myself: Here is a dual-core processor, one capable of doing two things at one time through two literal cores, a processor with virtualization","m_szDocBody":"inefficient microprocessor subscribing newsletter consent term privacy policy geek nvidia virtual reality year fix regular geekcom reader know recently purchased amd athlon dualcore processor rated watt now read front package began thinking myself dualcore processor capable time literal core processor virtualization bit logic built processor full dualcore energy efficient singlecore athlon previous process generation those efficient due process shrink efficient due fact core caches complete discrete set logic power budget beastie wouldve expected process shrink doubling internal component make microprocessor energyefficient dualcore configuration amd processor either intel well benefit power distribution single piece silicon recognising laymen power required distribute power core small percentage actual power core logic computation rest propagation insight post geek realworld flatly defy logic comment comment est mon effect physic namely thinner junction shorter channellength result lower onresistance for number electron gated lower power consumption factor industry handle gateleakage regularly suppresse opportunistic waste energy fewer electron shuttle order represent local number electron required scale directly process dimension due distributed capacitance effect overcoming sheet resistance newer processor physic work direction step pursued shut section chip nanosecond used cut current flow together goatguy hmmm est mon big paralell car engine firstly cylinder needed push car steady rate knot smaller thing stroke bore size suit engine task real fast slow alot work fuel injection refinement reduce fuel consumption akin highk metal whatever tune length header akin sse instruction bolted side add efficiency engine alloy steel engine block die shrink reducing weight increasing efficiency further draw parallel intel monopoly back car huge slow inneficient happy suited need petrol scare happened amd serious efficiency important coincidence maybe then guess human nature headley line est mon confused processor family core duo case similar power rating thermal power design operate frequency example from intel spec finder ghz tweak tweakboy bla bla bla est mon care microprocessor matter point big picture physic expert engineer fix fueldriven economy fast fucked wake joehaglund rejoehaglund est mon watch language signed agreement registerred expected honour fact rant energy left consumption level remaining reserve represent year oil year natural gas world fossil fuel year hat that est mon exchange paragraph assume benefit hodar joe energy etc est mon joe sentiment felt unique essentially time history singlechip computing power consumed nextgeneration family processor slightly down down grand energy equation allude personal level chip hum watt watt burst watt watt burst kwh kilowatt hour make precious chowder watt time hour year kwh kwh world efficiently inexpensively harvest renewable essentially limitless clean energy store tap doubt drive take car megajoule kilowatt hour juice year square metre temperate desert solar conversion hydrogen gas energy car square metre desert thing tap geothermal consequence actually iceland net exporter energy aluminium take prodigious amount electricity separated ore hydrogen gas geyser geothermal field northern california supply energy san francisco san jose bad smallish field too yellowstone time capacity cool significantly year problem alway water wind bad fickle nevertheless exploited hydroelectric dam form tapped out well talk wave power environmental issue there time time ethanol whateverol citing brazilian exmplary natch tropic plant material inefficient make dent desert world big nearlyworthless stretches land perfectly suited kind enterprise recent innovation tickeled idea roundtheworld superconducting transmission line distribute juice produced sunny side fortune eventually make sense cost refrigeration temp line far lower cost electricity lost conventional line carrying capacity wasting power generated heat heat heat heck efficient computing chip goatguy problem hydroelectric est mon govt hoover dam running capacity due limitation water generation limitation due govt recent legal issue noncompetitive clause taxpayer financed resource essentially boil argument taxpayer finance build hoover dam dam generate jigawatt obscene amount free power energy company complain compete dam pay taxe wage labour material shipping insurance processing cost business fair compete entity essentially operate free taxpayer financed net result immense project function flood prevention mechanism allowed law generate power pay maintenance hoover dam generated potential power mid shame power significant portion las vegas hodar glad est mon goatguy biodiesel freak future estimate oil natgas technology happen money spent battery technology fuel technology energy efficiency fact efficiency cpu low reason leave computer everybit help case point combustion processe plant gain increase power output energy sold offmarket offset reduce price point research money feasible option put dent world valid reason spend money copolymer battery increase power output life making electric car car now research needed reclaim stranded gas field offshore oil rig capturing natural gas due space storage limitsm flare natural gas oil field barrel oil field huge waste research small reactor convert low weigh gase low weight liquid fuel reclaim stranded natural gas more solar power efficiency largest generation plant highest efficiency solar panel mirror liquid salt classic turbine technology lastly develope efficient method generating power heating water running turbine efficiency known dont stream efficiency drop dont lot room research drop tech sector move sector lot impact world asdfasdfasd hoover dam est mon argue bit hodar comment firm power spead area arizona percent boulder city percent note power nevada las vegas water city metropolitan water district southern california pump pump water grow uss food lot food type feed water socal city anual average power output billion kilowatt hour agree point sell power bet billion kwhr hoover dam water areas produce power reduce water level store effect people water crop watered complicated power damsand fact dam flood prevention water storage mechanism create power put power asdfasdfasd free energy est mon take grow refine distribute maintain step cost money live excel energy option wind energy not wind energy cost normal rate assume excel make profit margin selling either stock holder accept less assume kind government subsidy windfarm expense form tax credit free land another artificially lowered taxpayer dollar cheaper tenessee vally authority testbedding sterling cycle solar array farm cost predict fall short funding storey thay existing solar closer pay looked solar riduculously expensive break cost decade alchohol take similar refining process facility oil cost cheaper either coal gasification cheaper pollute worse nateral gas wonderful oil nucleor france electricty good luck tree hugger that science economic burning stuff pretty simple nature job you fossil fuel burn coming ground make beating cost equation pretty tall order fill inconvienient truth alternate form energy multiple anytime people accept significantly higher cost everytime gas ready moronic protest contrary reasdfasdfasd est mon hydroelectric capacity hoover dam hodar reee est mon nuclear france electricity good luck tree hugger that navy full nuclear vessel battle operating perfect record close year summarise good design build ground based reactor complex proven design unfortunately work nuclear plant unique france select model properly sized model brought online area designed for foolishly build custom reactor money necessary timetable met nuclear facility essentially mothballed online hodar efficiency speed est mon power efficiency hold speed race continue unabated important instruction cycle instruction conflict reduce efficiency unfortunately fdc nuclear answer est mon nucleor france electricty but good luck tree hugger that worked national power back earlymid france nuclear decommission nuclear power station cost back astronomical needed build brand nuclear power station generate electricity bring profit cover cost decommissioning nuclear power station year decommission nuclear power station build nuclear power station decommissioning exponential cost equation ridiculous pursue and mid cost decommissioning increased increasing stringent environmental requirement started nuclear waste storage horrible legacy leave generation deal hope future energy supply renewable especially solar technology fusion reaction offer lot promise energy directly fom reaction turbine etc tech infancy decade away however increasing energy efficiency occur parallel development starting now moose est mon alchohol take similar refining process facility oil cost cheaper either coal gasification cheaper pollute worse nateral gas wonderful oil nucleor france electricty good luck tree hugger that hmmmmmmm truth making ethanol simpler refining crudeye fact distillation purify true gasifying enthanol talk hear today similarity distillation remove water ethanol shipping hydrophillic pumping vast pipeline mean pick lot water redistilled destiation ethanol issue crop grown suggest gasify black liqour extra energy run syn gas catalyst fisher trophes process make alchoholsthis cheaper based ethanol research year mass production lastly ethanol efficient make butanol worldsmore efficient current gas hydrophobic make easily ethanol coal gasificationnew gasifier pyrolosis unit polluting combustion technology place eastman chemical late prove emission combustion side note eastman chemical running coal gasifier consume rail car day syngas make steam burn syn gas fisher trophes syn gas make chemial feed stocksthere gasifier coal state running big problem coal power production current planned installation leiry switch technology fact coal power plant online combustion lastly nuke clean compared coalsince nuke plant start made tonne grade radioactive waste coal power production make million tonne low grade radioactive waste yearevery trace element add coal burn huge amount nuke reactor pebble bed reactor fuel pellet pumped reactor critical mass pebble drop bottom hour glass sand sand fall top globe fall bunch globe pellet mass small reach critical massso pump fail reactor stop completely fail safe nuke model flawed design top fuel load reactor bascially scaled model ship make problem refuelling reactor offline plug flow reactor continuely pushing fuel plug reactor rate outlet fuel spent fuel downtime asdfasdfasd hodar est mon fact werent busy dissing joe time proof read second assume benefit start year left retarded doh hodar est mon dam agian power production firstthey irrigation western dam flood prevention lastly power production run correctly ensure crop water flood prevented lastly pay dam produce power pay explained pump water fail solve likelyhood fail produce power dry summer month water level dip low power production winter month feel dam run power fail meet original requirementslook kid lived flood plain dam flooded year dam builtafter flood year army corp engineer handed dam power company started run dam produce power flood control second mean winter higth extremely produce power summer storm inches rain hour emergency flood house lot people failed dip dam low anticipate rainy winter month fail reason dam asdfasdfasd forgot hoover est mon link hodar horse mouth las vegas firm power production drinking water recheck maximum power year dam produce billion kwhr year plant produce megawatt mean maximum capacity power billion kwhr year produce theoretical max assuming water height amount optimum yearnot happen provide irrigation drinking water desert las vegas socal arizona utah etc care produce power dam hoover thought power water desertand feeding huge amount mainstream produce letuce asdfasdfasd wow est tue process deal world waste supplement dwindling supply oil slow global warming also save lot money interesting read surprised written feel dark apologise lashing community this computer fast power efficient sufficient productivity general population lot them ive heard govt read global warming biggest threat mankind happen year know read hear make sense ice cap melting chart clear reaching turning point cool video watched talk threat mankind earth enjoy too called day earth apologise community lashing out make sense myself joehaglund correction est tue reasdfasdfasd est tue misunderstanding dam full production capacity dam maximising poweroutput dam primary reason existence flood prevention however turbine removed offline due regulatory water bypass lane routed past generator wasted energy generation managing height water job corp engineer reason dam generate maximum power water flow them output low maximum power generation low expect constant power output dam rainfall unpredictable however dam make water allowed flow through hodar rejoehaglund est tue ice cap melting chart clear reaching turning point ice cap mar melting too man fault sun cycle too cycle sun measured year range coincidentally sun output fluctuation closely match weather pattern seeing carbon dioxide theory state fear michael crighton solid book book fiction jurasic park solid science storey hodar hodar est tue acknowledge fact contributing insignificant suppose deforestation city act huge heat sink effect weather cycle happening sun amplify damage minimise mattter opinion doh point cost more people vote wallet est tue form alternate power cost more bit fact local wind alternative close governemnt subsidy cost more state art solar expensive cost ten thousand normal home take decade pay single repair unreasonable expectation alcohol energy effiecient entire planting growing cycle oil have compete food supply vary depending weather just food large biological foot print service million american vehicle road today case partial solution replacement nucleor work tree hugger produce pretty nasty waste compared other nasty stuff backyard stuff decade gore tree hugger bretheren recently discovered internet make technology much expensive place time taxpayer money throw hump bottom line people wanted pay lot stop global warming break oil economy tomorrow dont forget liar mouth watch money problem science point usa save energy tax est tue fat wive suvs gas make buck gallon thatll shorten line local mcdonal starbux drive thru tax electricity thatll geek turn computer router leave night rich drive suvs make overindulgent middle class energy efficient fix problem ronjeremy lol est tue wanted point fact agree alcohol based fuel horrible ideas due vast amount need brazil ethanol sugar sugar cane failing utilise cellulose hemicellulose liginalso sugar efficiency sugar turned ethanol lost point forest product industry utilise mass basically entire tree replant tree cut down life cycle tree this cut down limb left forest nutrient land tree lumber mill bark off tree cut maximise lumber size waste chipped pulp mill bark burned hog fuel burned generate power stream mill either lumber pulp mill chip digested reduced pulp point black liqour pulp black liqour cumbusted recovery boiler recover inorganic cooking chemical generated stream power mill need pulp paper machine quality product recycled back process tree basically underutilised portion limb bioorganism eat chip storage pulp mill industry utilise mass source industry product recycled rate paper lumber recycled combusted make power discarded make cellulosicethanol modify process bit combustion black liqour gasify create syn gas stream rich hydrogen carbon monoxide stream burned create power combustion process yeild pulp mill power steam need question extra power idea burning send fisher trophes process generate fuel based hydrocarbon including ethanol sell power gridif account hog fuel burner power boiler equation generating powerso reduce burning extra syn gas make fuel sell power ideal forest product industry green industry already ideal ethanol extra crop forest replacing removing product paper lumber year round crop produce current gas price mill convert ultimatly tree mass efficiency thermodynamic efficiency nuke safe waste generated small compared power source waste nasty vitrified stored solid state fairly inert compared prior form basically france suggest dump glass cube pellet ocean fan politic entering debate gore moron basically suggesting ideas follow house power use write congress man woman funding battery research long life power yield electric car option especially city driver short distance commuter cellulosicethanol research oppose corn based subsity ethanol worse efficiency making ethanol way asdfasdfasd biodiesel est tue indian nut seaweed variety yield excess gallon oil acre grown arid place processing yield rickgeek rick est tue biodiesel issue common use good option production make area grow asdfasdfasd argument est tue hodar mar breakthrough study year old discredited scientific community culprit sun our giver life voting wallet vote wallet complete fck planet anymore vote brain lot job keeping planet alive future generation nuclear energy unfortunately option demand rediculous waste yield nuclear energy waste tricky bit dumping ocean worst idea heard while fling space great suggestion nuclear waste add nearly much atmosphere burning coal major point lose ignoring environmental need favourite food source fish petrolium forest which nice place visit venice holland florida sea level therealmark real mark est wed hodar comment sun cycle valid unproven idea bad talk global warming worry pumping chemical atmosphere include water vaporye people water vapour greenhouse gas highest heat capacity damaging short termnow short term eventually turn rain enter atmosphere water vapour carry huge amount energy heat gase gather energy sun phase change back liquid dumping vitrified radio active waste ocean talk france thisfigure radioactive waste sandthen store mine dumping super deep ocean trenches raise radioactive level part ocean due encapsulated nature waste ignoring environmental need speak forest destroyed talk preceive destroying forest world nation break world due illegal logging poor citizen country example amount forest land increasing year logging sustainable green product produce tree petrolium add stop wasting burning make product hard time making run quality life fall current waste amazing feed stock voting wallet make living doesnt matter country vote tech hold current tech subsidise bastard plan corn ethanol ethanol great money put sustainable economic ideas subsidising corn taxing foreign sugar creating law inact alternative fuel explicitly write emergy tech major industry people deem enviromentally unfriendly face voting nature right american people world idea voting for duped campaign telling truth fairy tale science community looked determine approach spend money research alternative fuel common public vote single item party line etc asdfasdfasd hodar est wed sir wake dont year human huge contribution speedy cycle global warming dont are unbelievable nuclear quote therealmark waste tricky bit dumping ocean worst idea heard while fling space great made laugh ocean idea plain stupid agree thinking day age flinging shit space wow astonishing seriously major effect flinging waste space doubt slightest idea let play second assuming fling stuff space space assume ate blackhole plain die outi dunno wrong idea sound afraid nuclear energy answer joehaglund sir rick est wed back gallon acre linky acre time looked square feet litre oil square foot plant material pretty suspicious claim density energy represented quart oil gallon diesel week year covered patch acre size plant photosynthesis efficient converting light biomass efficient algae perfect growing condition rest plant world muddle grant plant emminently easier grow cover huge tract land solar cell contraption ultimately solar conversion efficiency nearzerowater consuming desert solar array trump all practically run decade generate prodigeous quantity direct electricity instantly shippable grid world country depend gross energy term acre metre solar cell generate kwh annum power average car year now make significant dent require half vehicle hydrogen mechanism approachable problem car divided acre solar cell divided mile square mile blip land compared million square mile desert matter what equation coming back thing one scale solar cell production big business commercial size efficiency scale lot good engineering knowhow silicon great gift god ubiquitous sand goatguy goatguy est wed understood solar cell efficient placing vast array mirror desert aim central point central point column molten liquid salt mirror transfer heat liquid salt passed heat exchanger water tube side water converted hig pressure stream run pressure stream turbine method easier run maintain array solar cell scale solar array dump money battery tech time electric car pratical efficiency upward trump classic steam turbine technology asdfasdfasd goatguy est thu link wrong theoretical maximum gallon acre updated information rick est thu critically read line cut picked doe left making substantial gain yield compared doe work way but sustain average yield gallon acreyear algae system spread yield key wordingonly make real yeild par crop based yeild gallon acre depending plant biodiesel bad utilised current feed stock replacing million acre pond algaewhere evaporation huge problem production needed pump water specifically salty water seaweed pumping vast amount water state desert small task mean energy free technology emerging utilised raw material replace upward current fuel combination energy reduction fuel need utilise material spent energy moving starting system energy expended gain small compared picture crop based fuel ideas infrastructure transportation fuel road way piping practical ethanol biodiesel due water organism eating biodiesel storage issue biodiesel limited life time buggy storing oil easier longer ideas convert diesel run oil directly modification cost heat oil add heated fuel tank start rig diesel warm convert running oilthis production cost biodiesel dont make storage transportation easier glycerol made biodiesel tech highly doubt cost low biodiesel people large facility suggest due added cost including transportation utilised tech transported road system utilixed mass based thermodynamically based asdfasdfasd air car est sun thread dead love subject matter frenchman spent year life creating hybrid car sort car run compressed air when combined petrol engine reaches top speed mph run car air mph range mile india order car yay start world country therealmark est mon est mon est mon ","m_szGeo1":"United States","m_szSourceType":"source_news","m_szSrcUrl":"http://www.geek.com/chips/how-inefficient-are-microprocessors-564389/","m_Places":["Take","Est","Along","Iceland","California","San Jose","Yellowstone","United States","Dam","Las Vegas","Us","Arizona","Boulder City, Nv","Nevada","Socal","France","Uk","Fisher","The States","Socal, Arizona, Utah","Brazil","Moron","Venice","Florida","Mark","India"],"m_People":["Michael Crighton","Al Gore"],"m_Companies":["Nvidia","Amd","Intel","Intels","Guess","Indeed","Metropolitan Water District Of Southern California","Excel","Navy","Balled","Eastman Chemical","Eastman Chemicals","Critical Mass","Ive","Bottom Line","Mill","Diesel","Brains"],"m_BiGrams":["est mon","hoover dam","produce power","tree hugger","power production","solar cell","nuclear power","power station","syn gas","global warming","natural gas","flood prevention","las vegas","power output","good luck","luck tree","hugger that","black liqour","pulp mill","est wed","kilowatt hour","make sense","electric car","liquid salt","sell power","billion kwhr","solar array","nucleor france","france electricty","fisher trophes","gas make","coal power","radioactive waste","huge amount","hodar est","dam produce","maximum power","ice cap","cost more","rick est","nuclear energy","gallon acre"],"m_TriGrams":["good luck tree","luck tree hugger","tree hugger that","nuclear power station","nucleor france electricty"],"m_SocialTags":[],"m_Topics":[],"m_Industry":[],"m_Technology":[],"m_BiCnt":[22,6,6,6,6,6,5,5,5,5,4,4,4,4,4,4,4,4,4,4,3,3,3,3,3,3,3,3,3,3,3,3,3,3,3,3,3,3,3,3,3,3],"m_TriCnt":[4,4,4,4,3],"m_iDocBodyWordCnt":3279}
