{"m_szDocID":"383344","m_szDocTitle":"New $20 Million XPRIZE Aims to Tackle CO2 Emissions from Fossil Fuels - Oil & Gas 360","m_szYear":"2015","m_szDocSumamry":"New $20 Million XPRIZE Aims to Tackle CO2 Emissions from Fossil Fuels  September 29, 2015 - 8:02 AM EDT close New $20 Million XPRIZE Aims to Tackle CO2 Emissions from Fossil Fuels Global Competition Challenges Innovators to Develop Breakthrough        Technologies to Convert CO2 into Valuable        Products At Fortune’s        Brainstorm E conference today, XPRIZE Chairman and CEO Peter Diamandis announces the $20M        NRG COSIA Carbon XPRIZE , a competition to address CO2 emissions from fossil fuels. With registration opening today, teams are        challenged to develop breakthrough tech","m_szDocBody":"million xprize aim tackle emission fossil fuel edt close million xprize aim tackle emission fossil fuel global competition challenge innovator develop breakthrough technology convert valuable product fortune brainstorm conference today xprize chairman ceo peter diamandis announce nrg cosia carbon xprize competition address emission fossil fuel registration opening today team challenged develop breakthrough technology convert product highest net value cosponsored nrg cosia year competition include track technology tested coal power plant natural gas facility living age unprecedented technological progress prosperity driven energy diamandis yet energy burning fossil fuel leading contributor climate change embarking urgent step xprize energy roadmap incentivizing clean positive energy future addresse suite grand challenge international energy agency percent world energy supply derived fossil fuel cleaner energy source rise energy demand expected grow percent making carbon mitigation solution urgent challenge greater critical ensuring clean affordable abundant energy emission fossil fuel continue leading contributor climate change carbon xprize address global emission incentivizing solution convert liability asset carbon xprize incentivize breakthrough technology convert product suite product alternative cement concrete building material chemical manufacture variety industrial consumer good lowcarbon transportation fuel possibly product altogether carbon unique challenge move low zeroemission future continue fossil fuel meet current energy demand sicily dickenson chief marketing officer nrg highly effective xprize process engage world brightest mind solution help solve emission problem simultaneously create viable product day emission contribute climate change continually working improve environmental performance oil sand dan wicklum cosia chief executive competition catalyst accelerate progress cleaner global energy future converting emission valuable product team win money energy future win prize xprize appoint judging panel evaluate technology approaches developed team competition xprize appoint thirdparty scientific advisory board expert advise variety approaches conversion carbon xprize part xprize growing portfolio energy environment prize longterm vision accelerating revolutionary energy technology move world clean abundant energy future information intent compete visit carbonxprizeorg xprize founded xprize leading organisation solving world grand challenge creating managing largescale highprofile incentivized prize areas learning exploration energy environment global development life sciencesactive prize include lunar xprize global learning xprize qualcomm tricorder xprize adult literacy xprize information nrg energy nrg leading customerdriven change energy industry delivering cleaner smarter energy choice building strength nation largest diverse competitive power portfolio fortune company nrg create reliable efficient conventional generation driving innovation solar renewable power electric vehicle ecosystem carbon capture technology customercentric energy solution nrg retail electricity provider serve million residential commercial customer country information connect nrg energy follow cosia cosia canadas oil sand innovation alliance alliance oil sand producer representing percent production canadian oil sand cosias vision enable responsible sustainable development canadas oil sand global energy source delivering accelerated improvement environmental performance collaborative action innovation areas greenhouse gase land tailing water cosias inception member company shared environmental technology worth million follow source version businesswirecom xprize ","m_szGeo1":"","m_szSourceType":"source_industry","m_szSrcUrl":"http://www.oilandgas360.com/new-20-million-xprize-aims-to-tackle-co2-emissions-from-fossil-fuels/","m_Places":["Canada"],"m_People":["Peter Diamandis","Diamandis","Dickenson","Dan Wicklum"],"m_Companies":["Nrg","Energy Future","International Energy Agency","Google","Qualcomm","Nrg Energy","Facebook","Twitter","Alliance"],"m_BiGrams":["fossil fuel","oil sand","emission fossil","carbon xprize","energy future","breakthrough technology","technology convert","climate change"],"m_TriGrams":["emission fossil fuel","breakthrough technology convert"],"m_SocialTags":[],"m_Topics":[],"m_Industry":[],"m_Technology":[],"m_BiCnt":[7,5,4,4,4,3,3,3],"m_TriCnt":[4,3],"m_iDocBodyWordCnt":455}
