{"m_szDocID":"389386","m_szDocTitle":"Where Do the Presidential Candidates Stand on Environment and Energy? - Scientific American","m_szYear":"2008","m_szDocSumamry":"textArticle -------------------- Scientific American Where Do the Presidential Candidates Stand on Environment and Energy? From drilling for oil to climate change, the answers may surprise you By Nikhil Swaminathan on September 24, 2008 5: Water Shortage | Renewable Energy (Solar, Wind, Geothermal) Global Warming: Is It Man-Made? The Democratic presidential contender, Sen. Barack Obama (Ill.), acknowledges that climate change is real, man-made and an \"immediate threat.\" From a July 2007 speech on the floor of the Senate: \"I know that when it comes to the word 'carbon,' the range of views among","m_szDocBody":"scientific american presidential candidate stand environment energy drilling oil climate change answer surprise nikhil swaminathan water shortage renewable energy solar wind geothermal global warming manmade democratic presidential contender sen barack obama ill acknowledge climate change real manmade immediate threat speech floor senate word carbon range view colleague varied complex senator carbon human activity contribute climate change threat immediately require emission reduction strong capandtrade system arizona sen john mccain republican candidate sen joe lieberman iconn introduced climate stewardship act senate which break hardline republican acknowledge human activity accelerated global warming propose all energy solution called lexington project stem remark made wind turbinemanufacturer portland ore may for century profit motive basically led directiontoward machine method industry oil gas enormous good industrial growth beneficiary national prosperity built cost counting noticed terrible cost added nowin atmosphere ocean natural world wild card mccain strong record regard global warming running mate alaska gov sarah palin recent interview changing environment affect alaska state location attribute manmade softened stance interview abc newss charlie gibson man activity contributing global warming reducing carbon emission obama plan invest billion dollar decade fund private effort develop alternative energy put million mile kilometre pergallon plugin hybrid road plan raise fuel economy standard percent year institute capandtrade system limit industrial carbon emission carbon credit company buy pollute allowed auctioned market set government ultimate goal reduce carbon emission percent level speech portsmouth business allowed emit greenhouse gase free businesse sky public doe stop polluting put price pollution mccain platform revolve chiefly monetary challenge company consumersincluding tax credit consumer buy zeroemission car encouraging automaker create vehicle million prizelike competition develop battery plugin hybrid fully electric car obama support capandtrade systembut version government carbon credit free charge company continue pollute ultimate goal bring carbon emission percent level oped mccain wrote financial time american european substantially reducing greenhouse gas emission coming year hand muchdiminished world grandchildren successor kyoto capandtrade system deliver environmental impact economically responsible manner table content water shortage renewable energy solar wind geothermal offshore oil exploration drilling obama softened stance drilling protected areas coast bush administration opening exploration early democratic candidate solidly open limited drilling part larger effort curtail volatile gas pricesprovided environmentally responsible way call oil company drill million acre million hectare exploring offshore statement made obama campaign spokesman bill burton midjuly offshore drilling provide shortterm relief pump longterm strategy energy independence worthy consideration risk expert bush administration concede neither prolong failed energy policy washington year mccain favour drilling outer continental shelf federally controlled submerged land coast opposed statecontrolled seabedin order lessen american dependence foreign oil lower gas price early campaign rally lebanon ohio drill baby drill drill offshore drilling alaskas arctic national wildlife refuge anwr obama consistently opposed drilling anwr support keeping refuge free disruption human activity oil exploration negatively impact porcupine caribou blocking portion herd mile kilometre migration mccain official position anwr drilling reserve recent week however plan shifting selection palin favour drilling area recent weekly standard last friday mccain breakfast aspen colo texas oilman boone picken television ads promote effort end american dependence foreign oil breakfast picken told reporter pushed mccain drill anwr mccain picken continued said decided thatyet was know open question table content water shortage renewable energy solar wind geothermal clean coal obamas web site department energy control work private company design cleancoal plant advantage carbon capture sequestration early cosponsored coaltoliquid fuel promotion act measure lessen dependence foreign oil turning coal automobile fuel but scientific american other argued liquid coal worse gasoline environmentally economically mccain promise pour billion annually development cleancoal technology commercialise processe building plant technique capture sequestration usas export methodology country china support utilising coaltoliquid system interview grist magazine coal gasification subsidise r&d effort government funding basic r&d way kind coal technology emit greenhouse gase presentday coalfired utility plant wild card obamas running mate delaware sen joe biden believe developing cleancoal technology essential combating global climate change assert however coal wrong america suggest exporting coal technology emerging country china india depend heavily coalderived energy natural gas obama support construction alaska natural gas pipeline relieving dependence foreign oil and increasing american energy security building maintaining create job campaign pipeline supply trillion cubic feet billion cubic metre natural gas year early obama unveiled energy plan advocating cooperating with canadian government finally build alaska natural gas pipeline delivering clean natural gas creating good job process mccain booster tapping outer continental shelf extract oil natural gas campaign web site trillion cubic feet trillion cubic metre recoverable natural gas offshore year roughly trillion cubic feet billion cubic metre natural gas year energy information administration year supply current consumption level santa barbara calif speech late june every year federal government buy upward car vehicle including military law enforcement vehicle make civilian vehicle flexfuel capable plugin hybrid car fueled clean natural gas table content water shortage renewable energy solar wind geothermal nuclear energy illinois nuclear power plant state obama gung type energy john edward stalwart opposing nuke power obama believe role play mixed bag alternative aimed replacing oilbased energy town hall meeting newton iowa start premise nuclear energy optimal nuclear energy proponent mccain end moratorium building nuclear plantsthe broken ground year plan put country track open facility constructing total bloombergcom estimate proposal cost taxpayer billion speech missouri state university springfield every year the operating nuclear reactor spare atmosphere equivalent auto emission america benefit broken ground single nuclear plant year manufacturing base construct plant gone recover knowledge skill lost stagnant decade highly technical field endangered specy reported obama opposed bush administration proposal bar input independent scientist review plight endangered specy statement obama spokesman nick shapiro after year successfully protecting nation endangered wildlife bald eagle way improve weaken president sen obama fight maintain strong protection endangered specy act undo proposal pre bush mccain comment bush proposed blocking scientist input protection endangered specy did however oppose congressional spending study grizzly bear dna scientist believed aid protecting specieswhich considered threatened mccain called earmark pork barrel spending mccain spot two hundred thirtythree million bridge nowhere outrageous million study dna bear montana unbelievable million dollar woodstock museumin bill sponsored hillary clinton predictable gut stand wasteful government spending man john mccain wild card mccain palin sat opposite side ice floe deciding polar bear listed endangered specy earlier year mccain supported palin may department interior deemed polar bear threatened point contention socalled congressional earmark requested gov palin study genetic harbour seal mating habit crabswhich stand direct conflict mccain stance federal fund study grizzly bear dna table content water shortage renewable energy solar wind geothermal water shortage state predicted experience water shortage decade obama advocate developing national plan areas population growth manage waterrelated resource call waterefficiency regulation appliance landscaping farming obamas answer question presented science debate scientist engineer america solution critical problem require close collaboration federal state local government people businesse affected first price policy set way give clear incentive water efficiently avoid waste second information training and case economic assistance provided farm businesse shift efficient water practise mccain support renegotiating term colorado river compact guideline divvying river water california utah wyoming mexico nevada arizona colorado population region shifted wildly past year pact ratified campaign say speeches mccain gave month colorado hello john mccain arizona water renewable energy solar wind geothermal obama establish federal mandate percent electricity america sustainable source part billion year expenditurethe centrepiece energy planis develop resource shift ethanol production corn cellulosebased source affect food supply obama has however supporter ethanol made primarily corn prominent industry home state illinoisand recently told farmer support federal mandate make billion gallon billion litre ethanol fuel year speech michigan state university msu early august meet goal invest cleantechnology research development occurring lab research facility country msu working farm owner develop state wind potential developing nanotechnology make solar cell cheaper mccain campaign platform largely nonspecific regard renewable energy favour rationalising existing tax incentive renewable energy market sustainable require government support democrat noted mccain missed vote renewable energy bill finally failed senate july support ethanol biofuel recently urged environmental protection agency relax rule amount ethanol produced effect food livestock feed price nikhil swaminathan speech","m_szGeo1":"United States","m_szSourceType":"source_news","m_szSrcUrl":"http://www.scientificamerican.com/article/where-do-the-candidates-stand-on-environment/","m_Places":["Arizona","Conn.","Portland, Ore.","Alaska","Portsmouth, N.h.","Kyoto","United States","Washington","Lebanon , Ohio","Texas","Pickens","China","Delaware","America","India","Illinois","Iowa","Springfield","Montana","Woodstock","Colorado","California","Utah","Wyoming, New Mexico","Nevada"],"m_People":["Nikhil Swaminathan","Barack Obama","John Mccain","Joe Lieberman","Mccain, Pickens","Sarah Palin","Charlie Gibson","Bill Burton","T. Boone Pickens","Joe Biden","John Edwards","Nick Shapiro","Hillary Rodham Clinton","I'm John Mccain"],"m_Companies":["Scientific American","Senate","Abc News","X Prize","Financial Times","Bush Administration","Continental","Porcupine","Weekly Standard","Canadian Government","Energy Information Administration","Bloomberg.com","Missouri State University","Ap","U.s. Department Of The Interior","Michigan State University","Democrats","U.s. Environmental Protection Agency"],"m_BiGrams":["renewable energy","natural gas","water shortage","energy solar","solar wind","wind geothermal","shortage renewable","endangered specy","climate change","global warming","carbon emission","table content","content water","dependence foreign","foreign oil","trillion cubic","human activity","capandtrade system","john mccain","wild card","plugin hybrid","bush administration","cubic feet","cubic metre","nuclear energy"],"m_TriGrams":["renewable energy solar","energy solar wind","solar wind geothermal","water shortage renewable","shortage renewable energy","table content water","content water shortage","dependence foreign oil","trillion cubic feet"],"m_SocialTags":[],"m_Topics":[],"m_Industry":[],"m_Technology":[],"m_BiCnt":[9,9,7,6,6,6,5,5,4,4,4,4,4,4,4,4,3,3,3,3,3,3,3,3,3],"m_TriCnt":[6,6,6,5,5,4,4,4,3],"m_iDocBodyWordCnt":1325}
