{"m_szDocID":"428284","m_szDocTitle":"Mitsubishi Motors' 2014 Outlander & Outlander Sport Earn Coveted Insurance Institute for Highway Safety (IIHS) Top Safety Pick Awards, Offering Consumers the Safest Crossover Model Lineup in America - InsuranceNewsNet","m_szYear":"2014","m_szDocSumamry":"Insurance Institute for Highway Safety (IIHS) \"Top Safety Pick+\" – the highest safety achievement designated by the non-profit vehicle research and crash test ratings agency – and its 5-passenger 2014 Mitsubishi Outlander Sport designated the only IIHS \"Top Safety Pick\" model in the Small SUV category. With these accolades, Mitsubishi Motors offers automotive consumers the safest crossover model lineup available in America today. (Photo: http://photos.prnewswire.com/prnh/20131219/LA36201 ) Due to more stringent testing criteria for the IIHS \"Top Safety Pick+\" and \"Top Safety Pick\" awards, only","m_szDocBody":"insurance institute highway safety iih top safety pick highest safety achievement designated nonprofit vehicle research crash test rating agency passenger mitsubishi outlander sport designated iih top safety pick model small suv category accolade mitsubishi motor offer automotive consumer safest crossover model lineup america today photo due stringent testing criteria iih top safety pick top safety pick award vehicle model earned award drastic reduction compared vehicle model earned iih award recognition redesigned mitsubishi outlander vehicle earn iih top safety pick accolade order vehicle iih top safety pick test subject display exemplary performance stringent crash testing criteria have system prevent mitigate fronttorear crashes iih mitsubishi outlander exceptional iih top safety pick rating attributed superlative engineering rigid hightensile steel availability numerous advanced feature including radarbased forward collision mitigation fcm reduction technology evaluation mitsubishi outlander forward collision mitigation fcm system include audio visual warning driver initiate automatic braking iih awarded system advanced rating grade superior advanced basic nextgeneration safety technology feature include camerabased lane departure warning ldw radarbased adaptive cruise control acc starting msrp mitsubishi outlander lowestpriced vehicle segment advanced safety technology iih raised qualifying standard top safety pick rating achieved mitsubishi outlander sport vehicle evaluation include small overlap crash test agency small overlap crash test replicate front corner vehicle strike vehicle object tree utility pole weve made difficult manufacturer year iih president adrian lund following gradual phasein small overlap crash part basic battery test good acceptable performance part vehicle safety credential felt time offer extra recognition manufacturer offering proven crash test avoidance technology having allnew mitsubishi outlander named top safety pick mitsubishi outlander sport exclusive top safety pickrated vehicle small suv category testament precision design engineering strive instil vehicle yoichi yokozawa mitsubishi motor north america inc mmna key safety technology helped outlander sport starting msrp attain distinguished iih top safety pick safety rating mitsubishi motor patented reinforced impact safety evolution rise engineered mitsubishi motor vehicle rise mitsubishi motor safety body construction system featuring integrated energyabsorbing crumple zone engineered reinforcement strategically provide maximum protection vehicle occupant event impact absorbing dispersing great deal energy cabin information mitsubishi outlander outlander sport crossover vehicle visit mediamitsubishicarscom information top safety pick top safety pick award insurance institute highway safety iih visit iihsorg mitsubishi motor north america inc mitsubishi motor north america inc mmna responsible research development manufacturing marketing sale financial service mitsubishi motor united state mmna sell sedan network approximately dealer mmna leading development highlyefficient affordablypriced gasolinepowered automobile industryleading knowledge battery electric vehicle develop future phev model information contact mitsubishi motor new bureau visit mediamitsubishicarscom source ","m_szGeo1":"United States","m_szSourceType":"source_industry","m_szSrcUrl":"http://insurancenewsnet.com/oarticle/Mitsubishi-Motors-2014-Outlander-Outlander-Sport-Earn-Coveted-Insurance-Insti-a-439264","m_Places":["North America","United States"],"m_People":["Adrian Lund","Yoichi Yokozawa"],"m_Companies":["Insurance Institute For Highway Safety","Accolades","Mitsubishi Motors","America Today","Accolade","Acc"],"m_BiGrams":["top safety","safety pick","mitsubishi outlander","mitsubishi motor","iih top","crash test","outlander sport","safety technology","small overlap","overlap crash","motor north","north america","america inc"],"m_TriGrams":["top safety pick","iih top safety","mitsubishi outlander sport","small overlap crash","mitsubishi motor north","motor north america","north america inc"],"m_SocialTags":[],"m_Topics":[],"m_Industry":[],"m_Technology":[],"m_BiCnt":[13,12,9,9,7,4,4,3,3,3,3,3,3],"m_TriCnt":[12,7,3,3,3,3,3],"m_iDocBodyWordCnt":418}
