{"m_szDocID":"428876","m_szDocTitle":"Directory:Electric Trucks - PESWiki","m_szYear":"2015","m_szDocSumamry":"PESWiki.com -- Pure Energy Systems Wiki:  Finding and facilitating breakthrough clean energy technologies.      Directory:Electric Trucks From PESWiki Jump to: navigation, search At PESWiki The Hydraulic Battery-powered Electromagneti Generator from Tennessee - A trio of inventors from Tennessee have design a hydraulic, battery, electromagnetic system than they say can fuellessly run a home or a vehicle, or other devices. Several working prototypes have been built. Presently awaiting \"pending\" patent status, they are ready to build a business to bring this technology to market. Phoenix Motorca","m_szDocBody":"peswikicom pure energy system wiki finding facilitating breakthrough clean energy technology directoryelectric truck peswiki jump navigation peswiki hydraulic batterypowered electromagneti generator tennessee trio inventor tennessee design hydraulic battery electromagnetic system fuellessly run home vehicle device working prototype built presently awaiting pending patent status ready build business bring technology market phoenix motorcar electric car phoenix motorcar headquartered ojai california early leader mass production full function freeway speed electric automobile entertaining fleet order sport utility truck sut hybrid bus etraction revolution wheel whisper buse netherland mpg diesel engine electrical generator produce electricity run electric motor directly connected wheel electric truck utility vehicle rousch roush electric utility vehicle rugged comfortable clean solution limited mileage environment boshart tersus phoenix sut built ssanyong body nev esuv exv exv electric utility vehicle emission plugin electric vehicle designed commercial personal use esuvs affordable operate require maintenance plug esuv cell phone drive charge american electric vehicle performance road vehicle developed military commercial sale vehicle feature performace large lithiumpolymer battery pack performance motor rugged solar panel full recharge day machine gun available thank roger thompson dynamic vehicle featuring electric truck passenger van cargo van shuttle tram dymac international truck van utility vehicle designed carry heavy load port putting electric big rig work month intense testing port official officially rolling nautilus electric shorthaul truck developed santa anabased balqon corp daily breeze city rediscover allure streetcar mass utilised street car making comeback streetcar line lot cheaper subway carry people buse fuel passenger mile depending source electricity carbon free usa today jan delivery tonne carrying capacity mexicos modec mile range top speed mph zytec electric motor powered twin volt sodiumnickelchloride battery partially replenished van regenerative breaking system treehugger apr modec electric urban delivery van gorilla electric vehicle electric work utility vehicle electric vehicle international electric truck buse canadian comercial vehicle taylordunn electruck designed provide electric alternative current fleet full sized utility pickup truck alk electric vehicle european manufacturer compact performance electric vehicle onroad offroad transportation inside civil tourist industrial structure platform truck personnel carrier tow tractor zap xebra electric truck review small struck external appearance good fit finish lack surface handling truck pleasant problem driving find shifting involved xebra motor geared straight rear differential ian johnston zap xebra electric flat bed dump truck mile electric vehicle debut lowspeed allelectric truck mile electric vehicle unveiled allelectric zxst truck mile charge constant speed pound cargo capacity mile electric vehicle representative taking preorder advance truck planned delivery green car congress jul thunder sky electric buse ise corp smith electric vehicle heavy duty commercial industrial electric vehicle piaggio ltv electricpowered porter bestselling light commercial electricpropulsion vehicle europe distributed newteon ecofriendly vehicle france scandinavia monaco electric fuel zincair electric buse tantum automotive low speed electric truck spijkstaal electric tractor truck netherland columbia parcar industrial commercial vehicle mega multitruck electric vehicle travelling road made adaptability professionalism partner columbia parcar mega multitruck range ultra light commercial vehicle diesel electric ezgo industrial utility vehicle ebus electric shuttle trolley microvett electric bus truck italy distributed newteon ecofriendly vehicle france scandinavia monaco electroride developing zerotruck integrated zero emission fully electric gvwr medium duty truck commercial operator specification detailed worldwide launch las vegas alternative fuel vehicle conference bredamenarinibus battery electric minibus italy tecnobus electric hybrid minibuse italy graf carello electric small transporter tractor terrain vehicle lowfloor vehicle tiger truck light utility truck van powered variety fuel electric motor hybrid electric vehicle job garden zallysmade quality electric vehicle year construction garden more tran lectric industrial electric vehicle cart electric tractor electric mow tow grade push snow dibline french electric shuttle electric vehicle international tram truck shuttle trailer allelectric jeep lookalike france tender scarlette allelectric sale france run motor wheel electricity stored floor leadacid battery drive car mile cost car eur autobloggreen oct bad boy buggy allelectric wheel drive silent utility vehicle atv reverse hunting spot quietly bellier lutilitaire electrique cushman utility vehicle bluebird automotive commercial home delivery electric vehicle eride industry exv exv neighbourhood electric vehicle bradshaw electric vehicle tow tractor burden carrier cleansing vehicle personnel carrier electric isuzu outfit trash collector box dump elghe electric truck italy barefoot motor electric terrain vehicle good earth electric vehicle industry affordable practical electric vehicle deliver full mile range battery charge nemo urban truck nemo sell built aluminium chassis handle payload lsv limited mile hour mile range made north robust heater option ranging lithium ion battery radio player autobloggreen elcat electric vehicle finland elcat citywagon powerful greatly improved electric vehicle passenger use dragon electric vehicle electric vehicle footer directoryelectric vehicle powerpediaelectric vehicle newselectric vehicle directoryelectric car directoryelectric truck directoryplugin hybrid electric vehicle phev directoryelectric bike motorbike scooter directoryelectric vehicle recharging station fuel efficiency directoryfuel efficiency templatefuel efficiency footer listing directoryhybrid vehicle powerpediahybrid vehicle powerpediahybrid car powerpediahybrid adapter directory listing latest tree new peswiki home retrieved category electric vehicle view discussion source history personal tool log create account searching option translate navigation home nest introduction donate today new pesn twife hcat heat data palladium generator err flux generator symphony secret latest eviva qmogen hcat data anomalous heat peswiki blog corbett blacklight iss commentary sterling presentation tesla tech fisl sponsored link feature top hydrogen mogen ecat lenr blacklight power ymnee qmogen exotic exotic conventional event bedini secret space programme teslatech sponsor phi science serenata flower item sale sun oven scangauge making biodiesel make electricity recondition battery keppe motor department open source tech hcat freddy cell bedini directory tree aether alt fuel antigravity battery betavoltaic bioelectricity biofuel biodiesel biomass body electric brown gas cold fusion conservation electrolysis electromagnetic electrostatic fuel cell fuel efficiency electric vehicle engine hydroxy fusion geothermal gravity motor home generation human powered hydro hydrogen joe cell lighting magnet motor nanotechnology nuclear nucl remediation oil piezoelectric plasma plastic river salt water mix solar solid state gen storage tesla turbine thermal electric tidal vortex waste energy water water fuel wave ocean wind wireless electricty point energy powerpedia betavoltaic cold fusion nikola tesla conspiracy suppression buyer beware movy humour job review videos store sponsored link support special page popular stat recent category revision advertise contact toolbox link related upload file special page sponsored link map added mdt solarlite when step ahead crowd genius step ahead crackpot rabbi shlomo riskin feb modified accessed time gnu free documentation licence peswiki disclaimer","m_szGeo1":"United States","m_szSourceType":"source_industry","m_szSrcUrl":"http://peswiki.com/index.php/Directory:Electric_Trucks","m_Places":["Tennessee","Ojai, California","Bus","Mexico","Europe","France","Monaco","Columbia","U.s.","Italy","Las Vegas","Nemo","Finland","U.k.","Us","Tesla","Best","Gravity","Most"],"m_People":["Roger Thompson","Xebra Pk Machine Gun","Ian Johnston","Graf Carello","Boy Buggies","Eviva Qmogen","Joe Cells","Shlomo"],"m_Companies":["Phoenix","Revolution","Roush","American Electric","Vehicle Group","Santa Ana","Balqon Corp.","Youtube","Subways","Usa Today","Volt","Mm Group","Zap","Congress","Ise Corp","Piaggio","Diesel","Palladium","Freddy's","Brown's","Plastic"],"m_BiGrams":["electric vehicle","utility vehicle","electric truck","electric motor","mile range","vehicle electric","truck mile","mile electric","sponsored link"],"m_TriGrams":["mile electric vehicle"],"m_SocialTags":[],"m_Topics":[],"m_Industry":[],"m_Technology":[],"m_BiCnt":[28,8,6,3,3,3,3,3,3],"m_TriCnt":[3],"m_iDocBodyWordCnt":1028}
