{"m_szDocID":"458230","m_szDocTitle":"Mitsubishi Lancer Named an Insurance Institute for Highway Safety \"Top Safety Pick\" - InsuranceNewsNet","m_szYear":"2016","m_szDocSumamry":", July 30, 2014 /PRNewswire/ --Â Mitsubishi Motors North America, Inc. (MMNA) announces its affordably-priced and fun-to-drive 2014 Lancer compact sports sedan (excludes Ralliart and Evolution models) has been named a \"Top Safety Pick\" by the Insurance Institute for Highway Safety (IIHS). In its latest evaluation, the IIHS subjected a total of twelve \"small cars\" to their small overlap front crash test that has 25 percent of the vehicle's frontal area on the driver's side impact a barrier at 40 mph. Introduced in 2012, the small overlap front crash test \"replicates what happens when the front c","m_szDocBody":"mitsubishi motor north america inc mmna announce affordablypriced funtodrive lancer compact sport sedan exclude ralliart evolution model named top safety pick insurance institute highway safety iih latest evaluation iih subjected total twelve small car small overlap front crash test percent vehicle frontal area driver side impact barrier mph introduced small overlap front crash test replicate front corner vehicle collide vehicle object tree utility pole iih half vehicle evaluated achieved nonpassing grade marginal poor iih require vehicle earn grade good acceptable pass test iih small overlap front crash test more difficult headon crashes conducted national highway traffic safety administration nhtsa longstanding iih moderate overlap test great popular mitsubishi lancer named top safety pick insurance institute highway safety don swearingen executive vice president mmna lancer versatile compact sport sedan exceptional degree safety excellent fuel economy sporty performance plentiful standard feature price fit budget top safety pick designation insurance institute highway safety iih usbased nonprofit agency perform research crash test evaluation production vehicle model marketed america applicable model year mitsubishi lancer making mitsubishi motor dealership country summer mitsubishi lancer include host standard feature technology model year including heated side mirror turn indicator standard model advanced nextgeneration continuouslyvariable transmission cvt mimic operation precision speed transmission standard awc model version expanded standard feature including redesigned twotone alloy wheel fuse handsfree link system usb port contrast metre colour multiinformation display chrome interior door handle softtouch upper door trim speaker audio system fog light sport front fascia colorkeyed centre bumper awc model package lancer include featurerich package model sun sound package model mitsubishi lancer distinct version model year low lancer starting msrp fuel economy mpg powerful lancer awc standard allwheel control awc allwheel drive lancer exhilarating turbocharged lancer ralliart surefooted super allwheel control sawc rapidfire speed twinclutch sportronic shift transmission information mitsubishi lancer visit mitsubishi motor north america inc mitsubishi motor north america inc mmna responsible research development manufacturing marketing sale financial service mitsubishi motor united state mmna sell sedan network approximately dealer mmna leading development highlyefficient affordablypriced gasolinepowered automobile industryleading knowledge battery electric vehicle develop future phev model information contact mitsubishi motor new bureau visit mediamitsubishicarscom source ","m_szGeo1":"United States","m_szSourceType":"source_industry","m_szSrcUrl":"http://insurancenewsnet.com/oarticle/Mitsubishi-Lancer-Named-an-Insurance-Institute-for-Highway-Safety-Top-Safety-Pi-a-537726","m_Places":["North America","United States","America"],"m_People":["Don Swearingen"],"m_Companies":["Mitsubishi Motors","Insurance Institute For Highway Safety","National Highway Traffic Safety Administration","Awc","Clutch"],"m_BiGrams":["mitsubishi motor","mitsubishi lancer","crash test","motor north","north america","america inc","top safety","safety pick","insurance institute","institute highway","highway safety","small overlap","overlap front","front crash","standard feature","model year"],"m_TriGrams":["mitsubishi motor north","motor north america","north america inc","top safety pick","insurance institute highway","institute highway safety","overlap front crash","front crash test"],"m_SocialTags":[],"m_Topics":[],"m_Industry":[],"m_Technology":[],"m_BiCnt":[6,5,4,3,3,3,3,3,3,3,3,3,3,3,3,3],"m_TriCnt":[3,3,3,3,3,3,3,3],"m_iDocBodyWordCnt":351}
