{"m_szDocID":"458704","m_szDocTitle":"Wear resistant and anti-fretting Coatings for the Automotive industry by Poeton","m_szYear":"2016","m_szDocSumamry":"Contact Us About Us Vacancies Member Login Italiano Francais Polski Coatings APTICOTE Treatment Range APTICOTE 100 - Hard Chrome APTICOTE 200 - Polymer Composite APTICOTE 300 - Hard Anodising APTICOTE 300SU - Sulphuric & Chromic Acid Anodising APTICOTE 300TSA - Tartaric Sulphuric Anodising APTICOTE 350 - Hard Anodic/Polymer Composite APTICOTE 355/6 - Advanced Anodic Composites APTICOTE 400 - Electroless Nickel APTICOTE 450 - Electroless Nickel/PTFE Composite APTICOTE 460 - Electroless Nickel/Polymer Composite APTICOTE 600 - Silver Plating APTICOTE 800 - Thermal Spray Coatings APTICOTE 810 - Th","m_szDocBody":"contact vacancy member italiano francais polski coating apticote treatment range apticote hard chrome apticote polymer composite apticote hard anodising apticote sulphuric chromic acid anodising apticote tsa tartaric sulphuric anodising apticote hard composite apticote advanced anodic composite apticote electroless nickel apticote electroless composite apticote electroless composite apticote silver plating apticote thermal spray coating apticote thermal composite apticote cadmium apticote carbide composite coating apticote keronite apticote magnanoshield market aerospace defence medical healthcare energy power generation automotive chemical oil gas food drink equipment electronic telecom general engineering approval technical technical service select coating solve friction wear problem glossary surface engineering term surface engineering review send application problem successe enquiry send problem contact new latest new poeton newsletter premium designer guide tutorial white paper apticote coating automotive industry poeton offer wide range engineering coating automotive industry volume production car performance sport sector corrosion protection coating including nickel sprayed zinc engine cylinder bore coating including cylinder liner unrivalled lubricant retention low friction poeton aptec division antifretting coating surface treatment lightweight alloy providing low wear low friction corrosion protection thermal barrier system antiscuffing coating wear resistant coating hard chrome electroless nickel typical apticote automotive application universal coupling joint spark plug central electrode manifold heatshield exhaust turbocharger cylinder liner steel aluminium alloy cylinder block motorcycle housing gasket surface fastener tyre valve pully drive clutches spline coupling calliper fork poeton offer comprehensive coating service automotive industry volume production mass market highly specialised world competitive motorsport work kanban ppap runrate production system unrivalled laboratory underpin quality control quality assurance procedure demanded industry provide precision quality coating meet friction wear corrosion requirement automotive sector including surface treatment lightweight material aluminium magnesium forefront technology poeton coating applied emerging generation electric car long offer electroplate corrosion protection system apticote coating specify apticote coating coating type application areas benefit apticote precision hard chrome specialise precision plating jigging subsidiary anode custom designed workshop avoiding expensive postgrinding linishing part include manifold housing calliper fork heatshield apticote hard anodising sulphuric acid anodising aluminium sulphuric acid anodising salt spray protection rack plate large batches ideal corrosion protection aluminium casting bracket apticote hard anodising exceptional wear resistance suitable pulley housing apticote apticote composite hard anodising aluminium range anodic processe polymer infusion providing combined wear corrosion protection hour salt spray aluminium alloy part subject demanding environment apticote quality electroless nickel coating ideal precision part needing antifretting corrosion protection part spline coupling gasket face apticote electroless composite providing low friction wear resistance antifretting good gasket face risk relative thermal expansion apticote ultimate corrosion protection ultimate corrosion protection low friction system based electroless nickel advanced polymer infusion suitable low volume larger part massproduced small item apticote thermally sprayed coating offer wide range metal cermet ceramic thermal barrier manifold turbocharger heatshield recommend apticote antiscuffing bearing surface choose apticote apticote ceramic supreme cylinder bore coating ultimate engine performance providing increased power antiscuffing wear rpm coat hone liner block housing including twostroke visit poeton aptec division information apticote keronite electroceramic coating aluminium magnesium alloy ultimate wear protection aluminium pulley brake disc clutches magnesium housing apticote keronite exceptional corrosion protection more hour salt spray right ideal posttreatment painting case history spark plug problem ceramic body plug fired temperature pressure central steel electrode protected oxidation including terminal cap form contact tension lead solution poeton solved problem specially brightened sulphamate nickel barrel plated batches statistical process control ensure consistent thickness part laboratory devised quality assurance procedure based weighing batches pin plating accurately relating change coating thickness determined random metallographic section tyre valve problem customer alloy remote tyre pressure monitoring valve conventional sulphuric acid anodising failing provide hrs cyclic corrosion endurance solution working customer poeton solved problem laboratory making proprietary modification process racking producing coating hrs protection part rack sulphuric acid anodised batches laboratory developed unique accelerated corrosion procedure provide weekly quality assurance test protean electric wheel drive problem corrosion aluminium component protean electric wheel drive protean electric leading clean technology company design develop manufacture protean drive advanced inwheel electric drive system hybrid battery electric vehicle protean drive fullyintegrated directdrive solution motor builtin inverter control electronic software separate large heavy costly inverter required direct drive configuration reduce part count complexity cost removing traditional drive train component gearboxe driveshaft axle differential protean drive package easily inside conventional wheel original equipment vehicle bearing revolutionary protean drive inwheel propulsion system challenging status quo delivering practical way electrify fullsize vehicle compromise game changing design engineer integrator power space flexibility freedom create generation clean efficient vehicle compromising power fun curbappeal system electrification fullsize family car suvs commercial vehicle protean drive superior regenerative braking capability substantially increase driving range reduce battery size powerful match performance engine protean drive electrification fullsize family car suvs commercial vehicle system wheel drive configuration support plugin electric drive architecture throughtheroad ttrh parallel hybrid conversion extended range sery hybrid vehicle shevs battery powered nonrange extended electric vehicle bevs solution poeton solved corrosion tribological problem unique apticote apticote composite anodising working closely customer project basis poeton world leading company field coating surface treatment responsible dealing anodized component protean drive protean electric proud poeton specialist partner extremely grateful poeton expertise experience area andrew vallance protean electric make enquiry problem fill enquiry form engineer straight back you printer friendly version download printer friendly version retention detail processing capability size capacity follow link aerospace defence medical healthcare energy power generation automotive chemical oil gas food drink equipment electronic telecom general engineering global support poeton apticote supporting global manufacturing design support research development test sample article pre production full rate production coating poeton core standard coating apticote hard chrome apticote polymer composite apticote hard anodising apticote electroless nickel apticote silver apticote plasma thermal spray coating apticote keronite apticote cadmium technical coating apticote sulphuric anodising ptfe composite apticote hard anodic polymer composite apticote advanced anodic composite hrs corrosion protection apticote electroless nickel ptfe composite deposition apticote electroless nickel polymer composite apticote plasma thermal spray polymer composite technical composite coating apticote nickel silicon carbide composite coating research development support contracted r&d wear testing corrosion testing coating trial support coating development development trial failure analysis project coating characterisation optical microscopy metallography chemical analysis atomic absorption technique benchmarking poeton industry ltd head office eastern avenue gloucester england tel fax information web property poeton industry limited term map member web design birmingham seo birmingham","m_szGeo1":"United Kingdom","m_szSourceType":"source_general","m_szSrcUrl":"http://www.poeton.co.uk/coatings-automotive.htm","m_Places":["Us","Printer","Friendly","Eastern","Gloucester","England","Uk","Birmingham - Seo","Birmingham"],"m_People":["Andrew Vallance"],"m_Companies":["Universal","Ideal","Infusion","Poeton Industries Limited"],"m_BiGrams":["composite apticote","corrosion protection","apticote hard","coating apticote","apticote electroless","electroless nickel","protean drive","polymer composite","hard anodising","protean electric","hard chrome","anodising apticote","acid anodising","apticote keronite","low friction","sulphuric acid","electroless composite","thermal spray","composite coating","friction wear","apticote coating","automotive industry","surface treatment","quality assurance","salt spray","poeton solved","wheel drive"],"m_TriGrams":["polymer composite apticote","apticote hard anodising","apticote electroless nickel","composite apticote hard","apticote electroless composite","sulphuric acid anodising"],"m_SocialTags":[],"m_Topics":[],"m_Industry":[],"m_Technology":[],"m_BiCnt":[10,10,8,7,7,7,7,5,5,5,4,4,4,4,4,4,3,3,3,3,3,3,3,3,3,3,3],"m_TriCnt":[4,4,4,3,3,3],"m_iDocBodyWordCnt":1033}
