{"m_szDocID":"463969","m_szDocTitle":"Composites | News, Research","m_szYear":"2016","m_szDocSumamry":"Home Home Articles News Directory Equipment Software Market Reports Experts Books Journals Blogs Podcasts Videos Events Courses News 3D Printing Adhesives and Sealants Aerospace Materials Aluminum / Aluminium Automotive Materials Biomaterials Building and Construction Business Ceramic Materials Chemistry Clean Technology Coatings and Thin Films Composites Control Systems Corrosion Crystallography Design and Innovation Electronics Energy Events Ferrous Alloys and Metals Fibers Fuel Cell Graphene Iron and Steel Materials Analysis Materials Processing Materials Research Materials Science Material","m_szDocBody":"home home article new directory equipment software market report expert book journal blog podcast videos event course new printing adhesive sealant aerospace material aluminium aluminium automotive material biomaterial building construction business ceramic material chemistry clean technology coating thin film composite control system corrosion crystallography design innovation electronic energy event ferrous alloy metal fibre fuel cell graphene iron steel material analysis material processing material research material science material testing mineral mining modelling simulation nanomaterial nanotechnology product nonferrous alloy metal packaging petrochemical photonic photovoltaic pittcon plastic polymer precious metal rubber elastomer semiconductor sustainable technology titanium tribology article latest article thought leader insight industry azojomo material material supplier application industry metal store equipment chemical analysis atomic absorption spectrometer aas atomic optical emission spectrometer oes benchtop nmr spectrometer electrochemical analysis electron paramagnetic resonance epr spectrometer elemental analyzer ftir accessory ftir spectrophotometer ftnir fourier transform spectrometer fuel lubricant testing gas analyzer gas chromatography gel permeation chromatography handheld raman analyzer handheld xrf analyzer ion chromatography liquid chromatography mass spectrometer nmr spectroscopy analyzer pharmaceutical analysis equipment raman spectrometer secondary ion mass spectrometry sim spectrometer spectroscopy accessory titrator vapour pressure measurement xray gamma ray detector xray diffractometer xray fluorescence analyzer xray optic xray photoelectron spectroscopy xps xrf spectrometer coating deposition atomic layer deposition system thermal evaporation equipment thin film deposition system coating testing adhesion tester coating thickness gauge coating film deposition consumable eddy current tester ellipsometer glossmeter thin film characterization system electrical property electrical property characterization equipment hall effect measurement system scanning kelvin probe seebeck coefficient measurement system vibrating sample magnetometer vsm zeta potential analyzer equipment testing calibration battery testing solar cell testing fixing fastener bonding fastener flow controller metre field flow fractionation equipment heat treatment ageing oven industrial furnace oven laboratory furnace kiln vacuum furnace laboratory process equipment controlled atmosphere processing environment cryogenic evaporator concentrator laboratory gas generator laboratory heating cooling apparatus laboratory testing sample preparation equipment laboratory water purification system mixer shaker pcb smt handling workstation scientific illumination light source vacuum pump material processing manufacturing printing equipment material accessory boring machine mill particle size reduction plastic processing equipment ultrasonic welding equipment mechanical testing automatic material testing machine biomaterial testing equipment brittleness tester civil engineering material testing equipment cutter grinder polisher drop weight testing machine durometer fatigue testing machine force gauge gauge hardness testing machine impact testing machine material characterization equipment pipe burst hydrostatic tester plastic rubber testing equipment portable hardness tester scratch tester tensile testing machine torque gauge gauge tribometer friction wear tester universal material testing machine microscope acoustic microscope atom probe atomic force microscope afm electron beam source fibre analyzer ion beam microscope metallurgical microscope microscopy accessory consumable optical microscope polarising microscope raman microscope sample preparation equipment scanning electrochemical microscope secm scanning electron microscope sem scanning probe microscope scanning transmission electron microscope stem stereo microscope transmission electron microscope tem nondestructive testing ndt coating thickness gauge gas analyzer handheld xrf analyzer laser micrometre measurement nondestructive testing ndt equipment portable hardness tester scientific cameras sheet board counter ultrasonic flaw detector xray scattering system saxs waxs optical inspection acoustic microscope borescope ccd cameras colorimeter electron multiplying charge coupled device emccd ellipsometer monochromator optical comparator optical noncontact profiler measurement polarimeter polariscope refractometer scientific cameras oven furnace kiln ageing oven industrial furnace oven laboratory furnace kiln physical property testing adhesion tester analytical test sieve borescope chemisorption analyzer civil engineering material testing equipment density metre diffusivity tester dynamic vapour sorption dvs environmental test chamber extensometer extruded profile measurement system ferrography flexometer goodrich flexometer fogging tester gas adsorption analyzer gas pycnometer gas solubility analyzer glossmeter laser micrometre measurement light scattering instrument melt flow index tester metal testing equipment moisture analyzer optical noncontact profiler measurement particle counter particle size analyzer permeameter pharmaceutical analysis equipment plasma processing equipment pore size analyzer profilometer pycnometer rheometer metrology tool sheet board counter shock vibration test system spectrophotometer surface area analyzer surface energy gas chromatograph thickness gauge gauge vapour sorption analyzer viscometer wafer mapping system water sorption analyzer zeta potential analyzer plasma processing plasma diagnostic tool plasma processing equipment process control extruded profile measurement system flow controller metre lubricant condition monitor process control system radiation detector testing geiger counter liquid scintillation counter multichannel analyzer proportional counter radio chemistry sensor detector data logger control system controller data logger gas detector level sensor moisture sensor temperature sensor thermocouple thermal analysis calorimeter differential scanning calorimeter dsc dilatometer flash analysis lfa melting point metre peltier thermostat temperature measurement equipment temperature retraction tester thermal analysis equipment thermal conductivity system thermomechanical analyzer tma product software market report book alloy aluminium asm handbook biomaterial ceramic chemical engineering chemistry clean technology coating composite condensed matter conference proceeding copper corrosion design elastomer electronic engineering fluid fuel cell glass glaze heat treatment instrumentation iron magnetism material processing material science material testing measurement science mechanic mem metallurgy metal microscopy nanotechnology optic photonic cell physic plastic polymer semiconductor soft matter spectroscopy steel thermodynamic thermoplastic titanium welding journal biomaterial ceramic material chemistry coating thin film composite corrosion crystallography energy material processing material science metal alloy mineral nanotechnology polymer solgel videos adhesive bonding axaa conference biomaterial carbon fibre future direction interview ceramic material coating composite material corrosion emc manchester ferrous alloy functional material gas chromatography graphene hard material temperature material iconn interview light alloy m&m phoenix arizona usa machining mass spectrometry material austceram material processing material science technology mst material science technology mst material testing characterisation metal casting foundry mrs fall meeting video interview mrs fall meeting mrs fall meeting mrs fall meeting video interview nanomaterial nonferrous alloy pittcon interview pittcon interview pittcon interview pittcon pittcon precious metal recycled sustainable material rubber elastomer spectrometer stainless steel structural material thermoplastic thermosetting polymer welding brazing course course event contact meet team term advertise browse bymaterialsapplicationsindustry advertise term composite new oxygentrapping composite mof helper molecule hold potential energy application metalorganic framework mof lowcost material capable separating gase air combined gas stream separating oxygen material fail completely resolve issue researcher developed mof composite helper molecule work isolate oxygen type gase simple costeffective way more invisible cloak future innovative metaskin engineer iowa state university created flexible metaskin capable shielding object powerful radar wave stretchable tunable metaskin utilise row tiny liquidmetal device trap suppress radar wave specific frequency shield object sharp radar wave more flameretardant highmodulus thermoplastic textile prepreg developed toho tenax toho tenax ltd core company teijin group carbon fibre composite business announced today developed flameretardant highmodulus thermoplastic textile prepreg more researcher control property composite material biomedical application researcher number discipline north carolina state university collaborated create composite material capable emitting heat light exposed radiation specific wavelength material customised possess specific mechanical feature composite possibly adapted drug delivery biomedical imaging therapeutic treatment more carbon fibre electric vehicle successfully complete frontal crash test amazing result michael president motor inc announced today carbon fibre electric vehicle the ego commenced crash testing china successfully passed frontal crash test amazing result more renewable woodbased carbon fibre build car prototype world model car comprising woodbased carbon fibre roof battery produced swedish researcher decade ago station waggon wooden panelling however aesthetic vision wood current research decrease vehicle weight renewable material more sandia lab analyse impact composite nondestructive testing method researcher david moore timothy brigg sandia national laboratory team analysing part composite material moore rectangular piece carbon composite material surface smooth weak woven pattern more chomarat earn dnv certification glass carbon multiaxial reinforcement chomarat received dnv certification range glass carbon multiaxial reinforcement marine market brand name gplytm cplytm more scientist combine mathematic material science develop printed hydrogel composite structure scientist harvard john paulson school engineering applied science wyss institute biologically inspired engineering harvard university developed breakthrough printing method time fourth dimension inspired plant natural structure react environmental stimuli change form accordingly scientist developed printed hydrogel composite structure change form immersed water more mit researcher develop transparent polymer offer cheaper alternative smart window researcher massachusett institute technology mit developed theory predict amount light transmitted material level stretch thickness based theory researcher successfully predict varying transparency rubberlike transparent polymer stretched inflated more previous new sponsor trending material storey benchtop sem integrated eds revolutionising world structural analysis active vibration cancellation diamond turning interview jeff roblee igor kordunsky physicist create material control exciton uchicago scientist discover naturally occurring curium meteorite accurate density determination asphalt chemist synthesise kryptonite crystal insight industry active vibration cancellation diamond turning interview jeff roblee igor kordunsky benchtop sem integrated eds revolutionising world structural analysis throughput oem spectrometer raman spectroscopy interview michael foster latest material article handheld lib analyzer laserbased chromium analysis element alloy investigating aluminium alloy microxray fluorescence spectroscopy microxrf sem eds rolling shutter global shutter ccd cmos image sensor difference advantage mode demonstrating increased throughput transmission standoff raman experiment static fourier transform spectrometer accurate density determination asphalt home new article directory equipment software market report expert book journal blog podcast videos event course azomcom azonetwork owned operated azomcom limited copyright azomcom information service accordance term condition cooky continuing browse agreeing cooky here","m_szGeo1":"United Kingdom","m_szSourceType":"source_general","m_szSrcUrl":"http://www.azom.com/materials-news.aspx?CatID=14","m_Places":["Hall","Kilns","Boring","Surface Area","Manchester","Uk","United States","Helper","Meta","China"],"m_People":["Nir Fourier","Eddy Current","Diffusivity Tester","Michael Hu","David Moore","Timothy Briggs","John A. Paulson","Jeff Roblee","Igor Kordunsky","Michael Foster"],"m_Companies":["Plastics","Sec","Shakers","Particle","Plastic","Force Gages","Torque","Gages","Universal","Atom","Goodrich","Asm","Emc","M&m","Phoenix, Arizona","Iowa State University","Toho","Toho Tenax Co., Ltd.","Teijin Group","North Carolina State University","Sandia National Laboratories","Dnv Gl","School Of Engineering","Wyss Institute","Harvard University","Mit","Massachusetts Institute Of Technology","Eds","Cmos"],"m_BiGrams":["material testing","testing machine","material science","carbon fibre","material processing","testing equipment","composite material","thin film","processing material","measurement system","software market","market report","ceramic material","control system","analysis equipment","thickness gauge","furnace kiln","processing equipment","electron microscope","nondestructive testing","plasma processing","pittcon interview","interview pittcon","radar wave"],"m_TriGrams":["software market report"],"m_SocialTags":[],"m_Topics":[],"m_Industry":[],"m_Technology":[],"m_BiCnt":[7,7,6,6,5,5,5,4,4,4,3,3,3,3,3,3,3,3,3,3,3,3,3,3],"m_TriCnt":[3],"m_iDocBodyWordCnt":1468}
