{"m_szDocID":"464953","m_szDocTitle":"China Hardware product categories – Global hardware trade business opportunities from hardware-wholesale.com","m_szYear":"2016","m_szDocSumamry":"Home Products Suppliers Selling Leads Buying Leads Products Suppliers Buying Leads Images 提交网站»发布产品» Products by Category B-E     |    F-H     |    I-L     |    M-O     |    P-P     |    R-T B-E Brake Drums(6,475) building and construction |  hgh peptides |  brake drum and shoes |  compact wheel loader |  bundy brake tube |  apple iphone sync |  pto shaft tubing |  rolled ring forgings |  storage fabric ottoman |  mobile tool cabinet |  ... Custom Chemical Services(621) humanized monoclonal antibodies |  phosphorus in fertilizers |  industrial wastewater treatment systems |  protein a purifica","m_szDocBody":"home product supplier selling lead buying lead product supplier buying lead image product category brake drum building construction hgh peptide brake drum shoe compact wheel loader bundy brake tube apple iphone sync pto shaft tubing rolled ring forging storage fabric ottoman mobile tool cabinet custom chemical service humanised monoclonal antibody phosphorus fertiliser industrial wastewater treatment system protein purification testosterone dosing silicone fertiliser phosphorus synthetic organic that hgh metric tubing fitting chocolate fountain indoor wall water fountain camera door peephole vacuum bag storage indoor floor fountain npn power transistor indoor wall water fountain indoor floor fountain electric car gearbox calluse feet storage bag vacuum cement board external microphone smartphone marine battery pneumatic solenoid valve stone silicone sealant mastic tile adhesive glass screen protector card holder retractable concrete wall panel outdoor hand railing luxury hospital bed desktop skin treatment core motherboard hard drive desktop direct current cable power module par light bulb stand control system sony ericsson adjustable table lamp boring cylinder block energy saving fluorescent magnetic induction light bulb skoda lamp fog modern desk lamp atomic absorbtion spectrophotometer wooden floor texture contemporary pendant lamp scale train model modern design floor lamp led bucket light light floor lamp food cutter slicer kid sport game holiday cookie tin paper tray making machine home roller microdermabrasion machine wifi code scanner vegetable cutter dicer m&a manager modern sectional sofa kitchen slicer dicer nicer dicer vegetable chopper fresh cut flower lily fresh cut flower anthurium carnation chrysanthemum orchid rose ball fag bearing sale adjustable gaming mouse wide mouth glass jar lid freezer carbon block water philtre cartridge table top fridge plastic philtre cold food storage temperature freezer combined fridge freezer freezer defrost thermostat deep freezer temperature auto defrost freezer chest freezer lock general mechanical component processing service resistance wire deublin rotating union precision machining service phase brushless alternator top kitchen faucet roll forming aluminium turbo rotor assembly ball steel quality garage door continuous casting steel billet general mechanical component general mechanical component agent chain hydraulic pressure component mechanical transmission part general mechanical component shaft general mechanical component general mechanical component processing service seal flange home supply project galvanised steel greenhouse car wash granite shower wall panel room service trolley top dog training collar partition wall home beam expander laser washing laundry hand metal wire mesh educational robotic kit ice cube tray hardness rockwell bakeware cake pan honeycomb ceramic catalytic converter triangle sun shade canopy sail auto trunk storage custom microfiber cloth low bed container semi trailer clear plastic ice bucket jumping jet fountain nozzle apc attenuator insecticide stainless steel cig android set top box green gemstone modulating valve small diaphragm pump atv winch plate cleaning wiper traffic signal light wire wound resistor dual len car dvr kitchen scissor good lingerie kitchen cabinet light lotion body kitchen faucet spray handle kitchen faucet indoor sport court handle kitchen faucet kitchen faucet spout airtight kitchen canister modern kitchen faucet key folding gate design vehicle inspection face recognition attendance machine fedex international rate bill payment online telescopic mirror electric boom gate remove security tag metal detector security eas security system manufacturer living room furniture sofas sofa bed shoe rack cabinet bookcase bookshelve rack cabinet chest chaise lounge chair recliner coffee table coat rack living room set laser level sight glass tubing laser protective goggle waterproof polymer coating laser diode oil level indicator reci laser tube watt laser laser diode laser module oil sight gauge laser tube mechanical accessory part processing metal die stamp android box channel sock sewing thread cone press stamping dimmable led downlight led batten lighting air vent mobile holder usb wireless cost igbt bend test steel manufacturing processing machinery agent metered aerosol valve jib crane manufacturer manufacturing wood pellet maintained emergency light box blade ripper teeth custom juice depaneling machine welding stud bending roll machine pet film recycling nail clipper solar flood lighting industrial knife machine wall mounted air conditioner beauty product packaging nail acrylic kit resting hand drill nail electric winch machine acrylic nail baby nail cutter outdoor plant thick rabbit vibrator indoor playground kid playground horse toy school playground equipment women black sock children playground equipment scale model car acrylic plexiglass mirror train playground equipment indoor kid playground equipment firefighting supply fire fighting nozzle grooved end butterfly valve water slide commercial tile backsplash pressure ball valve water cooled scroll chiller electric actuated valve carbon fibre wrap led spotlight bulb outdoor composite decking tile beauty equipment freeze fat removal laser eye wrinkle freezing fat home treatment spider vein face laser therapy spider vein laser hair removal sale cryolipolysis cavitation vein laser cool freeze lipo glycerol price dental supply dental xray film dental impression bite tray dental xray unit dental disposable dental round bur dental bonding material panoramic dental ray ultrasonic piezo scaler portable suction unit dental resin composite pomegranate fruit can lcd panel supplier led tube stainless steel cable freeze dried fruit wholesale leather kindle case apple iphone car charger custom badminton racket weight gain bodybuilding micro usb connector pressure sensor water treatment process pressure sensitive adhesive tape surface frame panel constant pressure water system linear position sensor gsensor component part gas pressure sensor measurement gas fuel pressure sensor small load cell pneumatic component hand ray double screw extruder manufacture audio video switch reverse rotary drilling compressed air flow control valve front door side panel tie bar cufflink micro dispensing butterfly actuator valve gold purity test machine plastic toy model car scale car toy kid realistic artificial flower rolled stainless steel coil remote control vibrater badminton racket kid synthetic grass dog educational infant toy green house plant printing prototype peat density foam board long welding neck flange vacuum pump water removal cnc plasma cutting machine price ready strip plus sanitary napkin pad toshiba main board retractable air hose reel jump house rent nut rivet gun paving stone wifi signal jammer modern white kitchen cabinet organic pharmaceutical billboard advertising official soccer ball weight galaxy inflatable ball pool natural paving stone extruder machine wpc table lamp rocker switches triple pole isolator pulse jet fabric philtre personal tracking system amp isolator switch shake exhaust fan bathroom oil heating system pole switches auto light switch portable blood chemistry analyzer silk scarve silk scarve silk scarve square yellow silk scarf lady scarve wholesale custom silk scarve silk scarve women blue silk scarve women silk scarve scarf women custom printed scarf shaper size corset sexy blue tight lace corset bra die cast zinc corset size bosch capsule filling machine slim casual pant power bank wifi router magentis kia sticker label sander light led strip water bottle accessory extruded aluminium enclosure lcd open frame display electric diesel transfer pump round stainless steel table double gate dust extraction system tool orbital sander safe lock tool set diamond tipped blade thin wrench set rolling mechanic seat rolling mechanic seat rolling stool garage mechanic rolling seat polyester garage rolling stool pvc injection moulding machine supplier scan code teeth whitening teeth whitening gel teeth whitening home kit teeth whitening treatment teeth whitening laser white teeth whitening ripper shank excavator dental light teeth whitening light home teeth whitening kit steel pet grooming comb loading hardwarewholesalecomeverychina safety latest supplier tooling tech industrial beijing speedata technology hongkong yuancheng gongchuang technology limited guangzhou magical inflatable coltd guangzhou danq technology coltd golden future enterprise wuxi orient antiwear engineering coltd changzhou qishuyan jinda welding coltd hot keyword led spotlight bulb magnet truck diagnostic tool sealed roller bearing led candle light wireless bluetooth speaker replacement touch screen digitizer recessed lighting led stainless steel sheet stainless steel seamless tubing round led panel light storage racking system recommended hot product pvc single layer sheet twin screw extruder cpvc upvc plastic sheet machine custom printing single wall paper cup recyclable hot drink wire edm consumable string wound philtre cartridge micro clean philtre wire edm consumable string wound philtre cartridge micro clean philtre herringbone milking parlour receiving container receiver purple speed gate turnstile control board stainless steel outdoor flap barrier noiseless turnstile speed security gate sus gelatin melting tank layer water bath heating red mobile portable small silent diesel generator set iso flt deutz generator stamford alternator deepsea controller open diesel generator set gas genset deepsea comap smartgen refrigeration copeland condensing unit air cooled condensing unit cold room sery mhz insulated white fractional microneedle scar removal hormone nandrolone undecylate raw steroid powder raw human growth steroid cbm coverage spa room aroma diffuser super quiet refilled fragrance cute brown tiger plush baby rocking animal chair baby ride playing light colour hydrocarbon resin solvent adhesive aromatic resin rav aca toyota radiator aluminium replacement radiator car giant inflatable volleyball court bouncing castle type isuzu truck engine part fuel philtre asm supemarket security tagging system malaysia khz frequency inflatable air jumping bouncer car infatable jumping castle inflatable truck castle sale marine pneumatic rubber airbag salvage shipwreck balloon airbag marine rubber airbag ship launching upgrading interested led solar light micro usb paper bag handle muscle growth steroid usb micro usb usb pcb board assembly cigarette starter kit led street light fixture milling machine cnc rgb led flood light outdoor cctv cameras led strip rgb stainless steel tubing wheel scooter gps navigation car top cell phone water park power bank charge advertising display board home product supplier map contact help privacy policy china hot product copyright hardwarewholesalecom right reserved icp","m_szGeo1":"","m_szSourceType":"source_general","m_szSrcUrl":"http://www.hardware-wholesale.com/products/","m_Places":["Drums","Mobile","Guangzhou","Wuxi","Barrier","Bath","Toyota","Malaysia","Us","China","京"],"m_People":["Nail Clipper","Undecylate Raw","Brown Tiger","Beijing Icp"],"m_Companies":["Apple","Ericsson","Ball","Plastic","Ice Cube","Apc","Signal","Fedex","Cranes","Cnc","Pool","Diesel","Seat","Beijing Speedata Technology Co., Ltd","Hongkong Yuancheng Gongchuang Technology Co., Limited","Guangzhou Danq Technology Co.,ltd","Engineering Co.,ltd.","Changzhou Qishuyan Jinda Welding Co.,ltd","Wire Edm Consumables Pp","Receiver Group","Iso","Coverage Spa","Aca","Asm"],"m_BiGrams":["stainless steel","teeth whitening","silk scarve","general mechanical","mechanical component","kitchen faucet","playground equipment","product supplier","philtre cartridge","micro usb","pressure sensor","scarve silk"],"m_TriGrams":["general mechanical component"],"m_SocialTags":[],"m_Topics":[],"m_Industry":[],"m_Technology":[],"m_BiCnt":[8,8,7,6,6,6,4,3,3,3,3,3],"m_TriCnt":[6],"m_iDocBodyWordCnt":1535}
