{"m_szDocID":"483060","m_szDocTitle":"Zenyatta Announces Successful Completion & Testing of a Purification Process Yielding Highly Crystalline Graphite Exceeding 99.9% Purity; Data Submitted for Finalization of the Preliminary Economic Assessment - Oil & Gas 360","m_szYear":"2016","m_szDocSumamry":"textArticle -------------------- Zenyatta Announces Successful Completion & Testing of a Purification Process Yielding Highly Crystalline Graphite Exceeding 99.9% Purity; Data Submitted for Finalization of the Preliminary Economic Assessment  May 6, 2015 - 8:00 AM EDT close Receive Copy: yes               Zenyatta Announces Successful Completion & Testing of a Purification Process Yielding Highly Crystalline Graphite Exceeding 99.9% Purity; Data Submitted for Finalization of the Preliminary Economic Assessment THUNDER BAY, ON--(Marketwired - May 06, 2015) - Zenyatta Ventures Ltd. (\"Zenyatta\" o","m_szDocBody":"zenyatta announce successful completion testing purification process yielding highly crystalline graphite exceeding purity data submitted finalisation preliminary economic assessment edt close receive copy zenyatta announce successful completion testing purification process yielding highly crystalline graphite exceeding purity data submitted finalisation preliminary economic assessment thunder bay onmarketwired zenyatta venture ltd zenyatta company tsx venture zen pleased announce successfully completed tested innovative purification process production purity graphite albany deposit work performed sgs canada inc sgs significant progress made month improving earlier benchscale process designing distinctive flow sheet specifically albany hydrothermal graphite depositthe data submitted rpa inc rpa completion preliminary economic assessment pea due soon highlight zenyatta designed tested innovative process production purity natural graphite sgs analyse purified albany graphite sample yielded greater purity rpa possession process flow sheet data produce pea report term aubrey eveleigh president ceo zenyatta commented sgs developed benign purification process environmentally benign deposit produce highly crystalline graphite exceeding purityfeedback market including potential strategic partner cleantech sector suggest environmental consideration critical sourcing raw material today tech application energy storage sgs test work successfully designed tested process unique zenyattas albany deposita fully engineered simplified process flow sheet completed providing data crushing grinding flotation residence time temperature energy requirement water treatment reagent consumption equipment sizing mixing separation handlinga technically feasible distinctive process flow sheet developed purify albany graphite continued metallurgical work prefeasibility full feasibility study potential result additional optimizationthe complete process flow sheet engineering data submitted rpa inclusion pea zenyatta acknowledge federal provincial government important support innovative purification processthe national research council canada industrial research assistance programme nrcirap northern ontario heritage fund corporation nohfc initiated ministry northern development mine mndm provided financial contribution advance metallurgical work sgs zenyatta continue develop unique albany graphite deposit northern ontario canadathe project located north transcanada highway power line natural gas pipeline community constance lake nation hearsta rail line located away allweather road approximately graphite deposit outlook global graphite market promising demand growing rapidly applicationsgraphite considered strategic element leading industrial nation growing importance technology manufacturing emerging green industry component energy storage device electric vehicle computer smartphone etc application graphitic material constantly evolving due unique chemical electrical thermal property maintain stability strength temperature excess resistant chemical corrosion lightest reinforcing element natural lubricating ability key physical chemical property make critical modern industry metallurgical test work performed supervision alex mezei msc peng director engineering technical service sgs lakefield independent consultant zenyattaand peter wood peng pgeo exploration zenyattapeter wood alex mezei qualified person national instrument supervised preparation scientific technical information form basis disclosure contained new release reviewed new releasesg performed analyse purified albany graphite sample direct ash analysis platinum crucible validated method accurately quantify key trace level impurity subsequent icp analysisthis allowed sgs accurately characterise purified graphite support metallurgical balancing purpose pea study tsx venture exchange regulation service provider term defined policy tsx venture exchange accept responsibility adequacy accuracy release new release forward information zenyatta caution reader forward information based assumption risk factor actual result differ materially expectation zenyatta included new release new release include forwardlooking statement often alway identified word believe anticipate expect estimate may could would will plan statement based information zenyatta zenyatta assurance actual result meet management expectation forwardlooking statement include estimate statement respect zenyattas future plan objective goal effect zenyatta management expect stated condition result occur including expected timing release sample analyse preliminary economic assessment expected graphite future future graphite zenyattas albany deposit forwardlooking statement based assumption address future event condition nature involve inherent risk uncertainty actual result relating thing result exploration metallurgical processing project development reclamation capital cost zenyattas mineral property zenyattas financial condition prospect differ materially anticipated statement reason limited failure identify mineral resource failure convert estimated mineral resource reserve inability complete prefeasibility study preliminary nature metallurgical test result inability enter offtake agreement qualified purchaser delay obtaining failure obtain required governmental environmental project approval political risk uncertainty relating availability cost financing needed future equity market inflation exchange rate fluctuation commodity price delay development project capital operating cost varying significantly estimate risk involved mineral exploration development industry risk set zenyattas public document filed sedar list exhaustive factor affect zenyattas forwardlooking statement factor considered carefully reader place undue reliance zenyattas forwardlooking statement zenyatta believe assumption factor preparing forwardlooking information new release reasonable undue reliance information apply date new release assurance event occur disclosed time frame all zenyatta disclaim intention obligation update revise forwardlooking information result information future event otherwise required law more edt ","m_szGeo1":"United States","m_szSourceType":"source_industry","m_szSrcUrl":"http://www.oilandgas360.com/zenyatta-announces-successful-completion-testing-of-a-purification-process-yielding-highly-crystalline-graphite-exceeding-99-9-purity-data-submitted-for-finalization-of-the-preliminary-economic/","m_Places":["Thunder Bay","Albany","Ontario","Canada"],"m_People":["Aubrey Eveleigh","Constance Lake","Alex Mezei","Peter Wood"],"m_Companies":["Marketwired","Zenyatta Ventures Ltd.","Venture","Sgs Canada Inc.","'sgs'","Rpa Inc.","'rpa'","Rpa","Cleantech","Associated Engineering","National Research Council Of Canada","Northern Ontario Heritage Fund Corporation","'nohfc'"],"m_BiGrams":["new release","flow sheet","forwardlooking statement","purification process","data submitted","preliminary economic","economic assessment","albany graphite","process flow","highly crystalline","crystalline graphite","graphite exceeding","tsx venture","actual result"],"m_TriGrams":["preliminary economic assessment","process flow sheet","highly crystalline graphite","crystalline graphite exceeding"],"m_SocialTags":[],"m_Topics":[],"m_Industry":[],"m_Technology":[],"m_BiCnt":[6,5,5,4,4,4,4,4,4,3,3,3,3,3],"m_TriCnt":[4,4,3,3],"m_iDocBodyWordCnt":726}
