{"m_szDocID":"483717","m_szDocTitle":"A Fundamental Transformation: “Renewables Win Race on Costs”","m_szYear":"2016","m_szDocSumamry":"textArticle -------------------- A Fundamental Transformation: “Renewables Win Race on Costs” June 15, 2016 by Energy Post Leave a Comment The cost of wind and solar power will continue to fall massively over the next 25 years, bringing about a fundamental transformation of the global electricity sector, according to new reports from Bloomberg New Energy Finance (BNEF) and the International Renewable Energy Agency (IRENA). Electric cars will boom, cheap batteries will be everywhere and there will no Golden Age of Gas, despite continued low gas prices, BNEF predicts. “Low prices for coal and ga","m_szDocBody":"fundamental transformation renewable win race cost energy post leave comment cost wind solar power continue fall massively year bringing fundamental transformation global electricity sector report bloomberg energy finance bnef international renewable energy agency irena electric car boom cheap battery golden age gas continued low gas price bnef predict low price coal gas persist fail prevent fundamental transformation world electricity system coming decade renewable source wind solar balancing option battery key conclusion latest edition energy outlook bnef published june report assume significantly lower price coal gas oil previous edition show steeper decline wind solar cost result competitive advantage renewable energy overtake fossil fuel electricity sector however report growth renewable energy capacity global warming degree celsius trillion invested globally renewable third investment power generating capacity require trillion bring world emission track compatible united nation climate target seb henbest head europe middle east africa bnef lead neo conclusion surprise forecast show golden age gas north america particular rising coalfired generation india asian country lead level higher major conclusion report coal gas price stay lowbloomberg energy finance reduced longterm forecast coal gas price respectively reflecting projected supply glut commodity cut cost generating power burning coal gas wind solar cost fall sharplythe levelised cost generation mwh onshore wind fall solar photovoltaic making technology cheapest way producing electricity country world fossil fuel power attract trillioninvestment coal gas generation continue predominantly emerging economy trillion coalburning capacity billion gasfired plant renewable lion sharesome trillion invested green power onshore offshore wind attracting trillion utilityscale rooftop smallscale solar trillion hydroelectric billion scenario require moneyon top trillion world invest trillion zerocarbon power prevent coin atmosphere rising intergovernmental panel climate safe limit part million electric car boom support electricity demandevs add twh global electricity demand reflecting bnef forecast represent worldwide lightduty vehicle sale year equivalent car time figure smallscale battery storage marketthe rise evs drive cost lithiumion battery making increasingly attractive deployed alongside residential commercial solar system expect total behindthemeter energy storage rise dramatically mwh today gwh expect total behindthemeter energy storage rise dramatically mwh today gwh china coalfired generation follow weaker trend previously projectedchange chinese economy move renewable coalfired generation year time twh below predicted bnef year neo makesindia key future global emission trendit electricity demand forecast grow time investing renewable year billion nuclear continue rely heavily coal power station meet rising demand forecast result trebling annual power sector emission renewable dominate europe overtake gas uswind solar hydro renewable energy plant generate europe power share jump gas slip elena giannakopoulou senior energy economist project noted conclusion surprise forecast show golden age gas north america global generation source gas overtaken renewable renewable overtake coal energy outlook based combination project pipeline country current policy modelled path future electricity demand power system dynamic technology cost assume policy measure post speed decarbonisation intense competition auction irena report power change solar wind cost reduction potential predict similar case steeper cost reduction solar wind coming year irena solar cheaper concentrated solar power csp onshore wind offshore wind cost reduction driven increasing economy scale competitive supply chain technology improvement raise capacity factor reduce installed cost place backdrop increasing competitive pressure drive innovation note report germany morocco dubai peru mexico south africa intense competition auction tender focuse project developer applying practise result market competitive pressure driving cost rapidly efficient level ensuring solar wind power technology offer increasing value however irena note cost reduction potential identified report happen policy regulatory framework place unlike fossilfuelbased electricity generation cost renewable specific partly weather condition quality availability local infrastructure distance project existing transmission line important impact project development cost average residential solar installed cost germany california addition nonstructural factor contribute large variation cost solar particular market shifting today efficient cost structure offer larger cost reduction potential technological innovation economy scale relative practise cost level example average residential solar installed cost germany california utilityscale solar project germany estimated half average installed cost california difference reflect structural cost difference bridged analysis suggest significant opportunity reduce gap extreme example policy put place correct policy setting thus correct policy setting essential unlock ongoing technological improvement cost reduction market existing policy setting essential addressing challenging issue surrounding persistent cost premium case significantly national level local municipal regulation imposing additional cost similarly government proactive term setting policy framework minimise transaction cost forward report note equipment cost solar wind power continue fall balance system cost operation maintenance o&m cost capital rise importance cost reduction driver common o&m cost account onefifth onequarter total lcoe levellised cost electricity time irena note risk profile renewable power generation market individual project large impact cost capital lcoe avoid factor slowing lcoe reduction increased policy industry focus driving cost increasingly important solar and lesser extent csp wind power wide variation balance system bos cost today represent largest source cost reduction opportunity logged post comment logged post comment energy collective column coming soon latest comment bobmeinetz trump nonexistent environmental platform dakotas rick make sense average temp supposedly migratin june rick engebretson trump nonexistent environmental platform lot brag about bob honestly agree opinion not june engineer poet cruising vegas carbon climate change alternate scheme rail canal fuel efficiency frei june bobmeinetz trump nonexistent environmental platform rick brag consequence exception royal dut june advisory panel scott edward anderson consultant blogger media commentator blog green sceptic christine hertzog consultant author professional explainer focused smart grid elias hinckley strategic advisor energy finance energy policy investor energy company government gary hunt gary executiveinresidence deloitte investment extensive experience energy utility industry jesse jenkin graduate student researcher mit expertise energy technology policy innovation jim pierobon help trade government agency company communicate cleaner energy solution geoffrey style managing director gsw strategy group llc awardwinning blogger featured contributor june june ","m_szGeo1":"United Kingdom","m_szSourceType":"source_industry","m_szSrcUrl":"http://www.theenergycollective.com/energy-post/2380965/a-fundamental-transformation-renewables-win-race-on-costs?utm_source=feedburner&utm_medium=feed&utm_campaign=The+Energy+Collective+%28all+posts%29","m_Places":["Outlook","Middle East","Africa","North America","India","China","Europe","United States","Germany","Morocco","Dubai","Peru","Mexico","South Africa","California","Gary"],"m_People":["Seb Henbest","Elena Giannakopoulou","Rick Engebretson","Royal Dut","Scott Edward","Christine Hertzog","Elias Hinckley","Hunt Gary","Jesse Jenkins","Jim Pierobon","Geoffrey Styles"],"m_Companies":["Energy Agency","Irena","United Nations","Target","2020s","Intergovernmental Panel On Climate Change","2020","Deloitte","Strategy Group, Llc"],"m_BiGrams":["cost reduction","coal gas","wind solar","renewable energy","solar wind","installed cost","fundamental transformation","energy finance","golden age","age gas","gas price","coalfired generation","electricity demand","reduction potential","wind power","policy setting","trump nonexistent","nonexistent environmental","environmental platform"],"m_TriGrams":["golden age gas","cost reduction potential","trump nonexistent environmental","nonexistent environmental platform"],"m_SocialTags":[],"m_Topics":[],"m_Industry":[],"m_Technology":[],"m_BiCnt":[8,6,4,4,4,4,3,3,3,3,3,3,3,3,3,3,3,3,3],"m_TriCnt":[3,3,3,3],"m_iDocBodyWordCnt":934}
