{"m_szDocID":"486339","m_szDocTitle":"Video site Le Shi to grab in-car screens in partnership with Chinese carmarker | South China Morning Post","m_szYear":"2016","m_szDocSumamry":"Video site Le Shi to grab in-car screens in partnership with Chinese carmarker Enter multiple addresses separated by commas(,) To: * Message: * CAPTCHA This question is for testing whether or not you are a human visitor and to prevent automated spam submissions. What code is in the image? * Enter the characters shown in the image. Send email Video site Le Shi to grab in-car screens in partnership with Chinese carmarker Â  Video site Le Shi to grab in-car screens in partnership with Chinese carmarker PUBLISHED : Tuesday, 24 March, 2015, 9:38am UPDATED : Wednesday, 25 March, 2015, 8:03pm To forwa","m_szDocBody":"video shi grab incar screen partnership chinese carmarker enter multiple addresse separated commas message captcha question testing human visitor prevent automated spam submission code image enter character shown image send video shi grab incar screen partnership chinese carmarker video shi grab incar screen partnership chinese carmarker published tuesday march updated wednesday march forward default client outlook sent enter multiple addresse separated commas message captcha question testing human visitor prevent automated spam submission code image enter character shown image send hong kongbased startup delivery republic bag million expand asia young consumer lean web popular videosharing website chinais moving traditional media businessby expanding small incar screen shi operator popular online video platform letvcom fastgrowing investorin movie production inked landmark partnership stateowned baic motor chinas top biggest carmaker make connected smart electric car latest tieupbetween mainland carmaker internet firm joint venture unveil incar operating system month user internet entertainment firm application tvs senior executive told south china morning post interview made television introduce mobile phone supercar extension business telematic chief wont introducing car anytime soon weve working interface installed baic motor electric energy car chief executive telematic joint venture told post made television introduce mobile phone supercar extension business screen hope user fluid experience switch terminal another said car roll future wont driverless car smart car capable artificial intelligence run electricity said shis declined reveal function system have detail unveiled shanghai auto show april version androidbased operating system made tablet mobile phone unveiled shedlight upcoming system custom made vehicle version controlled voice touch motion capable automatic navigation chat music streaming online radio video roadside assistance service company cooperation began investment jointly made year atieva electric vehicle design engineering work tesla audi general motor beijingbased internet entertainment firm raised eyebrow announced plan break electriccar production fact set strong research development centre silicon valley year surprised people making disruptive innovation gene company shown history internet video webenabled tvs said referring firm early entry success settop box market forced mainland media regulator tightened control content shi latest number mainland internet company venturing connected vehicle project china encourage traditional vehicle manufacturersto collaborate noncar company boost innovation competition mainland largest engine operator baidu unveil autonomous car half year ecommerce giant alibaba announced start onebillion yuan billionfund saic motor mainland largest carmaker develop connected car sale year united state apple reportedly working electric car pushing begin production early aimed selfdriving car road year ","m_szGeo1":"Hong Kong","m_szSourceType":"source_news","m_szSrcUrl":"http://www.scmp.com/lifestyle/motoring/article/1745980/video-site-le-shi-grab-car-screens-partnership-chinese-carmarker","m_Places":["Enter","Outlook","Hong Kong","Us","Asia","China","Shanghai","Tesla","Beijing","Silicon Valley","United States"],"m_People":["He Yi","Le Telematics"],"m_Companies":["South China Morning Post","Audi","General Motors","Venturing","Alibaba","Saic","Apple","Google"],"m_BiGrams":["incar screen","video shi","shi grab","grab incar","screen partnership","partnership chinese","chinese carmarker","mobile phone"],"m_TriGrams":["video shi grab","shi grab incar","grab incar screen","incar screen partnership","screen partnership chinese","partnership chinese carmarker"],"m_SocialTags":[],"m_Topics":[],"m_Industry":[],"m_Technology":[],"m_BiCnt":[4,3,3,3,3,3,3,3],"m_TriCnt":[3,3,3,3,3,3],"m_iDocBodyWordCnt":394}
