{"m_szDocID":"492056","m_szDocTitle":"AUDI AG, BMW Group and Daimler AG agree with Nokia Corporation on joint acquisition of HERE digital","m_szYear":"2016","m_szDocSumamry":"INGOLSTADT, MUNICH and STUTTGART, Germany, Aug. 3, 2015 /PRNewswire/ --  Acquisition will secure and strengthen HERE as an independent company serving customers from all industries Real-time maps and location based services will be the basis for the mobility of tomorrow Transaction expected to close in first quarter 2016 2015AUDI AG, the BMW Group and Daimler AG have agreed with Nokia Corporation that they will acquire its mapping and location services business HERE. The acquisition is intended to secure the long term availability of HERE's products and services as an open, independent and val","m_szDocBody":"ingolstadt munichandstuttgart germany aug acquisition secure strengthen independent company serving customer industry realtime map location based service basis mobility tomorrow transaction expected close quarter audi bmw daimler agreed nokia corporation acquire mapping location service business here acquisition intended secure long term availability product service open independent creating platform cloudbased map mobility service accessible customer automotive industry sector partner hold equal stake here seek acquire majority interest subject approval relevant antitrust authority transaction expected close quarter laying foundation generation mobility location based service automotive industry basis assistance system ultimately fully autonomous driving extremely precise digital map combination realtime vehicle data order increase road safety facilitate innovative product service basis shared raw data automobile manufacturer offer customer differentiated brandspecific service our environment constantly changing information digital map continually updated maximum utility offered stated rupert stadler chairman board management audi highprecision cameras sensor installed modern car digital eye updating mobility data map way information speed limit critical driving situation recognised today data gained processed compliance strict dataprotection rule here play key role digital revolution mobility combining definition map data vehicle make travel safer easier everyone explained harald krueger chairman board management bmw knowledge benefit carmaker customer highprecision digital map crucial component mobility future joint acquisition here secure independence central service vehicle manufacturer supplier customer industry stated dieter zetsche chairman board management daimler swarm intelligence create information density road map here offer user continuously improving product bringing highly automated driving location based service step further volume anonymized data vehicle increase service convenient connected tailored user individual requirement ulrich hackenberg member board management audi technical development klaus froehlich member board management bmw development thomas weber member board management daimler research explicit intention customer benefit continuous optimization social benefit swarm intelligence enormous facilitate warning hazard real time icy road example based calculation individual data abs activation temperature upcoming traffic jam identified precisely future significantly reducing risk accident way vision accidentfree driving gradually reality stage data learn critical bend road order warn driver good time activate assistance system anticipation green phase stoplight navigate vehicle urban area green wave engine performance minimised fuel consumption highprecision map important autonomous driving form assistance system technology require uptodate plan vehicle surrounding exact nearest centimetre order react real time produce extremely precise static map verified continually updated constant flow data vehicle surrounding continue offer service product industry mapping location intelligence country language main provider mapping location service company continue develop position strong independent provider map locationbased service expand product offering continue make customer industry management continue independent goal moving business case forward platform open customer consortium interfere operational business audi delivered approximately car audi brand customer company achieved revenue billion operating profit billion audi operate globally market production facility ingolstadt neckarsulm germany gyor hungary brussel belgium bratislava slovakia martorell spain kaluga russia aurangabad india changchun foshan china jakarta indonesia brand ring start producing car curitiba brazil year san jose chiapa mexico wholly owned subsidiary audi include quattro gmbh neckarsulm automobili lamborghini spa santagata bolognese italy sport motorcycle manufacturer ducati motor holding spa bologna italy company employ approximately people worldwide thereof germany total investment billion planned primarily product sustainable technology audi committed corporate responsibility anchored principle sustainability product processe strategy long term goal neutral mobility brand bmw mini rollsroyce bmw world leading premium manufacturer automobile motorcycle premium financial mobility service global company bmw operate production assembly facility country global sale network country bmw sold approximately million car motorcycle worldwide profit tax financial year approximately billion revenue amounting billion bmw workforce employee success bmw based longterm thinking responsible action company established ecological social sustainability chain comprehensive product responsibility clear commitment conserving resource integral part strategy shape digital revolution car industry actively daimler world successful automotive company division mercedesbenz car daimler truck mercedesbenz van daimler buse daimler financial service daimler groupis biggest producer premium car world biggest manufacturer commercial vehicle global reach daimler financial service financing leasing fleet management insurance financial investment credit card innovative mobility service company founder gottlieb daimler carl benz made history invention automobile year pioneer automotive engineering daimler continue shape future mobility today group focus innovative green technology safe superior automobile appeal fascinate daimler invest development alternative drive train longterm goal emissionfree driving hybrid vehicle electric vehicle powered battery fuel cell furthermore company consistent path accidentfree driving intelligent connectivity autonomous driving daimler willingly accept challenge meeting responsibility environment daimler sell vehicle service country world production facility europe north south america asia africa current brand portfolio include addition world valuable premium automotive brand mercedesbenz mercedesamg mercedesmaybach brand smart freightliner western star bharatbenz fuso setra thomas built buse daimler financial service brand mercedesbenz bank mercedesbenz financial daimler truck financial moovel cargo company listed stock exchange frankfurt stuttgart stock exchange symbol dai sold million vehicle employed workforce people revenue totaled billion ebit amounted billion forwardlooking statement document forwardlooking statement reflect current view future event word anticipate assume believe estimate expect intend may can could plan project should similar expression identify forwardlooking statement statement subject risk uncertainty including adverse development global economic condition decline demand important market worsening sovereigndebt crisis increasing uncertainty euro zone increase political tension eastern europe deterioration refinancing possibility credit financial market event force majeure including natural disaster act terrorism political unrest industrial accident effect sale purchasing production financial service activity currency exchange rate shift consumer preference smaller lowermargin vehicle lack acceptance product service limit ability achieve price adequately utilise production capacity price increase fuel raw material disruption production due shortage material labour strike supplier insolvency decline resale price vehicle effective implementation costreduction efficiencyoptimization measure business outlook company hold significant equity interest successful implementation strategic cooperation joint venture law regulation government policy relating vehicle emission fuel economy safety resolution pending government investigation conclusion pending threatened future legal proceeding risk uncertainty describe heading risk opportunity report current annual report risk uncertainty materialise assumption underlying forwardlooking statement prove incorrect actual result materially express imply statement intend assume obligation update forwardlooking statement based solely circumstance date publication ","m_szGeo1":"United States","m_szSourceType":"source_news","m_szSrcUrl":"http://www.prnewswire.com/news-releases/audi-ag-bmw-group-and-daimler-ag-agree-with-nokia-corporation-on-joint-acquisition-of-here-digital-mapping-business-300122322.html","m_Places":["Ingolstadt","Munich","Stuttgart","Germany","Abs","Neckarsulm","Gyor","Hungary","Brussels","Belgium","Bratislava","Slovakia","Spain","Kaluga","Russian Federation","Aurangabad","India","Changchun","Foshan","China","Jakarta","Indonesia","Curitiba","Brazil","San Jose","Mexico","Italy","Bologna","Europe","South America","Asia","Africa","Frankfurt","Dai","Eastern"],"m_People":["Rupert Stadler","Harald Krueger","Dieter Zetsche","Ulrich Hackenberg","Klaus Froehlich","Thomas Weber","Agata Bolognese","Gottlieb Daimler","Carl Benz"],"m_Companies":["Bmw Group","Daimler Ag","Nokia Corporation","Audi Ag","Revolution","Bmw Ag.","Bmw","Audi Group","Audi","Automobili Lamborghini S.p.a.","Ducati Motor Holding S.p.a.","Rolls-royce","Mercedes-benz","Daimler Group","Path","Amg","Maybach","Freightliner","Mercedes-benz Bank"],"m_BiGrams":["board management","forwardlooking statement","financial service","customer industry","location based","based service","mapping location","product service","mobility service","assistance system","autonomous driving","digital map","chairman board","data vehicle","member board","daimler financial","risk uncertainty"],"m_TriGrams":["location based service","chairman board management","member board management"],"m_SocialTags":[],"m_Topics":[],"m_Industry":[],"m_Technology":[],"m_BiCnt":[],"m_TriCnt":[],"m_iDocBodyWordCnt":982}
