{"m_szDocID":"492255","m_szDocTitle":"EV Consumer Choice Insights","m_szYear":"2016","m_szDocSumamry":"textArticle -------------------- EV Consumer Choice Insights by Atlas Public Policy Leave a Comment The New York State Legislature passed a bill this past April requiring the creation of an important financial incentive for electric vehicles within 12 months. As the state starts up this rebate program to help achieve its climate goals, it’s worth exploring the market’s development to date to inform the program’s design. The interactive dashboard below tells an interesting story about EV adoption. Using data from EValuateNY , we can see plug-in hybrid vehicles have accounted for about three-qua","m_szDocBody":"consumer choice insight atlas public policy leave comment york state legislature passed bill past requiring creation important financial incentive electric vehicle month state start rebate programme achieve climate goal worth exploring market development date inform programme design interactive dashboard tell interesting storey adoption data evaluateny plugin hybrid vehicle accounted threequarter electric vehicle registered york nationally picture allelectric vehicle slight edge plugin hybrid research suggest plugin hybrid popular allelectric consumer dont rely public charging infrastructure technology easily integrated vehicle size vehicle consistent performance variable climate you enlarge dashboard clicking arrow bottomright corner embed website withtheembed code bottom post factor driving interest plugin hybrid allelectric york explore question market data evaluateny diving deeper data draw worthwhile insight interest northeast state direct financial incentive purchase evs let start evs registered potential effect public charging infrastructure adoption scatter chart top left dashboard observe plugin hybrid allelectric adoption year play button county stood early continue lead way suffolk nassau westchester rest state bunched bottom left corner low adoption vehicle technology discussed previous post fast charging york sparse limiting allelectric adoption driver unable easily travel vicinity home illustrate this let map bottom corner show public level fast charging location glance appear driver anywhere storey clear hide teslas proprietary station see charging network philtre upstate york fast charging presently excluding tesla supercharger highlight quick charging state automaker introduce longer range affordable evs chevy bolt tesla model lack infrastructure noticeably affect adoption structure upcoming state vehicle rebate incentive rebate doesnt distinguish plugin hybrid allelectric steer consumer choice plugin hybrid areas robust public charging adoption rate higher suffolk nassau westchester county york york clean pass programme stand key factor long island expressway connect suffolk nassau county york city clean pass programme eligible plugin vehicle including plugin hybrid single occupant driver expressway hov lane saving driver valuable time scatter chart top left show westchester leader allelectric adoption philtre glean what select automaker philtre unclick tesla expensive long range tesla model allelectric range time allelectric today teslas proprietary network long trip immediately picture clearer filtering tesla number allelectric westchester drop percent westchester wealthiest county state county allelectric excluding tesla albany highest allelectric adoption worth noting albany higher adoption level legacy allelectric vehicle percent cumulative evs albany registered mass market evs introduced now dashboard explore york compare national market insight glean plugin hybrid adoption philtre labelled vehicle top dashboard select chevrolet volt toyota prius vehicle make twothird plugin hybrid registration york prius beating volt toyota halting production gen plugin nationally chevrolet sold volt toyota sold prius plugin popularity volt prius york contrast national market number factor explain yorker flocked prius plugin volt stand out vehicle eligible aforementioned clean pass programme long island expressway research argonne national lab californias hov lane exemption made plugin hybrid limited allelectric range prius plugin viable state nationally popularity volt prius plugin fairly consistent york local dealer influence largely control vehicle lot auto sale staff influence consumer choice example easier explain consumer prius plugin cost upfront compared volt chevy expensive purchaser exercise federal tax credit general prius plugin easier familiar choice volt consumer today prius plugin larger cargo capacity volt longer electric range soontobereleased prius prime mile volt lower fuel economy running allelectric mode important yorker easy public charging study university california davis found prius plugin driver charging owner plugin hybrid longer electric range result driver fewer mile travelled electricity driver york prepare launch rebate programme electric vehicle state dive deep current market ensure valuable incentive desirable outcome evaluateny show consumer responding upfront price allelectric range presence public charging nonmonetary incentive varying degree york positioned structure programme complement factor accelerate adoption year bynick nigro founder atlas public policy embed dashboard code related post logged post comment logged post comment energy collective column coming soon latest comment engineer poet fast lane evs tesla robot arm charging system development time august mark heslep fast lane evs good idea distant future current world wide suite super charger august engineer poet fast lane evs driver buying food timely immediately disconnecting august mark heslep fast lane evs charger interstate highway city minute august advisory panel scott edward anderson consultant blogger media commentator blog green sceptic christine hertzog consultant author professional explainer focused smart grid elias hinckley strategic advisor energy finance energy policy investor energy company government gary hunt gary executiveinresidence deloitte investment extensive experience energy utility industry jesse jenkin graduate student researcher mit expertise energy technology policy innovation jim pierobon help trade government agency company communicate cleaner energy solution geoffrey style managing director gsw strategy group llc awardwinning blogger featured contributor august august ","m_szGeo1":"United Kingdom","m_szSourceType":"source_industry","m_szSrcUrl":"http://www.theenergycollective.com/atlaspublicpolicy/2384437/ev-consumer-choice-insights?utm_source=feedburner&utm_medium=feed&utm_campaign=The+Energy+Collective+%28all+posts%29","m_Places":["New York State","New York","Suffolk","Nassau","Westchester","Tesla","Long Island","New York City","Albany","Toyota","California","Gary"],"m_People":["Ev Drivers","Evs Tesla","Nick Nigro","Mark Heslep","Evs Good","Evs A Driver","Scott Edward","Christine Hertzog","Elias Hinckley","Hunt Gary","Jesse Jenkins","Jim Pierobon","Geoffrey Styles"],"m_Companies":["Charging Network","Westchester Counties","Nassau Counties","Volt","Volts","New Yorkers","University Of California At Davis","Deloitte","Strategy Group, Llc"],"m_BiGrams":["plugin hybrid","prius plugin","public charging","allelectric adoption","fast lane","lane evs","consumer choice","electric vehicle","hybrid allelectric","suffolk nassau","fast charging","clean pass","pass programme","allelectric range","volt toyota"],"m_TriGrams":["fast lane evs","plugin hybrid allelectric","clean pass programme"],"m_SocialTags":[],"m_Topics":[],"m_Industry":[],"m_Technology":[],"m_BiCnt":[12,8,5,4,4,4,3,3,3,3,3,3,3,3,3],"m_TriCnt":[4,3,3],"m_iDocBodyWordCnt":750}
