{"m_szDocID":"492947","m_szDocTitle":"Oil and Natural Gas Production Jobs in May Were 26% Lower Than in October 2014","m_szYear":"2014","m_szDocSumamry":"textArticle -------------------- Oil and Natural Gas Production Jobs in May Were 26% Lower Than in October 2014 August 8, 2016 by U.S. EIA: Today in Energy Leave a Comment Source: U.S. Bureau of Labor Statistics, Current Employment Statistics and Baker Hughes North America Rig Count . Note: Rig counts are U.S. totals for oil and natural gas, including offshore. Weekly rig count data are converted to monthly data by taking the average weekly readings each month. Despite increases in crude oil prices since the start of the year, employment in oil and natural gas extraction and support activities","m_szDocBody":"oil natural gas production job lower eia today energy leave comment source bureau labour statistic current employment statistic baker hughes north america rig count note rig count total oil natural gas including offshore weekly rig count data converted monthly data taking average weekly reading month increase crude oil price start year employment oil natural gas extraction support activity continued declining level reached fall onset falling oil price total rig count including oildirected natural gasdirected rig declined sharply rig fall weekly low rig crude oil production declined lesser extent employment rig count natural gas production levelled off employment oil natural gas production reached job then oil natural gas production employment declined loss job based latest job data available total decrease production job time job lost month period recession production job directly related drillingthe majority job extraction support activity include operation drilled well exploration excavation surveying casing work construction include maintenance producing well effect reduction drilling employment crude oil natural gas production modest production level respectively relative level compared peak month employment sector crude oil production lower natural gas production flat divergence trend rig count employment hand oil trend natural gas production attributable increase production key region driven part advance siting drilling technology instance newwell oil production rig level areas bakken eagle ford permian growing offshore crude oil production gulf mexico helped offset decline lower onshore production logged post comment logged post comment energy collective column coming soon latest comment bobmeinetz blockchain energy utility industry infographic david evidence contradict theory introducing needless complexity sys august engineer poet china blow fuse hinkley point delay french company operate themgood question that august helmut frik fast lane evs expected premium feature electric car future combination august hop gegangen dont book solarpowered flight aviation biofuel reasonable economic carbon footprint free saudis august advisory panel scott edward anderson consultant blogger media commentator blog green sceptic christine hertzog consultant author professional explainer focused smart grid elias hinckley strategic advisor energy finance energy policy investor energy company government gary hunt gary executiveinresidence deloitte investment extensive experience energy utility industry jesse jenkin graduate student researcher mit expertise energy technology policy innovation jim pierobon help trade government agency company communicate cleaner energy solution geoffrey style managing director gsw strategy group llc awardwinning blogger featured contributor august august ","m_szGeo1":"United Kingdom","m_szSourceType":"source_industry","m_szSrcUrl":"http://www.theenergycollective.com/todayinenergy/2384765/oil-and-natural-gas-production-jobs-in-may-were-26-lower-than-in-october-2014?utm_source=feedburner&utm_medium=feed&utm_campaign=The+Energy+Collective+%28all+posts%29","m_Places":["United States","North America","Gulf Of Mexico","China","Hinkley","Gary"],"m_People":["Helmut Frik","Scott Edward","Christine Hertzog","Elias Hinckley","Hunt Gary","Jesse Jenkins","Jim Pierobon","Geoffrey Styles"],"m_Companies":["U.s. Bureau Of Labor Statistics","Baker Hughes","Deloitte","Strategy Group, Llc"],"m_BiGrams":["natural gas","gas production","oil natural","rig count","crude oil","oil production","production job"],"m_TriGrams":["natural gas production","oil natural gas","crude oil production"],"m_SocialTags":[],"m_Topics":[],"m_Industry":[],"m_Technology":[],"m_BiCnt":[9,7,6,6,5,4,3],"m_TriCnt":[7,6,3],"m_iDocBodyWordCnt":376}
