{"m_szDocID":"494893","m_szDocTitle":"Most cars will be 'connected' by 2017: analysts - NY Daily News","m_szYear":"2016","m_szDocSumamry":"NYDailynews.com X Home New York News Politics Sports Entertainment Opinion Living Search DAILY NEWS Autos Car Buying Reviews News & Pics Most cars will incorporate Internet, automotive telematics technology by 2017, say analysts Market researcher ABI predicts that over 80% of cars in US, Western Europe will be 'connected' NEW YORK DAILY NEWS Friday, July 6, 2012, 12:46 PM A A A facebook Tweet email Lexus Lexus is working on connected systems like this one on the 2013 Lexus ES 300h. Internet, smart apps and other high-tech features will be standard in most cars five years from now, according to","m_szDocBody":"nydailynewscom home york new politic sport entertainment opinion living daily new autos car buying review new pic car incorporate internet automotive telematic technology analyst market researcher abi predict car western europe connected york daily new friday tweet lexus lexus working connected system lexus internet smart app hightech feature standard car year now analyst percent world car connected market researcher abi expect exceed percent western europe car pumped full smarter technology developing region latin america eastern europe large jump number vehicle telematic brazil russia lead trend driven countryspecific mandate incar connectivity quickly transforming automotive industry enabling passive active safety security offering infotainment connected lifestyle service consumer enabling car ownership usage experience mode car sharing semiautonomous driving dynamic demandresponse electric vehicle charging pricing customer vehicle relationship management service including prognostic preventive maintenance abi practise director dominique bonte abi global oem connected car system penetration hit percent car company ford toyota lexus audi bmw developing connected car future microsoft reportedly working generation connected car platform kinect window window phone window live bing azure tellme connected car future like software connected device cloud computing company symphony service created infographic pdf highlight incar feature expect join conversation autos video browse brand acura audi bmw buick cadillac chevrolet chrysler dodge fiat ford gmc honda hyundai infiniti jaguar jeep kia land rover lexus lincoln mazda mercedesbenz mini mitsubishi nissan porsche ram scion smart subaru toyota volkswagen volvo browse type convertible coupe crossover hatchback sedan luxury minivan suv diesel van waggon sport car truck cpo gallery bottom worst car category buy car car bottom list consumer report ranked vehicle worst respective classe based roadtest score reliability gas mileage price batman bmw superman bugatti match superheroe super car ukbased automotive website carwow match star war character car gave treatment top comic book heroe toyota corolla world bestselling car turn car die year toyota corolla strong year year york auto show speed luxury style supercar alley all york auto show floor massive difficult day attending public day absolute stop super car alley jawdropping capital world week york auto show nypd showcase cop car history collection classic nypd car ranging ford plymouth diplomat display inside york auto show car provided nypd museum private collector dna award winner daily new autos award car truck won big winner dna award winner mazda miata winner dna award winner honda odyssey winner dna award winner chevrolet volt winner dna award winner mazda winner dna award winner honda fit winner dna award winner chevrolet colorado winner dna award winner mazda winner dna award winner volvo winner dna award winner mercedesbenz sclass winner dna award winner honda pilot winner dna award winner porsche macan winner dna award winner mazda winner dna award winner mazda winner dna award winner cadillac ctsv winner dna award winner cadillac ats winner dna award winner mercedesamg winner media kit home delivery newsletter businesse place ads contact career faqs feed map website signify agreement term service privacy policy copyright nydailynewscom right reserved","m_szGeo1":"United States","m_szSourceType":"source_general","m_szSrcUrl":"http://www.nydailynews.com/autos/cars-incorporate-internet-automotive-telematics-technology-2017-analysts-article-1.1109048#","m_Places":["Most","Us","Europe","Latin America","Eastern","Brazil","Russia","Toyota","Lincoln","Subaru","Van","Well","Batman","U.k.","New York","Winners","Winner"],"m_People":["Dominique Bonte"],"m_Companies":["New York News","Daily News","New York Daily News","Facebook","Audi","Bmw","Microsoft","Afp","Cadillac","Honda","Hyundai","Infiniti","Jaguar","Land Rover","Mazda","Mercedes-benz","Volkswagen","Volvo","Diesel","Consumer Reports","Nypd Showcases","Nypd","Volvo Xc90","Mazda Cx-5","Cadillac Ats","Amg"],"m_BiGrams":["dna award","award winner","winner dna","winner mazda","connected car","york auto","auto show","mazda winner","daily new","winner honda"],"m_TriGrams":["dna award winner","winner dna award","award winner mazda","york auto show","award winner honda"],"m_SocialTags":[],"m_Topics":[],"m_Industry":[],"m_Technology":[],"m_BiCnt":[17,17,16,5,4,4,4,4,3,3],"m_TriCnt":[17,11,5,4,3],"m_iDocBodyWordCnt":488}
