{"m_szDocID":"496606","m_szDocTitle":"Car news | Auto Express","m_szYear":"2016","m_szDocSumamry":"//><! Skip to main content area User menu Site top menu Newsletter Free mobile app Get 6 issues for £1 Main menu Car News Car Reviews Best Cars Car Deals Find a review Choose a make Abarth Alfa Romeo Alpina Alpine Ariel Ascari Aston Martin Audi Bentley BMW Bristol Bugatti Cadillac Caterham Chevrolet Chrysler Citroen Corvette Dacia Daihatsu David Brown DFSK Dodge DS Elemental Ferrari Fiat Fisker Ford Genesis Ginetta Great Wall Honda Hummer Hyundai Infiniti Invicta Isuzu Iveco Jaguar Jeep Kia Kode KTM Lamborghini Land Rover LDV Lexus Lotus Lykan Marcos Maserati Maybach Mazda McLaren Mercedes MG ","m_szDocBody":"skip main area menu top menu newsletter free mobile app issue main menu car new car review car car deal review choose make abarth alfa romeo alpina alpine ariel ascari aston martin audi bentley bmw bristol bugatti cadillac caterham chevrolet chrysler citroen corvette dacia daihatsu david brown dfsk dodge elemental ferrari fiat fisker ford genesis ginetta great wall honda hummer hyundai infiniti invicta isuzu iveco jaguar jeep kia kode ktm lamborghini land rover ldv lexus lotus lykan marcos maserati maybach mazda mclaren mercede mini mitsubishi morgan nissan noble perodua peugeot polaris porsche proton qoros radical renault rollsroyce saab seat skoda smart srt ssangyong subaru suzuki tesla toyota trident vauxhall volkswagen volvo westfield zenos choose model secondary menu van videos accessory tyre opinion car driver power tip advice section here home car new car new trending manufacturer audi fiat ford honda mercede nissan peugeot renault citroen volkswagen dacia vauxhall show manufacturer abarth alfa romeo alpina alpine ariel ascari aston martin audi bentley bmw bristol bugatti cadillac caterham chevrolet chrysler citroen corvette dacia daihatsu david brown dfsk dodge elemental ferrari fiat fisker ford genesis ginetta great wall honda hummer hyundai infiniti invicta isuzu iveco jaguar jeep kia kode ktm lamborghini land rover ldv lexus lotus lykan marcos maserati maybach mazda mclaren mercede mini mitsubishi morgan nissan noble perodua peugeot polaris porsche proton qoros radical renault rollsroyce saab seat skoda smart srt ssangyong subaru suzuki tesla toyota trident vauxhall volkswagen volvo westfield zenos show trending manufacturer sponsored link tesla model new tesla model revealed price spec release date apr tesla model revealed tesla ceo elon musk delivery due know motor show new infiniti price sale date announced apr infinitis crossover version hit showroom summer priced geneva motor show new seat ateca suv price sale date full detail apr full specification pricing seat ateca suv now starting price volvo new updated volvo polestar bhp fourcylinder engine apr brand announce new evolution volvo polestar fast estate fourcylinder drivee power efficiency weight geneva motor show new newly facelifted bentley mulsanne uncovered geneva apr luxury bentley mulsanne speed lwb version promise most relaxing environment world rear passenger car new feature fool day joke car brand apr fool day year big car brand involved fool joke tokyo motor show new hydrogenpowered lexus lffc concept shown tokyo apr lexus unveil lffc luxury concept previewing hydrogen fuel cell powertrain striking styling tesla tesla model picture gallery consumer new new steel crisis force car maker shop abroad mar tata steel plant closure nissan vauxhall import steel model built supply tesla new tesla motor history rise upstart what mar tesla motor automotive industry zeros electric car heroe short year read feature car deal car test ford focus audi volkswagen golf new york motor show new roundup feature car new audi crossover price spec release date auto express update follow follow newsletter latest poll tvr set begin building car again car brand back business poll status open %plymouth %triumph %austin %rover %saab %de tomaso %pontiac sponsored link car car car search car car car search contact auto express editorial office cleveland street london connect subscription auto express subscription guillat avenue kent science park sittingbourne kent web overseas subscription issue gift subscription overseas sub renew link car new car review car car deal company website contact privacy notice feed author sitemap trending manufacturer audi bmw ford honda hyundai kia land rover mazda mercede nissan peugeot renault seat skoda toyota vauxhall volkswagen manufacturer new article award car comparison car test indepth review longterm test picture product test product review road test spy shot car test videos website carbuyer evo pro coach alphr mobile expert review channel pro digital slr photography den geek week magazine women fitness cloud pro magbook cyclist classic performance car restaurant deal copyright dennis limited auto express trademark felix dennis felix dennis app book job media information subscription enquire online choice","m_szGeo1":"United Kingdom","m_szSourceType":"source_general","m_szSrcUrl":"http://www.autoexpress.co.uk/car-news","m_Places":["Mobile","Best","Bristol","Kode","Subaru","Tesla","Toyota","Vauxhall","Uk","Geneva","Brand","Most","Tokyo","New York","Plymouth","Austin","London"],"m_People":["Elon Musk","Cleveland Street","Felix Dennis"],"m_Companies":["Aston Martin","Audi","Bmw","Cadillac","Citroen","Honda","Hyundai","Infiniti","Iveco","Jaguar","Lamborghini","Land Rover","Lotus","Maybach","Mazda","Peugeot","Polaris","Renault","Rolls-royce","Seat","Suzuki","Trident","Volkswagen","Volvo","Lf","News Uk","Tesla Motors","Volkswagen Golf R","Facebook","Youtube","Twitter","Rover","Coach","Copyright Dennis Publishing Limited"],"m_BiGrams":["car new","motor show","show new","auto express","new car","land rover","seat skoda","vauxhall volkswagen","trending manufacturer","tesla model","car brand","car test"],"m_TriGrams":["motor show new"],"m_SocialTags":[],"m_Topics":[],"m_Industry":[],"m_Technology":[],"m_BiCnt":[6,5,5,4,3,3,3,3,3,3,3,3],"m_TriCnt":[5],"m_iDocBodyWordCnt":638}
