{"m_szDocID":"498212","m_szDocTitle":"Next Big Future: IBM Watson providing superior cancer treatment plans and will accelerate the adoption of new cancer research","m_szYear":"2013","m_szDocSumamry":"Coverage of Disruptive Science and Technology Forum About Contact Facebook twitter Google February 09, 2013 IBM Watson providing superior cancer treatment plans and will accelerate the adoption of new cancer research artificial intelligence, cancer, databases, future, ibm, medicine, science Facebook Twitter linkedin google Reddit The IBM Watson system gained fame by beating human contestants on the television quiz show Jeopardy! almost two years ago. Since that time, Watson has evolved from a first-of-a-kind status, to a commercial cognitive computing system gaining a 240 percent improvement i","m_szDocBody":"coverage disruptive science technology forum contact ibm watson providing superior cancer treatment plan accelerate adoption cancer research artificial intelligence cancer database future ibm medicine science linkedin reddit ibm watson system gained fame beating human contestant television quiz show jeopardy year ago time watson evolved firstofakind status commercial cognitive computing system gaining percent improvement system performance reduction system physical requirement percent run single power server ibm watson trained medicine leverage million patient record million page cancer research ibm watson ingested piece medical evidence million page medical journal clinical trial area oncology research watson power sift million patient record representing decade cancer treatment history medical record patient outcome provide physician evidence based treatment option matter second year memorial sloankettering immersed watson complexity cancer explosion genetic research set stage changing care practise cancer patient highly specialised treatment based personal genetic tumour type starting lung cancer case memorial sloankettering clinician analyst training watson extract interpret physician note lab result clinical research sharing profound expertise experience treating hundred thousand patient cancer year latest development oncology reach practise setting combination transformational technology found watson cancer analytic decisionmaking process potential revolutionise accessibility information treatment cancer community country world craig bthompson president memorial sloankettering cancer centre ultimately expect comprehensive evidencebased approach profoundly enhance cancer care accelerating dissemination practicechanging research unprecedented pace ibm memorial sloankettering wellpoint introducing commercially based product based watson innovation represent breakthrough medical professional apply advance analytic natural language processing big data combined clinical knowledge base including genomic data order create evidence based decision support system watsonbased system designed assist doctor researcher medical centre insurance carrier ultimately enhance quality speed care product include interactive care insight oncology powered watson collaboration ibm memorial sloankettering wellpoint wellpoint interactive care guide interactive care reviewer powered watson designed utilisation management collaboration wellpoint ibm interactive care insight oncology cognitive system insight gleaned deep experience memorial sloankettering clinician provide individualised treatment option based patient medical information synthesis vast array updated vetted treatment guideline published research ofitskind watsonbased advisor cloud expected assist medical professional researcher helping identify individualised treatment option patient cancer starting lung cancer user detailed record data information reach treatment option oncologist located remotely detailed treatment option based updated research decide care individual patient wellpoint interactive care guide interactive care reviewer deliver watsonbased cognitive computing system anticipated streamline review processe patient physician health plan potentially speeding approval utilisation management professional reducing waste helping ensure evidencebased care provided expected accelerate accepted testing treatment shortening preauthorization approval time mean patient moving forward crucial step treatment quickly analyse treatment request matches wellpoint medical policy clinical guideline consistent evidencebased response clinical staff review anticipation providing faster informed decision patient care wellpoint deployed interactive care reviewer select number provider midwest believe provider product end year article give quick review ycombinator stumbleupon author brian linkedin reddit newer post older post home message archive ibm watson providing superior cancer treatment pla printing made awesome joy robohand piece president comman nonsmartphone mobile phone nonexisten german developing weed control laser armed micron long wing commander hellcat model propellentless emdrive research continue china middle class affluent america informal china aggressive step cleaner fujifilm printable bendable thin film thermoe nextbigfuture made front reddit seventh actor die unlucky babylon ground space based telescope charac gigabit internet deployment prospect hydro beat coal nuclear beat oil france constructed earthquake cloaking pro manufacturing job leaving china return bigelow aerospace announce pricing inflatable superconducting wire time yolkshell design store time energy laser based generation energy neutron printing human embryonic stem cell cable company make margin internet servic economical convert carbon dioxide selfassembled quantum dot nanowire system efficient computer display enhanced biome aubrey grey sen antiaging interviewed glu breakthrough organic spin electronic stor mixing polymer fibre carbon nanotube make pbs show gigapixel video feed analysi impulse drive mach effect thruster carnival nuclear energy carnival space joe eck report celsius superconductor top site fin nextbigfuture week biosingularity brian bio lifeboat foundation build world greatness centauri dream centre responsible nanotech coal bad diamond semiconductor mnt break improvement economic logjam foresight nanodot future pundit instapundit kinematic selfreplicating machine book online melanie swan futurememe methuselah foundation molecular nanotechnology engine nanotechnology nextbigfuture flipcard nuke mean coal nuclear cannon summary nuclear green charle barton quantum computer summary space nanotechnology synthetic biology assembly pathway thorium energy thorium mass produced clean nuclear power universe today blognano nanoscale material lifeboat foundation nanoparticle drug delivery community follow popular label future science energy technology united state china world space nuclear physic economic impact medicine material military prediction japan europe robotic oil gadget gdp astronomy environment nasa solar russia economy car future weapon google disease launch fusion india laser airplane battery canada propulsion life extension computer risk internet longevity policy artificial intelligence darpa public health politic population carbon nanotube carnival space spacex brain graphene quantum computer economic electric car controversial death cancer sensor dna nanotechnology telescope enabling technology gene therapy communication smartphone uranium qubit city singularity transhuman electronic coal stem cell navy commercialization war molecular nanotechnology antiaging climate change metamaterial nanoscale carnival nuclear energy fission mar wireless superconductor poverty water computer memory elon musk regeneration magnet mit air pollution dwave wind apple movy supercomputer tissue engineering uav cold fusion sen moon africa peak oil asia ibm intel adiabatic quantum computer imaging gadget building food additive manufacturing synthetic biology air force business quantum effect television cellphone germany display agriculture south korea nanoparticle public transportation hypersonic broadband dna nanotechnology gene sequencing lithography thorium wealth bootstrapping nanotechnology natural gas ship colonisation personalised medicine satellite genetic engineering israel low energy nuclear reaction taiwan australia bakken computer architecture north dakota nvidia superconductor iran assembly dense plasma focus fiction engineering computer korea transportation education hybrid samsung cameras iphone weapon ageing nanowire quantum dot focus fusion sander olson niac android army optical networking spintronic exoskeleton skyscraper drone geopolitic thermoelectric brain emulation microscope rossi futurist interview france geopolitical invisible optical computing mind computer interface printable electronic protein microsoft vaccine asteroid biofuel cyborg ocean singapore tablet room temperature superconductor ultracapacitor diamond petaflop iec fusion rna petaflop terahertz intelligence concentrated solar power exaflop molten salt mathematic faster moore law speed rail machine learning nanomedicine oilsand tablet cognitive enhancement italy nanomaterial mem manufacturing supercomputer telescope gpgpu memristor performance enhancement quantum annealing iraq rapid manufacturing engine regenerative medicine california global warming cloud computing finance neuron saudi arabia nanostructured virus nanoparticle drug delivery plasmonic silicon photonic solar sail alzheimer speculation transhumanist deepwater oil guided assembly aeroplane mach effect railgun alberta brazil molecular electronic planetary resource smartphone dna origami economy electric plane lab chip oil shale submarine direct energy weapon flexible electronic hydro rapid prototyping robot security facebook biomarker lifeboat foundation wearable electronic myostatin inhibitor nextbigfuture radiation crispr gpu mechanical nanotechnology drexler photonic propulsion active cloak fuel cell memristor mundane singularity ocean ukraine amd friedlander algorithm broad group euv lithography general fusion genomic presingularity submarine quantum computer space elevator teraflop electric bike job emdrive femtosecond laser nanophotonic precursor technology superlense tesla laser atomically precise manufacturing fish flash hologram mexico programmable molecular nanotechnology surveillance texas zettaflop material resolution neuromorphic policy saskatchewan wealthy flu blacklight power desalination millimetre wireless star war gigapixel dna synthesis project orion deep learning genome engineering nanoelectronic nanopatterning plasmon terrorism fabber mitochondria amazon diamondoid mechanosynthesis pollution video game exaflop gigabit hyperion power generation indonesia silicon challenge diabete entertainment exoplanet ocean mining winterberg xprize rna interference gene synthesis geoengineering mri bloodstream robot camera carbon capture hunger pathway casimir force heartland robotic teraflop oled freitas helion energy nanoimprint roll roll computational chemistry hyperloop open source robot social media fpgas electric sail kitegen nanomembrane spaceplane lighting plane robotic smart grid techonomy augmented reality brillouin energy contour crafting cubesat future weapon mobile nanolaser prediction quantum encryption semiconductor skyscraper big data biofuel crowdfunding hong kong kickstarter nanocomposite parkinson disease vietnam virtual reality zyvex atomic layer deposition dna manufacturing ebeam lithography flying car gps medical nanodiamond nanoribbon terabit ethernet verizon aircraft algae antimatter city electric futurist graphite nem nuclear fusion pakistan privacy spain superconducting synthetic life agi antenna defkalion exascale nanomagnet nanotechnology business satellite solve sport star trek tensilica transformation optic transgenic attosecond laser car cryonic display drone eestor gene led nanoplasmonic rapamycin resveratrol seastead sound syria urbanisation dna computer building communication dome double lithography genescient genome internet thing liquid fluoride petrobank quantum wimax adaptive clinical trial cloning cvd nanofactory nanofiber nanowire power beaming rejuvenation safety south africa spiderfab telomere claytronic ideas factory bitcoin crowdsourcing deep reinforcement learning epigenetic magnet nanorobotic state matter pluto sony lidar bolonkin construction electric car femtotech geothermal googlex hyperlense mram nanoantenna nanolithography nervous system petabyte phase change material reusable rocket south america thermophotovoltaic cell video vision cnano technology lpp fusion rfid bacteria chemistry concrete ereader gas graphane harvesting law enforcement metformin nanopore ovonic petawatt petrobakken renewable society space based solar power tourism toyota vertical farming dna nanoarray artificial organ bioprinting egypt electron beam farming fullerene funding gbp genetic honda leap motion lenr matter nanocomp technology optogenetic plasma port security programmable matter rethink robotic sensor terrestrial energy ilemm asteroid atomtronic brain computational lithography database ebola innovation meat factory nanobot nanoparticle nanosensor north korea red camera room temperature spintronic scooter scramjet smart dust superintelligence taxe war asic rotaxane aerogel atomic swiches biotechnology calico cement conservation dip pen lithography ecat electricity exawatt exosuit genomic engineering loon temperature reactor history hypertelescope illusion interview kurzweil mind reading movie nanodot nanorod nanotube obesity photonic poor replication soft exoskeleton fork tilera trialpha energy turkey work antennas atom circuit battery bigelow cleantech cloud cray cryocooling disruption fpga ftl futurism gene drive hybrid irna internet everything laptop magnetic monopole motorcycle nanodevice productivity quantum well risk silicon valley solar energy stratolaunch sun microsystem synapse terapixel tool topdown nanotechnology ultrasound vaccine microrna nigel cook annealing baidu cmos boron nanotube bubble commercial computational government corruption death deep mind diesel dubai entrepreneur ethic exoplanet flibe energy follistatin george church glass greece hoverboard industry infrastructure jetpack medicine memcapacitor meminductor microscale monopole nanomagnet logic nanomembrane nanometal nanomotor nanorod nanotip nuclear energy optical tweezer personal transport protein quantum biology rna nanotechnology sensing smartwatch super vision synthetic fuel terabyte trapped ion venus wolfram alpha abundance artificial life avagadro scale computing baldness bike bioengineering brain uploading chromebook cyberwar diblock copolymer dna brick ebook emc energy united state exabyte exponential manufacturing extinction fast boat faster light fat loss genome haptic interface health highlight ipad low power malnutrition material methuselarity mice microbiome micronutrient microscope middle class montana nanoionic memory nanomanufacturing nanopore nanotechnology ipo nantero nuclear fission nutrigenomic parallel petapixel plasmonic lithography political poll result ppp programmable metallization cell qubit railgun recombineering driving car service science ship silicene spaser spinplasmonic sport stm straintronic tech terabit transparent water wikileak wireless power world war xray zettawatt amazon baxter ben goertzel fgpa freeman dyson pacer usv alphabet antilaser automation beam pen lithography biochar buiding capri carbon atomic chain carbyne cella energy cloaking cluster state quantum computer crime data mining dell detection employment energy exciton existential risk fat field effect transistor fighter finfet flywheel freepiston engine future energy gdp economic impact gecko gigaflop future graphyne gravity head mounted display iarpa jovion corporation laser sintering liposuction magnetic magnetricity marine medicine megacity merkle metagenomic metamaterial metmaterial microtechnology miltary moon nanocrystalline cellulose nanocube nanodisk nanoenergetic nanoglue nanolattice nanooptic nanopillar nanoprobe nanosand nanosheet nanostore nanosurgery nanowelding neurorobotic pandemic personal aviation petahertz picometer picoprojector popululation printable robot quantum cellular automata quantum computing quantum dot rail ribosome russian rydberg matter science future skylon software space tower spinal cord subatomic tank techology telecope telsa thinfilm transmutation tricorder triple lithography utility fog venter bullet wave disc engine wet nanotechnology yottabyte yottaflop youtube zpinch point energy zettabyte tsunami british columbia cycle computing euclideon gna nanotechnology grant norton hcar herman kahn legend iedm jame miller jason stowe john mankin juan enriquez kardashev keith lofstrom lower montney montney nen peter glaser production rrnil red whittaker rodney brook upper montney vtol acer aerographite aid alaska algorithm alphago anodization nanolithography architecture astronomgy battery ibm bettery biosyntrolysis biocomputer biofab bionano blue origin brian ahern brontobyte buckypaper buckywire cardiovascular carmera cell china energy china nuclear chiplet chipsat cholesterol cold war history colloidal quantum dot comcast compute computing connectomic convergence copper nanowelding cornocopia cortical computing cosmology country crescent point cryosleep cryptocurrency cyborg camera dark knight data science dendrimer diamandis dielectrophoresis dry nanotechnology eagle ford econ economice ecoskeleton electrohydrodynamic elevator eor esail exalfop ferropaper flop free space optic freepiston linear alternator fure future physic future wireless futute gadget sensor gate around glycerol nucleic acid golden spike googlke graphen graphene monoxide graphic green halophyte handheld head transplant helium helphookupcom humour hypersound idaho national lab india science intel future interstellar intracellular machine ion beam ivf launch loop lifi litecoin lithium sulphur lunar lysosome magnetic magnetic resonance force microscopy magnetic superatom magnet future maker masdar maser mcam media equivalence memcomputing memflector metabolic engineering metalen metananocircuitry methane methylome microassembly microcontact printing miitary millimetre scale computing mining nabsy nanoorigami nanoarches nanobrain nanobubble nanobud nanocable nanocar nanoceramic nanochannel nanocone nanodiamond nanodome nanofluid nanofoam nanogravure nanoionic nanokite nanolipogel nanometer nanopantography nanopaper nanopost nanoscalpel nanoshell nanoshield nanosolder nanostar nanothread nanoweave nasa future nasa science nasa niac neural turing machine nias nokia nram nuclea numenta obama optalysy optical metamaterial assembly optoelectronic optomec paintable battery paperphone paralysis peptoid nanotechnology perfect len petabit phablet phycsic physic science picoscale plasmene polariton superfluid polariton polaritronic political future poltic popup mem probabilistic cmos propulsion launch protection protocell quad lithography quantum learning quantum simulation quantum spin liquid qudit regenerative dentistry remote rfstm scanning beam interference lithography scarcity sceince science fiction calculation science quantum communication sciencee sciene sense server sky server smart dew smokefree cooker sprayon solar power stanene startram statite ste stumbleupon supercavitation superinsulator superlattice synthetic chemistry tcarbon technogy technology energy technology gagdet technolology techonology tegra teleccope telemedicine terawatt hobbit timing tokomak topological quantum computer tpv cell train trialpha energy tristar tropic thunder turbine tyler formation ultrashort pulse ultravector united universal memory upu interface videos vietname voice recognition weapon wifi willow garage wind solar wnd word lab zeolite zeptojoule zram plugin energy space science technology world medicine robotic quantum computer artificial intelligence copyright big future inc right reserved registration constitute acceptance term service privacy policy uscontact ","m_szGeo1":"","m_szSourceType":"source_general","m_szSrcUrl":"http://nextbigfuture.com/2013/02/ibm-watson-providing-superior-cancer.html","m_Places":["Best","Made","China","America","United States","France","Japan","Europe","Russian Federation","India","Canada","Uk","Africa","Asia","Germany","South Korea","Israel","Taiwan","Australia","North Dakota","Iran","Korea","Singapore","Italy","Iraq","Saudi Arabia","Brazil","Ukraine","Mexico","Indonesia","Hong Kong","Viet Nam","Pakistan","Spain","Syria","South Africa","South America","Egypt","North Korea","Turkey","Silicon Valley","Dubai","Greece","British Columbia"],"m_People":["Craig B.thompson","Brian Wang","Joe Eck","Green - Charles Barton","Red Whittaker","Nigel B. Cook","Ben Goertzel","Freeman Dyson","Grant Norton","Herman Kahn","James Miller","Jason Stowe","John Mankins","Juan Enriquez","Keith Lofstrom","Peter Glaser","Rodney Brooks","Brian Ahern"],"m_Companies":["Facebook","Twitter","Google","Ibm","Watson","Reddit","Memorial Sloan-kettering Cancer Center","Wellpoint","Fujifilm","Shell","Pbs","Lifeboat Foundation","Kinematic","Nasa","Spacex","Apple","Intel","Nvidia","Olson","Microsoft","Direct Energy","Amd","Amazon","Verizon","Agi","Cnano Technology","Leap Motion","Rethink Robotics","Cmos","Diesel","Nantero","Pacer","Dell","Cycle","Acer","Comcast","United","Universal"],"m_BiGrams":["interactive care","quantum computer","memorial sloankettering","ibm watson","treatment option","quantum dot","cancer treatment","artificial intelligence","care reviewer","nuclear energy","lifeboat foundation","molecular nanotechnology","solar power"],"m_TriGrams":["interactive care reviewer"],"m_SocialTags":[],"m_Topics":[],"m_Industry":[],"m_Technology":[],"m_BiCnt":[7,7,6,5,5,4,3,3,3,3,3,3,3],"m_TriCnt":[3],"m_iDocBodyWordCnt":2316}
