{"m_szDocID":"499429","m_szDocTitle":"Economics Basics: Introduction | Investopedia","m_szYear":"2016","m_szDocSumamry":"Topics What's New Tesla Reveals First Mass Market Electric Vehicle McDonald's Hits Record High, Expands in China Topics Markets Financial Advisors Trading Tax Center Retirement Personal Finance ETFs & Mutual Funds Election Center Managing Wealth Investing Stock Analysis Reference Dictionary Term Of The Day Velocity Of Money The rate at which money is exchanged from one transaction to another, and how much ... Read More Â» Latest Videos Inside the $3 million Koenigsegg One:1 'Megacar' The 600hp Super-Luxury SUV Guides Stock Basics Economics Basics Options Basics Exam Prep Series 7 Exam CFA Level","m_szDocBody":"topic tesla reveal mass market electric vehicle mcdonald hit record high expand china topic market financial advisor trading tax centre retirement personal finance etf mutual fund election centre managing wealth investing stock analysis reference dictionary term day velocity money rate money exchanged transaction another read latest videos inside million koenigsegg one megacar superluxury suv guide stock basic economic basic option basic exam prep sery exam cfa level sery exam simulator stock simulator trade starting balance risk trader trade forex market risk free free forex trading simulator newsletter log economic basic share tweet economic basic introduction economic basic economic economic basic production possibility frontier growth opportunity cost trade economic basic supply demand economic basic elasticity economic basic utility economic basic monopoly oligopoly perfect competition economic basic conclusion economic basic introduction reem heakal economic study complicated table chart statistic number but specifically study constitute rational human behaviour endeavour fulfil want individual example face problem limited resource fulfil need result make choice money spend part money rent electricity food rest movy buy pair jean economist interested choice make inquire why instance choose spend money dvd player replacing buy carton cigarette price increased pack underlying essence economic understand individual nation behave response material constraint learn economic factor currency trading read forex walkthrough economic say therefore economic referred dismal science study aspect society adam smith father modern economic famous book inquiry nature wealth nation spawned discipline economic understand nation prospered lagged poverty explored nation allocation resource affect wealth study thing economic make assumption human being aim fulfil selfinterest assume individual rational effort fulfil unlimited need economic therefore social science examine people behaving selfinterest definition set turn twentieth century alfred marshall the principle economic reflect complexity underlying economic thus side study wealth other important side part study man economic basic economic economic basic introduction economic basic economic economic basic production possibility frontier growth opportunity cost trade economic basic supply demand economic basic elasticity economic basic utility economic basic monopoly oligopoly perfect competition economic basic conclusion related tutorial economic federal reserve investopedia staff economic macroeconomic stephen simpson cfa personal finance microeconomic marc davis retirement inflation investopedia staff related term marginal profit marginal profit profit earned firm individual quantity theory money economic theory propose positive relationship economic cycle natural fluctuation economy period expansion velocity money rate money exchanged transaction narrow moat slight competitive advantage company enjoy competing economic moat competitive advantage company company related faqs example ceteris paribus argument economic ceteris paribus argument applied economic including example money supply rent control read answer economic study human action behaviour economic considered deductive social science sociology human action behaviour inform read answer difference accounting economic discover difference accounting economic comparing contrasting financial discipline accounting read answer economic moat term economic moat coined popularised warren buffett refer business ability maintain competitive advantage read answer comparative advantage comparative advantage economic law demonstrate way protectionism mercantilism time read answer wall street prime rate forecast work learn wall street journal prime interest rate methodology discover trailing financial indicator engage read answer browse topic alfred marshall macroeconomic microeconomic monetary policy sponsored receive latest investopedia new hot definition velocity money rate money exchanged transaction another unit currency share class designation applied type security common stock mutual fund unit company clawback money benefit distributed back result special circumstance retraction stock capital allocation process businesse divide financial resource source capital processe people sharpe ratio sharpe ratio measure calculating riskadjusted return ratio industry standard helicopter drop hypothetical unconventional tool monetary policy involve printing large sum money distributing trading centre enter symbol dictionary article term videos guide slideshow faqs calculator chart advisor stock analysis stock simulator fxtrader exam prep quizzer net worth calculator connect investopedia work investopedia advertise write contact career free newsletter newsletter investopedia llc right reserved term privacy policy","m_szGeo1":"United States","m_szSourceType":"source_general","m_szSrcUrl":"http://www.investopedia.com/university/economics/","m_Places":["Tesla","China","Enter","Us"],"m_People":["Reem Heakal","Adam Smith","Alfred Marshall","Stephen D. Simpson","Marc Davis","Warren Buffett"],"m_Companies":["Mcdonald's","Election Center","Elasticity","The Federal Reserve","Investopedia Staff","Theory Of Money","Cycle","Narrow","Wall Street Journal"],"m_BiGrams":["economic basic","read answer","basic economic","velocity money","money rate","rate money","money exchanged","exchanged transaction","basic introduction","competitive advantage","economic moat"],"m_TriGrams":["velocity money rate","economic basic introduction"],"m_SocialTags":[],"m_Topics":[],"m_Industry":[],"m_Technology":[],"m_BiCnt":[17,6,4,3,3,3,3,3,3,3,3],"m_TriCnt":[3,3],"m_iDocBodyWordCnt":620}
