{"m_szDocID":"499446","m_szDocTitle":"Topics | Investopedia","m_szYear":"2016","m_szDocSumamry":"Topics What's New Tesla Reveals First Mass Market Electric Vehicle McDonald's Hits Record High, Expands in China Topics Markets Financial Advisors Trading Tax Center Retirement Personal Finance ETFs & Mutual Funds Election Center Managing Wealth Investing Stock Analysis Reference Dictionary Term Of The Day Velocity Of Money The rate at which money is exchanged from one transaction to another, and how much ... Read More Â» Latest Videos Inside the $3 million Koenigsegg One:1 'Megacar' The 600hp Super-Luxury SUV Guides Stock Basics Economics Basics Options Basics Exam Prep Series 7 Exam CFA Level","m_szDocBody":"topic tesla reveal mass market electric vehicle mcdonald hit record high expand china topic market financial advisor trading tax centre retirement personal finance etf mutual fund election centre managing wealth investing stock analysis reference dictionary term day velocity money rate money exchanged transaction another read latest videos inside million koenigsegg one megacar superluxury suv guide stock basic economic basic option basic exam prep sery exam cfa level sery exam simulator stock simulator trade starting balance risk trader trade forex market risk free free forex trading simulator newsletter log topic market retirement managing wealth personal finance financial advisor investing trading etf mutual fund stock analysis faqs topic investing tesla reveal mass market electric vehicle tesla yesterday unveiled world massmarket electric vehicle succeed investing mcdonald hit record high expand china china mcdonald secondlargest market plan open location country past investing today employment report change anything economy added job month taking total job added investing yellen global china federal reserve continue shift focus offshore event addressing monetary policy investing top corporate contributor clinton campaign finance world support hillary clinton managing wealth comparing wealth management service easy privilege checking private banking bank bad financial adviser good financial adviser improve life way bad financial dodge cox investment manager highlight dodbx learn dodge cox large employeeowned asset wealth money market rate finding account helpful rate calculator quickly show highest interest money market rate finding account helpful rate calculator quickly show highest interest online banking app safest cyber attack frequent sophisticated time step financial advisor conscious capitalism hippy anymore dichotomy dogooder profitseeker end proponent black millennial closing wealth gap african american millennial setting future children grandchildren reverse mortgage client reverse mortgage legitimate vehicle folk age tap liquid alt deliver volatile market liquid alternative fund etf delivered volatile stock market tax tip rmd big balance large balance way reduce taxe required minimum boomer top tip shoring retirement retirement situation baby boomer encouraging personal finance black millennial closing wealth gap african american millennial setting future children grandchildren succeed how tax tip rmd big balance large balance way reduce taxe required minimum distribution pension social security differ pension social security provide income stream retiree differ widely structured boomer top tip shoring retirement retirement situation baby boomer encouraging action shore decent income indecent risk struggling derive decent income indecent risk investment chart trading sector etf avoid xlf xle knowing avoid important knowing buy sector stock turnaround potential sny antm beaten stock showing sign turnaround case metal mining fund waking long slumber spdr s&p metal mining etf long downtrend finally coming end delta air line break delta air line inc move substantially higher amex airline index clear energy stock ready short sale diamond offshore drilling helmerich payne set test downtrend low stock strong performer wft swn stock strong tendency rise april stat investing warren buffett biography warren buffett top investor world learn amazing investing learn investing future fundamental future solid understanding them tutorial greatest investor read achievement mastered art investing stock analysis buy uwti option luck time option velocityshare long crude oil etn discover tesla reveal mass market electric vehicle tsla tesla yesterday unveiled world massmarket electric vehicle vwinx vanguard wellesley income fund portfolio trend evaluate composition vanguard wellesley income fund composition equity market trend slx spy learn equity market trend impacting stock price chartadvisor spy dia weekly technical summary major indexe mcdonald hit record high expand china mcd china mcdonald secondlargest market plan open retirement reverse mortgage client reverse mortgage legitimate vehicle folk age tap tax tip rmd big balance large balance way reduce taxe required minimum pension social security differ pension social security provide income stream retiree boomer top tip shoring retirement retirement situation baby boomer encouraging cisco stock trade exdividend csco cisco system send dividend payment shareholder record decent income indecent risk struggling derive decent income indecent risk investment receive latest investopedia new hot definition velocity money rate money exchanged transaction another unit currency share class designation applied type security common stock mutual fund unit company clawback money benefit distributed back result special circumstance retraction stock capital allocation process businesse divide financial resource source capital processe people sharpe ratio sharpe ratio measure calculating riskadjusted return ratio industry standard helicopter drop hypothetical unconventional tool monetary policy involve printing large sum money distributing trading centre partner link enter symbol dictionary article term videos guide slideshow faqs calculator chart advisor stock analysis stock simulator fxtrader exam prep quizzer net worth calculator connect investopedia work investopedia advertise write contact career free newsletter newsletter investopedia llc right reserved term privacy policy","m_szGeo1":"United States","m_szSourceType":"source_general","m_szSrcUrl":"http://www.investopedia.com/topics/","m_Places":["Tesla","China","U.s.","Best","Boomers","Enter","Us"],"m_People":["Hillary Rodham Clinton","Are Strong","Warren Buffett"],"m_Companies":["Mcdonald's","Election Center","Dodge & Cox","Gap","Social Security","Delta Air Lines","Delta Air Lines Inc.","Helmerich & Payne","Vanguard","Wellesley Income Fund","Dia","Cisco","Cisco Systems"],"m_BiGrams":["electric vehicle","stock analysis","reverse mortgage","pension social","social security","decent income","income indecent","indecent risk","tesla reveal","reveal mass","mass market","market electric","mcdonald hit","hit record","record high","high expand","expand china","financial advisor","personal finance","mutual fund","managing wealth","tax tip","tip rmd","rmd big","big balance","balance large","large balance","balance way","way reduce","reduce taxe","taxe required","required minimum","boomer top","top tip","tip shoring","shoring retirement","situation baby","baby boomer","boomer encouraging"],"m_TriGrams":["pension social security","decent income indecent","income indecent risk","tesla reveal mass","reveal mass market","mass market electric","market electric vehicle","mcdonald hit record","hit record high","record high expand","high expand china","tax tip rmd","tip rmd big","rmd big balance","big balance large","way reduce taxe","reduce taxe required","taxe required minimum","boomer top tip","top tip shoring","tip shoring retirement","situation baby boomer","baby boomer encouraging"],"m_SocialTags":[],"m_Topics":[],"m_Industry":[],"m_Technology":[],"m_BiCnt":[5,4,4,4,4,4,4,4,3,3,3,3,3,3,3,3,3,3,3,3,3,3,3,3,3,3,3,3,3,3,3,3,3,3,3,3,3,3,3],"m_TriCnt":[4,4,4,3,3,3,3,3,3,3,3,3,3,3,3,3,3,3,3,3,3,3,3],"m_iDocBodyWordCnt":746}
