{"m_szDocID":"499873","m_szDocTitle":"AutoGuide.Com News - Mercedes-Benz Forum","m_szYear":"2016","m_szDocSumamry":"Google search VB search Search Home Forums Mercedes-Benz News & Polls Mercedes-Benz News Mercedes-Benz Polls Mercedes CLA forum Mercedes GLE Forum Premium Members Only Forum Wide Open Throttle General Mercedes-Benz Forums General Mercedes-Benz Vintage Mercedes-Benz Recommended Repair Shops MB Safety & Testimonials Mercedes-Benz Motorsports & Racing Events For Sale/Wanted/Trade/Giveaway Off-Topic AutoGuide.Com News Mercedes-Benz Technical Forums Audio & Telematics Forum Wheels Detailing and Car Care The Discount Tire Direct Tire, Wheel, Brake & Suspension Mercedes-Benz AMG Forums General AMG Me","m_szDocBody":"home forum mercedesbenz new poll mercedesbenz new mercedesbenz poll mercede cla forum mercede gle forum premium member forum wide open throttle general mercedesbenz forum general mercedesbenz vintage mercedesbenz recommended repair shop safety testimonial mercedesbenz motorsport racing event offtopic autoguidecom new mercedesbenz technical forum audio telematic forum wheel detailing car care discount tyre direct tyre wheel brake suspension mercedesbenz amg forum general amg mercedesamg forum amg amg amg amg amg amg amg amg amg amg amg mercedesbenz sedan forum maybach aclass aclass aclass bclass bclass class cclass cclass cclass cclass ecedcdtdte class ecedtd class eclass eclass eclass sel class ssesecselsdsdl class sclass sclass sclass sclass mercedesbenz forum claclass eclass coupe cabriolet clkclass clkclass clclass clclass clsclass clsclass mercedesbenz roadster forum class slclass slkclass slkclass slkclass slclass slclass mercedesmclaren slr mercedesbenz sls amg mercedesbenz mclass mclass mclass gleclass gle coupe forum gclass glclass glsclass glkclass glcclass glaclass vclass vclass smart unimog rclass sprinter supporting vendor free car history report arnott inc caridcom discount tyre direct extreme dimension european auto part ecs tuning top hydraulic inc mboempartscom pelican part benzworld support forum benzworld issue forum benzworld test active topic today post gallery garage insurance remember community link member list tagging statistic forum show thread show post advanced page mercedesbenz forum general mercedesbenz forum autoguidecom new post thread thread forum autoguidecom new forum tool forum rating topic post reverse sort order reply view here reserve tesla model autoguidecom post autoguidecom minute ago reserve tesla model now waiting youll car reservation made reserve tesla model today autoguidecom post nissan take cargo van drifting fool autoguidecom post autoguidecom hour ago nissan day show world cargo van nissan started con fooling formula nissan day today autoguidecom post daily diecast lime lamborghini countach flashback autoguidecom post autoguidecom hour ago youre generation kid remember gorgeous specimen rage growing post daily diecast lime lam youre generation kid today autoguidecom post gallery tesla model live photos autoguidecom post autoguidecom hour ago tesla town design reminiscent stablemate model fresh well notic tesla town today autoguidecom post video craig cole blooper supercut autoguidecom post autoguidecom hour ago required watching craig cole craig cole video post video craig cole blooper supercut appeared autogui required watching craig cole today autoguidecom post hyundai delay apple carplay integration sonata autoguidecom post autoguidecom hour ago apple carplay integration hyundai sonata sedan delayed again post hyundai delay apple carplay integration apple carplay integration today autoguidecom post tesla model preorder top autoguidecom post autoguidecom hour ago far people reservation tesla model post tesla model preorder top appeared autog far people today autoguidecom post place car put tissue box autoguidecom post autoguidecom hour ago automaker give tonne attention cupholder car place put tissue boxe really tissue important automaker give tonne attention today autoguidecom post tesla model preorder top autoguidecom post autoguidecom hour ago far people reservation tesla model car unveiled concept form special event far people today autoguidecom post tesla model spec autoguidecom post autoguidecom hour ago tesla model revealed know post tesla model spec appeared fir tesla model today autoguidecom post gallery tesla model official photos autoguidecom post autoguidecom hour ago tesla model finally unveiled live hype post gallery tesla model official photos appeared tesla model finally yesterday autoguidecom post tesla made billion hour autoguidecom post autoguidecom hour ago people preordered tesla model hour post tesla made billion hour appeared people preordered yesterday autoguidecom post fact unveiled tesla model autoguidecom post autoguidecom hour ago tesla model made debut special event final production model post fact unveiled abou tesla model made debut yesterday autoguidecom post honda driving shoe inspired civic autoguidecom post autoguidecom hour ago honda driving shoe match brand honda civic post honda driving shoe inspired civic app honda driving yesterday autoguidecom post ford announce safety recall north america autoguidecom post autoguidecom hour ago ford announced separate recall affecting vehicle lineup post ford announce safety recall north america app ford announced separate yesterday autoguidecom post tesla model buyer eligible tax credit autoguidecom post autoguidecom hour ago tesla model buyer advantage federal tax credit electric vehicle post tesla model buyer tesla model buyer yesterday autoguidecom post toyota sienna highlander onboard vacuum cleaner autoguidecom post autoguidecom hour ago toyota sienna highlander model onboard vacuum post toyota sienna highlander onboard vacuum cleaner appeared toyota sienna highlander model yesterday autoguidecom post porsche catches fire dub section york auto show autoguidecom post autoguidecom hour ago porsche caught fire setting dub section york auto show post porsche catches fire dub section porsche caught fire setting yesterday autoguidecom post ford octane academy driving school returning autoguidecom post autoguidecom hour ago ford shopper forward return ford octane academy driving school post ford octane academy driving school returning ford shopper forward yesterday autoguidecom post toyota prius named iih top safety pick autoguidecom post autoguidecom hour ago toyota prius named top safety pick insurance institute highway safety iih highest accolade toyota prius named yesterday autoguidecom post cadillac plotting bentleyfighting suv autoguidecom post autoguidecom hour ago cadillac planning model cost post cadillac plotting bentleyfighting suv appeared cadillac planning model yesterday autoguidecom post watch tesla model live debut autoguidecom post autoguidecom hour ago tesla unveil model sedan tonight watch reveal live tesla ceo elon musk tesla unveil yesterday autoguidecom post daily diecast drifting easier bmw autoguidecom post autoguidecom day ago concept inspiration bmw spyder concept post daily diecast drifting easier concept inspiration yesterday autoguidecom post roborace teaser video kind terrifying autoguidecom post autoguidecom day ago roborace selfdriving race car revealed creepy teaser video full foreboding music tease motorsport league roborace selfdriving race car yesterday autoguidecom post here buick avista china autoguidecom post autoguidecom day ago buick sold delivered china post here buick avista china appeare buick sold yesterday autoguidecom post top car sale autoguidecom post autoguidecom day ago miss car back post top car sale appeared autoguidecom new more miss car yesterday autoguidecom post watch trailer revamped top gear autoguidecom post autoguidecom day ago official trailer bbc revampedtop gearhas released host brought season oft official trailer yesterday autoguidecom post scene designer porsche mission autoguidecom post autoguidecom day ago video released porsche taking scene designing mission concept video released yesterday autoguidecom post love hate cadillac convertible rendered autoguidecom post autoguidecom day ago move range rover evoque convertible cadillac dropping top post love hate cadillac convertible rendered move range rover evoque yesterday autoguidecom post teslas big model reveal concept production model autoguidecom post autoguidecom day ago tesla model revealed shortly full picture post teslas big model reveal concept tesla model revealed autoguidecom post post thread display option active user showing thread member guest sorted thread post time thread start time number reply number view thread rating sort order ascending descending day day week day week month day month day day year beginning forum tool post thread mark forum read forum parent forum forum show thread show post advanced post post reply view hot thread post post post post hot thread post closed thread thread closed posting rule post thread post reply post attachment edit post code smily img code html code forum rule premium vendor showcase recent discussion attachment post set today tkv coupe sudden demise today valicaddy bumper question today sgtcraig attachment related item for today mbzdoc transmission today abbyd carsoft software today sicelo attachment transmission today bad wtb mercede today dreurocar aux input today stclarke sec fuse box today teutone network link mercede wheel mercedesbenz forum full mercedesbenz forum classic mercedesbenz forum mobile contact advertise mercedesbenz forum archive privacy statement top close video description here read full storey viewing experience update browser chrome term ","m_szGeo1":"","m_szSourceType":"source_general","m_szSrcUrl":"http://www.benzworld.org/forums/autoguide-com-news/","m_Places":["Tesla","Made","Best","North America","New York","Drifting","China","Us","Mark"],"m_People":["Wtb Mercedes-benz","Mercedes-benz Gle","Craig Cole","A Porsche","Elon Musk","Eurocar"],"m_Companies":["Google","Mercedes-benz","Members Only","Vintage","Motorsports","Racing","Discount Tire","Amg","Maybach","Sel","Sec","C107 Sl","Mercedes-benz Sls Amg","Vendors","Arnott Inc.","Rm","Ecs","Pelican Parts Inc","Facebook","Daily Diecast","The Post Daily Diecast","The Post","Hyundai","Apple","The Post Gallery","Honda","Highlander","Iihs","Insurance Institute For Highway Safety","Accolade","Cadillac","Pt","Bmw","Avista","Wish","Bbc","Range Rover Evoque","Img","Vendor Showcase"],"m_BiGrams":["autoguidecom post","post autoguidecom","tesla model","autoguidecom hour","hour ago","yesterday autoguidecom","today autoguidecom","post tesla","mercedesbenz forum","autoguidecom day","ago tesla","craig cole","autoguidecom new","post gallery","post daily","daily diecast","apple carplay","carplay integration","far people","honda driving","post ford","model buyer","toyota sienna","sienna highlander","thread post","general mercedesbenz","forum general","show post","post thread","reserve tesla","model autoguidecom","gallery tesla","model preorder","preorder top","model revealed","driving shoe","post toyota","onboard vacuum","dub section","ford octane","octane academy","academy driving","driving school","toyota prius","prius named"],"m_TriGrams":["yesterday autoguidecom post","today autoguidecom post","post tesla model","hour ago tesla","autoguidecom post tesla","ago tesla model","post daily diecast","apple carplay integration","tesla model buyer","toyota sienna highlander","reserve tesla model","model autoguidecom post","post gallery tesla","gallery tesla model","tesla model preorder","model preorder top","tesla model revealed","honda driving shoe","ford octane academy","octane academy driving","academy driving school","toyota prius named"],"m_SocialTags":[],"m_Topics":[],"m_Industry":[],"m_Technology":[],"m_BiCnt":[60,30,28,21,21,19,10,9,8,8,6,5,4,4,4,4,4,4,4,4,4,4,4,4,4,3,3,3,3,3,3,3,3,3,3,3,3,3,3,3,3,3,3,3,3],"m_TriCnt":[19,10,7,6,5,5,4,4,4,4,3,3,3,3,3,3,3,3,3,3,3,3],"m_iDocBodyWordCnt":1242}
