{"m_szDocID":"501365","m_szDocTitle":"Are There Better Alternatives To The Clean Vehicle Rebate Projects?","m_szYear":"2016","m_szDocSumamry":"textArticle -------------------- Are There Better Alternatives To The Clean Vehicle Rebate Projects? September 26, 2016 by Anand Srinivasan 1 Comment The California state legislature recently approved the allocation of nearly $133 million to continue the Clean Vehicle Rebate Project. This is an initiative that was launched in 2009 to create incentives for the purchase of clean energy vehicles like battery-electric vehicles, plug-in hybrids and fuel-cell electric vehicles. The state has seen a steady growth in the number of car buyers coming under the ambit of this program. In 2012, less than 1","m_szDocBody":"alternative clean vehicle rebate project anand srinivasan comment california state legislature recently approved allocation million continue clean vehicle rebate project initiative launched create incentive purchase clean energy vehicle batteryelectric vehicle plugin hybrid fuelcell electric vehicle state steady growth number car buyer coming ambit programme car offered rebate purchase clean vehicle month today million spent programme till date time rebate programme produce intended result perspective million car light truck sold california around month percentage term car sold term emission gasoline car emit close gramme coe mile battery electric car emit coe argument simple assume car cvrp fuelelectric assuming average car travelled mile year cvrp helped california prevented emission thousand tonne coe car sold year lot emission saved put perspective total amount greenhouse emission california million metric tonne coe clean vehicle rebate programme helped prevent emission state healthy start however obvious electric vehicle sale driven rebate programme major chunk clean energy vehicle owned income individual purchasing decision influenced rebate cvrp open individual annual earning priceconscious buyer electric vehicle lucrative cvr programme electric vehicle cost roughly half gasoline car lot economical long run word electric vehicle greater acceptance car buyer rebate matter creating awareness stronger service network million investment car sale happened rebate programme wasteful expenditure avenue make vehicle cleaner electric vehicle estimated half car sold lot vehicle carbon emission hour identify way make car run gasoline cleaner funding research cleaner exhaust removal system number attempt creating emission capturing philtre recent year however fell lack sufficient interest gain traction government build partnership create incentive businesse provide exhaust removal service dealership invest deploy cleaner exhaust philtre customer vehicle successful implementation system potentially bring vehicular coe emission half longer creating cleaner vehicle let math here million car sold california million gasoline powered average coe emission gramme mile average mile year emission million tonne coe philtre brought emission percent coe emission prevented time achieved cvrp average price philtre million expense cvrp funded deployment philtre million car roughly percent number car sold california year coming soon latest comment mark heslep trumpism brexit geopolitical exceptionalism sink planet imagine wrongly care misguided target failed expensive outcome september nathan wilson future personal mobility vision part carfree lifestyle admit uscentric bias travelled overseas city ive don september bentvel economic moral bankruptcy energy policy strike price hinkley pound inflation corrected inflation september mark heslep trumpism brexit geopolitical exceptionalism sink planet decade prohibitive expensive ate solution today problem september advisory panel scott edward anderson consultant blogger media commentator blog green sceptic christine hertzog consultant author professional explainer focused smart grid elias hinckley strategic advisor energy finance energy policy investor energy company government gary hunt gary executiveinresidence deloitte investment extensive experience energy utility industry jesse jenkin graduate student researcher mit expertise energy technology policy innovation jim pierobon help trade government agency company communicate cleaner energy solution geoffrey style managing director gsw strategy group llc awardwinning blogger featured contributor ","m_szGeo1":"United Kingdom","m_szSourceType":"source_industry","m_szSrcUrl":"http://www.theenergycollective.com/anand-smartdata/2388586/are-there-better-alternatives-to-the-clean-vehicle-rebate-projects?utm_source=feedburner&utm_medium=feed&utm_campaign=The+Energy+Collective+%28all+posts%29","m_Places":["California","United States","Uk","Hinkley","Gary"],"m_People":["Anand Srinivasan","Mark Heslep","Will Trumpism","Nathan Wilson","Scott Edward","Christine Hertzog","Elias Hinckley","Hunt Gary","Jesse Jenkins","Jim Pierobon","Geoffrey Styles"],"m_Companies":["Indeed","Deloitte","Strategy Group, Llc"],"m_BiGrams":["electric vehicle","car sold","clean vehicle","rebate programme","vehicle rebate","million car","sold california","tonne coe","coe emission"],"m_TriGrams":["clean vehicle rebate"],"m_SocialTags":[],"m_Topics":[],"m_Industry":[],"m_Technology":[],"m_BiCnt":[6,5,4,4,3,3,3,3,3],"m_TriCnt":[3],"m_iDocBodyWordCnt":474}
