{"m_szDocID":"501375","m_szDocTitle":"Addicted to Oil: U.S. Gasoline Consumption is Higher than Ever","m_szYear":"2014","m_szDocSumamry":"textArticle -------------------- Addicted to Oil: U.S. Gasoline Consumption is Higher than Ever September 27, 2016 by Lucas Davis Leave a Comment August was the biggest month ever for U.S. gasoline consumption. Americans used a staggering 9.7 million barrels per day . That’s more than a gallon per day for every U.S. man, woman and child. The new peak comes as a surprise to many. In 2012, energy expert Daniel Yergin said , “The U.S. has already reached what we can call`peak demand.” Many others agreed . The U.S. Department of Energy forecast in 2012 that U.S. gasoline consumption would steadily","m_szDocBody":"addicted oil gasoline consumption higher lucas davis leave comment biggest month gasoline consumption american staggering million barrel day gallon day man woman child peak surprise many energy expert daniel yergin reached callpeak demand agreed department energy forecast gasoline consumption steadily decline foreseeable future source constructed lucas davis berkeley eia data motor gasoline week average make sense time gasoline consumption declined year row and million barrel day peak president obama announced aggressive fuel economy standard push average vehicle fuel economy mile gallon fast forward gasoline consumption increased steadily year row peak dramatic reversal important consequence petroleum market environment economy here number factor including great recession spike gasoline price end decade repeated time soon surprise income increasing low gasoline price american back buying big car driving mile before gas cheap american back car truck bysa great recession slowdown gasoline consumption occurred worst global recession world war national bureau economic research date great recession beginning beginning slowdown gasoline consumption economy remained anaemic unemployment percent gasoline consumption started increase again economist shown dozen study robust positive relationship income gasoline consumption people spend gasoline usage great recession american traded vehicle fuelefficient model drove fewer mile now income increasing again american buying bigger car truck bigger engine driving total mile gasoline price important explanation gasoline price half gasoline price increased sharply hard remember now gasoline price peaked summer gallon driven crude oil price topped gasoline price washington top gallon price shortlived gasoline price nonetheless remained steep falling sharply indeed price contributed decrease gasoline consumption demand curve all slope down economist shown american sensitive gasoline price strong negative relationship price gasoline consumption moreover gasoline price plummeted month american buying gasoline crazy year biggest year vehicle sale truck suvs leading charge summer american road record number average retail price gasoline gallon lowest labour day price year american driving more fuel economy standard turn tide hard make prediction still retrospect clear year great recession highly unusual decade gasoline consumption driven rising income appear back path illustrate deep challenge reducing fossil fuel transportation electricity generation contrast considerably greener period enormous decline coal consumption reducing gasoline consumption harder however substitute electric vehicle biofuel expensive necessarily carbonintensive example electric vehicle increase carbon emission state coalfired electricity american buying fuelefficient vehicle fuel economy standard turn tide perhap footprint based rule yielding smaller fuel economy gain expected rule fuel economy target vehicle depend size footprint american purchased truck suvs large vehicle relaxe stringency standard yes fuel economy improved mechanism also automaker pushing back hard arguing low gasoline price make standard hard meet lawmaker raised similar concern epas comment window standard midterm review end sept idea standard moving forward happen fuel economy standard fatal flaw fundamentally limit effectiveness increase fuel economy dont increase cost mile driving american drive trillion mile mile wouldnt gas cheap conversation related post logged post comment logged post comment energy collective column coming soon latest comment mark heslep trumpism brexit geopolitical exceptionalism sink planet imagine wrongly care misguided target failed expensive outcome september nathan wilson future personal mobility vision part carfree lifestyle admit uscentric bias travelled overseas city ive don september bentvel economic moral bankruptcy energy policy strike price hinkley pound inflation corrected inflation september mark heslep trumpism brexit geopolitical exceptionalism sink planet decade prohibitive expensive ate solution today problem september advisory panel scott edward anderson consultant blogger media commentator blog green sceptic christine hertzog consultant author professional explainer focused smart grid elias hinckley strategic advisor energy finance energy policy investor energy company government gary hunt gary executiveinresidence deloitte investment extensive experience energy utility industry jesse jenkin graduate student researcher mit expertise energy technology policy innovation jim pierobon help trade government agency company communicate cleaner energy solution geoffrey style managing director gsw strategy group llc awardwinning blogger featured contributor ","m_szGeo1":"United Kingdom","m_szSourceType":"source_industry","m_szSrcUrl":"http://www.theenergycollective.com/lucasdavis/2389311/addicted-to-oil-u-s-gasoline-consumption-is-higher-than-ever?utm_source=feedburner&utm_medium=feed&utm_campaign=The+Energy+Collective+%28all+posts%29","m_Places":["United States","Washington D.c.","Uk","Hinkley","Gary"],"m_People":["Lucas Davis","Daniel Yergin","Barack Obama","Mark Heslep","Will Trumpism","Nathan Wilson","Scott Edward","Christine Hertzog","Elias Hinckley","Hunt Gary","Jesse Jenkins","Jim Pierobon","Geoffrey Styles"],"m_Companies":["Uc Berkeley","National Bureau Of Economic Research","Indeed","Path","Target","Epa","Deloitte","Strategy Group, Llc"],"m_BiGrams":["gasoline consumption","gasoline price","fuel economy","great recession","economy standard","american buying"],"m_TriGrams":["fuel economy standard"],"m_SocialTags":[],"m_Topics":[],"m_Industry":[],"m_Technology":[],"m_BiCnt":[13,11,9,5,4,3],"m_TriCnt":[4],"m_iDocBodyWordCnt":618}
