{"m_szDocID":"502666","m_szDocTitle":"IT News Online - Features","m_szYear":"2016","m_szDocSumamry":"Date Jan Feb Mar April May June July Aug Sept Oct Nov Dec 1 2 3 4 5 6 7 8 9 10 11 12 13 14 15 16 17 18 19 20 21 22 23 24 25 26 27 28 29 30 31 2010 2011 2012 2013 2014 2015 2016 Search News Select Entire Story Company Archive Crawler Jan Feb Mar April May June July Aug Sept Oct Nov Dec Select India Asia Middle East Australasia Europe N America S America Africa Select Finance Personnel Hardware Software Gaming Internet Telecom General Features India Asia Middle East Australasia Europe N.America S.America Africa Home PR Newswire Business Wire India RealWire Finance Personnel Hardware Software Gam","m_szDocBody":"date sept new select entire storey company archive crawler sept select india asia middle east australasia europe america america africa select finance personnel hardware software gaming internet telecom general feature india asia middle east australasia europe namerica samerica africa home newswire business wire india realwire finance personnel hardware software gaming internet telecom general feature globe newswire bizwire express tech trivia free industry resource press release newswire cyber defence demand governmentindustry cooperation newswire scanning market analysis market estimated hit billion research market newswire telepresence robot device market million anticipated reach billion report research market newswire research market level teardown cost analysis parrot bebop drone newswire press release globe newswire eharmony announce launch elevated career eharmony firstever compatibilityfocused recruiting platform globe newswire sterling named crn tech elite list globe newswire compuware newest mainframe visualisation solution uniquely enable customer meet crossplatform devop pressure globe newswire compuware correlog give enterprise security compliance team vital applicationlevel mainframe insight globe newswire more more press release realwire accorhotel arena select avaya technology stateoftheart technology performance realwire spectromax commit paying living wage defined living wage foundation realwire computacenter achieve place whitelane european outsourcing survey realwire contactform launches integration captainform plugin wordpress user registration realwire press release business wire india lycos deal yahoo extend year business wire india ntt communication launches sap hana menu enterprise cloud business wire india panasonic awarded gold rating ecovadis sustainability survey business wire india lighting digitally connected display railway station india business wire india more more press release prcom consulting web named web marketing annual webaward competition prcom security survey show company size maturity level crucial security readiness prcom future electronic promote mallory mss sery medical alarm prcom mind mapping application adobe image editing tool prcom press release japan corporate new nec appoint apac ceo chart growth region jcn newswire gemalto verification protect private enterprise growing threat fraud acn newswire nec selected telenor network modernization sweden norway jcn newswire sheen tai enter cloud distribution information market prc acn newswire more more major league secret weapon training aeon sport major league baseball team setting virtual reality batting cage hitter hone swing unprecedented accuracy wearing pitcher worrying spring downpour videogame boy stereotype nachoeating sodasipping smelly teenage boy parent basement exist reason were time videogame inception penetration mainstream consciousness west wepod driverless car play traffic system automated electric vehicle wepod made history selfdriving shuttle public road vehicle world steering wheel licence plate technology training open door life stemsel foundation programme teach young people microchip application computer programming helping underprivileged children india pathway life smb security challenge protection constantly evolving threat landscape misconception cyberattack target big businesse thrown bin smb susceptible cyberattack enterprise fact large percentage businesse hit data breach category escan threat prediction end welcoming remembered year data breach witnessed data leak ashley madison morgan chase future mobile wallet pradeep sampath coo mmp mobiwallet payment system tata teleservice anticipate player develop integrated mobile wallet app usage heavy online offline marketing top collaboration trend today customer greater freedom flexibility choice collaboration need open environment replaced traditional meeting room hot desk shared space war game virtual computing advancing troop training advance gpupowered virtualization nvidia grid equipment instruction training battlefield combat delivered soldier location cloud confine boot camp zombie data draining life byte byte fan horror genre entertainment important aware zomby undead data attacked technology world too nvidia ceo kick predicting acceleration sweep supercomputing supercomputing swept rapidly edge science heart everyday live propelling forward bringing mobile phone pocket car driveway gpu acceleration weathering perfect mobile storm people assumption mobile industry booming outside however closely reality nuanced reliable sandbox gateway appliance past year spear phishing attack highly targeted message primary attack vector successful data breaches percent attack enterprise network result spear phishing method swiss tap gpus improve national weather forecast swiss federal office meteorology climatology meteoswiss major national weather service deploy gpuaccelerated supercomputer improve daily weather forecast mobile security threat trend ahead gartner security risk management summit dionisio zumerle research director gartner shared insight mobile security enterprise landscape including key threat trend ericsson acquire envivio million ericsson announced acquire envivio provider softwarebased video encoding solution mean tender offer price share cash million aggregate changing face learning english language learning tremendous evolutionary shift advent technology tool device empower promote learning individual level beer gpus gpus deep learning brewer improve sud jason cohen man solution problem bottom beer glass yearold entrepreneur found open letter microsoft ceo roll back clock choice control satya writing disturbing aspect window specifically update experience appear designed throw choice customer made internet experience want pursuing transformative technology impact challenge disability laura palmaro year old woke morning central vision left eye disappeared ill genetic issue completely blue importance skillbased training securing job brilliant student stupendous knowledge subject studied sufficient land dream job dynamically changing time today whatsapp scam pay attention success whatsapp downfall instant messaging service reached million active user summer number fraud emerging app growing steadily benefit diversity ethic workplace workplace spend half life home some argue before workplace focal point live revolve fact workplace family security trend dominate witnessed number highprofile threat bug heartbleed shellshock cryptolocker causing alarm disruption developer system administrator online security expert victory net neutrality finish line today heard won stunning victory fight protect net neutrality fcc put forward draught proposal strong enforceable net neutrality rule based classifying broadband communication service reason smb taking cloud computing cloud good shared computing service application platform internet granted small medium sized businesse unprecedented technology sophistication eus action misguided politically motivated professor innovation strategic information management michael wade topranked imd business school europe targeting irresponsible politically motivated cost benefit cloud telephony platform single biggest motivating factor business transformation businesse rapidly taking cloud technology big hope garnering cost advantage offer surely missing point they sure cloud mean capex upfront great reason ivr cloud cloud brought wave disruptive technology shore expect ivr buck trend hosted ivr cloud ivr ivr cloud big business communication mobility travel hospitality industry travel hospitality industry dramatic past year technological completely changed travel space consumer interact book travel earlier telecom supplier answer data dilemma cloud sdn nfv attending mobile world congress tbr believe telecom industry rapidly changing adopting core capability virtualization sdn respond increased network efficiency expect mobile world congress ovum expect mwc focus solution aimed driving mobile operator service revenue hype surrounding transformational capability lte reverberate exhibition hall sense reality riverbed technology technology trend draw close time step back understand exciting trend hold technology space riverbed technology performance company outlined technology trend nokias collapse continue window phone fail secure footing market nokias flagship lumia window phone smartphone continue battered tepid interest user overshadowed device mobile juggernaut apple samsung parallel nokias revenue profit withering apple samsung compromise emerge dispute drag decision london court ordering apple inc publicly correct impression samsung electronic copying apple ipad stand stark contrast ruling court true mobility trend future mobile computer rugged radical shift people work computer increasing availability affordability wireless broadband giving global workforce true mobility time history payperdrink mobile left bet bottom dollar trend prediction included hot tip mobility cloudbased computer software service application behaviour learning personal touch work stop favourite coffee shop barista recognise ask the usual answer yes note feel nice recognised morning coffee prepared nokia running time continued trouble facing nokia highlighted announcement yesterday device service operating margin negative additional restructuring charge ipv embrace change moment transition filled anxiety concern unknown reluctance move familiar however transition necessarily migration ","m_szGeo1":"","m_szSourceType":"source_general","m_szSrcUrl":"http://www.itnewsonline.com/Features/","m_Places":["India","Asia","Middle East","Europe","N America","S America","Africa","N.america","S.america","Hana","Japan","Sweden","Norway","China","Protection","Mobile","Gateway","Mobile Security","Brewers","Take","London","United States"],"m_People":["Accorhotels Arena","Ashley Madison","Pradeep Sampath","Dionisio Zumerle","Jason Cohen","Laura Palmaro"],"m_Companies":["Pr Newswire","Business Wire","Newswire","Parrot","Compuware","Avaya Technology","Yahoo","Ntt Communications","Sap","Cloud Business Wire","Panasonic","India Business Wire","Best Consulting","Marketing Association","Shows Company","Mallory","Adobe","Nec","Telenor","Ip Network","Major Leagues","Eon","Major League Baseball","Stemsel Foundation","Landscape","Target","Jp Morgan","Chase & Co.","Nvidia","Ericsson","Microsoft","Google","Eu","Capex","Congress","Riverbed Technology","Nokia","Apple","Samsung","Apple Inc.","Samsung Electronics"],"m_BiGrams":["business wire","wire india","globe newswire","press release","research market","net neutrality"],"m_TriGrams":["business wire india"],"m_SocialTags":[],"m_Topics":[],"m_Industry":[],"m_Technology":[],"m_BiCnt":[],"m_TriCnt":[],"m_iDocBodyWordCnt":1220}
