{"m_szDocID":"518917","m_szDocTitle":"New Tech and the Future of Clean Energy | The Energy Collective","m_szYear":"2014","m_szDocSumamry":"3 Posted March 14, 2014 Keywords: Energy Security , Tech , Communications and Messaging , Sustainability , Utilities , Efficiency , Environmental Policy , Cleantech , Public Health , Finance , Renewables , Risk Management , Energy and Economy , Fuels , Politics & Legislation , energy industry change , future technology Technology is the main driver for change – i.e. optimization, which leads to finding promising technological solutions for pressing global challenges – and for increased productivity in the modern world. However, for mankind to continue along this trajectory, appropriate investm","m_szDocBody":"posted keyword energy security tech communication messaging sustainability utility efficiency environmental policy cleantech public health finance renewable risk management energy economy fuel politic legislation energy industry change future technology technology main driver change optimization lead finding promising technological solution pressing global challenge increased productivity modern world however mankind continue trajectory investment dependent public understanding awareness promising technology potential application order put promising technological breakthrough public radar world economic forum publishes list top emerging technology annually key trend technological change identified latest world economic forum global agenda council emerging technology report technological breakthrough relevant energy realm gridscale electricity storage nanowire lithiumion battery general modern electric power company face challenge integrate intermittent renewable power source sun wind existing power grid originally designed base load fossilfuel power source nuclear time vast supply electricity produced peak sun hour met comparatively demand consume sudden spike electricity supply power supplier face problem finding buyer excess electricity but importantly elevate risk overwhelming power grid designed traditional premise predictable flexible base load fossilfuel power generation anyrenewable energy integration traditional grid complicatessupply demand balance constitute transformation decentralizedpower generation system picture spread individual solar pvbased electricity producer called distributed generation feeding excess power grid simultaneously relying grid time insufficient solar electricity generation source wholesale solar chart illustrate situation namely integration mean transformation main finding ieas report titled power transformation wind sun economic flexible power system published source iea viewing renewable forced remaining system adaptation entire electricity system perceived reoptimized promising gridscale electricity storage technology play world economic forum describe technology intellectual premise follow the development gridscale electricity storage option long holy grail clean energy system date pumped storage hydropower significant role expensive environmentally challenging totally dependent favourable geography sign range technology closer cracking challenge some flow battery may future store liquid chemical energy large quantity analogous storage coal gas solid battery option competing store electricity sufficiently energydense cheaply material newly invented graphene supercapacitor offer possibility extremely rapid charging discharging ten thousand cycle option kinetic potential energy large flywheel underground storage compressed air option explored medium scale germany comethanation hydrogen electrolysis surplus electricity split water hydrogen oxygen hydrogen reacted waste carbon dioxide form methane combustion necessary generate electricity rate technological advancement field world economic forum expect fundamental breakthrough term stressing storage potential economic future succeed producing scalable economically viable energy storage solution gain breaking energy new analysis thought leadership reference material discussion day important energy market trend breaking energy participant stay ahead breaking new participate highprofile event enjoy central hub industry community transform response fastmoving energy politic regulation deal financial challenge lead technological advance robert bernal say feal real game changer developed technological level decade ago put renewable energy scheme and coal expensive nuclear plant cheaper expensive diffuse intermittent source coupled storage make baseload option time educate public necessity developing meltdown proof reactor global level needed replace coal substantually reduce excess pollution charge electric car massive reduction excess pollution make clean liguid fuel for electrified most importantly provide power completely developed that happy billion person planetary civilization impossible diffise intermittant nature wind solar cost material input level material needed almost completely replace fossil fuel therefore know renewable energy activity indirect prolonger fossil fuel solar wind kill people indirectlybecause take nuclear development stop building coal plant intrinsically speaking advanced closed cycle meltdown proof nuclear cheaper coal nobody that ","m_szGeo1":"","m_szSourceType":"source_industry","m_szSrcUrl":"http://www.theenergycollective.com/jared-anderson/353321/technology-emerging-2014-potential-reshape-energy-space","m_Places":["Germany"],"m_People":["Wind, Sun","Robert Bernal"],"m_Companies":["Cleantech","World Economic Forum","Iea"],"m_BiGrams":["world economic","economic forum","gridscale electricity","electricity storage","power grid"],"m_TriGrams":["world economic forum","gridscale electricity storage"],"m_SocialTags":[],"m_Topics":[],"m_Industry":[],"m_Technology":[],"m_BiCnt":[4,4,3,3,3],"m_TriCnt":[4,3],"m_iDocBodyWordCnt":546}
