{"m_szDocID":"522850","m_szDocTitle":"News:PESN:Archive:2005 - PESWiki","m_szYear":"2005","m_szDocSumamry":"PESWiki.com -- Pure Energy Systems Wiki:  Finding and Facilitating the Best Exotic Free Energy Technologies      News:PESN:Archive:2005 From PESWiki Jump to: navigation, search 2005 archive of http://pesn.com news articles posted here at at PESWiki.com. Contents 1 PESN 2005 1.1 December, 2005 1.2 November, 2005 1.3 October, 2005 1.4 September, 2005 1.5 August, 2005 1.6 July, 2005 1.7 June, 2005 2 See also PESN 2005 December, 2005 Francoeur Installs Fuel Vaporizer on GMC CrewCab - System uses 200-degree engine coolant to vaporize the lighter chemicals out of the gasoline into an isolated chambe","m_szDocBody":"peswikicom pure energy system wiki finding facilitating exotic free energy technology newspesnarchive peswiki jump navigation archive new article posted peswikicom content pesn december november october september august july june pesn december francoeur instal fuel vaporizer gmc crewcab system degree engine coolant vaporise lighter chemical gasoline isolated chamber system inventor working crack heavier part gasoline pesn dec investigation energy anomaly magnetic circuit derek gerlach replicate refute harold aspden experiment aspden claimed produced anomaly science producing energy input pesn dec pes network osen split calling potential merger wishing well pesn dec venturing point bearden credit courage researcher haisch puthoff shown pushing zeropoint academically huge risk them career income pesn dec magenn power floating wind generator nearing deployment inflatable rotating balloon wind turbine design scheduled market readiness price close grid power pesn dec spinning power waste energy louis michaud atmosphere vortex engine tamedtornado anchoredvortex concept offer vast increase electrical output waste heat existing power plant small prototype promising pesn dec manmade cyclone clearing smog reader cite mainstream press coverage manmade cyclone reported evidence weather modification capability generally acknowledged pesn dec maxing earth buffer breaking point earth extremely resilient limit take buffering capacity saturated catastrophic ecosystem breakdown result beginning rapid now indicating edge buffer pesn dec november ihs preparing aftermarket hydrogen supplement device vehicle innovative hydrogen solution inc canada developing electrolysis unit extract hydrogen oxygen water inject air intake vehicle increase fuel economy pesn nov bowie line play nikola tesla prestige singer david bowie talk return film acting thriller competing turnofthecentury magician pesn nov hydrogen embrittlement substantial threat hydrogenconversion expert cleanfuel specialist tai robinson respond assertion hydrogen gas dissolve structure metal aluminium steel cracking failure metal component pesn nov defence contractor reticent antigravity discovery fabled top secret world war technology fully developed nazis individual allegedly killed process testing apparently replicated part mainstream californian defence contractor sara showing antigravity propulsion effect pesn nov tmas vertical axis wind turbine introduce competitive advantage design create pull back side contributing wind conversion efficiency kill bird run quietly installed high blend landscape generating cost estimated cent kilowatthour surpassing conventional energy source pesn nov focus fusion pose overwhelming competition tokamak purport feasible profoundly expensive approach hot fusion contrast international project iter france pursuing lawrenceville plasma physic researching developing plasma focus device hydrogenboron nuclear fusion pesn nov october tankless water heater brutal grid popularised tankless water heater draw energy demand thermal energy storage aspect multiplied customer hotwater usage pattern surge energy amount significantly higher peak load utility resulting increased cost and significantly increased waste nonpeak time pesn oct wilma super storm energy vacuum reflection dynamic recordbreaking hurricane principle physic atmosphere ramification unlimited energy vacuum space pesn oct skybuilt aim dell renewable energy system unique power grid deploy quickly rugged long time skybuilt call cia benefit pesn oct krystal planet alluring mainstream consumer market renewable energy energy star partner independent dealer selling wind solar biodiesel hydrogen fuel cell system encourage join make money save money clean planet pesn oct design improve turbulence combustion chamber somender singh radical design change face combustion chamber forming groove channel passage squish areas enhance incylinder turbulence multi flame front combustion contained patent doityourselfer cutting groove approach effect pesn oct stirling energy system sign contract stirling engine design company signed contract major utility california newest contract option grid competitive pesn oct darpa grand challenge real energy saving stanford win robotic vehicle competition start race autonomous ground vehicle automobile paul noel ponder competition featured clean energy technology advancement pesn oct offshore bobbing device harnessing wave energy manchester bobber patented wave energy device passed phase january testing scale working model phase involve testing scale device pesn oct findsolarcom launches launched intent preeminent online resource linking consumer solar professional solar energy system installer solar pros listed pesn oct secured solar power plant international automated system instal phase solar power plant barstow california claim solarheatturbine system competitive fossilbased power biomass application turbine progressing pesn oct september solar cell phone charger sale jeweller produce design cell phone hold charge day however heat battery longevity pesn sept new energy movement post website nonprofit organisation aim foster awareness activity mainstream conference held year presently feature essay prominent individual field energy pesn sept unfeasibility rebuilding orlean river moving city city sinking weight upbuilding muck decade cut fresh water sliding cliff the continental shelf oil gas industry extracting oil city intent purpose sea domain spend money developing alternative energy solution instead pesn sept rita headed houston key remaining refinery biggest remaining part oil refinery offshore shore recovery oil gas bull eye usa capacity ship supply pesn sept hurricane stronger number category hurricane worldwide doubled past year total number hurricane dropped shift occurred global sea surface temperature increased period pesn sept katrina wood waste create biomass opportunity green energy resource offering pay government release wood landfill burned ger harvested destruction weather event general power energy need pesn sept heard tilley carl tilley show pontiac bonneville call tilley electric vehicle sale year general motor heard tilley pesn sept tilley claim endlesslycharged allelectric vehicle ready sale carl tilley announce concept car bell whistle speed luxury combined ultra efficiency stage ongoing fraud stemming back decade pesn sept oildependence predict famine food production depend fertiliser derived natural gas natural sourced mineral valid alternative strong political action reclaim lost right save geneticallyunmodified seed pesn sept update hurricane katrinas damage gulf oil patch repercussion ominous hurricane impact gulf oil infrastructure remedy discussed including emergency spending alternative energy technology pesn sept lutec demo video allege unity video show watt rectified spinning device producing watt efficiency pesn sept biologist invent powergenerating backpack suspendedload backpack convert mechanical energy walking electricity watt energy power portable electronic device soldier field researcher disaster reliefworker pesn sept gulf oil disruption government ineptitude report gulf oil production disruption transportation woe situation brink government botching turn pesn sept weather modification longestablished secretive reality legislation designed foster pleasant productive weather planned tool weaponized weather control tested amateur hostile weathermaker alike lose technology military pesn sept gulf oil disruption cripple world economy damage gulf oil gas infrastructure tremendous gas short supply region hampering restorative effort snowball effect aorta commerce felt worldwide long overdue time alternative oil pesn sept august purdue announce hydrogen water organic material purdue researcher developed technique producing hydrogen water require water catalyst based metal rhenium reeneeum organic liquid called organosilane stored transported easily pesn aug pantone extension conversation hall geet inventor paul pantone oct nov establish competency argument interesting chat hall running car water pesn aug pantone bail geet inventor paul pantone released night preparing defence court morning tell criminality justice system pesn aug gouging peak oil oil company posting huge profit taking advantage perception scarcity hubert peak theory hype existence renewable magma oil pesn aug feedback magma oil adequate supply reason magma oil considered sufficient counteract peak oil phenomenon paul pantone incarcerated famous inventor geet mileage improvement system alleged method run car water brought custody aug charge security fraud violation protective order pesn aug downside power grid internet editorial cite concern interference eavesdropping pesn aug late grey nephew resurrect famed free energy motor grey motor marketready prototype replication nikola teslas radiant energy phenomenon made market reason nephew paranoia secrecy greed invention grave pesn aug million teragrid award herald era scientific computing interoperable cyberinfrastructure accessible entire science engineering community energy research field benefit turbocharged nextgeneration internet pesn aug urinepowered battery singapore physicist create paper battery generate electricity urine technology ideal match cheap disposable healthcare testkit pesn aug capital energy inventor dept agriculture aug deadline late piece million pot complexity application round come time prepare pesn aug world largest solar installation stirling engine technology year purchase agreement southern california edison stirling energy system inc result dish array covering acre capable generating solar project combined pesn aug dry rinse cycle washing machine save dryer energy cost team researcher florida developed method dry clothes percent spin cycle reducing surface tension water small portion detergent fabric softener pesn aug trouble removing oil water researcher centre water waste technology water research laboratory university south wale developed patented highperformance passive separator industrial civil engineering application pesn aug son late magnet motor inventor attest device authenticity thirtythree year lee bowman passing son speak attest witnessed device operation tell lingering family scar investor litigation pesn aug green mountain energy company ecoquest international team bring clean affordable electricity mainstream large sale force combined green energy programme offer nonpolluting electricity customer price comparable paying producing electricity pesn aug iaus push solar competitive range grid power thermal solar panel coming production produce electricity cent kilowatthour highlyefficient bladeless turbine wide range wasteheatharnessing application methanol production technique draw environment reversing global warming pesn aug july solar challenge race conclude calgary michigan take prize finishing mile hour fourteen twenty entrant completed race cross finish line kansas state hour winner pesn suspect arrested murder cold fusion champion joseph reilly arrested murder eugene mallove internationally renowned champion cold fusion alternative energy technology pesn cool light hot day fibre optic bring sun indoor piping sunlight electricity winwin proposition ecosystem human society home business customer anticipate energy saving pleasant indoor environment pesn nature aether william alek set property aether research capable absorbing emitting heat perfect insulator term resistance limit propagation light pesn extracting energy vacuum drop ocean tom bearden correspondence pastor purport current energy system tap vacuum deliberately inefficient manner disturb equilibrium nature zpe energy vacuum teslas wheelwork nature pesn wastetoenergy plant approved chi minh city vietnam pyrolysis technology handle reuse city municipal solid waste sewage treatment plant sludge waste hazardous waste operate profit north american facility planned aspiring lightning wrangler information todd livingstone plan rope power lightning phone interview recording explain set breakwater tame strike aec reveal hydrogen production demonstration unit alternate energy corporation demonstration unit produce hydrogen water demand production arrangement made shipment price projected comparable fossil fuel pesn researcher make advance wind energy generation engineer university alberta created wind energy generator hope people day power home pesn sonofusion bubbling mainstream recent media fawning purdue bench top fusion result leslie pastor point sonofusion research energy alternative overlooked similar controversy edison time pesn climate summit emphasise profitability green mayor meet learn problem climate change armed solution implement local level government pesn fear irrationality oil patch profittaking stock price rise fall fear unfounded oil shortage real fact hard philosophical argument rage pesn blamo power lightning demonstrated smaller prototype artificial lightning todd livingstone waiting lightning storm test fullscale prototype harnessing energy lightning strike technology reverse directed energy weaponspesn adopt global energy independence day county los angele california adopted global energy independence day held annually birth date nikola tesla pesn japanese firm develop world robot powered fuel cell humanoid robot powered easytoreplace environmentally friendly fuelcell battery sell centimetre inch tall kilogramme pound robot carry builtin hydrogen cylinder pesn june lutec gmcc bedini bearden technology common sterling allan wonder key varying electromagnetic technology include permanent magnet transiently flip polarity confronted properly pulsed coil opening gate kind yettobe defined energy june naudin claim extract free energy moller atomic hydrogen generator mahg experimenter claim derive free energy cleanly safely dissociation hydrogen atom data posted test plan schematic method listed openly encourage replication improvement result based decadesold concept set nobel laureate june holy grail evade lutec progress report australian company claimed year commercially ready free energy device june magnetic power inc nearing preproduction stage point energy module module built offtheshelf component expected generate electricity anywhere time cent kilowatthour module expected market year pesn shocking experience walking highpower line umbrella discovered umbrella tine act antenna turning umbrella holder mini transformer moist weather accentuate effect pesn konarka solaris nanoscience create joint research programme solaris nanoscale metallic structure boost solar energy conversion efficiency konarkas portable power plastic pesn pesn archive footer newspesnarchive newspesnarchivejanuaryfebruary marchapril mayjune julyaugust newspesnarchivejanuaryfebruary marchapril mayjune julyaugust septemberoctober novemberdecember newspesnarchivejanuaryfebruary marchapril mayjune julyaugust septemberoctober novemberdecember newspesnarchivejanuaryfebruary marchapril mayjune julyaugust septemberoctober novemberdecember newspesnarchive newspesnarchive newspesnarchive newspesnarchive newspesnarchive newspesnarchive newspesnarchive new footer free energy new peswiki daily world feature storey pes network inc latest leave lesser storey blogindex week free energy digest new topic active exotic cold fusion conspiracy earth magnetic field energy electromagnetic fuel efficiency hydroxy hho keshe plasma ecat spirituality water water fuel trickle alchemy alternative fuel battery electric vehicle emergency preparedness engine event fundraiser geothermal gravity motor grid humour hydro hydrogen magnet motor nanotech open source qmogen quantum solar storage tesla thermal electric top waste energy wind point energy peswiki new archive index newsappropriate slogan mainstream new peswiki main retrieved category new archive view discussion source history personal tool log create account searching option translate navigation home introduction donate today new pesn peswiki latest free energy feature top sale exotic exotic conventional sponsored link event teslatech sponsor phi science item sale making biodiesel make electricity recondition battery namecheapcom department open source tech directory tree aether alt fuel antigravity battery betavoltaic bioelectricity biofuel biodiesel biomass body electric brown gas cold fusion conservation electrolysis electromagnetic electrostatic fuel cell fuel efficiency electric vehicle engine hydroxy fusion geothermal gravity motor home generation human powered hydro hydrogen joe cell lighting magnet motor nanotechnology nuclear nucl remediation oil piezoelectric plasma plastic river salt water mix solar solid state gen storage tesla turbine thermal electric tidal vortex waste energy water water fuel wave ocean wind wireless electricty point energy powerpedia betavoltaic cold fusion nikola tesla conspiracy suppression buyer beware movy humour job review videos store sponsored link support special page popular stat recent category revision advertise contact toolbox link related upload file special page sponsored link map added pure energy system pes network inc when step ahead crowd genius step ahead crackpot rabbi shlomo riskin feb modified accessed time gnu free documentation licence peswiki disclaimer","m_szGeo1":"United States","m_szSourceType":"source_industry","m_szSrcUrl":"http://peswiki.com/index.php/News:PESN:Archive:2005","m_Places":["Best","Osen","Split","Bearden","Reader","Maxing","Canada","Singer","Gravity","France","Lawrenceville","Heaters","U.s.","Us","California","Manchester","Uk","New Orleans","Houston","Usa","Gulf","Hall","Singapore","Southern California","Son","Calgary","Michigan","Tesla","Ho Chi Minh City","Vietnam","Most","Los Angeles, California"],"m_People":["Derek Gerlach","Harold Aspden","Louis Michaud","David Bowie","Tai Robinson","Somender Singh","Paul Noel","Katrina Wood","Tilley - Carl Tilley","Carl Tilley","Geet","Lee Bowman","Champion - Joseph P. Reilly","Eugene F. Mallove","Tom Bearden","Todd Livingstone","Leslie R. Pastor","Sterling Allan","J.l. Naudin","Joe Cells","Shlomo"],"m_Companies":["Anomaly","Venturing","Buffering","Buffer","Iter","Dell","Cia","Combustion Chambers","Darpa","Continental","Bull","Eu","General Motors","Gulf Oil","Pantone","Magma","Dept. Of Agriculture","Dish","U. Of Florida","University Of New South Wales","Green Mountain Energy Company","Energy Corporation","University Of Alberta","Bearden Technologies","Magnetic Power Inc.","Solaris","Brown's","Plastic"],"m_BiGrams":["pesn aug","pesn sept","pesn oct","free energy","pesn dec","energy system","pesn nov","gulf oil","cold fusion","energy technology","energy vacuum","newspesnarchivejanuaryfebruary marchapril","marchapril mayjune","mayjune julyaugust","pes network","waste energy","power plant","nikola tesla","effect pesn","cent kilowatthour","fuel cell","oil gas","alternative energy","electric vehicle","hydrogen water","paul pantone","magma oil","magnet motor","point energy","julyaugust septemberoctober","septemberoctober novemberdecember","sponsored link"],"m_TriGrams":["newspesnarchivejanuaryfebruary marchapril mayjune","marchapril mayjune julyaugust","mayjune julyaugust septemberoctober","julyaugust septemberoctober novemberdecember"],"m_SocialTags":[],"m_Topics":[],"m_Industry":[],"m_Technology":[],"m_BiCnt":[16,15,10,8,8,7,6,6,5,4,4,4,4,4,3,3,3,3,3,3,3,3,3,3,3,3,3,3,3,3,3,3],"m_TriCnt":[4,4,3,3],"m_iDocBodyWordCnt":2242}
