{"m_szDocID":"522830","m_szDocTitle":"Directory:Free energy - PESWiki","m_szYear":"2015","m_szDocSumamry":"PESWiki.com -- Pure Energy Systems Wiki:  Finding and facilitating breakthrough clean energy technologies.      Directory:Free energy From PESWiki Jump to: navigation, search Contents 1 TV Series 2 Overviews 3 Videos 4 Websites 4.1 PES Network Inc. 4.2 General 4.3 Discussion groups and Usenet 4.4 Skeptics and anticrank 4.5 FE News 5 Books 6 Interviews 7 Commentary 8 Stories 9 Humor 10 Directories 11 See also See also: PowerPedia:Free energy Most of the thousands of pages on this site have to do with free energy technologies of one kind or another, whether it be conventional such as solar, wind","m_szDocBody":"peswikicom pure energy system wiki finding facilitating breakthrough clean energy technology directoryfree energy peswiki jump navigation content sery overview videos website pes network inc general discussion group usenet sceptic anticrank new book interview commentary storey humour directory also powerpediafree energy thousand page free energy technology kind another conventional solar wind geothermal tide exotic technology overunity electromagnetic system cold fusion magnet motor point energy purpose free energy defined energy obtained source free charge nondepleting list site investigator researcher achieve goal freedom user source dependent limited resource operate utilisation device purpose study device operate work adapt need design specification precondition this distribute anew copy specification neighbour reengineer specification release improvement public community benefit design specification precondition this sery featured exotic media exotic free energy technology free energy documentary producer pitches sery chris toussaint planning sery challenge fossilfuel paradigm first however people spread word show kickstart funding kickstartercom place join make happen peswiki comment overview featured free energy twentyfirst century technology road reindustrialization ground artificial intelligence expert explain lag scientific discovery explanation specify promising technology note including brown gas hydroxy rossis cold fusion turtur point energy avisos selfrunning electric car pesn trend free energy waste energy pollution ramification free energy cheap fossil fuel enabled rapid expansion human life resource run out free energy prolong reverse negative trend thought put long term trend mitigate negative impact cold fusion now videos featured free energy videos homepagefeatured free energy music video elevate luminary aishah set viral excellent music video released decry energy suppression sequestering free energy patent national security praise tesla point energy research etc encourage humanitarian similar supporting free energy emergence pesn beforeitsnew free energy videos freeenergytv live ready good folk start posting favourite free energy clip easy add favourite clip login post url short description clip front date order upload neverbeforeseen clip freeenergytruth featured free energy videos free energy world ready change craig freeenergytruth produced great minute teaser video free energy movement envisioning world exotic free energy technology emerged oil war massive desalination programme water harvesting air cheap irrigation transport food blackout evolution human consciousness peswiki free energy conspiracy suppression alex jone free energy video increasingly popular talk show host real free energy solution provide individual energy independence suppressed nominal solution solar wind supported compete status quo upcoming documentary film interactive website premiered alex jone site address issue youtube thealexjoneschannel aug featured videos free energy machine die for quest free energy onehour discoveryquality documentary addresse technology defy law physic film feature eric krieg nec sceptic investigate technology meet asyetunclaimed free energy challenge peswiki dec website pes network inc pes network inc general web site free energy image image free energy image jeanlouis naudin jln lab quest overunity tom bearden tom bearden website cheniereorg rex research jean usa bill beaty free energy device amascicom seattle educateyourself freedom knowledge power thought freeenergycc clear tech rod networking service patrick bailey padrak personal assistance development research acquired knowledge german zero point energy open source energy network las vegas nevada usa keelynetcom chapala jalisco mexico infinite energy energy foundation inc bimonthly magazine nuenergyorg rumney hampshire usa eagleresearch inc orocille black light powercom cranbury david waggoner fuelless powercom albany future horizonsnet marquette michigan advanced scientific inquiry palm harbour energy machine joseph newman joseph newman company free energycouk bessler wheel orffyreus wheel steorn dockland innovation park east wall road dublin ireland technology develop efficient micro generator free energy open source movement sery sery article steve windisch examine free energy device explain working simplified way discussing proposed theory them interview inventor researcher working open source energy movement today peswiki discussion group usenet realtime chat ircicqcom network #freeenergy channel xchat recommended platform group newsgroup free energy group freeenergy free energy claim yahoo inc altenergyrenewable fueling depleting everything activity usenet altenergyhomepower home power offgrid living medium activity usenet altsciphysicsnewtheory scientific theory journal science technology medium activity usenet scienergy discussion energy science technology science technology activity usenet scienvironment discussion environment ecology activity usenet altenergy alternative energy low activity usenet altenergyoverunity overunity energy discussion low activity usenet altenergyhighvoltage hivoltage discussion low activity usenet sceptic anticrank philadelphia critical thinking eric history perpetual motion free energy machine free energy archive new newssource new new new free energy new daily free energy new pure energy system new pesn team reporting alternative energy development zpenergy energy future altenergy todaycom delivering today new solar energy wind energy fuel cell alternative fuel hybrid technology book directorybook featured review breakthrough power book masse book round understanding gamechanging energy technology pass family friend excited possibility inspire involved helping remove barrier stood coming forward peswiki nov featured book free energy secret power beneath free energy frank acland novel the secret power beneath involve hidden nation learned harness exotic energy ramification revolutionary energy source obtained exclusive interview author describe book motivation writing pesn beforeitsnew book free energy book understanding nature quest free energy esoteric ebook netherland author johan oldenkamp phd construct free energy machine apply principle harmony the mathematical problem prime number finally solved discovering rhythm sery prime pateonl interview featured free energy movy thrive interview thrive documentary maker foster gamble yesterday sterling allan opportunity conduct hour long interview maker thrive documentary foster gamble conversation topic discussed including free energy issue facing society future path humanity utopia collapse pesn beforeitnew radio sailing knowledge podcast scratching surface free energy device patrick kelly carlita twohour interview patrick generously providing researches free open source downloadable chapter book practical guide free energy device patrick describe depth diversity free energy device available function energy production device capable sailing knowledge commentary featured free energy free energy future motivate exotic energy technology open countless possibility future imagination future based scarcity shortage resource free energy human civilization innovate problem facing humanity bright future motivated continue promoting alternative energy pesn beforeitsnew featured exotic free energy pes network wild wild west free energy innovation criticised wrong technology looked promising past turned bogus fraudulent excellent projected sanitised usually propagandised new service you bleeding edge hazardous place hang out pesn beforeitsnew storey featured free energy ufos reverse engineering emergency preparedness free energy hope doomsday disclosure primary reason national government suppressing ufo sighting downplaying possibility extraterrestrial visitation technology people realise real creative genius liberated replication follow shortly making oppressive government obsolete pesn feb comment free energy tesla searl nicola tesla greedy powerful guilty crime humanity century ago tesla offered free energy planet rebuffed insisted maintain control monetary incentive similar happened john searl sat back rich greedy power time men succeeding ufo digest oct featured free energy exotic haiti haiti opportunity free energy rollout calamity haiti disaster provide opportunity new emerging free energy technology step forward coming rescue matt imber short list technology make debut great heart softened pesn jan comment humour featured humour robot federation await free energy power domination malfunctioning droid floor denver airport divulged infinite power source free plug recharge amass force anywhere continue stopping achieved ultimate objective dominance planet pesn beforeitsnew directory directory powerpedia free energy visual directory free energy website energyplanetinfo practical guide freeenergy device quest free energy dawn industrial revolution today enthusiastic inventor nikola tesla joseph newman made free energy rubegoldberg directory listing latest tree new peswiki home retrieved view discussion source history personal tool log create account searching option translate navigation home nest introduction donate today new pesn twife hcat heat data palladium generator err flux generator symphony secret latest eviva qmogen hcat data anomalous heat peswiki blog corbett blacklight iss commentary sterling presentation tesla tech fisl sponsored link feature top hydrogen mogen ecat lenr blacklight power ymnee qmogen exotic exotic conventional event bedini secret space programme teslatech sponsor phi science serenata flower item sale sun oven scangauge making biodiesel make electricity recondition battery keppe motor department open source tech hcat freddy cell bedini directory tree aether alt fuel antigravity battery betavoltaic bioelectricity biofuel biodiesel biomass body electric brown gas cold fusion conservation electrolysis electromagnetic electrostatic fuel cell fuel efficiency electric vehicle engine hydroxy fusion geothermal gravity motor home generation human powered hydro hydrogen joe cell lighting magnet motor nanotechnology nuclear nucl remediation oil piezoelectric plasma plastic river salt water mix solar solid state gen storage tesla turbine thermal electric tidal vortex waste energy water water fuel wave ocean wind wireless electricty point energy powerpedia betavoltaic cold fusion nikola tesla conspiracy suppression buyer beware movy humour job review videos store sponsored link support special page popular stat recent category revision advertise contact toolbox link related upload file special page sponsored link map added mdt solarlite when step ahead crowd genius step ahead crackpot rabbi shlomo riskin feb modified accessed time gnu free documentation licence peswiki disclaimer","m_szGeo1":"United States","m_szSourceType":"source_industry","m_szSrcUrl":"http://peswiki.com/index.php/Directory:Free_energy","m_Places":["Most","Best","Tesla","Us","Usa","Seattle","Las Vegas, Nevada","Jalisco","Mexico","Rumney, New Hampshire","Cranbury, Nj","Albany, In.","Michigan","Fl","Uk","Docklands","Dublin","Ireland","Home-made","Haiti","Gravity"],"m_People":["Chris Toussaint","Alex Jones","Eric Krieg","Jean-louis Naudin","Tom Bearden","Bill Beaty","Patrick G. Bailey","David Waggoner","Joseph Newman","Steve Windisch","Frank Acland","Johan Oldenkamp","Maker, Foster","Sterling Allan","Patrick Kelly","John Searl","Nicola Tesla","Matt Imber","Eviva Qmogen","Joe Cells","Shlomo"],"m_Companies":["Network Inc.","Usenet","Century Technologies","Brown's","Youtube","Nec","Google","Jean Nv","Cc Clear Tech Inc","Horizons","Publishing Company","Yahoo! Inc.","Philadelphia Association","Solar Energy","Path","Utopia","Energy Future","Palladium","Freddy's","Plastic"],"m_BiGrams":["free energy","activity usenet","energy technology","featured free","cold fusion","point energy","pesn beforeitsnew","energy device","open source","pes network","energy machine","network inc","exotic free","energy videos","quest free","joseph newman","science technology","alternative energy","low activity","sponsored link"],"m_TriGrams":["featured free energy","free energy device","free energy technology","pes network inc","free energy videos","free energy machine","quest free energy","low activity usenet"],"m_SocialTags":[],"m_Topics":[],"m_Industry":[],"m_Technology":[],"m_BiCnt":[62,8,7,7,5,5,5,5,5,4,4,3,3,3,3,3,3,3,3,3],"m_TriCnt":[7,5,4,3,3,3,3,3],"m_iDocBodyWordCnt":1412}
