{"m_szDocID":"522867","m_szDocTitle":"Directory:Non-Conventional Free Energy Technologies - PESWiki","m_szYear":"2015","m_szDocSumamry":"PESWiki.com -- Pure Energy Systems Wiki:  Finding and Facilitating the Best Exotic Free Energy Technologies      Directory:Non-Conventional Free Energy Technologies From PESWiki Jump to: navigation, search FREE ENERGY DIRECTORY PES Network Inc. Directory in association with the Open Source Energy Network This site, http://freeenergynews.com/Directory , contains a directory of Tesla technologies and other advanced devices that move us away from fossil fuels and other planet-depleting energy sources, and toward abundance of 'free energy' that extracts inexhaustible power, such as solar, wind, ge","m_szDocBody":"peswikicom pure energy system wiki finding facilitating exotic free energy technology directorynonconventional free energy technology peswiki jump navigation free energy directory pes network inc directory open source energy network site directory tesla technology advanced device move fossil fuel planetdepleting energy source abundance free energy extract inexhaustible power solar wind geothermal conventional source point energy cold fusion magnet motor peswiki directory directory latest tree new free energy directory saturday communitybuilt free energy directory presented pes network inc this publiclyeditable site directory technology areas move fossil fuel planetdepleting energy source abundance free energy extract inexhaustible power solar wind geothermal conventional source point energy cold fusion magnet motor etc directory listing general categorised navigation listing topic handled encyclopaedic format powerpedia department directory listing magnetic motor example essentially link magnetic motor design company powerpedia listing magnetic motor encyclopaedic treatise theory general concept directory page listed main index page subtopic main areas energy development page specific company example indexed main topic page pertaining company free energy promulgate forward leap human progress akin discovery fire bring dawn civilization based freedom abundance sterling allan energy congress energy congress purpose reviewing promising claim free energy technology order weighted list recommendation technology top exotic free energy technology prioritised listing energy technology closest market criteria including renewable environmentally safe affordable credible reliable developed safe etc main directory listing listed alphabetically acoustic aether air conditioning alternative fuel algae oil biodiesel biodiesel algae biomass butanol clean fuel conversion diesel ethanol cellulosic ethanol hydrogen peroxide liquid nitrogen waste energy water fuel animal powered antigravity flying car atmospheric electrostatic energy pyramid power aether atmospheric pressure difference ball lightning battery betavoltaic capacitor charger flywheel inverter lithium lithium ion lithium sulphur proton polymer reconditioning solid state silver polymer storage utility scale vanadium redox battery bioenergetic strikeheel generation bioelectricity biofuel biofuel source directoryalgae hemp biomass rocket stove blue energy cavitation heater clean coal sequestration cold fusion lenr conservation dark energy earth magnetic field energy electric vehicle car hybrid sery buy hybrid vehicle new electric vehicle scooter solar powered truck electrogravitic electrolysis pressure electrolysis stanley meyer water fuel cell electromagnetic joule ringer linear motion power factor correction rotoverter solid state toroidal power electrostatic engine hydraulic ambient air engine noble gas engine stirling engine steam engine flight floating flywheel fuel efficiency additive acetone air car airship alternative fuel electric freight rail electric vehicle engine directoryfuel preheating mileage improvement hybrid vehicle hydraulic hydrogen injection directoryhydroxy hho injection system hypermiling new fuel effiency plugin hybrid powertrain retrofit device spark plug transmission vehicle fuel cell fusion focus fusion geoengineering geothermal hydrothermal vent new geothermal gravity motor secondary oscillation grand unified theory grid smart grid grey water recycling heat exchanger heat pump ground source heat pump home generation humanpowered pedalpower step action also hydro low impact hydro energy island also ocean river tide water hydrogen hydrogen water hydrogen production hydrogen storage hydrogen vehicle solar hydrogen joe cell kinetic energy device lighting solar lighting lightning magnet motor magnet microorganism energy production microwave energy tech nanotechnology aerogel nuclear directorybetavoltaic cold fusion fusion noble gas engine nuclear remediation thorium reactor ocean mixing sea river water ocean current ocean thermal energy conversion ocean wave wave buoy wave propulsion oil abiotic oil ecological impact oil fuelwatch worldwide geobioreactor microbial enhanced oil recovery microwavebased oil extraction nonfossil oil north american continent oil field petravoltaic piezoelectric plasma plastic energy propulsion quantum radiant rain river mixing sea river water low impact hydro solar application walipini underground greenhouse concentrated solar dye solar cell infrared installation consultation largest solar installation photosynthesis plastic solar cell photovoltaic silicon solar charger solar heating solar hydrogen solar lighting new solar solar paint solar pavement solar r&d solar sail solar thermal solar tower solar vehicle spacebased solar thin film solar solid state solid state generator storage stirling engine thermal electric tankless water heater thermoacoustic thermionic generator tidal time travel vibration videos algae fuel biodiesel geothermal global warming hydrogen pesnetwork wind vortex waste energy animal crop waste energy conservation plasma plastic refinery flaring recovery recycling sewage urine power waste heat generator water brown gas filtration hydrogen water purification running vehicle water water fuel water air water fuel cell weather control wind augmentation floating altitude home generation horizontalaxis new wind offshore past development vertical axis windbelt wind farm point energy tree main conventional exotic free energy genre featured directory conventional exotic free energy genre summary listing serve comprehensive compilation primary genre free energy technology extract energy wheelwork nature potentially way unconventional modality conventional clean energy tech peswiki specialised listing new active exotic cold fusion conspiracy earth magnetic field energy electromagnetic fuel efficiency hydroxy hho keshe plasma ecat spirituality water water fuel trickle alchemy alternative fuel battery electric vehicle emergency preparedness engine event fundraiser geothermal gravity motor grid humour hydro hydrogen magnet motor nanotech open source qmogen quantum solar storage tesla thermal electric top waste energy wind point energy exotic clean energy technology clean energy technology developing world buyer beware resource listing academy book building communication tool community conspiracy conservation directory discussion group diy emergency preparedness essay event financial resource general renewable energy retail outlet geoengineering global warming global warminggovernment politic inventor investment resource impact job legal magazine media movy new newsletter open source project organisation ocean trash vortexe gyre oxygen depletion political action committee prize profile quote radio recycling request proposal report review engine site sceptic spoof supression store tool goverment energy tax break utility vetting videos watchdog weather control zeitgeist latest featured videos pesnetwork videos index videos produced primarily pes network inc freeenergyrelated video resource peswiki dec latest development peswiki listing reverse chronological sequence significant addition peswikicom page computergenerated list page chronologically recent computer generated listing made site recent first peswiki new energy information current event free energy related directory precursor peswiki directory practical guide freeenergy device energy planet interactive visual renewable energy directory visitor preview rate green sustainable website aboutmyplanetcom environmental community alternative energy information free academic journal directory open journal service cover free full text quality controlled scientific scholarly journal covering subject language journal directory directorydirectory sponsor complete mcsa scjp itil exam pass resource website included latest certified ethical hacker testking training course congressspecialist show directory listing topic specialist energy congress directory latest tree new return main peswiki retrieved category directory view discussion source history personal tool log create account searching option translate navigation home introduction donate today new pesn peswiki latest free energy blog feature top sale exotic exotic conventional sponsored link event teslatech sponsor phi science item sale making biodiesel make electricity recondition battery namecheapcom department open source tech directory tree aether alt fuel antigravity battery betavoltaic bioelectricity biofuel biodiesel biomass body electric brown gas cold fusion conservation electrolysis electromagnetic electrostatic fuel cell fuel efficiency electric vehicle engine hydroxy fusion geothermal gravity motor home generation human powered hydro hydrogen joe cell lighting magnet motor nanotechnology nuclear nucl remediation oil piezoelectric plasma plastic river salt water mix solar solid state gen storage tesla turbine thermal electric tidal vortex waste energy water water fuel wave ocean wind wireless electricty point energy powerpedia betavoltaic cold fusion nikola tesla conspiracy suppression buyer beware movy humour job review videos store sponsored link support special page popular stat recent category revision advertise contact toolbox link related upload file special page sponsored link map added pure energy system pes network inc when step ahead crowd genius step ahead crackpot rabbi shlomo riskin feb modified accessed time gnu free documentation licence peswiki disclaimer","m_szGeo1":"United States","m_szSourceType":"source_industry","m_szSrcUrl":"http://peswiki.com/index.php/Directory:Non-Conventional_Free_Energy_Technologies","m_Places":["Best","U.s.","Us","Most","Gravity","Heel","Heaters","Energy Islands","Mixing Sea","Tesla"],"m_People":["Sterling D. Allan","Lithium Ion","Stanley Meyer","Joe Cell","Joe Cells","Shlomo"],"m_Companies":["Network Inc.","Tesla Technologies","Congress","Diesel","Ball","Capacitors","Theories","Plastic","Radiant","Underground","Pavement","Brown's","Axis","Action Committees","U.s. Goverment"],"m_BiGrams":["free energy","energy technology","cold fusion","point energy","magnet motor","waste energy","solid state","electric vehicle","exotic free","energy directory","pes network","network inc","open source","directory listing","fuel cell","magnetic motor","energy congress","alternative fuel","water fuel","fuel efficiency","geothermal gravity","gravity motor","home generation","plasma plastic","thermal electric","clean energy","sponsored link"],"m_TriGrams":["free energy technology","exotic free energy","pes network inc","free energy directory","geothermal gravity motor"],"m_SocialTags":[],"m_Topics":[],"m_Industry":[],"m_Technology":[],"m_BiCnt":[15,8,7,5,5,5,5,5,4,4,4,4,4,4,4,3,3,3,3,3,3,3,3,3,3,3,3],"m_TriCnt":[5,4,4,3,3],"m_iDocBodyWordCnt":1219}
