{"m_szDocID":"522901","m_szDocTitle":"Directory:Funding - PESWiki","m_szYear":"2015","m_szDocSumamry":"PESWiki.com -- Pure Energy Systems Wiki:  Finding and Facilitating the Best Exotic Free Energy Technologies      Directory:Funding From PESWiki Jump to: navigation, search Funding sources and resources. There are an abundant number of financial sources for the support of new energy research. This page is established to provide an index of the same. Task  Move here the contents from http://freeenergynews.com/Directory/Finance/ . Contents 1 Sources 1.1 Types 1.1.1 Crowdfunding 1.1.2 Tax-Free Donations 1.1.3 Open Source 1.1.4 Funds 1.1.5 Gust 1.1.6 Loans 1.1.7 CrytoCurrencies 1.1.8 Waste to Energ","m_szDocBody":"peswikicom pure energy system wiki finding facilitating exotic free energy technology directoryfunding peswiki jump navigation funding source resource abundant number financial source support energy research established provide index same task move content content source type crowdfunding taxfree donation open source fund gust loan crytocurrency waste energy comparison people organisation resource source type crowdfunding directoryfundraiser featured tool funding nest crowdfunding exotic free energy movement nest launching crowdfunding make funding clean energy venture democratic based vote people chip long now citizen make small investment crowdfunding pesn taxfree donation featured financial resource funding organisation north point charity taxfree donation inventor string attached yearold charity north point task receiving taxfree donation support exotic free energy technology project selected charity north point make nostringsattached investment promising technology pesn beforeitsnew open source open source revenue potential open source energy project pes network glad work inventor bring technology forward open source method confident revenue centre tapped make path worth while fund featured financial resource funding stageinnovation million fund seek new big technology stage extreme breakthrough technology big patent awarded filed welldeveloped prototype ready significant funding business expertise wrapped bring market month pesn beforeitsnew featured financial resource funding breakout lab offer grant radical ideas thiel fellowship announced opening breakout lab organisation offer grant individual radical ideas game changing technology application requesting funding development exotic energy technology accepted pesn featured organisation funding fire organisation assist inventor tim kerr director fire organisation help extreme breakthrough clean energy inventor develop technology interview share information organisation turn ideas reality pes beforeitsnew gust global platform startup funding loan funding small loan individual small world business person pay back loan money typically loaned back small business people organisation take small voluntary fee transaction easy due web pleasure participate crytocurrency holding back cryptocurrency bitcoin part mental reservation stem appear removed pyramid scheme balloon bound pop free energy blog waste energy funding waste energy wpp energy corp present waste energy power plant financing provide complete turnkey solution waste energy power plant project world financing government private sector loi bcl wppenergy sept comparison funding compare power generation choice people compare cost generate electricity renewable resource wind solar cost generate electricity coal nuclear natural gas comparing cost comparing apple orange understanding basic factor make informed comparison renewable energy world oct people featured funding rasa funding inventor functioning connect inventor funding funding problem anymore inventor funding contact grain salt suggested information include sterling peswiki feb directoryfinancial resource funding george soros investing billion clean energy hedgefund manager george soros latest billionaire throw money clean technology soros announced yesterday investing billion clean energy technology spending million create climate policy advisory organisation bloomberg oct organisation bill gate dedicate billion finding energy miracle free energy blog norda foundation clean energy award unclaimed year foundation awarded million social entrepreneurial charitable organisation year part mission fund new nonfossil fuel sustainable energy project year energy project recommended applied funding free energy blog featured organisation funding blue sun energy scouting clean energy tech haiti rebuilding company funding clean energy technology ready open exotic technology norm present great opportunity breakthrough modality ready beta test rollout favourite company know pesn mar featured funding investment resource hub lab offer investment capital exotic energy technology hub lab express purpose support early stage revolutionary energy science technology potential make huge gamechanging difference were open cold fusion overunity device vacuum zeropoint energy peswiki secretary chu calling cold fusion inventorsand revolutionary department energy accepting proposal energy r&d project disrupt status quo million programme part energy department emphasis breakthrough technology small thinker apply incremental progress current technology wall street journal cooper company investment bank focuse exclusively financing assistance emerging energy company walker enterprise llc provided list prospective source funding contact nora maccoby additional funding option advanced energy healing technology nora maccobycom usda grant assist developing method manure reduction resource post just edit button top header section log directoryinvestment opportunity finance index freeenergynewscom directoryrequest proposal energy finance footer directoryfinancial resource directoryfree energy economy directoryfunding directoryfundraiser directoryprize directorybarter directoryinvestment resource directoryinvestment opportunity directoryinvestmentstock directoryjob directoryuswhat green save money directoryrequest proposal energy directory listing latest tree new peswiki home retrieved category finance view discussion source history personal tool log create account searching option translate navigation home introduction donate today new pesn peswiki latest free energy blog feature top sale exotic exotic conventional sponsored link event teslatech sponsor phi science item sale making biodiesel make electricity recondition battery namecheapcom department open source tech directory tree aether alt fuel antigravity battery betavoltaic bioelectricity biofuel biodiesel biomass body electric brown gas cold fusion conservation electrolysis electromagnetic electrostatic fuel cell fuel efficiency electric vehicle engine hydroxy fusion geothermal gravity motor home generation human powered hydro hydrogen joe cell lighting magnet motor nanotechnology nuclear nucl remediation oil piezoelectric plasma plastic river salt water mix solar solid state gen storage tesla turbine thermal electric tidal vortex waste energy water water fuel wave ocean wind wireless electricty point energy powerpedia betavoltaic cold fusion nikola tesla conspiracy suppression buyer beware movy humour job review videos store sponsored link support special page popular stat recent category revision advertise contact toolbox link related upload file special page sponsored link map added pure energy system pes network inc when step ahead crowd genius step ahead crackpot rabbi shlomo riskin feb modified accessed time gnu free documentation licence peswiki disclaimer","m_szGeo1":"United States","m_szSourceType":"source_industry","m_szSrcUrl":"http://peswiki.com/index.php/Directory:Funding","m_Places":["Best","Us","Most","Grants","Oranges","Haiti","Hub","Cooper","Gravity","Tesla"],"m_People":["Tim Kerr","George Soros","Bill Gates","Chu","Nora Maccoby","Joe Cells","Shlomo"],"m_Companies":["Path","Wpp Energy Corp","Norda Foundation","Energy Department","Wall Street Journal","Walker Enterprises Llc","Usda","Brown's","Plastic"],"m_BiGrams":["free energy","clean energy","energy technology","open source","waste energy","taxfree donation","resource funding","energy blog","cold fusion","exotic free","featured financial","financial resource","north point","energy project","proposal energy","sponsored link"],"m_TriGrams":["free energy blog","exotic free energy","featured financial resource","financial resource funding"],"m_SocialTags":[],"m_Topics":[],"m_Industry":[],"m_Technology":[],"m_BiCnt":[7,7,6,6,6,4,4,4,4,3,3,3,3,3,3,3],"m_TriCnt":[4,3,3,3],"m_iDocBodyWordCnt":869}
