{"m_szDocID":"522933","m_szDocTitle":"News:Archive:2015:July - PESWiki","m_szYear":"2015","m_szDocSumamry":"PESWiki.com -- Pure Energy Systems Wiki:  Finding and Facilitating the Best Exotic Free Energy Technologies      News:Archive:2015:July From PESWiki Jump to: navigation, search PESWiki News -- July, 2015 Archive Click here for most recent news. 2015 August News:Archive:2015:August July Friday, July 31, 2015 Featured: Hydrogen > Production > SHT > SHT's former CEO, Konstantine Balakirian, a Soviet disinformation expert - When he was fired, Konstantine confessed that he had been one of the best disinformation experts. He's the one who put forth the misleading explanation last year that the copio","m_szDocBody":"peswikicom pure energy system wiki finding facilitating exotic free energy technology newsarchivejuly peswiki jump navigation peswiki new july archive recent new newsarchiveaugust friday featured hydrogen production sht sht ceo konstantine balakirian soviet disinformation expert fired konstantine confessed disinformation expert put misleading explanation year copious hydrogen production coming transmutation oxygen hydrogen chemical portion accounted pesn thursday motorbike litre water freeenergyblog wednesday featured electromagnetic qmogen daniel hick green line energy qmogen system include set battery power motor run hydraulic system power kva generator required recharge battery leaving net rotating set time step build megawatt plant peswiki sunday featured top hydrogen production sht constantine balakirian longer sht reaction primarily chemical reason fired clarification solar hydrogen trend sht reactor driven primarily aluminium reacting water produce hydrogen oxide film forming surface allowing continuous production transmutation detected metal aluminium precipitant pesn saturday featured hydrogen production sht consulting consulting produce aluminium water oxide coat buildup constantine balakirian announce process enable continuous reaction aluminium water produce hydrogen oxide film forming surface prevent continued reaction electrical input part process input driver pesn thursday featured top sale buoyancy rosch sale kpp kinetic power plant rosch innovation affordable power production price renewable utility plant system capable continuous capacity output include backup month build time depending order volume partytested german tuv patented pct guaranteed entertaining regional licence selling plant pes store featured humour law physic declare bumble bee fraud wing small enable fly there kind trickery involved hartmann overunitycom maybe hidden string sky michael adolph aeon decry scientific blasphemy dansie note inventor bee long history making false claim pesn wednesday featured solar grid government power company objective remedy unintended subsidy solar customer residential customer residential solar customer netmetering pay electricity grid regular residential customer end picking infrastructure cost subsidy remedy low facility charge netmetering customer pesn tuesday featured buoyancy rosch kpp gaia gaia plan continuous delivery power plant local licensee rosch provide key component generator air compressor control circuit gaia source local manufacturer rest component make home power system pushing delay gaia expect delivery week pesn monday featured tesla coil entertainment skyfireart tesla coil rock crowd vegas eye candy tesla electricity nerd all performed electric daisy carnival edc las vegas north americas largest electronic music festival tesla coil guy made lightning dance fingertip staff back precision pureenergyblog gds technology model promote product free energy blog sunday qeg overunity free webinar est free energy blog saturday featured conspiracy solution infowar military order okay fully informed jury cheque power cheque takeover military treason above proactive military measure fight domestic enemy pesn friday featured plasma keshe repentance keshes world view knowledgeseekerss workshop keshe made shunning publicly confessed weakness have notwithstanding effort healing response pesn thursday steve spisak qmogen watt produce free energy blog wednesday featured energybat lab sterling visit geoffrey miller key gsm tube core solid iron geoff discovered hollow slit iron steel core coil effective inducing current gsm tube core material weigh less work lot better peswiki tuesday featured plasma keshe keshe magravpower home car generator alleged keshe foundation website list generator technology sale euros give technical information including kilowatt produce video presentation live announcement bit chaotic interesting pesn staged isis execution video mccain office leaked hacker free energy blog sunday featured electromagnetic qeg qeg achieve selflooping energy left fix world organisation reached phase milestone achieved out stopping additional open source instruction focus coming commercial design detail provided selflooped system press release pesn thursday featured electromagnetic energybat lab sterling visit full video sterling visit geoffrey miller energybat lab feature include magnet motor rotating magnet large wheel generator infinity generator cold electricity generator bedini system wire thin hair gds technology analogue prototyping john searl rpm demo tesla turbine coil leedskalnin holder survey peswiki gerard morin lab plan free energy blog tuesday featured electromagnetic energybat lab maastricht netherland energy lab inspired geoffrey miller energybat lab bertoaus similar south netherland the enthusiasm geoffrey friend catching miss interested people space experiment field energy batlab webcam coming peswiki featured electromagnetic energybat lab sterling visit wattless generator geoffrey miller comprised disc embedded neodymium magnet situated alternating orientation disc disc situated geoff gsm tube core coil anticipated peswiki monday featured electromagnetic energybat lab sterling visit ecklin generator variant geoffrey miller ecklin generator outer horizontal slat rotate coil with geoffrey resistanceless gsm tube core creating break flux path stationary magnet middle portion generator pass horizontal slat generating electrical current coil pesn saturday featured new free energy digest rosch energybat free energy digest featuring rosch kpp energybat lab report rosch plant demo report energybat array technology technology team ceo sht pct patent platinuminvest inviting core licencing wardenclyffe reproduction project okke pektir qmogen sunvault graphene generator freeenergynew gravitylamp crowdfunder free energy blog friday live solar impulse aeroplane flight nagoya hawaii rtw attempt free energy blog thursday featured energybat lab sterling visit geoffrey miller key gsm tube core solid iron geoff discovered hollow slit iron steel core coil effective inducing current gsm tube core material weigh less work lot better peswiki keshe foundation live broadcast free energy blog newsarchivejune backward time new footer free energy new peswiki daily world feature storey pes network inc latest leave lesser storey blogindex week free energy digest new topic active exotic cold fusion conspiracy earth magnetic field energy electromagnetic fuel efficiency hydroxy hho keshe plasma ecat spirituality water water fuel trickle alchemy alternative fuel battery electric vehicle emergency preparedness engine event fundraiser geothermal gravity motor grid humour hydro hydrogen magnet motor nanotech open source qmogen quantum solar storage tesla thermal electric top waste energy wind point energy peswiki new archive index newsappropriate slogan mainstream new peswiki main retrieved category new archive view discussion source history personal tool log create account searching option translate navigation home introduction donate today new pesn peswiki latest free energy blog feature top sale exotic exotic conventional sponsored link event teslatech sponsor phi science item sale making biodiesel make electricity recondition battery namecheapcom department open source tech directory tree aether alt fuel antigravity battery betavoltaic bioelectricity biofuel biodiesel biomass body electric brown gas cold fusion conservation electrolysis electromagnetic electrostatic fuel cell fuel efficiency electric vehicle engine hydroxy fusion geothermal gravity motor home generation human powered hydro hydrogen joe cell lighting magnet motor nanotechnology nuclear nucl remediation oil piezoelectric plasma plastic river salt water mix solar solid state gen storage tesla turbine thermal electric tidal vortex waste energy water water fuel wave ocean wind wireless electricty point energy powerpedia betavoltaic cold fusion nikola tesla conspiracy suppression buyer beware movy humour job review videos store sponsored link support special page popular stat recent category revision advertise contact toolbox link related upload file special page sponsored link map added pure energy system pes network inc when step ahead crowd genius step ahead crackpot rabbi shlomo riskin feb modified accessed time gnu free documentation licence peswiki disclaimer","m_szGeo1":"United States","m_szSourceType":"source_industry","m_szSrcUrl":"http://peswiki.com/index.php/News:Archive:2015:July","m_Places":["Best","Most","Tesla","Us","Las Vegas","North America","Est","Holder","Maastricht","Netherlands","Nagoya","Hawaii","Gravity"],"m_People":["Konstantine Balakirian","Daniel Hicks","Michael Adolph","Daisy Carnival","M.t. Keshe","Steve Spisak","Geoffrey S. Miller's","John Searl","Gerard Morin","Geoffrey S. Miller","Joe Cells","Shlomo"],"m_Companies":["Kinetic","Innovations","Power Companies","Gaia","Core Uses","Keshe Foundation","Isis","World Organization","Path","Crowdfunder","Brown's","Plastic"],"m_BiGrams":["free energy","energy blog","energybat lab","featured electromagnetic","sterling visit","geoffrey miller","gsm tube","tube core","lab sterling","hydrogen production","pesn thursday","electromagnetic energybat","production sht","wednesday featured","saturday featured","thursday featured","tuesday featured","tesla coil","visit geoffrey","core coil","open source","magnet motor","energy digest","cold fusion","sponsored link"],"m_TriGrams":["free energy blog","gsm tube core","energybat lab sterling","lab sterling visit","featured electromagnetic energybat","electromagnetic energybat lab","hydrogen production sht","sterling visit geoffrey","visit geoffrey miller","free energy digest"],"m_SocialTags":[],"m_Topics":[],"m_Industry":[],"m_Technology":[],"m_BiCnt":[14,9,9,6,6,6,6,6,5,4,4,4,3,3,3,3,3,3,3,3,3,3,3,3,3],"m_TriCnt":[9,6,5,5,4,4,3,3,3,3],"m_iDocBodyWordCnt":1117}
