{"m_szDocID":"523294","m_szDocTitle":"Directory:Principle Power, Inc. - PESWiki","m_szYear":"2015","m_szDocSumamry":"PESWiki.com -- Pure Energy Systems Wiki:  Finding and Facilitating the Best Exotic Free Energy Technologies      Directory:Principle Power, Inc. From PESWiki Jump to: navigation, search WindFloat Provides Renewable Spinnoff Application from Oil Platform Tech Renewable energy company, Principle Energy Inc., is presently focused on two areas: a floating platform for offshore wind, wave, and current harnessing; and an inflatable concentrated solar technology developed by Cool Earth Solar. WindFloat, conceived by Marine Innovation & Technology and exclusivly licensed by Principle Power, is a float","m_szDocBody":"peswikicom pure energy system wiki finding facilitating exotic free energy technology directoryprinciple power inc peswiki jump navigation windfloat renewable spinnoff application oil platform tech renewable energy company principle energy inc presently focused areas floating platform offshore wind wave current harnessing inflatable concentrated solar technology developed cool earth solar windfloat conceived marine innovation technology exclusivly licenced principle power floating foundation offshore wind turbine simple elegant patented design innovative feature windfloat dampen wave turbine motion enabling wind turbine sited previously inaccessible location superior wind resource multiple project proposal submitted pilot utilityscale development windfloat deployed offshore not backyard nimby obstacle faced offshore wind technology content official website interview work windfloat advantage profile company principle energy inc alla weinstein ceo jon bonanno president coverage new comment contact official website interview download oct sterling allan conducted live hour interview ceo alla weinstein part free energy radio sery work windfloat quoting principle power target rapidly maturing offshore wind sector eliminating current deepwater limitation innovative solution windfloat conceived marine innovation technology exclusively licenced principle power floating foundation offshore wind turbine simple elegant patented design innovative feature windfloat dampen wave turbine motion enabling wind turbine sited previously inaccessible location superior wind resource multiple project proposal submitted pilot utilityscale development windfloat specification power rating displacement tonne rotor diameter hull weight tonne turbine height hull draught turbine weight tonne normal operation water depth tower weight tonne conventional mooring component download windfloat brochure pdf advantage quoting advantage windfloat foundation first stability negligible pitch yaw second design size onshore assembly third shallow draught flexibility windfloat semisubmersible offshore floating foundation fitted patented horizontal water entrapment heave plate base column plate reduce structure size cost achieving excellent performance practically free pitch yaw offshore environment addition windfloat superior stability augmented active ballast system design size windfloat enable structure assembled onshore towed final location significantly reducing construction cost providing improved flexibility profile company principle energy inc principle power inc technology developer focused deepwater offshore wind energy market deepwater depth greater metre offshore wind installation viable feasible due economic technological limitation principle power enabling product windfloat floating foundation wind turbine enable siting independent water depth exploiting world highest capacity wind resource principle power hold worldwide exclusive licence patented windfloat technology principle power sell windfloat foundation directly project developer municipal investor owned utility windfloat foundation enable enduser deepwater offshore wind resource ease delivery demand coastal loadcenter addition principle power design maintenance service windfloatequipped power project opportunistically licence technology needed breadth experience expertise proven track record principle power management team commensurate demand successful product technology developer further principle power personnel strategically located target market including united state united kingdom spain portugal principle power committed developing deepwater offshore wind market world commitment financing engineering product development expertise result significant triple bottom line investment opportunity attractive financial return clean energy generation social responsibility alla weinstein ceo alla founded aquabuoy sold finavera aquabuoy top clean energy technology ranked energy congress jon bonanno president jon bonanno cofounded principle power purpose applying entrepreneurial teambuilding finance experience making economically attractive renewable energy project vision portfolio principle power grow multiple gigawatt sustainable energy asset make difference offsetting fossil fuel usage serving chairman board director president principle power biography link jon member energy congress jon bonanno president priofile meetupcom linkedin profile coverage new comment description contact jackson street seattle washington email directoryconcentrated solar power general directorywind newswind videoswind powerpediawind power powerpediawind turbine directorywindpast development directorywindcaution type directorywindoffshore powerpediaoffshore wind power drawback directorywind farm powerpediawindfarm directoryhighefficiency horizontal axis wind turbine directoryhome generationwind turbine directoryvertical axis wind turbine directoryhigh altitude wind power directoryfloating directorywind augmentation directorypower atmospheric pressure difference specific directoryhumdinger windbelt directorywindplan directorywindlargest directorywind power united kingdom retrieved category wind concentrated solar view discussion source history personal tool log create account searching option translate navigation home freeenergyquest introduction advertise donate today new peswiki latest free energy pesn sponsored link feature top exotic exotic conventional event sponsor phi science item sale world space computer making biodiesel make electricity recondition battery namecheapcom department open source tech directory tree aether alt fuel antigravity battery betavoltaic bioelectricity biofuel biodiesel biomass body electric brown gas cold fusion conservation electrolysis electromagnetic electrostatic fuel cell fuel efficiency electric vehicle engine hydroxy fusion geothermal gravity motor home generation human powered hydro hydrogen joe cell lighting magnet motor nanotechnology nuclear nucl remediation oil piezoelectric plasma plastic river salt water mix solar solid state gen storage tesla turbine thermal electric tidal vortex waste energy water water fuel wave ocean wind wireless electricty point energy powerpedia betavoltaic cold fusion nikola tesla conspiracy suppression buyer beware movy humour job review videos store sponsored link support special page popular stat recent category revision advertise contact toolbox link related upload file special page sponsored link map added mdt when step ahead crowd genius step ahead crackpot rabbi shlomo riskin feb modified accessed time gnu free documentation licence peswiki disclaimer","m_szGeo1":"United States","m_szSourceType":"source_industry","m_szSrcUrl":"http://peswiki.com/index.php/Directory:Principle_Power,_Inc.","m_Places":["Best","United States","United Kingdom","Spain","Seattle, Washington","Us","Gravity","Tesla","Most"],"m_People":["Alla Weinstein","Jon Bonanno","Sterling D. Allan","93 S. Jackson Street","Joe Cells","Shlomo"],"m_Companies":["Principle Energy Inc.","Company: Principle Energy Inc.","Windfloat Foundation","Patented Windfloat Technology","Windfloat Foundations","Target","Congress","President Jon Bonanno Co","Meetup.com","Linkedin","Axis","Wor","L","Brown's","Plastic"],"m_BiGrams":["principle power","offshore wind","wind turbine","floating foundation","wind resource","jon bonanno","free energy","company principle","principle energy","energy inc","alla weinstein","bonanno president","weight tonne","windfloat foundation","deepwater offshore","sponsored link"],"m_TriGrams":["company principle energy","principle energy inc","jon bonanno president","deepwater offshore wind"],"m_SocialTags":[],"m_Topics":[],"m_Industry":[],"m_Technology":[],"m_BiCnt":[14,9,7,4,4,4,3,3,3,3,3,3,3,3,3,3],"m_TriCnt":[3,3,3,3],"m_iDocBodyWordCnt":796}
