{"m_szDocID":"523254","m_szDocTitle":"Directory:Cool Earth Solar - PESWiki","m_szYear":"2015","m_szDocSumamry":"PESWiki.com -- Pure Energy Systems Wiki:  Finding and Facilitating the Best Exotic Free Energy Technologies      Directory:Cool Earth Solar From PESWiki Jump to: navigation, search <> Cool Earth Solar (CES) has developed an inflatable solar concentrator technology that slashes materials costs, making solar competitive with commercial electricity generation systems. The design consists of two 2.5-meter diameter sheets of plastic (Mylar) sealed around the perimeter like a party balloon. One sheet is clear, and the other has a thin coating of aluminum to make it reflective. They are then inflated","m_szDocBody":"peswikicom pure energy system wiki finding facilitating exotic free energy technology directorycool earth solar peswiki jump navigation cool earth solar ces developed inflatable solar concentrator technology slashes material cost making solar competitive commercial electricity generation system design consist metre diameter sheet plastic mylar sealed perimeter party balloon sheet clear thin coating aluminium make reflective inflated balloon create concentrated beam collected photovoltaic cell suspended metal strut inside inflated space achieve sun concentration generating kilowatt electricity water receiver cool balloon pressure about atmosphere ambient balloon mounted frame track sun axis commercial plant slated begin construction central california summer expected installation cost year company think low making cost competitive coal power plant design lend deployed rapidly inexpensively significant contributing technology meeting gore challenge renewable year design resemble balloon strong wind problem system generate electricity mph wind shut down structurally withstand mph wind content official website interview video latest development work attribute price point patent company profile business model status new contact nec specialist comment official website presentation solar power pdf interview download aug sterling allan conducted hour interview rob lambkin ceo cool earth solar part free energy radio sery talk company inflatable solar concentrator technology slashes material cost making solar farm compete natural gas plant eventually coal plant commercial deployment expected year satisfy large portion gore yearsto%renewable initiative video inflatable solar collector coolearthsolarcom patented idea inflatable solar collector cheaper polished mirror concentrate sunlight photovoltaic chip design cheaper polished aluminium mirror withstand mph wind last year repair tape take minute change out cost balloon cent watt compared watt conventional installation minimal effect ground underneath array youtube latest development the utilityconnected cool earth project scheduled online half plant acre tracy financed firm million sery financing offtaker probably northern california utility lamkin cool earth scaling solar energy generation renewable energy world dec received million funding build pilot plant building prototype fall raising capital enable rapid growth work source attribute source inflatable mirror cheaper polished aluminium mirror diameter withstand mph wind year life span replaceable film repair tape replace minute cost rigging require steel truss work for conventional solar minimal ground preparation faster installation land habitat minimally affected price point phase system cost cent watt material cent watt installed large solar farm compared conventional solar installation patent patent filed process company profile founded company process building concentrated solar modular system ces top engineering business talent assist our goal cut cost solar electricity price competitive coal nonrenewable sourceswhile generating profit user par today investment company website business model source installation installation microutility franchise status source proof principle complete detail design subsystem prototyping seeking manufacturing partnership building manufacturing team seeking investment bring phase product market end new zeitgeist award excellence renewable energy north america award reader choice renewable energy world poll open reader select favourite finalist category including featured top enphase microinverter cool earth solar concentrator vote accepted renewable energy world cool earth scaling solar energy generation installed cost watt lower project roi maximum insolation rate delivery solar radiation unit horizontal surface type seek typically close transmission renewable energy world dec solar bubble funding cool earth solar received funding build pilot plant company developing inexpensive solar concentrating mirror transparent balloon lower cost solar photovoltaic ecogeek feb concentrated solar coolearth coolearth solar receive major funding coolearth develop own solar power plant utilising proprietary concentrated photovoltaic cpv technology reflective balloon received million funding cost efficient power plant compete economically conventional fuel inhabitat feb thank rlp inflatable solar coolearth concentrated photovoltaic coolearth solar patented design inflatable solar collector supposedly cheaper concentrate sunlight photovoltaic cell design time cheaper polished aluminium mirror treehugger dec balloon technology cut cost solar energy coolearth solar make solar energy cheaper coal year inflatable solar concentrator suspended farmland company hope cut cost electricity installation cent watt limited environmental impact mongabay won runner california cleantech open concept contact coolearth solar inc las positas road suite livermore phone fax email poc tony chen senior manager business development phone email nec specialist energy congress member jonathan bonanno investor sit board director cool earth solar comment discussion directoryconcentrated solar power directorysolarphotovoltaic directorysolar solar general directorysolar index resource newssolar current powerpediasolar energy encyclopaedic review history future directorysolar energy research development videossolar directorysolar problem solar modality directoryconcentrated solar power directorysolar infrared harvesting directorysolar photovoltaic directoryhome generationsolar directoryphotovoltaic research development directorysolar thermal directoryhome generationsolar heating directorythin film solar directorysolarphotosynthesis imitation directorysolar paint directorydye solar cell directorysolar tower directoryfloating solar chimney directoryspace based solar power directorysolar sail directorysolar window solar infrastructure directoryplastic solar cell directorysilicon efficient use alternative method directoryblack silicon directorysynchronous solar heliostat directorysolarinstallation consultation directorysolarlargest solar application directorysolar application directorysolarcharger directorysolarvehicle directorysolar hydrogen directorywalipini underground greenhouse ossolar ethanol distiller design directoryenergy roadway directorysolar pavement blackbody absorption asphalt retrieved category top solar concentrated solar view discussion source history personal tool log create account searching option translate navigation home freeenergyquest introduction advertise donate today new peswiki latest free energy pesn sponsored link feature top exotic exotic conventional event sponsor phi science item sale world space computer making biodiesel make electricity recondition battery namecheapcom department open source tech directory tree aether alt fuel antigravity battery betavoltaic bioelectricity biofuel biodiesel biomass body electric brown gas cold fusion conservation electrolysis electromagnetic electrostatic fuel cell fuel efficiency electric vehicle engine hydroxy fusion geothermal gravity motor home generation human powered hydro hydrogen joe cell lighting magnet motor nanotechnology nuclear nucl remediation oil piezoelectric plasma plastic river salt water mix solar solid state gen storage tesla turbine thermal electric tidal vortex waste energy water water fuel wave ocean wind wireless electricty point energy powerpedia betavoltaic cold fusion nikola tesla conspiracy suppression buyer beware movy humour job review videos store sponsored link support special page popular stat recent category revision advertise contact toolbox link related upload file special page sponsored link map added mdt when step ahead crowd genius step ahead crackpot rabbi shlomo riskin feb modified accessed time gnu free documentation licence peswiki disclaimer","m_szGeo1":"United States","m_szSourceType":"source_industry","m_szSrcUrl":"http://peswiki.com/index.php/Directory:Cool_Earth_Solar","m_Places":["Best","California","U.s.","Us","North America","Reader","Gravity","Tesla","Most"],"m_People":["Coolearth Solar","Sterling D. Allan","Al Gore","Tony Chen","Jonathan Bonanno","Joe Cells","Shlomo"],"m_Companies":["Plastic","Nec","Youtube","First Utility","Solar Energy","Congress","Underground","Pavement","Wor","L","Brown's"],"m_BiGrams":["cool earth","inflatable solar","earth solar","solar power","renewable energy","solar concentrator","mph wind","cheaper polished","cent watt","solar energy","energy world","free energy","power plant","withstand mph","solar collector","polished aluminium","aluminium mirror","concentrated solar","cut cost","cost solar","coolearth solar","sponsored link"],"m_TriGrams":["cool earth solar","renewable energy world","inflatable solar concentrator","withstand mph wind","inflatable solar collector","cheaper polished aluminium","polished aluminium mirror"],"m_SocialTags":[],"m_Topics":[],"m_Industry":[],"m_Technology":[],"m_BiCnt":[8,7,6,5,5,4,4,4,4,4,4,3,3,3,3,3,3,3,3,3,3,3],"m_TriCnt":[5,4,3,3,3,3,3],"m_iDocBodyWordCnt":970}
