{"m_szDocID":"523380","m_szDocTitle":"Kelley Blue Book","m_szYear":"2016","m_szDocSumamry":"ZIP CODE: | You have been signed out of My KBB Saved Cars Saved Comparisons Cars I might Like Most Researched Cars Dealer Price Quotes ZIP CODE: Account Profile Sign Out Not a Member? Become a member today for free and: Save your research Save car comparison Save price quote requests See our customized car recommendations Sign up today Sign In Email: Password: Remember me Sign in Forgot your password? Forgot Password? Enter your email address, and weâ€™ll send you a new password. Email: Go Sign Up for MyKBB I already have an account Email: Confirm Email: Set Password: Confirm Password: Profile","m_szDocBody":"zip code signed kbb saved car saved comparison car researched car dealer price quote zip code account profile member member today free and save research save car comparison save price quote request customised car recommendation today email password remember forgot password forgot password enter address send password email mykbb account email confirm email set password confirm password profile name acknowledge read accept term use receive tip tool resource kelley blue book affiliate privacy policy created personalised kbb profile start saving car research customised car recommendation link start recently viewed car profile save zip code browser accept cooky enter zip code enter valid digit zip code location save zip code provide information specific location privacy policy value united state home car value car price tradein private party value car sale local inventory sell car free dealer price quote vehicle history report local dealer car review kbb expert review car buyer guide consumer review safety quality rating award top top list kbb award car buyer guide latest car new auto show new research tool compare car payment calculator vehicle history report year cost car loan insurance cheque credit photos videos rebate incentive save zip code browser accept cooky enter zip code zip code save zip code lookup zip code kelley blue book value information specific location privacy policy value united state enter valid digit zip code advertisement enter valid digit zip code advertisement popular kbbcom class car ready roll coolest car luxury car car buyer guide home car year cost year cost own year cost total amount vehiclerelated cost cover year owning car include outofpocket expense fuel insurance vehicle depreciation loss value pocket expense repair based deductible extended warranty %average vehicle repair maintenance take car running %average vehicle maintenance state fee item tax licence registration %average vehicle state fee insurance include liability collision personal injury %average vehicle insurance financing based year loan term %average vehicle financing fuel based mile driven year %average vehicle fuel loss depreciation vehicle hold time important car year depreciation purchase price year average vehicle depreciation difference paid worth year year cost fuel fuel cost calculated epa mileage data make model style reflecting highway driving city driving kelley blue book update cost day based actual forecasted fuel cost insurance insurance cost assume driver clean record vehicle personal use quoted coverage include liability physical damage protection where applicable personal injury based mostoftenselected limit deductible financing financing assume buyer tier credit loan payment based fair purchase price msrp fair purchase price unavailable rebate incentive state fee state fee include registration fee based average newcar retail sale state vehicle fair purchase price msrp fair purchase price unavailable average state sale tax percent maintenance maintenance include cost manufacturer recommended service schedule amount based national average labour cost replacement part service item purchased manufacturer suggested list price repair repair based retail price zerodeductible extendedwarranty service contract cover vehicle initial fiveyear term ownership depreciation derived kelley blue book residual value updated day depreciation represent decrease vehicle based national fair purchase price msrp fair purchase price unavailable economic factor historical data hover detail full definition cheque year cost make required honda accord kbb year cost award winner brand vehicle recognised year cost champion stuck choose wisely year cost save money compare vehicle priced same doesnt cost time knowing year cost ahead time save money long run sample sedan purchase price pocket loss year cost sample sedan purchase price pocket loss year cost class compare classe subcompact car compact car midsize car fullsize car compact midsize fullsize entrylevel luxury car luxury car sport car midsize pickup truck fullsize pickup truck energy car hybrid electric vehicle compare favourite stack select car add class lowest year cost note show vehicle data year cost own calculation account added option info fair market range pay car review rating latest expert actual owner year cost advertisement search popular topic car car car sale car buying guide car award car review new car review car videos auto show car new car faq map car car worth kbbsm mobile company contact career corporate information industry relation advertising media centre linking policy business solution follow google linkedin roku mobile app iphone android kelley blue book inc right reserved copyright trademark term service privacy policy choice recently viewed car saved car back signed kbb vehicle advertisement","m_szGeo1":"","m_szSourceType":"source_general","m_szSrcUrl":"http://www.kbb.com/new-cars/total-cost-of-ownership/","m_Places":["Most","Enter","United States","Best","Winners","Van","Mobile","Us"],"m_People":[],"m_Companies":["U.s. Epa","Honda","Media Center","Facebook","Twitter","Google","Youtube","Linkedin","Roku","Kelley Blue Book Co."],"m_BiGrams":["year cost","zip code","purchase price","%average vehicle","fair purchase","kelley blue","blue book","save zip","car review","state fee","price quote","enter valid","valid digit","digit zip","buyer guide","luxury car","price msrp","msrp fair","price unavailable"],"m_TriGrams":["fair purchase price","kelley blue book","save zip code","enter valid digit","valid digit zip","digit zip code","car buyer guide","purchase price msrp","price msrp fair","msrp fair purchase","purchase price unavailable"],"m_SocialTags":[],"m_Topics":[],"m_Industry":[],"m_Technology":[],"m_BiCnt":[14,13,9,6,6,5,5,4,4,4,3,3,3,3,3,3,3,3,3],"m_TriCnt":[6,5,4,3,3,3,3,3,3,3,3],"m_iDocBodyWordCnt":709}
