{"m_szDocID":"523315","m_szDocTitle":"Directory:Xenotech Research - PESWiki","m_szYear":"2016","m_szDocSumamry":"PESWiki.com -- Pure Energy Systems Wiki:  Finding and Facilitating the Best Exotic Free Energy Technologies      Directory:Xenotech Research From PESWiki Jump to: navigation, search Page first featured July 4, 2009 Xenotech says their new modular Energy Pods will be available for home or business needs by around Dec. 2009. The small opening is for the focual point from a fresnel lens. See also Directory:Charles Shults' Fresnel Solar Design Xenotech Research, headed by Sir Charles Shults III, has several projects under way: 1) ramping up for manufacturing of an affordable, modular 500W Solar Po","m_szDocBody":"peswikicom pure energy system wiki finding facilitating exotic free energy technology directoryxenotech research peswiki jump navigation featured xenotech modular energy pod home business dec small opening focual point fresnel len directorycharle shult fresnel solar design xenotech research headed sir charle shult iii project way ramping manufacturing affordable modular solar pod purchase month moving mexico space port expedite development orbital solar power project deployment oct designing residential wind turbine expected cost other moving operation truth consequence mexico spaceport built there sir charle recently negotiating gene meyer terry martin space island group intend supply technology orbital solar power project received permission orbit solar power satellite demonstrator building receiving station ground proof principle xenotech research manufacturing solar furnace heat light power application shult negotiating investment supply large power station unit interest xenotech machine power growing rapidly june device ready production month similar refined compact power pod focus solar furnace produce basic electrical power developing wind turbine technology air diode principle hope cost residential wind turbine initial research conducted previously paid technically backer failed bring investor required move production decision explained shult proceeded develop alternative method generating power dispute technology intellectual property right economic reason decision backing space island investor xenotech employing people building open content official website related project site interview videos low cost solar power fresnel solar power solar power breakthrough patent profile company xenotech research inventor sir charle shult iii coverage new coverage related storey comment contact official website solar power spaceport space related paper article new xenotech forum created coast coast listener including information space island group channel related project site funding earlier solar work interview stream download sterling allan conducted live interview sir chale shult iii part free energy radio sery talked xenotech ramping manufacturing solar pod purchase month xenotech moving mexico space port expedite development orbital solar power project deployment oct designing residential wind turbine cost other storey pesncom july download jan sterling allan conducted live interview sir charle shult iii concentrated solar design part free energy radio show technology combine solar hot water panel large fresnel len turn hot water steam running turbine generate electricity roi year videos low cost solar power demonstrating turbine designed shult solar furnace power source provide energy home school village community youtube private project san juan college may prototype compatct turbine power june large rotary base solar fresnel len aparatus powered vey low current voltage june solar testing safety system boiler failure june steam volume immense volume steam realtime sunlight original concept kyberlogic llc boiler turbine technology international environmental trust fresnel solar power previous system overveiw solar thermal generation youtube solar power breakthrough sir charl shult show make solar system fraction today solar panel cost power home electric car system youtube patent profile company xenotech research our production facility truth consequence mexico opening soon inventor sir charle shult iii quoting sir charle shult iii worked martin marietta aerospace year weapon system computer based automated test equipment wrote nuclear emp test software pershing missile system worked patriot copperhead tank killer advanced attack helicopter system charle performed research grant nuclear fusion knighted received long term grant research robotic artificial intelligence written technical publication magazine article space astronomy atmosphere space resource development addition charle appeared radio programme book fossil hunter guide mar coverage new new xenotech featured solar spacebased xenotech spacetoearth solar power station targeted oct interview sir charle shult xenotech research describe current project including assisting deployment orbital solar power station ramping manufacturing affordable modular solar pod purchase month designing residential wind turbine expected cost other pesn comment examinercom energy technology hour interview george noory sir charle shult discussed work energy source shult working space island project orbiting solar station collect sunlight convert power beam energy groundbased receiver developing power pod small inexpensive device roof backyard single pod generate energy light home run appliance coast coast interview recording link xenotech show coverage list related storey flight spaceport america break ground flight departing virgin galactic spending usd million commercial space vehicle place land spaceport america world purposebuilt commercial spaceport broke ground mexico square foot facility cost gizmag comment discussion xenotech forum contact contact xenotech research located shader road suite orlando florida email sir charle career opportunity directoryshultslaboratory directorycharle shult fresnel solar design directoryangel nest project directoryspace based solar power directorywind solar general directorysolar index resource newssolar current powerpediasolar energy encyclopaedic review history future directorysolar energy research development videossolar directorysolar problem solar modality directoryconcentrated solar power directorysolar infrared harvesting directorysolar photovoltaic directoryhome generationsolar directoryphotovoltaic research development directorysolar thermal directoryhome generationsolar heating directorythin film solar directorysolarphotosynthesis imitation directorysolar paint directorydye solar cell directorysolar tower directoryfloating solar chimney directoryspace based solar power directorysolar sail directorysolar window solar infrastructure directoryplastic solar cell directorysilicon efficient use alternative method directoryblack silicon directorysynchronous solar heliostat directorysolarinstallation consultation directorysolarlargest solar application directorysolar application directorysolarcharger directorysolarvehicle directorysolar hydrogen directorywalipini underground greenhouse ossolar ethanol distiller design directoryenergy roadway directorysolar pavement blackbody absorption asphalt directory listing latest tree new peswiki home retrieved category solar company view discussion source history personal tool log create account searching option translate navigation home freeenergyquest introduction advertise donate today new peswiki latest free energy pesn sponsored link feature top exotic exotic conventional event sponsor phi science item sale world space computer making biodiesel make electricity recondition battery namecheapcom department open source tech directory tree aether alt fuel antigravity battery betavoltaic bioelectricity biofuel biodiesel biomass body electric brown gas cold fusion conservation electrolysis electromagnetic electrostatic fuel cell fuel efficiency electric vehicle engine hydroxy fusion geothermal gravity motor home generation human powered hydro hydrogen joe cell lighting magnet motor nanotechnology nuclear nucl remediation oil piezoelectric plasma plastic river salt water mix solar solid state gen storage tesla turbine thermal electric tidal vortex waste energy water water fuel wave ocean wind wireless electricty point energy powerpedia betavoltaic cold fusion nikola tesla conspiracy suppression buyer beware movy humour job review videos store sponsored link support special page popular stat recent category revision advertise contact toolbox link related upload file special page sponsored link map added mdt when step ahead crowd genius step ahead crackpot rabbi shlomo riskin feb modified accessed time gnu free documentation licence peswiki disclaimer","m_szGeo1":"","m_szSourceType":"source_industry","m_szSrcUrl":"http://peswiki.com/index.php/Directory:Xenotech_Research","m_Places":["Best","New Mexico","United States","Orlando, Florida","Gravity","Tesla","Most"],"m_People":["Charles Shults Iii","Gene Meyers","Terry Martin","Charls Shults","Sterling D. Allan","Martin Marietta","George Noory","Joe Cells","Shlomo"],"m_Companies":["Pods","Ramping","Pod","Space Island Group","Youtube","San Juan College","Environmental Trust","Fossil","Google","Spaceport America","Virgin Galactic","Solar Energy","Plastic","Underground","Pavement","Wor","L","Brown's"],"m_BiGrams":["solar power","sir charle","charle shult","xenotech research","shult iii","wind turbine","free energy","fresnel solar","orbital solar","residential wind","space island","fresnel len","solar design","ramping manufacturing","solar pod","pod purchase","purchase month","power project","designing residential","cost other","solar furnace","power station","interview sir","sponsored link"],"m_TriGrams":["sir charle shult","charle shult iii","orbital solar power","residential wind turbine","solar pod purchase","pod purchase month","solar power project","designing residential wind"],"m_SocialTags":[],"m_Topics":[],"m_Industry":[],"m_Technology":[],"m_BiCnt":[16,9,7,6,6,5,4,4,4,4,4,3,3,3,3,3,3,3,3,3,3,3,3,3],"m_TriCnt":[7,5,4,4,3,3,3,3],"m_iDocBodyWordCnt":1011}
