{"m_szDocID":"523733","m_szDocTitle":"China Sustainability Policy and Government Vehicles | The Energy Collective","m_szYear":"2014","m_szDocSumamry":"0 Posted July 16, 2014 Keywords: Carbon and De-carbonization , Electricity , Energy Security , Sustainability , Utilities , Environmental Policy , Cleantech , Green Business , Finance , China , Energy , Energy and Economy , Fuels , News , Politics & Legislation , Transportation , china , electric vehicles (evs) , governmental policy , green cars , purchasing power China has mandated that at least 30 percent of government vehicles purchased in the next two years will have to be fueled by alternative energy sources. The plan for \"new-energy vehicles,\" Chinaâ€™s term for alternative fuel vehicles, ","m_szDocBody":"posted keyword carbon decarbonization electricity energy security sustainability utility environmental policy cleantech green business finance china energy energy economy fuel new politic legislation transportation china electric vehicle evs governmental policy green car purchasing power china mandated percent government vehicle purchased year fueled alternative energy source plan newenergy vehicle chinas term alternative fuel vehicle include electric car plugin hybrid hydrogen electric fuel cell vehicle chinese announcement reported bloomberg new local province required meet target period percentage alternative vehicle government required buy rise annually spur market china announced week waive percent purchase tax electric car tax break domestic foreign electric car market demand evs china fallen short government target newenergy vehicle road end year fewer vehicle road far number hint difficult meet government target million newenergy vehicle government sedan purchase fleet shouldnt cost yuan each give boost chinese maker compete price point byd rule chinese government similar move government encourage adoption alternative fuel vehicle president obama pledged federal government convert percent fleet alternative fuel vehicle buying car chinese government build charging station open market consumer buy electric vehicle study international energy agency noted half chinese population clustered urban centre living multiunit dwelling lack charging infrastructure people purchased evs weekend charging infrastructure workplace key accelerate adoption china substantial network fast charger earlier month beijing released plan rapid public charging station transit hub airport train station necessarily apartment building byd denza electric vehicle released earlier year world offer fast charging home photo credit china vehicle greentech media gtm produce industryleading new research conference businesstobusiness greentech market coverage areas include solar smart grid energy efficiency wind nonincumbent energy market information visit greentechmediacom follow twitter facebook ","m_szGeo1":"China","m_szSourceType":"source_industry","m_szSrcUrl":"http://www.theenergycollective.com/katherinetweed/431791/chinas-latest-mandate-30-government-cars-need-be-electric-or-use-alternative-f","m_Places":["Beijing","Dc"],"m_People":["Obama","Denza"],"m_Companies":["Cleantech","Target","International Energy Agency","Facebook"],"m_BiGrams":["electric vehicle","newenergy vehicle","alternative fuel","fuel vehicle","electric car"],"m_TriGrams":["alternative fuel vehicle"],"m_SocialTags":[],"m_Topics":[],"m_Industry":[],"m_Technology":[],"m_BiCnt":[3,3,3,3,3],"m_TriCnt":[3],"m_iDocBodyWordCnt":270}
