{"m_szDocID":"525425","m_szDocTitle":"Wind Energy Growth in 2012 | The Energy Collective","m_szYear":"2013","m_szDocSumamry":"5 Posted August 9, 2013 Keywords: Electricity , Energy Security , Tech , Sustainability , Utilities , Efficiency , Cleantech , Wind , Energy and Economy , Fuels , News , market growth , wind energy industry Cai Steger, Energy Policy Analyst, New York, Center for Market Innovation Here’s some good news that shouldn’t get buried amid the summer heat and beach vacations: 2012 was a banner year for American wind power. That’s thanks in large part to federal and state policies and incentives that prioritize clean energy and the jobs, public health and global-warming benefits that come with it. So s","m_szDocBody":"posted keyword electricity energy security tech sustainability utility efficiency cleantech wind energy economy fuel new market growth wind energy industry cai steger energy policy analyst york centre market innovation here good new shouldnt buried amid summer heat beach vacation banner year american wind power large part federal state policy incentive prioritise clean energy job public health globalwarming benefit department energy wind technology market report seventh annual released yesterday fact new report impressive year wind power beat lowpriced natural gas largest source electricity capturing percent electric capacity power million home remarkable report author write persistently low natural gas price year state percent electricity wind power year end statesiowa south dakota kansasgot percent impressive growth traditionally slowmoving energy industry wind power job rose layoff attributed profound uncertainty renewal federal production tax credit tax credit help level playing field wind farm compete conventional energy technologiescoal gas oilthat received hundred billion dollar federal support plus year image courtesy department energy interactive map exponential growth wind doe wind report tell else too federal state policy incentive central continuing growth field developing earlier energy technology policy driver federal state level important expansion wind power market united state author write what more uncertainty continuation policy embattled production tax credit investment tax credit attack state renewable energy standard create additional hesitancy wind power market make sense field developer jump bank lend market unpredictable back good new america led world installed wind power capacity though early leader field china overtook moreover year wind power accounted quarter half electric capacity wind power increasingly affordable doe tell price turbine decreased percent late year installed price kilowatt dropped percent expected fall market wind power expensive option electric generation bar none increasingly wind power americanmade too percent wind power component manufactured here compared percent wind power industry take root foreign manufacturer set shop here close market and major importer wind power technology exporting wind power componentsto canada brazil mexico china way state policy big impact wind power growth percent wind farm built state renewable energy standard leveraging billion private investment good new track percent electricity wind power ahead schedule growth expected federal ptc extension incentivize wind power project begin construction projection certain report author write lack clarity fate federal tax incentive wind energy primary source uncertainty dont way gridlock washington make hard imagine nation elected representative good benefit federal state wind power policy incentive bring all examine number doe reported yesterdaywind power supply percent denmark electricity percent portugal spainsand start envisioning country dominate clean energy revolution john miller say wind power expanded significantly recent year level post granted power design max capacity apparently due wind turbine year include impact capacity factor typically reduce installed wind net generation design maximum wind power net generation increase billion kwh level however natural gas power net generation increased billion kwh natural gas power generation displace reduced coal power generation period provided critical peaking power needed backup stabilise power grid supplied added new variable wind power past year wind power net generation grown incredible billion kwh this however compare natural gas power growth billion kwh time wind power net generation wind turbine cost significantly past year expensive option electric generation bar none eia total system levelized cost dataindicate natural gas ccgt power cost onshore wind power lastly eia aeo project total renewable power source increase total generation capacity however half renewable source generation hydropower balance added renewable source power expected wind power post comment nathan wilson say celebrate affordability wind note wind farm built year turbine installed existing farm trade awea temporary lapse federal subsidy less day stall industry nuclear initial cost wind year soof depreciation make cheap power making cheap power year wind farm dy plus wind penetration time add expensive energy storage nuke robert bernal say wind but store concentrated solar thermal power molten salt storage molten salt fission reactor similar big three option fundamentally limited power density land constraint such biofuel wave tidal etc order power complete growing planetary civilization invented such deep geothermal fusion windpower rare earth element build billion wind turbine permanent magnet billion electric car motor mustdevelop expensive abundant safe low carbon sourcewhich stored distributed speed light fundamental potential prevent biofry time ","m_szGeo1":"","m_szSourceType":"source_industry","m_szSrcUrl":"http://www.theenergycollective.com/nrdcswitchboard/258781/power-wind-compels-you-read-report","m_Places":["Steger","New York","Iowa","South Dakota","Kansas","United States","America","China","Canada","Brazil","Mexico","Along","Washington","Denmark","Portugal","Spain"],"m_People":["Cai","Nathan Wilson","Robert Bernal"],"m_Companies":["Cleantech","Wind Technologies","Revolution"],"m_BiGrams":["wind power","natural gas","net generation","federal state","year wind","tax credit","wind farm","power net","billion kwh","wind energy","good new","state policy","policy incentive","author write","percent wind","wind turbine","gas power"],"m_TriGrams":["power net generation","year wind power","wind power net","natural gas power"],"m_SocialTags":[],"m_Topics":[],"m_Industry":[],"m_Technology":[],"m_BiCnt":[26,6,5,4,4,4,4,4,4,3,3,3,3,3,3,3,3],"m_TriCnt":[4,3,3,3],"m_iDocBodyWordCnt":690}
