{"m_szDocID":"526547","m_szDocTitle":"Renewables Policies and Making Them a Reality | The Energy Collective","m_szYear":"2014","m_szDocSumamry":"1 Posted September 5, 2014 Keywords: Electricity , Energy Security , Communications and Messaging , Sustainability , Utilities , Environmental Policy , Cleantech , Green Business , Wind , Energy and Economy , Fuels , News , Politics & Legislation , department of energy (doe) , offshore wind , renewables policy Could the U.S. go from being nowhere on offshore shore wind power to having over a dozen projects built over the next five to seven years? Thatâ€™s a very real possibility, according to a report just released by the U.S. Department of Energy (DOE). The report, prepared by Navigant Consulti","m_szDocBody":"posted keyword electricity energy security communication messaging sustainability utility environmental policy cleantech green business wind energy economy fuel new politic legislation department energy doe offshore wind renewable policy offshore shore wind power dozen project built year real possibility report released department energy doe report prepared navigant consulting annual offshore wind market economic analysis assesse progress country made building offshore wind power industry hold host benefit all new report here project navigant see advanced stage development representing gigawatt electricity project geographically diverse doe offshore wind market economic analysis report show project country advanced stage development map courtesy doe east coast wind resource tremendous floating offshore wind power technology work coast oregon ohio state water lake erie texas state water galveston and virgin island couple project dont fruition leave dozen offshore wind project pipeline worst new expiration federal investment tax credit itc offshore wind power help defray higher upfront cost fuelfree technology creating lack policy certainty hindering development important energy source start realising offshore wind power benefitsand here short compelling list emissionsfree electricity good paying job stable electric price leg rapidly expanding international marketplaceit imperative congress reauthorize itc immediately offshore wind power growing gangbuster worldwide report find shouldnt miss industry grow key point report close water offshore wind projectsthe megawatt cape wind project nantucket sound deepwater wind megawatt block island project rhode islandhave moved initial stage construction englander electricity project doe promote innovation year doe granted demonstration project million advance offshore wind power way spur technological innovation remove market barrier demonstrate leadingedge technology large majority funding pilot project located coast jersey virginia oregon additional support projectsone located lake erie coast maine price decline cost installing offshore wind power dropped percent year alone policy place offshore wind power costcompetitive conventional polluting power policy spark employment offshore wind power industry including manufacturer turbine cabling component employed fulltime worker report author estimated advancedstage project start construction wrote employment double triple support equipment installation moment project idle drawing board global industry grow alone doe report found megawatt installed worldwide additional plus megawatt construction these project arent europe either china work offshore wind power offer country full threequarter electricity consumed coastal state offshore wind power ease grid congestion cut electric cost create job mitigate increasing danger climate change give kid cleaner air breathe congress reinstate policy investment tax credit offshore wind power project drawing board water report highlight time congress act precisely now robert bernal say solar storage nuclear molten salt advantage wind storage gas gas gas killed electric car decade ago hydrogen economy excuse kill and gov swartzy drive hydrogen hummer glitz terrawat floating wind turbine needterrawatt molten salt nuclear needterrawatt cheap solar backed storage pumped hydro lot good ole fashioned engineering civil construction job right actually cheaper build nuclear because dependable higher require storage course gas gas gas douchebag and safety excuse fossil fuel kill unit energy let back trivial renewable lot inefficient natural gas clean coal germany flat wrong andthus worthy subsidy lower baseload threshold such expected solar variability pointless environmental point backed phs physic excess state mere reduction good enough ","m_szGeo1":"","m_szSourceType":"source_industry","m_szSrcUrl":"http://www.theenergycollective.com/nrdcswitchboard/483566/policies-can-move-offshore-wind-power-drawing-boards-and-water-new-doe-report#comments","m_Places":["Oregon","Ohio","Lake Erie","Texas","U.s. Virgin Islands","Nantucket","Deepwater","Block Island","Rhode Island","New Jersey","Virginia","Maine","Europe","China","Germany"],"m_People":["Robert Bernal"],"m_Companies":["Cleantech","Itc","Free Technology","Edge Technologies"],"m_BiGrams":["offshore wind","wind power"],"m_TriGrams":["offshore wind power"],"m_SocialTags":[],"m_Topics":[],"m_Industry":[],"m_Technology":[],"m_BiCnt":[17,13],"m_TriCnt":[12],"m_iDocBodyWordCnt":507}
