{"m_szDocID":"526756","m_szDocTitle":"Next Big Future: Breakthrough for superefficient conversion of heat to electricity could boost coal plant efficiency to 54% from 30-45% and concentrated solar power to 40%","m_szYear":"2013","m_szDocSumamry":"Coverage of Disruptive Science and Technology Forum About Contact Facebook twitter Google February 10, 2013 Breakthrough for superefficient conversion of heat to electricity could boost coal plant efficiency to 54% from 30-45% and concentrated solar power to 40% coal, concentrated solar power, energy, magnets, physics, science, solar Facebook Twitter linkedin google Reddit Arxiv - Thermionics (electronics for converting heat to electricity) previously had efficiency limitations due to “space current” – build-ups of electrons mutually repelling each other and choking the flow of current – so th","m_szDocBody":"coverage disruptive science technology forum contact breakthrough superefficient conversion heat electricity boost coal plant efficiency concentrated solar power coal concentrated solar power energy magnet physic science solar linkedin reddit arxiv thermionic electronic converting heat electricity previously efficiency limitation due space current buildup electron mutually repelling choking flow current system external electric magnetic field electron direction system promise fraction carnot limit converted directly electrical power efficient coal plant coal power thermoelectronic approach promise efficiency range achieving acting topping cycle lower temperature steam system coal furnace burn steam turbine run output significant loss due mismatch furnace steam powercycle thermoelectronic converter covering range add significantly power extracted powerplant pushing efficiency case efficient coal plant pushed increasing power output additional fuel cost moving part efficient concentrated solar power switching solarpower application imagine thermoelectronic converter centre concentrator system focuse sunlight time normal intensity temp photon enhanced thermionic emission cousin photoelectric effect system convert raw sunlight electrical power efficiency electric power may principle generated highly cient manner heat created focused solar irradiation chemical combustion nuclear decay mean thermionic energy conversion conversion ciency thermionic process degraded electron space charge ciency thermionic generator amounted fraction fundamentally possible show spacecharge problem resolved shaping electric potential distribution converter static electron spacecharge cloud transformed output current technical development practical generator require substantial ort conclude highly cient transformation heat electric power achieved optimization conversion effi ciency require development metal semiconductor surface desired ffective work function electron nity respectively nanostructuring electrode surface surface stable temperature vacuum tunability gate eld open possibility alter converter parameter operation generate ion neutralise spacecharge cloud eliminated adatom element lower work function electrode collector effi ciency device thermally optimised minimise heat losse wiring furthermore thermal radiation emitter reflected fficiently electrode ballistic electron transport emitter collector vacuum mbar required reminiscent radio tube device realised example flipchip arrangement oxidecoated wafer separated ten micrometre thermalinsulation spacer produce hundred watt power active areas magnetic eld typically large tolerance strength spatial distribution generated permanent magnet application power plant superconducting coil achieving viable highly fficient device require substantial material science effort develop functional possibly nanostructured material engineering ort achieve stable vacuum environment order minimise radiative conductive heat losse ensure competitive cost remarkably however obstacle fundamental nature impede highly fficient power generation based thermoelectronic energy converter article give quick review ycombinator stumbleupon author brian linkedin reddit newer post older post home message archive converting municipal waste energy industrial drone trade positive solveforx replace plastic comparing russian meteor tunguska yeste meteor hit russia force hiroshima bomb synthesising dna time cheaper making optical nanoparticle computing rethinking solar cheaper natural graphene supercapacitor producing terawatt economical energy storage tricking cmos generate terahertz frequency george miley lenr nanoparticle cold fusion planetary resource describe design adva rodney brook reimagine manufacturing locali accelerating intelligence technology powerf solve inflatable robot car solve lockheed skunkwork worki nanostructured nanowire appear solve loss carbon nanotube sheet solar sail synthetic biology circuit combine memory navy save money build aircraft carrier not exceed required spec repeatedl controversial eestor reemerge report pilot plan carnival space stem cell breakthrough lead bone repa research progress brain cancer breakthrough superefficient conversion heat top site fin nextbigfuture week biosingularity brian bio lifeboat foundation build world greatness centauri dream centre responsible nanotech blog coal bad diamond semiconductor mnt break improvement economic logjam foresight nanodot future pundit instapundit kinematic selfreplicating machine book online melanie swan futurememe methuselah foundation blog molecular nanotechnology engine nanotechnology nextbigfuture flipcard nuke mean coal nuclear cannon summary nuclear green charle barton quantum computer summary space nanotechnology synthetic biology assembly pathway thorium energy thorium mass produced clean nuclear power universe today blognano nanoscale material lifeboat foundation blog nanoparticle drug delivery community follow popular label future science energy technology united state china world space nuclear physic economic impact medicine material military prediction japan europe robotic oil gadget gdp astronomy environment nasa solar russia economy car future weapon google disease launch fusion india laser airplane battery canada propulsion life extension computer risk internet longevity policy artificial intelligence darpa public health politic population carbon nanotube carnival space spacex brain graphene quantum computer economic electric car controversial death cancer sensor dna nanotechnology telescope enabling technology gene therapy communication smartphone uranium qubit city singularity transhuman electronic coal stem cell navy commercialization war molecular nanotechnology antiaging climate change metamaterial nanoscale carnival nuclear energy fission mar wireless superconductor poverty water computer memory elon musk regeneration magnet mit air pollution dwave wind apple movy supercomputer tissue engineering uav cold fusion sen moon africa peak oil asia ibm intel adiabatic quantum computer imaging gadget building food additive manufacturing synthetic biology air force business quantum effect television cellphone germany display agriculture south korea nanoparticle public transportation hypersonic broadband dna nanotechnology gene sequencing lithography thorium wealth bootstrapping nanotechnology natural gas ship colonisation personalised medicine satellite genetic engineering israel low energy nuclear reaction taiwan australia bakken computer architecture north dakota nvidia superconductor iran assembly dense plasma focus fiction engineering computer korea transportation education hybrid samsung cameras iphone weapon ageing nanowire quantum dot focus fusion sander olson niac android army optical networking spintronic exoskeleton skyscraper drone geopolitic thermoelectric brain emulation microscope rossi futurist interview france geopolitical invisible optical computing mind computer interface printable electronic protein microsoft vaccine asteroid biofuel cyborg ocean singapore tablet room temperature superconductor ultracapacitor diamond petaflop iec fusion rna petaflop terahertz intelligence concentrated solar power exaflop molten salt mathematic faster moore law speed rail machine learning nanomedicine oilsand tablet cognitive enhancement italy nanomaterial mem manufacturing supercomputer telescope gpgpu memristor performance enhancement quantum annealing iraq rapid manufacturing engine regenerative medicine california global warming cloud computing finance neuron saudi arabia nanostructured virus nanoparticle drug delivery plasmonic silicon photonic solar sail alzheimer speculation transhumanist deepwater oil guided assembly aeroplane mach effect railgun alberta brazil molecular electronic planetary resource smartphone dna origami economy electric plane lab chip oil shale submarine direct energy weapon flexible electronic hydro rapid prototyping robot security facebook biomarker lifeboat foundation wearable electronic myostatin inhibitor nextbigfuture radiation crispr gpu mechanical nanotechnology drexler photonic propulsion active cloak fuel cell memristor mundane singularity ocean ukraine amd friedlander algorithm broad group euv lithography general fusion genomic presingularity submarine quantum computer space elevator teraflop electric bike job emdrive femtosecond laser nanophotonic precursor technology superlense tesla laser atomically precise manufacturing fish flash hologram mexico programmable molecular nanotechnology surveillance texas zettaflop material resolution neuromorphic policy saskatchewan wealthy flu blacklight power desalination millimetre wireless star war gigapixel dna synthesis project orion deep learning genome engineering nanoelectronic nanopatterning plasmon terrorism fabber mitochondria amazon diamondoid mechanosynthesis pollution video game exaflop gigabit hyperion power generation indonesia silicon challenge diabete entertainment exoplanet ocean mining winterberg xprize rna interference gene synthesis geoengineering mri bloodstream robot camera carbon capture hunger pathway casimir force heartland robotic teraflop oled freitas helion energy nanoimprint roll roll computational chemistry hyperloop open source robot social media fpgas electric sail kitegen nanomembrane spaceplane lighting plane robotic smart grid techonomy augmented reality brillouin energy contour crafting cubesat future weapon mobile nanolaser prediction quantum encryption semiconductor skyscraper big data biofuel crowdfunding hong kong kickstarter nanocomposite parkinson disease vietnam virtual reality zyvex atomic layer deposition dna manufacturing ebeam lithography flying car gps medical nanodiamond nanoribbon terabit ethernet verizon aircraft algae antimatter city electric futurist graphite nem nuclear fusion pakistan privacy spain superconducting synthetic life agi antenna defkalion exascale nanomagnet nanotechnology business satellite solve sport star trek tensilica transformation optic transgenic attosecond laser car cryonic display drone eestor gene led nanoplasmonic rapamycin resveratrol seastead sound syria urbanisation dna computer building communication dome double lithography genescient genome internet thing liquid fluoride petrobank quantum wimax adaptive clinical trial cloning cvd nanofactory nanofiber nanowire power beaming rejuvenation safety south africa spiderfab telomere claytronic ideas factory bitcoin crowdsourcing deep reinforcement learning epigenetic magnet nanorobotic state matter pluto sony lidar bolonkin construction electric car femtotech geothermal googlex hyperlense mram nanoantenna nanolithography nervous system petabyte phase change material reusable rocket south america thermophotovoltaic cell video vision cnano technology lpp fusion rfid bacteria chemistry concrete ereader gas graphane harvesting law enforcement metformin nanopore ovonic petawatt petrobakken renewable society space based solar power tourism toyota vertical farming dna nanoarray artificial organ bioprinting egypt electron beam farming fullerene funding gbp genetic honda leap motion lenr matter nanocomp technology optogenetic plasma port security programmable matter rethink robotic sensor terrestrial energy ilemm asteroid atomtronic brain computational lithography database ebola innovation meat factory nanobot nanoparticle nanosensor north korea red camera room temperature spintronic scooter scramjet smart dust superintelligence taxe war asic rotaxane aerogel atomic swiches biotechnology calico cement conservation dip pen lithography ecat electricity exawatt exosuit genomic engineering loon temperature reactor history hypertelescope illusion interview kurzweil mind reading movie nanodot nanorod nanotube obesity photonic poor replication soft exoskeleton fork tilera trialpha energy turkey work antennas atom circuit battery bigelow cleantech cloud cray cryocooling disruption fpga ftl futurism gene drive hybrid irna internet everything laptop magnetic monopole motorcycle nanodevice productivity quantum well risk silicon valley solar energy stratolaunch sun microsystem synapse terapixel tool topdown nanotechnology ultrasound vaccine microrna nigel cook annealing baidu cmos boron nanotube bubble commercial computational government corruption death deep mind diesel dubai entrepreneur ethic exoplanet flibe energy follistatin george church glass greece hoverboard industry infrastructure jetpack medicine memcapacitor meminductor microscale monopole nanomagnet logic nanomembrane nanometal nanomotor nanorod nanotip nuclear energy optical tweezer personal transport protein quantum biology rna nanotechnology sensing smartwatch super vision synthetic fuel terabyte trapped ion venus wolfram alpha abundance artificial life avagadro scale computing baldness bike bioengineering brain uploading chromebook cyberwar diblock copolymer dna brick ebook emc energy united state exabyte exponential manufacturing extinction fast boat faster light fat loss genome haptic interface health highlight ipad low power malnutrition material methuselarity mice microbiome micronutrient microscope middle class montana nanoionic memory nanomanufacturing nanopore nanotechnology ipo nantero nuclear fission nutrigenomic parallel petapixel plasmonic lithography political poll result ppp programmable metallization cell qubit railgun recombineering driving car service science ship silicene spaser spinplasmonic sport stm straintronic tech terabit transparent water wikileak wireless power world war xray zettawatt amazon baxter ben goertzel fgpa freeman dyson pacer usv alphabet antilaser automation beam pen lithography biochar buiding capri carbon atomic chain carbyne cella energy cloaking cluster state quantum computer crime data mining dell detection employment energy exciton existential risk fat field effect transistor fighter finfet flywheel freepiston engine future energy gdp economic impact gecko gigaflop future graphyne gravity head mounted display iarpa jovion corporation laser sintering liposuction magnetic magnetricity marine medicine megacity merkle metagenomic metamaterial metmaterial microtechnology miltary moon nanocrystalline cellulose nanocube nanodisk nanoenergetic nanoglue nanolattice nanooptic nanopillar nanoprobe nanosand nanosheet nanostore nanosurgery nanowelding neurorobotic pandemic personal aviation petahertz picometer picoprojector popululation printable robot quantum cellular automata quantum computing quantum dot rail ribosome russian rydberg matter science future skylon software space tower spinal cord subatomic tank techology telecope telsa thinfilm transmutation tricorder triple lithography utility fog venter bullet wave disc engine wet nanotechnology yottabyte yottaflop youtube zpinch point energy zettabyte tsunami british columbia cycle computing euclideon gna nanotechnology grant norton hcar herman kahn legend iedm jame miller jason stowe john mankin juan enriquez kardashev keith lofstrom lower montney montney nen peter glaser production rrnil red whittaker rodney brook upper montney vtol acer aerographite aid alaska algorithm alphago anodization nanolithography architecture astronomgy battery ibm bettery biosyntrolysis biocomputer biofab bionano blue origin brian ahern brontobyte buckypaper buckywire cardiovascular carmera cell china energy china nuclear chiplet chipsat cholesterol cold war history colloidal quantum dot comcast compute computing connectomic convergence copper nanowelding cornocopia cortical computing cosmology country crescent point cryosleep cryptocurrency cyborg camera dark knight data science dendrimer diamandis dielectrophoresis dry nanotechnology eagle ford econ economice ecoskeleton electrohydrodynamic elevator eor esail exalfop ferropaper flop free space optic freepiston linear alternator fure future physic future wireless futute gadget sensor gate around glycerol nucleic acid golden spike googlke graphen graphene monoxide graphic green halophyte handheld head transplant helium helphookupcom humour hypersound idaho national lab india science intel future interstellar intracellular machine ion beam ivf launch loop lifi litecoin lithium sulphur lunar lysosome magnetic magnetic resonance force microscopy magnetic superatom magnet future maker masdar maser mcam media equivalence memcomputing memflector metabolic engineering metalen metananocircuitry methane methylome microassembly microcontact printing miitary millimetre scale computing mining nabsy nanoorigami nanoarches nanobrain nanobubble nanobud nanocable nanocar nanoceramic nanochannel nanocone nanodiamond nanodome nanofluid nanofoam nanogravure nanoionic nanokite nanolipogel nanometer nanopantography nanopaper nanopost nanoscalpel nanoshell nanoshield nanosolder nanostar nanothread nanoweave nasa future nasa science nasa niac neural turing machine nias nokia nram nuclea numenta obama optalysy optical metamaterial assembly optoelectronic optomec paintable battery paperphone paralysis peptoid nanotechnology perfect len petabit phablet phycsic physic science picoscale plasmene polariton superfluid polariton polaritronic political future poltic popup mem probabilistic cmos propulsion launch protection protocell quad lithography quantum learning quantum simulation quantum spin liquid qudit regenerative dentistry remote rfstm scanning beam interference lithography scarcity sceince science fiction calculation science quantum communication sciencee sciene sense server sky server smart dew smokefree cooker sprayon solar power stanene startram statite ste stumbleupon supercavitation superinsulator superlattice synthetic chemistry tcarbon technogy technology energy technology gagdet technolology techonology tegra teleccope telemedicine terawatt hobbit timing tokomak topological quantum computer tpv cell train trialpha energy tristar tropic thunder turbine tyler formation ultrashort pulse ultravector united universal memory upu interface videos vietname voice recognition weapon wifi willow garage wind solar wnd word lab zeolite zeptojoule zram plugin energy space science technology world medicine robotic quantum computer artificial intelligence copyright big future inc right reserved registration constitute acceptance term service privacy policy uscontact ","m_szGeo1":"","m_szSourceType":"source_general","m_szSrcUrl":"http://nextbigfuture.com/2013/02/breakthrough-for-superefficient.html","m_Places":["Russia","Hiroshima","Best","United States","Japan","Europe","India","Canada","Uk","Africa","Asia","Germany","South Korea","Israel","Taiwan","Australia","North Dakota","Iran","Korea","France","Singapore","Italy","Iraq","Saudi Arabia","Brazil","Ukraine","Mexico","Indonesia","Hong Kong","Vietnam","Pakistan","Spain","Syria","South Africa","South America","Egypt","North Korea","Turkey","Silicon Valley","Dubai","Greece","British Columbia"],"m_People":["Brian Wang","George Miley","Rodney Brooks","Green - Charles Barton","Red Whittaker","Nigel B. Cook","Ben Goertzel","Freeman Dyson","Grant Norton","Herman Kahn","James Miller","Jason Stowe","John Mankins","Juan Enriquez","Keith Lofstrom","Peter Glaser","Brian Ahern"],"m_Companies":["Facebook","Twitter","Google","Reddit","Ups","Cycle","Photon","Cmos","Lockheed","Navy","Lifeboat Foundation","Kinematic","Nasa","Spacex","Apple","Ibm","Intel","Nvidia","Olson","Microsoft","Direct Energy","Amd","Amazon","Verizon","Agi","Cnano Technology","Leap Motion","Rethink Robotics","Diesel","Nantero","Pacer","Dell","Acer","Comcast","United","Universal"],"m_BiGrams":["quantum computer","solar power","concentrated solar","coal plant","synthetic biology","lifeboat foundation","molecular nanotechnology","quantum dot"],"m_TriGrams":["concentrated solar power"],"m_SocialTags":[],"m_Topics":[],"m_Industry":[],"m_Technology":[],"m_BiCnt":[7,6,4,3,3,3,3,3],"m_TriCnt":[4],"m_iDocBodyWordCnt":2196}
