{"m_szDocID":"529703","m_szDocTitle":"Environmental Risk and Replacement Fuels | The Energy Collective","m_szYear":"2014","m_szDocSumamry":"24 Posted October 7, 2014 Keywords: Carbon and De-carbonization , Electricity , Energy Security , Tech , Communications and Messaging , Storage , Sustainability , Utilities , Efficiency , Environmental Policy , Cleantech , Renewables , Risk Management , Electricity Grid , Energy , Energy and Economy , Fuels , clean energy transition , energy information administration (eia) , renewables adoption The United States Energy Information Agency estimates that 11% of the world's total energy comes from renewable sources, a number they project will grow modestly to 15% by 2040. They also estimate that","m_szDocBody":"posted keyword carbon decarbonization electricity energy security tech communication messaging storage sustainability utility efficiency environmental policy cleantech renewable risk management electricity grid energy energy economy fuel clean energy transition energy information administration eia renewable adoption united state energy information agency estimate world total energy renewable source number project grow modestly estimate world electricity renewable energy expect grow percentage viewed context worldwide growth energy consumption united state energy information agency world energy consumption grow quadrillion british thermal unit btu quadrillion btu growth nonoecd nonorganization economic cooperation development country demand driven strong economic growth renewable energy nuclear power world fastestgrowing energy source increasing year however fossil fuel continue supply world energy natural gas fastestgrowing fossil fuel global supply tight gas shale gas coalbed methane increase projection altered global warming degree control small hopeful sign pace change accelerate call projected trend transition renewable energy justin doom bloomberg new billion spent globally renewable energy project quarter percent period year chinese solar investment record bloomberg energy finance report spending quarter gained percent billion billion year earlier londonbased research company today statement billion china solar investing soared billion billion modest trend renewable energy promising trend discouraging energy information agency see continued increase fossil fuel increased release carbon dioxide specifically agency report that energyrelated carbon dioxide emission projected increase percent increased consumption oil natural gas coal developing asia expected account percent increase energyrelated carbon dioxide emission china india responsible half world increase energy consumption energy fuel economic growth clear eias assessment world energy picture nation increasing amount energy kind fossil energy source decade come public policy dilemma simple alter trend line accelerate renewable energy decelerate growth fossil fuel eventually reduce quartercentury single solution question government variety tool deploy order influence energy consumption corporation individual nation work began colleague sheldon kamieniecki student matthew cahn number year ago discussed strategic approach regulation detailed variety mechanism government influence behaviour work rejected idea needed choose market mechanism command control regulation instead viewed tool regulatory influence ranged highly coercive noncoercive method influencing behaviour adopt command control rule require individual behave way work traffic light speed limit failed miserably prohibition era made alcohol illegal influence behaviour pay people organisation specific thing give grant funding university conduct research area move scientific work area scientist alter research agenda lab intact food family table variety tax code provision influence behaviour federal income tax deduction mortgage interest property tax encourage home ownership favourable tax treatment renewable energy encourage installation home solar energy equipment oil depletion allowance encourage oil exploration production order change daunting trend line presented energy information agency analysis pursue path replace fossil fuel renewable energy reject idea setting price carbon magic bullet spark transition question feasibility united state time however recognise place time tool influence true command control regulation form tax complying rule raise price product increased cost product viewed indirect tax transition renewable energy behaviour limit change open individual example live manhattan rent apartment roof solar installation building owner control energy source heat hot water park car garage onehalf mile apartment garage include couple electric charging station use summer home long beach york small bungalow narrow street garage parking space located home short incentive buy electric car instal solar energy main residence summer home host solar array renovation required hurricane sandy solar wait excuse your way matter face institutional financial psychological barrier changing behaviour policy perspective question alter calculus drive behaviour encourage landlord homeowner instal energy efficiency renewable energy technology make electric car charging station plentiful convenient tax building code useful rule regulation helpful grant programme pay local government instal public charging station instantly effective part current problem technology itself car hold charge thousand mile hundred fifty convenient gasolinefueled auto charging minute hour people buy electric car electric car cheaper conventional car people buy them solar array size window patio deck people instal them price technology down adoption grow well improved technology unimaginable require massive amount basic applied research commercially viable world economy good adopting utilising technology recent cell phone billion planet fully integrated live imagine similar technological development commercialization process applied solar energy smart phone transformed live renewable energy breakthrough alter future planet breakthrough policydriven incentive alter trend line projected energy information agency hastening transition renewable energy economy difficult feasible task steven wolfowitz say effort increase energy efficiency solve number global energy problem technology recycle captured fossilfuel fired power station furnace repeatedly developed year proven regensburg university bavaria germany recently dumped wastefully pollutingly atmosphere converted back building block fossil fuel repeatedly recycled waste reducing fossil fuel etc thermodynamic requirement provided resource power station processe conversion easily accomplished mean patented equipment condition inexpensive control system detailed large scale rollout plant rapidly implemented authority commanding resource necessary widespread benefit including vast employment opportunity global warming climate change improvement fossil fuel reduction redistribution oilwealth delay ice age eliminate specy etc expected result robert bernal say number paragraph are indeed deppressing wait magic machine needed build solar wind main component storage planet fry again justtotally deploy advanced nuclear timeframe year redevelopment year preliminary phase year exponentiating deployment world fully developed ready step human evolution seek purpose continue learning and obey rule physic deny nature deny ourselve living city areoverkill intended horse buggy thetwo dimensional domination land create stress anger colonise space god willing conservation efficiency solar wind fact predominately nuclear powered world compromising future confined fossil fueled box post comment rick engebretson say sincerely humble outreach perspective different share cautious optimism left fanciest science lab nmr proton magnetic resonance learn rural living changed briefly food energy asked believed gmo crop responded choice gmo crop greatly expand farm labour starve average age farmer old size farm huge cost complexity prohibitive fill need people rebuild vast underperforming agricultural areas instead demographic worsened relentless growth government taxe willful ignorance wing grease monkey love npr classical music station programming linux applicable fancy science push wrong fundamental particle proton make electricity fuel chemistry quickly relearn respect disappearing farm skill disappearing physic skill disappearing work skill disappear post comment job gibson say nuclear guy bloviate same cant scientifically impossible unimaginable engineer low density intermittent uncontrollable spinning reserve costly backup short life long nuclear life blah blah blah undoubtedly negative working noninnovative noncost reducing monopolistic utility contrary evidence first world wide renewable energy rate growing second people tapped extorted cartel monopoly bankster financecdos healthdontcare tptb third frankly big monster utilitynuclear not create healthy energy market dictate block innovation promoting research free market fool people timeafter while work anymore nuclear great source energy monopolistic utility military political big government string attached attached string make nuclear hamstrung worthless investment instance buy nuclear plant small investor wind solar ngchp battery storage efficiency paradox investor elsewhere fast bob meinetz say steven column reveal technical misunderstanding responsible drastic overestimation capability renewable energy solar array size window patio deck people instal them solar array size patio deck energy sunlight wide net cast efficiency continue improve gain between improved technology unimaginable improved technology unimaginable engineer imagination adept filtering day physic put forever reach charging minute hour people buy electric car transfer amount electrical energy required charge tesla minute safely require cable large arm physical limit adapting reality charging night work happen long hurdle transition renewable energy behaviour limit change open individual wisely stated inconsistent view solar energy electric car charging electric car average home consume hour electrifying transporation prove impossible insist relying meagre source energy sun wind smart phone transformed live renewable energy breakthrough alter future planet renewable energy practically power modern civilization put way technology teach squeeze blood rock roger rabbit say assumption assume africa continue abject poverty point act enter rapid development china done stage africa estimated people fossil fuel world today year higher year irrespective solar wind nuclear built post comment developed country top norway sweden burn capita developed nation usa germany japan norway sweden model replicable enormous capita hydro resource line france pretty fully decarb electricity generation lot oil gas coal movement country french type renewable electricity grid plausible nuclear wind plis curtailment movement french type type system electrification unfeasible ","m_szGeo1":"Norway","m_szSourceType":"source_industry","m_szSrcUrl":"http://www.theenergycollective.com/stevenacohen/2116951/transition-renewable-energy-difficult-feasible#comments","m_Places":["United States","London","Asia","India","Manhattan","Long Beach, New York","Regensburg University","Bavaria","Germany","Mn","Tesla","Africa","Norway","Sweden","Usa","Japan","France"],"m_People":["Justin Doom","Sheldon Kamieniecki","Matthew Cahn","Steven Wolfowitz","Robert Bernal","Rick Engebretson","Steven","Roger"],"m_Companies":["Cleantech","Information Agency","Oecd","Organization For Economic Cooperation And Development","U.s. Government","Intact","Certain Times","Regensburg University","Indeed","Npr","Linux"],"m_BiGrams":["renewable energy","fossil fuel","electric car","energy information","information agency","energy consumption","transition renewable","solar energy","solar array","united state","world energy","energy source","carbon dioxide","trend line","influence behaviour","command control","charging station","buy electric","people buy","array size","patio deck","improved technology","technology unimaginable","solar wind","post comment"],"m_TriGrams":["energy information agency","transition renewable energy","buy electric car","solar array size","improved technology unimaginable"],"m_SocialTags":[],"m_Topics":[],"m_Industry":[],"m_Technology":[],"m_BiCnt":[17,9,7,6,5,4,4,4,4,3,3,3,3,3,3,3,3,3,3,3,3,3,3,3,3],"m_TriCnt":[5,4,3,3,3],"m_iDocBodyWordCnt":1323}
