{"m_szDocID":"531179","m_szDocTitle":"China and Solar Industry Growth | The Energy Collective","m_szYear":"2013","m_szDocSumamry":"1 Posted December 11, 2013 Keywords: Electricity , Energy Security , Tech , Solar Power , Sustainability , Utilities , Efficiency , Cleantech , Renewables , China , Energy and Economy , Fuels , News , china solar , industry growth   Chinese state news has announced that the country’s on-grid solar power capacity will reach 10 GW by the end of 2013, a 200% increase from a year ago, based on figures forecast by the National Energy Administration. The total energy generation capacity of the Chinese power grid is expected to reach 1,235 GW by the end of this year, with solar’s 10 GW making up an e","m_szDocBody":"posted keyword electricity energy security tech solar power sustainability utility efficiency cleantech renewable china energy economy fuel new china solar industry growth chinese state new announced country ongrid solar power capacity reach end increase year ago based figure forecast national energy administration total energy generation capacity chinese power grid expected reach end year solar making estimated growth hydro expected make grid wind nuclear state new agency xinhua noted china number measure including increasing investment clean energy boost share nonfossil fuel power structure npd solarbuzz projected year china top deployment predicting combined demand china japan expected reach half record level shipment china japan coincide corporate margin returning positive territory final shakeout phase uncompetitive manufacturer nearing completion finlay colville vice president npd solarbuzz entered highly cautious outlook tierone supplier poised exit year restored confidence ahead optimistic shipment margin guidance year china stated intended add solar power year year boosting coutnry solar capacity china recently announced intended stretch distributedsolar capacity target time date latest electric vehicle insight new closely watching solar power channel subscribing solar power newsletter ","m_szGeo1":"China","m_szSourceType":"source_industry","m_szSrcUrl":"http://www.theenergycollective.com/joshshill/314226/china-s-installed-pv-reach-10-gw-end-year#comments","m_Places":["Japan"],"m_People":["Finlay Colville"],"m_Companies":["Cleantech","Energy Administration","Xinhua","Npd","Target"],"m_BiGrams":["solar power"],"m_TriGrams":[],"m_SocialTags":[],"m_Topics":[],"m_Industry":[],"m_Technology":[],"m_BiCnt":[5],"m_TriCnt":[],"m_iDocBodyWordCnt":174}
