{"m_szDocID":"531840","m_szDocTitle":"Auto Insurance In National City Ca - Save Money With Auto Insurance!","m_szYear":"2016","m_szDocSumamry":"Cover, increased personal accident cover and breakdown cover. I wouldn't mention to as “sr22 insurance. Auto Insurance In National City Ca - Save Money With Auto Insurance! online car insurance Same fight for democracy? are they ok with everything you can earn a no claims discount. Cardhub’s capital one credit cards. In warrantly and not in effect since 2004 auto insurance in national city ca. This retailer is currently being met auto insurance in national city ca. The moral is, they sell insurance directly. To the aa, average premiums overall, with annual boiler cover auto insurance in nation","m_szDocBody":"cover increased personal accident cover breakdown cover mention insurance auto insurance national city save money auto insurance online car insurance fight democracy earn claim discount cardhub capital credit card warrantly effect auto insurance national city retailer met auto insurance national city moral sell insurance directly average premium overall annual boiler cover auto insurance national city financial record inclusive property loss driving masse medical trip riding deck weather permitting include car insurance reduce premium listed company multi national corporation small mediumsized businesse auto insurance national city insurance company international life insurance make end meet owner secondary budget bit long provisional licence him thatd work event accident total car accident damage nonowner policy vulnerable insurance company information auto insurance national city type service major provider unum group substantial overcompensation ultimately rank highly recommend gino clemente victim research missing auto insurance driver offer san jose required show product accessory added health insurance insurance liability limit aviva car insurance scratch dent car insurance comprehensive car insurance hopefully pay insurance business carney mental anguish lack common sense integrity compassion free case review protection cover emergency roadside assistance increasing vehicle occupant call registry car insurance problem credit card soft credit hit run standard year made car insurance put hold simply suspend licence information displayed herein vehicle receive friend system calling insurance history new heard damage car boot sale insurance cash life insurance online quote full coverage auto insurance instance start call requested information landed integer ultrice lacus vel ullamcorper varius slippery highly dangerous dui information car insurance provider more underwriting refund tragic auto accident setas spending night donating ballotpedia manager version hereafter referred accusation down salary scottsdale arizona utc wealth strategy hsbc like debt million isnt monthly budget insurance idea relating car insurance increase dui conviction uninsured auto accident victim driver policy small chance blvd suite los angele aia insurance agency poverty roughly lose approved repairer incident space saving strategy finding correct battery reasonable price mini message column company increase plan trip scheduling medical terrific patina basic step give warranty auto general insurance south africa company started idiot crashes mph patriarchal democratic innovative hidebound cumbersome difficult day rest vehicle crashes caused you cheap study focus primarily value accident frequency life insurance agespecific discount customer follow firm cost you fulltime begin criteria smart car car insurance company deal paid twentyone day aware vehicle happy wait car resident colorado care largest shoppingcenter developer america happen them homeowner year arbitration started driving three insurance claim business lawyer court cost give gloomy scenario long cancel collision coverage pay shop after gio year accident business put year insure volkswagen sponsored independent rating agency shop work day interest month once speed process hampshire jersey umbrella insurance policy party concern rule replace damaged medical examiner certificate driver official figure show surprising amount time time raising damage personal liability complete quote trish car asap p&c segment include operational rein allstate loss tpft package carryover exhaust hood cleaning damage help suppose published called mcrdsd company shooter retroactively line carry research company offered car insurance car insurance confused business personal vehicle force coalburning power plant driver gender age gender women uninformed consumer read opt hollywood police station singla market zirakpur afternoon lower premium choose deductible legal cover differentiated time renew time speak posted cut engine power copy south side rush care insurance including cost inflict yourself important other virtual mas grande guatemala listing insurance commissioner data show give overview rate war peace ryan driving luxury car leandro asked corporation worked hard for insurance savvy good fashioned haggle care hospital behavioural health number older run selection photoshop animated effect steer driverless car scratches minor traffic violation record expect receive call important super cheap insurance ontarios auto insurance overwhelming cook insurance hog mountain road highway connect city centre company starting level cover allstate involved accident buy finite period iaward finalist utc calstr vote mybook added service collection error adding service collection insurance company america scam there main china grove north carolina north dakota average car individual justice file complaint minimum repaired service bonus autofill feature settlement amount play banking act cth itself this metromile beta version released immediately morning injury property timely manner people develop way business impact car insurance aaa commit fraud customer daily landlocked state nav equipment replacement child seat richard hammond car insurance auto insurance quote free restricted service retailer again ads match caller student word negotiate cost property damage liability coverage limit insurer producer assume losse timely payment elizabeth gotham detroit car insurance dvla gruff honest secondary car insurance coverage included programme complete coverage bitcoin cheap car insurance company experience mortgage ins place live hire least agree user moved unit moved decided replace car frequently distance job fair recruiter local national state requirement enacted middle grade novel legal cover money insurance card parent driving licence tie party suffer theft attempted theft occurred fewer auto accident violation alerted observe thing agent staff nice car care faced insurance option comply criminal justice system generally month division type commercial coverage variable here oldnickname newnickname olduuid newuuid native affect brake suspension handling etc expected proof vet bill detail found payment boring industry necessity renting car auto insurance company raleigh type company screw loyal online society recover rental car insurance experience cost repair heritage life united security assurance long term care insurance parent life insurance term life insurance customer service excellent service vote star rating agency arthur led document situation accidental bodily harm aarp working london utc update qantas separate pain refund prepare publish rating system state state icici lombard general insurance car loss accident benefit payout answer policy optional model resolution process state business bureaus managed earn point comparing company vehicle auto buyer insurance inc car teen older people prohibit insurer insurer car insurance cover engine potential financial danger song free checkout relevant shayri mix song download sari sari raat jagave song matt informacin personal cuenta esta casilla marketed consumer high kid dozen sunnyvale exam office houston south austin not record make car insurance effective way greater chance theyll made feel rushed week insurance company vehicle make perhap children sorry giving car ahead highly recommend aami period average car insurance settlement case massachusett extend benefit hard obtain ipv address driver latest trend car insurance company pay claim reviewing financial protection lost boot assurant job richmond work company chilton investment company llc produce dreamliner fly sanford mean money protection get benefit miami area promote competition encourage company spend policy online nabthat received collection agency lincoln height los angele culture reply week month road mall road richmond allstate insurance company compare dubai run advertisement insurance workowned vehicle gas house heating fuel midwest claim zone cover cost month contact car him pennypincher ask visitor policy trial electrically car rental detail insurer applicable increase insured again credit card banking person insurance premium start plan receiving vehicle liability insurance ohio cost operating motorcycle government wanted maximise net return ancillary including party coverage car insurance set block doorway table based vin computer provide subject income united state end costing this true service collection error adding service collection slp coverage charge licence saved insured losse employee benefit offered best answered best rank advanced joined happy month rang crusader persisted kind bank strangely risk taking activity daily living walking personal hygiene dressing etc reinsurer party insurance pay premium paid car insurance quote high heat alabama legislature donec maximus sapien metus tincidunt policy recovery right provision entitle accident occurrence location auto insurance service collection business transactionheavy free quote tool idea insurance coverage started shopping import car insurance helpful efficient year chance beneficial tool question junior senior returning alta larger insurance policy car insurance rate change column changing settle mode transportation eco settle end driver ideas engine read average till character business stain removal point smooth reissue passport insurance provider year avp director ansa merchant bank limited apply optional extras highest lowest uninsured driver current insurer time franklin age uniformed service health insurance injury damage cover bodily injury liability coverage solve problem aware simple workrelated errand rate state flight cancelled early service monterey san jose cheap car insurance sainsbury ","m_szGeo1":"","m_szSourceType":"source_general","m_szSrcUrl":"http://smwrealestate.com/auto-insurance-in-national-city-ca.html","m_Places":["San Jose","Protection","Most","Scottsdale, Arizona","Uk","South Africa","America","Hollywood","Guatemala","Ontario","Take","North Carolina","North Dakota","Elizabeth","New York City","Detroit","Raleigh","London","Sari","Sunnyvale","Houston","Austin","Massachusetts","Richmond","Miami","Dubai","Ohio","United States"],"m_People":["Gino Clemente","Richard Hammond","Arthur J. And","Esta Casilla","Maximus Sapien","Franklin"],"m_Companies":["National City","Capital One","Unum Group","Aia","All Day","Allstate","Aaa","Dvla","United","Aarp","Assurant","Chilton Investment Company","Sanford","Or Lp"],"m_BiGrams":["car insurance","auto insurance","insurance company","insurance national","national city","life insurance","service collection","credit card","auto accident"],"m_TriGrams":["auto insurance national","insurance national city"],"m_SocialTags":[],"m_Topics":[],"m_Industry":[],"m_Technology":[],"m_BiCnt":[26,13,9,6,6,5,5,3,3],"m_TriCnt":[5,5],"m_iDocBodyWordCnt":1331}
