{"m_szDocID":"534574","m_szDocTitle":"Truck GPS Resources | Tips and advice for fleet managers and truck drivers","m_szYear":"2016","m_szDocSumamry":"Truck GPS Resources Tips and advice for fleet managers and truck drivers Twitter Search for: Whats the best truck GPS? 5 biggest dump trucks iPhone truck GPS? 5 dangerous truck jobs Used truck buying guide GPS Tracking Software – Buyers Guide October 27, 2015 admin Leave a comment GPS tracking software is growing in popularity with fleet owners as they discover the benefits, making better use of their resources – vehicles, drivers and mobile technicians. Frost and Sullivan report very real savings after deploying fleet management using GPS tracking. 25% decrease in fuel spend 30% reduction in ","m_szDocBody":"truck gps resource tip advice fleet manager truck driver for what truck gps biggest dump truck iphone truck gps dangerous truck job truck buying guide gps tracking software buyer guide admin leave comment gps tracking software growing popularity fleet owner discover benefit making resource vehicle driver mobile technician frost sullivan report real saving deploying fleet management gps tracking decrease fuel spend reduction unnecessary idling drop daily mileage increase asset utilisation saving auto insurance boost workforce productivity source benefit effective deployment fleet management system frost sullivan sort saving encouraging large number fleet owner purchasing gps fleet tracking increasing number provider popping offering variety gps tracking solution choice good choice make confusing buyer youre searching gps tracking software solution supplier starting bring headache what easy philtre supplier arent worth wasting time handy checklist question make youre gps tracking product solution achieve desired result future fleet grow meet challenge question provider gps tracking software architecture hardware older hardware limit option increase procurement cost prevent taking advantage cheaper android apple handheld device product release year frequent software release innovation quicker latest technology mobile app byod bring device allowing worker apple android device significantly lowering hardware cost fleet increasing adoption reducing training requirement iso accredited iso independent quality accreditation organisation system processe standard charge onboarding onboarding important part adopting fleet tracking software make return investment software run hardware locked hardware increase cost reduce flexibility limit feature access require additional hardware truck downtime cost additional hardware installed industry software designed for software flexible adapt industry cater specific industry customer support received award aftersale support important avoid minimise downtime touch truck activate larger fleet disruptive vehicle shop activated product financed part truck purchase financing software part vehicle purchase improve cash flow offer tax advantage see oem telematic below hardware company software company focus business determine effort dedicate improving software spend research development compliant eld hos mandate eld mandate requiring driver complete hour service paper logbook driving hour automatically tracked question particularly answer question determine quality solution company provide solution doesnt deliver even cheap solution fleet perform efficiently before delivering solid return investment question solution key purchasing product service knowing question ask gps tracking software solution fleet question quickly sort timewaster provider theyre deliver quality result gps tracking software doesnt aftermarket hardware gps tracking solution buy today require purchase expensive hardware expense mean downtime vehicle fitted good new manufacturer offering prewired installed option commercial vehicle builtin day one oem telematic mean activate vehicle online moment drive dealer yard youre benefiting gps fleet tracking oem telematic solution ford telematic offer additional benefit including richer data diagnostic tax advantage quickly preferred choice lot fleet owner gps tracking software worth fleet too fleet management what truck gps market admin comment gps truck critically important youre buy gps device truck realise buying standard gps youre truck driver special requirement unique challenge navigation important device work reliable doesnt lead astray missing destination costing time hitting fine driving restricted road total fleet management solution rush buy individual gps truck cheque total fleet management gps tracking solution telogis fleet isnt option business contact telogis directly advise commercial navigation device integrate management platform read gps unit top biggest dump truck admin comment truck big big truck past dump truck rule roost size height weight found working opencast mine world size apparent dwarfed larger digger crane small distance close personal start truck heavyweight trucking world people barely reach halfway tyre wall diesel engine weigh pound turbocharger arent average suburban shopping trolley read truck tpm stand for saving live admin comment tpm stand tyre pressure monitoring system compulsory vehicle year due stricter legislation vehicle safety system wake fatal accident involving significantly underinflated tyre benefit tpm recognised car truck maker vehicle manufactured equipped tpm standard equipment universallyrecognized alert icon appear thousand dashboard world giving driver easy tyre properly inflated important fleet owner advantage technology improve fleet safety fuel economy read maintenance trucking fleet fuel card plan admin leave comment question fuel precious commodity rising gas price make crucial trucking fleet carefully manage fuel acquired consumed fortunately technology making lot easier fleet owner control fuel purchase greater accountability reporting highlight areas attention switching fuel card programme manage monitor gas purchase read fleet management location intelligence truck driver scheduling admin comment joe run delivery business beverage company driver pay driver based number case deliver vary season case deliver low season rising peak month joe problem driver occupied evenly year round keeping operating cost minimum read routing hos ruling cut driver hour admin leave comment fmcsa released final ruling maximum number driving hour effort combat accident caused fatigued truck driver ruling month public consultation modification csa transportation secretary ray lahood announced final hos ruling basing latest research driver fatigue replacing existing fmcsa hoursofservice hos safety requirement commercial truck driver read fleet management truck oil price reach high truck driver stay profitable admin leave comment truck owner pay bill realise costly running truck multiply hundred surprising trucking fleet owner constantly keeping eye way reduce fuel cost oil price topping barrel recently pushed higher seasonal demand hint stability european financial market reminder truck owner fact freight industry fuel cost managed fleet single remain profitable read fleet management truck csa safer trucking admin leave comment year csa introduced carrier progressively rolled modified time make system workable government agency truck owner successful achieved aim compliance safety accountability expert industry warned danger receiving poor csa ranking affected fleet taking dangerous driver unsafe carrier road read fleet management truck electric truck fleet admin comment ongoing discussion converting commercial fleet electric vehicle company taking wait approach technology develop infrastructure establishes make viable option case smaller evs making progress isnt fast like heavy duty otr fleet converting ageing diesel truck electricity anytime soon read truck popular topic antienvironment truck gps beverage telematic brazil fleet management chile fleet management compliance crazy truck accident csa dangerous driving dangerous truck driving eco truck fleet optimization fmcsa freight act fuel efficiency gis data government fleet gps tracking gps unit truck driver green fleet green truck hazmat trucker load limit uturn oem software optimised driving optimised routing oversized load pretrip inspection reduce gas bill rising diesel price road restriction save fuel seasonal weight limit south america telematic tollway top website top tip truck driving job trucker resource truck height truck maintenance truck management tip truck route gps truck stupid question right word truck people large longhaul truck suvs commonly town chevy suburban toyota sequoia pickup truck flatbed back thinking lorry truckgpsorg mean thing commercial truck driver fleet manager face unique challenge challenge met gps technology truck gps turnbyturn navigation dispatching preventative maintenance monitoring mechanical health vehicle fleet manager truck secure operating efficiently fully utilised topic covered question gps work truck contact popular read truck gps market dangerous truck driver job truck gps iphone commercial truck buying guide top tip top biggest dump truck hour service eld electronic driver inspection report commercial navigation app ","m_szGeo1":"","m_szSourceType":"source_general","m_szSrcUrl":"http://truckgps.org/","m_Places":["Most","United States","Brazil","Chile","South America","Well","U.k."],"m_People":["Ray Lahood"],"m_Companies":["Twitter","Frost & Sullivan","Apple","Iso","What Industries","Telogis","Cranes","November 17","Diesel","Toyota Sequoia"],"m_BiGrams":["gps tracking","fleet management","truck driver","truck gps","tracking software","fleet owner","admin leave","leave comment","admin comment","dump truck","read fleet","fleet manager","biggest dump","dangerous truck","fleet tracking","tracking solution","oem telematic","gps truck","read truck","trucking fleet","commercial truck","management truck","truck owner"],"m_TriGrams":["gps tracking software","admin leave comment","read fleet management","biggest dump truck","gps tracking solution","fleet management truck"],"m_SocialTags":[],"m_Topics":[],"m_Industry":[],"m_Technology":[],"m_BiCnt":[13,11,9,8,8,6,5,5,5,4,4,3,3,3,3,3,3,3,3,3,3,3,3],"m_TriCnt":[7,5,4,3,3,3],"m_iDocBodyWordCnt":1138}
