{"m_szDocID":"554036","m_szDocTitle":"A Day In The Life Of A Model 3 Birth | CleanTechnica","m_szYear":"2016","m_szDocSumamry":"A Day In The Life Of A Model 3 Birth March 31st, 2016 by Zachary Shahan   I rolled into Los Angeles at 1:00am on March 31, catching sleep on the flights from Frankfurt to DC and DC to LA in order to be rested for an early arrival at a Tesla store in time to put down an early Tesla Model 3 reservation (or 4). Meeting Kyle Field at the Santa Monica Tesla store at about 6:30am, we found ourselves in a decent spot in the line. We were able to put down reservations for 2 cars each, which seemed to be numbers 41, 42, 43, and 44 at this location. A cool surprise walking up was immediately spotting Pa","m_szDocBody":"day life model birth zachary shahan rolled los angele catching sleep flight frankfurt order rested early arrival tesla store time put early tesla model reservation meeting kyle field santa monica tesla store amwe found decent spot line put reservation car each number location cool surprise walking immediately spotting paul scott founding member plug america legendary advocate there zan dubin scott work communication line plug america number cleantech company spent time interviewing people line couple guysarrived hour early interviewed paul founding plug america board member enthusiast alaska people front line putting reservation spotted bjorn nyland founder tesla motor club norway official tesla motor club spent time interviewing them left bjorn spend quality vacation time wife him line santa monica reached people time leftnot shabby spending hour there heard elon musk century city store apparently putting reservation people give five stream people lined store wemissed big guy enjoy epic line tesla model reservationist nice outdoor eating coffee area beautiful california weather time spare shot fiat dealer test drive place world one fun drive storey day drove kyle model unplugged performance toured founder ben schaeffer unplugged performance site tesla design studio spacex hosting bbq event model unveiling projected large screen watching moment turn coverage kyle field standing feverishly typing away cleantechnicas completely free electric car report electric car early adopter follower want attend cleantechnicas cleantech revolution tour event berlin germany date hottest cleantech new subscribing free cleantech newsletter eye sectorspecific new also free solar energy newsletter electric vehicle newsletter wind energy newsletter tag bjrn nyland elon musk paul scott plug america tesla tesla model unplugged performance zachary shahan tryin and specy letter time spend time cleantechnica director chief editor otherwise enthusiastically fulfilling duty obsession gas solar love planetsave bikocity president important media zach recognised globally solar energy electric car energy storage wind energy expert speak related conference event connect social media zacharyshahancom related post bright vlogger test model doorclosing sensor hand bolt bolted bolt better simply scaling work understood compare interior joe viocoe volt model youre entitled opinion this subjective minority bobwallace battery pack size supercharging included total win huge boost number destination charger mile range possibly fewer mile current scs autopilot capable turn fee long doesnt cost fortune huge number preorder number bolt expect sell year friggin internet provider presentation started crap missed entire presentation wondering missed wise mirai think steve grinwis dont front doesnt somehow side top gorgeous jamset flat portion front ugly porsche car philip understood car autopilot activated pay additional watch presentation youtube online think vensonata car front centre musk staggering infrastructure double supercharger year quadruple destination charger creating entire ecological system animal called electric car store proliferating rabbit moderate sized city purchase service course left hanging higher base model end range stay tuned part two expect reference kwh tesla model space kind announcement good stock price rawlasvegan exciting historic day sharing experience forward reading event article cubanx standard witnessed deathblow ice auto industry tonight styling wasnt car dream didnt dislike chevy bolt chance leaf reservation hour car steve grinwis elon put automotive industry notice year shit wuestenblitz automaker scratching head wondering tesla pulled preorder off list long top are electric stupid ota update money robbing macherdealershipsthat endure steve grinwis top performance base model faster camaro owned range wife suv tank pretty much utility trunk lot interior room doesnt silly model gimmick about yet styling better knetter didnt hard eye front grill side thought looked partial flat grey one dont forget order reveal fast charging utility decide steve grinwis range expected ground breaking good new fast charging huge jamset free hvdc charging people avoid charging home save full charge bobwallace sounded free price built supercharger access dont tesla deal overuse problem them charge local scs expect taxis fast tesla build them bobwallace mile electricity commercial day charging day taxis charge limit people ride taxis day reasonable advertising expense steve grinwis fine year year dont taxis costing year supercharging fee theyll prevent this elon smart guy theyll out bobwallace year tesla solar farm cousin electricity costing lot less theyve time actual data found allowing owner charge lot offset charge enquiring mind know steve grinwis data jamset make mistake free supercharging biggest mistake musk made jamset make pay service supercharger code phone scan code pay electricity steve grinwis dont theyll deal supercharger overruse car supercharging wuestenblitz comprise style aerodynamic room curious higher end model bet faster steve grinwis dont teeth view side top shot great interesting ended awful lot volt prius insight though hatchbacky style steve grinwis car isnt pretty model stat sound amazing dash looked odd production final important base model car great car ross good paying lot added option fun steve grinwis agree performance version car though point buying beat camaro straight line knetter car price agree dash looked strange hoped wasnt final hud dont infotainment screen car vital safest idea bill kalahurka showed store line weather great counted people line time still rare part awesome tesla day ","m_szGeo1":"United States","m_szSourceType":"source_industry","m_szSrcUrl":"http://cleantechnica.com/2016/03/31/a-day-in-the-life-of-a-model-3-birth/?utm_source=feedburner&utm_medium=feed&utm_campaign=Feed%3A+IM-cleantechnica+%28CleanTechnica%29","m_Places":["Los Angeles","Frankfurt","Tesla","America","Alaska","Norway","California","Kyle","Berlin, Germany","Ota"],"m_People":["Zachary Shahan","Paul Scott","Zan Dubin","Bjorn Nyland","Santa Monica","Elon Musk","Ben Schaeffer","Bjørn Nyland","Joe Viocoe","Steve Grinwis"],"m_Companies":["Spacex","Volt","Youtube","Hud"],"m_BiGrams":["steve grinwis","plug america","electric car","tesla model","unplugged performance","grinwis dont","base model"],"m_TriGrams":["steve grinwis dont"],"m_SocialTags":[],"m_Topics":[],"m_Industry":[],"m_Technology":[],"m_BiCnt":[10,4,4,3,3,3,3],"m_TriCnt":[3],"m_iDocBodyWordCnt":819}
