{"m_szDocID":"556597","m_szDocTitle":"66% Of Germans Would Consider A Tesla Model 3, According To Poll","m_szYear":"2016","m_szDocSumamry":"66% Of Germans Would Consider A Tesla Model 3, According To Poll Originally published on EV Obsession. Despite the strong bias that most German citizens have for German-made cars, it appears that the Tesla Model 3 unveiling has made quite an impact on the public there. A new poll from the German car magazine Autobild found that 66% of those queried said that they would consider buying a Model 3. While that may not sound like a substantial percentage, for a country as insular (in many ways) as Germany, thatâ€™s really quite impressive. Especially when considering that many of the top sellers on t","m_szDocBody":"german tesla model poll originally published obsession strong bias german citizen germanmade car appear tesla model unveiling made impact public there poll german car magazine autobild found queried buying model sound substantial percentage country insular way germany impressive top seller international auto market made german brand guess exec bmw mercede audi starting feel heat germany cash cow slaughtered shipped america all teslarati that recent unveiling tesla model daimler shareholder feeling defensive company annual meeting berlin wednesday pointed question management ingo speich portfolio manager union investment capital market concerned fat year premium german car maker over automobile industry radical upheaval driven attack silicon valley financial time shareholder wanted daimler counter pressure build electric car spearheaded tesla dont product competition tesla long term great vehicle virtual point shareholder pointed out worried company answer model reason that asked ceo daimler dieter zetsche commented company working plugin hybrid phev vehicle expected company working longrange allelectric car released end decade notably daimler share considerably bmw share reprinted permission cleantechnicas completely free electric car report electric car early adopter follower want attend cleantechnicas cleantech revolution tour event berlin germany date hottest cleantech new subscribing free cleantech newsletter eye sectorspecific new also free solar energy newsletter electric vehicle newsletter wind energy newsletter tag germany tesla model jame ayre background predominantly geopolitic history obsessive interest pretty everything early life spent imperial free city dortmund jame river ruhr cofbuokheim attended university astnide briefly considered entering coal mining business write living broad variety subject ranging science politic military history renewable energy follow work google related post tesla answer model question eric wadge love tesla revolution happen major car brand start suit tempting tesla knight shining armour car company worthwhile vehicle electrification but wanted objective wed major car brand teslas footstep started putting big million evs certainly tesla entrepreneurial vision however whilst tesla possess massive resource car company possess saddled legacy ice product devote creating evs can spend limited resource creating charging network etc reason existing pushing evs place ice vehicle brainer bmw mercede tata started leverage considerable financial muscle push evs ice car now arent simply dumb dont occurred them nissan produce selling leaf spent considerable effort concerned pushing ice vehicle shareholder about argue social conscience fair enough unlike tesla major car brand ice vehicle business run maintain feeling dont care sell evs ice vehicle care bottom line pretty costing conclusion moment time bottom line dictate bigger bang buck investing billion dollar generation suvs creating charging network when customer start abandoning ice vehicle favour electric card bet move evs full force tipping point wait bmw mercede race build hatchback longer range however ceo suggest brand spend evs big seller range fired unfortunate reality time tesla ice business good them goodness tesla role popularising electric vehicle wouldnt quick dismiss brand though dont stupid binding time reading market core business market bring change let hope sooner later respect legislator major role play europe legislator succeeded simply power incentive push share diesel petrol roughly incentive employed transition ice electrification vehicle omar hit evaporate freddy bam spend time germany working studying hanging citizenry significance headline now time smug however model price now model wont order pipeline cleared year automaker earth abruptly woken loud achtung daimler bmw audi big watch however seemingly invincible confidentinthemselve toyota honda owned top selling model year now comfortable reason move imagine detroit well detroit thier market wont threatened offering pickup midsize large suvs frank teslas secret plan working little tesla thing quality good enough ramp car year car year asap totota hondas attention plan ahead time there building buying building car plant tesla year champion dna bobwallace phev pickup coming detroit gms bolt move evs detroit ahead japan martin born germany surprise lot german quality pay force car maker board speak share holder exert lot power tesla secret good elon musk ","m_szGeo1":"United States","m_szSourceType":"source_industry","m_szSrcUrl":"http://cleantechnica.com/2016/04/11/66-of-germans-would-consider-a-tesla-model-3-according-to-poll/?utm_source=feedburner&utm_medium=feed&utm_campaign=Feed%3A+IM-cleantechnica+%28CleanTechnica%29","m_Places":["Tesla","Germany","America","Berlin","Silicon Valley","Berlin, Germany","Free City","Dortmund","Europe","Bam","Toyota","United States","Detroit","Well","Japan"],"m_People":["Ingo Speich","Dieter Zetsche","James Ayre","Eric Wadge","Even Nissan","Elon Musk"],"m_Companies":["Guess","Bmw","Audi","Union Investment","Financial Times","University Of Astnide","Google","Revolution","Diesel","Achtung!","Honda","Ramp"],"m_BiGrams":["ice vehicle","tesla model","bmw mercede","electric car","major car","car brand"],"m_TriGrams":["major car brand"],"m_SocialTags":[],"m_Topics":[],"m_Industry":[],"m_Technology":[],"m_BiCnt":[5,4,3,3,3,3],"m_TriCnt":[3],"m_iDocBodyWordCnt":631}
