{"m_szDocID":"589145","m_szDocTitle":"Hydrogen Hurdles: Hydrogen-powered Car Makers Suffer from High Prices, Lack of Infrastructure | BusinessKorea","m_szYear":"2016","m_szDocSumamry":"28 May 2015 - 12:15pm Jung Min-hee The big two auto makers that seek to dominate the hydrogen-powered car market, Hyundai Motor and Toyota, are struggling to expand supply.   Even though hydrogen-powered vehicles have enough potential to be called the “ultimate eco-friendly car,” they have difficulties in spreading due to high cost and a lack of proper infrastructure. In particular, Hyundai Motor is suffering more because of less government funding in comparison with Japan. According to industry sources, Toyota currently sells the Mirai fuel cell vehicle at a price of US$57,500 (62.34 million ","m_szDocBody":"jung minhee big auto maker seek dominate hydrogenpowered car market hyundai motor toyota struggling expand supply hydrogenpowered vehicle potential called ultimate ecofriendly car difficulty spreading due cost lack proper infrastructure particular hyundai motor suffering government funding comparison japan industry source toyota sell mirai fuel cell vehicle price million won expensive average mediumsized sedan leasing mirai consumer pay won month based price time higher toyotas corolla hyundai motor sell tucson million won domestic market company lowered price percent previous price million won however individual customer purchase model receive subsidy government tucson price won month deposit million won market research firm city research said hydrogenpowered vehicle lower price competitiveness internal combustion locomotive gap wider due prolonged low oil price they including mirai influence auto market hydrogen vehicle vehicle generate electricity reacting hydrogen oxygen fuel cell motive power emit exhaust gase pollutant water vehicle considered ultimate stage evolution ecofriendly vehicle releasing tucson hyundai motor established mass production system hydrogen vehicle time world korean government encouraged company dominate related market advance presenting green car development road map led birth world hydrogen vehicle korea however concrete development plan year then obstructing supply expansion state funding year dropped million won million million won million million won million year moreover plan expand hydrogen energy station year proper infrastructure fair consumer buy hydrogen vehicle estimated company sold car tucson home abroad year half official hyundai motor said build infrastructure not hard expect tucson model sell market price million won effective competition system established longterm expansion infrastructure government support related market formed toyota similar worry situation korea japanese government support million yen million million won hydrogen station subsidy currently private station japan country plan supply million hydrogen car government subsidy million won unit official industry said north american market fierce competition release honda fcx clarity model fiat chrysler korea lose hydrogen vehicle market electric vehicle market hard country secure competitiveness future ecofriendly vehicle sector category ","m_szGeo1":"Japan","m_szSourceType":"source_news","m_szSrcUrl":"http://www.businesskorea.co.kr/english/news/industry/10768-hydrogen-hurdles-hydrogen-powered-car-makers-suffer-high-prices-lack","m_Places":["Toyota","Japan","Corolla","Tucson","Korea"],"m_People":["Jung Min-hee","Fcx Clarity","Chrysler"],"m_Companies":["Hyundai","City","Gap","Honda"],"m_BiGrams":["million won","hyundai motor","hydrogen vehicle","price million","won million"],"m_TriGrams":["price million won"],"m_SocialTags":[],"m_Topics":[],"m_Industry":[],"m_Technology":[],"m_BiCnt":[7,5,5,3,3],"m_TriCnt":[3],"m_iDocBodyWordCnt":316}
