{"m_szDocID":"589174","m_szDocTitle":"Hyundai Tucson Hydrogen Fuel-Cell Vehicle Enters Production","m_szYear":"2013","m_szDocSumamry":"Hyundai Tucson Hydrogen Fuel-Cell Vehicle Enters Production Email This Page To (separate emails with commas) Message (optional) Your email was sent successfully. Close 37 3,184 views Feb 28, 2013 Follow Antony Enlarge Photo Fuel cell vehicles have been garnering more attention recently, with the high-profile agreements between Toyota and BMW , and Renault-Nissan, Daimler and Ford . Not yet ready for the mainstream, fuel cell vehicles have so far been restricted to limited-run production models like the Honda FCX Clarity. Korean giant Hyundai now has its own fuel cell production vehicle, and th","m_szDocBody":"hyundai tucson hydrogen fuelcell vehicle enter production separate email commas message optional successfully close view follow antony enlarge photo fuel cell vehicle garnering attention recently highprofile agreement toyota bmw renaultnissan daimler ford ready mainstream fuel cell vehicle restricted limitedrun production model honda fcx clarity korean giant hyundai fuel cell production vehicle hydrogen tucson crossover started rolling production line fuel cell tucson market developed fleet use europe budding hydrogen network make car practical hyundai working fuel cell vehicle year put hundred million dollar project million mile testingso tucson fuelcell real deal company build example making true massproduced fuel cell vehiclealbeit sell small number tucson fuelcell hydrogen tank pressurised bar storing kilogramme hydrogen pound efficiency rating kgh kilometre tucson approximately mile fill battery employed energy storage electric motor powering car second mph sprint top speed mph join carmaker blue drive subbrand include car sonata hybrid hyundai ibased blueon chevy sparksized electric car sold korea big automaker signed technology agreement develop future fuel cell technology korean brand make true production fuel cell vehicle ","m_szGeo1":"","m_szSourceType":"source_news","m_szSrcUrl":"http://www.greencarreports.com/news/1082609_hyundai-tucson-hydrogen-fuel-cell-vehicle-enters-production","m_Places":["Toyota","Tucson","Europe","Korea"],"m_People":["Fcx Clarity","Chevy Spark"],"m_Companies":["Bmw","Renault","Honda","Hyundai"],"m_BiGrams":["fuel cell","cell vehicle"],"m_TriGrams":["fuel cell vehicle"],"m_SocialTags":[],"m_Topics":[],"m_Industry":[],"m_Technology":[],"m_BiCnt":[8,4],"m_TriCnt":[4],"m_iDocBodyWordCnt":170}
