{"m_szDocID":"589170","m_szDocTitle":"Fuel-Cell 'Compliance Cars,' Faraday Future, Bob Lutz On VW: Today's Car News","m_szYear":"2015","m_szDocSumamry":"Fuel-Cell 'Compliance Cars,' Faraday Future, Bob Lutz On VW: Today's Car News Email This Page To (separate emails with commas) Message (optional) Your email was sent successfully. Close 2,998 views Nov 6, 2015 Honda Clarity Fuel Cell, 2015 Tokyo Motor Show Enlarge Photo Today, see why all hydrogen fuel-cell cars are really \"compliance cars,\" Faraday Future's plans for a $1 billion electric-car factory, and why Bob Lutz thinks the Volkswagen scandal will kill off \"clean diesel\" as a marketing concept. All this and more on Green Car Reports. See what effect the launch of the second-generation Ch","m_szDocBody":"fuelcell compliance car faraday future bob lutz today car new separate email commas message optional successfully close view honda clarity fuel cell tokyo motor show enlarge photo today hydrogen fuelcell car compliance car faraday future plan billion electriccar factory bob lutz think volkswagen scandal kill clean diesel marketing concept green car report effect launch secondgeneration chevrolet volt plugin electric car sale canada clean diesel dead general motor product czar bob lutz response volkswagen emission scandal mysterious electriccar startup faraday future spend billion factory car plan launch company location california georgia louisiana nevada hydrogen fuelcell car compliance car least break teslas unusual relationship lack thereof legacy automotive press lexus comfortable building car china finally tesla constrain autopilot system response videos showing nearmisse making round online ","m_szGeo1":"Canada","m_szSourceType":"source_news","m_szSrcUrl":"http://www.greencarreports.com/news/1100812_fuel-cell-compliance-cars-faraday-future-bob-lutz-on-vw-todays-car-news","m_Places":["Tokyo","Canada","California","Georgia","Louisiana","Nevada","Tesla","China"],"m_People":["Lutz","Honda"],"m_Companies":["Faraday","Volkswagen","Diesel","General Motors"],"m_BiGrams":["compliance car","faraday future","bob lutz"],"m_TriGrams":[],"m_SocialTags":[],"m_Topics":[],"m_Industry":[],"m_Technology":[],"m_BiCnt":[3,3,3],"m_TriCnt":[],"m_iDocBodyWordCnt":124}
