{"m_szDocID":"589164","m_szDocTitle":"For Hydrogen Fuel Cells, Blue Is The New Green | CleanTechnica","m_szYear":"2014","m_szDocSumamry":"For Hydrogen Fuel Cells, Blue Is The New Green January 14th, 2014 by Tina Casey   A team of researchers at Argonne National Laboratory has figured out an efficient way to split hydrogen gas from water, using a low cost cobalt-based catalyst instead of pricey platinum. Hmmm, well, we were just wondering when hydrogen fuel cell electric vehicles would start nudging ahead of plug-in EVs in the race for market share, and guess what: that’s not going to happen real soon, but the Argonne breakthrough demonstrates that it could happen sooner rather than later. While the media spotlight has been turne","m_szDocBody":"hydrogen fuel cell blue green tina casey team researcher argonne national laboratory figured efficient split hydrogen gas water low cost cobaltbased catalyst pricey platinum hmmm well wondering hydrogen fuel cell electric vehicle start nudging ahead plugin evs race market share guess what happen real soon argonne breakthrough demonstrate happen sooner later media spotlight turned plugin electric vehicle year tesla much evs powered hydrogen fuel cell lingering shadow change cost fuel cell fuel trend steadily downward cobalt blue wikimedia cheap hydrogen for now hydrogen ideal fuel massive market evs water problem usable form require enormous amount energy sun provide energy cheap adding carbon burden environment photochemical process mimic step natural photosynthesis see daniel noceras artificial leaf that sun water though catalyst low cost catalyst drive photosynthetic reaction efficiently national institute standard technology nist promising drive cost cut amount platinum needed efficient reaction argonne fuel cell approach approach eliminating platinum completely favour cobaltcontaining compound cobalt road low cost hydrogen cobalt efficient catalyst platinum cheaper attraction researcher argonne writer jared sagoff note cobalt explored catalyst efficiency angle hard nut crack research team argonne achieved breakthrough identifying link catalyst chromophore organic lightsensitive molecule typical cobalt catalyst chromophore connected directly cobalt atom compound lead unstable form hydrogen generation process eventually break down lot stimulated electron shift excited state ground state energy transfer occur argonne researcher formation connecting chromophore part organic ring cobalt atom loss state reaction sustained longer avenue exploration way pacific national laboratory researcher experimenting low cost nickel catalyst team researcher australia developing plastic film catalyst strip hydrogen seawater track lawrence livermore laboratory working company chemergy thermochemicalbased system squeezing hydrogen municipal wastewater follow google psst wanna latest clean tech new cleantechnica newsletter youd attend cleantechnica solar event date hottest cleantech new subscribing free cleantech newsletter eye sectorspecific new also free solar energy newsletter electric vehicle newsletter wind energy newsletter ","m_szGeo1":"Australia","m_szSourceType":"source_news","m_szSrcUrl":"http://cleantechnica.com/2014/01/14/hydrogen-fuel-cells-blue-new-green/","m_Places":["Tesla","Australia","Along"],"m_People":["Tina Casey","Daniel Nocera","Jared Sagoff","Lawrence Livermore"],"m_Companies":["Argonne National Laboratory","Guess","National Institute Of Standards And Technology","Twitter","Google"],"m_BiGrams":["fuel cell","low cost","hydrogen fuel","electric vehicle"],"m_TriGrams":["hydrogen fuel cell"],"m_SocialTags":[],"m_Topics":[],"m_Industry":[],"m_Technology":[],"m_BiCnt":[5,4,3,3],"m_TriCnt":[3],"m_iDocBodyWordCnt":305}
