{"m_szDocID":"589281","m_szDocTitle":"Should You Bet on a Hydrogen Fuel Cell Future? -- The Motley Fool","m_szYear":"2014","m_szDocSumamry":"Should You Bet on a Hydrogen Fuel Cell Future? Toyota, Hyundai, and Honda are betting on the future of fuel cell vehicles. Will it payoff? Katie Spence Apr 27, 2014 at 12:31PM 2015 Tucson Fuel Cell. Photo credit: Hyundai. When it comes to fuel cell electric vehicles, or FCEVs, two of the main barriers to widespread adoption are cost and the lack of a hydrogen-fueling infrastructure. However, recent advances could help solve these problems. For Toyota Motor ( NYSE:TM ), Hyundai Motor ( NASDAQOTH:HYMTF ), and Honda Motor ( NYSE:HMC ), this is great news. Reduced platinum One of the biggest drive","m_szDocBody":"bet hydrogen fuel cell future toyota hyundai honda betting future fuel cell vehicle payoff katie spence tucson fuel cell photo credit hyundai fuel cell electric vehicle fcevs main barrier widespread adoption cost lack hydrogenfueling infrastructure however recent advance solve problem toyota motor nysetm hyundai motor nasdaqothhymtf honda motor nysehmc great new reduced platinum biggest driver cost fcevs platinum catalyst fuel cell good new that amount platinum needed fuel cell dropped however scientist nrel working make ultrathin platinum film limited atomic layer reason nrel platinum decreased twothird hydrogen fuel cell reach precious metal loading parity catalytic converter today internalcombustion engine important catalytic converter mandatory pollution control internal combustion engine ice vehicle however emission fcev heat water consequently catalytic converter fcevs mean amount platinum future fcevs today ice vehicle utilise platinum moreover reducing platinum reduce cost fcevs remove platinum altogether recently wrote argonne national laboratory working polymer electrolyte fuel cell pefc replace platinum cathode cheaper catalyst successful reduce cost cathode electrocatalyst trigeneration fuel cell hydrogen energy station hydrogen fueling station fuel cell vehicle shell hydrogen photo credit michael penev nrel fuelcell energy nasdaqfcel energy department number agency opened world trigeneration fuel cell hydrogen energy station fountain valley cali station convert renewable biogas nearby wastewater treatment plant hydrogen vehicle fueling additionally installation produce electricity heat power warm facility energy department better accomplished onsite eliminating transport hydrogen fueling station importantly fuelcell energy announced department energy granted fuelcell energy million continuation award demonstrate trigen system technology course fuelcell energy company producing onsite hydrogen system hypersolar university california santa barbara working selfcontained photoelectrochemical nanosystem produce renewable hydrogen sunlight source water wastewater company working prototype process creating nanotechnology developed commercial hydrogenextraction solution called hgenerator standalone selfcontained solar hydrogen generator hypersolar intended installed produce hydrogen fuel local use bet hydrogen toyota fcv concept photo credit mytho wikimedia common future green transportation fcevs number them hydrogen energy density time higher lithiumion battery toyotas alternative fuel comparison chart fcevs refuelled minute driving range similar ice vehicle cost fuel cell hydrogen fuel fallen significantly energy department fuel cell vehicle fallen kilowatt projected cost gasolinegallon equivalent adding cost deliver distribute importantly auto manufacture betting big hydrogen california spring hyundai begin leasing hyundai tucson fuel cell vehicle month include unlimited free hydrogen refuelling plus toyota honda planning launching fuel cell vehicle consequently barrier overcome widespread fcev adoption barrier smaller day such invest future fcevs closer auto company betting hydrogen goodbye madeinchina time early day country position dominate global manufacturing landscape single revolutionary technology printing sound science fiction novel success printing foregone conclusion manufacturer world trick identify company stock prevail battle market share company positioned simply download invaluable free report topic clicking katie spence position stock mentioned motley fool position stock mentioned foolish newsletter service free day fool hold opinion diverse range insight make investor motley fool disclosure policy ","m_szGeo1":"United States","m_szSourceType":"source_news","m_szSrcUrl":"http://www.fool.com/investing/general/2014/04/27/should-you-bet-on-a-hydrogen-fuel-cell-future-2.aspx","m_Places":["Toyota","Tucson","California"],"m_People":["Honda","Katie Spence","Michael Penev"],"m_Companies":["Hyundai","Toyota Motor","Nyse","Hmc","Argonne National Laboratory","Nasdaq","Energy Department","University Of California At Santa Barbara","Motley Fool"],"m_BiGrams":["fuel cell","cell vehicle","hydrogen fuel","fuelcell energy","photo credit","catalytic converter","ice vehicle","cell hydrogen","hydrogen energy","energy department"],"m_TriGrams":["fuel cell vehicle","fuel cell hydrogen"],"m_SocialTags":[],"m_Topics":[],"m_Industry":[],"m_Technology":[],"m_BiCnt":[15,5,4,4,3,3,3,3,3,3],"m_TriCnt":[5,3],"m_iDocBodyWordCnt":465}
