{"m_szDocID":"589215","m_szDocTitle":"A Fuel Cell Vehicle Test Drive: The 2015 Hyundai Tucson Fuel Cell Electric Vehicle - The Equation","m_szYear":"2015","m_szDocSumamry":"Andrew Rosenberg | December 10, 2015 A Fuel Cell Vehicle Test Drive: The 2015 Hyundai Tucson Fuel Cell Electric Vehicle Josh Goldman , policy analyst, Clean Vehicles                        | October 9, 2014, 10:01 am EST On a sunny fall day last week, my Clean Vehicles colleagues and I had the opportunity to test drive the 2015 Hyundai Tucson Fuel Cell â€“ an electric vehicle that runs on electricity produced from hydrogen. Fuel cell electric vehicles (FCEVs) may not be as well-known as battery electric vehicles (BEVs) like the Nissan LEAF, or plug-in electric hybrid vehicles (PHEVs) like the Ch","m_szDocBody":"andrew rosenberg fuel cell vehicle test drive hyundai tucson fuel cell electric vehicle josh goldman policy analyst clean vehicle est sunny fall day week clean vehicle colleague opportunity test drive hyundai tucson fuel cell electric vehicle run electricity produced hydrogen fuel cell electric vehicle fcevs wellknown battery electric vehicle bevs nissan leaf plugin electric hybrid vehicle phevs chevy volt promising solution oil beginning hit road california bunsen burner main difference fcevs type evs storing electricity battery fcevs generate electricity fuel cell combine oxygen air hydrogen stored onboard hydrogen tank major advantage fcevs refuelled conventional vehicle tucson fuel cell example travel mile full tank hydrogen refilled mere minute additional background difference type evs and deeper dive particular fcev technology cheque post colleague dave fuel cell driving experience post part sery electric vehicle test drive review drive fcev exceedinglynormal hyundai tucson fuel cell accelerated braked cornered cruised conventional vehicle real difference engine silent operating provided additional power line due electric motor rev engine red light show youre ready race sound hear cabin wheel hitting pavement typical cascade honking driver attempting navigate traffic street heart downtown expected removing foot accelerator vehicle abruptly slow due regenerative braking tucson rolled smoothly foot pedal tucson roomy comfortably fitting people cabin equipped amenity driver expect bluetooth connectivity power lock window cargo space compact suv overall great test driving experience excited technology tachometer hyundai fcev gauge show power charge level what fuel cell vehicle promising aspect fuel cell technology aside fact fcevs produce tailpipe emission adding energy storage adding range require larger hydrogen tank mean fuel cell technology enable electrification bigger suvtype vehicle popular classe vehicle medium heavyduty truck course order fcev fill hydrogen california leading installing hydrogen station california expect hydrogen station open public end year automaker hyundai toyota honda working introduce fcevs select market year driver leasing hyundai tucson fuel cell california toyota seeking driver drive change leasing fcev fcevs part plan reduce oil battery electric fuel cell electric efficient gasoline vehicle portrayed competitor technology complementary plugin electric advantage existing electric infrastructure smaller electric car efficient costeffective urban dweller commuter fcevs good option larger vehicle longer driving distance driver spot recharge gasolinepowered vehicle continue sold coming year continuing increase fuel efficiency gasolineonly conventional vehicle play key role transformation transportation technology part strategy cut nation projected oil half imminent arrival fcevs clean vehicle option choose dealership ","m_szGeo1":"United States","m_szSourceType":"source_news","m_szSrcUrl":"http://blog.ucsusa.org/josh-goldman/fuel-cell-vehicle-test-drive-2015-hyundai-tucson-fuel-cell-electric-vehicle-678","m_Places":["California","Tucson","Dc","Toyota"],"m_People":["Andrew Rosenberg","Josh Goldman","Dave","Honda"],"m_Companies":["Volt","Fcev Technology","Bluetooth","Hyundai"],"m_BiGrams":["fuel cell","tucson fuel","electric vehicle","hyundai tucson","cell electric","test drive","clean vehicle","conventional vehicle"],"m_TriGrams":["tucson fuel cell","hyundai tucson fuel","fuel cell electric","cell electric vehicle"],"m_SocialTags":[],"m_Topics":[],"m_Industry":[],"m_Technology":[],"m_BiCnt":[13,5,5,4,4,3,3,3],"m_TriCnt":[5,4,4,3],"m_iDocBodyWordCnt":389}
