{"m_szDocID":"589293","m_szDocTitle":"Toyota is ready to sell fuel cell cars in 2015 after a decade of prototypes | ExtremeTech","m_szYear":"2015","m_szDocSumamry":"Toyota is ready to sell fuel cell cars in 2015 after a decade of prototypes Toyota is ready to sell fuel cell cars in 2015 after a decade of prototypes By David Cardinal on January 10, 2014 at 3:15 pm Comment Share This article Toyota is not the first company to announce plans for a commercial fuel cell vehicle — Hyundai announced its Tucson SUV earlier this month for example — but it makes a compelling case for its new car. A four-seat sedan, the car is only called Fuel Cell Vehicle (FCV) for now. The FCV’s range is expected to be similar to a high-end Tesla, but with the advantage that fill-","m_szDocBody":"toyota ready sell fuel cell car decade prototype toyota ready sell fuel cell car decade prototype david cardinal comment share toyota company announce plan commercial fuel cell vehicle hyundai announced tucson suv earlier month make compelling case car fourseat sedan car called fuel cell vehicle fcv now fcvs range expected similar highend tesla advantage fillup minute initially fcv sold california state made multihundredmillion dollar commitment hundred hydrogen filling station decade toyota fuel cell power train fuel cell vehicle engine start hydrogen provided filling station currently unlike gas propane isnt consumer store replenish hydrogen tank own fcvs fuel cell combine hydrogen oxygen atmosphere produce electricity and harmless water vapour electric motor power car electric vehicle fcvs motor specced produce power around horsepower giving vehicle mph time second similar toyota prius toyota didnt precise weight fcv yet told expected similar small fourdoor sedan similar plugin hybrid fcv small battery charged discharged needed store energy lowpowered driving provide additional power highpowered driving powercontrol unit mounted front car motor direct energy battery electric motor depending load fcv feature hydrogen tank rear car newlyredesigned boost converter increase voltage provided fuel cell needed motor complete power train picturetoyota worked make fuel cell tank small car comfortably seat passenger room luggage making hydrogenpowered car cool toyota style differentiate fcv expected competition front car emphasise large air intake provide oxygen turn combined hydrogen produce car power similarly side styling designed emphasise airtowater transition integral part fuel cell process car aerodynamic line key range huge hydrogen tank hydrogen highway compared electric vehicle hydrogen huge advantage major disadvantage side filling hydrogen tank doesnt longer filling gas tank minute mile range make refuelling simple gasolinepowered car hydrogen station disadvantage unlike electric car recharged outlet home time hydrogenfueled car refilled hydrogen station dozen hydrogen filling station california else end decade expected station southern california driver plan ahead wont make trip crosscountry remote areas asked toyota product specialist ces this eventually prepackaged tank hydrogen preprovisioned store transported consumer today research project ","m_szGeo1":"United States","m_szSourceType":"source_news","m_szSrcUrl":"http://www.extremetech.com/extreme/174503-toyota-is-ready-to-sell-fuel-cell-cars-in-2015-after-a-decade-of-prototypes","m_Places":["Toyota","Tucson","Tesla","California"],"m_People":["David Cardinal"],"m_Companies":["Hyundai","Seat","Ups"],"m_BiGrams":["fuel cell","hydrogen tank","cell vehicle","filling station"],"m_TriGrams":["fuel cell vehicle"],"m_SocialTags":[],"m_Topics":[],"m_Industry":[],"m_Technology":[],"m_BiCnt":[10,4,3,3],"m_TriCnt":[3],"m_iDocBodyWordCnt":328}
