{"m_szDocID":"589220","m_szDocTitle":"Intelligent Energy in £1.2bn deal to supply clean fuel cell power to 27,400 telecom towers in India - Renewable Energy Focus","m_szYear":"2015","m_szDocSumamry":"Intelligent Energy in £1.2bn deal to supply clean fuel cell power to 27,400 telecom towers in India Elsevier Ltd is not responsible for the content of external                     websites. Related Stories Hydrogen Mobility Europe to deploy more fuel cell electric vehicles plus pan-European hydrogen refueling network A coalition of European partners has launched the Hydrogen Mobility Europe (H2ME) flagship project, to deploy a total of 325 fuel cell electric vehicles and 29 new hydrogen refueling stations, creating the first pan-European network of hydrogen stations to serve FCEV drivers. Air ","m_szDocBody":"intelligent energy deal supply clean fuel cell power telecom tower india elsevier responsible external website related storey hydrogen mobility europe deploy fuel cell electric vehicle paneuropean hydrogen refuelling network coalition european partner launched hydrogen mobility europe hme flagship project deploy total fuel cell electric vehicle hydrogen refuelling station creating paneuropean network hydrogen station serve fcev driver air quality devil dont death globally related air pollution investing clean energy solution healthy dose medicine world alleviate social economic burden family national state alike powering sustainable future suggest henri winand company collaborating supply water purification technology india intelligent energy fuel cell providing electric power water purification system developed hydro industry new intelligent energy deal supply clean fuel cell power telecom tower india ukbased intelligent energy purchase contract gtl ltd major indian network service provider supply energy management service telecom tower india landmark deal worth billion billion year expected transformative impact indiasenergy market essential energy ies indian subsidiary assume power management mobile telecom tower this equivalent uks telecom tower uss essential energy intend transition managed telecom tower diesel power hydrogen fuel cell contract tenure deployment hydrogen fuel cell power indian telecom tower mark watershed transformation indian power grid previously faulted stifling indias economic growth due persistent unreliability indias telecom tower experience power outage approximately day leaving half country million cellphone user frequently disconnected extended period diesel generator main backup power source fuel cell efficient cleaner economical total cost ownership basis diesel generator technology india leapfrog informationdriven future assuming cost experiencing difficulty implementing conventional energy grid henri winand ceo intelligent energy deal set significant precedent shaping indias energy future intelligent energy working ascend telecom india successful trial ahead anticipated major fuel cell deployment telecom tower share ","m_szGeo1":"India","m_szSourceType":"source_news","m_szSrcUrl":"http://www.renewableenergyfocus.com/view/43153/intelligent-energy-in-1-2bn-deal-to-supply-clean-fuel-cell-power-to-27-400-telecom-towers-in-india/","m_Places":["India","Europe","Uk","Ie"],"m_People":["Henri Winand"],"m_Companies":["Elsevier Ltd","European Partners","01 October","Gtl Ltd","Diesel","Energy Future"],"m_BiGrams":["fuel cell","telecom tower","intelligent energy","energy deal","cell power","tower india"],"m_TriGrams":["intelligent energy deal","fuel cell power","telecom tower india"],"m_SocialTags":[],"m_Topics":[],"m_Industry":[],"m_Technology":[],"m_BiCnt":[9,9,6,3,3,3],"m_TriCnt":[3,3,3],"m_iDocBodyWordCnt":281}
