{"m_szDocID":"589242","m_szDocTitle":"Toyota Touts Cold-Weather Performance Of Hydrogen Fuel Cells","m_szYear":"2014","m_szDocSumamry":"Toyota Touts Cold-Weather Performance Of Hydrogen Fuel Cells Email This Page To (separate emails with commas) Message (optional) Your email was sent successfully. Close 3,061 views Feb 3, 2014 Follow Antony How did you fare in the Snowpocalypse? The recent polar vortex over the North American content dumped heavy snow on dozens of states and brought in truly Arctic temperatures, causing widespread travel disruption . While Toyota's hydrogen fuel cell vehicles aren't immune to snow-bound traffic, they are at least suffering no ill-effects from the cold--neither range nor performance have been a","m_szDocBody":"toyota tout coldweather performance hydrogen fuel cell separate email commas message optional successfully close view follow antony fare snowpocalypse recent polar vortex north american dumped heavy snow dozen state brought arctic temperature causing widespread travel disruption toyotas hydrogen fuel cell vehicle immune snowbound traffic suffering illeffect coldneither range performance affected recent chill toyota operating small fleet fuel cell vehicle launches fullblown production car electric car range figure tumble cold weather battery chemistry struggle cope toyota issue fuelcell vehiclesa lessthan subtle hint see fuel cell superior option connecticutbased proton onsite run tenvehicle fleet toyota fchvadv fuel cell vehicle realworld trial more toyota fcv hydrogen fuelcell test car concept shown ces snow low temperature proton vice president business development mark schiller reported issue vehiclesi continue range mile cold blasting heater say air product pennsylvania run test fleet troublefree driver carried normal state worst winter recent memory automaker toyota test vehicle extreme heat cold fuel cell vehicle spent long period testing yellowknife canadawhere temperature reach celsius fahrenheit owner faceor least owner expected face recent arctic snap aspect hydrogen fuel cell vehicle remain unproven nice handle cold weather than vehicle ","m_szGeo1":"United States","m_szSourceType":"source_news","m_szSrcUrl":"http://www.greencarreports.com/news/1090078_toyota-touts-cold-weather-performance-of-hydrogen-fuel-cells","m_Places":["Toyota","Connecticut","Pennsylvania","Canada"],"m_People":["Mark Schiller"],"m_Companies":["Proton Onsite"],"m_BiGrams":["fuel cell","cell vehicle","hydrogen fuel"],"m_TriGrams":["fuel cell vehicle","hydrogen fuel cell"],"m_SocialTags":[],"m_Topics":[],"m_Industry":[],"m_Technology":[],"m_BiCnt":[7,5,3],"m_TriCnt":[5,3],"m_iDocBodyWordCnt":186}
