{"m_szDocID":"589329","m_szDocTitle":"NEESC Announces 2015 Hydrogen & Fuel Cell Plans for Eight Northeastern States","m_szYear":"2015","m_szDocSumamry":"NEESC Announces 2015 Hydrogen & Fuel Cell Plans for Eight Northeastern States Share Article NEESC, administered by CCAT, created individual plans for Connecticut, Maine, Massachusetts, New Hampshire, New Jersey, New York, Rhode Island, and Vermont to aid in advancing the deployment of hydrogen and fuel cell technology. States that support the development of clean, efficient technologies such as fuel cells have realized the benefits, including increased energy reliability with low or zero emissions. EAST HARTFORD, Conn. (PRWEB) February 19, 2015 The Northeast Electrochemical Energy Storage Clus","m_szDocBody":"neesc announce hydrogen fuel cell plan northeastern state share neesc administered ccat created individual plan connecticut maine massachusett hampshire jersey york rhode island vermont aid advancing deployment hydrogen fuel cell technology state support development clean efficient technology fuel cell realised benefit including increased energy reliability low emission east hartford conn prweb northeast electrochemical energy storage cluster neesc administered connecticut centre advanced technology inc ccat today announced release hydrogen fuel cell development plan state northeast created individually connecticut maine massachusett hampshire jersey york rhode island vermont plan produced support small business administration sba input industry stakeholder including automaker government agency gas supplier hydrogen fuel cell company advance deployment hydrogen fuel cell technology plan helpful policymaker understand potential market fuel cell technology commented john mcguinness marketing leader fuel cell demand electric capacity expected increase due part replacement older efficient baseload generation facility fuel cell technology meet electric grid efficiency distributed generation asset located directly customer site distributed generation increase efficiency improve enduser reliability provide opportunity combined heat power reduce emission school hospital manufacturing facility mission critical facility deployment hydrogen fuel cell technology meet carbon dioxide emission reduction emission vehicle zev requirement utilise renewable energy indigenous source biomass wind photovoltaic power state support development clean efficient technology fuel cell realised benefit including increased energy reliability low emission commented morry markowitz president fuel cell hydrogen energy association hydrogen fuel cell technology provide emission vehicle mass transit fleet operation plan identify opportunity state northeast region fully employ hydrogen fuel cell transportation make region showcase renewable energy reducing air emission defined actionable goal deployment stationary transportation application state stated joel rinebold director energy initiative ccat goal represent shortterm investment longterm productivity rinebold hundred small businesse hydrogen fuel cell supply chain poised capture substantial share global energy transportation market manufacture implementation emerging technology significantly increase number clean energy job region plan cite cumulative goal northeast state approximately megawatt installed stationary fuel cell capacity fuel cell electric vehicle fuel cell powered buse hydrogen refuelling station support fuel cell electric vehicle buse neesc northeast electrochemical energy storage cluster neesc network industry academic government nongovernmental leader working provide energy storage solution based england york jersey network focuse innovative development production promotion deployment hydrogen fuel fuel cell meet pressing demand energy storage solution neesc administered connecticut centre advanced technology inc industry partner maine hydrogen energy centre hec massachusett hydrogen fuel cell stakeholder mhfc energy york neny clean energy state alliance cesa ccat connecticut centre advanced technology inc ccat nonprofit economic development organisation headquartered east hartford conn leader goto resource strengthening competitiveness hightech business development state region nation ccat focuse core areas technology efficiency workforce development expertise manufacturing technology education workforce strategy energy solution synergy experienced team advanced technology extensive partnership ccat manufacturer educator government nonprofit entrepreneur innovative solution tackle economic challenge compete succeed share socal media email via ","m_szGeo1":"United States","m_szSourceType":"source_news","m_szSrcUrl":"http://www.prweb.com/releases/2015/02/prweb12526628.htm","m_Places":["Connecticut","Maine","Massachusetts","New Hampshire","New Jersey","New York, Rhode Island","Vermont","Hartford","Conn.","Connecticut Center","The States","New York"],"m_People":["John Mcguinness","Zev","Morry Markowitz","Joel Rinebold","Rinebold"],"m_Companies":["Northeastern States","Advanced Technology Inc.","Small Business Administration","Energy Association","Advanced Technology, Inc.","Energy Center","Alliance","Cesa"],"m_BiGrams":["fuel cell","hydrogen fuel","cell technology","deployment hydrogen","energy storage","advanced technology","neesc administered","connecticut centre","centre advanced","technology inc"],"m_TriGrams":["hydrogen fuel cell","fuel cell technology","deployment hydrogen fuel","connecticut centre advanced","centre advanced technology","advanced technology inc"],"m_SocialTags":[],"m_Topics":[],"m_Industry":[],"m_Technology":[],"m_BiCnt":[20,11,6,4,4,4,3,3,3,3],"m_TriCnt":[10,6,4,3,3,3],"m_iDocBodyWordCnt":467}
