{"m_szDocID":"589330","m_szDocTitle":"2015 Hyundai Tucson Fuel Cell: Hydrogen Crossover First Drive","m_szYear":"2014","m_szDocSumamry":"2015 Hyundai Tucson Fuel Cell: Hydrogen Crossover First Drive Email This Page To (separate emails with commas) Message (optional) Your email was sent successfully. Close 22,956 views Dec 4, 2013 Follow John Add to circle Hyundai is an aggressive company, and that applies to its green cars as much as the bread-and-butter sedans and crossovers it sells in growing numbers. So when the company approached Green Car Reports to ask if we'd like to drive its new, hydrogen-powered 2015 Hyundai Tucson Fuel Cell vehicle, that was a no-brainer. All in all, we spent about two hours in the zero-emission com","m_szDocBody":"hyundai tucson fuel cell hydrogen crossover drive separate email commas message optional successfully close view follow john add circle hyundai aggressive company apply green car breadandbutter sedan crossover sell growing number company approached green car report drive new hydrogenpowered hyundai tucson fuel cell vehicle nobrainer all spent hour zeroemission compact crossover mixing freeway driving suburban stopandgo travel refuelling stop rare hydrogen filling station hyundais sibling rival kia launched kia soul batteryelectric conversion allnew soul tall box compact hatchback hyundai believe hydrogen fuel cell path zeroemission vehicle hyundai tucson fuel cell hyundai headquarter fountain valley enlarge photo hyundai developed fuelcell technology shown concept car year tucson fuel cell announced paris motor show fuel cell the tucson model europe entered production past february hydrogen fuelcell car shown november auto show tokyo los angele now lowvolume production hydrogen carbuilt tucson assembly line south korea gasoline version getis here offered spring cost month year down hyundai tucson fuel cell hyundai headquarter fountain valley enlarge photo hyundai motor america president ceo john krafcik company expect build sell roughly tucson fuel cell year demand higher that possibility number rise toyota launches production version fcv fuelcell carshown nearproduction form recent tokyo motor showthat make hydrogen tucson world highestvolume fuelcell vehicle bottom line alternative plugin batterypowered electric car front hydrogen hyundai european grille front fasciagiving appearance gasoline tucson trick hyundai sonata hybrid smart tactic good wheel pleasant quiet electricallydriven crossover buyer alternatively powered fuel and face challenge locating hydrogen station hyundai proud fuelcell stack operate close atmospheric pressure reduce sizeand noiseof pump compressor required operate cool cell result electriccar driver tucson driving experience familiar hyundai tucson fuel cell hyundai headquarter fountain valley enlarge photo front wheel driven kilowatt horsepower electric motor lbft torque meaning pull smartly and quietly stop spry heavy town hyundai included lithiumion battery pack sonata hybrid hydrogen tucson provide extra assist maximum power required located front seat pound pack nominal capacity kilowatthour usable energy kwh gil castillo hyundais senior manager alternative advanced vehicle strategy fuelcell tucson biggest drawback lack power highway speed acceleration fine town flooring say mph heavy hydrogen crossover gain speedbut agonisingly slowly passing manoeuvre highway require lot advance planning impossible lack highspeed acceleration feature fuelcell tucson fail provide capability gasoline model hyundai tucson fuel cell hyundai headquarter fountain valley enlarge photo standard hyundai tucson record litre fourcylinder engine driving front wheel sixspeed automatic transmission allwheel drive optional there awd option hydrogen tucson transverse tank hydrogen compressed pound square inch megapascal located rear seat rear load bay ahead rear axle fueling tucson similar standard gasoline refuelling combined naturalgas hydrogen station located orange county sanitation district facility fountain valley california hyundais headquarter located city ","m_szGeo1":"South Korea","m_szSourceType":"source_news","m_szSrcUrl":"http://www.greencarreports.com/news/1088865_2014-hyundai-tucson-fuel-cell-hydrogen-crossover-first-drive","m_Places":["Ca","Tucson","Paris","Europe","Tokyo","Los Angeles","South Korea","America","Toyota","California"],"m_People":["Kia Soul","John Krafcik","Gil Castillo"],"m_Companies":["Hyundai","Path","Hyundai Headquarters","Cell Technology","Los Angeles","Seat","Orange County Sanitation District Facility"],"m_BiGrams":["fuel cell","tucson fuel","hyundai tucson","fountain valley","cell hyundai","hyundai headquarter","headquarter fountain","valley enlarge","enlarge photo","hydrogen tucson"],"m_TriGrams":["tucson fuel cell","hyundai tucson fuel","fuel cell hyundai","cell hyundai headquarter","hyundai headquarter fountain","headquarter fountain valley","fountain valley enlarge","valley enlarge photo"],"m_SocialTags":[],"m_Topics":[],"m_Industry":[],"m_Technology":[],"m_BiCnt":[10,8,7,5,4,4,4,4,4,3],"m_TriCnt":[8,6,4,4,4,4,4,4],"m_iDocBodyWordCnt":440}
