{"m_szDocID":"589314","m_szDocTitle":"Is Honda's Hydrogen Fuel Cell Car The Future? - Business Insider","m_szYear":"2013","m_szDocSumamry":"I worked as a barista and a paralegal â€” and both my bosses broke the law in the same way At the Los Angeles Auto Show this week, Honda unveiled the FCEV Concept, a futuristic-looking car it says \"will feature the world's first application of a fuel-cell powertrain packaged completely in the engine room of the vehicle, allowing for efficiencies in cabin space.\" Although fuel cell electric vehicles (FCEV) are rare today, they may have what it takes to be very popular one day. The benefits of FCEV FCEVs run on hydrogen gas and oxygen, which an onboard fuel cell stack converts, via a chemical reac","m_szDocBody":"worked barista paralegal bosse broke law los angele auto show week honda unveiled fcev concept futuristiclooking car will feature world application fuelcell powertrain packaged completely engine room vehicle allowing efficiency cabin space fuel cell electric vehicle fcev rare today take popular day benefit fcev fcevs run hydrogen gas oxygen onboard fuel cell stack convert chemical reaction electricity version electric car offer performance environmental benefit batterypowered evs bev range conventional car refuelled more electricity generatedinthe car major downside bevs power stored battery run out quickly issue proper infrastructure hydrogen refuelling station which incorporated gas station fcevs unlimited range car internal combustion engine mean range anxiety long battery charging time jack nerad executive editorial director market analyst kelley blue book told business insider carbon dioxide pumped atmosphere noise made motor deliver torque enginepowered car translate great acceleration emission fcevs water vapour greenhouse gas but nerad say not generally regarded bad carbon dioxide technology vastly underdeveloped face challenge road driveway decade come problem fcev hurdle actual production hydrogen pure hydrogen industrially derived take energy energy renewable source fuelcell car clean seem meanwhile jack nerad kbb said its easy poke hole ground extract oil natural gas its cheap that that challenge lack infrastructure gas station invest ability refuel hydrogen tank fcevs practical customer road today were chickenegg situation nerad compounding lack infrastructure cost technology fuel cell still very expensive compared batterypowered evs nerad bevs cost lot internal combustion enginepowered car major challenge potential customer idea fcevs are electric drive transportation promote technology part suite electrification technology cullen said include improving awareness importance existence fuelcell electric were beginning process said step fcev people aware fuel cell technology fcevs road today part bus fleet europe genevieve cullen vicepresident electric drive transportation edta now fleet optimal application fcevs cullen told business insider follow set route refuelling station required large number vehicle create economy scale justify cost building station wellknown automaker working technology ford daimler which own mercedesbenz smart renaultnissan announced partnership speed development commercially viable fcevs jointlycreated automotive fuel cell cooperation afcc greg frenette afcc working serious largescale commercialization fuelcell vehicle timeline called cautious aston martin automaker put hydrogenpowered car nurburgring famed german circuit hybrid hydrogen rapide engine fuel cell run gasoline honda furthest ahead made fcev fcx clarity project lead widespread sale september honda ceo takanobu ito introduce fuelcell electric vehicle sale still people close technology argue largescale commercialization might decade awaynerad told business insider ford daimler nissan partnered fcevs effort cover themselve nerad said hand game case technology mainstream hydrogenpowered car completely viablethe process making hydrogen easier cheaper commensurate gain batterypowered electric car then fcev forever corner ","m_szGeo1":"","m_szSourceType":"source_news","m_szSrcUrl":"http://www.businessinsider.com/honda-hydrogen-fuel-cell-car-future-la-auto-show-2013-11","m_Places":["Los Angeles","Cullen","Europe"],"m_People":["Honda","Jack Nerad","Kelley","Nerad","Genevieve Cullen","Greg Frenette","Fcx Clarity","Takanobu Ito"],"m_Companies":["Los Angeles","Transportation Association","Edta","Daimler Ag","Mercedes-benz","Renault","Aston Martin"],"m_BiGrams":["fuel cell","told business","business insider"],"m_TriGrams":["told business insider"],"m_SocialTags":[],"m_Topics":[],"m_Industry":[],"m_Technology":[],"m_BiCnt":[6,3,3],"m_TriCnt":[3],"m_iDocBodyWordCnt":432}
