{"m_szDocID":"589303","m_szDocTitle":"Hyundai On Hydrogen Fuel-Cell Vehicles: Critiquing Its Claims","m_szYear":"2014","m_szDocSumamry":"Hyundai On Hydrogen Fuel-Cell Vehicles: Critiquing Its Claims Email This Page To (separate emails with commas) Message (optional) Your email was sent successfully. Close 9,248 views Feb 4, 2014 Follow John Add to circle Every so often, Hyundai posts an entry on its \"Hyundai Like Sunday\" blog, which promotes itself as \"Truth, Candor and Conversation.\" Two months ago, the company's Elizabeth Chun offered some thoughts on its upcoming 2015 Hyundai Tucson Fuel Cell compact crossover. That vehicle will be offered for lease this spring in selected markets in Southern California. We drove the Tucson ","m_szDocBody":"hyundai hydrogen fuelcell vehicle critiquing claim separate email commas message optional successfully close view follow john add circle often hyundai post entry hyundai sunday blog promote truth candour conversation month ago company elizabeth chun offered thought upcoming hyundai tucson fuel cell compact crossover vehicle offered spring selected market southern california drove tucson fuel cell early december found perfectly suitable daily longdistance usethough gutless higher speedsassuming hydrogen fuel available critical worth diving hyundais pros con hydrogen fuelcell vehicle critically assertion hyundai tucson fuel cell hydrogen fueling station fountain valley enlarge photo piece tucson fuel cell generation electric vehicle couches hydrogenpowered tucson electric car energy source power electric drive motor editor note hyundai motor america contacted note post written nowdeparted ceo john krafcik elizabeth chun company online administrator careful acknowledge batteryelectric technology continue improve viable alternative some user focuse inherent slowcharge limitation suggest limit batterypowered car distinct subset car buyer arguably true buyer regularly travel than say mile day workplace charging fastcharging station route hyundai tucson fuel cell hydrogen fueling station fountain valley today fastcharging location hydrogen fueling station total remotely close plus gas station blanket build hydrogen station hyundai note tucson fuel cell offered early adoptersin zip code easy hydrogen infrastructure piece limit sale vehicle company sell total gasolinepowered tucson year areas but say superb customer experience sale volume hyundai pace infrastructure developed parallel were hoping consumer interest spark additional action private company state local government write expedite infrastructure deployment word hyundai saying build hydrogen station provide car hyundai tucson fuel cell hydrogen fueling station fountain valley enlarge photo main point dive meat piece noting hyundai spent time some dean green car journalist field asked the key battleground debate gridpowered hydrogenfueled electric car editor note green car report outlet hyundai approached discussion led piece commented prepublication draught hyundai blog post final post say publish response final version piece summarise issue statement gridpowered car lower wellstowheel greenhousegas emission hydrogenfueled car cost hydrogen infrastructure pose fundamental barrier widespread deployment hydrogen vehicle slow charging plugin car offset convenience overnight home charging impossible hydrogen car fair summary main argument ucirvine study addressing wellstowheel carbon footprint issue piece note recent analysis advanced power energy programme university california irvine show essentially equivalent greenhousegas emission hydrogen battery vehicle accounting input including feedstock production transmission consumption batterypowered vehicle small advantage california based cleaner grid here fuelcell vehicle have small advantage national basis continue ","m_szGeo1":"United States","m_szSourceType":"source_news","m_szSrcUrl":"http://www.greencarreports.com/news/1089569_hyundai-on-hydrogen-fuel-cell-vehicles-critiquing-its-claims","m_Places":["Candor","Southern","California","Tucson","Ca","America","Dc","Tucsons","Irvine"],"m_People":["Elizabeth Chun","John Krafcik"],"m_Companies":["Hyundai","Uc","University Of California At Irvine"],"m_BiGrams":["tucson fuel","fuel cell","hyundai tucson","hydrogen fueling","fueling station","fuelcell vehicle","cell hydrogen","station fountain","fountain valley"],"m_TriGrams":["tucson fuel cell","hyundai tucson fuel","hydrogen fueling station","fuel cell hydrogen","cell hydrogen fueling","fueling station fountain","station fountain valley"],"m_SocialTags":[],"m_Topics":[],"m_Industry":[],"m_Technology":[],"m_BiCnt":[7,7,4,4,4,3,3,3,3],"m_TriCnt":[7,4,4,3,3,3,3],"m_iDocBodyWordCnt":394}
