{"m_szDocID":"589315","m_szDocTitle":"Hyundai ix35 Fuel Cell Sets New 24-Hour Hydrogen Record","m_szYear":"2015","m_szDocSumamry":"Hyundai ix35 Fuel Cell Sets New 24-Hour Hydrogen Record Drive a new Hyundai ix35 from $26,990* Name required Last Name should be a hidden field. Please delete if you are a real person. Valid Phone required Thank you for your enquiry. One of our accredited supply network will be in touch in the next 24 hours.   Or Call 1300 438 639 To get a great deal from our national accredited supply network.   See full gallery > Trevor Collett | Aug 9, 2015 A Hyundai ix35 Fuel Cell has set a new record for hydrogen-powered vehicles , with the SUV driving for 24 continuous hours while boasting zero emissions","m_szDocBody":"hyundai fuel cell set hour hydrogen record drive hyundai required hidden field delete real person valid phone required enquiry accredited supply network touch hour call great deal national accredited supply network full gallery trevor collett hyundai fuel cell set record hydrogenpowered vehicle suv driving continuous hour boasting emission hand norwegian arntgran hartvig sport scientist marius bornstein physicist travelled chosen route germany nonstop hour period clocking way route chosen connect hydrogen refuelling station hamburg berlin driver filling hydrogen tank required travelling back station car public road everyday condition including city driving highspeed motorway averaging test this endurance drive highlight practicality fuel cell electric vehicle long driving range environmental credential technology hyundai europe coo thomas schmid said fuel cell programme delivered world first fitting hyundai fuel cell delivered benchmark hyundai fuel cell australia separate demonstration practicality driver complete trip oslo monaco hydrogen refuelling station route hour challenge record journey year pair aimed set record maximum distance covered single tank hydrogen sole hyundai fuel cell arrived locally year test vehicle hyundai australia carmaker established australias hydrogen refuelling station sydney ","m_szGeo1":"Germany","m_szSourceType":"source_news","m_szSrcUrl":"http://www.themotorreport.com.au/62046/hyundai-ix35-fuel-cell-sets-new-24-hour-hydrogen-record","m_Places":["Germany","Hamburg","Berlin","Europe","Australia","Oslo","Monaco","Sydney"],"m_People":["Trevor Collett","Arnt","Marius Bornstein","Thomas Schmid"],"m_Companies":["Hyundai"],"m_BiGrams":["fuel cell","hyundai fuel","hydrogen refuelling","refuelling station"],"m_TriGrams":["hyundai fuel cell","hydrogen refuelling station"],"m_SocialTags":[],"m_Topics":[],"m_Industry":[],"m_Technology":[],"m_BiCnt":[7,5,3,3],"m_TriCnt":[5,3],"m_iDocBodyWordCnt":176}
