{"m_szDocID":"589319","m_szDocTitle":"New Low Cost Hydrogen Fuel Cell Eschews Platinum Catalyst","m_szYear":"2013","m_szDocSumamry":"November 21st, 2013 by Tina Casey   CleanTechnica came this close to unraveling the mystery behind CellEra’s new platinum free fuel cell last week during a visit to the Fuel Choices Summit in Tel Aviv. Company officials weren’t giving away any secrets, unfortunately for us, but we did get a chance to see the new fuel cell first hand and we can tell you how it fits into the big picture of the emerging hydrogen economy. The CellEra exhibit was part of an expo attached to the Fuel Choices Summit . The expo included a score of up-and-coming alternative fuel and mobility companies, showcasing techn","m_szDocBody":"tina casey cleantechnica close unravelling mystery celleras platinum free fuel cell week visit fuel choice summit tel aviv company official werent giving secret chance fuel cell hand fit big picture emerging hydrogen economy cellera exhibit part expo attached fuel choice summit expo included score upandcoming alternative fuel mobility company showcasing technology ranging synfuel made sunlight carbon dioxide portable handy suitcase wheel portable electric scooter multiplatform urban travel post now let dig platinum free fuel cell platinum free fuel cell electric vehicle platinum free hydrogen fuel cell courtesy cellera cellera fuel cell designed variety including electric vehicle stationary purpose let quick recent history fuel cell development nowretired space shuttle generation alkaline fuel cell technology good outer space uncontaminated environment however alkaline technology highly susceptible carbon dioxide poisoning make costly endeavour earth secondgeneration solution pem polymer electrolyte membrane fuel cell sticky wicket catalyst separate electron proton hydrogen typically made platinum costly platinum extra costly sensitive carbon monoxide poisoning require additional system prevent that cellera fuel cell deploy catalysed solid polymer electrolyte polymer refer form plastic render platinum unnecessary platinumfree membrane pfm cellera platinum unnecessary polymer electrolyte conduct hydroxyl ion proton mean pfm cell mildly alkaline enable low cost transition metal catalyst noble metal platinum transition metal good question asked answer company official expo simple secret well added bonus alkaline environment noncorrosive enabling pfm cell light weight aluminium infrastructure wait more contributing lower cost conducting membrane made inexpensive polymer hydrogen economy back neck started tingling heard hydrogen join club hydrogen fuel cell run hydrogen main source industrial hydrogen natural gas open raft issue relating impact fracking natural gas drilling method impact range local air water pollution earthquake fugitive methane emission methane potent greenhouse gas fracking wastewater disposal issue direct economic impact fracking site cellera suggest ammonia source hydrogen defer problem industrial ammonia produced natural gas extent petroleum source however ahead future sustainable method hydrogen production work hydrogen fuel cell company cellera level interesting project weve major municipal wastewatertohydrogen demonstration project california partnering lawrence livermore national laboratory company chemergy interesting twist wastewater themed project colorado deploy microbial fuel cell part low cost treatment process produce hydrogen byproduct landfill gas renewable form renewable alternative natural gas promising avenue sustainable hydrogen manufacturing top raft r&d project deploying solar power produce hydrogen water ranging affordable artificial leaf designed household potential costeffective commercial production renewable hydrogen fuel choice summit way aforementioned fuel choice summit tel aviv umbrella israel national fuel choice initiative aimed specifically reducing country dependence oil transportation israel growing reputation friendly environment tech startup small domestic market fuel choice initiative aim export israeli solution meet global challenge developing country week covered country solar power demo project arava region solar development area expected achieve percent energy independence tourist city eilat surrounding desert community year obvious implication solar power desert environment globe week talk exportable low tech diy solution chance israel tour sponsored israeli organisation kinetis follow google youd attend cleantechnica solar event date hottest cleantech new subscribing free cleantech newsletter eye sectorspecific new also free solar energy newsletter electric vehicle newsletter wind energy newsletter ","m_szGeo1":"United States","m_szSourceType":"source_news","m_szSrcUrl":"http://cleantechnica.com/2013/11/21/new-low-cost-hydrogen-fuel-cell-requires-no-platinum/","m_Places":["Summit","Tel Aviv","California","Colorado","Israel","Eilat"],"m_People":["Tina Casey","Eilat"],"m_Companies":["Lawrence Livermore National Laboratory","Ups","Israeli Solutions","Twitter","Google"],"m_BiGrams":["fuel cell","fuel choice","platinum free","choice summit","hydrogen fuel","natural gas","free fuel","electric vehicle","polymer electrolyte","solar power"],"m_TriGrams":["fuel choice summit","platinum free fuel","free fuel cell","hydrogen fuel cell"],"m_SocialTags":[],"m_Topics":[],"m_Industry":[],"m_Technology":[],"m_BiCnt":[13,6,4,4,4,4,3,3,3,3],"m_TriCnt":[4,3,3,3],"m_iDocBodyWordCnt":507}
