{"m_szDocID":"589359","m_szDocTitle":"Hydrogen Fuel-Cell Vehicle News From Los Angeles Auto Show","m_szYear":"2014","m_szDocSumamry":"Hydrogen Fuel-Cell Vehicle News From Los Angeles Auto Show Email This Page To (separate emails with commas) Message (optional) Your email was sent successfully. Close 2,735 views Dec 8, 2014 Follow John The biggest news in zero-emission vehicles at last month's Los Angeles Auto Show was the formal introduction of the 2016 Toyota Mirai. But several other companies made news in the hydrogen fuel-cell market as well. Here's our brief roundup of the hydrogen stories we covered in LA. 2016 Toyota Mirai hydrogen fuel-cell car, Newport Beach, CA, Nov 2014 2016 Toyota Mirai The maker of the world's hi","m_szDocBody":"hydrogen fuelcell vehicle new los angele auto show separate email commas message optional successfully close view follow john biggest new zeroemission vehicle month los angele auto show formal introduction toyota mirai company made new hydrogen fuelcell market well roundup hydrogen storey covered toyota mirai hydrogen fuelcell car newport beach toyota mirai maker world highestvolume hybrid toyota prius formally introduced production version hydrogen fuelcell vehicle firstgeneration prius toyota mirai the japanese word future lowvolume vehicle early year toyota firmly convinced fuelcell vehicle running highly compressed hydrogen zeroemission technology for halfcentury batteryelectric car maker hydrogen powered vehicle toyota helping fund development hydrogen fueling infrastructure serve theminitially southern california honda fcv concept enlarge photo carmaker fund fueling infrastructure honda too plan launch fuelcell vehicle year expected sale smaller japanese carmaker echo toyotas adamant position hydrogen vehicle sole solution honda room electric car too loan million element fuel startup company won contract state california instal network hydrogen fueling station hondas fund build hydrogen station southern california toyota previously loan element million station turn toyota provide fund air liquide build station northeast state connecticut massachusett jersey york rhode island volkswagen passat hymotion hydrogen fuel cell prototype los angele volkswagen passat hymotion prototype demonstrate hydrogen fuelcell hardware ready road currentgeneration passat converted run fuel cell drove prototype briefly found fully refined mirai quieter way company say however expect introduce model powered hydrogen fueling infrastructure exist clear demand volkswagen golf sportwagen hymotion concept los angele auto show volkswagen golf sportwagen hymotion concept stand volkswagen displayed hydrogen vehicle one adaption golf waggon showed hydrogen fuel tank fuelcell stack integrated company mqb architecture compromise space people cargo golf sportwagen offered powered gasoline tdi diesel engine replace previous jetta sportwagen ","m_szGeo1":"United States","m_szSourceType":"source_news","m_szSrcUrl":"http://www.greencarreports.com/news/1095804_hydrogen-fuel-cell-vehicle-news-from-los-angeles-auto-show","m_Places":["Los Angeles","Toyota","Newport","Ca","Southern","California","Connecticut","Massachusetts","New Jersey","New York","Rhode Island"],"m_People":["Honda","Jetta Sportwagen"],"m_Companies":["Los Angeles","State Of California","Volkswagen"],"m_BiGrams":["hydrogen fuelcell","fuelcell vehicle","los angele","toyota mirai","angele auto","auto show","hydrogen fueling","fueling infrastructure","golf sportwagen"],"m_TriGrams":["los angele auto","angele auto show"],"m_SocialTags":[],"m_Topics":[],"m_Industry":[],"m_Technology":[],"m_BiCnt":[5,4,4,4,3,3,3,3,3],"m_TriCnt":[3,3],"m_iDocBodyWordCnt":280}
