{"m_szDocID":"589364","m_szDocTitle":"Hydrogen Fuel Cell Cars: The Vehicle of the Future? -- The Motley Fool","m_szYear":"2014","m_szDocSumamry":"Login Hydrogen Fuel Cell Cars: The Vehicle of the Future? A closer look at what hydrogen fuel cell cars are, who's developing them, and what the infrastructure looks like so far. Bret Kenwell ( Bkenwell ) Sep 9, 2014 at 10:17AM The Toyota FCV, Toyota's new fuel cell vehicle, being introduced by Bob Carter, senior vice president of automotive operations. The vehicle is expected to come to market in 2015. Photo source: Toyota Motors.  Electric vehicles are becoming more mainstream and continue to gain momentum, both in the U.S. and internationally. But there's another type of emission-free vehic","m_szDocBody":"hydrogen fuel cell car vehicle future closer hydrogen fuel cell car are developing them infrastructure far bret kenwell bkenwell toyota fcv toyotas fuel cell vehicle introduced bob carter senior vice president automotive operation vehicle expected market photo source toyota motor electric vehicle arebecoming mainstream continue gain momentum internationally type emissionfree vehicle creeping consumer hydrogen fuel cell car and discussion surrounding feel oddly similar year ago electric vehicle hydrogen fuel cellvehicle work basic form hydrogen fuel stored vehicle tank gasoline prompted acceleration hydrogen pushed fuel cell stack combined oxygen chemical reaction generate electricity power engine byproduct water vapour crude definition put this hydrogen fuel cell car hybrid internal combustion engine power car hydrogen fuel cell work car traditional vehicle hydrogen car advantage starter pump harmful chemical toxic gas earth atmosphere world consumer conscious health environment plus fuel efficiency expected attractive too consumer environmentally conscious fuel efficiency ease stress walletshydrogen fuel cell car attractive travel mile filling close mile gallon toyotas nysetm converted highlander suv doe toyota company working technology past year plan finally introduce hydrogen fuel cell car japan bringing united state look price tag toyota fcv known expected cost japanese version expected price million yen roughly challenge ahead unlike electric vehicle generally charge overnight customer home minute charging station hydrogen fuel cell car amount time fill standard gasolinepowered car roughly equivalent traditional car price fill toyota state web dedicated fcv vehicle hydrogen fuel pricing development expect cost operation similar gasoline vehicle hydrogen fuel developed domestically reducing united state dependency foreign oil consumer similar cost gasoline negative however worth mentioning actualvehicledoe emit pollutant production hydrogenforthe vehicle doe produced renewable resource solar wind powertoday common formis steam reform involve natural gas create greenhouse gas emission better though pollutant produced today popular internal combustion engine infrastructure problem currently hydrogen fueling station california toyota expect fueling station state connecticut south carolina state public hydrogen fuel station apiece perspective electric charging station scattered united state customer convenient option charging home toyota fcv source toyota motor final thought hydrogen fuel cell car attractive driving range solid fuel economy harmful effect environment traditional automobile early stage development vehicle make hard consumer excited mind consumer tough timejustifying price toyotas fuel cell vehicle pay similar fueling cost limitedinfrastructure help either today investor buy toprated tesla motorsmodel equivalent starting price toyota fcv pricing japan roughly line attractive design splendid performance impressive driving distance hard toyotas ride model plus driver charge home teslas supercharger network expected cover population end toyota leading hydrogen fuel cell charge company working too general motor nissan mercedesbenz ford other project development well lower price type vehicle future toyota explain vehicle type intended dominate decade end instead management refer car power year affordable vehicle improved infrastructure lower fueling cost road company future hydrogen fuel cell vehicle long road ahead warren buffett worst auto nightmare hint tesla major technological shift happening automotive industry people sceptical impact warren buffett them recently called real threat favourite businesse executive ford called technology fantastic beauty investor easy ride megatrend exclusive report stock bret kenwell own share ford motley fool recommend ford general motor tesla motor own share ford tesla motor foolish newsletter service free day fool hold opinion diverse range insight make investor motley fool disclosure policy man made time money age important happened rex moore thought fun over hill past prime phrase time changed year suddenly fog lifted hour outlook completely changed see room senior citizen made time money blew candle birthday cake heard him warren buffett billionaire investor right buffett current fortune time turned imagine excited room warren buffett early buffett fielded question room hour catch was allowed record audio video write single word buffett uttered word hand ached boy glad did buffett shared master strategy older american build wealth life catch wall street clobbered again important happened share strategy tip today learn buffett made time money life gathered discovered buffett distilled simple step put exclusive free report below free you ","m_szGeo1":"United States","m_szSourceType":"source_news","m_szSrcUrl":"http://www.fool.com/investing/general/2014/09/09/hydrogen-fuel-cell-cars-the-vehicle-of-the-future.aspx","m_Places":["Toyota","Japan","United States","California","Connecticut","South Carolina","Tesla","Wall Street"],"m_People":["Bret Kenwell","Bob Carter","As Toyota","Warren Buffett","Man Made","Rex Moore"],"m_Companies":["Toyota Motors","Nyse","Highlander","Tesla Motors","General Motors","Mercedes-benz","Motley Fool"],"m_BiGrams":["hydrogen fuel","fuel cell","cell car","toyota fcv","vehicle hydrogen","warren buffett","cell vehicle","electric vehicle","united state","made time","time money"],"m_TriGrams":["hydrogen fuel cell","fuel cell car","fuel cell vehicle","vehicle hydrogen fuel","made time money"],"m_SocialTags":[],"m_Topics":[],"m_Industry":[],"m_Technology":[],"m_BiCnt":[15,14,8,4,4,4,3,3,3,3,3],"m_TriCnt":[10,8,3,3,3],"m_iDocBodyWordCnt":651}
