{"m_szDocID":"589448","m_szDocTitle":"Hydrogen Price War Imminent? Hyundai Slashes 43% Off Price of Hydrogen Fuel Cell CUV in South Korea | Transport Evolved","m_szYear":"2015","m_szDocSumamry":"Hydrogen Price War Imminent? Hyundai Slashes 43% Off Price of Hydrogen Fuel Cell CUV in South Korea Nikki Gordon-Bloomfield Self-confessed geek and mother of two, Nikki has been talking and writing about cars ever since she passed her driving test. Back then, her Internet contributions were all classic car-focused. Now, sheâ€™s all about greener, cleaner, safer and smarter cars. EV Price Fuel Cell Car Hyundai Tucscon Fuel Cell Vehcile Hyundai iX35 FCV First to market with a hydrogen fuel cell variant of its popular Tucson CUV, the Tucson FCV, South-Korean automaker Hyundai is no-longer the only ","m_szDocBody":"hydrogen price war imminent hyundai slashes price hydrogen fuel cell cuv south korea nikki gordonbloomfield selfconfessed geek mother two nikki talking writing car passed driving test back then internet contribution classic carfocused now shes greener cleaner safer smarter car price fuel cell car hyundai tucscon fuel cell vehcile hyundai fcv market hydrogen fuel cell variant popular tucson cuv tucson fcv southkorean automaker hyundai nolonger hydrogen fuel cell manufacturer block competition coming hondas asyet unnamed fcv sedan toyotas recentlylaunched mirai fuel cell sedan hybrid electric car revolution taught market doesnt secure company place history offer outstanding product price doe hyundai slashed price tucson fcv south korea cent surprise hyundai responded recent launch toyota mirai fuel cell sedan japan slash price fuel cell vehicle domestic market south korea what astonishing price slashis worth massive percent reduction price wardsauto reported hyundaihas slashed price tucson fcv south korea bringing hydrogen fuel cell car reach consumer previously government subsidy south korea lowered sticker price equivalent sayswardsauto price reduction generous south korean subsidy put net price consumer attentive willnote place hyundai tucson fcv alittle lower price toyotas promised sticker price mirai government subsidy pending price slash put hyundais fcv playing field toyota mirai seating epaapproved mile fill mile kilogramme hydrogen hyundai tucson fcv range teslas allelectric model sedan careful driving electric car range impressively extended unlike electric car tucson fcv refilled dedicated hydrogen filling station domestic wall outlet combat inconveninece hyundai toyota hondas limited testfleet clarity fcx car offering customer free fuel ownership car buy hyundai tucson fcv outright south korea leased europe north america time writing hyundaihasnt detailed price reduction tucson fcv north america europewhere sold fcv instead hyundaibosse expect price announcement nondomestic market month geneva motor show currently tucson fcv leaseonly north america month down europe leasing price notpublicly available european pricing reduction expected announced geneva month addition announcing massive price slash hydrogen fuel cell vehicle hyundai announced massive investment totalling million funding support automotive industry startup working fuel cell vehicle development hydrogen fuelling infrastructure investment local small mediumsized businesse southwestern city gwangju south korea hyundai centring hydrogen fuel cell innovation effort costly automaker admitted summerthat tuscon fcvwas lossleading compliance car hyundais announcement start pricing war hydrogen fuel cell vehicle manufacture win earlyadopter fuel cell vehicle start priced match alternative fuelled vehicle electric car hydrogen fuel cell vehicle price right leave thought comment below latest new world evolving transport dont forget followtransport evolvedon twitter channel latest new evolving transport dont forget followtransport evolvedon twitter channel support directly monthly supporting member simply share friend ","m_szGeo1":"South Korea","m_szSourceType":"source_news","m_szSrcUrl":"https://transportevolved.com/2015/02/05/hydrogen-price-war-imminent-hyundai-slashes-43-off-price-hydrogen-fuel-cell-cuv-south-korea/","m_Places":["South Korea","Tucson","Toyota","Japan","Tesla","Europe","North America","Geneva","Gwangju","Tuscon"],"m_People":["Nikki Gordon","Ev Price","Honda"],"m_Companies":["Hyundai","Revolutions","Epa","Twitter","Facebook","Youtube"],"m_BiGrams":["fuel cell","tucson fcv","hydrogen fuel","south korea","cell vehicle","electric car","hyundai tucson","north america"],"m_TriGrams":["hydrogen fuel cell","fuel cell vehicle","hyundai tucson fcv"],"m_SocialTags":[],"m_Topics":[],"m_Industry":[],"m_Technology":[],"m_BiCnt":[15,9,8,7,6,4,3,3],"m_TriCnt":[8,6,3],"m_iDocBodyWordCnt":419}
