{"m_szDocID":"589459","m_szDocTitle":"After Decades Of Promises, Are Hydrogen Cars Really Any Closer? - Gas 2","m_szYear":"2015","m_szDocSumamry":"After Decades Of Promises, Are Hydrogen Cars Really Any Closer? April 7th, 2015 by Christopher DeMorro     Originally posted on CleanTechnica Ever since the first Arab Oil Crisis sent gas prices skyrocketing in the early 1970s, automakers have paid platitudes to government officials and environmentalists demanding a cleaner alternative to petrol. Hydrogen fuel cell vehicles have long been touted as a replacement for petrol cars, and the chart below shows just how far back those promises go. This chart comes from the Catalytic Engineering blog of Bruce Lin, an admitted fan of hydrogen fuel cell","m_szDocBody":"decade promise hydrogen car closer christopher demorro originally posted cleantechnica arab oil crisis gas price skyrocketing early automaker paid platitude government official environmentalist demanding cleaner alternative petrol hydrogen fuel cell vehicle long touted replacement petrol car chart show back promise chart catalytic engineering bruce lin admitted fan hydrogen fuel cell technology remember countless promise automaker executive hydrogen fuel cell vehicle corner isnt automaker though los alamos national laboratory released report fuel cell vehicle viable production and well didnt happen though released hydrogenpowered concept van shelved technology proved expensive actual production automaker put hydrogen fuel cell vehicle back burner mid california pressed car company build zeroemission vehicle face stiff fine led generation electric vehicle gms firstgen toyota rav automaker interested selling future powered hydrogen back predicting opelbrand vehicle running hydrogen fuel cell daimler bolder predicting sell fuel cell vehicle decade century smattering vehicle back daimler daimlerchrysler executive predicted mercedesbranded fuel cell vehicle road didnt work planned hondas planned fcv pushed back rollout ironically honda automaker close meeting prediction suggested production fuel cell vehicle wouldnt make dealer util fair pick daimler though ford honda toyota hyundai made equally bold prediction close true today production hydrogen fuel cell vehicle sale toyota mirai hyundai tucson fuel cell sold unit past year demand mirai proven robust predicted toyotas decidedly slow rollout fuel cell car greater edge electric vehicle failed prediction automaker new hydrogen fuel cell mind time suit major automaker convince hydrogen fuel future year mass acceptance alibi dont fly more share ","m_szGeo1":"United States","m_szSourceType":"source_news","m_szSrcUrl":"http://gas2.org/2015/04/07/after-decades-of-promises-are-hydrogen-cars-really-any-closer/","m_Places":["Toyota"],"m_People":["Christopher Demorro","Bruce Lin","Mercedes","Honda"],"m_Companies":["Crisis","Los Alamos National Laboratory","California Pressed","Daimlerchrysler","Hyundai"],"m_BiGrams":["fuel cell","hydrogen fuel","cell vehicle"],"m_TriGrams":["fuel cell vehicle","hydrogen fuel cell"],"m_SocialTags":[],"m_Topics":[],"m_Industry":[],"m_Technology":[],"m_BiCnt":[13,8,8],"m_TriCnt":[8,7],"m_iDocBodyWordCnt":247}
