{"m_szDocID":"589404","m_szDocTitle":"Toyota launching fuel cell car Mirai - The Portland Press Herald / Maine Sunday Telegram","m_szYear":"2015","m_szDocSumamry":"increase font size Toyota launching fuel cell car Mirai Toyota is betting that fuel cell vehicles could over time equal or surpass plug-in electric hybrids in consumer acceptance. By GREG GARDNERDetroit Free Press Share Read Article 1 of 4 Toyota will begin selling its Mirai fuel cell car in five Northeast states (Maine not among them) next year. DETROIT â€“ Toyota will be launching its Mirai fuel cell car soon in California, in the teeth of falling gas prices, a paltry network of hydrogen fueling stations, and media infatuation with Tesla that is finally expected to build a salable version of i","m_szDocBody":"increase font size toyota launching fuel cell car mirai toyota betting fuel cell vehicle time equal surpass plugin electric hybrid consumer acceptance greg gardnerdetroit free press share read toyota begin selling mirai fuel cell car northeast state maine them year detroit toyota launching mirai fuel cell car california teeth falling gas price paltry network hydrogen fueling station media infatuation tesla finally expected build salable version muchdelayed model suv handful hydrogen station running golden state california fuel cell partnership plan station operate end state california spending million year project fuel cell lightest solution chris hostetter toyota vice president strategic planning cost advantage electric vehicle making electricity board pulling grid toyota bring hydrogen fuel cell car market honda sold handful fcx clarity fuel cell car year ended production model year expected launch fuel cell model year hyundai recently launched fuel cell version tucson sold far toyota making aggressive bet fuel cell vehicle time equal surpass plugin electric hybrid consumer acceptance mirai conceived time prius gaselectric hybrid early sale goal modest shipped end year goal selling country end sticker price tax credit mirai wont inexpensive early customer expected month toyota kicking year worth hydrogen recently sold range kilogramme emission water year set fueling station funded toyota partner air liquide stretch jersey york connecticut rhode island massachusett range mirai fill mile optional power takeoff feature deliver kilowatt power kwh total emergency situation glimpse car distinctive say strange front hood wrapping beltlike edge elevate grille highlighted trapezoid sitting beneath narrow head lamp slit rear mirai appear mainstream firstadopter ecoconscious consumer debate mirai casting smaller carbon foot print plugin electric vehicle challenge hydrogen vehicle term carbon footprint cleaner gasoline car clean plugin car john voelcker senior editor green car report kilowatt hour electricity recharge battery that turn power car create kilowatt hour electricity refining hydrogen feed stock commonly natural gas extracted hydraulic fracturing hydrogen compressed fed fuel cell create electricity losing percent hydrogen process voelcker said kilowatthour electricity youre mile fuel car vehicle said hydrogen win convenience perspective youre fueling station quick filling gasoline diesel carbon footprint equation change hydrogen created renewable energy source solar panel wind turbine prius mirai driven shortterm business case wont sexy silicon valley media star tesla motor ceo elon musk dismissed technology fool cell toyota broad product portfolio profitable mainstream automaker patience hydrogen mobility work long run toyota doesnt financial expectation mirai positioned teslakiller mike millikin editor green car congress significant step longterm strategy underscore incremental marketing mirai toyota interviewing prospective owner make live feasible distance fueling station driving mexican border oregon wont work station route again option growing menu mobility option germany see scandinavian country hostetter said japan government strongly partly backlash nuclear power fukushima said referring nuclear plant destroyed tsunami share morning new update delivered inbox email ","m_szGeo1":"United States","m_szSourceType":"source_news","m_szSrcUrl":"http://www.pressherald.com/2015/10/04/toyota-launching-fuel-cell-car-mirai/","m_Places":["Toyota","Maine","Detroit","California","Tesla","Tucson","New Jersey","New York, Connecticut","Rhode Island","Massachusetts","Silicon Valley","Oregon","Germany","Hostetter","Japan","Fukushima"],"m_People":["Greg Gardnerdetroit","Chris Hostetter","Honda","Fcx Clarity","John Voelcker, Senior","Voelcker","Elon","Mike Millikin"],"m_Companies":["Free Press","State Of California","Hyundai","Air Liquide","Diesel","Tesla Motors"],"m_BiGrams":["fuel cell","cell car","fueling station","plugin electric"],"m_TriGrams":["fuel cell car"],"m_SocialTags":[],"m_Topics":[],"m_Industry":[],"m_Technology":[],"m_BiCnt":[12,5,4,3],"m_TriCnt":[5],"m_iDocBodyWordCnt":458}
