{"m_szDocID":"589423","m_szDocTitle":"When It Comes to Fuel Cell Cars, the Future Is Already Here - Los Angeles Magazine","m_szYear":"2016","m_szDocSumamry":"No Account? Register here. When It Comes to Fuel Cell Cars, the Future Is Already Here The world’s greenest vehicles are at the L.A. Auto Show, as well as the city’s showrooms Neal Broverman Transportation Comments The L.A. Auto Show always features some of the greenest cars on the road. This year is no exception, although there are several new zero emission vehicles being showcased that might surprise green car aficionados. A lot of people still think zero emission vehicles with long range and quick refueling times are years away from reality, but this year there are two new fuel cell electri","m_szDocBody":"account here fuel cell car future world greenest vehicle auto show city showroom neal broverman transportation comment auto show feature greenest car road year exception emission vehicle showcased surprise green car aficionados lot people emission vehicle long range quick refuelling time year reality year fuel cell electric vehicle fcevs arent featured auto showtheyre select showroom toyota hyundai betting big fuel cell electric vehicle offer performance greater cargo capacity longer range fast refuelling time theyve recently launched sedan toyota mirai compact suv hyundai tucson meanwhile honda announced offering clarity sedan late year you cheque auto show making north american debut well people dont realise fcevs operate electric motor traditional battery plugin electric vehicle nissan leaf chevy volt use relying battery fcevs utilise hydrogen fuel cell generate electricity chemical reaction hydrogen oxygen power electric motor result water vapour exhaust ongoing support governor brown governor schwarzenegger hydrogen highway fueling station coming online vehicle beginning sold station expected open state californiacontinue lead advancing clean car technology clean air reach state pollution reduction goal fight climate change fcevs latest car provide cleaner greener option california driver youll soonbrian goldstein brian goldstein executive director energy independence ein nonprofit organisation dedicated advancing fuel cell electric vehicle fcevs hydrogen fueling infrastructure required catalyse rapid transition clean energy transportation economy ","m_szGeo1":"United States","m_szSourceType":"source_news","m_szSrcUrl":"http://www.lamag.com/driver/when-it-comes-to-fuel-cell-cars-the-future-is-already-here/","m_Places":["L.a.","Toyota","California","Independence"],"m_People":["Neal Broverman","Honda","Schwarzenegger","Brian Goldstein","Ein"],"m_Companies":["Hyundai","Volt"],"m_BiGrams":["fuel cell","electric vehicle","auto show","cell electric"],"m_TriGrams":["fuel cell electric","cell electric vehicle"],"m_SocialTags":[],"m_Topics":[],"m_Industry":[],"m_Technology":[],"m_BiCnt":[5,4,3,3],"m_TriCnt":[3,3],"m_iDocBodyWordCnt":211}
