{"m_szDocID":"589491","m_szDocTitle":"Canadians believe hydrogen fuel cell vehicles, not battery electrics the way of the future - Canadian Manufacturing","m_szYear":"2015","m_szDocSumamry":"Canadians believe hydrogen fuel cell vehicles, not battery electrics the way of the future Study shows 64 per cent of Canadians ready to drive a hydrogen FCV August 11, 2015 Oil & Gas Hyundai’s 2016 Tucson Fuel Cell Vehicle. The company says Canadians are overwhelming positive on the outlook for cars power by hydrogen fuel cells. PHOTO: Hyundai MARKHAM, Ont.—The majority of Canadians would love to get their vehicles off gasoline, but they aren’t eager to turn to electric, a new Hyundai Auto Canada Corp. research study, carried out in partnership with Ipsos Reid and Offsetters, found. “[Hyundai","m_szDocBody":"canadian hydrogen fuel cell vehicle battery electric future study show cent canadian ready drive hydrogen fcv oil gas hyundais tucson fuel cell vehicle company canadian overwhelming positive outlook car power hydrogen fuel cell photo hyundai markham ontthe majority canadian love vehicle gasoline arent eager turn electric hyundai auto canada corp research study carried partnership ipsos reid offsetter found hyundai uncovered strong appetite canadian hydrogen fuel cell electric nongasoline powered vehicle showing time change auto industry automaker said consumer insight survey revealed canadian drive vehicle powered gasoline arent keen turn traditional battery electric vehicle cent surveyed indicating constantly charge bev pain cent feeling hassle drive instead canadian hoping top periodic table provide transport energy future cent canadian demonstrated appetite drive vehicle powered hydrogen cent hydrogen fuel cell powered vehicle future canadian spoken appetite hydrogenpowered vehicle strong percent people agree government provide support technology don romano president ceo hyundai canada said made fuel cell vehicle canadian hydrogen refuelling infrastructure follow support expansion time automotive manufacturer government hydrogen industry citizen join initiative create healthier environment generation hyundai noted price gasoline fluctuated wildly year make ecofriendly vehicle relevant surface but ipsos reid survey revealed cent canadian major benefit fuel cell vehicle reliant highly volatile fuel price significantly cent producing greenhouse gas emission major benefit fuel cell vehicle canadian irrefutably concerned vehicle tailpipe emission effort demonstrate benefit fuel cell technology canadian environment hyundai commissioned broad environmental impact study conducted offsetter taking consideration emission created production hydrogen fuel study found driving hyundai tucson fcev example result cent greenhouse gas emission compared driving comparable gasolinepowered vehicle welltowheel basis tucson fcev found emit fewer air contaminant result smog acid rain demonstrating direct benefit air quality densely populated city together study provide conclusive evidence canadian auto industry environmentallyfriendly option romano said fuel cell powertrain range ease refuelling canadian producing pure water vapour exhaust study surveyed canadian online accurate percentage point time share post ","m_szGeo1":"Canada","m_szSourceType":"source_news","m_szSrcUrl":"http://www.canadianmanufacturing.com/sustainability/canadians-believe-hydrogen-fuel-cell-vehicles-not-battery-electrics-the-way-of-the-future-152695/","m_Places":["Tucson","Markham","Hyundai Auto Canada Corp.","Canada"],"m_People":["Don Romano","Romano"],"m_Companies":["Hyundai","Hyundai Auto Canada Corp.","Ipsos"],"m_BiGrams":["fuel cell","hydrogen fuel","cell vehicle","canadian hydrogen","cent canadian","benefit fuel"],"m_TriGrams":["fuel cell vehicle","hydrogen fuel cell","benefit fuel cell"],"m_SocialTags":[],"m_Topics":[],"m_Industry":[],"m_Technology":[],"m_BiCnt":[10,5,5,3,3,3],"m_TriCnt":[5,3,3],"m_iDocBodyWordCnt":314}
