{"m_szDocID":"589421","m_szDocTitle":"10 Questions On Hydrogen Fuel-Cell Cars To Ask Toyota, Honda & Hyundai","m_szYear":"2014","m_szDocSumamry":"10 Questions On Hydrogen Fuel-Cell Cars To Ask Toyota, Honda & Hyundai Email This Page To (separate emails with commas) Message (optional) Your email was sent successfully. Close 20,915 views Oct 16, 2014 Follow John Enlarge Photo Within the next two years, three different hydrogen fuel-cell vehicles will be offered to California buyers in small numbers. The 2015 Hyundai Tucson Fuel Cell has been available to lease since June, and journalists will be able to drive the new Toyota fuel-cell vehicle in November, just before the Los Angeles Auto Show. That Toyota will hit the market roughly a year","m_szDocBody":"question hydrogen fuelcell car toyota honda hyundai separate email commas message optional successfully close view follow john enlarge photo year hydrogen fuelcell vehicle offered california buyer small number hyundai tucson fuel cell june journalist drive toyota fuelcell vehicle november los angele auto show toyota hit market roughly year now fuelcell car honda nevertheless scepticism remain analyst greencar fansoften including electriccar advocatesabout ultimate viability practicality hydrogenfueled vehicle north america hyundai tucson fuel cell delivered lessee tustin hyundai enlarge photo discussion automaker suggested behove product executive ready address question undoubtedly raised hydrogen vehicle roll out vein question executive hyundai toyota honda prepared respond update company california fuel cell partnership responded question answer part hydrogen fuelcell car question toyota honda hyundai respond part volume sale term hydrogen fuelcell car delivered number greater minimum required california air resource board zev rule launch and say sell fuelcell car outright only toyota fuel cell sedan aspen ideas festival photo riccardo savi enlarge photo batteryelectric plugin hybrid vehicle expected percent global auto productionor million vehicle year expect hydrogen fuelcell vehicle reach level there comparison batteryelectric vehicle main advantage hydrogen vehicle refuel mile minute tesla model supercharge mile minute analyst suggest larger battery quickcharged future higher power teslas kilowatt affordable batteryelectric car offer mile range recharge percent say minutesthen advantage hydrogen fuelcell car retain disadvantage early adopter requirement travel mile specific location refuel compared home workplace charging majority electriccar mile today honda fcev concept los angele auto show small strong vocal lobby owner supporter advocate advocated electric car year now similar groundswell fuelcell advocate consumer demand car fueling infrastructure energy balance sector private enterprise see profitmaking business building station selling hydrogen fuel sector industry station from risk capital build thousand hydrogen fueling station million million apiece ","m_szGeo1":"United States","m_szSourceType":"source_news","m_szSrcUrl":"http://www.greencarreports.com/news/1094899_10-questions-on-hydrogen-fuel-cell-cars-to-ask-toyota-honda-hyundai","m_Places":["Toyota","California","Los Angeles","North America","Tustin Hyundai","Dc","Tesla"],"m_People":["Zev","Riccardo"],"m_Companies":["Honda","Hyundai","Los Angeles","Tustin Hyundai","California Air Resources Board"],"m_BiGrams":["hydrogen fuelcell","fuelcell car","fuel cell","toyota honda","enlarge photo","fuelcell vehicle"],"m_TriGrams":["hydrogen fuelcell car"],"m_SocialTags":[],"m_Topics":[],"m_Industry":[],"m_Technology":[],"m_BiCnt":[6,6,4,3,3,3],"m_TriCnt":[4],"m_iDocBodyWordCnt":288}
