{"m_szDocID":"589488","m_szDocTitle":"OPINION: The New, New Thing — Hydrogen Fuel Cell Vehicles - Law360","m_szYear":"2015","m_szDocSumamry":"OPINION: The New, New Thing — Hydrogen Fuel Cell Vehicles   Law360, New York (April 21, 2015,  4:10 PM ET) -- Elon Musk, who introduced us to his Tesla electric car, scoffed at the notion of a hydrogen fuel cell vehicle. He called it a “fool cell.” A former U.S. Energy Secretary said that for hydrogen fuel cell cars to become a real choice “they need four miracles, and it only takes three to become a saint.” But it didn’t take four miracles! And it isn’t a “fool cell.” Just a few months ago, Toyota announced the world’s first commercial hydrogen fuel cell vehicle for sale. It... To view the fu","m_szDocBody":"opinion new hydrogen fuel cell vehicle law york april elon musk introduced tesla electric car scoffed notion hydrogen fuel cell vehicle called fool cell energy secretary hydrogen fuel cell car real choice miracle take saint didnt miracle isnt fool cell month ago toyota announced world commercial hydrogen fuel cell vehicle sale full article now ","m_szGeo1":"United States","m_szSourceType":"source_news","m_szSrcUrl":"http://www.law360.com/articles/645787/opinion-the-new-new-thing-hydrogen-fuel-cell-vehicles","m_Places":["Law360, New York","Tesla","Toyota"],"m_People":["Elon"],"m_Companies":[],"m_BiGrams":["hydrogen fuel","fuel cell","cell vehicle"],"m_TriGrams":["hydrogen fuel cell","fuel cell vehicle"],"m_SocialTags":[],"m_Topics":[],"m_Industry":[],"m_Technology":[],"m_BiCnt":[4,4,3],"m_TriCnt":[4,3],"m_iDocBodyWordCnt":54}
