{"m_szDocID":"589402","m_szDocTitle":"Hyundai Tuscon Fuel Cell hits Californian roads with free hydrogen","m_szYear":"2015","m_szDocSumamry":"Hyundai Tuscon Fuel Cell hits Californian roads with free hydrogen Image Gallery (4 images) The hydrogen economy sounds great, and has ever since it was first proposed in the 1970s. The tricky bit is how to get there, because without the necessary infrastructure, a fuel cell car that runs on hydrogen is little more than a conversation piece. As Hyundai delivers its first Tucson Fuel Cell CUV to its new lessee, Timothy Bush, the South Korean carmaker unveiled its plan to jump-start the hydrogen car economy by giving the fuel away to its customers. When Tustin Hyundai's Dealer Principal, John Pa","m_szDocBody":"hyundai tuscon fuel cell hit californian road free hydrogen image gallery image hydrogen economy sound great proposed tricky bit there infrastructure fuel cell car run hydrogen conversation piece hyundai deliver tucson fuel cell cuv lessee timothy bush south korean carmaker unveiled plan jumpstart hydrogen car economy giving fuel customer tustin hyundais dealer principal john patterson handed key hyundais tucson fuel cell bush monday marked time federally certified fuel cell car retail customer hyundai hydrogenfueled tucson number advantage electric car based petrolpowered tucson called market tucson fuel cell tin fuel cell internal combustion engine fuel cell create electricity combining hydrogen oxygen solid catalyst trigger electrochemical reaction combustion hyundai tucson fuel cell performance comparable electric vehicle including instant torque electric car lack noise similar mechanical simplicity fuel cell moving part tucson range refuel minute emission produce water vapour good problem tucson fuel cell car faced hydrogen powered vehicle fill tank electric car plug main overnight rare house hydrogen pipe installed make transition petrol engined car hydrogen bypassing electric hyundais solution special leasing agreement selling tucson fuel cell outright hyundai providing car month term agreement month clever bit hyundai pick cost hydrogen fuel customer free charge inducement company develop refuelling network addition lessee hyundais service valet maintenance programme faulty vehicle picked hyundai dealer loaner charge repair made hyundai tucson fuel cell backed california air resource board completed million test mile sery crash safety test hyundai began mass production south korea market reason california selected rollout state government committed building hydrogen fueling station end state spending million build station mobile refueler bring number station stage development hydrogenpowered fuel cell vehicle represent generation zeroemission vehicle technology thrilled leader offering massproduced tucson fuel cell retail customer dave zuchowski president chief executive officer hyundai motor america the range refuelling speed tucson fuel cell compare favourably gasoline vehicle making seamless transition customer traditional gasoline vehicle fuel cell technology increase adoption zeroemission vehicle benefit commitment state california support creating hydrogen fueling infrastructure important part decision offer fuel cell vehicle public tucson fuel cell cuv southern california hyundai dealer los county region win hyundai carson tustin hyundai hardin hyundai anaheim advertisement david szondy freelance writer based monroe washington awardwinning playwright contributed charged magazine website tale future past ","m_szGeo1":"United States","m_szSourceType":"source_news","m_szSrcUrl":"http://www.gizmag.com/2015-hyundai-tucson-fuel-cell-free-hydrogen/32488/","m_Places":["Tucson","Tustin Hyundai","South Korea","California","California Hyundai","Los Angeles","Anaheim","Washington"],"m_People":["Timothy Bush","Dave Zuchowski","Hardin","David Szondy"],"m_Companies":["Hyundai","Tustin Hyundai","Patterson","California Air Resources Board","Hyundai Motor America","State Of California","Los Angeles","Orange County"],"m_BiGrams":["fuel cell","tucson fuel","cell car","electric car"],"m_TriGrams":["tucson fuel cell","fuel cell car"],"m_SocialTags":[],"m_Topics":[],"m_Industry":[],"m_Technology":[],"m_BiCnt":[19,10,3,3],"m_TriCnt":[10,3],"m_iDocBodyWordCnt":367}
