{"m_szDocID":"589443","m_szDocTitle":"Fuel Cell Vehicles of 2016: Toyota Mirai vs. Hyundai Tucson","m_szYear":"2014","m_szDocSumamry":"Fuel Cell Vehicles of 2016: Toyota Mirai vs. Hyundai Tucson Reddit DAMIEN MEYER/AFP/Getty Images Whether America is ready or not, there will be two  fuel cell vehicles available to consumers in 2015. While questions linger about the actual green benefits  of hydrogen cars and just 8 public fueling stations exist in the target markets, Californians have a choice to make if you’re lucky enough to find a fuel cell vehicle on the agenda. Here is a look at the Toyota Mirai versus the Hyundai Tucson Fuel Cell on paper. 2016 Hyundai Tucson Fuel Cell There are already a limited number of Honda FCX Cla","m_szDocBody":"fuel cell vehicle toyota mirai hyundai tucson reddit damien image america ready not fuel cell vehicle consumer question linger actual green benefit hydrogen car publicfueling station exist target market californian choice make youre lucky afuel cell vehicle agenda atthe toyota mirai versus hyundai tucson fuel cell paper hyundai tucson fuel cell limited number honda fcx clarity hyundai fuel cell car road california limited number leaseonly term honda discontinued current model prepare launch hydrogen car contrast hyundai leased model tucson fuel cell hydrogen car date green car report consumer part lottery tucson fuel cell david image automaker model feature proton exchange membrane total output horsepower poundsfeet torque singlespeed transmission hit mile hour standstill second reacha top speed mile hour total range mile equivalent electric vehicle road youneed juiceit time fillup public hydrogen station california take about minute report driver limited fueling infrastructure lack service station familiar technology hyundai chosen offer tucson fuel cell part southern california month month due signing fuel maintenance included price duration theterm clean vehicle rebate available fuel cell version dimension inches inches inches height thecargo space gasolinetucson crossover toyota mirai purchase way source toyota toyota mirai obvious difference car sedan form mirai nonetheless toyotas fuel cell vehicle longer inches slightly wide inches considerably lower height inches solidpolymer electrolyte fuel cell stack generate horsepower poundsfeet torque hitting mile hour standstill second top speed mile hour power spec improvement tucson mirai cover mile range full tank hydrogen needing fillup mile tucson hyundai toyota offer mirai california northern california san francisco san jose map orange county areas los angele total dealership offer mirai purchase month month due signing starting fall buyer lessee advantage clean energy incentive automaker hope plan hydrogen fueling infrastructure continue planned california fuel cell partnership hope tohave station running meanwhile effort increase amount renewable produce hydrogen fuel continue official hope sourced renewable end technology mean place justtwo hydrogen car hitting roadthis year fuel cell vehicle making alegitimate debut advance fuel production station infrastructure hold key early success ability automaker offer affordable product coming year posted ","m_szGeo1":"United States","m_szSourceType":"source_news","m_szSrcUrl":"http://www.cheatsheet.com/automobiles/fuel-cell-vehicles-of-2016-toyota-mirai-vs-hyundai-tucson.html/?a=viewall","m_Places":["Toyota","America","California","Tucson","Northern","San Francisco","San Jose","Los Angeles"],"m_People":["Damien Meyer","Fcx Clarity","David Mcnew"],"m_Companies":["Reddit","Afp","Getty Images","Target","Honda","Hyundai","Orange County","Los Angeles"],"m_BiGrams":["fuel cell","cell vehicle","tucson fuel","hydrogen car","mile hour","toyota mirai","hyundai tucson"],"m_TriGrams":["tucson fuel cell","fuel cell vehicle"],"m_SocialTags":[],"m_Topics":[],"m_Industry":[],"m_Technology":[],"m_BiCnt":[13,5,5,4,4,3,3],"m_TriCnt":[5,4],"m_iDocBodyWordCnt":338}
