{"m_szDocID":"589444","m_szDocTitle":"Hyundai iX35 (Tucson) Hydrogen Fuel Cell Car Goes on Sale in UK Priced at £53,105 After Incentives | Transport Evolved","m_szYear":"2015","m_szDocSumamry":"Hyundai iX35 (Tucson) Hydrogen Fuel Cell Car Goes on Sale in UK Priced at £53,105 After Incentives Nikki Gordon-Bloomfield Self-confessed geek and mother of two, Nikki has been talking and writing about cars ever since she passed her driving test. Back then, her Internet contributions were all classic car-focused. Now, she’s all about greener, cleaner, safer and smarter cars. Hydrogen. SUV FCV Hyundai Crossover ix35 Tuscon In a move that makes it the first automaker in Europe to offer private customers the chance to own a hydrogen fuel cell car, South Korean automaker Hyundai has officially pr","m_szDocBody":"hyundai tucson hydrogen fuel cell car sale priced incentive nikki gordonbloomfield selfconfessed geek mother two nikki talking writing car passed driving test back then internet contribution classic carfocused now shes greener cleaner safer smarter car hydrogen suv fcv hyundai crossover tuscon move make automaker europe offer private customer chance hydrogen fuel cell car south korean automaker hyundai officially priced hyundai hydrogen fuel cell crossover suv hyundai tucson fcv place commerciallyavailable fuel cell car europe price range customer add car purchase grant prohydrogen european initiative price consumer drop buy hyundai tucson fuel cell suv expensive firstgeneration earlyadopter vehicle note postincentive pricingshould place hyundai strong market position toyota mirai hydrogen fuel cell sedan due sale europe year themsrpof toyotas limitedproduction fuel cell car expected weigh massive purchase grant higher electric car purchase grant weve seen hydrogen innovative vehicle hyfive european project including fifteen partner firm assist deployment hydrogen fuel cell vehicle europe coming month supported major automaker working hydrogen fuel cell technology daimler hyundai honda bmw toyota hyfive charged installing cluster hydrogen refuelling station part europe make hydrogen fuel cell vehicle practical option corporate private customer early evs infrastructure problem earlyadopter hyundai based hyundais gasolinepowered crossover suv name customised floor pan designed accommodate compressed hydrogen fuel tank hood kilowatt electric motor powered kilowatt proton exchange membrane hydrogen fuel cell small kilowatthour lithiumion battery pack capable providing kilowatt instantaneous power required allowing fcv operate battery power low speed operating fuel cell stack prove inefficient grant hyundai incentive nedc test cycle hyundai quote range mile fill combined kilogramme litre capacity twin hydrogen fuel tank mph take second vehicle rated epaapproved mile fill combined fuel efficiency mile gallon equivalent gallon gasoline kilogramme fuel energy density translate range mile kilogramme hydrogen toyota hyundai spent year developing hydrogen fuel cell technology attempt make cost affordable everyone hyundai fcv firm commerciallyavailable hydrogen fuel cell vehicle hyundai car fourthgeneration technology percent fuel efficient hyundais thirdgeneration test vehicle hyundai welcoming order private corporate buyer note ensure sufficient refuelling nearby map show live south england london operate hydrogen fuel cell car significant range anxiety living north impractical time latest new evolving transport dont forget followtransport evolvedon twitter channel latest new evolving transport dont forget followtransport evolvedon twitter channel support directly monthly supporting member simply share friend ","m_szGeo1":"United Kingdom","m_szSourceType":"source_news","m_szSrcUrl":"https://transportevolved.com/2015/05/05/hyundai-ix35-tucson-hydrogen-fuel-cell-car-goes-on-sale-in-uk-priced-at-53105-after-incentives/","m_Places":["Tucson","Uk","Tuscon","Europe","Toyota","England","London"],"m_People":["Nikki Gordon","Honda"],"m_Companies":["Hyundai","Tucson","Bmw","Epa","Twitter","Facebook","Youtube"],"m_BiGrams":["fuel cell","hydrogen fuel","cell car","hyundai tucson","purchase grant","cell vehicle"],"m_TriGrams":["hydrogen fuel cell","fuel cell car","fuel cell vehicle"],"m_SocialTags":[],"m_Topics":[],"m_Industry":[],"m_Technology":[],"m_BiCnt":[15,13,5,3,3,3],"m_TriCnt":[11,5,3],"m_iDocBodyWordCnt":375}
