{"m_szDocID":"589567","m_szDocTitle":"Renewable Hydrogen Fuel Cells For Hawaii","m_szYear":"2015","m_szDocSumamry":"September 3rd, 2015 by Tina Casey   Talk about burying the lede! Sandia National Laboratories just announced a fuel cell project to bring clean energy to the Port of Honolulu, Hawaii, but you have to read all the way down to the bottom of the press release to get to the juicy bits. Unlike your garden variety fuel cells, which run on hydrogen sourced from natural gas, this fuel cell project runs on renewable hydrogen courtesy of the US Air Force. Thanks, Air Force! The Business Case For Fuel Cells — At Ports Along with our sister sites Gas2.org and EVObsession.com, CleanTechnica has been hostin","m_szDocBody":"tina casey talk burying lede sandia national laboratory announced fuel cell project bring clean energy port honolulu hawaii read bottom press release juicy bit unlike garden variety fuel cell run hydrogen sourced natural gas fuel cell project run renewable hydrogen courtesy air force thank air force business case fuel cell port sister site gasorg evobsessioncom cleantechnica hosting lively discussion fuel cell electric vehicle example wide areas disagreement general consensus state technology pricey however business case fuel cell street vehicle case fuel cell market weve noticed logistic industry interested fuel cell electric vehicle warehouse operation application market stationary fuel cell move shipping port form market currently diesel generator power source choice ship port board auxiliary berth emission generator werent priority recent year department environmental protection began taking closer air quality port city alternatively ship hook onshore electrical grid grid rely fossil fuel shift emission port power plant study year sandia national laboratory hydrogen fuel cell potentially efficient costly diesel generator cope load fluctuation characterise energy port generator frequently producing maximum power hawaii application efficiency advantage fuel cell compared combustion engine widened hydrogen kilogramme potentially save ten thousand dollar year generator hydrogen fuel cell potentially emphasise potentially resolve shifting emission addition sourcing methane biogas fossil natural gas efficient technology emerging split hydrogen water solar wind energy hydrogen fuel cell hawaii bring hydrogen fuel cell project hawaii project leader sandia national laboratory hydrogen fuel cell generator positioned port hawaii shipping facility young brother ltd subsidiary foss maritime for record department transportation funding partner energy department fuel unit designed built hydrogenic consist kilowatt fuel cell hydrogen storage system powerconversion equipment packaged foot shipping container kilogramme onboard hydrogen storage generator energy power refrigerated container continuous hour operation writing fuel cell unit refrigerate container shore end goal include young brotherss barge mix renewable hydrogen fuel cell hawaii new picked interesting point grid diesel generator earlier summer hawaii governor david ige signed bill requiring renewable energy hawaii make fuel cell demo unnecessary ship hook electrical grid emission shifting that first hawaii law timeline extend plenty time fuel cell serve transitional role second fuel cell project designed introduce clean energy port cranking fossilenabled grid mix long past sandia lab foresee wider market project lead joe pratt longrange goal develop commercialready technology widely port project team see strong market desire fuel cell solution maritime port user arent connected grid extend developing country remote location worldwide loose end hydrogen production process youre sourcing hydrogen fossil gas biogas water significant energy input job done bring hickham air force base honolulu providing hydrogen fuel cell project hickham hotbed hydrogen fuel cell r&d recent solarpowered hydrogen production facility tandem hydrogen fueling station sandia covering base thought that leave note comment thread repetitive anyway fuel cell emerge competitively market technology improve company fighting market share driving market improvement mobile fuel cell aka fuel cell electric vehicle follow google image credit top screenshot sandia national laboratory bottom senior airman carolyn viss dmamil youd attend cleantechnica solar event date hottest cleantech new subscribing free cleantech newsletter eye sectorspecific new also free solar energy newsletter electric vehicle newsletter wind energy newsletter ","m_szGeo1":"United States","m_szSourceType":"source_news","m_szSrcUrl":"http://cleantechnica.com/2015/09/03/renewable-hydrogen-fuel-cells-hawaii-theres-came/","m_Places":["Hawaii","Young Brothers Ltd.","Honolulu"],"m_People":["Tina Casey","Foss","Young Brothers","David Ige","Sandia","Joe Pratt","Carolyn Viss"],"m_Companies":["Sandia National Laboratories","Us Air Force","Air Force","Diesel","Us Department Of Environmental Protection","Young Brothers Ltd.","Maritime","Us Department Of Transportation","Energy Department","Twitter","Google"],"m_BiGrams":["fuel cell","hydrogen fuel","cell project","sandia national","national laboratory","electric vehicle","energy port","air force","case fuel","cell electric","diesel generator"],"m_TriGrams":["hydrogen fuel cell","fuel cell project","sandia national laboratory","case fuel cell","fuel cell electric","cell electric vehicle"],"m_SocialTags":[],"m_Topics":[],"m_Industry":[],"m_Technology":[],"m_BiCnt":[27,8,5,4,4,4,3,3,3,3,3],"m_TriCnt":[8,5,4,3,3,3],"m_iDocBodyWordCnt":514}
