{"m_szDocID":"589578","m_szDocTitle":"Why Do Fuel-Cell Vehicles Make Electric-Car Advocates So Crazy?","m_szYear":"2015","m_szDocSumamry":"Why Do Fuel-Cell Vehicles Make Electric-Car Advocates So Crazy? Email This Page To (separate emails with commas) Message (optional) Your email was sent successfully. Close 11,316 views Jul 28, 2015 Follow John Enlarge Photo Last Thursday, Green Car Reports published a story noting that the several dozen drivers of Hyundai Tucson Fuel Cell vehicles had expressed deep frustration with the unreliability of Southern California's current hydrogen fueling stations. That story hit a chord; as of this morning, it's accumulated more comments than any other article we've published, with 1,870 now and po","m_szDocBody":"fuelcell vehicle make electriccar advocate crazy separate email commas message optional successfully close view follow john enlarge photo thursday green car report published storey noting dozen driver hyundai tucson fuel cell vehicle expressed deep frustration unreliability southern californias current hydrogen fueling station storey hit chord morning accumulated comment published possibly end day miss fuelcell car driver hydrogen fuel unavailable station work mean comment pageview stunning startling volume indeed third comment highly negative concept hydrogen fuelcell vehicle vigorously viscerally tenor comment illustrate appear emerging fact zeroemission vehicle world electriccar advocate disdain hydrogenpowered vehicle increasingly fuelcell car major manufacturer start hit road hyundai tucson fuel cell hydrogen fueling station fountain valley roughly onehalf comment total highly prolific argumentative regular commenter weighed well identify electriccar owner advocate tone largely negative lead considerable pushback smaller number devoted hydrogen advocate commenter see question hydrogen fuelcell car toyota honda hyundai oct led numerous violation green car report commenting code forbid direct personal insultsof commenter author named sourcesas profanity polite time folk moderated regular reader green car report should point familiar point raised electriccar advocate fuelcell vehicle toyota mirai showroom hydrogen fueling station tokyo japan enlarge photo include higher carbon footprint mile required drive hydrogen versus energy recharge batterypowered car substantial cost billion dollar creating regional hydrogen fueling network ubiquitous north american network give coverage today gas station concern hydrogen end costing roughly mile gasoline electricity costpermile consumer lower time lower belief automaker hydrogen vehicle delaying tactic retard world inevitable transition electric vehicle powered grid belief big oil hydrogen vehicle maintain market fossil fuel hydrogen today made natural gas numerous antielectric car statement advertisement toyota main proponent hydrogen fuel cell worthwhile issue explore understand intensity rawness debate put politely see hyundai tucson fuel cell early driver discuss experience travelling hydrogen green car report work hard maintain civil discourse comment fervour passion commenter reflect nature internet debate people whove met lowercarbon future sight fear messagea hard deliver iswill muddied explanation too feedback reader impact hand grenade garden party think editor note gently remind reader civil avoid direct personal attack insult speak science politic issue advance ","m_szGeo1":"United States","m_szSourceType":"source_news","m_szSrcUrl":"http://www.greencarreports.com/news/1099288_who-do-fuel-cell-vehicles-make-electric-car-advocates-so-crazy","m_Places":["California","Ca","Toyota","Tokyo","Japan"],"m_People":["Drivers","Honda"],"m_Companies":["Indeed","Hyundai","Remind"],"m_BiGrams":["green car","car report","fuel cell","hydrogen fueling","fuelcell vehicle","electriccar advocate","hyundai tucson","tucson fuel","fueling station","fuelcell car"],"m_TriGrams":["green car report","hyundai tucson fuel","tucson fuel cell","hydrogen fueling station"],"m_SocialTags":[],"m_Topics":[],"m_Industry":[],"m_Technology":[],"m_BiCnt":[4,4,4,4,3,3,3,3,3,3],"m_TriCnt":[4,3,3,3],"m_iDocBodyWordCnt":347}
