{"m_szDocID":"589529","m_szDocTitle":"JCB just bought a controlling stake in a hydrogen fuel cell company. Hmmm… | Equipment World | Construction Equipment, News and Information | Heavy Construction Equipment","m_szYear":"2015","m_szDocSumamry":"JCB just bought a controlling stake in a hydrogen fuel cell company. Hmmm…   Wayne Grayson |  March 13, 2015 | JCB, the third-largest manufacturer of construction equipment in the world, just made a very interesting announcement that could point to future machines from the company being powered by hydrogen fuel cells. Through its Research arm, JCB has purchased more than 16 million shares valued at $7.21 million (£4.9 million) for a controlling stake in ITM Power. ITM is an energy company primarily concerned with hydrogen energy systems and hydrogen fuel cells. All of the company’s products us","m_szDocBody":"jcb bought controlling stake hydrogen fuel cell company hmmm wayne grayson march jcb thirdlargest manufacturer construction equipment world made interesting announcement point future machine company powered hydrogen fuel cell research arm jcb purchased million share valued million million controlling stake itm power itm energy company primarily concerned hydrogen energy system hydrogen fuel cell company product process called electrolysis create hydrogen water electrolyser split water molecule hydrogen oxygen cleaner process hydrogen traditionally created fossil fuel thisitm call process green hydrogen production now primary application itm electrolysersfor called powertogas energy storage itm hgas system create hydrogen introduce natural gas distribution system fuel heat mobility power generation second obvious and intriguing application hydrogenpowered vehicle itm put electrolyser portable stationsabout size shipping container capable refuelling hydrogen fuel cell car fuel hybrid itm refuel fuel cell electric vehicle fcev minute stored hydrogen gas giving vehicle range mile fact itmis businesse organisation involved husa public private partnership launched department energy order boost development fcevs jcb intend controlling stake itm developing hydrogenpowered hydrogen hybrid construction equipment statement jcb chairman lord anthony bamford company excited prospect hydrogen technology noting jcb forward tosharing expertise manufacturing engineering itm however itm ceo graham cooley added company plan scale business enter market speculation aside interesting investment industry expert technology future primary fuel source doubtful rise electric car surprise tesla founder elon musk recently referred vehicle powered hydrogen silly youre pick energy storage mechanism hydrogen extremely dumb pick musk recent stop detroit nonetheless car maker continuing explore technology toyota recently debuted mirai fcev sale california beginning fall beside hydrogen doesnt make splash car world doesnt prove suitable solution hybrid power industrial application interesting jcb take technology ","m_szGeo1":"United States","m_szSourceType":"source_news","m_szSrcUrl":"http://www.equipmentworld.com/jcb-just-bought-a-controlling-stake-in-a-hydrogen-fuel-cell-company-hmmm/","m_Places":["Tesla","Detroit","Toyota","California"],"m_People":["Wayne Grayson","Itm Power","Anthony Bamford","Graham Cooley","Elon","Mirai Fcev"],"m_Companies":["Hgas"],"m_BiGrams":["fuel cell","hydrogen fuel","controlling stake"],"m_TriGrams":["hydrogen fuel cell"],"m_SocialTags":[],"m_Topics":[],"m_Industry":[],"m_Technology":[],"m_BiCnt":[5,4,3],"m_TriCnt":[4],"m_iDocBodyWordCnt":273}
