{"m_szDocID":"589590","m_szDocTitle":"Seven Barriers To Alt-Fuel Vehicles: Can Hydrogen Fuel Cells Overcome Them?","m_szYear":"2015","m_szDocSumamry":"Seven Barriers To Alt-Fuel Vehicles: Can Hydrogen Fuel Cells Overcome Them? Email This Page To (separate emails with commas) Message (optional) Your email was sent successfully. Close 3,669 views Jun 24, 2015 2015 Hyundai Tucson Fuel Cell, 2016 Toyota Mirai at hydrogen fueling station, Fountain Valley, CA Enlarge Photo Among owners and advocates of zero-emission vehicles, few topics generate as much back-and-forth debate (to put it politely) as those cars powered by hydrogen fuel cells. Discussions of wells-to-wheels carbon footprint, the presently nonexistent hydrogen fueling infrastructure, ","m_szDocBody":"barrier altfuel vehicle hydrogen fuel cell overcome them separate email commas message optional successfully close view hyundai tucson fuel cell toyota mirai hydrogen fueling station fountain valley enlarge photo owner advocate zeroemission vehicle topic generate backandforth debate put politely car powered hydrogen fuel cell discussion wellstowheel carbon footprint presently nonexistent hydrogen fueling infrastructure purported advantage electric car produce energetic discussion miss question hydrogen fuelcell car toyota honda hyundai blogger joe romm created consider stipulation alternativefueled vehicle successful longterm market thinkprogress author elon muskclass critic hydrogen outlined barrier faced nongasoline vehicle recent post fuel cell mind are toyota mirai construction motomachi plant enlarge photo cost vehicle partially addressed toyotas megafactory jumpstart experience curve effect bringing sticker price onboard fuel storage addressed toyota mirai hyundai tucson fuelcell vehicle adequate range cargo space safety liability concern addressed tucson fuel cell customer pump hydrogen canada japan attendant pumping then generally pump gasoline hyundai tucson fuel cell hydrogen fueling station fountain valley fueling cost compared gasoline still barrier limited fuel station still huge barrier improvement competition partially addressed toyota expect fuelcell vehicle price premium equivalent hybrid vehicle economy scale fully realised problem delivering costeffective emission reduction major barrier usbut europe natural gas time expensive hydrogen renewableelectricity electrolysis costcompetitive hydrogen natural gas reforming for breakdown renewable hydrogen tab see toyota fuelcell megafactory matches tesla gigafactory impact romm list fact provide put impact toyotas megafactory context doubling global production protonexchange membrane fuel cell single year wont solve intractable fuel cell face infrastructure build scratch dozen hundred hydrogen fueling station region support population ten thousand hydrogenpowered vehicle hyundai tucson fuel cell hydrogen fueling station fountain valley enlarge photo toyotas announcement put smaller piece puzzle place kickstart production growth nascent hydrogen fuelcell vehicle industry begin reaping benefit experience curve effectsand cost reduction inevitably ensue word enable car built economically perhap half battle ","m_szGeo1":"Canada","m_szSourceType":"source_news","m_szSrcUrl":"http://www.greencarreports.com/news/1098821_seven-barriers-to-alt-fuel-vehicles-can-hydrogen-fuel-cells-overcome-them","m_Places":["Toyota","Ca","Motomachi Plant","Tucson","Canada","Japan","Europe","Tesla"],"m_People":["Honda","Joe Romm","Elon","Romm"],"m_Companies":["Seven","Hyundai"],"m_BiGrams":["fuel cell","hydrogen fueling","hyundai tucson","tucson fuel","fueling station","toyota mirai","station fountain","fountain valley","enlarge photo","fuelcell vehicle"],"m_TriGrams":["tucson fuel cell","hydrogen fueling station","hyundai tucson fuel","fueling station fountain","station fountain valley"],"m_SocialTags":[],"m_Topics":[],"m_Industry":[],"m_Technology":[],"m_BiCnt":[9,5,4,4,4,3,3,3,3,3],"m_TriCnt":[4,4,3,3,3],"m_iDocBodyWordCnt":303}
