{"m_szDocID":"589625","m_szDocTitle":"2016 Toyota Mirai Hydrogen Fuel-Cell Car: Quick Drive","m_szYear":"2016","m_szDocSumamry":"2016 Toyota Mirai Hydrogen Fuel-Cell Car: Quick Drive Email This Page To (separate emails with commas) Message (optional) Your email was sent successfully. Close 5,184 views Aug 6, 2015 Follow Bengt Add to circle While auto-industry insiders, analysts, and tech-savvy early adopters are split on whether a hydrogen infrastructure is viable in the near future, several automakers are pushing forward with productâ€”and hoping that infrastructure (and more product) will follow. At present, those automakers making significant investment in fuel-cell vehicles are Honda, Toyota, and Hyundai (with Nissan ","m_szDocBody":"toyota mirai hydrogen fuelcell car quick drive separate email commas message optional successfully close view follow bengt add circle autoindustry insider analyst techsavvy early adopter split hydrogen infrastructure viable future automaker pushing forward productand hoping infrastructure and product follow present automaker making significant investment fuelcell vehicle honda toyota hyundai with nissan recently investing year hyundai offering tucson fuel cell vehicle los angele region month due signing theyve vehicle household model southern california hydrogen infrastructure toyota mirai unlike tucson fuel cell mirai designed engineered fuelcell powertrain toyota hope mirai sedan worldwide end month down delivery beginning october production spring summer quietly ramping rate day mirai mile mile officially single tank hydrogenwhich toyota pointed out farther longestrange version tesla model electric car havent course tested range toyota argue theyre solution versus batteryelectric model long range quick refuelling time minute but ten account quietdriving big comfortable electric sedan past week portland chance make quick driving loop miraispecifically prototype drive mile altogether mph confirm earlier impression car driving experience mirai ride large comfortoriented sedan plush quiet insidemore toyotas fullsize avalon sedan ride quality priusand capacitive control bear likeness avalon backseat space limited avalon though due packaging fuelcell hardware floor performance lively provided youre low speed electric vehicle mirai accelerate strongly mph sluggish that toyota claim mph time second simplify fuel cell battery doesnt recharged refuelled hydrogen hydrogen long issue transporting tricky take considerable energy reform hydrogenoften natural gas fuel station recent issue infrastructure needed station posed issue recently driver hyundai tucson fuel cell toyota expect station operation end year station planned funded toyota mirai enlarge photo mirai store hydrogen roughly pressure about psi previous generation fuelcell vehicle didnt driving range impressive previous iteration fuelcell vehicle tended loud whirring whining bit vacuum cleaner system fed hydrogen fuelcell stack proper rate newer generation fuel cell smaller higherpressure tank lighter compact vehicle quiet battery electric car mirai sound background rising slightly correspond quicker aggressive driving exterior styling design mirai different loud itll turn head people talking hydrogen fuel cellswhich part point ","m_szGeo1":"United States","m_szSourceType":"source_news","m_szSrcUrl":"http://www.thecarconnection.com/news/1099480_2016-toyota-mirai-hydrogen-fuel-cell-car-quick-drive","m_Places":["Toyota","Tucson","Los Angeles","Southern","California","Portland","Avalon"],"m_People":["Honda"],"m_Companies":["Hyundai","Los Angeles","Ramping","Seat"],"m_BiGrams":["fuel cell","toyota mirai","fuelcell vehicle","tucson fuel"],"m_TriGrams":["tucson fuel cell"],"m_SocialTags":[],"m_Topics":[],"m_Industry":[],"m_Technology":[],"m_BiCnt":[5,3,3,3],"m_TriCnt":[3],"m_iDocBodyWordCnt":334}
