{"m_szDocID":"589657","m_szDocTitle":"Honda's hydrogen fuel cell sedan can power your entire house","m_szYear":"2015","m_szDocSumamry":"Honda's hydrogen fuel cell sedan can power your entire house 7.4k Honda Clarity Fuel Cell will go 434 miles on a single tank of hydrogen. Image:  Honda 2015-10-27 22:25:09 UTC Honda unveiled its first production hydrogen-powered fuel cell sedan, the Clarity Fuel Cell, at the Tokyo Motor Show on Tuesday. Though Honda has dabbled in hydrogen power since the late 1980s, the five-passenger Clarity Fuel Cell sedan is the first hydrogen-powered model that the Japanese carmaker has intended to offer up to the public. See also: Construction of $150 million hyperloop test track beginning in weeks Image","m_szDocBody":"hondas hydrogen fuel cell sedan power entire house honda clarity fuel cell mile single tank hydrogen image honda utc honda unveiled production hydrogenpowered fuel cell sedan clarity fuel cell tokyo motor show tuesday honda dabbled hydrogen power late fivepassenger clarity fuel cell sedan hydrogenpowered model japanese carmaker intended offer public also construction million hyperloop test track beginning week image honda quick refresher hydrogen fuel cell vehicle car transform hydrogen unit called fuel cell stack electricity fed lithiumion battery pack electric motor turn drive wheel essentially electric vehicle refilled minute emit water vapour tailpipe clarity fuel cell represent leap forward hydrogen fuel cell vehicle fcvs honda managed shrink size hydrogen fuel cell stack size gasoline engine compact shape designer fit underneath hood car fcvs point fuel cell large needed packaged vehicle toyotas mirai fuel cell stack centre vehicle cutting interior space image honda fuel cell stack hood gasolinepowered car cabin shaped standard fivepassenger layout room comfortably seat adult full hydrogen clarity fuel cell travel mile single charge toyota mirai junky honda boast fuel cell stack power output electric motor drive wheel maximum output love translate mph time honda revealed figure image honda acceleration aside honda revealed cool feature clarity fuel cell plugged honda gizmo called power exporter clarity fuel cell produce electricity power average home approximately day perfect natural disaster run mill power outage granted honda mean average japanese house american home number bit power exporter stateside honda begin leasing clarity fuel cell japanese municipality businesse open sale general public entry european market that now clarity fuel cell priced million yen hold price offered america unclear image honda ","m_szGeo1":"United States","m_szSourceType":"source_news","m_szSrcUrl":"http://mashable.com/2015/10/27/honda-clarity-fuel-cell/","m_Places":["Tokyo","Toyota","America"],"m_People":["Honda"],"m_Companies":["Seat","Mill"],"m_BiGrams":["fuel cell","clarity fuel","image honda","cell stack","hydrogen fuel","cell sedan"],"m_TriGrams":["clarity fuel cell","fuel cell stack","hydrogen fuel cell","fuel cell sedan"],"m_SocialTags":[],"m_Topics":[],"m_Industry":[],"m_Technology":[],"m_BiCnt":[19,9,5,5,4,3],"m_TriCnt":[9,5,4,3],"m_iDocBodyWordCnt":267}
