{"m_szDocID":"589618","m_szDocTitle":"Mercedes-Benz to create hydrogen fuel cell GLC Class by 2018","m_szYear":"2015","m_szDocSumamry":"Home / Interesting / Mercedes-Benz to create hydrogen fuel cell GLC… Mercedes-Benz to create hydrogen fuel cell GLC Class by 2018 Tweet BMW took quite a bit of flak from the EV-loyal crowd when it said that it would be heavily investing in hydrogen fuel. Most EV … BMW took quite a bit of flak from the EV-loyal crowd when it said that it would be heavily investing in hydrogen fuel . Most EV fans tend to think that hydrogen fuel is a waste of time and money and that those resources should be spent into pure battery electric vehicles. The reason for this opinion is that most people tend to think ","m_szDocBody":"home interesting mercedesbenz create hydrogen fuel cell glc mercedesbenz create hydrogen fuel cell glc class tweet bmw bit flak evloyal crowd heavily investing hydrogen fuel bmw bit flak evloyal crowd heavily investing hydrogen fuel fan tend hydrogen fuel waste time money resource spent pure battery electric vehicle reason opinion people tend evs future hydrogen fuel stopgap waste time resource however automaker tend feel otherwise hydrogen fuel answer now point hydrogen abundant element universe put emission refuelled minute gasoline vehicle hydrogen vehicle benefit electric vehicle emission greater efficiency sustainable future benefit gasoline diesel car easy refuelling pay instal charging station home hydrogen vehicle surface cake eat too people disagree tesla owner elon musk however isnt stopping automaker jumping board hydrogen train bmw toyota honda board weve word mercedesbenz mix bmw sery hydrogen fuel cell recent report autocar mercedesbenz planning hydrogen fuel cellpowered variant brandnew glc class crossover glc fcell mercede calling due premier frankfurt motor show sale mercedesbenz claiming range fast refuelling time targeting combined range fuel cell battery mile refuelling time hydrogen tank minute saidthomas weber mercedesbenzs head research development early report mercedesbenz creating hydrogen variant current class electric vehicle however due cost purpose mercede forced utilise upscale vehicle hydrogen fuel cell car technology matured greatly recent year improved packaging efficiency remain infancy expensive conventional driveline standard weber bmw hydrogen fuel cell prototype debate hydrogen current answer armchair engineer sit back talk know end day automaker what industry whole automotive giant bmw toyota mercedesbenz heavily investing technology good reason bmw isnt foolish spending resource hydrogen fuel technology competitor well hydrogen isnt beallendall answer carmaker bmw carmakerat party one ","m_szGeo1":"","m_szSourceType":"source_news","m_szSrcUrl":"http://www.bmwblog.com/2015/11/22/mercedes-benz-to-create-hydrogen-fuel-cell-vehicle-by-2018/","m_Places":["Tesla","Toyota","Frankfurt"],"m_People":["Elon","Honda","Mercedes","Thomas Weber"],"m_Companies":["Mercedes-benz","Bmw","Diesel","Autocar"],"m_BiGrams":["hydrogen fuel","fuel cell","heavily investing","electric vehicle"],"m_TriGrams":["hydrogen fuel cell"],"m_SocialTags":[],"m_Topics":[],"m_Industry":[],"m_Technology":[],"m_BiCnt":[12,6,3,3],"m_TriCnt":[5],"m_iDocBodyWordCnt":268}
