{"m_szDocID":"589664","m_szDocTitle":"Kia believes hydrogen is the best answer for tomorrow's cars","m_szYear":"2015","m_szDocSumamry":"Kia believes hydrogen is the best answer for tomorrow’s cars December 14, 2015 | In: Green Car Industry , Technology Leave a Comment Dr Sae Hoon Kim is the head of environmental research and development for Kia and Hyundai. Just as Elon Musk believes passionately in battery electric cars, Kim believes passionately in hydrogen fuel cell cars. Dr. Kim says Kia will begin producing a fuel cell vehicle built on a dedicated chassis in 2020. A fuel cell car and a battery electric car are kissing cousins. One gets charged from the electrical grid and carries that stored energy around with it. The oth","m_szDocBody":"kia believe hydrogen answer tomorrow car green car industry technology leave comment sae hoon kim head environmental research development kia hyundai elon musk believe passionately battery electric car kim believe passionately hydrogen fuel cell carsdr kim kia begin producing fuel cell vehicle built dedicated chassis fuel cell car battery electric car kissing cousin charged electrical grid carry stored energy make electricity rely electric motor move road kia plan leader green car transportation hybrid plugin hybrid battery fuel cell car portfolio isspending billion hiring engineer work advanced low zerocarbon powertrain day technology meet regulation kim europe manufacturer average carbon dioxide exceed gramme kilometre the emission hybrid average gramme kilometre hit regulationtarget those kim trend plugin hybrid fuel cell lot manufacturer kim say honda start selling fuel cell vehicle daimler enter market bmw volkswagen join kim answer objection future fuel cell carsworld hydrogen production million tonne million fuel cell vehicle say produced kind energy moment byproduct future hydrogen renewable say store man control supply demand king produce hydrogen electricity store easily lack backup infrastructure form refuelling network political issue cost issue kim say german writer germany put reach hydrogen station cost kilometre highway korea kilometre kim claim obstacle relation safety extreme weather performance fuel cell system overcome remain solved long term durability introduction support infrastructure make mass production feasible bring cost guaranteeing year reliability guarantee year work lot say difficulty heat rejection temperature system installed car designed internal combustion engine bespoke car add bigger radiator cold weather performance diesel range refuelling key factor favour fuel cell car morerange conventional car time refuel hydrogen refuelling station make fuel cell car choice mainstream driver question wont answer decade more share ","m_szGeo1":"Germany","m_szSourceType":"source_news","m_szSrcUrl":"http://ecomento.com/2015/12/14/kia-believes-hydrogen-is-the-best-answer-for-tomorrows-cars/","m_Places":["Europe","Germany","Korea"],"m_People":["Sae","Hoon","Kim","Elon","Honda"],"m_Companies":["Hyundai","Bmw","Volkswagen","Diesel"],"m_BiGrams":["fuel cell","cell car","cell vehicle"],"m_TriGrams":["fuel cell car","fuel cell vehicle"],"m_SocialTags":[],"m_Topics":[],"m_Industry":[],"m_Technology":[],"m_BiCnt":[11,4,3],"m_TriCnt":[4,3],"m_iDocBodyWordCnt":276}
