{"m_szDocID":"589643","m_szDocTitle":"Taking the Hyundai Tucson FCEV out for a spin | Metro News","m_szYear":"2015","m_szDocSumamry":"Taking the Hyundai Tucson FCEV out for a spin Hydrogen-fuelled, zero-emissions vehicle now on the streets of Surrey, B.C. Share on Facebook The Hyundai Tucson FCEV looks like a regular Tucson ... until you open it up. By: Mike Goetz For Metro Published on Last week I drove an example of the first fuel-cell vehicle to go on sale in Canada. The first jolt was that the Hyundai Tucson FCEV looks alarmingly like any other 2013 to 2015 Tucson. Your brain expects a car that runs on a chemical process (expressed in very long and complicated formulas) to turn hydrogen into electricity to not look like ","m_szDocBody":"taking hyundai tucson fcev spin hydrogenfuelled zeroemission vehicle street surrey share hyundai tucson fcev regular tucson open mike goetz metro published week drove fuelcell vehicle sale canada jolt hyundai tucson fcev alarmingly tucson brain expect car run chemical process expressed long complicated formulas turn hydrogen electricity compact suv rented year ago airport hyundai canadas communication manager chad heard open fcevs hatch show cargo floor inches higher regular tucson underneath bigger hydrogen storage tank the other smaller tank passenger seat fcevs tank rated psi hold hydrogen kilometre magic happen heard next lifting front hood hyundais proprietary fuel cell turn hydrogen electricity completely housed engine bay tight fit there packed battery storing electricity electric motor capable lbft torque transaxle connecting motor front wheel mike metro rear bigger hydrogen storage tank mike metro hood proprietary fuel cell engine bay heard throw key climb short drive lunch episode jerry seinfeld comedian car coffee comedy star power thousand view fact driving future emissionsbelching oldtimey sport car hit start button instrument life powertrain sound regular hybrid cold bit fuel cell working battery power shift drive drive virtually electric vehicle seamless smooth silent propulsion loudest sound heater fan tyre noise hear sense fuel cell powering motor charging battery both simply standby conserve hydrogen thing good acceleration town highway speed problem feel bit slow fcev good chunk heavier regular tucson extra weight upfront affect handling somewhat adjust nature easily forget youre driving hydrogenpowered vehicle emission hydrogen future hold reason driving fuelcell car substandard experience great experience tucson threeyear lease month include free hydrogen maintenance leased far surrey area home canadas publicly accessed hydrogen refuelling station dealership trained equipped fuelcell vehicle lot one hyundai make fuelcell experience good prospective buyer now effectively mean customer area country kind shame ","m_szGeo1":"Canada","m_szSourceType":"source_news","m_szSrcUrl":"http://www.metronews.ca/drive/2015/12/22/taking-the-tucson-fcev-out-for-a-spin.html","m_Places":["Surrey","Tucson","Canada"],"m_People":["Mike Goetz","Chad Heard","Jerry Seinfeld"],"m_Companies":["Facebook","Hyundai","Hatch","Seat"],"m_BiGrams":["fuel cell","hyundai tucson","tucson fcev","regular tucson"],"m_TriGrams":["hyundai tucson fcev"],"m_SocialTags":[],"m_Topics":[],"m_Industry":[],"m_Technology":[],"m_BiCnt":[4,3,3,3],"m_TriCnt":[3],"m_iDocBodyWordCnt":289}
