{"m_szDocID":"589645","m_szDocTitle":"Hydrogen Fuel Cell Cars Return for Another Run  - The New York Times","m_szYear":"2015","m_szDocSumamry":"The New York Times Automobiles |Hydrogen Fuel Cell Cars Return for Another Run Advertisement By LAWRENCE ULRICH APRIL 16, 2015 Inside Photo A refilling station for hydrogen fuel cell vehicles near the University of California, Irvine. Credit Stuart Palley for The New York Times Advertisement Continue reading the main story FOR decades, hydrogen has been the Dracula of automotive fuels: Just when you think a stake has been driven through its zero-emissions heart, the technology rises from the grave. In 2015, even with gasoline cheaper than it has been in years, hydrogen is back to haunt those w","m_szDocBody":"york time automobile hydrogen fuel cell car return run advertisement lawrence ulrich inside photo refilling station hydrogen fuel cell vehicle university california irvine credit stuart palley york time advertisement continue reading main storey decade hydrogen dracula automotive fuel stake driven zeroemission heart technology rise grave gasoline cheaper year hydrogen back haunt insist battery electric vehicle longterm solution reducing fossil fuel consumption carbon dioxide emission time hydrogen fuel cell cost falling significantly tiny budding network public fueling station automaker placing latest longodd bet hydrogen car hyundai latest wave fuel cell model electric car important difference plugin battery draw power electrical grid fuel cell generate power electrochemical reaction onboard hydrogen oxygen air clean water trickle tailpipe byproduct technical riposte battery electric vehicle generally travel mile charge hour recharge fuel cell car operate conveniently gasoline model travel roughly mile tank ultrastrong carbonfiber tank pumped full hydrogen minute count david uselton wife suelyn true believer june couple dana point california family hydrogen version hyundai tucson crossover sport utility vehicle paying month down decisively tucson gasoline engine perk include purchase rebate state year worth free hydrogen hyundai uselton director global ecommerce company remember teenage son assembling toy car model year ago toy scooted floor powered fuel cell sunlight generate hydrogen water advertisement continue reading main storey thought cool asked car work this uselton said people leased hydrogenfueled tucson uselton checked hyundai ensure car fit lifestyle criteria included geographic proximity public hydrogen station operating los angele san francisco shamelessly drive dealership part programme uselton say enthusiasm driven belief automobile require reinvention oil forever said combustion engine longterm answer grandchildren answer there uselton appreciate tucson roomier typical small electric car swallowing gear weekend music gig unlike battery evs hydrogen technology easily scale power larger vehicle advertisement continue reading main storey devin lindsay powertrain analyst ihs automotive evs work people drive set distance plan trip charging hydrogen fit people spent lifetime pumping gasoline evs arent consumer lindsay said fuel cell promising range fillup time match weve grown with paper hydrogen car green dream arent people driving them proponent note hydrogen abundant element universe deriving element efficiently major catch dearth place refuel car onboard fuel cell storage tank exorbitantly expensive honda tested fcx fuel cell car california analyst estimated car cost million produce automaker talked hydrogen car sceptic technology pipe dream automaker hand way forced californias powerful regulator decreed largest automaker build increasing number zeroemission model goal percent car produce tailpipe emission automaker receive credit california fuelcell car produce versus battery electric californias rebate fuelcell car buyer compare industry analyst labelled costly slowselling hydrogen model compliance car created satisfy regulation consumer demand general motor introduced test fleet chevrolet equinox hydrogen suvs company boldly predicted sell million fuelcell vehicle development stalled industry turned attention evs plugin hybrid honda mercede leased small test fleet hydrogen car california customer small honda put fcx fcx clarity model consumer hand million passenger car californias road barely carry hydrogen onboard still automaker including toyota unmatched king hybrid remain bullish hydrogen toyota offer mirai fuel cell compact year exclusively california now car mean future japanese honda follow car based streamlined fcv concept model toyota began developing hydrogen technology year ago began work prius hybrid john hanson toyotas spokesman advanced technology company reduced mirais fuel cell cost percent compared previousgeneration car toyota linked bmw develop fuel cell alliance formed honda daimler ford nissan advertisement continue reading main storey answer vexing chickenandegg question automaker providing seed money operate fueling station reassuring energy provider build them car customer eventually come california committed million year develop station expected operation end uselton hope station open north los angele extend hyundais range visit daughter college student santa barbara today hydrogen derived natural gas production diminishing environmental edge backer promise producing hydrogen splitting water solar wind renewable power fountain valley calif uselton fill tucson demonstration station created energy department grant turn municipal waste hydrogen fuel car day lindsay ihs internal combustion engine continuing evolve improve decade majority american switch alternativefuel car car infrastructure hydrogen valuable part energy portfolio end emission technology move gasoline said toyota confident sell mirais small number company envision hydrogen nucleus spread east coast eventually nation year vehicle market long road socialise technology hanson said pretty good place now version appear print york edition headline hydrogen fuel cell car return run order reprint today paper ","m_szGeo1":"United States","m_szSourceType":"source_news","m_szSrcUrl":"http://www.nytimes.com/2015/04/17/automobiles/hydrogen-fuel-cell-cars-return-for-another-run.html?_r=0","m_Places":["California","Tucson","Tucsons","Los Angeles","San Francisco","Toyota","Calif.","New York"],"m_People":["Lawrence Ulrich","Stuart Palley","David Uselton","Suelyn","Dana Point","Uselton","Devin Lindsay","Lindsay","Honda","Mercedes","Fcx Clarity","John Hanson","Hanson"],"m_Companies":["New York Times","University Of California, Irvine","Hyundai","Los Angeles","Hydrogen Cars Can Indeed Appear To Be","General Motors","Bmw","Alliances","G.m.","Energy Department"],"m_BiGrams":["fuel cell","hydrogen fuel","cell car","advertisement continue","hydrogen car","battery electric"],"m_TriGrams":["hydrogen fuel cell","fuel cell car","advertisement continue reading"],"m_SocialTags":[],"m_Topics":[],"m_Industry":[],"m_Technology":[],"m_BiCnt":[14,5,4,4,4,3],"m_TriCnt":[4,4,4],"m_iDocBodyWordCnt":715}
