{"m_szDocID":"589669","m_szDocTitle":"What will we be driving in the future? Electric vs. hydrogen fuel cell vehicles. | Public Radio International","m_szYear":"2015","m_szDocSumamry":"What will we be driving in the future? Electric vs. hydrogen fuel cell vehicles. The 2016 Toyota Mirai sedan.  Credit: Toyota “It drives like a regular car, operates like a regular car. You can refuel in three to five minutes and, you know, do 350 miles on a trip,” says Craig Scott, Toyota’s national manager for advanced technologies in the US.  Player utilities    Scott is overseeing the US release of the Mirai, Toyota's hydrogen fuel cell car.   “We're really excited,” Scott says. “This will be the first time for US consumers to get a chance to actually own a real live fuel cell electric veh","m_szDocBody":"driving future electric hydrogen fuel cell vehicle toyota mirai sedan credit toyota drive regular car operate regular car refuel minute and know mile trip craig scott toyotas national manager advanced technology player utility scott overseeing release mirai toyotashydrogen fuel cell car excited scott saysthis time usconsumer chance real live fuel cell electric vehicle mirai kind hybrid powered kilowatt battery fuel cell run pressure hydrogen order refuel mirai car owner bereliant anetwork hydrogen refuelling station moment toyota planning sell mirai vehicle year year expect sell levi tillemann fellow american foundation great race global quest car future lack hydrogen refuelling station big barrier people decide whetheto hydrogen fuel cell car huge amount infrastructure centralised infrastructure tillemann say today public hydrogen refuelling station entire country california tillemann launch giant research development initiative toyota important remember context fuel cell vehicle whattoyota kind deployed researchand development tillemann saystheyre cutting edge technology put hand consumer early stage gather knowledge long run vehicle perform addition infrastructure problem fuel cell vehicle face big hurdle race power car emission technology hydrogen fuel cell vehicle rely hydrogen product methane hydrogen fuel cell potentially great technology long distance emissiontravel tillemann saysbut problem produce standard hybrid electric vehicle fact hydrogen methane produce hydrogen methane release lot require lot energy hope future produce carbon hydrogen that hydrogen fuel cell vehicle great idea hard place low carbon future scott point out however electric car face hurdle true evs electric vehicle right develop carbon free electricity scott saysfuel cell evs par emission point view roughly percent cleaner standard gasoline vehicle considered again know goal make moving emission technology plenty player competing market develop cleaner car toyota selling prius year tesla produceselectric car rumour apple developing vehicle socalled titanproject lot media report talked shape apple car people mobile office people minivan people quoted level apple exec apple give tesla run money project titan like scott saysbut lot buzz media apple raised r&d budget coming year substantially making significant investment investing future electric versus hybrid vehicle however tillemann think electric vehicle upper hand good research dramatically efficient standpoint carbon emission hybrid potential hydrogen vehiclein myexperience report analysis carbon footprint vehicle show electric vehicle potential cleanest car based interview aired pris science ira flatow ","m_szGeo1":"United States","m_szSourceType":"source_news","m_szSrcUrl":"http://www.pri.org/stories/2015-10-12/what-will-we-be-driving-future-electric-vs-hydrogen-fuel-cell-vehicles","m_Places":["Toyota","California","Tesla"],"m_People":["Craig Scott","Levi Tillemann","As Scott","Ira Flatow"],"m_Companies":["Apple","Ira Flatow"],"m_BiGrams":["fuel cell","hydrogen fuel","cell vehicle","electric vehicle","hydrogen refuelling","refuelling station"],"m_TriGrams":["fuel cell vehicle","hydrogen fuel cell","hydrogen refuelling station"],"m_SocialTags":[],"m_Topics":[],"m_Industry":[],"m_Technology":[],"m_BiCnt":[10,5,5,5,3,3],"m_TriCnt":[5,4,3],"m_iDocBodyWordCnt":366}
