{"m_szDocID":"589647","m_szDocTitle":"Hyundai sees hydrogen fuel cell cars as the future | Computerworld","m_szYear":"2015","m_szDocSumamry":"Hyundai sees hydrogen fuel cell cars as the future More like this The Toyota Mirai's two fuel tanks hold up to 5 kg of compressed hydrogen. Credit: Image: Melissa Riofrio Hyundai plans to invest another $10B in eco-friendly cars Email a friend Use commas to separate multiple email addresses From Your message has been sent. Sorry Computerworld | Jun 29, 2015 12:54 PM       PT RELATED TOPICS Comments Despite slow market uptake, Hyundai Motor Co. said today that hydrogen fuel cell vehicles representÂ the future of eco-friendly cars more than all-electric vehicles. Hyundai, the largest carmaker in ","m_szDocBody":"hyundai see hydrogen fuel cell car future toyota mirais fuel tank hold compressed hydrogen credit image melissa riofrio hyundai plan invest ecofriendly car friend commas separate multiple addresse message sent computerworld related topic comment slow market uptake hyundai motor today hydrogen fuel cell vehicle representthe future ecofriendly car allelectric vehicle hyundai largest carmaker south korea began selling tucson fuel cell suv year target vehicle purchased leased hyundai hyundai tucson fuel cell suv fallen short sale estimate expected grow time price vehicle decline fueling station grow tucson fuel cell vehicle retail purchased europe california report confirmed hyundai america year hyundai plan invest billion hybrid car electric battery vehicle hydrogen fuel cell model fuel cell vehicle however represent opportunity growing sale electric vehicle market competition kim sae hoon general manager hyundais fuel cell engineering design team hydrogen vehicle offer grater flexibility designer scale size small car buse hoon said hydrogen fuel cell vehicle truck buse advantage hydrogen vehicle allelectric engine perform larger vehicle require bigger battery charging devin lindsay ihs automotive senior analyst addition hyundai toyota released mirai fuel cell base sticker price meanwhile honda announced delay release fuel cell car fcx clarity fuel cell electric vehicle hydrogen fuel cell vehicle emit water vapour exhaust remarkable advantage allelectric vehicle tesla model travel mile tank fuel refuel minute comparison tesla company socalled supercharger require minute achieve halfcharged battery full charge provide range mile toyotas rav electric vehicle maximum mile charge hyundai tucson fuel cell the european model travel mile model achieve mile single fill price dearth fueling station barrier sale fuel cell vehicle hyundai year hydrogen car start gaining wider acceptance today hybrid car electric vehicle dominating greenvehicle market method creating hydrogen fuel common today called steammethane reformation process hightemperature steam degree celsius create reaction methane gas presence catalyst produce hydrogen carbon monoxide small amount carbon dioxide carbon dioxide impurity removed process called pressureswing adsorption leaving essentially pure hydrogen steam reformation ethanol propane gasoline produce hydrogen steammethane reformation commonly oil refinery remaining hydrogen remove impurity sulphur petroleum diesel fuel case allelectric vehicle emerged mid price lack fueling station stifled uptake fuel cell vehicle statement hyundai decade hydrogen car gain wider acceptance related topic ","m_szGeo1":"South Korea","m_szSourceType":"source_news","m_szSrcUrl":"http://www.computerworld.com/article/2941874/sustainable-it/hyundai-sees-hydrogen-fuel-cell-cars-as-the-future.html","m_Places":["Toyota","South Korea","Tucson","Europe","California","America","Tesla"],"m_People":["Melissa Riofrio","Kim Sae Hoon","Hoon","Devin Lindsay","Honda","Fcx Clarity"],"m_Companies":["Hyundai","Computerworld","Pt","Hyundai Motor Co","Target"],"m_BiGrams":["fuel cell","cell vehicle","hydrogen fuel","tucson fuel","electric vehicle","allelectric vehicle","fueling station"],"m_TriGrams":["fuel cell vehicle","hydrogen fuel cell","tucson fuel cell"],"m_SocialTags":[],"m_Topics":[],"m_Industry":[],"m_Technology":[],"m_BiCnt":[16,7,6,4,4,3,3],"m_TriCnt":[7,5,4],"m_iDocBodyWordCnt":360}
