{"m_szDocID":"589662","m_szDocTitle":"Recent breakthroughs in 100% clean hydrogen fuel - News - Stephenville Empire-Tribune - Stephenville, TX","m_szYear":"2015","m_szDocSumamry":"Recent breakthroughs in 100% clean hydrogen fuel Posted Dec. 24, 2015 at 8:32 AM Updated Dec 24, 2015 at 8:33 AM By J. MICHAEL ROSS Posted Dec. 24, 2015 at 8:32 AM Updated Dec 24, 2015 at 8:33 AM Editorâ€™s note: This is the fourth in a five-part series on energy and climate change by Empire-Tribune staff writers this week. Hydrogen gas is the cleanest fuel known on the planet and several milestones have recently been reached that may bring the reality of cars that run completely free of polluting greenhouse emissions into the present. Hydrogen fuel can be made from just about anything: Garbage ","m_szDocBody":"recent breakthrough clean hydrogen fuel posted dec updated michael ross posted dec updated editor note fourth fivepart sery energy climate change empiretribune staff writer week hydrogen gas cleanest fuel planet milestone recently reached bring reality car run completely free polluting greenhouse emission present hydrogen fuel made anything garbage landfill plant byproduct corn stover cow manure expensive process regular hydrogen fuel back burner corn stover way leftover stuff corn edible kernel removed stalk cob husk called dirty biomass corn stover hydrogen fuel breakthrough make inexpensive hydrogen scientist percival zhang joe rollin virginia tech university released finding proceeding national academy science magazine invented inexpensive biological process corn stover create hydrogen statement office university relation say this work build previous study zhang team xylone abundant simple plant pentose sugar produce hydrogen yield previously attainable theory word invented cheaper make hydrogen fuel castoff plant product university put greatly reduce time money take produce zeroemission fuel hydrogen fuel breakthrough water company called hypersolar invented create renewable hydrogen sunlight water information published company explain for century splitting water molecule hydrogen oxygen electrolysis known theoretically technology produce unlimited amount clean renewable hydrogen fuel power carbonfree world optimising science water electrolysis low cost photoelectrochemical process efficiently sunlight separate hydrogen source water produce clean environmentallyfriendly renewable hydrogen innovative solar hydrogen generator eliminate conventional electrolyzer expensive energy intensive bring hydrogenfuel related innovation toyota introduced automobile mirai electricpowered vehicle run electricity created car hydrogen fuel cell system require recharging electrical outlet electric car toyotas mirai new fuel cell technology fuel cell generator developed francis thomas bacon fuel cell powered kind fork lift german submarine spacecraft mirai hydrogen gas pumped car gasoline diesel pumped conventional vehicle said electric car internal combustion engine hydrogen pumped stored car fuel cell system toyota literature explain when pump hydrogen vehicle gas travel carbonfiber reinforced fuel cell stored toyota drive the mirais front intake grill deliver air fuel cell stack put foot gas pedal electricity fuel cell stack motor better coming tailpipe hydrogenpowered vehicle heated water vapour human cusp mind boggling hydrogenfuelrelated breakthrough prove out possibility largely emissionsfree hydrogenpowered planet point reality interested detail fuel cell create electricity good threeminute video michael ross posted dec updated ","m_szGeo1":"United States","m_szSourceType":"source_news","m_szSrcUrl":"http://www.yourstephenvilletx.com/article/20151224/NEWS/151229772","m_Places":["Virginia Tech University","University Relations","University","Toyota"],"m_People":["Michael Ross","Percival Zhang","Joe Rollin","Zhang","Francis Thomas Bacon"],"m_Companies":["Tribune","Virginia Tech University","Academy","University Relations","Diesel"],"m_BiGrams":["fuel cell","hydrogen fuel","corn stover","posted dec","dec updated","renewable hydrogen"],"m_TriGrams":["posted dec updated"],"m_SocialTags":[],"m_Topics":[],"m_Industry":[],"m_Technology":[],"m_BiCnt":[9,8,4,3,3,3],"m_TriCnt":[3],"m_iDocBodyWordCnt":359}
