{"m_szDocID":"589666","m_szDocTitle":"Gore Joins Industry in Celebrating National Hydrogen and Fuel Cell Day -- ELKTON, Md., Oct. 8, 2015 /PRNewswire/ --","m_szYear":"2015","m_szDocSumamry":"Gore Joins Industry in Celebrating National Hydrogen and Fuel Cell Day -- ELKTON, Md., Oct. 8, 2015 /PRNewswire/ -- Gore Joins Industry in Celebrating National Hydrogen and Fuel Cell Day ELKTON, Md., Oct. 8, 2015 /PRNewswire/ -- Today, W.L. Gore & Associates (Gore) joins the nation in celebrating National Hydrogen and Fuel Cell Day to raise awareness of fuel cell and hydrogen technologies that provide reliable and resilient power, reduce greenhouse gas emissions, and increase America's energy security. The 8th of October was chosen to observe National Hydrogen and Fuel Cell Day in recognition ","m_szDocBody":"gore join industry celebrating national hydrogen fuel cell day elkton oct gore join industry celebrating national hydrogen fuel cell day elkton oct today gore associate gore join nation celebrating national hydrogen fuel cell day raise awareness fuel cell hydrogen technology provide reliable resilient power reduce greenhouse gas emission increase americas energy security chosen observe national hydrogen fuel cell day recognition atomic weight hydrogen fuel cell utilise hydrogen hydrogen rich fuel chemical reaction combustion generate electricity clean efficient quiet gore proud company organisation participating national hydrogen fuel cell day laura geiman sale leader gore fuel cell technology part robust industry proud growing role proven technology providing sustainable transportation improved business operation resilient power gore active fuel cell technology late developed portfolio fuel cell membrane goreselect membrane industry highest performance highest durability key factor life automotive power train gore fuel cell component thousand fuel cell application worldwide including transportation stationary backup power portable power cogeneration gore maintain research testing manufacturing facility fuel cell component japan sale office worldwide continued growth industry americas strong national interest join industry supporting government policy place fuel cell vehicle equal footing electric vehicle added laura keough business leader gore fuel cell technology the fuel cell hydrogen energy industry grown tremendously start united state space programme today fuel cell system operation generating clean power vehicle forklift utility businesse home more morry markowitz president fuel cell hydrogen energy fchea information national hydrogen fuel cell day participating organisation source gore associate inc related link ","m_szGeo1":"United States","m_szSourceType":"source_news","m_szSrcUrl":"http://www.prnewswire.com/news-releases/gore-joins-industry-in-celebrating-national-hydrogen-and-fuel-cell-day-300155924.html","m_Places":["Elkton, Md","America","Japan","United States"],"m_People":["Laura Geiman","Laura Keough","Morry Markowitz"],"m_Companies":["Gore","W.l. Gore & Associates","Energy Association","Fchea","W.l. Gore & Associates, Inc."],"m_BiGrams":["fuel cell","hydrogen fuel","national hydrogen","cell day","gore join","join industry","celebrating national","cell hydrogen","gore fuel","cell technology"],"m_TriGrams":["hydrogen fuel cell","national hydrogen fuel","fuel cell day","celebrating national hydrogen","fuel cell hydrogen","gore fuel cell","fuel cell technology"],"m_SocialTags":[],"m_Topics":[],"m_Industry":[],"m_Technology":[],"m_BiCnt":[19,7,6,6,3,3,3,3,3,3],"m_TriCnt":[7,6,6,3,3,3,3],"m_iDocBodyWordCnt":244}
