{"m_szDocID":"589634","m_szDocTitle":"Honda to introduce new hydrogen fuel cell vehicle in 2016","m_szYear":"2015","m_szDocSumamry":"To find out more about Facebook commenting please read the Conversation Guidelines and FAQs Honda betting big on hydrogen fuel cell car Brent Snavely , Detroit Free Press 4:38 p.m. EDT June 15, 2015 Honda said today it plans to introduce a mainstream hydrogen fuel cell vehicle along with a new plug-in hybrid vehicle and a new battery electric vehicle over the next several years. The Honda FCV Concept is displayed during media previews for the North American International Auto Show in Detroit on Jan. 13. (Photo: Paul Sancya) Honda said today  it plans to introduce a mainstream hydrogen fuel cel","m_szDocBody":"commenting read conversation guideline faqs honda betting big hydrogen fuel cell car brent snavely detroit free press edt honda today plan introduce mainstream hydrogen fuel cell vehicle plugin hybrid vehicle battery electric vehicle year honda fcv concept displayed media preview north american international auto show detroit jan photo paul sancya honda today plan introduce mainstream hydrogen fuel cell vehicle plugin hybrid vehicle battery electric vehicle year company discontinued production compressed natural gas version honda civic hybrid version civic year attract buyer model japanese automaker plan introduce fuel cell vehicle named company provide date electric car crossover plan introduce vehicle model name john mendel executive vice president american honda today detroit developing generation vehicle starting introduction nextgeneration fuel cell vehicle mendel said this allnew battery electric model allnew plugin hybrid model plugin electric hybrid powered electric motor internal combustion engine battery electric vehicle electric motor powered battery were developing entire generation electrified vehicle mendel said limited network hydrogen fueling station mendel confident substantial market develop hydrogen fuel vehicle government support stronger hydrogen said natural gas hyundais introduction fuel cell version tuscon toyotas plan introduce mirai year create support development refuelling mendel said hondas fuel cell vehicle mendel said will mainstream performer honda brand honda revealed fcv concept concept version vehicle north american international auto show detroit january honda reveal fuelcell powered car meanwhile automaker terminated production compressed natural gas version honda civic hybrid version civic prepare launch redesigned version civic fall company temporarily discontinue plugin version honda accord replace car allnew plugin hybrid vehicle mendel automaker year create demand compressed natural gas vehicle decided market mainstream anytime soon company sold compressed natural gas civic gave long run tried mendel said but market taxicab commercial vehiclesis experiencing uptick expected civic hybrid produced early selling fewer year contact brent snavely follow connect tweet linkedin commentemailmore read share storey storey ","m_szGeo1":"United States","m_szSourceType":"source_news","m_szSrcUrl":"http://www.freep.com/story/money/business/2015/06/15/honda-civic-pilot-automotive-sales/71248262/","m_Places":["Detroit","Tuscon","Toyota"],"m_People":["Brent Snavely","John Mendel"],"m_Companies":["Facebook","Honda","Detroit Free Press","International Auto Show","Hyundai","Twitter","Linkedin"],"m_BiGrams":["fuel cell","plan introduce","cell vehicle","natural gas","mendel said","hydrogen fuel","plugin hybrid","battery electric","compressed natural","vehicle mendel","honda today","hybrid vehicle","electric vehicle","version honda","civic hybrid","version civic"],"m_TriGrams":["fuel cell vehicle","compressed natural gas","hydrogen fuel cell","plugin hybrid vehicle","battery electric vehicle","vehicle mendel said"],"m_SocialTags":[],"m_Topics":[],"m_Industry":[],"m_Technology":[],"m_BiCnt":[7,5,5,5,5,4,4,4,4,4,3,3,3,3,3,3],"m_TriCnt":[5,4,3,3,3,3],"m_iDocBodyWordCnt":306}
