{"m_szDocID":"589754","m_szDocTitle":"Hyundai Sonata Plug-In Hybrid has engine experts singing a different tune |       cleveland.com","m_szYear":"2016","m_szDocSumamry":"Hyundai Sonata Plug-In Hybrid has engine experts singing a different tune Terry Troy By Terry Troy The Plain Dealer on January 03, 2016 at  5:00 AM, updated January 03, 2016 at  5:05 AM Comments It used to be that when Ward's editors and automotive experts gathered at the North American International Auto Show to honor the magazine's 10 Best Engines, the list mostly included gas powered V8s. But times have changed since the award's inception in 1995. The 2016 Sonata Plug-in Hybrid pricing starts at $34,600 for a well-equipped model.Cleveland.comÂ  The 2016 Sonata Plug-In Hybrid is powered by Hy","m_szDocBody":"hyundai sonata plugin hybrid engine expert singing tune terry troy terry troy plain dealer updated comment ward editor automotive expert gathered north american international auto show honour magazine engine list included gas powered time changed award inception sonata plugin hybrid pricing start wellequipped modelclevelandcom sonata plugin hybrid powered hyundais litre fourcylinder gdi engine paired electric motorclevelandcom year ward engine list include hyundai sonata plugin hybrid electric vehicle powertrain time plugin hybrid powertrain made list for hyundais entry plugin hybrid segment hyundai engineer impeccable job blending fuel efficiency refinement daily usability drew winter editorinchief wardsauto world magazine transition allelectric hybrid mode completely seamless driver undoubtedly long journey sixspeed automatic transmission driver greater sense connexion compared hybrid segment ward engine list began hyundaihas received award time tau list tau litre made list hyundai gamma hit list hydrogen fuel cell powertrain made list year award ceremony place banquet north american international auto show jan detroit receiving award demonstrate hyundais continued momentum leader advanced powertrain mike obrien vice president corporate product planning hyundai motor america significant potential sonata phev best world carbon solution award recognised platform highlight technological environmental leadership entire sonata family sonata plugin hybrid powered hyundais litre fourcylinder gdi engine produce horsepower lbft torque unlike hybrid sonata plugin hybrid utilise sixspeed automatic transmission electric motor place standard torque converter electric motor percent powerful electric motor found conventional sonata hybrid allowing operation engine load speed total system output horsepower electric motor coupled automatic transmission heightened sense connexion cvt transmission common hybrid segment addition vehicle kwh lithium polymer battery pack allelectric range mile folk complete daily commute single drop fuel lithium polymer battery system time larger conventional sonata hybrid battery help plugin achieve mpge combined rating chargedepleting electric vehicle mode larger battery system charged external electric power source levelone power outlet hour leveltwo charging station hour manage monitor sonata plugin hybrid electric vehicle remotely exclusive blue link smartphone app include threeyear complimentary trial blue link connected care charge management app vehicle charging option select car however manage option remotely smartphone example option manage car charging schedule setting specific date time advantage offpeak electric rate app monitor plug charge status time left car fully charged current battery level real time electric fuel range stop start charging run vehicle diagnostic addition impressive powertrain hyundai engineer implemented active safety technology sonata plugin hybrid assist driver prevent accident advanced safety technology forward collision warning lane departure warning automatic beam assist rear parking sensor equipped sonata plugin hybrid limited additional convenience technology expect luxury vehicle available including electronic parking brake automatic vehicle hold driver memory seat heated steering wheel ventilated front seat power front seat fourway adjustable driver lumbar smart cruise control featuring full stop capability ","m_szGeo1":"United States","m_szSourceType":"source_news","m_szSrcUrl":"http://www.cleveland.com/automotive/plaindealer/index.ssf/2016/01/hyundai_sonata_plug-in_hybrid_has_engine_experts_singing_a_different_tune.html","m_Places":["Cleveland","Detroit"],"m_People":["Terry Troy","Drew Winter","Mike O'brien"],"m_Companies":["Hyundai","International Auto Show","World Magazine","Transitions","Hyundai Motor America","Seat"],"m_BiGrams":["plugin hybrid","sonata plugin","electric motor","engine list","electric vehicle","made list","hybrid segment","automatic transmission"],"m_TriGrams":["sonata plugin hybrid"],"m_SocialTags":[],"m_Topics":[],"m_Industry":[],"m_Technology":[],"m_BiCnt":[11,9,4,3,3,3,3,3],"m_TriCnt":[8],"m_iDocBodyWordCnt":447}
