{"m_szDocID":"589770","m_szDocTitle":"Hydrogen fuel cell vehicle market to experience growth through 2024 | Hydrogen Fuel News","m_szYear":"2016","m_szDocSumamry":"Categorized | Featured News , Industry , Hydrogen Fuel Cell Hydrogen fuel cell vehicle market to experience growth through 2024 Share on Tumblr Report provides forecast into the growth in sales of fuel cell vehicles Navigant Research has released a new report concerning the future of the fuel cell vehicle market. Globally, clean transportation is gaining more support, with several countries looking to promote the adoption of zero emission vehicles in order to cut down on emissions production. Vehicles equipped with hydrogen fuel cells have become particularly popular, as these vehicles are see","m_szDocBody":"categorised featured new industry hydrogen fuel cell hydrogen fuel cell vehicle market experience growth share tumblr report forecast growth sale fuel cell vehicle navigant research released report future fuel cell vehicle market globally clean transportation gaining support country promote adoption emission vehicle order cut emission production vehicle equipped hydrogen fuel cell popular vehicle efficient capable batterypowered counterpart global sale fuel cell vehicle reach report navigant research number fuel cell vehicle global market reach significant growth hybrid plugin vehicle expected continue popular making hydrogen fuel conventional electric vehicle expensive support established infrastructure ensure consumer vehicle convenient fashion coming year however sale fuel cell vehicle increase hydrogen fuel infrastructure established prominent market automaker finding modest success fuel cell vehicle company toyota hyundai succeeded bringing fuel cell vehicle commercial market company vehicle acquire significant success available japan promising market vehicle toyota witnessed major increase demand mirai equipped hydrogen fuel cell fuel cell popular public transit space power tram buse train lacking hydrogen fuel infrastructure slow adoption fuel cell vehicle comprehensive infrastructure fuel cell vehicle limited success country begun investing heavily development infrastructure building hydrogen fuel station slow work moreover fuel cell vehicle expensive conventional counterpart limit appeal consumer interested clean transportation related post ","m_szGeo1":"Japan","m_szSourceType":"source_news","m_szSrcUrl":"http://www.hydrogenfuelnews.com/hydrogen-fuel-cell-vehicle-market-experience-growth-2024/8526700/","m_Places":["Toyota","Japan"],"m_People":[],"m_Companies":["Hyundai"],"m_BiGrams":["fuel cell","cell vehicle","hydrogen fuel","sale fuel"],"m_TriGrams":["fuel cell vehicle","hydrogen fuel cell","sale fuel cell"],"m_SocialTags":[],"m_Topics":[],"m_Industry":[],"m_Technology":[],"m_BiCnt":[15,11,8,3],"m_TriCnt":[11,4,3],"m_iDocBodyWordCnt":200}
