{"m_szDocID":"590448","m_szDocTitle":"Advanced Energy Storage Systems Market Worth 15.96 Billion USD by 2020 -- PUNE, India, December 2, 2015 /PRNewswire/ --","m_szYear":"2015","m_szDocSumamry":"http://www.marketsandmarkets.com/Market-Reports/advanced-energy-storage-systems-market-1306.html Early buyers will receive 10% customization on this report.Â  The market report defines and segments the global energy storage systems market with an analysis and forecast of the market size. Advanced Energy Storage Systems Market is expected to grow from an estimated USD 12.89 Billion in 2015 to USD 15.96 Billion by 2020, at a CAGR of 4.4% during the forecast period. Energy arbitrage opportunities, renewable energy installations, and growing electric vehicles market are driving the energy storage s","m_szDocBody":"early buyer receive customization report market report define segment global energy storage system market analysis forecast market size advanced energy storage system market expected grow estimated usd billion usd billion cagr forecast period energy arbitrage opportunity renewable energy installation growing electric vehicle market driving energy storage system market globally energy storage system transportation application emerging major segment aess market transportation segment accounted major share energy storage system market lithiumion nickelmetal hydride battery held major share transportation sector batterypowered vehicle today include hybrid vehicle plugin hybrid vehicle electric vehicle ongoing research development activity company honda motor company ltd japan chrysler llc toyota motor corporation japan usage lithiumion battery expected electric vehicle sample page increasing preference lithium ion battery advance energy storage system report segment advance energy storage system market basis technology lithium ion battery pumped hydro storage nas battery cae flow battery supercapacitor other lithium ion battery segment estimated account largest market share varied application technology including usage large transportation application contributing growth larger market share however cae market expected grow highest cagr forecast period growth attributed drastic change energy mix trend renewable energy power source renewable energy result frequent incident volatility load profile require interference energy storage system asiapacific dominant market energy storage system market report energy storage system market analysed respect region namely asiapacific europe north america rest world row energy storage system market expanding developing country owing progress renewable energy installation growth electric vehicle market asiapacific energy storage system market expected dominate share region expected maintain dominance energy storage system market forecast period report include profile leading player energy storage system market provide indepth understanding competitive landscape leading player include yuasa corporation japan samsung sdi ltd south korea hitachi limited japan exide technology chem limited south korea other major company energy storage system market comprise battery technology providing company major technology pumped hydro energy storage dominated company toshiba corporation japan abb limited switzerland siemen germany voith germany alstom france dominion energy dominant player penetrate developing economy adopting method grab bigger market share furthermore market share analysis revenue key company included report scope aid market participant identify growth market managing key investment decision report major player energy storage system market identified primary secondary source include annual report top market player interview key opinion leader ceos director marketing people based research market share evaluated validated browse related report small wind market type horizontal axis wind turbine vertical axis wind turbine application ongrid offgrid geography asiapacific north america europe global trend forecast marketsandmarket marketsandmarket world firm term annually published premium market research report serving global fortune enterprise premium study year m&m catering multitude client industrial vertical specialise consulting assignment business research growth market cutting edge technology newer application fulltime analyst sme marketsandmarket tracking global growth market growth engagement model gem gem aim proactive collaboration client identify opportunity identify important customer write attack avoid defend strategy identify source incremental revenue company competitor m&m flagship competitive intelligence market research platform connect market entire chain deeper understanding unmet insight market sizing forecast niche market included chapter methodology benchmarking presented quality analytical infographic report complete visibility number arrived defend accuracy number marketsandmarket inspired client grow providing apt business insight huge market intelligence repository contact ","m_szGeo1":"United States","m_szSourceType":"source_news","m_szSrcUrl":"http://www.prnewswire.com/news-releases/advanced-energy-storage-systems-market-worth-1596-billion-usd-by-2020-560013231.html","m_Places":["Japan","Asia","Europe","North America","South Korea","Switzerland","Germany","France"],"m_People":["Honda","Nas","Voith"],"m_Companies":["Aess","Motor Company Ltd.","Chrysler Group Llc","Toyota Motor Corporation","Yuasa Corporation","Samsung Sdi Co. Ltd.","Hitachi Limited","Exide Technologies","U.s.","Toshiba Corporation","Abb Limited","Siemens A.g.","Alstom","Dominion","Top","Axis","M&m"],"m_BiGrams":["energy storage","storage system","system market","market share","renewable energy","electric vehicle","market expected","forecast period","corporation japan","lithium ion","ion battery","growth market"],"m_TriGrams":["energy storage system","storage system market","lithium ion battery"],"m_SocialTags":[],"m_Topics":[],"m_Industry":[],"m_Technology":[],"m_BiCnt":[17,16,13,5,4,4,3,3,3,3,3,3],"m_TriCnt":[16,13,3],"m_iDocBodyWordCnt":529}
