{"m_szDocID":"594157","m_szDocTitle":"North American International Auto Show 2016: Toyota Displays Future of Mobility - I4U News","m_szYear":"2016","m_szDocSumamry":"North American International Auto Show 2016: Toyota Displays Future of Mobility Jan 8 2016, 9:29am CST | by M. Affan , in News | Cars & Vehicles Toyota KIKAI Concept 4 images Toyota will showcase its vision of the connected car and future mobility through its IA at its booth in Detroit. Toyota claims to display the future of mobility at the NAIAS 2016. The display will include advanced technology concepts by Toyota. The Toyota exhibit at North American International Auto Show 2016 provides a glimpse at this transformational change to mobility. Toyota will show off the full line of new cars, tr","m_szDocBody":"north american international auto show toyota display future mobility cst affan new car vehicle toyota kikai concept image toyota showcase vision connected car future mobility booth detroit toyota claim display future mobility naias display include advanced technology concept toyota toyota exhibit north american international auto show glimpse transformational change mobility toyota show full line car truck suvs today toyota exhibit focus clean power greater safety convenience toyota arrive detroit showcase vision connected car toyota show vision future mobility north american international auto show toyota make connected technology development announcement naias exhibit display toyota storey toyota show groundbreaking fuel cell electric vehicle marai addition toyota show fcv concept vehicle north american international auto show concept toyota demonstrate vision connected sustainable hydrogen society concept claim car generate electricity directly hydrogen hydrogen stored vehicle stable source electric power kikai concept toyota display naias kikai explore fundamental appeal machine kikai true concept car reliant core concept automobile kikai highlight appeal physical tactile digital age fan favourite concept iroad make appearance naias iroad threewheel personal electric vehicle equipped active lean technology operate shifting intuitively body driver intelligent transport system technology connect vehicle naias north american international auto show hosted mgm grand detroit ninth year ultraluxury automotive event naias constitute release car naias january ","m_szGeo1":"","m_szSourceType":"source_news","m_szSrcUrl":"http://www.i4u.com/2016/01/102663/north-american-international-auto-show-2016-toyota-displays-future-mobility","m_Places":["Toyota","Ia","Detroit"],"m_People":["Affan","Ai","Marai"],"m_Companies":["International Auto Show","Will Showcase","Mgm Grand"],"m_BiGrams":["north american","american international","international auto","auto show","future mobility","toyota show","vision connected","concept toyota"],"m_TriGrams":["north american international","american international auto","international auto show"],"m_SocialTags":[],"m_Topics":[],"m_Industry":[],"m_Technology":[],"m_BiCnt":[5,5,5,5,4,4,3,3],"m_TriCnt":[5,5,5],"m_iDocBodyWordCnt":208}
