{"m_szDocID":"594261","m_szDocTitle":"Honda Partnering With GM On Plug-in Hybrid Cars - Gas 2","m_szYear":"2016","m_szDocSumamry":"Honda Partnering With GM On Plug-in Hybrid Cars January 8th, 2016 by Steve Hanley     Honda and General Motors are already working together on hydrogen fuel cell technology. Now, they are prepared to expand their working relationship to focus also on plug-in hybrid cars. While EV enthusiasts decline to recognize plug-ins as real electric cars, most manufacturers see them as the bridge between the conventional cars of today and the zero emissions battery electric cars of the future. The International Energy Agency estimates that plug-in hybrids will account for 5% of new car sales worldwide in ","m_szDocBody":"honda partnering plugin hybrid car steve hanley honda general motor working hydrogen fuel cell technology now prepared expand working relationship focus plugin hybrid car enthusiast decline recognise plugin real electric car manufacturer bridge conventional car today emission battery electric car futurethe international energy agency estimate plugin hybrid account car sale worldwide expect number rise chicago tribune plugin avoid problem restricting growth electric car market present range anxiety eliminated battery completely depleted onboard engine simply take over smaller battery fully electric vehicle mean sell thousand true electric vehicle chevy bolt cost maximum range mile chevy plugin hybrid volt larger car sell travel mile needing stop fuel japan new partnership company bring plugin hybrid model market sooner worked individually negotiate favourable price supplier anxious sharpen pencil order sell product honda expected introduce plugin hybrid america believe working move project forward year possibility honda decide build plugin fuel cell car together built car toyota year part general motor expect collaboration honda compete effectively toyota honda believed ahead general motor fuel cell technology thought ahead honda plugin hybrid system let hope joint working relationship turn honda illfated collaboration ford ended badly honda share ","m_szGeo1":"Japan","m_szSourceType":"source_news","m_szSrcUrl":"http://gas2.org/2016/01/08/honda-partnering-with-gm-on-plug-in-hybrid-cars/","m_Places":["Japan","America","Toyota"],"m_People":["Honda","Steve Hanley","Chevy Bolt"],"m_Companies":["General Motors","International Energy Agency","Chicago Tribune","Volt"],"m_BiGrams":["plugin hybrid","general motor","fuel cell","electric car"],"m_TriGrams":[],"m_SocialTags":[],"m_Topics":[],"m_Industry":[],"m_Technology":[],"m_BiCnt":[7,3,3,3],"m_TriCnt":[],"m_iDocBodyWordCnt":189}
