{"m_szDocID":"594248","m_szDocTitle":"Tesla Catches Fire While Charging in Norway: Tesla Investigating | Transport Evolved","m_szYear":"2016","m_szDocSumamry":"Tesla Catches Fire While Charging in Norway: Tesla Investigating Nikki Gordon-Bloomfield Self-confessed geek and mother of two, Nikki has been talking and writing about cars ever since she passed her driving test. Back then, her Internet contributions were all classic car-focused. Now, sheâ€™s all about greener, cleaner, safer and smarter cars. Electric Car Fire Plug-in Car Supercharger Tesla Model S Just over two years ago, electric car fires were very much in the crosshairs of the mass-media, after several incidents in which Tesla Model S electric cars caught fire following accidents in which ","m_szDocBody":"tesla catches fire charging norway tesla investigating nikki gordonbloomfield selfconfessed geek mother two nikki talking writing car passed driving test back then internet contribution classic carfocused now shes greener cleaner safer smarter car electric car fire plugin car supercharger tesla model year ago electric car fire crosshair massmedia incident tesla model electric car caught fire accident object penetrated belly luxury sedan speed puncturing industryleading lithiumion battery pack case highspeed impact caused damaged cell inside battery pack shortcircuit ultimately causing battery pack pack overheat catch firein response statistically set event led incident tesla responded swiftly developing fitted brandnew highstrength belly shield customer car reduce risk fire breaking due underbody impact picture burned tesla model elisabeth grosvold via nrk then single fire involving tesla model electric car year day changed tesla model completely destroyed fire norway time however fire appear started luxury electric car plugged teslas proprietary supercharger quick charge station local station nrk report owner car left tesla model plugged tesla supercharger brokelandsheia gjerstad about hour drive south oslo time left plugin caught fire tesla model battery lot energy tank full gasoline hydrogen photograph scene show left model bearing testament ferocity fire chemical energy stored model battery pack fire consume entire car worth mentioning firefighter attending scene car burn time spraying water electric car fire increase fire extinguish instead firefighter disconnected car charging station pushed clear supercharger waiting fire subsided slightly dosing foam extinguishing injured fire vehicle damaged local fire department tesla motor explanation time caused fire harmed undergoing full investigation share finding possible tesla spokesperson toldtransport evolved emailed statement earlier today vehicular safety occupant safety tesla motor nasdaqtsla keen world safest automaker part safety record suggest that fewer reported incident car automaker bring received earlier today berating taking day report tesla fire adversarialin nature make pretty allegation bothtransport evolved tesla motor allegation wed dismiss read follow from christine message body plan completely ignore tesla caught fire supercharger norway youve discredited ridiculous elon musk bias expect seriously youre joke worth time load browser love product way taking slack making people lithium fire teslas fad joke belligerent bit billionaire dissed fuel cell wanted sell battery shame rest idiot blog separate fact misguided fandom truth day fire investigated alway reader comment respond praise criticism equal measure point small editorial team prefer wait context storey reporting jumping salacious bandwagon proper understanding background storey tesla fire norway exception aware storey year day weve waiting expanded statement tesla local fire department storey subject alway continue cover storey information available juncture important note basic statistic vehicular fire vehicle powered hydrogen fuel electrochemical battery fossil fuel store large amount energy onboard order power road time large amount energy compressed small space risk fire explosion car plugin hybrid car hydrogen fuel cell vehicle lithiumion battery addition gasoline hydrogen fuel power gasoline dieselpowered vehicle fire lower number today twenty year ago improved engine design improved safety system vehicle built data collected suggest electric car statistically time catch fire comparable gasolinepowered one far hydrogen fuel cell vehicle market provide statistic vehicle fire alsoimpossible car company prevent eventuality manufacturing process car used image burned tesla distressing sight burned car isolated incident alarm stage naturally keen caused fire hope tesla motor norwegian emergency service make determined fire occur similar situation refrain salacious finger waving latest new evolving transport dont forget followtransport evolvedon twitter channel support directly monthly supporting member simply share friend ","m_szGeo1":"Norway","m_szSourceType":"source_news","m_szSrcUrl":"https://transportevolved.com/2016/01/05/tesla-catches-fire-while-charging-in-norway-tesla-investigating/","m_Places":["Tesla","Norway","Oslo"],"m_People":["Nikki Gordon","Elisabeth Grosvold","Gjerstad","Elon"],"m_Companies":["Did Indeed Consume","Tesla Motors","Nasdaq","Slack","Diesel","Indeed","Twitter","Facebook","Youtube"],"m_BiGrams":["electric car","tesla model","battery pack","tesla motor","hydrogen fuel","car fire","caught fire","fuel cell"],"m_TriGrams":[],"m_SocialTags":[],"m_Topics":[],"m_Industry":[],"m_Technology":[],"m_BiCnt":[7,7,4,4,4,3,3,3],"m_TriCnt":[],"m_iDocBodyWordCnt":559}
