{"m_szDocID":"594214","m_szDocTitle":"Putting aside diesels, Audi unveils hydrogen concept car","m_szYear":"2016","m_szDocSumamry":"FacebookEmail Twitter Google+ LinkedIn Pinterest Putting aside diesels, Audi unveils hydrogen concept car DETROIT -- Snared in Volkswagen Group's diesel scandal, Audi sought to direct attention to the future -- way, way out in the future -- in unveiling a hydrogen-powered concept at the North American International Auto Show here. Post to Facebook Putting aside diesels, Audi unveils hydrogen concept car DETROIT -- Snared in Volkswagen Group's diesel scandal, Audi sought to direct attention to the future -- way, way out in the future -- in unveiling a hydrogen-powered concept at the North Ameri","m_szDocBody":"facebookemail google linkedin pinterest putting diesel audi unveil hydrogen concept car detroit snared volkswagen group diesel scandal audi sought direct attention future way future unveiling hydrogenpowered concept north american international auto show here post putting diesel audi unveil hydrogen concept car detroit snared volkswagen group diesel scandal audi sought direct attention future way future unveiling hydrogenpowered concept north american international auto show here cheque storey usatodaycom cancelsend link friend address posted link posted feed join nation conversation commenting read conversation guideline faqs putting diesel audi unveil hydrogen concept car usa today est audi htron quattro concept automobile presented north american international auto show photo epa connect tweet linkedin commentemailmore detroit snared volkswagen group diesel scandal audi sought direct attention future way future unveiling hydrogenpowered concept north american international auto show here german luxury brand rolled fifthgeneration hydrogen fuelcell vehicle htron quattro concept stage represent company great engineering challenge car powered electric motor take minute refill hydrogen tank veiled swipe hour take recharge battery pure electric car rupert stadler audis chairman management board etron concept arrive audi field electric sedan word time soon bright yellow htron presented great focus diesel scandal audi stop selling diesel model vws admission rigged beat emission law volkswagen announce plan fix car stadler scandal give forward brand unique opportunity change innovation make audi for better told reporter diesel forward future diesel positive way said read share storey top videos ","m_szGeo1":"United States","m_szSourceType":"source_news","m_szSrcUrl":"http://www.usatoday.com/story/money/cars/2016/01/11/putting-aside-diesels-audi-unveils-hydrogen-concept-car/78623044/","m_Places":["Detroit"],"m_People":["Rupert Stadler","No Time Soon","Stadler"],"m_Companies":["Twitter","Google","Linkedin","Pinterest","Diesels","Audi","Volkswagen Group","Diesel","International Auto Show","Facebook","Usatoday.com","Usa Today","Epa"],"m_BiGrams":["diesel scandal","scandal audi","north american","american international","international auto","auto show","putting diesel","diesel audi","audi unveil","unveil hydrogen","hydrogen concept","concept car","detroit snared","snared volkswagen","volkswagen group","group diesel","audi sought","sought direct","direct attention","attention future","future way","way future","future unveiling","unveiling hydrogenpowered","hydrogenpowered concept","concept north","show here"],"m_TriGrams":["diesel scandal audi","north american international","american international auto","international auto show","putting diesel audi","diesel audi unveil","audi unveil hydrogen","unveil hydrogen concept","hydrogen concept car","detroit snared volkswagen","snared volkswagen group","volkswagen group diesel","group diesel scandal","scandal audi sought","audi sought direct","sought direct attention","direct attention future","attention future way","unveiling hydrogenpowered concept","hydrogenpowered concept north","concept north american","auto show here"],"m_SocialTags":[],"m_Topics":[],"m_Industry":[],"m_Technology":[],"m_BiCnt":[4,4,4,4,4,4,3,3,3,3,3,3,3,3,3,3,3,3,3,3,3,3,3,3,3,3,3],"m_TriCnt":[4,4,4,4,3,3,3,3,3,3,3,3,3,3,3,3,3,3,3,3,3,3],"m_iDocBodyWordCnt":233}
