{"m_szDocID":"596116","m_szDocTitle":"Nissan chief welcomes competition in electric vehicles","m_szYear":"2016","m_szDocSumamry":"Nissan chief welcomes competition in electric vehicles Carlos Ghosn talks electric market expansion, driverless future and succession plans Post to Facebook Nissan chief welcomes competition in electric vehicles Carlos Ghosn talks electric market expansion, driverless future and succession plans Check out this story on detroitnews.com: http://detne.ws/1RkVxEs CancelSend A link has been sent to your friend's email address. Posted! A link has been posted to your Facebook feed. Join the Conversation To find out more about Facebook commenting please read the Conversation Guidelines and FAQs Nissan","m_szDocBody":"nissan chief welcome competition electric vehicle carlos ghosn talk electric market expansion driverless future succession plan post nissan chief welcome competition electric vehicle carlos ghosn talk electric market expansion driverless future succession plan cheque storey detroitnewscom cancelsend link friend address posted link posted feed join conversation commenting read conversation guideline faqs nissan chief welcome competition electric vehicle kevin wilson special new est buy photo nissan ceo carlos ghosn introduce infiniti north american international auto show cobo centre night photo daniel mear detroit newsbuy photo connect tweet linkedin commentemailmore maker bestselling affordable electric car past year nissan leaf renaultnissan alliance president ceo carlos ghosn welcome arrival competitor chevy bolt speaking automotive new world congress night detroit marriott ghosn said essence merrier expansion electric car market drive government consumer power industry quicker expansion recharging infrastructure part thing said questionandanswer format discussion automotive new publisher crain ghosn discussed company plan autonomous vehicle grooming successor ceo job hes merged company past year noted nissan gained market share primary japanesebased competitor and remain toyota honda here rank china japan government play bigger role expanding infrastructure recharging station electric hydrogen station fuel cell car crain asked complain ghosn chinese japanese european government that ghosn pointedly leaving government develop supporting infrastructurewe public sector job way leaf said deliberately designed massmarket affordable product ensure sale volume needed contribute company fuel economy carbon emission target grow market easy engineer expensive electric car said cost constraint nothat need crain asked ghosn accept nickname electric car nickname dont belong well replied elon musk tesla motor recent month sale expensive luxurious electric sedan outpace leaf ghosn recently announced renaultnissan produce autonomous car year talking driverless car clarified telling driver drive can not also long tenure atop nissanrenault ghosn increasingly asked succession plan made advised board company still separate think separate ceos retire board gone problem year japan year france board decide step down make decision pass baton point youre proud what accomplished ghosn said noting company percent market share north america percent hes set percent share target think achieved but noted hed make entity executive corp turned over built sustainable durable connect tweet linkedin commentemailmore read share storey top videos ","m_szGeo1":"United States","m_szSourceType":"source_news","m_szSrcUrl":"http://www.detroitnews.com/story/business/autos/detroit-auto-show/2016/01/12/ghosn-renault-nissan-detroit-auto-show/78720496/","m_Places":["Detroit","Toyota","Japan","France","North America"],"m_People":["Carlos Ghosn","Kevin A. Wilson","Cobo","Daniel Mears","Chevy Bolt","Marriott","Ghosn","Crain","Job He","Honda","Elon"],"m_Companies":["Facebook","Infiniti","International Auto Show","Detroit News","Linkedin","Renault","Nissan Alliance","Automotive News","Automotive News Group","Tesla Motors","Target"],"m_BiGrams":["carlos ghosn","electric car","nissan chief","chief welcome","welcome competition","competition electric","electric vehicle","succession plan"],"m_TriGrams":["nissan chief welcome","chief welcome competition","welcome competition electric","competition electric vehicle"],"m_SocialTags":[],"m_Topics":[],"m_Industry":[],"m_Technology":[],"m_BiCnt":[4,4,3,3,3,3,3,3],"m_TriCnt":[3,3,3,3],"m_iDocBodyWordCnt":358}
