{"m_szDocID":"596189","m_szDocTitle":"BMW Hydrogen Fuel Cell car only in 2023 - Indian Cars Bikes","m_szYear":"2016","m_szDocSumamry":"BMW Hydrogen Fuel Cell car only in 2023 by sourabh on January 18, 2016No Comments        BMW has been pioneers in bringing many tehnologies to cars, but Hydrogen Fuel Cell will not be counted amongst those for sure. And this has come from none other than vice-president  of drivetrain research, Matthias Klietz. “There will be nothing whatsoever from the Toyota and BMW partnership in production next year or 2017,” Klietz admitted during the Detroit motor show. “2019 is probably the best bet for that, and that’s the normal development cycle. But it will be somewhere between 2020 and 2025 from the","m_szDocBody":"bmw hydrogen fuel cell car sourabh comment bmw pioneer bringing tehnology car hydrogen fuel cell counted sure vicepresident drivetrain research matthias klietzthere whatsoever toyota bmw partnership production year klietz admitted detroit motor show bet that normal development cycle hydrogen fuelcell development bmw hydrogen fuel cell car prototype target hfc hydrogen fuel cell component ready klietz admitted show then concept car prototype hfc stack sery prototype toyota mirai sery prototype produce power stack part each black beauty stack totally storey industrialised pure research prototype part german giant hydrogen fuel cell technology playing catch japanese counterpart toyota advanced technology bmw are started develop target klietz admitted phase main task speed development end continue level development competence toyota phase develop level competence develop target for stack share stack from mirai development now cost reduction fuelcell system stack life cell technology term performance efficiency integration system dont expect toyota bmw fuel stack eventually drive way bmw power toyota stretching range stack space power them industrialisation target include cost decreasing rareearth material use clear bmw toyota ideas fuel cell most toyota starting smallest small car bmw intend big production sery generation time model fuelcell vehicle long driving electric vehicle power source klietz insisted categorised large vehicle work year sery fuel cell prototype testing deliver power sprint second top speed bar hydrogen gas tank inserted length newer system cryogenic tank hold liquid hydrogen biggest difference older tank hold hydrogen newschool cold tank internal pressure bar hold effectively increase range standard that car identical electric motor driving rear wheel identical twospeed transmission well adding spring stiffness cope extra weight chassis suspension braking steering system carried standard sery technical development partnership necessarily share complete architecture knowledge component operation necessarily share car brand ","m_szGeo1":"","m_szSourceType":"source_news","m_szSrcUrl":"http://www.indiancarsbikes.in/auto-news/bmw-hydrogen-fuel-cell-car-only-in-2023-139424/","m_Places":["Toyota","Detroit"],"m_People":["Matthias Klietz"],"m_Companies":["Bmw","Target","Sprint"],"m_BiGrams":["fuel cell","hydrogen fuel","klietz admitted"],"m_TriGrams":["hydrogen fuel cell"],"m_SocialTags":[],"m_Topics":[],"m_Industry":[],"m_Technology":[],"m_BiCnt":[7,5,3],"m_TriCnt":[5],"m_iDocBodyWordCnt":284}
