{"m_szDocID":"596191","m_szDocTitle":"Report: Mercedes-Benz Will Release a Hydrogen Fuel Cell GLC Next Year","m_szYear":"2016","m_szDocSumamry":"Report: Mercedes-Benz Will Release a Hydrogen Fuel Cell GLC Next Year ​Like Audi, Mercedes-Benz is making big bets on hydrogen and electric cars. E-mail Soon, Toyota and Honda won't be the only automakers to offer a hydrogen fuel cell vehicle to the public. Mercedes-Benz R&D chief Dr. Thomas Weber said that Mercedes will launch a fuel cell version of its GLC crossover next year, in an interview with  Autocar . Mercedes joins Audi, BMW and others in investing in both hydrogen and electric cars. Mercedes previously offered a hydrogen-powered version of the B-Class called the F-Cell, though it on","m_szDocBody":"report mercedesbenz release hydrogen fuel cell glc year audi mercedesbenz making big bet hydrogen electric car soon toyota honda automaker offer hydrogen fuel cell vehicle public mercedesbenz r&d chief thomas weber mercede launch fuel cell version glc crossover year interview autocar mercede join audi bmw investing hydrogen electric car mercede previously offered hydrogenpowered version bclass called fcell leased fcell customer southern california predecessor footstep weber hydrogenpowered glc called glc fcell advertisement continue reading weber told autocar significant improvement hydrogen fuel cell technology year key component generating power reduction size glc fcell minute refuel fuel cell mounted engine ordinary glc toyota mirai glc market relative lack refuelling infrastructure popular glc fcell release electric car mercedesbenz arrive weber type car allelectric vehicle toldautocar mile range pure electric hydrogen fuel cell vehicle commonly touted car future interesting mercedesbenz make investment technology emerge dominant mercede clearlydoesnt left investing other think ","m_szGeo1":"United States","m_szSourceType":"source_news","m_szSrcUrl":"http://www.roadandtrack.com/new-cars/future-cars/news/a27925/report-mercedes-benz-hydrogen-glc/","m_Places":["Toyota","Southern","California","Reading"],"m_People":["Audi","Honda","Thomas Weber","Mercedes"],"m_Companies":["Mercedes-benz","Autocar","Bmw"],"m_BiGrams":["fuel cell","hydrogen fuel","electric car","glc fcell"],"m_TriGrams":["hydrogen fuel cell"],"m_SocialTags":[],"m_Topics":[],"m_Industry":[],"m_Technology":[],"m_BiCnt":[6,4,3,3],"m_TriCnt":[4],"m_iDocBodyWordCnt":146}
