{"m_szDocID":"596182","m_szDocTitle":"Company Update (NASDAQ:FCEL): Renewable Hydrogen From Tri-Generation FuelCell Energy Inc Included Under California Low Carbon Fuel Standard - Smarter Analyst","m_szYear":"2016","m_szDocSumamry":"Company Update (NASDAQ:FCEL): Renewable Hydrogen From Tri-Generation FuelCell Energy Inc Included Under California Low Carbon Fuel Standard SHARE ON: Corey Williams — January 14, 2016, 8:40 AM EDT FuelCell Energy, Inc. (NASDAQ: FCEL ), a global leader in the design, manufacture, operation and service of ultra‐clean, efficient and reliable fuel cell power plants, has received contingent certification for a prospective pathway for its renewable hydrogen generation solution using fuel cells at wastewater treatment facilities under the Low Carbon Fuel Standard (LCFS), administered by the Californi","m_szDocBody":"company update nasdaqfcel renewable hydrogen trigeneration fuelcell energy included california low carbon fuel standard share corey william edt fuelcell energy inc nasdaq fcel global leader design manufacture operation service ultraclean efficient reliable fuel cell power plant received contingent certification prospective pathway renewable hydrogen generation solution fuel cell wastewater treatment facility low carbon fuel standard lcf administered california air resource board carb lcf certified pathway define carbon intensity type alternative fuel trigeneration pathway remarkable negative carbon intensity meaning vehicle hydrogen fuel trigeneration carbon free fact offsetting carbon emission compared alternative production renewable hydrogen megawattclass fuelcell energy power plant transportation fuel fuel cell electric vehicle fcev generated carbonneutral nonpolluting process inclusion trigeneration fuelcell energy power plant lcf credit market mean kilogramme renewable hydrogen supplied vehicle fueling eligible lcf credit sold traded offset carbonintensive petroleum fuel usage final certification expected period operation review performance data megawattclass trigeneration system utilising renewable biogas fuel source commercial solution generating hydrogen technologically operationally financially superior conventional hydrogen generation alternative ability generate renewable hydrogen affordably private capital gamechanger addresse challenge faced regulator auto manufacturer chip bottone chief executive officer fuelcell energy inc key aspect supporting hydrogen infrastructure widespread fuel cell electric vehicle adoption clean carbonfriendly solution priced competitively cost gasoline deliver lcf established governor executive order require producer petroleumbased fuel reduce carbon intensity product beginning quarter percent culminating percent total reduction petroleum importer refiner wholesaler develop low carbon fuel product buy lcf credit company develop sell low carbon alternative fuel renewable hydrogen trigeneration fuel cell plant california senate bill direct carb develop regulation ensure production hydrogen transportation undertaken manner consistent environmental goal carb team performed complete life cycle analysis lca trigeneration system determined negative carbon footprint power hydrogen generation process net carbonneutral due renewable biogas cleaner biogas compared alternative tony leo vice president application engineering advanced technology development fuelcell energy inc mean overall negative carbon emitter superior result comparison hydrogen generation technology electrolysis traditional steam reforming lcf standard focused carbon emission notable trigeneration produce hydrogen water consumed electrolysis conventional steam methane reforming trigeneration waste heat water byproduct produced fuel cell power generation make hydrogen efficiently external water consumption increasingly concern region including california continued leo original source share fuelcell energy closed yesterday fcel year year low stock day moving average day moving average rating front fuelcell energy subject number recent research report report issued cowen analyst jeff osborne maintained buy rating fcel price target imply upside current level separately day fbr carter driscoll reiterated buy rating stock price target tiprankscom rank financial analyst blogger gauge performance past recommendation jeff osborne carter driscoll total average return respectively osborne success rate ranked analyst driscoll success rate ranked fuelcell energy integrated fuel cell company company design manufacture sell instal operate service ultraclean efficient stationary fuel cell power plant distributed power generation fcel fuelcell energy receive new analyst rating update fcel enter address analyst stock significant new hit market completely free ","m_szGeo1":"United States","m_szSourceType":"source_news","m_szSrcUrl":"http://www.smarteranalyst.com/2016/01/14/company-update-nasdaqfcel-renewable-hydrogen-tri-generation-fuelcell-energy-inc-included-california-low-carbon-fuel-standard-lcfs/","m_Places":["California","California Senate","Cowen"],"m_People":["Corey","Chip Bottone","Tony Leo","Leo","Jeff Osborne","Carter Driscoll","Driscoll"],"m_Companies":["Nasdaq","Generation Fuelcell Energy Inc","Williams","Fuelcell Energy, Inc.","California Air Resources Board","Carb","Advanced Technology","Target","Fuelcell Energy Inc"],"m_BiGrams":["fuelcell energy","fuel cell","renewable hydrogen","low carbon","power plant","hydrogen generation","carbon fuel","energy inc","cell power","carbon intensity","negative carbon","lcf credit"],"m_TriGrams":["low carbon fuel","fuelcell energy inc","fuel cell power"],"m_SocialTags":[],"m_Topics":[],"m_Industry":[],"m_Technology":[],"m_BiCnt":[10,7,6,4,4,4,3,3,3,3,3,3],"m_TriCnt":[3,3,3],"m_iDocBodyWordCnt":479}
