{"m_szDocID":"596298","m_szDocTitle":"Audi Q8 h-Tron Quattro Concept Swaps In Hydrogen Fuel Cell For e-Tron's Battery","m_szYear":"2016","m_szDocSumamry":"Audi Q8 h-Tron Quattro Concept Swaps In Hydrogen Fuel Cell For e-Tron's Battery Email This Page To (separate emails with commas) Message (optional) Your email was sent successfully. Close 3,997 views Jan 14, 2016 Follow John Add to circle Hot on the heels of the all-electric Audi e-Tron Quattro Concept it revealed last fall, VW Group's luxury brand Audi has released a second iteration of the same concept. This one still has all four wheels powered by electric motors, but the electricity to run them comes not from a large battery pack but a hydrogen fuel cell. The orange Audi h-Tron Quattro Con","m_szDocBody":"audi htron quattro concept swap hydrogen fuel cell etron battery separate email commas message optional successfully close view follow john add circle hot heel allelectric audi etron quattro concept revealed fall group luxury brand audi released iteration concept wheel powered electric motor electricity run large battery pack hydrogen fuel cell orange audi htron quattro concept debuted week detroit auto show unexpected reveal conventionally powered audi allroad waggon miss audi etron quattro concept electric car previewed frankfurt motor show audi ceo rupert stadler casually mentioned allelectric utility vehicle time referring etron etron htron concept built adaptation audis latest mlbevo architecture vehicle engine sited longitudinally transversely siegfried pint audis electric powertrain chief point out electricdrive version mlbevo emotor mounted transverselybut matter audi htron quattro concept detroit auto show enlarge photo previous etron quattro concept pair kilowatt horsepower electric motor rear axle single motor front axle htron concept rearrange component front motor moving rear axle single rear motor powering front wheel etron large flat battery pack hydrogenpowered quattro concept kilowatthour lithiumion battery audi plugin hybrid model accommodate transient power demand store recaptured braking energy see audi htron quattro performance fuelcell plugin car unveiled auto show nov fuelcell stack power electronic mounted front concept hood battery pack deliver higher power output usual sustained output possible adding total maximum power delivery temporary burst acceleration total hydrogen stored tank mounted lengthwise tunnel front seat sit transversely rear seat load bay audi htron quattro concept detroit auto show pint noted unusual power electronic work audi term tripod arrangement dcdc converter allowing power shuttled direction fuel cell battery pack emotor etron htron variant audis electricdrive platform designed concurrently from start pint said arrangement powertrain component version safety structure handle crash energy noted cheque out audi bmw mercede plan compete teslaand dec batteryelectric etron route energy flat battery pack strong structural member door sill larger tunnel htron absorb energy route lengthwise centre structure hydrogen tank fully filled audi htron quattro deliver mile range european nedc test cycle quote tomph acceleration time second pint referred hydrogenpowered next evolutionary step electricdrive vehicle audi htron quattro concept detroit auto show enlarge photo audi ceo stadler production plan htron committing brand delivering batteryelectric etron latest new car concept detroit detroit auto show new ","m_szGeo1":"","m_szSourceType":"source_news","m_szSrcUrl":"http://www.greencarreports.com/news/1101859_audi-q8-h-tron-quattro-concept-swaps-in-hydrogen-fuel-cell-for-e-trons-battery","m_Places":["Orange","Detroit","Frankfurt","Dc","Tesla"],"m_People":["Audi","Rupert Stadler","Evo","Mercedes","Stadler"],"m_Companies":["Vw Group","Mlb","Seat","Bmw"],"m_BiGrams":["quattro concept","audi htron","htron quattro","auto show","battery pack","detroit auto","concept detroit","fuel cell","etron quattro"],"m_TriGrams":["audi htron quattro","htron quattro concept","detroit auto show","etron quattro concept","quattro concept detroit","concept detroit auto"],"m_SocialTags":[],"m_Topics":[],"m_Industry":[],"m_Technology":[],"m_BiCnt":[9,7,7,6,5,4,4,3,3],"m_TriCnt":[7,5,4,3,3,3],"m_iDocBodyWordCnt":370}
