{"m_szDocID":"596245","m_szDocTitle":"3 takeaways from rare meeting with Honda CEO","m_szYear":"2015","m_szDocSumamry":"FacebookEmail Twitter Google+ LinkedIn Pinterest 3 takeaways from rare meeting with Honda CEO DETROIT—Honda's global CEO, Takahiro Hachigo, held a rare meeting with U.S. media Monday on the sidelines of the Detroit auto show. Post to Facebook 3 takeaways from rare meeting with Honda CEO DETROIT—Honda's global CEO, Takahiro Hachigo, held a rare meeting with U.S. media Monday on the sidelines of the Detroit auto show. Check out this story on USATODAY.com: http://usat.ly/1P3YFya CancelSend A link has been sent to your friend's email address. Posted! A link has been posted to your Facebook feed. 1","m_szDocBody":"facebookemail google linkedin pinterest takeaway rare meeting honda ceo detroithondas global ceo takahiro hachigo held rare meeting media sideline detroit auto show post takeaway rare meeting honda ceo detroithondas global ceo takahiro hachigo held rare meeting media sideline detroit auto show cheque storey usatodaycom cancelsend link friend address posted link posted feed commenting read conversation guideline faqs takeaway rare meeting honda ceo nathan bomey usa today est honda motor global ceo takahiro hachigo photo honda connect tweet linkedin commentemailmore detroitjapanese automaker honda posted record sale american consumer fled small car company typically favoured automaker global ceotakahiro hachigo held rare meeting media sideline detroit auto show threekey takeaway conversation translated japanese company skittish discussing embattledsupplier takata exploding air bag blamed death honda vehicle massive recall automaker relationship takata deteriorated honda blamed supplier lying test data air bag crisis publicly exposed hachigo honda focused accelerating repair identifying root rupturing air bag regulator related ammonium nitrate accelerant right working make make problem customer hachigo appointed ceo early takata scandal engulfed automaker reporter sought question takata press meeting monday spokesman asked submit question supplier writing the people charge takatas business takata comment theyre doing hachigo said company plan bring plugin hybrid vehicle north america plugin hybrid typically battery run electricity number mile gasoline engine kick company accord plugin hybrid performed poorly chevrolet volt plugin hybrid lagged sale fuelefficient conventional engine vehicle hachigo company also investigating battery electric vehicle run purely electric charge declined company bring back honda fit electric vehicle natural gas vehicle focus honda abandoned civic sedan ran natural gas plan revisit technology instead company focusing hydrogen fuel cell vehicle scheduled make debut honda heading toward realising future cofree hachigo said follow usa today reporter nathan bomey nathanbomey connect tweet linkedin commentemailmore read share storey top videos ","m_szGeo1":"United States","m_szSourceType":"source_news","m_szSrcUrl":"http://www.usatoday.com/story/money/cars/2016/01/11/takahiro-hachigo-honda-ceo-detroit-auto-show/78632608/","m_Places":["Detroit","North America"],"m_People":["Takahiro Hachigo","Nathan Bomey","Takata"],"m_Companies":["Twitter","Google","Linkedin","Pinterest","Honda","Facebook","Usatoday.com","Usa Today"],"m_BiGrams":["rare meeting","plugin hybrid","takeaway rare","meeting honda","honda ceo","global ceo","ceo takahiro","takahiro hachigo","hachigo held","held rare","meeting media","media sideline","sideline detroit","detroit auto","auto show","air bag"],"m_TriGrams":["takeaway rare meeting","rare meeting honda","meeting honda ceo","global ceo takahiro","ceo takahiro hachigo","hachigo held rare","held rare meeting","rare meeting media","meeting media sideline","media sideline detroit","sideline detroit auto","detroit auto show"],"m_SocialTags":[],"m_Topics":[],"m_Industry":[],"m_Technology":[],"m_BiCnt":[6,4,3,3,3,3,3,3,3,3,3,3,3,3,3,3],"m_TriCnt":[3,3,3,3,3,3,3,3,3,3,3,3],"m_iDocBodyWordCnt":294}
