{"m_szDocID":"596284","m_szDocTitle":"German car makers are getting hyped about hydrogen | Ars Technica","m_szYear":"2016","m_szDocSumamry":"German car makers are getting hyped about hydrogen Audi and Mercedes-Benz are the latest to jump on the H2 train. by Jonathan M. Gitlin - Jan 18, 2016 3:08 pm UTC Audi's h-tron quattro fuel cell concept. Audi Audi's h-tron quattro fuel cell concept. The h-tron's insides. Mercedes-Benz This is the Mercedes-Benz GLC. A fuel-cell version is due to go on sale in 2017. Mercedes-Benz Several years ago, Mercedes-Benz leased 50 fuel-cell powered F-Cells to environmentalists and celebrities in California. Toyota The 2016 Toyota Mirai. This is an actual production car you can buy, and we've even tested ","m_szDocBody":"german car maker hyped hydrogen audi mercedesbenz latest jump train jonathan gitlin utc audis htron quattro fuel cell concept audi audis htron quattro fuel cell concept htron inside mercedesbenz mercedesbenz glc fuelcell version due sale mercedesbenz year ago mercedesbenz leased fuelcell powered fcell environmentalist celebrity california toyota toyota mirai actual production car buy tested jonathan gitlin hondas fuel cell auto industry hydrogenfever add audi mercedesbenz list audi week north american international auto show detroit debut htron quattro fuel cell suv concept uks autocar reporting mercedesbenz greenlit production fuel cell version glc suv audis htron quattro fairly similar etron quattro concept los angele lot powertrain knowhow full tank range mile onboard lithiumion battery topped gigantic solar panel roof meanwhile mercedesbenz told autocar detroit show middle rolling fuel cellpowered glc berevealed world year frankfurt auto show mercedesbenz previouslyventuredinto world hwith fuelcell version bclass called fcell year ago mercedesbenz leased fcell environmentalist california reading toyota mirai review futuristic supersmooth hydrogen fuel cell car toyotas step sustainable mobility expensivebut highly impressive too bmw playing while company experimenting internal combustion engine traditional hydrocarbon fuel recently showed sery powered fuel cell set production japan company toyota honda bullish fuel cell electric vehicle now concerted push government start economy company bringing concept production car auto show now meanwhile general motor joined army test suitable fuel cell evs military application live california buy fuel cell resident state wait publicly accessible filling station reality california increased subsidy fuel cell evup top federal tax incentivein order hasten uptake technology convinced fuel cell answer though elon musk dismissive technology lot people pointed efficient electricity produce hand store electricity charge battery quickerrefueling timessimilar hydrocarbonfueled vehiclecompared battery evs expect fuel cell announcement future listing image audi ","m_szGeo1":"United States","m_szSourceType":"source_news","m_szSrcUrl":"http://arstechnica.com/cars/2016/01/german-car-makers-are-getting-hyped-about-hydrogen/","m_Places":["California","Toyota","Detroit","Uk","Los Angeles","Frankfurt","Reading","Japan"],"m_People":["Audi","Jonathan M. Gitlin","Jonathan Gitlin","Honda","Elon"],"m_Companies":["Mercedes-benz","International Auto Show","Autocar","Bmw","General Motors","Us Army"],"m_BiGrams":["fuel cell","htron quattro","audis htron","quattro fuel","auto show"],"m_TriGrams":["audis htron quattro","htron quattro fuel","quattro fuel cell"],"m_SocialTags":[],"m_Topics":[],"m_Industry":[],"m_Technology":[],"m_BiCnt":[13,4,3,3,3],"m_TriCnt":[3,3,3],"m_iDocBodyWordCnt":283}
