{"m_szDocID":"597981","m_szDocTitle":"Rumor: Honda, General Motors To Work Together on New Fuel Cell Production Facility In Attempt To Lower Costs | Transport Evolved","m_szYear":"2016","m_szDocSumamry":"Rumor: Honda, General Motors To Work Together on New Fuel Cell Production Facility In Attempt To Lower Costs Nikki Gordon-Bloomfield Self-confessed geek and mother of two, Nikki has been talking and writing about cars ever since she passed her driving test. Back then, her Internet contributions were all classic car-focused. Now, sheâ€™s all about greener, cleaner, safer and smarter cars. General Motors honda Hydrogen Fuel Cell Rumors Aside from the challenges of building an entirely new hydrogen filling station infrastructure, one of the biggest challenges facing the mass marketability of hydrog","m_szDocBody":"rumour honda general motor work fuel cell production facility attempt lower cost nikki gordonbloomfield selfconfessed geek mother two nikki talking writing car passed driving test back then internet contribution classic carfocused now shes greener cleaner safer smarter car general motor honda hydrogen fuel cell rumour challenge building hydrogen filling station infrastructure biggest challenge facing mass marketability hydrogen fuel cell car today sheer cost building complex fuel cell stack heart hydrogen fuel cell vehicle whilerecent advance hydrogen fuel cell stack technology reduced cost building hydrogen fuel cell stack order magnitude compared fuel cell made year ago making hydrogen fuel cell stack complex costly business partnership honda work reducing cost fuel cell toyota mirai hydrogen fuel cell sedan example toyotas production hydrogen fuel cell vehicle kilowatt fuel cell stack heart toyota mirai car painstakingly constructed hand costingtoyota estimated fuel cell made now mean massive loss mirai roll production line cost drop hydrogen fuel cell vehicle wont profitable automaker faced production costsautomaker aredoing whattheyalwaysdo faced new expensive vehicle technology collaborate automaker attempt bring cost level mutually beneficial firm honda clarity hondas production fuel cell vehicle cost more that claim asahi shimbun via autobloggreen honda general motor production hydrogen fuel cell stack quoting anonymous senior official honda newspaper company plan work joint factory hydrogen fuel cell stack produced honda gmbrand vehicle due online time factory leverage economy scale experience automaker produce energydense highly efficient hydrogen fuel cell stack cost produce thehydrogen fuel cell stack found toyota mirai hyundai tucson fcv commerciallyavailable hydrogen fuel cell car sale world today year honda automaker enter hydrogen vehicle marketplace clarity fuel cell sedan car designed ground maximise efficiency vehicle range compromising interior space honda begin roll limitednumber clarity fuel cell year production cost production fuel cell car expected similarly mirai point point collaboration hydrogen fuel cell car fuel cell stack isnt new indeed major automaker world paired partnership hydrogen fuel cell vehicle researched developed mutuallybeneficial circumstance ford example partnered daimler nissan sharing fuel cell technology toyota paired bmw honda confirmed existing hydrogen fuel cell partnership extend building joint fuel cell production facility wed place plausible focused electrified vehicle recent year longstanding hydrogen fuel cell development programme and automaker quietly working technology alongside electric vehicle ensure competitor case hydrogen fuel cell breakthrough occur latest new evolving transport dont forget followtransport evolvedon twitter channel support directly monthly supporting member simply share friend ","m_szGeo1":"","m_szSourceType":"source_news","m_szSrcUrl":"https://transportevolved.com/2016/01/20/rumor-honda-general-motors-to-work-together-on-new-fuel-cell-production-facility-in-attempt-to-lower-costs/","m_Places":["Take","Toyota"],"m_People":["Nikki Gordon"],"m_Companies":["Honda","General Motors","Stack Technology","The Asahi Shimbun","2020s","Indeed","Bmw","Twitter","Facebook","Youtube"],"m_BiGrams":["fuel cell","hydrogen fuel","cell stack","cell vehicle","cell car","general motor","toyota mirai"],"m_TriGrams":["hydrogen fuel cell","fuel cell stack","fuel cell vehicle","fuel cell car"],"m_SocialTags":[],"m_Topics":[],"m_Industry":[],"m_Technology":[],"m_BiCnt":[32,18,10,5,4,3,3],"m_TriCnt":[18,10,5,4],"m_iDocBodyWordCnt":392}
