{"m_szDocID":"599894","m_szDocTitle":"Why Fuel Cell Vehicles Are Stumbling out of the Gate","m_szYear":"2015","m_szDocSumamry":"Why Fuel Cell Vehicles Are Stumbling out of the Gate Reddit Source: Toyota When the Toyota Mirai went on sale in October, reports said demand was high in California, where as many as 2,000 pre-orders had been made on the fuel cell vehicle. Though only half that amount would be available on the U.S. market, the Mirai’s debut months have seen even slower sales than expected. Because of problems in the hydrogen station infrastructure, the numbers are going to get worse before they get better. According to a report in Ward’s Auto, Toyota has asked dealers in California to hold off on delivering ne","m_szDocBody":"fuel cell vehicle stumbling gate reddit source toyota toyota mirai sale october report demand california preorder made fuel cell vehicle half amount market mirais debut month slower sale expected problem hydrogen station infrastructure number worse better report ward auto toyota asked dealer california hold delivering model fuel cell vehicle hydrogen station open public dozen station expected remain limbo inaccessible early adopter leaving automaker tough spot station open andsome experienced problem keeping tank full mirais range exceeding mile understand limited infrastructure start toyota north america ceo bob lentz told ward green light consumer work rather live open hydrogen stationotherwise request filed time future early dealership return mirai reflect limitation insideevs total sale made toyota month market battery electric vehicle struggle penetrate market debut month challenge unique fuel cell vehicle source honda electrical outlet charging station norm city hydrogen storey driver face range anxiety travel town aston martin ceo andy palmer coined phrase describe fuel cell vehicle owner face that range anxiety palmer quipped financial time range panic car result toyota effectively scaled rollout mirai automaker expect sell unit end station open alternative fuel market game necessarily winning honda preparing launch clarity fuel cell year happy didnt debut model earlier japanese automaker segment hyundai tucson fuel cell limited quantity leasing california areasaudi previewed fuel cell concept auto show recent year including htron quattro concept showed naias detroit pioneer tough road fuel cell vehicle learning hard way cheque autos cheat sheet tumblr follow eric ","m_szGeo1":"United States","m_szSourceType":"source_news","m_szSrcUrl":"http://www.cheatsheet.com/automobiles/why-fuel-cell-vehicles-are-stumbling-out-of-the-gate.html/?a=viewall","m_Places":["Toyota","California","North America","Palmer","Tucson","Detroit"],"m_People":["Bob Lentz","Honda","Andy Palmer","Audi","Eric"],"m_Companies":["Reddit","Aston Martin","Financial Times","Hyundai","Facebook","Twitter"],"m_BiGrams":["fuel cell","cell vehicle","station open"],"m_TriGrams":["fuel cell vehicle"],"m_SocialTags":[],"m_Topics":[],"m_Industry":[],"m_Technology":[],"m_BiCnt":[9,6,3],"m_TriCnt":[6],"m_iDocBodyWordCnt":241}
