{"m_szDocID":"599841","m_szDocTitle":"Is China Right To End Green Car Subsidies By 2020","m_szYear":"2016","m_szDocSumamry":"Is China Right To End Green Car Subsidies By 2020 By Muhammad Saad Khan on Jan 25, 2016 at 11:49 am EST Is China Right To End Green Car Subsidies By 2020 DIVIDENDS & SPLITS Incorrect Tesla Motors raised $226.1 million dollars in an Initial Public Offering on June 19, 2010. Shares closed at $23.89 after opening at $17. Next Question Correct Tesla Motors raised $226.1 million dollars in an Initial Public Offering on June 19, 2010. Shares closed at $23.89 after opening at $17. VIEW FINANCIAL PERFORMANCE 1 China is planning to end heavy subsidies offered to electric cars by 2020, in a move to make","m_szDocBody":"china end green car subsidy muhammad saad khan est china end green car subsidy dividend split incorrect tesla motor raised million dollar initial public offering share closed opening question correct tesla motor raised million dollar initial public offering share closed opening financial performance china planning end heavy subsidy offered electric car move make automaker selfdependent china decided gradually reduce subsidy energy vehicle elimination financial incentive year finance minister lou kiwei country phase financial incentive manufacturer green car automaker selfreliant production government announced offer heavy incentive energy market support production zeroemission vehicle order lower carbon emission vehicle china urban city choking smog government lower dependence oil import result government incentivized production electric car hybrid hydrogenpowered fuel cell vehicle order catch foreign automaker licence plate offered free owner green car bloomberg green car buyer yuan subsidy offered central government entrepreneur leshi owner jia yeuting pooled money open teslalike venture faraday future chinabased company planning big player billion investment nevada incentive helped production green car ramp year bloomberg incentive fruitful far energy car sale quadrupled unit year government invested billion yuan billion alternative fuel vehicle gao feng advisory billion yuan expected invested end quarter mainland government set fiveyear plan target put million electric car road end making local producer byd baic motor zoyte auto ramp production byd chairman chuanfu see full electrification passenger car commercial vehicle completely electrified year end kiwei expect manufacturer longer dependent government subsidy that government planned gradually reduce financial subsidy kiwei government cut incentive year incentive eliminated however government focusing alternative plan support production green car california kiwei studying pointbased system green car company tesla motor nasdaqtsla gather environmental credit production zeroemission vehicle credit sold company traded automaker type option discussed chinese regulator editing asad rizvi graphic arshad abbasi ","m_szGeo1":"China","m_szSourceType":"source_news","m_szSrcUrl":"http://www.bidnessetc.com/61897-is-china-right-to-end-green-car-subsidies-by-2020/","m_Places":["Tesla","Nevada","California"],"m_People":["China Right","Muhammad Saad Khan","Lou Kiwei","Jia","Feng","Wang Chuanfu","Asad","Rizvi","Arshad Abbasi"],"m_Companies":["Tesla Motors","Pooled","Ramp","Target","Tesla Motors Inc","Nasdaq"],"m_BiGrams":["green car","tesla motor","electric car"],"m_TriGrams":[],"m_SocialTags":[],"m_Topics":[],"m_Industry":[],"m_Technology":[],"m_BiCnt":[8,3,3],"m_TriCnt":[],"m_iDocBodyWordCnt":290}
