{"m_szDocID":"599924","m_szDocTitle":"Hexagon Composites steps up hydrogen business development  | JEC Composites","m_szYear":"2016","m_szDocSumamry":"Hexagon Composites steps up hydrogen business development The company sets up a separate business unit for hydrogen storage and transportation systems. Business , Pipes & Tanks , Other sectors Hydrogen is considered an essential part of the fuel mix required for the green transition. Hexagon Composites has already taken a significant role in shaping the hydrogen storage industry with contracts supporting OEMs, refueling station builders, and research laboratories in Asia, Europe and North America. The company is well positioned across the hydrogen value chain with cylinders for passenger and c","m_szDocBody":"hexagon composite step hydrogen business development company set separate business unit hydrogen storage transportation system business pipe tank sector hydrogen considered essential part fuel mix required green transition hexagon composite significant role shaping hydrogen storage industry contract supporting oem refuelling station builder research laboratory asia europe north america company positioned hydrogen chain cylinder passenger commercial vehicle ground storage transportation backup power solution based proven type technology hydrogen cylinder futureoriented product jon erik engeset ceo hexagon composite hydrogen clean fuel emit greenhouse gase use establishment separate business unit strengthen organisational capability lead development highgrowth market niche fuel cell vehicle number leading oem introducing hydrogen fuel cell vehicle fcv alternative battery electric vehicle market potential fcv segment significant strong presence experience natural gas vehicle ngv market fcvs natural expansion company ground storage introduction fuel cell vehicle drive demand hydrogen refuelling station hrs generate good market opportunity company type cylinder technology fatigueresistant cycling property composite pressure cylinder make suitable storage steel alternative gas distribution demand hydrogen distribution solution grow strongly function demand fuel system hexagon composite mobile pipeline solution certified hydrogen distribution type tank gas transported trailer space backup power hydrogen fuel cell efficient emerging choice lowemission reliable backup power telecommunication emergency service medical service remote location hexagon composite offer backup power solution lightweight hydrogen tank enhance system performance payback business unit reported segment highpressure cylinder business area quarter rick rashilla vice president global hydrogen team hexagon lincoln head unit reporting jack schimenti president highpressure cylinder business area rashilla lead team focusing research development marketing existing product solution team member located germany austria norway maintain strong relation key industry player ","m_szGeo1":"United States","m_szSourceType":"source_news","m_szSrcUrl":"http://www.jeccomposites.com/news/composites-news/hexagon-composites-steps-hydrogen-business-development","m_Places":["Asia","Europe","North America","Mobile Pipeline Solutions","Lincoln","Germany","Austria","Norway"],"m_People":["Jon Erik Engeset","Rick Rashilla","Jack Schimenti"],"m_Companies":["Hexagon","Power Solutions","Mobile Pipeline Solutions"],"m_BiGrams":["hexagon composite","backup power","fuel cell","business unit","cell vehicle"],"m_TriGrams":["fuel cell vehicle"],"m_SocialTags":[],"m_Topics":[],"m_Industry":[],"m_Technology":[],"m_BiCnt":[5,4,4,3,3],"m_TriCnt":[3],"m_iDocBodyWordCnt":267}
