{"m_szDocID":"600073","m_szDocTitle":"I’m putting my money where my mouth is and betting against climate change » The Spectator","m_szYear":"2016","m_szDocSumamry":"I’m putting my money where my mouth is and betting against climate change I’ve invested in a fund that will aim to short-sell overvalued renewable energy stocks Email ‘As oil crashes, is it time to short solar stocks?’ Gosh, I wish I’d read that headline a year ago. The solar stock it tipped for doom in January 2015 has since plummeted from $19 to $2.65. Yes, hindsight can be a wonderful thing. But what if there were an area of the markets which you knew to be grotesquely overvalued as a result of ignorance, dishonesty, and false sentiment? You’d be mad not to bet against it, wouldn’t you? It ","m_szDocBody":"putting money mouth betting climate change ive invested fund aim shortsell overvalued renewable energy stock oil crashes time short solar stock gosh read headline year ago solar stock tipped doom plummeted yes hindsight wonderful thing area market knew grotesquely overvalued result ignorance dishonesty false sentiment youd mad bet wouldnt you gambling plain common sense ive felt time climate change industry read expert commentator writing subject city page shocked invariably financier big corporate opinion rest assumption manmade global warming real renewable viable alternative fossil fuel data hasnt fiddled premise false then hedge fund hedge fund startup ive donated internet cost single share management company dont make rich principle matter this know investment vehicle explicitly bet climate change consensus time big short principle good guy called rigged market bluff bad guy made running annual climate change industry worth roughly online shopping industry trillion perform valuable service giving people want cheaply efficiently exact opposite racket form statesanctioned organised crime choice save odd bearded poi enthusiast spend penny income wind turbine solar panel research grant dubious climate science project local council sustainability officer climate change potemkin industry emblem crony capitalism dependent existence favour granted rentseeking trougher political class warren buffett famously said tax credit build wind farm reason build them height scare main reason advanced justify outrageous scam first world appeared warming unprecedented potentially catastrophic rate due anthropogenic emission secondly fossil fuel needed replacing give future generation viable energy alternative thirdly column phenomenon called ocean acidification carbon dioxide apparently killing seas rationale hold more global warming making nonsense computer model predicting oil glut shown fossil fuel arent running time soon ocean acidification appear alarmist junk science meme mean trillion global industry predicated spurious proposition harmless trace gas carbon dioxide menace regulating existence carbon dioxide threat isnt implication enormous thing mean heavily coweighted computer model predicting global climate fatally flawed another mean taxpaying public grow increasingly impatient green taxe regulation subsidy hurled problem imaginary meanwhile developing nation china india burning fossil fuel tomorrow then canny investor advantage personally qualified make recommendation here understand fund strategy part long position undervalued fossilfuel stock short position overvalued renewable energy stock price theory plummet subsidy dry fate solyndra company obama subsidised tune million collapsed offer encouraging precedent here spanish nearequivalent abengoa another complicated part based enforcing due diligence judicial review suppose basis demonstrably flawed science local council declared coastal area nobuild zone rising sea level lot hidden realised court overturn council decision finally global cooling cool future fund inhouse expert believe entering period low solar activity akin ice age manner trouble affect latitude wheat grown kind place live holiday will course opportunity amid gloom farmland valuable land reclamation temperate zone lucrative prospect agricultural technology pressing look spectacular cropper hedge fund succeed represent massive triumph man mention honest science free market dark force enronstyle postcapitalism cheque website judge spectator less receive issue delivered full web app access join polidorisghost ive invested fund aim shortsell overvalued renewable energy stock careful dude timing everything shorted corrupt there adetoz yeah underestimate rugged steadfastness corrupt people jame morgan hmmm website give end state page fact page annual carbon dioxide emission produced nature human emission contributing tree plant produce more what tree plant produce huh again plant photosynthesis stupid website fact completely wrong kentgeordie alive give back die right point manmade negligible impact delingpole right climate scam hoax mistake lie indictment integrity rationality humanity western civilisation abrogard convincing videos anthropogenic global warming argument contrary dont more select sidebar youve kafkaesque tendency live australia what all courtesy intelligentsia world class carefully coiffed politician frank position short long writer delingpole lapse jargon writing stock money matter jamesdelingpole einstein reputedly said make simple possible simpler long short concept abstruse spectator reader word column tight put equally succinctly tell frank true hadnt considered word constraint print dont suppose concept wit spectator reader word short long dont obvious connexion refer still help separate bear bull one ecclesiam programme called google people about sort interesting website second explanation taxing all taxed abrogard youre smart witty rest dumb comprehensible make web searches order understand you guide rest pathfinder leader but wait bit abrogard buy promise sell butler graph there side argument single addressed knocked down can swarm drone excuse didnt short solar stock whilst shorting oil multi stock time chris hobson claptrap solar power earth middle century year alone itdoesntaddup global electricity generation pwh based typical global average solar output produce twh annum global electricity consumption global energy consumption real animec nice calculation predicated assumption btw middle century revise account probability increased capacity middle century trend foresee wrt demand itdoesntaddup revise calculation capacity year century make current level power generation half millennia provide global energy use understand there suggest start here exdent solar doubled year electricity production early now doubling double year reach electricity planet happen show respect kurzweil effect worked human genome mapping itdoesntaddup show respect engineering economic reality reason solar company broke world notably china bulk panel made spain cut subsidy germany building fired power station cope sun doesnt shine neighbour taking step block german export midsummer solar surpluse with insane energy policy account half world capacity covered china japan usa tiny solar leader germany account electricity generation major problem grid integration exdent dont company broke success industry large number bankruptcy part major disruptive change technology early car industry tory majority control cut subsidy wind solar popular announced coal burning plant closed spain financial trouble showing sign renewing effort renewable germany treating coal burning short term coverage close nuclear plant time energiewende popular germany gather statement clean energy grid integration problem directly contradicted ceo hertz company boris schucht manage large transmission company eastern northern germany company electricity input wind solar outage decade renewable problem that accurate weather forecasting important dont answer basic premise solar and lesser degree wind exponential growth curve result price subsidy dropping levelized cost fossil fuel place world year factoring health pollution global warming cost example india gigawatt solar wind base year ago cleantechnicacom update contract wind solar globe warningwarning hazard wing brain itdoesntaddup gwh tiny output drax day suffer innumeracy common green exdent sorry misspoke gigawatt equate gigawatt nuclear plant india taxing coal time pay clean energy plant trend important china spent clean energy vietnam rethink coal trendthe trend allen starr bill butler read printed reference page paper show wide range observed climate indicator continue show consistent globally warming world understanding climate system work allen starr now lot word nothing goinlike billio admit pause warming show model evidence based wrong pause significant absence warming swiveleyed loon love paper hasnt warming doesnt wont warming hope charllize theron yet eric jenning jeez dumb alarmist comment here take cake met office case youve forgotten future british children snow happen winter recordsetting amount fallen snow hasnt since put way realist word called philip haddad doubt mind global warming caused heat emitted burning fossil fuel nuclear power industry heat emission time attributed rise air temperature enough combined fact higher temperature prevented normal dissipation geothermal heat flow explain problem blamed bernd felsche reporting thermometer heat source extinction surface reporting station remote areas end cold war rise average reported depended removal remote station unafflicted urban heat island effect midsummer bbq midnight fundamentallyflawed read interesting rise fall ecological economic fallen vigorously pushed overlord dismantle premise method result neatly concisely imagine year ecological economic substituted climate change philip haddad bernd world heating denying global warming real bernd felsche satellite balloon data show warming year longer previous period warming alarmed minor fluctuation temperature place cagw total bunkum sat fundamental thermodynamic fluid mechanic starting boundary condition greenhouse gase determine atmospheric not radiative surface temperature due diurnal insolation nosmokewithout hardly highest rise temperature recorded arctic recollection heat source there fact barren unpopulated wilderness suggest totally incorrect assertion bernd felsche global average nonsense nonetheless alarmist calculated algorithm beside surface station arctic number perimeter airport thatve expanded runway sealed black stuff support traffic jet aircraft exhaust temperature approaching further arctic station tend coast cahnge current oceanic oscillation account antarctic newly discovered geothermal activity account ice expanding nosmokewithout analysis recording station trend show difference rural sited recording station urban station uhi myth arctic station show trend cited citing station trend important revealed independently location geothermal activity regional account majority ice loss accelerate effect ice loss ocean erosion glacial edge ice expansion increase cooling year extent ice extension previous year lot post suggest david lot post suggest well uhi absolutely myth drive london country temperature question extent effect influenced global land temperature dataset analysis guess referring fatal flaw taking crude approach rural versus urban station erasing effect conclusion rural temperature increasing fast urban one take small percentage previously rural station encroached development big dollop uhi added dataset urban station show warming uhi established increase incrementally people fuel centefire covered international finance business degree course brush strangely bet commodity rise bet commodity fall paul paulson prime mortgage racket know paul spot benefit impending collapse ordinary people dont money invest idea pooling resource mind trillion lot bread mulp paulson betting housing housing dropping long term bet building housing hundred year paulson betting housing built absurd borrowed money pay house labour cost built explain logic apple stock priced basis selling phone labour cost make growth rate year planet buying apple phone year pay cheaper android phone need fraser magee carbon dioxide dismissed basis trace gas inhaled nitric oxide regularly patient respiratory failure concentration part million profound effect pulmonary circulation climate scientist insulating gas similar effect global temperature allbuss what point pressure oxygen toxic breath atmosphere made primarily helium irrelevant fraser magee delingpole dismiss basis trace element meant couldnt effect global temperature nonsense temperature havent increased nosmokewithout poley bothered conduct easy experiment kitchen discover greenhouse gas waste space david daft video exposed fraud angus couple drop blue ink bucket water turn water blue spite ink ppm tickertapeguy ocean biggest absorber carbon dioxide largest producer oxygen global warming occur factor reach man including fluctuation sun mulp factor considered example sun average moving earth octmar period cool climate leading ice age sun moving closer end ice age century begun reverse temperature continue rise sun hotter excluded monitoring sun space decade increase output warming continued scientist stupid wild imagination justify research lead paper published phd tenure grant foundation including koch tickertapeguy start bottom comment age scientist make god priest word infallible mind scientist human make big mistake call mistake lesson way scientist biassed objective example steven hawkin believe world government problem concept power remain wealthy nation bank control decision process closest world government system lean heavily powerful wealthy nation world called infallible scientist considered heard solar issue brought global warming heard effect rim fire atlantic ocean long line undersea volcanoe spewing noxious fume century helena erupted spewed noxious fume surpass industrial age human race innocent solely guilty climate change mini ice age reason operation barbarossa launched axis force russia failed faced bitter winter russias written history massive happen control change earth climate nosmokewithout fluctuation factored concentration greatest warming arctic continue warm decade destroy arctic risk humanity inhabit northern hemisphere clear problem satellite data reflect surface temperature satellite data flat earther delingpole faith physical sign planet earth continue heat fool realise narrative emperor clothes tickertapeguy warm wouldnt water dry water dry heat wouldnt rain rain wouldnt good deal washed wouldnt cloud cover rain temperature cool down nivek ecyoj regulating tickertapeguy conclusion earth believe million year atmosphere change nitrogen based atmosphere oxygen nitrogen based one nitrogen feeding algae emitted oxygen that earth complex distance earth sun earth gravity large hold atmosphere presence massive amount water dozen aspect life thrive gulf stream england weather doe stream disrupted england cold arctic nosmokewithout clear atmospheric change changed climate planet long time past clear reengineering atmosphere affect climate human year remarkable quick article informed delingpole muster good human raise curiosity level point show interest planet live what them tickertapeguy climate change occurring act human not human change that specy consciously make effort manage climate human nosmokewithout correct tickertapeguy bug environmentalist protest land cordoned mind bring back bug genetic extinct specy bug consciously darn save human race nosmokewithout wondered personal insult start nosmokewithout youll simple water atmosphere due warming evidence intensity extreme rainfall increasing cloud insulating effect clear night colder cloudy night washed atmosphere concentration continue rise increased water vapour changing balance atmosphere significant consequence resulting tickertapeguy fine continue live life normal avoid political correctness force drive electric car economy run coal live burn back yard leave open care god bollinger bolshevik human atmosphere control temperature molecule atmosphere cubic mile benign mandatory life control temperature million cubic mile oceanand billion cubic mile molten rock cubic mile override effect elliptical orbit earth variable output sun mass solar system energy solar system human powerful force solar system control tax environmentalist nosmokewithout wouldnt survive david barely temperature station arctic difference satellite agree balloon measurement land based record land based record subject constant adjustment cooling past data consistent rationale audit trail people vociferous commitment idea catastrophic global warming realclimate run dataset bet dano bring satellite balloon measurement topic surface temp arctic weird best mulp betting climate change raising cash capital property insurance company provided complete property insurance florida seaside property renewal fixed premium year based weather average past year capital asset property flooded requiring payout insolvent current interest rate return capital loss rate past century yield generous return risk correct climate change ocean rise flood developed florida shore property betting people happily kill job energy based job lose miss cheap stuff paid wage unemployed paying price produce dead job wage cut climate change destroy property betting climate change betting die action driving fast eating much playing loaded gun mother nature kill you exdent ball put money long coal ozboy trick timing end subsidy inside knowledge there knowledge generally held bad guy bad convince dark side beany hey suggest commit crime point short selling create momentum critical mass investment wall street journalist talk majority investor arent buying global warming figuratively literally critical mass easier achieve fund creator believe timing right macrol wouldnt give nickle macrol coal oil gas heavily subsidised heavily subsidised decade remove subsidy watch fade bollinger bolshevik oil state rich wind revenue wind free subsidy medication today angus cost solar halving year wind power making significant improvement too guess tend technology going lindzenpm back century fire going cave chilly reid angus nonsense problem germany wind grid parilous situation require computer control stable worse wind generation reid macrol dont silly essential back stone age renewable generation electricity work fossil fuel generation worldwide biggest reliable electrical generation nuclear industry expertise had form generation favourable reliable unlike wind toy solar nosmokewithout well delingpole man know construct sentence make sense gambling climate change straight forward bet exist not playing market thing jaria day mocking follow green policy claimed icelandic volcano caused pollution human caused year hasnt eruption making lot money angus volcanoe account gigatonne year burning fossil fuel account gigatonne mankind increased atmospheric increasing atmospheric concentration ppm ppm jaria angus clear public mixed information subject information respected australasian scientist detailed information back assertion member public hope reasonable amount intelligence conflicting information coming expert subject difficult decide opinion correct stupidicus discredited dishonest flat earther today deserving death penalty better agw community hes suggested kaschner congratulate writer chosen perfectly fitting name credit due stupidicus coming obvious impotent meaning significance fact lack rebuttal charge presented stupid reid realise course day flat earther consensus current wrong alarmist pro agw like bet delingpole stupidicus conceding validity observation accompanying remark idiot delingpole muster defence documented irrefutable criminal stupidity subject agw indicative lack intellectual heft integrity both jaria impossible dismiss multi national oil company strangled birth alternative fuel put existence weve heard rumour inventor bought truth rumour mikewaller principle count money stupid put equity house fund idiot principled idiot puerile attention seeker anthony global cooling either derekcolman fossil fuel investment good moment share depressed divestment campaign low level reflect true worth eventually rise true bought low price make killing coincidence advocate divestment people world richest family multi millionaire celebrity usual idiot job protesting famous institution easily hot headed lefty manipulated super rich dirty work gordon fulk view fossil fuel good investment left attacked fuel driven company deliver wellknown billionaire supporting attack picked bankrupt coal company intention restarting charging premium coal that selling coal green indulgence absolve guilt burning premium coal neat honest ruse similarly sierra club ten million dollar chesapeake energy malign coal electric power company switch natural gas abundance giant marcellus field neat honest ruse gordon fulk phd physic corbett oregon usa dano view fossil fuel good investment bank investment house dont leave grifter taking gullible money best gordon fulk commend jame delingpole superior knowledge subject accustomed journalist base related global warming delingpole right amazing treat read make sense change gordon fulk phd physic corbett oregon usa yup lucky rational trump potus dano denialist paid shill losing money betting climate ill trend ill bet delingpole climate metric courage conviction have best dano impressive lack knowledge science history physic light science support belief validate selfidentity zip zilch nothing nada nil null set squat jack bupkis best putin phd theoretical physicist experience application numerical method solution differential equation required computational model respect field computational fluid dynamic relevant current climate model excellent knowledge history physic fail relevant doubt experience fluid dynamic filling car weekly basis putin doubt are elbow you base statement either substance acidic basic neutral scale measure acidic basic substance scale range neutral acidic fairly educated scot solution simply equal concentration hydrogen hydroxyl ion adding effect increasing concentration ion hco produced disassociate hco extra ion definition solution acidic scale logarithmic mean concentration ion time concentration hydrogen mean time apparently small change graph correspond significant change ocean chemistry dano taxpayer ocean acidification easiest myth bust agw warmist with schoollevel chemistry warmist claim atmospheric manmade absorbed ocean form uspecified dilute acid acidic ocean school level chemistry physic warm water capacity dissolve gase water warm gase longer held solution cloudy bubble kettle hot water tap ocean warming acidic discuss physic chemistry level ocean warming naturally releasing atmosphere round coincidence causation dano oceanographer oceanographic institute then wasting time going say best ignore science actual fact repeating nonsense you dano ","m_szGeo1":"United Kingdom","m_szSourceType":"source_news","m_szSrcUrl":"http://www.spectator.co.uk/2016/01/im-putting-my-money-where-my-mouth-is-and-betting-against-climate-change/","m_Places":["China","India","Australia","Nice","Spain","Uk","Germany","Japan","Usa","U.k.","Northern","Vietnam","London","Atlantic Ocean","Russia","England","Florida","Wall Street","Oregon","Nada"],"m_People":["Gosh","Potemkin","Warren Buffett","Obama","James Morgan","Huh","Chris Hobson","Boris Schucht","Allen Starr","Charllize Theron","Eric Jennings","Philip Haddad","Bernd Felsche","Bernd","David S","Paul Paulson","Fraser Magee","Steven Hawkins","Bollinger","Gordon J. Fulks","Marcellus Field","James Delingpole"],"m_Companies":["Abengoa","Enron","Spectator","Youtube","Bulls","Google","Pathfinders","Hertz Company","Drax","Greens","O2","Guess","Pooling","Apple","Un","Axis","As Capital","Critical Mass","Lg","Indicative","Sierra Club","Chesapeake Energy"],"m_BiGrams":["climate change","global warming","fossil fuel","carbon dioxide","betting climate","ice age","cubic mile","gordon fulk","overvalued renewable","renewable energy","energy stock","solar stock","hedge fund","ocean acidification","burning fossil","middle century","wind solar","clean energy","bernd felsche","urban station","flat earther","solar system"],"m_TriGrams":["betting climate change","overvalued renewable energy","renewable energy stock","burning fossil fuel"],"m_SocialTags":[],"m_Topics":[],"m_Industry":[],"m_Technology":[],"m_BiCnt":[13,11,11,6,4,4,4,4,3,3,3,3,3,3,3,3,3,3,3,3,3,3],"m_TriCnt":[3,3,3,3],"m_iDocBodyWordCnt":2995}
