{"m_szDocID":"601372","m_szDocTitle":"Oil Prices and Fuel Economy Regulation and Support | The Energy Collective","m_szYear":"2016","m_szDocSumamry":"0 Posted February 6, 2016 Keywords: Energy Security , Tech , Sustainability , Utilities , Efficiency , Environmental Policy , Oil , Risk Management , Energy and Economy , Fuels , Politics & Legislation , Fuel Economy Standards , oil price collapse Roland Hwang, Transportation Program Director, San Francisco Now that pump prices have dropped, automakers are once again rushing to sell gas-thirsty SUVs and pickups and calling for a weakening of the coming historic 54.5 miles-per-gallon fuel economy standard. But is that a smart strategy given the volatility of the global oil market, U.S. vulnerab","m_szDocBody":"posted keyword energy security tech sustainability utility efficiency environmental policy oil risk management energy economy fuel politic legislation fuel economy standard oil price collapse roland hwang transportation programme director san francisco pump price dropped automaker rushing sell gasthirsty suvs pickup calling weakening coming historic milespergallon fuel economy standard smart strategy volatility global oil market vulnerability event unstable unfriendly oilproducing country auto industry history shortsighted business decision make sense retreat key initiative reduce carbon pollution time public increasingly anxious climate change threat health environment economy word forgotten lesson president obamawho scheduled visit detroit auto show todayreached historic agreement strengthen standard equivalent mpg model year automaker stood president support lower oil price automaker eager weaken historic standard agreed year ago auto industry forgotten lesson past oil shock past year detroit automaker caught flatfooted selling gasthirsty vehicle wanted buy gas price needing taxpayer bailout year ago american taxpayer agreed bail chrysler eventually providing total billion loan bailout estimated saved million job job risk gas price skyrocket again putting job innovation risk betting oil price remain low weakening standard highoctane gamble undermine huge investment clean vehicle technology generating job catalysing innovation creating profit year ago found worker located facility state manufacturing component technology contribute increased fuel efficiency see supplying ingenuity based data environmental protection agency epa job grown faster anticipated auto industry adopting fuelefficient technology turbocharging advanced transmission faster pace epa projected major investment electric car including ford chrysler poised start paying well car touted month detroit auto show chevrolet bolt travel mile charge federal tax credit the average price car groundbreaking vehicle crack code mainstream electric car nissan tesla poised follow similar product latetothegame chrysler introducing plugin minivan standard working rhetoric automaker struggling comply current fuel economy standard gradually rise equivalent mpg model year contrary automaker complied clean car standard time row overcomplied record margin latest epa data overall automobile sold mile gallon fuel efficient year ago averaging mpg epa fuel economy trend report increasing fuel economy standard prevent automaker record sale year million unit demonstrating strong sale higher fuel efficiency handinhand and fact consumer gallon gas benefit fuel economy standard high low oil price standard combined earlier round fueleconomy standard issued obama administration projected billion metric tonne carbon pollution atmosphere life vehicle lower oil price standard offer fuel saving pollution reduction benefit well excess cost council foreign relation fellow varun sivaram michael levi concluded recent paper found energy security environmental benefit stronger government projected fuel economy standard back strong standard needed ever rollercoaster world oil market lend smart planning betting low oil price rushing sell gasthirsty vehicle weakening standard threaten health climate energy security put auto company worker investor risk today low oil price auto industry strong north star guide longterm investment record sale healthy profit time automaker double innovation leadership clean car technology photo mike mozart post comment ","m_szGeo1":"United States","m_szSourceType":"source_industry","m_szSrcUrl":"http://www.theenergycollective.com/nrdcswitchboard/2318024/strong-fuel-economy-standards-needed-even-when-oil-prices-are-low?utm_source=feedburner&utm_medium=feed&utm_campaign=The+Energy+Collective+%28all+posts%29","m_Places":["San Francisco","Detroit","Tesla"],"m_People":["Roland Hwang","Obama","Chrysler","Michael A. Levi","Mike Mozart"],"m_Companies":["Environmental Protection Agency","Epa","Flickr"],"m_BiGrams":["fuel economy","oil price","economy standard","auto industry","energy security","low oil"],"m_TriGrams":["fuel economy standard","low oil price"],"m_SocialTags":[],"m_Topics":[],"m_Industry":[],"m_Technology":[],"m_BiCnt":[7,7,6,4,3,3],"m_TriCnt":[6,3],"m_iDocBodyWordCnt":467}
