{"m_szDocID":"601577","m_szDocTitle":"Auto expo off to a start with 51 launches, hybrids hog show - The Economic Times","m_szYear":"2016","m_szDocSumamry":"Auto expo off to a start with 51 launches, hybrids hog show By PTI | 3 Feb, 2016, 09.57PM IST Toyota displayed its range of hybrid and fuel cell vehicles, including the Mirai hydrogen car. German auto major VW showcased its plug in hybrid Passat GT and Hyundai displayed it fuel cell electric model Sonata FCEV. RELATED COMPANIES ET SPECIAL: Love visual aspect of news? Enjoy this exclusive slideshows treat! GREATER NOIDA: India's flagship automobile show, the Auto Expo, kicked off today as 51 new products made their debut, with Bollywood celebrities, including Katrina Kaif and Ranbir Kapoor, alo","m_szDocBody":"auto expo start launches hybrid hog show pti feb ist toyota displayed range hybrid fuel cell vehicle including mirai hydrogen car german auto major showcased plug hybrid passat hyundai displayed fuel cell electric model sonata fcev related company special love visual aspect new enjoy exclusive slideshow treat greater noida indias flagship automobile show auto expo kicked today product made debut bollywood celebrity including katrina kaif ranbir kapoor sportstar sachin tendulkar virat kohli adding glamour quotient keeping theme mobility all expo opened car market leader maruti suzuki unveiling muchawaited compact suv vitara brezza host hybrid electric vehicle manufacturer represented technology future show jointly organised siam society indian automobile manufacturer acma automotive component manufacturer association confederation indian industry opened public auto expo lot vehicle covering underlying theme mobility all time lot electric hybrid vehicle launches siam president vinod dasari told pti expo held time automobile company scanner due rising concern pollution dasari said auto industry vehicle safer greener norm auto industry meet auto industry showcasing product ahead regulation alternate fuel technology hero motocorp showcased electric scooter concept duete mahindra genze unveiled genze connected allelectric scooter toyota displayed range hybrid fuel cell vehicle including mirai hydrogen car german auto major showcased plug hybrid passat hyundai displayed fuel cell electric model sonata fcev motor show began india expo mart industry hoping model boost sale vitara brezza scheduled hit market upcoming week general motor announced chevrolet essentia chevrolet beat active india hyundai unveiled suv tucson honda car india cover suv brv time india toyota kirloskar motor drove allnew innova crysta luxury segment tata motorsowned jlr launched jaguar sport saloon priced upto lakh exshowroom delhi audi launched plus exshowroom price mumbai delhi crore bmw launched sery price ranging crore crore exshowroom delhi allnew priced lakh lakh hand mercedesbenz unveiled global suv glc sclass cabriolet premium luxury maybach guard auto expo here stay top business new economic time app download now missany storey follow follow ","m_szGeo1":"India","m_szSourceType":"source_news","m_szSrcUrl":"http://economictimes.indiatimes.com/industry/auto/news/industry/auto-expo-off-to-a-start-with-51-launches-hybrids-hog-show/articleshow/50840413.cms","m_Places":["Toyota","Greater Noida","India","Siam","Tucson","Tata","Delhi","Mumbai"],"m_People":["Katrina Kaif","Ranbir Kapoor","Sachin Tendulkar","Virat Kohli","Maruti Suzuki","Honda","Kirloskar","Audi"],"m_Companies":["Hyundai","Related Companies","Manufacturers Association","Hero Motocorp Showcased","General Motors","Jaguar","Bmw","Mercedes-benz","Economic Times","Twitter"],"m_BiGrams":["auto expo","fuel cell","auto industry"],"m_TriGrams":[],"m_SocialTags":[],"m_Topics":[],"m_Industry":[],"m_Technology":[],"m_BiCnt":[4,4,3],"m_TriCnt":[],"m_iDocBodyWordCnt":318}
