{"m_szDocID":"601575","m_szDocTitle":"Auto Expo kicks off; Maruti unveils Vitara Brezza","m_szYear":"2016","m_szDocSumamry":"FLASH Delhi HC dismisses plea of AAP leader seeking rejection of defamation suit filed against him by Jaitley. Business Posted at: Feb  3 2016 11:16PM Auto Expo kicks off; Maruti unveils Vitara Brezza Also in this section Reimbursement in lieu of notice pay taxable President and COO Suzuki Motor Corporation Toshihiro Suzuki (R) and Kenichi Ayukawa, MD and CEO Maruti Suzuki India, pose with the newly launched SUV Vitara Brezza at the Indian Auto Expo 2016 in Greater Noida, on the outskirts of New Delhi, on February 3, 2016.  — PTI Greater Noida, February 3 India’s flagship automobile show, the ","m_szDocBody":"flash delhi dismisse plea aap leader seeking rejection defamation suit filed jaitley business posted auto expo kick off maruti unveil vitara brezza section reimbursement lieu notice pay taxable president coo suzuki motor corporation toshihiro suzuki kenichi ayukawa ceo maruti suzuki india pose newly launched suv vitara brezza indian auto expo greater noida outskirt delhi pti greater noida indias flagship automobile show auto expo kicked product made debut bollywood celebrity including katrina kaif ranbir kapoor sportstar sachin tendulkar virat kohli adding glamour quotient auto expo pic keeping theme mobility all expo opened car market leader maruti suzuki unveiling muchawaited compact suv vitara brezza host hybrid electric vehicle manufacturer represented technology future show jointly organised siam society indian automobile manufacturer acma automotive component manufacturer association confederation indian industry opened public auto expo lot vehicle covering underlying theme mobility all time lot electric hybrid vehicle launches siam president vinod dasari told pti expo held time automobile company scanner due rising concern pollution dasari said auto industry vehicle safer greener norm auto industry meet auto industry showcasing product ahead regulation alternate fuel technology hero motocorp showcased electric scooter concept duete mahindra genze unveiled genze connected allelectric scooter toyota displayed range hybrid fuel cell vehicle including mirai hydrogen car german auto major showcased plug hybrid passat hyundai displayed fuel cell electric model sonata fcev motor show began india expo mart industry hoping model boost sale vitara brezza scheduled hit market upcoming week general motor announced chevrolet essentia chevrolet beat active india hyundai unveiled suv tucson honda car india cover suv brv time india toyota kirloskar motor drove allnew innova crysta luxury segment tata motorsowned jlr launched jaguar sport saloon priced upto lakh exshowroom delhi audi launched plus exshowroom price mumbai delhi crore bmw launched sery price ranging crore crore exshowroom delhi allnew priced lakh lakh hand mercedesbenz unveiled global suv glc sclass cabriolet premium luxury maybach guard auto expo here twowheeler segment unveiling motorcycle dsk benelli tvs suzuki motorcycle hero motocorp unveiled splendour ismart motorcycle developed completely inhouse firm research development r&d team rival honda motorcycle scooter india introduced model scheduled india launch later company miss citing cost low return investment include bajaj auto daimler india commercial vehicle dicv royal enfield harley davidson organiser upbeat increase number footfall lakh time lakh people visited show edition pti ","m_szGeo1":"India","m_szSourceType":"source_news","m_szSrcUrl":"http://www.tribuneindia.com/news/business/auto-expo-kicks-off-maruti-unveils-vitara-brezza/191455.html","m_Places":["Delhi","Ayukawa","India","Greater Noida","New Delhi","Siam","Toyota","Tucson","Tata","Mumbai"],"m_People":["Jaitley","Toshihiro Suzuki","Maruti Suzuki","Katrina Kaif","Ranbir Kapoor","Sachin Tendulkar","Virat Kohli","Honda","Kirloskar","Audi","Bajaj","Royal Enfield"],"m_Companies":["Suzuki Motor Corporation","Manufacturers Association","Hero Motocorp Showcased","Hyundai","General Motors","Jaguar","Bmw","Mercedes-benz","Harley Davidson"],"m_BiGrams":["auto expo","vitara brezza","auto industry"],"m_TriGrams":[],"m_SocialTags":[],"m_Topics":[],"m_Industry":[],"m_Technology":[],"m_BiCnt":[6,4,3],"m_TriCnt":[],"m_iDocBodyWordCnt":381}
