{"m_szDocID":"601640","m_szDocTitle":"Global Automotive Fuel Cell Market 2015-2019 with Ballard Power Systems, ACAL, Nuvera Fuel... -- DUBLIN, Feb. 3, 2016 /PRNewswire/ --","m_szYear":"2015","m_szDocSumamry":"Research and Markets Logo. DUBLIN, Feb. 3, 2016 /PRNewswire/ -- Research and Markets ( http://www.researchandmarkets.com/research/2wkdwl/global_fuel_cell ) has announced the addition of the \"Global Fuel Cell Market in the Automotive Industry 2015-2019\" report to their offering. The global fuel cell market in the automotive industry to grow at a CAGR of 45.27% during the period 2016-2020. The report covers the present scenario and the growth prospects of the global fuel cell market in the automotive industry for 2015-2019. The market size has been calculated based on the revenue generated from ","m_szDocBody":"research market logo dublin feb research market announced addition global fuel cell market automotive industry report offering global fuel cell market automotive industry grow cagr period report cover scenario growth prospect global fuel cell market automotive industry market size calculated based revenue generated global unit shipment fuel cell automotive industry report include discussion key vendor operating market company making huge investment r&d fuel cell industry university government organisation engaged research demonstration project technology industry instance national energy foundation working energy industrial technology development organisation nedo fuel cell research project report development hydrogen infrastructure key driver growth market hydrogen primary fuel fuel cell electric vehicle fcevs million tonne hydrogen produced year meet growing hydrogen fuel cell fcevs further report state vendor address functional issue fuel cell system include improving thermal air water management market divided segment based type vehicle lightduty vehicle ","m_szGeo1":"United States","m_szSourceType":"source_news","m_szSrcUrl":"http://www.prnewswire.com/news-releases/global-automotive-fuel-cell-market-2015-2019-with-ballard-power-systems-acal-nuvera-fuel-cells-plug-power--hydrogenics-dominating-300214643.html","m_Places":["Dublin","Uk"],"m_People":["Nedo"],"m_Companies":["Logo"],"m_BiGrams":["fuel cell","automotive industry","global fuel","cell market","market automotive"],"m_TriGrams":["global fuel cell","fuel cell market","cell market automotive","market automotive industry"],"m_SocialTags":[],"m_Topics":[],"m_Industry":[],"m_Technology":[],"m_BiCnt":[8,4,3,3,3],"m_TriCnt":[3,3,3,3],"m_iDocBodyWordCnt":140}
