{"m_szDocID":"601688","m_szDocTitle":"Auto Expo 2016: Hyundai unveils the all-new Tucson; price starts at Rs 18 Lakh","m_szYear":"2016","m_szDocSumamry":"Auto Expo 2016: Hyundai unveils the all-new Tucson; price starts at Rs 18 Lakh Early Bird Early Bird Hyundai Motor India, the country's largest exporter and the second largest car manufacturer in India, on Wednesday showcased its global SUV, the Tucson at the 2016 Auto Expo, here. Hyundai Tucson represents a significant step forward in the future SUV line-up for the Indian Automobile Market. Hyundai has high aspirations for the brand globally. The All-New Tucson is a bold car bringing our brand slogan 'New Thinking, New Possibilities' to life. Through great design and advanced technologies, it","m_szDocBody":"auto expo hyundai unveil allnew tucson price start lakh early bird early bird hyundai motor india country largest exporter largest car manufacturer india showcased global suv tucson auto expo here hyundai tucson represent significant step forward future suv lineup indian automobile market hyundai aspiration brand globally allnew tucson bold car bringing brand slogan new thinking possibility life great design advanced technology represent future hyundai product india expectation tucson design expresse progressive spirit passion transforming brand age hyundai allnew tucson bold athletic presence achieved refined flowing surface bold proportion sharp line importantly newest generation hexagonal grille hyundai brand signature allnew tucson adopt strong proportion profile suv design confidently create sense vehicle sleek agile speaking tucson unveil auto expo koo ceo hmil said our theme auto expo experience hyundai goal offer intuitive experience customer touch live adding brilliant moment experience hyundai auto expo important platform showcase hyundais strength design technology future product spirit challenge innovation expand experience hyundai programme strengthen hyundai brand read auto expo cricketer bollywood star brand car hyundai motor showcased highperformance subbrand result intensive testing product development subbrand build hyundai motor successful motorsport experience technology capability drive future performanceoriented racetrackcapable model forward bring the thrilling winding road fun customer love car developed participation worldrenowned playstation gran turismo racing game sery hyundai vision gran turismo concept highlight sustainable technology race car design representing future potential hyundai capitalise hyundai motor fastgrowing strength signify pace change brand matching company ambition challenge perception making real emotional connexion customer hnd carlino metre concept suv developed hyundai namyang design centre hnd carlino boast multifunction lifestyle ability making urban iconic statement unique design stylish exterior futuristic design direction showcase hyundais commitment meet growing aspiration indian customer opting suvs hyundai motor showcased allnew global luxury brand genesis deliver humancentered luxury range model feature highest standard performance design innovation genesis mean beginning hint value standard brand bring global luxury car market active possesse stylish design advanced technology redefine hyundais automotive excellence india active offer urban mobility complete package style performance design expresse hyundais progressive spirit passion aggressive tall stance hyundai evolved everincreasing pace year significantly improved internal combustion gasoline diesel engine higher fuel efficiency sonata phev built driver environment setting hyundai motor milestone contribution humanity advanced technology aim protect global environment lead industry regenerative environmental technology hyundai displayed fcev mockup auto expo fuel cell stack electric motor battery hydrogen tank main component fuel cell electric vehicle fcev ","m_szGeo1":"India","m_szSourceType":"source_news","m_szSrcUrl":"http://www.catchnews.com/auto-expo/auto-expo-2016-hyundai-unveils-the-all-new-tucson-price-starts-at-rs-18-lakh-1454485798.html","m_Places":["Tucson","India","Centre"],"m_People":["Yk Koo","Carlino"],"m_Companies":["Hyundai","Progressive"],"m_BiGrams":["auto expo","hyundai motor","allnew tucson","advanced technology","experience hyundai"],"m_TriGrams":[],"m_SocialTags":[],"m_Topics":[],"m_Industry":[],"m_Technology":[],"m_BiCnt":[7,6,4,3,3],"m_TriCnt":[],"m_iDocBodyWordCnt":399}
