{"m_szDocID":"601638","m_szDocTitle":"Hybrids vehicles at Auto Expo 2016 could be solution to industry's search for green mobility: SIAM | ET Auto","m_szYear":"2016","m_szDocSumamry":"#Auro Expo 2016 Hybrids vehicles at Auto Expo 2016 could be solution to industry's search for green mobility: SIAM The hybrid vehicles launched at the Auto Expo 2016 could be an answer to the industry's search for green mobility. TNN  |  08 February 2016, 12:07 PM IST Follow ETAuto Share   GREATER NOIDA: The hybrid vehicles launched at the Auto Expo 2016 could be an answer to the industry's search for green mobility. The newly launched vehicles enable a driver to instantaneously switch a car into electric mode and are part of the reason SIAM director general Vishnu Mathur feels the expo has be","m_szDocBody":"#auro expo hybrid vehicle auto expo solution industry green mobility siam hybrid vehicle launched auto expo answer industry green mobility tnn ist follow etauto share greater noida hybrid vehicle launched auto expo answer industry green mobility newly launched vehicle enable driver instantaneously switch car electric mode part reason siam director general vishnu mathur feel expo meet expectation promote green mobility technology incorporated vehicle manufacturer several electronic hybrid vehicle launched motor show latest technology enable vehicle switch electric power need hence vehicle ecofriendly said manufacturer hybrid electric vehicle auto show hero motocorp duete mahindra genze genze range electric scooter display toyota launched hybrid fuel cell run vehicle mirai hydrogen fuelled car electronic buse jbm attraction mathur said vehicle designed sophisticated technology day huge footfall show immense potential industry country mathur huge response visitor heartening the auto expo biennial huge response making event annual future said exhibitor receiving good response visitor this promising india significant market automobile industry exceed customer expectation accelerate growth year strengthen brand country katsushi inoue president ceo honda car india ltd friday day public exhibition auto expo registered total visitor number increased lakh saturday official expecting increase visitor edition motor show day show jointly organised indian automobile manufacturer siam automotive component manufacturer india acma confederation indian industry cii ","m_szGeo1":"India","m_szSourceType":"source_news","m_szSrcUrl":"http://auto.economictimes.indiatimes.com/news/industry/hybrids-vehicles-at-auto-expo-2016-could-be-solution-to-industrys-search-for-green-mobility-siam/50898356","m_Places":["Siam","Greater Noida","Toyota","India","Cars India Ltd."],"m_People":["Mathur","Katsushi Inoue","Honda"],"m_Companies":["Tnn","Diesel","Jbm","Cars India Ltd."],"m_BiGrams":["auto expo","hybrid vehicle","green mobility","industry green","vehicle launched"],"m_TriGrams":["industry green mobility","hybrid vehicle launched"],"m_SocialTags":[],"m_Topics":[],"m_Industry":[],"m_Technology":[],"m_BiCnt":[5,4,4,3,3],"m_TriCnt":[3,3],"m_iDocBodyWordCnt":210}
