{"m_szDocID":"601694","m_szDocTitle":"Auto Expo 2016: Hyundai unveils Tucson, showcases Hyundai N 2025 Vision Gran Turismo","m_szYear":"2016","m_szDocSumamry":"Auto Expo 2016: Hyundai unveils Tucson, showcases Hyundai N 2025 Vision Gran Turismo India Infoline News Service          |          Mumbai |          February 03, 2016         11:16 IST The Tucson design expresses progressive spirit and passion, transforming the brand to New Age Hyundai. The All-New Tucson has a bold and athletic presence achieved through refined, flowing surfaces, bold proportions, sharp lines and most importantly, the newest generation hexagonal grille – Hyundai brand signature. Article saved successfully to my page. You must be Logged in to save article.       Hyundai Moto","m_szDocBody":"auto expo hyundai unveil tucson showcase hyundai vision gran turismo india infoline new service mumbai ist tucson design expresse progressive spirit passion transforming brand age hyundai allnew tucson bold athletic presence achieved refined flowing surface bold proportion sharp line importantly newest generation hexagonal grille hyundai brand signature saved successfully page logged save article hyundai motor india country largest exporter largest car manufacturer india showcased global suv tucson auto expo greater noida hyundai tucson represent significant step forward future suv lineup indian automobile market hyundai aspiration brand globally allnew tucson bold car bringing brand slogan thinking possibility life great design advanced technology represent future hyundai product india expectation tucson design expresse progressive spirit passion transforming brand age hyundai allnew tucson bold athletic presence achieved refined flowing surface bold proportion sharp line importantly newest generation hexagonal grille hyundai brand signature allnew tucson adopt strong proportion profile suv design confidently create sense vehicle sleek agile speaking tucson unveil auto expo koo ceo hmil said theme auto expo experience hyundai goal offer intuitive experience customer touch live adding brilliant moment experience hyundai auto expo important platform showcase hyundais strength design technology future product spirit challenge innovation expand experience hyundai programme strengthen hyundai brand hyundai vision gran turismo hyundai motor showcased performance subbrand result intensive testing product development subbrand build hyundai motor successful motorsport experience technology capability drive future performanceoriented racetrackcapable model forward bring thrilling winding road fun customer love car developed participation worldrenowned playstation gran turismo racing game sery hyundai vision gran turismo concept highlight sustainable technology race car design representing future potential hyundai capitalise hyundai motor fastgrowing strength signify pace change brand matching company ambition challenge perception making real emotional connexion customer hnd carlino hnd carlino metre concept suv developed hyundai namyang design centre hnd carlino boast multifunction lifestyle ability making urban iconic statement unique design stylish exterior futuristic design direction showcase hyundais commitment meet growing aspiration indian customer opting suvs genesis zone hyundai motor showcased allnew global luxury brand genesis deliver humancentered luxury range model feature highest standard performance design innovation genesis mean beginning hint value standard brand bring global luxury car market sport zone active possesse stylish design advanced technology redefine hyundais automotive excellence india active offer urban mobility complete package style performance design expresse hyundais progressive spirit passion aggressive tall stance sonata phev hyundai evolved increasing pace year significantly improved internal combustion gasoline diesel engine higher fuel efficiency sonata phev built driver environment setting hyundai motor milestone contribution humanity advanced technology fcev mock aim protect global environment lead industry regenerative environmental technology hyundai displayed fcev mock auto expo fuel cell stack electric motor battery hydrogen tank main component fuel cell electric vehicle fcev icoty zone loved trusted car manufacturer india hyundai motor india won icoty successively product creta elite grand icoty respectively hyundai age brand modern premium brand direction redefined segment setting benchmark year technology zone hyundai displayed world class refined powertrain transmission kappa gdi kappa litre tgdi dct speed kappa gdi broadening engine lineup hyundai motor downsized kappa gdi engine displayed part generation small turbocharged gasoline engine kappa gdi engine tuned maximise fuel economy focus comfort facilitate spirited driving sacrificing efficiency kappa litre tgdi unit incorporate highpressure singlescroll turbocharger integrated exhaust manifold design inject fuel directly inside cylinder improving combustion rate power fuel efficiency dct global sevenspeed doubleclutch transmission dct improvement fuel consumption emission compared conventional sixgear automated transmission acceleration performance increase speed hyundai motor india unveiled auto expo eightspeed automatic transmission frontwheel drive vehicle improving fuel economy sixspeed auto speed showcase light agile element hyundai technology globally eightspeed auto initially large luxury car segment genesis crash car genesis hyundais flagship model offer level physical crashworthiness excellent safety feature standard genesis crash car test exhibited hyundai pavilion auto expo genesis aced safety evaluation small overlap front crash evaluation superioror advancedrated front crash prevention system automatic braking capability structural integrity strength key priority hyundai motor company engineering team vehicle advanced highstrength steel body structure designed outset pass world demanding crash test traffic safety poli specially designed engage youth children hyundai developed kid zone pavilion encourage safety education awareness part safe move csr initiative famous animation sery traffic safety poli screened kid zone theatre ","m_szGeo1":"India","m_szSourceType":"source_news","m_szSrcUrl":"http://www.indiainfoline.com/article/news-top-story/auto-expo-2016-hyundai-unveils-tucson-showcases-hyundai-n-2025-vision-gran-turismo-116020300193_1.html","m_Places":["Tucson","India","Mumbai","Greater Noida","Centre"],"m_People":["Yk Koo","Carlino","Genesis Zone","Icoty Zone","Creta","Genesis Crash","Poli","Safe Move"],"m_Companies":["Hyundai","Progressive","Clutch","Hyundai Technology","Hyundai Motor Company"],"m_BiGrams":["hyundai motor","auto expo","gran turismo","allnew tucson","kappa gdi","hyundai vision","vision gran","design expresse","progressive spirit","spirit passion","tucson bold","hyundai brand","motor india","advanced technology","experience hyundai","hnd carlino"],"m_TriGrams":["vision gran turismo","progressive spirit passion","allnew tucson bold","hyundai motor india"],"m_SocialTags":[],"m_Topics":[],"m_Industry":[],"m_Technology":[],"m_BiCnt":[10,8,4,4,4,3,3,3,3,3,3,3,3,3,3,3],"m_TriCnt":[3,3,3,3],"m_iDocBodyWordCnt":693}
