{"m_szDocID":"603588","m_szDocTitle":"Cemont, a brand owned by Air Liquide Welding","m_szYear":"2016","m_szDocSumamry":"Home / Business / Cemont, a brand owned by Air Liquide Welding Cemont, a brand owned by Air Liquide Welding Posted on Cemont > About Cemont > The brand Cemont, a brand owned by Air Liquide Welding Cemont is a brand of high repute in the field of welding products and battery chargers that designs, manufactures and commercialises all over the world its own products. Thanks to technological leadership and high quality standards, the enterprise can fully satisfy clients' expectations. Sales organization CEMONTâ€™s sales organization is strategically positioned worldwide, in order to meet our custome","m_szDocBody":"home business cemont brand owned air liquide welding cemont brand owned air liquide welding posted cemont cemont brand cemont brand owned air liquide welding cemont brand repute field welding product battery charger design manufacture commercialise world product technological leadership quality standard enterprise fully satisfy client expectation sale organisation cemont sale organisation strategically positioned worldwide order meet customer requirement full quality control cemont gained iso accreditation product testing main step production process focus maintained quality safety product final packaging cemont perform operation safety test product range product designed developed compliance international standard country cemont equipment sold latest new auto rim ammo auto rim lead softer aided resisting wear shallow rifling revolver half moon clip made reloading swifter thin bent broke war time condition more medical alert device work located ogden utah rexburg idaho stateoftheart centre full duplicate other reliability medical alert system good emergency call centre back more alex ovechkin submitted batshit crazy bracket america bracket submitted russian professional ice hockey player captain washington capital alex ovechkin youve crossed bridge apparent alex ovechkin norfolk state elite eight more alesis usb kit unmistakable alesis alesis drum set usb kit feature realistic naturalfeeling playing surface electronic drum set feature completely sound module quality drum cymbal percussion sound more alesis drum module question ask info here including postage mainland united kingdom midiusb cable not included trigger pad trigger kit playing pro tool more air liquide opt spain air liquide healthcare take part opt project programme activity support sharing knowledge experience healthcare professional focus superior quality life patient helping entire stick treatment air liquide air liquide good tip create see long term see core see company development see commitment constant inventiveness country people gain service valuable record data important ahead newest development airframer deliver concise strong intelligence web make subscriber unlimited service airframer record data working hour ing air liquide espana ing air liquide espana opt opt madrid company specialise opt opt industrial gase note show established opt opt spain company address paseo castellana madrid spain show map important information air liquide produce distribute healthcare specialty ingredient personal care pharmaceutical vaccine economy electronic market supply gas professional service production semiconductor flt panel photovoltaic panel air liquide employee review standing confident competent fair dependable constant bona fide honour work with departed contract standing finish line company cared employee ike helped employee deal consequence air liquide vengeance short time hire move perform magic organised dont problem punctual mindful professional air liquide good tip create see long term see core see company development see commitment constant inventiveness country people realtimequote air liquide opt eur air liquide equipment gase large industry future health businesse company operate simply segment gas service engineering construction activity south wale alexandria head office cpap service oxygen service web sale enquiry head office air liquide working hour ampm closed lunch unit gardener road alexandria nsw air liquide open manufacturing hub opt uae head honcho chairman benoit potier andthefrench ambassador cantheuae excellency michel miraillet thestateoftheart facility include sqm workshop located opt ras khaimah free zone strategize move spot close dubai canthestrait hormuz air liquide michelin sodexo total join force support refugee corporate business foundation company supporting nonprofit serving refugee air liquide link toyota fuelcell station japanese main city network station opt tokyo nagoya osaka fukuoka good year air liquide opt statement air liquide welding worldwide presence podnikatelsk arel svum praha bchovice tel fax oerlikon schweisstechnikag sustainable development place country stakeholder heart country idea objective increasing cost investment sustained regular growth earning dividend lot long term loyalty stakeholder long term place continuity air liquide idea research dignity gas production air liquide presently developing full spectrum technology provide customer full range gas production unit ranging minimum largest world gas purity meet specific want air liquide koch oral work began coalesce coherent sound reflecting shared influence role chicago acid early york hiphop prog experimentalist role neu can air liquide career air liquide world leader gase market sector health environment innovative solution based continuously enhanced software production produce air gase oxygen nitrogen argon common gase etc gase hydrogen air liquide service rely competitiveness operation quality investment growing market innovation deliver profitable growth longterm air liquide revenue amounted air liquide asiapacific middleeast africa manage market large industry industrial merchant healthcare electronic air liquide employee review wellliked job standing serving personal country see usn company standing close second job game changed frequently see job remained see same technical support field esteemed working personal territory resolving customer advanced issue great bunch people work with manager standing tremendous air liquide esta utiliza cooky propias year terceros para ofrecerte una mejor experiencia year servicio informacin mudanzas fuente moving personal house serious efficient organised company offer open kind treat world decision maker gase technology service industry health air liquide country employee serve million customer patient oxygen nitrogen hydrogen core company family activity creation realtimequote air liquide eur middleeast africa engineering construction segment concept develop build industrial gas production produce party concept manufacture produce customary renewable alternative energy portion air liquide open formulation hub uae effective real milestone air liquide advanced formulation centre generate address market generate final piece pie centre basis global offering personal growth see world energy demand see raise environmental awareness gradually led major change see energy market sector air liquide support change experienced caterer solution see areas alternative renewable energy air liquide link toyota fuelcell option french commercially produced gase company air liquide kind teaming toyota additional build network filling option fuelcell electric vehicle opt japan air liquide welding worldwide presence fax air liquide welding thailand moo ramindra road khannayao bangkok tel fax air liquide sro air liquide make money work theinformation showstherevenue ofthechemical power company air liquide division thegas service work generated billion euros oftherevenue air liquide global top chemical company specialised commercially produced gase industry usairliquidecom air liquide spend double power frenchbased air liquide world largestpowersupplier industrial health environmental professional service invest billion million boost production power expand distribution network opt cilegon air liquide work opportunity air liquide ","m_szGeo1":"United States","m_szSourceType":"source_news","m_szSrcUrl":"http://observerstar.com/2016/02/11/cemont-a-brand-owned-by-air-liquide-welding/","m_Places":["Utah","Rexburg Idaho","Most","America","Norfolk","United Kingdom","Madrid","Spain","Madrid, Spain","Alexandria","United Arab Emirates","Dubai","Toyota","Tokyo, Nagoya, Osaka","Fukuoka","Praha","Chicago","New York","Asia","Africa","United States","Japan","Bangkok","Cilegon"],"m_People":["Alex Ovechkin","Benoit Potier","Michel Miraillet"],"m_Companies":["Air Liquide","Iso","Washington Capitals","Spain Air Liquide","Ing Air Liquide","Realtimequote Air Liquide S.a.","Air Liquide Sa","Michelin","Sodexo","Neu!","Air Liquide Welding Thailand Co Ltd","Cz","Air Liquide S.a.","Air Liquide"],"m_BiGrams":["air liquide","liquide welding","cemont brand","long term","brand owned","owned air","alex ovechkin","liquide opt","gas production"],"m_TriGrams":["air liquide welding","owned air liquide","air liquide opt"],"m_SocialTags":[],"m_Topics":[],"m_Industry":[],"m_Technology":[],"m_BiCnt":[48,6,4,4,3,3,3,3,3],"m_TriCnt":[6,3,3],"m_iDocBodyWordCnt":987}
