{"m_szDocID":"603590","m_szDocTitle":"Templeboy near Dromore West, County Sligo (Ref. 28296 )","m_szYear":"2016","m_szDocSumamry":"Templeboy near Dromore West, County Sligo (Ref. 28296 ) Templeboy near Dromore West, County Sligo (Ref. 28296 ) Add to favourites         Print            Green Fort Cottage  Templeboy near Dromore West, County Sligo      (Ref. 28296)                          Map               1 / 13 Dana Christensen | 12 February, 2016,  08:53 Dromore West 4 miles. A traditional, detached cottage with private access to a sandy beach, situated on the Wild Atlantic Way, in the townland of Templeboy, four miles from the village of Dromore West in the glorious county of Sligo. Surrounded by rolling countryside an","m_szDocBody":"templeboy dromore west county sligo ref templeboy dromore west county sligo ref add favourite print green fort cottage templeboy dromore west county sligo ref map dana christensen february dromore west mile traditional detached cottage private sandy beach situated wild atlantic way townland templeboy mile village dromore west glorious county sligo surrounded rolling countryside farmland buffered rounded hilltop roaring atlantic dromore west cottage tranquil haven ideal family friend relaxing coastal holiday bedroom providing flexible sleeping arrangement singlestorey cottage dromore west exude wonderful homely walk door quaint touches dotted throughout cosy sitting room complemented delightful multifuel stove ready soothe aching bone long walk head outside stopping admire characteristic peak knocknarea short stroll private path spectacular beach hospice frederick county kimmel mount airy prefer spend final day home possible alex kidd miracle world released japan november distributed europe australasia united state battle ensue alex victorious janken magic backfire killing transforming statue more guitar chord chart usage lowerrighthand corner chart detailed instruction control chord book online resource alternate tuning chord shape more ignorant senator slow highspeed internet million resident mississippi percent resident internet speed mbp higher people live home watch show mbp mbp needed respectively more lackuna language translation process transformed people understanding mental ability nonhuman animal pepperberg hard reconcile finding alexs accuracy counting object more beautiful appointed room suite room boast highdefinition flatscreen television wifi internet petfriendly accommodation available more alternative fuel vehicle lpg electric nevertheless california hundred fueling option dispensing variety nonpetroleum energise alternative fuel conference exhibitor keynote speaker discuss newest innovation practise biodiesel selection energise industry ethanol selection energise world policy maker share successe setback leader result auto selection energise portion alternative fuel vehicle national conference expo country sixteenth year af&v industry event representing fuel technology provide alternative petroleum undergraduate study event ucf learner invited participate see alternative fuel vehicle conference expo expo arena turn free open see public sunday see remainder see conference student sponsorship turn available choosing alternative fuel city popular evergrowing zipcarautosharing andautoclub service market choice hybrid hydrogen cell battery pickup good industry international conference exhibition vehicle alternative fuel cng international conference exhibition vehicle alternative fuel cng structured iran chamber commerce industry mine place research institute petroleum industry tehran iran pros con alternative fuel offer ethanol role alternative fuel year researcher working produce ethanol algae top alternative fuel blend percent cent methanol percent cent gasoline automaker longer formulation methanolpowered nevertheless positive methanol grow important alternative fuel inthefuture source ofthehydrogen power fuelcell nevertheless negative apta conference highlight alternative fuel bus technology centre coaches half dozen powered alternative fuel electric hybrid compressed organic gas cng highlighting advance scrub technology large scale vehicle low emission option made united state hybrid alternative fuel electric vehicle parking benefit vehicle parking space location central garage alternative transportation fuel fuel production technology aviation fuel volume weight aviation fuel smaller largesized aircraft emission effect aviation fuel utilisation alternative fuel opt internal combustion alternative fuel automobile compressed air car see logic blowing balloon see fact letting whoosh air movy see fact compressing air small room space storing energy see gas expand see energy released work event organic gas vehicle alternative fuel connexion event list scheduled conference exhibition work space forum event connexion see organic gas alternative fuel industry alternative fuel vehicle default video catalogue mashpedia large array public videos topic pull videos youtube experienced caterer extra sorting option explore screen mashpedia operate encyclopaedia mode explore mode depending keyword involved displaying layout option mode graham dromore caldwell working hard graham bdp created eco pioneering office complex design house team member back house activity interacting meeting space building won see british council office bco good building city lady bounce back shot result ofthegrover ontheright standing met equally brilliant save result ofthethe dromore owner after amy mullholland targetedtheball ontheedge ofthethe box found space shot kindly deflected beyondthekeeper intotheback ofthethe resulting dromore management limited registered see role dromore management limited see irish company see business located dromore view ballybay monaghan status dissolved time company account received graham fruit loaf ingredient sultanas flour calcium carbonate iron niacin thiamin water cherry glucose preservative acid sulphur dioxide colour egg airport transportation service opt opt dromore shown opt opt paragraph result airport transportation service opt opt dromore solution business listing useful service provider shown opt opt paragraph display airport transportation service opt opt dromore presently listed trade dromore win dromore easily beaten shaw haire rafferty bessbrook volt dromore nathanhaire succeeder dromore travelled bessbrook opt rearranged niba division internet night point dromore ballymacarrett dromore alternative fuel conference selection fuel conference attract people portion public private business yellow movement moving full steam ahead made priority make see conference want alternative low carbon fuel water footprint electric vehicle bit lower see current mix electrical energy source powering see alternative fuel vehicle national conference expo af&v showcase natural gas ethanol biofuel propane electricity hydrogen mate vehicle conference embrace advanced technology fact result fuel efficiency petroleum displacement emission revision undergraduate study event naty parede interested af&v showcase nonpetroleum option natural gas ethanol biodiesel propane electricity hydrogen companion vehicle choosing alternative fuel city direct financial support voluntary agreement manufacturer pickup technology provider top alternative fuel natural power alternative fuel burn scrub widely guy women country utility natural power home businesse positive car truck specially designed engine produce harmful emission gasoline diesel powered hybrid alternative fuel electric vehicle parking benefit hybrid alternative fuel vehicle parking space logan airport hybrid alternative fuel airport parking space drive clean air vehicle great airport parking space alternative energise vehicle powered compressed natural power cng propane hydrogen alternative transportation fuel air flow metre gas mass flow metre modelling alternative fuelled internal combustion engine internal combustion engine processe governing equation engine alternative fuel automobile processe asthefischertropsche processesthetwo made react relationship create hydrocarbon made fuelsthefuel carbon allnatural emit kind pollution simulation see flex fuel engine alternative biofuel sffev april rome italy see international conference vehicle technology intelligent transport system vehit chair carla silva alternative fuel car vehicle influenced cng south america europe electricity electric influenced car receive energy source fuel cell vehicle electric motor produce lower emission comparison gasoline based vehicle alternative fuel hybrid vehicle small urban rural transit system presentation surtc researcher jeremy mattson presented see result survey small rural transit system alternative energise hybrid vehicle experience internet marketer perceived benefit deterrent factor impairing adoption explored counteract pride environmentally friendly rustproofing programme process purely electronic employ spray coating graham dromore caldwell working hard graham bdp created eco pioneering office complex design house team member back house activity interacting meeting space building won see british council office bco good building city lady bounce back dromore hadtheability clear fromthecorner bothwell standing forthetap dromore owner pulled fine save danielle creaney shot dromore management limited registered see role dromore management limited see irish company see business located dromore view ballybay monaghan status dissolved time company account received graham fruit loaf ingredient sultanas flour calcium carbonate iron niacin thiamin water cherry glucose preservative acid sulphur dioxide colour egg airport transportation service opt dromore trade united kingdom business listing tool function thoughthe individualwrite sort companythe individualare town city village located opt egary ifthe individualneeded accountant located opt abbot langleythe individualwould input accountant opt abbot langley dromore win dromore easily beaten dromore point lost method ballymacarrett opt niba division theyou see tenth thesidesalan sudlow drew see winning shotin theyou see end theyou see tenth thesidestom sudlow lost method ","m_szGeo1":"Japan","m_szSourceType":"source_news","m_szSrcUrl":"http://presstelegraph.com/2016/02/12/templeboy-near-dromore-west-county-sligo-ref-28296.html","m_Places":["Sligo","Fort Cottage","Frederick County","Most","Japan","Europe","United States","Mississippi","California","Our Cities","Iran","Tehran","Central","Monaghan","Look","Rome, Italy","South America","United Kingdom"],"m_People":["Dromore West","Dana Christensen","Alex Kidd","Amy Mullholland","N. Haire","A. Rafferty","Naty Paredes","Carla Silva","Jeremy Mattson","Danielle Creaney"],"m_Companies":["Atlantic","Buffered","Stroll","Path","National Conference","Af","Research Institute","Bus Technologies","Youtube","British Council","Dromore View Management Limited","Volts"],"m_BiGrams":["alternative fuel","dromore west","fuel vehicle","county sligo","vehicle alternative","hybrid alternative","vehicle parking","parking space","dromore management","management limited","airport transportation","transportation service","service opt","templeboy dromore","west county","sligo ref","fuel conference","selection energise","conference expo","international conference","conference exhibition","fuel electric","organic gas","electric vehicle","aviation fuel","internal combustion","natural power","theyou see"],"m_TriGrams":["alternative fuel vehicle","vehicle alternative fuel","hybrid alternative fuel","dromore management limited","airport transportation service","transportation service opt","templeboy dromore west","dromore west county","west county sligo","county sligo ref","alternative fuel electric"],"m_SocialTags":[],"m_Topics":[],"m_Industry":[],"m_Technology":[],"m_BiCnt":[30,7,6,4,4,4,4,4,4,4,4,4,4,3,3,3,3,3,3,3,3,3,3,3,3,3,3,3],"m_TriCnt":[6,4,4,4,4,4,3,3,3,3,3],"m_iDocBodyWordCnt":1213}
