{"m_szDocID":"603579","m_szDocTitle":"BMW holds back as rivals steal a marque on fuel cell vehicles | Innovation | BDlive","m_szYear":"2016","m_szDocSumamry":"BMW holds back as rivals steal a marque on fuel cell vehicles South African gold miner says studies ‘have confirmed a robust investment case’ for the Papua New Guinea joint venture with Australian group Newcrest More News BMW holds back as rivals steal a marque on fuel cell vehicles by Michael Taylor,        February 09 2016, 06:33 Michael Taylor BMW holds back as rivals steal a marque on fuel cell vehicles DESPITE all its talk about hydrogen lately, senior BMW officials have now confirmed that the company won’t have a fuel cell-powered car on sale before 2023 at the earliest. That will be abo","m_szDocBody":"bmw hold back rival steal marque fuel cell vehicle south african gold miner study confirmed robust investment case papua guinea joint venture australian newcrest new bmw hold back rival steal marque fuel cell vehicle michael taylor michael taylor bmw hold back rival steal marque fuel cell vehicle talk hydrogen lately senior bmw official confirmed company wont fuel cellpowered car sale earliest year major rival mercedesbenz year audi lexus head start bavarian company bmw recently gave journalist test drive prototype version sery hydrogen fuel cell power drive secretive black beauty fuelcell sport car based production car bmw plan wait generation fuelcell development conducting research partner toyota car maker long wait there whatsoever toyota bmw partnership production year bmw vicepresident drivetrain research matthias klietz conceded recent detroit motor show bet that normal development cycle hydrogen fuelcell development mean talking supraz connexion mite premature prediction matter concern wont deliver productionready fuelcell part fully developed car showroom world our target hydrogen fuelcell component ready klietz said show then concept car prototype the hydrogen fuelcell stack sery prototype toyota mirai sery prototype produce power stack part each the black beauty stack totally storey industrialised pure research prototype part bmw long year production fuelcell car life catching partner toyota seem toyota advanced technology bmw are started develop target klietz conceded phase one main task speed development end continue level development competence toyota added phase develop level competence now target stack now share stack from mirai development now klietz said its costreduction fuelcell system stack life cell technology term performance efficiency integration system added dont expect toyota bmw fuelstack vehicle eventually drive way bmw power toyota achieving range the stack space power them klietz the industrialisation target include costdown decreasing rareearth material use clear bmw toyota ideas company fuel cell most toyota starting installing technology smallest small car bmw intend big production sery generation time model fuelcell vehicle long driving electric vehicle electric vehicle power source klietz said that categorised large vehicle work year added that publicly admitted sery fuelcell prototype deliver power sprint second top speed bar hydrogen gas tank inserted length newer system cryogenic tank hold liquid hydrogen biggest difference older tank hold hydrogen newschool cold tank internal pressure bar hold effectively double range standard one pushing that car identical electric motor driving rear wheel identical twospeed transmission adding spring stiffness cope extra weight carrying chassis suspension braking steering system carried standard sery production eventually begin wont share architecture production bmw toyotas matter having technical development partnership necessarily share complete architecture knowledge component klietz the operation necessarily share car brand kindle bmw hydrogen vehicle powered hydrogen gas bmw fuel cellpowered car sale mean mercedesbenz audi lexus head start bmw picture berry related article ","m_szGeo1":"South Africa","m_szSourceType":"source_news","m_szSrcUrl":"http://www.bdlive.co.za/business/innovation/2016/02/09/bmw-holds-back-as-rivals-steal-a-marque-on-fuel-cell-vehicles","m_Places":["Papua New Guinea","Toyota","Detroit","Toyotas"],"m_People":["Michael Taylor","Matthias Klietz"],"m_Companies":["Bmw","Mercedes-benz","Audi — Even","Target","Sprint","Bmws","Audi"],"m_BiGrams":["fuel cell","bmw hold","hold back","back rival","rival steal","steal marque","marque fuel","cell vehicle","hydrogen fuelcell","klietz said"],"m_TriGrams":["bmw hold back","hold back rival","back rival steal","rival steal marque","steal marque fuel","marque fuel cell","fuel cell vehicle"],"m_SocialTags":[],"m_Topics":[],"m_Industry":[],"m_Technology":[],"m_BiCnt":[5,3,3,3,3,3,3,3,3,3],"m_TriCnt":[3,3,3,3,3,3,3],"m_iDocBodyWordCnt":448}
