{"m_szDocID":"604082","m_szDocTitle":"Hydrogen Cars Invade Britain But Face Dearth Of Charging Stations | OilPrice.com","m_szYear":"2016","m_szDocSumamry":"Hydrogen Cars Invade Britain But Face Dearth Of Charging Stations Hydrogen Cars Invade Britain But Face Dearth Of Charging Stations By Andy Tully Posted on Thu, 05 November 2015 20:58 | 0 Britons now can buy hydrogen cars, even if they have virtually no place to recharge them. Two manufacturers, Toyota and Hyundai, have already begun marketing their fuel cell cars in the UK. Toyota plans an aero-styled sedan priced, for now at least, at a little over $100,000. Hyundai's first offering is expected to be a “crossover” model, an SUV that looks like a car, for about $81,000. Honda says it will joi","m_szDocBody":"hydrogen car invade britain face dearth charging station hydrogen car invade britain face dearth charging station andy tully posted thu briton buy hydrogen car virtually place recharge them manufacturer toyota hyundai begun marketing fuel cell car toyota plan aerostyled sedan priced least hyundais offering expected crossover model suv car honda join britain emission back car water water vapour droplet toxic nitrogen oxide particulate robin hayle manager sustainable fuel development hyundai told guardian relatedoil sand face pipeline problem advantage petrol diesel term range performance refill time advantage electric vehicle emission smooth drive instant torque hayle said key emission important feature car kingdom briton drive dieselpowered volkswagen country exceeding pollution safety limit set european union german automaker defeat device million vehicle vastly underreport emission toxic nitrogen oxide far toyota hyundai sold hydrogen car individual customer car expensive rebate vehicle cost electric car far expensive powered fossil fuel now potential customer company connexion industry involved recharging vehicle include company fleet car taxi firm local government body transport london responsible public transit united kingdom capital relateduk subsea cable tap icelandic geothermal power reason essentially problem plague electric vehicle evs california recharging station california leader united state adopting electric car evs road charging station serve regularly gasolinepowered car travel mile refuelling mile single charge gov jerry brown signed legislation include language encouraging californias leading utility compete set thousand charging station state true britain respect hydrogen charging station fact kingdom raise chickenandegg conundrum dearth charging station buy hydrogen car buy car build charging station britain faced problem serve electric vehicle solved easily accessible charging post road country cost thousand dollar each hydrogen charging station cost significantly more relatednorth dakota longer attractive driller refiner result government industry expect hydrogen charging station britain urban areas michael dolman consultancy element energy country station achieve comprehensive coverage british government stepped forward financial help example contributed million million grant company itm power build hydrogen charging station london small start steep cost hydrogen car time driving range electric car hyundais boast range mile cold comfort nearest charging station mile away andy tully oilpricecom top read oilpricecom ","m_szGeo1":"United Kingdom","m_szSourceType":"source_industry","m_szSrcUrl":"http://oilprice.com/Latest-Energy-News/World-News/Hydrogen-Cars-Invade-Britain-But-Face-Dearth-Of-Charging-Stations.html","m_Places":["Britain","Toyota","Uk","United Kingdom","California","United States","North Dakota","London"],"m_People":["Andy Tully","Robin Hayles","Michael Dolman"],"m_Companies":["Hyundai","Honda","Guardian","Diesel","Volkswagens","European Union","Eu","Transport For London","British Government"],"m_BiGrams":["charging station","hydrogen car","hydrogen charging","dearth charging","electric vehicle","electric car"],"m_TriGrams":["hydrogen charging station","dearth charging station"],"m_SocialTags":[],"m_Topics":[],"m_Industry":[],"m_Technology":[],"m_BiCnt":[11,6,4,3,3,3],"m_TriCnt":[4,3],"m_iDocBodyWordCnt":344}
