{"m_szDocID":"604513","m_szDocTitle":"Global Flow Battery Market to Reach USD 185 Million by 2020, According to Technavio - Oil & Gas 360","m_szYear":"2016","m_szDocSumamry":"Global Flow Battery Market to Reach USD 185 Million by 2020, According to Technavio  February 16, 2016 - 1:40 PM EST close yes               Global Flow Battery Market to Reach USD 185 Million by 2020, According to Technavio According to Technavio’s latest report, the        global flow battery market is likely to grow at a CAGR of        over 9% during the forecast period. Flow batteries such as zinc bromide, vanadium redox, sodium bromide, and        hydrogen bromide are primarily used as advanced energy storage systems.        These are best suited for microgrid applications. Their benefici","m_szDocBody":"global flow battery market reach usd million technavio est close global flow battery market reach usd million technavio technavios latest report global flow battery market grow cagr forecast period flow battery zinc bromide vanadium redox sodium bromide hydrogen bromide primarily advanced energy storage system suited microgrid application beneficial characteristic longer lifecycle discharge hour contribute growth market global flow battery market expected witness steady growth forecast period attributed rising flow battery application government support funding investment r&d sayani roy lead researcher technavio energy storage say abrupt rise demand energy met battery country india africa power outage expected battery low discharge rate flow battery ideal report technavio cover scenario growth prospect global flow battery market report present vendor landscape detailed analysis top vendor operating market market segmented region americas apac americas government support intensive r&d boost growth flow battery market americas exceed usd million growing cagr flow battery market americas expected witness steady growth forecast period government support intensive r&d instance department energy doe listed flow battery project globally total power project considered list included announced construction operational facility automobile manufacturer increasingly deploying flow battery electric vehicle redt developed electric vehicle refuelling system vanadium redox flow technology this technology instantly recharge battery replacing chargeless electrolyte charged electrolyte reducing time charge electric vehicle sayani request sample emea flow battery market exceed usd million flow battery market emea expected witness steady growth forecast period growing cagr europe primarily flow battery transportation segment electric vehicle instance nanoflowcell car manufacturer granted permission sell quant model concept car powered flow battery germany rest europe application flow battery growing technology ideal utility sector ups require energy burst second minute growth industrial demand region boost flow battery market apac fastestgrowing region flow battery market flow battery market apac predicted exceed usd million growing cagr market expected undergo significant growth forecast period owing fluctuation power outage largescale energy storage system growing environmental concern instance increased demand energy storage system flow battery predicted apac country china plan invest usd billion improving power grid flow battery market expected widely due effectiveness pitch control peak power support key vendor global telecom power system market purchase report price technavio subscriber subscribing technavios report download report month price one contact requirement link subscription platform technavio technavio leading global technology research advisory company company develop piece research year covering technology country technavio analyst globally specialise customised consulting business research assignment latest leading edge technology technavio analyst employ primary secondary research technique ascertain size vendor landscape range market analyst obtain information combination bottomup topdown approaches inhouse market modelling tool proprietary database corroborate data data obtained market participant stakeholder chain including vendor service provider distributor reseller enduser interested information contact media team source version businesswirecom technavio research ","m_szGeo1":"India","m_szSourceType":"source_industry","m_szSrcUrl":"http://www.oilandgas360.com/global-flow-battery-market-to-reach-usd-185-million-by-2020-according-to-technavio/","m_Places":["Est","India","Africa","Americas","Europe","Germany","China"],"m_People":["Sayani Roy"],"m_Companies":["Vendors","Us Department Of Energy","Doe","Ups"],"m_BiGrams":["flow battery","battery market","global flow","usd million","forecast period","energy storage","growth forecast","electric vehicle","storage system","market expected","expected witness","witness steady","steady growth","government support","exceed usd","growing cagr"],"m_TriGrams":["flow battery market","global flow battery","growth forecast period","energy storage system","expected witness steady","witness steady growth","steady growth forecast","exceed usd million"],"m_SocialTags":[],"m_Topics":[],"m_Industry":[],"m_Technology":[],"m_BiCnt":[22,13,5,5,5,4,4,4,3,3,3,3,3,3,3,3],"m_TriCnt":[13,5,4,3,3,3,3,3],"m_iDocBodyWordCnt":449}
