{"m_szDocID":"604753","m_szDocTitle":"Oil and What to Do About It | The Energy Collective","m_szYear":"2016","m_szDocSumamry":"0 Posted February 17, 2016 Keywords: Carbon and De-carbonization , Energy Security , Tech , Sustainability , Utilities , Efficiency , Environmental Policy , Cleantech , Oil , Environment , Finance , Renewables , Risk Management , Energy , Energy and Economy , Fuels , News , Politics & Legislation , energy tax policy , obama administration Co-Authored by Anthony Eggert Climate Works Oil Campaign Director Just last week President Obama made headlines by floating a $10 per barrel oil tax . This needs to be the opening salvo in a renewed effort to move the country beyond oil, but the effort also n","m_szDocBody":"posted keyword carbon decarbonization energy security tech sustainability utility efficiency environmental policy cleantech oil environment finance renewable risk management energy energy economy fuel new politic legislation energy tax policy obama administration coauthored anthony eggert climate work oil campaign director week president obama made headline floating barrel oil tax opening salvo renewed effort move country oil effort ambitious clock ticking degree future climate activist innovative effort drive vehicle electrification mean taking closer harnessing shared electrified autonomous vehicle reduce ghg coal first oil next year ago starry eyed unicorn chasing activist climate community dreamed that electricity projection greenpeace accurate wind solar clean technology dominating coal market generation capacity fundamentally remade power sector economic political landscape iea project clean energy constitute third capacity addition short done moving coal oil begun market growing rapidly represent vehicle sale united state political establishment slowly warming economic benefit growing political power renewable power oil dominate political landscape transportation despite half shale oil driller facing bankruptcy plunging oil price californias landmark legislation oil company dramatically outspent opponent completely eliminating goal reduce oil consumption indeed today imagine future oil coal today source iea shared autonomous electrified mobility midst turmoil revolution brewing dramatically upend oil driven confluence separate powerful trend advent sharing economy including transportation network company tnc long range affordable electric vehicle autonomous vehicle source forbe utopian future eliminate oil sharing automation turbocharger transportation electrification dramatically impact critical variable time prevailing wisdom car sale inflexion point herald arrival technology problem average fleet turnover year convince evs future ditch clunker time optimistic put mainstream deployment time frame beyond shared autonomous vehicle shortcircuit glacial speed fleet turnover greatly increasing utilisation current vehicle sit parked time expensive inefficient capital asset people own put work shared fleet take year drop year increased utilisation reduce cost example morgan stanley estimate autonomous vehicle generate saving trillion year productivity gain avoided accident fuel saving indirect impact time from example reduced vehicle parking insurance police shared driverless car allocated smart technology reduce mile cost low due greater efficiency reduced fuel cost increased capacity utilisation rate mean shared avs drive electrification current effort left competing margin incredibly important today growing interest struggle dealer stock sell car shared autonomous future vehicle lower operating maintenance cost inherent advantage sweet spot evs sweeter battery price fall ironically contribute equitable future shared electrified avs integrate existing effort provide transit biking walking expand consumer choice affordable mobility city improve business model efficiency transit offering lowercost solution lowcapacity route schedule imagine subsidised free voucher shared autonomous lyft uber ride low income community turn prevailing wisdom tech giant head finally evs effort clean power sector providing flexible load utility manage smart charging make greater fixed utility asset enable renewable integration lowering cost clean energy ratepayer revenue electricity sale fund grid upgrade future renewable traditionally conservative edison electric institute note electrification transportation sector potential quadruple win electric utility society enable company support environmental goal build customer satisfaction reduce operating cost assure future existing asset bring important consideration impact politic climate shared electrified autonomous world fundamentally redraw battle line shakeup political alliance beginning age oil century cash rich tech company utility suddenly line side climate policy debate putting oil industry heel shared autonomous vehicle silicon valley unicorn chance silicon valley bubble perspective remember year ago tnc uber lyft exist now operate hundred city host million ride daily valued billion life vehicle fleet cost driver expensive piece more autonomous driving system expected cost fraction make figuring autonomy job number continue grow time avs pursued host powerful company cash reserve greater dozen country include like apple google tesla uber other instance testing fully autonomous selfdriving car road year million mile accumulated teslas chief executive predict selfdriving vehicle buy year federal government game president obama proposed billion year fund pilot project accelerate development adoption safe vehicle automation connected electric autonomous vehicle key part department transportation smart city challenge partnership vulcan assured technology barrier shared autonomous electrified future lack good policy worse wellmeaning perverse policy stall revolution prime recent proposal california dmv force car utilising autonomous technology include driver time eliminate ability easily share vehicle barrier adoption shared electric autonomous vehicle affect variable matter time deploying regulation inhibit slow adoption technology extending age oil dramatic level carbon emission associated policy important smooth mobility ensure benefit widely shared future transition horseless carriage driverless car profound impact sector economy policy required transition maximise benefit ensure socioeconomic disparity exist current transportation system exacerbated similarly trend reinforce advance together indeed affordable longrange electric vehicle reduction oil consumption existing gas engine facto standard future autonomous uber ride stand crossroad marginal growth dystopian future fleet gas propelled autonomous car shared autonomous electrified future compatible safe climate seize post comment ","m_szGeo1":"United States","m_szSourceType":"source_industry","m_szSrcUrl":"http://theenergycollective.com/guayjguay/2322495/what-are-we-going-do-about-oil?utm_source=feedburner&utm_medium=feed&utm_campaign=The+Energy+Collective+%28all+posts%29","m_Places":["United States","California","Silicon Valley","Tesla","Smart Cities"],"m_People":["Anthony Eggert","Barack Obama"],"m_Companies":["Cleantech","Obama Administration","Greenpeace","Iea","Indeed","Revolution","Network Companies","Tncs","Forbes","Morgan Stanley","Lyft","Uber","Edison Electric Institute","Alliances","Silicon Valley Unicorn","Eu","Apple","Google","California Dmv"],"m_BiGrams":["autonomous vehicle","shared autonomous","shared electrified","autonomous electrified"],"m_TriGrams":["shared autonomous electrified"],"m_SocialTags":[],"m_Topics":[],"m_Industry":[],"m_Technology":[],"m_BiCnt":[7,7,3,3],"m_TriCnt":[3],"m_iDocBodyWordCnt":772}
