{"m_szDocID":"605350","m_szDocTitle":"Aston Martin Electric, Fuel-Cell Lightweight, Tesla Restricts Summon: The Week In Reverse","m_szYear":"2016","m_szDocSumamry":"The Week In Reverse Aston Martin Electric, Fuel-Cell Lightweight, Tesla Restricts Summon: The Week In Reverse Email This Page To (separate emails with commas) Message (optional) Your email was sent successfully. Close 3,972 views Feb 20, 2016 Follow Bengt Enlarge Photo Late this week, we brought you some new technical details for the ultra-lightweight Riversimple Rasa , a carbon-fiber two-seater with a hydrogen fuel-cell powertrain. Although its underpinnings remind us a bit of the ultra-exotic Volkswagen XL1 hypercar, Riversimple plans not to sell this car but to offer it by subscription, for","m_szDocBody":"week reverse aston martin electric fuelcell lightweight tesla restrict summon week reverse separate email commas message optional successfully close view follow bengt enlarge photo late week brought technical detail ultralightweight riversimple rasa carbonfiber twoseater hydrogen fuelcell powertrain underpinning remind bit ultraexotic volkswagen hypercar riversimple plan sell car offer subscription price similar ownership cost new familysized hatchback aston martin rapide concept enlarge photo reported aston martin luxury touring sportscar maker plan partner leeco chinese company the netflix china develop production version rapide conceptan anticipated rival tesla model porsche mission concept midweek gave update tally public health damage due volkswagen emission defeat device diesel vehicle also feeling lot geeking glimpse vehicle service screen right tesla model enlarge photo teslas summon function autopilot feature highway driving betatesting stage recently agreed place limitation function brought detail earlier week case son daughter tesla bug electric car enthusiasm yet cheque radio flyer model early ","m_szGeo1":"China","m_szSourceType":"source_news","m_szSrcUrl":"http://www.greencarreports.com/news/1102462_aston-martin-electric-fuel-cell-lightweight-tesla-restricts-summon-the-week-in-reverse","m_Places":["Tesla","Leeco","China"],"m_People":["Riversimple Rasa"],"m_Companies":["Aston Martin","Remind","Volkswagen","Netflix","Diesel"],"m_BiGrams":["aston martin","enlarge photo"],"m_TriGrams":[],"m_SocialTags":[],"m_Topics":[],"m_Industry":[],"m_Technology":[],"m_BiCnt":[3,3],"m_TriCnt":[],"m_iDocBodyWordCnt":148}
