{"m_szDocID":"605331","m_szDocTitle":"Rep. Paul Tonko And Rep. Chris Gibson Visit Plug Power  | WAMC","m_szYear":"2016","m_szDocSumamry":"Rep. Paul Tonko And Rep. Chris Gibson Visit Plug Power Congressman Paul Tonko, Plug Power CEO Andy Marsh, Congressman Chris Gibson WAMC photo by Dave Lucas Plug Power products ready to be shipped around the world. WAMC Photo by Dave Lucas Reps. Gibson and Tonko chat with a Plug Power employee. WAMC photo by Dave Lucas Reps. Gibson and Tonko at Plug Power , Latham NY (February 2016) WAMC photo by Dave Lucas Listen / 2:07 Two powerful Capital Region congressmen on the opposite sides of the aisle met in Latham Tuesday afternoon to tour the Plug Power facility. Congressmen Paul Tonko and Chris Gib","m_szDocBody":"rep paul tonko rep chris gibson visit plug power congressman paul tonko plug power ceo andy marsh congressman chris gibson wamc photo dave lucas plug power product ready shipped world wamc photo dave lucas rep gibson tonko chat plug power employee wamc photo dave lucas rep gibson tonko plug power latham february wamc photo dave lucas listen powerful capital region congressmen opposite side aisle met latham afternoon tour plug power facility congressmen paul tonko chris gibson full tour company manufacturing operation plug power ceo andy marsh firm lead york state nation hydrogen fuel cell system development manufacturing last year increased revenue hundred million dollar revenue million dollar booking hundred fifty million dollar revenue year growing cent building hydrogen fueling station delivering hydrogen electric vehicle world company grown employee year time speaking employee tonko vowed work federal investment tax credit fuel cell purchase set expire end year extended were today share partner you hear storey witness pride commitment strong company strong argument advance investment tax credit policy tonko gibson appeared plug power year ago pleased progress company made gibson dont granted grateful hard work positive contribution make economy important economy argue important foreign policy too tour middle east business energy independence man congressional tour week plant rolled red carpet senator chuck schumer vowed rally senate support investment tax credit proclaimed critical stimulus company success related programme ","m_szGeo1":"United States","m_szSourceType":"source_news","m_szSrcUrl":"http://wamc.org/post/rep-paul-tonko-and-rep-chris-gibson-visit-plug-power","m_Places":["Latham Ny","Latham","New York State","Middle East"],"m_People":["Paul Tonko","Chris Gibson","Andy Marsh","Dave Lucas","Chuck Schumer"],"m_Companies":["Senate"],"m_BiGrams":["plug power","wamc photo","photo dave","dave lucas","paul tonko","chris gibson","million dollar","investment tax","tax credit"],"m_TriGrams":["wamc photo dave","photo dave lucas","investment tax credit"],"m_SocialTags":[],"m_Topics":[],"m_Industry":[],"m_Technology":[],"m_BiCnt":[8,4,4,4,3,3,3,3,3],"m_TriCnt":[4,4,3],"m_iDocBodyWordCnt":225}
