{"m_szDocID":"605429","m_szDocTitle":"Hydrogen cars have a 'chicken or egg' problem in New England - News and reviews - Boston.com","m_szYear":"2016","m_szDocSumamry":"Previous -- of -- Next BMW i8. With swan-wing doors and a shark-nose grille, the i8 plug-in hybrid is a truly eye-catching vehicle. Its fuel economy is just under 30 combined mpg -- not bad for a supercar, and its speed tops out at 155 mph. It starts at $141,695. Ryan Breslin/Boston.com Previous -- of -- Next Subaru XV Crosstrek Hybrid. With high fuel efficiency and low emissions, the Crosstrek Hybrid delivers sleek styling and road-gripping symmetrical all-wheel drive. It has a 31 combined mpg. Youâ€™ll feel even better knowing it was built in a zero-landfill plant, where 100 percent of waste i","m_szDocBody":"previous bmw swanwing door sharknose grille plugin hybrid eyecatching vehicle fuel economy combined mpg bad supercar speed top mph start ryan previous subaru crosstrek hybrid fuel efficiency low emission crosstrek hybrid deliver sleek styling roadgripping symmetrical allwheel drive combined mpg youll knowing built zerolandfill plant percent waste recycled turned electricity start olivia spinale bostoncom previous volkswagen golf egolf mile charge fuel economy city highway combined mpge forwardcollision warning automated emergency braking park assist feature start olivia spinale bostoncom previous toyota rav hybrid toyotas firstever rav hybrid joining hybrid vehicle toyotas green family offer driving mode sport eco electriconly electriconly travel mile low speed battery charged fuel economy estimated combined mpg start olivia spinale bostoncom previous toyota mirai mirai run solely hydrogen emission water include safety feature lane departure alert blindspot monitor front rear parking assist sonar fuel economy combined mpg range mile take minute recharge start olivia spinale bostoncom previous nissan leaf leaf percent electric car predecessor option larger battery give driver percent increase range total mile starting price base model include fancy battery olivia spinale bostoncom previous mercedesbenz eclass diesel midsize luxury car superb ride wide variety body style option smooth powerful diesel engine standard led lowbeam headlamp enhance driver nighttime vision heated ventilated seat available fuel economy mpg city mpg highway start olivia spinale bostoncom previous chevrolet colorado diesel colorado diesel smaller pickup truck size lack mass make refinement sleek truck combined mpg offer safety feature forward collision alert lane departure warning plus tow pound pound gasoline start olivia spinale bostoncom hyundai sonata plugin sonata plugin hybrid boast fuel economy combined mpg noticeably quieter predecessor start olivia spinale bostoncom previous chevrolet volt sleek volt offer pure electric mile single charge total range mile full charge full tank gas take hour chargeup fully safety feature lane assist forward collision alert regular gas combined mpg start olivia spinale bostoncom ","m_szGeo1":"United States","m_szSourceType":"source_news","m_szSrcUrl":"http://www.boston.com/cars/news-and-reviews/2016/02/17/the-chicken-egg-problem-hydrogen-fueled-cars-new-england/KyFTbVaZZzeZSO3mektS6N/story.html","m_Places":["Toyota"],"m_People":["Ryan Breslin","Olivia Spinale"],"m_Companies":["Bmw","Boston.com","Subaru Xv Crosstrek","Diesel","Volt"],"m_BiGrams":["olivia spinale","spinale bostoncom","start olivia","combined mpg","bostoncom previous","fuel economy","economy combined","safety feature"],"m_TriGrams":["olivia spinale bostoncom","start olivia spinale","spinale bostoncom previous","fuel economy combined","economy combined mpg"],"m_SocialTags":[],"m_Topics":[],"m_Industry":[],"m_Technology":[],"m_BiCnt":[9,9,8,7,7,6,3,3],"m_TriCnt":[9,8,7,3,3],"m_iDocBodyWordCnt":309}
