{"m_szDocID":"605522","m_szDocTitle":"17 governors make bipartisan pledge toward clean energy - CSMonitor.com","m_szYear":"2016","m_szDocSumamry":"17 governors make bipartisan pledge toward clean energy Latest News A general view shows solar panels used to produce renewable energy at the photovoltaic park in Les Mees, in the department of Alpes-de-Haute-Provence, southern France March 31, 2015. Jean-Paul Pelissier/Reuters View Caption of Citing the economic benefits of clean energy, 17 governors  – including four Republicans – have agreed to expand clean energy programs involving solar, wind, hydroelectric, and geothermal power technologies. Titled the “Governors’ Accord for a New Energy Future,” the signed document pledged the collabora","m_szDocBody":"governor make bipartisan pledge clean energy latest new general show solar panel produce renewable energy photovoltaic park les mee department alpesdehauteprovence southern france jeanpaul caption citing economic benefit clean energy governor including republican agreed expand clean energy programme involving solar wind hydroelectric geothermal power technology titled governor accord energy future signed document pledged collaboration state make policy build renewable power infrastructure mentioning term climate change media conference call tuesday democratic gov jerry brown california deliberately avoided climate change due divisive nature focusing economic incentive protecting resource posterity recommended hopeful sign global energy cleaner sharp cleavage united state climate change lot partisan coloration reporter move forward important stuff bogged larger controversy photos day photos day content pact deal specific consequence climate change air pollution extreme weather extreme weather event flood drought wildfire sealevel rise negatively impact electric reliability economy document read embracing energy solution provide durable resilient infrastructure enable economic growth protecting health community natural resource goal listed pact include integrating alternative power source regional electrical grid investing clean transportation option biofuel hydrogen cooperating federal agency promoting national shift clean energy powerful message theyre sending country todd foley chief strategy officer american council renewable energy tell christian science monitor number state led chief executive coming bipartisan basis virtually part country talking important renewable energy economic development behalf renewable energy industry pleased added temporary halting president barack obamas clean power plan supreme court expert governor accord auspicious step curbing effect climate change court temporarily blocked clean power plan block progress wind solar energy affordable electric vehicle modern efficient electric grid rob sargent senior director environment americas clean energy programme told scientific american kudos governor pledging forge path forward climate progress clean air governor however energy policy past debra kahn scientific american point out michigan gov rick snyder plaintiff lawsuit clean power plan foley governor cultivated substantial clean energy policy separately respective state sending message rest country what important leadership governor demonstrating explain state championed renewable energy policy what interesting theyre coming talk role renewable forward related storey monitor storey care delivered inbox daily ","m_szGeo1":"United States","m_szSourceType":"source_news","m_szSrcUrl":"http://www.csmonitor.com/Environment/2016/0217/17-governors-make-bipartisan-pledge-toward-clean-energy","m_Places":["France","California","United States","America","Michigan"],"m_People":["Jean-paul Pelissier","Todd Foley","Barack Obama","Rob Sargent","Debra Kahn","Rick Snyder"],"m_Companies":["Department Of Alpes","Reuters","Energy Future","American Council","Christian Science Monitor","Supreme Court","Scientific American","Path"],"m_BiGrams":["clean energy","renewable energy","climate change","clean power","power plan","energy policy"],"m_TriGrams":["clean power plan"],"m_SocialTags":[],"m_Topics":[],"m_Industry":[],"m_Technology":[],"m_BiCnt":[6,5,5,3,3,3],"m_TriCnt":[3],"m_iDocBodyWordCnt":341}
