{"m_szDocID":"607383","m_szDocTitle":"Renewable energy: The world needs a big change","m_szYear":"2016","m_szDocSumamry":"Renewable energy: The world needs a big change 23 Feb 2016 Barny Evans We need to prepare clients for the challenges ahead, writes Barny Evans Our energy systems are in the foothills of a revolution that will change the way we do business and the way we live, even those of us not working in the energy sector. WSP | Parsons Brinckerhoff renewable expert Barny Evans says the Middle East is likely to experience this more than most. We are moving to a future where the majority of our power comes from renewable sources and our transport and buildings become fully electrified; but we are also moving","m_szDocBody":"renewable energy world big change barny evan prepare client challenge ahead write barny evan energy system foothill revolution change business live working energy sector wsp parson brinckerhoff renewable expert barny evan middle east experience most moving future majority power renewable source transport building fully electrified moving future supply demand blurred selfgeneration growing region benefit import oil gas air quality lower emission reduced energy bill creation intelligent network efficient middle east level solar power available benefit greater challenge fact demand oil gas fall greatly solar power position costeffective deploy unit power produced fossil fuel option solar intermittent renewable long acted irresponsible teenager taking credit producing power taking responsibility fact power network bank account pay power year seesaw balance supply demand minute minute power supply problem demand country level deployment date mean largely ignoring problem untenable germany dealing problem this jurisdiction suggesting intermittent renewable pay additional cost maintaining standby generation balancing cost backdrop power storage white knight shining steed galloping rescue power storage mean renewable power produced dont held essentially system bank account seesaw balancing demand supply important britain country similar latitude solar power power storage provide power foreseeable future approach equator day season uniform solar power linked storage demand management provide country power undertaken analysis development tropical africa solar power storage considered option standard diesel generator lifetime cost similar opportunity middle east ly fact power demand broadly proportional solar power generation reduce storage parallel power storage solar power obvious battery flywheel compressed air hydrogen whatever today power storage expensive deployable grid scale solar power year ago solar level human financial capital invested power storage enormous potential economy scale narrowing focus winning technology standardisation government putting place incentive structure big future require enormous level investment engineering happen denial example recent opec report future oil suggest electric vehicle represent global fleet unlikely iea projecting oil consumption vehicle start decline rapidly that time resulting rise electrical consumption uae gulf country plan this affected declining oil demand increased electrical demand summary future incredibly exciting company wsp parson brinckerhoff ensure preparing client government company challenge ahead ensure fully grasp benefit barny evan renewable energy sustainable development expert wsp parson brinckerhoff expert ","m_szGeo1":"Germany","m_szSourceType":"source_news","m_szSrcUrl":"http://meconstructionnews.com/story/5538/renewable-energy-the-world-needs-a-big-change","m_Places":["Middle East","Germany","Britain","Africa","The Uae","Uk"],"m_People":["Barny Evans"],"m_Companies":["Revolution","Parsons Brinckerhoff","Equator","Diesel","Opec","Iea"],"m_BiGrams":["solar power","power storage","barny evan","wsp parson","parson brinckerhoff","middle east"],"m_TriGrams":["wsp parson brinckerhoff"],"m_SocialTags":[],"m_Topics":[],"m_Industry":[],"m_Technology":[],"m_BiCnt":[8,6,4,3,3,3],"m_TriCnt":[3],"m_iDocBodyWordCnt":355}
