{"m_szDocID":"608965","m_szDocTitle":"Infrastructure cess fumes automakers, car prices to go up over Rs 1 lakh | union-budget$budget-and-industry | Hindustan Times","m_szYear":"2016","m_szDocSumamry":"Infrastructure cess fumes automakers, car prices to go up over Rs 1 lakh PTI, New Delhi |  Updated: Feb 29, 2016 22:20 IST Prices of mass market vehicles may go up by up to Rs 2,000 more, while big diesel SUVs and sedans may get costlier by over Rs 1 lakh due to the infrastructure cess of up to 4%.      (HT File Photo) Share Finance minister Arun Jaitley’s call to levy an ‘infrastructure cess’ of up to 4% is set to cause a hike prices of mass market vehicles by up to Rs 2,000 more, while big diesel SUVs and sedans may get costlier by over Rs 1 lakh. In the aftermath of pollution problems in th","m_szDocBody":"infrastructure cess fume automaker car price lakh pti delhi updated ist price mass market vehicle more big diesel suvs sedan costlier lakh due infrastructure cess file photo share finance minister arun jaitley call levy infrastructure cess set hike price mass market vehicle more big diesel suvs sedan costlier lakh aftermath pollution problem capital jaitley singled diesel vehicle decided impose cess subfourmetre diesel vehicle engine capacity exceeding higher engine capacity suvs bigger sedan slapped cess car cess driven vehicle length exceeding metre engine capacity exceeding reacting proposal maruti suzuki chairperson bhargava told pti lead rise car price surprise expecting kind cess lamenting jaitley announcement bhargava said pollution asked euro emission norm involve substantial amount investment add cost vehicle addition additional cess car contribute air pollution surprise however declined comment quantum price hike industry estimate result cess increase price range entry level small car maruti alto tata nano lakh rupee highend vehicle priced lakh budget speech finance minister said pollution traffic situation indian city matter concern propose levy infrastructure cess small petrol lpg cng car diesel car capacity cent engine capacity vehicle suvs proposed collect tax source rate purchase luxury car exceeding lakh hyundai motor india hmil senior vicepresident marketing sale rakesh srivastava infrastructure cess dampener auto industry auto industry experiencing growth challenge expectation scrappage scheme remove emission low mileage vehicle taxation infra cess dampener effect demand creating challenge sustainable growth said asked company vehicle price range entry level small car aeon suv santafe priced ranging lakh lakh exshowroom delhi expressing disappointment mahindra chairman anand mahindra tweeted summary disappointment tax car reason mayhem market mahindra mahindra executive director pawan goenka imposing cess passenger vehicle concern auto industry however stride priority economy industry manage good additional revenue cess phase older vehicle added hitting budget proposal audi india head joe king said government announced positive initiative industry contribute heavily manufacturing sector economy stating negatively impact automobile industry said disappointed industry demand reducing excise duty addressed contrary infra cess added affect price demand also said industry evaluate impact extra tax levy purchase car lakh expressing displeasure toyota kirloskar motor vicechairman wholetime director shekar viswanathan said encourage government based size vehicle relation technology taking older vehicle road priority government tata motor spokesperson said passenger vehicle industry facing challenge year barely begun show sign recovery additional cesse disincentivise passenger vehicle customer impacting industry nissan india operation president guillaume sicard cess impact price foresee major burden small car buyer luxury car suvs feel heat added presentation roadmap gst implementation additional incentive electric vehicle hybrid fame scheme plan vehicle scrappage scheme damper sicard said renault india operation country ceo managing director sumit sawhney said budget didnt automobile sector hopeful probusiness policy continual basis benefit industry hinduja company india chairman ashok hinduja auto sector stand benefit proposed amendment motor vehicle act private sector participation passenger vehicle segment price waterhouse partner abdul majeed said increase tax luxury vehicle infrastructure cess withholding taxe bigger vehicle negative impact bigger passenger vehicle kpmg india head automotive sector rajeev singh passenger vehicle significant negative impact due infrastructure cess announcement deduct tds luxury vehicle lakh dampen demand short term added measure negatively impact automotive company include benefit deduction research limited added kind model including threewheeled vehicle electrically operated vehicle hybrid vehicle hydrogen vehicle based fuel cell technology taxis car physically handicapped person vehicle cleared ambulance registered solely ambulance exempt infrastructure cess credit cess allowed credit duty allowed pay cess jaitley said jaitley however gave relief environment friendly vehicle exemption rate duty existed part environment friendly vehicle expiry year planning continue that jaitley said excise duty concerned currently small car metre length attract excise duty car metre length engine capacity attract duty further vehicle engine capacity charged excise duty ground clearance attract excise duty tag ","m_szGeo1":"India","m_szSourceType":"source_news","m_szSrcUrl":"http://www.hindustantimes.com/union-budget/infrastructure-cess-fumes-automakers-car-prices-to-go-up-over-rs-1-lakh/story-E0uz0L6WDGhuPsDNOtgbjO.html","m_Places":["New Delhi","Delhi","Anand","India","Toyota"],"m_People":["Arun Jaitley","Maruti Suzuki","Rc Bhargava","Maruti Alto","Rakesh Srivastava","Pawan Goenka","Joe King","Shekar","Guillaume Sicard","Ashok P Hinduja","Rajeev Singh"],"m_Companies":["Diesel","Hyundai Motor India Ltd","Hmil","Eon","Audi","Renault","Hinduja Group","Price Waterhouse","Kpmg"],"m_BiGrams":["infrastructure cess","engine capacity","passenger vehicle","excise duty","small car","auto industry"],"m_TriGrams":[],"m_SocialTags":[],"m_Topics":[],"m_Industry":[],"m_Technology":[],"m_BiCnt":[8,6,6,5,4,3],"m_TriCnt":[],"m_iDocBodyWordCnt":618}
