{"m_szDocID":"609061","m_szDocTitle":"Pininfarina converts hydrogen into speed - Roadshow","m_szYear":"2016","m_szDocSumamry":"Pininfarina converts hydrogen into speed Here's everything we loved from Day 2 of the 2016 Geneva Motor Show Pininfarina converts hydrogen into speed With its H2 Speed car, shown off here at the Geneva Motor Show, the Italian automotive designer debuts an environmentally friendly race car that uses hydrogen to generate electricity. Wayne Cunningham Wayne Cunningham reviews cars and writes about automotive technology for CNET's Roadshow. Prior to the automotive beat, he covered spyware, Web building technologies, and computer hardware. He began covering technology and the Web in 1994 as an edit","m_szDocBody":"pininfarina convert hydrogen speed loved day geneva motor show pininfarina convert hydrogen speed speed car shown geneva motor show italian automotive designer debut environmentally friendly race car hydrogen generate electricity wayne cunningham wayne cunningham review car write automotive technology cnet roadshow prior automotive beat covered spyware web building technology computer hardware began covering technology web editor net magazine full bio pininfarina convert hydrogen speed share concept car pininfarina convert hydrogen speed idea hydrogen fuel cell part car drivetrain risen fallen time year rise again toyota honda launched fuel cell passenger car italian automotive designer pininfarina jumped bandwagon showing fuel cell race car geneva motor show car display speed built carbon fibre exhibiting line man lmp race car fuel cell stack power electric drive motor hydrogen fuel cell stack compressed hydrogen tank oxygen air combining element reaction produce electricity water electric car fuel cell stack place supplement battery powering car electric drive motor automaker interested technology produce harmful emission hydrogen tank filled faster battery charged pininfarinas eco race car run hydrogen full gallery prev speed pininfarina partnered swiss company called greengt produce performance fuel cell drive system tested prototype race car system speed electric drive motor making horsepower kilowatt fuel cell stack system pound car mph second top speed mph speed made carbon fibre weight heavier typical man car pound speed store pound compressed hydrogen tank range figure posted europe developing rule restrict emission speed represent future professional racing make fuel cell technology attractive car toyotas mirai tag ","m_szGeo1":"United States","m_szSourceType":"source_news","m_szSrcUrl":"http://www.cnet.com/roadshow/news/pininfarina-converts-hydrogen-into-speed/","m_Places":["Geneva","Toyota","Le Mans","Europe"],"m_People":["Wayne Cunningham"],"m_Companies":["Pininfarina","Cnet","Honda"],"m_BiGrams":["fuel cell","race car","pininfarina convert","convert hydrogen","hydrogen speed","cell stack","geneva motor","motor show","electric drive","drive motor","hydrogen tank"],"m_TriGrams":["pininfarina convert hydrogen","convert hydrogen speed","fuel cell stack","geneva motor show","electric drive motor"],"m_SocialTags":[],"m_Topics":[],"m_Industry":[],"m_Technology":[],"m_BiCnt":[9,5,4,4,4,4,3,3,3,3,3],"m_TriCnt":[4,4,4,3,3],"m_iDocBodyWordCnt":247}
