{"m_szDocID":"609035","m_szDocTitle":"NEL ASA: NEL enters into final agreement with Uno-X for hydrogen station network | Business Wire","m_szYear":"2016","m_szDocSumamry":"OSLO, Norway--( BUSINESS WIRE )--Regulatory News: Reference is made to the stock exchange notification 3 December 2016,        regarding the letter of intent with Uno-X Gruppen AS (Uno-X), part of        Reitangruppen AS. NEL Fuel AS (NEL), a subsidiary of NEL ASA, and Uno-X        have now entered into a final agreement for the rollout of minimum 20        hydrogen refuelling stations covering all the major cities in Norway        within 2020. Following the agreement, NEL and Uno-X have established the joint        venture Uno-X Hydrogen AS, owned by Uno-X and NEL with 51 % and 49 %        re","m_szDocBody":"oslo norway business wire regulatory new reference made stock exchange notification letter intent unox gruppen unox part reitangruppen nel fuel nel subsidiary nel asa unox entered final agreement rollout minimum hydrogen refuelling station covering major city norway agreement nel unox established joint venture unox hydrogen owned unox nel respectively joint venture build network hydrogen refuelling station hydrogen production fuel cell electric vehicle fcevs operate major city norway station deployed city oslo bergen trondheim stavanger kristiansand corridor location nel pleased announce landmark agreement partner unox rollout commercial network hydrogen refuelling station norway combining joint strength unox nel build network minimum hydrogen refuelling station covering major city norway martin nes chairman nel unox main brand joint venture whilst nel provide technology hydrogen production hydrogen refuelling station unox proud partner nel establish commercial network hydrogen refuelling station norway nel forefront hydrogen technology competence world leading car manufacturer investing heavily hydrogen preferred clean energy technology large scale rollout hydrogen vehicle expected accelerate forward contribute transition low emission providing hydrogen refuelling station customer vegar kulset ceo unox nel nel asa dedicated hydrogen company oslo stock exchange foundation nel hydrogen proud history development continual improvement hydrogen plant nel global supplier hydrogen solution covering entire chain hydrogen production technology hydrogen refuelling station fuel cell electric vehicle logic leading manufacturer hstation hydrogen refuelling station fuel cell electric vehicle fast fuelling long range conventional vehicle today information brought cision contact ","m_szGeo1":"United States","m_szSourceType":"source_news","m_szSrcUrl":"http://www.businesswire.com/news/home/20160301007226/en/NEL-ASA-NEL-enters-final-agreement-Uno-X","m_Places":["Oslo","Norway","Bergen","Trondheim","Stavanger"],"m_People":["Martin Nes","Vegar Kulset"],"m_Companies":["Business Wire","Nel Asa","Oslo Stock Exchange","H2 Logic A/s"],"m_BiGrams":["hydrogen refuelling","refuelling station","major city","city norway","joint venture","unox nel","network hydrogen","hydrogen production","fuel cell","cell electric","electric vehicle"],"m_TriGrams":["hydrogen refuelling station","major city norway","network hydrogen refuelling","fuel cell electric","cell electric vehicle"],"m_SocialTags":[],"m_Topics":[],"m_Industry":[],"m_Technology":[],"m_BiCnt":[9,9,3,3,3,3,3,3,3,3,3],"m_TriCnt":[8,3,3,3,3],"m_iDocBodyWordCnt":231}
