{"m_szDocID":"609048","m_szDocTitle":"VBB-3 To Target 372 MPH Land Speed Record This Summer","m_szYear":"2016","m_szDocSumamry":"VBB-3 To Target 372 MPH Land Speed Record This Summer 16 hours ago    by Mark Kane 0Comments Venturi Buckeye Bullet 3 (VBB-3) Venturi Buckeye Bullet 2.5 (2010: 307.66 mph / 495 km/h The most powerful “electric car” Venturi Buckeye Bullet 3 (VBB-3) with nearly 3,000 horsepower (2200 kW) will be back at the Bonneville Salt Flats this year with the goal of setting a new electric land speed record of some 400 mph (over 640 km/h). Previous version 2.5 set a record of  307.66 mph (495 km/h) in 2010. VBB-3 has so far been very unlucky with weather, which prevented higher speeds in 2013, 2014 and 2015","m_szDocBody":"vbb target mph land speed record summer hour ago mark kane comment venturi buckeye bullet vbb venturi buckeye bullet mph powerful electric car venturi buckeye bullet vbb horsepower back bonneville salt flat year goal setting electric land speed record mph over previous version set record mph vbb unlucky weather prevented higher speed project fruit partnership venturi automobile ohio state university centre automotive research car long process prepare year trip bonneville salt flat resumed early venturi buckeye bullet vbb workshop columbus ohio usa vehicle part ongoing project venturi buckeye bullet racing team began partnership venturi automobile ohio state university centre automotive research car team world landspeed record achieved year hydrogen fuel cell vehicle mph next team returned salt flat fully electric battery powered vehicle vbbb set world record mph venturis partner project student ohio state university centre automotive research dismantled metre long electric streamliner examine mechanical electrical component include mile cable cell battery pack step vehicle return utah bonneville salt flat partner car aiming exceed electric fia land speed record established previous model venturi buckeye bullet show potential unique prototype venturis lead project engineer delphine biscaye vbb equipped electric motor nearly horsepower each awd lithiumion battery cell supply power venturi buckeye bullet vbb venturi vbb project unique research development challenge venturi automobile car fantastic test benchmark performance electric powertrain design extreme operation harsh condition component vehicle studied designed built specific application widely conventional automotive use scope work vbb innovation field electric propulsion energy efficiency prominent challenge automotive industry racing venturi automobile vehicle manufacturer fia formulae championship running racing team venturi formulae team experience vbb bring unique dimension development formulae programme venturis partner ohio state university young student engineer project offer opportunity exposed reality advanced vehicle development fast paced world racing experience development implementation cutting edge automotive technology experience world recent graduate evan maley said working vbb project allowed lot connexion time interview job interview vbb biggest talked about people interested activity involved managed time academic working vbb vbb programme passionate club supporter focused innovation sustainable mobility generously make donation support record attempt logistic sending team engineer student salt flat morning christine benard ceo kathia bemon ceo business human connect michel montfort head hade business centre official support club member certificate unique adventure christine linked innovation sustainable development mobility education value share supported ","m_szGeo1":"United States","m_szSourceType":"source_news","m_szSrcUrl":"http://insideevs.com/vbb-3-to-target-370-mph-land-speed-record-this-summer/","m_Places":["United States","Utah"],"m_People":["Mark Kane","Delphine Biscaye","Evan Maley","Christine Benard","Kathia Bemon","Michel Montfort"],"m_Companies":["372 Mph Land","Ohio State University","Business Center"],"m_BiGrams":["venturi buckeye","buckeye bullet","salt flat","bullet vbb","venturi automobile","ohio state","state university","land speed","speed record","bonneville salt","record mph","university centre","centre automotive","automotive research"],"m_TriGrams":["venturi buckeye bullet","buckeye bullet vbb","ohio state university","land speed record","bonneville salt flat","state university centre","university centre automotive","centre automotive research"],"m_SocialTags":[],"m_Topics":[],"m_Industry":[],"m_Technology":[],"m_BiCnt":[7,7,5,4,4,4,4,3,3,3,3,3,3,3],"m_TriCnt":[7,4,4,3,3,3,3,3],"m_iDocBodyWordCnt":381}
