{"m_szDocID":"609031","m_szDocTitle":"Vancouver Declaration's magic wand thinking | Gunter | Columnists | Opinion | Ot","m_szYear":"2016","m_szDocSumamry":"Vancouver Declaration's magic wand thinking By Lorne  Gunter , Edmonton Sun First posted: Saturday, March 05, 2016 06:00 PM EST Prime Minister Justin Trudeau, second from right, walks out of the First Minister's Meeting with provincial premiers to address the media in Vancouver, March 3, 2016. (REUTERS/Ben Nelms) Article Report an error Back in the 1970s, there was a science mag at my grandparents’ cabin that I recall for two reasons: It seemed sooo old (from 1948) and the cover predicted that by the 1990s we would all be commuting in flying cars. Hey! We’re 20 years past the ‘90s. Where’s my ","m_szDocBody":"vancouver declaration magic wand thinking lorne gunter edmonton sun posted saturday est prime minister justin trudeau right walk minister meeting provincial premier address media vancouver nelm report error back science mag grandparent cabin recall reason sooo from cover predicted commuting flying car hey year past where soaring sedan trouble future dang hard predict meeting vancouver thursday prime minister justin trudeau provincial territorial premier foresee certainty happen year now vancouver declaration climate change highly speculative future forecast masquerading policy document symbol magicwand thinking magicwand thinking belief problem solved magic politician wave money political vancouver declaration pledge spend ten billion tax dollar belief make global warming away commitment advance electrification vehicle transportation word spend billion convincing canadian buy electric car admittedly ten thousand hybrid car sold canada year time electriconly car luxury good suppose government subsidise purchase price the typical allelectric car cost comparable gasolinepowered model canadian buy one matter making practical decade perfect electric car world carmaker make fast car internal combustion engine single charge considered good warm weather case prime minister selfie preem havent noticed cold canada winter cold loss range common electric car winter take hour recharge electric arent powerful wont replace pickup wheeler hauling argue government funding solve problem future also performance problem solved remain problem electricity and emission generating from perfecting electric car simply pushes emission problem supply chain moreover guarantee bucket money mine perfect electric car remember time canada liberal government threw hundred million task perfecting hydrogen fuelcell car those vancouver olympic ottawa spent million fleet hydrogen buse transit time cost bus diesel model operating cost kilometre double year buse parked garage year converted diesel politician predicting future rest magic wand ","m_szGeo1":"Canada","m_szSourceType":"source_news","m_szSrcUrl":"http://www.ottawasun.com/2016/03/04/vancouver-declarations-magic-wand-thinking","m_Places":["Vancouver","Est","Take","Canada","Ottawa"],"m_People":["Lorne Gunter","Justin Trudeau","Ben Nelms","Dang Hard"],"m_Companies":["Edmonton Sun","Reuters","Diesel"],"m_BiGrams":["electric car","vancouver declaration","prime minister"],"m_TriGrams":[],"m_SocialTags":[],"m_Topics":[],"m_Industry":[],"m_Technology":[],"m_BiCnt":[5,3,3],"m_TriCnt":[],"m_iDocBodyWordCnt":275}
