{"m_szDocID":"610832","m_szDocTitle":"Toyota partners in making wind-power hydrogen for fuel cells | News & Observer","m_szYear":"2016","m_szDocSumamry":"March 14, 2016 5:22 AM Toyota partners in making wind-power hydrogen for fuel cells A Toyota fuel cell forklift, right, and a truck designed for hydrogen fueling station and carrying hydrogen, background, are displayed in Yokohama, near Tokyo, after a press event for Hydrogen Supply Chain Demonstration Project Monday, March 14, 2016. Toyota Motor Corp. is trying to answer the main criticism of fuel cell cars: That making the hydrogen for the fuel is not clean. And so the Japanese automaker is going to make hydrogen from wind power. In a project, announced Monday, hydrogen from wind-power plant","m_szDocBody":"toyota partner making windpower hydrogen fuel cell toyota fuel cell forklift right truck designed hydrogen fueling station carrying hydrogen background displayed yokohama tokyo press event hydrogen supply chain demonstration project monday toyota motor corp answer main criticism fuel cell car making hydrogen fuel clean japanese automaker make hydrogen wind power project announced monday hydrogen windpower plant hama wing yokohama southwest tokyo compressed transported truck power fuelcell forklift site port area factory vegetableandfruit market warehouse participant are left right kawasaki city general planning bureau director general masasuke takitoge toshiba corporation energy solution project subproject manager hiroyuki ota iwatani corporation director executive officer katsuya takemoto toyota motor corporation senior managing officer shigeki tomoyama yokohama city director climate change policy headquarter norihiko nomura kanagawa prefecture government director general energy harumi matsuura shizuo kambayashi photo toyota fuel cell forklift front hydrogen fueling station carrying hydrogen background displayed yokohama tokyo press event hydrogen supply chain demonstration project monday toyota motor corp answer main criticism fuel cell car making hydrogen fuel clean japanese automaker make hydrogen wind power project announced monday hydrogen windpower plant hama wing yokohama southwest tokyo compressed transported truck power fuelcell forklift site port area factory vegetableandfruit market warehouse shizuo kambayashi photo order reprint storey yokohama japan toyota motor corp responding main criticism fuel cell car making hydrogen fuel clean plan make hydrogen wind power fuel cell zeroemission running power created hydrogen combine oxygen air make water totally clean supply chain hydrogen cleanly made now hydrogen produced fossil fuel project announced monday hydrogen windpower plant hama wing yokohama southwest tokyo compressed transported truck power fuelcell forklift site area factory vegetableandfruit market warehouse project partnership toyota city yokohama nearby kawasaki prefectural kanagawa government japanese electronic energy company toshiba corp energy supplier iwatani corp involved electricity produced wind power electric vehicle bother making hydrogen defending project toyota senior managing officer shigeki tomoyama stressed easier store hydrogen electricity clean hydrogen fix global warming energy security said stable supply cofree hydrogen needed told reporter yokohama hotel toyota make prius gaselectric hybrid electric vehicle limited cruise range windpowered hydrogen expected reduce carbondioxide emission percent compared gas grid electricity company hydrogen truck newly developed serve hydrogen fueling station forklift japan hope leader hydrogen power plan showcase prowess tokyo olympic cost ensuring adequate hydrogen supply obvious challenge toyotas japanese rival honda motor rolled latest model clarity fuel cell vehicle week toyotas fuel cell vehicle called mirai vehicle expensive regular consumer leased ministry company ","m_szGeo1":"Japan","m_szSourceType":"source_news","m_szSrcUrl":"http://www.newsobserver.com/news/business/article65906102.html","m_Places":["Yokohama","Tokyo","Hama","Kawasaki","Kanagawa","Japan","Toyota"],"m_People":["A Toyota","Masasuke Takitoge","Hiroyuki Ota","Katsuya Takemoto","Shigeki Tomoyama","Harumi Matsuura","Shizuo Kambayashi"],"m_Companies":["Toyota Partners","Toyota Motor Corp","Planning Bureau Director General","Toshiba Corporation","Iwatani Corporation","Toyota Motor Corporation","Ap","Kanagawa Government","Toshiba Corp","Iwatani Corp.","Honda Motor Co"],"m_BiGrams":["fuel cell","hydrogen fuel","toyota motor","making hydrogen","wind power","hydrogen fueling","fueling station","hydrogen supply","supply chain","motor corp","main criticism","criticism fuel","cell car","car making","fuel clean","make hydrogen","hydrogen wind","project announced","announced monday","monday hydrogen","hydrogen windpower","windpower plant","plant hama","hama wing","wing yokohama","yokohama southwest","southwest tokyo","tokyo compressed","compressed transported","transported truck","truck power","power fuelcell","fuelcell forklift","forklift site","area factory","factory vegetableandfruit","vegetableandfruit market","market warehouse"],"m_TriGrams":["hydrogen fueling station","toyota motor corp","main criticism fuel","criticism fuel cell","fuel cell car","cell car making","car making hydrogen","making hydrogen fuel","hydrogen fuel clean","make hydrogen wind","hydrogen wind power","project announced monday","announced monday hydrogen","monday hydrogen windpower","hydrogen windpower plant","windpower plant hama","plant hama wing","hama wing yokohama","wing yokohama southwest","yokohama southwest tokyo","southwest tokyo compressed","tokyo compressed transported","compressed transported truck","transported truck power","truck power fuelcell","power fuelcell forklift","fuelcell forklift site","area factory vegetableandfruit","factory vegetableandfruit market","vegetableandfruit market warehouse"],"m_SocialTags":[],"m_Topics":[],"m_Industry":[],"m_Technology":[],"m_BiCnt":[9,4,4,4,4,3,3,3,3,3,3,3,3,3,3,3,3,3,3,3,3,3,3,3,3,3,3,3,3,3,3,3,3,3,3,3,3,3],"m_TriCnt":[3,3,3,3,3,3,3,3,3,3,3,3,3,3,3,3,3,3,3,3,3,3,3,3,3,3,3,3,3,3],"m_iDocBodyWordCnt":403}
