{"m_szDocID":"610830","m_szDocTitle":"Hyundai Delivers First Fuel Cell Vehicle in Ontario :: NGT News","m_szYear":"2016","m_szDocSumamry":"Hyundai Delivers First Fuel Cell Vehicle in Ontario Categories : New & Noteworthy Hyundai handed over the keys to the first Tucson Fuel Cell Vehicle (FCEV) to a customer in Ontario. Joseph Cargnelli, chief technology officer and co-founder of Mississauga-based Hydrogenics Corp., took delivery of his 2015 Tucson Fuel Cell vehicle. “I am extremely proud to be Hyundai’s first customer in Ontario to take delivery of a fuel cell vehicle,” says Cargnelli. “Hydrogen-powered fuel cell technology has the incredible potential to revolutionize our world by delivering clean energy to meet our every need; ","m_szDocBody":"hyundai deliver fuel cell vehicle ontario category noteworthy hyundai handed key tucson fuel cell vehicle fcev customer ontario joseph cargnelli chief technology officer cofounder mississaugabased hydrogenic corp delivery tucson fuel cell vehicle extremely proud hyundais customer ontario delivery fuel cell vehicle cargnelli hydrogenpowered fuel cell technology incredible potential revolutionise world delivering clean energy meet need true transportation hyundai auto canada announced canadian automotive company offer tucson fuel cell actual realworld customer vehicle delivery place tucson fcevs delivering thousand zeroemission kilometre road british columbia doubt mind fuel cell powertrain ready prime time proven time again don romano president ceo hyundai auto canada fuel cell future automotive industry hyundai shown technology matured step facing government level investing network hydrogen fueling station customer enjoy zeroemission driving hyundais advanced fuel cell technology effectively replace battery pack electric vehicle generating electricity electrochemical process involve stored hydrogen oxygen atmosphere process involve hydrogen combustion moving part fuel cell stack byproduct pure water vapour making tucson fcev zeroemission electric vehicle tucson fcev take minute refuel hydrogen gas deliver estimated mile emissionsfree driving ","m_szGeo1":"Canada","m_szSourceType":"source_news","m_szSrcUrl":"http://ngtnews.com/hyundai-delivers-first-fuel-cell-vehicle-in-ontario/","m_Places":["Ontario","Tucson","Mississauga","Canada","British Columbia"],"m_People":["Joseph Cargnelli","Don Romano"],"m_Companies":["Hyundai","Hydrogenics Corp."],"m_BiGrams":["fuel cell","cell vehicle","tucson fuel"],"m_TriGrams":["fuel cell vehicle","tucson fuel cell"],"m_SocialTags":[],"m_Topics":[],"m_Industry":[],"m_Technology":[],"m_BiCnt":[10,4,3],"m_TriCnt":[4,3],"m_iDocBodyWordCnt":174}
