{"m_szDocID":"610838","m_szDocTitle":"Audi To Lead Hydrogen Fuel Cell Technology For The Volkswagen Group - Overdrive","m_szYear":"2016","m_szDocSumamry":"Overdrive Audi to lead hydrogen fuel cell technology for the Volkswagen group   Audi to lead hydrogen fuel cell technology for the Volkswagen group 14 Mar 2016 /  Team OD Staff The Volkswagen group has been in the eye of the storm with the recent diesel emission scandal. However, the company is making amends and is using one of its flagship brands, Audi to lead its hydrogen fuel cell efforts. Despite electric vehicles gaining traction in International markets, Audi’s new development chief Stefan Knirsch feels that hydrogen fuel cell vehicles are the way forward. Electric vehicles have many sho","m_szDocBody":"overdrive audi lead hydrogen fuel cell technology volkswagen audi lead hydrogen fuel cell technology volkswagen team staff volkswagen eye storm recent diesel emission scandal however company making amend flagship brand audi lead hydrogen fuel cell effort electric vehicle gaining traction international market audis development chief stefan knirsch feel hydrogen fuel cell vehicle forward electric vehicle shortcoming battery pack size cooling issue battery weight hydrogen fuel cell vehicle hand require smaller battery cheaper build lighter significantly reducing toll vehicle performance also battery minute fill opposed battery electric vehicle require hour full charge audi htron quattro concept showcased detroit motor show vehicle vehicle hydrogen fuel cell technology concept suv audi hydrogen full tank travel hydrogen tank located beneath passenger seat area luggage compartment liberating interior space unlike conventional electric car htron quattro thevw group generation modular longitudinal platform mlb evo audi reduce cost reducing amount precious material platinum common catalyst proton exchange membrane pem fuel cell stackswhile production ready model while itll interesting audis hydrogen fuel cell vehicle turn out read ","m_szGeo1":"","m_szSourceType":"source_news","m_szSrcUrl":"http://overdrive.in/news/audi-to-lead-hydrogen-fuel-cell-technology-for-the-volkswagen-group/","m_Places":["Detroit"],"m_People":["Stefan Knirsch"],"m_Companies":["Audi","Volkswagen","Diesel","Seat","Mlb"],"m_BiGrams":["fuel cell","hydrogen fuel","audi lead","lead hydrogen","cell technology","electric vehicle","cell vehicle"],"m_TriGrams":["hydrogen fuel cell","audi lead hydrogen","lead hydrogen fuel","fuel cell technology","fuel cell vehicle"],"m_SocialTags":[],"m_Topics":[],"m_Industry":[],"m_Technology":[],"m_BiCnt":[8,7,3,3,3,3,3],"m_TriCnt":[7,3,3,3,3],"m_iDocBodyWordCnt":169}
