{"m_szDocID":"610827","m_szDocTitle":"Audi will lead fuel cell cars for VW Group","m_szYear":"2016","m_szDocSumamry":"Audi will lead fuel cell cars for VW Group Audi says the H-tron quattro concept's aerodynamic design helps to reduce fuel use. Automotive News Europe March 9, 2016 06:01 CET INGOLSTADT, Germany -- Audi will lead Volkswagen Group's development efforts in emissions-free hydrogen fuel cell cars to better position the brand as a innovation leader, its executives said. Audi has assumed the lead function as the group's \"center of excellence\" for fuel cells. Its first fuel cell car could be an SUV previewed by the H-tron quattro concept unveiled at the Detroit auto show in January. Speaking to report","m_szDocBody":"audi lead fuel cell car audi htron quattro concept aerodynamic design help reduce fuel use automotive new europe cet ingolstadt germany audi lead volkswagen group development effort emissionsfree hydrogen fuel cell car position brand innovation leader executive said audi assumed lead function group centre excellence fuel cell fuel cell car suv previewed htron quattro concept unveiled detroit auto show january speaking reporter brand headquarter here audis development chief stefan knirsch defended invest fuel cell technology electric car begin gain traction market big discussion why fuel cell future battery electric point charging infrastructure electric range increase fuel cell car black white moment press event knirsch believe decisive advantage fuel cell vehicle fully electric car smaller battery substantially cheaper build lighter improving vehicle performance addition fuel cell car minute fill battery powered car hour fully recharge aiming reduce minute volt technology launch date given knirsch future audi fuel cell car similar appearance upcoming electric car debut fullsize suv benefit growing popularity vehicle chose body style battery electric clear feedback market gain volume including fleet true higher price car said adopt similar approach fuel cell car cutting production cost audi reduce production cost reducing amount precious metal platinum common catalyst proton exchange membrane pem fuel cell stack knirsch declined kind price audis fuel cell car early stage naturally price euros intend sell them knirsch said knirsch audi thinking step solving problem procuring hydrogen prevalent element earth hydrogen bind quickly atom result naturally found gas methane audis plant werlte germany produce hydrogen electrolysis energyintensive method electric current run pole submerged water splitting liquid molecule hydrogen oxygen gase receiving regulatory permission facility purchase excess renewable energy power process generated windpark directly utility time price low middle night offer hydrogen produced coneutral future knirsch said audis htron quattro concept hydrogen mile range mile hydrogen tank located beneath passenger luggage compartment impinge interior audi said car group secondgeneration modular longitudinal platform mlb evo underpin etron quattro concept battery powered car unveiled frankfurt show september audi isnt developing fuel technology sery production mercedesbenz plan coordinate launch fuel cell vehicle based glc midsize crossover year ford motor nissan hope spurring investment hydrogen filling station infrastructure reach christiaan hetzner ","m_szGeo1":"Germany","m_szSourceType":"source_news","m_szSrcUrl":"http://europe.autonews.com/article/20160309/ANE/160309884/audi-will-lead-fuel-cell-cars-for-vw-group","m_Places":["Europe","Ingolstadt","Detroit","Germany","Frankfurt"],"m_People":["Stefan Knirsch","Christiaan Hetzner"],"m_Companies":["Audi","Vw Group","Automotive News","Volkswagen Group","Volt","Mlb","Mercedes-benz","Ford Motor"],"m_BiGrams":["fuel cell","cell car","quattro concept","htron quattro","electric car"],"m_TriGrams":["fuel cell car","htron quattro concept"],"m_SocialTags":[],"m_Topics":[],"m_Industry":[],"m_Technology":[],"m_BiCnt":[14,8,4,3,3],"m_TriCnt":[7,3],"m_iDocBodyWordCnt":359}
