{"m_szDocID":"612444","m_szDocTitle":"Toyota counters hydrogen criticism with partnerships","m_szYear":"2016","m_szDocSumamry":"FacebookEmail Twitter Google+ LinkedIn Pinterest Toyota counters hydrogen criticism with partnerships The project is a partnership between Toyota and the cities of Yokohama and Kawasaki, and the prefectural Kanagawa Post to Facebook Toyota counters hydrogen criticism with partnerships The project is a partnership between Toyota and the cities of Yokohama and Kawasaki, and the prefectural Kanagawa Check out this story on detroitnews.com: http://detne.ws/1pklmsF CancelSend A link has been sent to your friend's email address. Posted! A link has been posted to your Facebook feed. Join the Conversa","m_szDocBody":"facebookemail google linkedin pinterest toyota counter hydrogen criticism partnership project partnership toyota city yokohama kawasaki prefectural kanagawa post toyota counter hydrogen criticism partnership project partnership toyota city yokohama kawasaki prefectural kanagawa cheque storey detroitnewscom cancelsend link friend address posted link posted feed join conversation commenting read conversation guideline faqs toyota counter hydrogen criticism partnership yuri kageyama press edt yokohama japan toyota motor corp responding main criticism fuel cell car making hydrogen fuel clean plan make hydrogen wind power fuel cell zeroemission running power created hydrogen combine oxygen air make water totally clean supply chain hydrogen cleanly made now hydrogen produced fossil fuel project announced monday hydrogen windpower plant hama wing yokohama southwest tokyo compressed transported truck power fuelcell forklift site area factory vegetableandfruit market warehouse project partnership toyota city yokohama nearby kawasaki prefectural kanagawa government japanese electronic energy company toshiba corp energy supplier iwatani corp involved electricity produced wind power electric vehicle bother making hydrogen defending project toyota senior managing officer shigeki tomoyama stressed easier store hydrogen electricity clean hydrogen fix global warming energy security said stable supply cofree hydrogen needed told reporter yokohama hotel toyota make prius gaselectric hybrid electric vehicle limited cruise range windpowered hydrogen expected reduce carbondioxide emission percent compared gas grid electricity company hydrogen truck newly developed serve hydrogen fueling station forklift japan hope leader hydrogen power plan showcase prowess tokyo olympic cost ensuring adequate hydrogen supply obvious challenge toyotas japanese rival honda motor rolled latest model clarity fuel cell vehicle week toyotas fuel cell vehicle called mirai vehicle expensive regular consumer leased ministry company copyright press right reserved material published broadcast rewritten redistributed read share storey top videos ","m_szGeo1":"United States","m_szSourceType":"source_news","m_szSrcUrl":"http://www.detroitnews.com/story/business/autos/foreign/2016/03/14/toyota-counters-hydrogen-criticism-partnerships/81790440/","m_Places":["Toyota","Yokohama","Kawasaki","Kanagawa","Japan","Hama","Tokyo"],"m_People":["Yuri Kageyama","Shigeki Tomoyama"],"m_Companies":["Twitter","Google","Linkedin","Pinterest","Facebook","Associated Press","Toyota Motor Corp","Kanagawa Government","Toshiba Corp","Iwatani Corp.","Honda Motor Co"],"m_BiGrams":["fuel cell","toyota counter","counter hydrogen","hydrogen criticism","criticism partnership","project partnership","partnership toyota","toyota city","city yokohama","kawasaki prefectural","prefectural kanagawa"],"m_TriGrams":["toyota counter hydrogen","counter hydrogen criticism","hydrogen criticism partnership","toyota city yokohama","kawasaki prefectural kanagawa"],"m_SocialTags":[],"m_Topics":[],"m_Industry":[],"m_Technology":[],"m_BiCnt":[4,3,3,3,3,3,3,3,3,3,3],"m_TriCnt":[3,3,3,3,3],"m_iDocBodyWordCnt":273}
