{"m_szDocID":"612460","m_szDocTitle":"Audi to lead hydrogen fuel cell technology for the Volkswagen group - Firstpost","m_szYear":"2016","m_szDocSumamry":"firstpost Audi to lead hydrogen fuel cell technology for the Volkswagen group by Overdrive   Mar 14, 2016 19:30 IST #Audi   #audi h-tron quattro concept   #Audi India   #audi to develop hydrogen fuel cell technology   #audi to lead volkswagen's hydrogen fuel cell technology   #automonitor   #Volkswagen Group   The Volkswagen group has been in the eye of the storm with the recent diesel emission scandal. However, the company is making amends and is using one of its flagship brands, Audi to lead its hydrogen fuel cell efforts. Despite electric vehicles gaining traction in International markets, ","m_szDocBody":"firstpost audi lead hydrogen fuel cell technology volkswagen overdrive ist #audi #audi htron quattro concept #audi india #audi develop hydrogen fuel cell technology #audi lead volkswagen hydrogen fuel cell technology #automonitor #volkswagen volkswagen eye storm recent diesel emission scandal however company making amend flagship brand audi lead hydrogen fuel cell effort electric vehicle gaining traction international market audis development chief stefan knirsch feel hydrogen fuel cell vehicle forward electric vehicle shortcoming battery pack size cooling issue battery weight hydrogen fuel cell ","m_szGeo1":"India","m_szSourceType":"source_news","m_szSrcUrl":"http://www.firstpost.com/auto/audi-to-lead-hydrogen-fuel-cell-technology-for-the-volkswagen-group-2675026.html","m_Places":["India"],"m_People":["Stefan Knirsch"],"m_Companies":["Audi","Volkswagen","Diesel"],"m_BiGrams":["hydrogen fuel","fuel cell","cell technology"],"m_TriGrams":["hydrogen fuel cell","fuel cell technology"],"m_SocialTags":[],"m_Topics":[],"m_Industry":[],"m_Technology":[],"m_BiCnt":[6,6,3],"m_TriCnt":[6,3],"m_iDocBodyWordCnt":81}
