{"m_szDocID":"612411","m_szDocTitle":"Hyundai Exec, Korea President Tour EV Factory | Engines content from WardsAuto","m_szYear":"2016","m_szDocSumamry":"Home > Engines > Hyundai Exec, Korea President Tour EV Factory Hyundai Exec, Korea President Tour EV Factory What is in this article?: Hyundai Exec, Korea President Tour EV Factory Hyundai Vice Chairman Chung Eui-Sun had been billed as a key presenter at the EV Expo, but changed plans to show Korean President  Park Guen-hye how the all-electric Ioniq is produced at the automaker’s Asan plant. Ioniq key to Hyundai goal of 100,000 EVs on Korean roads by 2020.   Hyundai Says Ioniq World-Beater in Fuel Efficiency One of the biggest events at the 3rd International Electric Vehicle Expo which opened","m_szDocBody":"home engine hyundai exec korea president tour factory hyundai exec korea president tour factory article hyundai exec korea president tour factory hyundai vice chairman chung euisun billed key presenter expo changed plan show korean president park guenhye allelectric ioniq produced automaker asan plant ioniq key hyundai goal evs korean road hyundai ioniq worldbeater fuel efficiency biggest event international electric vehicle expo opened jeju island south coast korea place hundred mile hyundai plant asan allelectric hyundai ioniq making korean debut expo hyundai vice chairman chung euisun asan plant escorting korea president park guenhye visited ioniq assembly line heard presentation technology chung billed key presenter expo suddenly changed plan show korean president ioniq produced park visit government keen interest making korea world leader technology expressed confidence korean automaker compete globally developing ecofriendly vehicle autonomous vehicle mentioned autonomous car specifically automaker lag global competitor stay ahead them park told official further park encouraged chung hyundai official push ahead programme develop hydrogenfuelcell electric buse showcased winter olympic held pyeongchang korea park vowed korean government fully back company involved development artificial intelligence key autonomouscar technology ","m_szGeo1":"","m_szSourceType":"source_news","m_szSrcUrl":"http://wardsauto.com/engines/hyundai-exec-korea-president-tour-ev-factory","m_Places":["Jeju Island","Korea"],"m_People":["Chung","Hye How"],"m_Companies":["Hyundai","Google","Korean Government"],"m_BiGrams":["korea president","hyundai exec","exec korea","president tour","tour factory"],"m_TriGrams":["hyundai exec korea","exec korea president","korea president tour","president tour factory"],"m_SocialTags":[],"m_Topics":[],"m_Industry":[],"m_Technology":[],"m_BiCnt":[4,3,3,3,3],"m_TriCnt":[3,3,3,3],"m_iDocBodyWordCnt":180}
