{"m_szDocID":"612426","m_szDocTitle":"Linde researches hydrogen power | SHD Logistics","m_szYear":"2016","m_szDocSumamry":"Linde researches hydrogen power March 18, 2016 by Peter MacLeod Tweet SHD Logistics RSS Email this page A new collaborative research project, H2IntraDrive, has proved that using industrial trucks with hydrogen drive is the most sustainable and cost-effective way of powering materials handling equipment in the automotive industry. The project, led by the BMW Group, Linde Material Handling and the fml Institute of Technical University Munich (TUM), investigated the viability of using hydrogen drive systems in fork lift trucks and tow tractors and confirmed an increase in overall productivity. As","m_szDocBody":"linde researches hydrogen power peter macleod tweet shd logistic collaborative research project hintradrive proved industrial truck hydrogen drive sustainable costeffective powering material handling equipment automotive industry project led bmw group linde material handling fml institute technical university munich tum investigated viability hydrogen drive system fork lift truck tow tractor confirmed increase productivity part project tum institute material handling material flow logistic fml carried independent survey showed industry expert regard hydrogen power source beneficial feel insufficiently informed potential opportunity hydrogen drive produce tum researcher compared electric hydrogen drive system based parameter energy efficiency reliability durability environmental economic sustainability conducted bmw group plant leipzig scientist established thing improved life cycle truck carrying nearpractice calculation fleet vehicle found that conventional battery change carried minute hydrogen powered tow tractor refuelled half minute hydrogen powered fork lift truck refuelling process time faster compared replacing comparable battery saving time report highlighted fact costly equipment infrastructure required battery powered machinery longer hydrogen power linde cso christophe lautray said fact hydrogen technology successfully completed endurance test bmw production reached market maturity important signal customer research gain important insight develop vehicle industry pioneer project substantiated technology leader compared conventional electric vehicle operating range hydrogenpowered tow tractor standard operating range fork lift truck lower larger tank volume higher tank pressure resolve future fml chair holder munich prof willibald gnthner said judge result research project clear success logistic germany road pioneering alternative drive technology research report document achievement important intermediate goal question detailed refinement explored followup project research leading report funded federal ministry transport digital infrastructure germany grant million part national innovation programme hydrogen fuel cell technology nip senior manager steering logistic cfrp production purchasing bmw michael strbel said bmw set standard sustainability leipzig production innovative electric car hydrogen drive system making significant contribution logistic optimisation thing due green hydrogen link ","m_szGeo1":"Germany","m_szSourceType":"source_news","m_szSrcUrl":"http://www.shdlogistics.com/news/linde-researches-hydrogen-power","m_Places":["Linde","Leipzig","Munich","Germany"],"m_People":["Peter Macleod","Christophe Lautray","Willibald A. Günthner","Michael Ströbel"],"m_Companies":["Bmw Group","Institute Of Technical University Munich","Linde Cso","Bmw","Signal","Ministry Of Transport","I3"],"m_BiGrams":["hydrogen drive","hydrogen power","material handling","drive system","fork lift","lift truck","tow tractor"],"m_TriGrams":["hydrogen drive system","fork lift truck"],"m_SocialTags":[],"m_Topics":[],"m_Industry":[],"m_Technology":[],"m_BiCnt":[5,3,3,3,3,3,3],"m_TriCnt":[3,3],"m_iDocBodyWordCnt":300}
