{"m_szDocID":"612428","m_szDocTitle":"Toyota partner in making wind-power hydrogen for fuel cells | TheLedger.com","m_szYear":"2016","m_szDocSumamry":"Enlarge Text Toyota partner in making wind-power hydrogen for fuel cells A Toyota fuel cell forklift, front, and a hydrogen fueling station and carrying hydrogen, background, are displayed in Yokohama, near Tokyo, after a press event for Hydrogen Supply Chain Demonstration Project on Monday. SHIZUO KAMBAYASHI/AP Published: Monday, March 14, 2016 at 5:18 p.m. Last Modified: Monday, March 14, 2016 at 5:18 p.m. YOKOHAMA, Japan â€” Toyota Motor Corp. is responding to the main criticism of fuel cell cars, that making the hydrogen for the fuel is not clean, with plans to help make the hydrogen using w","m_szDocBody":"enlarge toyota partner making windpower hydrogen fuel cell toyota fuel cell forklift front hydrogen fueling station carrying hydrogen background displayed yokohama tokyo press event hydrogen supply chain demonstration project monday shizuo published monday modified monday yokohama japan toyota motor corp responding main criticism fuel cell car making hydrogen fuel clean plan make hydrogen wind power fuel cell zeroemission running power created hydrogen combine oxygen air make water totally clean supply chain hydrogen cleanly made now hydrogen produced fossil fuel project announced monday hydrogen windpower plant hama wing yokohama southwest tokyo compressed transported truck power fuelcell forklift site area factory vegetableandfruit market warehouse project partnership toyota city yokohama nearby kawasaki prefectural kanagawa government japanese electronic energy company toshiba corp energy supplier iwatani corp involved electricity produced wind power electric vehicle bother making hydrogen defending project toyota senior managing officer shigeki tomoyama stressed easier store hydrogen electricity clean hydrogen fix global warming energy security said stable supply cofree hydrogen needed told reporter yokohama hotel toyota make prius gaselectric hybrid electric vehicle limited cruise range windpowered hydrogen expected reduce carbondioxide emission percent compared gas grid electricity company hydrogen truck newly developed serve hydrogen fueling station forklift japan hope leader hydrogen power plan showcase prowess tokyo olympic cost ensuring adequate hydrogen supply obvious challenge toyotas japanese rival honda motor rolled latest model clarity fuel cell vehicle week toyotas fuel cell vehicle called mirai vehicle expensive regular consumer leased ministry company toyota fuel cell forklift front hydrogen fueling station carrying hydrogen background displayed yokohama tokyo theledgercom yokohama japan toyota motor corp responding main criticism fuel cell car making hydrogen fuel clean plan make hydrogen wind power fuel cell zeroemission running power created hydrogen combine oxygen air make water totally clean supply chain hydrogen cleanly made now hydrogen produced fossil fuel project announced monday hydrogen windpower plant hama wing yokohama southwest tokyo compressed transported truck power fuelcell forklift site area factory vegetableandfruit market warehouse project partnership toyota city yokohama nearby kawasaki prefectural kanagawa government japanese electronic energy company toshiba corp energy supplier iwatani corp involved electricity produced wind power electric vehicle bother making hydrogen defending project toyota senior managing officer shigeki tomoyama stressed easier store hydrogen electricity clean hydrogen fix global warming energy security said stable supply cofree hydrogen needed told reporter yokohama hotel toyota make prius gaselectric hybrid electric vehicle limited cruise range windpowered hydrogen expected reduce carbondioxide emission percent compared gas grid electricity company hydrogen truck newly developed serve hydrogen fueling station forklift japan hope leader hydrogen power plan showcase prowess tokyo olympic cost ensuring adequate hydrogen supply obvious challenge toyotas japanese rival honda motor rolled latest model clarity fuel cell vehicle week toyotas fuel cell vehicle called mirai vehicle expensive regular consumer leased ministry company ","m_szGeo1":"Japan","m_szSourceType":"source_news","m_szSrcUrl":"http://www.theledger.com/article/20160314/news/160319709","m_Places":["Toyota","Yokohama","Tokyo","Japan","Hama","Kawasaki"],"m_People":["A Toyota","Shizuo Kambayashi","Shigeki Tomoyama"],"m_Companies":["Ap","Toyota Motor Corp","Kanagawa Government","Toshiba Corp","Iwatani Corp.","Honda Motor Co"],"m_BiGrams":["fuel cell","hydrogen fueling","fueling station","making hydrogen","wind power","electric vehicle","cell vehicle","hydrogen fuel","hydrogen supply","supply chain"],"m_TriGrams":["hydrogen fueling station","fuel cell vehicle"],"m_SocialTags":[],"m_Topics":[],"m_Industry":[],"m_Technology":[],"m_BiCnt":[11,4,4,4,4,4,4,3,3,3],"m_TriCnt":[4,4],"m_iDocBodyWordCnt":452}
