{"m_szDocID":"614168","m_szDocTitle":"2016 China Market For Fuel Cell Electric Vehicles Industry: MarketResearchReports.biz > Hydrogen Fuel News | Hydrogen Fuel News","m_szYear":"2016","m_szDocSumamry":"MarketResearchReports.Biz has announced addition of new report “China Fuel Cell Electric Vehicles Industry 2016 Market Research Report” to its database. Summary The China Fuel Cell Electric Vehicles Industry 2016 Market Research Report is a professional and in-depth study on the current state of the Fuel Cell Electric Vehicles industry. The report provides a basic overview of the industry including definitions, classifications, applications and industry chain structure. The Fuel Cell Electric Vehicles market analysis is provided for the China markets including development trends, competitive l","m_szDocBody":"marketresearchreportsbiz announced addition report china fuel cell electric vehicle industry market research report database summary china fuel cell electric vehicle industry market research report professional indepth study current state fuel cell electric vehicle industry report basic overview industry including definition classification application industry chain structure fuel cell electric vehicle market analysis provided china market including development trend competitive landscape analysis key region development status development policy plan discussed manufacturing processe bill material cost structure analysed report state consumption supply demand figure cost price revenue gross margin report focuse china major leading industry player providing information company profile product picture specification capacity production price cost revenue contact information upstream raw material equipment downstream demand analysis carried out fuel cell electric vehicle industry development trend marketing channel analysed finally feasibility investment project assessed research conclusion offered download sample copy report table figure report key statistic state industry valuable source guidance direction company individual interested market definition specification fuel cell electric vehicle classification fuel cell electric vehicle application fuel cell electric vehicle industry chain structure fuel cell electric vehicle industry overview fuel cell electric vehicle industry policy analysis fuel cell electric vehicle industry new analysis fuel cell electric vehicle manufacturing cost structure analysis fuel cell electric vehicle bill material bom fuel cell electric vehicle bom price analysis fuel cell electric vehicle labour cost analysis fuel cell electric vehicle depreciation cost analysis fuel cell electric vehicle manufacturing cost structure analysis fuel cell electric vehicle manufacturing process analysis fuel cell electric vehicle china price cost gross fuel cell electric vehicle marketresearchreportsbiz comprehensive collection market research report marketresearchreportsbiz service specially designed save time money client stop solution research need main offering syndicated research report custom research subscription consulting service serve size type company spanning industry browse latest industry press release ","m_szGeo1":"China","m_szSourceType":"source_news","m_szSrcUrl":"http://www.hydrogenfuelnews.com/2016-china-market-fuel-cell-electric-vehicles-industry-marketresearchreports-biz/8528074/","m_Places":["China","United States"],"m_People":[],"m_Companies":["Upstream","Industry Press"],"m_BiGrams":["fuel cell","cell electric","electric vehicle","vehicle industry","analysis fuel","research report","market research","cost structure","vehicle manufacturing"],"m_TriGrams":["fuel cell electric","cell electric vehicle","electric vehicle industry","analysis fuel cell","market research report","electric vehicle manufacturing"],"m_SocialTags":[],"m_Topics":[],"m_Industry":[],"m_Technology":[],"m_BiCnt":[20,20,20,8,8,4,3,3,3],"m_TriCnt":[20,20,8,8,3,3],"m_iDocBodyWordCnt":294}
