{"m_szDocID":"614253","m_szDocTitle":"Capitol Hyundai In San Francisco Bay Area Added To Growing Collection Of Hyundai Tucson Fuel Cell Dealers","m_szYear":"2016","m_szDocSumamry":"News |   March 24, 2016 Capitol Hyundai In San Francisco Bay Area Added To Growing Collection Of Hyundai Tucson Fuel Cell Dealers Capitol Hyundai Joins Keyes Hyundai, Tustin Hyundai, Win Hyundai in Carson and Hardin Hyundai in Anaheim as Fifth Qualified Hydrogen Fuel Cell Dealer San Jose, CA /PRNewswire/ - Capitol Hyundai in San Jose, California, a proud member of the Del Grande Dealer Group, became the fifth qualified dealer for Hyundai's zero-emissions  Tucson Fuel Cell  hydrogen electric vehicle today. Capitol Hyundai of San Jose will be the first Hyundai Tucson Fuel Cell dealer in Northern","m_szDocBody":"new capitol hyundai san francisco bay area added growing collection hyundai tucson fuel cell dealer capitol hyundai join keye hyundai tustin hyundai win hyundai carson hardin hyundai anaheim qualified hydrogen fuel cell dealer san jose capitol hyundai insan jose california proud member del grande dealer group qualified dealer hyundais zeroemission tucson fuel cell hydrogen electric vehicle today capitol hyundai ofsan josewill hyundai tucson fuel cell dealer innorthern californiasbay area region hyundai manufacturer offer consumer opportunity massproduced fuel cell vehicle zeroemission tucson fuel cell cuv launch injune tucson fuel cell driver accumulated million zeroemission mile street ofsouthern california accumulated mileage helped improve air quality region tonne coemission compared similar internalcombustionpowered cuv hyundai delivered tucson fuel cell introduction massproduced fuel cell vehicle market injune capitol hyundai excited added qualified dealer hyundais zeroemission tucson fuel cell hydrogen electric vehicle mrshaun del grande owner capitol grande dealer group our location bay area region hyundais innorthern california making convenient local resident conveniently acquire tucson fuel cell cuv helping reduce greenhouse gas emission work live hyundai proud add capitol hyundai growing collection approved zeroemission tucson fuel cell dealer saiddave zuchowski president ceo hyundai motor america capitol hyundai add convenient location thesan francisco bay areato serve newest fuel cell customer innorthern california capitol hyundai join existing hyundai fuel cell dealer keye hyundai tustin hyundai win hyundai incarsonand hardin hyundai inanaheim total qualified fuel cell dealer southern andnorthern california qualified hyundai fuel cell dealer approved dealer fulfil significant additional hydrogen fuel cell requirement customer service technical service tucsonfuel cell advantage hyundai tucson fuel cell cuv number advantage alternative fuel energyrich hydrogen fuel estimated driving range mile fillup similar gasoline vehicle further fuel cell driving range vehicle performance minimally affected extreme hot cold ambient temperature giving owner extra measure peace mind day important consumer transitioning gasoline vehicle tucson fuel cell refilled hydrogen time typical gasoline vehicle size finally fuel cell vehicle due compact lightweight fuel cell stack design completely production scalable small large vehicle urbanfocused minicompact car fullsize buse truck hyundai motor america hyundai motor america headquartered infountain valley calif subsidiary hyundai motor korea hyundai vehicle distributed throughoutthe united statesby hyundai motor america sold serviced dealership nationwide hyundai vehicle sold covered hyundai assurance programme include fully transferable vehicle limited warranty hyundais powertrain limited warranty year complimentary roadside assistance hyundai blue link connected care owner hyundai model equipped blue link telematic system proactive safety car care service complimentary year enrollment service include automatic collision notification enhanced roadside assistance vehicle diagnostic alert monthly vehicle health report invehicle service scheduling detail hyundai assurance visit visit media website blog ","m_szGeo1":"United States","m_szSourceType":"source_news","m_szSrcUrl":"http://www.pollutiononline.com/doc/capitol-hyundai-in-san-francisco-bay-area-added-hyundai-tucson-fuel-cell-dealers-0001","m_Places":["San Francisco Bay Area","Anaheim","San Jose, Ca","San Jose, California","Tucson","San Jose","Northern California","Bay Area","United States","Southern California","Korea"],"m_People":["Mr. Shaun Del Grande"],"m_Companies":["Hyundai","Hyundai Tucson","Tustin Hyundai","Del Grande Dealer Group","Hyundai Motor America","Ups","Hyundai Motor Co","Nationwide"],"m_BiGrams":["fuel cell","tucson fuel","capitol hyundai","cell dealer","hyundai motor","zeroemission tucson","motor america","hyundai tucson","hydrogen fuel","cell vehicle","cell cuv","gasoline vehicle"],"m_TriGrams":["tucson fuel cell","fuel cell dealer","zeroemission tucson fuel","hyundai motor america","hyundai tucson fuel","fuel cell vehicle","fuel cell cuv"],"m_SocialTags":[],"m_Topics":[],"m_Industry":[],"m_Technology":[],"m_BiCnt":[22,11,8,7,5,4,4,3,3,3,3,3],"m_TriCnt":[11,7,4,4,3,3,3],"m_iDocBodyWordCnt":426}
