{"m_szDocID":"614270","m_szDocTitle":"Everyday drivers: Half-ton Titan joins Nissan’s pickup lineup | Driving","m_szYear":"2016","m_szDocSumamry":"Everyday drivers: Half-ton Titan joins Nissan’s pickup lineup The New York Auto Show has its fair share of practical vehicles, too By Driving , David Booth and John LeBlanc Originally published: March 23, 2016 SMALL MEDIUM LARGE As much as the auto shows may showcase the glitz and glamour of everything on four wheels, the everyday drivers – from crossovers and pickups to compact sedans and hybrids – are the bread and butter of the business. Here are some of the notable mainstream automakers debuting at this year’s New York show. 2017 Nissan Titan 2017 Nissan Titan XD Darren Begg, Driving What ","m_szDocBody":"everyday driver halfton titan join nissan pickuplineup york auto show fair share practical vehicle driving david booth john leblanc originally published small medium large auto show showcase glitz glamour wheel everyday driver crossover pickup compact sedan hybrid bread butter business notable mainstream automaker debuting year york show nissan titan nissan titan darren begg driving nissan call standard bearer revitalised pickup lineup essentially halfton crew cab version titan powered nissan evergreen litre gasolinefueled good competitive horsepower guise interesting that familial resemblance titan titan fundamentally vehicle built chassis titan share aggressive style titan vehicle completely underneath skin steve rhind nissan canadas director marketing titan compete heart fullsize pickup segment halfton titan unique solution customer bridging cost capability gap traditional halfton full heavyduty pickup titan titan cover cent fullsize truck market nissan titan darren begg driving important nissan launching fullfrontal attack big three pickup hegemony first cummin diesel powered titan now halfton time japanese manufacturer attacked detroit vestige outright superiority significance underestimated coming late summer buy yes people excited cummin dieselpowered titan game changer nissan truck lineup david booth toyota prius prime toyota prius prime darren begg driving love child regular prius liftback hybrid mirai fuel cell vehicle toyota prius prime followup outgoing prius plugin gaselectric hybrid apparently prime larger kwh battery pack estimated electric range outgoing prius plugin kilometre estimate full tank gas toyota claim prius prime score classleading estimated total driving range lower litre equivalent kilometre rating cent reduction fuel consumption predecessor matter toyota leader hybrid technology prius prime range short kilometre estimate main rival chevrolet volt plugin coming expect toyota prius prime sale fall buy usual plugin electric car youll homework prius prime premium pricing inconvenience plug fit driving budget lifestyle john leblanc subaru impreza itafter concept car diagram subaru global platform sit underneath fifthgeneration subaru impreza fourdoor sedan hatchback made world debut yorkwhile exterior move style needle current fourthgen model that impreza promise roomier deliver significantly higher level driving pleasure agility crash protection ride comfortthe imprezas updated litre fourcylinder engine directinjection time and enhancement boost horsepower cvt stepped gear new subaru upping imprezas hightech quotient automaker eyesight system withadaptive cruise control automatic precollision brakinglane departure warninglane assistblind spot detection rear cross traffic alert compact impreza subaru starlink inch touchscreen multimedia system dont step sportier wrx model which debut impreza sport model great compromise visually theyll inch wheel mechanically sport suspension active torque vectoring andof courseevery impreza standard subarus symmetrical allwheel drive mattersubaru build recent surge sale canada imprezaand eventual wrx crosstrek forester model subaru global platformis expected big part plan made time ever comingexpect impreza rolledout canadian showroom year buy itwhile improvement found conservatively styled skin impreza measurably improved way john leblanc toyota corolla toyota corolla darren begg driving anniversary edition toyotas corolla unique theyve sold million year nonetheless significant corolla full complement toyotas safety sense technology precollision system pedestrian detection function dynamic radar cruise control lane departure alert steering assist function automatic beam standard feature include biled headlamp model multiled standard xse display audio new uncommonly for corolla least front grille wider choice colour important comment million them upgrade earthshattering but remember corolla world bestselling automobile time corolla new important new coming corolla september buy not has north american corolla ownership passage toyota highlander toyota highlander darren begg driving ita midcycle refresh generation toyotas midsize threerow crossover redesigned updated version remain front allwheeldrive seating passenger exterior look powerful fuelefficient directinjected technology eightspeed automatic transmission sportier model unique aluminium alloy wheel tuned suspension sportier ride dark paint front grille toyotas safety sense new multifeature advanced safety package including automated precollision braking standard fare awd highlander hybrid continue offered matterlook nip tuck highlander foundation longawaited lexus version due year coming revised toyota highlander showroom year buy itthere arelot choice segment buyer cheque honda pilot ford explorer john leblanc mini cooper clubman all mini cooper clubman all darren begg driving mini cooper clubman all darren begg driving itafter experiment firstgeneration mini clubman conventional functional instead older model three door clubman buyer mini driving experience carry briefcase ride debut all that minispeak allwheel drive make clubman attractive ondemand awd system fully electronic targeting engine power thefront wheel duringnormal drivingbut dole power rear needed matterawd canadian winter driving cmon brainer right comingfor now minis all technology offered topoftheline horsepower clubman cooper order awd mini station waggon now delivery starting april buy ituntil larger secondgeneration countryman arrive clubman all roomiest vehicle mini badge traction wheel john leblanc chevrolet sonic chevrolet sonic david booth driving itreplacing aveo chevrolet subcompact offering frontwheeldrive fivepassenger fourdoor sonic sedan hatchback makeover addition revised styling make tiny car newer chevy such malibu sonic big car goody gms latest inch mylink touchscreen infotainment system including apple carplay android auto compatibility lte wifi hotspot heated steering wheel segmentfirst power driver seat matterdespite low fuel price spurring crossover suv truck sale automaker sell small car sonic lower corporate average fuel economy cafe number comingthe sonic sale fall buy itthe luxury infotainment feature sonic competitive class car competing buyer prefer drive larger vehicle john leblanc kia cadenza kia cadenza darren begg driving year debut kia redesigning frontwheeldrive cadenza large sedan attempt people kia fourdoor youll styling body stronger lighter rigid enjoyable driving experience inside big kia sedan interior visually widened wraparound dashboard flow door panel power kias fwd eightspeed automatic transmission new advanced smart cruise control stopandgo functionality kia cadenza darren begg driving matter good question mere cadenzas sold canada evidence sisterbrand hyundai doesnt bother importing frontwheeldrive fivepassenger fourdoor cadenza sedan platformmate azera canada coming secondgeneration cadenza set onsale late pricing announced closer vehicle launch date buy largeish frontwheeldrive midszie sedan korea kia cadenza good get john leblanc volkswagen golf alltrack volkswagen golf alltrack darren begg driving longawaited allwheeldrive version critically acclaimed volkswagen golf sportwagon finally shown north american production form dubbed golf alltrack grippy compact fourdoor waggon powertrain horsepower litre gas mated sixspeed automatic transmission diesel fan eurospec alltrack tdi drove germany fall coming anytime soon matter distract customer german automaker ongoing deiselgate scandal good thing canadian fond frontdrive golf sportwagon offering traction wheel expand appeal diesel power volkswagen golf alltrack darren begg driving coming expect volkswagen golf alltrack sale fall buy expensive roomier funtodrive typical small crossover volkswagen tiguan golf alltrack make great antisuv statement sophisticated buyer john leblanc jeep grand cherokee trailhawk jeep grand cherokee trailhawk graeme fletcher driving ","m_szGeo1":"United States","m_szSourceType":"source_news","m_szSrcUrl":"http://driving.ca/toyota/auto-shows/new-york-auto-show/everyday-drivers-mini-goes-awd-toyota-beefs-up-the-prius","m_Places":["New York","Most","Detroit","Toyota","Subaru","United States","Canada","Corolla","Look","Cooper","Malibu","Korea","Germany"],"m_People":["David Booth","John Leblanc","Darren Begg","Steve Rhind","Nissan Canada","Graeme Fletcher"],"m_Companies":["Nissan","Gap","Cummins","Diesel","Subaru Impreza","Subaru Starlink","Toyota Highlander","Highlander","Apple","Seat","Hyundai","Volkswagen"],"m_BiGrams":["darren begg","begg driving","john leblanc","prius prime","golf alltrack","volkswagen golf","toyota prius","clubman all","kia cadenza","david booth","nissan titan","sale fall","fall buy","cruise control","toyota highlander","automatic transmission","mini cooper","cooper clubman"],"m_TriGrams":["darren begg driving","toyota prius prime","volkswagen golf alltrack","sale fall buy","mini cooper clubman","cooper clubman all"],"m_SocialTags":[],"m_Topics":[],"m_Industry":[],"m_Technology":[],"m_BiCnt":[11,11,8,7,6,5,4,4,4,3,3,3,3,3,3,3,3,3],"m_TriCnt":[11,4,4,3,3,3],"m_iDocBodyWordCnt":1048}
