{"m_szDocID":"614322","m_szDocTitle":"Toyota Mirai manga: hydrogen fuel cell beats electric cars, plug-in hybrids","m_szYear":"2016","m_szDocSumamry":"Toyota Mirai manga: hydrogen fuel cell beats electric cars, plug-in hybrids Email This Page To (separate emails with commas) Message (optional) Your email was sent successfully. Close 3,588 views Mar 25, 2016 Japanese manga comic about Toyota Mirai [from Motorfan: New Model Special Edition issue 502] Enlarge Photo Manga are comics created in Japan, conforming to a style set more than 100 years ago and still very much a part of popular culture. While they may look like no more than light entertainment, they're widely read by people of all agesâ€”and sometimes used to market commercial products. A","m_szDocBody":"toyota mirai manga hydrogen fuel cell beat electric car plugin hybrid separate email commas message optional successfully close view japanese manga comic toyota mirai from motorfan model special edition enlarge photo manga comic created japan conforming style set year ago part popular culture light entertainment widely read people agesand market commercial product year ago explain toyota mirai hydrogen fuelcell car launched home market japan excerpt japanese auto aficionado magazine motorfan model special edition carry date motorfan model special edition covering toyota mirai hydrogen fuelcell vehicle misprint throwback west ancient rome japanese company date based year current emperor reign apply publication dating system hightech component too motorfan nmse devote upcoming vehicle mirai tucked page introductory photos rendering specification iswhat elsea short manga chronicle storey fictionalised mirai early adopter cheque out toyota mirai spawning entire family hydrogen fuel cell model pleased translate reader merriment heroic patience mrs klippenstein editor note reproduced section fourpage comic doctrine fair use motorfan nmse link entire manga character mirai comic adapted doraemon popular kid comic book television show merchandising empire comic doraemona robot cat centurybefriend nobita hapless young boy whos occasionally teased rich kid suneo japanese manga comic toyota mirai from motorfan model special edition enlarge photo comic mizuemona robotic thermos bottlehelp sobita hapless middleaged man whos teased nextdoor neighbour soneo reminder japanese comic read righttoleft toptobottom basically mirror image read english comic book note recognisable mirai triumph batteryelectric nissan leaf rangeextended bmw rex and surprisingly toyotas prius plugin hybrid effort translation entire manga ","m_szGeo1":"Japan","m_szSourceType":"source_news","m_szSrcUrl":"http://www.greencarreports.com/news/1103074_toyota-mirai-manga-hydrogen-fuel-cell-beats-electric-cars-plug-in-hybrids","m_Places":["Toyota","Japan","Rome","United States"],"m_People":["Mirai Manga","Klippenstein"],"m_Companies":["Mirror Image","Bmw","I3"],"m_BiGrams":["toyota mirai","motorfan model","model special","special edition","manga comic"],"m_TriGrams":["motorfan model special","model special edition"],"m_SocialTags":[],"m_Topics":[],"m_Industry":[],"m_Technology":[],"m_BiCnt":[6,4,4,4,3],"m_TriCnt":[4,4],"m_iDocBodyWordCnt":247}
