{"m_szDocID":"617624","m_szDocTitle":"Fuel-cell concepts from 50 years ago: famed designer Brooks Stevens","m_szYear":"2016","m_szDocSumamry":"Fuel-cell concepts from 50 years ago: famed designer Brooks Stevens Email This Page To (separate emails with commas) Message (optional) Your email was sent successfully. Close 2,086 views Apr 8, 2016 Follow John Enlarge Photo Most car buyers would be hard-pressed to name a single automobile designer working today. But it wasn't always that way: names like Raymond Loewy and Harley Earl were known well outside the design studios where they created the \"cars of tomorrow.\" A half-century-old concept from designer Brooks Stevens underscores the futuristic nature of hydrogen fuel-cell propulsion, bo","m_szDocBody":"fuelcell concept year ago famed designer brook steven separate email commas message optional successfully close view follow john enlarge photo car buyer hardpressed single automobile designer working today way name raymond loewy harley earl design studios created car tomorrow halfcenturyold concept designer brook steven underscore futuristic nature hydrogen fuelcell propulsion today miss toyota mirai manga hydrogen fuel cell beat electric car plugin hybrid hemming motor new utopia concept created steven pioneered numerous ideas advanced auto manufacturing propulsion envisioned vehicle decade later innovation elimination redundant stamping door panel leftfront rightrear door rightfront leftrear hood deck lid similarly interchangeable single horizontal headlight bar taillamp housing red len swapped utopia waggon concept designer brook steven image courtesy milwaukee art museum utopia waggon concept featured sliding roof panel made production studebaker wagonaire waggon briefly revived gmc envoy xuv sport utility vehicle hydrogen fuelcell powertrain utopian utopias feature steven believed future fuel cell compact powertrain giving greater flexibility provide space passenger cargo see toyota mirai drive hydrogen fuelcell sedan dec immediately clear required highpressure hydrogen tank located utopia design steven return idea hydrogen power gondola terra motor home bank fuel cell provide power electric motor wheel vehicle pair tank located transversely floor terra gondola fuelcell powertrain designer brook steven image courtesy milwaukee art museum enlarge photo optimistic licence plate vehicle turned differently steven imagined creation environmental protection agency led regulation vehicle emission host regulation national highway traffic safety administration crash safety cheque out honda clarity fuel cell priced around launch end year car period referred malaise era vehicle cookiecutter styling strangled performance abysmal assembly quality zeroemission electric propulsion provided electricity hydrogen fuel cell futuristic dream today toyota mirai quick drive portland photo doug berger enlarge photo fewer fuelcell car world today close million plugin vehicle batteryelectric plugin hybrid tempting designer steven viewed appearance toyota mirai production fuelcell car world ","m_szGeo1":"","m_szSourceType":"source_news","m_szSrcUrl":"http://www.greencarreports.com/news/1103311_fuel-cell-concepts-from-50-years-ago-famed-designer-brooks-stevens","m_Places":["Most","Toyota","Portland"],"m_People":["Brooks Stevens","Raymond Loewy","Harley Earl","Mirai Manga","Doug Berger"],"m_Companies":["Hemmings Motor News","Utopia","Milwaukee Art Museum","Environmental Protection Agency","National Highway Traffic Safety Administration","Honda"],"m_BiGrams":["fuel cell","designer brook","brook steven","toyota mirai","enlarge photo","hydrogen fuelcell"],"m_TriGrams":["designer brook steven"],"m_SocialTags":[],"m_Topics":[],"m_Industry":[],"m_Technology":[],"m_BiCnt":[5,4,4,4,3,3],"m_TriCnt":[4],"m_iDocBodyWordCnt":304}
