{"m_szDocID":"617644","m_szDocTitle":"BeeZero fuel cell car sharing service by Hyundai and Linde","m_szYear":"2016","m_szDocSumamry":"Posted on 8 Apr 2016 by Tim Brown 50 Hyundai ix35 Fuel Cell power the new BeeZero car sharing programme by The Linde Group launching this summer in Munich - image courtesy of Hyundai. Fuel cell vehicles received a boost this week thanks to a new partnership between German engineering group, Linde, and South Korean car company, Hyundai. The two companies have joined forces to create BeeZero, the world’s first fuel cell electric vehicle (FCEV) car sharing service , with Linde’s newly founded subsidiary, Linde Hydrogen Concepts, to operate the service from this summer in Munich, Germany. “Bavaria","m_szDocBody":"posted tim brown hyundai fuel cell power beezero car sharing programme linde launching summer munich image courtesy hyundai fuel cell vehicle received boost week partnership german engineering group linde south korean car company hyundai company joined force create beezero world fuel cell electric vehicle fcev car sharing service linde newly founded subsidiary linde hydrogen concept operatethe service fromthis summer munich germany bavaria leader hydrogen technology beezero constitute largescale deployment hydrogen fuel cell technology carsharing industry ilse aigner economic energy minister bavaria hyundai provide vehicle beezero hyundai motor fuel cell vehicle star beezero fuel cell electric vehicle made public use beezero car sharing offer pioneering sustainable mobility thomas schmid chief operating officer hyundai motor europe featuring hyundai fuel cell beezero car sharing service hydrogenpowered zeroemission car offer comfortable reliable transportation public everyday need expect gain valuable information daytoday fleet operation develop hydrogen technology expand hydrogen infrastructure christian bruch member executive board linde beezero synergise mobility trend gaining lot ground moment car sharing emission and bring benefit fuel cell technology wider potential user mileson single tank beezero car sharing service run zonebased model fleet fifty fuel cell car munich city centre areas schwabing haidhausen glockenbachviertel conventional car sharing service car easily booked online smartphone app hyundai fuel cell travel kilometre single tank making ideal longer journey too bavarian lake mountain example short trip city hydrogen fuel beezero sourced sustainable production processe making completely carbon neutral interest live munich thinking visiting year drive fcev move emission interest hyundai offer full spectrum fuel cell world massproduced commercially fuel cell electric vehicle fcev hyundai fuel cell suvs european road country fcevs manufacturer combined ioniq launched year europe hyundai introduce world car offer hybrid plugin hybrid allelectric powertrain single body type fuel cell electric vehicle hybrid plugin hybrid model sold world hyundai motor pioneered electric powertrain thomas schmid chief operating officer hyundai motor europe now launch ioniq lead car brand hybrid plugin hybrid electric fuel cell vehicle production making low zeroemission car accessible everyone read ","m_szGeo1":"Germany","m_szSourceType":"source_news","m_szSrcUrl":"http://www.themanufacturer.com/articles/hyundai-and-linde-launch-beezero-the-worlds-first-fuel-cell-car-sharing-service/","m_Places":["Munich","Linde","Germany","Europe","Most"],"m_People":["Ilse Aigner","Thomas A. Schmid","Dr Christian Bruch"],"m_Companies":["Hyundai","Linde Group","Linde Ag"],"m_BiGrams":["fuel cell","car sharing","hyundai fuel","beezero car","cell electric","electric vehicle","sharing service","hyundai motor","cell vehicle","hybrid plugin","plugin hybrid"],"m_TriGrams":["hyundai fuel cell","beezero car sharing","fuel cell electric","cell electric vehicle","car sharing service","fuel cell vehicle"],"m_SocialTags":[],"m_Topics":[],"m_Industry":[],"m_Technology":[],"m_BiCnt":[15,7,5,4,4,4,4,4,3,3,3],"m_TriCnt":[5,4,4,4,4,3],"m_iDocBodyWordCnt":329}
