{"m_szDocID":"617754","m_szDocTitle":"The world's first fuel cell car sharing program launches in Germany","m_szYear":"2016","m_szDocSumamry":"The world's first fuel cell car sharing program launches in Germany BeeZero to launch in Munich with 50 Hyundai Tucson Fuel Cell Vehicles. Hyundai Tucson Fuel Cell in BeeZero Hydrogen Carsharing Program Beezero Hyundai Tucson Fuel Cell Image Credit: Hyundai Beezero Hyundai Tucson Fuel Cell Beezero Hyundai Tucson Fuel Cell Image Credit: Hyundai Beezero Hyundai Tucson Fuel Cell Beezero Hyundai Tucson Fuel Cell Image Credit: Hyundai Beezero Hyundai Tucson Fuel Cell Beezero Hyundai Tucson Fuel Cell Image Credit: Hyundai Beezero Hyundai Tucson Fuel Cell Beezero Hyundai Tucson Fuel Cell Image Credit","m_szDocBody":"world fuel cell car sharing programme launches germany beezero launch munich hyundai tucson fuel cell vehicle hyundai tucson fuel cell beezero hydrogen carsharing programme beezero hyundai tucson fuel cell image credit hyundai beezero hyundai tucson fuel cell beezero hyundai tucson fuel cell image credit hyundai beezero hyundai tucson fuel cell beezero hyundai tucson fuel cell image credit hyundai beezero hyundai tucson fuel cell beezero hyundai tucson fuel cell image credit hyundai beezero hyundai tucson fuel cell beezero hyundai tucson fuel cell image credit hyundai beezero hyundai tucson fuel cell beezero hyundai tucson fuel cell image credit hyundai john beltz snyder evs increasingly mainstream found natural home carsharing service blueindy left mark indianapolis ford testing sharing programme japan china share programme pop electric carsharing helping lowincome neighbourhood los angele model continue emerge flip side cargo made new recently pulled evs fleet san diego absent carsharing scene though hydrogen fuel cell vehicle changing munich germany industrial gase company think hydrogen linde launched beezero carsharing service comprised completely fuel cell vehicle fleet made hyundai tucson fuel cell crossover called fuel cell europe hydrogenpowered carsharing service world bavaria hub hydrogen research technology beezero subsidiary linde begin public service summer fleet tucson fuel cell offer user ondemand zeroemission driving range limitation battery electric vehicle hpowered hyundais travel mile single tank offering flexibility travel surrounding areas user visit nearby lake mountain room cart gear them driver reserve car online smartphone app vehicle zone city munich hydrogen fuel fleet linde create sustainable source promising carbonneutral voyage public hydrogenpowered mobility linde learn experience expect gain valuable information daytoday fleet operation develop hydrogen technology expand hydrogen infrastructure linde executive board member christian bruch beezero synergise mobility trend gaining lot ground moment car sharing emission bring benefit fuel cell technology wider potential user read press release below related video show full hero beezero hyundai motor power world fuel cell car sharing service hyundai fuel cell vehicle power beezero car sharing programme linde launching summer munich hyundai fuel cell world massproduced commercially fuel cell electric vehicle offer impressive range zeroemission mobility hydrogen fuel hyundai motor leading fuel cell electric vehicle roll europe strengthen position electric mobility provider offering hybrid plugin hybrid electric fuel cell vehicle wycombe hyundai motor fuel cell star world fuel cell powered zeroemission car sharing service beezero launched munich germany summer beezero run newly founded subsidiary linde group feature hyundai fuel cell electric vehicle public use the beezero car sharing offer pioneering sustainable mobility thomas schmid chief operating officer hyundai motor europe featuring hyundai fuel cell beezero car sharing service hydrogenpowered zeroemission car offer comfortable reliable transportation public everyday need expect gain valuable information daytoday fleet operation develop hydrogen technology expand hydrogen infrastructure christian bruch member executive board linde beezero synergise mobility trend gaining lot ground moment car sharing emission and bring benefit fuel cell technology wider potential user kilometre single tank beezero car sharing service run zonebased model fleet fifty fuel cell car munich city centre areas schwabing haidhausen glockenbachviertel conventional car sharing service car easily booked online smartphone app hyundai fuel cell travel kilometre single tank making ideal longer journey too bavarian lake mountain example short trip city hydrogen fuel beezero sourced sustainable production processe making completely carbon neutral leader electric mobility fuel cell world massproduced commercially fuel cell electric vehicle fcev hyundai fuel cell suvs european road country fcevs manufacturer combined ioniq launched year hyundai introduce world car offer hybrid plugin hybrid allelectric powertrain single body type with fuel cell electric vehicle hybrid plugin hybrid model sold world hyundai motor pioneered electric powertrain thomas schmid chief operating officer hyundai motor europe now launch ioniq lead car brand hybrid plugin hybrid electric fuel cell vehicle production making low zeroemission car accessible everyone ","m_szGeo1":"Germany","m_szSourceType":"source_news","m_szSrcUrl":"http://www.autoblog.com/2016/04/10/world-first-fuel-cell-carsharing-program/","m_Places":["Germany","Munich","Indianapolis","Japan","China","Los Angeles","San Diego","Linde","Europe","Tucson","Wycombe"],"m_People":["John Beltz Snyder","Christian Bruch","Thomas A. Schmid","Dr Christian Bruch"],"m_Companies":["Hyundai Tucson","Hyundai","Hero","Linde Group","Linde Ag"],"m_BiGrams":["fuel cell","tucson fuel","hyundai tucson","beezero hyundai","car sharing","cell beezero","cell vehicle","cell image","image credit","credit hyundai","electric vehicle","hyundai motor","hyundai fuel","hyundai beezero","sharing service","cell electric","hydrogen fuel","beezero car","hybrid plugin","plugin hybrid","world fuel","cell car","sharing programme","carsharing service","single tank","zeroemission car"],"m_TriGrams":["tucson fuel cell","hyundai tucson fuel","fuel cell beezero","fuel cell vehicle","beezero hyundai tucson","fuel cell image","cell image credit","image credit hyundai","hyundai fuel cell","credit hyundai beezero","cell beezero hyundai","car sharing service","fuel cell electric","cell electric vehicle","beezero car sharing","world fuel cell","fuel cell car"],"m_SocialTags":[],"m_Topics":[],"m_Industry":[],"m_Technology":[],"m_BiCnt":[38,15,14,12,10,7,6,6,6,6,6,6,6,5,5,5,4,4,4,4,3,3,3,3,3,3],"m_TriCnt":[15,9,7,6,6,6,6,6,6,5,5,5,5,5,4,3,3],"m_iDocBodyWordCnt":616}
