{"m_szDocID":"617736","m_szDocTitle":"Dutch politicians move to ban gas, diesel cars by 2025 - Roadshow","m_szYear":"2016","m_szDocSumamry":"Dutch politicians move to ban gas, diesel cars by 2025 Towing with a Tesla not as bad as you might think Dutch politicians move to ban gas, diesel cars by 2025 It may not have a snowball's chance in hell at becoming law, but it's likely that we'll be seeing more proposals like these in the future. Andrew Krok Cars are Andrew's jam, as is strawberry. He started his auto-industry career working as a photographer and social media coordinator for Fluid MotorUnion, a prominent aftermarket parts fabrication garage for late-model European vehicles. That led to a job writing freelance features for \"To","m_szDocBody":"dutch politician move ban gas diesel car towing tesla bad dutch politician move ban gas diesel car snowball chance hell law proposal future andrew krok car andrew jam strawberry started autoindustry career working photographer social media coordinator fluid motorunion prominent aftermarket part fabrication garage latemodel european vehicle led job writing freelance feature total porsche magazine recent job prior cnet senior writer webcarzcom helped tweak develop buyingandselling site editorial department bring today day buy dream day full bio dutch politician move ban gas diesel car share dutch politician move ban gas diesel car enlarge image gas diesel ban batteryelectric hydrogen fuelcell vehicle like honda clarity here allowed bear mind car sale antuan reach time selfdriving car ferrying around running advanced electric powertrain good time talk future gaspowered car time stop lawmaker netherland ban gas dieselpowered car member dutch labour party pvda drafted proposal ban sale gasoline dieselpowered vehicle idea provide sufficient time fuel cell electric vehicle commonplace proposed hefty government investment autonomous vehicle partly reduce nasty traffic jam course involve load wishful thinking fact digital trend wrote lawmaker party called proposition overambitious unrealistic the wishful thinking headless chicken pvda party member shied idea passing dutch parliament lower house board evs yet send voter running early any country put ideas motion infrastructure finally coming around hydrogen sorely lacking giant car market usa single projection put market share percent mind nearing percent turn person idea literally forcing interesting idea evs fuel cell vehicle welltowheel figure gas vehicle autonomous vehicle chance send accident rate basement concept slowly proving road decade massive shift public opinion infrastructure fleshed out ","m_szGeo1":"United States","m_szSourceType":"source_news","m_szSrcUrl":"http://www.cnet.com/roadshow/news/dutch-politicians-move-to-ban-gas-diesel-cars-by-2025/","m_Places":["Tesla","United States"],"m_People":["Andrew Krok","Antuan Goodwin"],"m_Companies":["Diesel","Cnet","Honda","Dutch Labor Party"],"m_BiGrams":["ban gas","gas diesel","dutch politician","politician move","move ban","diesel car"],"m_TriGrams":["dutch politician move","politician move ban","move ban gas","ban gas diesel","gas diesel car"],"m_SocialTags":[],"m_Topics":[],"m_Industry":[],"m_Technology":[],"m_BiCnt":[5,5,4,4,4,4],"m_TriCnt":[4,4,4,4,4],"m_iDocBodyWordCnt":263}
