{"m_szDocID":"618007","m_szDocTitle":"Hydrogen fuel cars are on the market | Examiner.com","m_szYear":"2016","m_szDocSumamry":"Hydrogen fuel cars are on the market Use your key for the next article Hydrogen Fuel cell schematic US Department of Energy Alternative Fuels Data Center Hydrogen powered cars, called fuel cell electric vehicles (FCEVs), are already on the market. But the hydrogen infrastructure to fuel them is still in the early stages of deployment. Fuel cell electric vehicles (FCEVs) are powered by hydrogen and have the potential to completely revolutionize our entire transportation system. FCEVs are more efficient than conventional internal combustion engine vehicles and they produce no harmful tailpipe ex","m_szDocBody":"hydrogen fuel car market key hydrogen fuel cell schematic department energy alternative fuel data centre hydrogen powered car called fuel cell electric vehicle fcevs market hydrogen infrastructure fuel early stage deployment fuel cell electric vehicle fcevs powered hydrogen potential completely revolutionise entire transportation system fcevs efficient conventional internal combustion engine vehicle produce harmful tailpipe exhaust instead hydrogen powered vehicle emit water vapour warm air fuel cell electric vehicle electricity power motor located vehicle wheel fuel cell vehicle produce primary electricity fuel cell powered hydrogen drawing electricity battery common type fuel cell fcevs polymer electrolyte membrane pem fuel cell where electrolyte membrane sandwiched positive electrode cathode negative electrode anode hydrogen introduced anode oxygen from air introduced cathode hydrogen molecule break proton electron electrochemical reaction fuel cell catalyst proton travel membrane cathode electron forced travel external circuit provide power car electron recombine proton cathode side proton electron oxygen molecule combine form water newest entry fcev market toyota mirai car driver published review hydrogen powered car japanese mirai mean future mirai future motoring run solely hydrogen emission water car driver mirai introduced late initially sold leased california infrastructure hydrogen fueling exist mirais range mile refuelling minute lure customer toyota including fuel year ownership mirais powertrain warranty allay earlyadopter concern issue car driver opportunity review rank hydrogen powered car market mirai rank sixth hydrogen powered car chevrolet spark price volkswagen egolf price ford focus electric price kia soul price hyundai tucson fuel cell price toyota mirai price nissan leaf price fiate price chevrolet spark market general motor spark feature innovative electric propulsion system drive unit paired lithiumion battery lbft torque electric vehicle bestinclass volkswagen egolf egolf golf gas golf drive one too plug charge enjoy solid funtodrive ride love ford focus electric market ford avoiding gas station fun youre driving focus electric focus electric gas oil emission ford offer charging option standard charging cord home charging station kia introduced soul kias massmarket electric vehicle estimated highway driving mile city driving mile hyundai tucson fuel cell sold california location nationwide including rochester york nissan leaf sold rochester nissan dealer hydrogen infrastructure fuel fcevs place too fiate estimated mpge highway rating epa estimated fuel consumption rate kilowatt hour kwh mile state california honda hydrogen powered car market didnt make car drive list honda bill fcx clarity fuel cell electric vehicle fcev zeroemission hydrogen powered car zeroemission electric vehicle future reality today advertising mirai toyota say wait beginning age hydrogen powered car side storey hydrogen fcevs from now hydrogen produced natural gas hydrocarbon steam reforming hydrogen tied fossil fuel hydrogen produced electrolysis water electrolysis process electricity split water hydrogen oxygen fuel produce electricity drawback growth hydrogen powered car market add lack infrastructure short range today hydrogen powered car drawback hydrogen powered car efficient gasoline powered automobile future bright fcevs ","m_szGeo1":"United States","m_szSourceType":"source_news","m_szSrcUrl":"http://www.examiner.com/article/hydrogen-fuel-cars-are-on-the-market","m_Places":["Toyota","California","Rochester, New York","Rochester"],"m_People":["Mirai Toyota"],"m_Companies":["Us Department Of Energy","Data Center","Car And Driver","Volkswagen","Hyundai Tucson","General Motors","Volt","Nationwide","Epa","Honda"],"m_BiGrams":["fuel cell","hydrogen powered","powered car","electric vehicle","car market","cell electric","focus electric","car driver"],"m_TriGrams":["hydrogen powered car","fuel cell electric","cell electric vehicle","powered car market"],"m_SocialTags":[],"m_Topics":[],"m_Industry":[],"m_Technology":[],"m_BiCnt":[12,11,10,7,4,4,4,3],"m_TriCnt":[10,4,4,3],"m_iDocBodyWordCnt":462}
