{"m_szDocID":"619778","m_szDocTitle":"Rapid Progress for Electric Vehicles?","m_szYear":"2016","m_szDocSumamry":"Rapid Progress for Electric Vehicles? April 18, 2016 by David Hone Leave a Comment The last few weeks have brought great excitement for electric vehicle (EV) enthusiasts with the announcement of the Tesla Model 3 and the subsequent filling of its order book with over 250,000 vehicles. With costs coming down and vehicle range improving, there appears to be real consumer interest in EVs, including battery electric, plug-in hybrid and hydrogen fuel cell types. The International Energy Agency has been following the development of EVs for some time now and an excellent info-graphic is available wit","m_szDocBody":"rapid progress electric vehicle david hone leave comment week brought great excitement electric vehicle enthusiast announcement tesla model subsequent filling order book vehicle cost coming vehicle range improving appear real consumer interest evs including battery electric plugin hybrid hydrogen fuel cell type international energy agency development evs time excellent infographic variety deployment statistic period including quickly evs deploy align ambition paris agreement passenger vehicle sector reach direct emission early half century outcome required track shot year growth rate range annum typical technology small base base increase year year percentage growth slow quickly absolute production continue increase goal deployment reach installed base million vehicle global fleet target set electric vehicle initiative clean energy ministerial global minister forum promote policy share practise accelerate global transition clean energy initiative seek facilitate global deployment evs including plugin hybrid electric vehicle fuel cell vehicle end global stock heading million year produce million car require year year growth rate annum resulting additional production million vehicle annum reach total annual production million vehicle annum itself iea infographic production annum growth rate continue additional production surpassing million annum balance global stock million vehicle total expected fleet time absolute annual growth slowing influenced outlook see production approaching global passenger vehicle production assuming consumer resistance evs love roar finely tuned powered internal combustion engine ice production evs completely eclipse ice vehicle remain generational timespan turn entire fleet europe age distribution vehicle broad shouldnt expect ice vehicle disappear overnight average age rising year europe decade wide distribution netherland passenger vehicle fleet year old year poland putting single chart rapid accelerated switch ice picture below sake calculation assumed global fleet topping billion vehicle number highly uncertain instance evs beginning make progress market autonomous vehicle possibly offering completely model car ownership fewer car global fleet prospect smaller market start send ripple entire investment chain slowing uptake evs considerably equally personal motoring progresse rapidly developing country fleet larger half century argue older fleet ice vehicle remaining road longer simply fleet growth existing production total million vehicle annum maximum ice stock isnt reached topping billion vehicle million today ice number return current level mid decline low level unknown factor supply chain current battery technology call lithium price month risen chinese lithium hydroxide price risen year market observer noted volatility uncertainty surrounding tesla appearing street model manufacturer shown year ahead interesting passenger vehicle market scott edward anderson consultant blogger media commentator blog green sceptic christine hertzog consultant author professional explainer focused smart grid elias hinckley strategic advisor energy finance energy policy investor energy company government gary hunt gary executiveinresidence deloitte investment extensive experience energy utility industry jesse jenkin graduate student researcher mit expertise energy technology policy innovation jim pierobon help trade government agency company communicate cleaner energy solution geoffrey style managing director gsw strategy group llc awardwinning blogger featured contributor ","m_szGeo1":"United Kingdom","m_szSourceType":"source_industry","m_szSrcUrl":"http://www.theenergycollective.com/davidhone/2376473/rapid-progress-for-electric-vehicles?utm_source=feedburner&utm_medium=feed&utm_campaign=The+Energy+Collective+%28all+posts%29","m_Places":["Tesla","Paris","Europe","Gary"],"m_People":["Scott Edward Anderson","Christine Hertzog","Elias Hinckley","Hunt Gary","Jesse Jenkins","Jim Pierobon"],"m_Companies":["Rapid","International Energy Agency","Target","2020s","Iea","Deloitte","Strategy Group, Llc"],"m_BiGrams":["million vehicle","electric vehicle","passenger vehicle","growth rate","global fleet","vehicle annum","ice vehicle"],"m_TriGrams":["million vehicle annum"],"m_SocialTags":[],"m_Topics":[],"m_Industry":[],"m_Technology":[],"m_BiCnt":[5,4,4,3,3,3,3],"m_TriCnt":[3],"m_iDocBodyWordCnt":464}
