{"m_szDocID":"628953","m_szDocTitle":"Fuel Economy Standards Won't Be Met Without 16% Electric Car Market Share By 2020 (World Energy Council) | CleanTechnica","m_szYear":"2016","m_szDocSumamry":"textArticle -------------------- Published on June 30th, 2016 | by James Ayre 0 Fuel Economy Standards Won’t Be Met Without 16% Electric Car Market Share By 2020 (World Energy Council) June 30th, 2016 by James Ayre   If the fuel-economy standards set by many regulators around the world are to be achieved, then electric vehicle market share will need to rise to 16% by the year 2020, according to a new report from the UN-accredited global energy body known as the World Energy Council. As it stands now, of course, electric vehicles (EVs) and plug-in hybrids (PHEVs) comprise less than 1% share of ","m_szDocBody":"published jame ayre fuel economy standard wont met electric car market share world energy council jame ayre fueleconomy standard set regulator world achieved electric vehicle market share rise year report unaccredited global energy body world energy council stand now course electric vehicle evs plugin hybrid phevs comprise share global passenger vehicle automotive market report make clear though electric vehicle technology considered central part policy strategy based lowering transportation sector emission provide background report china set fueleconomy improvement target time period unlikely analyst target achieved solely improvement internal combustion engine ice vehicle design change gap achieved solely ice technology improvement requirement dubbed gap report note gap million vehicle estimated passenger vehicle sale european union million million china projected sale managing director accenture strategy stuart solomon commented close emission gap widespread adoption evs utility play critical role ensure reliable electricity supply added pressure plugging evs stressed grid network making added demand electricity power evs increasingly clean power source primary report include industry recommendation automanufacturer respond regulatory pressure shift product portfolio avoid material penalty additionally opportunity vehicle manufacturer utility electricity provider partner deliver superior proposition consumer year market individually add terrawatthour twh european union twh twh china policymaker recommendation policymaker examine proposed fuel requirement matched working industry financial operational incentive order achieve desired improvement emission consumer recommendation consumer provide feedback regulator manufacturer evaluating economic environmental benefit evs alongside alternative online transportation method report found date hottest cleantech new subscribing free cleantech newsletter eye sectorspecific new also free solar energy newsletter electric vehicle newsletter wind energy newsletter tag china europe fuel economy fuel economy standard world energy council jame ayre background predominantly geopolitic history obsessive interest pretty everything early life spent imperial free city dortmund jame river ruhr cofbuokheim attended university astnide briefly considered entering coal mining business write living broad variety subject ranging science politic military history renewable energy follow work google related post ","m_szGeo1":"United States","m_szSourceType":"source_industry","m_szSrcUrl":"http://cleantechnica.com/2016/06/30/fuel-economy-standards-wont-met-without-16-electric-car-market-share-2020-world-energy-council/?utm_source=feedburner&utm_medium=feed&utm_campaign=Feed%3A+IM-cleantechnica+%28CleanTechnica%29","m_Places":["United States","China","Europe","Free City","Dortmund"],"m_People":["James Ayre","Stuart Solomon"],"m_Companies":["2020","Energy Council","Un","World Energy Council","Eu","The Gap","Gap","European Union","Accenture","University Of Astnide","Google"],"m_BiGrams":["electric vehicle","jame ayre","fuel economy","world energy","energy council"],"m_TriGrams":["world energy council"],"m_SocialTags":[],"m_Topics":[],"m_Industry":[],"m_Technology":[],"m_BiCnt":[4,3,3,3,3],"m_TriCnt":[3],"m_iDocBodyWordCnt":311}
