{"m_szDocID":"635323","m_szDocTitle":"Cost Of Solar Systems From SolarCity vs Sunrun & Vivint Solar, + Cost Per Watt Of Solar Sales/Acquisition | CleanTechnica","m_szYear":"2016","m_szDocSumamry":"textArticle -------------------- Cost Of Solar Systems From SolarCity vs Sunrun & Vivint Solar, + Cost Per Watt Of Solar Sales/Acquisition July 19th, 2016 by Zachary Shahan   We’ve written a lot about average solar power prices, especially in the US — utility-scale solar power prices and rooftop solar power prices. But we’ve seldom found or teased out prices from different rooftop solar installers. I think the last time I did so was when I highlighted that SolarCity’s prices (per watt) were about 34% higher than average rooftop solar prices in California , according to a Pick My Solar analysis","m_szDocBody":"cost solar system solarcity sunrun vivint solar cost watt solar zachary shahan weve written lot average solar power price utilityscale solar power pricesandrooftop solar power price weve seldom found teased price rooftop solar installersi time highlighted solarcity price per watt higher thanaverage rooftop solar price california pick solar analysis recent seeking alpha simple investment ideas put company light indicating solarcity price per watt lower price top competitor sunrun run vivint solar vslr full disclosure scty shareholder run vslr shareholder silevo solar panel solarcity market dominance include significant competitive advantage analyst write solarcity lead cost front cost structure watt contrast vivint solar sunrun reported cost structure watt watt quarter make matter worse vivint solar sunrun solarcity cost structure unusually company result inflated sale coststo idea solarcity affected rising sale cost company sale cost stood watt company sale cost stood watt rising sale cost resulted company cost structure grow watt watt qoq clearly interesting simply process sale watt good quarter and watt bad quarter solarcity average installed cost rooftop solar system sitting watt sizable soft cost noted year ago key reason solar power cost german solar power seeking alpha analyst key argument solarcity price drop tesla motor acquire solarcity result challenging storey sunrun vivint solar analyst noted solarcity installation cost low solarcity superior operational capability evident company incredibly low installation cost watt large sale cost advantage vivint solar sunrun devastating company solarcity manage bring sale cost back watt range company conceivably cost structure advantage watt closest cost competitor vivint solar pick solar finding solarcity price higher average california curious dig large solar installation company cost more assuming mix financing package offered all company heavily focused solar till nowandhigh acquisition cost see case largest homesolar installer right date hottest cleantech new subscribing free cleantech newsletter eye sectorspecific new also free solar energy newsletter electric vehicle newsletter wind energy newsletter havent reader survey yet now tag run scty solarcity sunrun tesla energy tesla motor vivint solar vslr zachary shahan tryin and specy letter time spend time cleantechnica director chief editor otherwise enthusiastically fulfilling duty obsession gas solar love planetsave bikocity president important media zach recognised globally solar energy electric car energy storage wind energy expert speak related conference event connect social media zacharyshahancom related post ","m_szGeo1":"United States","m_szSourceType":"source_industry","m_szSrcUrl":"http://cleantechnica.com/2016/07/19/cost-solarcity-solar-systems-vs-sunrun-vivint-solar-cost-per-watt-solar-salesacquisition/?utm_source=feedburner&utm_medium=feed&utm_campaign=Feed%3A+IM-cleantechnica+%28CleanTechnica%29","m_Places":["United States","California","Tesla"],"m_People":["Per Watt","Zachary Shahan"],"m_Companies":["Solarcity","Vivint Solar","Vslr","Tesla Motors","Given Solarcity"],"m_BiGrams":["vivint solar","sale cost","solar power","cost structure","solarcity price","rooftop solar","solar sunrun"],"m_TriGrams":["vivint solar sunrun"],"m_SocialTags":[],"m_Topics":[],"m_Industry":[],"m_Technology":[],"m_BiCnt":[8,6,5,5,4,3,3],"m_TriCnt":[3],"m_iDocBodyWordCnt":371}
