{"m_szDocID":"636490","m_szDocTitle":"Photovoltaics Miniseries #10: World’s First Practical Solar Cell Victim to Exigencies of Cold War | CleanTechnica","m_szYear":"2015","m_szDocSumamry":"Photovoltaics Miniseries #10: World’s First Practical Solar Cell Victim to Exigencies of Cold War February 3rd, 2015 by Glenn Meyers   Welcome to our tenth entry about the first practical solar cell. This miniseries is a celebration of the UN’s 2015 Year of Light  featuring John Perlin , author of “Let It Shine: The 6000-Year Story of Solar Energy.” For those who may have missed an episode in this miniseries, here is what has been published: Photovoltaics Miniseries #9: Saved by Silicon – Part 2  In the last episode looked further at the impact of the semiconductor revolution and its principal","m_szDocBody":"photovoltaic minisery world practical solar cell victim exigency cold war glenn meyer tenth entry practical solar cell minisery celebration uns year light featuring john perlin shine year storey solar energy missed episode minisery published photovoltaic minisery saved silicon part episode looked impact semiconductor revolution principalmaterial silicon spurred development practical solar cell cleantechnica early development solar cell viewed public perlin evoked great interest new world report speculated excitedly device provide power world coal oil uranium cleantechnica predominant thinking modern civilization readied standard energy perlin respect yes york time suggested discovery mark beginning era leading eventually realisation mankind cherished dream harnessing limitless energy sun civilization cleantechnica happened perlin timing solar cell discovery bode success month bell laboratory public regard greatest breakthrough history solar energy america detonated practical hydrogen bomb blast contaminated area square mile causing worst radiological disaster history raising spectre complete annihilation planet powerful antiwar movement arose worldwide consequence powerful antiamerican overtone cleantechnica incident generated numerous strong reaction worldwide correct perlin yes diffuse growing opposition buildup thermonuclear arsenal presented world atom peace programme thenpresident eisenhower programme lead miraculous inventiveness man dedicated death consecrated life cleantechnica contend atom peace meant selling nuclear panacea world future energy need perlin yes achieve expressed goal meeting future energy need congress passed atomic energy act making industry nation topsecret nuclear research valued minimum billion dollar onehundred billion dollar dollar pledging additional million dollar billion dollar fund programme conducting assisting fostering research development encourage maximum scientific industrial progress nuclear future cleantechnica solar energy perlin contrast solar received year government funding general electric largest recipient nuclear largess told american public stake winning heart mind world engulfed midst cold war whine discrepancy communism failed proclaimed national advertising campaign communism nuclear power succeed americas clear cleantechnica pathway built optimistically powered world perlin americas universal nuclear theology solar recent resurrection promising power source future newsweek belittled sun diffuse radiation paltry compared power atom month praising bell solar breakthrough york time joined nuclear choir predicting electricity atom industry turning home lighted century energy sun atomic fuel gone pundit estimated year away bell solar cell buried public deeply pronuke fallout led inventor wonder baby coming nextsolargate nixon administration shred national science foundation plan nation solar photos shine year storey solar energy cleantechnicas completely free electric car report electric car early adopter follower want date hottest cleantech new subscribing free cleantech newsletter eye sectorspecific new also free solar energy newsletter electric vehicle newsletter wind energy newsletter tag atom peace bell solar cell general electric john perlin shine year storey solar energy nuclear energy photovoltaic photovoltaic minisery world practical solar cell victim exigency cold war president eisenhower year light glenn meyer writer producer director meyer editor director green building element contributing writer cleantechnica founder green street mediatrain communication connexion elearning hub independent producer involved development production distribution television distance learning programme education industry corporate sector avid gardener love sustainable innovation related post ","m_szGeo1":"United States","m_szSourceType":"source_news","m_szSrcUrl":"http://cleantechnica.com/2015/02/03/photovoltaics-miniseries-10-worlds-first-practical-solar-cell-victim-exigencies-cold-war/?utm_source=feedburner&utm_medium=feed&utm_campaign=Feed%3A+IM-cleantechnica+%28CleanTechnica%29","m_Places":["America","United States"],"m_People":["Bell Solar","Glenn Meyers","John Perlin"],"m_Companies":["Un","Story Of Solar Energy","Revolution","U.s. News And World Report","New York Times","Bell Laboratories","Atoms","Congress","General Electric","Universal","Newsweek","Nixon Administration","National Science Foundation"],"m_BiGrams":["solar cell","solar energy","practical solar","cold war","shine year","year storey","storey solar","atom peace","billion dollar","bell solar"],"m_TriGrams":["practical solar cell","shine year storey","year storey solar","storey solar energy"],"m_SocialTags":[],"m_Topics":[],"m_Industry":[],"m_Technology":[],"m_BiCnt":[8,6,4,3,3,3,3,3,3,3],"m_TriCnt":[4,3,3,3],"m_iDocBodyWordCnt":477}
