{"m_szDocID":"648488","m_szDocTitle":"Composites Market Insights, April 18, 2016","m_szYear":"2016","m_szDocSumamry":"ANASAYFA  KOMPOZİT DERNEĞİ  Dernek Künyesi  Dernek Amacı  Dernek Misyonu  Yapılan Çalışmalar  Planlanan Çalışmalar  YÖNETİM  YÖNETİM KURULU  DENETİM KURULU  TEMSİLCİLİKLER  TÜZÜK  ÜYELER  Üye Kuruluşlar Listesi  Üye Listesi  Onursal Üyeler  Üyelik Şartları  Üyelik Aidatları  Üye Kayıt Formu  Üyelik İçin Gerekli Evrak Listesi  KOMPOZİT HAKKINDA  Standartlar  Meslek Standartları  Diğer Standartlar  Mevzuat/Sunuşlar  Yayınlar  Üye Yayınları  Bilgi Bankası  Basın  Belediyelerde Kompozit Kullanımı  Sık Sorulan Sorular  Videolar  LİNKLER  İLETİŞİM  Composites Market Insights, April 18, 2016  |  Havi","m_szDocBody":"anasayfa kompozit dernei dernek knyesi dernek amac dernek misyonu yaplan almalar planlanan almalar ynetim ynetim kurulu denetim kurulu temsilcilikler tzk yeler kurulular listesi listesi onursal yeler yelik artlar yelik aidatlar kayt formu yelik iin gerekli evrak listesi kompozit hakkinda standartlar meslek standartlar dier standartlar yaynlar yaynlar bilgi bankas basn belediyelerde kompozit kullanm sorulan sorular videolar linkler iletiim composite market insight trouble viewing email eposta adresi istek postalardan korunmaktadr grntlyebilmek iin etkinletirilmelidir account follow home consulting market report country research lucintel training composite market insigh copyright lucintel irving usa tel newsletter circulated subscriber worldwide subscription only spend minute newsletter week stay top business submit company latest development new announce job opening write eposta adresi istek postalardan korunmaktadr grntlyebilmek iin etkinletirilmelidir eposta adresi istek postalardan korunmaktadr grntlyebilmek iin etkinletirilmelidir forward free newsletter friend colleague uptodate current happening composite industry headline detail new new article divided section business developmen new material application development technology development financial award certification event people business development argosy open facility bolster aerospace material manufacturing argosy international inc leading supplier advanced composite related material asia pacific aerospace industry started construction squaremeter manufacturing facility located jing road wuqi district taichung city taiwan facility located taichung duty free zone qualified include clean room cutting table freezer process cuttoshape composite kit configuration sonoco present composite package han freitag fit fun biscuit han freitag cookie waffle bakery located verde germany rely carefully selected ingredient latest biscuit creation developed collaboration fit fun wellness magazine introduced market sonocos enclosable gramme composite can term packaging baked good specialist verden employee annual revenue approximately million euros decided sonocos composite can ruag supply carbonfiberreinforced structure vulcan rocket ruag space supply carbon structure united launch alliance ulas vulcan centaur launch vehicle informed company space symposium colorado spring agreement effect signed launch manufacturer united launch alliance ruag expansion supplier partnership enabling significant future saving composite structure agreement govern supply carbonfiberreinforced structure ula launcher baic bjev dresden university technology sinogerman strategic cooperation agreement baic bjev leading energy automaker china signed strategic cooperation agreement sinogerman automotive light weighting technology joint r&d centre dresden university technology tud council chamber state sachsen ceremony side entered letter intent establishment sinogerman automotive light weighting technology engineering centre ltd due comprehensive strategic arrangement baic bjev velox broaden distribution activity topas advanced polymer velox gmbh european leader marketing distribution raw material specialty plastic composite rubber paint coating industry apprise extended distribution partnership topas advanced polymer effective velox distributing topas coc topasblend sery denmark sweden norway finland topas cyclic olefin copolymer coc class polymer property profile varied wide range alaska airline gain abaris training composite repair skill competition amc event alaska airline won abaris training composite skill event aerospace maintenance competition amc recently held mro americas event kay baily hutchinson convention centre dallas noted winning team formal composite repair training experience compared team exposure composite repair skill addition judging composite repair skill competition abaris hexion inc albester albecor ltc powder coating resin north america hexion inc highly durable powder coating resin albester brand durable superdurable polyester resin albecor ltc brand low temperature cure carboxylterminated polyester resin including innovative low temperature cure option north america albester brand wellknown superior outdoor durability resin range include pure polyester applied system comply stringent international standard quali smc line begin aliancy r&d facility aliancy installed stateoftheart smc line r&d facility zwolle netherland line capability make full range smc material including product based carbon fibre aliancy equipment joint development project key customer pushing limit smc processing moulded component enduse performance aliancy smc equipment temperature controlled enabling operation elevated temperature hexion inc launches nextgen epoxy waterborne system costeffective ultralow voc highperformance coating hexion inc introduce nextgen epoxy waterborne system american coating show indianapolis system offer coating performance comparable solventborne system meeting stringent volatile organic compound voc regulation premium price highperformance waterborne epoxy key system novel watersoluble amine curing agent called research curing agent rsc solventfree curing agent material rice university team create hexagonal boron nitridebased electrolyte composite liion battery operation room temperature rice university material scientist introduced combined electrolyte separator rechargeable lithiumion battery supply energy usable voltage temperature essential part nonflammable toothpastelike composite hexagonal boron nitride hbn atomthin compound called white graphene rice team led material scientist pulickel ajayan battery made composite functioned perfectly temperature degre garmor advance electrically conductive composite energy storage electronic application garmor leading graphene technology provider developer advanced customerdriven application developed graphenebased composite ideal highvolume electronic energy storage application leveraging inexpensive manufacturing method produce fewlayer graphene oxide tandem innovative composite compression moulding processe garmor produced compressionmoldable gocomposite shaped stamped form factor compressionmold grant awarded osutulsa researcher develop tougher carbonfiber reinforced composite team oklahoma state university student awarded grant prepare development tougher reliable carbonfiber reinforced composite commercialization team composed undergraduate student kevin keith postdoctoral fellow kunal mishra school material science engineering graduate student haley marie kurtz school entrepreneurship nathanial evan graduate research assistant helmerich research centre chemtrend promote primer addition waterbased portfolio composite chemtrend apprise addition waterbased primer product sery sery primer chemlease zyvax brand create full waterbased release system composite manufacturer industry first specially formulated overcome challenge wind aerospace fiberreinforced plastic frp market primer sery country expected worldwide distribution coming month sery join chemtrend application development urge bike product launched downomatic made urge bike product unequalled technology glass fibre linen composite downomatic lightest highend helmet market smallest detail studied perfect helmet enjoy safely comfortably riding key practise mtb make proud talk sport urge root grow deep company dedicated knowledge engineer kba launches rotajet digital press composite panel show kba north america introduce rotajet digital press spring meeting composite panel westin paloma tucson arizona cpas annual spring meeting premiere business networking event north american composite panel industry rotajet sery start inch web width supplied kba width inches kba rotajet rotajet digital inkjet presse perfect industrial dura composite major achievement square metre frp dura platform supplied month dura composite completed supply square metre awardwinning dura platform month company surpassed initial goal sqm speed groundbreaking composite station platform solution deployed exceeded expectation rail contractor station operator alike dura platform precision engineered product made fibre reinforced plastic frp comply network rail specifi medtec europe lubrizol lifescience exhibited expanded medical device solution lubrizol corporation lifescience business showcase total solution capability medtec europe messe stuttgart stuttgart germany lifescience coexhibit resin event velox gmbh leading european supplier specialty raw material lifescience offer custom medical device contract manufacturing service specialising comprehensive exel parasol introduced wallpaper handmade exhibition space milan wallpaper exhibit exel parasol solarpowered portable desk salone del mobile world prestigious show design furnishing sector exel composite carbon tube displayed wallpaper handmade exhibition exel composite introduce totally concept portable desk chair shaded umbrella exel parasol power laptop mobile device solar energy chair table top shade made deep orange nextgeneration toyota concept vehicle reinforced textreme deep orange nextgeneration toyota concept vehicle developed engineered student clemson university displayed sae international world congress exhibition detroit textreme carbon fabric door panel rear hatch dashboard bumper cladding significant weight saving improved mechanical performance superior surface smoothness achieved textreme unique material differ conventional carbon fibre technology development teijin water purification technology special fibre carrier adopted bdash project consortium comprised ihi enviro ltd teijin limited japan sewage work agency town tatsuno nagano prefecture informed joint project special fibre carrier reduce waste sludge wastewater treatment adopted breakthrough dynamic approach sewage technology bdash project ministry land infrastructure transport tourism mlit technology contribute solution issue achieve exel composite biotrickling filtration eliminate styrene emission exel composite invested considerable resource year tackling emission environment exel composite pioneer composite technology field environmental protection main ecological concern exel composite composite industry general styrene emission presented possibility explore biotrickling filtration cooperation university valencia spain pure air tepex drethan lanxess make hondas fcv clarity fuel cell emission vehicle lighter lanxess featured recently launched fcv fuel cell vehicle clarity fuel cell latest model hydrogen electric vehicle honda motor tepex continuous longfiber reinforced thermoplastic composite matrix lanxess subsidiary bondlaminate combination durethan hightech plastic grade lanxess honda introduced worldfirst development hybridmolded rear bumper beam model oneshot moulding technology ena financial gurit report solid start fiscal year quarter sale annual general meeting gurit reported unaudited result quarter net sale month developed line expectation slightly lower quarter gurit composite material achieved net sale chf million quarter represent decline currencyadjusted compared net sale chf million month gurit composite component revenue declin award certification fibermaqs rtm machine certified accordance fibermaq brazilian leader equipment composite moulding company segment certified standard brazilian ministry labour intended increase safety operator type machinery general determine danger zone opening passageway enclosed require installation protection fairing prevent operator moving part gear pulley bureau veritas accept fpso composite repair system classification bureau veritas approved principle repair offshore structure bonded composite product coldshield developed parisbased startup cold pad coldshield composite structural reinforcement specifically developed harsh environment offshore unit matthieu tugny senior vicepresident head offshore bureau veritas said coldshield offer long awaited solution repair corroded offshore structure event registration open providing confidence composite construction event ncc hosting providing confidence composite event event run registration open free day event publicise demonstrate duracomp project benefit industry academia include tour ncc facility duracomp project funded year epsrc looked tackle significant factor limiting uptake construction industr teijin showcase china international occupational safety health good expo teijin group worldleading supplier highperformance fibre informed teijin limited shanghaibased teijin aramid asia ltd group aramid fibre business exhibit china international occupational safety health good expo held shanghai international expo centre teijin booth hall stand ctd sho optimization lightweight composite structure composide case study converting metallic structure lighter stronger composite design date time gmt cet webinar case study performed redesign portable helipad structure lighter stronger structure composite material composide design develop lightweight portable helipad initial aluminium alloy structure lighter stronger glass fibre webinar focus design engineering step create import original structure material selection attend school advanced composite processe material student academic technician business owner state understanding latest development advanced material processe result attending twoday school presented composite partnership institute advanced composite manufacturing innovation iacmi organisation comprising national network manufacturing innovation held iacmi composite institute headquarter jec americas composite show conference atlanta programme registration people triumph establishes marketfocused business unit appoint executive triumph group inc informed company realigning business unit meet evolving customer triumph align organisational structure operation financial reporting fiscal year business unit follow integrated system integrated solution including design development support proprietary component subsystem system production complex assembly exter sponsor newsletter write eposta adresi istek postalardan korunmaktadr grntlyebilmek iin etkinletirilmelidir become part powerful costeffective marketing tool growing business guaranteed result free newsletter write eposta adresi istek postalardan korunmaktadr grntlyebilmek iin etkinletirilmelidir subject line click newsletter unsubscribe newsletter republished written permission lucintel lucintel lascolinasblvdwest suite irving safeunsubscribe forward service provider eposta adresi istek postalardan korunmaktadr grntlyebilmek iin etkinletirilmelidir tweet follow kompozit sanayicileri dernei haklar sakldr","m_szGeo1":"Turkey","m_szSourceType":"source_general","m_szSrcUrl":"http://www.kompozit.org.tr/component/content/article/74-bildirimler/2694--composites-market-insights-april-18-2016","m_Places":["United States","Irving, Tx","Wuqi District","Taichung City","Taiwan","Germany","Verden","Colorado Springs","China","Denmark","Sweden","Norway","Finland","Americas","Dallas, Tx.","North America","Zwolle","Netherlands","Indianapolis","Made","Tulsa","Paloma","Tucson, Arizona","Europe","Stuttgart","Milan","Mobile","Orange","Toyota","In Detroit, Mi","Carriers","Japan","Nagano Prefecture","Spain","Paris","Shanghai","Atlanta","Irving"],"m_People":["Hans Freitag","Rsc","Pulickel Ajayan","Kevin Keith","Kunal Mishra","Haley Marie Kurtz","Nathanial Evans","Matic Rr","Matthieu De Tugny, Senior Vice-president"],"m_Companies":["International Inc.","Asia Pacific","United","Alliance","Dresden University Of Technology","Sino","Tud","Technology Engineering Center Co., Ltd.","Velox Gmbh","Alaska Airlines","Amc","Kay Baily Hutchinson Convention Center","Hexion Inc.","Rice University","Rice","Oklahoma State University","School Of Entrepreneurship","Research Center","Frp","Panel Association Show","Panel Association","Plastic","Lubrizol","Lubrizol Corporation","Exel","Wallpaper","Salone","Clemson University","Sae International","Congress","Hatch","Ihi Enviro Co., Ltd","Teijin Limited","University Of Valencia","Lanxess","Honda","Honda Motor Co","Matrix","Brazilian Ministry Of Labor","Bureau Veritas","Society Bureau","Veritas","Teijin Group","Teijin Aramid Asia Co., Ltd.","National Network","Composites Institute","Triumph Group","Triumph Group, Inc."],"m_BiGrams":["eposta adresi","adresi istek","istek postalardan","postalardan korunmaktadr","korunmaktadr grntlyebilmek","grntlyebilmek iin","iin etkinletirilmelidir","exel composite","composite repair","hexion inc","training composite","write eposta","advanced composite","baic bjev","repair skill","north america","curing agent","composite panel","dura platform","exel parasol","fuel cell","net sale","bureau veritas","structure lighter","lighter stronger","business unit"],"m_TriGrams":["eposta adresi istek","adresi istek postalardan","istek postalardan korunmaktadr","postalardan korunmaktadr grntlyebilmek","korunmaktadr grntlyebilmek iin","grntlyebilmek iin etkinletirilmelidir","write eposta adresi","composite repair skill","structure lighter stronger"],"m_SocialTags":[],"m_Topics":[],"m_Industry":[],"m_Technology":[],"m_BiCnt":[6,6,6,6,6,6,6,6,5,4,3,3,3,3,3,3,3,3,3,3,3,3,3,3,3,3],"m_TriCnt":[6,6,6,6,6,6,3,3,3],"m_iDocBodyWordCnt":1772}
