{"m_szDocID":"652675","m_szDocTitle":"Sunvault's graphene-based supercapacitor declared to someday replace Lithium-ion batteries and compete with Tesla's battery aspirations | Graphene-Info","m_szYear":"2015","m_szDocSumamry":"Skip to main content  Home  About us  What is graphene?  The Graphene Handbook  Our services  Information products  Business development  Market outreach  Material brokerage  More  Market reports  More  Graphene Batteries  Solar panels  Graphene Oxide  Supercapacitors  Investing  Aerogels  Inks  Applications  Companies  Events  ...  You are here  Home  »  Graphene News  »  Sunvault's graphene-based supercapacitor declared to...  Sunvault's graphene-based supercapacitor declared to someday replace Lithium-ion batteries and compete with Tesla's battery aspirations  Apr 10, 2015  Graphene applica","m_szDocBody":"skip main home graphene graphene handbook service information product business development market outreach material brokerage market report graphene battery solar panel graphene oxide supercapacitor investing aerogel ink application company event home graphene new sunvault graphenebased supercapacitor declared sunvault graphenebased supercapacitor declared someday replace lithiumion battery compete teslas battery aspiration graphene application graphene printing graphene solar supercapacitor sunvault representative canadian sunvault recently attendedthe wall street conference florida theypresented farad graphene supercapacitor claimed company largest graphene supercapacitor developed date technology future compete with potentially replace lithium battery company ceo quoted conference currently cost manufacture lithium battery usd kwh tesla recently announced super factory built nevada promise price lithium battery usd kwh current cost estimated type graphene base supercapacitor kwh today feel confident cut pricing half end company alsodisplayed ability print device part significantly reduce manufacturing cost wiring device result unit approximately size computer tower store energy power home work sunvault planned stand solar appliance power generation larger air conditioning unit supply home grid potential future rapid charging ability impactthe smart phone electric car power grid stabilisation home grid market result veritable revolution fieldsthe company additional opportunity deployment graphene base heating power storage system started areas set manufacturing product ready marketready sunvault announced intention develop graphenebased supercapacitor solar cell source alternergymag permalink posted roni peleg add comment similar entry sunvault energy edison power farad graphene supercapacitor sunvault energy sign agreement edison power company enter alberta electricity market sunvault energy edison power company kickstart graphenebased smartphone battery case prototype sunvault energy edison power solar energy storage project delaware sunvault develop graphenebased supercapacitor cell science bostonpower collaborate develop battery silicongraphene anode edison power sunvault energy create unique graphenereinforced plastic grapheneinfo sponsor free weekly newsletter popular storey graphene enable ultra performance infrared photodetector hydrogen atom magnetise graphene graphene artificial atom open door quantum computing expert roundup graphene oxide composite graphene balloon endure extreme pressure evaluate material grapheneinfo metalgrass software contact ","m_szGeo1":"United States","m_szSourceType":"source_industry","m_szSrcUrl":"http://www.graphene-info.com/sunvaults-graphene-based-supercapacitor-declared-someday-replace-lithium-ion-batteries-and-compete","m_Places":["Tesla","Florida","Nevada","Alberta","Delaware","Boston-power"],"m_People":["Edison Power","Roni Peleg"],"m_Companies":["2020","Revolution","Permalink","Edison Power Company","Kickstart"],"m_BiGrams":["sunvault energy","edison power","graphenebased supercapacitor","graphene supercapacitor","lithium battery","energy edison"],"m_TriGrams":["sunvault energy edison","energy edison power"],"m_SocialTags":[],"m_Topics":[],"m_Industry":[],"m_Technology":[],"m_BiCnt":[5,5,4,3,3,3],"m_TriCnt":[3,3],"m_iDocBodyWordCnt":314}
