{"m_szDocID":"653246","m_szDocTitle":"Monthly Archive, February 2015 | Graphene-Info","m_szYear":"2015","m_szDocSumamry":"Skip to main content  Home  About us  What is graphene?  The Graphene Handbook  Our services  Information products  Business development  Market outreach  Material brokerage  More  Market reports  More  Graphene Batteries  Solar panels  Graphene Oxide  Supercapacitors  Investing  Aerogels  Inks  Applications  Companies  Events  ...  You are here  Home  Â»  Monthly archive  Monthly Archive, February 2015  Up close and personal: Andrew Smaha  Feb 27, 2015  This week's Graphene-info personal interview features Andrew T. Smaha. If you wish to be featured,  contact us here  .  Andrew T. Smaha, Confe","m_szDocBody":"skip main home graphene graphene handbook service information product business development market outreach material brokerage market report graphene battery solar panel graphene oxide supercapacitor investing aerogel ink application company event home monthly archive monthly archive close personal andrew smaha week grapheneinfo personal interview feature andrew smaha featured contact andrew smaha conference director smither information andrew manage create portfolio include emerging technology material oled led ssl graphene tyre technology vehicle dynamic colour science pigment tio carbon black met coke silicone elastomer tpe other sector andrew connect researcher supplier producer buyer producing marketleading global business technology summit permalink read full storey posted year roadmap graphene related material ascience technology roadmap graphene related twodimensional crystal material hybrid system put togetherin joint effort academic industrialist theroadmap cover year beyond objective guide research community industry development product based graphene related material roadmap highlight broad areas activity task identify layered material assess potential develop reliable reproducible safe mean producing industrial scale identification device concept enabled material required development component technology ultimate goal integrate component structure based material system capable providing functionality application areas permalink read full storey posted graphene oxide discovered great anticancer potential scientist university manchester found graphene oxide act anticancer agent selectively target cancer stem cell csc combination existing treatment eventually lead tumour shrinkage preventing spread cancer recurrence treatment team prepared variety graphene oxide formulation testing cancer type breast pancreatic lung brain ovarian prostate flake inhibited formation tumour sphere formation type suggesting graphene oxide effective large number cancer blocking processe place surface cell researcher suggest deliver clinical outcome combination conventional cancer treatment permalink read full storey posted grapheneinfo new faster server today moved grapheneinfo web server server lot faster previous one notice displayed faster past month server service outage mostly due server load traffic increase server suffer issue see error weird behaviour fix enjoy new fastergrapheneinfo permalink read full storey posted haydale intend cooperate alex thomson racing explore grapheneenhanced racing boat haydale announced intention enter collaborative agreement withalex thomson racingthe hugo boss sponsored extreme sailing teamhaydale newly acquired subsidiary epl composite solution limited work atr incorporate graphene enhancedmaterial research development programme improve strength stiffness number key structure atr boat incorporating graphene enhanced material future boat design atr seeking vessel light ensure optimum speed compromising strength initial work include review ascertain weight saving opportunity party keen make recent work haydale adding functionalised hdplas graphene nano platelet gnp carbon fibre reinforced plastic cfrp epoxy resin permalink read full storey posted graphene sensor inc sign memorandum understanding meditel test medical sensor canadian graphene sensor inc announced signing memorandum understanding meditel major hospital chain based chennai india agreement meditel test evaluate company sensor provide graphene sensor inc detailed feedback appropriate graphene sensor inc relayed relationship meditel great opportunity leading medical tech developer india work team surgeon company continue advance development robotic surgical technology meditel chairman added nano assisted surgery represent exciting innovation thoracic abdominal pelvic surgery year forward offering procedure patient combat cardiac disease prostate uterine cancer permalink read full storey posted haydale enter year agreement swansea university haydale announced entered year exclusive pipeline agreement swansea university swansea innovation agreement stipulate thatswansea carry seriesof internally funded research project produce prototype application usinga range haydale material material functionalised haydalegraphene nano platelet gnp haydale conductive insulatingink formulated collaboration partner welsh centre printing andcoating wcpc permalink read full storey posted graphene esd stony brook university research agreement development graphenebased supercapacitor lomiko metal recently announced forming graphenerelated venture called graphene energy storage device graphene esd corp commercialise energy storage technology now lomiko announced signing research agreement graphene esd stony brook university graphene esd corp partner sbu centre advanced sensor technology sensor cat develop supercapacitor designed energy storage device designed versatile energy storage solution electronic electric vehicle electric gridsbu leverage experience electrochemistry responsible design electrode electrolyte formulation graphene esd team work device assembly testing permalink read full storey posted rice scientist test nanoparticle toxicity recent study performed rice university explored toxicity nanomaterial major difficulty assessing nanomaterial toxicity variety nanomaterial costly test traditional method goal study develop lowcost highthroughput method solve problem scientist achieved goal testing nanomaterial worm called nematode elegan designed assay test hundred nanomaterial week assay test effect nanomaterial thousand worm material cost assay cent demonstration applied technology test nanomaterial found showed degree toxicity method serve effectively rapid initial screen prioritise nanomaterial expensive dedicated toxicology testing permalink read full storey posted cambridge graphene centre team nippon kayaku cambridgegraphene centre announced teaming japanese company nippon kayakua chemical manufacturer global activity functional material pharmaceutical automotive safety component agrochemical permalink read full storey posted page grapheneinfo sponsor free weekly newsletter popular storey graphene enable ultra performance infrared photodetector hydrogen atom magnetise graphene graphene artificial atom open door quantum computing expert roundup graphene oxide composite graphene balloon endure extreme pressure evaluate material grapheneinfo metalgrass software contact ","m_szGeo1":"Japan","m_szSourceType":"source_industry","m_szSrcUrl":"http://www.graphene-info.com/archive/201502","m_Places":["Smithers","Chennai","India","Swansea","Nippon"],"m_People":["Andrew T. Smaha","Alex Thomson","Graphene Nano"],"m_Companies":["Permalink","University Of Manchester","Cscs","Racing","Hugo Boss","Epl Composite Solutions Limited","Plastic","'cfrp'","Graphene Sensors Inc.","Major Hospital","Swansea University","Swansea Innovations","Stony Brook University","Graphene Esd Corp.","Graphene Esd Corp","Rice University"],"m_BiGrams":["graphene oxide","graphene esd","graphene sensor","sensor inc","energy storage","andrew smaha","graphene related","posted graphene"],"m_TriGrams":["graphene sensor inc","storey posted graphene"],"m_SocialTags":[],"m_Topics":[],"m_Industry":[],"m_Technology":[],"m_BiCnt":[6,5,4,4,4,3,3,3],"m_TriCnt":[4,3],"m_iDocBodyWordCnt":790}
