{"m_szDocID":"653835","m_szDocTitle":"We Are Entering The Sustainable Energy Age | Development Unplugged","m_szYear":"2016","m_szDocSumamry":"We Are Entering The Sustainable Energy Age Posted: By Guy Dauncey Goal 7: Ensure access to affordable, reliable, sustainable, and modern energy for all The United Nations Sustainable Development Goals have such a grand, evocative ring, and they include a goal on energy, a huge concern for everyone's future. So what does the goal ask for -- and can we meet it? Affordable: Solar energy was not affordable when NASA first used it in space, but its price has fallen 100-fold since the 1970s , and in many parts of the world it is now a financially viable long-term option . Wind energy is now the chea","m_szDocBody":"entering sustainable energy age posted guy dauncey goal ensure affordable reliable sustainable modern energy united nation sustainable development goal grand evocative ring include goal energy huge concern everyone future goal meet affordable solar energy affordable nasa space price fallen fold part world financially viable longterm option wind energy cheapest kind power increase efficiency building vehicle appliance cost run reliable put qualified engineer job reliability sustainable firewood sustainable small managed scale fossil fuel sustainable host reason nuclear power sustainable source sustainable renewable energy sun solar wind wave hydro sustainably managed biofuel tidal energy moon sun geothermal energy earth combined efficiency power storage load management modern back motorcar modern picassos art time all real challenge achieve transition cent renewable energy earth include country russia saudi arabia economy depend fossil fuel export china india hooked coal challenge enormous climate crisis breathing neck increasing fire flood storm sealevel rise possible technology finance politic enter stage electricity transition political will policy send positive signal investor alberta announced phase coalfired power saskatchewan announced produce half power renewable european union target produce cent electricity renewable china engaged massive solar acceleration world achieve technically climate alarm bell ring loudly widely including congress generating urgent act transportation challenge difficult early falling price battery electric car priced regular car cost run bmw cease making regular car electric buse operation city make road pedestrian bicyclefriendly longdistant transportation road air sea solution sight yet breakthrough battery hydrogen long heat challenge tougher policy building built passive house standard constructed cent heat obtained heat recovery ventilation unit brussel german city building meet passive house standard million existing building factory highrise retrofit task huge make building efficient replace oil gas heatpump renewably sourced district heat stored summer solar heat drake landing okotok alberta industrial heat make iron steel cement proposal prototype ready roll out age firewood lasted year age fossil fuel year fossil fuel dirt danger developed science engineering underlie cherish solar age billion year passing month technology improve price fall canada clear goal politician drift canada set clear goal vancouver done cent renewable energy quickly possible temperature rising climate science tell let put goal table global energy transition huge historically significant easily lose sight amid local battle pipeline coalmine happening challenge make happen fast enough guy dauncey futurist work develop positive vision sustainable future translate vision action live vancouver island canada view expressed blog author necessarily reflect position ccic member huffpost number represent annual energy consumption person represented kilogramme oil number represent annual energy consumption person represented kilogramme oil number represent annual energy consumption person represented kilogramme oil number represent annual energy consumption person represented kilogramme oil number represent annual energy consumption person represented kilogramme oil number represent annual energy consumption person represented kilogramme oil number represent annual energy consumption person represented kilogramme oil number represent annual energy consumption person represented kilogramme oil number represent annual energy consumption person represented kilogramme oil number represent annual energy consumption person represented kilogramme oil share ","m_szGeo1":"United States","m_szSourceType":"source_news","m_szSrcUrl":"http://www.huffingtonpost.ca/development-unplugged/sustainable-energy-age_b_8751660.html?utm_hp_ref=canada-politics&ir=Canada+Politics","m_Places":["Russian Federation","Saudi Arabia","China","India","Alberta","Brussels","Landing","Canada","Vancouver"],"m_People":["Guy Dauncey"],"m_Companies":["United Nations","Solar Energy","Nasa","Signal","European Union","Target","U.s. Congress","2020s","Bmw"],"m_BiGrams":["number represent","represent annual","annual energy","energy consumption","consumption person","person represented","represented kilogramme","kilogramme oil","oil number","fossil fuel","renewable energy"],"m_TriGrams":["number represent annual","represent annual energy","annual energy consumption","energy consumption person","consumption person represented","person represented kilogramme","represented kilogramme oil","kilogramme oil number","oil number represent"],"m_SocialTags":[],"m_Topics":[],"m_Industry":[],"m_Technology":[],"m_BiCnt":[10,10,10,10,10,10,10,10,9,4,3],"m_TriCnt":[10,10,10,10,10,10,10,9,9],"m_iDocBodyWordCnt":488}
