{"m_szDocID":"660612","m_szDocTitle":"Burlington, Oakville students excel at national science fair in Montreal","m_szYear":"2016","m_szDocSumamry":"textArticle -------------------- Burlington, Oakville students excel at national... | May 24, 2016  |  Vote 0    0 Burlington, Oakville students excel at national science fair in Montreal Burlington, Oakville students excel at national science fair in Montreal Photo by the Bay Area Science and Engineering Fair Caroline Mahut of M.M. Robinson High School won a gold medal and a special award at the recent national science and engineering fair in Montreal. Burlington, Oakville students excel at national science fair in Montreal Photo by the Bay Area Science and Engineering Fair Katie Brent of Not","m_szDocBody":"burlington oakville student excel national vote burlington oakville student excel national science fair montreal burlington oakville student excel national science fair montreal photo bay area science engineering fair caroline mahut robinson school won gold medal special award recent national science engineering fair montreal burlington oakville student excel national science fair montreal photo bay area science engineering fair katie brent notre dame secondary school burlington oakville resident won silver medal recent national science engineering fair montreal pre burlington post burlington oakville resident dozen bay area pupil won top award recent canadawide science fair sixteen area student competed pupil canada national fair held montreal local student trip quebec paid bay area science engineering fair based performance year basef competition basef regional science fair held annually hamilton grade student hamilton halton region haldimand norfolk brant county nation basef canadawide science fair competitor brought home award gold medal silver bronze challenge award special award bay area tied calgary medalwinning project robinson grade student caroline mahut regular participant highlevel science engineering competition gold medal winner burlington halton region year national won gold special challenge award top senior innovation project work entitled slowing power town silver medal special award australian national youth science forum award jack mogus grade garth webb secondary school oakville project graphene reinforced guayule rubber conductive hypoallergenic super nanocomposite oakville katie brent grade notre dame secondary school burlington received silver medal project measured step orthopaedic pressurebased rehabilitative insole michael wolfe grade trinity christian school burlington won silver project witricity wheel wireless charging electric vehicle paul drakos oakville grade hillfieldstrathallan college hamilton won silver project prototype water coil generating electricity national bronze medal won halton student david vidican grade matthew school oakville project taguchi method applied optimising performance trebuchet alexander waldie mississauga grade king christian collegiate oakville project synthesis silver nanoparticle effect plant growth tim whitnell reporter burlington post reached follow burlington post ","m_szGeo1":"Canada","m_szSourceType":"source_news","m_szSrcUrl":"http://www.insidehalton.com/news-story/6688257-burlington-oakville-students-excel-at-national-science-fair-in-montreal/","m_Places":["Burlington","Oakville","Montreal","Bay Area Science And Engineering Fair","Bay Area","Canada","Quebec","Hamilton","Halton","Norfolk","Brant Counties","Calgary","Your Town","Mississauga"],"m_People":["Caroline Mahut","Katie Brent","Robinson Grade","Michael Wolfe","Trinity Christian","Paul Drakos","David Vidican","Alexander Waldie","Silver Nanoparticles","Tim Whitnell"],"m_Companies":["Mogus","Strathallan College","St. Matthew School","Optimizing","Twitter","Facebook"],"m_BiGrams":["burlington oakville","science fair","science engineering","national science","fair montreal","bay area","engineering fair","oakville student","student excel","excel national","area science","gold medal","special award","secondary school","school burlington","won silver","silver medal","burlington post","oakville project"],"m_TriGrams":["science engineering fair","burlington oakville student","oakville student excel","student excel national","excel national science","national science fair","science fair montreal","bay area science","area science engineering"],"m_SocialTags":[],"m_Topics":[],"m_Industry":[],"m_Technology":[],"m_BiCnt":[6,6,6,5,5,5,5,4,4,4,3,3,3,3,3,3,3,3,3],"m_TriCnt":[5,4,4,4,3,3,3,3,3],"m_iDocBodyWordCnt":309}
