{"m_szDocID":"661138","m_szDocTitle":"Research Article","m_szYear":"2015","m_szDocSumamry":"Toggle navigation  Services  Reports  3D Printing  3D Printing Platforms & Applications  Materials  Bioprinting  Advanced Materials  Active Electrodes  Conductive Inks  Electrically Conductive Adhesives  Functional & 3D Printing Materials  Graphene & Carbon Nanotubes  Quantum Dots  Thermal Interface Materials  Transparent Conductive Films  Automotive & Electric Vehicles  Overview Report  Aircraft & Water Vehicles  Cars, Motorcycles & Bikes  Energy Storage for EVs  Industrial, Commercial & Military  Powertrain, electrics, electronics & structure  Emerging Devices  Display, Lighting & TFTs  Micr","m_szDocBody":"toggle navigation service report printing printing platform application material bioprinting advanced material active electrode conductive ink electrically conductive adhesive functional printing material graphene carbon nanotube quantum dot thermal interface material transparent conductive film automotive electric vehicle overview report aircraft water vehicle car motorcycle bike energy storage evs industrial commercial military powertrain electric electronic structure emerging device display lighting tft microcontroller smart packaging smart window smart glass wireless power energy harvesting overview report energy independent vehicle power energy harvesting photovoltaic piezoelectric thermoelectric energy storage supercapacitor battery fuel cell material power electronic internet people internet internet people positioning system printed electronic application conductive ink display lighting material manufacture overview report sensor logic battery rfid overview report passive rfid nfc active rfid rtl application robotic overview report sensor application haptic sensor technology wearable technology wearable electronic etextile stretchable electronic subscription subscription company profile webinar report premium article benchmarking tool company presentation advisory service idtechex market intelligence interpreted business consulting consulting areas expertise analyst success storey service future growth opportunity commercialization strategy product positioning competitive analysis partnership customer development technology scouting due diligence product development client introduction service client introduction service client introduction facetoface meeting service event webinar forthcoming event asia usa europe usa previous event webinar presentation technology emerging technology printing advanced material hybrid pure electric vehicle emerging device energy harvesting energy storage internet people printed flexible organic electronic rfid robotic sensor wearable technology research highlight research article web journal idtechex overview press career contact estore submit emerging technology printing advanced material hybrid pure electric vehicle emerging device energy harvesting energy storage internet people printed flexible organic electronic rfid robotic sensor wearable technology research highlight research article web journal idtechex research home technology research highlight research article commercialising graphene solution composite battery idtechex invited number leading player graphene industry write opinion piece reflecting produce latest research market insight commercialisation experience releasing article week idtechex invited number leading player graphene industry write opinion piece reflecting product latest research market insight commercialisation experience releasing article week angelos kyrlidis principal scientist project manager cabot corporation leading supplier speciality carbon black worldwide cabot attractive programme kyrlidis share market insight learn industry refer report graphene material market technology opportunity graphene graphene graphenelike material make family carbon material derived pristine single layer graphite cabot corporation long history carbon material business producing carbon black year carbon black commonly deliver function important application reinforcement tyre electrical conductivity battery plastic application ranging electrostatic dissipation wire cable colour coating ranging automotive black matrix colour philtre display exception colour the thinner graphene transparent are application graphene potentially deliver performance fraction loading carbon black required turn advantage graphenecontaining composite lighter preserve mechanical property deliver function material bring thermal conductivity barrier property mapping application cabot invested development technology production graphene establishing team focused leveraging company experience carbon material deliver graphene solution break tradeoff customer deliver unique performance year evaluated production route from topdown bottomup see inhouse development external collaboration selected production route produce material unique morphology property map application customer process planning scale production material customer advantage performance benefit commercially morphology map graphene produced major process route leverage existing customer base cabot expertise existing market carbonbased additive development work focused classe application existing customer keen understanding problem customer facing example polymer composite application graphene deliver valuable performance low loading working leading company solve toughest problem graphenecontaining compound masterbatches elastomer finding graphene increase modulus fraction loading carbon black break important performance tradeoff offering customer breakthrough product improvement enable application plastic grapheneoxide derived graphene see deliver electrical conductivity low loading meet thermal stability mechanical cleanliness requirement grapheneoxide derived graphene good customer feedback battery energy storage focused liion pbacid battery target market liion battery working leading battery producer develop graphenebased dispersion deliver long range conductivity needed develop thicker electrode increased capacity morphology graphene formulation low viscosity electrode paste good capacity pbacid battery material enable reduction system cost application excited customer feedback receiving forward delivering graphene market dispersion paste easy handle apply parallel lookout development technology application opportunity committed commercialising material invite customer connect discuss material competency solve challenging problem learn leading event topic wearable usa santa clara usa hosted idtechex print forward tweet share previous related research article webinar graphene hype graphene nanoflakebased film developed thermal interface material graphene market reach tonne year webinar tue november graphene affordable copyright logged login map privacy policy term condition idtechex test close ","m_szGeo1":"United Kingdom","m_szSourceType":"source_news","m_szSrcUrl":"http://www.idtechex.com/research/articles/commercializing-graphene-solutions-for-composites-and-batteries-00008049.asp","m_Places":["Asia","Usa","Europe","Santa Clara, Ca"],"m_People":["Angelos Kyrlidis","Given Cabot"],"m_Companies":["Rtls","Cabot Corporation","Cabot","Matrix","Target"],"m_BiGrams":["overview report","energy storage","carbon black","energy harvesting","research article","advanced material","electric vehicle","emerging device","internet people","wearable technology","development technology","client introduction","technology research","research highlight","highlight research","market insight","carbon material"],"m_TriGrams":["technology research highlight"],"m_SocialTags":[],"m_Topics":[],"m_Industry":[],"m_Technology":[],"m_BiCnt":[5,5,5,4,4,3,3,3,3,3,3,3,3,3,3,3,3],"m_TriCnt":[3],"m_iDocBodyWordCnt":720}
