{"m_szDocID":"661885","m_szDocTitle":"Organic Photovoltaic Markets, 2025 - Research and Markets","m_szYear":"2007","m_szDocSumamry":"textArticle -------------------- Organic Photovoltaic Markets, 2025 - Research and Markets August 11, 2016 Share DUBLIN, August 11, 2016 /PRNewswire/ -- Research and Markets has announced the addition of the \"Organic Photovoltaic Markets 2016 - 2025\" report to their offering. Research and Markets Logo More This report pinpoints the opportunities that n-tech sees emerging in the OPV space over the next ten years. In this case, the assessment is based on insiders view of the area, since the market has been covered since inception. Although major firms have dropped out of this market in the past ","m_szDocBody":"organic photovoltaic market research market share dublin research market announced addition organic photovoltaic market report offering research market logo report pinpoint opportunity ntech see emerging opv space year case assessment based insider area market covered inception major firm dropped market past year report believe business case opv increasingly compelling conversion efficiency lifetime opv increase future opv early niche application solar charging offthegrid use lucrative market opv believe ly bipv begin earnest year opv start exceed percent energy efficiency production cell report show latest development opv material innovation cell module design moving opv goal discusse opv compete cig addition report strategic profile leading firm opv space including assessment marketing manufacturing segment finally report volume forecast opv market breakout application material used key topic covered opv neverending storey realistic expectation opv conversion efficiency step commercial readiness technologyenabled opportunity efficiency record achieved path improved lifetime production trend device structure competition material threat threat dsc perovskite cig versus opv application update entering promised land outstanding issue opv bipv beckon opv great fit solar charger opv future future roadmap opv summary opportunity material specialty chemical supplier company watch market strategy opv now summary tenyear forecast opv market chapter one introduction background report opv struggling good longterm potential opv versus dsc cig opv key technical challenge probable solution market opv decision made objective scope report methodology report plan report chapter two technology trend organic photovoltaic latest opv performance improvement efficiency closer lifetime long production approaches progress printing material trend evolution opv merck kit mathero development china korea japan polymer small molecule direction finding transparent conductor graphene photoactive layer fullerenefree acceptor material opv substrate change read improved hole electron extraction layer electrode moving tunable bandgap solubility single architecture collaborative industry opv research effort key point chapter chapter three market opv case opv bipv bipv ready not challenge opv bipv glass opvenabled bipv nonglass substrate active project supplier opvenabled bipv solar charger example application commercial success offgrid application case made bipv automotive competition opv dsc thinfilm opv dsc now thinfilm cig cdte opv compete energy production key point chapter chapter four opv supplier strategy heliatek germany areas technology improvement manufacturing progress energy united state technology summary market strategy business outlook eight longer picture konarka chapter five tenyear forecast market analysis opv key factor driving opv forecasting methodology tenyear forecast opv offgrid opv market opv material device summary opv market information visit sector photovoltaic media contact est office hour call toll free call gmt office hour call fax original version newswire visit reblog dont symbol list read press business rich dad robert kiyosaki youre investing long term youre crazy robert kiyosaki bestselling book including rich dad poor dad joined marketwatch live interview today offered insight making money entrepreneur touched politic highlight talk listen full interview here advice rich rich work money people understand that theyre taught school job money rich dont work money reason money longer money reason president nixon dollar gold standard basically screwed marketwatch truck carrying takata air bag material explode texas killing takata truck operated subcontractor travelling takata plant mose lake washington takata warehouse eagle pass texas early aug accident occurred driver tractortrailer failed negotiate curve highway crashed house preliminary statement texas department public safety local media report inside house explosion place reuter getty imagesdmambmcmdmemgzgzqzrzsztzumost american filled regret financial regretsfully four fact admit harbour financial regret survey adult bankratecom biggest regret marketwatch chinas electriccar startup face wipeout aug regulation expected pull plug company make chinas electric car industry government imposing strict standard technology cap number manufacturer bloomberg kongho chua report daybreak asia bloomberg video ford offer month financing car loan defaultssurge ford motor nyse offer annual percentage rate apr sixyear month entire model line clear model deal time car finance default blamed extent long loan repayment programme skyrocketed ford degree trouble trend ford freedom sale event require buyer ford credit financing ford credit part ford mean take benefit problem loan put loan perspective paid carfax dont fooled thinking depreciation slow year wallstcom way successful middle class family invest government define mean live poverty doesnt provide clarity mean middle class tend hear lot presidential election year middle class family make majority american household middle class economist slice dice way typical definition categorise family middle class annual household income pew research centre define middle class family earn annually source draw line typical middle class aspiration home ownership vacation college investopedia tim cook cashed million apple stock million share earned cook lasted year apple ceo remainder awarded apple outperformed twothird company s&p year cook apple revenue profit doubled apple stock outpaced broader market taking account dividend stock buyback business insider liz weston money myth money myth time closer financial reality certified financial planner typically recommend client saving cover expense month course shoot starter emergency fund cover small car repair insurance deductible press cleaning trump talk race worst job politic job dont thankless person designated clean donald trump campaign manager kellyanne conway found morning deeply uncomfortable interview fox new host chris wallace focused largely gop nominee supposed outreach africanamerican discussion civil measured wallace unsparing asked conway account trump positioned race respect black community fiscal time half highpaying job america require skill term sql python arent radar employer interested hiring you roughly half job top income quartile defined paying year occupation commonly require applicant computer coding knowledge skill analysis million online job posting released month job market analytic firm burning glass oracle academy philanthropic arm oracle focused computer science education redwood city calif simple term coder write instruction computer indemand programming language include sql java javascript marketwatch wheel chinas aeroengine china officially launched multibillion dollar jet engine conglomerate employee weekend beijing seek aerospace power compete like roll royce general electric aero engine corporation china aecc registered capital billion yuan billion previous report incorporate subsidiary sery stateowned firm including aviation industrial corp china avic president jinping founding company strategic move make china aviation power modernise military official xinhua new agency reported afp healthy dividend stock quality security finding great dividend stock sector natural winner steady growing demand bigtime cash flow large economic moat hallmark prime dividend stock sector factor enable sector throw plenty bigtime dividend healthcare stock meet requirement some demand treatment continue grow exponentially population increase age meanwhile long patent timeline drug delivery medical product plenty stable cash flow factor enable healthcare stock produce enviable cash flow earning translate hefty dividend kiplingercom takata trouble worsen truck explode kill texas woman air bag maker takata corp trouble worsened company confirmed truck carrying inflator volatile chemical exploded week texas border town killing woman injuring other truck operated subcontractor crashed caught fire exploded aug small town quemado mile san antonio levelling woman house takata warehouse nearby eagle pass texas air bag inflator factory border monclova mexico press brexit send down drain german vice chancellor germany vicechancellor warned future doubt uks exit handled badly sigmar gabriel down drain state britain lead nice thing europe taking responsibility theresa summoned minister meeting discuss ideas uks withdrawal downing street brexit top prime minister agenda report time suggested cabinet split leaving single market voted leave european union referendum vote june gabriel economy minister germany bbc new gold turn fiveweek low dollar ease reuter gold rebounded fiveweek low dollar dropped monday shrugging earlier pressure top federal reserve official comment fuelling speculation interest rate rise sooner later speaking meeting leading central banker jackson hole wyoming fed chair janet yellen improvement economy boosted case rate rise vice chair stanley fischer central bank track lift rate year cme group fedwatch tool showed market pricing percent chance hike september percent yellen deputy fischer spoke reuter obamacare price hike cost democrat control senate odd remain fairly good democrat regain control senate november democratic presidential nominee continue strong showing republican businessman donald trump poll race including veteran republican sen john mccain reelection effort arizona deemed competitive political expert year republican vow dismantle replace affordable care act obamacare received attention presidential congressional race now fiscal time cnbc eamon javer report latest presidential race including donald trump announcing immigration speech obama aide calling trump the clinical definiation psychopath cnbc videos samsung ahead apple marc benioff appear technically incorrect offer slightly twisted tech live thought tech ceos nice public offering criticism ceos company masoniclike wink nod code word moved therefore night splendidly forthright salesforce ceo marc benioff retweet this crazy apple catch samsung battery life waterproofing blue colour front led light &curved screen samsung set standard original tweet emitted basketball coach dennis marshall benioff apparent endorsement man thered salesforce cnet oklahomabased pipeline company william company inc wmb agreed procure approximately million common unit priced master limited partnership william partner wpz purchase expected zack mylan launching generic version epipen mylan start selling cheaper version epipen absorbing wave criticism list price emergency allergy treatment grown twopack making unaffordable patient drugmaker launch week generic epipen version identical branded option list price twopack consumer politician accused company pricegouging list price pair epipen climbed repeatedly mylan acquired product mylan ceo heather bresch defended price hike week company received total price twinpackage insurer pharmacy party divvy rest abc new ","m_szGeo1":"United States","m_szSourceType":"source_news","m_szSrcUrl":"http://finance.yahoo.com/news/organic-photovoltaic-markets-2025-research-171000077.html;_ylt=AwrC1CoUqsRXoSgA2Y3QtDMD;_ylu=X3oDMTBydDI5cXVuBGNvbG8DYmYxBHBvcwM2BHZ0aWQDBHNlYwNzcg--","m_Places":["Dublin","China","Korea","Japan","Made","Germany","United States","Outlook","U.k.","Most","Texas","Washington","Asia","America","Redwood City","Java","Beijing","Quemado","San Antonio","Monclova","Mexico","Uk","Britain","Europe","Downing Street","New York","London","Jackson Hole, Wyoming","Arizona","Oklahoma"],"m_People":["Rich Dad","Robert Kiyosaki","Rich Dad Poor","Moses Lake","Kongho Chua","Tim Cook","Liz Weston","Donald Trump","Kellyanne Conway","Chris Wallace","Xi Jinping","Sigmar Gabriel","Janet Yellen","Stanley Fischer","John Mccain","Eamon Javers","Marc Benioff","Dennis Marshall","Heather Bresch"],"m_Companies":["Lifetimes Of Opv","Lifetimes","New Directions","Strategy And Business","Pr Newswire","Associated Press","Marketwatch","Facebook","Texas Department Of Public Safety","Reuters","Bankrate.com","Car Startups","Ford Motor Co","U.s. Government","Slice","Pew Research Center","Apple","Fox News","Fiscal Times","Oracle","General Electric","Engine Corporation","Aviation Industrial Corp.","Xinhua News Agency","Afp","Takata Corp.","Eu","Sunday Times","European Union","Bbc","Federal Reserve","Central Bank","Cme Group","Cost Democrats","Senate","Democrats","Cnbc","Samsung","Coach","Cnet","Williams Companies, Inc.","Williams Partners L.p.","Mylan","Abc News"],"m_BiGrams":["middle class","market opv","opv market","dividend stock","organic photovoltaic","research market","forecast opv","opv bipv","tenyear forecast","air bag","class family","donald trump","cash flow","list price"],"m_TriGrams":["middle class family"],"m_SocialTags":[],"m_Topics":[],"m_Industry":[],"m_Technology":[],"m_BiCnt":[7,4,4,4,3,3,3,3,3,3,3,3,3,3],"m_TriCnt":[3],"m_iDocBodyWordCnt":1494}
