{"m_szDocID":"663170","m_szDocTitle":"Tech Company Graphene Investing","m_szYear":"2013","m_szDocSumamry":"You must have javascript enabled to use this site.  Please  click here  to learn how to enable javascript.  (877) 303-4529  111 Market Place #720  Baltimore, MD  21202  Contact Us  FAQ  Whitelist  Sitemap  Wealth Daily  About  Editors  Videos  Archives  Reports  Resources  Contact Us  Download  your  FREE  report  now: Gold and Silver Mining Stocks  Tech Company Graphene Investing  Companies Eye Graphene Technology  Written by Marcelina Hardy  Posted August 28, 2013 at 7:44PM  Are you looking for a new investment that hasnâ€™t been widely discovered yet so you can get a head start on the returns","m_szDocBody":"enabled site learn enable javascript market place baltimore contact faq whitelist sitemap wealth daily editor videos archive report resource contact download free report now gold silver mining stock tech company graphene investing company eye graphene technology written marcelina hardy posted investment hasnt widely discovered head start return graphene graphene strongest material now industry carbon nanotube turning miracle material instead material sheet carbon atom thick electrical thermal conductivity mechanical strength optical purity else make stronger composite material researcher korean advance institute science technology recently created composite material time stronger raw material made graphene extreme tech report list application super material huge manufacturer electronic make transistor computer display laser photodetector battery aircraft wing biomedical equipment drug delivery tissue engineering company seek patent head otc hedyy austrian sport equipment manufacturer make tennis racket give player completely play sport graphene make shaft stronger increase manoeuvrability distributing tip grip racket evenly financial time recently rice university researcher found add boron atom graphene lithiumion battery anode charge battery faster give lasting energy interest electric car industry kia hyundai eye technology patent place battery electric car prove effective rice university battery recharge second holding charging power cycle graphene mixed vanadium oxide good new material produced low cost large quantity application graphene numerous impossible identify here evident demand material due demand government globe piece revolution financially supporting research britain million euros research addition research centre popping manchester university recently announced constructing world leading centre graphene research national graphene institute completed cambridge university designing research centre raised million euros research material company making selling demand graphene industry these run manchester university company sell singlecrystal graphene flake big company ibm nyse ibm lux research report graphene industry growing alarming rate project industry reach free investment youll make join wealth daily today free well top hottest investment ideas hit wall street member today latest free report gold outlook full detail incredibly important that unfolding affecting gold classified investment spam privacy policy graphene investing graphene world storm showing slowing down researcher working hard application miracle material slice graphene pie invest easy material larger company privately held invest company material included graphene research samsung kse sony nyse sne ibm invest graphene mine reserve china resource canada romania brazil india focus graphite otc fcsmf mine technology developer equipment now working graphene research company grafoid american graphite technology otc agin mineral exploration company own mineral claim recently partnered cti nanotechnology llc successful investing mean jumping train beginning ride waiting off graphene application amazing research done company start increase demand price mean higher return you article enjoy graphene company explore technology graphene electronic investing free investment make receive wealth daily newsletter absolutely free issue investment research designed build lifetime wealth minus risk plus signing instantly receive report surviving coming economic collapse related article graphene computer technology material capable providing efficient cooling electronic device graphene investing lomiko metal tsxv lmr hired graphene specialist explore production graphene graphite graphene patent graphene popularity technology research country hold world graphene patent comment buffett envy annual return guaranteed warren buffett told investor annual shareholder meeting its huge structural advantage lot money make year million could guarantee that buffett talk incredible advantage average smaller investor berkshire point blank oracle omaha envy people invest small cap stock cant join community reader wealth daily today free started top smallcap tech stock pick kind highreturn investment warren buffet dream making learn wealth daily privacy policy top rated rate hike pffft trump talking top fixed income investment valuable retirement plan buying precious metal bullion trending article reason cannabis socially profitable cannabis virtual reality stock buy today mark zuckerberg next investing marijuana wealth daily editor videos archive report investment resource contact copyright fair contact wealth daily market place baltimore tel fax assembled investment mind market offer expert field record none flagship eletter angel publishing wealth daily bring market insight commentary day directly inbox editor combined year investment research sector wealth dailyall right reserved report make fortune stock real secret consistent reliable stock market profit simple top quality dividend stock show consistent reliable income dividend stock send free report ","m_szGeo1":"United States","m_szSourceType":"source_general","m_szSrcUrl":"http://www.wealthdaily.com/articles/tech-company-graphene-investing/4619","m_Places":["Baltimore, Md","United States","Britain","Best","Wall Street","Outlook","China","Canada","Romania","Brazil","India","Most","Omaha","Warren"],"m_People":["Marcelina Hardy","Warren Buffett","Mark Zuckerberg"],"m_Companies":["Tech Company","Eye Graphene Technology","Financial Times","Rice University","Hyundai","Revolution","Manchester University","Graphene Institute","Cambridge University","Graphene Industries","Ibm","2020","Slice","Samsung","Sony","Cti Nanotechnologies Llc.","Graphene Companies","Wealth Daily","Oracle","Real"],"m_BiGrams":["wealth daily","free report","graphene investing","graphene research"],"m_TriGrams":[],"m_SocialTags":[],"m_Topics":[],"m_Industry":[],"m_Technology":[],"m_BiCnt":[8,3,3,3],"m_TriCnt":[],"m_iDocBodyWordCnt":671}
