{"m_szDocID":"668917","m_szDocTitle":"Phenolic carbon cloth-based electric double-layer capacitors with conductive interlayers and graphene coating","m_szYear":"2015","m_szDocSumamry":"RESEARCH ARTICLE Phenolic carbon cloth-based electric double-layer capacitors with conductive interlayers and graphene coating Chunhong Lei1,2 • Foivos Markoulidis1 • Peter Wilson1 • Constantina Lekakou1 Received: 6 August 2015 /Accepted: 8 December 2015 / Published online: 28 December 2015 � The Author(s) 2015. This article is published with open access at Springerlink.com Abstract Phenolic resin-derived activated carbon (AC) cloths are used as electrodes for large-scale electric double- layer capacitors or supercapacitors. To increase the energy and power density of the supercapacitor, the c","m_szDocBody":"research phenolic carbon clothbased electric doublelayer capacitor conductive interlayer graphene coating chunhong lei foivos markoulidis peter wilson constantina lekakou received published online author published open springerlinkcom phenolic resinderived activated carbon cloth electrode largescale electric double layer capacitor supercapacitor increase energy power density supercapacitor contact resistance carbon cloth aluminium foil current collector reduced modifying current collector modified current collector including toyalcarbosurfacemodified dag deflocculated achesontm graphite coating polyethylenedioxythiophene pedot coating tested compared modified current collector shown greatly reduce contact resis tance cloth foil solution investigated study coat cloth graphene electrophoretic deposition epd graphene coated cloth shown increased capaci tance greatly reduced internal resistance graphical keyword phenolic carbon cloth conductive interlayer graphene coating current collector introduction electrochemical doublelayer capacitor edlc supercapacitor ultracapacitor fast energy storage delivery device power energy den sity performance traditional dielectric capaci tor power output cell chunhong lei constantina lekakou advanced material group department mechanical engineering science faculty engineering physical science university surrey guildford school chemistry university southampton southampton electrochem large energy storage alternative complementary power source application including telecommunication device standby power system portable electronic device hybrid electric vehicle phenolic resin shown flexible precursor highpurity carbon allowing production carbon material wide range pore structure phenolic resinderived fibre reported promising electrode material highperformance elec trochemical supercapacitor due specific area micro mesopore interconnected carbon bulk ensure free charged ion surface cloth made knitted carbon fibre directly electrode large area edlc cloth individual carbon fibre connected weaving knitting binder involved reduce bet coatingtype electrode furthermore cloth flexible tough cloth based edlc assem bled shape curved surface car easy scaledup disadvantage cloth include contact resistance aluminium foil commonly current collector supercapacitor free space carbon fibre waste electrolyte woven carbon fibre cloth compressed maximum fibre volume fraction resulting space carbon fibre carbon foil contact resistance low contact area lack adhesion carbon material aluminium surface intrinsic aluminium oxidation layer formed surface foil order reduce contact resistance modification current col lector necessary chemical change surface introducing conductive interlayer carbon cloth foil bind component together study modified foil toyalcarbo carbon black coated surface current collector previous study secondly conducting polymer poly ethylenedioxythiophenepolystyrene sulphonate ped otpss interlayer study pedot exhibit conductivity unusual stability oxidised state considered stable conducting polymer therefore researcher considered pedot electrode material supercapacitor conductive binder electrode previous study advantage aqueous pedotpss that drying pedotpss film highly conducting mechanically durable insoluble common solvent thirdly dag deflocculated achesontm graphite foil current collector study dag foil comprised dispersion highpurity micrographite particle thermoplastic material coated foil elevated temperature dag coating layer highly adhesive bind cloth firmly foil finally graphene material introduced carbon cloth order reduce contact resistance graphene utilised alternative elec trode material supercapacitor good performance due unique property large electrical conductivity vast surface area introduction graphene cloth increase capacitance reduce contact resistance graphene conducting interlayer study pristine graphene combined cloth electrophoretic deposition epd cloth spongy sufficient space accom modate nano material form binary composite textile study include investigation manu facturing interlayer cloth electrode current collector fabrication full edlc cell organic electrolyte tetraethyl ammonium tetrafluoroborate teabf propylene car bonate used edlc cell analysed electrochemical impedance spectroscopy eis gal vanostatic chargedischarge gcd experimental detail fabrication capacitor characterization method demonstration full edlc cell fabricated symmetric configuration cellulosebased paper separator square piece phenolic derived cloth kynol bet measured areal den sity thick active elec trode piece aluminium foil bare modified current collector contact carbon cloth electrolyte edlc tested eis gcd eis measurement edlc cell carried bias sinusoidal signal frequency range mhz eis measurement nyquist plot obtained analysed gcd test carried cell potential range current electrochem electrode carbonmodified foil toyalcarbo used surface foil thin carbon blackcoated layer held alc nano whisker alc nanometer scale whisker grown underneath oxide layer hence provide electric con ducting channel oxide layer serve mechanical locker hold carbon particle sur face cloth modified foil directly binder edlc electrode electrode dagcoated foil current col lector cloth bonded pressing weight heating block min cooling naturally carbon cloth adhere substrate fairly well electrode prepare pedot interlayer carbon black acet ylene based alfa aesar added pedotpss sigmaaldrich dispersion solution make slurry slurry coated foil bar coater gap yielded coat ing thickness dried immediately coating cloth top com pressed aid flat steel plate block dried oven cooling carbon cloth adhere substrate fairly well epd graphene activated carbon cloth unfunctionalized graphene produced liquidphase exfoliation graphite procedure reported hernandez graphite foil alfa aesar thick metal basis cut piece immersed nmp nmethylpyrrolidone exfoliated sonication highpower sonicator produced graphene dispersed nmp shown photograph fig graphene dispersion produced concentration approx mono layer yield approx absence defect oxide nmp chosen hansen solubility parameter hsp dhnmp close graphene dhgraphene mpa soproduced graphene fabri cation binary composite textile cloth epd fig unfunctionalized graphene sheet nmp negatively charged electric field graphene sheet migrate positive electrode adhere electrode surface vander waal force adhesion reinforced pvdf polyvinylidene fluoride immersing graphene coated cloth solution nmp pvdf minute fig graphene dispersed nmp graphene deposition cloth epd electrochem result discussion effect modified current collector display nyquist plot edlc cell made electrode inter layer carbon cloth foil nyquist plot solution resistance obtained left intersection point semicircle real axis diameter semicircle represent charge transfer resistance rct bulk solution resistance magnitude depend electrolyte conductivity material thickness separator rct charge transfer resistance separated component electronic ionic resistance electronic resistance include intrinsic electronic conductivity carbon material fibre electronic contact carbon fibre contact active layer current collector ionic resistance electrolyte ionic resistance inside pore electrode depend electrolyte con ductivity porous texture electrode thickness active layer nyquist plot total internal resistance cell rint estimated extrapolating low frequency straight curve nyquist plot intersect xaxis understand eis measurement gener alised equivalent circuit model fit nyquist plot equivalent circuit consist bulk solution resistance electrolyte charge transfer resistance rct interfacial contact capacitance electrical doublelayer capacitance cdl warburg impedance presented fig fitting equivalent circuit model carried eis spectrum analyser software equivalent circuit fig represent rct respectively constant phase element cpe cpe cpe cpe cdl respectively found nyquist plot fitted replacing pure capacitor warburg element constant phase element cpe parameter impedance element formula zcpe qjxn imaginary unit angular frequency cpe capacitor capacitance cpe resistor resistance unit ssn siemen second table present value parameter generalised equivalent circuit model type tested supercapacitor cell give fit data nyquist plot shown fig dashed line fit ting well indicating equivalent circuit fig represent actual supercapacitor cell cell constructed carbon contact difference charge transfer resistance rct cell contact resistance table cloth bare foil highest contact resistance rct dag interlayer reduced contact resistance considerably rct dag worked conducting adhesive bind individual carbon fibre surface contact resistance toyalcarbo pedot interlayer carbon cloth contact toyalcarbo carboncarbon contact pedot fig nyquist plot dotted line clothbased edlc current collector fitting dashed line equivalent circuit inset fig generalised equivalent circuit model supercapacitor cell equivalent circuit model eis spectrum analyser fitting electrochem worked conducting adhesive bind individual carbon fibre surface thus modified conducting interlayer greatly reduced conducting resistance prove carbon fibre foil contact resistance due low contact area lack adhesion carbon material surface intrinsic oxidation layer formed surface foil electrode lowest internal resistance rint electrode due penetration pedot bulk cloth heating pressing process preparation electrode addition reduced contact resistance conducting pedot cell pedot binder show highest capacitance biggest table due added pseudoca pacitance pedot display gcd curve cell current cell showed approxi mately linear chargedischarge curve suggesting electrode tested obvious redox reaction drop turning point chargedischarge line smaller cell modified current col lector due reduced contact resistance obvious current capacitance edlc cell similar cloth main contributor total capacitance slightly higher capacitance exhibited cell pedot binder discharge current discharge slop smaller added capacitance pseudocapacitance pedot smaller due slower chargedischarge process pseudocapacitance graphenecoated cloth pristine graphene deposited carbon cloth epd min solution graphene nmp prepared sonication graphite foil longer deposition time found increase amount graphene deposited carbon cloth epd time longer min resulted electrode increased resistance additional resistance graphene interlayer sem image fig show graphene sheet large range size adhered carbon fabric everywhere graphene sheet adhered cloth cloth dipped graphene dispersion applying voltage adhesion graphene carbon cloth vander waal force weak prevent graphene removal electrolyte pvdf added consequence pvdf polymer cover micropore carbon fibre magnified sem image fig electro chemical performance graphenecoated cloth analysed toyalcarbo current collector toyal carbo led lower contact resistance bare electrode easy prepare require heatpressing process integrate interlayer made system easier fabrication large pouch cell low contact resistance result direct carboncarbon contact carbon cloth beadslike carbon black surface toyalcarbo foil fig shown fig nyquist plot edlc cell bare cloth graphenecoated cloth electrode cell charge transfer resistance rct same fig gcd curve clothbased edlc current collector current table parameter generalised equivalent circuit model type cell derived numerical fitting eis experimental data cell electrode cpe ssn cpe ssn cpe ssn electrochem indicating graphene change contact resis tance however cell graphenecoated cloth show lower internal resistance rint higher capacitance reduction internal resistance graphenecoated cloth due filling bridging graphene sheet carbon fibre carbon fibre surface graphene increase capacitance providing additional surface area theacelectrodewithout increase total weight graphene light deposition graphene cloth changed weight gcd curve cell fig higher capacitance lower internal resistance graphenecoated carbon cloth electrode massspecific capacitance calculated discharge slope chargedischarge cycle current plotted current shown fig capacitance graphenecoated cloth low power end lower cloth graphene coating due blocking part themicropore carbonfibre thesemicropore contribute capacitancemainly lower power region however capacitance cloth drop rapidly increasing current decreaseof capacitancewith increasingcurrent slower beginning graphenecoated cloth caught surpassed cloth current increased constant large rang current translated higher energy density current graphenecoated cloth word rate performance improved fig sem image graphenecoated cloth epd surface toyalcarbo current collector electrochem conclusion phenolic resinderived clothbased edlc devel oped consistently performance applying differ ent modified foil current collector greatly reduced contact resistance pedot interlayer increased capacitance added pseudocapacitance epd coating graphene cloth changed weight produced obvious change per formance edlc cell reduced internal resistance increased capacitance improved rate performance reducing internal resistance acknowledgment study funded european com munity project autosupercap open distributed term creative common attribution international licence permit unrestricted use distribution reproduction medium provided give credit original author source provide link creative common licence made reference khomenko raymundopinero beguin highen ergy density capacitor organic electrolyte power source burke ultracapacitor why how technology power source tennison phenolicresinderived activated carbon catal szczurek jurewicz amarallabat fierro pizzi celzard structure electrochemical capacitance carbon cryogel derived phenolformaldehyde resin car bon xue yan liu tian effect activation carbon fibre phenolformaldehyde resin electro chemical supercapacitor electrochem nawa nogami mikawa application activated carbon fibre fabric electrode rechargeable battery organic electrolyte capacitor electrochem soc lei amini markoulidis wilson tennison lekakou activated carbon phenolic resin controlled mesoporosity electric doublelayer capacitor edlc mater chem markoulidis lei lekakou duff khalil martorana cannavaro method increase energy density supercapacitor cell addition multiwall carbon nan otube activated carbon electrode carbon saunder lekakou bader compression microstructure fibre plain woven cloth processing polymer composite compos saunder lekakou bader compression processing polymer composite mechanical microstructural study glass fabric resin compos sci technol lei markoulidis ashitaka lekakou reduction porous contact resistance electric double layer capacitor edlc electrochim acta groenendaal jonas freitag pielartzik reynold polyethylenedioxythiophene derivative past present future adv mater fig edlc bare graphenecoated cloth electrode toyalcarbo nyquist plot gcd curve fig ragone plot bare graphenecoated cloth electrode toyalcarbo electrochem ryu lee hong park kim kang park chang polyethylenedioxythiophene pedot polymer electrode redox supercapacitor elec trochim acta laforgue alltextile flexible supercapacitor electrospun polyethylenedioxythiophene nanofiber power source liu cho lee polyethylenedioxythiophene nanotube electrode material highpowered superca pacitor nanotechnology lei wilson lekakou effect poly ethylenedioxythiophene pedot carbonbased composite electrode electrochemical supercapacitor power source shao elkady zhang mousavi kaner graphenebased material flexible supercapacitor chem soc rev vermisoglou devlin giannakopoulou romanos boukos psycharis lei lekakou petridis trapalis reduced graphene carbide nanocomposite magnetic supercapacitor application alloy compd liu neff zhamu jang graphenebased supercapacitor ultrahigh energy density nano lett hernandez highyield production graphene liquidphase exfoliation graphite nature nanotech hansen hansen solubility parameter hand book crc press hernandez lotya rickard bergin coleman measurement multicomponent solubility parameter graphene facilitate solvent discovery langmuir stoller ruoff practise method deter mining electrode material performance ultracapacitor energy environ sci zhao gao burke measurement method determination internal resistance battery supercapacitor electrochem commun electrochem phenolic carbon clothbased electric doublelayer capacitor conductive interlayer graphene coating graphical introduction experimental detail fabrication capacitor characterization method electrode electrode electrode epd graphene activated carbon cloth result discussion effect modified current collector graphenecoated cloth conclusion acknowledgment reference","m_szGeo1":"","m_szSourceType":"source_academic","m_szSrcUrl":"http://download.springer.com/static/pdf/72/art%253A10.1007%252Fs10800-015-0909-x.pdf?originUrl=http%3A%2F%2Flink.springer.com%2Farticle%2F10.1007%2Fs10800-015-0909-x&token2=exp=1472582221~acl=%2Fstatic%2Fpdf%2F72%2Fart%25253A10.1007%25252Fs10800-015-0909-x.pdf%3ForiginUrl%3Dhttp%253A%252F%252Flink.springer.com%252Farticle%252F10.1007%252Fs10800-015-0909-x*~hmac=2e1d1d663195562c83cb9388a79d24e9c44afb2aeced1585d1cb6f0353767a84","m_Places":["Guildford","Uk","Southampton","Waals","Best","Nawa","Nogami","Amini","Groenendaal","Jonas"],"m_People":["Chunhong Lei","Constantina Lekakou","J Electrochem","Nano Lett","Y. Hernandez","Appl Catal","Saunders Ra","Electrochim Acta","Coleman Jn"],"m_Companies":["Department Of Mechanical Engineering Sciences","University Of Surrey","School Of Chemistry","University Of Southampton","X","Signal","Alfa","Sigma-aldrich","H2o","Gap","R2","Creative Commons","Lee Sb","Vermisoglou Ec","Crc","Af"],"m_BiGrams":["current collector","carbon cloth","contact resistance","carbon fibre","graphenecoated cloth","nyquist plot","equivalent circuit","internal resistance","edlc cell","activated carbon","cloth electrode","modified current","circuit model","power source","cloth epd","graphene sheet","charge transfer","transfer resistance","resistance rct","doublelayer capacitor","conductive interlayer","graphene coating","foil current","reduce contact","carbon material","electrode material","supercapacitor cell","reduced contact","gcd curve","phenolic carbon","electric doublelayer","interlayer graphene","phenolic resinderived","aluminium foil","cloth foil","epd graphene","greatly reduced","capacitor edlc","individual carbon","low contact","surface foil","current col","col lector","interlayer carbon","modified foil","carbon black","graphite foil","adhesive bind","resistance graphene","graphene cloth","organic electrolyte","contact carbon","eis measurement","pedot interlayer","solubility parameter","solution resistance","ionic resistance","generalised equivalent","fibre surface","clothbased edlc","higher capacitance","sem image","cpe ssn","energy density"],"m_TriGrams":["equivalent circuit model","modified current collector","charge transfer resistance","transfer resistance rct","reduced contact resistance","electric doublelayer capacitor","conductive interlayer graphene","interlayer graphene coating","activated carbon cloth","foil current collector","individual carbon fibre","reduce contact resistance","current col lector","generalised equivalent circuit"],"m_SocialTags":[],"m_Topics":[],"m_Industry":[],"m_Technology":[],"m_BiCnt":[18,17,17,14,12,11,10,9,8,7,6,6,6,5,5,5,5,5,5,4,4,4,4,4,4,4,4,4,4,3,3,3,3,3,3,3,3,3,3,3,3,3,3,3,3,3,3,3,3,3,3,3,3,3,3,3,3,3,3,3,3,3,3,3],"m_TriCnt":[6,5,5,4,4,3,3,3,3,3,3,3,3,3],"m_iDocBodyWordCnt":2034}
