{"m_szDocID":"672719","m_szDocTitle":"New Graphene + Carbon Nanotube Supercapacitor Rivals Lithium Battery | CleanTechnica","m_szYear":"2014","m_szDocSumamry":"Surprise Article!  Electric Cars  Solar Power  Wind Power  100% Renewable Energy?  RSS  Sponsor A Post  Advertise  CleanTechnica is the   #1 cleantech-focused  news & analysis site   in the world.  Subscribe today!  The future is now  .  About  About  Our Team  CleanTechnica Comment Policy  Use Of Our Content  Important Media Network  Important Media Jobs  Contact Us  Sponsor A Post  Buy Banner Ad Space  Local Solar Discounts  Electric Car Reviews  Audi A3 e-tron Review  BMW i3 Review  BMW i3 vs Mercedes B-Class Electric  BMW i3 vs Nissan LEAF vs Chevy Volt  BMW i3 vs Tesla Model S 70D  BMW i8","m_szDocBody":"surprise article electric car solar power wind power renewable energy sponsor post advertise cleantechnica cleantechfocused new analysis world today future team cleantechnica comment policy important media network important media job contact sponsor post buy banner space local solar discount electric car review audi etron review bmw review bmw mercede bclass electric bmw nissan leaf chevy volt bmw tesla model bmw tesla model cadillac elr porsche panamera ehybrid bmw chevy spark review chevy volt review chevy volt cost ownership review fiat review mercede bclass electric drive mitsubishi outlander phev review nissan leaf longterm review renault twizy review renault zoe review smart electric drive review smart electric drive camaro tesla model longterm review tesla model review tesla model review zach tesla model review kyle volkswagen egolf review volkswagen eup review exclusive page electric car report free exclusive cleantechnica event cleantechnica report cleantechnica review cleantech talk our podcast cleantechnica videos longterm nissan leaf review longterm tesla model review power solar energy new local solar discount solar solar energy wind energy new wind energy energy efficiency lighting led energy storage smart grid geothermal energy hydroelectricy marine energy biomass transport electric vehicle electric vehicle new electric car sale electric car greener tesla motor bicycle benefit bicycling biofuel car boat mass transit public transit train rail aviation shipping surprise navigation surprise article electric car solar power wind power renewable energy sponsor post advertise energy storage published tina casey graphene carbon nanotube supercapacitor rival lithium battery tina casey international team researcher recipe microscale flexible energy storage device made graphene carbon nanotube store energy rival gold standard lithium battery significant device battery supercapacitor charge discharge faster battery significant research team devised fabrication method result long fibre long metre long far open sort opportunity weaving supercapacitor clothing power portable electronic fibre double conductor place wire reduce size weight portable device including medical implant previous study supercapacitor published courtesy case western battery supercapacitor quick review battery supercapacitor store energy catch battery higher energy density mean store energy longer period low power density mean discharge quickly supercapacitor opposite problem low energy density mean store energy power density enable deliver energy rapidly needed trick solving energy density problem supercapacitor material proportion surface area energy storage graphene nanomaterial millennium material discovered year ago graphene consist sheet carbon atom thick twodimensional structure basically surface area notoriously finicky graphene present raft challenge translating power energy storage photovoltaic field taming graphene nanotube supercapacitor schematic work nanotube hybrid supercapacitor dingshang nanyang technological university singapore case western laming dai member current international research team china participating tsinghua university work tackled huge problem graphene effort shown hybrid approach promising graphene cooperating abovementioned technique for obtaining graphene film suffer lack film control leading loss surface area energy storage due graphene aggregation energy storage application therefore highly desirable onedimensional carbon nanotube cnt physically separate gns preserve graphene surface area study arrived selfassembly process solve problem resulting nanotube film hybrid supercapacitor fibre current study led yuan nayang technological university coauthored dai published nature nanotechnology detail team translated selfassembly technique long fibre solution acidoxidized singlewall nanotube graphene oxide ethylenediamine promote synthesis dope graphene nitrogen pumped flexible narrow reinforced tube called capillary column heated oven hour advantage structure enormous amount surface area energy storage charge conduction clocking whopping square metre gramme fibre favourable comparison lithium demonstrated solid state microsupercapacitor research team assembled nanotube fibre polyvinyl acid gel electrolyte device achieved density microwatt hour cubic millimetre research team compare microamperehour thin film lithium battery found interesting fibre arranged pair fibre arranged sery voltage tripled time stayed same however pair arranged parallel output current time tripled significant advantage cost supply chain issue compared lithium carbon nanotube graphene cheaper readily available lending assist favourable cost comparison hybrid supercapacitor appear longer lifecycle conventional rechargeable battery team tested supercapacitor cycle performance retention percent conventional rechargeable generally lose performance hit cycle mark cap off fibre retained performance subjected flexibility stress test stay tuned research team thinking ahead applying supercapacitor battery solar cell microbial fuel cell follow google latest clean tech new cleantechnica newsletter drive electric car complete short survey electric car report date hottest cleantech new subscribing free cleantech newsletter eye sectorspecific new also free solar energy newsletter electric vehicle newsletter wind energy newsletter share reddit open window share google open window share linkedin open window share open window share flipboard open window friend open window share pinterest open window share open window share tumblr open window print open window share pocket open window press this open window tag carbon nanotube case western university graphene supercapacitor tina casey specialise military corporate sustainability advanced technology emerging material biofuel water wastewater issue tinas article reposted frequently reuter scientific american site view expressed own follow google related post researcher hack fluffy powder solve energy storage riddle common bug open door nextgen graphene solar cell solarpowered graphene evaporator zap dirty water bacteria graphene demo work tiny farmingdale john sound encouraging comparison lith battery bank car mile range battery density range graphene supercap mile range percentage size graphene supercap chi zeta ive reading nanotube capacitor year hint theyll sale kent beuchert cotton corner wayne williamson carbon cheaperpretty free copper make conductor copper cheaper multi billion trillion dollar industry fun stuff carbon fibre for let copper demand million tonne billion kilos dollar kilo billion dollarsok trillion khisanthus carbon common true processing energy make conducting trivial boris sound good true catch mint really volumetric density isnt close lithium ion cell tiny button cell good result compared thin film lithium battery apparently dont scale well application pretty limited back top follower follow fan subscriber fan follow follower follow fan love advertisement top storey cleantechnica tesla model deliver gas vehicle history gasoline automotive service dealer america exec tesla battery improvement tesla model randy carlson dive american electric power ceo love tesla buy tesla wind solar alternative energy anymore world allelectric sanitation truck lineup launched byd beijing environmental sanitation engineering sponsor cleantechnica bring brand million reader month advertisement cool cleantech event yale sustainability leadership forum haven bringing business government ngos academia examine concept sustainability detail cleantech event advertisement cleantechnica electric car report address cost solar panel reason solar wind win wind solar price beat fossil illuminating solar chart advantage solar power solar power fact michael liebreich evs solar akon tesla evs solar tesla model faq answered evannex tesla model review tesla model exclusive video tesla model exclusive picture tesla model review video tesla model review pic nissan leaf longterm review president iceland evs solar impulse pilot interview cheque cleantechnica videos join solar revolution network cleantechnica cleantechfocused new analysis website world focusing primarily electric car solar energy wind energy energy storage part important media network progressive blog working make world better greener place follow produced entertainment purpose only opinion comment published sanctioned necessarily represent view sustainable enterprise media inc owner sponsor affiliate subsidiary sustainable enterprise media surprise article electric car solar power wind power renewable energy sponsor post advertise back top send address address cancel post cheque addresse cheque failed sorry blog share post email","m_szGeo1":"United States","m_szSourceType":"source_general","m_szSrcUrl":"https://cleantechnica.com/2014/05/12/new-graphene-carbon-nanotube-supercapacitor/","m_Places":["United States","Banner","Tesla","Kyle","Nanyang","Singapore","Dai","China","Farmingdale, Ny","Lith","America","Beijing","New Haven , Retweet","Iceland"],"m_People":["Mercedes-benz B-class","Chevy Volt","Renault Twizy","Renault Zoe","Tina Casey","Case Western University","Dingshang Yu","Yuan Chen","Gen Graphene","Kent Beuchert","Wayne Williamson","Randy Carlson","Michael Liebreich","Evannex Tesla"],"m_Companies":["Cleantech","Audi A3","Bmw","I3","Cadillac","Volkswagen","Solar Energy","Tesla Motors","Tsinghua University","Cnts","Nayang Technological University And Co","Volt","Twitter","Google","Reddit","Linkedin","Flipboard","Pinterest","Facebook","Reuters","Scientific American","American Electric Power","Engineering Group","Fossils","Im Network","Progressive"],"m_BiGrams":["tesla model","open window","electric car","energy storage","window share","model review","solar power","carbon nanotube","research team","surface area","car solar","sponsor post","nissan leaf","wind energy","lithium battery","store energy","surprise article","article electric","power wind","wind power","power renewable","renewable energy","energy sponsor","post advertise","important media","chevy volt","electric drive","longterm review","review tesla","car report","solar energy","electric vehicle","tina casey","battery supercapacitor","case western","energy density","density mean","area energy","hybrid supercapacitor","evs solar"],"m_TriGrams":["open window share","tesla model review","electric car solar","article electric car","car solar power","solar power wind","renewable energy sponsor","energy sponsor post","sponsor post advertise","review tesla model","electric car report","surface area energy","area energy storage"],"m_SocialTags":[],"m_Topics":[],"m_Industry":[],"m_Technology":[],"m_BiCnt":[15,12,11,9,8,7,5,5,5,5,4,4,4,4,4,4,3,3,3,3,3,3,3,3,3,3,3,3,3,3,3,3,3,3,3,3,3,3,3,3],"m_TriCnt":[8,7,4,3,3,3,3,3,3,3,3,3,3],"m_iDocBodyWordCnt":1153}
