{"m_szDocID":"673062","m_szDocTitle":"10 Uses for Graphene - The World's Strongest Material","m_szYear":"2013","m_szDocSumamry":"World  Exploration  Science  Shows  Seekers  Discovernator  Election 창혱\u0085 2016  Follow us  World  Exploration  Science  Shows  Seekers  Election 창혱\u0085 2016  History  Global Issues  Politics  100 Years Ago: Shackleton Rescued His Men  Traces of Prehistoric Baked Salmon Found  Tribes Block Construction of Dakota Access Pipeline  Meet The Next Generation of Aviation Engineers  Russian Hackers Blamed for Voter Database Attacks  Gender Doesn't Matter to U.S. Voters  Adventure  Ideas  Culture  Montana Tourism  100 Years Ago: Shackleton Rescued His Men  Riders Bungee-Cycle off Victoria Falls Bridge  Sho","m_szDocBody":"world exploration science show seeker discovernator election follow world exploration science show seeker election history global issue politic year ago shackleton rescued men trace prehistoric baked salmon found tribe block construction dakota pipeline meet generation aviation engineer russian hacker blamed voter database attack gender matter voter adventure ideas culture montana tourism year ago shackleton rescued men rider bungeecycle victoria fall bridge boston change time zone significance storytelling ancient bonfire tradition techsavvy twist areas men higher marriage rate incredible beauty montana glacier national park awesome animal tech space human earth age aerospace zimbabwe dehorning adult rhinos curb poaching tasmanian devil evolving resistance deadly tumour tattoos skin literally spaceage fusion machine underway ghost particle slowing star tattoos skin literally year ago shackleton rescued men trace prehistoric baked salmon found year ago shackleton rescued men vast reef revealed great barrier reef chapter startup chapter moving mail earth tech history human animal space shark feed boston change time zone year ago shackleton rescued men russian hacker blamed voter database attack spaceage fusion machine underway trace prehistoric baked salmon found ancient hand grenade found israel random russian hacker blamed voter database attack zimbabwe dehorning adult rhinos curb poaching tasmanian devil evolving resistance deadly tumour mystery groove mar moon finally understood sending animal space north atlantic great white shark nursery found millionyearold shark cannibal seeker daily dnew seeker storey dnew shot awe spain uks complicated relationship kosovo survive independent state random ghost particle slowing star meet generation aviation engineer pilot explain deep desire fly tattoos skin literally origin tattoo culture world significance storytelling seeker posted dnew tech top world strongest material graphene strong lightweight conduct electricity resist rust sheet graphene thin single atom thick graphene world material thinnest electronic material invented consisting layer carbon atom single atom thick atom arranged hexagonal pattern weigh nothing coming gramme square metre analysis nanotube spun spool wire lightweight graphene time stronger steel thickness conduct heat electricity copper outstanding optical mechanical property produced industrial scale graphene revolutionise field electronic body armour recently european union awarded finnish company nokia billion research grant commercialise graphene areas graphene make huge difference sooner think graphene repel water mixed polymer work rustproofing coating graphene repel water highly conductive combination steel coming contact water slow electrochemical reaction oxidise iron suny buffalo chemist designed polymer coating exotic form carbon painted steel coating dipped coated metal brine stay rustfree entire month coating eliminate rusted car forever analysis rare green rust offer glimpse ancient seas graphene transmit heat energy electrical current make sound university texas won suk university texas researcher put layer graphene single nanometer thick glass type plastic next ran alternating current layer produced sound graphene speaker thin transmit heat energy electrical current make sound vibrating diaphragm made shape computer chip graphene supercapacitor make battery obsolete photo capacitor store charge plate discharge quickly common electronic power camera flashes capacitor store lot charge supercapacitor typically made layer ordinary carbon store more capacitor hold power unit weight battery electronic new supercapacitor power laptop day graphene change that etched laser create surface area turn capacitor store energy ordinary carbon brethren capacitor cycle battery failing future graphene supercapacitor power electronic electric car microscopic bit graphene oxide bind radioactive contaminant make cleaning nuclear waste safe cheap karen graphene oxide remarkably good absorbing radioactive waste researcher rice university lomonosov moscow state university found microscopic bit graphene oxide bind radioactive contaminant turning clump easily collected new nuclear plant powered spent fuel cleaning nuclear accident fukushima disaster big mining natural gas drilling industry generate lot naturallyoccurring contaminant local water supply integrated circuit made graphene made researcher ibm ibm silicon semiconductor chip give computer brainpower process binary code fundamental building block digital information graphene potential process faster silicon conduct electricity better power generating heat mean laptop operate time faster cooling fan year giant ibm developed working graphenebased processor wireless device company digital core design poland announced built processor work tablet graphene processor reaching consumer year manufacturer refine fabrication process layer graphene affixed polymer crumple straighten current run laguna photo sheet graphene crumple paper difficult flatten out duke university scientist recently attached graphene prestretched rubber sheet found sheet relaxed graphene adhered rubber crumpled led layer graphene polymer expanded contracted current run key component building artificial muscle new artificial muscle stronger real graphene foam pick small concentration explosive compound nikhil koratkar graphene foam pick small concentration nitrate ammonia found explosive sensor developed rensselaer polytechnic institute size postage stamp day regular part kit carried bomb squad graphene turned foam philtre sequence dna moon dallas controlling size pore graphene make kind philtre sort dna molecule size capability researcher sequence dna lower cost current technique person currently sequencing person genome cost time that san franciscobased life technology rolled machine year job unfortunately machine composite fibre made graphene carbon nanotube stronger kevlar conventional bulletproof vest tim australian researcher found make fibre composite material made graphene stronger kevlar adding equal amount graphene carbon nanotube polymer produced superstrong fibre spun fabric make bulletproof vest fibre strengthen material layer graphene dotted lead sulphide create ultrasensitive flexible photodector night vision john image photodetector computer chip convert photon light electrical signal digital camera made silicon frank koppen colleague institute photonic science barcelona dotted layer graphene lead sulphide created ultrasensitive flexible photodector lead thinner cameras lightweight night vision goggle material science graphene material nanotechnology electronic related storey tasmanian devil evolving resistance deadly tumour mystery mar crater chain solved dog interesting seti signal detected noise alien star jar spaceage fusion machine underway amazing storey world exploration science show seeker discovery digital network animalist defranco network dnew revision seeker sourcefed corporate discovery communication viewer relation advertising career discovery privacy policy online closed captioning visitor agreement copyright discovery communication llc leader global entertainment","m_szGeo1":"United States","m_szSourceType":"source_general","m_szSrcUrl":"http://www.seeker.com/top-10-uses-for-the-worlds-strongest-material-1767195089.html","m_Places":["United States","Victoria Falls","Boston","Why Areas","Zimbabwe","Israel","North Atlantic","Spain","Uk","Kosovo","Buffalo","Ancient Seas","Fukushima","Laguna","Ut","Dallas","Barcelona"],"m_People":["Moon Kim","Karen Kasmauski","Nikhil Koratkar","Tim Graham","John Moore","Frank Koppens"],"m_Companies":["Baked","Cycle","Savvy","Particles","Awe","European Union","Nokia","Suny","University Of Texas","Ji Won","Ab Still Ltd","Corbis","Capacitors","Rice University","Lomonosov","Moscow State University","Ibm","Duke University","Real","Rensselaer Polytechnic Institute","Sygma","Getty Images","Institute Of Photonic Sciences","Seti Signal","Defranco Network","Discovery Communications","Discovery Communications, Llc."],"m_BiGrams":["shackleton rescued","rescued men","layer graphene","world exploration","exploration science","science show","show seeker","trace prehistoric","prehistoric baked","baked salmon","salmon found","russian hacker","hacker blamed","blamed voter","voter database","database attack","tasmanian devil","devil evolving","evolving resistance","resistance deadly","deadly tumour","tattoos skin","skin literally","spaceage fusion","fusion machine","machine underway","capacitor store","graphene oxide","made graphene"],"m_TriGrams":["year ago shackleton","ago shackleton rescued","shackleton rescued men","world exploration science","exploration science show","science show seeker","trace prehistoric baked","prehistoric baked salmon","baked salmon found","russian hacker blamed","hacker blamed voter","blamed voter database","voter database attack","tasmanian devil evolving","devil evolving resistance","evolving resistance deadly","resistance deadly tumour","tattoos skin literally","spaceage fusion machine","fusion machine underway"],"m_SocialTags":[],"m_Topics":[],"m_Industry":[],"m_Technology":[],"m_BiCnt":[5,5,5,3,3,3,3,3,3,3,3,3,3,3,3,3,3,3,3,3,3,3,3,3,3,3,3,3,3],"m_TriCnt":[5,5,5,3,3,3,3,3,3,3,3,3,3,3,3,3,3,3,3,3],"m_iDocBodyWordCnt":939}
