{"m_szDocID":"675539","m_szDocTitle":"Fiber Reinforced Rebar","m_szYear":"2008","m_szDocSumamry":"Toggle navigation  News  Companies  TOP 200 Companies  Full Directory  Amazon  Apple  Boeing  Ebay  Facebook  Google  IBM  Microsoft  Nike  Qualcomm  Samsung  Sony  MIT  UC  Topics  Augmented Reality  Beverage  Brain  Cancer  Cloud Computing  Electric Vehicle  Gesture  Golf  Graphene  Machine Learning  Medical Device  Robots  Solar  Social Network  Virtual Reality  Wearables  Login / Register  Free Services    MONITOR KEYWORDS  Enter keywords & we'll notify you when a new patent matches your request (weekly update).  ORGANIZER  Save & organize patents so you can view them later.  ARCHIVE  View","m_szDocBody":"toggle navigation new company top company full directory amazon apple boeing ebay ibm microsoft nike qualcomm samsung sony mit topic augmented reality beverage brain cancer cloud computing electric vehicle gesture golf graphene machine learning medical device robot solar social network virtual reality wearable freeservice monitor keyword enter keyword notify patent matches request weekly update organiser save organise patent later archive month keyword email company directory patent sorted company follow browse patent prev fibre reinforced rebar title fibre reinforced rebar abstract composite reinforcing bar formed providing reinforcing material supply fibre strand roving resin supply bath puller pulling resinimpregnated reinforcing material resin bath reinforcing fibre include sery roving longitudinal bar helical wrapping roving wrapped roving opposed direction wrapping resin permeated roving wrapped roving outer surface roving part thereof wrapped roving exposed bulged outwardly tension applied wrapping curing bulged part defining component outer surface portion bar rough exposed engaging material reinforced transfer longitudinal load material reinforced roving winnipeg inventor randel brandstrom uspto applicaton patent description claim data uspto patent application fibre reinforced rebar advertise freshpatentscom rate info monitor keyword tracking patent relating fibre reinforced rebar patent application ### keyword monitor work free service freshpatent take second fill keyword monitored week receive patent application related keyword start now receive info patent app fibre reinforced rebar areas interest ### previous patent application composite facer wallboard protective composite facer method manufacture patent application method producing nanofibre mesofibre electrospinning colloidal dispersion industry class stock material miscellaneous article viewing fibre reinforced rebar patent info result second interesting freshpatentscom category qualcomm monsanto yahoo corning ### data source patent application published public domain united state patent trademark office uspto information published purpose only freshpatent affiliated uspto assignee company inventor law firm assignee patent application document image trademark respective freshpatent responsible accuracy validity content public document patent application filing complete provided however case presented sampling full patent application display purpose freshpatentscom browse patent prev patent info application publish date document file date uspto class uspto classe international class drawing follow browse patent prev fibre reinforced rebara composite reinforcing bar formed providing reinforcing material supply fibre strand roving resin supply bath puller pulling resinimpregnated reinforcing material resin bath reinforcing fibre include sery roving longitudinal bar ","m_szGeo1":"United States","m_szSourceType":"source_general","m_szSrcUrl":"http://www.freshpatents.com/Fiber-reinforced-rebar-dt20081023ptan20080261042.php","m_Places":["Enter","United States","Winnipeg"],"m_People":["Randel Brandstrom"],"m_Companies":["Amazon","Apple","Boeing","Ebay","Facebook","Google","Ibm","Microsoft","Nike","Qualcomm","Samsung","Sony","Uc","Twitter","Uspto","Monsanto","Yahoo","Corning","United States Patent And Trademark Office"],"m_BiGrams":["fibre reinforced","reinforced rebar","reinforcing material","browse patent","patent prev","wrapped roving"],"m_TriGrams":["fibre reinforced rebar"],"m_SocialTags":[],"m_Topics":[],"m_Industry":[],"m_Technology":[],"m_BiCnt":[7,6,4,3,3,3],"m_TriCnt":[6],"m_iDocBodyWordCnt":363}
