{"m_szDocID":"679383","m_szDocTitle":"Humber Gateway Offshore Transmission Project Reaches Financial Close | CleanTechnica","m_szYear":"2016","m_szDocSumamry":"textArticle -------------------- Humber Gateway Offshore Transmission Project Reaches Financial Close September 8th, 2016 by Joshua S Hill   International infrastructure group Balfour Beatty announced Thursday that it had reached financial close for the £162.9 million Humber Gateway offshore transmission project which will connect North Sea offshore wind with the east Yorkshire coast in England. Balfour Beatty revealed on Thursday that its consortium with investment firm Equitix reached financial close for the £162.9 million Humber Gateway offshore transmission project — of which Balfour Beatt","m_szDocBody":"humber gateway offshore transmission project reaches financial close joshua hill international infrastructure balfour beatty announced reached financial close the million humber gateway offshore transmission project connect north sea offshore wind east yorkshire coast england balfour beatty revealed consortium investment firm equitix reached financial close the million humber gateway offshore transmission project balfour beatty invest million total required equity million separately european investment bank announced providing million project link humber gateway offshore wind farm electricity grid humber gateway offshore wind farm capacity project generating wind turbine kilometerseast spurn point coast east riding yorkshire north sea england resulting humber gateway offshore transmission project comprise highvoltage electricity transmission link connecting wind farm owned aeon onshore transmission grid owned operated balfour beatty equitix consortium period year fourth ofto contract reach financial close establishes position offshore transmission market ian rylatt balfour beatty investment chief executive technical expertise ensure efficiently effectively support government target meet uks energy renewable source equitixs commitment offshore transmission market testament investor appetite long term availabilitybased inflationlinked infrastructure added hugh crossley equitixs chief investment officer pleased working partnership balfour beatty ofgem benefit investor stakeholder involvement european investment bank eib continue group phenomenal achievement investing european renewable energy project decade world largest international public bank eib invested than billion energy infrastructure investment harness uks offshore wind resource clean energy creating thousand skilled job country jonathan taylor european investment bank vicepresident offshore transmission connexion key part uks future energy infrastructure european investment bank pleased support significant investment connect humber gateway windfarm national network scheme represent tenth offshore transmission link supported europe longterm lending institution year drive electric car complete short survey electric car report date hottest cleantech new subscribing free cleantech newsletter eye sectorspecific new also free solar energy newsletter electric vehicle newsletter wind energy newsletter ","m_szGeo1":"United States","m_szSourceType":"source_industry","m_szSrcUrl":"https://cleantechnica.com/2016/09/08/humber-gateway-offshore-transmission-project-reaches-financial-close/?utm_source=feedburner&utm_medium=feed&utm_campaign=Feed%3A+IM-cleantechnica+%28CleanTechnica%29","m_Places":["Gateway","North Sea","Yorkshire","England","Uk","Europe"],"m_People":["Joshua S Hill","Balfour Beatty","Ian Rylatt","Hugh Crossley","Jonathan Taylor"],"m_Companies":["Equitix","European Investment Bank","Eib"],"m_BiGrams":["offshore transmission","humber gateway","gateway offshore","balfour beatty","transmission project","financial close","offshore wind","european investment","investment bank","wind farm"],"m_TriGrams":["humber gateway offshore","gateway offshore transmission","offshore transmission project","european investment bank"],"m_SocialTags":[],"m_Topics":[],"m_Industry":[],"m_Technology":[],"m_BiCnt":[8,7,6,6,4,4,4,4,4,3],"m_TriCnt":[6,4,4,4],"m_iDocBodyWordCnt":292}
