{"m_szDocID":"680336","m_szDocTitle":"Economic Growth Has Decoupled From Carbon For Good | CleanTechnica","m_szYear":"2016","m_szDocSumamry":"textArticle -------------------- Economic Growth Has Decoupled From Carbon For Good September 13th, 2016 by Michael Barnard   Economic advancement goes through stages: agriculturally dominated societies to industrially dominated societies to consumer and information worker societies. It’s typically only as the shift to the consumer and information worker societies occurs that significant negative externalities such as climate change and air pollution start to be truly addressed by most nations. Industrially dominated societies require a tremendous amount of cheap energy. The cheapest form of e","m_szDocBody":"economic growth decoupled carbon good michael barnard economic advancement stage agriculturally dominated society industrially dominated society consumer information worker society typically shift consumer information worker society occur significant negative externality climate change air pollution start addressed nation industrially dominated society require tremendous amountof cheap energy cheapest form energy long time coal coal hideous negative externality short term long term short term polluting form energy weve discovered nox sox hydrocarbon particulate emission typically make city region coal heavily polluted significant population health impact longer term cleanup cost basically coal foul nest coal large source coal producing time weight fouling nest fouling planet simplistic argument made greenhouse gas emission developed developing economy argument aimed arguing side heavy lifting argument increasingly irrelevant arent unreasonable argument heart unreasonable way reasonable side rich developed country source emission atmosphere naturally occurring emission bear lion share cost dealing problem posited cash transfer rich economy poor economy reasonable argument there global agency world bank providing financial support clean energy good grid part that limiting support coal similarly rich country invested heavily wind solar technology manufacturing supply chain driving cost technology globally poorer country buy clean technology cheaply reasonable side posited place reasonable side developing world majority future emission from dont solve problem them wont good clean nest rationalisation continuing drive suvs burn gas developed world china cited anything action traditionally developed country nought however fixing nest necessary capita emission dwarf developing world global problem pointing finger claiming insignificance rich australia doesnt wash important factor pay attention set discussion globally gross domestic product decoupled emission time year past year trending year gdp rising emission flat itself empirical observation invalidate argument country emit order richer country world richer carbon emission stayed flat causation broken worth developed nation transitioned consumer information worker stage mean increased gdp inherently lower energy requirement form economy banking information technology luxury good further farther scale driving efficiency part information worker element led ubiquitous fraction lifetime energy emission previous lighting product automobile truck fleet mileage standard driving transportation emission capita down peak car reached urban densification good transit system prevalent country care health populace population health strong correlation population economic effectiveness clean air promote growth clean water promote growth heavily regulated efficiency driven country greatest penetration renewable mentioned earlier europe leader usa leader let leader promise path developing nation take china turned capacity installed globally year itself turned lot coal plant stopped permit coal plant built part centrally planned economy intentionally bringing people poverty rapidly country region world lot coal argue rich require coal argument china isnt industrialization hasnt transitioned consumer information worker status massive work clean air fouled pleasant side effect primary purpose dropping lot carbon emission big stake climate change course pearl river delta guangzhou centre largest urban centre world huge source chinas economic miracle heavily threatened climate change vast plain shallow river rising ocean china weighed cost benefit realised climate change continue lot economic prosperity threatened hideous air pollution chinas growth astoundingly good country reached peak coal leader developing world follow suit make world solar panel couple biggest wind turbine oem largest electric vehicle sale country globally byd firm sell pretty much brand global sure common analyst bloomberg energy predict slipping oil consumption due electric vehicle ive analysis show softening growth actual decline starting impact ridesharing autonomy leading potential peak car scenarios back pure economic argument wind energy global price cent usd kwh lcoe jurisdiction longer rare baseline onshore wind energy negative externality solar energy regularly cent usd kwh lcoe good condition falling price faster wind energy directly competitive jurisdiction tropical one fossil fuel generation today outcompete tomorrow negative externality mainstream automotive manufacturer delivering multiple affordable developed world standard fully partially electric vehicle year california bellwether pure electric growth eating hybrid growth meaning shift starting dominate china supportive country world evs key pragmatic programme maximise deployment happening battery price plummeting too virtuous cycle wind solar grid lower carbon wind solar manufacturing are wind solar grid lower carbon electric car are wind solar generation electric car country cleaner air water reducing negative health impact wind solar renewable economic driver require capital outlay manufacturing distribution construction operation employ people job lot virtuously employed coal industry money part people working solar usa coal electric car economic driver transformation opportunity growth economy china betting big taking largest industrial market world what clear country insist building coal answer economic wont competitive country shift renewable instead wont employ people pay electricity push negative externality populace effective driver economy pollution inhibitor productivity drive electric car complete short survey electric car report date hottest cleantech new subscribing free cleantech newsletter eye sectorspecific new also free solar energy newsletter electric vehicle newsletter wind energy newsletter tag china climate change coal electric car electricity energy gdp green economy united state michael barnard past year michael analysing report article decarbonization technology business model policy piece electrical generation transformation electrification transportation published cleantechnica newsweek slate forbe huffington post quartz reneweconomy renewablesinternational gizmag included textbook thirdparty article analyse interview mike published dozen new site globally reached reddit science work originate quoracom mike top writer annually published climatefiction novel guangzhou future tense related post ","m_szGeo1":"United States","m_szSourceType":"source_industry","m_szSrcUrl":"https://cleantechnica.com/2016/09/13/economic-growth-decoupled-carbon-good/?utm_source=feedburner&utm_medium=feed&utm_campaign=Feed%3A+IM-cleantechnica+%28CleanTechnica%29","m_Places":["Most","China","Australia","Europe","United States","Atmosphere","Guangzhou","California"],"m_People":["Michael Barnard"],"m_Companies":["World Bank","Path","Pearl River","Delta","Solar Energy","Newsweek","Forbes","Huffington Post","Reddit","Quora"],"m_BiGrams":["wind solar","electric car","information worker","negative externality","climate change","consumer information","electric vehicle","wind energy","dominated society","reasonable side","developing world"],"m_TriGrams":["consumer information worker"],"m_SocialTags":[],"m_Topics":[],"m_Industry":[],"m_Technology":[],"m_BiCnt":[6,6,5,5,5,4,4,4,3,3,3],"m_TriCnt":[4],"m_iDocBodyWordCnt":846}
