{"m_szDocID":"683379","m_szDocTitle":"San Francisco: It’s Time Not Just to Divest, But Reinvest","m_szYear":"2016","m_szDocSumamry":"textArticle -------------------- San Francisco: It’s Time Not Just to Divest, But Reinvest February 7, 2014 by Billy Parish Leave a Comment The Board of Supervisors recently passed a resolution urging The City’s Retirement Board to divest municipal pension funds of $583 million in fossil fuel stocks. The Retirement Board didn’t take up the recommendation, opting instead to join shareholder resolutions promoting change in the fossil fuel industry and to continue to study the possibility of full divestment. This result is not ideal, but it does pave the way for a historic discussion. As the boar","m_szDocBody":"san francisco time divest reinvest billy parish leave comment board supervisor recently passed resolution urging city retirement board divest municipal pension fund million fossil fuel stock retirement board didnt recommendation opting join shareholder resolution promoting change fossil fuel industry continue study possibility full divestment result ideal pave historic discussion board study divestment discover powerful financial argument selling fossil fuel stock highlight question major implication city divest reinvest san franciscowould largest institutional investor divest fossil fuel first university religious organisation insurer municipality dumping dirty energy stock consideration financial ethical recent report group standard poor hsbc warned fossil fuel industry face immense systemic risk government follow commitment reduce carbon emission world reserve oil coal remain underground writeoff asset cost fossil fuel investor including pensioner trillion dollar pressing institutional investor representing trillion asset recently asked fossil fuel company conduct urgent risk assessment stock performance lowcarbon scenario forsan francisco financial risk posed investing fossil fuel starker recent nature study estimated sealevel rise incur billion dollar annual damage bay area word fossil fuel produce return pensioner theyll cripple future municipal budget divestment avoiding risk present powerful opportunity reimagine city divested fund reinvest local green infrastructure money weve putting globalised fossil fuel stock build worldleading cleanenergy economy home california trouble infrastructure billion investment projected decade government feasibly borrow doesnt account climate change start prepare infrastructure world rising sea level drought fire dramatically accelerate transition clean energy transportation system imagine kind jump start halfbillion dollar investment imagine city public school covered solar panel financed public pensioner imagine resource equal vision ambition city energy efficiency electric vehicle public transportation importantly imagine doubling capacity cleantech innovation world urban population growing fast concern climate change investing climate solutionssan franciscowould position spend decade exporting ideas product key word invest asset manager financial researcher learning return investment clean infrastructure match exceed return investment fossil fuel industry moreover local infrastructure investment provide pension fund manager hedge volatility inflation global market san franciscois verge realising huge opportunity divest fossil fuel fitting city lead tough moral issue reinvest cleanenergy economy live other equally powerful part municipal reputation part innovation bold thinking persistent belief power build brighter future logged post comment logged post comment energy collective column coming soon latest comment nathan wilson model masdar institutemit collaboration support cooler sustainable abu dhabi reducing urban heatisland effect guess city choose light coloured pavement may steven howard johnson sierra club michael brune offer lousy excuse nuclear energy position support approach proper approach sierra club affirm may josh nilsen saudi arabia realism vision saudi arabia represent wrong country horrific inequality ram may advisory panel scott edward anderson consultant blogger media commentator blog green sceptic christine hertzog consultant author professional explainer focused smart grid elias hinckley strategic advisor energy finance energy policy investor energy company government gary hunt gary executiveinresidence deloitte investment extensive experience energy utility industry jesse jenkin graduate student researcher mit expertise energy technology policy innovation jim pierobon help trade government agency company communicate cleaner energy solution geoffrey style managing director gsw strategy group llc awardwinning blogger featured contributor may may ","m_szGeo1":"United Kingdom","m_szSourceType":"source_news","m_szSrcUrl":"http://www.theenergycollective.com/billyparish/337406/san-francisco-it-s-time-not-just-divest-reinvest","m_Places":["Bay Area","California","Abu Dhabi","Saudi Arabia","Gary"],"m_People":["Billy Parish","Nathan Wilson","Steven Howard","Michael Brune","Josh Nilsen","Scott Edward","Christine Hertzog","Elias Hinckley","Hunt Gary","Jesse Jenkins","Jim Pierobon","Geoffrey Styles"],"m_Companies":["Board Of Supervisors","Standard & Poor","Hsbc","Masdar Institute","Guess","Sierra Club","Deloitte","Strategy Group, Llc"],"m_BiGrams":["fossil fuel","fuel stock","fuel industry"],"m_TriGrams":["fossil fuel stock","fossil fuel industry"],"m_SocialTags":[],"m_Topics":[],"m_Industry":[],"m_Technology":[],"m_BiCnt":[12,3,3],"m_TriCnt":[3,3],"m_iDocBodyWordCnt":503}
