{"m_szDocID":"696049","m_szDocTitle":"Fuel-efficient cars enough to curb US greenhouse gases : Nature News","m_szYear":"2004","m_szDocSumamry":"Published online 25 October 2004 |  Nature  | doi:10.1038/news041025-7 News Fuel-efficient cars enough to curb US greenhouse gases Today's technology could have immediate impact on global warming. Helen Pearson No need to wait for tomorrow's technology.Â© Photodisc The United States could slash its greenhouse gas emissions by switching to today's fuel-efficient cars, US scientists have calculated, challenging the idea that reducing emissions is too expensive or will require new technologies to be developed. Many methods have been put forward to curb emissions of heat-trapping carbon dioxide, su","m_szDocBody":"published online nature new fuelefficient car curb greenhouse gase today technology impact global warming helen pearson wait tomorrow technology photodisc united state slash greenhouse gas emission switching today fuelefficient car scientist calculated challenging idea reducing emission expensive require technology developed method put forward curb emission heattrapping carbon dioxide growing plantation tree soak gas idea stop ploughing farm field slow release carbon dioxide normal bacterial breakdown plant waste robert jackson william schlesinger duke university durham north carolina wanted realistic proposal are figure previously published study calculated widespread measure slice carbon emission farmer stopped tilling cropland country switched alternative farming technique left land fallow carbon emission drop researcher report today proceeding national academy science order hit target land planted forest sop carbon dioxide reduce food supply unknown additional consequence environment study show people expect method jackson point limit united state could however achieve emission cut doubling fuel efficiency car sport utility vehicle suvs jackson schlesinger estimate show switching existing hybrid electric vehicle run partly electricity reduce emission cheaply robert jackson duke university durham north carolina price pay cleaner car hybrid vehicle cost thousand dollar conventional gasguzzler jackson exercise highlight small existing technology make considerable dent emission were now cheaply say additional price subsidy consumer hike gasoline price encourage driver switch hybrid vehicle suggest showing car make big difference really important agree chris field specialist global climate change carnegie institution washington stanford california its set calculation say action united state pump greenhouse gase country world environmentalist criticised president bush taking action pulling kyoto protocol international pact curb emission bush administration focuse voluntary emission cut longerterm improvement fuel efficiency move hydrogenpowered vehicle nuclear energy jackson study show current technology ability lower pollution now united state adopt drastic step clean field country struggle achieve cut equivalent required industrialised country kyoto agreement reduction relative level equate cutback today level say single policy technology switch make big dent pollution field combined make real difference the sum compatible finding solution say duke university durham north carolina ","m_szGeo1":"United States","m_szSourceType":"source_academic","m_szSrcUrl":"http://www.nature.com/news/2004/041025/full/news041025-7.html","m_Places":["United States Greenhouse","United States","Durham, North Carolina","Jackson","California","Kyoto"],"m_People":["Helen Pearson","Robert Jackson","William Schlesinger"],"m_Companies":["Duke University","Proceedings Of The National Academy Of Sciences","Target","Carnegie Institution Of Washington","Bush Administration"],"m_BiGrams":["united state","carbon dioxide","duke university","university durham","durham north","north carolina"],"m_TriGrams":["duke university durham","university durham north","durham north carolina"],"m_SocialTags":[],"m_Topics":[],"m_Industry":[],"m_Technology":[],"m_BiCnt":[4,3,3,3,3,3],"m_TriCnt":[3,3,3],"m_iDocBodyWordCnt":328}
