{"m_szDocID":"725376","m_szDocTitle":"South Australia Aims For 100% Renewable Energy","m_szYear":"2015","m_szDocSumamry":"South Australia Aims For 100% Renewable Energy December 11th, 2015 by Giles Parkinson   Originally published on RenewEconomy . South Australia is expected to pass its 50 per cent renewable energy target next year – nearly a decade ahead of schedule – and the Labor government will now aim to get the state as close to 100 per cent renewable energy as possible. Premier Jay Weatherill said in Paris on Monday that the state was leading the world in the incorporation of variable renewable energy sources such as wind and solar, and hoped the knowledge gained would create a massive economic opportunit","m_szDocBody":"south australia aim renewable energy gile parkinson originally published reneweconomy south australia expected pass cent renewable energy target year decade ahead schedule labour government aim state close cent renewable energy possible premier jay weatherill paris state leading world incorporation variable renewable energy source wind solar hoped knowledge gained create massive economic opportunity state struggling decline longterm industry car manufacturing running big international experiment now weatherill launch paris compact state region initiative state region reduce emission tonne long skinny transmission system cent renewable energy including lot wind solar technology breakthrough largescale storage pumped hydro battery massive technological challenge exciting opportunity state south australia cutting edge transition fossilfuel based economy energy system dominated technology wind solar storage coal fired power generator due close year cent renewable energy target formally announced year met ahead time addition snowton wind farm construction hornsdale wind farm growth rooftop solar state threshold indeed australian energy market operator forecast state daytime demand occasion met rooftop solar decade recently undertook scenario planning suggested state reach close cent renewable energy decade reality state cent renewable electrification transport bigger priority close interview later reneweconomy weatherill state aim close cent renewable energy could part plan attain net emission attract billion investment state decade close cent renewable power possible weatherill interviewthere small proportion baseload power system period time effective solution storing energy wind solar dispatching peak period remove baseload power fossil fuel energy source transition closely scrutinised huge number detractor fossil fuel interest nuclear lobby mainstream media recent outage caused equipment failure blamed state reliance wind energy weatherill conceded state taking risk real choice demise traditional industry car manufacturing huge opportunity clean technology challenge here weatherill told reneweconomy big risk big opportunity imperative strong planet state state point transformation risk show future community like that said mover opportunity solve these issue south australia other turn exciting challenge burden state focusing transport electrify bus private car network keen attract interest electric vehicle manufacturing conduct tender fleet government vehicle conceivably electric vehicle manufacturer the contract ly general motor holden cease manufacturing state driverless car technology supporting capital city adelaide push large carbon neutral city world target hope achieve decade state government city council pushed incentive encourage battery storage home businesse weatherill called tender ensure government electricity demand met renewable energy south australia hosting royal commission nuclear fuel cycle release report late month predicting nuclear technology cost wind solar decade chance nuclear power built south australia australia appear negligible nuclear viable south australia nation viable country building frightening amount coal fired power station weatherill said weatherill admitted resistance quarter number climate sceptic reducing noted south australia fair share prominent sceptic like senator corey bernardi senator nick minchin other point interesting note comment california governor jerry brown joint press conference brown california reach cent renewable energy plan fiercely resisted business powerful fossil fuel lobby decarbonising global economy economy require heroic undertaking brown said lot opposition pointed thefossil fuelindustry sceptical resistant people business community elected official opposition silent vote regulatory policy needed job weatherill business decarbonisation opportunity attract company lowcarbon plan part business objective frankly driven theiremployee ethical offering attracting good people great company part ofthe hightech innovative future state believed massive advantage mover economy make adjustment earliest reap benefit avoid worst cost australias federal government announce longterm renewable target weatherill hoping cooperative environment destuctive negative attitude climate change year wanted canberra remove uncertainty renewable energy target project struggling gain finance agreement cut ret earlier year reintroduce carbon price prime minister supportive scheme party him reprinted permission cleantechnicas completely free electric car report electric car early adopter follower want date hottest cleantech new subscribing free cleantech newsletter eye sectorspecific new also free solar energy newsletter electric vehicle newsletter wind energy newsletter tag australia south australia gile parkinson founding editor reneweconomycomau australianbased website new analysis cleantech carbon climate issue gile based sydney watching slow quickening transformation australias energy grid great interest related post gile please energy electricity roughly half energy ronald brakel falsely blamed state reliance wind energy power outage caused failure state operating interconnector undergoing repair spin gas capacity cover shortfall wind power gile the author this phrased sentence slip tongue very people this gile type word minute tongue alone ","m_szGeo1":"United States","m_szSourceType":"source_industry","m_szSrcUrl":"http://cleantechnica.com/2015/12/11/south-australia-aims-for-100-renewable-energy/","m_Places":["Paris","Adelaide","Australia","California","Canberra","Sydney"],"m_People":["Giles Parkinson","Jay Weatherill","Corey Bernardi","Nick Minchin","Jerry Brown","Ronald Brakels"],"m_Companies":["Target","Labor Government","Indeed","General Motors"],"m_BiGrams":["renewable energy","south australia","cent renewable","wind solar","close cent","energy target","fossil fuel","wind energy","electric vehicle"],"m_TriGrams":["cent renewable energy","close cent renewable","renewable energy target"],"m_SocialTags":[],"m_Topics":[],"m_Industry":[],"m_Technology":[],"m_BiCnt":[11,9,9,5,4,3,3,3,3],"m_TriCnt":[7,4,3],"m_iDocBodyWordCnt":692}
