{"m_szDocID":"727616","m_szDocTitle":"Directory: Mike Adams and Natural News - PESWiki","m_szYear":"2016","m_szDocSumamry":"Directory: Mike Adams and Natural News From PESWiki A directory of links to Natural News and other selections by Mike Adams, the \"Health Ranger\" Page first featured Oct. 17, 2010 Mike Adams Pure Energy Systems News Oct. 17, 2010 I've been following the work of Mike Adams for a couple of years now, and have a deep admiration and respect for the work he is doing, not only in alerting people to important health issues that you will not hear in the mainstream press, but other issues as well, whether political, spiritual, or other, including clean energy technology advancements. I'm sure we would b","m_szDocBody":"directory mike adam natural new peswiki directory link natural new selection mike adam health ranger featured oct mike adam pure energy system new oct work mike adam couple year now deep admiration respect work doing alerting people important health issue hear mainstream press issue well political spiritual other including clean energy technology advancement good friend circle friend large overflowing wife who made aware adam considered moving community project vilcabamba ecuador couple year ago encourage free daily newsletter amazing people compiling important material time day read list headline day inbox morale boost knowing people giving support life exposing vast corruption exist today world impede emergence superior method phenomenon apply alternative health nutrition alternative energy realise lot alt health website there personally natural new favourite pretty pay attention limited time addition great reporting writer great entertainer great instructive parody videos political cartoon great work mike official website bio coverage mike adam free energy destroy planet mike premise extremely pessimistic assuming humankind continue trajectory foreseeable future free energy blog conspiracy media spell media hypnosis simple test mike adam show media hypnotic method people official storey mark twain said its easier fool people convince fooled naturalnew conspiracy health vaccination blaylock expose obamas nazi healthcare system vaccine autism interview melissa melton blaylock addresse psychotropic drug that mass shooter taking induce homicidal tendency vaccine minimal effect state purpose irreversibly damage immune system damaging brain cdc complicit massive medical fraud youtube infowar featured top trend zeitgeist highlight review free energy prediction year bring technology market predicted year due you deserve yet lack adequate awakening great progress made highlight leading trend upward fading gratefully pesn conspiracy health mike adam infowar top health conspiracy storey mustsee video heath ranger mike adam naturalnewscom leading alternative media giant interview david ortiz infowar nightly new leading health tyranny storey trend including vaccination industry fraud psychosis population barrage health affront proposition election fraud gmo danger youtube thealexjoneschannel conspiracy health gmos romney project bain propel monsanto monsanto brink failure due blowback agent orange pcb bain capital romney rescue portraying monsanto prestigious agribusiness biotech company introducing brighter future romney bain recommended monsanto focus business genetically engineered crop roundup massively profitable and hugely detrimental weed killer organic natural new trend zeitgeist free energy prediction plus happen addition prediction big unknown big happen left field foresee talking gamechanging big perhap invention bonafide free energy device contact nonhuman civilization planet natural new conspiracy occupied america senate bill military detain murder antigovernment protester american city national defence authorization act openly legalise government detainment murder ows protester assassination talk show host blogger journalist hold socalled antigovernment point view open blatant declaration war tsa thug reaching pant goldman sach economic takeover nation secret arrest torture american citizen act outright tyranny waged outofcontrol government natural new infowar featured exotic trend rossi alternative media fail free energy promotion activist leadership role potential free energy provide affordable backup power case short longterm grid failure provide clean cheap distributed energy create zillion job reinvigorate world economy instil hope depressed time alternative media playing instigating leadership roll ignoring topic pesn beforeitsnew conspiracy infowar infowarsmoneybombcom meant link couple day ago running weekend lot amazing material covered hour blitz heard george noory david icke joel skousen jame corbett charlotte iserbyt jesse ventura mike adam katherine albrecht webster tarpley posted thealexjoneschannel november featured health conspiracy writer natural new citizen journalist natural new cover alternative health issue cover alternative energy included answer sample writing questionnaire include screening process consideration pesn beforeitsnew nuclear drawback meltdown fukushima worse meltdown government report devastating meltthrough occurred fukushima official suggest japan uninhabitable recent report confirming reactor fukushima daiichi nuclear facility completely melted hour devastating earthquake tsunami trumped worse new reactor melted through situation the worst possibility nuclear accident natural new health cannabis hemp medicine politic science understanding cannabis therapeutic censored milestone quietly occurred month federal government prefer ignore yet step direction hundred thousand million people centuriesold botanical medicine cannabis natural new humanpowered piezoelectric technological breakthrough generate free power portable device simple body movement scientist georgia institute technology breakthrough discovery utilise zinc oxide nanowire generate electricity strained flexed body movement day eliminate external charging system natural new nuclear drawback japan scramble avert nuclear meltdown official worked desperately stop fuel rod damaged reactor overheating government building housing reactor risk exploding blast blew roof day complex mile north tokyo fear fuel rod cool melt container house core explode releasing radioactive material wind reuter naturalnew edt health buyer beware mainstream media website promoting acai berry diet weight loss scam weird belly fat tip ads take fraudulent newslooking claim minimal shipping charge free sample small print bottom announcing nonrefundable oneyear membership fee charged day impose fee continued product shipment furthermore acai berry health benefit weight loss them natural new conspiracy health emergency preparedness black madness reveal animalistic behaviour modern people mike adam produced excellent minute video poison modern diet caused chemical labotamy brain human population diminish social advancement make ready act animalistic way stress imagine behave food water scarce natural new alt fuel microorganism fuel production bacteria make car fuel thin air enzyme produced common soil bacterium produce usable automobile fuel vehicle exhaust pipe study conducted researcher university california california institute technology deprived nitrogen oxygen supplied carbon monoxide vanadium nitrogenase produce twotothreeatom carbon chain ethane propane natural new battery electric vehicle govt energy government investing billion battery technology electric vehicle obama administration invested billion advanced battery industry attempt make united state world foremost supplier battery electric car natural new conspiracy health new mike adam gmo music video feature health ranger rapping danger genetically modified food written performed michael adam song take aim biotech industry exposing danger genetically engineered food promoting nongmo project verified logo help consumer identify food free dangerous gmos naturalnew oct conspiracy health big pharmas secret global eugenic agenda video mike adam health ranger overview upsidedown value pharmaceutical industry benefit sickness facilitate intentional thinning herd medication vaccination heal create mindset dependency youtube thealexjoneschannel oct global warming conspiracy climate depict children assassinated reducing carbon footprint video interview health ranger mike adam alex jone show clip campaign climate change campaign depict children blown classroom green agenda disturbing read enthusiastic comment support reader guardian sick eugenic mentality infowar oct corbett report alt fuel biofuel source bioelectricity scientist discover recharge laptop cell phone soda pop vegetable oil saint louis university researcher created fuel cell produce electricity technology borrowed natural biological powerhouse biofuel cell transform sugar fat energy running host machine device reported national meeting american chemical society natural new bioenergetic body natural electricity human eye emit energy beam psychiatrist colin ross people shoot energy beam eye claim published data supporting hypothesis anthropology consciousness titled the electrophysiological basis evil eye belief natural new oil ecological impact gulf oil disaster conspiracy gulf coast police state law enforcement conspire intimidate journalist local law enforcement department homeland security working british petroleum fascist corporatocracy police state america answer financial interest corporation expense freedom people one parish extra shift week devoting security detail paying sheriff office natural new health conspiracy inject the swine flu vaccine song music video health ranger mike adam touches point swine flue manmade vaccine intentionally noxious health vitamin natural remedy flus part big brother control paradigm aug codex threaten health billion eat healthy food supplement choice rapidly vanishing effort made dark coming nutricide codex alimentarius scheduled full global implementation word spoken main stream media threat humanity natural new ","m_szGeo1":"United States","m_szSourceType":"source_industry","m_szSrcUrl":"http://peswiki.com/index.php/Directory:_Mike_Adams_and_Natural_News","m_Places":["Health Ranger","Ecuador","Take","The States","Romney","America","Best","Fukushima","Japan","Tokyo","United States"],"m_People":["Michael Adams","Mark Twain","Blaylock","Melissa Melton","Heath Ranger","David Ortiz","George Noory","David Icke","Joel Skousen","James Corbett","Charlotte Iserbyt","Jesse Ventura","Katherine Albrecht","Webster Tarpley","Just Say No","Rapping","Alex Jones","Colin A. Ross"],"m_Companies":["Entertainer","Cdc","Youtube","Monsanto","Bain Capital","Senate","U.s. Military","U.s. Government","Goldman Sachs","Georgia Institute Of Technology","Reuters","University Of California","California Institute Of Technology","Us Government","Obama Administration","Guardian","Saint Louis University","American Chemical Society","Gulf Oil","Bp","Department Of Homeland Security","British Petroleum"],"m_BiGrams":["natural new","mike adam","free energy","conspiracy health","health ranger","health conspiracy","ranger mike","alternative media","new conspiracy"],"m_TriGrams":["ranger mike adam","natural new conspiracy"],"m_SocialTags":[],"m_Topics":[],"m_Industry":[],"m_Technology":[],"m_BiCnt":[19,14,7,6,5,3,3,3,3],"m_TriCnt":[3,3],"m_iDocBodyWordCnt":1214}
