{"m_szDocID":"727739","m_szDocTitle":"Top 10 States for Electric Cars | CleanTechnica","m_szYear":"2011","m_szDocSumamry":"Top 10 States for Electric Cars December 27th, 2011 by Zachary Shahan     SolarChargedDriving.com recently created a list of the top 10 states in the U.S. for electric cars . It’s got a nice, long intro to the topic and a paragraph for each of the top states. Below, I’m just going to share their list and some of the key points they make about each state. Essentially, the whole analysis is based on the electricity mix of each state — how clean it is. For more, check out the full post, linked above. Idaho! Say what? Yep, Idaho is a cleanest energy leader (at least as far as air pollution and glo","m_szDocBody":"top state electric car zachary shahan solarchargeddrivingcom recently created list top state electric car nice long intro topic paragraph top state below share list key point make state essentially analysis based electricity mix state clean more cheque full post linked above idaho what yep idaho cleanest energy leader air pollution global warming concerned hydropower generate full percent idahos electricity add renewable mix jump percentnatural gas cleanburning source energy fossil fuel source the environmental impact drilling natural gas issue account additional percentless percent idahos electricity produced burning coalplug idaho extremely close drive air pollutionfree car dont solarcharge washingtonhydro power king washington accounting percent state electricity production add renewable percent electricity washington produced essentially air pollution whatsoeverjust percent washington electricity dirty coal oregonoregon percent electricity hydro power make top sweep northwest united state add renewable equation percent electricity generated oregon generated airpollution freenatural gas account percent oregon electricity coal generate percent maine getenergyactiveorg percent maine electricity generated nonhydro renewable other yes total biofuel including wood add percent hydropower percent electricity youre drawing plugin maine generated renewable energy formsnatural gas account percent meaning approaching percent electricity produced maine generated clean form energy california getenergyactiveorghydro produce percent californias electricity nonhydro renewable account percent mean onethird state electricity generated renewable energy form natural gas account bulk californias electricity percentcoal percent californias electricity south dakotathis shocker ussouth dakota generate percent electricity renewable energy form percent hydro percent nonhydro renewable otherhowever pretty rest electricity burning coal percentadditionally south dakota isnt friendly residential renewable energy investment solar fact worst state solar due state statemandated utility incentive such rebate homeowner montana percent electricity generated hydropower montana south dakota outperform california percent renewable energy front however rank sixth montana produce electricity nonhydro renewable just percent additionally burning coal account percent montanas electricity generation californias tiny percent coal minnesotaminnesota make position state plug plugin ranking due thecomparativelyhigh amount electricity generate nonhydro renewable form percentanother percent produced hydro pushes total electricity generated renewable energy form percentof course percent minnesotas electricity generated burning coal plug plug couple year buying one can put solar panel residential wind turbine offset state comparatively heavy reliance coal hampshirein hampshire percent electricity produced renewable energy form this include hydro percent burning coalhowever nuclear energy generate percent hampshire electricity youre pronuke mean plug plugin dont change thing youre and not putting solar panel home planting home wind turbine yard home yard offset hampshire nuke percent electricity burning coal yorkif energy diversity gig york place live plug innuclear energy account electricity production empire state percent natural gas percent close behind hydro power percent nonhydro renewable accounting additional percent electricity produced coal percent oil percent round diverse mix york finetuned analysis tackle biggest electricity mix driving electric car air climate course individual simple step power electric car solar panel make irrelevant state live trump option cleantechnicas completely free electric car report electric car early adopter follower want date hottest cleantech new subscribing free cleantech newsletter eye sectorspecific new also free solar energy newsletter electric vehicle newsletter wind energy newsletter tag california eashington idaho maine minnesota montana hampshire york oregon south dakota zachary shahan tryin and specy letter time spend time cleantechnica director chief editor otherwise enthusiastically fulfilling duty obsession gas solar love planetsave bikocity president important media zach recognised globally solar energy electric car energy storage wind energy expert speak related conference event connect social media zacharyshahancom related post hydrogen technology anonymous make hydrogen natural gas put atmosphere renewable energy make hydrogen water waste electricity mile electricity directly hydrogen inefficient store power power source guest intentioned sending wrong message electricity sourced coal efficient gas engine mention advantage evs evs charge night power utilisation lowest take longer green entire auto fleet green power industry jumpstarting industry hmm encouraging people state and know top list fun youre discourage implying hope ","m_szGeo1":"United States","m_szSourceType":"source_industry","m_szSrcUrl":"http://cleantechnica.com/2011/12/27/top-10-states-for-electric-cars/","m_Places":["United States","Idaho","Yep, Idaho","Washington","Oregon","Northwest United States","Maine","California","South Dakota","Additionally, South Dakota","Minnesota","Best","New Hampshire","New York","Most","Eashington , Idaho , Maine","New York , Oregon"],"m_People":["Zachary Shahan"],"m_Companies":["Jumpstarting"],"m_BiGrams":["percent electricity","renewable energy","electric car","electricity generated","nonhydro renewable","natural gas","electricity produced","account percent","energy form","burning coal","top state","add renewable","gas account","generate percent","generated renewable","californias electricity","south dakota","solar panel"],"m_TriGrams":["renewable energy form","generated renewable energy","percent electricity produced"],"m_SocialTags":[],"m_Topics":[],"m_Industry":[],"m_Technology":[],"m_BiCnt":[10,8,7,6,6,4,4,4,4,4,3,3,3,3,3,3,3,3],"m_TriCnt":[4,3,3],"m_iDocBodyWordCnt":627}
