{"m_szDocID":"727780","m_szDocTitle":"East Anglia gets world's largest offshore wind farm","m_szYear":"2014","m_szDocSumamry":"June 19th, 2014 by Tina Casey   No, seriously, NUTS 2 is a thing. But first let’s get to the world’s largest offshore wind farm-to-be. Earlier this week the UK greenlighted an offshore wind farm called East Anglia One, which they’re billing as one of the biggest wind farms in the world. What’s with the qualifier? If built as planned the new project will sport 240 wind turbines.  That tops the London Array , which is the current global offshore record holder (a proposed expansion of the Array has been shelved for now, btw). Offshore wind farm (cropped) courtesy of EAOW. World’s Largest Offshore","m_szDocBody":"tina casey seriously nut thing let world largest offshore wind farmtobe earlier week greenlighted offshore wind farm called east anglia one theyre billing biggest wind farm world what qualifier built planned project sport wind turbine top london array current global offshore record holder proposed expansion array shelved now btw offshore wind farm cropped courtesy eaow world largest offshore wind farm east anglia offshore wind farm project announced department energy climate change earlier week agency bill turbine project cheque project information uks national infrastructure planning portal impressive writing plan call wind turbine installed capacity megawatt located kilometre coast suffolk cover area addition turbine project include offshore collector converter station kilometre seabed cable needed national grid connexion bramford substation bramford plan call onshore cable duct needed east anglia one because project suggest beginning offshore wind power developer east anglia joint venture energy developer scottish power renewable part iberdrola group sweden vattenfall wind power stateowned utility company moniker east anglia offshore wind limited venture right develop offshore wind farm capacity east anglia zone keeping score home offshore wind power million typical home humming along space staked offshore wind farm east anglia four happened company aiming total wind farm shale gas too shale gas angle truth universally acknowledged carbon asset ground out department energy climate enthusiastic embrace wind power set exploiting shale gas reserve move mounting evidence link oil gas fracking earthquake earthquake however piece decc policymaking record earlier year agency launched ambitious solar plan part broader energy roadmap update included plan nuclear energy too nut fracking east anglia time explain nut nut stand nomenclature unit territorial statistic wont detail here note east anglia classified nut region fracking boil east anglia year follow google cleantechnicas completely free electric car report electric car early adopter follower want date hottest cleantech new subscribing free cleantech newsletter eye sectorspecific new also free solar energy newsletter electric vehicle newsletter wind energy newsletter tag east anglia east anglia wind farm offshore wind farm tina casey specialise military corporate sustainability advanced technology emerging material biofuel water wastewater issue tinas article reposted frequently reuter scientific american site view expressed own follow google related post nut tla sorry tla stand letter acronym ill post sit corner feel bad wasting cleantechnica server storage jameswimberley british conservative politician love fracking free money landowner immensely unpopular oil gas industry clout usa offshore wind fairly pricey option politically line resistance happening huge scale meaning playing role offshore wind germany fulfilled solar sugar daddy price affordable else ","m_szGeo1":"United States","m_szSourceType":"source_industry","m_szSrcUrl":"http://cleantechnica.com/2014/06/19/east-anglia-gets-worlds-largest-offshore-wind-farm/","m_Places":["Uk","London","Suffolk","Sweden","United States","Germany"],"m_People":["Tina Casey"],"m_Companies":["Scottish Power","Iberdrola Group","Vattenfall","Anglia Offshore Wind Limited","Department Of Energy","Eu","Twitter","Google","Reuters","Scientific American"],"m_BiGrams":["offshore wind","east anglia","wind farm","wind power","shale gas"],"m_TriGrams":["offshore wind farm"],"m_SocialTags":[],"m_Topics":[],"m_Industry":[],"m_Technology":[],"m_BiCnt":[13,12,10,4,3],"m_TriCnt":[7],"m_iDocBodyWordCnt":410}
