{"m_szDocID":"728911","m_szDocTitle":"Hydrogen Storage-Fuel Cell System to Smooth Out Intermittent Wind Power in Germany | CleanTechnica","m_szYear":"2011","m_szDocSumamry":"Hydrogen Storage-Fuel Cell System to Smooth Out Intermittent Wind Power in Germany October 12th, 2011 by Andrew   Photo courtesy of Siemens AG Ontario’s Hydrogenics has won a contract to supply a hydrogen production, storage and fuel cell system to the German city of Herten, the Mississauga-based company announced today. Developing the means to manage intermittent electricity generation from wind power farms has been a key challenge for grid operators, one that Herten city officials decided was best addressed by using a Hydrogenics’ HySTAT 30 hydrogen generator to electrolyze water, storing th","m_szDocBody":"hydrogen storagefuel cell system smooth intermittent wind power germany andrew photo courtesy siemen ontarios hydrogenic won contract supply hydrogen production storage fuel cell system german city herten mississaugabased company announced today developing mean manage intermittent electricity generation wind power farm key challenge grid operator herten city official decided addressed hydrogenic hystat hydrogen generator electrolyze water storing resulting hydrogen converting back electricity hydrogenic hypm kilowatt fuel cell power system electrolyzing water hydrogen excess intermittent renewable energy optimal clean pathway smart grid stabilisation energy storage capacity hydrogenic president ceo daryl wilson stated press release real advantage alternative energy storage solution pleased globally recognised hydrogen cluster city herten awarded opportunity demonstrate capability wind power storage emission conversion system key benefit entire hydrogen production storage power generation process accomplished carbon dioxide emission common produce hydrogen fuel cell natural gas lesser growing extent biogas electrolyzing water produce hydrogen require energy costly system herten however ready availability electricity wind power local water resource success system large implication germany country energy industry strive shut nuclear power plant replace lost electrical power electricity clean renewable power source project make big impact fortune nasdaqlisted developer manufacturer hydrogen generation fuel cell system located state north rhine westphalia herten recognised major german hydrogen cluster electromobility renewable energy project press release success provide hydrogenic proven solid system market widely germany europe shared fortune fortune fuel cell system hydrogen production storage company tied degree commercial fuel cell rely hydrogen gas feedstock produce electricity hydrogenic active both demand hydrogen production storage fuel cell system ramping globally commercialization fuel cell vehicle viewed key driver recently released report pike research forecast commercialization fuel cell vehicle fcvs accelerate grow reach billion annual revenue demand asiapacific region outstrip region pike research possibility business prospect equally great combination wind powerhydrogen generation storagefuel cell system prove successful september hydrogenic announced received million million worth order deliver electrolyzer unnamed company asia south america ensuing month hydrogen storage fuel cell cheque out cleantechnicas completely free electric car report electric car early adopter follower want date hottest cleantech new subscribing free cleantech newsletter eye sectorspecific new also free solar energy newsletter electric vehicle newsletter wind energy newsletter tag fcvs fuel cell vehicle fuel cell germany renewable power grid stabilisation herten hydrogen economy hydrogenic renewable energy storage renewable power storage andrew reporting writing wide range topic nexus economic technology year now asiapacific europe americas africa middle east issue related broad topical areas pose tremendous opportunity challenge define quality live relationship natural environment related post ","m_szGeo1":"United States","m_szSourceType":"source_industry","m_szSrcUrl":"http://cleantechnica.com/2011/10/12/hydrogen-storage-fuel-cell-system-to-smooth-out-intermittent-wind-power-in-germany/","m_Places":["Germany","Ontario","Herten","Mississauga","United States","Europe","Asia","South America","Africa","Middle East"],"m_People":["Daryl Wilson"],"m_Companies":["Siemens Ag","Nasdaq","Ramping","Nexus"],"m_BiGrams":["fuel cell","cell system","wind power","hydrogen production","production storage","storage fuel","renewable energy","energy storage","renewable power","cell vehicle"],"m_TriGrams":["hydrogen production storage","fuel cell system","storage fuel cell","fuel cell vehicle"],"m_SocialTags":[],"m_Topics":[],"m_Industry":[],"m_Technology":[],"m_BiCnt":[12,6,4,4,4,3,3,3,3,3],"m_TriCnt":[4,4,3,3],"m_iDocBodyWordCnt":410}
