{"m_szDocID":"729317","m_szDocTitle":"The Future of Germany's Wind Industry","m_szYear":"2014","m_szDocSumamry":"Originally Published in the ECOreport goodmorning windraeder – Photo by Dirk Ingo Franke, CC by SA 2.0 Germany has long been one of the world’s leading centers of the wind industry, so I welcomed an opportunity to question Esther Frey, renewable energies expert at Germany Trade & Invest (GTAI), about this technology’s effectiveness and future development. GTAI is the foreign trade and inward investment promotion agency of the Federal Republic of Germany. Ms Frey provided some valuable insight into the future of Germany’s Wind Industry. Esther Frey, renewable energies expert at Germany Trade & ","m_szDocBody":"originally published ecoreport goodmorning windraeder photo dirk ingo franke germany long world leading centre wind industry welcomed opportunity question esther frey renewable energy expert germany trade invest gtai technology effectiveness future development gtai foreign trade investment promotion agency federal republic germany frey provided valuable insight future germany wind industry esther frey renewable energy expert germany trade invest gtai addition climate change western europe drive adapt renewable technology arise scarcity fossil fuel germany possesse lignite coal dependent imported gas oil make vulnerable external force unexpected price rise renewable energy source offer reduce dependence import improve energy supply security frey pointed germany started develop renewable energy technology wind solar early hope obtain energy renewable source course climate change major factor germany move renewable energy said enshrined federal government energy plan energiekonzept renewableenergy source act eeg purpose act facilitate sustainable development energy supply sake protecting climate environment reduce cost energy supply national economy incorporating external longterm effect conserve fossil fuel promote development technology generation electricity renewable energy source wind blow time wind farm example produce average nameplate capacity europe term full load hour limited knowing break point andthat complicated factor considered geographical condition wind speed cost project type turbine characteristic curve etc german wind farm inter city express berlin courtesy john seb barber impressed fact germany offshore wind project achieve equivalent full load theestimate onshore facility lower performing areas achieved average record german wind load document but again figure limited themselve schleswigholstein expected achieve electricity renewable however majority power wind state feed huge amount electricity german grid windy day frey said electricity consumed rest germany wind state import energy german grid schleswigholstein hope producing time electricity require wind constant technology require backup article george taylor palmetto energy research told generally fossil fuel producing plant coal gas expensive run capacity flexibility fossil fuel power plant depend technology fossil fuel used frey wrote generally speaking gas power plant flexible coal power plant affect ability produce socalled balancing power peak electricity demand efficient run fossil fuel power plant full capacity share renewable energy increase germany today major challenge integrate fluctuating renewable energy wind solar energy infrastructure ensuring demand met supply germany electricity renewable energy source wind energy wind energy supplied nation electricity demand order harvest desired amount renewable energy germany upgrade transmission grid transmit electricity wind solar efficiently areas overproduction areas lack supply develop technology capture store excess electricity untilit needed storage device operation project planned future frey wrote project supported eur million german government funding example vanadium redox flow battery pilot project schleswigholstein planned summer capacity mwh enough theory supply home day built optimise grid integration braderuptinningstedt wind farm lithiumion battery store mwh feldheim planned start operation year project younicos schwerin coming online year mwh battery stabilise grid frequency region power gas project electrolysisrhwka pilot project altenbrak running aeon pilot project falkenhagen system output megawatt equivalent hydrogen hour die schlei chez eskay germany investing large sum money developing grid infrastructure storage system investment transmission grid amount eur year nep initial draught dena estimate investment eur needed period integration grid technology dena verteilnetzstudie eur planned offshore grid connexion already partly completed onep draught term storage capacity required important note germany integrated european market frey said grid connect european country developed further enable renewable energy distributed europe delivered region demand high integration european grid investment transmission distribution grid germany storage system necessary result switch renewable technology germany saved theequivalent million metric tonne electricity tonne heat tonne biofuel tonne link this nation emission grown past yearsm frey retirement nuclear power station play role power station retired period pointed toa twh increase energy export candidate cleantechnicas completely free electric car report electric car early adopter follower want date hottest cleantech new subscribing free cleantech newsletter eye sectorspecific new also free solar energy newsletter electric vehicle newsletter wind energy newsletter tag esther frey germany wind industry gtai vanadium redox flow battery wind industry windplusstorage roy hale editor ecoreport website dedicated exploring lifestyle choice technology affect west coast north america write cleantechnica planetsave important media research junkie written thousand article published roy live corte island canada related post ","m_szGeo1":"United States","m_szSourceType":"source_industry","m_szSrcUrl":"http://cleantechnica.com/2014/07/04/future-germanys-wind-industry/","m_Places":["Germany","Federal Republic Of Germany","Europe","United States","Inter City","Berlin","Schleswig","Schwerin","North America","Cortes Island","Canada"],"m_People":["Dirk Ingo","Esther Frey","George Taylor","Chez Eskay","Dena Verteilnetzstudie","Roy L Hales"],"m_Companies":["John Seb"],"m_BiGrams":["renewable energy","fossil fuel","wind industry","power plant","esther frey","germany wind","energy source","energy supply","wind solar","electricity renewable","wind farm","wind energy","pilot project"],"m_TriGrams":["renewable energy source"],"m_SocialTags":[],"m_Topics":[],"m_Industry":[],"m_Technology":[],"m_BiCnt":[11,6,4,4,3,3,3,3,3,3,3,3,3],"m_TriCnt":[3],"m_iDocBodyWordCnt":677}
