{"m_szDocID":"738901","m_szDocTitle":"Tech Videos : Discovery News","m_szYear":"2016","m_szDocSumamry":"  Discovery News Follow @dnews Tech    Alternative Power Sources Apps Biotechnology Gear and Gadgets Robotics Tech Videos Featured Cities Have Unique Bacterial Fingerprints Space    Alien Life & Exoplanets Galaxies Asteroids, Meteors & Meteorites History of Space Private Spaceflight Space Videos Featured Watching a Spacecraft Wreck Tumble Through Space Human    Psychology Genetics Health Evolution Life Human Videos Featured Prince: Why Tenors Rule in Pop Music Earth    Weather & Extreme Events Plants Oceans Global Warming Earth Videos Featured Polar Bears Forced to Swim More as Ice Retreats Hi","m_szDocBody":"discovery new follow tech alternative power source app biotechnology gear gadget robotic tech videos featured city unique bacterial fingerprint space alien life exoplanet galaxy asteroid meteor meteorite history space private spaceflight space videos featured watching spacecraft wreck tumble space human psychology genetic health evolution life human videos featured prince tenor rule pop music earth weather extreme event plant ocean global warming earth videos featured polar bear forced swim ice retreat history featured harriet tubman replace jackson archaeology history ancient egypt art history religion history videos animal featured giant prehistoric bear evolved fill scavenger gap dinosaur endangered specy shark whale dolphin zoo animal animal videos adventure featured journey sherpa decade director adventure activity adventure travel adventure trip guide extreme sport national park outdoor activity survival video tweet tech videos playing solid state design perf aeroplane tech help breathe close star trek warp dri featured collectionsin tech videos clip dnew dnew psychology videos view clip dnew dnew human life videos view clip dnew dnew space videos view clip dnew dnew astronomy videos view clip dnew dnew history videos view clip dnew dnew health videos view clip dnew dnew asteroid meteor meteorite videos view clip dnew dnew archaeology videos view clip dnew dnew ancient egypt videos view clip dnew dnew life videos view clip dnew dnew earth videos view clip iditarod iditarod view clip archaeology discovery new archaeology view clip dnew dnew ocean videos view clip dnew dnew shark videos view clip earth discovery new earth view clip animal discovery new cool job view clip animal discovery new animal view clip earth sustainable earth view clip animal discovery new shark view clip animal pet view clip earth explainer view clip tech amazing feat view clip dnew dnew animal videos view clip history discovery new history view clip earth discovery new weather climate view clip new dog view clip archaeology ancient egypt view clip dnew dnew dinosaur videos view clip dnew dnew endangered specy videos view clip earth natural disaster view clip dnew dnew tech videos view watchedin tech videos dnew dnew microwave cook food view dnew dnew fukushima radiation heard ly view dnew dnew laser beam drunk driver view dnew dnew phone giving phantom vibration view tech robot gripper pick view dnew dnew internet work view tech technology track team race trail view dnew dnew robocop tech future policing view dnew dnew graphene change world view tech mindcontrolled robot human brainwave view tech avatar future film view dnew dnew cell phone ban make road safer view tech avatar motion capture mirror emotion view dnew dnew time switch metric system view tech inside flavour lab view dnew dnew scientist create labgrown vaginas view dnew dnew hologram view tech electric car feed grid view dnew dnew atomic clock redefine time view dnew dnew finally invisibility cloak well sort view tech special effect science lesson view tech future yet voting view dnew dnew close harnessing nuclear fusion view tech human cloning view dnew dnew pop music make solar cell efficient view dnew dnew robot soldier coming view dnew dnew firework work view dnew dnew amazon delivery drone work view dnew dnew artificial intelligence destroy view real reason tech giant hate porn view tech man control robotic hand mind view dnew dnew ready cryogenic ready view videos tech videos test tube new science competition fue view solid state design perf view aeroplane tech help breathe view close star trek warp dri view test tube new air force one nut view online life employer busi view test tube new ahead view braincomputer interface move stuff view hydrogen bomb atomic bomb view future plane environmentally view money fake view laser weapon future view music captured vinyl view test tube new world energy view test tube new anonymous train key view audio future sound view seeker storey africa hacking view test tube new powerful hack view air force working reallife view test tube new russian ship uncomforta view back future view volkswagen beat epas emission view when when jetpack view home run battery view site american heroe channel animal planet animalist curiosity discovery channel discovery kid discovery fit health investigation discovery own oprah winfrey network destination america science channel tlc velocity discovery new revision discovery family channel sourcefed testtube discovery education student competition discovery discovery retreat discovery music source video discovery new video shop discovery store dvd book custom gear toy game gift set sale discovery toy gadget student adventure discovery time square discovery corporate sale stay connected newsletter corporate discovery communication llc viewer relation advertising career discovery privacy policy visitor agreement copyright discovery communication llc numberone nonfiction media company","m_szGeo1":"United States","m_szSourceType":"source_general","m_szSrcUrl":"http://news.discovery.com/tech/videos","m_Places":["Jackson","United States","Egypt","Most","Fukushima","Africa","America","Sale"],"m_People":["Harriet Tubman","Oprah Winfrey"],"m_Companies":["Asteroids","Polar","Bears","Gap","Journey","Amazon","Animal Planet","Discovery Channel","Tlc","Family Channel","Discovery Education","Discovery Store","Twitter","Facebook","Discovery Communications, Llc","Discovery Communications, Llc."],"m_BiGrams":["view clip","view dnew","clip dnew","videos view","view tech","discovery new","test tube","tube new","tech videos","view test","clip earth","videos featured","clip animal","ancient egypt","animal discovery","work view"],"m_TriGrams":["videos view clip","view clip dnew","test tube new","view test tube","view clip earth","view clip animal","clip animal discovery","animal discovery new"],"m_SocialTags":[],"m_Topics":[],"m_Industry":[],"m_Technology":[],"m_BiCnt":[31,19,17,17,11,10,7,7,6,6,5,4,4,3,3,3],"m_TriCnt":[16,16,7,6,5,4,3,3],"m_iDocBodyWordCnt":759}
