{"m_szDocID":"742152","m_szDocTitle":"Auto News, New Launches, Prices, User Guides","m_szYear":"2016","m_szDocSumamry":"India World Videos Photos Cricket Movies Auto Sports Lifestyle Tech Education Business Cosmopolitan NEWS LIST INDIA WORLD PHOTOS VIDEOS CRICKET MOVIES AUTO SPORTS LIFESTYLE TECH EDUCATION BUSINESS News Inbox Top News Most Read Editor's Picks Funalytics Opinion Hot Right Now See MoreSee Less India Today NEWS TV MAGAZINE Search Jobs IPL 2016 Assembly Elections India World Photos videos Movies Cricket Tech FYI Auto Lifestyle Travel Sports Politics Food Education Business Money Top news Opinion Most Read Editor's Pick Funalytics Cosmopolitan Auto NEWS INDIA WORLD CRICKET MOVIES AUTO SPORTS LIFESTY","m_szDocBody":"india world videos photos cricket movy auto sport lifestyle tech education business cosmopolitan new list india world photos videos cricket movy auto sport lifestyle tech education business new inbox top new read editor pick funalytic opinion hot moresee india today new magazine job ipl assembly election india world photos videos movy cricket tech fyi auto lifestyle travel sport politic food education business money top new opinion read editor pick funalytic cosmopolitan auto new india world cricket movy auto sport lifestyle volkswagen reach diesel emission deal david shepardson share kitna deti hai kitne airbag hai dhruv paliwal delhi share generation honda crv work indiatodayin delhi share tesla model received order elon musk indiatodayin delhi share launches share yamaha launches cygnus rayzr scooter priced the company showcased scooter auto expo february car share renault kwid race lakh booking launchto maintain hold market renault india launch kwid manual automatic amt version showcased auto expo car share hyundai creta petrol automatic variant priced lakhlike diesel variant hyundai creta petrol variant sixspeed transmission paired engine car share nissan kick teased ahead rio debut india launch nissan kick travel country important part sponsorship game rio car share indiamade maruti suzuki baleno star safety rating euro ncaphowever test safety pack global model japanese firm received fourstar rating car share renault unveil koleos beijing international automotive exhibition koleos designed engineered global appeal play part boosting renault international growth car share volvo car ambitious target million electrified car the gothenburgbased company reach goal making hybrid version model releasing allelectric car magazine share honda shine comfortable rider pillionthe shine capable daily commute motorcycle segment cold start require attempt cranking motor magazine share mahindra mojo hoot ride cityonce remove killer mojo deep note exhaust ensure people turn head catch glimpse motorcycle comparison share renault duster renault dusterwe compare duster made car share tata tiago receive lakh enquiry launchtata tiago talk town due innovative design competitive pricing leaving maruti suzuki hyundai sweating latest auto new share mitsubishi motor admit cheating fuel economy testthe affected minivehicle produced mitsubishi brand japan including model model produce nissan motor car share mahindra launches add standard featuresmahindra launched electric car united kingdom car variant buyer latest auto new share renault expand dealership end currently renault sale outlet sale outlet bike share triumph conduct training tiger ownersbritish motorcycling brand triumph conducted training event owner triumph tiger motorcycle pune magazine share fuel efficient balenowe finally managed kmpl mark baleno spirited driving magazine share highway stint scrossin chapter review highway capability scross solid companion long highway run magazine share hyundai creta fare city trafficthe hyundai creta longterm fleet fair share highway great india drive time bustling city traffic new share tyre complete crore buyout cavendishthe acquisition line strategic vision tyre leading tyre company world wellrounded portfolio advisor share breathe drive outcar air purifier perfect solution cabin car hospitable dusty smog filled road simran rastogi review aeroguard deliver new share tata tiago receive lakh booking mitsubishi motor admit cheating fuel economy test moreauto newswrap bike share harleydavidson roadster unveiled priced lakhlike dark custom range harleydavidson roadster focused younger audience magazine share saddle soresay byebye backache helpful addition make commute road trip enjoyable simran rastogi explain science seat latest auto new share dealer start taking booking honda brvhonda dealership started taking booking brv compact suv rival hyundai creta renault duster new share auto newswrap maruti suzuki hit jackpot baleno moreauto newswrap top new read editor pick detained misbehaving air hostesse board indigo flight army undertake war game deal nuclear attack babulal gaur again caught cam touching woman inappropriately london naked restaurant pakistan army chief raheel sharif sack officer corruption charge vijay mallya condos trump building york declare rajya sabha affidavit militant killed encounter security force kupwara centre refuse acknowledge mehboobas proposal returning militant congress govt karnataka fight yeddyurappas acquittal excise department reap profit bihar liquor ban babulal gaur again caught cam touching woman inappropriately vijay mallya condos trump building york declare rajya sabha affidavit nsa doval raise masood azhar china uttarakhand president rule struck down court vijay mallya deported write foreign ministry photos heat moment india battling summer photos dilip kumar discharged leave hospital wife saira banu exercise shatrujeet indian army desert storm lightsaber mock fight prince william prince harry trip star war set baaghi tiger shroff shraddha kapoor realllly hot still make day danceab india baari star judge set dance war picture kabul women orchestra fighting taliban ideology music rainbow favourite meal good much prevnext watch passenger detained making videos indigo air hostesse uttarakhand strike president rule floor test uttar pradesh fearing riot hindumuslim couple refused marriage registration mallya refuse reveal overseas asset offer pay back crore angry bird feather flock didi west bengal top take caught camera woman dragged workplace brutally raped amritsar pop superstar prince dy minnesota home tahawwur rana wanted plotting attack headley mallya luxury flat declare rajya sabha affidavit new india world photos cricket movy auto sport lifestyle tech education business sitemap publication india today india today hindi business today cosmopolitan men health woman money today prevention reader digest good housekeeping time harvard business review gadget gizmos television aaj tak delhi aaj tak tez india today radio oye education vasant valley online course learn today india today education online shopping bag today india today diary event agenda aajtak india today conclave india today woman summit india today youth summit state state conclave india today education summit printing thomson press welfare care today music music today distribution rate card das application form contact person das phase iii syndication india today image distribution rate card link dailyo partner press release ichowk prevnext copyright living media india limited reprint right syndication today","m_szGeo1":"","m_szSourceType":"source_general","m_szSrcUrl":"http://indiatoday.intoday.in/section/230/1/auto.html","m_Places":["India","Most","United States","New Delhi","Tesla","Gothenburg","Japan","Uk","United Kingdom","Pune","London","Pakistan","New York","Bihar","China","Uttarakhand","Ab India Ki Baari","Kabul","West Bengal","Amritsar","Minnesota","Ny","Delhi","Summit","The States"],"m_People":["Moresee Less","David Shepardson","Deti Hai","Airbag Hai","Elon Musk","Maruti Suzuki","Simran Rastogi","Raheel Sharif","Masood Azhar","Dilip Kumar","Shraddha Kapoor","Tahawwur Rana","Aaj Tak"],"m_Companies":["India Today","Volkswagen","Diesel","Honda Cr-v","Yamaha","Renault","Hyundai","Volvo","Honda","Sp","Mojo","Mitsubishi Motors","Nissan Motor","Jk","Harley-davidson","Seat","Indigo","Army","Congress","Nsa Doval","Indian Army","Harry's","Taliban","Men's Health","Reader's Digest","Good Housekeeping","Harvard Business Review","Thomson Press","Living Media India Limited"],"m_BiGrams":["india today","car share","magazine share","new share","india world","hyundai creta","cricket movy","movy auto","auto sport","sport lifestyle","education business","auto new","share renault","lifestyle tech","tech education","world photos","top new","read editor","editor pick","delhi share","maruti suzuki","latest auto","vijay mallya","declare rajya","rajya sabha","sabha affidavit","today india"],"m_TriGrams":["cricket movy auto","movy auto sport","auto sport lifestyle","sport lifestyle tech","lifestyle tech education","tech education business","india world photos","read editor pick","latest auto new","auto new share","declare rajya sabha","rajya sabha affidavit"],"m_SocialTags":[],"m_Topics":[],"m_Industry":[],"m_Technology":[],"m_BiCnt":[11,8,6,6,5,5,4,4,4,4,4,4,4,3,3,3,3,3,3,3,3,3,3,3,3,3,3],"m_TriCnt":[4,4,4,3,3,3,3,3,3,3,3,3],"m_iDocBodyWordCnt":931}
