{"m_szDocID":"746127","m_szDocTitle":"Vermont Nuclear Plant Seeks Decommission But Lacks Funds To Do So","m_szYear":"2014","m_szDocSumamry":"April 2nd, 2014 by Sandy Dechert Â  On Friday, the Vermont Public Service Board voted to authorize Entergy Nuclear Operations, Inc. , the operators of the Vermont Yankee electricity generating station at 546 Governor Hunt Rd. in Vernon, to close down their nuclear power plant by the end of this year. Because Entergy planned to shut the Vermont nuclear plant down prior to its licensed end-term, the board was required to approve the shutdown. Vermont Yankee was built at Vernon (5 miles south of Brattleboro) by Vermont Yankee Nuclear Power Corporation. It was first licensed on March 21, 1972, and ","m_szDocBody":"sandy dechert friday vermont public service board voted authorise entergy nuclear operation inc operator vermont yankee electricity generating station governor hunt vernon close nuclear power plant end year entergy planned shut vermont nuclear plant prior licenced endterm board required approve shutdown vermont yankee built vernon mile south brattleboro vermont yankee nuclear power corporation licenced officially opened entergy bought plant vermont nuclear plant similar tepcos ruined fukushima daiichi site power capacity general electric type commercial boiling water reactor mark wet containment boilingwater reactor fuel assembly vermont yankee detractor year history antinuclear protest clouded plant decade operation cooling tower cell collapsed tritium leak million picocury time epa drinkingwater standard occurred nonetheless nuclear regulatory commission renewed licence vermont nuclear plant year ago operation mwe entergy announced intended shut reactor late year economic reason happened elsewhere declining natural gas price low wind power price making nucleargenerated power expensive coalfired plant region risk closure state company adopted memo understanding require entergy provide million economic development windham county lose job shutdown remaining yearold national pollutant discharge elimination system permit review vermont agency natural resource past year continued discharge warm water connecticut river adversely affected water quality downstream altered ecological system watershed entergy reserved million date decommissioning vermont nuclear plant department public service amount adequate meet cost full deconstruction estimated billion company decommissioning cost analysis report company pledged put million restoration decommissioning plant however presumably pledge moot entergy totally decommission plant million gap raise issue money dismantle plant safely masslive editorialise related storey cleantechnicas completely free electric car report electric car early adopter follower want date hottest cleantech new subscribing free cleantech newsletter eye sectorspecific new also free solar energy newsletter electric vehicle newsletter wind energy newsletter tag decommissioning mark reactor npde nuclear energy nuclear plant vermont yankee sandy dechert cover environmental health renewable conventional energy climate change new climate beat important media attended year cop lima peru sandy worked groundbreaking environmental consultant fortune health care firm write weblog attribute modest success indelible habit poking satisfy curiosity related post ","m_szGeo1":"United States","m_szSourceType":"source_industry","m_szSrcUrl":"http://cleantechnica.com/2014/04/02/vermont-nuclear-plant-seeks-decommission-lacks-funds/","m_Places":["Vermont","Vernon","Brattleboro","Fukushima","Mark","Windham County","Connecticut River"],"m_People":["Sandy Dechert","Lima Peru"],"m_Companies":["Entergy Nuclear","Vermont Yankee","Entergy","Nuclear Power Corporation","Tepco","General Electric","Epa","Nuclear Regulatory Commission","Agency Of Natural Resources","Department Of Public Service","Gap"],"m_BiGrams":["vermont yankee","nuclear plant","vermont nuclear"],"m_TriGrams":["vermont nuclear plant"],"m_SocialTags":[],"m_Topics":[],"m_Industry":[],"m_Technology":[],"m_BiCnt":[5,5,4],"m_TriCnt":[4],"m_iDocBodyWordCnt":332}
