{"m_szDocID":"746424","m_szDocTitle":"Directory: Jurgen Parysek's Free Energy for Electric Vehicles - PESWiki","m_szYear":"2016","m_szDocSumamry":"Directory: Jurgen Parysek's Free Energy for Electric Vehicles From PESWiki Pure Energy Systems News November 28, 2013 Inventor, Jurgen Parysek of Germany, has a website that claims (if I understand correctly) to have a generator technology that will enable indefinite range for electric vehicles so they do not have to stop to be recharged. He sent me an email with a long diatribe about the need for such a technology -- something our audience is already aware of. No evidence is provided. No photos, no video, no data, no witness statements, no specs. Contents 2013 November, Free energy Germany Ju","m_szDocBody":"directory jurgen parysek free energy electric vehicle peswiki pure energy system new inventor jurgen parysek germany website claim understand correctly generator technology enable indefinite range electric vehicle stop recharged long diatribe technology audience aware evidence provided photos video data witness statement spec content november free energy germany jurgen open letter jurgen parysek completed project related free energy power announce november offer world worth wait world wrong direction pull vault project save world depend fall electric car crude oil nuclear power fearing work loss profit that end sometime learn save free energy required produce agriculture industry worth wait watch taking part development free energy technology electric car threat pose world today battery crude oil government grant endless debt country tremendous rate road fix anything million car brush electric time take remove nuclear power plant start late save climate world change score better energy bury head sand talk problem direction road see pchajmy world destruction facility wonderful project stronger flash sun brighten dark corner country brighten mind hope for started work free energy professor wturtur claus work reaching energy source leader embarrass front nation world providing support project research free energy corporation car worth support private project indeed study reached successful scientist physicist achieve success direction end physicist right developed work led achievement free energy electric samochod oil crisis driving force people world began project research reducing fuel consumption car day number project patent circled history conspiracy patent appeal global motor industry talk free energy electric car global patent part you way state equal start draaniu home free energy miss poor rich country zniemy patent office prior announcement free energy agree that announce tomorrow draught free energy convinced day queue patent office problem move term reward developer bet electric car industry feet giving power free energy creator invention biggest loser programme confused authority hope jointly work global patent reason cooperation young people world put patent patent lawyer hire you future guy create foundation free energy year ago strong brand change live night perform sit home pozamykaj factory power off wait change situation today free energy announced home monday closing factory office hospital nursery school bank stock exchange free energy release work support continue develop industry take year big support dead energy fear manipulate energy false prophet structure preach untruth small glimmer hope future stood black suit world harmony kerosene show black face owe kerosene study interrupted revived anew hope fairy tale bit truth waiting future range electric vehicle unlimited global economy develop anew energy enable survive device simple design power increased will district fairy tale spoken you fairy tale truth japan fukushin long ago eye world japan created power based free energy problem completely safe addition problem transfer energy distance city village power put centre city technically ready today problem device proposed device fund itself energy produced power achieve more wind farm north sea launched largest german naval wind farm turbine capacity megawatt meet annually thousand household cost billion euros progress reservation price profitability investment germany renewable energy european commission spokesperson pia ahrenkilde hansen said reduce dependence oil transportation depend data european commission imported oil day amount billion day put free energy cost billion euros meet germany energy demand million household price energy extremely low september announced project free energy year research finished project called leonardo vinci worked technology hydrogen magnetic energy decided focus free energy laugh project advise scientist physicist patent office speak put diplomas title professor scientific quietly familiar detail start talk introduction energy life blame world threaten anyone survive continue grow cheap energy cheap generator beginning flourishing electric car incredible range panic intimidated anyone trigger global crisis free energy great hope government future children occupy workplace retirement humane end day afraid work year oil stock million fan thousand nuclear power plant end cheap oil terrestrial landscape similar moon reason hid free energy carpet people comment structure prefer free energy save climate wind solar energy supplement main source energy main source nuclear power plant free energy future professor michio kaku read lot you invite physicist review work received free energy convinced concern future planet achievement free energy world survive continue free energy cheap energy generator simple design set direction dispel republican john mccain announced support development electric vehicle technology offered reward improving battery performance reduce cost production blow amount forget however award future work battery ready implemented project difference mccain exchange battery offer generator free energy electric car give limited range investment battery electric car dead end world registered billion million car day credit amount electrical current car charger needed number car cable world electricity pylon wind turbine nuclear power plant bear cost taxpayer limit crude oil zadurzymy world future electric car free energy generator reduce demand crude oil benefit global climate appeal world automotive company german japanese chinese american french british italian meet discuss future electric car driven based free energy cheap generator simple design end recoiling electric car street amazing range ball tour earth filling charging electric car imagine nuclear power plant failure town night minute electric car supply city electricity remain silent start industrial revolution germany jurgen parysek new featured electromagnetic evs jurgen parysek free energy electric vehicle german inventor website claim generator technology enable indefinite range electric vehicle stop recharged evidence provided photos video data witness statement spec peswiki contact ","m_szGeo1":"United States","m_szSourceType":"source_industry","m_szSrcUrl":"http://peswiki.com/index.php/Directory:_Jurgen_Parysek's_Free_Energy_for_Electric_Vehicles","m_Places":["Germany","Japan","North Sea"],"m_People":["Jurgen Parysek","Turtur Claus","Pia Ahrenkilde Hansen","Leonardo Da Vinci","Michio Kaku","John Mccain"],"m_Companies":["Eu","Indeed","European Commission"],"m_BiGrams":["free energy","electric car","electric vehicle","nuclear power","jurgen parysek","energy electric","power plant","crude oil","range electric","patent office","fairy tale","simple design","energy cheap"],"m_TriGrams":["free energy electric","nuclear power plant","range electric vehicle"],"m_SocialTags":[],"m_Topics":[],"m_Industry":[],"m_Technology":[],"m_BiCnt":[31,12,6,6,5,5,5,4,3,3,3,3,3],"m_TriCnt":[5,5,3],"m_iDocBodyWordCnt":874}
