{"m_szDocID":"747412","m_szDocTitle":"BrightSource Going Big on Energy Storage | CleanTechnica","m_szYear":"2011","m_szDocSumamry":"BrightSource Going Big on Energy Storage November 29th, 2011 by Zachary Shahan   BrightSource Energy is a leading solar thermal energy company. In California, it’s in the process of planning and building some of the largest solar thermal power plants in the world. (For more on its technology, see the last paragraph of this post. For more background, check out our BrightSource Energy page.) Yesterday, the company announced that it is adding “its SolarPLUS thermal energy storage capability to three of its power purchase agreements with Southern California Edison (SCE).” It now has two solar ther","m_szDocBody":"brightsource big energy storage zachary shahan brightsource energy leading solar thermal energy company california process planning building largest solar thermal power plant world for technology paragraph post background cheque brightsource energy page yesterday company announced adding solarplus thermal energy storage capability power purchase agreement southern california edison sce solar thermal power plant scheduled finished delivering energy three storage scheduled deliver electricity and brightsource partner nrg energy google bechtel building megawatt plant southern california edison ivanpah solar project southeast california energy storage benefit adding storage solar thermal power plant brightsource reduce thetotal cost energy increasing capacity factor power plant produce ayear extending production electricity part day needed byutility company note added storage capability brightsource doesnt build extra megawatt solar power station build power station seven save approximately acre desert land save utility customer money added storage cut additional power plant including costly coal nuclear plant avoid variability integration cost solar wind power face agreement demonstrating power tower technology advancing solar thermal industry utilityscale solar generation cost effective reliable john woolard president ceo brightsource energy clean energy mix moving forward argue benefit rooftop beat benefit solar thermal power plant argue wind power beat both personally opinion point happy brightsource california moving forward pioneering project brightsource power plant brightsource power tower solar thermal system field softwarecontrolled mirror called heliostat reflect sun energy boiler atop tower produce temperature pressure steam steam turn highly efficient steam turbine produce electricity storage added steam directed heat exchanger molten salt heated higher temperature efficiently storing heat energy future use later energy storage needed heat stored molten salt generate steam run turbine great reader storey tip cleantechnicas completely free electric car report electric car early adopter follower want date hottest cleantech new subscribing free cleantech newsletter eye sectorspecific new also free solar energy newsletter electric vehicle newsletter wind energy newsletter tag brightsource brightsource energy brightsource energy storage brightsource solar brightsource solar thermal solar thermal power zachary shahan tryin and specy letter time spend time cleantechnica director chief editor otherwise enthusiastically fulfilling duty obsession gas solar love planetsave bikocity president important media zach recognised globally solar energy electric car energy storage wind energy expert speak related conference event connect social media zacharyshahancom related post david nyc hate pristine desert areas covered human development million acre commercial roof space parking lot open roadway solar power production weve ruined planet chinese solar production environmental nightmare solar doesnt part problem too eric david roof space commercial residential close producing amount power desert farm will additionally time farm end live company competing right recycle excess panel put back circulation agree excess roof parking lot space used desert open possibility suburban areas contest both time board appearing sit sideline carp tropical day concept good understand sentiment alternative add significant cost reducing yield point future desire common practise small scale areas northeast land premium topology woodland natural inhibitor concept happen large scale solar panel increase efficiency reducing cost take investment industry large scale solar project inject required capital consideration current source coal oil gas nuclear hydro wind year breakthrough solar panel efficiency application easy dismantle solar farm wind farm matter minimal negative impact alternative continue destroy natural world seek protect greater investment solar technology sooner achieve goal ","m_szGeo1":"United States","m_szSourceType":"source_industry","m_szSrcUrl":"http://cleantechnica.com/2011/11/29/brightsource-going-big-on-energy-storage/","m_Places":["California","Southern California","Nyc","Take"],"m_People":["Zachary Shahan","John Woolard"],"m_Companies":["Brightsource Energy","Nrg Energy","Google"],"m_BiGrams":["solar thermal","power plant","energy storage","thermal power","brightsource energy","electric car"],"m_TriGrams":["solar thermal power","thermal power plant"],"m_SocialTags":[],"m_Topics":[],"m_Industry":[],"m_Technology":[],"m_BiCnt":[9,7,6,5,4,3],"m_TriCnt":[4,4],"m_iDocBodyWordCnt":531}
