{"m_szDocID":"752256","m_szDocTitle":"Carmakers prepare to shift to hydrogen fuel cells - Sun Sentinel","m_szYear":"2014","m_szDocSumamry":"Carmakers prepare to shift to hydrogen fuel cells Automakers look to hydrogen fuel cell technology Christina House / For The Times Hyundai started leasing a hydrogen fuel cell version of its Tucson SUV, above, this year. To the right is a fuel cell stack on display at the 2013 L.A. Auto Show. Hyundai started leasing a hydrogen fuel cell version of its Tucson SUV, above, this year. To the right is a fuel cell stack on display at the 2013 L.A. Auto Show. (Christina House / For The Times) Privacy Policy Concerned about slow sales of electric cars and plug-in hybrids, automakers are increasingly b","m_szDocBody":"carmaker prepare shift hydrogen fuel cell automaker hydrogen fuel cell technology christina house time hyundai started leasing hydrogen fuel cell version tucson suv above year fuel cell stack display auto show hyundai started leasing hydrogen fuel cell version tucson suv above year fuel cell stack display auto show christina house time privacy policy concerned slow sale electric car plugin hybrid automaker increasingly betting future green car hydrogen fuel cell technology toyota motor corp maker popular prius gaselectric hybrid hydrogen battery power generation green vehicle today toyota favour fuel cell zeroemission vehicle pure battery electric vehicle craig scott company national manager advanced technology selling car gas coming door build electric car hydrogen ardent proponent agree technology face enormous hurdle electric car hydrogen fuel cell vehicle expensive infrastructure refuel them car company slow put hydrogen fuel cell vehicle market part lack fueling station operator fueling station turn build retail outlet fuel cell car sale automaker hydrogen fuel cell bob chamberlin los angele time selling car gas coming door build electric car toyotas craig scott selling car gas coming door build electric car toyotas craig scott bob chamberlin los angele time dan poppe early investor hydrogen station wearing hard hat coverall burbank hydrogen station poppe chew edge moustache worry future told car road california car poppe company frontier build operate station california today hydrogen fuel cell car maker station operator poppe subsidised state california set goal million zeroemission car road year state car sold zeroemission vehicle selling car gas coming door build electric car craig scott toyotas national manager advanced technology category include plugin hybrid travel mile battery power gas engine kick include traditional hybrid sell lower cost higher volume automaker working electric car technology sale battery electric plugin hybrid vehicle year still total sale zeroemission vehicle represent car nationally popular california else state driver nation zeroemission vehicle plugin hybrid battery electric vehicle automaker struggling produce massmarket electric car fuel cell increasingly ascendant platform hydrogen fuel cell designed power electric motor battery storing energy battery pack take hour recharge fuelcell vehicle store hydrogen gas onboard tank refilled minute gasoline tank state subsidise hydrogenpowered car batterypowered car rebate offered buyer electric car early day electric car buyer eligible state rebate fuel cell car buyer qualify end federal rebate car hit road earlier year state award automaker environmental credit building them comply california clean air mandate sell automaker credit comply automaker credit fuel cell car battery electric plugin hybrid hydrogen refuelling station operator poppe money state agency california energy commission california air resource board south coast air quality management district poppe received million state build station chino energy commission air quality district operate station burbank district spent million construction operation maintenance southern california station considerably fund spent energy commission air resource board agency spokesman sam atwood said qualify million grant poppe invest money receive grant cover operational expense hit specific performance goal number pump open operating capacity date face disqualified risk entrepreneur poppe believe future hydrogen fuel cell vehicle address main shortcoming today batterypowered car short driving range long recharging time car company agree toyota launch fuel cell sedan japan early year summer hyundai motor started leasing hydrogen fuel cell version tucson sport utility vehicle year honda motor spent year testing leasing fcx clarity fuel cell vehicle preparing launch fuel cell car year ford motor put million test mile fleet fuel cell vehicle year recently cut deal daimler renault nissan develop joint fuel cell technology company share general motor hold patent hydrogen fuel cell technology carmaker similarly tested hydrogen car partnered honda rival number fuel cell patent year codevelop automotive fuel cell application car arrive cheap toyota set price car here launched japan sticker price buyer qualify government rebate fuel cell car range gaspowered vehicle mile fueling stop electric car range mile expensive batterypowered car namely tesla model offer mile driving range tesla model start cost upward largest battery luxury option addition fuel cell advocate point multiple source hydrogen including hydroelectric wind generator nuclear power plant natural gas elon musk chairman batteryelectric vehicle manufacturer tesla motor inc deride hydrogenpowered car call science overcomplicated call fool cell musk told shareholder june earlier dismissed technology load rubbish musk elaborate specific weaknesse hydrogen power believe battery remain dominant power source zeroemission car tesla spokesperson declined request interview musk executive observer caution appearance competing technology misleading clean transportation necessarily found single system fuel cell car longer range visit gas station plug home gas station all don anair union concerned scientist its eitheror proposition bothand proposition california leading edge subsidising fuel cell movement state legislature passed late year dedicating million year finance construction hydrogen fueling station station california now number increase station year automaker station owner incentive invest government subsidy develop car station without government support viable business poppe said nascent technology mainstream hydrogen station operator poppe believer technology wife drive mercedesbenz bclass fuel cell car wait businesse profitable burbank station serve car day recoup investment expert put price building single hydrogen fueling station excluding cost real estate million single nozzle burbank station cost poppe said expensive gasoline station drilling refining operation feed them put nationwide network hydrogen station cost building alaska pipeline charlie freese head fuel cell vehicle programme there lot hidden cost too cost keeping strait hormuz open ","m_szGeo1":"United States","m_szSourceType":"source_news","m_szSrcUrl":"http://www.sun-sentinel.com/business/la-fi-hy-fuel-cell-cars-20141026-story.html","m_Places":["Tucson","L.a.","Toyota","Most","Burbank","California","Chino","Southern California","Japan","United States","Tesla","Alaska"],"m_People":["Craig Scott","Bob Chamberlin","Dan Poppe","Sam Atwood","Elon Musk","Charlie Freese"],"m_Companies":["Hyundai","Toyota Motor Corp","Los Angeles Times","State Of California","California Energy Commission","California Air Resources Board","South Coast Air Quality Management District","Hyundai Motor Co","Honda Motor Co","Ford Motor Co","Renault","General Motors Co.","Honda","Tesla Motors Inc.","Union Of Concerned Scientists","Mercedes-benz","Nationwide"],"m_BiGrams":["fuel cell","hydrogen fuel","electric car","cell car","cell vehicle","plugin hybrid","cell technology","zeroemission vehicle","battery electric","craig scott","selling car","car gas","gas coming","coming door","door build","build electric","fueling station","station operator","hydrogen station","started leasing","leasing hydrogen","cell version","version tucson","car hydrogen","operator poppe","vehicle year","batterypowered car","energy commission"],"m_TriGrams":["hydrogen fuel cell","fuel cell car","fuel cell vehicle","fuel cell technology","selling car gas","car gas coming","gas coming door","coming door build","door build electric","build electric car","started leasing hydrogen","leasing hydrogen fuel","fuel cell version","cell version tucson","station operator poppe"],"m_SocialTags":[],"m_Topics":[],"m_Industry":[],"m_Technology":[],"m_BiCnt":[33,13,11,8,6,5,4,4,4,4,4,4,4,4,4,4,4,4,4,3,3,3,3,3,3,3,3,3],"m_TriCnt":[13,8,6,4,4,4,4,4,4,4,3,3,3,3,3],"m_iDocBodyWordCnt":870}
