{"m_szDocID":"768945","m_szDocTitle":"Plug in your hybrid car | Science! | Geek.com","m_szYear":"2016","m_szDocSumamry":"Plug in your hybrid car By  Apr. 7, 2005 11:57 am Subscribing to a newsletter indicates your consent to our Terms of Use and Privacy Policy . More Geek Chinese satellite proves reproduction still works in space Hybrid cars have become very popular over the last few years, developing a cult following that rivals many computer game communities. The most popular hybrids are the Toyota Prius and the Honda Civic, which can get between 50 and 60 miles per gallon. Those two automobile companies and many others are working to increase this mileage, but it seems that third-parties with a different idea","m_szDocBody":"plug hybrid car apr subscribing newsletter consent term privacy policy geek chinese satellite prove reproduction work space hybrid car popular year developing cult rival computer game community popular hybrid toyota prius honda civic mile gallon automobile company working increase mileage thirdparty idea beating energyc engineering company based california modified prius reach mpg typical commute converted plugin hybrid mile electric power alone estimate show commuter mile daily gasoline fillup required longer outoftown trip professor university california davis working goal gas mileage converted vehicle well including ford explorer mile internal combustion engine mpg difference modified car original built manufacturer modified car plug standard home electrical outlet stock battery combined additional battery increase power output car charged retain charge drawback plugin hybrid larger battery add thousand cost car affect consumer uptake technology info businessweek joshuas opinion main idea power home wall outlet pollutiongenerating power plant coal natural gasburning plant heard home outlet charge electric car invariably create pollutant prevent cost idea granted saving money gasoline cost charging battery kilowatt hour burn expansion hybrid technology interested future purchase hybrid car point hybrid car hold suv gasguzzling premium cost operation standard gas automobile otherwise hybrid prayer comment comment point source pollution est thu true dated power plant coal oil fired produce pollution easier control pollution source easier controlling large number car electricgasoline hybrid step direction paradigm internal combustion engine very technology efficient right gallon gasoline make vehicle forward remaining make pollution heat pretty crude smart solution vehicle propulsion lead world relying inneficient year technology time evolveagain home power cheap est thu compared burning gasoline diesel recharge motive power battery run cost additional battery front deciding factor people fuel economy issue pollution electric power plant electricity home typically back yard driveway equate cost recharging vehicle hot shower electric water heater choice clear fuel cost increase cost extra battery attractive burn fuel trip short tripno fuel hybrid concept original back prius intermediate vehicle end rcaman quick battery est thu day battery car time plugged mean time drawing power power plant pollute fubar natural gas home est thu device convert natural gas electicity house plug car house power polution natural gas idea cost house power heavy polution generation technique plug plug est thu power socket wall cleaner power hybrid generate own fact power generation striving less fairly tight environmental standard fossil fuel station part world solar wind tidal hydro nuclear natural gas clean burn coal carbon scrubber power genheration industry lot option reduced emission generation not course battery technology better recently reported lion technology vastly reduce recharge time solar panel technology promise drastically increase efficiency solar cell envisage hybrid vehicle multiple battery technology small turbo diesel tuned run regular diesel biodiesel solar panel adorning roof plug car home charge topped lithium ion battery recharge energy recovery braking manuever which provide energy power manoeuvre needed town driving remaining ordinary battery recharge normal manner lean burn turbodiesel action arrive work park car day solar panel roof charge battery journey home interesting technology here round corner hybrid vehicle remain flexible tech added existing solar panel tech manufacturer stuck roof trickle charge battery system car bake day parking lot course fuel cell powered methanol eminently renewable material technology mature sufficenlty replace ice hybrid system back reality highlander pollution est thu wtf gas gallon mention pollution refining consumption costing environment tree huggin folk tired raped bit ole plugin mobile long push cutting semi driver est thu gas riciculously cheap gasoline nonrenewable resource gas cheaper milk crying loud stuff leak cow free highlander est thu gas pretty expensive bleachblond wife screaming mile per excursion make nail appointment town awayhehehe fubar work est thu toshiba lithium ion battery charge faster energy plugged time pulled energy filling bucket fill sink fire hose take longer bucket hold amount water tomuchphysic disclaimer est thu scream sexismsave key stroke comment generalising sexist onesided gas beer est thu gallon gas running mark buck slightly bigger gallon bit bigger anyway measure litre day litre gas onethirdlitre bottle bud bought bar typically gas litre bud litre gas highly volatile explosive flammable liquid gotta drill pipe refine transport store retail beer highly inert nonflammable liquid throw handful grass bucket water wait transport store retail profitable pumbie battery car est thu car awesome city folk what gonna happen travel allowed charge battery hybred car combo motor reason hydrogen car suv probaly big prolly future year buy solar car mention life span battery nimh lithium battery remember battery hold charge hard train minite home plug car case forget emergincy unplug stufftothinkabout pumbie est thu british people stupid ust curious cousin jeb pollution est thu live manitoba watt electricity hydroelectric dam wind power province state same amount greenhouse gase signifigantly reduce cfour time evolve est thu efficiency guess off nowaday average internal combustion engine efficiency burning petroleum rest heat and noise pollution byproduct johnyd reduced est thu reduce reduce idea cfour recfour est thu mountain range back yard did congress fighting tooth nail prevent existing energy producing resource making dime simply stated govt regulation prevent running capacity talking running capacity folk law allowed compete energy producing corperation dam paid taxpayer purpose flood abatement power generate free company purchase good generate power compete free damn forced federal law generate power pay maintenance payroll turbine turned off water diverted nonpower generating channel govt great hodar highlander idiot est thu gas cheaper good armani suit comparison make make car what left bowl capn crunch finished comment wookie wookie make sense johnyd est thu well stand corrected effeciency machine suck put miserable effeciency rating employee process put combustion engine way call byproduct called pollution bad health fact make better evolve highlander est thu gas gallon end year prediction coming back down time weened petrol gas pollution est thu coal burned cleaner gasoline burned natural gas cleaner burning both improvement turbo diesel hybrid tdih low selfesteem est thu guess guy hummer show manly are not way ugly vehicle bashed repeatedly ugly stick dont build recover est thu wasted energy car form heat converting electricity blah word est thu biodiesel jrink est thu big hummer evolve est thu arguing shouldve stated post efficiency awful move combustion related energy production needed solar hydro tidal avg earth receive maryland average receive more summer winter point pretty rediculous accepting paltry oodle energy mega profit made oil oil product continue dependant such oil industry money segment good bad matter major responsible energy hopefully moved oil ideal situation responsible energy need generate power solar collector house land car collect solar power drive etc business same however utopia anyway fruition johnyd forgot url est thu figure above johnyd est thu glad civil debate skill lost you armani suit require lot work produce raw material processing skill cutting assebling garment milk leak cow collected put big tank mixed heated some packed shipped gasoline product drilling deep hole ground hazardous condition pumping viscous black glop big tank refining hideously expensive refinery prone explosion finished product retank shipped gas station unlike milk oil simply eat grass make milk tomorrow gone concentrate mind people sufficiently suv gas milage sherman tank greatest idea gasoline cheaper milk crazy gasoline precious vanishing resource folk you whining problem seemingly solution highlander highlander est thu agree idea solar wind chagrin sure solar wind power lake house stick regular power sake looked pretty hard research cheaper link solar power designing include power regulator charge vehicle tremendous help link regulation selling power back power company great too geekzilla point est thu post highfalutin stuff efficiency coal natural gas source pollution fine well misse point heck family type drive suvs anyway point company make doh before hybridnice car battery electric motor plug occasionally mileage energy cheaper assume drive kid hybrid ford escape suv save buck sound pretty simple obvious doh basic info plugin hybrid est thu founder california car initiatve nonprofit combining technology development advocacy prius large community people connect online thoughtful comment urge read page fact sheet found form felix kramer redoh est thu suvs rest world subcompact micro car really small sedan sporty hatchback assume suvs aircontaminating country sure gasoline price expensive visit mexico further europe asia island australia etc citizen realise live messing neighbour electrical energy cheaper pollution hydroelectric dam wind solar million year process guess pretty simple obvious change lifestyle mexican evolving est thu evolution biological cultural case economic take time higher price gas acting catalyst change attempt improving efficiency technology alternate source energy move forward evolving power direct response topic experimenting growing technology thought watch oil corporation guy tonne money oil long profitable while bigger corporation quietly putting big money research own writing wall dont tank sorry painful grandpa humour couldnt resist work fringe oil gas industry glimpse more technical hurdle favoured energy hydrogen from corporation view partially due fact infrastructure central delivery point pipeline station with modification mean economically control energy distribution say technological advancement experiment step forward industry reading btw chuckling hummer comment thank jingjang biodiesel est thu people obvious buy diesel vehicle convert vegetable oil easy conversion oil restaurant whatever alternatively buy diesel biodiesel fuel brewed vegetable oil home increasingly commercially brainer free fuel citizen walk philly est thu damn operating output right true reason needed drill alaska hydroelectricity damn familly car live philly pennsylvania usa good public transport not great good engine run cheesteak release methane mixture highly volitile engine place weigh metric tonne car car share buisness america polluting bugger fuzzybaffy small car est thu own prefer walk face big place car around remember gasoline crisis car company quick change small effecient car now can concerned american charge depleating hybrid cost low efficiency est thu nice trybut technology merit here proving range charge depleating hybrid function variablemoney beside good wall charging discipline vehicle efficiency worse standard prius result extended period charging soc back problem valence lion technology low power density large pack handle charge mode work vehicle power density charge poor lfp cathode valence use technical flaw good academic mpg effort duckfude losse power est thu decline voltage increase convert immediately higher point source argument hold easier control cheaper control control joshua usual provide source hearsay pollution outled found regulation est thu for solar net metering put state get free design plan geekzilla outlet est thu hybrid car est thu why drive car mile gallon enjoy great alive year shortage fuel god bless america postman pollution national security est thu plug hybrid draw energy offpeak improve efficiency power plant burn coal further extending electric operating range lessen demand imported oil strengthen economy currency begin shut flow fund regime support incubate harm plug hybrid cleaner time passe technology investment diverted purchase imported oil clean power plant emission prius owner orlando rich evan cpa battery pollution est thu folk narrow minded lithium nickle lead acid battery chemical form tonne chemical byproduct involved making baterry time toxic burning hydrocarbon wood matter burning oil cleaned europe environment restored forest paris london burned wood warm deforested area mile artefact period identified layer soot switched batery tomorrow toxic garbage dump full spent battery leaking nasty chemical place produce enegry produce waste star run fuel burn leave huge amount waste ultimate magic solution exterminate human race consume nateral resource whatsoever ice age mass extintion cycle many carry untamper sun burn explode end life solar system btw universe day star born die else dawinism mexican est thu ramble point time hybrid suv mileage subcompact car save money plug night you drive sporty hatchback sorry family man where kid sit talking apple orange here guess pretty simple obvious missing point talk car size america suvs price gas point put power cable hybrid make hybrid point mileage good thing doh heard est thu illinformed ignorant bullshit life crack textbook learn internal combustion engine battery peak load air pollution statistic comparative efficiency drive back home mom civic dah grumpyoldgeek mexican est thu polluting country website reference made excellent stride producing less point car today emit pollution car catalytic converter state vegetation clean stink coal power plant compare developing country epa enviromentalist breathing neck pollution control mexico have america asia europe read badly pollution front improving let good work polluting capable technology work reduce dependence oil sheesh car efficiency est thu fuel movement gasoline engine move car lose transmission friction wheel air conditioner radio etc plus fair electric vehicle pollute charge polluting power plant fair factor oil refining transportation process electric vehicle cleaner hybrid single big power plant easier manage million small car inteluser hmmm est thu well grumpyoldgeek sumed perfectly man dog say work air pollute expend energy type example polluting country that show sillyness usa pollutant country earth gonna mongolia now another why drive car mile gallon enjoy great alive year shortage fuel short sighted that removed gene pool you wake smell bloody rose remember gasoline crisis car company quick change small effecient car now can can economic root all car different people big car advertising word mouth actual use etc make selling big car profitable suv corner shop bread milk time time making future liveable human important eventually equal pass economic simply important what point million dollar bank dead pollution far seen attempt combine environmental situation economic kyoto protocol specifically trade carbon credit tree have that grossly simplistic example overall car gonna away far usefull simply abandon clean act hydrogen hybrid bio diesel solar eletrical ethanol bigger bigger stream fix like planting tree bury carbon underground etc solution hurt environment sooner think that headley misdirected est thu talk changing energy source save world make sense end changed first rolling stock take energy make follow driving cycle using mean designing building mush lighter streamlined vehicle highway traffic control light level efficiency embedded vehicle sensor centralised computer running optimising programme require huge advance technology side benefit enjoyable driving stop further community planning provide alternate autos short trip community dean postman est fri alive year shortage fuel mistaken impression oil year was price buy sheesh technology reduce oil lack will government doe let forget mrbush refusal kyoto protocol country pretty good controling pollution that admit china leader pollution bet usa second wee bit bitter air pollution live area canada half air pollution american karmek fdsv est fri actaully usa number pollution judging anount oil consumption alone china pollution stake bescause developed west year allowed pollute place china india dveloping exempt year kyoto protocol make step fall line year fefd guac est fri answer simple exempt suvs gas milage requirement cut fuel consumption guac water est fri hydrogen fuel cell powered car general moter showing british programme ran water kafuk urk est fri gas fuckng cheap usa screwed rising fuel price running car expencive bad driver spend insurance year road tax buying car paying fuel plan drive lawnmower work first thought idea hybrid car catch price fuel cheaper electricity fuel use better however tax same insurance worse sting bank account due expense potential car still aside big hit public step direction avoid potential crippling human race fossil fuel run fine tramp hunting spear wood roast sewer rat pound coin lying mcdonald prefer rat goddamned tramp yeah est fri car insurance legal requirement illegal drive goddamned tramp bet est fri govt spent money developing bomb weapon mass destruction causing war solution problem read time amount roof space power country solar power change home electricity solar power surely afford plug car thegrasshopper amen postman est fri battery powered vehicle car car loud fast fun electric car quiet slow boring drive guy driving batterypowered rollerskate weekend driving mustang without pollution control much dual exhaust roaring mpg smiling while heck add bit real lead additive lubricate exhaust valve neener neener est sat excellent information andy free ringtone est tue air pollution est mon air pollution air pollution renewable resource est tue amount hot air spouted conserving energy warm transported decacade surely harness resource threebleflushwhisket city mpg est wed favourite car diesel rabbit city mpg day light major intersection red front worked clock found idleing minute equated mph idle top gear topping tank started shutting engine long light fillup mpg jumped mobil economy run gave increbible milage figure dave roth tesla motor est thu tesla motor selling allelectric sportscar mph second mile range bet cost crazy tho douglas hvistendahl ","m_szGeo1":"United States","m_szSourceType":"source_news","m_szSrcUrl":"http://www.geek.com/science/plug-in-your-hybrid-car-559722/","m_Places":["Most","California","United States","Est","Uk","Manitoba","Maryland","Well","Nice","Mexico","Europe","Asia","Australia","Nz","United States Citizen","Philly","Pennsylvania","America","Valence","Orlando","Paris","London","Oranges","S. America","Mongolia","Kyoto","China","Canada","India","Amen","Topping"],"m_People":["Lithium Ion","Felix Kramer","Rich Evans","Dave Roth"],"m_Companies":["Mpg","Ups","University Of California At Davis","Businessweek","Diesel","All Day","Highlander","Toshiba","Guess","Congress","Armani","Utopia","Tank","Gg","Epa","Indeed","Pool","Bio Diesel","Us Air","Mcdonalds","Mph","Mobil","Tesla Motors"],"m_BiGrams":["power plant","est fri","hybrid car","pollution est","natural gas","air pollution","combustion engine","internal combustion","plug car","solar panel","solar power","plug hybrid","mile gallon","plugin hybrid","solar wind","charge battery","car est","generate power","pretty simple","simple obvious","alive year","year shortage","shortage fuel","kyoto protocol"],"m_TriGrams":["pollution est thu","internal combustion engine","est thu gas","car est thu","pretty simple obvious","alive year shortage","year shortage fuel"],"m_SocialTags":[],"m_Topics":[],"m_Industry":[],"m_Technology":[],"m_BiCnt":[8,8,6,6,6,6,5,4,4,4,4,3,3,3,3,3,3,3,3,3,3,3,3,3],"m_TriCnt":[5,4,4,3,3,3,3],"m_iDocBodyWordCnt":2671}
