{"m_szDocID":"770220","m_szDocTitle":"News:Archive:Page 3:October 28, 2011 Test of the One Megawatt E-Cat - PESWiki","m_szYear":"2011","m_szDocSumamry":"News:Archive:Page 3:October 28, 2011 Test of the One Megawatt E-Cat From PESWiki Jump to: navigation , search Page 3 of our archives of the updates we have been posting about the October 28, 2011 test of the 1 MW E-Cat (Energy Catalyzer) in Bologna, Italy, attended by around 30 observers, and carried out by scientists/engineers of the customer. Covering October 29-31, 2011 Click here for the most recent updates. Contents Sent: Monday, October 31, 2011 4:12 PM [MST] Subject: Re: Transcription & Video of Report and Q&A with Rossi [...] Yesterday I looked over the Italian translation of your rebu","m_szDocBody":"newsarchivepage october test megawatt ecat peswiki jump navigation archive update posting test ecat energy catalyzer bologna italy attended observer carried customer covering recent update content sent monday mst subject transcription video report q&a rossi yesterday looked italian translation rebuttal krivit lastest attack eat steve guy drove town rossi bologna idea turn sour rossi passi silverthunder pdt rossi additional ecat plant sold project exponential growth sale year ready make exponentially faster time asked united state working hiring people listed miami manchester boston gotta make job ecatnew oct silverthunder pdt short video less minute made end test francesco pdt defkalion congratulate rossi freeenergytruth oct ecat censorship new report killed press sitting andrea rossi world exclusive day now wondered media controlled surely answer now fact new coverage live event apparently curtailed give supposed exclusive angry start holding freeenergytruth silverthunder pdt quoting bag customer queue month deliver one andrea rossi silverthunder pdt hightraffic forum cover alternative stuff ufos silverthunder pdt from bart myer sterlingda sent monday mst subject request comment quora discussion rossis cold fusion device excellent piece rossi cold fusion device test interesting sery discussion progression test happening quora posted question participation moment potentially significant discovery sufficient discussion opinion quora forum detailed scientific dialogue excellent venue thoughtful discussion this thank silverthunder pdt featured exotic nuclear cold fusion rossi validation oct ecat test report q&a rossi successful test megawatt plant performed rossi read official report attended time answer question video reading report part full transcription pesn beforeitsnew silverthunder pdt andrea rossi start production plant andrea rossi started manufacturing plant buy nation contact warm regard francesco pdt francesco pdt domenico fioravanti nato colonelengineer andrea rossi dear jame bowery dissipator designed person leaded test engineer nato colonel year experience thermopower plant thermodynamical system francesco pdt missed published day ago ecat test achieve live streaming test youtube rossi reveal theory happening inside energy catalyzer customer made public ecatworld oct silverthunder pdt joe sheas mentioned below posted cnn ireport not vetted cnn viewed time now silverthunder pdt silverthunder pdt americanreportercom home big splash ecat test calling invention millennium article silverthunder pdt sunday stateowned new programme important italy report ecat today national edition italian course link online coverage silverthunder pdt francesco pdt link wired article silverthunder pdt organisation bought andrea rossis ecat system cryptogon read alphabet agency military branches member congress staff white house reading post answer simple question bought andrea rossis ecat system cryptagon oct silverthunder pdt part rossi reading test result plant customer bought validated q&a session linked yet posted yesterday silverthunder pdt hour ago believing cold fusion ecat mark gibb reported week philosophical background sincere side fence not believing energy bully exist suppression crackpot scientific politic way hold hope here evidence believe forbe oct silverthunder pdt francesco pdt mention received guy fox new yesterday located fergus fall talked phone minute fact checking today followup question silverthunder pdt rossi building plant customer luke mortensen dear andrea container gone started building container improvement version buyer container customer customer andrea rossi dear luke mortensen francesco pdt cold fusion plant verified customer anonymous reader write history appeared made bologna italy test conducted cold fusion power plant called ecat andrea rossi due glitch plant produce full power run kilowatt continuously selflooped mode external power input pump fan hour reactor combine hydrogen nickel pressure heat produce copper copious amount heat requiring radioactive element producing radioactive waste price point now building time kilowatt installed roughly coal natural gas plant cost mass produced rossi expect price installed kicker device fuel fuel super cheap ubiquitous engineer testing device behalf undisclosed customer apparently signed purchase test public report read evening back january rossi announced technology running press conference bologna unit begin commercial sale meeting goal astonishing itself guest privately invited including journalist scientist business interest reporter press expected post storey day passing editor silverthunder pdt wired report silverthunder pdt francesco pdt finally uploaded part rossi reading test plant customer bought validated also ecatnew posted storey ecat post mortem business financial market government notice customer competent independent ecat team oct silverthunder pdt featured exotic nuclear cold fusion rossi sceptic rebuttal krivit accusation andrea rossi fraudster lenr expert steven krivit travelled bologna june impressed andrea rossis ecat reactor technology highly critical since crossed line accusing rossi running intentional scam buy pesn beforeitsnew silverthunder pdt andrea rossi made comment blog nuclear physic read comment link important comment are sustain mode began system consumed kilowatt hour produced seeking certification approval home unit correction made report programme university bologna begin soon nocompromise pdt magnus write comment below quote today newscnetcom technology creating serving energy grid there shipping container supply megawatt minute aes chose lithium ion battery expensive application proven auto industry shelton aes energy storage president said wow container supply megawatt minute amazing hangon rossi created megawatt energy single container running selfsustain mode hour ago yes truth sceptical possibility there test done working unit possibility change live hope silverthunder pdt half megawatt ecat bologna excerpt reprint nyteknik article link zpenergy oct silverthunder pdt part part rossi reading test plant customer bought validated uploaded part iii next hour around each silverthunder pdt new bullet interview gary hendershot smartscarecrow show night oct test featured new smartscarecrow free energy week sterling weekly free energy review smartscarecrow show tracking ecat test cheap power overnight revolution commentary analyse oct ecat test witt water powered car video posted ces duel fuel system philippine doe report avisos overunity electric vehicle aviso report hho progress upcoming conference freeenergynew silverthunder pdt andrea rossi provided reaponse question cable running genset ecat understood question from andrea rossi leonardo corp sterling allan sent saturday mst subject cable genset dear friend honour hope meet usa status cable temperature absolutely cold due low amount energy produced respect power genset warm regard silverthunder pdt archived earlier entry here newsarchivepage october test megawatt ecat oct silverthunder pdt exotic nuclear cold fusion rossi validation oct success andrea rossis ecat cold fusion system mystery remain odd andrea rossis ecat cold fusion power plant passed biggest test yesterday producing average kilowatt hour technical glitch prevented achieving megawatt originally planned demonstration monitored closely engineer rossis mysterious customer evidently satisfied paid wiredcouk link pesn coverage silverthunder pdt radio citt del capo francesco pdt andrea rossi warning correction draught test made ecat draught correct typos weight hydrogen measured gramme erroneously written flow rate water pump reduced operating pump erroneously written paragraph correct flow rate written paragraph base calculation produced energy made typo sorry yesterday tired warm regard andrea rossi today publish comment answer sorry full day off tired gotta play tennis francesco pdt ","m_szGeo1":"United States","m_szSourceType":"source_industry","m_szSrcUrl":"http://peswiki.com/index.php/News:Archive:Page_3:October_28,_2011_Test_of_the_One_Megawatt_E-Cat","m_Places":["Bologna","Italy","United States","Miami, Fl","Manchester, Nh","Boston, Ma","Made","Take","Best","Us","Warm","U.s.","Falls, Mn","Ny","Usa","Uk","Cape Town"],"m_People":["Andrea Rossi","Steven Krivit","Bart Myers","Domenico Fioravanti","James Bowery","Mark Gibbs","Luke Mortensen","Gary Hendershot","Sterling Allan","Philippine Doe","Just A Typo"],"m_Companies":["Ap","Associated Press","Quora","Nato","Youtube","Cnn","Congress","White House","Forbes","Fox News","University Of Bologna","Aes","Revolution","Leonardo Corp.","Not Kg"],"m_BiGrams":["silverthunder pdt","andrea rossi","francesco pdt","cold fusion","oct silverthunder","ecat test","andrea rossis","rossis ecat","pdt andrea","pdt francesco","plant customer","test megawatt","megawatt ecat","mst subject","oct ecat","exotic nuclear","nuclear cold","fusion rossi","warm regard","rossi reading","reading test","customer bought","bought validated"],"m_TriGrams":["oct silverthunder pdt","andrea rossis ecat","pdt andrea rossi","exotic nuclear cold","nuclear cold fusion","cold fusion rossi","silverthunder pdt andrea","silverthunder pdt francesco","rossi reading test","plant customer bought","customer bought validated"],"m_SocialTags":[],"m_Topics":[],"m_Industry":[],"m_Technology":[],"m_BiCnt":[28,13,10,10,7,5,5,5,4,4,4,3,3,3,3,3,3,3,3,3,3,3,3],"m_TriCnt":[7,5,4,3,3,3,3,3,3,3,3],"m_iDocBodyWordCnt":1080}
