{"m_szDocID":"812382","m_szDocTitle":"Ovidiu Sandru","m_szYear":"2016","m_szDocSumamry":"The Green Optimistic - alternative energy news, environmental awareness Show Navigation Hide Navigation Home About Us Contact Us Green Tech Environment Green Energy Transportation Currently browsing author Ovidiu Sandru Green Electronics Ovidiu Sandru April 18, 2016 Lighty, the Smart Robotic Projector That’s Greener Than a TV Electronic junk is renowned nowadays for being one of the worst pollution sources ever. People don’t recycle their old phones, TVs, radios … Thermoelectric Ovidiu Sandru April 6, 2016 Fire-Powered Wifi Router in a Stone Aims to Take You Online in the Wild A Wi-Fi router e","m_szDocBody":"green optimistic alternative energy new environmental awareness show navigation hide navigation home contact green tech environment green energy transportation browsing ovidiu sandru green electronic ovidiu sandru lighty smart robotic projector greener electronic junk renowned nowaday worst pollution source ever people dont recycle phone tvs radios thermoelectric ovidiu sandru firepowered wifi router stone aim online wild wifi router embedded ina tonne rock powered fire connected deepest forest wireless tesla motor ovidiu sandru tesla model unveiled today cost cut feel tesla tesla model finally unveiled hour ago hawthorne spacex studio usualthis elon musk tesla motor ovidiu sandru review tesla model youve secretly admiring tesla model lately surely watch this energy new ovidiu sandru ultraefficient urine fuel cell produce electricity unprecedented rate dream turning urine seemingly humanity age turned energy elon musk ovidiu sandru tesla logo found model firmware elon musk react totally unexpected hacker aka security expert named jason hughes cracked open firmware tesla model revealed green new ovidiu sandru flushing toilet harvested rainwater save planet water shortage worst nightmare city summer month electric vehicle ovidiu sandru top hottest electric car geneva motor show geneva motor show promised lot delivered spark caught eye green electronic ovidiu sandru bet smart led lightbulb ditch cfl world important lightbulb maker decided shift led lighting already solar power ovidiu sandru solar power solar poweris undeniably future energy harness free everlasting power source convert tesla motor ovidiu sandru tesla model russia style test drive ive lot tesla model test drive ive russian guy who hereally love ovidiu sandru top energy drain household and greenify them hour day make sense biggest energy waster ovidiu sandru green home security system imagine this small white fence nice green lawn tree cosy house bedroom tesla motor ovidiu sandru model crushed huge tree ended havent heard tesla model crashes death injury time because elon musk ovidiu sandru mile range tesla car elon musk recent interviewwith danish television station elon musk revealed tesla working hard increase range tesla motor ovidiu sandru tesla model drag race row temptation searching model couple drag race category biofuel biodiesel biogas ethanol environment climate change green new green policy pollution recycling sustainable food video exotic energy free energy gravity magnetic power nikola tesla water car green energy energy new energy storage geothermal power hydro power hydrogen power nuclear power piezoelectric solar power synthetic fuel thermoelectric wave power wind power green tech experiment green building green design green electronic nanotechnology invention pointless green power saving superconductor water purifier humour transportation air powered car industry efficient engine electric vehicle tesla motor elon musk hybrid vehicle stirling engine uncategorized new address green optimistic disclaimer website cooky assume this optout wishok read ","m_szGeo1":"","m_szSourceType":"source_general","m_szSrcUrl":"http://www.greenoptimistic.com/author/ovidiu/","m_Places":["United States","Tesla","Best","Flushing","Geneva","Russian Federation","Gravity"],"m_People":["Ovidiu Sandru","Elon Musk","Jason Hughes"],"m_Companies":["Tesla Motors","Hawthorne Spacex Studio","Youtube"],"m_BiGrams":["ovidiu sandru","tesla model","elon musk","tesla motor","motor ovidiu","sandru tesla","green electronic","solar power"],"m_TriGrams":["tesla motor ovidiu","motor ovidiu sandru","ovidiu sandru tesla","sandru tesla model"],"m_SocialTags":[],"m_Topics":[],"m_Industry":[],"m_Technology":[],"m_BiCnt":[17,8,7,6,5,4,3,3],"m_TriCnt":[5,5,4,3],"m_iDocBodyWordCnt":440}
