{"m_szDocID":"812438","m_szDocTitle":"Transportation Archives – The Green Optimistic","m_szYear":"2016","m_szDocSumamry":"The Green Optimistic - alternative energy news, environmental awareness Show Navigation Hide Navigation Home About Us Contact Us Green Tech Environment Green Energy Transportation Currently browsing category Transportation Electric Vehicles Mila Luleva April 20, 2016 The Netherlands to Ban Sales of Diesel and Petrol Vehicles by 2025 The Netherlands might become the first country in the world to ban all sales of diesel, petrol and even hybrid vehicles. The … Electric Vehicles Matija Kordic April 8, 2016 Electric Vehicles May Replace Gas Cars by 2025, MIT Professor Says We are entering a new era","m_szDocBody":"green optimistic alternative energy new environmental awareness show navigation hide navigation home contact green tech environment green energy transportation browsing category transportation electric vehicle mila luleva netherland ban sale diesel petrol vehicle netherland country world ban sale diesel petrol hybrid vehicle electric vehicle matija kordic electric vehicle replace gas car mit professor entering era era sustainable development renewable energy elon musk leader electric vehicle matija kordic selfdiagnosing smart electric motor powering future evs scientist world realised time make change implement them time create technology tesla motor ovidiu sandru tesla model unveiled today cost cut feel tesla tesla model finally unveiled hour ago hawthorne spacex studio usualthis elon musk tesla motor ovidiu sandru review tesla model youve secretly admiring tesla model lately surely watch this electric vehicle mila luleva bmw bubble car inspire electric microlino bmw iconic isetta bubble car inspire line join theelectric vehicle family meet allelectric microlino microlino electric vehicle mila luleva london red double decker allelectric london famous red doubledecker receive electric makeover london attracted considerable amount ecofriendly innovative solution number elon musk ovidiu sandru tesla logo found model firmware elon musk react totally unexpected hacker aka security expert named jason hughes cracked open firmware tesla model revealed electric vehicle ovidiu sandru top hottest electric car geneva motor show geneva motor show promised lot delivered spark caught eye efficient engine natalie pullen international agreement slash aircraft carbon emission airline harder sector decarbonise reduce carbon emission country signed landmark agreement car industry natalie pullen energy live saved toyotas thermotect lime green paint road runner vital visibility safety remain paramount fashion thankfully running apparel fashion electric vehicle satya sivani charge phone booth spark plug spark plug simple solution range anxiety spark ventureshas converted selected phone booth auckland electric vehicle mila luleva veemo electric velomobile make pedal veemo smart pedalelectric powered alternative electric bicycle electric car choose electric market electric vehicle mila luleva generation nissan battery made latest nissan generation battery electric vehicle made time company electric vehicle mila luleva electric food truck lead sustainability allelectric food truck philadelphia lead sustainable pollutionfree eating food truck convenient argue hydrogen power mila luleva easyjet power aircraft hydrogen fuel cell easyjet ofuksleading low cost airline company announced plan power plane hydrogen fuel cell past category biofuel biodiesel biogas ethanol environment climate change green new green policy pollution recycling sustainable food video exotic energy free energy gravity magnetic power nikola tesla water car green energy energy new energy storage geothermal power hydro power hydrogen power nuclear power piezoelectric solar power synthetic fuel thermoelectric wave power wind power green tech experiment green building green design green electronic nanotechnology invention pointless green power saving superconductor water purifier humour transportation air powered car industry efficient engine electric vehicle tesla motor elon musk hybrid vehicle stirling engine uncategorized new address green optimistic disclaimer website cooky assume this optout wishok read ","m_szGeo1":"","m_szSourceType":"source_general","m_szSrcUrl":"http://www.greenoptimistic.com/category/transportation/","m_Places":["United States","Ban Sales","Tesla","Best","London","Geneva","Toyota","Auckland","Made","Uk","Philadelphia","Gravity"],"m_People":["Mila Luleva","Matija Kordic","Elon Musk","Ovidiu Sandru","Jason Hughes","Natalie Pullen","Satya Sivani"],"m_Companies":["Diesel","Tesla Motors","Hawthorne Spacex Studio","Bmw","Booths","Nissan","Easyjet"],"m_BiGrams":["electric vehicle","mila luleva","vehicle mila","elon musk","ovidiu sandru","tesla model","tesla motor","food truck"],"m_TriGrams":["vehicle mila luleva","electric vehicle mila"],"m_SocialTags":[],"m_Topics":[],"m_Industry":[],"m_Technology":[],"m_BiCnt":[13,7,6,5,4,4,3,3],"m_TriCnt":[6,5],"m_iDocBodyWordCnt":471}
