{"m_szDocID":"812439","m_szDocTitle":"Green Energy Archives – The Green Optimistic","m_szYear":"2016","m_szDocSumamry":"The Green Optimistic - alternative energy news, environmental awareness Show Navigation Hide Navigation Home About Us Contact Us Green Tech Environment Green Energy Transportation Currently browsing category Green Energy Solar Power Mila Luleva April 22, 2016 Thermophotovoltaic Solar Cells Produce Electricity in the Dark Scientists developed a new nanomaterial that can make solar cells generate electricity in the dark. “Solar power generation in the dark? How … Energy news Mila Luleva April 18, 2016 Watly, Solar-Powered Computer that Provides Clean Water, Electricity and Internet Watly is the ","m_szDocBody":"green optimistic alternative energy new environmental awareness show navigation hide navigation home contact green tech environment green energy transportation browsing category green energy solar power mila luleva thermophotovoltaic solar cell produce electricity dark scientist developed nanomaterial make solar cell generate electricity dark solar power generation dark energy new mila luleva watly solarpowered computer clean water electricity internet watly world largest solarpowered computer clean drinking water green solar power internet connectivity part energy new mila luleva ges compact carbon dioxide turbine power town latest development global research desksized supercritical carbon dioxide turbine capacity power solar power mila luleva graphene solar cell produce electricity sun rain adding graphene solar cell make generate power rain solar power continuous rise past thermoelectric ovidiu sandru firepowered wifi router stone aim online wild wifi router embedded ina tonne rock powered fire connected deepest forest wireless hydrogen power mila luleva energy offer affordable hydrogen generator home lowcost hydrogen generator energy renaissance coming soonto wipe fossil fuel remarkable clean energy technology michael rush exhaust heat recovery system charge phone world constantly moving cleaner greener mean transportation complete transition kind transport energy new michael rush cheap oil mean money green energy price fuel fallen dramatically recent month culprit lack profitability international oil green building mila luleva cochin airport india world fully powered solar panel cochin international airport kerala india airport completely powered solar success storey invention mila luleva revolutionary roll solar panel invented renovagen flexible solar panel renovagen rolled transported pretty everywhere safe solar power energy new ovidiu sandru ultraefficient urine fuel cell produce electricity unprecedented rate dream turning urine seemingly humanity age turned energy energy new mila luleva artificial tree osu harness energy vibration artificial tree inspired nature harness energy ofsurrounding vibration traffic earthquake recent year covered energy storage mila luleva recycled rechargeable battery energizer energizer product line offer world recycled rechargeable battery nowaday difficult imagine live battery solar power mila luleva world thinnest lightest solar cell developed mit team researcher mit developed world lightest thinnest solar cell electronic smarter better sophisticated energy solar power mila luleva massive floating solar array construction london massive floating solar array installed suburb oflondon thame water runner experiment satya sivani material greatly improve solar fuel cell peformance chemist university texas arlingtonuta devised material performance solar cellsto split carbon dioxide water category biofuel biodiesel biogas ethanol environment climate change green new green policy pollution recycling sustainable food video exotic energy free energy gravity magnetic power nikola tesla water car green energy energy new energy storage geothermal power hydro power hydrogen power nuclear power piezoelectric solar power synthetic fuel thermoelectric wave power wind power green tech experiment green building green design green electronic nanotechnology invention pointless green power saving superconductor water purifier humour transportation air powered car industry efficient engine electric vehicle tesla motor elon musk hybrid vehicle stirling engine uncategorized new address green optimistic disclaimer website cooky assume this optout wishok read ","m_szGeo1":"","m_szSourceType":"source_general","m_szSrcUrl":"http://www.greenoptimistic.com/category/green-energy-2/","m_Places":["United States","Means","India","London","Gravity"],"m_People":["Mila Luleva","Ovidiu Sandru","Satya Sivani","Elon Musk"],"m_Companies":["Ge Global Research","Renaissance","Energizer","Thames Water","University Of Texas At Arlington","Uta","Tesla Motors"],"m_BiGrams":["mila luleva","solar power","solar cell","energy new","power mila","green energy","cell produce","produce electricity","new mila","carbon dioxide","solar panel"],"m_TriGrams":["power mila luleva","solar power mila","cell produce electricity","new mila luleva"],"m_SocialTags":[],"m_Topics":[],"m_Industry":[],"m_Technology":[],"m_BiCnt":[11,9,6,5,5,4,3,3,3,3,3],"m_TriCnt":[4,3,3,3],"m_iDocBodyWordCnt":479}
