{"m_szDocID":"822412","m_szDocTitle":"Nuclear Power Plant Instrumentation And Control Systems For Safety And Security | Download eBook PDF/EPUB","m_szYear":"2016","m_szDocSumamry":"Privacy Policy nuclear power plant instrumentation and control systems for safety and security Download nuclear power plant instrumentation and control systems for safety and security or read online here in PDF or EPUB. Please click button to get nuclear power plant instrumentation and control systems for safety and security book now. All books are in clear copy here, and all files are secure so don't worry about it. This site is like a library, you could find million book here by using search box in the widget. Format Available : PDF, ePub, Mobi Total Read : 79 Total Download : 520 File Size ","m_szDocBody":"privacy policy nuclear power plant instrumentation control system safety security download nuclear power plant instrumentation control system safety security read online epub button nuclear power plant instrumentation control system safety security book now book clear copy here file secure worry library million book box widget format pdf epub mobi total read total download file size description accident natural disaster involving nuclear power plant chernobyl mile island recent meltdown fukushima rare effect devastating warrant increased vigilance addressing safety concern nuclear power plant instrumentation control system safety security evaluate risk inherent nuclear power method preventing accident computer control system emerging technology student scholar operator designer insight latest security technology potential make future nuclear energy clean safe reliable committee application digital instrumentation control system nuclear power plant operation safety languange publisher national academy press format pdf epub mobi total read total download file size description nuclear industry nuclear regulatory commission usnrc working year development adequate process guide replacement ageing analogue monitoring control instrumentation nuclear power plant modern digital instrumentation introducing offsetting safety problem book identify criteria usnrc review acceptance digital application nuclear power plant focuse areas software quality assurance commonmode software failure potential system aspect digital instrumentation control technology human factor humanmachine interface safety reliability assessment method dedication commercial offtheshelf hardware software casebycase licencing process adequacy technical infrastructure committee application digital instrumentation control system nuclear power plant operation safety languange publisher national academy press format pdf epub mobi total read total download file size description nuclear industry nuclear regulatory commission usnrc working year development adequate process guide replacement ageing analogue monitoring control instrumentation nuclear power plant modern digital instrumentation introducing offsetting safety problem book identify criteria usnrc review acceptance digital application nuclear power plant focuse areas software quality assurance commonmode software failure potential system aspect digital instrumentation control technology human factor humanmachine interface safety reliability assessment method dedication commercial offtheshelf hardware software casebycase licencing process adequacy technical infrastructure publisher phi learning pvt ltd format pdf epub mobi total read total download file size description edition present overview power generation discusse type equipment steam thermal power generation unit book describe conventional nonconventional energy source elaborate instrumentation control watersteam fuelair flue gas circuit optimization combustion deal power plant management system including combustion process boiler efficiency calculation maintenance safety aspect addition book explain supervisory control data acquisition scada system turbine monitoring control book designed undergraduate student electronic instrumentation engineering electrical electronic engineering edition chapter nuclear power plant instrumentation added elaborate electricity generated nuclear power plant key feature include numerous figure clarify concept number workedout problem student enhance learning skill chapterend exercise enable student test understanding subject publisher oreilly media inc format pdf epub mobi total read total download file size description stuxnet computer worm damaged iranian nuclear programme public small glimpse modern cyber warfarewithout realising scope global conflict inside cyber warfare fascinating disturbing detail nation group individual world increasingly rely internet attack gain military political economic advantage adversary updated edition take detailed complex domain cyberspace player strategy involved youll discover sophisticated hacker working behalf state organised crime patiently play highstake game target anyone affiliation nationality discover russian investment social network benefit kremlin learn role social network fomenting revolution middle east northern africa explore rise anarchist group anonymous lulzsec inside cyber warfare capability nation including china israel understand legally engage covert cyber operation learn intellectual property war primary focus statesponsored cyber operation jeffrey carr founder ceo taia global inc cyber intelligence expert consultant specialise investigation cyber attack government infrastructure state nonstate hacker format pdf epub mobi total read total download file size description aimed novice expert security industrial control system ics book reader gain understanding protecting icss electronic threat cyber security attention scada security supervisory control data acquisition important part field distributed control system dcs programmable logic controller plc remote terminal unit rtus intelligent electronic device iedsand other field controller sensor drive emission control make intelligence modern industrial building facility book reader understand industrial control system cyber security security happened date done load practical advice offered clarity current cybersecurity system integrated general system conduct risk assessment obtain certification future trend legislative regulatory issue affecting industrial security bela liptak languange format pdf epub mobi total read total download file size description instrument engineer handbook volume process software digital network fourth edition latest addition enduring collection industrial automation professional refer bible published entire handbook approximately page designed standalone volume cover measurement volume control volume software volume aspect automation fourth edition volume indepth stateoftheart review control software package plant optimization control maintenance safety updated volume renowned reference require year prepare revised instalment issued decade taking account numerous development occur next assessing rapid evolution automation optimization control system type industrial plant book detail communication software used include everincreasing number application intelligent instrument enhanced network internet use virtual private network integration control system main network management operate linked global environment topic covered include advance display operator quickly assess respond plant condition software network monitor control optimise industrial processe determine efficiency energy consumption profitability operation strategy counteract market condition energy raw material cost technique fortify safety plant operation security digital communication system volume explore holistic approach integrating process enterprise network convenient efficient problem involving cyber local network security energy conservation issue show firewall separate business operation automation technology domain guarantee safe function industrial plant book illustrate concern addressed effective technical solution proper management policy practise reinforcing fact industrial control system are general critically interdependent handbook wide range software application example industry including automotive mining renewable energy steel dairy pharmaceutical mineral processing oil gas electric power utility nuclear power format pdf epub mobi total read total download file size description instrumentation defined subject fuzzy boundary number discipline categorised technique application book addresse application needed reference practical technique instrumentation measurement specific physical quantity quality make direct interest working process control instrumentation field measurement essential comprehensive authoritative collection technical information written collection specialist contributor updated include chapter fieldbus standard reliability emc virtual instrumentation fibre optic smart intelligent transmitter analyzer level flow metre diane company languange format pdf epub mobi total read total download file size description exportimport bank approved decision guarantee loan million work performed westinghouse electric corp temelin nuclear power plant sovietdesigned reactor czech republic report information reason bank loan guarantee action bank ensure soundness project including project safety issue involving government potential liability case nuclear accident result loan guarantee bela liptak languange format pdf epub mobi total read total download file size description instrument engineer handbook edition volume three process software digital network indepth stateoftheart review existing evolving digital communication control system book highlight transportation digital information buse network total coverage stop there describe variety processcontrol software package suited plant optimization maintenance safety related application addition topic include plant design modernization safety operation related logic system design integrated workstation control centre book conclude appendix providing practical information bidder list addresse steam table material selection corrosive service more buy threevolume set instrument engineer handbook process control engineer instrumentation technician need buy volume fingertip software digital network related information needed i&c engineer resource reach again format pdf epub mobi total read total download file size description master storyteller leading energy expert daniel yergin continue riveting storey begun pulitzer prizewinning book prize quest yergin show energy engine global political economic change conflict storey span energy civilization built energy competing replace them quest tell inside storey tackle tough question reveal surprising insight coal electricity natural gas explain climate change great lead reader rebirth renewable energy energy independence return electric car epic scope timely quest vividly reveal decision technology individual shaping future richard dorf languange format pdf epub mobi total read total download file size description published engineering handbook quickly definitive engineering reference remain bestseller advance realised traditional engineering field emergence rapid growth field biomedical engineering computer engineering nanotechnology time bring standardsetting reference date edition completely chapter addressing important topic bioinstrumentation control system nanotechnology image signal processing electronic environmental system structural system chapter fully revised updated expanded list engineering association society engineering handbook edition designed enlighten expert areas specialty refresh knowledge mature practitioner educate engineering novice work industry government academia simply best engineering reference personal office institutional library kenneth kok languange format pdf epub mobi total read total download file size description nuclear power has recent year undergone major transformation resulting major technical development generation nuclear scientist engineer comprehensive book reflect latest nuclear technology lackinguntil now nuclear engineering handbook response global resurgence interest commercial nuclear power broad overview nuclear power engineering limitless potential basic introduction field indepth discussion power plant extensive coverage nuclear fuel cycle waste disposal related engineering technology organised sectionsnuclear power reactor nuclear fuel cycle processe facility engineering analytical applicationsthis book addresse entire nuclear fuel cycle process topic include mining milling enrichment uranium thorium fuel resource fuel fabrication nuclear material transportation fuel reprocessing safe waste disposal allencompassing volume discusse current analytical technique related nuclear engineering addressing safety heat transfer shielding thermohydraulic heat physic covering reactor operation radiation protection outline economic consideration involved building nuclear power station large fossilfueled plant elaborate concern control emission latter review past current nuclear engineering capability valuable resource cover gamut crucial topic including historical perspective detailed technological review assessment field future direction exceptional tool reader foster optimal understanding nuclear power electricity generation future format pdf epub mobi total read total download file size description sound introduction radiation detection measurement newcomer nuclear science engineering bestselling edition advance field radiation detection notably practical application incorporating important development measurement detection radiation fourth edition uptodate accessible introduction radiation detector material system application fourth edition chapter nuclear forensic nuclear medicine instrumentation covering basic principle application openended problem encourage indepth research updated reference bibliography expanded problem student nuclear professional popular predecessor fourth edition continue carefully explain latest radiation detector technology measurement technique discusse correct way perform measurement analyse result current health physic procedure raymond murray languange format pdf epub mobi total read total download file size description expanded revised updated fourth edition nuclear energy maintain tradition providing clear comprehensive coverage aspect subject emphasis explanation trend development earlier edition book divided part achieve natural flow ideas basic concept including fundamental energy particle interaction fission fusion nuclear system including accelerator isotope separator detector nuclear reactor nuclear energy man covering application radionuclide radiation reactor discussion waste weapon minimum mathematical background required ample opportunity learn characteristic number illustrative calculation exercise updated solution manual instructor feature aid student set computer exercise diskette personal computer programme basic spreadsheet supplied nominal cost book principal introduction nuclear science technology early college student benefit science teacher lecturer nuclear utility trainee engineer field john shultis languange format pdf epub mobi total read total download file size description bestselling edition numerous advance field nuclear science medicine accelerator based teletherapy electronbeam therapy standard demand national security stimulated major advance nuclear instrumentationan ideal introduction fundamental nuclear science engineering book present basic nuclear science needed understand quantify extensive range nuclear phenomena edition chapter radiation detection douglas mcgregor uptodate coverage radiation hazard reactor design medical application flexible organisation material quick reference edition take indepth particle accelerator nuclear fusion reaction device nuclear technology medical diagnostic treatment addition discusse application direct conversion nuclear energy electricity breadth coverage unparalleled ranging theory design characteristic nuclear reactor identification biological risk ionising radiation topic supplemented extensive nuclear data compilation perform wealth calculation providing extensive coverage physic nuclear science nuclear technology type uptodate edition fundamental nuclear science engineering key reference physicist engineer catherine majumdar languange publisher springer science business media format pdf epub mobi total read total download file size description conference brought expert country discuss application artificial intelligence technique nuclear industry apparent meeting active field surprised extent work progress made strong impression application technology nuclear power plant inevitable benefit improved operation design safety simply significant ignored conclusion reached year ago technology people struggling understand significance meeting reflect major turning point technology moved topic understood specialist situation user active people field broad array innovative work participating country activity large diverse nationally focussed policy research activity reported here japan france strong drive integrate technology nuclear plant reflecteq proceeding publisher mcgraw hill professional format pdf epub mobi total read total download file size description featuring foreword michael chertoff secretary homeland security mcgrawhill homeland security handbook onestop guide professional student involved counterterrorism homeland security business continuity disaster risk management indispensable book government official corporate risk manager business security executive responder homeland security emergency preparedness professional wideranging definitive overview critical homeland security issue handbook addresse virtually aspect homeland security including terrorism motivated radical islamist extremism transportation infrastructure protection community business resilience intelligence information role business academia science private sector confronting terrorism natural disaster enriched insight knowledge renowned national international expertsfrom senator captain industry key figure intelligence military affair diplomacy international organisation academiathis peerless guide offer prescriptive strategy guidance security professional effectively manage risk terrorism prepare respond natural disaster conveniently organised thematic section mcgrawhill homeland security handbook cover terrorist criminal threat policy governance legal response interoperability information sharing collaboration risk management decision making communication protecting critical infrastructure disaster preparedness emergency management private sector security resilience thinking education training science technology civil liberty legal issue international challenge approaches mcgrawhill homeland security handbook synthesise latest information unmatched scope detail discusse government businesse citizen manage risk disaster counter evolving threat ","m_szGeo1":"United States","m_szSourceType":"source_general","m_szSrcUrl":"http://www.ebooksdownloads.xyz/search/nuclear-power-plant-instrumentation-and-control-systems-for-safety-and-security","m_Places":["Chernobyl","Three Mile Island","Fukushima","Middle East","Africa","Look","China","Israel","United States","Czech Republic","Japan","France","Hill"],"m_People":["Jeffrey Carr","Bela G. Liptak","Daniel Yergin","Richard C. Dorf","Kenneth D. Kok","Raymond L. Murray","John K. Shultis","Douglas Mcgregor","M. Catherine Majumdar","Michael Chertoff"],"m_Companies":["Academies Press","U.s. Nuclear Regulatory Commission","Usnrc","O'reilly Media, Inc.","Target","Revolution","Dcs","Boundary","Emc","Publishing Company","Export-import Bank","Westinghouse Electric Corp","U.s. Government","Quest","Signal","Cycle","Mcgraw-hill"],"m_BiGrams":["nuclear power","format pdf","pdf epub","epub mobi","mobi total","total read","read total","total download","download file","file size","size description","power plant","control system","instrumentation control","homeland security","languange format","nuclear science","digital instrumentation","fourth edition","plant instrumentation","system safety","safety security","nuclear energy","natural disaster","plant operation","languange publisher","description nuclear","nuclear industry","monitoring control","control instrumentation","maintenance safety","edition chapter","industrial control","instrument engineer","engineer handbook","software digital","digital network","engineering handbook","nuclear technology","nuclear engineering","nuclear fuel","fuel cycle","radiation detection","science engineering","mcgrawhill homeland","security handbook"],"m_TriGrams":["format pdf epub","pdf epub mobi","epub mobi total","mobi total read","download file size","file size description","nuclear power plant","languange format pdf","instrumentation control system","power plant instrumentation","plant instrumentation control","control system safety","system safety security","digital instrumentation control","size description nuclear","industrial control system","instrument engineer handbook","software digital network","nuclear fuel cycle","nuclear science engineering","mcgrawhill homeland security","homeland security handbook"],"m_SocialTags":[],"m_Topics":[],"m_Industry":[],"m_Technology":[],"m_BiCnt":[22,18,18,18,18,18,18,18,18,18,18,17,15,9,8,7,7,6,6,5,4,4,4,3,3,3,3,3,3,3,3,3,3,3,3,3,3,3,3,3,3,3,3,3,3,3],"m_TriCnt":[18,18,18,18,18,18,15,7,6,5,4,4,4,4,3,3,3,3,3,3,3,3],"m_iDocBodyWordCnt":2171}
