{"m_szDocID":"829577","m_szDocTitle":"BHP – TradingStocks.me","m_szYear":"2016","m_szDocSumamry":"Several little-know macroeconomic factors are changing the global supply and demand of gold. Read on to find out what they are. -Posted by Alejandro Guillú Mendoza Introduction This article tries to explain in a simple way to readers without a college degree in economics or finance some macroeconomic factors that are currently changing the global supply and demand of gold. They’re not often talked about, but they are very important to understanding the precious metals market! Ground rules Gold coins ARE NOT INVESTMENTS. Gold coins are still minted by countries to satisfy the unlimited demand f","m_szDocBody":"littleknow macroeconomic factor changing global supply demand gold read are posted alejandro guill mendoza introduction explain simple reader college degree economic finance macroeconomic factor changing global supply demand gold theyre talked about important understanding precious metal market ground rule gold coin investment gold coin minted country satisfy unlimited demand numismatist world acquire gold coin paying precious metal graphic design minting country make billion dollar year buying gold tonne reselling coin wrong collecting coin millionaire not sell coin collection highest bidder problem gold coin pay insurance year cost eat profit invest gold buy gold mine etf iau gld financial instrument sophisticated investor cover article write drop line mexico bullion superpower carlos slim hel country world produce gold mexico however annual gold production grown doubledigit rate unlike country mexico dont gold land gold backyard government take mexican prospector point modern technology gold mine mexico buy land make literally tonne cash imagine demand geologist mexico monetize natural resource year gold mining united state america peru canada remain third sixth seventh largest gold producer world mexico similar country geological point mined gold yet word mountain gold mexico supply gold continent america vast unlimited current global demand gold pay entire debt country continent america rest world year faster cheaper way extract gold innovation apply extraction gold important factor gold found remote location civilization gold mine invest lot money diesel transport precious metal nearest dhl ups federal express location electric car increase profit gold mine coming year economic crisis mexico expert hired avoid economic crisis future suggestion billionaire foreign publiclytraded mining company extract gold save rainy day fresnillo london fre ftse company thlargest diversified metal mining company world forbe annual profit million bad idea set limit order buy company case price drop current level due panic selloff mexico hold tonne gold buying gold fresnillo mining company operating mexico gold reserve tonne venezuela hold mexico richest country world billion foreign exchange reserve afford buy gold buy amount gold extract attract lot gold mining company dont invest capital mexico lend cash instal mine pay loan gold pay mastercard bank america gold coin billiondollar syndicated loan mining company russia south africa peru canada indonesia uzbekistan ghana start golden arches bank foreign publiclytraded mining company bhp billiton bhp freeportmcmoran fcx apply billiondollar loan build gold mine move mexico gold mart india like gold jewellery lot fact buy gold jewellery exception china smart china australia united state america russia south africa peru canada indonesia uzbekistan ghana mexico increase export gold jewellery simply lend money young entrepreneur pakistan nepal buthan burma bangladesh sri lanka maldive open gold mart franchise fictional gold mart franchise strategically located city border india encourage small business owner buy gold jewellery sell consumer india gold mart include large selection jewellery small company dont infrastructure export small quantity gold jewellery india country handle logistic ship product largest market gold jewellery create lot job gold jewellery industry lot tax revenue obviously consultant country previously mentioned hired people smarter demand gold lot clever solution export gold jewellery india regular guy country entire army consultant thinking solve problem day long conclusion india force people stop wearing gold jewellery systematically sell gold reserve time price gold usual reserve depleted gold stored vault produce cash unless course lend gold lend share gold mine time india invest ghana stock exchange uzbekistan stock exchange indonesia stock exchange thought alway prepared volatility gold market matter allocate portfolio precious metal remember gold hedge currency collapse guarantee currency collapse preserving capital trump desire make large profit world largest silver producer year world largest silver producer dominated company fresnillo plc lonfre bhp billiton ltd nysebhp changed year world largest silver producer dominated company fresnillo plc lonfre bhp billiton ltd nysebhp fresnillo named mammoth fresnillo silver mine mexico bhp operate cannington mine australia fresnillo cannington mine primary silver mine mean silver predominant metal mined site year mine helped bhp fresnillo world largest silver producer though crown polish mining company kghm polska miedz pinkkghpf what interesting fact kghm doesnt primary silver mine captured world largest silver producer mining silver byproduct metal world top silver producer kghm polska miedz pinkkghpf million ounce silver bhp billiton ltd nysebhp million ounce silver fresnillo plc lonfre million ounce silver lead changing guard silver production fresnillo cannington decline quality ore coming site dropped cheque year number difference world top silver producer bhp billiton ltd nysebhp million ounce silver fresnillo plc lonfre million ounce silver kghm polska miedz pinkkghpf million ounce silver source market oracle course read number potential investment opportunity that recommend searching junior mining company make good buyout candidate company acquired bhp fresnillo instance cheque recent post silver mining stock more top uranium mining stock obvious industry leader uranium mining difficult small midcap mining stock differentiated sector here uranium mining stock warrant deeper look obvious industry leader uranium mining cameco corporation nyseccj bhp billiton limited nysebhp difficult small midcap mining stock differentiated sector pinetree capital business development philip william recently offered favourite uranium mining stock interview energy report ticker commentary name mega uranium ltd tsemga based canada mega uranium focused property cameroon canada australia home world largest uranium deposit megas massive lake maitland project feasibility study stage project resource million tonne inferred resource million tonne stock percent yeartodate percent past month rockgate capital corp tsergt share rockgate fire rising percent start year percent past month company flagship project percent owned falea deposit mali shown uncapped resource pound uranium ounce silver rockgate potential takeover target large foreign uranium miner grow holding africa corp pinkutref project guyana colombia argentina corp significant foothold south america area long uraniummining company company cerro solo area argentina hold million pound kurupung batholith project guyana hold more william call south america frontier uranium development expect expand resource project tenfold year share percent year date percent past month energy fuel inc tseefr based canada energy fuel focused uranium deposit southwestern utah colorado stock big boost earlier year company application pinon ridge uranium mill approved turn energy fuel consolidator uranium mining space seek right property area share percent year date percent past year mawson resource ltd tsemaw based vancouver mawson flagship project highgrade uranium gold deposit rompas finland surface sample shown ounce tonne gold percent uranium william call freakishly highgrade gold uranium share exploded upward strength early result yeartodate maw returned percent percent past month ","m_szGeo1":"Mexico","m_szSourceType":"source_general","m_szSrcUrl":"http://tradingstocks.me/tag/bhp/","m_Places":["Mendoza","Take","Mexico","United States","Peru","Canada","America","London","Venezuala","Russian Federation","South Africa","Indonesia","Uzbekistan","Ghana","India","China","Australia","Pakistan","Nepal","Burma","Bangladesh","Sri Lanka","Maldives","Polska","Cameroon","Maitland","Mali","Africa","Guyana","Colombia","Argentina","South America","Cerro","Utah","Pinon","Vancouver","Finland"],"m_People":["Alejandro Guillú","Carlos Slim Helú","Philip Williams"],"m_Companies":["Diesel","Ups","Federal Express","Forbes","Mastercard","Bank Of America","Golden Arches Bank","Bhp Billiton","Bhp","Freeport-mcmoran","Fcx","Ghana Stock Exchange","Uzbekistan Stock Exchange","Indonesia Stock Exchange","Fresnillo Plc","Bhp Billiton Ltd.","Crown","Oracle","Cameco Corporation","Bhp Billiton Limited","Mega Uranium Ltd.","Rockgate Capital Corp.","Target","U3o8 Corp.","Williams","Mill","Mawson Resources Ltd."],"m_BiGrams":["gold jewellery","mining company","silver producer","ounce silver","gold mine","bhp billiton","world largest","million ounce","mining stock","uranium mining","gold coin","largest silver","demand gold","precious metal","buy gold","gold mart","fresnillo plc","plc lonfre","billiton ltd","ltd nysebhp","percent past","past month","peru canada","stock exchange","silver mine","kghm polska","polska miedz","miedz pinkkghpf","energy fuel"],"m_TriGrams":["million ounce silver","world largest silver","largest silver producer","fresnillo plc lonfre","bhp billiton ltd","billiton ltd nysebhp","kghm polska miedz","polska miedz pinkkghpf","uranium mining stock"],"m_SocialTags":[],"m_Topics":[],"m_Industry":[],"m_Technology":[],"m_BiCnt":[9,8,7,7,6,6,6,6,6,6,5,5,4,4,4,4,4,4,4,4,4,4,3,3,3,3,3,3,3],"m_TriCnt":[6,5,5,4,4,4,3,3,3],"m_iDocBodyWordCnt":1040}
