{"m_szDocID":"842516","m_szDocTitle":"News:Archive:2009:March - PESWiki","m_szYear":"2009","m_szDocSumamry":"News:Archive:2009:March Click here for most recent news. 2009 News:Archive:2009:April - moving forward in time March Biodiesel > from Algae > 'First Economical Process' For Making Biodiesel Fuel From Algae - One of the problems with current methods for producing biodiesel from algae oil is the processing cost.  Researchers from New York say their innovative process is at least 40 percent cheaper than that of others now being used. (Science Daily; March 31, 2009) U.S. Government and Energy / Fuel Efficiency > Obama to Automakers: Make Greener American Cars or Go Under - One of the reasons cited","m_szDocBody":"newsarchivemarch recent new newsarchiveapril moving forward time biodiesel algae first economical process making biodiesel fuel algae problem current method producing biodiesel algae oil processing cost researcher york innovative process percent cheaper used science daily government energy fuel efficiency obama automaker make greener american car reason cited obama denying chrysler bailout fund planned green enough order viable put effort resource developing selling fuel efficient vehicle treehugger monday fuel efficiency hybrid sery wheel motor drive dutch buse netherland company etraction developed sery hybrid bus diesel generator charge battery turn supply electricity motor rear wheel yielding increase mileage mit technology review tool communication jaxtr free international phone call service enter cell phone number cell phone number person call internationally received message local number call connect free place regular international call low rate sunday magnet motor howard johson howard johnson linear magnetic track accelerator video video video show howard johnson giving demonstration banana magnet magnetic gate apparent repelling force pound thrusting force measured scale accelerated gate continuing track overunitycom body electric grand unified theory free will electron mathematician proven human experimenter demonstrate free will choosing measurement particle axiom quantum mechanic require free property particle measured universe whole video slashdot building twelve amazing shipping container house number resourceful people converted shipping container makeshift shelter margin year architect green designer increasingly turning strong cheap boxe source building block yahoo green saturday magnet magnet motor howard johnson discovering magnetism video howard johnson demonstrate number unique magnetic gate accelerate car track littleknown ability magnet fire burst energy gun force thousand time powerful base magnet strength cheniereorg store tesla motor tesla model electric sedan break cover tesla motor electriccar maker unveiled model sedan thursday expected delivered customer quarter battery range mile mile mile based model priced federal tax credit time fuel efficient vehicle rave review world cheapest car tata nano hailed world cheapest car one greatest bargain time triumph indian ingenuity tiny car cute cartoon caricature cost rupee dollar autoblitz friday featured magnet motor howard johson mylow witherspoon howard johnson famous magnet motor inventor neighbour friend associate howard johnson witnessed allmagnet motor running jan johnson passed away pesn magnet magnet motor howard johnson secret world magnet book howard johnson claim magnet fire energy burst hundred time stronger base strength againthat similar magnetic pole attract repelor pattern iron filing magnet bear resemblance force field spinning vortice cheniereorg store grid electrical power grid blasted solar storm second catastrophe reliance technology unwittingly exposed extraordinary danger plasma ball spewed surface sun wipe power grid solution distributed free energy solution championed organisation nem nec orion project examiner see scientist thursday mar magnet motor howard johnson howard johnson motor report page report tom valone include scientific description article patent including copy virginia polytechnic professor report motor importance unique shape arc magnet science invention article analysis patented magnetic motor integrity research institute store magnet motor cycclone qeensland supreme court rule manget motor claimant pdf judgement rule deceptive representation respondent hoped develop machine powered magnet prototype made respondent stated attempt run machine successful respondent alleged represented worked sclqldorgau government energy stimulus appear sparking altenergy revival sign federal stimulus pumping life alternativeenergy industry financier law firm specialising renewable energy growing interest reviving moribund project breaking ground deal truthout wednesday mar featured magnet motor mylow corresepondence mylow collection sterling report phone conversation mylow appear successfully replicated howard johnson allmagnet motor open sourcing simple design making world peswiki government energy solar europe encouraging solar power arrive payment method referred feedin tariff europe essence mandate government telling utility pay abovemarket rate green electricity year shift burden subsidising green energy taxpayer electricity ratepayer new york time tuesday mar featured magnet motor mylow magmo interview mylow magnet motor night sterling allan conducted live hour interview mylow witherspoon associate howard johnson motor running called expressing approval mylow model open source approach freeenergynow gravity motor milkovic oscillator breakthrough theory milkovic twostage oscillator established parameter pdf aleksandar slavkovic propose milkovic invention belong category device called doublefulcrumbounded parametric oscillator show stage oscillator viewed damped parametric oscillator veljkomilkoviccom thank bobsy diy solar home building solar panel dutch guy build solar panel garage material expensive mass produced solar panel european market bought solar cell ebay create panel olino renewable energy also slashdot type energycouk renewable public interest website expert advice energy type consumption overview information hydro biomass geothermal solar wind conventional nuclear fossil conservation monday mar featured magnet motor mylow magmo mylow magnet motor video glass table mylow posted videos allmagnet motor based howard johnson stonehenge design allaluminum stator support video motor set glass table peswiki cold fusion neutron track revive hope cold fusion twenty year initial cold fusion announcement utah video event separate team made similar state time evidence seriously new scientist hydrogen production desalination salt water system generate hydrogen researcher university salerno italy suggest flowing salt water generate electromotive force turn generate electric power output electrode water split oxygen hydrogen gas electrode chlorine gas produced physorg sunday mar free energy perpetual commotion mark golde free energy sceptic abound device mylow magnet motor open door wider appreciation extremely important potential rapidly reducing dependency fossil fuel reviving automotive industry zpenergy suppression free energy labelled economic terrorism widespread adoption new nonpolluting energy propulsion system effectively replace oil gas coal nuclear power impacting trillion dollar year world economic activity replace current geopolitical order based decentralised abundance examiner grid bioenergetic cattle respond magnetic field power line researcher reported year cow deer tend orient northsouth alignment found power line disorient animal power line run eastwest grazing cattle tend line salt lake tribune nature saturday mar featured anti gravity magnet motor project home project home video show levitating magnetpropelled vehicle project featuring australian yearold inventor beginning posted video labelled magnetpowered vehicle toy size buzzing snow mud creek astonishing shown apparently levitating pesn fuel efficiency vehicle economic car world developed roadproven seater car apparently small size aerodynamic tear shape ready launched singleseater sale shanghai mere rmb mph travel mile gallon oneshift mar flight flying car terrafugia terrafugias flying car successfully take terrafugias transition small aircraft fold wing drive road fuel normal gas station park single car garage successfully tested plattsburgh international airport york flight lasted minute feet air video autoblitz mar friday mar featured magnet motor mylow mylow replicated howard johnson magnet motor storey garage tinkerer year persistence finally paid apparently replicating publicly announced allmagnet motor realise inventiveness bear pesn alt fuel ethanol honda sell world bike bioethanol mixed fuel honda motor company developed world motorcycle powered ecofriendly fuel mixed bioethanol gasoline put sale midmarch brazil world largest producer user bioethanol india time top thin film solar utilityscale thinfilm plant germany total germany host range thinfilm project illustrate technology potential largescale thinfilm installation recently commissioned combined capacity manufacturer solar renewable energy world gov energy obama put billion electric vehicle president barack obama unveiled billion dollar boost electric vehicle development vowing compete foreign nation race world leader renewable energy truthout thursday mar featured magnet motor perendev translation alleged perendev kwelectromagnet motor demo pending result storey netjournal ran perendev file box full correspondence sceptic angry customer received order etc the editor unit recently impressed apparently demo pending peswiki mar electric car tesla motor tesla unveil electric seat sedan week tesla motor announced unveil fiveseat sedan roll assembly line zeroemission model prototype lithiumion battery pack range mile kilometre charge car anticipated base price dollar yahoo new energy ocean world leading event held maine usa focus renewable sustainable energy ocean primary education platform networking event key player industry wednesday mar featured magnet motor mylow magnetic motor based howard johnson design mylow chicago apparently successfully replicated open sourcing late howard johnson allmagnet motor stonehenge model johnson worked early demonstrate patent office peswiki may update shown hoax alt fuel photosynthesis imitation turning sunlight liquid fuel researcher department energy lawrence berkeley national laboratory process major breakthrough artificial photosynthesis banking cobalt oxide effectively carry crucial photosynthetic reaction splitting water molecule develop fuel alt energy mar electric car irvinebased fisker run plugin canadian battery irvine automaker buy battery advanced lithium power inc alp luxury sedan karma alp vancouver supply battery military time ocean wave buoy pelamis portugal pelamis wave power project dead water million agucadoura project portugal end citing technical financial setback world current largest commercial wave power project offline indefinitely treehugger tuesday mar featured building tool barotex technology corporation company actively engaged innovation creation specialty fibre solution volcanic rock significantly redefine composite material industry impact world just composite barotex better money sustainable manner peswiki fuel efficiency engineer devise way reduce air drag vehicle plane researcher washington university louis developing active flow control afc technology deploy actuator surface vehicle modify air flow resistance reduced percent physorg electric car plugin electric car charge ahead car company worldwide offer plugin vehicle electric motor primary mean propulsion plugin america activist group allelectric drive vehicle plugin hybrid electric vehicle phev small gasoline engine backup christian science monitor obama deception entire film film released alex jone purport obama phenomenon carefully crafted hoax captain centuriesincoming world order based world domination control freedom monday mar top featured solar thin film solar break manufacturing barrier arizona company congratulated reducing manufacturing cost solar module cent watt breaking watt price barrier environmental downside highly toxic cadmium overlooked peswiki flight fuel cell italian allfuel cell flight planned allelectric skyspark prototype designed demonstrate takeoff cruise flight fuel cell power batterypowered flight test aircraft allelectric system safety precaution fuel cell december flightgobal store solar cooking sun oven cooking power sun larue howell bought global sun oven year ago prepared emergency time week allyear round share knowledge member church baked bread degree outside ksl pes sale price sunday mar featured videos energy vacuum sery part available feature tom bearden john bedini walter rosenthal deborah chung howard johnson peter lindemann daniel sheehan sparky sweet henry moray even tiny efficiency tapping space energy extract energy wish peswiki electrical grid smart grid prime time super bowl beginning outreach effort utility legislator public campaign place special emphasis smart grid area deployable offer great benefit scarecrow pluck smart grid new feb directory renewable energy incentive region salt lake county eye solar home live salt lake county current incentive utility company government reduce system cost percent cheque regional incentive directory incentive area deseret new earthship biotecture earthship global company offering proven totally sustainable design construction service worldwide company lead michael reynold principle biotect creator earthship concept saturday mar featured flight carter copter carter aviation technology research development company pioneering aviation concept focusing slowrotor compound aircraft vertol small efficient wing speed flight mph complexity tiltrotor vectored thrust vehicle peswiki electric bike motorbike scooter top gear electric bike top gear committed providing highest quality electric bike product including electric mountain bike folding electric bike provide excellent money optimal specification superior build warranty customer service advice aftersale service videos electric car byd pure electric vehicle include video range charge mile claimed mph acceleration second projected top speed mph lifepo lithium iron phosphate battery pack quickcharged percent capacity minute percent capacity minute engineering nuclear remediation patience pay methanol uranium bioremediation microcosm experiment uraniumcontaminated sediment ground water demonstrated equivalent rapid uranium reduction amended ethanol glucose contrast reduction delayed day microcosm amended methanol science daily feb friday mar featured alt fuel boron boronpowered vehicle unusual valid idea real prospect boron powered car main reason car fuelled boron safety reason boron combustible difficult light great car because accident made worse flammability fuel peswiki battery physicist develop battery source energy researcher prove existence spin battery battery charged applying large magnetic field nanomagnet device called magnetic tunnel junction mtj step creation computer hard drive moving part faster expensive energy current one physorg nanotechnology fuel cell method produce longest platinum nanowire yet increased fuel cell longevity efficiency platinum nanowire roughly nanometer diameter centimetre length long create selfsupporting web pure platinum serve electrode fuel cell published acs nano letter green car congress featured government energy green tax break united state government extending tax break homeowner decided green home due stimulus bill forward movement time rule governing tax code outdated peswiki earth battery lighting soil powered lamp fresh dirty energy dutch designer marieke strap soil lamp conductive plate made copper zinc buried soil provide constant nearly eternal light led bulb feed splash water energy flowing inhabitat electrical grid invisible underground hvdc power cost ugly tower sweden began voltage hvdc power transmission system created nikola tesla hvdc light transmission technology offer numerous environmental benefit including invisible power line neutral electromagnetic field oilfree cable compact converter station renewable energy world featured wind electromagnetic boswell boswell power production unit run continuously wind finally found clean energy device purchase capable powering home conventional device company claim hundred installed late pesn mar nuclear travelingwave reactor privately funded reactor technology depleteduranium fuel packed inside hundred hexagonal pillar wave move core centimetre year fuel transformed bred plutonium undergoe fission technology review award rosenblatt energy award rosenblatt energy award spectacular event renewable energy sector recognising achievement management team company project made significant contribution sector past month annual event vitesse media feb featured event financial resource event cleantech capital summit cleantech capital summit san diego bring decisionmaker cleantech energy technology industry leading capital provider delve full range financing energy clean technology industry peswiki electromagnetic mathematical proof free energy pdf paper allege simple formulas electromagnetic proven newton law valid case electrical charge electrical generator voltage achieved rpm energy surplus comparison generator low voltage current veljkomilkoviccom thank bobsy biofuel community entire swedish city switches biofuel environmentally friendly kalmar sweden surrounding town region quartermillion people traded oil gas electric furnace community district heat produced plant burn sawdust wood waste left timber company hydropower nuclear power windmill provide percent region electricity chicago tribune featured electromagnetic alan francoeur interference disc generator alan francoeur describe generator multiphase interchangeable variable frequency dynamo machine efficiency due prior art controversy interest history resurrect information peswiki electrolysis cleaning simple elixir called miracle liquid include video stuff simple mixture table salt tap water ion scrambled electric current sanitizer decade russia japan electrolyzed water slowly winning acceptance united state proton lab manufacturer time hydrogen production cheap hydrogen scrap now unassuming stainlesssteel brush microbial electrolysis cell mec step forward steel brush replace expensive platinum employed electrolysis cell cathode slashing cost percent mit technology review solar emergency preparedness sunnight dualuse solar flashlight play greener gadget greener gadget conference york sunnight solar chief executive mark bent admitted problem exec kill tough economic time customer venturebeat hydrogen production hydrogen produced aluminium water scientist pennsylvania state university virginia commonwealth university producing hydrogen exposing cluster aluminium atom water unlike hydrogen production processe method room temperature require application heat electricity work the future thing feb evaporative cooling solar maisotsenko mcycle coolerado finally solarpowered air conditioner tonne solar panel interesting trick coolerado use exhaust air unit cool solar panel cooling panel exhaust air producing more reducing cost fewer panel needed treehugger feb thorium reactor liquid fluoride thorium lftr paradigm thorium reactor concept chemicallystable fluoride salt medium nuclear reaction place fuel form yield flexibility operation eliminate fabricate fuel element energy thorium molten salt reactor including lftr simple the oil drum jan thank sepp solar notsosunny side solar panel semiconductor electronic industry long perceived green industry egregious impact unaddressed year precautionary approach apply regulating photovoltaic due toxic chemical material involved manufacturiing voice san diego feb ","m_szGeo1":"United States","m_szSourceType":"source_industry","m_szSrcUrl":"http://peswiki.com/index.php/News:Archive:2009:March","m_Places":["Most","New York","Us","Europe","U.s.","Gravity","Uk","Utah","Italy","Shanghai","Brazil","Germany","Tesla","Maine","Usa","Chicago","Irvine","Vancouver","America","Barrier","Arizona","Carter","Sweden","San Diego, Ca","Russia","Japan","United States","Mecs","San Diego"],"m_People":["Barack Obama","A Netherland","Mylow Magnet","Howard Johson","Howard Johnson","Tom Valone","Sterling D. Allan","Milkovic","Aleksandar Slavkovic","Mark Goldes","Energy Ocean","Alex Jones","Larue Howells","Tom Bearden","John Bedini","Walter Rosenthal","Deborah Chung","Peter Lindemann","Daniel Sheehan","Sparky Sweet","T Henry Moray","Michael Reynolds","Alan L. Francoeur","Mark Bent"],"m_Companies":["U.s. Government","Diesel","Technology Review","Theories","Axioms","Slashdot","Yahoo","Tesla Motors","Ny Times","Nem","Nec","New Scientist","Supreme Court","Revival","Howard Johnson's","New York Times","Theory","Ebay","Stonehenge","University Of Salerno","Salt Lake Tribune","Ap","Mph","Honda","India Times","First Solar","Seat","Youtube","U.s. Patent Office","Lawrence Berkeley National Laboratory","Advanced Lithium Power Inc.","Alp","U.s. Military","La Times","Barotex Technology Corporation","Washington University In St. Louis","Afc","Christian Science Monitor","New World","Pluck","Salt Lake County","Deseret News","H2o","Acs","Congress","United States Government","Strap","Underground","Chicago Tribune","Sunnight Solar","Pennsylvania State University","Virginia Commonwealth University","Cycle","Paradigm"],"m_BiGrams":["howard johnson","magnet motor","mar featured","featured magnet","renewable energy","solar panel","fuel cell","motor howard","allmagnet motor","free energy","motor mylow","electric car","government energy","fuel efficiency","tesla motor","hydrogen production","power line","electric vehicle","electric bike","technology review","mylow magnet","cold fusion","salt lake","alt fuel","smart grid"],"m_TriGrams":["featured magnet motor","mar featured magnet","magnet motor mylow","magnet motor howard","motor howard johnson"],"m_SocialTags":[],"m_Topics":[],"m_Industry":[],"m_Technology":[],"m_BiCnt":[17,16,11,7,7,6,6,5,5,5,5,5,4,4,4,4,4,4,4,3,3,3,3,3,3],"m_TriCnt":[7,5,5,3,3],"m_iDocBodyWordCnt":2508}
