{"m_szDocID":"842986","m_szDocTitle":"Latest - PESWiki","m_szYear":"2015","m_szDocSumamry":"Latest Latest Features Here at PESWiki The Primary RSS feed is based on the content of this page. B O O K M A R K - T H I S - P A G E Monday, February 22, 2016 New Pages - Computer-generated list of all new pages, chronologically. Recent changes - Computer generated listing of all changes made to the site, most recent first. PESWiki Blogs Featured / Top 5 : Magnet Motors > U-Plug > U-Plug March 26 Test Blog - Tracking the progress of the third party testing we at PES are coordinating along with U-Plug Products LLC, of their 2 kW U-Plug magnet motor that is a 24\"x6\" portable cylinder weighing 2","m_szDocBody":"latest latest feature peswiki primary feed based page monday page computergenerated list page chronologically recent computer generated listing made site recent first peswiki blog featured top magnet motor uplug uplug test blog tracking progress party testing pes coordinating uplug product llc uplug magnet motor portable cylinder weighing pound expected cost run time longer hour battery provide peswiki februaryapril lookingforheatcom post promo video prelaunch video announce lenr website coming video entertaining piece viral free energy blog saturday featured top magnet motor uplug blog test uplug product llc seeking good thirdparty testing entity easy qualified testing agency appear defy existing understanding law physic uplug agreed scientist including phd test unit publish report pesn wednesday featured top sale earth mag field lighting elfe sale stuart campbell our moderator test nimh battery determine bounceback clear test regular torch elfe flashlight compare them nimh battery regular torch halogen bulb load amp pesn sunday featured top sale earth mag field lighting elfe sale adgex post official elfe flashlight video explaining function component video explain scientific principle elfe flashlight harnesse endless free energy environment earth magnetic field work region other show inside torch word antennae component pesn saturday ecw orbo ocube testing week feb back plate removed the ophone capacitor directly power phone extensive capacitor discharged capacitor constantly trickle charged orbo period time capacitor recharged phone functional again essence phone charging itself free energy blog unexpected threeyear payment pureenergyblogcom good deal unexpectedly help free energy blog friday featured top sale earth mag field lighting elfe sale adgex business meeting tomsk russia company figured harness earth magnetic field produce usable power selling elfe flashlight two customer report developing generator week holding business meeting international distributor pesn thursday edgar mitchell wish peace space free energy blog norda foundation clean energy award unclaimed year foundation awarded million social entrepreneurial charitable organisation year part mission fund new nonfossil fuel sustainable energy project year energy project recommended applied funding free energy blog emp deactivating implanted chip body riddled electronic chip varying size hoping deactivate them suggested military test localised emp weapon theyll her free energy blog tuesday featured electromagnetic solid state joule ringer govt deepthroat forum joule ringer development market government agent worked technology decade ago similar professor steven jone joule ringer think conceivable eventually scale solid state technology device size price air conditioner providing peswiki monday featured sale gravity motor ozzog sale ozzog selfpowered generator installed running customer nagendra singh mumbai india inform built running customer presently kva range presently expensive costing usd kva kva peswiki donation pes account infusion make end month revenue free energy blog sunday featured top plasma blacklight power video brilliant light power suncell demonstration suncell solid state sun box module weigh pound energy production cost return investment day expected commercially pesn saturday featured top sale earth mag field lighting elfe sale customer receive adgex elfe flashlight powered earth magnetic field today received elfe flashlight work time meet claim automatically recharging depleted hold claim real breakthrough technologie accomplished german customer peswiki friday featured top sale electromagnetic steorn sale steorn ophone arriving put test phone battery indicator stay full heavy usage day the battery charged internal ocube pull energy wheelwork nature solid state peswiki thursday featured nanotech battery hydrogen production fuel cell consulting konstantin balakiryan protonnd energy storage technology revolutionise battery industry capacity protonnd proton nano diffusion battery projected time capacity lithium battery electric vehicle battery power mileage extra charge pesn wednesday featured hydrogen water electrolysis derek zupancic erxxaon water electrolizer water fuel cell create pure hydrogen volt battery big diesel cell tested litre cat engine carb testing ran low amp low volt peswiki tuesday featured battery conspiracy suppression govt deepthroat endless battery technology year ago govt anonymous government worker describe effort bring public awareness highlighting presently public domain energy antigravity technology government operational year ago public pesn cold incandescent light bulb imagine incandescent bulb efficient led well exist mit recycling light free energy blog monday world reaction free energy smbccomicscom posted fun spoof sceptic free energy blog steorn orbo compared battery lot people difference orbo power cell traditional battery battery store energy orbo generate energy trickle charge lithium ion battery free energy blog featured plasma keshe mehran tavakoli keshe rampage bring peswiki keshe misleading field free energy experience year ive exposed work take blow proportion barely resemble fact extrapolated infinity demand close peswiki now peswiki saturday featured grid utility boast lowest retail rate giving briefing dad brilliant light power demo mentioned price range pulled recent newsletter local power company bragging garkane energy rate rank lowest nation cent kilowatthour free energy blog friday brilliant light power demo lecture amazing achieved solid state operation electromagnetic pump spray molten silver electrode continuous pulsing continuous power production free energy blog thursday buyer beware john byde waterstarter account hacked scammed guy who thought was skype profile legitimate free energy technology pursuer talked helping purchasing iphone gift card resell reimbursed promised call john account hacked peswiki tuesday featured waste energy sale adgex greenblaze mswtoenergy plant greenblaze cuttingedge lucrative solution capable converting wide range feestock waste safe alternative energy source greenblaze universal mobile multifunctional complex closed cycle open combustion based technology hightemperature vacuum destruction peswiki monday answer quora renewable energy project united state list include ecat brillouin nuenergy cavitation err fluxgenerator brilliant light power nanospire cavitation myt aviation focus fusion quora sunday ontario pull plug rural smart metre year obvious problem hydro finally admitted rural smart metre work decided pull plug start utility begin likewise update hydro announced plan remove metre suspected failure free energy blog saturday featured top magnet motor sale magnet transduced generator mtg magnetic inducer engine mie noca clean energy now global company dealt commodity distribution office country larger mtg unit cost levelized cost electricity established energy source future transportation miepowered peswiki friday mixing glow stick chemical ferrofluid effect visible spectrum fascinating videos free energy blog thursday featured flight vision vtol quadcopter water trust imagine remote control quadcopter scaled human passenger energy storage technology reached needed threshold human quadcoptor travel ready offtheshelf component peswiki wednesday featured nuclear fusion lenr key info inadvertently omitted pon fleischmann report mild magnetic field created transformer side wall removed profound number oscillation megahertz range created piece equipment experiment basement peswiki monday financial time hope spring eternal nuclear fusion breakthrough cold fusion research take place world own mainstream scientist touch lenr tainted cold fusion fiasco prof fleischmann pon claimed achieved fusion lab bench experiment reproduce free energy blog pesncom hold day computer worked computer edit pesncom day resume there edit peswiki computer free energy blog sunday featured viktor schauberger viktor schauberger comprehend copy nature documentary austrian inventor sought emulate nature generation energy thought human technology backward basically running controlled explosion observation nature revealed energy generated implosion mean vortice free energy blog saturday featured health alternative cure cancer good alternative healing modality effective fighting cancer effective safe cheap natural chemo radiation etc good natural cure source inform comment peswiki friday featured fundraiser plasma brilliant light power fundraiser trip brilliantpower suncell demo purchased plane hotel car rental ticket demo revolutionary technology suncell produced million watt power power density significantly higher power source helping reimbursement indiegogo thursday featured pendulum art mckay pendulum motor art openly share design hes harvest gravitational energy pendulum time digest this thought knowing discussing here peswiki tuesday featured david puchta searl magnetic david puchta videos searl magnetic demonstration show small copper cylinder attracted larger rotating copper cylinder repelled show copper cylinder turned closer larger rotating cylinder unusual phenomenon david helping into production sooner later pesn monday featured magnetism mcconnell magnetic gate experiment ray mcconnell monopole magnet array received ray set material experimentation effect thought mild steel rod attached neodymium magnet create magnetic monopole effect creating array produce net propulsion pesn sunday featured organisation visual education project perpetual motion videos visual education project fake motor pulse coil camera hidden battery peswiki saturday featured gds technology generator gds unit roll the unit gds released ready delivery accepting application distributorship distributorship fee plant photos posted pure energy blog friday putin peace guru promoting christian pragmatism president putin genuine intellectual interview speeches show indepth knowledge history literature geopolitic psychology straightforward common sense philosophy spent lifetime developing free energy blog thursday featured adgex elfe flashlight elfe flashlight defect postpone shipment initially announced order endoftheyear holiday fact some them were however found defect testing caused careless unsatisfactory assembly subcontractor detected flaw rectified elfe dispatched week free energy blog tuesday featured magnetism magnet motor ray mcconnell magnetic gate philadelphia inventor demonstrate net propulsion power overunity simple setup neodymium magnet mild steel rod smaller hot roll steel rod wood block clay fasten neos atop hot wheel steel rod attached larger neodymium magnet create magnetic monopole effect peswiki sunday adgex flashlight heard own now germany ordered elfe flashlight sept ceo person told receive item shortly happen can cancel order money back paid paypal free energy blog saturday featured top zeitgeist exotic free energy technology advancement review prediction created featuring exotic free energy technology sale preorder process manufacturing vision global consciousness shift make hitherto overlooked marginalised modality flood earth pesn friday featured lenr ecat reveal midnight rossi several night ago dream ecat produced billion piece assembled combination make public lamp town totally illuminated ecat lamp network pipe wire distribute heat electricity house free energy blog ","m_szGeo1":"United States","m_szSourceType":"source_industry","m_szSrcUrl":"http://www.peswiki.com/index.php/Latest","m_Places":["Tomsk","Russia","Gravity","Mumbai","India","U.s.","Well","Uk","United States","Ontario","Springs","Gate - Philadelphia","Germany"],"m_People":["Adgex Elfe","Stuart Campbell","Edgar Mitchell","Professor Steven","E. Jones","Nagendra Singh","Konstantin Balakiryan","Derek Zupancic","Keshe","Mehran Tavakoli","John Byde","Viktor Schauberger","Art Mckay","David Puchta","Ray Mcconnell","Putin"],"m_Companies":["Plug Products Llc","Aa","Orbo","Wish","Norda Foundation","Infusion","Storage Technology","Volt","Diesel","Volts","U.s. Government","Skype","Universal","Quora","Hydro One","Bc Hydro","Glow","Financial Times","Paypal"],"m_BiGrams":["free energy","energy blog","featured top","elfe flashlight","saturday featured","magnet motor","top sale","tuesday featured","solid state","brilliant light","light power","blog saturday","sale earth","earth mag","mag field","field lighting","lighting elfe","elfe sale","sunday featured","magnetic field","friday featured","thursday featured","steel rod","top magnet","wednesday featured","sale adgex","earth magnetic","blog friday","energy project","joule ringer","peswiki monday","peswiki friday","peswiki tuesday","blog thursday","energy technology","copper cylinder","neodymium magnet"],"m_TriGrams":["free energy blog","featured top sale","brilliant light power","energy blog saturday","blog saturday featured","saturday featured top","top sale earth","sale earth mag","earth mag field","mag field lighting","field lighting elfe","lighting elfe sale","featured top magnet","top magnet motor","earth magnetic field","energy blog friday","peswiki tuesday featured","energy blog thursday","free energy technology"],"m_SocialTags":[],"m_Topics":[],"m_Industry":[],"m_Technology":[],"m_BiCnt":[27,22,10,9,7,5,5,5,5,5,5,4,4,4,4,4,4,4,4,4,4,4,4,3,3,3,3,3,3,3,3,3,3,3,3,3,3],"m_TriCnt":[21,5,5,4,4,4,4,4,4,4,4,4,3,3,3,3,3,3,3],"m_iDocBodyWordCnt":1529}
