{"m_szDocID":"843570","m_szDocTitle":"News:Energy Storage - PESWiki","m_szYear":"2015","m_szDocSumamry":"News:Energy Storage See also Directory:Storage and News:Batteries Energy Storage in the news. Page Commenced Feb. 9, 2010 2016 Featured : Nanotech / Batteries > Hydrogen > Production / Fuel Cells > BK Consulting > Konstantin Balakiryan: Proton-3ND Energy Storage Technology Could Revolutionize Battery Industry - The capacity of the Proton-3ND (Proton -3 Nano Diffusion) battery is projected to be 44 times the capacity of lithium batteries. Electric vehicles with these batteries would have more power and much more mileage at no extra charge. (PESN; January 4, 2016) Featured : Batteries / Conspira","m_szDocBody":"newsenergy storage directorystorage newsbattery energy storage new commenced feb featured nanotech battery hydrogen production fuel cell consulting konstantin balakiryan protonnd energy storage technology revolutionise battery industry capacity protonnd proton nano diffusion battery projected time capacity lithium battery electric vehicle battery power mileage extra charge pesn featured battery conspiracy suppression govt deepthroat endless battery technology year ago govt anonymous government worker describe effort bring public awareness highlighting presently public domain energy antigravity technology government operational year ago public pesn featured solar storage capacitor graphene sunvault energy inc graphene generator supercapacitor technology coming clever make graphene collect solar energy store sunvault expect rollout storage device price point year end application include phone recharged peswiki featured solar storage capacitor sunvault sunvault energy edison power company create massive farad graphene supercapacitor farad graphene supercapacitor battery powerful power semi truck size paperback point price point expected start lower rollout market tesla expect year half year end pesn germany open renewable energy storage facility germany launched claim europe largest commercial battery plant free energy blog storage battery lithiumsulphur battery design solar wind power grid stanford researcher demonstrated partially liquid battery made inexpensive lithium sulphur allegedly easy make thousand charging cycle material manufacturing cost battery low meet goal kilowatthour storage capacity make economically attractive utility pureenergyblog storage plasma plasma device considered holy grail energy generation storage scientist university missouri devised create control plasma transform american energy generation storage team developed device launches ring plasma distance feet plasma reaches temperature hotter surface sun doesnt emit radiation completely safe pureenergyblog storage battery university illinois microbattery powerful technology deliver power high current energy delivery longer period time capability compact package battery owe performance internal threedimensional microstructure pureenergyblog featured storage battery new phinergy phinergy metalair battery yield mile range israeli company called phinergy metalairwater battery technology enable vehicle travel mile charge couple stop refill system water hho magic mixed there pureenergyblog nuclear betavoltaic commerciallyavailable nanotritium battery power microelectronic year city lab announced commercial launch nanotritium betavoltaic power source thumbsized battery draw energy released radioactive element provide continuous nanowatt power year gizmag piezoelectric storage battery liion selfcharging battery transform vibration directly chemical energy research team georgia institute technology invented lithium ion battery charge environment vibration unlike similar device highly efficient convert mechanical energy chemical energy directly electricity middleman piezoelectric membrane lithium cobalt green optimistic storage capacitor eestor eestor announce energy density milestone eestor inc announced successfully completed production electrical energy storage unit eesu dielectric layer potentially technology achieve energy density competitive electrical energy storage technology prnewswire storage battery nickel iron thomas edison nickeliron battery stcentury makeover power electric car nickeliron battery originally conceived edison century ago back scientist stanford upgraded battery recharged half minute opposed hour present discharge second make boon renewableenergy industry power car edison originally envisaged daily new newsletter future energy enew future energy enew tom valone headline month include antimatter propulsion engine redesigned tinted window produce electricity lithium air battery move forward metal oxide gree energy tech zenn eestor team storage battery lithium air air battery electric car outlast gas guzzler ibm claim solved fundamental problem lithiumair cell technology lead creation battery kilometre mile range letting evs potentially compete petrol engine time newscientist fuel efficiency storage capacitor mazda announce world capacitorbased regenerative braking system ieloop billed world passenger vehicle regenerative braking system capacitor place rechargeable battery temporarily store energy captured braking mazda claim ieloop system improve fuel economy vehicle gizmag featured nanotech storage battery solid state prieto battery offer power density amy prieto colorado state university developing battery technology utilise copper antimonide nanowire ultra thin polymer electrolyte fully developed battery expected offer huge increase power density reduction time take charge unlimited recharge cycle pesn beforeitsnew earth battery event bedini conference bedini battery run mountain dew john bedini demonstrated stepbystep novice make iontransferring crystal power cell light led lightemitting diode bright read cell electrical power source quit working occasionally top water changing power featured top solid state generator electret eefg energetic future endless electric field generator endless electric field generator breakthrough solid state device safe cost effective seemingly ending source electricity consuming fuel collecting energy undisclosed source technology potential change energy landscape pesn beforeitsnew featured top solid state generator battery capacitor eefg breakthrough solid state generator finally permission discuss technology top list emerging clean energy technology solid state low for now continuous power commercial month cheap power density radioactivity existing physic law broken pesn beforeitsnew featured battery waterpowered cenimas paper battery charge water humidity cenimat researcher portugal developed paper battery technology store harvest energy water charging process automatically initiated site moisture atmosphere innovation production power electronic peswiki beforeitsnew storage battery semisolid flow cell battery design give electric vehicle jolt radically approach design battery developed researcher mit provide lightweight inexpensive alternative existing battery electric vehicle power grid technology make refuelling battery quick easy pumping gas conventional car mit storage capacitor battery tesla motor tesla ceo supercapacitor trump electric car battery unlike battery supercapacitor lose ability store charge age supercapacitor higher power density battery provide power quickly existing battery technology supply energy charge discharging allcarselectric nanotech storage battery capacitor battery technology complete recharging minute battery developed university illinois urbanachampaign offer advantage capacitor battery unit rapid capability capacitor ability store large amount energy battery gizmag storage battery evs material double chevy volt battery capacity chevy volt set appealing announced working generation battery double energystorage capacity gms licenced batteryelectrode material developed argonne national laboratory department energy lab mixedmetal oxide increase storage capacity improve safety durability car battery inhabitat storage capacitor lithiumion ultracapacitor charge tool second yorkbased company ioxus developed type lithium ion ultracapacitor potentially deliver large amount energy small amount time make ideal item require large amount power acceleration energy capture power application power tool inhabitat featured battery thermal electric solid state generator karpen pile battery produced energy continuously battery designed nicolae vasilescukarpen patented called the uniformtemperature thermoelectric pile allegedly producing energy continuously romanian museum peswiki storage battery air ibm project holographic phone airdriven battery survey ibm scientist predict mobile phone project holographic image caller predicted battery move lithiumion construction energydense material greatly increasing power capacity allowing recharge breathing air them eweekeurope nanotech battery liion sandia create world smallest single nanowire battery researcher sandia national laboratory succeeded creating world smallest battery consist single nanowire battery anode seventhousandth thickness human hair hope scientist discover occur inside lithiumion storage device charge discharge inhabitat storage battery ion bioelectricity microorganism tobacco mosaic virus boost battery tobacco mosaic virus destructive beast infecting hundred specy plant including tomatoe weird eco benefit incorporated lithium battery increase storage capacity time slashdot storage capacitor superconductor graphene supercapacitor break storage record researcher made graphenebased supercapacitor store energy unit mass nickel metal hydride battery unlike battery charged discharged minute second device specific energy density room temperature physicsworld battery liion world powerful industrial lithiumion battery corvus energy transforming marine transportation energy industry release advanced lithiumion battery technology store distribute energy megawatt size capacity output sustained power comparable diesel engine hybrid fullelectric vessel vehicle energy daily nov solar storage thermal thermochemical solar energy efficient indefinitely storable researcher mit working process thermochemical solar energy molecular structure reconfiguration capture energy sun potentially storing forever molecule fulvalene diruthenium configuration absorb heat release heat snap back original shape mit new oct storage flywheel beacon power stronger costeffective flywheel grid storage beacon power working department energy advanced research project agency energy arpae development nextgeneration flywheel storage flywheel storage system expected store time energy flywheel oneeighth kilowatthour cost ecogeek oct nanotech storage battery liion paperthin battery provide bendable power carbon nanotubebased technology literally company paint layer electricityholding lithiumion standard piece paper battery thick thinner flexible exhibit higher energy density electrical advantage compared type thin battery chemical engineering new sept microorganism storage battery lithium ion virusbuilt wearable battery power military viruse create cathode anode lithiumion battery research pan out part grown harvested tobacco plant woven sprayed clothing power wide range electronic device discovery new storage battery utilityscale bradwell cheap reliable battery store renewable energy battery designed mit grad student david bradwell active component liquid enable handle current fracturing eventually cost kilowatthour bradwell battery based electrolyte dissolve compound consisting metal magnesium antimony mit technology review aug storage capacitor international research team develop ultrahighpower energy storage device team researcher france report development mircosupercapacitor remarkable property paper published premier scientific nature nanotechnology online microsupercapacitor potential power nomad electronic wireless sensor network biomedical implant active rfid tag physorg storage grid cryogen energy storage system cut peak fuel half energy storage system developed university leed chinese academy science excess energy peak time chill nitrogenoxygen mixture called cryogen then time demand spike mixture boiled waste heat produce power inhabitat aug storage battery ultrabattery world powerful nonnuclear storage battery forget today primitive energy storage device day ultra battery made xenon fluoride development washington state university ultrabattery store condensed energy type battery existence inhabitat storage neverbeforeseen material store vast amount energy superhigh pressure similar found deep earth giant planet researcher washington state university created compact neverbeforeseen material capable storing vast amount energy researcher condensed form energy storage nuclear energy material hold potential creating class energetic material gizmag nanotech battery carbon nanotube battery pack punch carbon nanotube attractive material batterymaking surface area accept positive ion potentially longer conventional battery design researcher mit introduced chemically modified carbon nanotube positive ion source themselve science electromagnetic electric vehicle chris hunter power trip inventor chris hunter local coverage review amazing pursuit eccentric alaskan inventor including way extend life battery creating motor electric vehicle conversion project way draw heat power ambient air frintiersman storage battery airfuelled stair battery time longer traditional cell revolutionary stair andrew air battery cell charged traditional discharged open mesh section battery draw oxygen surrounding air react porous carbon component inside battery create energy help continually charge cell discharged telegraph storage battery lithium ion planar energy display breakthrough battery technology fully tested ucf researcher breakthrough planar energy florida involve generation solid state electrolyte lithium ion battery typical liquid electrolyte found today technology lead reduced cost performance large format lithiumion electric vehicle battery allcarselectric featured storage utilityscale refrigeration isentropic gravel battery renewable grid storage large tank gravel argon gas special heat pump design british company isentropic temperature difference tank inexpensive energy storage retrieval mechansim applicaction include solar generation peswiki apr storage capacitor big energy storage thin film researcher drexel university philadelphia demonstrated technique borrowed chipmaking industry make thinfilm carbon ultracapacitor store time energy volume conventional ultracapacitor material operate replaced mit technology review storage battery lithium air lithiumair battery offer time energy density lithiumair battery potential providing energy density time conventional lithiumion battery found portable consumer electronic device electric vehicle researcher mit made breakthrough make commercial development lightweight rechargeable battery reality gizmag apr storage battery lithium ecolocap claim battery technology efficient nano lithium battery ecolocap offer percent efficiency the world highest energy density output mass battery found fastest recharge time comparable commercial battery lowest cost energy output gizmag storage flywheel flywheel energy storage greener efficient battery overview principle flywheel operation application range acting ups hospital putting entire train movement cruise speed power greenoptimistic plastic battery battery dead scientist invent waferthin plastic store electricity british scientist created plastic store release electricity revolutionising phone drive car wear clothes technology lead flexible computer screen folded carried piece paper dailymail feb ","m_szGeo1":"United States","m_szSourceType":"source_industry","m_szSrcUrl":"http://peswiki.com/index.php/News:Energy_Storage","m_Places":["U.s.","Tesla","Germany","Europe","Most","New York","Us","France","Punch","Uk","Florida","Philadelphia"],"m_People":["Konstantin Balakiryan","Nano Lithium","Lithium Ion","Lithium Cobalt","Thomas Edison","Tom Valone","Amy Prieto","John Bedini","Chevy Volt","Nicolae Vasilescu","David Bradwell","Chris Hunter"],"m_Companies":["Storage Technology","U.s. Government","Capacitors","Sunvault Energy Inc.","Supercapacitor Technology","Solar Energy","Edison Power Company","University Of Missouri","University Of Illinois","Georgia Institute Of Technology","Eestor Inc.","Ny Daily News","Ibm","Mazda","Colorado State University","Tesla Motors","Argonne National Laboratory","Sandia National Laboratories","Mosaic","Slashdot","Technology Review","Nomad","University Of Leeds","Washington State University","St Andrews","Planar","Drexel University","Ups","Plastic"],"m_BiGrams":["storage battery","energy storage","battery technology","storage capacitor","solid state","electric vehicle","energy density","lithium ion","battery lithium","storage device","battery liion","power density","state generator","researcher mit","amount energy","lithiumion battery","nanotech battery","lithium battery","battery electric","battery power","featured battery","solar storage","solar energy","graphene supercapacitor","battery design","storage capacity","electric car","lithium air","technology lead","nanotech storage","state university","pesn beforeitsnew","paper battery","capacitor battery","large amount","inhabitat storage","storage flywheel","storage system","time energy","carbon nanotube"],"m_TriGrams":["storage battery lithium","solid state generator","nanotech storage battery"],"m_SocialTags":[],"m_Topics":[],"m_Industry":[],"m_Technology":[],"m_BiCnt":[21,13,9,9,8,7,7,5,5,4,4,4,4,4,4,4,3,3,3,3,3,3,3,3,3,3,3,3,3,3,3,3,3,3,3,3,3,3,3,3],"m_TriCnt":[5,4,3],"m_iDocBodyWordCnt":1850}
