{"m_szDocID":"853591","m_szDocTitle":"Ideology and Sustainability","m_szYear":"2016","m_szDocSumamry":"Up to: Main Sustainability Page Ideology and Sustainability I get some very quick reactions to my main page on the sustainability of material progress .   Quick reactions, whether favorable or unfavorable, cannot be based on reading the 50 or so pages.  They are reactions to my attitude, which is apparent in the first paragraph. For many, prophesying doom if we don't change our ways, is a signal of virtue.  Others are irritated by doom-saying and have an immediate favorable reaction.  There are at least some who are worried by the problems that have been proposed as obstacles to sustainability","m_szDocBody":"main sustainability ideology sustainability quick reaction main sustainability material progress quick reaction favourable unfavourable based reading page reaction attitude apparent paragraph many prophesying doom change way signal virtue irritated doomsaying favourable reaction worried problem proposed obstacle sustainability relieved information stop progress few judging small number question elaboration point understand politic environment attitude people group question material progress sustainability understand ideology social political force webster dictionary ideology visionary theorising systematic body concept esp human life culture manner thinking characteristic individual group culture integrated assertion theory aim constitute sociopolitical programme concerned ideological tribe america battle human ideology martian point view american social thought polarised axis liberal conservative axis people pay attention issue belong ideological tribe tribe view spectrum issue logically issue strongly correlated issue abortion communism cuba soviet communism multiculturalism poverty environment gay right relative importance equality opportunity equality outcome punishment harassing offending free speech people attitude issue tend strongly correlated logically connexion person attitude abortion attitude multiculturalism nice reaction web nuclear energy illustrate membership tribe cause person religious independent view issue denomination adhere tribe other politically aware people opinion separate issue media leader tribe view bad guy good guy influential tribe member specific issue outlast opinion issue substantial biological childhood experience component ideology ideology determined early notion bad guy notion bad guy stable notion good guy politically active people most fighting evil perceived important good scholar distinguish classical romantic personality supposedly interested feel think fit classical model majority public pay attention ideological matter read editorial opinion column spend time watching opinionoriented reason majority solidly enrolled tribe opinion issue uncorrelated independent spite tribalism objective thinking issue problem play role determining person position interaction subjective factor understood objective thinking distinguished thinking argument favour preexisting position primary reservoir objective thinking human professional science however scientist preserve scientific attitude issue field however individual differ great deal breadth scientific study read narrow field informed many ideological vested interest written public attitude suppose public react directly fact example chauncey starr writing public respond risk assume this however public information media media people tribal loyalty moreover media strongly affected existence organisation kind hysteresis public response event organisation existence founder reaction event founder control organisation attitude change however organisation set way event effect attitude individual react directly fact issue official organisation commitment cannot lawyer organisation organisation position lawyer organisation client true public relation people organisation pessimism ideology pessimism regarded ideology phenomena person pessimistic about psychological pessimism realisation individual inevitable death misfortune remember disappointed age realised eventually die nevertheless people differ personal attitude pessimism optimism pessimist generally morally superior optimist derogatory term refer optimistic view plan put example here include cornucopian polyannas technooptimistsetc derogatory term technofix fix problem technology fixed reforming people ideas obvious published expression pessimism human future side political spectrum moderate pessimistic extremist interesting collapse soviet union end prospect substantially destroyed soviet missile writing speeches begin now pessimism people dominated sense sin people stop space exploration now reason humanity messed planet allowed space link died hope guy changed mind note alas changed address work now egalitarianism equal idea intrinsic appeal however sense equality favour other equality law idea law apply equally everyone however idea new society established conquest conqueror made nobility specific legal privilege japan samurai legal privilege samurai carry sword france revolution nobility exempt taxe revolution establish equality law country society equality law totally effective however established violation noted scandalous feudal society commoner legally obliged make street noble equality law major component statement american declaration independence all men created equal presentday demand inequality law behalf upper class equality opportunity equality opportunity conflict freedom parent provide improved opportunity children modern society issue tend compromised america school district richer taxpayer required subsidise poorer district free provide son individualised computerised mathematic instruction britain extreme leftist long proposed make private school called public school illegal equality outcome egalitarianism proper amount demand equality outcome person intelligent hard working kind reputation honestly fulfilling commitment make money fate made stupid malevolent violent lazy dishonest frank belief equality outcome human exist common common today belief inequality outcome evidence failure provide equality opportunity lead demand frank egalitarianism outcome major disadvantage legislating equality outcome domain eliminate incentive work hard achieve reward domain lead flight part able middle class flight suburb country stimulated emigration acceptable conservative doctrine usually government maintain minimal standard living unfortunate extent misfortune caused unfortunate person action negligence however technologically advanced prosperous society backward society hardworking killed bad winter plague sufficiently desperate condition undeserving helped killing deserving practical reason allowing intelligence hard work lead material success long country world government strong policy make money faced emigration elsewhere communist country forbid emigration extreme east germany similarly government determined view citizen freedom speech press communist government this nationalist government ruled dictator american british university punished student faculty speech writing successsful yet environmentalist ideology environmentalist ideology america thread descended movement preserve nature century movement led creation national park starting yellowstone presidency grant theodore roosevelt big conservation establishment park collision environmentalism progress damming hetchhetchy valley shortly provide water supply san francisco john muir infant sierra club opposed dam obvious alternative think secretary interior offered dam california wanted hear movement taking offer however conservation movement favoured progress establishment national park bipartisan approval important change environmentalist ideology silent spring rachel carson book introduced doomsaying note anticapitalist anticorporation note caused confluence environmentalism leftist anticapitalist ideology banthebomb movement began oppose nuclear power important step switch sierra club supporting nuclear power polluting burning fossil fuel opposing environmentalism allied antiestablishment countercultural antivietnam movement american indian recently played major role environmentalist ideology romanticism noble savage back rousseau century traced sense roman admiration german tribe ancient time fake version speech chief seattle live spite exposed fake year ago quote message explain fake speech live open eye amazed touched fake version chief seattle speech conveyed mystical wisdom comforting what chief word been beginning embellished good word coming time hear them spirit chief seattle whispering tuned ear environmentalist rewriting word remain strand web today environmentalist ideology dominant educational system kindergarten college media schoolchildren taught recite slogan son role pageant recite repeatedly quickly full circle food cycle forget grade time pageant rehearsed performed class local station moralism people felt neighbour live wished reform violently good reason not historically moralist reformism religious form moralist win political power lose while relevant literary quotation human being good good time george orwell hardened reformer make mind beautiful word language compulsory forbidden robert ryder quoted jame thurber collection quotation expressing strike extremist view written author endorse today wriggling part them interesting note paul ehrlich prediction massive famine proved spectacularly wrong received swedish crafoord prize recent tyler prize ehrlich prediction file quotation substantial part environmentalist movement inclined predict doom repentance quick abovementioned foundation prize attitude influence fact environmenalist ideology law environmental ideology dominate law regulation making rule costeffective regulation cost billion expected life saved recent year congress put requirement costeffectiveness enthusiastic bureaucrat evade congressional requirement interesting case wishful thinking california air resource board made rule requiring fraction car sold california manufacturer nonpolluting carb ruled electric car powered leadacid battery met requirement general motor ford built electric car them car low range leased ford project abandoned billion dollar wasted performance unacceptable predicted electric car consortium consisting henry ford thomas edison alexander graham bell consortium develop good battery gave recent attempt spent vastly money gave reason made ford edison bell give perhap energy religion reason discussed page energy energy commodity adequate supply indefinite future nevertheless today politician press make religion energy possible economy engineering effort squandered achieving small energy saving spent improving product suspect energy star compliance computer equipment represent misplaced engineering effort money spent spent developing large flat panel display bigger now purely incidentally flat panel display half energy crt display note flat panel display wall size energy religion phenomenon started early origin antinuclear movement turn banthebomb movement antiwestern antiamerican ideology intellectually association loose however term tribal allegiance association strong movement another antinuclear power movement boost vietnam war ended radical needed cause california governor jerry brown nuclear power vietnam left marxism identification capitalism source evil play important role ideology marxist doctrine unknown environmentalist left web marxist ideology sin belief man inherently vile arose repeatedly human history prominent early christian prevalent christian denomination arise time literary intellectual environmentalist man vile vileness limited white european male nice prominent literary ideologist truth mozart pascal boolean algebra shakespeare parliamentary government baroque churches newton emancipation women kant marx balanchine ballet redeem civilization wrought world white race cancer human history white race aloneit ideology invention eradicate autonomous civilization spread upset ecological balance planet threaten existence life itself susan sontag partisan review winter susan sontag strongly hinted yorker terrorist attack deserved show remarkable consistency attitude year year scientist attack view offend religion leftism plaintiff lawyer knownothing political foe scientific study human nature morton hunt describe attack left attack right attack classified way left study genetic behaviour intelligence study sex feminist dislike woman uncovered memory childhood sex abuse put psychotherapist plaintiff lawyer report evidence breast implant caused major disease hunt book excellent summary antiscientific attitude stemmed left right wwii left powerful ideologically dangerous freedom objectivity effort part religious bar teaching evolution failed kansas majority state school board eliminated evolution state examination requirement protest including jeering kansas member voted banning evolution requirement defeated republican primary requirement including evolution examination restored global warming global warming major ideological bandwagon preparation kyoto conference vicepresident gore call dissenter unamerican firing dissenter apparently instigation vicepresident link science energy policy project leading dissenting organisation organisation leading budget year ideology scientific community excellent reminiscence effect ideology science entitled science ideology edward wilson wilson famous work ant sociobiology evolutionary explanation aspect animal human behaviour wilson ideas controversial today proposed them element evolutionary psychology study important human psychological characteristic evolved sociobiology evolutionary psychology fiercely attacked claim incorrect ground racist imperialist exorcising sociobiology microbiologist paul gross describe recent attack anthropologist napoleon chagnon late geneticist jame neel racist imperialist etc charge neel set epidemic measle yanomamo indian amazon promptly refuted withdrawn opponent evolutionary psychology hoped salvage scandal work scientist today affected ideology intellectual example ucs statement scientist name solicited statement agree formulation decide agreed thought warning statement important justify signing course people refuse statement agree bit them science new published iron fertilisation richard monastersky html form note iron fertilisation researched involve tinkering nature depend specific scientific fact however exponent give scientific consideration interpreted supporting view case involve emphasising possibility iron fertilisation work harmful doe commentary nature donald anderson entitled turning back harmful red tide discussed possibility control measure kill ocean bacteria red tide kill million fish make shell fish poisonous people anderson discusse ideological objection hinder attacking marine pest way similar attack pest land quote later scientific community strongly affected ideological milieu report inter governmental panel climate change ipcc out comment people blame global warming heat cold made global warming bring tropical disease malaria dengue yellow fever north made scientist eager good apparently specialist disease paul reiter chief entomology section dengue fever branch centre disease control wrote global warming vectorborne disease warmer sicker complain rocket scientist spreading myth tropical disease side remark long tell current state insect borne disease world wide main point wealthier healthier elimination malaria western country matter climate afford screen air conditioning antimosquito control measure evidence effect ideology scientist field simulation reported science soot important influence regional climate largest input cooking coal animal dung china india affect weather country neighbour ideological opposite underdeveloped country problem backward way cooking heating soot effect turn large predict change environmentalist ideas villain climate control gregory benford physicist irvine science fiction writer describe possibility mitigating global warming describe ideological objection actively mitigating global warming scientist benford quote sherwood rowland codiscoverer danger ozone layer recipient honour unalterably opposed global mitigation note apparently rowland changed mind extent george orwell wrote nationalism conventional meaning notion overlap tribalism discussed above orwell wrote extremely informative found orwell web political writing fred singer atmospheric physicist head science environmental policy project sceptical global warming offer evidence good part scientific establishment sufficiently committed green ideology distort consequence science field fear ideological attack excerpt science technology review house magazine lawrence livermore national laboratory deal collection energy project llnl involved important note storing waste yucca mountain subject fierce attack ideological antinuke lawsuit however writer choose notice ideological component decision activate yucca mountain waste storage opposition decision decision ignore ideological attack undoubtedly correct point work done however mean counterattack antinuke ideologist left amateur publicly analysis antinuke meme note bill authorise work yucca mountain repository passed house senate vetoed successfully president clinton lack progress permanent waste extremely important antinuke movement note bill passed house signed president bush alas predicted waste stored mistake common predict widespread extinction doubt prediction including idsos consider intentional human action move range specy discovered specy tree grow mile north northernmost boundary tree planted area discussing action common scientist engineer discussion global engineering fri belong remember referred william calvin atlantic monthly predicted doom gulf stream disappearing giving western europe climate siberia predicted stream refugee war european invent engineer problem student calculate cost greenhouse western europe agricultural areas predicted calvin lead disaster flic day tomorrow soontobe released disaster flic line science letter wallace broecker originated idea gulf stream clobbered past future broecker denounce lurid year prediction happen year alas broecker see worry boredom prosperity peace stimulate people adopt aggressive ideological extremist view new interesting wwii interesting cold war bcame interesting collapse soviet union safety monotony primaeval savagery nature remote mere pleasing condiment ordered routine world dream amid war guelf ghibelline william jamess protest call block universe classical tradition nietsches worship force verbal bloodthirstiness quiet literary men barbaric substratum human nature unsatisfied action find outlet imagination philosophy elsewhere tendency visible this formal argument thrust classical tradition philosophy fancy virile vital bertrand russell our knowledge external world delivered lowell lecture note world war started month russell lecture suppose philosophy made emperor franz joseph austriahungary tsar nicholas russia kaiser wilhelm germany bored peace mark twain wrote american civil war partly fault walter scott romanticised chivalry undid good cervante making fun man misery arise sit quietly room alone blaise pascal perspective global warming ice age andrew weaver claude hillairemarcel science current effect milder disaster flic predict january time update recent quote general effect change much media rational leadership scientific community slightly rational attack exxon supporting scientist sceptical global warming send comment make suggested them john mccarthy number hit ","m_szGeo1":"United States","m_szSourceType":"source_general","m_szSrcUrl":"http://www-formal.stanford.edu/jmc/progress/ideology.html","m_Places":["United States","America","Most","Cuba","Equality","Soviet Union","Japan","France","Britain","East Germany","Yellowstone","California","Viet Nam","Seattle","Kansas","China","India","Irvine","Yucca Mountain","Europe","Siberia","Austria","Hungary","Germany"],"m_People":["Chauncey Starr","Theodore Roosevelt","John Muir","Rachel Carson","George Orwell","Robert Ryder","James Thurber","Paul Ehrlich","Henry Ford","Thomas Edison","Alexander Graham Bell","Jerry Brown","Blaise Pascal","Susan Sontag","Edward O. Wilson","Paul Reiter","Napoleon Chagnon","James Neel","Richard Monastersky","Donald M. Anderson","Gregory Benford","Sherwood Rowland","William Calvin","Wallace Broecker","William James","Bertrand Russell","Mark Twain","Walter Scott","Andrew J. Weaver","Claude Hillaire","John Mccarthy"],"m_Companies":["Signal","Vested Interests","Revolution","Revolutions","Sierra Club","Congress","California Air Resources Board","General Motors","Crt","Partisan Review","Amazon","Science News","Shell","Centers For Disease Control","Uc","Science And Environmental Policy Project","Technology Review","House","Lawrence Livermore National Laboratory","Senate","Boundary","Atlantic Monthly","Indeed","Nicholas Of Russia","Exxon"],"m_BiGrams":["global warming","equality outcome","environmentalist ideology","equality opportunity","equality law","bad guy","objective thinking","nuclear power","chief seattle","electric car","flat panel","panel display","scientific community","evolutionary psychology","iron fertilisation","yucca mountain","disaster flic"],"m_TriGrams":["flat panel display"],"m_SocialTags":[],"m_Topics":[],"m_Industry":[],"m_Technology":[],"m_BiCnt":[10,5,5,4,4,3,3,3,3,3,3,3,3,3,3,3,3],"m_TriCnt":[3],"m_iDocBodyWordCnt":2355}
