{"m_szDocID":"868243","m_szDocTitle":"Latin American Herald Tribune - Cactus-Inspired Membrane to Revolutionize Electric Cars","m_szYear":"2016","m_szDocSumamry":"Cactus-Inspired Membrane to Revolutionize Electric Cars SYDNEY, Australia - A newly-developed membrane, based on the characteristics of a cactus plant, can improve the performance of fuel cells and revolutionize the electric cars industry, according to a study published Thursday. The membrane, developed by scientists from the Commonwealth Scientific and Industrial Research Organisation, or CSIRO, and South Korean Hanyang University, can improve fuel cell efficiency by four times. Aaron Thornton, CSIRO expert and co-author of the study published in the scientific journal Nature, says the coatin","m_szDocBody":"cactusinspired membrane revolutionise electric car sydney australia newlydeveloped membrane based characteristic cactus plant improve performance fuel cell revolutionise electric car industry study published thursday membrane developed scientist commonwealth scientific industrial research organisation csiro south korean hanyang university improve fuel cell efficiency time aaron thornton csiro expert coauthor study published scientific nature coating work cactus plant doe natural mechanism retain water harsh arid environment fuel cell electric vehicle generate energy mixing simple gase hydrogen oxygen thornton statement csiro however order maintain efficiency proton exchange membrane electric battery constantly hydrated expert fuel cell radiator water reservoir humidifier car occupy lot space energyintensive cactus plant tiny crack called stomatal pore open night cool humid close day condition hot arid study coauthor cara doherty csiro this membrane work similar way water generated electrochemical reaction regulated nanocrack skin widen exposed humidifying condition close drier added membrane fuel cell remain hydrated bulky humidifier making fourtime efficient dry hot condition head investigation south korean lee moo young membrane revolutionise electric car industry face major challenge term management water heat fuel cell system enter address free headline and great cartoon happy ending latin american herald tribune ","m_szGeo1":"Australia","m_szSourceType":"source_news","m_szSrcUrl":"http://www.laht.com/article.asp?ArticleId=2410977&CategoryId=13936","m_Places":["Sydney, Australia","Enter"],"m_People":["Aaron Thornton","Cara Doherty","Lee Moo Young"],"m_Companies":["Csiro","South Korean Hanyang University","Herald Tribune"],"m_BiGrams":["fuel cell","revolutionise electric","electric car","cactus plant"],"m_TriGrams":["revolutionise electric car"],"m_SocialTags":[],"m_Topics":[],"m_Industry":[],"m_Technology":[],"m_BiCnt":[6,3,3,3],"m_TriCnt":[3],"m_iDocBodyWordCnt":188}
