{"m_szDocID":"868228","m_szDocTitle":"Cactus Skin Could Improve Fuel Cell Performance - Gas 2","m_szYear":"2016","m_szDocSumamry":"Cactus Skin Could Improve Fuel Cell Performance April 29th, 2016 by Steve Hanley     Researchers from the  Commonwealth Scientific and Industrial Research Organisation in Australia and  Hanyang University in Korea have published a report in Nature this week that promises greater efficiency for fuel cells. Yes, we know that fuel cell cars won’t be a practical alternative to electric cars until someone figures out how to extract hydrogen from water or hydrocarbons without using less energy than the liberated hydrogen has to offer, but that is a subject for someone else to research. A fuel cell w","m_szDocBody":"cactus skin improve fuel cell performance steve hanley researcher commonwealth scientific industrial research organisation australia hanyang university korea published report nature week promise greater efficiency fuel cell yes fuel cell car wont practical alternative electric car figure extract hydrogen water hydrocarbon energy liberated hydrogen offer subject research fuel cell work passing electron porous membrane actually porous bit overstatement opening microscopic sizefuel cell electric vehicle generate energy mixing simple gase hydrogen oxygen aaron thornton researcher csiro coauthor study report however order maintain performance proton exchange membrane fuel cell pemfc stay constantly hydratedat moment achieved placing cell alongside radiator water reservoir humidifierthe downside vehicle occupy large amount space consume significant power researcher decided study skin cactus plantswhich thrive retaining water harsh arid environment result study created membrane mimic characteristic cactus skinaccording csiro researcher coauthor cara dohertya cactus plant tiny crack called stomatal pore open night cool humid close day condition hot aridthis help retain water membrane work similar way water generated electrochemical reaction regulated nanocrack skinthe crack widen exposed humidifying condition close drierthis mean fuel cell remain hydrated bulky external humidifier equipmentwe found skin made fuel cell time efficient hot dry condition professor young moo lee hanyang university led research major implication industry including development electric vehiclesat moment main barrier uptake fuel cell electric vehicle water management heat management fuel cell system professor lee said research addresse hurdle bringing step closer fuel cell electric vehicle widely availablethis technique applied existing technology require hydrated membrane including device water treatment gas separation case breakthrough easily bear thought mind university team working year year team researcher obtain free hydrogen reasonable cost dont write hydrogen fuel cell yet spurce electric car report image credit csiro share ","m_szGeo1":"Australia","m_szSourceType":"source_news","m_szSrcUrl":"http://gas2.org/2016/04/29/cactus-skin-improve-fuel-cell-performance/","m_Places":["Australia","Korea"],"m_People":["Steve Hanley","Aaron Thornton","Cara Doherty","Professor Lee"],"m_Companies":["Hanyang University","Csiro"],"m_BiGrams":["fuel cell","cell electric","electric vehicle"],"m_TriGrams":["cell electric vehicle"],"m_SocialTags":[],"m_Topics":[],"m_Industry":[],"m_Technology":[],"m_BiCnt":[11,3,3],"m_TriCnt":[3],"m_iDocBodyWordCnt":280}
