{"m_szDocID":"870198","m_szDocTitle":"The World's First Fuel-Cell Car-Sharing Program Will Open In Germany | Co.Exist | ideas + impact","m_szYear":"2016","m_szDocSumamry":"1 minute read The World's First Fuel-Cell Car-Sharing Program Will Open In Germany The service wants to create a market for hydrogen vehicles, which have been slow to develop. 01 /05 Hydrogen cars are stuck in a chicken-and-egg problem, with not enough filling stations to create a real market for the cars (and vice versa). 02 /05 To break the impasse, Linde, a big industrial gases company in Germany, is getting into the transportation business. 03 /05 From this summer, it's launching the world's first car sharing service for hydrogen cars. 04 /05 It hopes Germans will think differently about h","m_szDocBody":"minute read world fuelcell carsharing programme open germany service create market hydrogen vehicle slow develop hydrogen car stuck chickenandegg problem filling station create real market car and vice versa break impasse linde big industrial gase company germany transportation business summer launching world car sharing service hydrogen car hope german differently hydrogen start experiencing this amazing technology developing fast hope sandra scherb general manager beezero ben schiller today world fuelcell car stuck chickenandegg scenario people hydrogen car company build hydrogen filling station and people hydrogen car filling station break impasse linde big industrial gase company germany transportation business summer launching world carsharing service hydrogen car hope german differently hydrogen start experiencing this amazing technology developing fast hope sandra scherb general manager service called beezero wait develop lead ourselve beezero offer hyundai fuel cell electric vehicle munich model maximum range mile linde hope customer longer tripssay mountain visiting family country hope emphasise superior range hydrogen fuel cell compared batteryelectric vehicle typically offer mile single charge driver rent car app long like fill tank bring car back empty likely germany hydrogen filling station currently hydrogen car quicker recharge battery vehicle take long standard gas vehicle produce tailpipe emission aside water and potentially hydrogen good store renewable power immediately linde hydrogen made excess wind energy biomethane landfill main car model marketthe hyundai honda fcx clarity toyota mirai mercede audi announced model recently offer sharing longer trip city scherb its experience bring technology endconsumer decide market success technology photos beezero ","m_szGeo1":"Germany","m_szSourceType":"source_news","m_szSrcUrl":"http://www.fastcoexist.com/3059128/the-worlds-first-fuel-cell-car-sharing-program-will-open-in-germany","m_Places":["Germany","Linde","Munich","Toyota"],"m_People":["Sandra Scherb","Ben Schiller"],"m_Companies":["Hyundai","Honda","Audi"],"m_BiGrams":["hydrogen car","filling station"],"m_TriGrams":[],"m_SocialTags":[],"m_Topics":[],"m_Industry":[],"m_Technology":[],"m_BiCnt":[6,4],"m_TriCnt":[],"m_iDocBodyWordCnt":245}
