{"m_szDocID":"870197","m_szDocTitle":"Capitol Hyundai Of San Jose Celebrates First Fuel Cell Customer Delivery In Northern California","m_szYear":"2016","m_szDocSumamry":"May 02, 2016, 13:50 ET      from Hyundai Motor America SAN JOSE, Calif., May 2, 2016 /PRNewswire/ --Â Capitol Hyundai of San Jose, California, a proud member of the Del Grande Dealer Group, delivered the first zero-emissions Hyundai Tucson Fuel Cell hydrogen electric vehicle in the Northern California region today. Capitol Hyundai is the fifth qualified dealer for Hyundai's Tucson Fuel Cell, and the first Hyundai fuel cell dealer in Northern California. Hyundai was the first manufacturer in the U.S. to offer consumers the opportunity to lease a mass-produced fuel cell vehicle, the zero-emission","m_szDocBody":"hyundai motor america san jose calif capitol hyundai san jose california proud member del grande dealer group delivered zeroemission hyundai tucson fuel cell hydrogen electric vehicle northern california region today capitol hyundai qualified dealer hyundais tucson fuel cell hyundai fuel cell dealer northern california hyundai manufacturer offer consumer opportunity massproduced fuel cell vehicle zeroemission tucson fuel cell cuv continue reading capitol hyundai san jose california proud member del grande dealer group delivered zeroemission hyundai tucson fuel cell hydrogen electric vehicle northern california region today capitol hyundai excited qualified dealer hyundais zeroemission tucson fuel cell hydrogen electric vehicle shaun del grande owner capitol grande dealer group our location bay area region hyundais northern california making convenient local resident conveniently acquire tucson fuel cell cuv helping reduce greenhouse gas emission work live launch tucson fuel cell driver accumulated million zeroemission mile street california zeroemission cumulative mileage accumulated mileage helped improve air quality region tonne emission compared emission similar internalcombustionpowered cuv hyundai delivered tucson fuel cell introduction massproduced fuel cell vehicle market hyundai proud add capitol hyundai growing collection approved zeroemission tucson fuel cell dealer dave zuchowski president ceo hyundai motor america capitol hyundai add convenient location bay area serve newest fuel cell customer northern california capitol hyundai join existing hyundai fuel cell dealer keye hyundai tustin hyundai win hyundai carson hardin hyundai anaheim total qualified fuel cell dealer southern northern california qualified hyundai fuel cell dealer approved dealer fulfil significant additional hydrogen fuel cell requirement customer service technical service tucson fuel cell advantage hyundai tucson fuel cell cuv number advantage alternative fuel energyrich hydrogen fuel estimated driving range mile fillup similar gasoline vehicle further fuel cell driving range vehicle performance minimally affected extreme hot cold ambient temperature giving owner extra measure peace mind day important consumer transitioning gasoline vehicle tucson fuel cell refilled hydrogen time typical gasoline vehicle size hydrogen refuelling station colocated traditional fossil fuel station finally fuel cell vehicle due compact lightweight fuel cell stack design completely production scalable small large vehicle urbanfocused minicompact car fullsize buse truck hyundai motor america hyundai motor america headquartered fountain valley calif subsidiary hyundai motor korea hyundai vehicle distributed united state hyundai motor america sold serviced dealership nationwide hyundai vehicle sold covered hyundai assurance programme include fully transferable vehicle limited warranty hyundais powertrain limited warranty year complimentary roadside assistance hyundai blue link connected care owner hyundai model equipped blue link telematic system proactive safety car care service complimentary year enrollment service include automatic collision notification enhanced roadside assistance vehicle diagnostic alert monthly vehicle health report invehicle service scheduling detail hyundai assurance visit visit media website blog hyundai motor america ","m_szGeo1":"United States","m_szSourceType":"source_news","m_szSrcUrl":"http://www.prnewswire.com/news-releases/capitol-hyundai-of-san-jose-celebrates-first-fuel-cell-customer-delivery-in-northern-california-300260968.html","m_Places":["San Jose, Calif.","San Jose, California","Northern California","Tucson","United States","Bay Area","California","Anaheim","Korea"],"m_People":["Mr. Shaun Del Grande","Dave Zuchowski"],"m_Companies":["Hyundai Motor America","Hyundai","Del Grande Dealer Group","Hyundai Tucson","Tustin Hyundai","Hyundai Motor Co","Nationwide","Twitter","Youtube","Facebook"],"m_BiGrams":["fuel cell","tucson fuel","hyundai motor","capitol hyundai","motor america","northern california","cell dealer","san jose","del grande","grande dealer","dealer group","hyundai tucson","cell hydrogen","hydrogen electric","electric vehicle","hyundai fuel","cell vehicle","zeroemission tucson","cell cuv","gasoline vehicle"],"m_TriGrams":["tucson fuel cell","hyundai motor america","fuel cell dealer","grande dealer group","hyundai tucson fuel","fuel cell hydrogen","cell hydrogen electric","hydrogen electric vehicle","hyundai fuel cell","fuel cell vehicle","zeroemission tucson fuel","fuel cell cuv"],"m_SocialTags":[],"m_Topics":[],"m_Industry":[],"m_Technology":[],"m_BiCnt":[23,12,7,7,6,6,5,3,3,3,3,3,3,3,3,3,3,3,3,3],"m_TriCnt":[12,6,5,3,3,3,3,3,3,3,3,3],"m_iDocBodyWordCnt":435}
