{"m_szDocID":"870242","m_szDocTitle":"Fuel-Cell Electric Vehicle Production Charged Up For 2017 - But Still     Inconsequential As Ubiquitous Alternative To Gasoline","m_szYear":"2016","m_szDocSumamry":"TACH's TAKE: Fuel-Cell Madness...SLAP!...Thanks I Needed That! SOUTHFIELD, MI - May 4, 2016: Production of Global Hydrogen Fuel Cell Electric Vehicles (FCEVs) is expected to reach more than 70,000 vehicles annually by 2027, as more automotive OEMs bring FCEVs to market, according to a new FCEV report from IHS Automotive, part of IHS, Inc. . The report takes a holistic view on FCEV production, components and hydrogen and infrastructure markets. â€œRecently there has been an increasing focus on battery electric vehicles and battery technology, but FCEVs could also play a key role in zero-carbon mo","m_szDocBody":"tach take fuelcell madnessslapthank needed that southfield production global hydrogen fuel cell electric vehicle fcevs expected reach vehicle annually automotive oem bring fcevs market fcev report ihs automotive part ihs inc report take holistic fcev production component hydrogen infrastructure market recently increasing focus battery electric vehicle battery technology fcevs play key role zerocarbon mobility ben scott senior analyst ihs automotive wave fcevs oem hydrogen refuelling infrastructure beginning rolled out said situation fcevs mass market mobility oem offering fcevs consumer toyota mirai hyundai honda clarity select market however year number fcev model expected jump oem add fcevs product portfolios ihs say expected nearterm fcev production expected japan korea european fcev production lead globally shift regional momentum fcevs oem meet emission target however fcev represent percent vehicle produced ihs automotive forecast comparison made battery electric vehicle bevs fcevs current generation fcevs share similar benefit conventional car short refuelling time long range bevs road today advantage refuelling habit fcev similar conventional car customer acceptance fcevs scott said battery technology improving year decreasing energy density increase hydrogen advantage term refuelling time range battery technology catching happen fcev market window opportunity establish contender long term zerocarbon mobility ihs analyst say fcev market reached stage year moved past early adopter phase fcevs remain niche application hydrogen refuelling infrastructure fcevs advantage short refuelling time long range problem hydrogen refuelling infrastructure date approximately plus public hydrogen refuelling station globally oem defining early adopter market hydrogen refuelling station deployed hydrogen refuelling station typically large oftentime dedicated site charging station inexpensive hydrogen refuelling station cost million usd established hydrogen market percent hydrogen produced derived fossil fuel brown hydrogen feedstock natural gas liquid hydrocarbon coal sustainable zerocarbon mobility hydrogen refuel fcevs renewable source green hydrogen achieved electrolyzer electricity renewable source solar wind turbine etc however cost green hydrogen premium compared hydrogen existing plant steam methane reformer market today justify premium market created encourage investment upstream hydrogen production capability tradeoff hydrogen carbon footprint cost scott said platinum platinum catalyst fuel cell therefore fcevs key player longterm carbon mobility demand platinum increase current generation fcevs amount platinum time diesel catalytic converter aim reduce amount platinum fully commercialised r&d nonnoble metal catalyst scott said however fcevs offer good opportunity platinum producer pessimist sentiment longterm demand prospect diesel engine vehicle platinum automotive catalyst demand full report purchase here additional research analysis electric vehicle hybrid market visit ihs automotive hybridev portal #### ihs automotive ihs automotive part ihs inc offer client comprehensive deepest expertise insight automotive industry world today addition polk ihs automotive expertise predictive insight entire automotive chain product inceptionacross design productionto sale marketing effort maximise potential marketplace source complete picture global automotive industry ihs leading source information insight analytic critical areas shape today business landscape ihs business publicly traded company york stock exchange headquartered englewood colorado usa ihs committed sustainable profitable growth employ people country world auto channel ","m_szGeo1":"Japan","m_szSourceType":"source_news","m_szSrcUrl":"http://www.theautochannel.com/news/2016/05/05/230405-fuel-cell-electric-vehicle-production-charged-up-for-2017.html","m_Places":["Take","Toyota","Tucson","Most","Japan","Korea","Englewood, Colorado","United States"],"m_People":["Ben Scott","Ev Portal"],"m_Companies":["Madness","Mi","Hyundai","Honda","Diesel","Ihs Inc.","Polk"],"m_BiGrams":["ihs automotive","hydrogen refuelling","electric vehicle","refuelling station","fcev production","battery technology","zerocarbon mobility","refuelling infrastructure","refuelling time","scott said"],"m_TriGrams":["hydrogen refuelling station","hydrogen refuelling infrastructure"],"m_SocialTags":[],"m_Topics":[],"m_Industry":[],"m_Technology":[],"m_BiCnt":[7,7,4,4,3,3,3,3,3,3],"m_TriCnt":[4,3],"m_iDocBodyWordCnt":474}
