{"m_szDocID":"870332","m_szDocTitle":"Toyota hydrogen research leads to a better battery - Roadshow","m_szYear":"2016","m_szDocSumamry":"Toyota hydrogen research leads to a better battery Your next Lyft driver may be in a GM self-driving car Toyota hydrogen research leads to a better battery A Toyota scientist developing hydrogen storage technology stumbles on a discovery that could make for more energy dense batteries. Wayne Cunningham Wayne Cunningham reviews cars and writes about automotive technology for CNET's Roadshow. Prior to the automotive beat, he covered spyware, Web building technologies, and computer hardware. He began covering technology and the Web in 1994 as an editor of The Net magazine. See full bio Toyota hyd","m_szDocBody":"toyota hydrogen research lead battery lyft driver selfdriving car toyota hydrogen research lead battery toyota scientist developing hydrogen storage technology stumble discovery make energy dense battery wayne cunningham wayne cunningham review car write automotive technology cnet roadshow prior automotive beat covered spyware web building technology computer hardware began covering technology web editor net magazine full bio toyota hydrogen research lead battery share toyota hydrogen research lead battery toyotas graphic show magnesium anode new energy dense battery toyota toyota launched mirai fuel cell car abandon idea pure battery electric vehicle favour hydrogen power but rana mohtadi scientist working hydrogen storage toyota research institute north america trina found technology developing applied innovative magnesium battery toyota point press release magnesium lithium ion material battery anode lead greater energy density improved electricity storage battery make electric car run longer faster electronic device smartphone magnesium battery century prominently commercial magnesium air fuel cell backup power source industrial application researcher recognised magnesium superior anode material battery suitable electrolyte convey ion anode cathode found talking battery researcher trina mohtadi realised material developing hydrogen storage electrolyte magnesium battery mohtadi fellow scientist published research angewandte chemie announcement breakthrough battery technology fair degree frequency couple year researcher touted simple carbon titanium dioxide gel improve charging speed energy density toyota caution press release magnesium technology year commercialise however massive increase portable electronic growing electric car world put battery research greater demand improvement technology certainty tag ","m_szGeo1":"United States","m_szSourceType":"source_news","m_szSrcUrl":"http://www.cnet.com/roadshow/news/toyota-hydrogen-research-leads-to-better-battery/","m_Places":["Toyota","North America"],"m_People":["A Toyota","Wayne Cunningham","Rana Mohtadi","Angewandte Chemie"],"m_Companies":["Lyft","Cnet","Toyota Research Institute"],"m_BiGrams":["toyota hydrogen","hydrogen research","research lead","lead battery","battery toyota","hydrogen storage","magnesium battery"],"m_TriGrams":["toyota hydrogen research","hydrogen research lead","research lead battery"],"m_SocialTags":[],"m_Topics":[],"m_Industry":[],"m_Technology":[],"m_BiCnt":[4,4,4,4,3,3,3],"m_TriCnt":[4,4,4],"m_iDocBodyWordCnt":234}
