{"m_szDocID":"870341","m_szDocTitle":"World's first fuel-cell car-sharing program to launch in Germany","m_szYear":"2016","m_szDocSumamry":"World's first fuel-cell car-sharing program to launch in Germany Email This Page To (separate emails with commas) Message (optional) Your email was sent successfully. Close 144 views May 9, 2016 Hyundai ix35 Fuel Cell for BeeZero car-sharing service Enlarge Photo Car-sharing services have become increasingly popular over the past few years, and many of them operate fleets of battery-electric cars. Now, a German company believes it's time to pair this new approach to car use with hydrogen fuel-cell vehicles. The Linde Group—which manufactures and distributes industrial gases—believes such a ser","m_szDocBody":"world fuelcell carsharing programme launch germany separate email commas message optional successfully close view hyundai fuel cell beezero carsharing service enlarge photo carsharing service increasingly popular past year operate fleet batteryelectric car now german company believe time pair approach car hydrogen fuelcell vehicle linde groupwhich manufacture distribute industrial gasesbelieve service promote fuelcell car giving consumer chance familiar them miss germany announce billion electriccar incentive plan called beezero launching summer munich hyundai fuel cell crossover fuel cell sold tucson fuel cell california state fuelcell car available carsharing service driver rent vehicle app refuel returning hyundai fuel cell beezero carsharing service enlarge photo well public hydrogen fueling station operating germany linde hope beezero carsharing service spur greater interest fuelcell car lead greater support expanding infrastructure further germany plan deploy nationwide network hydrogen station fully funded early site delayed online wait develop beezero general manager sandra scherb told coexist lead ourselve particular beezero hope emphasise greater range hydrogen fuelcell car compared batteryelectric fuel cell rated kilometre mile range optimistic european testing cycle hyundai fuel cell beezero carsharing service enlarge photo usmarket tucson fuel cell carry epa range rating mile due stricter epa testing regimen korean carmaker supplied fuel cell crossover paris taxi service step socit taxi electrique parisien back december more hyundai supply tucson fuel cell taxis paris fleet dec hyundai previously delivery put number fuel cell vehicle european road past unit mark hyundai delivered tucson fuel cell crossover model ","m_szGeo1":"Germany","m_szSourceType":"source_news","m_szSrcUrl":"http://www.greencarreports.com/news/1103841_worlds-first-fuel-cell-car-sharing-program-to-launch-in-germany","m_Places":["Germany","Munich","Tucson","California","United States","Linde","Paris"],"m_People":["Sandra Scherb"],"m_Companies":["Hyundai","Linde Group","Nationwide","Epa"],"m_BiGrams":["fuel cell","carsharing service","hyundai fuel","beezero carsharing","fuelcell car","tucson fuel","cell beezero","service enlarge","enlarge photo","cell crossover"],"m_TriGrams":["hyundai fuel cell","beezero carsharing service","tucson fuel cell","fuel cell beezero","cell beezero carsharing","carsharing service enlarge","service enlarge photo","fuel cell crossover"],"m_SocialTags":[],"m_Topics":[],"m_Industry":[],"m_Technology":[],"m_BiCnt":[12,6,4,4,4,4,3,3,3,3],"m_TriCnt":[4,4,4,3,3,3,3,3],"m_iDocBodyWordCnt":237}
