{"m_szDocID":"877820","m_szDocTitle":"Predictions in Technology and Health    | Worldhealth.net Anti-Aging News","m_szYear":"2016","m_szDocSumamry":"Predictions in Technology and Health Posted on June 6, 2016, 6 a.m. in Industry News Artificial Intelligence Biotechnology Longevity What happened to Kodak will happen in a lot of industries in the next 10 years - and most people don't see it coming. - Dr. Robert M. Goldman MD, PhD, DO, FAASP - Image courtesy of Dr. Robert M. Goldman MD, PhD, DO, FAASP INTRODUCTION: by Dr. Ronald Klatz MD, DO: We live in a miraculous time, due to the rapid growth of new technology. For those following the anti-aging lifestyle, life expectancy is increasing by three months per year. People utilizing the anti-ag","m_szDocBody":"prediction technology health posted industry new artificial intelligence biotechnology longevity happened kodak happen lot industry year people coming robert goldman phd faasp image courtesy robert goldman phd faasp introduction ronald klatz live miraculous time due rapid growth technology antiaging lifestyle life expectancy increasing month year people utilising antiaging tenet health life expectancy rate growing predicted year ago medicine nowat finally transforming treatment illness disease preventative measure extension human lifespan robert goldman prediction expect future impact live future prediction kodak employee sold photo paper worldwide year business model disappeared bankrupt happened kodak happen lot industry year people coming year picture paper film again digital cameras invented pixel moore law exponential technology disappointment long time superior mainstream short year happen artificial intelligence health autonomous electric car education printing agriculture job industrial revolution exponential age software disrupt traditional industry year uber software tool car biggest taxi company world airbnb biggest hotel company world property artificial intelligence computer exponentially understanding world year computer beat player world year earlier expected young lawyer job ibm watson legal advice basic stuff second accuracy compared accuracy human study law stop immediately fewer lawyer future specialist remain watson help nurse diagnosing cancer time accurate human nurse pattern recognition software recognise face human computer intelligent human autonomous car selfdriving car public complete industry start disrupted car anymore call car phone show location drive destination park pay driven distance productive driving kid driver licence car change city fewer car that transform parking space park million people die year car accident worldwide accident autonomous driving drop accident million save million live year car company bankrupt traditional car company evolutionary approach build car tech company tesla apple google revolutionary approach build computer wheel spoke lot engineer volkswagen audi completely terrified tesla insurance company massive trouble accident insurance cheaper car insurance business model disappear real estate change work commute people move live beautiful neighbourhood electric car wont mainstream city noisy car run electric electricity incredibly cheap clean solar production exponential curve year impact year solar energy installed worldwide fossil price solar drop coal company business cheap electricity cheap abundant water desalination kwh cubic metre scarce water place scarce drinking water imagine clean water want cost health company build medical device called tricorder star trek work phone take retina scan blood sample breathe analyse biomarker identify disease cheap year planet world class medicine free printing price cheapest printer year time time faster major shoe company started printing shoe spare aeroplane part printed remote airport space station printer eliminate large number spare part past end year smart phone scanning possibility scan feet print perfect shoe home china printed complete storey office building produced printed business opportunity niche yourself future that answer yes make happen sooner work phone forget idea idea designed success century doomed failure century work job disappear year lot job clear job small time agriculture agricultural robot future farmer world country manager field working day field agroponic water petri dish produced veal cheaper cowproduced veal now agricultural surface cow imagine space anymore startup bring insect protein market shortly protein meat labelled alternative protein source because people reject idea eating insect app called moody mood are app facial expression lying imagine political debate displayed telling truth not bitcoin mainstream year default reserve currency longevity now average life span increase month year year ago life span year year increase increasing year increase year live long long time education cheapest smart phone africa asia human smart phone mean world class education robert goldman phd faasp cofounder chairmanworld academy antiaging medicine world chairmaninternational medical commission cofounder chairman boardam founder chairmaninternational sport hall fame president emeritusnational academy sport medicine nasm chairmanus sport academy board visitor ","m_szGeo1":"United States","m_szSourceType":"source_news","m_szSrcUrl":"http://www.worldhealth.net/news/predictions-technology-health/","m_Places":["Most","United States","Tesla","China","Farmers","Africa","Asia"],"m_People":["Robert M. Goldman","Ronald Klatz"],"m_Companies":["Kodak","Tenets","Lifespan","Uber","Airbnb","Ibm","Watson","Facebook","Around 2020","Apple","Google","Volkswagen","Audi","2020","Star","All Days","Sports Hall Of Fame","National Academy Of Sports Medicine","Nasm"],"m_BiGrams":["robert goldman","artificial intelligence","industry year","year people","goldman phd","phd faasp","smart phone"],"m_TriGrams":["robert goldman phd","goldman phd faasp"],"m_SocialTags":[],"m_Topics":[],"m_Industry":[],"m_Technology":[],"m_BiCnt":[4,3,3,3,3,3,3],"m_TriCnt":[3,3],"m_iDocBodyWordCnt":606}
