{"m_szDocID":"919248","m_szDocTitle":"Home - ChinaAbout.net","m_szYear":"2016","m_szDocSumamry":"textArticle -------------------- ChinaAbout.net Ask A Question, Get An Answer Have a question about China? Need advice? Write an email to [email protected] and include \"Ask ChinaAbout.net\" in the subject line. All emails will be read and may be replied & published on our site. Recent Changes 10 Reasons Why China is Successful and Efficient March 15th, 2016 “Made in China” really doesn't mean what it used to be, quality of Chinese-made products is rising fast. In addition, China is moving very fast in technological [...] Why Chinese consumers will continue to surprise the world March 8th, 2016 ","m_szDocBody":"chinaaboutnet question answer question chinaneed advice write emailprotected include ask chinaaboutnet subject line email read replied published site recent reason china successful efficient made china quality chinesemade product rising fast addition china moving fast technological chinese consumer continue surprise world china great consumer market recently easy people ignore new slowgrowth dilemma china headingin china shaking world chinas continual slowing economic growth inevitable trend difficult position fear world concern international invest showbiz barbie hsu big birth girl taiwanese famous actress barbie hsu big gave birth girl posted thanksgiving daughter footprint sin hawick lau exposed romantic couple picture photo source fashionqqcom wedding hawick lau held bali lowk famous car show girl shoushou returned job show girl guangzhou auto show ongoing guangzhou international auto part accessory exhibition nov famous car show girl shoushou returned job business china edge financial crisis happening global financial crisis number economist famousbusinessperson predicted global crisis china global leader electric vehicle market year china surpassed largest plugin electric car market term total annual sale china ranked best big reason china hold treasury bond economic reform china buying treasury bond decade what more trade deficit china largest sport big reason chinese super league csl biggest noneuropean league chinese football club competing luring top international footballer coaches huge wage football world order changing guangzhou evergrande released poster challenging bayern munich winning african champion club world cup final afc champion guangzhou evergrande won ahly fifaclub world cup final score liqin lin quit national table tennis team evening beijing time olympic champion lin married girlfriend zhang yaqing wedding scene lin announced tha travel photos shanghai located east china shanghai junction yangtze river qiantang river approx foreign resident living city shan shanghai french concession shanghai french concession concession shanghai the shanghai international settlement located insid kunming welcomed snowfall affected strong cold air obvious temperature drop witnessed spring city culture northeast china region northeast china simplified chinese traditional chinese pinyinzhnggu dngbi dongbei major geographical region northwest china region northwestern china simplified chinese pinyin xbi major geographical region china divided physical human characte south china region south china simplified chinese traditional chinese pinyin major geographical region china divided physical opinion china edge financial crisis happening global financial crisis number economist famousbusinessperson predicted global crisis china abandon onechild policy year china strict limitation population growth adopting socalled onechild policy initiated late china final china devalue chinese yuan renminbi people bank china announced surprising decision depreciate chinese yuan dollar central bank language happy year chinese popular chinese greeting year horse happy year chinese xnnin kuil new year happy standard mandarin the widely chinese safest jiangnan area history chinajiangnan area southern area welldeveloped beautiful rich region word jiangnan addressed ink definition meaning definition refer fake lowquality product term cantonese mean small manufacturer small workshop engaged piracy china face jack mas longterm vision alibaba jack yun attended joint meeting strategic cooperation alibaba hangzhou city profile guangmei yan guangmei yan phd vice president sun yatsen university professor zhangshan school medicine sun yatsen university sysueducn profile jianlin jianlin born sichuan hejoined army demobilised armyandbecametheoffice manager dalian city peopl ","m_szGeo1":"China","m_szSourceType":"source_news","m_szSrcUrl":"https://www.chinaabout.net/","m_Places":["China","Made","Hawick","Bali","Guangzhou","U.s.","Us","Beijing","Shanghai","East China , Shanghai","Kunming","Spring City","Northeast China","Zhōngguó","Northwest China","Northwestern China","South China","華","Most","Jiangnan Area","And Hangzhou City","Dalian City"],"m_People":["Barbie Hsu","Wang Liqin","Zhang Yaqing","Guangmei Yan"],"m_Companies":["Mi","U.s. Treasury","Chinese Super League","Csl","Ea","Evergrande Fc","Bayern Munich","Afc","Fifa","People's Bank Of China","The Central Bank","Alibaba","Alibaba Group","Ma Sa","Sun Yat-sen University","School Of Medicine","林"],"m_BiGrams":["financial crisis","show girl","china region","china simplified","simplified chinese","major geographical","geographical region"],"m_TriGrams":["china simplified chinese","major geographical region"],"m_SocialTags":[],"m_Topics":[],"m_Industry":[],"m_Technology":[],"m_BiCnt":[4,3,3,3,3,3,3],"m_TriCnt":[3,3],"m_iDocBodyWordCnt":506}
