{"m_szDocID":"934968","m_szDocTitle":"Real-time news feed - BadBlue","m_szYear":"2016","m_szDocSumamry":"badblue.com/ News Cars Fame Guns Money Prep Sports Tech Watches    Donate >>>    Now Last 24 Hours Last 7 Days Last 30 Days 210 popularmechanics.com Rank Buzz Clicks Premiered Headline Source Link 1 17538 0 16-05-17 19:14 Hail to the Computer popularmechanics.com ∞ 2 15141 0 16-05-20 21:14 This Stunning Motorcycle Was 3D Printed From Aluminum Power popularmechanics.com ∞ 3 10434 0 16-06-07 21:14 Chile Generates So Much Solar Power That It Just Gives the Extra Away: Chile has so much solar energy ... #Solar popularmechanics.com ∞ 4 9435 0 16-05-24 13:14 The Hidden Science of Elevators popularme","m_szDocBody":"new car fame gun money prep sport tech watches donate hour day day popularmechanicscom rank buzz click premiered headline source link hail computer popularmechanicscom stunning motorcycle printed aluminium power popularmechanicscom chile generate solar power extra away chile solar energy #solar popularmechanicscom hidden science elevator popularmechanicscom limitededition patek philippe grandmaster chime ref complex #watches world popularmechanicscom yes #twitter character limit popularmechanicscom wear safety glasse popularmechanicscom map airport connect show real shape world popularmechanicscom suck messy history vacuum cleaner popularmechanicscom vintage car toy worth buck popularmechanicscom onefourth world energy renewable source popularmechanicscom combat vehicle military giant poster popularmechanicscom father taught joe hunter biden family bond popularmechanicscom sony smart contact patent imagine future sight popularmechanicscom belgian city built underground beer pipeline popularmechanicscom gps tracking reveal ewaste exported illegally popularmechanicscom scientist turn bacteria living hard drive popularmechanicscom watch spacex land rocket popularmechanicscom flyby world largest optical telescope popularmechanicscom buy portable air conditioner popularmechanicscom world largest math proof take terabyte popularmechanicscom jukebox groove popularmechanicscom mile cable carry internet atlantic blistering speed popularmechanicscom stunning motorcycle printed aluminium power popularmechanicscom world largest solar plant set fire popularmechanicscom declassified photos show soviet union hero space dog colour popularmechanicscom speeding bird caught traffic camera popularmechanicscom turtle eat sixpack ring caught popularmechanicscom faa warn mysterious planned gps outage desert popularmechanicscom tyre pressure important car popularmechanicscom shooting reported dallas love field baggage popularmechanicscom magnet copper coil battery make tiny hyperloop popularmechanicscom watch year drone footage second popularmechanicscom neanderthal built mystery cave ring year ago popularmechanicscom glass tree house aibek almassov popularmechanicscom tattoo artist lose arm build tattoodrawing prosthetic sheitan tenet lost arm year ago #tattoo popularmechanicscom army rolling superhuman hearing soldier popularmechanicscom machine fold laundry pinnacle modern engineering popularmechanicscom watch navy locust launcher fire swarm autonomous drone popularmechanicscom watch nasa inflate expandable habitat iss live popularmechanicscom difference cement concrete mortar explained minute popularmechanicscom drone taxi cleared flight test nevada popularmechanicscom vietnam mach missilemuch chinas chagrin popularmechanicscom nato upgrade tank pace russia popularmechanicscom turned bmw pickup truck popularmechanicscom ride world craziest roller coaster desk popularmechanicscom giant planet huge make sun spin faster popularmechanicscom silos converted house nontraditional home popularmechanicscom mar opposition blue moon weekend stargazer midwest southwest sight popularmechanicscom india building million monsoonpredicting supercomputer popularmechanicscom difference cement concrete mortar explained minute popularmechanicscom weird quirk make image transform magic popularmechanicscom king tut knife outer space popularmechanicscom mar closer earth tonight decade popularmechanicscom belgian city built underground beer pipeline popularmechanicscom invented electric guitar popularmechanicscom ever finally totally wireless earbud work popularmechanicscom pineapple protect iphone drop popularmechanicscom stunt fast furious real city street terrifying popularmechanicscom faraway earthsized planet habitable popularmechanicscom #history #vacuum cleaner popularmechanicscom remember floppy disc well turn pentagon nuclear mission popularmechanicscom steampunk lowtech masterpiece popularmechanicscom glimpse inside ultramodern chinese guided missile destroyer popularmechanicscom interesting shifter made popularmechanicscom coming soon firefighting mask augmented reality thermal imaging popularmechanicscom boston shipwreck shipwreck unearthed boston popularmechanicscom tank robot carry glock popularmechanicscom woman gps told drive lake listened popularmechanicscom expensive car brand maintain popularmechanicscom #connected popularmechanicscom number end runway hidden meaning popularmechanicscom traffic jam happen seemingly reason popularmechanicscom boeing patent weird solar plane fly forever popularmechanicscom evidence mount elon musk tony stark popularmechanicscom ejected rolling rally car popularmechanicscom world largest tunnel open switzerland popularmechanicscom budget airline cut corner make flight cheap popularmechanicscom watch tonight spacex launch live popularmechanicscom requirement awful hate popularmechanicscom visual history air force linkiscom popularmechanicscom flexible waterproof bandaid battery power future wearable tech popularmechanicscom hail computer popularmechanicscom beijing enraged pentagon report chinas military popularmechanicscom quantum physic solve time travel famous paradox popularmechanicscom nasa build supersonic plane boom popularmechanicscom gadget make home #smart save money popularmechanicscom carpetcleaning secret pros popularmechanicscom war bot climb mess popularmechanicscom tesla tucker similarity automaker popularmechanicscom dday planning operation overlord world war popularmechanicscom dead blue angel jet crashes tennessee popularmechanicscom soviet union make tank fly popularmechanicscom chrome secret dinosaur game saviour patchy internet signal popularmechanicscom suck messy history vacuum cleaner popularmechanicscom nsa spy thermostat refrigerator pacemaker #iot popularmechanicscom china plan space station lab beneath sea popularmechanicscom finnish government bury nuclear waste year popularmechanicscom million password apparently leaked deny hacked popularmechanicscom fullcolor photos invasion normandy show dday looked popularmechanicscom future navy electromagnetic railgun big step backward popularmechanicscom statesponsored #hacker stepping attack infrastructure popularmechanicscom augmented reality app solve rubik cube popularmechanicscom working plan prevent skynet situation popularmechanicscom google selfdriving car beep bad human driver popularmechanicscom record summer shark attack popularmechanicscom stealth dirtbike special force popularmechanicscom diy air conditioner surprisingly effective linkiscom popularmechanicscom coolest truck time pickup man popularmechanicscom giant robot squid creepily awesome popularmechanicscom build cornhole board popularmechanicscom wash wax protect car popularmechanicscom rattled russia sweden reveal fighter jet popularmechanicscom crew fail place nato tank competition popularmechanicscom declassified photos soviet union space dog popularmechanicscom reason jigsaw popularmechanicscom video japanese papermaking calmest day popularmechanicscom man survived entire year artificial heart backpack popularmechanicscom algorithm built dystopian cityscape popularmechanicscom smart glass swap transparent opaque flick switch popularmechanicscom make spacesaving foldup workbench popularmechanicscom statesponsored hacker stepping attack infrastructure popularmechanicscom build standup desk popularmechanicscom elon musk hope congress mar #mar popularmechanicscom blade spin lego chainsaw popularmechanicscom making electric car battery popularmechanicscom multi tool task pocket tool multitool popularmechanicscom coolest jame bond car aston martin popularmechanicscom reallife pong game rec room popularmechanicscom converted mercede run vegetable oil popularmechanicscom watch tonight spacex launch live popularmechanicscom watch nasa inflate expandable habitat iss live popularmechanicscom high life tourist charged yellowstone photos trespassing grand prismatic spring popularmechanicscom making plastic create gorgeous static electricity static eliminator popularmechanicscom world worst traffic problem solved popularmechanicscom woman drove world model popularmechanicscom mystery force nature unlock dark matter popularmechanicscom coolest tool dad enough laser tape measure #dadblogsaboutgiftchat popularmechanicscom name newest chemical element popularmechanicscom spacex plan reuse rocket time fall popularmechanicscom north korea started making plutonium again north korean nuclear plant shut internatio popularmechanicscom thunderbird jet crashes flyover air force academy commencement popularmechanicscom tyre pressure important car popularmechanicscom trick turn grill great smoker popularmechanicscom part squid part robot lot awesome mechateuthis sight behold popularmechanicscom revisiting morley safer minute report lamborghini countach popularmechanicscom forge knife railroad spike popularmechanicscom built radarcontrolled watch magic early prot popularmechanicscom turn atari game cartridge wallet popularmechanicscom uber selfdriving car sensor popularmechanicscom government buying dronejamming radio rifle popularmechanicscom russia happy american antimissile system moscow concerned system popularmechanicscom roman shipwreck full treasure found israel popularmechanicscom watch lego porsche assembled piece piece cooler lego build popularmechanicscom greatest wildernesse world popularmechanicscom clean metal shaving arrow welding magnet popularmechanicscom warcraft massively unwatchable disaster popularmechanicscom drone giving apache helicopter set eye popularmechanicscom neighbourhood waze car popularmechanicscom make mosquito repellent popularmechanicscom trick iphone boss popularmechanicscom touch stuff museum popularmechanicscom nicely done animated guide battle #jutland biggest naval battle world war popularmechanicscom army air force agonise picking handgun popularmechanicscom watch airstrike destroy isis oil popularmechanicscom asus announce family friendly household assistant bot zenbo running house popularmechanicscom notifly pant technology tell fly popularmechanicscom micro distilling macro popularmechanicscom tsa delta fixed security checkpoint popularmechanicscom watch spacex launch here live stream start matter minute popularmechanicscom fascinating fact bike popularmechanicscom electric #motorcycle #dprinted aluminium powder cost euros popularmechanicscom army bringing back gun fight popularmechanicscom screwdriver atomic bomb simple slip los alamos turned deadly assembled tri #bomb popularmechanicscom darth darthwest mashes star war hitchcock popularmechanicscom yes run window xbox popularmechanicscom auto patent flypaper pedestrian popularmechanicscom crashes shortly takeoff guam popularmechanicscom photographed spacex falcon landing accident popularmechanicscom turn drill press vertical woodworking lathe popularmechanicscom teaser star trek show popularmechanicscom megatsunamis mar #mar popularmechanicscom version android support splitscreen pictureinpicture app popularmechanicscom internet slow cheque popularmechanicscom app read solve handwritten math problem popularmechanicscom gps woman drive lake popularmechanicscom colour photos soviet space dog declassified popularmechanicscom booby trap bike alarm pop blank terrorise thieve popularmechanicscom scientist modelling flow manure gas make farm safer popularmechanicscom snake bite snake bite aid popularmechanicscom time gave #car good wash awhile great guide now #carcare popularmechanicscom mrzrd allterrain vehicle built war popularmechanicscom star trek movy ranked popularmechanicscom mother nature angriest popularmechanicscom air force drone perch power line bird popularmechanicscom traffic simulator show jam form real time popularmechanicscom today gif ship #deepsn popularmechanicscom drive long prosper tiny spock hot wheel set popularmechanicscom fastest lap isle man popularmechanicscom giant planet huge make sun spin faster popularmechanicscom mistake popularmechanicscom braintobrain communication closer think neuroscientist monkey thought contr popularmechanicscom transformer benches picnic table popularmechanicscom iraqi army flying chinesemade killer drone popularmechanicscom literally impossible throw good party piata drone popularmechanicscom gonna wanna watch silly string crushed popularmechanicscom perfect place crash bike popularmechanicscom sound favourite scifi ship hum freezer popularmechanicscom nail screw popularmechanicscom animated guide battle jutland popularmechanicscom suggestion copyright working resource inc right reserved generated badblue software visit software site","m_szGeo1":"","m_szSourceType":"source_general","m_szSrcUrl":"http://badbluetech.bitnamiapp.com/c/d.php?did=popularmechanics.com","m_Places":["Chile","Most","Bucks","Belgian City","Us","Soviet Union","Best","Nevada","Vietnam","China","Russia","India","Well","Made","Boston","Switzerland","Beijing","Tesla","Jet","Tennessee","U.s.","Sweden","Yellowstone","North Korea","Moscow","Israel","Noti","Los Alamos","Guam","Isle Of Man"],"m_People":["Joe","Hunter Biden","Tiny Hyperloop","Aibek Almassov","Sheitan Tenet","King Tut","Elon Musk","Tony Stark","Morley Safer","Made Kill"],"m_Companies":["Patek Philippe","Chime","Character","Vintage","U.s. Military","Sony","Underground","Spacex","Atlantic","U.s. Army","Navy","Nasa","Taxi","Nato","Bmw","Silos","Blue Moon","Sights","Twitter","R2","Jams","Boeing","How Nasa","Google","Signal","Nsa","Special Forces","Giant Robot","Congress","Aston Martins","Plastic","Lamborghini Countach","Atari","Uber","U.s. Government","Apache","Us Army","Air Force","Isis","Delta","Army","Drill Press","Iraqi Army","Hum","Working Resources Inc."],"m_BiGrams":["popularmechanicscom watch","car popularmechanicscom","world largest","popularmechanicscom world","live popularmechanicscom","air force","world popularmechanicscom","cleaner popularmechanicscom","soviet union","space dog","popularmechanicscom army","drone popularmechanicscom","minute popularmechanicscom","popularmechanicscom giant","spacex launch","war popularmechanicscom","popularmechanicscom coolest"],"m_TriGrams":["popularmechanicscom world largest"],"m_SocialTags":[],"m_Topics":[],"m_Industry":[],"m_Technology":[],"m_BiCnt":[10,5,4,4,4,4,3,3,3,3,3,3,3,3,3,3,3],"m_TriCnt":[3],"m_iDocBodyWordCnt":1406}
