{"m_szDocID":"940718","m_szDocTitle":"Jeff Desjardins - Business Insider","m_szYear":"2016","m_szDocSumamry":"BI Intelligence Events Trending Tech Finance Politics Strategy Life Sports Video All Jeff Desjardins Jeff Desjardins Sort: Newest Oldest Most Read Snapchat has a monetization problem Jeff Desjardins, Visual Capitalist Jun. 10, 10:06 AM 703 2 This awesome infographic shows the evolution of money Jeff Desjardins, Visual Capitalist Jun. 7, 6:49 PM 1,622 1 This infographic shows where the ultra-rich are scrambling to buy homes Jeff Desjardins, Visual Capitalist Jun. 6, 7:33 PM 6,750 1 Here's the story of how Vancouver's housing market lost its mind Jeff Desjardins, Visual Capitalist Jun. 2, 6:49 P","m_szDocBody":"intelligence event trending tech finance politic strategy life sport video jeff desjardin jeff desjardin sort newest oldest read snapchat monetization problem jeff desjardin visual capitalist jun awesome infographic show evolution money jeff desjardin visual capitalist jun infographic show ultrarich scrambling buy home jeff desjardin visual capitalist jun storey vancouver housing market lost mind jeff desjardin visual capitalist jun popular mint world jeff desjardin visual capitalist infographic show teslas rival electric vehicle industry jeff desjardin visual capitalist awesome infographic show millennial spend money jeff desjardin visual capitalist movement cashless snowballing jeff desjardin visual capitalist awesome infographic estimate size chinas massive debt bomb jeff desjardin visual capitalist map tell lot wealth geopolitical influence natural resource middle east jeff desjardin visual capitalist infographic explain rare coin jeff desjardin visual capitalist infographic show world tallest building evolved time jeff desjardin visual capitalist infographic show explosion bankruptcy energy industry jeff desjardin visual capitalist stunning visualisation show oil import changed jeff desjardin visual capitalist map show china dominating global trade jeff desjardin visual capitalist map show china dominating global trade jeff desjardin visual capitalist apr canadas mining industry horror storey jeff desjardin visual capitalist apr stunning visualisation show consumption realtime jeff desjardin visual capitalist apr infographic show time buy sell stock jeff desjardin visual capitalist apr infographic show job created jeff desjardin visual capitalist apr infographic show elon musk built massive empire jeff desjardin visual capitalist apr history credit card jeff desjardin visual capitalist apr infographic show bad imf forecast jeff desjardin visual capitalist apr infographic show select commodity performed jeff desjardin visual capitalist apr infographic show gigantic arctic undiscovered oil reserve jeff desjardin visual capitalist apr brazil home mind boggling top murderous city world jeff desjardin visual capitalist apr infographic show make buy home city jeff desjardin visual capitalist apr infographic show job extinct due robot jeff desjardin visual capitalist apr infographic break world richest people age location source fortune jeff desjardin visual capitalist apr wealthiest billionaire jeff desjardin visual capitalist mar richest poorest country world jeff desjardin visual capitalist mar city propping canadas housing market jeff desjardin visual capitalist mar infographic show relationship currency debasement assassination roman emperor jeff desjardin money project mar startup reached unicorn status fastest jeff desjardin visual capitalist mar infographic show crazy growth chinas province jeff desjardin visual capitalist mar millennial love brand jeff desjardin visual capitalist mar infographic show devastation great depression jeff desjardin money project mar animation show japan demographic headwind jeff desjardin visual capitalist mar infographic show raw material teslas model jeff desjardin visual capitalist mar people buying gold etf record pace jeff desjardin visual capitalist mar previous recommended featured hightech classe coolest happening school today future now neil degrasse tyson gore future planet innovator business insider email alert signup learn business insider select featured business insider select tech select tech chart day market chart day opening bell instant mba business insider event intelligence daily finance finance select market select scouting report money select financial advisor insight smart investor cfo insider finance insider wealth advisor select strategy strategy select advertising select retail select career select advertising politic politic select military select life life select transportation select education select entertainment select breaking new tech enterprise select science select mobile chart day ecommerce chart day payment chart day digital media chart day iot chart day fintech briefing chart day sport chart day top tech closing bell sport sport latest research top tech prediction payment ecosystem report fintech ecosystem report internet report read business insider iphone ipad android job tech job clevel job media job design job finance job sale job job partner copyright business insider inc right reserved registration constitute acceptance term service privacy policy disclaimer commerce policy made nyc stock quote finanzennet international edition aus ","m_szGeo1":"United States","m_szSourceType":"source_general","m_szSrcUrl":"http://www.businessinsider.com/author/jeff-desjardins","m_Places":["Most","Vancouver","Tesla","China","United States","Middle East","Canada","Brazil","Japan","Mobile","Made","Nyc","Uk"],"m_People":["Jeff Desjardins","Elon Musk","Neil Degrasse","Tyson","Al Gore"],"m_Companies":["Imf","Fintech","Business Insider Inc."],"m_BiGrams":["jeff desjardin","desjardin visual","visual capitalist","infographic show","capitalist apr","apr infographic","capitalist mar","chart day","business insider","capitalist jun","capitalist infographic","mar infographic","awesome infographic","world jeff","capitalist map"],"m_TriGrams":["jeff desjardin visual","desjardin visual capitalist","visual capitalist apr","capitalist apr infographic","visual capitalist mar","apr infographic show","visual capitalist jun","visual capitalist infographic","capitalist mar infographic","mar infographic show","world jeff desjardin","capitalist infographic show","visual capitalist map"],"m_SocialTags":[],"m_Topics":[],"m_Industry":[],"m_Technology":[],"m_BiCnt":[42,38,38,18,14,9,9,9,6,4,4,4,3,3,3],"m_TriCnt":[38,38,14,9,9,8,4,4,4,4,3,3,3],"m_iDocBodyWordCnt":617}
