{"m_szDocID":"961119","m_szDocTitle":"Public (EU) | TRIP","m_szYear":"2016","m_szDocSumamry":"Skip to main content Jump to navigation Transport Research and Innovation Portal About this site Glossary Legal notice What's new Contact us Main menu Home Sector Mode Policy Technology Evaluation You are here Home › Public (EU) Public (EU) Funding Type Public (EU) EU financial instrument supporting environmental, nature conservation and climate action projects Submitted by Dan on Wed, 2016-04-27 10:58 Programme details EU financial instrument supporting environmental, nature conservation and climate action projects   Outline Funding Projects Contact Leading Institutions: Project Profiles: Air","m_szDocBody":"skip main jump navigation transport research innovation portal glossary legal notice contact main menu home sector mode policy technology evaluation home public public funding type public financial instrument supporting environmental nature conservation climate action project submitted dan wed programme detail financial instrument supporting environmental nature conservation climate action project outline funding project contact leading institution project profile airbus corporate answer disseminate integrated environmental management system demonstration project development disassemblyfriendly recyclable railway vehicle graz noise emission reduction promotion alternative mean transport citizen personal wellbeing inovative solution railway noise management parking green service environment historic town planning model urban district naple involving local rail network reopening disused line horizon smart green integrated transport submitted lukejone tue programme detail horizon smart green integrated transport outline funding project contact leading institution project profile fuel saving commercial vessel hybrid wind motor cruise mode fold reduction international transport empty container folding compact dynamic positioning system general purpose marine unit craft ship fast ecoefficient transhipment system ultra large container vessel flexible hybrid forklift utilise advanced power technology electronic offer performance efficiency indoor outdoor application logistic industry lightweight fast charging platform utilised car share urban mobility system low environmental impact brake system mile runway modular compact controller design light electric vehicle generation car seat baby practical portable robust scanning system infrastructure inspection radar iir investigation rail track substructure ballast tunnel infrastructure action plan future mobility europe adaptive selftuning flight control system complete qualified additive manufacturing optimization simulation platform repairing remanufacturing aerospace component advanced analytic trip origindestination matrice advanced smart system optimising nonconformity concession processe aerospace industry advanced bearing technology increase capability advanced measure reduce cyclist fatality increase comfort interaction motorised vehicle advanced generation landing system advanced generation landing system advanced plugin hybrid electric drive system commercial fleet truck aerodynamic acoustic highbypass ratio turbofan integration aeroelastic gust modelling affordable personal refuelling appliance pra natural gas vehicle oilfree coaxial compression air air automatic refuelling airbag bicycle helmet based piece woven technology aircraft generation mdo innovative collaboration heterogeneous team expert airlander civil exploitation project airline maintenance operation implementation maintenance service architecture enabler automated hev vehicle fire early warning suppression system innovative hybrid propulsion generation system yacht innovative people localisation system safe evacuation large passenger ship innovative range extending service electric vehicle based modular range extender demand rental attached occasionally long distance trip augmented reality aerial navigation safer effective aviation automatic rail safety solution automation intelligence solution automated road transport system automation concept technology aircraft assembly line aircraft factory future automotive residue valorization bespoke acoustic emission system realtime ship hull monitoring weather condition birdwatch integral modular mobility security solution smart parking management blindfast innovative blind fastener monitoring technology quality control brake disc automotive performance enhancement insertion diamond particle bringing lngtank technology industrial readiness building sustainable logistic trusted collaborative network entire supply chain business aviation laminar nacelle business model enhancing funding enabling financing infrastructure transport circulation pilot continuous control multimodal air cargo container clean air reduce vehicle emission clearview trade cloud based collaborative custom system cloud based vessel allocation decision support system vessel chartering cng fuel mother daughter cng station concept compa market study composite patch repair marine pipesa costefficient durable pipe repair urgency composite repair solution aeronautical business development phase comprehensive aerodynamicaeroacoustic analysis trimmed compound helicopter computeraided road marking machine roadwriter conductive fast charge system electric buse public transport conexbird wind speed container prevent damage congestion reduction europe advancing transport efficiency converting conventional car hybrid solar vehicle cooperative deployment coordination support cooperative mobility european city core noise engine technology cost effective wireless electrical transportation costeffective aluminium die casting automotive industry crack growth threshold analysis tial alloy cror bladeout impact simulation sample manufacturing cror engine debris impact shielding design manufacturing simulation impact test preparation crowdsourcing technology change people car move city data driven approach seamless efficient european travelling datadriven decision intelligent management public transportation decision support tool rail infrastructure manager delivering generation transport management system european transport sme demonstrating unique property nanocellulose composite automotive application demonstration binarylogic hybrid transmission heavyduty vehicle demonstration innovative concept quality transport perishable agro food liquid inducing modal shift short sea river transport design distortion metallic aerospace part based combination numerical modelling activity topology optimisation developing advanced engine multidisciplinary optimization simulation demos development manufacturing alloxide inter turbine duct aeroengine development commercial manufacturing process low cost small footprint efficiency fully electric compressor power control fulfil market heavy good vehicle development cost effective reliable hydrogen fuel cell vehicle refuelling system development generic digital controller hydraulic load profiling control system significantly reduce cost time aircraft test rig development commissioning development reliable quality control system advanced nondestructive evaluation nde technology production environment leakfree fuel tank plastic composite development titanium composite brake part weight reduction lower fuel burn emission large long haul aircraft development innovative welding process rapid assembly thermoplastic bracket thermosetmatrix composite structure development maintenance architecture process method enabling reliable economic air transport system development experimental technique predictive tool characterise thermomechanical fatigue behaviour damage mechanism development performance turbocharger aeronautical application development modelica library ecs thermal management architecture development polymer halter oil philtre development replacement method kind dynamically tested aircraft cushion development smart flexible freight waggon facility improved transport granular multimaterial development voc ozone microanalyser based microfluidic device aircraft cabin air monitoring macao diode die fatigue characterisation testing disruptive process construction railway transition zone reducing drastically construction maintenance cost door door information airport airline drag reduction turbulent boundary layer flow control dual active mode component dual fuel euro engine conversion feasibility study dynamic road casting erescue system level postaccidentsafety saving time live goldenhour easily distributed personal rapid transit ecological multifunctional composite application aircraft interior secondary structure effective coordinated road infrastructure safety operation efficiensea efficient safe sustainable traffic sea efficient costeffective intermodal roadrail container freight system efficient composite part manufacturing efficient manufacturing aerospace component additive manufacturing net shape hip investment casting efficient urban light vehicle electric axle hybrid electric commercial vehicle electric smart eco vacuum pump green car electrification public transport city electrolyte cathode anode improvement marketnear nextgeneration lithium ion battery electromagnetic platform lightweight electrical system composite electrical aircraft electronic scanning mimo radar railway level crossing obstruction detection alerting empowering reduction conventionally fueled vehicle positive policy measure enforcement environmental regulation sulphur emission ship drone technology engine installation integration enhance efficiency combustion engine monitoring internal chamber pressure novelcontactless optical sensor enhanced onstreet parking management system enhanced real time service optimised multimodal mobility relying cooperative network open data enhancing fuel efficiency reducing vehicle maintenance downtime cost realtime data vehicle sensor iot machine learning algorithm big data analysis environmentally friendly fire suppression system cargo innovative green technology establishing ecodriving method score driver enhance good driving habit based advanced analytical software platform connected car european bus system future european collaborative dissemination aeronautical research application european competitiveness commercial hybrid automotive powertrain european transport network alliance everyday life radar sensor transportation express delivery endtoend management system collaborative intelligence extreme dynamic loading pushing boundary aerospace composite material structure fast moving container caming solution fast radio technology uninterrupted train trackside communication feasibility assessment greenflux service operation platform smart charging gsopsc feasibility study development pfc harmonic philtre missing link creation simultaneous multipoint fast charging station electric vehicle feasibility study energy battery metallic lithium anode feasibility study superefficient hybrid power train replacement unit existing engine hybrid power general aviation hypoga volt lithium ion battery silicon anode produced generation electric vehicle flightworthy flush lightweight door unpressurized fast rotorcraft fluidised bed heat treatment furnace hpdc engine block transport component offering opportunity lightweight cost competitiveness energy saving flutter free flight envelope expansion economical performance improvement forever open infrastructure transport mode freeway safely effortless commute urban environment freight auction reinvented bilbao oslo intermodal mobility solution interface people good supported innovative communication network fuel flexible nearzero emission adaptive performance marine engine full fairing rotor head aerodynamic design optimization furthering congestion creating opportunity walking cycling future cabin asian market future outboard run conventionally electrically future sky safety gasonly internal combustion engine generation business plan production compact reliable device measure realtime cerebral workload state responsibility operator transport domain giving driver conventional electric car parking lot wesmartpark enhanced management system green batteryless tyre pressure monitoring system green efficient outboard greenrail sustainability safety saving railroad sleeper tomorrow groundbreaking convenient electronic bicycle fleet management system mass adoption hard chrome replacement automotive mould heavy duty gas engine integrated vehicle helicopter engine air intake optimization tool helping europe infrastructure draw europe increasing economic performance sustainable easy load securing heat dissipating brake heavy duty vehicle enabling annular disc fan effect fanbrake precision positioning cooperative application voltage direct current distribution electrical master box higher performance engine light sport aircraft hydrogen mobility europe intelligence drive situ manufactured carbonthermoplast curved stiffened panel inwheel electric drive ecommercial vehicle independent smart machinevision based cargo counting module indev indepth understanding accident causation vulnerable road user induction starter generator information technology shift rail infrared structural monitoring crack thermoelastic analysis production environment innovative automatic battery powered washing robot aviation industry aerowash innovative climatecontrol system extend range electric vehicle improve comfort innovative easa certified dynamic test method aircraft seat cushion innovative fuel sensor engine optimisation innovative intelligent rail innovative internal combustion engine incorporate unidirectional rotary design obey perfection otto cycle giving efficiency innovative laser solution cutting welding twip steel improved performance innovative laser solution cutting welding twip steel improved performance innovative methodology technology reducing aircraft noise generation emission innovative sealing sensing technology extended life lubricated element innovative service platform sustainable transport based ecodriving technique innovative steeringtriangle realised aluminium foam technology motorcycle industry innovative textile based heating system technical application special focus electric vehicle innovative transport equipment coal coke ore innovative welding processe rail infrastructure inspection sensor evaluation criteria assessing surface quality hole cfrp part instant foam fighting forest fire integra service provider drone civil integrated permanent magnet motorclutch drive parallel hybrid power marine propulsion system integrated solution enhance cold chain logistic tracking integrated intelligent modular power electronic converter intelligent bearing intelligent hydraulic system enabling service business heavy transport investigation contra rotating open rotor engine configuration wind tunnel experiment observatory libralato rotary engine gamechange cost competitive gasoline engine plugin hybrid car linear infrastructure efficiency improvement automated learning optimised predictive maintenance technique long lifespan battery hybrid vehicle low cost onshore power supply locop low energy emission ship low energy passenger comfort system based joule peltier effect machine vision system road safety inspection mobile ticketing system urban transport mobility based aggregation service application integration mobility innovation dawn sustainable european transport system modular carbon fibre footbridge modular eco waterbus divided identical indipendenthybrid unit allowing operating flexibility transportation modular innodrive powered reel drive maritime environment modular intelligent hydraulic modular scalable multifuntional power density power controller electrical taxi cost time efficient euwide crossborder automated parcel delivery solution multisource big data fusion driven proactivity intelligent mobility navigational decision support system improved colreg safety management adaptable equipment geometric auscultation railway overhead line aerospace advanced cost effective material rapid manufacturing technology bus refuelling european hydrogen bus depot cooperative business model guidance sustainable city logistic dependable rolling stock sustainable intelligent comfortable rail transport europe electric vehicle chassiscab urban logistic enhanced acoustic damping composite material generation adas enhanced driving experience wiring vehicle nicenav navigationgrade itarfree certifiable equipment navigation manned unmanned air vehicle based fog technology compound rotary engine range extender electric vehicle devulcanization machine industrial tyre rubber recycling integration powerplant system equipment processe equipment composite repair technology rail open obdii telematic platform optepla open social transport network urban approach carpooling opening cycling walking tracking potential optical acoustooptic sensor technology railwayapplication optilift offshore lifting logistic optimisation demonstration implementation allencompassing smart management system infrastructure construction maintenance optimised systematic energy management electric vehicle optimised energy management optimodal european travel ecosystem personalised airport system seamless mobility experience piggybaggy uber parcel delivery piloting industrial validation autonomous sustainable animal deterring system rail transport power conversion unit lifercraft demonstrator precise fluid metering equipment precise fluid metering equipment private garage system realtime keyless solution cheaper faster prime innercity parking proactive passenger flow management airport advanced forecasting system proactive safety pedestrian cyclist project buffer solution fast charging electrical vehicle road promoting innovation inland waterway transport sector proving ibc robotic container cleaning system economic climate environmentallyfriendly safe contribution transport system order disrupt global market prozero carbon based fast boat professional pyrolysis derived residue waste providing improved gas vehicle engine rail track monitoring system wireless autonomous onboard system measuring vibration continuous reporting reduce maintenance cost enhance reliability safety range electric solution lcategory vehicle rapid data communication network connected car reuse thermoplastic composite real world advanced technology diesel engine reduce recycle reuseemobility retrofittingkit buse regional turboprop load control active passive technology research alternative diversity aspect truck rethinking container management system rethinking future infrastructure network rethinking urban transportation advanced tool supply chain collaboration retrofit allelectric bus reduced operator operating cost urban transport reboot retrofit allelectric bus reduced operator operating cost urban transport reboot revamping train advanced broadband communication system road rail tunnel fire protection runway independent automatic launch landing system civil uav based grolas safety causation benefit efficiency safetyenhancing innovation older road user sensing skin monitoringbased maintenance transport infrastructure senskin share knowledge effective management aviation safety silicon polyanionic chemistry architecture liion cell energy battery simulation tool development composite manufacturing process default prediction integrated quality control system situationaware mobile platform airport collaborative decisionmaking smart farmer assistant itractor smart integrated system reliable parking information guidance smart protective coating classic material generation ecologically sustainable green railway vehicle smart road modular sensor smarm prototype testing commercialization viability smart supply chain oriented rail freight service smartrail smash smart sharing device mobility social innovation light electric vehicle revolution street ambient solar energy pressure sensor based solution truck weighing solution tco optimised electrification city bus system southpark social universal technology searching local parking space spatial decision support system transportation planning stprm sustainable truck parking reservation management system strengthening european transport research innovation strategy supericephobic surface prevent ice formation aircraft support aerodynamic analysis design propeller compound helicopter support future cror uhbr propulsion system maturation surface heat exchanger aero engine surveillance maritime surrounding laser technology sustainable network japaneurope aerospace research technology cooperation synchromodal supply chain econet development planocentric gearbox closed cage sgear tooth flank european traveller club accountbased travelling european union reversible variable transmission visionary transmission unprecedented fuel cost saving sustainable mobility planner smp validation certification industrial testing advanced road marking retro reflectance measuring equipment retrotekm global market themotion revolution motion torque vectoring platform generation electric driven vehicle total full ecologic embedded railway jacket system industrial aeronautic paving future accurate cfd tra vision trafficflow analytic smarter city transforming biodiesel industry meet europe sustainable aviation fuel business feasibility study technical validation realworld demonstration transport system artificial intelligence safety fare evasion truck security fuel cargo theft detection alarm system tunnel fire stopper tfs shortly ultra low emission technology innovation midcentury aircraft turbine engine ultralight ultrasafe adaptable wheeler ultrasonic inspection solution railway crossing point ultrasonic system antifouling protection ship ultrasound nde tomograph design construction portable ultrasound scanner nondestructive testing evaluation ndt nde concrete bridge building structure upscale electrical pulse technology capable fragmenting hydrocarbon chain fuel maritime application user safety security energy transport infrastructure usharepark smart secure system share parking place private garage validated surge model validation integrated safetyenhanced intelligent flight control vez volume manufacturing pem stack transportation inline quality assurance wattsup electric flight future life rail axle assessment improvement ultrasonic phased array corrosion inspection system wise wide instantaneous support equipment specific programme cooperation food agriculture biotechnology submitted lukejone tue programme detail specific programme cooperation food agriculture biotechnology outline funding project contact leading institution specific programme cooperation space submitted lukejone tue programme detail specific programme cooperation space outline funding project contact leading institution project profile deorbiting satellite solar sail magneticsuperconductor cryogenic noncontact harmonic drive specific programme cooperation nanoscience nanotechnology material production technology submitted lukejone mon programme detail specific programme cooperation nanoscience nanotechnology material production technology outline funding project contact leading institution project profile development power density supercapacitor automotive application ecodesign validation inwheel concept electric vehicle multilevel protection material vehicle smart nanocontainer specific programme cooperation joint technology initiative submitted lukejone mon programme detail specific programme cooperation joint technology initiative outline funding project contact leading institution project profile battery modular system integrated conversion clean hydrogen european city contribution design optimization tiltrotor component drag reduction demonstration european sofc truck apu development advanced software tool aircraftlevel investigation impact architecture avionic onboard general system green regional aircraft fatigue test fuel cell based power generation future regional aircraft requirement study green regional aircraft avionic architecture mission trajectory management leading edge box design swept flow control wing methodology application emission measurement rotorcraft nanostructured thermoelectric system green transport energy efficient application numerical experimental shock control laminar wing numerical tool aerodynamic optimization laminar wing partitioning modelling sip preparing socio economic evaluation future lighthouse project supporting action prepare largescale hydrogen vehicle demonstration europe north sea region programme submitted christianbyrith thu programme detail north sea region programme outline funding contact operational programme transport transport infrastructure submitted skaraivanova thu programme detail operational programme transport transport infrastructure outline funding project contact leading institution operational transport programme submitted sekretariat fri programme detail operational transport programme outline funding contact operational programme infrastructure environment submitted sekretariatkmpoiis wed programme detail operational programme infrastructure environment outline funding project contact page country profile programme browse country browse organisation database project transport theme browse funding origin browse partner database publication theme analysis report compendium videos archive event newsroom new archive press release newsletter flash report trip trip benefit user download form project newsletter follow log submit update username create account request captchaantispam question math question solve simple math problem enter result enter submit event submit new submit project trip funded european commission directorate general mobility transport seventh framework programme research technological development top","m_szGeo1":"","m_szSourceType":"source_general","m_szSrcUrl":"http://www.transport-research.info/trip-portal-funding-type/public-eu","m_Places":["Friendly","Graz","Europe","Landing","Clearview","European Cities","Short Sea","Macao","Bus","Bilbao","Oslo","Mobile","Most","Protection","Japan","Smarter Cities","North Sea"],"m_People":["A Mile","Airlander Civil","Cror Blade","Lithium Ion","Waterbus Able"],"m_Companies":["Eu","Airbus","Inovative Solutions","2020","Seat","Bespoke","Monitoring Technology","Rapid","Matrix","Ecs","Boundary","Innovative Green Technology","Alliance","Caming Solutions","Volt","Parking Lots","Information Technologies","Otto","Integra A/s","Clutch","Power Marine","Lifespan","Innovations","Adas","Uber","Advanced Technologies","Revolution","Solar Energy","Universal Technology","Through Laser Technology","European Union","Torque","Pem Fc","Joint Technology","2014-2020","European Commission"],"m_BiGrams":["electric vehicle","programme detail","outline funding","management system","funding project","project contact","specific programme","programme cooperation","contact leading","leading institution","institution project","project profile","submitted lukejone","transport system","feasibility study","control system","supply chain","decision support","european transport","system green","detail specific","operational programme","lukejone tue","tue programme","fast charging","landing system","system advanced","quality control","support system","cost effective","combustion engine","hybrid power","urban transport","regional aircraft","detail operational"],"m_TriGrams":["outline funding project","funding project contact","specific programme cooperation","project contact leading","contact leading institution","leading institution project","institution project profile","programme detail specific","detail specific programme","submitted lukejone tue","lukejone tue programme","tue programme detail","decision support system","programme detail operational"],"m_SocialTags":[],"m_Topics":[],"m_Industry":[],"m_Technology":[],"m_BiCnt":[11,10,10,9,8,8,8,8,7,7,5,5,5,5,5,4,4,4,4,4,4,4,3,3,3,3,3,3,3,3,3,3,3,3,3],"m_TriCnt":[8,8,8,7,7,5,5,4,4,3,3,3,3,3],"m_iDocBodyWordCnt":2898}
