{"m_szDocID":"964372","m_szDocTitle":"Littelfuse's (LFUS) CEO Gordon Hunter on Q3 2015 Results - Earnings Call Transcript | Seeking Alpha","m_szYear":"2015","m_szDocSumamry":"textArticle -------------------- Littelfuse's (LFUS) CEO Gordon Hunter on Q3 2015 Results - Earnings Call Transcript Q3 2015 Earnings Conference Call October 28, 2015 11:00 AM ET Executives Gordon Hunter - Chairman, President and CEO Phil Franklin - EVP and CFO Analysts Josh Chan - Robert W. Baird Shawn Harrison - Longbow Research Gary Prestopino - Barrington Research Operator Good day, everyone, and welcome to the Littelfuse Inc.â€™s third quarter 2015 conference call. Today's call is being recorded. At this time, I will turn the call over to Chairman, President, and Chief Executive Officer Mr.","m_szDocBody":"littelfuse lfus ceo gordon hunter result earning call transcript earning conference call executive gordon hunter chairman president ceo phil franklin evp cfo analyst josh chan robert baird shawn harrison longbow research gary prestopino barrington research operator good day everyone littelfuse inc quarter conference call today call recorded time turn call chairman president chief executive officer gordon hunter ahead sir gordon hunter good morning littelfuse quarter conference call joining today phil franklin executive vice president chief financial officer strong quarter challenging economic environment total sale constant currency finished quarter adjusted operating margin recent history testament excellent execution adjusted eps record higher midpoint guidance segment electronic sale declined slightly sluggish environment continued fourth quarter automotive good quarter slowing car build china tempered growth electrical business continued steadily improve top bottom line operating cash flow outstanding manufacturing performance continue improve discuss quarter performance detail minute first turn call phil give safe harbour statement summary new release phil franklin gordon good morning proceed remind comment made call include forwardlooking statement based environment such include risk uncertainty refer press release sec filing information specific risk factor actual result differ materially expressed forwardlooking statement sale quarter million yearoveryear constant currency gaap earning quarter included million noncash pension charge including charge diluted share compared prior year excluding special item earning quarter diluted share compared prior year midpoint guidance strong performance quarter reflected excellent manufacturing execution good expense control success highermargin product weaker currency country manufacture favourable onetime item strong quarter cash flow making final pension contribution million month generated cash operation million compared year record cash performance capital expenditure million month ahead year million primarily reflecting spending philippine plant capacity addition automotive product quarter advantage temporary dip stock price repurchase share average price share quarter completed final settlement pension plan transfered full administrative payment responsibility nonrecourse basis insurance company turn back gordon colour business performance market trend gordon hunter thank phil begin electronic segment account total littelfuse sale electronic sale constant currency compared quarter year primarily due continued adjustment channel inventory continued capacity constraint electronic sensor product transfer production philippine electronic channel inventory slightly end quarter compared quarter decrease primarily north america trend continuing fourth quarter continue sign sluggishness global market reflect reduced lead time industry resulting channel partner comfortable current inventory level strongest region europe quarter yearoveryear sale constant currency growth coming green initiative smart metering led lighting smart metering growth opportunity europe plan replace existing power metre approximately million unit year smart metre complex require higher level protection large european manufacturer approved thermally protected tmov metal oxide varistor smart metre expected add incremental revenue year similar smart metering led lighting driven save energy quarter added led lighting customer europe asia americas expect generate annualised incremental revenue global sale led related product total million slowing china market reported experiencing modest growth key china market year sale targeted market segment flat broadest win china automotive electronic industrial market segment won million business year weve successful application electric vehicle highspeed rail system differentiated product set apart key market telecom infrastructure continue win business major chinese oem tvs diode tvs diode array fuse product line include win current highvoltage countage fuse leading chinese telecom equipment manufacturer product performance larger expensive power fuse smaller economical package power distribution unit design win bring annualised revenue solid position leading chinese oem ems company manufacturing china continue manage growth sluggish economic environment earlier mentioned telecom infrastructure win china nice win korea surface mount nano fuse current highvoltage protection small package fuse protect receive repeat designed large korean telecom equipment company growing area custom sensor product line variety industrial commercial end product detect position flow level interesting application data centre server airflow extremely important recent design win major data centre manufacturer reed switch sensor detect cover critical airflow correct position number successful design win semiconductor product automotive electronic market providing protection bus powertrain body control module infotainment system growth area internet thing recent win diode array remotecontrolled smart air purifier thermostat total revenue application total year electronic business outperformed peer market attribute brag end market led lighting data centre smart metre automotive electronic helped diversify business consumer electronic region korea japan typically strong consumer electronic continue explore opportunity expand industrial business segment summary electronic business wellestablished market strategy develop product provide higher performance smaller package generating business existing customer factor provide solid foundation continued growth automotive business account sale quarter automotive sale constant currency continue make progress goal improving profit margin detail quarter address question potential impact littelfuse result diesel emission issue car buyer avoid purchasing diesel vehicle emission issue select model car manufacturer diesel vehicle gas vehicle vehicle produced large global oem result expect reduction diesel sale significant impact revenue back result quarter continued growth passenger car revenue increase fuse sale sensor sale growth constant currency time global car production grew geographically europe strongest performer due model introduced jaguar land rover volvo masterfuse inline fuse vehicle audi skoda auto north america sale passenger car fuse continue strong pickup truck fullsize suvs continue sell well asia passenger car fuse sale moderately constant currency driven weakness china car build quarter lmc track data won business geographic region mcase fuse standard blade fuse mcase fuse strategically important future growth company offer type fuse designed medium current fuse application enable customer introduce lowercost box architecture medium current growing market segment unique position distinct advantage north america business included win cablepro midsize pickup suvs europe mcase fuse designed nissan micra subcompact model land rover discovery sport win europe include blade fuse ford midsize car platform jaguar won business highvoltage fuse jaguar land rover hybrid suvs design win asia include standard fuse jeep local oem china surface mount fuse battery management system made korea renault model cablepro win thailand standard fuse tier supplier india total thirdquarter win million annually peak fourth quarter expect continued growth north america europe wellpositioned leading oem climate positive anticipating lower growth rate quarter due timing order asia expect end year slow quarter chinese government recently announced incentive programme reduce consumer tax car small engine expect impact programme automotive sensor business good quarter thirdquarter sale matched secondquarter record traditionally weaker quarter driver robust demand seatbelt solar sensor sold strong north american market automotive sensor revenue growing faster market continue win business launch product growth driver sensing business reason strategy build global sensing platform increasing demand complex electronic system vehicle improve environmental performance passenger comfort occupant safety quarter expanded line automotive sensor acquisition sigmar italian company produce sensor gas diesel engine fuel system urea level quality sensor diesel emission reduction system sigmar annual revenue million sale commercial vehicle product cvp constant currency compared year quarter north american heavyduty truck market largest market serve increasing quarter year reached record production quarter begun modestly taper truck sale return normal run rate business win quarter include low current switch north american material handling customer current switch power distribution module north american agricultural customer total annual revenue addition previously announced programme agricultural customer started production contribute annual revenue peak summary automotive business performing well executing growth strategy positioned longterm growth continue focus profitability improvement electrical business unit account total littelfuse sale continued improvement quarter sale constant currency sale electrical fuse custom product increased protection relay sale remained soft improvement commercial construction segment strong solar performance globally main driver increase electrical fuse sale offset weaker sale core industrial distribution market solar sale quarter increased million yearoveryear innovative product introduced year continued build momentum strong backlog entering fourth quarter fuse business significant design win quarter including world largest manufacturer industrial drive motion control product opportunity open door sale highspeed semiconductor fuse product protection relay sale due soft mining oil gas segment part diversification strategy recently completed development testing product move market car control product energyefficient automatic transfer switch ats communication capability ats developed conjunction industryleading customer data centre market wanted ensure uninterrupted power global data centre operation awarded multiple order totaling product moving custom electrical product sale significantly low point potash order gradually returning normal level evidenced order totaling million major potash mining company quarter thirdquarter sale benefited acquisition jrs manufacturing earlier year recall jrs fabricate ehouse electrical equipment plant utility addition jrs combined expertise continue generate business based recent order expect enter strong backlog electrical segment continue move positive direction solar market strong potash mining improving levering synergy jrs existing custom product business conclude update business unit cover topic chinas slower growth rate impact littelfuse thirdquarter sale increase china singledigit performing company challenging economic environment attribute growth targeted market led lighting solar automotive electronic robust automotive business difficult thirdquarter china moving forward strategy expand market share secure business recent win jeep working local chinese oem fuse technology increase model opportunity combined wellestablished relationship western oem drive continued growth china long term area comment europe quarter sale increased constant currency business segment grew double digit europe quarter constant currency manufacturer growing market led lighting solar green product located europe automotive side largest customer european oem written slow european economy targeted growth strategy helping perform environment update production transfer largest transfer reed switch sensor production square foot plant philippine schedule move expect capacity issue experiencing ease beginning early year schedule complete transfer half year saving expected reach full million run rate time addition consolidation symcom plant york south dakota track completed yearend projected annual saving million piedras negras plant mexico initiative improve productivity reduce cost made positive contribution margin improvement passenger car electrical fuse product line work making good progress finally comment m&a strategy earlier mentioned sigmar acquisition small strategic acquisition sensor product line working opportunity optimistic announce end year previously stated revisiting capital allocation target yearend target depend progress making acquisition front that turn call back phil provide fourth quarter outlook question phil franklin thank gordon fourth quarter continued softness electronic sale order automotive electrical demand holding fairly well press release fourth quarter year include week usual including extra holiday shortened week guidance fourth quarter follow sale expected range million million earning fourth quarter expected range diluted share conclude prepared remark wed open question questionandanswer session operator instruction stifel matt sheerin online matt sheerin couple question extra week phil quarter doesnt sound youre full week end quarter customer cutting inventory order point and full week cost difference there quarter then expect bit seasonal extra week inventory refresh fact low season market bit different phil franklin yes bit hard call quarter point roll year kind normal sequential progression youd million extra week contribute number guidance relative trend talk about visibility point comment that matt sheerin youve nice margin improvement year year automotive electronic continue track execution talked about benefit costcutting initiative benefit quarter phil franklin costcutting planned consolidation gordon referred benefit yet fact continue negative impact fourth quarter close completing philippine move roll start benefit start slow quarter start ramp there talked talked gordon reiterated million benefit philippine transfer kicked million symcom consolidation south dakota plant start bit quarter year ramp close full contribution middle year improvement quarter doesnt relate thing relate mentioned weve decent top line leverage benefit good manufacturing performance including improvement mexico facility cited weakness quarter ago pretty favourable product mix quarter number contributed good expense control small onetime item werent worth pointing individually total added order basis point margin quarter wouldnt margin sustainable number margin improvement trend wellestablished year start contribution big restructuring project matt sheerin quick question commentary gordon revisiting capital allocation strategy end year here suppose contingent m&a activity pipeline deal not gordon hunter yes matt right number deal working depending success directly reflect capital allocation strategy make decision end year talk fourth quarter conference call january operator baird josh chan online josh chan talk cadence demand electronic business kind order pattern month quarter bridging youre october month sort fold there gordon hunter dont change pattern weve talked sluggishness electronic quarter now slightly typical book bill token seasonal pattern shipment strong weakness electronic business real major there lot change distributor behaviour term ordering pattern continue order short lead time end market characterise point improving noticeably worse noticeably china weakened china business held competitor have josh chan steady pattern compared earlier year guess talk normal seasonality fourth quarter electronic talking kind decline sort average year ballpark gordon hunter yes company mid singledigit decline electronic business closer bit that bit masked extra week well million extra week add expect pretty normal seasonality electronic business josh chan switch electrical business solar contributed significantly growth quarter count contributing growth similar rate assume contribute rate segment grow modest level gordon hunter extremely bullish solar business strong introduced lot product good traction bump reason called step quarter level depend end market good set product weve industryleading product good global traction success part world confident growth rate quarter solid outlook year josh chan question pension settlement income statement benefit point future pension settlement that phil franklin significant benefit ongoing taking significant charge p&l ongoing basis there benefited administrative cost pension moved insurance company actuarial fee administrative cost relate that million dollar million million year kind number saving for operator longbow research shawn harrison line shawn harrison guess couple clarification end first remember correctly quarter sensor company dont youd signed memorandum understanding acquisition line close quarter give update company phil franklin number pipeline fairly optimistic about sensor company signed deal contingency happen completely dead happen pipeline feel pretty good about stay tuned those shawn harrison guess couple clarification guidance expectation tax rate fourth quarter kind capex year phil franklin yes tax rate realm running expect improve materially year weve talked low year big change happen start quarter year capex changed there track spent million year weve million million range range full year shawn harrison guess final question supply chain peer talked china automotive discrepancy local oem production level versus multinational production level citing cited production substantially that kind talk youre china automotive production excess inventory expect production half based youre now gordon hunter shawn right data independent source show production level significantly doubledigit western oem add korean oem fairly good growth growth local oem change market lot vehicle coming made local oem brought vehicle good feature small suv segment long time thought eventually local oem start catchup brand image quality starting happen tougher competition western oem data show total production level understand happened market western oem vehicle increasing local oem long term staying close local oem critically important vehicle increase time shawn harrison dramatic variance multinational local production shift move bit favourably term mix growth gordon hunter pretty hard tell long time follow pretty closely feeling chinese oem consolidation success amazing chinese public preferred western brand brand image quality vehicle local oem improving continue quarter depend chinese consumer hard predict feeling recently strong performance long term chinese oem brand image quality western level operator oppenheimer christopher glynn line christopher glynn hey kind generally point relative longterm growth target structurally cyclically contemplate implication market share transition china automotive electronic early handicapping done phil franklin weve quarter kind car build weve benefiting year expecting modest low singledigit kind number year automotive growth depend play sensor area market share gain bring programme platform oem growth play pretty optimistic that automotive grow double digit year lower car build mid singledigit growth doable based there electronic pretty hard handicap point optimistic inventory level low distributor careful point theyre back kind standard normal behaviour benefit happen term end market clear yet electrical side showing good progress certainly optimistic relay business opportunity gordon mentioned power fuse business rebounded nicely solar gordon talked helping order receiving custom encouraging segment recovery potash market opportunity jrs electrical positioned pretty growth well christopher glynn million extra week localising segment kind proportional phil franklin completely proportional businesse asia business impacted electronic bit normal week business asia affected christmas holiday end spectrum electrical business majority business vast majority business north america impacted automotive between christopher glynn gave good level comment margin basis point helped auto kind surged margin there somewhere talk sound mix negative sensor outpaced fuse mix effort making sensor big deal quarter phil franklin yes nice step sensor margin quarter automotive margin related favourable mix talking about mix favourable expect nearterm there count quarter automotive margin kind normal margin back expect steady improvement year initiative talked previously benefit cost programme manufacturing improvement programme starting kick christopher glynn sidoti company john franzreb line john franzreb m&a pipeline talk size acquisition hoping close yearend size sigmar secondly sigmar quality sensor onetime sizable opportunity europe talk bit sigmar position product line phil franklin early talk that typically spend time effort acquire million revenue company significant growth opportunity there leave comment that bought company technology product million revenue feel good that talked past larger potential deal pipeline case give update that working kind smaller midsize deal bigger sigmar working new end year working currently gordon hunter add couple word sigmar visited plant highly automated plant extremely talented technical operation focused founder leader business good team people small company scope contact european customer base customer small europe rest automotive sensor business growing taking businesse acquired globally product customer relationship world explain part growth automotive sensor business overall good technology good team product customer grow business john franzreb automotive commentary tempered expectation encompass likelihood hearing lower commercial vehicle product sale year built expectation phil franklin built thinking well number peer company commented trend segment market buoyed year strength heavy truck market market growth rate slowed significantly expect recurrence strength great sign construction market coming back opportunity programme win product market overlay commercial vehicle weaker year past couple year john franzreb question give sense size solar business you light fact end tax incentive solar thinking business post transition phil franklin north million depend shy million north million let put way operator ","m_szGeo1":"United States","m_szSourceType":"source_investments","m_szSrcUrl":"http://seekingalpha.com/article/3617336-littelfuses-lfus-ceo-gordon-hunter-q3-2015-results-earnings-call-transcript?all=true&find=peer-to-peer+AND+insurance","m_Places":["China","Well","United States","Philippines","North America","Europe","Asia","Korea","Japan","Thailand","India","New York","South Dakota","Mexico"],"m_People":["Gordon Hunter","Phil Franklin","Josh Chan","Chan - Robert W. Baird","Shawn Harrison","Gary Prestopino - Barrington","Nissan Micra","Matt Sheerin","Christopher Glynn","John Franzreb"],"m_Companies":["Littelfuse Inc.","Remind","Sec","2020","Diesel","Jaguar","Land Rover","Volvo","Audi","Renault","Chinese Government","Cadence","Guess","Capex","Transitions Of China"],"m_BiGrams":["phil franklin","fourth quarter","gordon hunter","constant currency","local oem","josh chan","shawn harrison","led lighting","automotive electronic","electronic business","extra week","sale constant","quarter year","north america","chinese oem","product line","design win","data centre","end year","automotive sensor","christopher glynn","conference call","quarter automotive","car build","electrical business","china automotive","end market","continued growth","passenger car","growth rate","north american","western oem","matt sheerin","production level","john franzreb","quarter conference","turn call","economic environment","electronic sale","sale quarter","diluted share","sensor product","europe quarter","smart metering","smart metre","market segment","year weve","fuse product","market led","automotive business","fuse sale","land rover","mcase fuse","sensor business","thirdquarter sale","annual revenue","commercial vehicle","electrical fuse","market share","long term","margin improvement","capital allocation","franklin yes","million extra","harrison guess","image quality"],"m_TriGrams":["sale constant currency","quarter conference call","market led lighting","automotive sensor business","phil franklin yes","million extra week","shawn harrison guess"],"m_SocialTags":[],"m_Topics":[],"m_Industry":[],"m_Technology":[],"m_BiCnt":[15,13,12,11,8,6,6,6,6,6,6,5,5,5,5,5,5,5,5,5,5,4,4,4,4,4,4,4,4,4,4,4,4,4,4,3,3,3,3,3,3,3,3,3,3,3,3,3,3,3,3,3,3,3,3,3,3,3,3,3,3,3,3,3,3,3],"m_TriCnt":[4,3,3,3,3,3,3],"m_iDocBodyWordCnt":2928}
