{"m_szDocID":"973921","m_szDocTitle":"Ford puts self-driving car project in fast lane - Times of India","m_szYear":"2015","m_szDocSumamry":"Ford puts self-driving car project in fast lane America’s second largest automaker Ford is shifting focus from Detroit to Silicon Valley as it plays catch up to technology innovations in the fast-changing mobility space. | TNN | Jul 4, 2015, 01.30 AM IST America’s second largest automaker Ford is shifting focus from Detroit to Silicon Valley as it plays catch up ... Read More PALO ALTO, CA: America's second largest automaker Ford is shifting focus from Detroit to Silicon Valley as it plays catch up to technology innovations in the fast-changing mobility space. The company said it's moving the ","m_szDocBody":"ford put selfdriving car project fast lane americas largest automaker ford shifting focus detroit silicon valley play catch technology innovation fastchanging mobility space tnn ist americas largest automaker ford shifting focus detroit silicon valley play catch read palo alto americas largest automaker ford shifting focus detroit silicon valley play catch technology innovation fastchanging mobility space company moving development autonomous vehicle technology selfdriving car research lab palo alto advanced engineering programme giving timeline intend sell car commercially moving experimentation implementation mark field ford president ceo sideline automaker annual ford trend conference palo alto learned lot past month ready put insight action ford appointed director autonomous vehicle development randy visintainer created fullfledged team work programme ford technology push time big automobile company fighting like tesla uber disrupting conventional mobility city world concept driverless car ridesharing electric vehicle silicon valley hotbed technology innovation quintessential outpost automaker ford opening research development lab earlier year field dearborn michiganbased company year ago steering effort ford viewed part ecosystem silicon valley ford squareft palo alto lab include researcher scientist engineer end auto giant uber airbnbpioneered shared economy space launch peerpeer car sharing pilot programme select customer city london carmaker inviting customer rent ford creditfinanced vehicle prescreened driver shortterm use offsetting monthly vehicle ownership cost general motor bmw announced similar programme car owner earn money renting vehicle driversthis recently announced godrive ondemand public carsharing pilot service offer fleet car oneway journey easy parking london beside techbacked innovation car ford solution consumer big city driving vehicle home work feasible revealed electric bike prototype smartphone app make ebike easier urban commute ford collaborating startup silicon valley printing wearable technology space the writer palo alto invitation ford motor company related ","m_szGeo1":"India","m_szSourceType":"source_news","m_szSrcUrl":"http://timesofindia.indiatimes.com/business/international-business/Ford-puts-self-driving-car-project-in-fast-lane/articleshow/47932039.cms","m_Places":["America","Detroit","Silicon Valley","Palo Alto, Ca","Palo Alto","Tesla","Dearborn, Michigan","Us","London"],"m_People":["Mark Fields","Randy Visintainer"],"m_Companies":["Tnn","Google","Uber","Airbnb","General Motors","Bmw","Ford Motor Company"],"m_BiGrams":["silicon valley","palo alto","automaker ford","americas largest","largest automaker","ford shifting","shifting focus","focus detroit","detroit silicon","valley play","play catch","technology innovation"],"m_TriGrams":["americas largest automaker","largest automaker ford","automaker ford shifting","ford shifting focus","shifting focus detroit","focus detroit silicon","detroit silicon valley","silicon valley play","valley play catch"],"m_SocialTags":[],"m_Topics":[],"m_Industry":[],"m_Technology":[],"m_BiCnt":[6,5,4,3,3,3,3,3,3,3,3,3],"m_TriCnt":[3,3,3,3,3,3,3,3,3],"m_iDocBodyWordCnt":279}
