{"m_szDocID":"975464","m_szDocTitle":"GM debuts car-sharing brand as it speeds up urban mobility focus - The Portland Press Herald / Maine Sunday Telegram","m_szYear":"2016","m_szDocSumamry":"textArticle -------------------- increase font size GM debuts car-sharing brand as it speeds up urban mobility focus As ride-sharing and car-sharing grow, General Motors swants to be at the forefront, but says selling cars will remain a big part of its business. By TOM KRISHERThe Associated Press Share Read Article DETROIT — The final destination is a mystery, but General Motors is taking another step on its fast-moving journey into new ways of getting around. The company on Thursday announced that it’s formed a brand called “Maven” that will run its car-sharing ventures, including a new one t","m_szDocBody":"increase font size debut carsharing brand speed urban mobility focus ridesharing carsharing grow general motor swant forefront selling car remain big part business tom krisherthe press share read detroit final destination mystery general motor taking step fastmoving journey way around company announced formed brand called maven run carsharing venture including begin competing zipcar month ann arbour michigan spread metro areas year zipcar face competition general motor maven brand launches month ann arbour mich spread metro areas year invested lyft ridehailing company press file file friday file photo show general motor logo company world headquarter detroit final destination mystery general motor taking step fastmoving journey way around company thursday jan announced formed brand called maven run carsharing venture including begin competing zipcar month ann arbour michigan spread metro areas year sancya file jan photo lyft driver nancy tcheou wait car dropping passenger taxi cab passe san francisco final destination mystery general motor taking step fastmoving journey way around company thursday jan announced formed brand called maven run carsharing venture including begin competing zipcar month ann arbour michigan spread metro areas year executive expect main business model selling car people continue large big coming ride carsharing chiu file photos purchase photo store executive expect main business model selling car people continue large big coming ride carsharing significant opportunity change occur president dan ammann said company make forefront that unveiling maven heel mobility deal announced year million investment ridehailing company lyft purchasing remnant defunct ridehailing company sidecar maven parking space vehicle assigned area university michigan campus ann arbour including spot dormitory lot expanding residential carsharing project apartment building york city chicago ann arbour project people rent car hour smartphone app connect car onstar system customer car remotely unlock app service recruiting customer testing now open public february julia steyn vice president urban mobility recently year executive nonplussed trend transportationsharing economy ammann plan work long ago mile chevrolet bolt electric car deal work company doesnt expect huge boost revenue initially million million people worldwide sharing vehicle real commercial opportunity ammann said now lyft remain maven brand see deploy selfdriving bolt limited geographic areas ammann said automaker poking mobility while daimler started cargo carsharing service operate european north american city year daimler bought ridescout austin texas app show fastest buse bike transportation bmw operate carsharing service drivenow european city toyota motor corp part programme grenoble france let people short trip tiny electric car honda motor partnered zipcar providing fleet honda fit ford motor year started carsharing service called godrive london let people car location driver book car mobile phone app bangalore india ford testing idea small coworker family sharing vehicle ford executive chairman bill ford company understand experiment fail change dramatically ford partner acquire company done project own longer make sell car addressing share vehicle hail ride share ","m_szGeo1":"United States","m_szSourceType":"source_news","m_szSrcUrl":"http://www.pressherald.com/2016/01/21/gm-debuts-car-sharing-brand-as-it-speeds-up-urban-mobility-focus/","m_Places":["Detroit","Ann Arbor, Michigan","Ann Arbor, Mich.","Ann Arbor","New York City","Chicago","Austin, Texas","Grenoble","France","London","Bangalore","India"],"m_People":["Nancy Tcheou","Jeff Chiu","Dan Ammann","Julia Steyn","Ford Will"],"m_Companies":["General Motors","Tom Krisherthe Associated Press","Zipcar","Lyft","Associated Press","Ap","University Of Michigan","Daimler Ag","Bmw","Toyota Motor Corp","Honda Motor Co","Honda","Ford Motor Co"],"m_BiGrams":["general motor","ann arbour","month ann","spread metro","metro areas","areas year","selling car","final destination","destination mystery","mystery general","motor taking","taking step","step fastmoving","fastmoving journey","journey way","way around","around company","announced formed","formed brand","brand called","called maven","maven run","run carsharing","carsharing venture","venture including","including begin","begin competing","competing zipcar","zipcar month","arbour michigan","michigan spread","ridehailing company","ammann said","carsharing service"],"m_TriGrams":["month ann arbour","spread metro areas","metro areas year","final destination mystery","destination mystery general","mystery general motor","general motor taking","motor taking step","taking step fastmoving","step fastmoving journey","fastmoving journey way","journey way around","way around company","announced formed brand","formed brand called","brand called maven","called maven run","maven run carsharing","run carsharing venture","carsharing venture including","venture including begin","including begin competing","begin competing zipcar","competing zipcar month","zipcar month ann","ann arbour michigan","arbour michigan spread","michigan spread metro"],"m_SocialTags":[],"m_Topics":[],"m_Industry":[],"m_Technology":[],"m_BiCnt":[6,6,4,4,4,4,3,3,3,3,3,3,3,3,3,3,3,3,3,3,3,3,3,3,3,3,3,3,3,3,3,3,3,3],"m_TriCnt":[4,4,4,3,3,3,3,3,3,3,3,3,3,3,3,3,3,3,3,3,3,3,3,3,3,3,3,3],"m_iDocBodyWordCnt":463}
