{"m_szDocID":"BINGHARVEST618130cd-a396-6f75-1582-bba1834604a3","m_szDocTitle":"virtual reality Latest News, Photos & Videos | WIRED","m_szYear":"2016","m_szDocSumamry":"WIRED is where tomorrow is realized ... Subscribe now to get 6 months for $5 - plus a FREE Portable Phone Charger.","m_szDocBody":"virtual reality latest new photos videos wired skip curated storey visually open navgo wired home page virtual reality open fieldsearch business culture design gear science security transportation photo video photo video magazine wired insider innovation insight fallback image magazine month free portable phone charger newsletter wired biggest storey delivered inboxsubmit invalid follow hour apocalyptic tweet predicted world sery year ago follow follow miss latest new feature videosfollow pinterest inspiring usfollow follow miss wired latest videosfollow advertisementskip latest newsvirtual reality virtual reality summer lesson playstation vrs boring sexy game gear entropy youll love watching psvr teardown video virtual reality watch haunting trailer vrs scripted sery wired classic pilot million aviation virtual reality epic shooter bullet train wacky robo recall virtual reality oculus game lone echo fun ive zerog popular skip curated storey review home review review home hour alexa home versus amazon echo test voice interface alexa home versus amazon echo test hour dismal science standing rock pipeline protest climate change dismal science standing rock pipeline protest hour block ultrasonic signal didnt tracking privacy block ultrasonic signal didnt tracking hour waiting gadot woman trailer here movy waiting gadot woman trailer here hour tesla unveil line camouflaged solar panel innovation tesla unveil line camouflaged solar panel apocalyptic tweet predicted world sery year ago apocalyptic tweet predicted world sery year ago hour watching twitter cleaned comment web watching twitter cleaned comment hour storey latest new skip popular apocalyptic tweet predicted world sery year ago apocalyptic tweet predicted world sery year ago hour waiting gadot woman trailer here movy waiting gadot woman trailer here hour ignore troll vote psa ignore troll vote day buy facebook internal propoganda poster social media buy facebook internal propoganda poster day ready buy stuff straight instagram ecommerce ready buy stuff straight instagram day wired pilot programme people earth wired pilot programme people earth henrik fisker back again tesla rival again electric vehicle henrik fisker back again tesla rival again white house prepare hand potus election white house prepare hand potus new product review sony playstation poised win headset war virtual reality daydream google plushy headset masse virtual reality gravity sketch wild app draw midair gadget headset make iphone videos virtual reality music salvation selling song virtual reality ghostbusting finally power psychology make empathetic artist activist journalist vrs potential empathy engineload result wired wired wired pinterest wired wired tumblr wired instagram advertise map press centre faq customer care contact tshirt collection newsletter wired staff job constitute acceptance agreement effective privacy policy effective affiliate link policy california privacy right material reproduced distributed transmitted cached used prior written permission cond nast","m_szGeo1":"United States","m_szSourceType":"Technology_Internet","m_szSrcUrl":"https://www.wired.com/tag/virtual-reality","m_Places":[],"m_People":["Henrik Fisker"],"m_Companies":["Instagram","Sony","Twitter","Google","Youtube","Facebook"],"m_BiGrams":["virtual reality","apocalyptic tweet","tweet predicted","predicted world","world sery","sery year","waiting gadot","gadot woman","woman trailer","trailer here","latest new"],"m_TriGrams":["apocalyptic tweet predicted","tweet predicted world","predicted world sery","world sery year","sery year ago","waiting gadot woman","gadot woman trailer","woman trailer here"],"m_SocialTags":["Software","Virtual reality","Computing"],"m_Topics":[],"m_Industry":[],"m_Technology":[],"m_BiCnt":[10,5,5,5,5,5,4,4,4,4,3],"m_TriCnt":[5,5,5,5,5,4,4,4],"m_iDocBodyWordCnt":428}
